Workbook
Name AprSun1: DATE(CalendarYear,4,1)-WEEKDAY(DATE(CalendarYear,4,1))
Name AugSun1: DATE(CalendarYear,8,1)-WEEKDAY(DATE(CalendarYear,8,1))
Name CalendarYear: [0]!Year1
Name Categories: OFFSET(#REF!,0,0,COUNTIF(#REF!,"<>"&"--"),1)
Name CategoryIdentifiers: Categories!$B$8:$B$273
Name CategoryNames: #REF!
Name CategoryNames: Categories!$C$8:$C$273
Name DecSun1: DATE(CalendarYear,12,1)-WEEKDAY(DATE(CalendarYear,12,1))
Name Essential: #REF!
Name Expense_Lookup: [1]Discover!$S:$T
Name FebSun1: DATE(CalendarYear,2,1)-WEEKDAY(DATE(CalendarYear,2,1))
Name HiddenCategoriesCategoryNames: _xlfn.ANCHORARRAY(HiddenCategories!$B$2)
Name HiddenCategoriesSubcategoryNames: HiddenCategories!$C$2:$C$100
Name HiddenCategoriesSubcategoryNamesRows: HiddenCategories!$C$2:$CX$100
Name JanSun1: DATE(CalendarYear,1,1)-WEEKDAY(DATE(CalendarYear,1,1))
Name JulSun1: DATE(CalendarYear,7,1)-WEEKDAY(DATE(CalendarYear,7,1))
Name JunSun1: DATE(CalendarYear,6,1)-WEEKDAY(DATE(CalendarYear,6,1))
Name LastCol: COUNTA('[1]PERSONAL BUDGET - WIP'!$4:$4)+1
Name MarSun1: DATE(CalendarYear,3,1)-WEEKDAY(DATE(CalendarYear,3,1))
Name MaySun1: DATE(CalendarYear,5,1)-WEEKDAY(DATE(CalendarYear,5,1))
Name MonthlyBudgetAvailableDates: _xlfn.ANCHORARRAY(MonthlyBudgetHidden!$C$2)
Name MonthlyBudgetAvailableDateValues: MonthlyBudgetHidden!$C$2:$C$26
Name MonthlyBudgetCurrentDate: MonthlyBudgetHidden!$A$2
Name MonthlyBudgetDate: MonthlyBudget!$O$3
Name MonthlyBudgetDates: MonthlyBudgetHidden!$C$2
Name MonthlyBudgetFavoriteCategory1: MonthlyBudget!$J$25
Name MonthlyBudgetFavoriteCategory1BudgetPercentage: MonthlyBudget!$K$27
Name MonthlyBudgetFavoriteCategory1DetailsText: MonthlyBudget!$J$28
Name MonthlyBudgetFavoriteCategory1LeftText: MonthlyBudget!$L$25
Name MonthlyBudgetFavoriteCategory1Percentages: MonthlyBudget!$J$27:$L$27
Name MonthlyBudgetFavoriteCategory1RemainingPercentage: MonthlyBudget!$L$27
Name MonthlyBudgetFavoriteCategory1SpentPercentage: MonthlyBudget!$J$27
Name MonthlyBudgetFavoriteCategory2: MonthlyBudget!$O$25
Name MonthlyBudgetFavoriteCategory2BudgetPercentage: MonthlyBudget!$P$27
Name MonthlyBudgetFavoriteCategory2DetailsText: MonthlyBudget!$O$28
Name MonthlyBudgetFavoriteCategory2LeftText: MonthlyBudget!$Q$25
Name MonthlyBudgetFavoriteCategory2Percentages: MonthlyBudget!$O$27:$Q$27
Name MonthlyBudgetFavoriteCategory2RemainingPercentage: MonthlyBudget!$Q$27
Name MonthlyBudgetFavoriteCategory2SpentPercentage: MonthlyBudget!$O$27
Name MonthlyBudgetIncomeVsSpendingDescriptionText: MonthlyBudget!$C$8
Name MonthlyBudgetNearestTransactionDate: MonthlyBudgetHidden!$C$2
Name MonthlyBudgetSpendingOverTime: MonthlyBudget!$K$12:$K$17
Name MonthlyBudgetSpendingOverTimeDescriptionText: MonthlyBudget!$J$8
Name MonthlyBudgetTextDates: MonthlyBudgetHidden!$B$2:$B$2000
Name MonthlyBudgetTitle: MonthlyBudget!$B$2
Name MonthlyBudgetTotalBudget: MonthlyBudget!$J$33
Name MonthlyBudgetTotalBudgetDescriptionText: MonthlyBudget!$C$23
Name MonthlyBudgetTotalBudgetDetailsText: MonthlyBudget!$C$28
Name MonthlyBudgetTotalBudgetLeftText: MonthlyBudget!$F$25
Name MonthlyBudgetTotalBudgetPercentage: MonthlyBudget!$D$27
Name MonthlyBudgetTotalExpenses: MonthlyBudget!$F$16
Name MonthlyBudgetTotalIncome: MonthlyBudget!$F$13
Name MonthlyBudgetTotalPercentages: MonthlyBudget!$C$27:$E$27
Name MonthlyBudgetTotalRemaining: MonthlyBudget!$L$33
Name MonthlyBudgetTotalRemainingPercentage: MonthlyBudget!$E$27
Name MonthlyBudgetTotalSpent: MonthlyBudget!$F$33
Name MonthlyBudgetTotalSpentPercentage: MonthlyBudget!$C$27
Name MonthlyBudgetTransactionDates: MonthlyBudgetHidden!$A$3
Name MonthlyBudgetUnusedCategories: MonthlyBudgetHidden!$F$2:$F$2000
Name MonthlyBudgetUnusedCategoryNames: _xlfn.ANCHORARRAY(MonthlyBudgetHidden!$G$2)

Sheet Income
B1: 05/31/2021 - 06/13/2021 (Bi-Weekly (Payroll)) | C1: 06/14/2021 - 06/27/2021 (Bi-Weekly (Payroll)) | D1: 06/28/2021 - 07/11/2021 (Bi-Weekly (Payroll)) | E1: 07/12/2021 - 07/25/2021 (Bi-Weekly (Payroll)) | F1: 07/26/2021 - 08/08/2021 (Bi-Weekly (Payroll)) | G1: 08/09/2021 - 08/22/2021 (Bi-Weekly (Payroll)) | H1: 08/23/2021 - 09/05/2021 (Bi-Weekly (Payroll)) | I1: 09/06/2021 - 09/19/2021 (Bi-Weekly (Payroll)) | J1: 09/20/2021 - 10/03/2021 (Bi-Weekly (Payroll)) | K1: 10/04/2021 - 10/17/2021 (Bi-Weekly (Payroll)) | L1: 10/18/2021 - 10/31/2021 (Bi-Weekly (Payroll)) | M1: 11/01/2021 - 11/14/2021 (Bi-Weekly (Payroll)) | N1: 11/15/2021 - 11/28/2021 (Bi-Weekly (Payroll)) | O1: 11/29/2021 - 12/12/2021 (Bi-Weekly (Payroll)) | P1: 12/13/2021 - 12/26/2021 (Bi-Weekly (Payroll))
A2: Earnings
A3: Bonus - Non Discretionary | J3: 0 | K3: 0 | L3: 0 | M3: 0 | N3: 0 | O3: 0 | P3: 1200
A4: Grossed Up Earnings | B4: 4098.37 | K4: 224.74
A5: LTD Benefit Credit | B5: 0 | C5: 4.86 | D5: 4.86 | E5: 4.86 | F5: 4.86 | G5: 4.86 | H5: 4.86 | I5: 4.86 | J5: 4.86 | K5: 4.86 | L5: 4.86 | M5: 4.86 | N5: 4.86 | O5: 4.86 | P5: 4.86
A6: My Health Completion Credit | B6: 0 | C6: 20 | D6: 20 | E6: 20 | F6: 20 | G6: 20 | H6: 20 | I6: 20 | J6: 20 | K6: 20 | L6: 20 | M6: 20 | N6: 20 | O6: 20 | P6: 20
A7: Regular | B7: 2700 | C7: 3000 | D7: 3000 | E7: 3000 | F7: 3000 | G7: 3000 | H7: 3000 | I7: 3000 | J7: 3000 | K7: 3000 | L7: 3000 | M7: 3000 | N7: 3000 | O7: 3000 | P7: 3076.93
A8: Deductions
A9: Bravo Award - No Cash Net | K9: 150
A10: Charitable Giving | K10: 38.47 | L10: 38.47 | M10: 38.47 | N10: 38.47 | O10: 38.47 | P10: 38.47
A11: Federal | B11: 1225.93 | C11: 363.68 | D11: 363.68 | E11: 363.64 | F11: 363.64 | G11: 363.64 | H11: 363.64 | I11: 363.64 | J11: 363.64 | K11: 413.09 | L11: 363.64 | M11: 363.64 | N11: 310.84 | O11: 310.84 | P11: 569.29
A12: Health Savings Account | B12: 0 | C12: 54.77 | D12: 54.77 | E12: 54.77 | F12: 54.77 | G12: 54.77 | H12: 54.77 | I12: 54.77 | J12: 54.77 | K12: 54.77 | L12: 54.77 | M12: 54.77 | N12: 54.77 | O12: 54.77 | P12: 54.77
A13: Life Insurance Coverage | B13: 0 | C13: 1.13 | D13: 1.13 | E13: 1.13 | F13: 1.13 | G13: 1.13 | H13: 1.13 | I13: 1.13 | J13: 1.13 | K13: 1.13 | L13: 1.13 | M13: 1.13 | N13: 1.13 | O13: 1.13 | P13: 1.13
A14: Long Term Disability Coverage | B14: 0 | C14: 9.69 | D14: 9.69 | E14: 9.69 | F14: 9.69 | G14: 9.69 | H14: 9.69 | I14: 9.69 | J14: 9.69 | K14: 9.69 | L14: 9.69 | M14: 9.69 | N14: 9.69 | O14: 9.69 | P14: 9.69
A15: Medical Coverage | B15: 0 | C15: 87 | D15: 87 | E15: 87 | F15: 87 | G15: 87 | H15: 87 | I15: 87 | J15: 87 | K15: 87 | L15: 87 | M15: 87 | N15: 87 | O15: 87 | P15: 87
A16: Medicare | B16: 98.58 | C16: 41.74 | D16: 41.75 | E16: 41.74 | F16: 41.75 | G16: 41.75 | H16: 41.74 | I16: 41.75 | J16: 41.75 | K16: 45 | L16: 41.75 | M16: 41.74 | N16: 41.75 | O16: 41.74 | P16: 60.27
A17: Nationwide Savings Plan | B17: 0 | C17: 0 | D17: 0 | E17: 0 | F17: 0 | G17: 0 | H17: 0 | I17: 0 | J17: 0 | K17: 0 | L17: 0 | M17: 0 | N17: 240 | O17: 240 | P17: 342.15
A18: NSP AfterTax Deduction NonRoth | C18: 450 | D18: 450 | E18: 300
A19: OASDI | B19: 421.5 | C19: 178.5 | D19: 178.5 | E19: 178.5 | F19: 178.5 | G19: 178.5 | H19: 178.5 | I19: 178.5 | J19: 178.5 | K19: 192.44 | L19: 178.5 | M19: 178.5 | N19: 178.5 | O19: 178.5 | P19: 257.67
A20: Roth 401k Deduction - ROTH | J20: 150 | K20: 240 | L20: 240 | M20: 240
A21: State Tax (VA) | B21: 371.05 | C21: 145.69 | D21: 145.69 | E21: 145.69 | F21: 145.69 | G21: 145.69 | H21: 145.69
A22: State Tax (AZ) | B22: 244.74 | C22: 103.65 | D22: 103.65 | E22: 103.65 | F22: 103.65 | G22: 103.65 | H22: 103.65 | I22: 103.65 | J22: 103.65 | K22: 111.74 | L22: 103.65 | M22: 103.65 | N22: 95.01 | O22: 95.01 | P22: 137.3
A23: Supplemental Accident Coverage | B23: 0 | C23: 1.6 | D23: 1.6 | E23: 1.6 | F23: 1.6 | G23: 1.6 | H23: 1.6 | I23: 1.6 | J23: 1.6 | K23: 1.6 | L23: 1.6 | M23: 1.6 | N23: 1.6 | O23: 1.6 | P23: 1.6
A24: Vision Coverage | B24: 0 | C24: 3.79 | D24: 3.79 | E24: 3.79 | F24: 3.79 | G24: 3.79 | H24: 3.79 | I24: 3.79 | J24: 3.79 | K24: 3.79 | L24: 3.79 | M24: 3.79 | N24: 3.79 | O24: 3.79 | P24: 3.79
A26: Net Income | B26: =SUM(B3:B7)-SUM(B9:B24) -> 4436.57 | C26: =SUM(C3:C7)-SUM(C9:C24) -> 1583.62 | D26: =SUM(D3:D7)-SUM(D9:D24) -> 1583.61 | E26: =SUM(E3:E7)-SUM(E9:E24) -> 1733.66 | F26: =SUM(F3:F7)-SUM(F9:F24) -> 2033.65 | G26: =SUM(G3:G7)-SUM(G9:G24) -> 2033.65 | H26: =SUM(H3:H7)-SUM(H9:H24) -> 2033.66 | I26: =SUM(I3:I7)-SUM(I9:I24) -> 2179.34 | ... P26: =SUM(P3:P7)-SUM(P9:P24) -> 2738.66

Sheet Snapshot
C2: Snapshot | Q2: Choose month below
C4: See your spending trends month over month with easy to read graphs. To switch months, click on the blue date box to the right. | Q4: January 2022 | W4: =_xlfn.XLOOKUP(TEXT(Q4,"mmmm yyyy"),$V$7:$V$200,$W$7:$W$200) -> 44562 | Y4: Monthly Summary | AC4: Category | AD4: Count | AE4: Rank | AF4: Order | AG4: Category | AH4: $ | AJ4: Display Axis | AK4: Current Mon. | AL4: $ | AM4: =TEXT(AK6,"MMMM")&" Spending" -> January Spending | AN4: Max Date | AO4: Last Mon. | AP4: $ | AQ4: =TEXT(AO6,"MMMM")&" Spending" -> December Spending | AR4: Max Date | AT4: Merchants | AU4: $ | AV4: Trans Count | AW4: Trans Rank | AX4: $ Rank
V6: Input | W6: Month Filter | Y6: =TEXT(ABS(Z9),"$#,##0")&" "&IF(Z7>Z8,"less was spent compared to last month","more was spent compared to last month") -> $127 more was spent compared to last month | AC6: {=_xlfn.UNIQUE(INDEX(_xlfn._xlws.FILTER(CategoriesTable[],(CategoriesTable[Category type]="expense")*(NOT(CategoriesTable[ID]=0)),""),0,2),FALSE)} -> Auto/Transport | AD6: =SUMIFS(Table1[Amount $],Table1[Category],Snapshot!AC6,Table1[Month],Snapshot!$W$4)*-1 -> 0 | AE6: =RANK(AD6,$AD$6:$AD$35,0)+COUNTIF(AD6:$AD$6,AD6)-1 -> 5 | AF6: 1 | AG6: {=IF(INDEX($AD$6:$AD$35,MATCH(AF6,$AE$6:$AE$35,0),0)=0,"",INDEX($AC$6:$AC$35,MATCH(AF6,$AE$6:$AE$35,0),0))} -> Home | AH6: {=IF(INDEX($AD$6:$AD$35,MATCH(AF6,$AE$6:$AE$35,0),0)=0,0,INDEX($AD$6:$AD$35,MATCH(AF6,$AE$6:$AE$35,0),0))} -> 485 | AJ6: =DATE(2000,1,1) -> 36526 | AK6: =DATE(YEAR(W4),MONTH(W4),DAY(W4)) -> 44562 | AL6: =SUMIFS(Table1[Amount $],Table1[Category Type],"Expense",Table1[Date],Snapshot!AK6)*-1 -> 102.84 | AM6: =IF(AK6>TODAY(),NA(),SUM(AL6:$AL$6)) -> 102.84 | AN6: =IF(OR(AK6=EOMONTH($AK$6,0),AK6=TODAY()),AM6,NA()) -> #N/A | AO6: =DATE(YEAR(AK6),MONTH(AK6)-1,DAY(AK6)) -> 44531 | AP6: =SUMIFS(Table1[Amount $],Table1[Category Type],"Expense",Table1[Date],Snapshot!AO6)*-1 -> 156.42 | AQ6: =IF(AO6<=EOMONTH($AO$6,0),SUM(AP$6:$AP6),NA()) -> 156.42 | AR6: =IF(AO6=EOMONTH($AO$6,0),AQ6,NA()) -> #N/A | AT6: {=_xlfn.UNIQUE(_xlfn._xlws.FILTER(Table1[Merchant],(Table1[Merchant]<>"")*(Table1[Amount $]<0)*(Table1[Month]=Snapshot!$W$4)*(Table1[Category Type]="Expense")))} -> Best Buy | AU6: =IF(ISBLANK(AT6),"",SUMIFS(Table1[Amount $],Table1[Merchant],Snapshot!AT6,Table1[Month],Snapshot!$W$4)*-1) -> 241.99 | AV6: =IF(ISBLANK(AT6),"",COUNTIFS(Table1[Merchant],Snapshot!AT6,Table1[Month],Snapshot!$W$4)) -> 1 | AW6: =IFERROR(RANK(AV6,$AV$6:$AV$200)+COUNTIF($AV$6:AV6,AV6)-1,"") -> 1 | AX6: =IFERROR(RANK(AU6,$AU$6:$AU$200)+COUNTIF($AU$6:AU6,AU6)-1,"") -> 3
D7: Current vs. previous month spending | M7: This month's top spending categories | V7: =IF(ISBLANK(W7),"--",TEXT(W7,"mmmm")&" "&TEXT(W7,"YYYY")) -> January 2022 | W7: {=_xlfn._xlws.SORT(_xlfn.UNIQUE(_xlfn._xlws.FILTER(Table1[Month],Table1[Month]<>"",)),1,-1)} -> 44562 | Y7: =IFERROR(TEXT(AO6,"mmmm"),"--") -> December | Z7: =SUMIFS(Table1[Amount $],Table1[Category Type],"Expense",Table1[Month],DATE(YEAR(Snapshot!$W$4),MONTH(Snapshot!$W$4)-1,DAY(Snapshot!$W$4)))*-1 -> -177.55 | AC7: Bills/Utilities | AD7: =SUMIFS(Table1[Amount $],Table1[Category],Snapshot!AC7,Table1[Month],Snapshot!$W$4)*-1 -> 0 | AE7: =RANK(AD7,$AD$6:$AD$35,0)+COUNTIF(AD$6:$AD7,AD7)-1 -> 6 | AF7: 2 | AG7: {=IF(INDEX($AD$6:$AD$35,MATCH(AF7,$AE$6:$AE$35,0),0)=0,"",INDEX($AC$6:$AC$35,MATCH(AF7,$AE$6:$AE$35,0),0))} -> Restaurants/Dining | AH7: {=IF(INDEX($AD$6:$AD$35,MATCH(AF7,$AE$6:$AE$35,0),0)=0,0,INDEX($AD$6:$AD$35,MATCH(AF7,$AE$6:$AE$35,0),0))} -> 88.02 | AJ7: =DATE(YEAR(AJ6),MONTH(AJ6),DAY(AJ6)+1) -> 36527 | AK7: =IF(MONTH(AK6)=MONTH(DATE(YEAR(AK6),MONTH(AK6),DAY(AK6)+1)),DATE(YEAR(AK6),MONTH(AK6),DAY(AK6)+1),NA()) -> 44563 | AL7: =SUMIFS(Table1[Amount $],Table1[Category Type],"Expense",Table1[Date],Snapshot!AK7)*-1 -> -2031.99 | AM7: =IF(AK7>TODAY(),NA(),SUM(AL$6:$AL7)) -> -1929.15 | AN7: =IF(OR(AK7=EOMONTH($AK$6,0),AK7=TODAY()),AM7,NA()) -> #N/A | AO7: =IF(MONTH(AO6)=MONTH(DATE(YEAR(AO6),MONTH(AO6),DAY(AO6)+1)),DATE(YEAR(AO6),MONTH(AO6),DAY(AO6)+1),NA()) -> 44532 | AP7: =SUMIFS(Table1[Amount $],Table1[Category Type],"Expense",Table1[Date],Snapshot!AO7)*-1 -> -1939.09 | AQ7: =IF(AO7<=EOMONTH($AO$6,0),SUM(AP$6:$AP7),NA()) -> -1782.67 | AR7: =IF(AO7=EOMONTH($AO$6,0),AQ7,NA()) -> #N/A | AT7: Discover E Payment Lewis | AU7: =IF(ISBLANK(AT7),"",SUMIFS(Table1[Amount $],Table1[Merchant],Snapshot!AT7,Table1[Month],Snapshot!$W$4)*-1) -> 1800 | AV7: =IF(ISBLANK(AT7),"",COUNTIFS(Table1[Merchant],Snapshot!AT7,Table1[Month],Snapshot!$W$4)) -> 1 | AW7: =IFERROR(RANK(AV7,$AV$6:$AV$200)+COUNTIF($AV$6:AV7,AV7)-1,"") -> 2 | AX7: =IFERROR(RANK(AU7,$AU$6:$AU$200)+COUNTIF($AU$6:AU7,AU7)-1,"") -> 1
D8: =Y6 -> $127 more was spent compared to last month | M8: =Q10&" accounts for "&TEXT(S10/S22,"0%")&" of money spent this month" -> Home accounts for -953% of money spent this month | V8: =IF(ISBLANK(W8),"--",TEXT(W8,"mmmm")&" "&TEXT(W8,"YYYY")) -> December 2021 | W8: 44531 | Y8: =IFERROR(TEXT(AK6,"mmmm"),"--") -> January | Z8: =SUMIFS(Table1[Amount $],Table1[Category Type],"Expense",Table1[Month],Snapshot!$W$4)*-1 -> -50.9 | AC8: Entertainment | AD8: =SUMIFS(Table1[Amount $],Table1[Category],Snapshot!AC8,Table1[Month],Snapshot!$W$4)*-1 -> 0 | AE8: =RANK(AD8,$AD$6:$AD$35,0)+COUNTIF(AD$6:$AD8,AD8)-1 -> 7 | AF8: 3 | AG8: {=IF(INDEX($AD$6:$AD$35,MATCH(AF8,$AE$6:$AE$35,0),0)=0,"",INDEX($AC$6:$AC$35,MATCH(AF8,$AE$6:$AE$35,0),0))} -> Shopping | AH8: {=IF(INDEX($AD$6:$AD$35,MATCH(AF8,$AE$6:$AE$35,0),0)=0,0,INDEX($AD$6:$AD$35,MATCH(AF8,$AE$6:$AE$35,0),0))} -> 37.81 | AJ8: =DATE(YEAR(AJ7),MONTH(AJ7),DAY(AJ7)+1) -> 36528 | AK8: =IF(MONTH(AK7)=MONTH(DATE(YEAR(AK7),MONTH(AK7),DAY(AK7)+1)),DATE(YEAR(AK7),MONTH(AK7),DAY(AK7)+1),NA()) -> 44564 | AL8: =SUMIFS(Table1[Amount $],Table1[Category Type],"Expense",Table1[Date],Snapshot!AK8)*-1 -> 1878.25 | AM8: =IF(AK8>TODAY(),NA(),SUM(AL$6:$AL8)) -> -50.9 | AN8: =IF(OR(AK8=EOMONTH($AK$6,0),AK8=TODAY()),AM8,NA()) -> #N/A | AO8: =IF(MONTH(AO7)=MONTH(DATE(YEAR(AO7),MONTH(AO7),DAY(AO7)+1)),DATE(YEAR(AO7),MONTH(AO7),DAY(AO7)+1),NA()) -> 44533 | AP8: =SUMIFS(Table1[Amount $],Table1[Category Type],"Expense",Table1[Date],Snapshot!AO8)*-1 -> 250.77 | AQ8: =IF(AO8<=EOMONTH($AO$6,0),SUM(AP$6:$AP8),NA()) -> -1531.9 | AR8: =IF(AO8=EOMONTH($AO$6,0),AQ8,NA()) -> #N/A | AT8: Paypal Inst Xfer Louisck | AU8: =IF(ISBLANK(AT8),"",SUMIFS(Table1[Amount $],Table1[Merchant],Snapshot!AT8,Table1[Month],Snapshot!$W$4)*-1) -> 10 | AV8: =IF(ISBLANK(AT8),"",COUNTIFS(Table1[Merchant],Snapshot!AT8,Table1[Month],Snapshot!$W$4)) -> 1 | AW8: =IFERROR(RANK(AV8,$AV$6:$AV$200)+COUNTIF($AV$6:AV8,AV8)-1,"") -> 3 | AX8: =IFERROR(RANK(AU8,$AU$6:$AU$200)+COUNTIF($AU$6:AU8,AU8)-1,"") -> 8
V9: =IF(ISBLANK(W9),"--",TEXT(W9,"mmmm")&" "&TEXT(W9,"YYYY")) -> November 2021 | W9: 44501 | Y9: Difference | Z9: =Z8-Z7 -> 126.65 | AC9: Fees/Charges | AD9: =SUMIFS(Table1[Amount $],Table1[Category],Snapshot!AC9,Table1[Month],Snapshot!$W$4)*-1 -> 0 | AE9: =RANK(AD9,$AD$6:$AD$35,0)+COUNTIF(AD$6:$AD9,AD9)-1 -> 8 | AF9: 4 | AG9: {=IF(INDEX($AD$6:$AD$35,MATCH(AF9,$AE$6:$AE$35,0),0)=0,"",INDEX($AC$6:$AC$35,MATCH(AF9,$AE$6:$AE$35,0),0))} -> Payment | AH9: {=IF(INDEX($AD$6:$AD$35,MATCH(AF9,$AE$6:$AE$35,0),0)=0,0,INDEX($AD$6:$AD$35,MATCH(AF9,$AE$6:$AE$35,0),0))} -> 10 | AJ9: =DATE(YEAR(AJ8),MONTH(AJ8),DAY(AJ8)+1) -> 36529 | AK9: =IF(MONTH(AK8)=MONTH(DATE(YEAR(AK8),MONTH(AK8),DAY(AK8)+1)),DATE(YEAR(AK8),MONTH(AK8),DAY(AK8)+1),NA()) -> 44565 | AL9: =SUMIFS(Table1[Amount $],Table1[Category Type],"Expense",Table1[Date],Snapshot!AK9)*-1 -> 0 | AM9: =IF(AK9>TODAY(),NA(),SUM(AL$6:$AL9)) -> -50.9 | AN9: =IF(OR(AK9=EOMONTH($AK$6,0),AK9=TODAY()),AM9,NA()) -> #N/A | AO9: =IF(MONTH(AO8)=MONTH(DATE(YEAR(AO8),MONTH(AO8),DAY(AO8)+1)),DATE(YEAR(AO8),MONTH(AO8),DAY(AO8)+1),NA()) -> 44534 | AP9: =SUMIFS(Table1[Amount $],Table1[Category Type],"Expense",Table1[Date],Snapshot!AO9)*-1 -> 76.04 | AQ9: =IF(AO9<=EOMONTH($AO$6,0),SUM(AP$6:$AP9),NA()) -> -1455.86 | AR9: =IF(AO9=EOMONTH($AO$6,0),AQ9,NA()) -> #N/A | AT9: Transfer To Lewis Sharon | AU9: =IF(ISBLANK(AT9),"",SUMIFS(Table1[Amount $],Table1[Merchant],Snapshot!AT9,Table1[Month],Snapshot!$W$4)*-1) -> 485 | AV9: =IF(ISBLANK(AT9),"",COUNTIFS(Table1[Merchant],Snapshot!AT9,Table1[Month],Snapshot!$W$4)) -> 1 | AW9: =IFERROR(RANK(AV9,$AV$6:$AV$200)+COUNTIF($AV$6:AV9,AV9)-1,"") -> 4 | AX9: =IFERROR(RANK(AU9,$AU$6:$AU$200)+COUNTIF($AU$6:AU9,AU9)-1,"") -> 2
Q10: {=INDEX($AG$6:$AG$11,MATCH(1,$AF$6:$AF$11,0),0)} -> Home | S10: {=INDEX($AH$6:$AH$11,MATCH(1,$AF$6:$AF$11,0),0)} -> 485 | V10: =IF(ISBLANK(W10),"--",TEXT(W10,"mmmm")&" "&TEXT(W10,"YYYY")) -> October 2021 | W10: 44470 | AC10: Groceries | AD10: =SUMIFS(Table1[Amount $],Table1[Category],Snapshot!AC10,Table1[Month],Snapshot!$W$4)*-1 -> 0 | AE10: =RANK(AD10,$AD$6:$AD$35,0)+COUNTIF(AD$6:$AD10,AD10)-1 -> 9 | AF10: 5 | AG10: {=IF(INDEX($AD$6:$AD$35,MATCH(AF10,$AE$6:$AE$35,0),0)=0,"",INDEX($AC$6:$AC$35,MATCH(AF10,$AE$6:$AE$35,0),0))} | AH10: {=IF(INDEX($AD$6:$AD$35,MATCH(AF10,$AE$6:$AE$35,0),0)=0,0,INDEX($AD$6:$AD$35,MATCH(AF10,$AE$6:$AE$35,0),0))} -> 0 | AJ10: =DATE(YEAR(AJ9),MONTH(AJ9),DAY(AJ9)+1) -> 36530 | AK10: =IF(MONTH(AK9)=MONTH(DATE(YEAR(AK9),MONTH(AK9),DAY(AK9)+1)),DATE(YEAR(AK9),MONTH(AK9),DAY(AK9)+1),NA()) -> 44566 | AL10: =SUMIFS(Table1[Amount $],Table1[Category Type],"Expense",Table1[Date],Snapshot!AK10)*-1 -> 0 | AM10: =IF(AK10>TODAY(),NA(),SUM(AL$6:$AL10)) -> -50.9 | AN10: =IF(OR(AK10=EOMONTH($AK$6,0),AK10=TODAY()),AM10,NA()) -> #N/A | AO10: =IF(MONTH(AO9)=MONTH(DATE(YEAR(AO9),MONTH(AO9),DAY(AO9)+1)),DATE(YEAR(AO9),MONTH(AO9),DAY(AO9)+1),NA()) -> 44535 | AP10: =SUMIFS(Table1[Amount $],Table1[Category Type],"Expense",Table1[Date],Snapshot!AO10)*-1 -> 255.37 | AQ10: =IF(AO10<=EOMONTH($AO$6,0),SUM(AP$6:$AP10),NA()) -> -1200.49 | AR10: =IF(AO10=EOMONTH($AO$6,0),AQ10,NA()) -> #N/A | AT10: Hulu | AU10: =IF(ISBLANK(AT10),"",SUMIFS(Table1[Amount $],Table1[Merchant],Snapshot!AT10,Table1[Month],Snapshot!$W$4)*-1) -> 12.99 | AV10: =IF(ISBLANK(AT10),"",COUNTIFS(Table1[Merchant],Snapshot!AT10,Table1[Month],Snapshot!$W$4)) -> 1 | AW10: =IFERROR(RANK(AV10,$AV$6:$AV$200)+COUNTIF($AV$6:AV10,AV10)-1,"") -> 5 | AX10: =IFERROR(RANK(AU10,$AU$6:$AU$200)+COUNTIF($AU$6:AU10,AU10)-1,"") -> 7
V11: =IF(ISBLANK(W11),"--",TEXT(W11,"mmmm")&" "&TEXT(W11,"YYYY")) -> September 2021 | W11: 44440 | AC11: Health/Fitness | AD11: =SUMIFS(Table1[Amount $],Table1[Category],Snapshot!AC11,Table1[Month],Snapshot!$W$4)*-1 -> 0 | AE11: =RANK(AD11,$AD$6:$AD$35,0)+COUNTIF(AD$6:$AD11,AD11)-1 -> 10 | AF11: 6 | AG11: =IF(SUM(AH6:AH10)=SUM(AD6:AD35),"","All Other Categories") -> All Other Categories | AH11: =SUM(AD6:AD35)-SUM(AH6:AH10) -> -671.73 | AJ11: =DATE(YEAR(AJ10),MONTH(AJ10),DAY(AJ10)+1) -> 36531 | AK11: =IF(MONTH(AK10)=MONTH(DATE(YEAR(AK10),MONTH(AK10),DAY(AK10)+1)),DATE(YEAR(AK10),MONTH(AK10),DAY(AK10)+1),NA()) -> 44567 | AL11: =SUMIFS(Table1[Amount $],Table1[Category Type],"Expense",Table1[Date],Snapshot!AK11)*-1 -> 0 | AM11: =IF(AK11>TODAY(),NA(),SUM(AL$6:$AL11)) -> -50.9 | AN11: =IF(OR(AK11=EOMONTH($AK$6,0),AK11=TODAY()),AM11,NA()) -> -50.9 | AO11: =IF(MONTH(AO10)=MONTH(DATE(YEAR(AO10),MONTH(AO10),DAY(AO10)+1)),DATE(YEAR(AO10),MONTH(AO10),DAY(AO10)+1),NA()) -> 44536 | AP11: =SUMIFS(Table1[Amount $],Table1[Category Type],"Expense",Table1[Date],Snapshot!AO11)*-1 -> 1012.43 | AQ11: =IF(AO11<=EOMONTH($AO$6,0),SUM(AP$6:$AP11),NA()) -> -188.06 | AR11: =IF(AO11=EOMONTH($AO$6,0),AQ11,NA()) -> #N/A | AT11: Krystal And Saagar Dc | AU11: =IF(ISBLANK(AT11),"",SUMIFS(Table1[Amount $],Table1[Merchant],Snapshot!AT11,Table1[Month],Snapshot!$W$4)*-1) -> 10 | AV11: =IF(ISBLANK(AT11),"",COUNTIFS(Table1[Merchant],Snapshot!AT11,Table1[Month],Snapshot!$W$4)) -> 1 | AW11: =IFERROR(RANK(AV11,$AV$6:$AV$200)+COUNTIF($AV$6:AV11,AV11)-1,"") -> 6 | AX11: =IFERROR(RANK(AU11,$AU$6:$AU$200)+COUNTIF($AU$6:AU11,AU11)-1,"") -> 9
Q12: {=INDEX($AG$6:$AG$11,MATCH(2,$AF$6:$AF$11,0),0)} -> Restaurants/Dining | S12: {=INDEX($AH$6:$AH$11,MATCH(2,$AF$6:$AF$11,0),0)} -> 88.02 | V12: =IF(ISBLANK(W12),"--",TEXT(W12,"mmmm")&" "&TEXT(W12,"YYYY")) -> August 2021 | W12: 44409 | AC12: Home | AD12: =SUMIFS(Table1[Amount $],Table1[Category],Snapshot!AC12,Table1[Month],Snapshot!$W$4)*-1 -> 485 | AE12: =RANK(AD12,$AD$6:$AD$35,0)+COUNTIF(AD$6:$AD12,AD12)-1 -> 1 | AG12: Total | AH12: =SUM(AH6:AH11) -> -50.9 | AJ12: =DATE(YEAR(AJ11),MONTH(AJ11),DAY(AJ11)+1) -> 36532 | AK12: =IF(MONTH(AK11)=MONTH(DATE(YEAR(AK11),MONTH(AK11),DAY(AK11)+1)),DATE(YEAR(AK11),MONTH(AK11),DAY(AK11)+1),NA()) -> 44568 | AL12: =SUMIFS(Table1[Amount $],Table1[Category Type],"Expense",Table1[Date],Snapshot!AK12)*-1 -> 0 | AM12: =IF(AK12>TODAY(),NA(),SUM(AL$6:$AL12)) -> #N/A | AN12: =IF(OR(AK12=EOMONTH($AK$6,0),AK12=TODAY()),AM12,NA()) -> #N/A | AO12: =IF(MONTH(AO11)=MONTH(DATE(YEAR(AO11),MONTH(AO11),DAY(AO11)+1)),DATE(YEAR(AO11),MONTH(AO11),DAY(AO11)+1),NA()) -> 44537 | AP12: =SUMIFS(Table1[Amount $],Table1[Category Type],"Expense",Table1[Date],Snapshot!AO12)*-1 -> -5.99 | AQ12: =IF(AO12<=EOMONTH($AO$6,0),SUM(AP$6:$AP12),NA()) -> -194.05 | AR12: =IF(AO12=EOMONTH($AO$6,0),AQ12,NA()) -> #N/A | AT12: Jimmy Johns | AU12: =IF(ISBLANK(AT12),"",SUMIFS(Table1[Amount $],Table1[Merchant],Snapshot!AT12,Table1[Month],Snapshot!$W$4)*-1) -> 18.02 | AV12: =IF(ISBLANK(AT12),"",COUNTIFS(Table1[Merchant],Snapshot!AT12,Table1[Month],Snapshot!$W$4)) -> 1 | AW12: =IFERROR(RANK(AV12,$AV$6:$AV$200)+COUNTIF($AV$6:AV12,AV12)-1,"") -> 7 | AX12: =IFERROR(RANK(AU12,$AU$6:$AU$200)+COUNTIF($AU$6:AU12,AU12)-1,"") -> 5
V13: =IF(ISBLANK(W13),"--",TEXT(W13,"mmmm")&" "&TEXT(W13,"YYYY")) -> July 2021 | W13: 44378 | AC13: Income | AD13: =SUMIFS(Table1[Amount $],Table1[Category],Snapshot!AC13,Table1[Month],Snapshot!$W$4)*-1 -> -671.73 | AE13: =RANK(AD13,$AD$6:$AD$35,0)+COUNTIF(AD$6:$AD13,AD13)-1 -> 30 | AJ13: =DATE(YEAR(AJ12),MONTH(AJ12),DAY(AJ12)+1) -> 36533 | AK13: =IF(MONTH(AK12)=MONTH(DATE(YEAR(AK12),MONTH(AK12),DAY(AK12)+1)),DATE(YEAR(AK12),MONTH(AK12),DAY(AK12)+1),NA()) -> 44569 | AL13: =SUMIFS(Table1[Amount $],Table1[Category Type],"Expense",Table1[Date],Snapshot!AK13)*-1 -> 0 | AM13: =IF(AK13>TODAY(),NA(),SUM(AL$6:$AL13)) -> #N/A | AN13: =IF(OR(AK13=EOMONTH($AK$6,0),AK13=TODAY()),AM13,NA()) -> #N/A | AO13: =IF(MONTH(AO12)=MONTH(DATE(YEAR(AO12),MONTH(AO12),DAY(AO12)+1)),DATE(YEAR(AO12),MONTH(AO12),DAY(AO12)+1),NA()) -> 44538 | AP13: =SUMIFS(Table1[Amount $],Table1[Category Type],"Expense",Table1[Date],Snapshot!AO13)*-1 -> 37.3 | AQ13: =IF(AO13<=EOMONTH($AO$6,0),SUM(AP$6:$AP13),NA()) -> -156.75 | AR13: =IF(AO13=EOMONTH($AO$6,0),AQ13,NA()) -> #N/A | AT13: Olive Garden | AU13: =IF(ISBLANK(AT13),"",SUMIFS(Table1[Amount $],Table1[Merchant],Snapshot!AT13,Table1[Month],Snapshot!$W$4)*-1) -> 60 | AV13: =IF(ISBLANK(AT13),"",COUNTIFS(Table1[Merchant],Snapshot!AT13,Table1[Month],Snapshot!$W$4)) -> 1 | AW13: =IFERROR(RANK(AV13,$AV$6:$AV$200)+COUNTIF($AV$6:AV13,AV13)-1,"") -> 8 | AX13: =IFERROR(RANK(AU13,$AU$6:$AU$200)+COUNTIF($AU$6:AU13,AU13)-1,"") -> 4
Q14: {=INDEX($AG$6:$AG$11,MATCH(3,$AF$6:$AF$11,0),0)} -> Shopping | S14: {=INDEX($AH$6:$AH$11,MATCH(3,$AF$6:$AF$11,0),0)} -> 37.81 | V14: =IF(ISBLANK(W14),"--",TEXT(W14,"mmmm")&" "&TEXT(W14,"YYYY")) -> June 2021 | W14: 44348 | AC14: Misc | AD14: =SUMIFS(Table1[Amount $],Table1[Category],Snapshot!AC14,Table1[Month],Snapshot!$W$4)*-1 -> 0 | AE14: =RANK(AD14,$AD$6:$AD$35,0)+COUNTIF(AD$6:$AD14,AD14)-1 -> 11 | AJ14: =DATE(YEAR(AJ13),MONTH(AJ13),DAY(AJ13)+1) -> 36534 | AK14: =IF(MONTH(AK13)=MONTH(DATE(YEAR(AK13),MONTH(AK13),DAY(AK13)+1)),DATE(YEAR(AK13),MONTH(AK13),DAY(AK13)+1),NA()) -> 44570 | AL14: =SUMIFS(Table1[Amount $],Table1[Category Type],"Expense",Table1[Date],Snapshot!AK14)*-1 -> 0 | AM14: =IF(AK14>TODAY(),NA(),SUM(AL$6:$AL14)) -> #N/A | AN14: =IF(OR(AK14=EOMONTH($AK$6,0),AK14=TODAY()),AM14,NA()) -> #N/A | AO14: =IF(MONTH(AO13)=MONTH(DATE(YEAR(AO13),MONTH(AO13),DAY(AO13)+1)),DATE(YEAR(AO13),MONTH(AO13),DAY(AO13)+1),NA()) -> 44539 | AP14: =SUMIFS(Table1[Amount $],Table1[Category Type],"Expense",Table1[Date],Snapshot!AO14)*-1 -> 579.36 | AQ14: =IF(AO14<=EOMONTH($AO$6,0),SUM(AP$6:$AP14),NA()) -> 422.61 | AR14: =IF(AO14=EOMONTH($AO$6,0),AQ14,NA()) -> #N/A | AT14: Netflix | AU14: =IF(ISBLANK(AT14),"",SUMIFS(Table1[Amount $],Table1[Merchant],Snapshot!AT14,Table1[Month],Snapshot!$W$4)*-1) -> 14.83 | AV14: =IF(ISBLANK(AT14),"",COUNTIFS(Table1[Merchant],Snapshot!AT14,Table1[Month],Snapshot!$W$4)) -> 1 | AW14: =IFERROR(RANK(AV14,$AV$6:$AV$200)+COUNTIF($AV$6:AV14,AV14)-1,"") -> 9 | AX14: =IFERROR(RANK(AU14,$AU$6:$AU$200)+COUNTIF($AU$6:AU14,AU14)-1,"") -> 6
V15: =IF(ISBLANK(W15),"--",TEXT(W15,"mmmm")&" "&TEXT(W15,"YYYY")) -> May 2021 | W15: 44317 | AC15: Mortgage/Rent | AD15: =SUMIFS(Table1[Amount $],Table1[Category],Snapshot!AC15,Table1[Month],Snapshot!$W$4)*-1 -> 0 | AE15: =RANK(AD15,$AD$6:$AD$35,0)+COUNTIF(AD$6:$AD15,AD15)-1 -> 12 | AJ15: =DATE(YEAR(AJ14),MONTH(AJ14),DAY(AJ14)+1) -> 36535 | AK15: =IF(MONTH(AK14)=MONTH(DATE(YEAR(AK14),MONTH(AK14),DAY(AK14)+1)),DATE(YEAR(AK14),MONTH(AK14),DAY(AK14)+1),NA()) -> 44571 | AL15: =SUMIFS(Table1[Amount $],Table1[Category Type],"Expense",Table1[Date],Snapshot!AK15)*-1 -> 0 | AM15: =IF(AK15>TODAY(),NA(),SUM(AL$6:$AL15)) -> #N/A | AN15: =IF(OR(AK15=EOMONTH($AK$6,0),AK15=TODAY()),AM15,NA()) -> #N/A | AO15: =IF(MONTH(AO14)=MONTH(DATE(YEAR(AO14),MONTH(AO14),DAY(AO14)+1)),DATE(YEAR(AO14),MONTH(AO14),DAY(AO14)+1),NA()) -> 44540 | AP15: =SUMIFS(Table1[Amount $],Table1[Category Type],"Expense",Table1[Date],Snapshot!AO15)*-1 -> -26.79 | AQ15: =IF(AO15<=EOMONTH($AO$6,0),SUM(AP$6:$AP15),NA()) -> 395.82 | AR15: =IF(AO15=EOMONTH($AO$6,0),AQ15,NA()) -> #N/A | AT15: Spotify | AU15: =IF(ISBLANK(AT15),"",SUMIFS(Table1[Amount $],Table1[Merchant],Snapshot!AT15,Table1[Month],Snapshot!$W$4)*-1) -> 9.99 | AV15: =IF(ISBLANK(AT15),"",COUNTIFS(Table1[Merchant],Snapshot!AT15,Table1[Month],Snapshot!$W$4)) -> 1 | AW15: =IFERROR(RANK(AV15,$AV$6:$AV$200)+COUNTIF($AV$6:AV15,AV15)-1,"") -> 10 | AX15: =IFERROR(RANK(AU15,$AU$6:$AU$200)+COUNTIF($AU$6:AU15,AU15)-1,"") -> 10
Q16: {=INDEX($AG$6:$AG$11,MATCH(4,$AF$6:$AF$11,0),0)} -> Payment | S16: {=INDEX($AH$6:$AH$11,MATCH(4,$AF$6:$AF$11,0),0)} -> 10 | V16: =IF(ISBLANK(W16),"--",TEXT(W16,"mmmm")&" "&TEXT(W16,"YYYY")) -> April 2021 | W16: 44287 | AC16: Payment | AD16: =SUMIFS(Table1[Amount $],Table1[Category],Snapshot!AC16,Table1[Month],Snapshot!$W$4)*-1 -> 10 | AE16: =RANK(AD16,$AD$6:$AD$35,0)+COUNTIF(AD$6:$AD16,AD16)-1 -> 4 | AJ16: =DATE(YEAR(AJ15),MONTH(AJ15),DAY(AJ15)+1) -> 36536 | AK16: =IF(MONTH(AK15)=MONTH(DATE(YEAR(AK15),MONTH(AK15),DAY(AK15)+1)),DATE(YEAR(AK15),MONTH(AK15),DAY(AK15)+1),NA()) -> 44572 | AL16: =SUMIFS(Table1[Amount $],Table1[Category Type],"Expense",Table1[Date],Snapshot!AK16)*-1 -> 0 | AM16: =IF(AK16>TODAY(),NA(),SUM(AL$6:$AL16)) -> #N/A | AN16: =IF(OR(AK16=EOMONTH($AK$6,0),AK16=TODAY()),AM16,NA()) -> #N/A | AO16: =IF(MONTH(AO15)=MONTH(DATE(YEAR(AO15),MONTH(AO15),DAY(AO15)+1)),DATE(YEAR(AO15),MONTH(AO15),DAY(AO15)+1),NA()) -> 44541 | AP16: =SUMIFS(Table1[Amount $],Table1[Category Type],"Expense",Table1[Date],Snapshot!AO16)*-1 -> 30.39 | AQ16: =IF(AO16<=EOMONTH($AO$6,0),SUM(AP$6:$AP16),NA()) -> 426.21 | AR16: =IF(AO16=EOMONTH($AO$6,0),AQ16,NA()) -> #N/A | AU16: =IF(ISBLANK(AT16),"",SUMIFS(Table1[Amount $],Table1[Merchant],Snapshot!AT16,Table1[Month],Snapshot!$W$4)*-1) | AV16: =IF(ISBLANK(AT16),"",COUNTIFS(Table1[Merchant],Snapshot!AT16,Table1[Month],Snapshot!$W$4)) | AW16: =IFERROR(RANK(AV16,$AV$6:$AV$200)+COUNTIF($AV$6:AV16,AV16)-1,"") | AX16: =IFERROR(RANK(AU16,$AU$6:$AU$200)+COUNTIF($AU$6:AU16,AU16)-1,"")
V17: =IF(ISBLANK(W17),"--",TEXT(W17,"mmmm")&" "&TEXT(W17,"YYYY")) -> March 2021 | W17: 44256 | AC17: Professional Services | AD17: =SUMIFS(Table1[Amount $],Table1[Category],Snapshot!AC17,Table1[Month],Snapshot!$W$4)*-1 -> 0 | AE17: =RANK(AD17,$AD$6:$AD$35,0)+COUNTIF(AD$6:$AD17,AD17)-1 -> 13 | AJ17: =DATE(YEAR(AJ16),MONTH(AJ16),DAY(AJ16)+1) -> 36537 | AK17: =IF(MONTH(AK16)=MONTH(DATE(YEAR(AK16),MONTH(AK16),DAY(AK16)+1)),DATE(YEAR(AK16),MONTH(AK16),DAY(AK16)+1),NA()) -> 44573 | AL17: =SUMIFS(Table1[Amount $],Table1[Category Type],"Expense",Table1[Date],Snapshot!AK17)*-1 -> 0 | AM17: =IF(AK17>TODAY(),NA(),SUM(AL$6:$AL17)) -> #N/A | AN17: =IF(OR(AK17=EOMONTH($AK$6,0),AK17=TODAY()),AM17,NA()) -> #N/A | AO17: =IF(MONTH(AO16)=MONTH(DATE(YEAR(AO16),MONTH(AO16),DAY(AO16)+1)),DATE(YEAR(AO16),MONTH(AO16),DAY(AO16)+1),NA()) -> 44542 | AP17: =SUMIFS(Table1[Amount $],Table1[Category Type],"Expense",Table1[Date],Snapshot!AO17)*-1 -> 179.52 | AQ17: =IF(AO17<=EOMONTH($AO$6,0),SUM(AP$6:$AP17),NA()) -> 605.73 | AR17: =IF(AO17=EOMONTH($AO$6,0),AQ17,NA()) -> #N/A | AU17: =IF(ISBLANK(AT17),"",SUMIFS(Table1[Amount $],Table1[Merchant],Snapshot!AT17,Table1[Month],Snapshot!$W$4)*-1) | AV17: =IF(ISBLANK(AT17),"",COUNTIFS(Table1[Merchant],Snapshot!AT17,Table1[Month],Snapshot!$W$4)) | AW17: =IFERROR(RANK(AV17,$AV$6:$AV$200)+COUNTIF($AV$6:AV17,AV17)-1,"") | AX17: =IFERROR(RANK(AU17,$AU$6:$AU$200)+COUNTIF($AU$6:AU17,AU17)-1,"")
Q18: {=INDEX($AG$6:$AG$11,MATCH(5,$AF$6:$AF$11,0),0)} | S18: {=INDEX($AH$6:$AH$11,MATCH(5,$AF$6:$AF$11,0),0)} -> 0 | V18: =IF(ISBLANK(W18),"--",TEXT(W18,"mmmm")&" "&TEXT(W18,"YYYY")) -> February 2021 | W18: 44228 | AC18: Refund | AD18: =SUMIFS(Table1[Amount $],Table1[Category],Snapshot!AC18,Table1[Month],Snapshot!$W$4)*-1 -> 0 | AE18: =RANK(AD18,$AD$6:$AD$35,0)+COUNTIF(AD$6:$AD18,AD18)-1 -> 14 | AJ18: =DATE(YEAR(AJ17),MONTH(AJ17),DAY(AJ17)+1) -> 36538 | AK18: =IF(MONTH(AK17)=MONTH(DATE(YEAR(AK17),MONTH(AK17),DAY(AK17)+1)),DATE(YEAR(AK17),MONTH(AK17),DAY(AK17)+1),NA()) -> 44574 | AL18: =SUMIFS(Table1[Amount $],Table1[Category Type],"Expense",Table1[Date],Snapshot!AK18)*-1 -> 0 | AM18: =IF(AK18>TODAY(),NA(),SUM(AL$6:$AL18)) -> #N/A | AN18: =IF(OR(AK18=EOMONTH($AK$6,0),AK18=TODAY()),AM18,NA()) -> #N/A | AO18: =IF(MONTH(AO17)=MONTH(DATE(YEAR(AO17),MONTH(AO17),DAY(AO17)+1)),DATE(YEAR(AO17),MONTH(AO17),DAY(AO17)+1),NA()) -> 44543 | AP18: =SUMIFS(Table1[Amount $],Table1[Category Type],"Expense",Table1[Date],Snapshot!AO18)*-1 -> 129.04 | AQ18: =IF(AO18<=EOMONTH($AO$6,0),SUM(AP$6:$AP18),NA()) -> 734.77 | AR18: =IF(AO18=EOMONTH($AO$6,0),AQ18,NA()) -> #N/A | AU18: =IF(ISBLANK(AT18),"",SUMIFS(Table1[Amount $],Table1[Merchant],Snapshot!AT18,Table1[Month],Snapshot!$W$4)*-1) | AV18: =IF(ISBLANK(AT18),"",COUNTIFS(Table1[Merchant],Snapshot!AT18,Table1[Month],Snapshot!$W$4)) | AW18: =IFERROR(RANK(AV18,$AV$6:$AV$200)+COUNTIF($AV$6:AV18,AV18)-1,"") | AX18: =IFERROR(RANK(AU18,$AU$6:$AU$200)+COUNTIF($AU$6:AU18,AU18)-1,"")
V19: =IF(ISBLANK(W19),"--",TEXT(W19,"mmmm")&" "&TEXT(W19,"YYYY")) -> January 2021 | W19: 44197 | AC19: Restaurants/Dining | AD19: =SUMIFS(Table1[Amount $],Table1[Category],Snapshot!AC19,Table1[Month],Snapshot!$W$4)*-1 -> 88.02 | AE19: =RANK(AD19,$AD$6:$AD$35,0)+COUNTIF(AD$6:$AD19,AD19)-1 -> 2 | AJ19: =DATE(YEAR(AJ18),MONTH(AJ18),DAY(AJ18)+1) -> 36539 | AK19: =IF(MONTH(AK18)=MONTH(DATE(YEAR(AK18),MONTH(AK18),DAY(AK18)+1)),DATE(YEAR(AK18),MONTH(AK18),DAY(AK18)+1),NA()) -> 44575 | AL19: =SUMIFS(Table1[Amount $],Table1[Category Type],"Expense",Table1[Date],Snapshot!AK19)*-1 -> 0 | AM19: =IF(AK19>TODAY(),NA(),SUM(AL$6:$AL19)) -> #N/A | AN19: =IF(OR(AK19=EOMONTH($AK$6,0),AK19=TODAY()),AM19,NA()) -> #N/A | AO19: =IF(MONTH(AO18)=MONTH(DATE(YEAR(AO18),MONTH(AO18),DAY(AO18)+1)),DATE(YEAR(AO18),MONTH(AO18),DAY(AO18)+1),NA()) -> 44544 | AP19: =SUMIFS(Table1[Amount $],Table1[Category Type],"Expense",Table1[Date],Snapshot!AO19)*-1 -> 134.03 | AQ19: =IF(AO19<=EOMONTH($AO$6,0),SUM(AP$6:$AP19),NA()) -> 868.8 | AR19: =IF(AO19=EOMONTH($AO$6,0),AQ19,NA()) -> #N/A | AU19: =IF(ISBLANK(AT19),"",SUMIFS(Table1[Amount $],Table1[Merchant],Snapshot!AT19,Table1[Month],Snapshot!$W$4)*-1) | AV19: =IF(ISBLANK(AT19),"",COUNTIFS(Table1[Merchant],Snapshot!AT19,Table1[Month],Snapshot!$W$4)) | AW19: =IFERROR(RANK(AV19,$AV$6:$AV$200)+COUNTIF($AV$6:AV19,AV19)-1,"") | AX19: =IFERROR(RANK(AU19,$AU$6:$AU$200)+COUNTIF($AU$6:AU19,AU19)-1,"")
Q20: {=INDEX($AG$6:$AG$11,MATCH(6,$AF$6:$AF$11,0),0)} -> All Other Categories | S20: {=INDEX($AH$6:$AH$11,MATCH(6,$AF$6:$AF$11,0),0)} -> -671.73 | V20: =IF(ISBLANK(W20),"--",TEXT(W20,"mmmm")&" "&TEXT(W20,"YYYY")) -> December 2020 | W20: 44166 | AC20: Shopping | AD20: =SUMIFS(Table1[Amount $],Table1[Category],Snapshot!AC20,Table1[Month],Snapshot!$W$4)*-1 -> 37.81 | AE20: =RANK(AD20,$AD$6:$AD$35,0)+COUNTIF(AD$6:$AD20,AD20)-1 -> 3 | AJ20: =DATE(YEAR(AJ19),MONTH(AJ19),DAY(AJ19)+1) -> 36540 | AK20: =IF(MONTH(AK19)=MONTH(DATE(YEAR(AK19),MONTH(AK19),DAY(AK19)+1)),DATE(YEAR(AK19),MONTH(AK19),DAY(AK19)+1),NA()) -> 44576 | AL20: =SUMIFS(Table1[Amount $],Table1[Category Type],"Expense",Table1[Date],Snapshot!AK20)*-1 -> 0 | AM20: =IF(AK20>TODAY(),NA(),SUM(AL$6:$AL20)) -> #N/A | AN20: =IF(OR(AK20=EOMONTH($AK$6,0),AK20=TODAY()),AM20,NA()) -> #N/A | AO20: =IF(MONTH(AO19)=MONTH(DATE(YEAR(AO19),MONTH(AO19),DAY(AO19)+1)),DATE(YEAR(AO19),MONTH(AO19),DAY(AO19)+1),NA()) -> 44545 | AP20: =SUMIFS(Table1[Amount $],Table1[Category Type],"Expense",Table1[Date],Snapshot!AO20)*-1 -> -100 | AQ20: =IF(AO20<=EOMONTH($AO$6,0),SUM(AP$6:$AP20),NA()) -> 768.8 | AR20: =IF(AO20=EOMONTH($AO$6,0),AQ20,NA()) -> #N/A | AU20: =IF(ISBLANK(AT20),"",SUMIFS(Table1[Amount $],Table1[Merchant],Snapshot!AT20,Table1[Month],Snapshot!$W$4)*-1) | AV20: =IF(ISBLANK(AT20),"",COUNTIFS(Table1[Merchant],Snapshot!AT20,Table1[Month],Snapshot!$W$4)) | AW20: =IFERROR(RANK(AV20,$AV$6:$AV$200)+COUNTIF($AV$6:AV20,AV20)-1,"") | AX20: =IFERROR(RANK(AU20,$AU$6:$AU$200)+COUNTIF($AU$6:AU20,AU20)-1,"")
V21: =IF(ISBLANK(W21),"--",TEXT(W21,"mmmm")&" "&TEXT(W21,"YYYY")) -> November 2020 | W21: 44136 | AC21: Transfer | AD21: =SUMIFS(Table1[Amount $],Table1[Category],Snapshot!AC21,Table1[Month],Snapshot!$W$4)*-1 -> 0 | AE21: =RANK(AD21,$AD$6:$AD$35,0)+COUNTIF(AD$6:$AD21,AD21)-1 -> 15 | AJ21: =DATE(YEAR(AJ20),MONTH(AJ20),DAY(AJ20)+1) -> 36541 | AK21: =IF(MONTH(AK20)=MONTH(DATE(YEAR(AK20),MONTH(AK20),DAY(AK20)+1)),DATE(YEAR(AK20),MONTH(AK20),DAY(AK20)+1),NA()) -> 44577 | AL21: =SUMIFS(Table1[Amount $],Table1[Category Type],"Expense",Table1[Date],Snapshot!AK21)*-1 -> 0 | AM21: =IF(AK21>TODAY(),NA(),SUM(AL$6:$AL21)) -> #N/A | AN21: =IF(OR(AK21=EOMONTH($AK$6,0),AK21=TODAY()),AM21,NA()) -> #N/A | AO21: =IF(MONTH(AO20)=MONTH(DATE(YEAR(AO20),MONTH(AO20),DAY(AO20)+1)),DATE(YEAR(AO20),MONTH(AO20),DAY(AO20)+1),NA()) -> 44546 | AP21: =SUMIFS(Table1[Amount $],Table1[Category Type],"Expense",Table1[Date],Snapshot!AO21)*-1 -> -2327.26 | AQ21: =IF(AO21<=EOMONTH($AO$6,0),SUM(AP$6:$AP21),NA()) -> -1558.46 | AR21: =IF(AO21=EOMONTH($AO$6,0),AQ21,NA()) -> #N/A | AU21: =IF(ISBLANK(AT21),"",SUMIFS(Table1[Amount $],Table1[Merchant],Snapshot!AT21,Table1[Month],Snapshot!$W$4)*-1) | AV21: =IF(ISBLANK(AT21),"",COUNTIFS(Table1[Merchant],Snapshot!AT21,Table1[Month],Snapshot!$W$4)) | AW21: =IFERROR(RANK(AV21,$AV$6:$AV$200)+COUNTIF($AV$6:AV21,AV21)-1,"") | AX21: =IFERROR(RANK(AU21,$AU$6:$AU$200)+COUNTIF($AU$6:AU21,AU21)-1,"")
P22: Total spending | S22: =S10+S12+S14+S16+S18+S20 -> -50.9 | V22: =IF(ISBLANK(W22),"--",TEXT(W22,"mmmm")&" "&TEXT(W22,"YYYY")) -> October 2020 | W22: 44105 | AC22: Travel | AD22: =SUMIFS(Table1[Amount $],Table1[Category],Snapshot!AC22,Table1[Month],Snapshot!$W$4)*-1 -> 0 | AE22: =RANK(AD22,$AD$6:$AD$35,0)+COUNTIF(AD$6:$AD22,AD22)-1 -> 16 | AJ22: =DATE(YEAR(AJ21),MONTH(AJ21),DAY(AJ21)+1) -> 36542 | AK22: =IF(MONTH(AK21)=MONTH(DATE(YEAR(AK21),MONTH(AK21),DAY(AK21)+1)),DATE(YEAR(AK21),MONTH(AK21),DAY(AK21)+1),NA()) -> 44578 | AL22: =SUMIFS(Table1[Amount $],Table1[Category Type],"Expense",Table1[Date],Snapshot!AK22)*-1 -> 0 | AM22: =IF(AK22>TODAY(),NA(),SUM(AL$6:$AL22)) -> #N/A | AN22: =IF(OR(AK22=EOMONTH($AK$6,0),AK22=TODAY()),AM22,NA()) -> #N/A | AO22: =IF(MONTH(AO21)=MONTH(DATE(YEAR(AO21),MONTH(AO21),DAY(AO21)+1)),DATE(YEAR(AO21),MONTH(AO21),DAY(AO21)+1),NA()) -> 44547 | AP22: =SUMIFS(Table1[Amount $],Table1[Category Type],"Expense",Table1[Date],Snapshot!AO22)*-1 -> 462.84 | AQ22: =IF(AO22<=EOMONTH($AO$6,0),SUM(AP$6:$AP22),NA()) -> -1095.62 | AR22: =IF(AO22=EOMONTH($AO$6,0),AQ22,NA()) -> #N/A | AU22: =IF(ISBLANK(AT22),"",SUMIFS(Table1[Amount $],Table1[Merchant],Snapshot!AT22,Table1[Month],Snapshot!$W$4)*-1) | AV22: =IF(ISBLANK(AT22),"",COUNTIFS(Table1[Merchant],Snapshot!AT22,Table1[Month],Snapshot!$W$4)) | AW22: =IFERROR(RANK(AV22,$AV$6:$AV$200)+COUNTIF($AV$6:AV22,AV22)-1,"") | AX22: =IFERROR(RANK(AU22,$AU$6:$AU$200)+COUNTIF($AU$6:AU22,AU22)-1,"")
V23: =IF(ISBLANK(W23),"--",TEXT(W23,"mmmm")&" "&TEXT(W23,"YYYY")) -> September 2020 | W23: 44075 | AC23: Uncategorized | AD23: =SUMIFS(Table1[Amount $],Table1[Category],Snapshot!AC23,Table1[Month],Snapshot!$W$4)*-1 -> 0 | AE23: =RANK(AD23,$AD$6:$AD$35,0)+COUNTIF(AD$6:$AD23,AD23)-1 -> 17 | AJ23: =DATE(YEAR(AJ22),MONTH(AJ22),DAY(AJ22)+1) -> 36543 | AK23: =IF(MONTH(AK22)=MONTH(DATE(YEAR(AK22),MONTH(AK22),DAY(AK22)+1)),DATE(YEAR(AK22),MONTH(AK22),DAY(AK22)+1),NA()) -> 44579 | AL23: =SUMIFS(Table1[Amount $],Table1[Category Type],"Expense",Table1[Date],Snapshot!AK23)*-1 -> 0 | AM23: =IF(AK23>TODAY(),NA(),SUM(AL$6:$AL23)) -> #N/A | AN23: =IF(OR(AK23=EOMONTH($AK$6,0),AK23=TODAY()),AM23,NA()) -> #N/A | AO23: =IF(MONTH(AO22)=MONTH(DATE(YEAR(AO22),MONTH(AO22),DAY(AO22)+1)),DATE(YEAR(AO22),MONTH(AO22),DAY(AO22)+1),NA()) -> 44548 | AP23: =SUMIFS(Table1[Amount $],Table1[Category Type],"Expense",Table1[Date],Snapshot!AO23)*-1 -> 271.33 | AQ23: =IF(AO23<=EOMONTH($AO$6,0),SUM(AP$6:$AP23),NA()) -> -824.29 | AR23: =IF(AO23=EOMONTH($AO$6,0),AQ23,NA()) -> #N/A | AU23: =IF(ISBLANK(AT23),"",SUMIFS(Table1[Amount $],Table1[Merchant],Snapshot!AT23,Table1[Month],Snapshot!$W$4)*-1) | AV23: =IF(ISBLANK(AT23),"",COUNTIFS(Table1[Merchant],Snapshot!AT23,Table1[Month],Snapshot!$W$4)) | AW23: =IFERROR(RANK(AV23,$AV$6:$AV$200)+COUNTIF($AV$6:AV23,AV23)-1,"") | AX23: =IFERROR(RANK(AU23,$AU$6:$AU$200)+COUNTIF($AU$6:AU23,AU23)-1,"")
V24: =IF(ISBLANK(W24),"--",TEXT(W24,"mmmm")&" "&TEXT(W24,"YYYY")) -> August 2020 | W24: 44044 | AC24: Food | AD24: =SUMIFS(Table1[Amount $],Table1[Category],Snapshot!AC24,Table1[Month],Snapshot!$W$4)*-1 -> 0 | AE24: =RANK(AD24,$AD$6:$AD$35,0)+COUNTIF(AD$6:$AD24,AD24)-1 -> 18 | AJ24: =DATE(YEAR(AJ23),MONTH(AJ23),DAY(AJ23)+1) -> 36544 | AK24: =IF(MONTH(AK23)=MONTH(DATE(YEAR(AK23),MONTH(AK23),DAY(AK23)+1)),DATE(YEAR(AK23),MONTH(AK23),DAY(AK23)+1),NA()) -> 44580 | AL24: =SUMIFS(Table1[Amount $],Table1[Category Type],"Expense",Table1[Date],Snapshot!AK24)*-1 -> 0 | AM24: =IF(AK24>TODAY(),NA(),SUM(AL$6:$AL24)) -> #N/A | AN24: =IF(OR(AK24=EOMONTH($AK$6,0),AK24=TODAY()),AM24,NA()) -> #N/A | AO24: =IF(MONTH(AO23)=MONTH(DATE(YEAR(AO23),MONTH(AO23),DAY(AO23)+1)),DATE(YEAR(AO23),MONTH(AO23),DAY(AO23)+1),NA()) -> 44549 | AP24: =SUMIFS(Table1[Amount $],Table1[Category Type],"Expense",Table1[Date],Snapshot!AO24)*-1 -> 340.97 | AQ24: =IF(AO24<=EOMONTH($AO$6,0),SUM(AP$6:$AP24),NA()) -> -483.32 | AR24: =IF(AO24=EOMONTH($AO$6,0),AQ24,NA()) -> #N/A | AU24: =IF(ISBLANK(AT24),"",SUMIFS(Table1[Amount $],Table1[Merchant],Snapshot!AT24,Table1[Month],Snapshot!$W$4)*-1) | AV24: =IF(ISBLANK(AT24),"",COUNTIFS(Table1[Merchant],Snapshot!AT24,Table1[Month],Snapshot!$W$4)) | AW24: =IFERROR(RANK(AV24,$AV$6:$AV$200)+COUNTIF($AV$6:AV24,AV24)-1,"") | AX24: =IFERROR(RANK(AU24,$AU$6:$AU$200)+COUNTIF($AU$6:AU24,AU24)-1,"")
V25: =IF(ISBLANK(W25),"--",TEXT(W25,"mmmm")&" "&TEXT(W25,"YYYY")) -> July 2020 | W25: 44013 | AC25: Insurance | AD25: =SUMIFS(Table1[Amount $],Table1[Category],Snapshot!AC25,Table1[Month],Snapshot!$W$4)*-1 -> 0 | AE25: =RANK(AD25,$AD$6:$AD$35,0)+COUNTIF(AD$6:$AD25,AD25)-1 -> 19 | AJ25: =DATE(YEAR(AJ24),MONTH(AJ24),DAY(AJ24)+1) -> 36545 | AK25: =IF(MONTH(AK24)=MONTH(DATE(YEAR(AK24),MONTH(AK24),DAY(AK24)+1)),DATE(YEAR(AK24),MONTH(AK24),DAY(AK24)+1),NA()) -> 44581 | AL25: =SUMIFS(Table1[Amount $],Table1[Category Type],"Expense",Table1[Date],Snapshot!AK25)*-1 -> 0 | AM25: =IF(AK25>TODAY(),NA(),SUM(AL$6:$AL25)) -> #N/A | AN25: =IF(OR(AK25=EOMONTH($AK$6,0),AK25=TODAY()),AM25,NA()) -> #N/A | AO25: =IF(MONTH(AO24)=MONTH(DATE(YEAR(AO24),MONTH(AO24),DAY(AO24)+1)),DATE(YEAR(AO24),MONTH(AO24),DAY(AO24)+1),NA()) -> 44550 | AP25: =SUMIFS(Table1[Amount $],Table1[Category Type],"Expense",Table1[Date],Snapshot!AO25)*-1 -> 556.71 | AQ25: =IF(AO25<=EOMONTH($AO$6,0),SUM(AP$6:$AP25),NA()) -> 73.39 | AR25: =IF(AO25=EOMONTH($AO$6,0),AQ25,NA()) -> #N/A | AU25: =IF(ISBLANK(AT25),"",SUMIFS(Table1[Amount $],Table1[Merchant],Snapshot!AT25,Table1[Month],Snapshot!$W$4)*-1) | AV25: =IF(ISBLANK(AT25),"",COUNTIFS(Table1[Merchant],Snapshot!AT25,Table1[Month],Snapshot!$W$4)) | AW25: =IFERROR(RANK(AV25,$AV$6:$AV$200)+COUNTIF($AV$6:AV25,AV25)-1,"") | AX25: =IFERROR(RANK(AU25,$AU$6:$AU$200)+COUNTIF($AU$6:AU25,AU25)-1,"")
V26: =IF(ISBLANK(W26),"--",TEXT(W26,"mmmm")&" "&TEXT(W26,"YYYY")) -> June 2020 | W26: 43983 | AC26: Medical & Healthcare | AD26: =SUMIFS(Table1[Amount $],Table1[Category],Snapshot!AC26,Table1[Month],Snapshot!$W$4)*-1 -> 0 | AE26: =RANK(AD26,$AD$6:$AD$35,0)+COUNTIF(AD$6:$AD26,AD26)-1 -> 20 | AJ26: =DATE(YEAR(AJ25),MONTH(AJ25),DAY(AJ25)+1) -> 36546 | AK26: =IF(MONTH(AK25)=MONTH(DATE(YEAR(AK25),MONTH(AK25),DAY(AK25)+1)),DATE(YEAR(AK25),MONTH(AK25),DAY(AK25)+1),NA()) -> 44582 | AL26: =SUMIFS(Table1[Amount $],Table1[Category Type],"Expense",Table1[Date],Snapshot!AK26)*-1 -> 0 | AM26: =IF(AK26>TODAY(),NA(),SUM(AL$6:$AL26)) -> #N/A | AN26: =IF(OR(AK26=EOMONTH($AK$6,0),AK26=TODAY()),AM26,NA()) -> #N/A | AO26: =IF(MONTH(AO25)=MONTH(DATE(YEAR(AO25),MONTH(AO25),DAY(AO25)+1)),DATE(YEAR(AO25),MONTH(AO25),DAY(AO25)+1),NA()) -> 44551 | AP26: =SUMIFS(Table1[Amount $],Table1[Category Type],"Expense",Table1[Date],Snapshot!AO26)*-1 -> 42.73 | AQ26: =IF(AO26<=EOMONTH($AO$6,0),SUM(AP$6:$AP26),NA()) -> 116.12 | AR26: =IF(AO26=EOMONTH($AO$6,0),AQ26,NA()) -> #N/A | AU26: =IF(ISBLANK(AT26),"",SUMIFS(Table1[Amount $],Table1[Merchant],Snapshot!AT26,Table1[Month],Snapshot!$W$4)*-1) | AV26: =IF(ISBLANK(AT26),"",COUNTIFS(Table1[Merchant],Snapshot!AT26,Table1[Month],Snapshot!$W$4)) | AW26: =IFERROR(RANK(AV26,$AV$6:$AV$200)+COUNTIF($AV$6:AV26,AV26)-1,"") | AX26: =IFERROR(RANK(AU26,$AU$6:$AU$200)+COUNTIF($AU$6:AU26,AU26)-1,"")
D27: Cumulative spending throughout month | V27: =IF(ISBLANK(W27),"--",TEXT(W27,"mmmm")&" "&TEXT(W27,"YYYY")) -> May 2020 | W27: 43952 | AC27: Personal Spending | AD27: =SUMIFS(Table1[Amount $],Table1[Category],Snapshot!AC27,Table1[Month],Snapshot!$W$4)*-1 -> 0 | AE27: =RANK(AD27,$AD$6:$AD$35,0)+COUNTIF(AD$6:$AD27,AD27)-1 -> 21 | AJ27: =DATE(YEAR(AJ26),MONTH(AJ26),DAY(AJ26)+1) -> 36547 | AK27: =IF(MONTH(AK26)=MONTH(DATE(YEAR(AK26),MONTH(AK26),DAY(AK26)+1)),DATE(YEAR(AK26),MONTH(AK26),DAY(AK26)+1),NA()) -> 44583 | AL27: =SUMIFS(Table1[Amount $],Table1[Category Type],"Expense",Table1[Date],Snapshot!AK27)*-1 -> 0 | AM27: =IF(AK27>TODAY(),NA(),SUM(AL$6:$AL27)) -> #N/A | AN27: =IF(OR(AK27=EOMONTH($AK$6,0),AK27=TODAY()),AM27,NA()) -> #N/A | AO27: =IF(MONTH(AO26)=MONTH(DATE(YEAR(AO26),MONTH(AO26),DAY(AO26)+1)),DATE(YEAR(AO26),MONTH(AO26),DAY(AO26)+1),NA()) -> 44552 | AP27: =SUMIFS(Table1[Amount $],Table1[Category Type],"Expense",Table1[Date],Snapshot!AO27)*-1 -> -32.19 | AQ27: =IF(AO27<=EOMONTH($AO$6,0),SUM(AP$6:$AP27),NA()) -> 83.93 | AR27: =IF(AO27=EOMONTH($AO$6,0),AQ27,NA()) -> #N/A | AU27: =IF(ISBLANK(AT27),"",SUMIFS(Table1[Amount $],Table1[Merchant],Snapshot!AT27,Table1[Month],Snapshot!$W$4)*-1) | AV27: =IF(ISBLANK(AT27),"",COUNTIFS(Table1[Merchant],Snapshot!AT27,Table1[Month],Snapshot!$W$4)) | AW27: =IFERROR(RANK(AV27,$AV$6:$AV$200)+COUNTIF($AV$6:AV27,AV27)-1,"") | AX27: =IFERROR(RANK(AU27,$AU$6:$AU$200)+COUNTIF($AU$6:AU27,AU27)-1,"")
D28: =IFERROR(IF(AND(MONTH(W4)=MONTH(TODAY()),YEAR(W4)=YEAR(TODAY())),AK39,AK42),"") -> Spent $137 more than this time last month | V28: =IF(ISBLANK(W28),"--",TEXT(W28,"mmmm")&" "&TEXT(W28,"YYYY")) -> April 2020 | W28: 43922 | AC28: Recreational & Entertainment | AD28: =SUMIFS(Table1[Amount $],Table1[Category],Snapshot!AC28,Table1[Month],Snapshot!$W$4)*-1 -> 0 | AE28: =RANK(AD28,$AD$6:$AD$35,0)+COUNTIF(AD$6:$AD28,AD28)-1 -> 22 | AJ28: =DATE(YEAR(AJ27),MONTH(AJ27),DAY(AJ27)+1) -> 36548 | AK28: =IF(MONTH(AK27)=MONTH(DATE(YEAR(AK27),MONTH(AK27),DAY(AK27)+1)),DATE(YEAR(AK27),MONTH(AK27),DAY(AK27)+1),NA()) -> 44584 | AL28: =SUMIFS(Table1[Amount $],Table1[Category Type],"Expense",Table1[Date],Snapshot!AK28)*-1 -> 0 | AM28: =IF(AK28>TODAY(),NA(),SUM(AL$6:$AL28)) -> #N/A | AN28: =IF(OR(AK28=EOMONTH($AK$6,0),AK28=TODAY()),AM28,NA()) -> #N/A | AO28: =IF(MONTH(AO27)=MONTH(DATE(YEAR(AO27),MONTH(AO27),DAY(AO27)+1)),DATE(YEAR(AO27),MONTH(AO27),DAY(AO27)+1),NA()) -> 44553 | AP28: =SUMIFS(Table1[Amount $],Table1[Category Type],"Expense",Table1[Date],Snapshot!AO28)*-1 -> 97.82 | AQ28: =IF(AO28<=EOMONTH($AO$6,0),SUM(AP$6:$AP28),NA()) -> 181.75 | AR28: =IF(AO28=EOMONTH($AO$6,0),AQ28,NA()) -> #N/A | AU28: =IF(ISBLANK(AT28),"",SUMIFS(Table1[Amount $],Table1[Merchant],Snapshot!AT28,Table1[Month],Snapshot!$W$4)*-1) | AV28: =IF(ISBLANK(AT28),"",COUNTIFS(Table1[Merchant],Snapshot!AT28,Table1[Month],Snapshot!$W$4)) | AW28: =IFERROR(RANK(AV28,$AV$6:$AV$200)+COUNTIF($AV$6:AV28,AV28)-1,"") | AX28: =IFERROR(RANK(AU28,$AU$6:$AU$200)+COUNTIF($AU$6:AU28,AU28)-1,"")
V29: =IF(ISBLANK(W29),"--",TEXT(W29,"mmmm")&" "&TEXT(W29,"YYYY")) -> March 2020 | W29: 43891 | AC29: Savings, Investing, &Debt | AD29: =SUMIFS(Table1[Amount $],Table1[Category],Snapshot!AC29,Table1[Month],Snapshot!$W$4)*-1 -> 0 | AE29: =RANK(AD29,$AD$6:$AD$35,0)+COUNTIF(AD$6:$AD29,AD29)-1 -> 23 | AJ29: =DATE(YEAR(AJ28),MONTH(AJ28),DAY(AJ28)+1) -> 36549 | AK29: =IF(MONTH(AK28)=MONTH(DATE(YEAR(AK28),MONTH(AK28),DAY(AK28)+1)),DATE(YEAR(AK28),MONTH(AK28),DAY(AK28)+1),NA()) -> 44585 | AL29: =SUMIFS(Table1[Amount $],Table1[Category Type],"Expense",Table1[Date],Snapshot!AK29)*-1 -> 0 | AM29: =IF(AK29>TODAY(),NA(),SUM(AL$6:$AL29)) -> #N/A | AN29: =IF(OR(AK29=EOMONTH($AK$6,0),AK29=TODAY()),AM29,NA()) -> #N/A | AO29: =IF(MONTH(AO28)=MONTH(DATE(YEAR(AO28),MONTH(AO28),DAY(AO28)+1)),DATE(YEAR(AO28),MONTH(AO28),DAY(AO28)+1),NA()) -> 44554 | AP29: =SUMIFS(Table1[Amount $],Table1[Category Type],"Expense",Table1[Date],Snapshot!AO29)*-1 -> 60 | AQ29: =IF(AO29<=EOMONTH($AO$6,0),SUM(AP$6:$AP29),NA()) -> 241.75 | AR29: =IF(AO29=EOMONTH($AO$6,0),AQ29,NA()) -> #N/A | AU29: =IF(ISBLANK(AT29),"",SUMIFS(Table1[Amount $],Table1[Merchant],Snapshot!AT29,Table1[Month],Snapshot!$W$4)*-1) | AV29: =IF(ISBLANK(AT29),"",COUNTIFS(Table1[Merchant],Snapshot!AT29,Table1[Month],Snapshot!$W$4)) | AW29: =IFERROR(RANK(AV29,$AV$6:$AV$200)+COUNTIF($AV$6:AV29,AV29)-1,"") | AX29: =IFERROR(RANK(AU29,$AU$6:$AU$200)+COUNTIF($AU$6:AU29,AU29)-1,"")
V30: =IF(ISBLANK(W30),"--",TEXT(W30,"mmmm")&" "&TEXT(W30,"YYYY")) -> February 2020 | W30: 43862 | AC30: Transportation | AD30: =SUMIFS(Table1[Amount $],Table1[Category],Snapshot!AC30,Table1[Month],Snapshot!$W$4)*-1 -> 0 | AE30: =RANK(AD30,$AD$6:$AD$35,0)+COUNTIF(AD$6:$AD30,AD30)-1 -> 24 | AJ30: =DATE(YEAR(AJ29),MONTH(AJ29),DAY(AJ29)+1) -> 36550 | AK30: =IF(MONTH(AK29)=MONTH(DATE(YEAR(AK29),MONTH(AK29),DAY(AK29)+1)),DATE(YEAR(AK29),MONTH(AK29),DAY(AK29)+1),NA()) -> 44586 | AL30: =SUMIFS(Table1[Amount $],Table1[Category Type],"Expense",Table1[Date],Snapshot!AK30)*-1 -> 0 | AM30: =IF(AK30>TODAY(),NA(),SUM(AL$6:$AL30)) -> #N/A | AN30: =IF(OR(AK30=EOMONTH($AK$6,0),AK30=TODAY()),AM30,NA()) -> #N/A | AO30: =IF(MONTH(AO29)=MONTH(DATE(YEAR(AO29),MONTH(AO29),DAY(AO29)+1)),DATE(YEAR(AO29),MONTH(AO29),DAY(AO29)+1),NA()) -> 44555 | AP30: =SUMIFS(Table1[Amount $],Table1[Category Type],"Expense",Table1[Date],Snapshot!AO30)*-1 -> 216.78 | AQ30: =IF(AO30<=EOMONTH($AO$6,0),SUM(AP$6:$AP30),NA()) -> 458.53 | AR30: =IF(AO30=EOMONTH($AO$6,0),AQ30,NA()) -> #N/A | AU30: =IF(ISBLANK(AT30),"",SUMIFS(Table1[Amount $],Table1[Merchant],Snapshot!AT30,Table1[Month],Snapshot!$W$4)*-1) | AV30: =IF(ISBLANK(AT30),"",COUNTIFS(Table1[Merchant],Snapshot!AT30,Table1[Month],Snapshot!$W$4)) | AW30: =IFERROR(RANK(AV30,$AV$6:$AV$200)+COUNTIF($AV$6:AV30,AV30)-1,"") | AX30: =IFERROR(RANK(AU30,$AU$6:$AU$200)+COUNTIF($AU$6:AU30,AU30)-1,"")
V31: =IF(ISBLANK(W31),"--",TEXT(W31,"mmmm")&" "&TEXT(W31,"YYYY")) -> January 2020 | W31: 43831 | AC31: Utilities | AD31: =SUMIFS(Table1[Amount $],Table1[Category],Snapshot!AC31,Table1[Month],Snapshot!$W$4)*-1 -> 0 | AE31: =RANK(AD31,$AD$6:$AD$35,0)+COUNTIF(AD$6:$AD31,AD31)-1 -> 25 | AJ31: =DATE(YEAR(AJ30),MONTH(AJ30),DAY(AJ30)+1) -> 36551 | AK31: =IF(MONTH(AK30)=MONTH(DATE(YEAR(AK30),MONTH(AK30),DAY(AK30)+1)),DATE(YEAR(AK30),MONTH(AK30),DAY(AK30)+1),NA()) -> 44587 | AL31: =SUMIFS(Table1[Amount $],Table1[Category Type],"Expense",Table1[Date],Snapshot!AK31)*-1 -> 0 | AM31: =IF(AK31>TODAY(),NA(),SUM(AL$6:$AL31)) -> #N/A | AN31: =IF(OR(AK31=EOMONTH($AK$6,0),AK31=TODAY()),AM31,NA()) -> #N/A | AO31: =IF(MONTH(AO30)=MONTH(DATE(YEAR(AO30),MONTH(AO30),DAY(AO30)+1)),DATE(YEAR(AO30),MONTH(AO30),DAY(AO30)+1),NA()) -> 44556 | AP31: =SUMIFS(Table1[Amount $],Table1[Category Type],"Expense",Table1[Date],Snapshot!AO31)*-1 -> 112.26 | AQ31: =IF(AO31<=EOMONTH($AO$6,0),SUM(AP$6:$AP31),NA()) -> 570.79 | AR31: =IF(AO31=EOMONTH($AO$6,0),AQ31,NA()) -> #N/A | AU31: =IF(ISBLANK(AT31),"",SUMIFS(Table1[Amount $],Table1[Merchant],Snapshot!AT31,Table1[Month],Snapshot!$W$4)*-1) | AV31: =IF(ISBLANK(AT31),"",COUNTIFS(Table1[Merchant],Snapshot!AT31,Table1[Month],Snapshot!$W$4)) | AW31: =IFERROR(RANK(AV31,$AV$6:$AV$200)+COUNTIF($AV$6:AV31,AV31)-1,"") | AX31: =IFERROR(RANK(AU31,$AU$6:$AU$200)+COUNTIF($AU$6:AU31,AU31)-1,"")
V32: =IF(ISBLANK(W32),"--",TEXT(W32,"mmmm")&" "&TEXT(W32,"YYYY")) -> -- | AD32: =SUMIFS(Table1[Amount $],Table1[Category],Snapshot!AC32,Table1[Month],Snapshot!$W$4)*-1 -> 0 | AE32: =RANK(AD32,$AD$6:$AD$35,0)+COUNTIF(AD$6:$AD32,AD32)-1 -> 26 | AJ32: =DATE(YEAR(AJ31),MONTH(AJ31),DAY(AJ31)+1) -> 36552 | AK32: =IF(MONTH(AK31)=MONTH(DATE(YEAR(AK31),MONTH(AK31),DAY(AK31)+1)),DATE(YEAR(AK31),MONTH(AK31),DAY(AK31)+1),NA()) -> 44588 | AL32: =SUMIFS(Table1[Amount $],Table1[Category Type],"Expense",Table1[Date],Snapshot!AK32)*-1 -> 0 | AM32: =IF(AK32>TODAY(),NA(),SUM(AL$6:$AL32)) -> #N/A | AN32: =IF(OR(AK32=EOMONTH($AK$6,0),AK32=TODAY()),AM32,NA()) -> #N/A | AO32: =IF(MONTH(AO31)=MONTH(DATE(YEAR(AO31),MONTH(AO31),DAY(AO31)+1)),DATE(YEAR(AO31),MONTH(AO31),DAY(AO31)+1),NA()) -> 44557 | AP32: =SUMIFS(Table1[Amount $],Table1[Category Type],"Expense",Table1[Date],Snapshot!AO32)*-1 -> 426.95 | AQ32: =IF(AO32<=EOMONTH($AO$6,0),SUM(AP$6:$AP32),NA()) -> 997.74 | AR32: =IF(AO32=EOMONTH($AO$6,0),AQ32,NA()) -> #N/A | AU32: =IF(ISBLANK(AT32),"",SUMIFS(Table1[Amount $],Table1[Merchant],Snapshot!AT32,Table1[Month],Snapshot!$W$4)*-1) | AV32: =IF(ISBLANK(AT32),"",COUNTIFS(Table1[Merchant],Snapshot!AT32,Table1[Month],Snapshot!$W$4)) | AW32: =IFERROR(RANK(AV32,$AV$6:$AV$200)+COUNTIF($AV$6:AV32,AV32)-1,"") | AX32: =IFERROR(RANK(AU32,$AU$6:$AU$200)+COUNTIF($AU$6:AU32,AU32)-1,"")
V33: =IF(ISBLANK(W33),"--",TEXT(W33,"mmmm")&" "&TEXT(W33,"YYYY")) -> -- | AD33: =SUMIFS(Table1[Amount $],Table1[Category],Snapshot!AC33,Table1[Month],Snapshot!$W$4)*-1 -> 0 | AE33: =RANK(AD33,$AD$6:$AD$35,0)+COUNTIF(AD$6:$AD33,AD33)-1 -> 27 | AJ33: =DATE(YEAR(AJ32),MONTH(AJ32),DAY(AJ32)+1) -> 36553 | AK33: =IF(MONTH(AK32)=MONTH(DATE(YEAR(AK32),MONTH(AK32),DAY(AK32)+1)),DATE(YEAR(AK32),MONTH(AK32),DAY(AK32)+1),NA()) -> 44589 | AL33: =SUMIFS(Table1[Amount $],Table1[Category Type],"Expense",Table1[Date],Snapshot!AK33)*-1 -> 0 | AM33: =IF(AK33>TODAY(),NA(),SUM(AL$6:$AL33)) -> #N/A | AN33: =IF(OR(AK33=EOMONTH($AK$6,0),AK33=TODAY()),AM33,NA()) -> #N/A | AO33: =IF(MONTH(AO32)=MONTH(DATE(YEAR(AO32),MONTH(AO32),DAY(AO32)+1)),DATE(YEAR(AO32),MONTH(AO32),DAY(AO32)+1),NA()) -> 44558 | AP33: =SUMIFS(Table1[Amount $],Table1[Category Type],"Expense",Table1[Date],Snapshot!AO33)*-1 -> 11 | AQ33: =IF(AO33<=EOMONTH($AO$6,0),SUM(AP$6:$AP33),NA()) -> 1008.74 | AR33: =IF(AO33=EOMONTH($AO$6,0),AQ33,NA()) -> #N/A | AU33: =IF(ISBLANK(AT33),"",SUMIFS(Table1[Amount $],Table1[Merchant],Snapshot!AT33,Table1[Month],Snapshot!$W$4)*-1) | AV33: =IF(ISBLANK(AT33),"",COUNTIFS(Table1[Merchant],Snapshot!AT33,Table1[Month],Snapshot!$W$4)) | AW33: =IFERROR(RANK(AV33,$AV$6:$AV$200)+COUNTIF($AV$6:AV33,AV33)-1,"") | AX33: =IFERROR(RANK(AU33,$AU$6:$AU$200)+COUNTIF($AU$6:AU33,AU33)-1,"")
V34: =IF(ISBLANK(W34),"--",TEXT(W34,"mmmm")&" "&TEXT(W34,"YYYY")) -> -- | AD34: =SUMIFS(Table1[Amount $],Table1[Category],Snapshot!AC34,Table1[Month],Snapshot!$W$4)*-1 -> 0 | AE34: =RANK(AD34,$AD$6:$AD$35,0)+COUNTIF(AD$6:$AD34,AD34)-1 -> 28 | AJ34: =DATE(YEAR(AJ33),MONTH(AJ33),DAY(AJ33)+1) -> 36554 | AK34: =IF(MONTH(AK33)=MONTH(DATE(YEAR(AK33),MONTH(AK33),DAY(AK33)+1)),DATE(YEAR(AK33),MONTH(AK33),DAY(AK33)+1),NA()) -> 44590 | AL34: =SUMIFS(Table1[Amount $],Table1[Category Type],"Expense",Table1[Date],Snapshot!AK34)*-1 -> 0 | AM34: =IF(AK34>TODAY(),NA(),SUM(AL$6:$AL34)) -> #N/A | AN34: =IF(OR(AK34=EOMONTH($AK$6,0),AK34=TODAY()),AM34,NA()) -> #N/A | AO34: =IF(MONTH(AO33)=MONTH(DATE(YEAR(AO33),MONTH(AO33),DAY(AO33)+1)),DATE(YEAR(AO33),MONTH(AO33),DAY(AO33)+1),NA()) -> 44559 | AP34: =SUMIFS(Table1[Amount $],Table1[Category Type],"Expense",Table1[Date],Snapshot!AO34)*-1 -> -918.57 | AQ34: =IF(AO34<=EOMONTH($AO$6,0),SUM(AP$6:$AP34),NA()) -> 90.17 | AR34: =IF(AO34=EOMONTH($AO$6,0),AQ34,NA()) -> #N/A | AU34: =IF(ISBLANK(AT34),"",SUMIFS(Table1[Amount $],Table1[Merchant],Snapshot!AT34,Table1[Month],Snapshot!$W$4)*-1) | AV34: =IF(ISBLANK(AT34),"",COUNTIFS(Table1[Merchant],Snapshot!AT34,Table1[Month],Snapshot!$W$4)) | AW34: =IFERROR(RANK(AV34,$AV$6:$AV$200)+COUNTIF($AV$6:AV34,AV34)-1,"") | AX34: =IFERROR(RANK(AU34,$AU$6:$AU$200)+COUNTIF($AU$6:AU34,AU34)-1,"")
V35: =IF(ISBLANK(W35),"--",TEXT(W35,"mmmm")&" "&TEXT(W35,"YYYY")) -> -- | AD35: =SUMIFS(Table1[Amount $],Table1[Category],Snapshot!AC35,Table1[Month],Snapshot!$W$4)*-1 -> 0 | AE35: =RANK(AD35,$AD$6:$AD$35,0)+COUNTIF(AD$6:$AD35,AD35)-1 -> 29 | AJ35: =DATE(YEAR(AJ34),MONTH(AJ34),DAY(AJ34)+1) -> 36555 | AK35: =IF(MONTH(AK34)=MONTH(DATE(YEAR(AK34),MONTH(AK34),DAY(AK34)+1)),DATE(YEAR(AK34),MONTH(AK34),DAY(AK34)+1),NA()) -> 44591 | AL35: =SUMIFS(Table1[Amount $],Table1[Category Type],"Expense",Table1[Date],Snapshot!AK35)*-1 -> 0 | AM35: =IF(AK35>TODAY(),NA(),SUM(AL$6:$AL35)) -> #N/A | AN35: =IF(OR(AK35=EOMONTH($AK$6,0),AK35=TODAY()),AM35,NA()) -> #N/A | AO35: =IF(MONTH(AO34)=MONTH(DATE(YEAR(AO34),MONTH(AO34),DAY(AO34)+1)),DATE(YEAR(AO34),MONTH(AO34),DAY(AO34)+1),NA()) -> 44560 | AP35: =SUMIFS(Table1[Amount $],Table1[Category Type],"Expense",Table1[Date],Snapshot!AO35)*-1 -> -352.09 | AQ35: =IF(AO35<=EOMONTH($AO$6,0),SUM(AP$6:$AP35),NA()) -> -261.92 | AR35: =IF(AO35=EOMONTH($AO$6,0),AQ35,NA()) -> #N/A | AU35: =IF(ISBLANK(AT35),"",SUMIFS(Table1[Amount $],Table1[Merchant],Snapshot!AT35,Table1[Month],Snapshot!$W$4)*-1) | AV35: =IF(ISBLANK(AT35),"",COUNTIFS(Table1[Merchant],Snapshot!AT35,Table1[Month],Snapshot!$W$4)) | AW35: =IFERROR(RANK(AV35,$AV$6:$AV$200)+COUNTIF($AV$6:AV35,AV35)-1,"") | AX35: =IFERROR(RANK(AU35,$AU$6:$AU$200)+COUNTIF($AU$6:AU35,AU35)-1,"")
V36: =IF(ISBLANK(W36),"--",TEXT(W36,"mmmm")&" "&TEXT(W36,"YYYY")) -> -- | AD36: =SUMIFS(Table1[Amount $],Table1[Category],Snapshot!AC36,Table1[Month],Snapshot!$W$4)*-1 -> 0 | AE36: =RANK(AD36,$AD$6:$AD$35,0)+COUNTIF(AD$6:$AD36,AD36)-1 -> 30 | AJ36: =DATE(YEAR(AJ35),MONTH(AJ35),DAY(AJ35)+1) -> 36556 | AK36: =IF(MONTH(AK35)=MONTH(DATE(YEAR(AK35),MONTH(AK35),DAY(AK35)+1)),DATE(YEAR(AK35),MONTH(AK35),DAY(AK35)+1),NA()) -> 44592 | AL36: =SUMIFS(Table1[Amount $],Table1[Category Type],"Expense",Table1[Date],Snapshot!AK36)*-1 -> 0 | AM36: =IF(AK36>TODAY(),NA(),SUM(AL$6:$AL36)) -> #N/A | AN36: =IF(OR(AK36=EOMONTH($AK$6,0),AK36=TODAY()),AM36,NA()) -> #N/A | AO36: =IF(MONTH(AO35)=MONTH(DATE(YEAR(AO35),MONTH(AO35),DAY(AO35)+1)),DATE(YEAR(AO35),MONTH(AO35),DAY(AO35)+1),NA()) -> 44561 | AP36: =SUMIFS(Table1[Amount $],Table1[Category Type],"Expense",Table1[Date],Snapshot!AO36)*-1 -> 84.37 | AQ36: =IF(AO36<=EOMONTH($AO$6,0),SUM(AP$6:$AP36),NA()) -> -177.55 | AR36: =IF(AO36=EOMONTH($AO$6,0),AQ36,NA()) -> -177.55 | AU36: =IF(ISBLANK(AT36),"",SUMIFS(Table1[Amount $],Table1[Merchant],Snapshot!AT36,Table1[Month],Snapshot!$W$4)*-1) | AV36: =IF(ISBLANK(AT36),"",COUNTIFS(Table1[Merchant],Snapshot!AT36,Table1[Month],Snapshot!$W$4)) | AW36: =IFERROR(RANK(AV36,$AV$6:$AV$200)+COUNTIF($AV$6:AV36,AV36)-1,"") | AX36: =IFERROR(RANK(AU36,$AU$6:$AU$200)+COUNTIF($AU$6:AU36,AU36)-1,"")
V37: =IF(ISBLANK(W37),"--",TEXT(W37,"mmmm")&" "&TEXT(W37,"YYYY")) -> -- | AD37: =SUMIFS(Table1[Amount $],Table1[Category],Snapshot!AC37,Table1[Month],Snapshot!$W$4)*-1 -> 0 | AE37: =RANK(AD37,$AD$6:$AD$35,0)+COUNTIF(AD$6:$AD37,AD37)-1 -> 31 | AU37: =IF(ISBLANK(AT37),"",SUMIFS(Table1[Amount $],Table1[Merchant],Snapshot!AT37,Table1[Month],Snapshot!$W$4)*-1) | AV37: =IF(ISBLANK(AT37),"",COUNTIFS(Table1[Merchant],Snapshot!AT37,Table1[Month],Snapshot!$W$4)) | AW37: =IFERROR(RANK(AV37,$AV$6:$AV$200)+COUNTIF($AV$6:AV37,AV37)-1,"") | AX37: =IFERROR(RANK(AU37,$AU$6:$AU$200)+COUNTIF($AU$6:AU37,AU37)-1,"")
V38: =IF(ISBLANK(W38),"--",TEXT(W38,"mmmm")&" "&TEXT(W38,"YYYY")) -> -- | AD38: =SUMIFS(Table1[Amount $],Table1[Category],Snapshot!AC38,Table1[Month],Snapshot!$W$4)*-1 -> 0 | AE38: =RANK(AD38,$AD$6:$AD$35,0)+COUNTIF(AD$6:$AD38,AD38)-1 -> 32 | AK38: =TODAY() -> 44567 | AM38: {=INDEX(AM6:AM36,MATCH(AK38,AK6:AK36,0),0)} -> -50.9 | AO38: =DATE(YEAR(AK38),MONTH(AK38)-1,DAY(AK38)) -> 44536 | AQ38: {=INDEX(AQ6:AQ36,MATCH(AO38,AO6:AO36,0),0)} -> -188.06 | AU38: =IF(ISBLANK(AT38),"",SUMIFS(Table1[Amount $],Table1[Merchant],Snapshot!AT38,Table1[Month],Snapshot!$W$4)*-1) | AV38: =IF(ISBLANK(AT38),"",COUNTIFS(Table1[Merchant],Snapshot!AT38,Table1[Month],Snapshot!$W$4)) | AW38: =IFERROR(RANK(AV38,$AV$6:$AV$200)+COUNTIF($AV$6:AV38,AV38)-1,"") | AX38: =IFERROR(RANK(AU38,$AU$6:$AU$200)+COUNTIF($AU$6:AU38,AU38)-1,"")
V39: =IF(ISBLANK(W39),"--",TEXT(W39,"mmmm")&" "&TEXT(W39,"YYYY")) -> -- | AD39: =SUMIFS(Table1[Amount $],Table1[Category],Snapshot!AC39,Table1[Month],Snapshot!$W$4)*-1 -> 0 | AE39: =RANK(AD39,$AD$6:$AD$35,0)+COUNTIF(AD$6:$AD39,AD39)-1 -> 33 | AK39: =IF(AM38>AQ38,"Spent "&TEXT(AM38-AQ38,"$#,##0")&" more","Spent "&TEXT((AM38-AQ38)*-1,"$#,##0")&" less")&" than this time last month" -> Spent $137 more than this time last month | AU39: =IF(ISBLANK(AT39),"",SUMIFS(Table1[Amount $],Table1[Merchant],Snapshot!AT39,Table1[Month],Snapshot!$W$4)*-1) | AV39: =IF(ISBLANK(AT39),"",COUNTIFS(Table1[Merchant],Snapshot!AT39,Table1[Month],Snapshot!$W$4)) | AW39: =IFERROR(RANK(AV39,$AV$6:$AV$200)+COUNTIF($AV$6:AV39,AV39)-1,"") | AX39: =IFERROR(RANK(AU39,$AU$6:$AU$200)+COUNTIF($AU$6:AU39,AU39)-1,"")
V40: =IF(ISBLANK(W40),"--",TEXT(W40,"mmmm")&" "&TEXT(W40,"YYYY")) -> -- | AD40: =SUMIFS(Table1[Amount $],Table1[Category],Snapshot!AC40,Table1[Month],Snapshot!$W$4)*-1 -> 0 | AE40: =RANK(AD40,$AD$6:$AD$35,0)+COUNTIF(AD$6:$AD40,AD40)-1 -> 34 | AU40: =IF(ISBLANK(AT40),"",SUMIFS(Table1[Amount $],Table1[Merchant],Snapshot!AT40,Table1[Month],Snapshot!$W$4)*-1) | AV40: =IF(ISBLANK(AT40),"",COUNTIFS(Table1[Merchant],Snapshot!AT40,Table1[Month],Snapshot!$W$4)) | AW40: =IFERROR(RANK(AV40,$AV$6:$AV$200)+COUNTIF($AV$6:AV40,AV40)-1,"") | AX40: =IFERROR(RANK(AU40,$AU$6:$AU$200)+COUNTIF($AU$6:AU40,AU40)-1,"")
V41: =IF(ISBLANK(W41),"--",TEXT(W41,"mmmm")&" "&TEXT(W41,"YYYY")) -> -- | AD41: =SUMIFS(Table1[Amount $],Table1[Category],Snapshot!AC41,Table1[Month],Snapshot!$W$4)*-1 -> 0 | AE41: =RANK(AD41,$AD$6:$AD$35,0)+COUNTIF(AD$6:$AD41,AD41)-1 -> 35 | AK41: =IFERROR(MAX(AK6:AK36),IFERROR(AK35,IF(AK34,AK33))) -> 44592 | AM41: {=INDEX(AM6:AM36,MATCH(AK41,AK6:AK36,0),0)} -> #N/A | AO41: =IFERROR(MAX(AO6:AO36),IFERROR(AO35,IF(AO34,AO33))) -> 44561 | AQ41: {=INDEX(AQ6:AQ36,MATCH(AO41,AO6:AO36,0),0)} -> -177.55 | AU41: =IF(ISBLANK(AT41),"",SUMIFS(Table1[Amount $],Table1[Merchant],Snapshot!AT41,Table1[Month],Snapshot!$W$4)*-1) | AV41: =IF(ISBLANK(AT41),"",COUNTIFS(Table1[Merchant],Snapshot!AT41,Table1[Month],Snapshot!$W$4)) | AW41: =IFERROR(RANK(AV41,$AV$6:$AV$200)+COUNTIF($AV$6:AV41,AV41)-1,"") | AX41: =IFERROR(RANK(AU41,$AU$6:$AU$200)+COUNTIF($AU$6:AU41,AU41)-1,"")
V42: =IF(ISBLANK(W42),"--",TEXT(W42,"mmmm")&" "&TEXT(W42,"YYYY")) -> -- | AD42: =SUMIFS(Table1[Amount $],Table1[Category],Snapshot!AC42,Table1[Month],Snapshot!$W$4)*-1 -> 0 | AE42: =RANK(AD42,$AD$6:$AD$35,0)+COUNTIF(AD$6:$AD42,AD42)-1 -> 36 | AK42: ="Compared to "&TEXT(AO6,"mmmm")&", you "&IF(AM41>AQ41,"spent "&TEXT(AM41-AQ41,"$#,##0")&" more","spent "&TEXT((AM41-AQ41)*-1,"$#,##0")&" less") -> #N/A | AU42: =IF(ISBLANK(AT42),"",SUMIFS(Table1[Amount $],Table1[Merchant],Snapshot!AT42,Table1[Month],Snapshot!$W$4)*-1) | AV42: =IF(ISBLANK(AT42),"",COUNTIFS(Table1[Merchant],Snapshot!AT42,Table1[Month],Snapshot!$W$4)) | AW42: =IFERROR(RANK(AV42,$AV$6:$AV$200)+COUNTIF($AV$6:AV42,AV42)-1,"") | AX42: =IFERROR(RANK(AU42,$AU$6:$AU$200)+COUNTIF($AU$6:AU42,AU42)-1,"")
V43: =IF(ISBLANK(W43),"--",TEXT(W43,"mmmm")&" "&TEXT(W43,"YYYY")) -> -- | AD43: =SUMIFS(Table1[Amount $],Table1[Category],Snapshot!AC43,Table1[Month],Snapshot!$W$4)*-1 -> 0 | AE43: =RANK(AD43,$AD$6:$AD$35,0)+COUNTIF(AD$6:$AD43,AD43)-1 -> 37 | AU43: =IF(ISBLANK(AT43),"",SUMIFS(Table1[Amount $],Table1[Merchant],Snapshot!AT43,Table1[Month],Snapshot!$W$4)*-1) | AV43: =IF(ISBLANK(AT43),"",COUNTIFS(Table1[Merchant],Snapshot!AT43,Table1[Month],Snapshot!$W$4)) | AW43: =IFERROR(RANK(AV43,$AV$6:$AV$200)+COUNTIF($AV$6:AV43,AV43)-1,"") | AX43: =IFERROR(RANK(AU43,$AU$6:$AU$200)+COUNTIF($AU$6:AU43,AU43)-1,"")
D44: Frequented merchants | M44: Merchants where the most was spent | V44: =IF(ISBLANK(W44),"--",TEXT(W44,"mmmm")&" "&TEXT(W44,"YYYY")) -> -- | AD44: =SUMIFS(Table1[Amount $],Table1[Category],Snapshot!AC44,Table1[Month],Snapshot!$W$4)*-1 -> 0 | AE44: =RANK(AD44,$AD$6:$AD$35,0)+COUNTIF(AD$6:$AD44,AD44)-1 -> 38 | AU44: =IF(ISBLANK(AT44),"",SUMIFS(Table1[Amount $],Table1[Merchant],Snapshot!AT44,Table1[Month],Snapshot!$W$4)*-1) | AV44: =IF(ISBLANK(AT44),"",COUNTIFS(Table1[Merchant],Snapshot!AT44,Table1[Month],Snapshot!$W$4)) | AW44: =IFERROR(RANK(AV44,$AV$6:$AV$200)+COUNTIF($AV$6:AV44,AV44)-1,"") | AX44: =IFERROR(RANK(AU44,$AU$6:$AU$200)+COUNTIF($AU$6:AU44,AU44)-1,"")
V45: =IF(ISBLANK(W45),"--",TEXT(W45,"mmmm")&" "&TEXT(W45,"YYYY")) -> -- | AD45: =SUMIFS(Table1[Amount $],Table1[Category],Snapshot!AC45,Table1[Month],Snapshot!$W$4)*-1 -> 0 | AE45: =RANK(AD45,$AD$6:$AD$35,0)+COUNTIF(AD$6:$AD45,AD45)-1 -> 39 | AU45: =IF(ISBLANK(AT45),"",SUMIFS(Table1[Amount $],Table1[Merchant],Snapshot!AT45,Table1[Month],Snapshot!$W$4)*-1) | AV45: =IF(ISBLANK(AT45),"",COUNTIFS(Table1[Merchant],Snapshot!AT45,Table1[Month],Snapshot!$W$4)) | AW45: =IFERROR(RANK(AV45,$AV$6:$AV$200)+COUNTIF($AV$6:AV45,AV45)-1,"") | AX45: =IFERROR(RANK(AU45,$AU$6:$AU$200)+COUNTIF($AU$6:AU45,AU45)-1,"")
D46: Merchant | G46: Count | I46: Total cost | M46: Merchant | Q46: Category | S46: Total cost | V46: =IF(ISBLANK(W46),"--",TEXT(W46,"mmmm")&" "&TEXT(W46,"YYYY")) -> -- | AD46: =SUMIFS(Table1[Amount $],Table1[Category],Snapshot!AC46,Table1[Month],Snapshot!$W$4)*-1 -> 0 | AE46: =RANK(AD46,$AD$6:$AD$35,0)+COUNTIF(AD$6:$AD46,AD46)-1 -> 40 | AU46: =IF(ISBLANK(AT46),"",SUMIFS(Table1[Amount $],Table1[Merchant],Snapshot!AT46,Table1[Month],Snapshot!$W$4)*-1) | AV46: =IF(ISBLANK(AT46),"",COUNTIFS(Table1[Merchant],Snapshot!AT46,Table1[Month],Snapshot!$W$4)) | AW46: =IFERROR(RANK(AV46,$AV$6:$AV$200)+COUNTIF($AV$6:AV46,AV46)-1,"") | AX46: =IFERROR(RANK(AU46,$AU$6:$AU$200)+COUNTIF($AU$6:AU46,AU46)-1,"")
B47: 1 | D47: {=IFERROR(INDEX($AT:$AT,MATCH($B47,$AW:$AW,0),0),"")} -> Best Buy | G47: {=IF(IFERROR(INDEX($AV:$AV,MATCH($B47,$AW:$AW,0),0),"")=0,"",IFERROR(INDEX($AV:$AV,MATCH($B47,$AW:$AW,0),0),""))} -> 1 | I47: {=IF(IFERROR(INDEX($AU:$AU,MATCH($B47,$AW:$AW,0),0),"")=0,"",IFERROR(INDEX($AU:$AU,MATCH($B47,$AW:$AW,0),0),""))} -> 241.99 | M47: {=IFERROR(INDEX($AT:$AT,MATCH($B47,$AX:$AX,0),0),"")} -> Discover E Payment Lewis | Q47: {=IFERROR(INDEX(Table1[Category],MATCH(Snapshot!M47,Table1[Merchant],0),0),"")} -> Payment | S47: {=IF(IFERROR(INDEX($AU:$AU,MATCH($B47,$AX:$AX,0),0),"")=0,"",IFERROR(INDEX($AU:$AU,MATCH($B47,$AX:$AX,0),0),""))} -> 1800 | V47: =IF(ISBLANK(W47),"--",TEXT(W47,"mmmm")&" "&TEXT(W47,"YYYY")) -> -- | AD47: =SUMIFS(Table1[Amount $],Table1[Category],Snapshot!AC47,Table1[Month],Snapshot!$W$4)*-1 -> 0 | AE47: =RANK(AD47,$AD$6:$AD$35,0)+COUNTIF(AD$6:$AD47,AD47)-1 -> 41 | AU47: =IF(ISBLANK(AT47),"",SUMIFS(Table1[Amount $],Table1[Merchant],Snapshot!AT47,Table1[Month],Snapshot!$W$4)*-1) | AV47: =IF(ISBLANK(AT47),"",COUNTIFS(Table1[Merchant],Snapshot!AT47,Table1[Month],Snapshot!$W$4)) | AW47: =IFERROR(RANK(AV47,$AV$6:$AV$200)+COUNTIF($AV$6:AV47,AV47)-1,"") | AX47: =IFERROR(RANK(AU47,$AU$6:$AU$200)+COUNTIF($AU$6:AU47,AU47)-1,"")
B48: =B47+1 -> 2 | D48: {=IFERROR(INDEX($AT:$AT,MATCH($B48,$AW:$AW,0),0),"")} -> Discover E Payment Lewis | G48: {=IF(IFERROR(INDEX($AV:$AV,MATCH($B48,$AW:$AW,0),0),"")=0,"",IFERROR(INDEX($AV:$AV,MATCH($B48,$AW:$AW,0),0),""))} -> 1 | I48: {=IF(IFERROR(INDEX($AU:$AU,MATCH($B48,$AW:$AW,0),0),"")=0,"",IFERROR(INDEX($AU:$AU,MATCH($B48,$AW:$AW,0),0),""))} -> 1800 | M48: {=IFERROR(INDEX($AT:$AT,MATCH($B48,$AX:$AX,0),0),"")} -> Transfer To Lewis Sharon | Q48: {=IFERROR(INDEX(Table1[Category],MATCH(Snapshot!M48,Table1[Merchant],0),0),"")} -> Home | S48: {=IF(IFERROR(INDEX($AU:$AU,MATCH($B48,$AX:$AX,0),0),"")=0,"",IFERROR(INDEX($AU:$AU,MATCH($B48,$AX:$AX,0),0),""))} -> 485 | V48: =IF(ISBLANK(W48),"--",TEXT(W48,"mmmm")&" "&TEXT(W48,"YYYY")) -> -- | AD48: =SUMIFS(Table1[Amount $],Table1[Category],Snapshot!AC48,Table1[Month],Snapshot!$W$4)*-1 -> 0 | AE48: =RANK(AD48,$AD$6:$AD$35,0)+COUNTIF(AD$6:$AD48,AD48)-1 -> 42 | AU48: =IF(ISBLANK(AT48),"",SUMIFS(Table1[Amount $],Table1[Merchant],Snapshot!AT48,Table1[Month],Snapshot!$W$4)*-1) | AV48: =IF(ISBLANK(AT48),"",COUNTIFS(Table1[Merchant],Snapshot!AT48,Table1[Month],Snapshot!$W$4)) | AW48: =IFERROR(RANK(AV48,$AV$6:$AV$200)+COUNTIF($AV$6:AV48,AV48)-1,"") | AX48: =IFERROR(RANK(AU48,$AU$6:$AU$200)+COUNTIF($AU$6:AU48,AU48)-1,"")
B49: =B48+1 -> 3 | D49: {=IFERROR(INDEX($AT:$AT,MATCH($B49,$AW:$AW,0),0),"")} -> Paypal Inst Xfer Louisck | G49: {=IF(IFERROR(INDEX($AV:$AV,MATCH($B49,$AW:$AW,0),0),"")=0,"",IFERROR(INDEX($AV:$AV,MATCH($B49,$AW:$AW,0),0),""))} -> 1 | I49: {=IF(IFERROR(INDEX($AU:$AU,MATCH($B49,$AW:$AW,0),0),"")=0,"",IFERROR(INDEX($AU:$AU,MATCH($B49,$AW:$AW,0),0),""))} -> 10 | M49: {=IFERROR(INDEX($AT:$AT,MATCH($B49,$AX:$AX,0),0),"")} -> Best Buy | Q49: {=IFERROR(INDEX(Table1[Category],MATCH(Snapshot!M49,Table1[Merchant],0),0),"")} -> Payment | S49: {=IF(IFERROR(INDEX($AU:$AU,MATCH($B49,$AX:$AX,0),0),"")=0,"",IFERROR(INDEX($AU:$AU,MATCH($B49,$AX:$AX,0),0),""))} -> 241.99 | V49: =IF(ISBLANK(W49),"--",TEXT(W49,"mmmm")&" "&TEXT(W49,"YYYY")) -> -- | AD49: =SUMIFS(Table1[Amount $],Table1[Category],Snapshot!AC49,Table1[Month],Snapshot!$W$4)*-1 -> 0 | AE49: =RANK(AD49,$AD$6:$AD$35,0)+COUNTIF(AD$6:$AD49,AD49)-1 -> 43 | AU49: =IF(ISBLANK(AT49),"",SUMIFS(Table1[Amount $],Table1[Merchant],Snapshot!AT49,Table1[Month],Snapshot!$W$4)*-1) | AV49: =IF(ISBLANK(AT49),"",COUNTIFS(Table1[Merchant],Snapshot!AT49,Table1[Month],Snapshot!$W$4)) | AW49: =IFERROR(RANK(AV49,$AV$6:$AV$200)+COUNTIF($AV$6:AV49,AV49)-1,"") | AX49: =IFERROR(RANK(AU49,$AU$6:$AU$200)+COUNTIF($AU$6:AU49,AU49)-1,"")
B50: =B49+1 -> 4 | D50: {=IFERROR(INDEX($AT:$AT,MATCH($B50,$AW:$AW,0),0),"")} -> Transfer To Lewis Sharon | G50: {=IF(IFERROR(INDEX($AV:$AV,MATCH($B50,$AW:$AW,0),0),"")=0,"",IFERROR(INDEX($AV:$AV,MATCH($B50,$AW:$AW,0),0),""))} -> 1 | I50: {=IF(IFERROR(INDEX($AU:$AU,MATCH($B50,$AW:$AW,0),0),"")=0,"",IFERROR(INDEX($AU:$AU,MATCH($B50,$AW:$AW,0),0),""))} -> 485 | M50: {=IFERROR(INDEX($AT:$AT,MATCH($B50,$AX:$AX,0),0),"")} -> Olive Garden | Q50: {=IFERROR(INDEX(Table1[Category],MATCH(Snapshot!M50,Table1[Merchant],0),0),"")} -> Restaurants/Dining | S50: {=IF(IFERROR(INDEX($AU:$AU,MATCH($B50,$AX:$AX,0),0),"")=0,"",IFERROR(INDEX($AU:$AU,MATCH($B50,$AX:$AX,0),0),""))} -> 60 | V50: =IF(ISBLANK(W50),"--",TEXT(W50,"mmmm")&" "&TEXT(W50,"YYYY")) -> -- | AD50: =SUMIFS(Table1[Amount $],Table1[Category],Snapshot!AC50,Table1[Month],Snapshot!$W$4)*-1 -> 0 | AE50: =RANK(AD50,$AD$6:$AD$35,0)+COUNTIF(AD$6:$AD50,AD50)-1 -> 44 | AU50: =IF(ISBLANK(AT50),"",SUMIFS(Table1[Amount $],Table1[Merchant],Snapshot!AT50,Table1[Month],Snapshot!$W$4)*-1) | AV50: =IF(ISBLANK(AT50),"",COUNTIFS(Table1[Merchant],Snapshot!AT50,Table1[Month],Snapshot!$W$4)) | AW50: =IFERROR(RANK(AV50,$AV$6:$AV$200)+COUNTIF($AV$6:AV50,AV50)-1,"") | AX50: =IFERROR(RANK(AU50,$AU$6:$AU$200)+COUNTIF($AU$6:AU50,AU50)-1,"")
B51: =B50+1 -> 5 | D51: {=IFERROR(INDEX($AT:$AT,MATCH($B51,$AW:$AW,0),0),"")} -> Hulu | G51: {=IF(IFERROR(INDEX($AV:$AV,MATCH($B51,$AW:$AW,0),0),"")=0,"",IFERROR(INDEX($AV:$AV,MATCH($B51,$AW:$AW,0),0),""))} -> 1 | I51: {=IF(IFERROR(INDEX($AU:$AU,MATCH($B51,$AW:$AW,0),0),"")=0,"",IFERROR(INDEX($AU:$AU,MATCH($B51,$AW:$AW,0),0),""))} -> 12.99 | M51: {=IFERROR(INDEX($AT:$AT,MATCH($B51,$AX:$AX,0),0),"")} -> Jimmy Johns | Q51: {=IFERROR(INDEX(Table1[Category],MATCH(Snapshot!M51,Table1[Merchant],0),0),"")} -> Restaurants/Dining | S51: {=IF(IFERROR(INDEX($AU:$AU,MATCH($B51,$AX:$AX,0),0),"")=0,"",IFERROR(INDEX($AU:$AU,MATCH($B51,$AX:$AX,0),0),""))} -> 18.02 | V51: =IF(ISBLANK(W51),"--",TEXT(W51,"mmmm")&" "&TEXT(W51,"YYYY")) -> -- | AD51: =SUMIFS(Table1[Amount $],Table1[Category],Snapshot!AC51,Table1[Month],Snapshot!$W$4)*-1 -> 0 | AE51: =RANK(AD51,$AD$6:$AD$35,0)+COUNTIF(AD$6:$AD51,AD51)-1 -> 45 | AU51: =IF(ISBLANK(AT51),"",SUMIFS(Table1[Amount $],Table1[Merchant],Snapshot!AT51,Table1[Month],Snapshot!$W$4)*-1) | AV51: =IF(ISBLANK(AT51),"",COUNTIFS(Table1[Merchant],Snapshot!AT51,Table1[Month],Snapshot!$W$4)) | AW51: =IFERROR(RANK(AV51,$AV$6:$AV$200)+COUNTIF($AV$6:AV51,AV51)-1,"") | AX51: =IFERROR(RANK(AU51,$AU$6:$AU$200)+COUNTIF($AU$6:AU51,AU51)-1,"")
B52: =B51+1 -> 6 | D52: {=IFERROR(INDEX($AT:$AT,MATCH($B52,$AW:$AW,0),0),"")} -> Krystal And Saagar Dc | G52: {=IF(IFERROR(INDEX($AV:$AV,MATCH($B52,$AW:$AW,0),0),"")=0,"",IFERROR(INDEX($AV:$AV,MATCH($B52,$AW:$AW,0),0),""))} -> 1 | I52: {=IF(IFERROR(INDEX($AU:$AU,MATCH($B52,$AW:$AW,0),0),"")=0,"",IFERROR(INDEX($AU:$AU,MATCH($B52,$AW:$AW,0),0),""))} -> 10 | M52: {=IFERROR(INDEX($AT:$AT,MATCH($B52,$AX:$AX,0),0),"")} -> Netflix | Q52: {=IFERROR(INDEX(Table1[Category],MATCH(Snapshot!M52,Table1[Merchant],0),0),"")} -> Shopping | S52: {=IF(IFERROR(INDEX($AU:$AU,MATCH($B52,$AX:$AX,0),0),"")=0,"",IFERROR(INDEX($AU:$AU,MATCH($B52,$AX:$AX,0),0),""))} -> 14.83 | V52: =IF(ISBLANK(W52),"--",TEXT(W52,"mmmm")&" "&TEXT(W52,"YYYY")) -> -- | AD52: =SUMIFS(Table1[Amount $],Table1[Category],Snapshot!AC52,Table1[Month],Snapshot!$W$4)*-1 -> 0 | AE52: =RANK(AD52,$AD$6:$AD$35,0)+COUNTIF(AD$6:$AD52,AD52)-1 -> 46 | AU52: =IF(ISBLANK(AT52),"",SUMIFS(Table1[Amount $],Table1[Merchant],Snapshot!AT52,Table1[Month],Snapshot!$W$4)*-1) | AV52: =IF(ISBLANK(AT52),"",COUNTIFS(Table1[Merchant],Snapshot!AT52,Table1[Month],Snapshot!$W$4)) | AW52: =IFERROR(RANK(AV52,$AV$6:$AV$200)+COUNTIF($AV$6:AV52,AV52)-1,"") | AX52: =IFERROR(RANK(AU52,$AU$6:$AU$200)+COUNTIF($AU$6:AU52,AU52)-1,"")
B53: =B52+1 -> 7 | D53: {=IFERROR(INDEX($AT:$AT,MATCH($B53,$AW:$AW,0),0),"")} -> Jimmy Johns | G53: {=IF(IFERROR(INDEX($AV:$AV,MATCH($B53,$AW:$AW,0),0),"")=0,"",IFERROR(INDEX($AV:$AV,MATCH($B53,$AW:$AW,0),0),""))} -> 1 | I53: {=IF(IFERROR(INDEX($AU:$AU,MATCH($B53,$AW:$AW,0),0),"")=0,"",IFERROR(INDEX($AU:$AU,MATCH($B53,$AW:$AW,0),0),""))} -> 18.02 | M53: {=IFERROR(INDEX($AT:$AT,MATCH($B53,$AX:$AX,0),0),"")} -> Hulu | Q53: {=IFERROR(INDEX(Table1[Category],MATCH(Snapshot!M53,Table1[Merchant],0),0),"")} -> Shopping | S53: {=IF(IFERROR(INDEX($AU:$AU,MATCH($B53,$AX:$AX,0),0),"")=0,"",IFERROR(INDEX($AU:$AU,MATCH($B53,$AX:$AX,0),0),""))} -> 12.99 | V53: =IF(ISBLANK(W53),"--",TEXT(W53,"mmmm")&" "&TEXT(W53,"YYYY")) -> -- | AD53: =SUMIFS(Table1[Amount $],Table1[Category],Snapshot!AC53,Table1[Month],Snapshot!$W$4)*-1 -> 0 | AE53: =RANK(AD53,$AD$6:$AD$35,0)+COUNTIF(AD$6:$AD53,AD53)-1 -> 47 | AU53: =IF(ISBLANK(AT53),"",SUMIFS(Table1[Amount $],Table1[Merchant],Snapshot!AT53,Table1[Month],Snapshot!$W$4)*-1) | AV53: =IF(ISBLANK(AT53),"",COUNTIFS(Table1[Merchant],Snapshot!AT53,Table1[Month],Snapshot!$W$4)) | AW53: =IFERROR(RANK(AV53,$AV$6:$AV$200)+COUNTIF($AV$6:AV53,AV53)-1,"") | AX53: =IFERROR(RANK(AU53,$AU$6:$AU$200)+COUNTIF($AU$6:AU53,AU53)-1,"")
B54: =B53+1 -> 8 | D54: {=IFERROR(INDEX($AT:$AT,MATCH($B54,$AW:$AW,0),0),"")} -> Olive Garden | G54: {=IF(IFERROR(INDEX($AV:$AV,MATCH($B54,$AW:$AW,0),0),"")=0,"",IFERROR(INDEX($AV:$AV,MATCH($B54,$AW:$AW,0),0),""))} -> 1 | I54: {=IF(IFERROR(INDEX($AU:$AU,MATCH($B54,$AW:$AW,0),0),"")=0,"",IFERROR(INDEX($AU:$AU,MATCH($B54,$AW:$AW,0),0),""))} -> 60 | M54: {=IFERROR(INDEX($AT:$AT,MATCH($B54,$AX:$AX,0),0),"")} -> Paypal Inst Xfer Louisck | Q54: {=IFERROR(INDEX(Table1[Category],MATCH(Snapshot!M54,Table1[Merchant],0),0),"")} -> Restaurants/Dining | S54: {=IF(IFERROR(INDEX($AU:$AU,MATCH($B54,$AX:$AX,0),0),"")=0,"",IFERROR(INDEX($AU:$AU,MATCH($B54,$AX:$AX,0),0),""))} -> 10 | V54: =IF(ISBLANK(W54),"--",TEXT(W54,"mmmm")&" "&TEXT(W54,"YYYY")) -> -- | AD54: =SUMIFS(Table1[Amount $],Table1[Category],Snapshot!AC54,Table1[Month],Snapshot!$W$4)*-1 -> 0 | AE54: =RANK(AD54,$AD$6:$AD$35,0)+COUNTIF(AD$6:$AD54,AD54)-1 -> 48 | AU54: =IF(ISBLANK(AT54),"",SUMIFS(Table1[Amount $],Table1[Merchant],Snapshot!AT54,Table1[Month],Snapshot!$W$4)*-1) | AV54: =IF(ISBLANK(AT54),"",COUNTIFS(Table1[Merchant],Snapshot!AT54,Table1[Month],Snapshot!$W$4)) | AW54: =IFERROR(RANK(AV54,$AV$6:$AV$200)+COUNTIF($AV$6:AV54,AV54)-1,"") | AX54: =IFERROR(RANK(AU54,$AU$6:$AU$200)+COUNTIF($AU$6:AU54,AU54)-1,"")
B55: =B54+1 -> 9 | D55: {=IFERROR(INDEX($AT:$AT,MATCH($B55,$AW:$AW,0),0),"")} -> Netflix | G55: {=IF(IFERROR(INDEX($AV:$AV,MATCH($B55,$AW:$AW,0),0),"")=0,"",IFERROR(INDEX($AV:$AV,MATCH($B55,$AW:$AW,0),0),""))} -> 1 | I55: {=IF(IFERROR(INDEX($AU:$AU,MATCH($B55,$AW:$AW,0),0),"")=0,"",IFERROR(INDEX($AU:$AU,MATCH($B55,$AW:$AW,0),0),""))} -> 14.83 | M55: {=IFERROR(INDEX($AT:$AT,MATCH($B55,$AX:$AX,0),0),"")} -> Krystal And Saagar Dc | Q55: {=IFERROR(INDEX(Table1[Category],MATCH(Snapshot!M55,Table1[Merchant],0),0),"")} -> Payment | S55: {=IF(IFERROR(INDEX($AU:$AU,MATCH($B55,$AX:$AX,0),0),"")=0,"",IFERROR(INDEX($AU:$AU,MATCH($B55,$AX:$AX,0),0),""))} -> 10 | V55: =IF(ISBLANK(W55),"--",TEXT(W55,"mmmm")&" "&TEXT(W55,"YYYY")) -> -- | AD55: =SUMIFS(Table1[Amount $],Table1[Category],Snapshot!AC55,Table1[Month],Snapshot!$W$4)*-1 -> 0 | AE55: =RANK(AD55,$AD$6:$AD$35,0)+COUNTIF(AD$6:$AD55,AD55)-1 -> 49 | AU55: =IF(ISBLANK(AT55),"",SUMIFS(Table1[Amount $],Table1[Merchant],Snapshot!AT55,Table1[Month],Snapshot!$W$4)*-1) | AV55: =IF(ISBLANK(AT55),"",COUNTIFS(Table1[Merchant],Snapshot!AT55,Table1[Month],Snapshot!$W$4)) | AW55: =IFERROR(RANK(AV55,$AV$6:$AV$200)+COUNTIF($AV$6:AV55,AV55)-1,"") | AX55: =IFERROR(RANK(AU55,$AU$6:$AU$200)+COUNTIF($AU$6:AU55,AU55)-1,"")
B56: =B55+1 -> 10 | D56: {=IFERROR(INDEX($AT:$AT,MATCH($B56,$AW:$AW,0),0),"")} -> Spotify | G56: {=IF(IFERROR(INDEX($AV:$AV,MATCH($B56,$AW:$AW,0),0),"")=0,"",IFERROR(INDEX($AV:$AV,MATCH($B56,$AW:$AW,0),0),""))} -> 1 | I56: {=IF(IFERROR(INDEX($AU:$AU,MATCH($B56,$AW:$AW,0),0),"")=0,"",IFERROR(INDEX($AU:$AU,MATCH($B56,$AW:$AW,0),0),""))} -> 9.99 | M56: {=IFERROR(INDEX($AT:$AT,MATCH($B56,$AX:$AX,0),0),"")} -> Spotify | Q56: {=IFERROR(INDEX(Table1[Category],MATCH(Snapshot!M56,Table1[Merchant],0),0),"")} -> Shopping | S56: {=IF(IFERROR(INDEX($AU:$AU,MATCH($B56,$AX:$AX,0),0),"")=0,"",IFERROR(INDEX($AU:$AU,MATCH($B56,$AX:$AX,0),0),""))} -> 9.99 | V56: =IF(ISBLANK(W56),"--",TEXT(W56,"mmmm")&" "&TEXT(W56,"YYYY")) -> -- | AD56: =SUMIFS(Table1[Amount $],Table1[Category],Snapshot!AC56,Table1[Month],Snapshot!$W$4)*-1 -> 0 | AE56: =RANK(AD56,$AD$6:$AD$35,0)+COUNTIF(AD$6:$AD56,AD56)-1 -> 50 | AU56: =IF(ISBLANK(AT56),"",SUMIFS(Table1[Amount $],Table1[Merchant],Snapshot!AT56,Table1[Month],Snapshot!$W$4)*-1) | AV56: =IF(ISBLANK(AT56),"",COUNTIFS(Table1[Merchant],Snapshot!AT56,Table1[Month],Snapshot!$W$4)) | AW56: =IFERROR(RANK(AV56,$AV$6:$AV$200)+COUNTIF($AV$6:AV56,AV56)-1,"") | AX56: =IFERROR(RANK(AU56,$AU$6:$AU$200)+COUNTIF($AU$6:AU56,AU56)-1,"")
V57: =IF(ISBLANK(W57),"--",TEXT(W57,"mmmm")&" "&TEXT(W57,"YYYY")) -> -- | AD57: =SUMIFS(Table1[Amount $],Table1[Category],Snapshot!AC57,Table1[Month],Snapshot!$W$4)*-1 -> 0 | AE57: =RANK(AD57,$AD$6:$AD$35,0)+COUNTIF(AD$6:$AD57,AD57)-1 -> 51 | AU57: =IF(ISBLANK(AT57),"",SUMIFS(Table1[Amount $],Table1[Merchant],Snapshot!AT57,Table1[Month],Snapshot!$W$4)*-1) | AV57: =IF(ISBLANK(AT57),"",COUNTIFS(Table1[Merchant],Snapshot!AT57,Table1[Month],Snapshot!$W$4)) | AW57: =IFERROR(RANK(AV57,$AV$6:$AV$200)+COUNTIF($AV$6:AV57,AV57)-1,"") | AX57: =IFERROR(RANK(AU57,$AU$6:$AU$200)+COUNTIF($AU$6:AU57,AU57)-1,"")
V58: =IF(ISBLANK(W58),"--",TEXT(W58,"mmmm")&" "&TEXT(W58,"YYYY")) -> -- | AD58: =SUMIFS(Table1[Amount $],Table1[Category],Snapshot!AC58,Table1[Month],Snapshot!$W$4)*-1 -> 0 | AE58: =RANK(AD58,$AD$6:$AD$35,0)+COUNTIF(AD$6:$AD58,AD58)-1 -> 52 | AU58: =IF(ISBLANK(AT58),"",SUMIFS(Table1[Amount $],Table1[Merchant],Snapshot!AT58,Table1[Month],Snapshot!$W$4)*-1) | AV58: =IF(ISBLANK(AT58),"",COUNTIFS(Table1[Merchant],Snapshot!AT58,Table1[Month],Snapshot!$W$4)) | AW58: =IFERROR(RANK(AV58,$AV$6:$AV$200)+COUNTIF($AV$6:AV58,AV58)-1,"") | AX58: =IFERROR(RANK(AU58,$AU$6:$AU$200)+COUNTIF($AU$6:AU58,AU58)-1,"")
V59: =IF(ISBLANK(W59),"--",TEXT(W59,"mmmm")&" "&TEXT(W59,"YYYY")) -> -- | AD59: =SUMIFS(Table1[Amount $],Table1[Category],Snapshot!AC59,Table1[Month],Snapshot!$W$4)*-1 -> 0 | AE59: =RANK(AD59,$AD$6:$AD$35,0)+COUNTIF(AD$6:$AD59,AD59)-1 -> 53 | AU59: =IF(ISBLANK(AT59),"",SUMIFS(Table1[Amount $],Table1[Merchant],Snapshot!AT59,Table1[Month],Snapshot!$W$4)*-1) | AV59: =IF(ISBLANK(AT59),"",COUNTIFS(Table1[Merchant],Snapshot!AT59,Table1[Month],Snapshot!$W$4)) | AW59: =IFERROR(RANK(AV59,$AV$6:$AV$200)+COUNTIF($AV$6:AV59,AV59)-1,"") | AX59: =IFERROR(RANK(AU59,$AU$6:$AU$200)+COUNTIF($AU$6:AU59,AU59)-1,"")
V60: =IF(ISBLANK(W60),"--",TEXT(W60,"mmmm")&" "&TEXT(W60,"YYYY")) -> -- | AD60: =SUMIFS(Table1[Amount $],Table1[Category],Snapshot!AC60,Table1[Month],Snapshot!$W$4)*-1 -> 0 | AE60: =RANK(AD60,$AD$6:$AD$35,0)+COUNTIF(AD$6:$AD60,AD60)-1 -> 54 | AU60: =IF(ISBLANK(AT60),"",SUMIFS(Table1[Amount $],Table1[Merchant],Snapshot!AT60,Table1[Month],Snapshot!$W$4)*-1) | AV60: =IF(ISBLANK(AT60),"",COUNTIFS(Table1[Merchant],Snapshot!AT60,Table1[Month],Snapshot!$W$4)) | AW60: =IFERROR(RANK(AV60,$AV$6:$AV$200)+COUNTIF($AV$6:AV60,AV60)-1,"") | AX60: =IFERROR(RANK(AU60,$AU$6:$AU$200)+COUNTIF($AU$6:AU60,AU60)-1,"")
V61: =IF(ISBLANK(W61),"--",TEXT(W61,"mmmm")&" "&TEXT(W61,"YYYY")) -> -- | AD61: =SUMIFS(Table1[Amount $],Table1[Category],Snapshot!AC61,Table1[Month],Snapshot!$W$4)*-1 -> 0 | AE61: =RANK(AD61,$AD$6:$AD$35,0)+COUNTIF(AD$6:$AD61,AD61)-1 -> 55 | AU61: =IF(ISBLANK(AT61),"",SUMIFS(Table1[Amount $],Table1[Merchant],Snapshot!AT61,Table1[Month],Snapshot!$W$4)*-1) | AV61: =IF(ISBLANK(AT61),"",COUNTIFS(Table1[Merchant],Snapshot!AT61,Table1[Month],Snapshot!$W$4)) | AW61: =IFERROR(RANK(AV61,$AV$6:$AV$200)+COUNTIF($AV$6:AV61,AV61)-1,"") | AX61: =IFERROR(RANK(AU61,$AU$6:$AU$200)+COUNTIF($AU$6:AU61,AU61)-1,"")
V62: =IF(ISBLANK(W62),"--",TEXT(W62,"mmmm")&" "&TEXT(W62,"YYYY")) -> -- | AD62: =SUMIFS(Table1[Amount $],Table1[Category],Snapshot!AC62,Table1[Month],Snapshot!$W$4)*-1 -> 0 | AE62: =RANK(AD62,$AD$6:$AD$35,0)+COUNTIF(AD$6:$AD62,AD62)-1 -> 56 | AU62: =IF(ISBLANK(AT62),"",SUMIFS(Table1[Amount $],Table1[Merchant],Snapshot!AT62,Table1[Month],Snapshot!$W$4)*-1) | AV62: =IF(ISBLANK(AT62),"",COUNTIFS(Table1[Merchant],Snapshot!AT62,Table1[Month],Snapshot!$W$4)) | AW62: =IFERROR(RANK(AV62,$AV$6:$AV$200)+COUNTIF($AV$6:AV62,AV62)-1,"") | AX62: =IFERROR(RANK(AU62,$AU$6:$AU$200)+COUNTIF($AU$6:AU62,AU62)-1,"")
V63: =IF(ISBLANK(W63),"--",TEXT(W63,"mmmm")&" "&TEXT(W63,"YYYY")) -> -- | AD63: =SUMIFS(Table1[Amount $],Table1[Category],Snapshot!AC63,Table1[Month],Snapshot!$W$4)*-1 -> 0 | AE63: =RANK(AD63,$AD$6:$AD$35,0)+COUNTIF(AD$6:$AD63,AD63)-1 -> 57 | AU63: =IF(ISBLANK(AT63),"",SUMIFS(Table1[Amount $],Table1[Merchant],Snapshot!AT63,Table1[Month],Snapshot!$W$4)*-1) | AV63: =IF(ISBLANK(AT63),"",COUNTIFS(Table1[Merchant],Snapshot!AT63,Table1[Month],Snapshot!$W$4)) | AW63: =IFERROR(RANK(AV63,$AV$6:$AV$200)+COUNTIF($AV$6:AV63,AV63)-1,"") | AX63: =IFERROR(RANK(AU63,$AU$6:$AU$200)+COUNTIF($AU$6:AU63,AU63)-1,"")
V64: =IF(ISBLANK(W64),"--",TEXT(W64,"mmmm")&" "&TEXT(W64,"YYYY")) -> -- | AD64: =SUMIFS(Table1[Amount $],Table1[Category],Snapshot!AC64,Table1[Month],Snapshot!$W$4)*-1 -> 0 | AE64: =RANK(AD64,$AD$6:$AD$35,0)+COUNTIF(AD$6:$AD64,AD64)-1 -> 58 | AU64: =IF(ISBLANK(AT64),"",SUMIFS(Table1[Amount $],Table1[Merchant],Snapshot!AT64,Table1[Month],Snapshot!$W$4)*-1) | AV64: =IF(ISBLANK(AT64),"",COUNTIFS(Table1[Merchant],Snapshot!AT64,Table1[Month],Snapshot!$W$4)) | AW64: =IFERROR(RANK(AV64,$AV$6:$AV$200)+COUNTIF($AV$6:AV64,AV64)-1,"") | AX64: =IFERROR(RANK(AU64,$AU$6:$AU$200)+COUNTIF($AU$6:AU64,AU64)-1,"")
V65: =IF(ISBLANK(W65),"--",TEXT(W65,"mmmm")&" "&TEXT(W65,"YYYY")) -> -- | AD65: =SUMIFS(Table1[Amount $],Table1[Category],Snapshot!AC65,Table1[Month],Snapshot!$W$4)*-1 -> 0 | AE65: =RANK(AD65,$AD$6:$AD$35,0)+COUNTIF(AD$6:$AD65,AD65)-1 -> 59 | AU65: =IF(ISBLANK(AT65),"",SUMIFS(Table1[Amount $],Table1[Merchant],Snapshot!AT65,Table1[Month],Snapshot!$W$4)*-1) | AV65: =IF(ISBLANK(AT65),"",COUNTIFS(Table1[Merchant],Snapshot!AT65,Table1[Month],Snapshot!$W$4)) | AW65: =IFERROR(RANK(AV65,$AV$6:$AV$200)+COUNTIF($AV$6:AV65,AV65)-1,"") | AX65: =IFERROR(RANK(AU65,$AU$6:$AU$200)+COUNTIF($AU$6:AU65,AU65)-1,"")
V66: =IF(ISBLANK(W66),"--",TEXT(W66,"mmmm")&" "&TEXT(W66,"YYYY")) -> -- | AD66: =SUMIFS(Table1[Amount $],Table1[Category],Snapshot!AC66,Table1[Month],Snapshot!$W$4)*-1 -> 0 | AE66: =RANK(AD66,$AD$6:$AD$35,0)+COUNTIF(AD$6:$AD66,AD66)-1 -> 60 | AU66: =IF(ISBLANK(AT66),"",SUMIFS(Table1[Amount $],Table1[Merchant],Snapshot!AT66,Table1[Month],Snapshot!$W$4)*-1) | AV66: =IF(ISBLANK(AT66),"",COUNTIFS(Table1[Merchant],Snapshot!AT66,Table1[Month],Snapshot!$W$4)) | AW66: =IFERROR(RANK(AV66,$AV$6:$AV$200)+COUNTIF($AV$6:AV66,AV66)-1,"") | AX66: =IFERROR(RANK(AU66,$AU$6:$AU$200)+COUNTIF($AU$6:AU66,AU66)-1,"")
V67: =IF(ISBLANK(W67),"--",TEXT(W67,"mmmm")&" "&TEXT(W67,"YYYY")) -> -- | AD67: =SUMIFS(Table1[Amount $],Table1[Category],Snapshot!AC67,Table1[Month],Snapshot!$W$4)*-1 -> 0 | AE67: =RANK(AD67,$AD$6:$AD$35,0)+COUNTIF(AD$6:$AD67,AD67)-1 -> 61 | AU67: =IF(ISBLANK(AT67),"",SUMIFS(Table1[Amount $],Table1[Merchant],Snapshot!AT67,Table1[Month],Snapshot!$W$4)*-1) | AV67: =IF(ISBLANK(AT67),"",COUNTIFS(Table1[Merchant],Snapshot!AT67,Table1[Month],Snapshot!$W$4)) | AW67: =IFERROR(RANK(AV67,$AV$6:$AV$200)+COUNTIF($AV$6:AV67,AV67)-1,"") | AX67: =IFERROR(RANK(AU67,$AU$6:$AU$200)+COUNTIF($AU$6:AU67,AU67)-1,"")
V68: =IF(ISBLANK(W68),"--",TEXT(W68,"mmmm")&" "&TEXT(W68,"YYYY")) -> -- | AD68: =SUMIFS(Table1[Amount $],Table1[Category],Snapshot!AC68,Table1[Month],Snapshot!$W$4)*-1 -> 0 | AE68: =RANK(AD68,$AD$6:$AD$35,0)+COUNTIF(AD$6:$AD68,AD68)-1 -> 62 | AU68: =IF(ISBLANK(AT68),"",SUMIFS(Table1[Amount $],Table1[Merchant],Snapshot!AT68,Table1[Month],Snapshot!$W$4)*-1) | AV68: =IF(ISBLANK(AT68),"",COUNTIFS(Table1[Merchant],Snapshot!AT68,Table1[Month],Snapshot!$W$4)) | AW68: =IFERROR(RANK(AV68,$AV$6:$AV$200)+COUNTIF($AV$6:AV68,AV68)-1,"") | AX68: =IFERROR(RANK(AU68,$AU$6:$AU$200)+COUNTIF($AU$6:AU68,AU68)-1,"")
... V98: =IF(ISBLANK(W98),"--",TEXT(W98,"mmmm")&" "&TEXT(W98,"YYYY")) -> -- | AD98: =SUMIFS(Table1[Amount $],Table1[Category],Snapshot!AC98,Table1[Month],Snapshot!$W$4)*-1 -> 0 | AE98: =RANK(AD98,$AD$6:$AD$35,0)+COUNTIF(AD$6:$AD98,AD98)-1 -> 92 | AU98: =IF(ISBLANK(AT98),"",SUMIFS(Table1[Amount $],Table1[Merchant],Snapshot!AT98,Table1[Month],Snapshot!$W$4)*-1) | AV98: =IF(ISBLANK(AT98),"",COUNTIFS(Table1[Merchant],Snapshot!AT98,Table1[Month],Snapshot!$W$4)) | AW98: =IFERROR(RANK(AV98,$AV$6:$AV$200)+COUNTIF($AV$6:AV98,AV98)-1,"") | AX98: =IFERROR(RANK(AU98,$AU$6:$AU$200)+COUNTIF($AU$6:AU98,AU98)-1,"")
V99: =IF(ISBLANK(W99),"--",TEXT(W99,"mmmm")&" "&TEXT(W99,"YYYY")) -> -- | AU99: =IF(ISBLANK(AT99),"",SUMIFS(Table1[Amount $],Table1[Merchant],Snapshot!AT99,Table1[Month],Snapshot!$W$4)*-1) | AV99: =IF(ISBLANK(AT99),"",COUNTIFS(Table1[Merchant],Snapshot!AT99,Table1[Month],Snapshot!$W$4)) | AW99: =IFERROR(RANK(AV99,$AV$6:$AV$200)+COUNTIF($AV$6:AV99,AV99)-1,"") | AX99: =IFERROR(RANK(AU99,$AU$6:$AU$200)+COUNTIF($AU$6:AU99,AU99)-1,"")
V100: =IF(ISBLANK(W100),"--",TEXT(W100,"mmmm")&" "&TEXT(W100,"YYYY")) -> -- | AU100: =IF(ISBLANK(AT100),"",SUMIFS(Table1[Amount $],Table1[Merchant],Snapshot!AT100,Table1[Month],Snapshot!$W$4)*-1) | AV100: =IF(ISBLANK(AT100),"",COUNTIFS(Table1[Merchant],Snapshot!AT100,Table1[Month],Snapshot!$W$4)) | AW100: =IFERROR(RANK(AV100,$AV$6:$AV$200)+COUNTIF($AV$6:AV100,AV100)-1,"") | AX100: =IFERROR(RANK(AU100,$AU$6:$AU$200)+COUNTIF($AU$6:AU100,AU100)-1,"")
V101: =IF(ISBLANK(W101),"--",TEXT(W101,"mmmm")&" "&TEXT(W101,"YYYY")) -> -- | AU101: =IF(ISBLANK(AT101),"",SUMIFS(Table1[Amount $],Table1[Merchant],Snapshot!AT101,Table1[Month],Snapshot!$W$4)*-1) | AV101: =IF(ISBLANK(AT101),"",COUNTIFS(Table1[Merchant],Snapshot!AT101,Table1[Month],Snapshot!$W$4)) | AW101: =IFERROR(RANK(AV101,$AV$6:$AV$200)+COUNTIF($AV$6:AV101,AV101)-1,"") | AX101: =IFERROR(RANK(AU101,$AU$6:$AU$200)+COUNTIF($AU$6:AU101,AU101)-1,"")
V102: =IF(ISBLANK(W102),"--",TEXT(W102,"mmmm")&" "&TEXT(W102,"YYYY")) -> -- | AU102: =IF(ISBLANK(AT102),"",SUMIFS(Table1[Amount $],Table1[Merchant],Snapshot!AT102,Table1[Month],Snapshot!$W$4)*-1) | AV102: =IF(ISBLANK(AT102),"",COUNTIFS(Table1[Merchant],Snapshot!AT102,Table1[Month],Snapshot!$W$4)) | AW102: =IFERROR(RANK(AV102,$AV$6:$AV$200)+COUNTIF($AV$6:AV102,AV102)-1,"") | AX102: =IFERROR(RANK(AU102,$AU$6:$AU$200)+COUNTIF($AU$6:AU102,AU102)-1,"")
V103: =IF(ISBLANK(W103),"--",TEXT(W103,"mmmm")&" "&TEXT(W103,"YYYY")) -> -- | AU103: =IF(ISBLANK(AT103),"",SUMIFS(Table1[Amount $],Table1[Merchant],Snapshot!AT103,Table1[Month],Snapshot!$W$4)*-1) | AV103: =IF(ISBLANK(AT103),"",COUNTIFS(Table1[Merchant],Snapshot!AT103,Table1[Month],Snapshot!$W$4)) | AW103: =IFERROR(RANK(AV103,$AV$6:$AV$200)+COUNTIF($AV$6:AV103,AV103)-1,"") | AX103: =IFERROR(RANK(AU103,$AU$6:$AU$200)+COUNTIF($AU$6:AU103,AU103)-1,"")
V104: =IF(ISBLANK(W104),"--",TEXT(W104,"mmmm")&" "&TEXT(W104,"YYYY")) -> -- | AU104: =IF(ISBLANK(AT104),"",SUMIFS(Table1[Amount $],Table1[Merchant],Snapshot!AT104,Table1[Month],Snapshot!$W$4)*-1) | AV104: =IF(ISBLANK(AT104),"",COUNTIFS(Table1[Merchant],Snapshot!AT104,Table1[Month],Snapshot!$W$4)) | AW104: =IFERROR(RANK(AV104,$AV$6:$AV$200)+COUNTIF($AV$6:AV104,AV104)-1,"") | AX104: =IFERROR(RANK(AU104,$AU$6:$AU$200)+COUNTIF($AU$6:AU104,AU104)-1,"")
V105: =IF(ISBLANK(W105),"--",TEXT(W105,"mmmm")&" "&TEXT(W105,"YYYY")) -> -- | AU105: =IF(ISBLANK(AT105),"",SUMIFS(Table1[Amount $],Table1[Merchant],Snapshot!AT105,Table1[Month],Snapshot!$W$4)*-1) | AV105: =IF(ISBLANK(AT105),"",COUNTIFS(Table1[Merchant],Snapshot!AT105,Table1[Month],Snapshot!$W$4)) | AW105: =IFERROR(RANK(AV105,$AV$6:$AV$200)+COUNTIF($AV$6:AV105,AV105)-1,"") | AX105: =IFERROR(RANK(AU105,$AU$6:$AU$200)+COUNTIF($AU$6:AU105,AU105)-1,"")
V106: =IF(ISBLANK(W106),"--",TEXT(W106,"mmmm")&" "&TEXT(W106,"YYYY")) -> -- | AU106: =IF(ISBLANK(AT106),"",SUMIFS(Table1[Amount $],Table1[Merchant],Snapshot!AT106,Table1[Month],Snapshot!$W$4)*-1) | AV106: =IF(ISBLANK(AT106),"",COUNTIFS(Table1[Merchant],Snapshot!AT106,Table1[Month],Snapshot!$W$4)) | AW106: =IFERROR(RANK(AV106,$AV$6:$AV$200)+COUNTIF($AV$6:AV106,AV106)-1,"") | AX106: =IFERROR(RANK(AU106,$AU$6:$AU$200)+COUNTIF($AU$6:AU106,AU106)-1,"")
V107: =IF(ISBLANK(W107),"--",TEXT(W107,"mmmm")&" "&TEXT(W107,"YYYY")) -> -- | AU107: =IF(ISBLANK(AT107),"",SUMIFS(Table1[Amount $],Table1[Merchant],Snapshot!AT107,Table1[Month],Snapshot!$W$4)*-1) | AV107: =IF(ISBLANK(AT107),"",COUNTIFS(Table1[Merchant],Snapshot!AT107,Table1[Month],Snapshot!$W$4)) | AW107: =IFERROR(RANK(AV107,$AV$6:$AV$200)+COUNTIF($AV$6:AV107,AV107)-1,"") | AX107: =IFERROR(RANK(AU107,$AU$6:$AU$200)+COUNTIF($AU$6:AU107,AU107)-1,"")
V108: =IF(ISBLANK(W108),"--",TEXT(W108,"mmmm")&" "&TEXT(W108,"YYYY")) -> -- | AU108: =IF(ISBLANK(AT108),"",SUMIFS(Table1[Amount $],Table1[Merchant],Snapshot!AT108,Table1[Month],Snapshot!$W$4)*-1) | AV108: =IF(ISBLANK(AT108),"",COUNTIFS(Table1[Merchant],Snapshot!AT108,Table1[Month],Snapshot!$W$4)) | AW108: =IFERROR(RANK(AV108,$AV$6:$AV$200)+COUNTIF($AV$6:AV108,AV108)-1,"") | AX108: =IFERROR(RANK(AU108,$AU$6:$AU$200)+COUNTIF($AU$6:AU108,AU108)-1,"")
V109: =IF(ISBLANK(W109),"--",TEXT(W109,"mmmm")&" "&TEXT(W109,"YYYY")) -> -- | AU109: =IF(ISBLANK(AT109),"",SUMIFS(Table1[Amount $],Table1[Merchant],Snapshot!AT109,Table1[Month],Snapshot!$W$4)*-1) | AV109: =IF(ISBLANK(AT109),"",COUNTIFS(Table1[Merchant],Snapshot!AT109,Table1[Month],Snapshot!$W$4)) | AW109: =IFERROR(RANK(AV109,$AV$6:$AV$200)+COUNTIF($AV$6:AV109,AV109)-1,"") | AX109: =IFERROR(RANK(AU109,$AU$6:$AU$200)+COUNTIF($AU$6:AU109,AU109)-1,"")
V110: =IF(ISBLANK(W110),"--",TEXT(W110,"mmmm")&" "&TEXT(W110,"YYYY")) -> -- | AU110: =IF(ISBLANK(AT110),"",SUMIFS(Table1[Amount $],Table1[Merchant],Snapshot!AT110,Table1[Month],Snapshot!$W$4)*-1) | AV110: =IF(ISBLANK(AT110),"",COUNTIFS(Table1[Merchant],Snapshot!AT110,Table1[Month],Snapshot!$W$4)) | AW110: =IFERROR(RANK(AV110,$AV$6:$AV$200)+COUNTIF($AV$6:AV110,AV110)-1,"") | AX110: =IFERROR(RANK(AU110,$AU$6:$AU$200)+COUNTIF($AU$6:AU110,AU110)-1,"")
... V200: =IF(ISBLANK(W200),"--",TEXT(W200,"mmmm")&" "&TEXT(W200,"YYYY")) -> -- | AU200: =IF(ISBLANK(AT200),"",SUMIFS(Table1[Amount $],Table1[Merchant],Snapshot!AT200,Table1[Month],Snapshot!$W$4)*-1) | AV200: =IF(ISBLANK(AT200),"",COUNTIFS(Table1[Merchant],Snapshot!AT200,Table1[Month],Snapshot!$W$4)) | AW200: =IFERROR(RANK(AV200,$AV$6:$AV$200)+COUNTIF($AV$6:AV200,AV200)-1,"") | AX200: =IFERROR(RANK(AU200,$AU$6:$AU$200)+COUNTIF($AU$6:AU200,AU200)-1,"")

Sheet Transactions
B2: Transactions
B3: Transactions from your added accounts are automatically imported here. Click Sync in the task pane to import more transactions. Edit the Merchant and Category columns to better reflect where and how you spend your money.
B6: Date | C6: Merchant | D6: Category | E6: Subcategory | F6: Amount $ | G6: Account | H6: Account Number | I6: Institution | J6: Transaction_ID | K6: Account_ID | L6: Institution_ID | M6: Category_ID | N6: Subcategory_ID | O6: Category Type | P6: Date_Day | Q6: Date_Month | R6: Date_Year | S6: Beginning of Week | T6: Month
B7: 44564 | C7: Atm Cash Deposit On | D7: Income | F7: 194 | G7: =_xlfn.XLOOKUP(Table1[[#This Row],[Account_ID]], Accounts[ID], Accounts[Account nickname], "Unknown") -> WF | H7: =_xlfn.XLOOKUP(Table1[[#This Row],[Account_ID]], Accounts[ID], Accounts[Account'#], "Unknown") -> 4636 | I7: =_xlfn.XLOOKUP(_xlfn.XLOOKUP(Table1[[#This Row],[Account]],Accounts[Account nickname],Accounts[Institution ID]),Institutions[ID],Institutions[Institution nickname],"Unknown") -> Wells Fargo | J7: 52442766181a4ee1ae10578c563a3cca | K7: 4918dbe6db3e4b9384fdfe7083417a5f | L7: 8b5374947e1d46e7a0f86b54ee722e44 | M7: =IF(NOT(_xlfn.XLOOKUP(Table1[[#This Row],[Category]],CategoriesTable[Category name],CategoriesTable[ID])=0),_xlfn.XLOOKUP(Table1[[#This Row],[Category]],CategoriesTable[Category name],CategoriesTable[ID]),_xlfn.XLOOKUP("Uncategorized",CategoriesTable[Category name],CategoriesTable[ID])) -> fabfe582932d48b78ac2846c1ec3d43f | N7: =IF(AND(NOT(ISBLANK(Table1[[#This Row],[Subcategory]])),NOT(_xlfn.XLOOKUP(Table1[[#This Row],[Subcategory]],SubcategoriesTable[Subcategory name],SubcategoriesTable[ID])=0)),_xlfn.XLOOKUP(Table1[[#This Row],[Subcategory]],SubcategoriesTable[Subcategory name],SubcategoriesTable[ID]),"") | O7: {=IFERROR(INDEX(CategoriesTable[Category type],MATCH(Table1[[#This Row],[Category]],CategoriesTable[Category name],0),0),"")} -> Expense | P7: 3 | Q7: =MONTH(Table1[[#This Row],[Date]]) -> 1 | R7: 2022 | S7: =IF(ISBLANK(Table1[[#This Row],[Date]]),"",Table1[[#This Row],[Date]]-WEEKDAY(Table1[[#This Row],[Date]],2)+1) -> 44564 | T7: =IF(ISBLANK(Table1[[#This Row],[Date]]),"",DATE(Table1[[#This Row],[Date_Year]],Table1[[#This Row],[Date_Month]],1)) -> 44562
B8: 44564 | C8: Best Buy | D8: Payment | F8: -241.99 | G8: =_xlfn.XLOOKUP(Table1[[#This Row],[Account_ID]], Accounts[ID], Accounts[Account nickname], "Unknown") -> WF | H8: =_xlfn.XLOOKUP(Table1[[#This Row],[Account_ID]], Accounts[ID], Accounts[Account'#], "Unknown") -> 4636 | I8: =_xlfn.XLOOKUP(_xlfn.XLOOKUP(Table1[[#This Row],[Account]],Accounts[Account nickname],Accounts[Institution ID]),Institutions[ID],Institutions[Institution nickname],"Unknown") -> Wells Fargo | J8: c6da6d2af0494ea79fdf99c46548c854 | K8: 4918dbe6db3e4b9384fdfe7083417a5f | L8: 8b5374947e1d46e7a0f86b54ee722e44 | M8: =IF(NOT(_xlfn.XLOOKUP(Table1[[#This Row],[Category]],CategoriesTable[Category name],CategoriesTable[ID])=0),_xlfn.XLOOKUP(Table1[[#This Row],[Category]],CategoriesTable[Category name],CategoriesTable[ID]),_xlfn.XLOOKUP("Uncategorized",CategoriesTable[Category name],CategoriesTable[ID])) -> 6385c1768b814d3d89087c436c9cab15 | N8: =IF(AND(NOT(ISBLANK(Table1[[#This Row],[Subcategory]])),NOT(_xlfn.XLOOKUP(Table1[[#This Row],[Subcategory]],SubcategoriesTable[Subcategory name],SubcategoriesTable[ID])=0)),_xlfn.XLOOKUP(Table1[[#This Row],[Subcategory]],SubcategoriesTable[Subcategory name],SubcategoriesTable[ID]),"") | O8: {=IFERROR(INDEX(CategoriesTable[Category type],MATCH(Table1[[#This Row],[Category]],CategoriesTable[Category name],0),0),"")} -> Expense | P8: 3 | Q8: =MONTH(Table1[[#This Row],[Date]]) -> 1 | R8: 2022 | S8: =IF(ISBLANK(Table1[[#This Row],[Date]]),"",Table1[[#This Row],[Date]]-WEEKDAY(Table1[[#This Row],[Date]],2)+1) -> 44564 | T8: =IF(ISBLANK(Table1[[#This Row],[Date]]),"",DATE(Table1[[#This Row],[Date_Year]],Table1[[#This Row],[Date_Month]],1)) -> 44562
B9: 44564 | C9: Discover E Payment Lewis | D9: Payment | F9: -1800 | G9: =_xlfn.XLOOKUP(Table1[[#This Row],[Account_ID]], Accounts[ID], Accounts[Account nickname], "Unknown") -> WF | H9: =_xlfn.XLOOKUP(Table1[[#This Row],[Account_ID]], Accounts[ID], Accounts[Account'#], "Unknown") -> 4636 | I9: =_xlfn.XLOOKUP(_xlfn.XLOOKUP(Table1[[#This Row],[Account]],Accounts[Account nickname],Accounts[Institution ID]),Institutions[ID],Institutions[Institution nickname],"Unknown") -> Wells Fargo | J9: bae995958c8746ec90e0ffce08df69ac | K9: 4918dbe6db3e4b9384fdfe7083417a5f | L9: 8b5374947e1d46e7a0f86b54ee722e44 | M9: =IF(NOT(_xlfn.XLOOKUP(Table1[[#This Row],[Category]],CategoriesTable[Category name],CategoriesTable[ID])=0),_xlfn.XLOOKUP(Table1[[#This Row],[Category]],CategoriesTable[Category name],CategoriesTable[ID]),_xlfn.XLOOKUP("Uncategorized",CategoriesTable[Category name],CategoriesTable[ID])) -> 6385c1768b814d3d89087c436c9cab15 | N9: =IF(AND(NOT(ISBLANK(Table1[[#This Row],[Subcategory]])),NOT(_xlfn.XLOOKUP(Table1[[#This Row],[Subcategory]],SubcategoriesTable[Subcategory name],SubcategoriesTable[ID])=0)),_xlfn.XLOOKUP(Table1[[#This Row],[Subcategory]],SubcategoriesTable[Subcategory name],SubcategoriesTable[ID]),"") | O9: {=IFERROR(INDEX(CategoriesTable[Category type],MATCH(Table1[[#This Row],[Category]],CategoriesTable[Category name],0),0),"")} -> Expense | P9: 3 | Q9: =MONTH(Table1[[#This Row],[Date]]) -> 1 | R9: 2022 | S9: =IF(ISBLANK(Table1[[#This Row],[Date]]),"",Table1[[#This Row],[Date]]-WEEKDAY(Table1[[#This Row],[Date]],2)+1) -> 44564 | T9: =IF(ISBLANK(Table1[[#This Row],[Date]]),"",DATE(Table1[[#This Row],[Date_Year]],Table1[[#This Row],[Date_Month]],1)) -> 44562
B10: 44564 | C10: Paypal Inst Xfer Louisck | D10: Restaurants/Dining | F10: -10 | G10: =_xlfn.XLOOKUP(Table1[[#This Row],[Account_ID]], Accounts[ID], Accounts[Account nickname], "Unknown") -> WF | H10: =_xlfn.XLOOKUP(Table1[[#This Row],[Account_ID]], Accounts[ID], Accounts[Account'#], "Unknown") -> 4636 | I10: =_xlfn.XLOOKUP(_xlfn.XLOOKUP(Table1[[#This Row],[Account]],Accounts[Account nickname],Accounts[Institution ID]),Institutions[ID],Institutions[Institution nickname],"Unknown") -> Wells Fargo | J10: b312850ec24c4cbcbae15dcb87f30b7b | K10: 4918dbe6db3e4b9384fdfe7083417a5f | L10: 8b5374947e1d46e7a0f86b54ee722e44 | M10: =IF(NOT(_xlfn.XLOOKUP(Table1[[#This Row],[Category]],CategoriesTable[Category name],CategoriesTable[ID])=0),_xlfn.XLOOKUP(Table1[[#This Row],[Category]],CategoriesTable[Category name],CategoriesTable[ID]),_xlfn.XLOOKUP("Uncategorized",CategoriesTable[Category name],CategoriesTable[ID])) -> 3dafc6bd8d7c45ae9840ff09e01567d1 | N10: =IF(AND(NOT(ISBLANK(Table1[[#This Row],[Subcategory]])),NOT(_xlfn.XLOOKUP(Table1[[#This Row],[Subcategory]],SubcategoriesTable[Subcategory name],SubcategoriesTable[ID])=0)),_xlfn.XLOOKUP(Table1[[#This Row],[Subcategory]],SubcategoriesTable[Subcategory name],SubcategoriesTable[ID]),"") | O10: {=IFERROR(INDEX(CategoriesTable[Category type],MATCH(Table1[[#This Row],[Category]],CategoriesTable[Category name],0),0),"")} -> Expense | P10: 3 | Q10: =MONTH(Table1[[#This Row],[Date]]) -> 1 | R10: 2022 | S10: =IF(ISBLANK(Table1[[#This Row],[Date]]),"",Table1[[#This Row],[Date]]-WEEKDAY(Table1[[#This Row],[Date]],2)+1) -> 44564 | T10: =IF(ISBLANK(Table1[[#This Row],[Date]]),"",DATE(Table1[[#This Row],[Date_Year]],Table1[[#This Row],[Date_Month]],1)) -> 44562
B11: 44564 | C11: Transfer To Lewis Sharon | D11: Home | F11: -485 | G11: =_xlfn.XLOOKUP(Table1[[#This Row],[Account_ID]], Accounts[ID], Accounts[Account nickname], "Unknown") -> WF | H11: =_xlfn.XLOOKUP(Table1[[#This Row],[Account_ID]], Accounts[ID], Accounts[Account'#], "Unknown") -> 4636 | I11: =_xlfn.XLOOKUP(_xlfn.XLOOKUP(Table1[[#This Row],[Account]],Accounts[Account nickname],Accounts[Institution ID]),Institutions[ID],Institutions[Institution nickname],"Unknown") -> Wells Fargo | J11: 1d628293b9194a33ad7125ab032b2e2e | K11: 4918dbe6db3e4b9384fdfe7083417a5f | L11: 8b5374947e1d46e7a0f86b54ee722e44 | M11: =IF(NOT(_xlfn.XLOOKUP(Table1[[#This Row],[Category]],CategoriesTable[Category name],CategoriesTable[ID])=0),_xlfn.XLOOKUP(Table1[[#This Row],[Category]],CategoriesTable[Category name],CategoriesTable[ID]),_xlfn.XLOOKUP("Uncategorized",CategoriesTable[Category name],CategoriesTable[ID])) -> 0613345f0a8b4edfb294d0fdc6fe7382 | N11: =IF(AND(NOT(ISBLANK(Table1[[#This Row],[Subcategory]])),NOT(_xlfn.XLOOKUP(Table1[[#This Row],[Subcategory]],SubcategoriesTable[Subcategory name],SubcategoriesTable[ID])=0)),_xlfn.XLOOKUP(Table1[[#This Row],[Subcategory]],SubcategoriesTable[Subcategory name],SubcategoriesTable[ID]),"") | O11: {=IFERROR(INDEX(CategoriesTable[Category type],MATCH(Table1[[#This Row],[Category]],CategoriesTable[Category name],0),0),"")} -> Expense | P11: 3 | Q11: =MONTH(Table1[[#This Row],[Date]]) -> 1 | R11: 2022 | S11: =IF(ISBLANK(Table1[[#This Row],[Date]]),"",Table1[[#This Row],[Date]]-WEEKDAY(Table1[[#This Row],[Date]],2)+1) -> 44564 | T11: =IF(ISBLANK(Table1[[#This Row],[Date]]),"",DATE(Table1[[#This Row],[Date_Year]],Table1[[#This Row],[Date_Month]],1)) -> 44562
B12: 44564 | C12: Venmo | D12: Income | F12: 477.73 | G12: =_xlfn.XLOOKUP(Table1[[#This Row],[Account_ID]], Accounts[ID], Accounts[Account nickname], "Unknown") -> WF | H12: =_xlfn.XLOOKUP(Table1[[#This Row],[Account_ID]], Accounts[ID], Accounts[Account'#], "Unknown") -> 4636 | I12: =_xlfn.XLOOKUP(_xlfn.XLOOKUP(Table1[[#This Row],[Account]],Accounts[Account nickname],Accounts[Institution ID]),Institutions[ID],Institutions[Institution nickname],"Unknown") -> Wells Fargo | J12: 4ad2fd262f754e32be7970af4947f59a | K12: 4918dbe6db3e4b9384fdfe7083417a5f | L12: 8b5374947e1d46e7a0f86b54ee722e44 | M12: =IF(NOT(_xlfn.XLOOKUP(Table1[[#This Row],[Category]],CategoriesTable[Category name],CategoriesTable[ID])=0),_xlfn.XLOOKUP(Table1[[#This Row],[Category]],CategoriesTable[Category name],CategoriesTable[ID]),_xlfn.XLOOKUP("Uncategorized",CategoriesTable[Category name],CategoriesTable[ID])) -> fabfe582932d48b78ac2846c1ec3d43f | N12: =IF(AND(NOT(ISBLANK(Table1[[#This Row],[Subcategory]])),NOT(_xlfn.XLOOKUP(Table1[[#This Row],[Subcategory]],SubcategoriesTable[Subcategory name],SubcategoriesTable[ID])=0)),_xlfn.XLOOKUP(Table1[[#This Row],[Subcategory]],SubcategoriesTable[Subcategory name],SubcategoriesTable[ID]),"") | O12: {=IFERROR(INDEX(CategoriesTable[Category type],MATCH(Table1[[#This Row],[Category]],CategoriesTable[Category name],0),0),"")} -> Expense | P12: 3 | Q12: =MONTH(Table1[[#This Row],[Date]]) -> 1 | R12: 2022 | S12: =IF(ISBLANK(Table1[[#This Row],[Date]]),"",Table1[[#This Row],[Date]]-WEEKDAY(Table1[[#This Row],[Date]],2)+1) -> 44564 | T12: =IF(ISBLANK(Table1[[#This Row],[Date]]),"",DATE(Table1[[#This Row],[Date_Year]],Table1[[#This Row],[Date_Month]],1)) -> 44562
B13: 44564 | C13: Hulu | D13: Shopping | F13: -12.99 | G13: =_xlfn.XLOOKUP(Table1[[#This Row],[Account_ID]], Accounts[ID], Accounts[Account nickname], "Unknown") -> Discover | H13: =_xlfn.XLOOKUP(Table1[[#This Row],[Account_ID]], Accounts[ID], Accounts[Account'#], "Unknown") -> 4618 | I13: =_xlfn.XLOOKUP(_xlfn.XLOOKUP(Table1[[#This Row],[Account]],Accounts[Account nickname],Accounts[Institution ID]),Institutions[ID],Institutions[Institution nickname],"Unknown") -> Discover | J13: d703fb25253548039c981740cd4ec881 | K13: 0048d75f4d1d47f3b69428db4a68f3dd | L13: d09d1b66884d43439b5dad982b7d9e52 | M13: =IF(NOT(_xlfn.XLOOKUP(Table1[[#This Row],[Category]],CategoriesTable[Category name],CategoriesTable[ID])=0),_xlfn.XLOOKUP(Table1[[#This Row],[Category]],CategoriesTable[Category name],CategoriesTable[ID]),_xlfn.XLOOKUP("Uncategorized",CategoriesTable[Category name],CategoriesTable[ID])) -> 4144f48502914015b998277a326fcedc | N13: =IF(AND(NOT(ISBLANK(Table1[[#This Row],[Subcategory]])),NOT(_xlfn.XLOOKUP(Table1[[#This Row],[Subcategory]],SubcategoriesTable[Subcategory name],SubcategoriesTable[ID])=0)),_xlfn.XLOOKUP(Table1[[#This Row],[Subcategory]],SubcategoriesTable[Subcategory name],SubcategoriesTable[ID]),"") | O13: {=IFERROR(INDEX(CategoriesTable[Category type],MATCH(Table1[[#This Row],[Category]],CategoriesTable[Category name],0),0),"")} -> Expense | P13: 3 | Q13: =MONTH(Table1[[#This Row],[Date]]) -> 1 | R13: 2022 | S13: =IF(ISBLANK(Table1[[#This Row],[Date]]),"",Table1[[#This Row],[Date]]-WEEKDAY(Table1[[#This Row],[Date]],2)+1) -> 44564 | T13: =IF(ISBLANK(Table1[[#This Row],[Date]]),"",DATE(Table1[[#This Row],[Date_Year]],Table1[[#This Row],[Date_Month]],1)) -> 44562
B14: 44563 | C14: Internet Payment | D14: Payment | F14: 1800 | G14: =_xlfn.XLOOKUP(Table1[[#This Row],[Account_ID]], Accounts[ID], Accounts[Account nickname], "Unknown") -> Discover | H14: =_xlfn.XLOOKUP(Table1[[#This Row],[Account_ID]], Accounts[ID], Accounts[Account'#], "Unknown") -> 4618 | I14: =_xlfn.XLOOKUP(_xlfn.XLOOKUP(Table1[[#This Row],[Account]],Accounts[Account nickname],Accounts[Institution ID]),Institutions[ID],Institutions[Institution nickname],"Unknown") -> Discover | J14: 99b79c9fcfb64c89928781184ebe4cf8 | K14: 0048d75f4d1d47f3b69428db4a68f3dd | L14: d09d1b66884d43439b5dad982b7d9e52 | M14: =IF(NOT(_xlfn.XLOOKUP(Table1[[#This Row],[Category]],CategoriesTable[Category name],CategoriesTable[ID])=0),_xlfn.XLOOKUP(Table1[[#This Row],[Category]],CategoriesTable[Category name],CategoriesTable[ID]),_xlfn.XLOOKUP("Uncategorized",CategoriesTable[Category name],CategoriesTable[ID])) -> 6385c1768b814d3d89087c436c9cab15 | N14: =IF(AND(NOT(ISBLANK(Table1[[#This Row],[Subcategory]])),NOT(_xlfn.XLOOKUP(Table1[[#This Row],[Subcategory]],SubcategoriesTable[Subcategory name],SubcategoriesTable[ID])=0)),_xlfn.XLOOKUP(Table1[[#This Row],[Subcategory]],SubcategoriesTable[Subcategory name],SubcategoriesTable[ID]),"") | O14: {=IFERROR(INDEX(CategoriesTable[Category type],MATCH(Table1[[#This Row],[Category]],CategoriesTable[Category name],0),0),"")} -> Expense | P14: 2 | Q14: =MONTH(Table1[[#This Row],[Date]]) -> 1 | R14: 2022 | S14: =IF(ISBLANK(Table1[[#This Row],[Date]]),"",Table1[[#This Row],[Date]]-WEEKDAY(Table1[[#This Row],[Date]],2)+1) -> 44557 | T14: =IF(ISBLANK(Table1[[#This Row],[Date]]),"",DATE(Table1[[#This Row],[Date_Year]],Table1[[#This Row],[Date_Month]],1)) -> 44562
B15: 44563 | C15: Online Payment | D15: Payment | F15: 241.99 | G15: =_xlfn.XLOOKUP(Table1[[#This Row],[Account_ID]], Accounts[ID], Accounts[Account nickname], "Unknown") -> BB | H15: =_xlfn.XLOOKUP(Table1[[#This Row],[Account_ID]], Accounts[ID], Accounts[Account'#], "Unknown") -> 4561 | I15: =_xlfn.XLOOKUP(_xlfn.XLOOKUP(Table1[[#This Row],[Account]],Accounts[Account nickname],Accounts[Institution ID]),Institutions[ID],Institutions[Institution nickname],"Unknown") -> Best Buy - Citi Card | J15: dfa426ee419f4157ac4ea3b22b361e53 | K15: a82d9aba872e4e9b9684a363d4cc52b5 | L15: e7a999902ffc4e26bd6b6c2d4214aabd | M15: =IF(NOT(_xlfn.XLOOKUP(Table1[[#This Row],[Category]],CategoriesTable[Category name],CategoriesTable[ID])=0),_xlfn.XLOOKUP(Table1[[#This Row],[Category]],CategoriesTable[Category name],CategoriesTable[ID]),_xlfn.XLOOKUP("Uncategorized",CategoriesTable[Category name],CategoriesTable[ID])) -> 6385c1768b814d3d89087c436c9cab15 | N15: =IF(AND(NOT(ISBLANK(Table1[[#This Row],[Subcategory]])),NOT(_xlfn.XLOOKUP(Table1[[#This Row],[Subcategory]],SubcategoriesTable[Subcategory name],SubcategoriesTable[ID])=0)),_xlfn.XLOOKUP(Table1[[#This Row],[Subcategory]],SubcategoriesTable[Subcategory name],SubcategoriesTable[ID]),"") | O15: {=IFERROR(INDEX(CategoriesTable[Category type],MATCH(Table1[[#This Row],[Category]],CategoriesTable[Category name],0),0),"")} -> Expense | P15: 2 | Q15: =MONTH(Table1[[#This Row],[Date]]) -> 1 | R15: 2022 | S15: =IF(ISBLANK(Table1[[#This Row],[Date]]),"",Table1[[#This Row],[Date]]-WEEKDAY(Table1[[#This Row],[Date]],2)+1) -> 44557 | T15: =IF(ISBLANK(Table1[[#This Row],[Date]]),"",DATE(Table1[[#This Row],[Date_Year]],Table1[[#This Row],[Date_Month]],1)) -> 44562
B16: 44563 | C16: Krystal And Saagar Dc | D16: Payment | F16: -10 | G16: =_xlfn.XLOOKUP(Table1[[#This Row],[Account_ID]], Accounts[ID], Accounts[Account nickname], "Unknown") -> Discover | H16: =_xlfn.XLOOKUP(Table1[[#This Row],[Account_ID]], Accounts[ID], Accounts[Account'#], "Unknown") -> 4618 | I16: =_xlfn.XLOOKUP(_xlfn.XLOOKUP(Table1[[#This Row],[Account]],Accounts[Account nickname],Accounts[Institution ID]),Institutions[ID],Institutions[Institution nickname],"Unknown") -> Discover | J16: 59dadcea3eec4565b1eee790074c6188 | K16: 0048d75f4d1d47f3b69428db4a68f3dd | L16: d09d1b66884d43439b5dad982b7d9e52 | M16: =IF(NOT(_xlfn.XLOOKUP(Table1[[#This Row],[Category]],CategoriesTable[Category name],CategoriesTable[ID])=0),_xlfn.XLOOKUP(Table1[[#This Row],[Category]],CategoriesTable[Category name],CategoriesTable[ID]),_xlfn.XLOOKUP("Uncategorized",CategoriesTable[Category name],CategoriesTable[ID])) -> 6385c1768b814d3d89087c436c9cab15 | N16: =IF(AND(NOT(ISBLANK(Table1[[#This Row],[Subcategory]])),NOT(_xlfn.XLOOKUP(Table1[[#This Row],[Subcategory]],SubcategoriesTable[Subcategory name],SubcategoriesTable[ID])=0)),_xlfn.XLOOKUP(Table1[[#This Row],[Subcategory]],SubcategoriesTable[Subcategory name],SubcategoriesTable[ID]),"") | O16: {=IFERROR(INDEX(CategoriesTable[Category type],MATCH(Table1[[#This Row],[Category]],CategoriesTable[Category name],0),0),"")} -> Expense | P16: 2 | Q16: =MONTH(Table1[[#This Row],[Date]]) -> 1 | R16: 2022 | S16: =IF(ISBLANK(Table1[[#This Row],[Date]]),"",Table1[[#This Row],[Date]]-WEEKDAY(Table1[[#This Row],[Date]],2)+1) -> 44557 | T16: =IF(ISBLANK(Table1[[#This Row],[Date]]),"",DATE(Table1[[#This Row],[Date_Year]],Table1[[#This Row],[Date_Month]],1)) -> 44562
B17: 44562 | C17: Jimmy Johns | D17: Restaurants/Dining | E17: Resteraunts | F17: -18.02 | G17: =_xlfn.XLOOKUP(Table1[[#This Row],[Account_ID]], Accounts[ID], Accounts[Account nickname], "Unknown") -> Discover | H17: =_xlfn.XLOOKUP(Table1[[#This Row],[Account_ID]], Accounts[ID], Accounts[Account'#], "Unknown") -> 4618 | I17: =_xlfn.XLOOKUP(_xlfn.XLOOKUP(Table1[[#This Row],[Account]],Accounts[Account nickname],Accounts[Institution ID]),Institutions[ID],Institutions[Institution nickname],"Unknown") -> Discover | J17: 3c43aac1f46c43a5bcfd57e9fdb26e4c | K17: 0048d75f4d1d47f3b69428db4a68f3dd | L17: d09d1b66884d43439b5dad982b7d9e52 | M17: =IF(NOT(_xlfn.XLOOKUP(Table1[[#This Row],[Category]],CategoriesTable[Category name],CategoriesTable[ID])=0),_xlfn.XLOOKUP(Table1[[#This Row],[Category]],CategoriesTable[Category name],CategoriesTable[ID]),_xlfn.XLOOKUP("Uncategorized",CategoriesTable[Category name],CategoriesTable[ID])) -> 3dafc6bd8d7c45ae9840ff09e01567d1 | N17: =IF(AND(NOT(ISBLANK(Table1[[#This Row],[Subcategory]])),NOT(_xlfn.XLOOKUP(Table1[[#This Row],[Subcategory]],SubcategoriesTable[Subcategory name],SubcategoriesTable[ID])=0)),_xlfn.XLOOKUP(Table1[[#This Row],[Subcategory]],SubcategoriesTable[Subcategory name],SubcategoriesTable[ID]),"") -> 500e6ba7cba37a7a2a33da8c057b4cb8 | O17: {=IFERROR(INDEX(CategoriesTable[Category type],MATCH(Table1[[#This Row],[Category]],CategoriesTable[Category name],0),0),"")} -> Expense | P17: 1 | Q17: =MONTH(Table1[[#This Row],[Date]]) -> 1 | R17: 2022 | S17: =IF(ISBLANK(Table1[[#This Row],[Date]]),"",Table1[[#This Row],[Date]]-WEEKDAY(Table1[[#This Row],[Date]],2)+1) -> 44557 | T17: =IF(ISBLANK(Table1[[#This Row],[Date]]),"",DATE(Table1[[#This Row],[Date_Year]],Table1[[#This Row],[Date_Month]],1)) -> 44562
B18: 44562 | C18: Olive Garden | D18: Restaurants/Dining | E18: Resteraunts | F18: -60 | G18: =_xlfn.XLOOKUP(Table1[[#This Row],[Account_ID]], Accounts[ID], Accounts[Account nickname], "Unknown") -> Discover | H18: =_xlfn.XLOOKUP(Table1[[#This Row],[Account_ID]], Accounts[ID], Accounts[Account'#], "Unknown") -> 4618 | I18: =_xlfn.XLOOKUP(_xlfn.XLOOKUP(Table1[[#This Row],[Account]],Accounts[Account nickname],Accounts[Institution ID]),Institutions[ID],Institutions[Institution nickname],"Unknown") -> Discover | J18: aac185fe32ae4c87809f3a3c96cdd8eb | K18: 0048d75f4d1d47f3b69428db4a68f3dd | L18: d09d1b66884d43439b5dad982b7d9e52 | M18: =IF(NOT(_xlfn.XLOOKUP(Table1[[#This Row],[Category]],CategoriesTable[Category name],CategoriesTable[ID])=0),_xlfn.XLOOKUP(Table1[[#This Row],[Category]],CategoriesTable[Category name],CategoriesTable[ID]),_xlfn.XLOOKUP("Uncategorized",CategoriesTable[Category name],CategoriesTable[ID])) -> 3dafc6bd8d7c45ae9840ff09e01567d1 | N18: =IF(AND(NOT(ISBLANK(Table1[[#This Row],[Subcategory]])),NOT(_xlfn.XLOOKUP(Table1[[#This Row],[Subcategory]],SubcategoriesTable[Subcategory name],SubcategoriesTable[ID])=0)),_xlfn.XLOOKUP(Table1[[#This Row],[Subcategory]],SubcategoriesTable[Subcategory name],SubcategoriesTable[ID]),"") -> 500e6ba7cba37a7a2a33da8c057b4cb8 | O18: {=IFERROR(INDEX(CategoriesTable[Category type],MATCH(Table1[[#This Row],[Category]],CategoriesTable[Category name],0),0),"")} -> Expense | P18: 1 | Q18: =MONTH(Table1[[#This Row],[Date]]) -> 1 | R18: 2022 | S18: =IF(ISBLANK(Table1[[#This Row],[Date]]),"",Table1[[#This Row],[Date]]-WEEKDAY(Table1[[#This Row],[Date]],2)+1) -> 44557 | T18: =IF(ISBLANK(Table1[[#This Row],[Date]]),"",DATE(Table1[[#This Row],[Date_Year]],Table1[[#This Row],[Date_Month]],1)) -> 44562
B19: 44562 | C19: Netflix | D19: Shopping | F19: -14.83 | G19: =_xlfn.XLOOKUP(Table1[[#This Row],[Account_ID]], Accounts[ID], Accounts[Account nickname], "Unknown") -> Discover | H19: =_xlfn.XLOOKUP(Table1[[#This Row],[Account_ID]], Accounts[ID], Accounts[Account'#], "Unknown") -> 4618 | I19: =_xlfn.XLOOKUP(_xlfn.XLOOKUP(Table1[[#This Row],[Account]],Accounts[Account nickname],Accounts[Institution ID]),Institutions[ID],Institutions[Institution nickname],"Unknown") -> Discover | J19: 954fe1093eb34396b68429642e970fe1 | K19: 0048d75f4d1d47f3b69428db4a68f3dd | L19: d09d1b66884d43439b5dad982b7d9e52 | M19: =IF(NOT(_xlfn.XLOOKUP(Table1[[#This Row],[Category]],CategoriesTable[Category name],CategoriesTable[ID])=0),_xlfn.XLOOKUP(Table1[[#This Row],[Category]],CategoriesTable[Category name],CategoriesTable[ID]),_xlfn.XLOOKUP("Uncategorized",CategoriesTable[Category name],CategoriesTable[ID])) -> 4144f48502914015b998277a326fcedc | N19: =IF(AND(NOT(ISBLANK(Table1[[#This Row],[Subcategory]])),NOT(_xlfn.XLOOKUP(Table1[[#This Row],[Subcategory]],SubcategoriesTable[Subcategory name],SubcategoriesTable[ID])=0)),_xlfn.XLOOKUP(Table1[[#This Row],[Subcategory]],SubcategoriesTable[Subcategory name],SubcategoriesTable[ID]),"") | O19: {=IFERROR(INDEX(CategoriesTable[Category type],MATCH(Table1[[#This Row],[Category]],CategoriesTable[Category name],0),0),"")} -> Expense | P19: 1 | Q19: =MONTH(Table1[[#This Row],[Date]]) -> 1 | R19: 2022 | S19: =IF(ISBLANK(Table1[[#This Row],[Date]]),"",Table1[[#This Row],[Date]]-WEEKDAY(Table1[[#This Row],[Date]],2)+1) -> 44557 | T19: =IF(ISBLANK(Table1[[#This Row],[Date]]),"",DATE(Table1[[#This Row],[Date_Year]],Table1[[#This Row],[Date_Month]],1)) -> 44562
B20: 44562 | C20: Spotify | D20: Shopping | F20: -9.99 | G20: =_xlfn.XLOOKUP(Table1[[#This Row],[Account_ID]], Accounts[ID], Accounts[Account nickname], "Unknown") -> Discover | H20: =_xlfn.XLOOKUP(Table1[[#This Row],[Account_ID]], Accounts[ID], Accounts[Account'#], "Unknown") -> 4618 | I20: =_xlfn.XLOOKUP(_xlfn.XLOOKUP(Table1[[#This Row],[Account]],Accounts[Account nickname],Accounts[Institution ID]),Institutions[ID],Institutions[Institution nickname],"Unknown") -> Discover | J20: 42b81f432a3a452ba9e4ade8695b11ef | K20: 0048d75f4d1d47f3b69428db4a68f3dd | L20: d09d1b66884d43439b5dad982b7d9e52 | M20: =IF(NOT(_xlfn.XLOOKUP(Table1[[#This Row],[Category]],CategoriesTable[Category name],CategoriesTable[ID])=0),_xlfn.XLOOKUP(Table1[[#This Row],[Category]],CategoriesTable[Category name],CategoriesTable[ID]),_xlfn.XLOOKUP("Uncategorized",CategoriesTable[Category name],CategoriesTable[ID])) -> 4144f48502914015b998277a326fcedc | N20: =IF(AND(NOT(ISBLANK(Table1[[#This Row],[Subcategory]])),NOT(_xlfn.XLOOKUP(Table1[[#This Row],[Subcategory]],SubcategoriesTable[Subcategory name],SubcategoriesTable[ID])=0)),_xlfn.XLOOKUP(Table1[[#This Row],[Subcategory]],SubcategoriesTable[Subcategory name],SubcategoriesTable[ID]),"") | O20: {=IFERROR(INDEX(CategoriesTable[Category type],MATCH(Table1[[#This Row],[Category]],CategoriesTable[Category name],0),0),"")} -> Expense | P20: 1 | Q20: =MONTH(Table1[[#This Row],[Date]]) -> 1 | R20: 2022 | S20: =IF(ISBLANK(Table1[[#This Row],[Date]]),"",Table1[[#This Row],[Date]]-WEEKDAY(Table1[[#This Row],[Date]],2)+1) -> 44557 | T20: =IF(ISBLANK(Table1[[#This Row],[Date]]),"",DATE(Table1[[#This Row],[Date_Year]],Table1[[#This Row],[Date_Month]],1)) -> 44562
B21: 44561 | C21: Walmart | D21: Food | E21: Groceries | F21: -77.81 | G21: =_xlfn.XLOOKUP(Table1[[#This Row],[Account_ID]], Accounts[ID], Accounts[Account nickname], "Unknown") -> Discover | H21: =_xlfn.XLOOKUP(Table1[[#This Row],[Account_ID]], Accounts[ID], Accounts[Account'#], "Unknown") -> 4618 | I21: =_xlfn.XLOOKUP(_xlfn.XLOOKUP(Table1[[#This Row],[Account]],Accounts[Account nickname],Accounts[Institution ID]),Institutions[ID],Institutions[Institution nickname],"Unknown") -> Discover | J21: e5b838cdf2d1465fa0f5e18aabcfffbe | K21: 0048d75f4d1d47f3b69428db4a68f3dd | L21: d09d1b66884d43439b5dad982b7d9e52 | M21: =IF(NOT(_xlfn.XLOOKUP(Table1[[#This Row],[Category]],CategoriesTable[Category name],CategoriesTable[ID])=0),_xlfn.XLOOKUP(Table1[[#This Row],[Category]],CategoriesTable[Category name],CategoriesTable[ID]),_xlfn.XLOOKUP("Uncategorized",CategoriesTable[Category name],CategoriesTable[ID])) -> fec746a44521f2118fef19237dbf4f91 | N21: =IF(AND(NOT(ISBLANK(Table1[[#This Row],[Subcategory]])),NOT(_xlfn.XLOOKUP(Table1[[#This Row],[Subcategory]],SubcategoriesTable[Subcategory name],SubcategoriesTable[ID])=0)),_xlfn.XLOOKUP(Table1[[#This Row],[Subcategory]],SubcategoriesTable[Subcategory name],SubcategoriesTable[ID]),"") -> fd72ce5cfeedbe66d13df9602b6cff7d | O21: {=IFERROR(INDEX(CategoriesTable[Category type],MATCH(Table1[[#This Row],[Category]],CategoriesTable[Category name],0),0),"")} -> Expense | P21: 31 | Q21: =MONTH(Table1[[#This Row],[Date]]) -> 12 | R21: 2021 | S21: =IF(ISBLANK(Table1[[#This Row],[Date]]),"",Table1[[#This Row],[Date]]-WEEKDAY(Table1[[#This Row],[Date]],2)+1) -> 44557 | T21: =IF(ISBLANK(Table1[[#This Row],[Date]]),"",DATE(Table1[[#This Row],[Date_Year]],Table1[[#This Row],[Date_Month]],1)) -> 44531
B22: 44561 | C22: Wow Wow Hawaiian Le | D22: Restaurants/Dining | E22: Resteraunts | F22: -6.56 | G22: =_xlfn.XLOOKUP(Table1[[#This Row],[Account_ID]], Accounts[ID], Accounts[Account nickname], "Unknown") -> Discover | H22: =_xlfn.XLOOKUP(Table1[[#This Row],[Account_ID]], Accounts[ID], Accounts[Account'#], "Unknown") -> 4618 | I22: =_xlfn.XLOOKUP(_xlfn.XLOOKUP(Table1[[#This Row],[Account]],Accounts[Account nickname],Accounts[Institution ID]),Institutions[ID],Institutions[Institution nickname],"Unknown") -> Discover | J22: 207347bc03ee4af1ad79f94bde78710c | K22: 0048d75f4d1d47f3b69428db4a68f3dd | L22: d09d1b66884d43439b5dad982b7d9e52 | M22: =IF(NOT(_xlfn.XLOOKUP(Table1[[#This Row],[Category]],CategoriesTable[Category name],CategoriesTable[ID])=0),_xlfn.XLOOKUP(Table1[[#This Row],[Category]],CategoriesTable[Category name],CategoriesTable[ID]),_xlfn.XLOOKUP("Uncategorized",CategoriesTable[Category name],CategoriesTable[ID])) -> 3dafc6bd8d7c45ae9840ff09e01567d1 | N22: =IF(AND(NOT(ISBLANK(Table1[[#This Row],[Subcategory]])),NOT(_xlfn.XLOOKUP(Table1[[#This Row],[Subcategory]],SubcategoriesTable[Subcategory name],SubcategoriesTable[ID])=0)),_xlfn.XLOOKUP(Table1[[#This Row],[Subcategory]],SubcategoriesTable[Subcategory name],SubcategoriesTable[ID]),"") -> 500e6ba7cba37a7a2a33da8c057b4cb8 | O22: {=IFERROR(INDEX(CategoriesTable[Category type],MATCH(Table1[[#This Row],[Category]],CategoriesTable[Category name],0),0),"")} -> Expense | P22: 31 | Q22: =MONTH(Table1[[#This Row],[Date]]) -> 12 | R22: 2021 | S22: =IF(ISBLANK(Table1[[#This Row],[Date]]),"",Table1[[#This Row],[Date]]-WEEKDAY(Table1[[#This Row],[Date]],2)+1) -> 44557 | T22: =IF(ISBLANK(Table1[[#This Row],[Date]]),"",DATE(Table1[[#This Row],[Date_Year]],Table1[[#This Row],[Date_Month]],1)) -> 44531
B23: 44560 | C23: Money Transfer Authorized On | D23: Income | F23: 40 | G23: =_xlfn.XLOOKUP(Table1[[#This Row],[Account_ID]], Accounts[ID], Accounts[Account nickname], "Unknown") -> WF | H23: =_xlfn.XLOOKUP(Table1[[#This Row],[Account_ID]], Accounts[ID], Accounts[Account'#], "Unknown") -> 4636 | I23: =_xlfn.XLOOKUP(_xlfn.XLOOKUP(Table1[[#This Row],[Account]],Accounts[Account nickname],Accounts[Institution ID]),Institutions[ID],Institutions[Institution nickname],"Unknown") -> Wells Fargo | J23: e7a6f43e36bf4e729a2ae870bbd8df9f | K23: 4918dbe6db3e4b9384fdfe7083417a5f | L23: 8b5374947e1d46e7a0f86b54ee722e44 | M23: =IF(NOT(_xlfn.XLOOKUP(Table1[[#This Row],[Category]],CategoriesTable[Category name],CategoriesTable[ID])=0),_xlfn.XLOOKUP(Table1[[#This Row],[Category]],CategoriesTable[Category name],CategoriesTable[ID]),_xlfn.XLOOKUP("Uncategorized",CategoriesTable[Category name],CategoriesTable[ID])) -> fabfe582932d48b78ac2846c1ec3d43f | N23: =IF(AND(NOT(ISBLANK(Table1[[#This Row],[Subcategory]])),NOT(_xlfn.XLOOKUP(Table1[[#This Row],[Subcategory]],SubcategoriesTable[Subcategory name],SubcategoriesTable[ID])=0)),_xlfn.XLOOKUP(Table1[[#This Row],[Subcategory]],SubcategoriesTable[Subcategory name],SubcategoriesTable[ID]),"") | O23: {=IFERROR(INDEX(CategoriesTable[Category type],MATCH(Table1[[#This Row],[Category]],CategoriesTable[Category name],0),0),"")} -> Expense | P23: 30 | Q23: =MONTH(Table1[[#This Row],[Date]]) -> 12 | R23: 2021 | S23: =IF(ISBLANK(Table1[[#This Row],[Date]]),"",Table1[[#This Row],[Date]]-WEEKDAY(Table1[[#This Row],[Date]],2)+1) -> 44557 | T23: =IF(ISBLANK(Table1[[#This Row],[Date]]),"",DATE(Table1[[#This Row],[Date_Year]],Table1[[#This Row],[Date_Month]],1)) -> 44531
B24: 44560 | C24: Nationwide Payroll Sean Lewis | D24: Income | F24: 2738.66 | G24: =_xlfn.XLOOKUP(Table1[[#This Row],[Account_ID]], Accounts[ID], Accounts[Account nickname], "Unknown") -> WF | H24: =_xlfn.XLOOKUP(Table1[[#This Row],[Account_ID]], Accounts[ID], Accounts[Account'#], "Unknown") -> 4636 | I24: =_xlfn.XLOOKUP(_xlfn.XLOOKUP(Table1[[#This Row],[Account]],Accounts[Account nickname],Accounts[Institution ID]),Institutions[ID],Institutions[Institution nickname],"Unknown") -> Wells Fargo | J24: 79f9409daf7346b5860b6682b97f76c0 | K24: 4918dbe6db3e4b9384fdfe7083417a5f | L24: 8b5374947e1d46e7a0f86b54ee722e44 | M24: =IF(NOT(_xlfn.XLOOKUP(Table1[[#This Row],[Category]],CategoriesTable[Category name],CategoriesTable[ID])=0),_xlfn.XLOOKUP(Table1[[#This Row],[Category]],CategoriesTable[Category name],CategoriesTable[ID]),_xlfn.XLOOKUP("Uncategorized",CategoriesTable[Category name],CategoriesTable[ID])) -> fabfe582932d48b78ac2846c1ec3d43f | N24: =IF(AND(NOT(ISBLANK(Table1[[#This Row],[Subcategory]])),NOT(_xlfn.XLOOKUP(Table1[[#This Row],[Subcategory]],SubcategoriesTable[Subcategory name],SubcategoriesTable[ID])=0)),_xlfn.XLOOKUP(Table1[[#This Row],[Subcategory]],SubcategoriesTable[Subcategory name],SubcategoriesTable[ID]),"") | O24: {=IFERROR(INDEX(CategoriesTable[Category type],MATCH(Table1[[#This Row],[Category]],CategoriesTable[Category name],0),0),"")} -> Expense | P24: 30 | Q24: =MONTH(Table1[[#This Row],[Date]]) -> 12 | R24: 2021 | S24: =IF(ISBLANK(Table1[[#This Row],[Date]]),"",Table1[[#This Row],[Date]]-WEEKDAY(Table1[[#This Row],[Date]],2)+1) -> 44557 | T24: =IF(ISBLANK(Table1[[#This Row],[Date]]),"",DATE(Table1[[#This Row],[Date_Year]],Table1[[#This Row],[Date_Month]],1)) -> 44531
B25: 44560 | C25: Venmo | D25: Income | E25: Rent | F25: -1866.67 | G25: =_xlfn.XLOOKUP(Table1[[#This Row],[Account_ID]], Accounts[ID], Accounts[Account nickname], "Unknown") -> WF | H25: =_xlfn.XLOOKUP(Table1[[#This Row],[Account_ID]], Accounts[ID], Accounts[Account'#], "Unknown") -> 4636 | I25: =_xlfn.XLOOKUP(_xlfn.XLOOKUP(Table1[[#This Row],[Account]],Accounts[Account nickname],Accounts[Institution ID]),Institutions[ID],Institutions[Institution nickname],"Unknown") -> Wells Fargo | J25: cc2649a8506141369f17a9974c7e49db | K25: 4918dbe6db3e4b9384fdfe7083417a5f | L25: 8b5374947e1d46e7a0f86b54ee722e44 | M25: =IF(NOT(_xlfn.XLOOKUP(Table1[[#This Row],[Category]],CategoriesTable[Category name],CategoriesTable[ID])=0),_xlfn.XLOOKUP(Table1[[#This Row],[Category]],CategoriesTable[Category name],CategoriesTable[ID]),_xlfn.XLOOKUP("Uncategorized",CategoriesTable[Category name],CategoriesTable[ID])) -> fabfe582932d48b78ac2846c1ec3d43f | N25: =IF(AND(NOT(ISBLANK(Table1[[#This Row],[Subcategory]])),NOT(_xlfn.XLOOKUP(Table1[[#This Row],[Subcategory]],SubcategoriesTable[Subcategory name],SubcategoriesTable[ID])=0)),_xlfn.XLOOKUP(Table1[[#This Row],[Subcategory]],SubcategoriesTable[Subcategory name],SubcategoriesTable[ID]),"") -> 01a08ee0780d41da979351ef7694e331 | O25: {=IFERROR(INDEX(CategoriesTable[Category type],MATCH(Table1[[#This Row],[Category]],CategoriesTable[Category name],0),0),"")} -> Expense | P25: 30 | Q25: =MONTH(Table1[[#This Row],[Date]]) -> 12 | R25: 2021 | S25: =IF(ISBLANK(Table1[[#This Row],[Date]]),"",Table1[[#This Row],[Date]]-WEEKDAY(Table1[[#This Row],[Date]],2)+1) -> 44557 | T25: =IF(ISBLANK(Table1[[#This Row],[Date]]),"",DATE(Table1[[#This Row],[Date_Year]],Table1[[#This Row],[Date_Month]],1)) -> 44531
B26: 44560 | C26: Phoenix Suns Half Season Tickets | D26: Recreational & Entertainment | E26: Sporting Events | F26: -366.66 | G26: =_xlfn.XLOOKUP(Table1[[#This Row],[Account_ID]], Accounts[ID], Accounts[Account nickname], "Unknown") -> Discover | H26: =_xlfn.XLOOKUP(Table1[[#This Row],[Account_ID]], Accounts[ID], Accounts[Account'#], "Unknown") -> 4618 | I26: =_xlfn.XLOOKUP(_xlfn.XLOOKUP(Table1[[#This Row],[Account]],Accounts[Account nickname],Accounts[Institution ID]),Institutions[ID],Institutions[Institution nickname],"Unknown") -> Discover | J26: b3240a8a3993470db73c2249aa4331dc | K26: 0048d75f4d1d47f3b69428db4a68f3dd | L26: d09d1b66884d43439b5dad982b7d9e52 | M26: =IF(NOT(_xlfn.XLOOKUP(Table1[[#This Row],[Category]],CategoriesTable[Category name],CategoriesTable[ID])=0),_xlfn.XLOOKUP(Table1[[#This Row],[Category]],CategoriesTable[Category name],CategoriesTable[ID]),_xlfn.XLOOKUP("Uncategorized",CategoriesTable[Category name],CategoriesTable[ID])) -> f870f35280fadaf3c3539ad54e3062cd | N26: =IF(AND(NOT(ISBLANK(Table1[[#This Row],[Subcategory]])),NOT(_xlfn.XLOOKUP(Table1[[#This Row],[Subcategory]],SubcategoriesTable[Subcategory name],SubcategoriesTable[ID])=0)),_xlfn.XLOOKUP(Table1[[#This Row],[Subcategory]],SubcategoriesTable[Subcategory name],SubcategoriesTable[ID]),"") -> 9fbba331d1ae096cbce7fb1035aebbc1 | O26: {=IFERROR(INDEX(CategoriesTable[Category type],MATCH(Table1[[#This Row],[Category]],CategoriesTable[Category name],0),0),"")} -> Expense | P26: 30 | Q26: =MONTH(Table1[[#This Row],[Date]]) -> 12 | R26: 2021 | S26: =IF(ISBLANK(Table1[[#This Row],[Date]]),"",Table1[[#This Row],[Date]]-WEEKDAY(Table1[[#This Row],[Date]],2)+1) -> 44557 | T26: =IF(ISBLANK(Table1[[#This Row],[Date]]),"",DATE(Table1[[#This Row],[Date_Year]],Table1[[#This Row],[Date_Month]],1)) -> 44531
B27: 44560 | C27: Jiffy Lube | D27: Transportation | E27: Maintenance | F27: -93.25 | G27: =_xlfn.XLOOKUP(Table1[[#This Row],[Account_ID]], Accounts[ID], Accounts[Account nickname], "Unknown") -> Discover | H27: =_xlfn.XLOOKUP(Table1[[#This Row],[Account_ID]], Accounts[ID], Accounts[Account'#], "Unknown") -> 4618 | I27: =_xlfn.XLOOKUP(_xlfn.XLOOKUP(Table1[[#This Row],[Account]],Accounts[Account nickname],Accounts[Institution ID]),Institutions[ID],Institutions[Institution nickname],"Unknown") -> Discover | J27: 92e6afa929204d4f9d270e233a4f7a1e | K27: 0048d75f4d1d47f3b69428db4a68f3dd | L27: d09d1b66884d43439b5dad982b7d9e52 | M27: =IF(NOT(_xlfn.XLOOKUP(Table1[[#This Row],[Category]],CategoriesTable[Category name],CategoriesTable[ID])=0),_xlfn.XLOOKUP(Table1[[#This Row],[Category]],CategoriesTable[Category name],CategoriesTable[ID]),_xlfn.XLOOKUP("Uncategorized",CategoriesTable[Category name],CategoriesTable[ID])) -> e6c07c144d52704210419358ba4a8d2e | N27: =IF(AND(NOT(ISBLANK(Table1[[#This Row],[Subcategory]])),NOT(_xlfn.XLOOKUP(Table1[[#This Row],[Subcategory]],SubcategoriesTable[Subcategory name],SubcategoriesTable[ID])=0)),_xlfn.XLOOKUP(Table1[[#This Row],[Subcategory]],SubcategoriesTable[Subcategory name],SubcategoriesTable[ID]),"") -> 839f3d84f34900d3e634555e77251d93 | O27: {=IFERROR(INDEX(CategoriesTable[Category type],MATCH(Table1[[#This Row],[Category]],CategoriesTable[Category name],0),0),"")} -> Expense | P27: 30 | Q27: =MONTH(Table1[[#This Row],[Date]]) -> 12 | R27: 2021 | S27: =IF(ISBLANK(Table1[[#This Row],[Date]]),"",Table1[[#This Row],[Date]]-WEEKDAY(Table1[[#This Row],[Date]],2)+1) -> 44557 | T27: =IF(ISBLANK(Table1[[#This Row],[Date]]),"",DATE(Table1[[#This Row],[Date_Year]],Table1[[#This Row],[Date_Month]],1)) -> 44531
B28: 44560 | C28: Microsoft 365 Yearly Subscription | D28: Personal Spending | E28: Subscription | F28: -99.99 | G28: =_xlfn.XLOOKUP(Table1[[#This Row],[Account_ID]], Accounts[ID], Accounts[Account nickname], "Unknown") -> Discover | H28: =_xlfn.XLOOKUP(Table1[[#This Row],[Account_ID]], Accounts[ID], Accounts[Account'#], "Unknown") -> 4618 | I28: =_xlfn.XLOOKUP(_xlfn.XLOOKUP(Table1[[#This Row],[Account]],Accounts[Account nickname],Accounts[Institution ID]),Institutions[ID],Institutions[Institution nickname],"Unknown") -> Discover | J28: 6d3a310a1cac436eb53c614641e87336 | K28: 0048d75f4d1d47f3b69428db4a68f3dd | L28: d09d1b66884d43439b5dad982b7d9e52 | M28: =IF(NOT(_xlfn.XLOOKUP(Table1[[#This Row],[Category]],CategoriesTable[Category name],CategoriesTable[ID])=0),_xlfn.XLOOKUP(Table1[[#This Row],[Category]],CategoriesTable[Category name],CategoriesTable[ID]),_xlfn.XLOOKUP("Uncategorized",CategoriesTable[Category name],CategoriesTable[ID])) -> f9fd776a16da81a948d166fcd5952d14 | N28: =IF(AND(NOT(ISBLANK(Table1[[#This Row],[Subcategory]])),NOT(_xlfn.XLOOKUP(Table1[[#This Row],[Subcategory]],SubcategoriesTable[Subcategory name],SubcategoriesTable[ID])=0)),_xlfn.XLOOKUP(Table1[[#This Row],[Subcategory]],SubcategoriesTable[Subcategory name],SubcategoriesTable[ID]),"") -> 8aa9b4db7e16cd2041aa6bfdc219e567 | O28: {=IFERROR(INDEX(CategoriesTable[Category type],MATCH(Table1[[#This Row],[Category]],CategoriesTable[Category name],0),0),"")} -> Expense | P28: 30 | Q28: =MONTH(Table1[[#This Row],[Date]]) -> 12 | R28: 2021 | S28: =IF(ISBLANK(Table1[[#This Row],[Date]]),"",Table1[[#This Row],[Date]]-WEEKDAY(Table1[[#This Row],[Date]],2)+1) -> 44557 | T28: =IF(ISBLANK(Table1[[#This Row],[Date]]),"",DATE(Table1[[#This Row],[Date_Year]],Table1[[#This Row],[Date_Month]],1)) -> 44531
B29: 44559 | C29: Venmo | D29: Income | E29: Rent | F29: 933.33 | G29: =_xlfn.XLOOKUP(Table1[[#This Row],[Account_ID]], Accounts[ID], Accounts[Account nickname], "Unknown") -> WF | H29: =_xlfn.XLOOKUP(Table1[[#This Row],[Account_ID]], Accounts[ID], Accounts[Account'#], "Unknown") -> 4636 | I29: =_xlfn.XLOOKUP(_xlfn.XLOOKUP(Table1[[#This Row],[Account]],Accounts[Account nickname],Accounts[Institution ID]),Institutions[ID],Institutions[Institution nickname],"Unknown") -> Wells Fargo | J29: ea3fa667d2c5433b9f9eb2d0d3538115 | K29: 4918dbe6db3e4b9384fdfe7083417a5f | L29: 8b5374947e1d46e7a0f86b54ee722e44 | M29: =IF(NOT(_xlfn.XLOOKUP(Table1[[#This Row],[Category]],CategoriesTable[Category name],CategoriesTable[ID])=0),_xlfn.XLOOKUP(Table1[[#This Row],[Category]],CategoriesTable[Category name],CategoriesTable[ID]),_xlfn.XLOOKUP("Uncategorized",CategoriesTable[Category name],CategoriesTable[ID])) -> fabfe582932d48b78ac2846c1ec3d43f | N29: =IF(AND(NOT(ISBLANK(Table1[[#This Row],[Subcategory]])),NOT(_xlfn.XLOOKUP(Table1[[#This Row],[Subcategory]],SubcategoriesTable[Subcategory name],SubcategoriesTable[ID])=0)),_xlfn.XLOOKUP(Table1[[#This Row],[Subcategory]],SubcategoriesTable[Subcategory name],SubcategoriesTable[ID]),"") -> 01a08ee0780d41da979351ef7694e331 | O29: {=IFERROR(INDEX(CategoriesTable[Category type],MATCH(Table1[[#This Row],[Category]],CategoriesTable[Category name],0),0),"")} -> Expense | P29: 29 | Q29: =MONTH(Table1[[#This Row],[Date]]) -> 12 | R29: 2021 | S29: =IF(ISBLANK(Table1[[#This Row],[Date]]),"",Table1[[#This Row],[Date]]-WEEKDAY(Table1[[#This Row],[Date]],2)+1) -> 44557 | T29: =IF(ISBLANK(Table1[[#This Row],[Date]]),"",DATE(Table1[[#This Row],[Date_Year]],Table1[[#This Row],[Date_Month]],1)) -> 44531
B30: 44559 | C30: Jimmy Johns | D30: Recreational & Entertainment | E30: Resteraunts | F30: -14.76 | G30: =_xlfn.XLOOKUP(Table1[[#This Row],[Account_ID]], Accounts[ID], Accounts[Account nickname], "Unknown") -> Discover | H30: =_xlfn.XLOOKUP(Table1[[#This Row],[Account_ID]], Accounts[ID], Accounts[Account'#], "Unknown") -> 4618 | I30: =_xlfn.XLOOKUP(_xlfn.XLOOKUP(Table1[[#This Row],[Account]],Accounts[Account nickname],Accounts[Institution ID]),Institutions[ID],Institutions[Institution nickname],"Unknown") -> Discover | J30: 3b662439b2b14af9b5f217ef83d83f80 | K30: 0048d75f4d1d47f3b69428db4a68f3dd | L30: d09d1b66884d43439b5dad982b7d9e52 | M30: =IF(NOT(_xlfn.XLOOKUP(Table1[[#This Row],[Category]],CategoriesTable[Category name],CategoriesTable[ID])=0),_xlfn.XLOOKUP(Table1[[#This Row],[Category]],CategoriesTable[Category name],CategoriesTable[ID]),_xlfn.XLOOKUP("Uncategorized",CategoriesTable[Category name],CategoriesTable[ID])) -> f870f35280fadaf3c3539ad54e3062cd | N30: =IF(AND(NOT(ISBLANK(Table1[[#This Row],[Subcategory]])),NOT(_xlfn.XLOOKUP(Table1[[#This Row],[Subcategory]],SubcategoriesTable[Subcategory name],SubcategoriesTable[ID])=0)),_xlfn.XLOOKUP(Table1[[#This Row],[Subcategory]],SubcategoriesTable[Subcategory name],SubcategoriesTable[ID]),"") -> 500e6ba7cba37a7a2a33da8c057b4cb8 | O30: {=IFERROR(INDEX(CategoriesTable[Category type],MATCH(Table1[[#This Row],[Category]],CategoriesTable[Category name],0),0),"")} -> Expense | P30: 29 | Q30: =MONTH(Table1[[#This Row],[Date]]) -> 12 | R30: 2021 | S30: =IF(ISBLANK(Table1[[#This Row],[Date]]),"",Table1[[#This Row],[Date]]-WEEKDAY(Table1[[#This Row],[Date]],2)+1) -> 44557 | T30: =IF(ISBLANK(Table1[[#This Row],[Date]]),"",DATE(Table1[[#This Row],[Date_Year]],Table1[[#This Row],[Date_Month]],1)) -> 44531
B31: 44558 | C31: Panda Express | D31: Recreational & Entertainment | E31: Resteraunts | F31: -11 | G31: =_xlfn.XLOOKUP(Table1[[#This Row],[Account_ID]], Accounts[ID], Accounts[Account nickname], "Unknown") -> Discover | H31: =_xlfn.XLOOKUP(Table1[[#This Row],[Account_ID]], Accounts[ID], Accounts[Account'#], "Unknown") -> 4618 | I31: =_xlfn.XLOOKUP(_xlfn.XLOOKUP(Table1[[#This Row],[Account]],Accounts[Account nickname],Accounts[Institution ID]),Institutions[ID],Institutions[Institution nickname],"Unknown") -> Discover | J31: a590701b23ac4e849f451cadc1f2eafd | K31: 0048d75f4d1d47f3b69428db4a68f3dd | L31: d09d1b66884d43439b5dad982b7d9e52 | M31: =IF(NOT(_xlfn.XLOOKUP(Table1[[#This Row],[Category]],CategoriesTable[Category name],CategoriesTable[ID])=0),_xlfn.XLOOKUP(Table1[[#This Row],[Category]],CategoriesTable[Category name],CategoriesTable[ID]),_xlfn.XLOOKUP("Uncategorized",CategoriesTable[Category name],CategoriesTable[ID])) -> f870f35280fadaf3c3539ad54e3062cd | N31: =IF(AND(NOT(ISBLANK(Table1[[#This Row],[Subcategory]])),NOT(_xlfn.XLOOKUP(Table1[[#This Row],[Subcategory]],SubcategoriesTable[Subcategory name],SubcategoriesTable[ID])=0)),_xlfn.XLOOKUP(Table1[[#This Row],[Subcategory]],SubcategoriesTable[Subcategory name],SubcategoriesTable[ID]),"") -> 500e6ba7cba37a7a2a33da8c057b4cb8 | O31: {=IFERROR(INDEX(CategoriesTable[Category type],MATCH(Table1[[#This Row],[Category]],CategoriesTable[Category name],0),0),"")} -> Expense | P31: 28 | Q31: =MONTH(Table1[[#This Row],[Date]]) -> 12 | R31: 2021 | S31: =IF(ISBLANK(Table1[[#This Row],[Date]]),"",Table1[[#This Row],[Date]]-WEEKDAY(Table1[[#This Row],[Date]],2)+1) -> 44557 | T31: =IF(ISBLANK(Table1[[#This Row],[Date]]),"",DATE(Table1[[#This Row],[Date_Year]],Table1[[#This Row],[Date_Month]],1)) -> 44531
B32: 44557 | C32: Best Buy | D32: Refund | F32: 108.59 | G32: =_xlfn.XLOOKUP(Table1[[#This Row],[Account_ID]], Accounts[ID], Accounts[Account nickname], "Unknown") -> BB | H32: =_xlfn.XLOOKUP(Table1[[#This Row],[Account_ID]], Accounts[ID], Accounts[Account'#], "Unknown") -> 4561 | I32: =_xlfn.XLOOKUP(_xlfn.XLOOKUP(Table1[[#This Row],[Account]],Accounts[Account nickname],Accounts[Institution ID]),Institutions[ID],Institutions[Institution nickname],"Unknown") -> Best Buy - Citi Card | J32: f5f8a5cec3be438a807543d2d37e8642 | K32: a82d9aba872e4e9b9684a363d4cc52b5 | L32: e7a999902ffc4e26bd6b6c2d4214aabd | M32: =IF(NOT(_xlfn.XLOOKUP(Table1[[#This Row],[Category]],CategoriesTable[Category name],CategoriesTable[ID])=0),_xlfn.XLOOKUP(Table1[[#This Row],[Category]],CategoriesTable[Category name],CategoriesTable[ID]),_xlfn.XLOOKUP("Uncategorized",CategoriesTable[Category name],CategoriesTable[ID])) -> fca5dd8329b743f7b77704e23a1e63ad | N32: =IF(AND(NOT(ISBLANK(Table1[[#This Row],[Subcategory]])),NOT(_xlfn.XLOOKUP(Table1[[#This Row],[Subcategory]],SubcategoriesTable[Subcategory name],SubcategoriesTable[ID])=0)),_xlfn.XLOOKUP(Table1[[#This Row],[Subcategory]],SubcategoriesTable[Subcategory name],SubcategoriesTable[ID]),"") | O32: {=IFERROR(INDEX(CategoriesTable[Category type],MATCH(Table1[[#This Row],[Category]],CategoriesTable[Category name],0),0),"")} -> Expense | P32: 27 | Q32: =MONTH(Table1[[#This Row],[Date]]) -> 12 | R32: 2021 | S32: =IF(ISBLANK(Table1[[#This Row],[Date]]),"",Table1[[#This Row],[Date]]-WEEKDAY(Table1[[#This Row],[Date]],2)+1) -> 44557 | T32: =IF(ISBLANK(Table1[[#This Row],[Date]]),"",DATE(Table1[[#This Row],[Date_Year]],Table1[[#This Row],[Date_Month]],1)) -> 44531
B33: 44557 | C33: Best Buy | D33: Refund | F33: -108.59 | G33: =_xlfn.XLOOKUP(Table1[[#This Row],[Account_ID]], Accounts[ID], Accounts[Account nickname], "Unknown") -> BB | H33: =_xlfn.XLOOKUP(Table1[[#This Row],[Account_ID]], Accounts[ID], Accounts[Account'#], "Unknown") -> 4561 | I33: =_xlfn.XLOOKUP(_xlfn.XLOOKUP(Table1[[#This Row],[Account]],Accounts[Account nickname],Accounts[Institution ID]),Institutions[ID],Institutions[Institution nickname],"Unknown") -> Best Buy - Citi Card | J33: f3d6000b84744fe988e883a6ccb0d561 | K33: a82d9aba872e4e9b9684a363d4cc52b5 | L33: e7a999902ffc4e26bd6b6c2d4214aabd | M33: =IF(NOT(_xlfn.XLOOKUP(Table1[[#This Row],[Category]],CategoriesTable[Category name],CategoriesTable[ID])=0),_xlfn.XLOOKUP(Table1[[#This Row],[Category]],CategoriesTable[Category name],CategoriesTable[ID]),_xlfn.XLOOKUP("Uncategorized",CategoriesTable[Category name],CategoriesTable[ID])) -> fca5dd8329b743f7b77704e23a1e63ad | N33: =IF(AND(NOT(ISBLANK(Table1[[#This Row],[Subcategory]])),NOT(_xlfn.XLOOKUP(Table1[[#This Row],[Subcategory]],SubcategoriesTable[Subcategory name],SubcategoriesTable[ID])=0)),_xlfn.XLOOKUP(Table1[[#This Row],[Subcategory]],SubcategoriesTable[Subcategory name],SubcategoriesTable[ID]),"") | O33: {=IFERROR(INDEX(CategoriesTable[Category type],MATCH(Table1[[#This Row],[Category]],CategoriesTable[Category name],0),0),"")} -> Expense | P33: 27 | Q33: =MONTH(Table1[[#This Row],[Date]]) -> 12 | R33: 2021 | S33: =IF(ISBLANK(Table1[[#This Row],[Date]]),"",Table1[[#This Row],[Date]]-WEEKDAY(Table1[[#This Row],[Date]],2)+1) -> 44557 | T33: =IF(ISBLANK(Table1[[#This Row],[Date]]),"",DATE(Table1[[#This Row],[Date_Year]],Table1[[#This Row],[Date_Month]],1)) -> 44531
B34: 44557 | C34: Best Buy | D34: Refund | F34: 65.15 | G34: =_xlfn.XLOOKUP(Table1[[#This Row],[Account_ID]], Accounts[ID], Accounts[Account nickname], "Unknown") -> BB | H34: =_xlfn.XLOOKUP(Table1[[#This Row],[Account_ID]], Accounts[ID], Accounts[Account'#], "Unknown") -> 4561 | I34: =_xlfn.XLOOKUP(_xlfn.XLOOKUP(Table1[[#This Row],[Account]],Accounts[Account nickname],Accounts[Institution ID]),Institutions[ID],Institutions[Institution nickname],"Unknown") -> Best Buy - Citi Card | J34: e7db14402d9d429fbed29d3643c869dd | K34: a82d9aba872e4e9b9684a363d4cc52b5 | L34: e7a999902ffc4e26bd6b6c2d4214aabd | M34: =IF(NOT(_xlfn.XLOOKUP(Table1[[#This Row],[Category]],CategoriesTable[Category name],CategoriesTable[ID])=0),_xlfn.XLOOKUP(Table1[[#This Row],[Category]],CategoriesTable[Category name],CategoriesTable[ID]),_xlfn.XLOOKUP("Uncategorized",CategoriesTable[Category name],CategoriesTable[ID])) -> fca5dd8329b743f7b77704e23a1e63ad | N34: =IF(AND(NOT(ISBLANK(Table1[[#This Row],[Subcategory]])),NOT(_xlfn.XLOOKUP(Table1[[#This Row],[Subcategory]],SubcategoriesTable[Subcategory name],SubcategoriesTable[ID])=0)),_xlfn.XLOOKUP(Table1[[#This Row],[Subcategory]],SubcategoriesTable[Subcategory name],SubcategoriesTable[ID]),"") | O34: {=IFERROR(INDEX(CategoriesTable[Category type],MATCH(Table1[[#This Row],[Category]],CategoriesTable[Category name],0),0),"")} -> Expense | P34: 27 | Q34: =MONTH(Table1[[#This Row],[Date]]) -> 12 | R34: 2021 | S34: =IF(ISBLANK(Table1[[#This Row],[Date]]),"",Table1[[#This Row],[Date]]-WEEKDAY(Table1[[#This Row],[Date]],2)+1) -> 44557 | T34: =IF(ISBLANK(Table1[[#This Row],[Date]]),"",DATE(Table1[[#This Row],[Date_Year]],Table1[[#This Row],[Date_Month]],1)) -> 44531
B35: 44557 | C35: Taco Bell | D35: Recreational & Entertainment | E35: Resteraunts | F35: -8.46 | G35: =_xlfn.XLOOKUP(Table1[[#This Row],[Account_ID]], Accounts[ID], Accounts[Account nickname], "Unknown") -> Discover | H35: =_xlfn.XLOOKUP(Table1[[#This Row],[Account_ID]], Accounts[ID], Accounts[Account'#], "Unknown") -> 4618 | I35: =_xlfn.XLOOKUP(_xlfn.XLOOKUP(Table1[[#This Row],[Account]],Accounts[Account nickname],Accounts[Institution ID]),Institutions[ID],Institutions[Institution nickname],"Unknown") -> Discover | J35: d4c41bfc59f94a4c9f4e8a5c273e3670 | K35: 0048d75f4d1d47f3b69428db4a68f3dd | L35: d09d1b66884d43439b5dad982b7d9e52 | M35: =IF(NOT(_xlfn.XLOOKUP(Table1[[#This Row],[Category]],CategoriesTable[Category name],CategoriesTable[ID])=0),_xlfn.XLOOKUP(Table1[[#This Row],[Category]],CategoriesTable[Category name],CategoriesTable[ID]),_xlfn.XLOOKUP("Uncategorized",CategoriesTable[Category name],CategoriesTable[ID])) -> f870f35280fadaf3c3539ad54e3062cd | N35: =IF(AND(NOT(ISBLANK(Table1[[#This Row],[Subcategory]])),NOT(_xlfn.XLOOKUP(Table1[[#This Row],[Subcategory]],SubcategoriesTable[Subcategory name],SubcategoriesTable[ID])=0)),_xlfn.XLOOKUP(Table1[[#This Row],[Subcategory]],SubcategoriesTable[Subcategory name],SubcategoriesTable[ID]),"") -> 500e6ba7cba37a7a2a33da8c057b4cb8 | O35: {=IFERROR(INDEX(CategoriesTable[Category type],MATCH(Table1[[#This Row],[Category]],CategoriesTable[Category name],0),0),"")} -> Expense | P35: 27 | Q35: =MONTH(Table1[[#This Row],[Date]]) -> 12 | R35: 2021 | S35: =IF(ISBLANK(Table1[[#This Row],[Date]]),"",Table1[[#This Row],[Date]]-WEEKDAY(Table1[[#This Row],[Date]],2)+1) -> 44557 | T35: =IF(ISBLANK(Table1[[#This Row],[Date]]),"",DATE(Table1[[#This Row],[Date_Year]],Table1[[#This Row],[Date_Month]],1)) -> 44531
B36: 44557 | C36: Venmo | D36: Savings, Investing, &Debt | E36: Personal Debt | F36: -76.5 | G36: =_xlfn.XLOOKUP(Table1[[#This Row],[Account_ID]], Accounts[ID], Accounts[Account nickname], "Unknown") -> WF | H36: =_xlfn.XLOOKUP(Table1[[#This Row],[Account_ID]], Accounts[ID], Accounts[Account'#], "Unknown") -> 4636 | I36: =_xlfn.XLOOKUP(_xlfn.XLOOKUP(Table1[[#This Row],[Account]],Accounts[Account nickname],Accounts[Institution ID]),Institutions[ID],Institutions[Institution nickname],"Unknown") -> Wells Fargo | J36: 996140cb46ef406c8360366fd966ca2e | K36: 4918dbe6db3e4b9384fdfe7083417a5f | L36: 8b5374947e1d46e7a0f86b54ee722e44 | M36: =IF(NOT(_xlfn.XLOOKUP(Table1[[#This Row],[Category]],CategoriesTable[Category name],CategoriesTable[ID])=0),_xlfn.XLOOKUP(Table1[[#This Row],[Category]],CategoriesTable[Category name],CategoriesTable[ID]),_xlfn.XLOOKUP("Uncategorized",CategoriesTable[Category name],CategoriesTable[ID])) -> f59903268bc5a7b5382a7eb44e1c5e95 | N36: =IF(AND(NOT(ISBLANK(Table1[[#This Row],[Subcategory]])),NOT(_xlfn.XLOOKUP(Table1[[#This Row],[Subcategory]],SubcategoriesTable[Subcategory name],SubcategoriesTable[ID])=0)),_xlfn.XLOOKUP(Table1[[#This Row],[Subcategory]],SubcategoriesTable[Subcategory name],SubcategoriesTable[ID]),"") -> 29203f6b3d0b39d0da4dd72a306dbe8d | O36: {=IFERROR(INDEX(CategoriesTable[Category type],MATCH(Table1[[#This Row],[Category]],CategoriesTable[Category name],0),0),"")} -> Expense | P36: 27 | Q36: =MONTH(Table1[[#This Row],[Date]]) -> 12 | R36: 2021 | S36: =IF(ISBLANK(Table1[[#This Row],[Date]]),"",Table1[[#This Row],[Date]]-WEEKDAY(Table1[[#This Row],[Date]],2)+1) -> 44557 | T36: =IF(ISBLANK(Table1[[#This Row],[Date]]),"",DATE(Table1[[#This Row],[Date_Year]],Table1[[#This Row],[Date_Month]],1)) -> 44531
B37: 44557 | C37: Best Buy | D37: Refund | F37: -307.14 | G37: =_xlfn.XLOOKUP(Table1[[#This Row],[Account_ID]], Accounts[ID], Accounts[Account nickname], "Unknown") -> BB | H37: =_xlfn.XLOOKUP(Table1[[#This Row],[Account_ID]], Accounts[ID], Accounts[Account'#], "Unknown") -> 4561 | I37: =_xlfn.XLOOKUP(_xlfn.XLOOKUP(Table1[[#This Row],[Account]],Accounts[Account nickname],Accounts[Institution ID]),Institutions[ID],Institutions[Institution nickname],"Unknown") -> Best Buy - Citi Card | J37: 20fdc87bfa0f4b8ca4abfda02bf55ee8 | K37: a82d9aba872e4e9b9684a363d4cc52b5 | L37: e7a999902ffc4e26bd6b6c2d4214aabd | M37: =IF(NOT(_xlfn.XLOOKUP(Table1[[#This Row],[Category]],CategoriesTable[Category name],CategoriesTable[ID])=0),_xlfn.XLOOKUP(Table1[[#This Row],[Category]],CategoriesTable[Category name],CategoriesTable[ID]),_xlfn.XLOOKUP("Uncategorized",CategoriesTable[Category name],CategoriesTable[ID])) -> fca5dd8329b743f7b77704e23a1e63ad | N37: =IF(AND(NOT(ISBLANK(Table1[[#This Row],[Subcategory]])),NOT(_xlfn.XLOOKUP(Table1[[#This Row],[Subcategory]],SubcategoriesTable[Subcategory name],SubcategoriesTable[ID])=0)),_xlfn.XLOOKUP(Table1[[#This Row],[Subcategory]],SubcategoriesTable[Subcategory name],SubcategoriesTable[ID]),"") | O37: {=IFERROR(INDEX(CategoriesTable[Category type],MATCH(Table1[[#This Row],[Category]],CategoriesTable[Category name],0),0),"")} -> Expense | P37: 27 | Q37: =MONTH(Table1[[#This Row],[Date]]) -> 12 | R37: 2021 | S37: =IF(ISBLANK(Table1[[#This Row],[Date]]),"",Table1[[#This Row],[Date]]-WEEKDAY(Table1[[#This Row],[Date]],2)+1) -> 44557 | T37: =IF(ISBLANK(Table1[[#This Row],[Date]]),"",DATE(Table1[[#This Row],[Date_Year]],Table1[[#This Row],[Date_Month]],1)) -> 44531
B38: 44557 | C38: Venmo | D38: Savings, Investing, &Debt | E38: Personal Debt | F38: -100 | G38: =_xlfn.XLOOKUP(Table1[[#This Row],[Account_ID]], Accounts[ID], Accounts[Account nickname], "Unknown") -> WF | H38: =_xlfn.XLOOKUP(Table1[[#This Row],[Account_ID]], Accounts[ID], Accounts[Account'#], "Unknown") -> 4636 | I38: =_xlfn.XLOOKUP(_xlfn.XLOOKUP(Table1[[#This Row],[Account]],Accounts[Account nickname],Accounts[Institution ID]),Institutions[ID],Institutions[Institution nickname],"Unknown") -> Wells Fargo | J38: 0e668774beeb4182b5ea2d7a8677e014 | K38: 4918dbe6db3e4b9384fdfe7083417a5f | L38: 8b5374947e1d46e7a0f86b54ee722e44 | M38: =IF(NOT(_xlfn.XLOOKUP(Table1[[#This Row],[Category]],CategoriesTable[Category name],CategoriesTable[ID])=0),_xlfn.XLOOKUP(Table1[[#This Row],[Category]],CategoriesTable[Category name],CategoriesTable[ID]),_xlfn.XLOOKUP("Uncategorized",CategoriesTable[Category name],CategoriesTable[ID])) -> f59903268bc5a7b5382a7eb44e1c5e95 | N38: =IF(AND(NOT(ISBLANK(Table1[[#This Row],[Subcategory]])),NOT(_xlfn.XLOOKUP(Table1[[#This Row],[Subcategory]],SubcategoriesTable[Subcategory name],SubcategoriesTable[ID])=0)),_xlfn.XLOOKUP(Table1[[#This Row],[Subcategory]],SubcategoriesTable[Subcategory name],SubcategoriesTable[ID]),"") -> 29203f6b3d0b39d0da4dd72a306dbe8d | O38: {=IFERROR(INDEX(CategoriesTable[Category type],MATCH(Table1[[#This Row],[Category]],CategoriesTable[Category name],0),0),"")} -> Expense | P38: 27 | Q38: =MONTH(Table1[[#This Row],[Date]]) -> 12 | R38: 2021 | S38: =IF(ISBLANK(Table1[[#This Row],[Date]]),"",Table1[[#This Row],[Date]]-WEEKDAY(Table1[[#This Row],[Date]],2)+1) -> 44557 | T38: =IF(ISBLANK(Table1[[#This Row],[Date]]),"",DATE(Table1[[#This Row],[Date_Year]],Table1[[#This Row],[Date_Month]],1)) -> 44531
B39: 44556 | C39: Amazon | D39: Personal Spending | F39: -78.06 | G39: =_xlfn.XLOOKUP(Table1[[#This Row],[Account_ID]], Accounts[ID], Accounts[Account nickname], "Unknown") -> Discover | H39: =_xlfn.XLOOKUP(Table1[[#This Row],[Account_ID]], Accounts[ID], Accounts[Account'#], "Unknown") -> 4618 | I39: =_xlfn.XLOOKUP(_xlfn.XLOOKUP(Table1[[#This Row],[Account]],Accounts[Account nickname],Accounts[Institution ID]),Institutions[ID],Institutions[Institution nickname],"Unknown") -> Discover | J39: 7ccc2c916ed24fb78bf93a048583fef1 | K39: 0048d75f4d1d47f3b69428db4a68f3dd | L39: d09d1b66884d43439b5dad982b7d9e52 | M39: =IF(NOT(_xlfn.XLOOKUP(Table1[[#This Row],[Category]],CategoriesTable[Category name],CategoriesTable[ID])=0),_xlfn.XLOOKUP(Table1[[#This Row],[Category]],CategoriesTable[Category name],CategoriesTable[ID]),_xlfn.XLOOKUP("Uncategorized",CategoriesTable[Category name],CategoriesTable[ID])) -> f9fd776a16da81a948d166fcd5952d14 | N39: =IF(AND(NOT(ISBLANK(Table1[[#This Row],[Subcategory]])),NOT(_xlfn.XLOOKUP(Table1[[#This Row],[Subcategory]],SubcategoriesTable[Subcategory name],SubcategoriesTable[ID])=0)),_xlfn.XLOOKUP(Table1[[#This Row],[Subcategory]],SubcategoriesTable[Subcategory name],SubcategoriesTable[ID]),"") | O39: {=IFERROR(INDEX(CategoriesTable[Category type],MATCH(Table1[[#This Row],[Category]],CategoriesTable[Category name],0),0),"")} -> Expense | P39: 26 | Q39: =MONTH(Table1[[#This Row],[Date]]) -> 12 | R39: 2021 | S39: =IF(ISBLANK(Table1[[#This Row],[Date]]),"",Table1[[#This Row],[Date]]-WEEKDAY(Table1[[#This Row],[Date]],2)+1) -> 44550 | T39: =IF(ISBLANK(Table1[[#This Row],[Date]]),"",DATE(Table1[[#This Row],[Date_Year]],Table1[[#This Row],[Date_Month]],1)) -> 44531
B40: 44556 | C40: Trader Joe's | D40: Food | E40: Groceries | F40: -34.2 | G40: =_xlfn.XLOOKUP(Table1[[#This Row],[Account_ID]], Accounts[ID], Accounts[Account nickname], "Unknown") -> Discover | H40: =_xlfn.XLOOKUP(Table1[[#This Row],[Account_ID]], Accounts[ID], Accounts[Account'#], "Unknown") -> 4618 | I40: =_xlfn.XLOOKUP(_xlfn.XLOOKUP(Table1[[#This Row],[Account]],Accounts[Account nickname],Accounts[Institution ID]),Institutions[ID],Institutions[Institution nickname],"Unknown") -> Discover | J40: 55e23a392b864140b8e2c4f8b3309989 | K40: 0048d75f4d1d47f3b69428db4a68f3dd | L40: d09d1b66884d43439b5dad982b7d9e52 | M40: =IF(NOT(_xlfn.XLOOKUP(Table1[[#This Row],[Category]],CategoriesTable[Category name],CategoriesTable[ID])=0),_xlfn.XLOOKUP(Table1[[#This Row],[Category]],CategoriesTable[Category name],CategoriesTable[ID]),_xlfn.XLOOKUP("Uncategorized",CategoriesTable[Category name],CategoriesTable[ID])) -> fec746a44521f2118fef19237dbf4f91 | N40: =IF(AND(NOT(ISBLANK(Table1[[#This Row],[Subcategory]])),NOT(_xlfn.XLOOKUP(Table1[[#This Row],[Subcategory]],SubcategoriesTable[Subcategory name],SubcategoriesTable[ID])=0)),_xlfn.XLOOKUP(Table1[[#This Row],[Subcategory]],SubcategoriesTable[Subcategory name],SubcategoriesTable[ID]),"") -> fd72ce5cfeedbe66d13df9602b6cff7d | O40: {=IFERROR(INDEX(CategoriesTable[Category type],MATCH(Table1[[#This Row],[Category]],CategoriesTable[Category name],0),0),"")} -> Expense | P40: 26 | Q40: =MONTH(Table1[[#This Row],[Date]]) -> 12 | R40: 2021 | S40: =IF(ISBLANK(Table1[[#This Row],[Date]]),"",Table1[[#This Row],[Date]]-WEEKDAY(Table1[[#This Row],[Date]],2)+1) -> 44550 | T40: =IF(ISBLANK(Table1[[#This Row],[Date]]),"",DATE(Table1[[#This Row],[Date_Year]],Table1[[#This Row],[Date_Month]],1)) -> 44531
B41: 44555 | C41: Phoenix Suns Concessions Phoenix | D41: Recreational & Entertainment | E41: Sporting Events | F41: -33 | G41: =_xlfn.XLOOKUP(Table1[[#This Row],[Account_ID]], Accounts[ID], Accounts[Account nickname], "Unknown") -> Discover | H41: =_xlfn.XLOOKUP(Table1[[#This Row],[Account_ID]], Accounts[ID], Accounts[Account'#], "Unknown") -> 4618 | I41: =_xlfn.XLOOKUP(_xlfn.XLOOKUP(Table1[[#This Row],[Account]],Accounts[Account nickname],Accounts[Institution ID]),Institutions[ID],Institutions[Institution nickname],"Unknown") -> Discover | J41: f50c9fae77584e65a96ce119fdb760c6 | K41: 0048d75f4d1d47f3b69428db4a68f3dd | L41: d09d1b66884d43439b5dad982b7d9e52 | M41: =IF(NOT(_xlfn.XLOOKUP(Table1[[#This Row],[Category]],CategoriesTable[Category name],CategoriesTable[ID])=0),_xlfn.XLOOKUP(Table1[[#This Row],[Category]],CategoriesTable[Category name],CategoriesTable[ID]),_xlfn.XLOOKUP("Uncategorized",CategoriesTable[Category name],CategoriesTable[ID])) -> f870f35280fadaf3c3539ad54e3062cd | N41: =IF(AND(NOT(ISBLANK(Table1[[#This Row],[Subcategory]])),NOT(_xlfn.XLOOKUP(Table1[[#This Row],[Subcategory]],SubcategoriesTable[Subcategory name],SubcategoriesTable[ID])=0)),_xlfn.XLOOKUP(Table1[[#This Row],[Subcategory]],SubcategoriesTable[Subcategory name],SubcategoriesTable[ID]),"") -> 9fbba331d1ae096cbce7fb1035aebbc1 | O41: {=IFERROR(INDEX(CategoriesTable[Category type],MATCH(Table1[[#This Row],[Category]],CategoriesTable[Category name],0),0),"")} -> Expense | P41: 25 | Q41: =MONTH(Table1[[#This Row],[Date]]) -> 12 | R41: 2021 | S41: =IF(ISBLANK(Table1[[#This Row],[Date]]),"",Table1[[#This Row],[Date]]-WEEKDAY(Table1[[#This Row],[Date]],2)+1) -> 44550 | T41: =IF(ISBLANK(Table1[[#This Row],[Date]]),"",DATE(Table1[[#This Row],[Date_Year]],Table1[[#This Row],[Date_Month]],1)) -> 44531
B42: 44555 | C42: Cafe Rio Camelback | D42: Recreational & Entertainment | E42: Resteraunts | F42: -39.64 | G42: =_xlfn.XLOOKUP(Table1[[#This Row],[Account_ID]], Accounts[ID], Accounts[Account nickname], "Unknown") -> Discover | H42: =_xlfn.XLOOKUP(Table1[[#This Row],[Account_ID]], Accounts[ID], Accounts[Account'#], "Unknown") -> 4618 | I42: =_xlfn.XLOOKUP(_xlfn.XLOOKUP(Table1[[#This Row],[Account]],Accounts[Account nickname],Accounts[Institution ID]),Institutions[ID],Institutions[Institution nickname],"Unknown") -> Discover | J42: e6a1f22f719d4387ba5283b7c9965959 | K42: 0048d75f4d1d47f3b69428db4a68f3dd | L42: d09d1b66884d43439b5dad982b7d9e52 | M42: =IF(NOT(_xlfn.XLOOKUP(Table1[[#This Row],[Category]],CategoriesTable[Category name],CategoriesTable[ID])=0),_xlfn.XLOOKUP(Table1[[#This Row],[Category]],CategoriesTable[Category name],CategoriesTable[ID]),_xlfn.XLOOKUP("Uncategorized",CategoriesTable[Category name],CategoriesTable[ID])) -> f870f35280fadaf3c3539ad54e3062cd | N42: =IF(AND(NOT(ISBLANK(Table1[[#This Row],[Subcategory]])),NOT(_xlfn.XLOOKUP(Table1[[#This Row],[Subcategory]],SubcategoriesTable[Subcategory name],SubcategoriesTable[ID])=0)),_xlfn.XLOOKUP(Table1[[#This Row],[Subcategory]],SubcategoriesTable[Subcategory name],SubcategoriesTable[ID]),"") -> 500e6ba7cba37a7a2a33da8c057b4cb8 | O42: {=IFERROR(INDEX(CategoriesTable[Category type],MATCH(Table1[[#This Row],[Category]],CategoriesTable[Category name],0),0),"")} -> Expense | P42: 25 | Q42: =MONTH(Table1[[#This Row],[Date]]) -> 12 | R42: 2021 | S42: =IF(ISBLANK(Table1[[#This Row],[Date]]),"",Table1[[#This Row],[Date]]-WEEKDAY(Table1[[#This Row],[Date]],2)+1) -> 44550 | T42: =IF(ISBLANK(Table1[[#This Row],[Date]]),"",DATE(Table1[[#This Row],[Date_Year]],Table1[[#This Row],[Date_Month]],1)) -> 44531
B43: 44555 | C43: Clr Stretch T Item | D43: Personal Spending | E43: Health (Experimental) | F43: -79 | G43: =_xlfn.XLOOKUP(Table1[[#This Row],[Account_ID]], Accounts[ID], Accounts[Account nickname], "Unknown") -> Discover | H43: =_xlfn.XLOOKUP(Table1[[#This Row],[Account_ID]], Accounts[ID], Accounts[Account'#], "Unknown") -> 4618 | I43: =_xlfn.XLOOKUP(_xlfn.XLOOKUP(Table1[[#This Row],[Account]],Accounts[Account nickname],Accounts[Institution ID]),Institutions[ID],Institutions[Institution nickname],"Unknown") -> Discover | J43: d77f24f8411849b4aba0ea3c0cec785b | K43: 0048d75f4d1d47f3b69428db4a68f3dd | L43: d09d1b66884d43439b5dad982b7d9e52 | M43: =IF(NOT(_xlfn.XLOOKUP(Table1[[#This Row],[Category]],CategoriesTable[Category name],CategoriesTable[ID])=0),_xlfn.XLOOKUP(Table1[[#This Row],[Category]],CategoriesTable[Category name],CategoriesTable[ID]),_xlfn.XLOOKUP("Uncategorized",CategoriesTable[Category name],CategoriesTable[ID])) -> f9fd776a16da81a948d166fcd5952d14 | N43: =IF(AND(NOT(ISBLANK(Table1[[#This Row],[Subcategory]])),NOT(_xlfn.XLOOKUP(Table1[[#This Row],[Subcategory]],SubcategoriesTable[Subcategory name],SubcategoriesTable[ID])=0)),_xlfn.XLOOKUP(Table1[[#This Row],[Subcategory]],SubcategoriesTable[Subcategory name],SubcategoriesTable[ID]),"") -> bade29a2da6ab874d122981857355aa8 | O43: {=IFERROR(INDEX(CategoriesTable[Category type],MATCH(Table1[[#This Row],[Category]],CategoriesTable[Category name],0),0),"")} -> Expense | P43: 25 | Q43: =MONTH(Table1[[#This Row],[Date]]) -> 12 | R43: 2021 | S43: =IF(ISBLANK(Table1[[#This Row],[Date]]),"",Table1[[#This Row],[Date]]-WEEKDAY(Table1[[#This Row],[Date]],2)+1) -> 44550 | T43: =IF(ISBLANK(Table1[[#This Row],[Date]]),"",DATE(Table1[[#This Row],[Date_Year]],Table1[[#This Row],[Date_Month]],1)) -> 44531
B44: 44555 | C44: Phoenix Suns | D44: Recreational & Entertainment | E44: Sporting Events | F44: -65.14 | G44: =_xlfn.XLOOKUP(Table1[[#This Row],[Account_ID]], Accounts[ID], Accounts[Account nickname], "Unknown") -> Discover | H44: =_xlfn.XLOOKUP(Table1[[#This Row],[Account_ID]], Accounts[ID], Accounts[Account'#], "Unknown") -> 4618 | I44: =_xlfn.XLOOKUP(_xlfn.XLOOKUP(Table1[[#This Row],[Account]],Accounts[Account nickname],Accounts[Institution ID]),Institutions[ID],Institutions[Institution nickname],"Unknown") -> Discover | J44: 24a2adb4a96146c8a08017bd1e3681f8 | K44: 0048d75f4d1d47f3b69428db4a68f3dd | L44: d09d1b66884d43439b5dad982b7d9e52 | M44: =IF(NOT(_xlfn.XLOOKUP(Table1[[#This Row],[Category]],CategoriesTable[Category name],CategoriesTable[ID])=0),_xlfn.XLOOKUP(Table1[[#This Row],[Category]],CategoriesTable[Category name],CategoriesTable[ID]),_xlfn.XLOOKUP("Uncategorized",CategoriesTable[Category name],CategoriesTable[ID])) -> f870f35280fadaf3c3539ad54e3062cd | N44: =IF(AND(NOT(ISBLANK(Table1[[#This Row],[Subcategory]])),NOT(_xlfn.XLOOKUP(Table1[[#This Row],[Subcategory]],SubcategoriesTable[Subcategory name],SubcategoriesTable[ID])=0)),_xlfn.XLOOKUP(Table1[[#This Row],[Subcategory]],SubcategoriesTable[Subcategory name],SubcategoriesTable[ID]),"") -> 9fbba331d1ae096cbce7fb1035aebbc1 | O44: {=IFERROR(INDEX(CategoriesTable[Category type],MATCH(Table1[[#This Row],[Category]],CategoriesTable[Category name],0),0),"")} -> Expense | P44: 25 | Q44: =MONTH(Table1[[#This Row],[Date]]) -> 12 | R44: 2021 | S44: =IF(ISBLANK(Table1[[#This Row],[Date]]),"",Table1[[#This Row],[Date]]-WEEKDAY(Table1[[#This Row],[Date]],2)+1) -> 44550 | T44: =IF(ISBLANK(Table1[[#This Row],[Date]]),"",DATE(Table1[[#This Row],[Date_Year]],Table1[[#This Row],[Date_Month]],1)) -> 44531
B45: 44554 | C45: Hodori Restaurant | D45: Recreational & Entertainment | E45: Resteraunts | F45: -60 | G45: =_xlfn.XLOOKUP(Table1[[#This Row],[Account_ID]], Accounts[ID], Accounts[Account nickname], "Unknown") -> Discover | H45: =_xlfn.XLOOKUP(Table1[[#This Row],[Account_ID]], Accounts[ID], Accounts[Account'#], "Unknown") -> 4618 | I45: =_xlfn.XLOOKUP(_xlfn.XLOOKUP(Table1[[#This Row],[Account]],Accounts[Account nickname],Accounts[Institution ID]),Institutions[ID],Institutions[Institution nickname],"Unknown") -> Discover | J45: c7c04d50a9334048b5725f4f5938937d | K45: 0048d75f4d1d47f3b69428db4a68f3dd | L45: d09d1b66884d43439b5dad982b7d9e52 | M45: =IF(NOT(_xlfn.XLOOKUP(Table1[[#This Row],[Category]],CategoriesTable[Category name],CategoriesTable[ID])=0),_xlfn.XLOOKUP(Table1[[#This Row],[Category]],CategoriesTable[Category name],CategoriesTable[ID]),_xlfn.XLOOKUP("Uncategorized",CategoriesTable[Category name],CategoriesTable[ID])) -> f870f35280fadaf3c3539ad54e3062cd | N45: =IF(AND(NOT(ISBLANK(Table1[[#This Row],[Subcategory]])),NOT(_xlfn.XLOOKUP(Table1[[#This Row],[Subcategory]],SubcategoriesTable[Subcategory name],SubcategoriesTable[ID])=0)),_xlfn.XLOOKUP(Table1[[#This Row],[Subcategory]],SubcategoriesTable[Subcategory name],SubcategoriesTable[ID]),"") -> 500e6ba7cba37a7a2a33da8c057b4cb8 | O45: {=IFERROR(INDEX(CategoriesTable[Category type],MATCH(Table1[[#This Row],[Category]],CategoriesTable[Category name],0),0),"")} -> Expense | P45: 24 | Q45: =MONTH(Table1[[#This Row],[Date]]) -> 12 | R45: 2021 | S45: =IF(ISBLANK(Table1[[#This Row],[Date]]),"",Table1[[#This Row],[Date]]-WEEKDAY(Table1[[#This Row],[Date]],2)+1) -> 44550 | T45: =IF(ISBLANK(Table1[[#This Row],[Date]]),"",DATE(Table1[[#This Row],[Date_Year]],Table1[[#This Row],[Date_Month]],1)) -> 44531
B46: 44553 | C46: Safeway | D46: Food | E46: Groceries | F46: -47.58 | G46: =_xlfn.XLOOKUP(Table1[[#This Row],[Account_ID]], Accounts[ID], Accounts[Account nickname], "Unknown") -> Discover | H46: =_xlfn.XLOOKUP(Table1[[#This Row],[Account_ID]], Accounts[ID], Accounts[Account'#], "Unknown") -> 4618 | I46: =_xlfn.XLOOKUP(_xlfn.XLOOKUP(Table1[[#This Row],[Account]],Accounts[Account nickname],Accounts[Institution ID]),Institutions[ID],Institutions[Institution nickname],"Unknown") -> Discover | J46: 3b0e345b6a8e4b34a508b6ba49e35b44 | K46: 0048d75f4d1d47f3b69428db4a68f3dd | L46: d09d1b66884d43439b5dad982b7d9e52 | M46: =IF(NOT(_xlfn.XLOOKUP(Table1[[#This Row],[Category]],CategoriesTable[Category name],CategoriesTable[ID])=0),_xlfn.XLOOKUP(Table1[[#This Row],[Category]],CategoriesTable[Category name],CategoriesTable[ID]),_xlfn.XLOOKUP("Uncategorized",CategoriesTable[Category name],CategoriesTable[ID])) -> fec746a44521f2118fef19237dbf4f91 | N46: =IF(AND(NOT(ISBLANK(Table1[[#This Row],[Subcategory]])),NOT(_xlfn.XLOOKUP(Table1[[#This Row],[Subcategory]],SubcategoriesTable[Subcategory name],SubcategoriesTable[ID])=0)),_xlfn.XLOOKUP(Table1[[#This Row],[Subcategory]],SubcategoriesTable[Subcategory name],SubcategoriesTable[ID]),"") -> fd72ce5cfeedbe66d13df9602b6cff7d | O46: {=IFERROR(INDEX(CategoriesTable[Category type],MATCH(Table1[[#This Row],[Category]],CategoriesTable[Category name],0),0),"")} -> Expense | P46: 23 | Q46: =MONTH(Table1[[#This Row],[Date]]) -> 12 | R46: 2021 | S46: =IF(ISBLANK(Table1[[#This Row],[Date]]),"",Table1[[#This Row],[Date]]-WEEKDAY(Table1[[#This Row],[Date]],2)+1) -> 44550 | T46: =IF(ISBLANK(Table1[[#This Row],[Date]]),"",DATE(Table1[[#This Row],[Date_Year]],Table1[[#This Row],[Date_Month]],1)) -> 44531
B47: 44553 | C47: Direct Deposit From Lifetime | D47: Income | F47: 5.99 | G47: =_xlfn.XLOOKUP(Table1[[#This Row],[Account_ID]], Accounts[ID], Accounts[Account nickname], "Unknown") -> WF | H47: =_xlfn.XLOOKUP(Table1[[#This Row],[Account_ID]], Accounts[ID], Accounts[Account'#], "Unknown") -> 4636 | I47: =_xlfn.XLOOKUP(_xlfn.XLOOKUP(Table1[[#This Row],[Account]],Accounts[Account nickname],Accounts[Institution ID]),Institutions[ID],Institutions[Institution nickname],"Unknown") -> Wells Fargo | J47: 2e482857a7ec46fc85c5d63b1ece1f5f | K47: 4918dbe6db3e4b9384fdfe7083417a5f | L47: 8b5374947e1d46e7a0f86b54ee722e44 | M47: =IF(NOT(_xlfn.XLOOKUP(Table1[[#This Row],[Category]],CategoriesTable[Category name],CategoriesTable[ID])=0),_xlfn.XLOOKUP(Table1[[#This Row],[Category]],CategoriesTable[Category name],CategoriesTable[ID]),_xlfn.XLOOKUP("Uncategorized",CategoriesTable[Category name],CategoriesTable[ID])) -> fabfe582932d48b78ac2846c1ec3d43f | N47: =IF(AND(NOT(ISBLANK(Table1[[#This Row],[Subcategory]])),NOT(_xlfn.XLOOKUP(Table1[[#This Row],[Subcategory]],SubcategoriesTable[Subcategory name],SubcategoriesTable[ID])=0)),_xlfn.XLOOKUP(Table1[[#This Row],[Subcategory]],SubcategoriesTable[Subcategory name],SubcategoriesTable[ID]),"") | O47: {=IFERROR(INDEX(CategoriesTable[Category type],MATCH(Table1[[#This Row],[Category]],CategoriesTable[Category name],0),0),"")} -> Expense | P47: 23 | Q47: =MONTH(Table1[[#This Row],[Date]]) -> 12 | R47: 2021 | S47: =IF(ISBLANK(Table1[[#This Row],[Date]]),"",Table1[[#This Row],[Date]]-WEEKDAY(Table1[[#This Row],[Date]],2)+1) -> 44550 | T47: =IF(ISBLANK(Table1[[#This Row],[Date]]),"",DATE(Table1[[#This Row],[Date_Year]],Table1[[#This Row],[Date_Month]],1)) -> 44531
B48: 44553 | C48: Safeway | D48: Food | E48: Groceries | F48: -56.23 | G48: =_xlfn.XLOOKUP(Table1[[#This Row],[Account_ID]], Accounts[ID], Accounts[Account nickname], "Unknown") -> Discover | H48: =_xlfn.XLOOKUP(Table1[[#This Row],[Account_ID]], Accounts[ID], Accounts[Account'#], "Unknown") -> 4618 | I48: =_xlfn.XLOOKUP(_xlfn.XLOOKUP(Table1[[#This Row],[Account]],Accounts[Account nickname],Accounts[Institution ID]),Institutions[ID],Institutions[Institution nickname],"Unknown") -> Discover | J48: 12f8d2575dfd416499f19b62e129192c | K48: 0048d75f4d1d47f3b69428db4a68f3dd | L48: d09d1b66884d43439b5dad982b7d9e52 | M48: =IF(NOT(_xlfn.XLOOKUP(Table1[[#This Row],[Category]],CategoriesTable[Category name],CategoriesTable[ID])=0),_xlfn.XLOOKUP(Table1[[#This Row],[Category]],CategoriesTable[Category name],CategoriesTable[ID]),_xlfn.XLOOKUP("Uncategorized",CategoriesTable[Category name],CategoriesTable[ID])) -> fec746a44521f2118fef19237dbf4f91 | N48: =IF(AND(NOT(ISBLANK(Table1[[#This Row],[Subcategory]])),NOT(_xlfn.XLOOKUP(Table1[[#This Row],[Subcategory]],SubcategoriesTable[Subcategory name],SubcategoriesTable[ID])=0)),_xlfn.XLOOKUP(Table1[[#This Row],[Subcategory]],SubcategoriesTable[Subcategory name],SubcategoriesTable[ID]),"") -> fd72ce5cfeedbe66d13df9602b6cff7d | O48: {=IFERROR(INDEX(CategoriesTable[Category type],MATCH(Table1[[#This Row],[Category]],CategoriesTable[Category name],0),0),"")} -> Expense | P48: 23 | Q48: =MONTH(Table1[[#This Row],[Date]]) -> 12 | R48: 2021 | S48: =IF(ISBLANK(Table1[[#This Row],[Date]]),"",Table1[[#This Row],[Date]]-WEEKDAY(Table1[[#This Row],[Date]],2)+1) -> 44550 | T48: =IF(ISBLANK(Table1[[#This Row],[Date]]),"",DATE(Table1[[#This Row],[Date_Year]],Table1[[#This Row],[Date_Month]],1)) -> 44531
B49: 44552 | C49: Track Market & Liquor | D49: Recreational & Entertainment | E49: Conveinence Store | F49: -12 | G49: =_xlfn.XLOOKUP(Table1[[#This Row],[Account_ID]], Accounts[ID], Accounts[Account nickname], "Unknown") -> Discover | H49: =_xlfn.XLOOKUP(Table1[[#This Row],[Account_ID]], Accounts[ID], Accounts[Account'#], "Unknown") -> 4618 | I49: =_xlfn.XLOOKUP(_xlfn.XLOOKUP(Table1[[#This Row],[Account]],Accounts[Account nickname],Accounts[Institution ID]),Institutions[ID],Institutions[Institution nickname],"Unknown") -> Discover | J49: d610f2a777114d5b951e10092a80b839 | K49: 0048d75f4d1d47f3b69428db4a68f3dd | L49: d09d1b66884d43439b5dad982b7d9e52 | M49: =IF(NOT(_xlfn.XLOOKUP(Table1[[#This Row],[Category]],CategoriesTable[Category name],CategoriesTable[ID])=0),_xlfn.XLOOKUP(Table1[[#This Row],[Category]],CategoriesTable[Category name],CategoriesTable[ID]),_xlfn.XLOOKUP("Uncategorized",CategoriesTable[Category name],CategoriesTable[ID])) -> f870f35280fadaf3c3539ad54e3062cd | N49: =IF(AND(NOT(ISBLANK(Table1[[#This Row],[Subcategory]])),NOT(_xlfn.XLOOKUP(Table1[[#This Row],[Subcategory]],SubcategoriesTable[Subcategory name],SubcategoriesTable[ID])=0)),_xlfn.XLOOKUP(Table1[[#This Row],[Subcategory]],SubcategoriesTable[Subcategory name],SubcategoriesTable[ID]),"") -> 34adc8b6f193384cf07b408d6a4dfac6 | O49: {=IFERROR(INDEX(CategoriesTable[Category type],MATCH(Table1[[#This Row],[Category]],CategoriesTable[Category name],0),0),"")} -> Expense | P49: 22 | Q49: =MONTH(Table1[[#This Row],[Date]]) -> 12 | R49: 2021 | S49: =IF(ISBLANK(Table1[[#This Row],[Date]]),"",Table1[[#This Row],[Date]]-WEEKDAY(Table1[[#This Row],[Date]],2)+1) -> 44550 | T49: =IF(ISBLANK(Table1[[#This Row],[Date]]),"",DATE(Table1[[#This Row],[Date_Year]],Table1[[#This Row],[Date_Month]],1)) -> 44531
B50: 44552 | C50: Schlotzsky's | D50: Recreational & Entertainment | E50: Resteraunts | F50: -29.19 | G50: =_xlfn.XLOOKUP(Table1[[#This Row],[Account_ID]], Accounts[ID], Accounts[Account nickname], "Unknown") -> Discover | H50: =_xlfn.XLOOKUP(Table1[[#This Row],[Account_ID]], Accounts[ID], Accounts[Account'#], "Unknown") -> 4618 | I50: =_xlfn.XLOOKUP(_xlfn.XLOOKUP(Table1[[#This Row],[Account]],Accounts[Account nickname],Accounts[Institution ID]),Institutions[ID],Institutions[Institution nickname],"Unknown") -> Discover | J50: d29321bf3dac4d53883375ecf4369d35 | K50: 0048d75f4d1d47f3b69428db4a68f3dd | L50: d09d1b66884d43439b5dad982b7d9e52 | M50: =IF(NOT(_xlfn.XLOOKUP(Table1[[#This Row],[Category]],CategoriesTable[Category name],CategoriesTable[ID])=0),_xlfn.XLOOKUP(Table1[[#This Row],[Category]],CategoriesTable[Category name],CategoriesTable[ID]),_xlfn.XLOOKUP("Uncategorized",CategoriesTable[Category name],CategoriesTable[ID])) -> f870f35280fadaf3c3539ad54e3062cd | N50: =IF(AND(NOT(ISBLANK(Table1[[#This Row],[Subcategory]])),NOT(_xlfn.XLOOKUP(Table1[[#This Row],[Subcategory]],SubcategoriesTable[Subcategory name],SubcategoriesTable[ID])=0)),_xlfn.XLOOKUP(Table1[[#This Row],[Subcategory]],SubcategoriesTable[Subcategory name],SubcategoriesTable[ID]),"") -> 500e6ba7cba37a7a2a33da8c057b4cb8 | O50: {=IFERROR(INDEX(CategoriesTable[Category type],MATCH(Table1[[#This Row],[Category]],CategoriesTable[Category name],0),0),"")} -> Expense | P50: 22 | Q50: =MONTH(Table1[[#This Row],[Date]]) -> 12 | R50: 2021 | S50: =IF(ISBLANK(Table1[[#This Row],[Date]]),"",Table1[[#This Row],[Date]]-WEEKDAY(Table1[[#This Row],[Date]],2)+1) -> 44550 | T50: =IF(ISBLANK(Table1[[#This Row],[Date]]),"",DATE(Table1[[#This Row],[Date_Year]],Table1[[#This Row],[Date_Month]],1)) -> 44531
B51: 44552 | C51: Purchase Authorized On | D51: Personal Spending | F51: -78.62 | G51: =_xlfn.XLOOKUP(Table1[[#This Row],[Account_ID]], Accounts[ID], Accounts[Account nickname], "Unknown") -> WF | H51: =_xlfn.XLOOKUP(Table1[[#This Row],[Account_ID]], Accounts[ID], Accounts[Account'#], "Unknown") -> 4636 | I51: =_xlfn.XLOOKUP(_xlfn.XLOOKUP(Table1[[#This Row],[Account]],Accounts[Account nickname],Accounts[Institution ID]),Institutions[ID],Institutions[Institution nickname],"Unknown") -> Wells Fargo | J51: a327d9b412774b01be2a18955fd0fb72 | K51: 4918dbe6db3e4b9384fdfe7083417a5f | L51: 8b5374947e1d46e7a0f86b54ee722e44 | M51: =IF(NOT(_xlfn.XLOOKUP(Table1[[#This Row],[Category]],CategoriesTable[Category name],CategoriesTable[ID])=0),_xlfn.XLOOKUP(Table1[[#This Row],[Category]],CategoriesTable[Category name],CategoriesTable[ID]),_xlfn.XLOOKUP("Uncategorized",CategoriesTable[Category name],CategoriesTable[ID])) -> f9fd776a16da81a948d166fcd5952d14 | N51: =IF(AND(NOT(ISBLANK(Table1[[#This Row],[Subcategory]])),NOT(_xlfn.XLOOKUP(Table1[[#This Row],[Subcategory]],SubcategoriesTable[Subcategory name],SubcategoriesTable[ID])=0)),_xlfn.XLOOKUP(Table1[[#This Row],[Subcategory]],SubcategoriesTable[Subcategory name],SubcategoriesTable[ID]),"") | O51: {=IFERROR(INDEX(CategoriesTable[Category type],MATCH(Table1[[#This Row],[Category]],CategoriesTable[Category name],0),0),"")} -> Expense | P51: 22 | Q51: =MONTH(Table1[[#This Row],[Date]]) -> 12 | R51: 2021 | S51: =IF(ISBLANK(Table1[[#This Row],[Date]]),"",Table1[[#This Row],[Date]]-WEEKDAY(Table1[[#This Row],[Date]],2)+1) -> 44550 | T51: =IF(ISBLANK(Table1[[#This Row],[Date]]),"",DATE(Table1[[#This Row],[Date_Year]],Table1[[#This Row],[Date_Month]],1)) -> 44531
B52: 44552 | C52: Atm Cash Deposit On | D52: Income | F52: 21 | G52: =_xlfn.XLOOKUP(Table1[[#This Row],[Account_ID]], Accounts[ID], Accounts[Account nickname], "Unknown") -> WF | H52: =_xlfn.XLOOKUP(Table1[[#This Row],[Account_ID]], Accounts[ID], Accounts[Account'#], "Unknown") -> 4636 | I52: =_xlfn.XLOOKUP(_xlfn.XLOOKUP(Table1[[#This Row],[Account]],Accounts[Account nickname],Accounts[Institution ID]),Institutions[ID],Institutions[Institution nickname],"Unknown") -> Wells Fargo | J52: 9faed51681ea4d488f6a11dd9f0dd412 | K52: 4918dbe6db3e4b9384fdfe7083417a5f | L52: 8b5374947e1d46e7a0f86b54ee722e44 | M52: =IF(NOT(_xlfn.XLOOKUP(Table1[[#This Row],[Category]],CategoriesTable[Category name],CategoriesTable[ID])=0),_xlfn.XLOOKUP(Table1[[#This Row],[Category]],CategoriesTable[Category name],CategoriesTable[ID]),_xlfn.XLOOKUP("Uncategorized",CategoriesTable[Category name],CategoriesTable[ID])) -> fabfe582932d48b78ac2846c1ec3d43f | N52: =IF(AND(NOT(ISBLANK(Table1[[#This Row],[Subcategory]])),NOT(_xlfn.XLOOKUP(Table1[[#This Row],[Subcategory]],SubcategoriesTable[Subcategory name],SubcategoriesTable[ID])=0)),_xlfn.XLOOKUP(Table1[[#This Row],[Subcategory]],SubcategoriesTable[Subcategory name],SubcategoriesTable[ID]),"") | O52: {=IFERROR(INDEX(CategoriesTable[Category type],MATCH(Table1[[#This Row],[Category]],CategoriesTable[Category name],0),0),"")} -> Expense | P52: 22 | Q52: =MONTH(Table1[[#This Row],[Date]]) -> 12 | R52: 2021 | S52: =IF(ISBLANK(Table1[[#This Row],[Date]]),"",Table1[[#This Row],[Date]]-WEEKDAY(Table1[[#This Row],[Date]],2)+1) -> 44550 | T52: =IF(ISBLANK(Table1[[#This Row],[Date]]),"",DATE(Table1[[#This Row],[Date_Year]],Table1[[#This Row],[Date_Month]],1)) -> 44531
B53: 44552 | C53: Atm Cash Deposit On | D53: Income | F53: 131 | G53: =_xlfn.XLOOKUP(Table1[[#This Row],[Account_ID]], Accounts[ID], Accounts[Account nickname], "Unknown") -> WF | H53: =_xlfn.XLOOKUP(Table1[[#This Row],[Account_ID]], Accounts[ID], Accounts[Account'#], "Unknown") -> 4636 | I53: =_xlfn.XLOOKUP(_xlfn.XLOOKUP(Table1[[#This Row],[Account]],Accounts[Account nickname],Accounts[Institution ID]),Institutions[ID],Institutions[Institution nickname],"Unknown") -> Wells Fargo | J53: 0b56103a18204ea9a0a1196c64364514 | K53: 4918dbe6db3e4b9384fdfe7083417a5f | L53: 8b5374947e1d46e7a0f86b54ee722e44 | M53: =IF(NOT(_xlfn.XLOOKUP(Table1[[#This Row],[Category]],CategoriesTable[Category name],CategoriesTable[ID])=0),_xlfn.XLOOKUP(Table1[[#This Row],[Category]],CategoriesTable[Category name],CategoriesTable[ID]),_xlfn.XLOOKUP("Uncategorized",CategoriesTable[Category name],CategoriesTable[ID])) -> fabfe582932d48b78ac2846c1ec3d43f | N53: =IF(AND(NOT(ISBLANK(Table1[[#This Row],[Subcategory]])),NOT(_xlfn.XLOOKUP(Table1[[#This Row],[Subcategory]],SubcategoriesTable[Subcategory name],SubcategoriesTable[ID])=0)),_xlfn.XLOOKUP(Table1[[#This Row],[Subcategory]],SubcategoriesTable[Subcategory name],SubcategoriesTable[ID]),"") | O53: {=IFERROR(INDEX(CategoriesTable[Category type],MATCH(Table1[[#This Row],[Category]],CategoriesTable[Category name],0),0),"")} -> Expense | P53: 22 | Q53: =MONTH(Table1[[#This Row],[Date]]) -> 12 | R53: 2021 | S53: =IF(ISBLANK(Table1[[#This Row],[Date]]),"",Table1[[#This Row],[Date]]-WEEKDAY(Table1[[#This Row],[Date]],2)+1) -> 44550 | T53: =IF(ISBLANK(Table1[[#This Row],[Date]]),"",DATE(Table1[[#This Row],[Date_Year]],Table1[[#This Row],[Date_Month]],1)) -> 44531
B54: 44551 | C54: Paypal Inst Xfer Pp | D54: Recreational & Entertainment | E54: Streaming Services | F54: -7.99 | G54: =_xlfn.XLOOKUP(Table1[[#This Row],[Account_ID]], Accounts[ID], Accounts[Account nickname], "Unknown") -> WF | H54: =_xlfn.XLOOKUP(Table1[[#This Row],[Account_ID]], Accounts[ID], Accounts[Account'#], "Unknown") -> 4636 | I54: =_xlfn.XLOOKUP(_xlfn.XLOOKUP(Table1[[#This Row],[Account]],Accounts[Account nickname],Accounts[Institution ID]),Institutions[ID],Institutions[Institution nickname],"Unknown") -> Wells Fargo | J54: e1e384a202a441928b53c496f99c39dd | K54: 4918dbe6db3e4b9384fdfe7083417a5f | L54: 8b5374947e1d46e7a0f86b54ee722e44 | M54: =IF(NOT(_xlfn.XLOOKUP(Table1[[#This Row],[Category]],CategoriesTable[Category name],CategoriesTable[ID])=0),_xlfn.XLOOKUP(Table1[[#This Row],[Category]],CategoriesTable[Category name],CategoriesTable[ID]),_xlfn.XLOOKUP("Uncategorized",CategoriesTable[Category name],CategoriesTable[ID])) -> f870f35280fadaf3c3539ad54e3062cd | N54: =IF(AND(NOT(ISBLANK(Table1[[#This Row],[Subcategory]])),NOT(_xlfn.XLOOKUP(Table1[[#This Row],[Subcategory]],SubcategoriesTable[Subcategory name],SubcategoriesTable[ID])=0)),_xlfn.XLOOKUP(Table1[[#This Row],[Subcategory]],SubcategoriesTable[Subcategory name],SubcategoriesTable[ID]),"") -> 62ae30b53561aa5d303e08e4369dbfc3 | O54: {=IFERROR(INDEX(CategoriesTable[Category type],MATCH(Table1[[#This Row],[Category]],CategoriesTable[Category name],0),0),"")} -> Expense | P54: 21 | Q54: =MONTH(Table1[[#This Row],[Date]]) -> 12 | R54: 2021 | S54: =IF(ISBLANK(Table1[[#This Row],[Date]]),"",Table1[[#This Row],[Date]]-WEEKDAY(Table1[[#This Row],[Date]],2)+1) -> 44550 | T54: =IF(ISBLANK(Table1[[#This Row],[Date]]),"",DATE(Table1[[#This Row],[Date_Year]],Table1[[#This Row],[Date_Month]],1)) -> 44531
B55: 44551 | C55: Ccbill Az Item Transferred | D55: Personal Spending | E55: Subscription | F55: -3.3 | G55: =_xlfn.XLOOKUP(Table1[[#This Row],[Account_ID]], Accounts[ID], Accounts[Account nickname], "Unknown") -> Discover | H55: =_xlfn.XLOOKUP(Table1[[#This Row],[Account_ID]], Accounts[ID], Accounts[Account'#], "Unknown") -> 4618 | I55: =_xlfn.XLOOKUP(_xlfn.XLOOKUP(Table1[[#This Row],[Account]],Accounts[Account nickname],Accounts[Institution ID]),Institutions[ID],Institutions[Institution nickname],"Unknown") -> Discover | J55: e151fee603eb4c71a352160f83228333 | K55: 0048d75f4d1d47f3b69428db4a68f3dd | L55: d09d1b66884d43439b5dad982b7d9e52 | M55: =IF(NOT(_xlfn.XLOOKUP(Table1[[#This Row],[Category]],CategoriesTable[Category name],CategoriesTable[ID])=0),_xlfn.XLOOKUP(Table1[[#This Row],[Category]],CategoriesTable[Category name],CategoriesTable[ID]),_xlfn.XLOOKUP("Uncategorized",CategoriesTable[Category name],CategoriesTable[ID])) -> f9fd776a16da81a948d166fcd5952d14 | N55: =IF(AND(NOT(ISBLANK(Table1[[#This Row],[Subcategory]])),NOT(_xlfn.XLOOKUP(Table1[[#This Row],[Subcategory]],SubcategoriesTable[Subcategory name],SubcategoriesTable[ID])=0)),_xlfn.XLOOKUP(Table1[[#This Row],[Subcategory]],SubcategoriesTable[Subcategory name],SubcategoriesTable[ID]),"") -> 8aa9b4db7e16cd2041aa6bfdc219e567 | O55: {=IFERROR(INDEX(CategoriesTable[Category type],MATCH(Table1[[#This Row],[Category]],CategoriesTable[Category name],0),0),"")} -> Expense | P55: 21 | Q55: =MONTH(Table1[[#This Row],[Date]]) -> 12 | R55: 2021 | S55: =IF(ISBLANK(Table1[[#This Row],[Date]]),"",Table1[[#This Row],[Date]]-WEEKDAY(Table1[[#This Row],[Date]],2)+1) -> 44550 | T55: =IF(ISBLANK(Table1[[#This Row],[Date]]),"",DATE(Table1[[#This Row],[Date_Year]],Table1[[#This Row],[Date_Month]],1)) -> 44531
B56: 44551 | C56: Ccbill Az Item Transferred | D56: Personal Spending | E56: Subscription | F56: -3.49 | G56: =_xlfn.XLOOKUP(Table1[[#This Row],[Account_ID]], Accounts[ID], Accounts[Account nickname], "Unknown") -> Discover | H56: =_xlfn.XLOOKUP(Table1[[#This Row],[Account_ID]], Accounts[ID], Accounts[Account'#], "Unknown") -> 4618 | I56: =_xlfn.XLOOKUP(_xlfn.XLOOKUP(Table1[[#This Row],[Account]],Accounts[Account nickname],Accounts[Institution ID]),Institutions[ID],Institutions[Institution nickname],"Unknown") -> Discover | J56: 9ccd6f96b6c34ba883748011aba18927 | K56: 0048d75f4d1d47f3b69428db4a68f3dd | L56: d09d1b66884d43439b5dad982b7d9e52 | M56: =IF(NOT(_xlfn.XLOOKUP(Table1[[#This Row],[Category]],CategoriesTable[Category name],CategoriesTable[ID])=0),_xlfn.XLOOKUP(Table1[[#This Row],[Category]],CategoriesTable[Category name],CategoriesTable[ID]),_xlfn.XLOOKUP("Uncategorized",CategoriesTable[Category name],CategoriesTable[ID])) -> f9fd776a16da81a948d166fcd5952d14 | N56: =IF(AND(NOT(ISBLANK(Table1[[#This Row],[Subcategory]])),NOT(_xlfn.XLOOKUP(Table1[[#This Row],[Subcategory]],SubcategoriesTable[Subcategory name],SubcategoriesTable[ID])=0)),_xlfn.XLOOKUP(Table1[[#This Row],[Subcategory]],SubcategoriesTable[Subcategory name],SubcategoriesTable[ID]),"") -> 8aa9b4db7e16cd2041aa6bfdc219e567 | O56: {=IFERROR(INDEX(CategoriesTable[Category type],MATCH(Table1[[#This Row],[Category]],CategoriesTable[Category name],0),0),"")} -> Expense | P56: 21 | Q56: =MONTH(Table1[[#This Row],[Date]]) -> 12 | R56: 2021 | S56: =IF(ISBLANK(Table1[[#This Row],[Date]]),"",Table1[[#This Row],[Date]]-WEEKDAY(Table1[[#This Row],[Date]],2)+1) -> 44550 | T56: =IF(ISBLANK(Table1[[#This Row],[Date]]),"",DATE(Table1[[#This Row],[Date_Year]],Table1[[#This Row],[Date_Month]],1)) -> 44531
B57: 44551 | C57: Chino Bandido | D57: Recreational & Entertainment | E57: Resteraunts | F57: -27.95 | G57: =_xlfn.XLOOKUP(Table1[[#This Row],[Account_ID]], Accounts[ID], Accounts[Account nickname], "Unknown") -> Discover | H57: =_xlfn.XLOOKUP(Table1[[#This Row],[Account_ID]], Accounts[ID], Accounts[Account'#], "Unknown") -> 4618 | I57: =_xlfn.XLOOKUP(_xlfn.XLOOKUP(Table1[[#This Row],[Account]],Accounts[Account nickname],Accounts[Institution ID]),Institutions[ID],Institutions[Institution nickname],"Unknown") -> Discover | J57: 24fb6f442d164cc885ee0eea5902b65b | K57: 0048d75f4d1d47f3b69428db4a68f3dd | L57: d09d1b66884d43439b5dad982b7d9e52 | M57: =IF(NOT(_xlfn.XLOOKUP(Table1[[#This Row],[Category]],CategoriesTable[Category name],CategoriesTable[ID])=0),_xlfn.XLOOKUP(Table1[[#This Row],[Category]],CategoriesTable[Category name],CategoriesTable[ID]),_xlfn.XLOOKUP("Uncategorized",CategoriesTable[Category name],CategoriesTable[ID])) -> f870f35280fadaf3c3539ad54e3062cd | N57: =IF(AND(NOT(ISBLANK(Table1[[#This Row],[Subcategory]])),NOT(_xlfn.XLOOKUP(Table1[[#This Row],[Subcategory]],SubcategoriesTable[Subcategory name],SubcategoriesTable[ID])=0)),_xlfn.XLOOKUP(Table1[[#This Row],[Subcategory]],SubcategoriesTable[Subcategory name],SubcategoriesTable[ID]),"") -> 500e6ba7cba37a7a2a33da8c057b4cb8 | O57: {=IFERROR(INDEX(CategoriesTable[Category type],MATCH(Table1[[#This Row],[Category]],CategoriesTable[Category name],0),0),"")} -> Expense | P57: 21 | Q57: =MONTH(Table1[[#This Row],[Date]]) -> 12 | R57: 2021 | S57: =IF(ISBLANK(Table1[[#This Row],[Date]]),"",Table1[[#This Row],[Date]]-WEEKDAY(Table1[[#This Row],[Date]],2)+1) -> 44550 | T57: =IF(ISBLANK(Table1[[#This Row],[Date]]),"",DATE(Table1[[#This Row],[Date_Year]],Table1[[#This Row],[Date_Month]],1)) -> 44531
B58: 44550 | C58: Youtube Tv G Co | D58: Recreational & Entertainment | E58: Streaming Services | F58: -102.06 | G58: =_xlfn.XLOOKUP(Table1[[#This Row],[Account_ID]], Accounts[ID], Accounts[Account nickname], "Unknown") -> Discover | H58: =_xlfn.XLOOKUP(Table1[[#This Row],[Account_ID]], Accounts[ID], Accounts[Account'#], "Unknown") -> 4618 | I58: =_xlfn.XLOOKUP(_xlfn.XLOOKUP(Table1[[#This Row],[Account]],Accounts[Account nickname],Accounts[Institution ID]),Institutions[ID],Institutions[Institution nickname],"Unknown") -> Discover | J58: e7bc6c1b1c7b43abacec2482fed332de | K58: 0048d75f4d1d47f3b69428db4a68f3dd | L58: d09d1b66884d43439b5dad982b7d9e52 | M58: =IF(NOT(_xlfn.XLOOKUP(Table1[[#This Row],[Category]],CategoriesTable[Category name],CategoriesTable[ID])=0),_xlfn.XLOOKUP(Table1[[#This Row],[Category]],CategoriesTable[Category name],CategoriesTable[ID]),_xlfn.XLOOKUP("Uncategorized",CategoriesTable[Category name],CategoriesTable[ID])) -> f870f35280fadaf3c3539ad54e3062cd | N58: =IF(AND(NOT(ISBLANK(Table1[[#This Row],[Subcategory]])),NOT(_xlfn.XLOOKUP(Table1[[#This Row],[Subcategory]],SubcategoriesTable[Subcategory name],SubcategoriesTable[ID])=0)),_xlfn.XLOOKUP(Table1[[#This Row],[Subcategory]],SubcategoriesTable[Subcategory name],SubcategoriesTable[ID]),"") -> 62ae30b53561aa5d303e08e4369dbfc3 | O58: {=IFERROR(INDEX(CategoriesTable[Category type],MATCH(Table1[[#This Row],[Category]],CategoriesTable[Category name],0),0),"")} -> Expense | P58: 20 | Q58: =MONTH(Table1[[#This Row],[Date]]) -> 12 | R58: 2021 | S58: =IF(ISBLANK(Table1[[#This Row],[Date]]),"",Table1[[#This Row],[Date]]-WEEKDAY(Table1[[#This Row],[Date]],2)+1) -> 44550 | T58: =IF(ISBLANK(Table1[[#This Row],[Date]]),"",DATE(Table1[[#This Row],[Date_Year]],Table1[[#This Row],[Date_Month]],1)) -> 44531
B59: 44550 | C59: Ups | D59: Personal Spending | E59: Gifts/Donations | F59: -186.56 | G59: =_xlfn.XLOOKUP(Table1[[#This Row],[Account_ID]], Accounts[ID], Accounts[Account nickname], "Unknown") -> Discover | H59: =_xlfn.XLOOKUP(Table1[[#This Row],[Account_ID]], Accounts[ID], Accounts[Account'#], "Unknown") -> 4618 | I59: =_xlfn.XLOOKUP(_xlfn.XLOOKUP(Table1[[#This Row],[Account]],Accounts[Account nickname],Accounts[Institution ID]),Institutions[ID],Institutions[Institution nickname],"Unknown") -> Discover | J59: c642bc1a4077442187526fc9a55889c9 | K59: 0048d75f4d1d47f3b69428db4a68f3dd | L59: d09d1b66884d43439b5dad982b7d9e52 | M59: =IF(NOT(_xlfn.XLOOKUP(Table1[[#This Row],[Category]],CategoriesTable[Category name],CategoriesTable[ID])=0),_xlfn.XLOOKUP(Table1[[#This Row],[Category]],CategoriesTable[Category name],CategoriesTable[ID]),_xlfn.XLOOKUP("Uncategorized",CategoriesTable[Category name],CategoriesTable[ID])) -> f9fd776a16da81a948d166fcd5952d14 | N59: =IF(AND(NOT(ISBLANK(Table1[[#This Row],[Subcategory]])),NOT(_xlfn.XLOOKUP(Table1[[#This Row],[Subcategory]],SubcategoriesTable[Subcategory name],SubcategoriesTable[ID])=0)),_xlfn.XLOOKUP(Table1[[#This Row],[Subcategory]],SubcategoriesTable[Subcategory name],SubcategoriesTable[ID]),"") -> 184c9cbdd77dcd3cf895b482a60b53ae | O59: {=IFERROR(INDEX(CategoriesTable[Category type],MATCH(Table1[[#This Row],[Category]],CategoriesTable[Category name],0),0),"")} -> Expense | P59: 20 | Q59: =MONTH(Table1[[#This Row],[Date]]) -> 12 | R59: 2021 | S59: =IF(ISBLANK(Table1[[#This Row],[Date]]),"",Table1[[#This Row],[Date]]-WEEKDAY(Table1[[#This Row],[Date]],2)+1) -> 44550 | T59: =IF(ISBLANK(Table1[[#This Row],[Date]]),"",DATE(Table1[[#This Row],[Date_Year]],Table1[[#This Row],[Date_Month]],1)) -> 44531
B60: 44550 | C60: Atm Withdrawal Authorized On | D60: Recreational & Entertainment | F60: -200 | G60: =_xlfn.XLOOKUP(Table1[[#This Row],[Account_ID]], Accounts[ID], Accounts[Account nickname], "Unknown") -> WF | H60: =_xlfn.XLOOKUP(Table1[[#This Row],[Account_ID]], Accounts[ID], Accounts[Account'#], "Unknown") -> 4636 | I60: =_xlfn.XLOOKUP(_xlfn.XLOOKUP(Table1[[#This Row],[Account]],Accounts[Account nickname],Accounts[Institution ID]),Institutions[ID],Institutions[Institution nickname],"Unknown") -> Wells Fargo | J60: b6e5c869f3854c879010a34d71ac1d82 | K60: 4918dbe6db3e4b9384fdfe7083417a5f | L60: 8b5374947e1d46e7a0f86b54ee722e44 | M60: =IF(NOT(_xlfn.XLOOKUP(Table1[[#This Row],[Category]],CategoriesTable[Category name],CategoriesTable[ID])=0),_xlfn.XLOOKUP(Table1[[#This Row],[Category]],CategoriesTable[Category name],CategoriesTable[ID]),_xlfn.XLOOKUP("Uncategorized",CategoriesTable[Category name],CategoriesTable[ID])) -> f870f35280fadaf3c3539ad54e3062cd | N60: =IF(AND(NOT(ISBLANK(Table1[[#This Row],[Subcategory]])),NOT(_xlfn.XLOOKUP(Table1[[#This Row],[Subcategory]],SubcategoriesTable[Subcategory name],SubcategoriesTable[ID])=0)),_xlfn.XLOOKUP(Table1[[#This Row],[Subcategory]],SubcategoriesTable[Subcategory name],SubcategoriesTable[ID]),"") | O60: {=IFERROR(INDEX(CategoriesTable[Category type],MATCH(Table1[[#This Row],[Category]],CategoriesTable[Category name],0),0),"")} -> Expense | P60: 20 | Q60: =MONTH(Table1[[#This Row],[Date]]) -> 12 | R60: 2021 | S60: =IF(ISBLANK(Table1[[#This Row],[Date]]),"",Table1[[#This Row],[Date]]-WEEKDAY(Table1[[#This Row],[Date]],2)+1) -> 44550 | T60: =IF(ISBLANK(Table1[[#This Row],[Date]]),"",DATE(Table1[[#This Row],[Date_Year]],Table1[[#This Row],[Date_Month]],1)) -> 44531
B61: 44550 | C61: Prep & Pastry | D61: Recreational & Entertainment | E61: Resteraunts | F61: -34.04 | G61: =_xlfn.XLOOKUP(Table1[[#This Row],[Account_ID]], Accounts[ID], Accounts[Account nickname], "Unknown") -> Discover | H61: =_xlfn.XLOOKUP(Table1[[#This Row],[Account_ID]], Accounts[ID], Accounts[Account'#], "Unknown") -> 4618 | I61: =_xlfn.XLOOKUP(_xlfn.XLOOKUP(Table1[[#This Row],[Account]],Accounts[Account nickname],Accounts[Institution ID]),Institutions[ID],Institutions[Institution nickname],"Unknown") -> Discover | J61: aa428a24c52d469188a92d3442f07301 | K61: 0048d75f4d1d47f3b69428db4a68f3dd | L61: d09d1b66884d43439b5dad982b7d9e52 | M61: =IF(NOT(_xlfn.XLOOKUP(Table1[[#This Row],[Category]],CategoriesTable[Category name],CategoriesTable[ID])=0),_xlfn.XLOOKUP(Table1[[#This Row],[Category]],CategoriesTable[Category name],CategoriesTable[ID]),_xlfn.XLOOKUP("Uncategorized",CategoriesTable[Category name],CategoriesTable[ID])) -> f870f35280fadaf3c3539ad54e3062cd | N61: =IF(AND(NOT(ISBLANK(Table1[[#This Row],[Subcategory]])),NOT(_xlfn.XLOOKUP(Table1[[#This Row],[Subcategory]],SubcategoriesTable[Subcategory name],SubcategoriesTable[ID])=0)),_xlfn.XLOOKUP(Table1[[#This Row],[Subcategory]],SubcategoriesTable[Subcategory name],SubcategoriesTable[ID]),"") -> 500e6ba7cba37a7a2a33da8c057b4cb8 | O61: {=IFERROR(INDEX(CategoriesTable[Category type],MATCH(Table1[[#This Row],[Category]],CategoriesTable[Category name],0),0),"")} -> Expense | P61: 20 | Q61: =MONTH(Table1[[#This Row],[Date]]) -> 12 | R61: 2021 | S61: =IF(ISBLANK(Table1[[#This Row],[Date]]),"",Table1[[#This Row],[Date]]-WEEKDAY(Table1[[#This Row],[Date]],2)+1) -> 44550 | T61: =IF(ISBLANK(Table1[[#This Row],[Date]]),"",DATE(Table1[[#This Row],[Date_Year]],Table1[[#This Row],[Date_Month]],1)) -> 44531
B62: 44550 | C62: Interest Charge On Purchases | D62: Uncategorized | F62: 0 | G62: =_xlfn.XLOOKUP(Table1[[#This Row],[Account_ID]], Accounts[ID], Accounts[Account nickname], "Unknown") -> BB | H62: =_xlfn.XLOOKUP(Table1[[#This Row],[Account_ID]], Accounts[ID], Accounts[Account'#], "Unknown") -> 4561 | I62: =_xlfn.XLOOKUP(_xlfn.XLOOKUP(Table1[[#This Row],[Account]],Accounts[Account nickname],Accounts[Institution ID]),Institutions[ID],Institutions[Institution nickname],"Unknown") -> Best Buy - Citi Card | J62: a7830dbe4c0b4ad88deb3d383a0daf84 | K62: a82d9aba872e4e9b9684a363d4cc52b5 | L62: e7a999902ffc4e26bd6b6c2d4214aabd | M62: =IF(NOT(_xlfn.XLOOKUP(Table1[[#This Row],[Category]],CategoriesTable[Category name],CategoriesTable[ID])=0),_xlfn.XLOOKUP(Table1[[#This Row],[Category]],CategoriesTable[Category name],CategoriesTable[ID]),_xlfn.XLOOKUP("Uncategorized",CategoriesTable[Category name],CategoriesTable[ID])) -> de9b1d2511bc45a9bb2d484aa9e33b31 | N62: =IF(AND(NOT(ISBLANK(Table1[[#This Row],[Subcategory]])),NOT(_xlfn.XLOOKUP(Table1[[#This Row],[Subcategory]],SubcategoriesTable[Subcategory name],SubcategoriesTable[ID])=0)),_xlfn.XLOOKUP(Table1[[#This Row],[Subcategory]],SubcategoriesTable[Subcategory name],SubcategoriesTable[ID]),"") | O62: {=IFERROR(INDEX(CategoriesTable[Category type],MATCH(Table1[[#This Row],[Category]],CategoriesTable[Category name],0),0),"")} -> Expense | P62: 20 | Q62: =MONTH(Table1[[#This Row],[Date]]) -> 12 | R62: 2021 | S62: =IF(ISBLANK(Table1[[#This Row],[Date]]),"",Table1[[#This Row],[Date]]-WEEKDAY(Table1[[#This Row],[Date]],2)+1) -> 44550 | T62: =IF(ISBLANK(Table1[[#This Row],[Date]]),"",DATE(Table1[[#This Row],[Date_Year]],Table1[[#This Row],[Date_Month]],1)) -> 44531
B63: 44550 | C63: Interest Charge On Cash | D63: Uncategorized | F63: 0 | G63: =_xlfn.XLOOKUP(Table1[[#This Row],[Account_ID]], Accounts[ID], Accounts[Account nickname], "Unknown") -> BB | H63: =_xlfn.XLOOKUP(Table1[[#This Row],[Account_ID]], Accounts[ID], Accounts[Account'#], "Unknown") -> 4561 | I63: =_xlfn.XLOOKUP(_xlfn.XLOOKUP(Table1[[#This Row],[Account]],Accounts[Account nickname],Accounts[Institution ID]),Institutions[ID],Institutions[Institution nickname],"Unknown") -> Best Buy - Citi Card | J63: 8c8758c46f05406a9478c77924c4f4f4 | K63: a82d9aba872e4e9b9684a363d4cc52b5 | L63: e7a999902ffc4e26bd6b6c2d4214aabd | M63: =IF(NOT(_xlfn.XLOOKUP(Table1[[#This Row],[Category]],CategoriesTable[Category name],CategoriesTable[ID])=0),_xlfn.XLOOKUP(Table1[[#This Row],[Category]],CategoriesTable[Category name],CategoriesTable[ID]),_xlfn.XLOOKUP("Uncategorized",CategoriesTable[Category name],CategoriesTable[ID])) -> de9b1d2511bc45a9bb2d484aa9e33b31 | N63: =IF(AND(NOT(ISBLANK(Table1[[#This Row],[Subcategory]])),NOT(_xlfn.XLOOKUP(Table1[[#This Row],[Subcategory]],SubcategoriesTable[Subcategory name],SubcategoriesTable[ID])=0)),_xlfn.XLOOKUP(Table1[[#This Row],[Subcategory]],SubcategoriesTable[Subcategory name],SubcategoriesTable[ID]),"") | O63: {=IFERROR(INDEX(CategoriesTable[Category type],MATCH(Table1[[#This Row],[Category]],CategoriesTable[Category name],0),0),"")} -> Expense | P63: 20 | Q63: =MONTH(Table1[[#This Row],[Date]]) -> 12 | R63: 2021 | S63: =IF(ISBLANK(Table1[[#This Row],[Date]]),"",Table1[[#This Row],[Date]]-WEEKDAY(Table1[[#This Row],[Date]],2)+1) -> 44550 | T63: =IF(ISBLANK(Table1[[#This Row],[Date]]),"",DATE(Table1[[#This Row],[Date_Year]],Table1[[#This Row],[Date_Month]],1)) -> 44531
B64: 44550 | C64: Paypal Inst Xfer Steam | D64: Recreational & Entertainment | E64: Video Games | F64: -29.99 | G64: =_xlfn.XLOOKUP(Table1[[#This Row],[Account_ID]], Accounts[ID], Accounts[Account nickname], "Unknown") -> WF | H64: =_xlfn.XLOOKUP(Table1[[#This Row],[Account_ID]], Accounts[ID], Accounts[Account'#], "Unknown") -> 4636 | I64: =_xlfn.XLOOKUP(_xlfn.XLOOKUP(Table1[[#This Row],[Account]],Accounts[Account nickname],Accounts[Institution ID]),Institutions[ID],Institutions[Institution nickname],"Unknown") -> Wells Fargo | J64: 2f8ba1ac6c4b403789e354ade283542d | K64: 4918dbe6db3e4b9384fdfe7083417a5f | L64: 8b5374947e1d46e7a0f86b54ee722e44 | M64: =IF(NOT(_xlfn.XLOOKUP(Table1[[#This Row],[Category]],CategoriesTable[Category name],CategoriesTable[ID])=0),_xlfn.XLOOKUP(Table1[[#This Row],[Category]],CategoriesTable[Category name],CategoriesTable[ID]),_xlfn.XLOOKUP("Uncategorized",CategoriesTable[Category name],CategoriesTable[ID])) -> f870f35280fadaf3c3539ad54e3062cd | N64: =IF(AND(NOT(ISBLANK(Table1[[#This Row],[Subcategory]])),NOT(_xlfn.XLOOKUP(Table1[[#This Row],[Subcategory]],SubcategoriesTable[Subcategory name],SubcategoriesTable[ID])=0)),_xlfn.XLOOKUP(Table1[[#This Row],[Subcategory]],SubcategoriesTable[Subcategory name],SubcategoriesTable[ID]),"") -> 9cd371244b15c28471085d92021aa420 | O64: {=IFERROR(INDEX(CategoriesTable[Category type],MATCH(Table1[[#This Row],[Category]],CategoriesTable[Category name],0),0),"")} -> Expense | P64: 20 | Q64: =MONTH(Table1[[#This Row],[Date]]) -> 12 | R64: 2021 | S64: =IF(ISBLANK(Table1[[#This Row],[Date]]),"",Table1[[#This Row],[Date]]-WEEKDAY(Table1[[#This Row],[Date]],2)+1) -> 44550 | T64: =IF(ISBLANK(Table1[[#This Row],[Date]]),"",DATE(Table1[[#This Row],[Date_Year]],Table1[[#This Row],[Date_Month]],1)) -> 44531
B65: 44550 | C65: Usps Po | D65: Personal Spending | E65: Gifts/Donations | F65: -4.06 | G65: =_xlfn.XLOOKUP(Table1[[#This Row],[Account_ID]], Accounts[ID], Accounts[Account nickname], "Unknown") -> Discover | H65: =_xlfn.XLOOKUP(Table1[[#This Row],[Account_ID]], Accounts[ID], Accounts[Account'#], "Unknown") -> 4618 | I65: =_xlfn.XLOOKUP(_xlfn.XLOOKUP(Table1[[#This Row],[Account]],Accounts[Account nickname],Accounts[Institution ID]),Institutions[ID],Institutions[Institution nickname],"Unknown") -> Discover | J65: 0cb38e83b0b8455b99de06ff350e9b37 | K65: 0048d75f4d1d47f3b69428db4a68f3dd | L65: d09d1b66884d43439b5dad982b7d9e52 | M65: =IF(NOT(_xlfn.XLOOKUP(Table1[[#This Row],[Category]],CategoriesTable[Category name],CategoriesTable[ID])=0),_xlfn.XLOOKUP(Table1[[#This Row],[Category]],CategoriesTable[Category name],CategoriesTable[ID]),_xlfn.XLOOKUP("Uncategorized",CategoriesTable[Category name],CategoriesTable[ID])) -> f9fd776a16da81a948d166fcd5952d14 | N65: =IF(AND(NOT(ISBLANK(Table1[[#This Row],[Subcategory]])),NOT(_xlfn.XLOOKUP(Table1[[#This Row],[Subcategory]],SubcategoriesTable[Subcategory name],SubcategoriesTable[ID])=0)),_xlfn.XLOOKUP(Table1[[#This Row],[Subcategory]],SubcategoriesTable[Subcategory name],SubcategoriesTable[ID]),"") -> 184c9cbdd77dcd3cf895b482a60b53ae | O65: {=IFERROR(INDEX(CategoriesTable[Category type],MATCH(Table1[[#This Row],[Category]],CategoriesTable[Category name],0),0),"")} -> Expense | P65: 20 | Q65: =MONTH(Table1[[#This Row],[Date]]) -> 12 | R65: 2021 | S65: =IF(ISBLANK(Table1[[#This Row],[Date]]),"",Table1[[#This Row],[Date]]-WEEKDAY(Table1[[#This Row],[Date]],2)+1) -> 44550 | T65: =IF(ISBLANK(Table1[[#This Row],[Date]]),"",DATE(Table1[[#This Row],[Date_Year]],Table1[[#This Row],[Date_Month]],1)) -> 44531
B66: 44549 | C66: 5Guys Qsr | D66: Recreational & Entertainment | E66: Resteraunts | F66: -17.78 | G66: =_xlfn.XLOOKUP(Table1[[#This Row],[Account_ID]], Accounts[ID], Accounts[Account nickname], "Unknown") -> Discover | H66: =_xlfn.XLOOKUP(Table1[[#This Row],[Account_ID]], Accounts[ID], Accounts[Account'#], "Unknown") -> 4618 | I66: =_xlfn.XLOOKUP(_xlfn.XLOOKUP(Table1[[#This Row],[Account]],Accounts[Account nickname],Accounts[Institution ID]),Institutions[ID],Institutions[Institution nickname],"Unknown") -> Discover | J66: 6dafdb18dbe34033af0bc9a73b76a32f | K66: 0048d75f4d1d47f3b69428db4a68f3dd | L66: d09d1b66884d43439b5dad982b7d9e52 | M66: =IF(NOT(_xlfn.XLOOKUP(Table1[[#This Row],[Category]],CategoriesTable[Category name],CategoriesTable[ID])=0),_xlfn.XLOOKUP(Table1[[#This Row],[Category]],CategoriesTable[Category name],CategoriesTable[ID]),_xlfn.XLOOKUP("Uncategorized",CategoriesTable[Category name],CategoriesTable[ID])) -> f870f35280fadaf3c3539ad54e3062cd | N66: =IF(AND(NOT(ISBLANK(Table1[[#This Row],[Subcategory]])),NOT(_xlfn.XLOOKUP(Table1[[#This Row],[Subcategory]],SubcategoriesTable[Subcategory name],SubcategoriesTable[ID])=0)),_xlfn.XLOOKUP(Table1[[#This Row],[Subcategory]],SubcategoriesTable[Subcategory name],SubcategoriesTable[ID]),"") -> 500e6ba7cba37a7a2a33da8c057b4cb8 | O66: {=IFERROR(INDEX(CategoriesTable[Category type],MATCH(Table1[[#This Row],[Category]],CategoriesTable[Category name],0),0),"")} -> Expense | P66: 19 | Q66: =MONTH(Table1[[#This Row],[Date]]) -> 12 | R66: 2021 | S66: =IF(ISBLANK(Table1[[#This Row],[Date]]),"",Table1[[#This Row],[Date]]-WEEKDAY(Table1[[#This Row],[Date]],2)+1) -> 44543 | T66: =IF(ISBLANK(Table1[[#This Row],[Date]]),"",DATE(Table1[[#This Row],[Date_Year]],Table1[[#This Row],[Date_Month]],1)) -> 44531
B67: 44549 | C67: Ups | D67: Personal Spending | F67: -50.62 | G67: =_xlfn.XLOOKUP(Table1[[#This Row],[Account_ID]], Accounts[ID], Accounts[Account nickname], "Unknown") -> Discover | H67: =_xlfn.XLOOKUP(Table1[[#This Row],[Account_ID]], Accounts[ID], Accounts[Account'#], "Unknown") -> 4618 | I67: =_xlfn.XLOOKUP(_xlfn.XLOOKUP(Table1[[#This Row],[Account]],Accounts[Account nickname],Accounts[Institution ID]),Institutions[ID],Institutions[Institution nickname],"Unknown") -> Discover | J67: 613693300b614d358e7729c1860ec5e5 | K67: 0048d75f4d1d47f3b69428db4a68f3dd | L67: d09d1b66884d43439b5dad982b7d9e52 | M67: =IF(NOT(_xlfn.XLOOKUP(Table1[[#This Row],[Category]],CategoriesTable[Category name],CategoriesTable[ID])=0),_xlfn.XLOOKUP(Table1[[#This Row],[Category]],CategoriesTable[Category name],CategoriesTable[ID]),_xlfn.XLOOKUP("Uncategorized",CategoriesTable[Category name],CategoriesTable[ID])) -> f9fd776a16da81a948d166fcd5952d14 | N67: =IF(AND(NOT(ISBLANK(Table1[[#This Row],[Subcategory]])),NOT(_xlfn.XLOOKUP(Table1[[#This Row],[Subcategory]],SubcategoriesTable[Subcategory name],SubcategoriesTable[ID])=0)),_xlfn.XLOOKUP(Table1[[#This Row],[Subcategory]],SubcategoriesTable[Subcategory name],SubcategoriesTable[ID]),"") | O67: {=IFERROR(INDEX(CategoriesTable[Category type],MATCH(Table1[[#This Row],[Category]],CategoriesTable[Category name],0),0),"")} -> Expense | P67: 19 | Q67: =MONTH(Table1[[#This Row],[Date]]) -> 12 | R67: 2021 | S67: =IF(ISBLANK(Table1[[#This Row],[Date]]),"",Table1[[#This Row],[Date]]-WEEKDAY(Table1[[#This Row],[Date]],2)+1) -> 44543 | T67: =IF(ISBLANK(Table1[[#This Row],[Date]]),"",DATE(Table1[[#This Row],[Date_Year]],Table1[[#This Row],[Date_Month]],1)) -> 44531
B68: 44549 | C68: Desert Botanical Garde Phoenix | D68: Recreational & Entertainment | E68: Family Activities | F68: -265 | G68: =_xlfn.XLOOKUP(Table1[[#This Row],[Account_ID]], Accounts[ID], Accounts[Account nickname], "Unknown") -> Discover | H68: =_xlfn.XLOOKUP(Table1[[#This Row],[Account_ID]], Accounts[ID], Accounts[Account'#], "Unknown") -> 4618 | I68: =_xlfn.XLOOKUP(_xlfn.XLOOKUP(Table1[[#This Row],[Account]],Accounts[Account nickname],Accounts[Institution ID]),Institutions[ID],Institutions[Institution nickname],"Unknown") -> Discover | J68: 61305873f0e94ec99b1f8edbe336c4ce | K68: 0048d75f4d1d47f3b69428db4a68f3dd | L68: d09d1b66884d43439b5dad982b7d9e52 | M68: =IF(NOT(_xlfn.XLOOKUP(Table1[[#This Row],[Category]],CategoriesTable[Category name],CategoriesTable[ID])=0),_xlfn.XLOOKUP(Table1[[#This Row],[Category]],CategoriesTable[Category name],CategoriesTable[ID]),_xlfn.XLOOKUP("Uncategorized",CategoriesTable[Category name],CategoriesTable[ID])) -> f870f35280fadaf3c3539ad54e3062cd | N68: =IF(AND(NOT(ISBLANK(Table1[[#This Row],[Subcategory]])),NOT(_xlfn.XLOOKUP(Table1[[#This Row],[Subcategory]],SubcategoriesTable[Subcategory name],SubcategoriesTable[ID])=0)),_xlfn.XLOOKUP(Table1[[#This Row],[Subcategory]],SubcategoriesTable[Subcategory name],SubcategoriesTable[ID]),"") -> b33a143786e5accb584d33cda08d2b69 | O68: {=IFERROR(INDEX(CategoriesTable[Category type],MATCH(Table1[[#This Row],[Category]],CategoriesTable[Category name],0),0),"")} -> Expense | P68: 19 | Q68: =MONTH(Table1[[#This Row],[Date]]) -> 12 | R68: 2021 | S68: =IF(ISBLANK(Table1[[#This Row],[Date]]),"",Table1[[#This Row],[Date]]-WEEKDAY(Table1[[#This Row],[Date]],2)+1) -> 44543 | T68: =IF(ISBLANK(Table1[[#This Row],[Date]]),"",DATE(Table1[[#This Row],[Date_Year]],Table1[[#This Row],[Date_Month]],1)) -> 44531
