Workbook
Name allowance: #REF!
Name AprSun1: DATE(CalendarYear,4,1)-WEEKDAY(DATE(CalendarYear,4,1))
Name AugSun1: DATE(CalendarYear,8,1)-WEEKDAY(DATE(CalendarYear,8,1))
Name budget: '[1]Pivot (2021)'!$A$2
Name Budget: #REF!
Name CalendarYear: [0]!Year1
Name Categories: [2]!TableAssetAllocation[Category]
Name DecSun1: DATE(CalendarYear,12,1)-WEEKDAY(DATE(CalendarYear,12,1))
Name Expense_Categories: 'Categories - WIP'!$A$2:$A$12
Name Expense_Lookup: Discover!$Q:$R
Name FebSun1: DATE(CalendarYear,2,1)-WEEKDAY(DATE(CalendarYear,2,1))
Name fixed: #REF!
Name income: #REF!
Name JanSun1: DATE(CalendarYear,1,1)-WEEKDAY(DATE(CalendarYear,1,1))
Name JulSun1: DATE(CalendarYear,7,1)-WEEKDAY(DATE(CalendarYear,7,1))
Name JunSun1: DATE(CalendarYear,6,1)-WEEKDAY(DATE(CalendarYear,6,1))
Name LastCol: COUNTA('PERSONAL BUDGET - WIP'!$4:$4)+1
Name MarSun1: DATE(CalendarYear,3,1)-WEEKDAY(DATE(CalendarYear,3,1))
Name MaySun1: DATE(CalendarYear,5,1)-WEEKDAY(DATE(CalendarYear,5,1))
Name NovSun1: DATE(CalendarYear,11,1)-WEEKDAY(DATE(CalendarYear,11,1))
Name OctSun1: DATE(CalendarYear,10,1)-WEEKDAY(DATE(CalendarYear,10,1))
Name PrintArea_SET: OFFSET('PERSONAL BUDGET - WIP'!$C$2,,,MATCH(REPT("z",255),'PERSONAL BUDGET - WIP'!$C:$C),LastCol)
Name Robinhood: #REF!
Name SepSun1: DATE(CalendarYear,9,1)-WEEKDAY(DATE(CalendarYear,9,1))
Name StartMonth: #REF!
Name Tail_Rent: '[1]2021 Income'!#REF!
Name Title2: #REF!
Name valdate: #REF!
Name Year1: VALUE(LEFT(#REF!,4))

Sheet Wells Fargo
A1: Month | B1: Day | C1: Date | D1: Description2 | E1: Description | F1: Amount | G1: Primary
A2: =MONTH(C2) -> 1 | B2: =DAY(C2) -> 4 | C2: 44200 | D2: DISCOVER | E2: DISCOVER E-PAYMENT 210101 4732 LEWIS SEAN | F2: -700 | G2: Credit
A3: =MONTH(C3) -> 1 | B3: =DAY(C3) -> 4 | C3: 44200 | D3: IRS | E3: IRS TREAS 310 XXTAXEIP2 010421 XXXXXXXXXX00908 LEWIS, SEAN | F3: 600 | G3: Stimulus 1
A4: =MONTH(C4) -> 1 | B4: =DAY(C4) -> 15 | C4: 44211 | D4: DISCOVER | E4: DISCOVER E-PAYMENT 210115 4732 LEWIS SEAN | F4: -729.23 | G4: Credit
A5: =MONTH(C5) -> 1 | B5: =DAY(C5) -> 15 | C5: 44211 | D5: Elephant | E5: Elephant Ins PAYROLL 210113 2087 Lewis Sean | F5: 1459.65 | G5: Elephant
A6: =MONTH(C6) -> 1 | B6: =DAY(C6) -> 19 | C6: 44215 | D6: VENMO | E6: VENMO PAYMENT 5101219782 SEAN LEWIS | F6: -569.12 | G6: Vincent
A7: =MONTH(C7) -> 1 | B7: =DAY(C7) -> 19 | C7: 44215 | D7: VENMO | E7: VENMO PAYMENT 5101208453 SEAN LEWIS | F7: -78.86 | G7: Amar - Electric
A8: =MONTH(C8) -> 1 | B8: =DAY(C8) -> 19 | C8: 44215 | D8: VENMO | E8: VENMO CASHOUT 5117912825 SEAN LEWIS | F8: 150 | G8: Venmo Cash Out
A9: =MONTH(C9) -> 1 | B9: =DAY(C9) -> 21 | C9: 44217 | D9: PURCHASE | E9: PURCHASE AUTHORIZED ON 01/20 CASH APP* 8774174551 CA S461020486646597 CARD 6634 | F9: -155 | G9: Cairo
A10: =MONTH(C10) -> 1 | B10: =DAY(C10) -> 22 | C10: 44218 | D10: PURCHASE | E10: PURCHASE AUTHORIZED ON 01/21 SOCIETY OF ACTUARI 847-706-3620 IL S581021446560343 CARD 6634 | F10: -75 | G10: SOA
A11: =MONTH(C11) -> 1 | B11: =DAY(C11) -> 26 | C11: 44222 | D11: MONEY | E11: MONEY TRANSFER AUTHORIZED ON 01/26 FROM Sean Lewis VA S00581026542833832 CARD 6634 | F11: 155 | G11: Cairo
A12: =MONTH(C12) -> 1 | B12: =DAY(C12) -> 28 | C12: 44224 | D12: ROBINHOOD | E12: ROBINHOOD Funds 210127 XXXXX4480 Sean Lewis | F12: -100 | G12: Investment
A13: =MONTH(C13) -> 1 | B13: =DAY(C13) -> 28 | C13: 44224 | D13: ROBINHOOD | E13: ROBINHOOD Funds 210127 XXXXX4480 Sean Lewis | F13: -50 | G13: Investment
... A127: =MONTH(C127) -> 6 | B127: =DAY(C127) -> 17 | C127: 44364 | D127: Nationwide | E127: Nationwide PAYROLL 01 HRP0007397914 Sean Lewis | F127: 4436.57 | G127: Nationwide
A128: =MONTH(C128) -> 6 | B128: =DAY(C128) -> 18 | C128: 44365 | D128: =LEFT(E128, FIND(" ",E128)-1) -> PRINCIPAL | E128: PRINCIPAL TRUST DR CR 210617 PACT#179541394 SEAN LEWIS | F128: 3967.1 | G128: Principal retirement
A129: =MONTH(C129) -> 6 | B129: =DAY(C129) -> 18 | C129: 44365 | D129: =LEFT(E129, FIND(" ",E129)-1) -> Elephant | E129: Elephant Ins PAYROLL 210616 2087 Lewis Sean | F129: 680.02 | G129: Elephant
A130: =MONTH(C130) -> 6 | B130: =DAY(C130) -> 21 | C130: 44368 | D130: =LEFT(E130, FIND(" ",E130)-1) -> VENMO | E130: VENMO PAYMENT 210620 1014291472980 SEAN LEWIS | F130: -2738.5 | G130: Matt Bozz
A131: =MONTH(C131) -> 6 | B131: =DAY(C131) -> 21 | C131: 44368 | D131: =LEFT(E131, FIND(" ",E131)-1) -> VENMO | E131: VENMO PAYMENT 210620 1014291497592 SEAN LEWIS | F131: -615 | G131: Anush Rohani Shukla
A132: =MONTH(C132) -> 6 | B132: =DAY(C132) -> 23 | C132: 44370 | D132: =LEFT(E132, FIND(" ",E132)-1) -> DISCOVER | E132: DISCOVER E-PAYMENT 210623 7328 LEWIS SEAN | F132: -1869 | G132: Credit
A133: =MONTH(C133) -> 6 | B133: =DAY(C133) -> 23 | C133: 44370 | D133: =LEFT(E133, FIND(" ",E133)-1) -> PURCHASE | E133: PURCHASE AUTHORIZED ON 06/22 STITCH FIX STYLIN 844-386-3850 CA S581173332274659 CARD 6634 | F133: -20 | G133: Headshot
A134: =MONTH(C134) -> 6 | B134: =DAY(C134) -> 23 | C134: 44370 | D134: =LEFT(E134, FIND(" ",E134)-1) -> PRINCIPAL | E134: PRINCIPAL TRUST DR CR 210622 PACT#180033360 Sean Lewis | F134: 198.46 | G134: Principal retirement
A135: =MONTH(C135) -> 6 | B135: =DAY(C135) -> 25 | C135: 44372 | D135: =LEFT(E135, FIND(" ",E135)-1) -> PURCHASE | E135: PURCHASE AUTHORIZED ON 06/23 TST* TIO PABLO TAQ RICHMOND VA S461175013934521 CARD 6634 | F135: -58.57 | G135: Resteraunt
A136: =MONTH(C136) -> 6 | B136: =DAY(C136) -> 30 | C136: 44377 | D136: =LEFT(E136, FIND(" ",E136)-1) -> New | E136: New Manchester F WEB PMTS 063021 M7CVM7 Sean Lewis | F136: -1804.34 | G136: New Manchester - Rent
A137: =MONTH(C137) -> 7 | B137: =DAY(C137) -> 1 | C137: 44378 | D137: =LEFT(E137, FIND(" ",E137)-1) -> DISCOVER | E137: DISCOVER E-PAYMENT 210701 7328 LEWIS SEAN | F137: -871.96 | G137: Credit
A138: =MONTH(C138) -> 7 | B138: =DAY(C138) -> 1 | C138: 44378 | D138: =LEFT(E138, FIND(" ",E138)-1) -> Nationwide | E138: Nationwide PAYROLL 01 HRP0007447918 Sean Lewis | F138: 1583.62 | G138: Nationwide
A139: =MONTH(C139) -> 7 | B139: =DAY(C139) -> 6 | C139: 44383 | D139: =LEFT(E139, FIND(" ",E139)-1) -> DISCOVER | E139: DISCOVER E-PAYMENT 210705 7328 LEWIS SEAN | F139: -367.73 | G139: Credit
... A215: =MONTH(C215) -> 10 | B215: =DAY(C215) -> 1 | C215: 44470 | D215: =LEFT(E215, FIND(" ",E215)-1) -> VENMO | E215: VENMO PAYMENT 211001 1016029881790 SEAN LEWIS | F215: -1866.67 | G215: Rent - Artisan Village
A216: =MONTH(C216) -> 10 | B216: =DAY(C216) -> 4 | C216: 44473 | D216: =LEFT(E216, FIND(" ",E216)-1) -> VENMO | E216: VENMO PAYMENT 211003 1016066822276 SEAN LEWIS | F216: -155
A217: =MONTH(C217) -> 10 | B217: =DAY(C217) -> 5 | C217: 44474 | D217: =LEFT(E217, FIND(" ",E217)-1) -> MONEY | E217: MONEY TRANSFER AUTHORIZED ON 10/05 FROM Sean Lewis VA S00301278504520063 CARD 6634 | F217: 170
A218: =MONTH(C218) -> 10 | B218: =DAY(C218) -> 5 | C218: 44474 | D218: =LEFT(E218, FIND(" ",E218)-1) -> MONEY | E218: MONEY TRANSFER AUTHORIZED ON 10/05 FROM Sean Lewis VA S00461278489165227 CARD 6634 | F218: 100
A219: =MONTH(C219) -> 10 | B219: =DAY(C219) -> 7 | C219: 44476 | D219: =LEFT(E219, FIND(" ",E219)-1) -> Nationwide | E219: Nationwide PAYROLL 01 HRP0007713476 Sean Lewis | F219: 2029.34 | G219: Nationwide
A220: =MONTH(C220) -> 10 | B220: =DAY(C220) -> 8 | C220: 44477 | D220: =LEFT(E220, FIND(" ",E220)-1) -> BEST | E220: BEST BUY PAYMENT 211007 610557584343627 SEAN LEWIS | F220: -2378.52
A221: =MONTH(C221) -> 10 | B221: =DAY(C221) -> 12 | C221: 44481 | D221: =LEFT(E221, FIND(" ",E221)-1) -> APS | E221: APS electric pmt PAYMENT 211008 5175354092 Lewis,Sean | F221: -14.71 | G221: APS
A222: =MONTH(C222) -> 10 | B222: =DAY(C222) -> 12 | C222: 44481 | D222: =LEFT(E222, FIND(" ",E222)-1) -> PURCHASE | E222: PURCHASE AUTHORIZED ON 10/11 WAL-MART #2515 PHOENIX AZ P00000000177097893 CARD 6634 | F222: -34.43
A223: =MONTH(C223) -> 10 | B223: =DAY(C223) -> 12 | C223: 44481 | D223: =LEFT(E223, FIND(" ",E223)-1) -> PURCHASE | E223: PURCHASE AUTHORIZED ON 10/08 CASH APP*SHEVON LE 8774174551 CA S381281823108419 CARD 6634 | F223: -350 | G223: Shevon
A224: =MONTH(C224) -> 10 | B224: =DAY(C224) -> 12 | C224: 44481 | D224: =LEFT(E224, FIND(" ",E224)-1) -> FIDELITY | E224: FIDELITY 10077 P FIDELITY 10077 XXXXX0268 SEAN LEWIS | F224: 1201.6 | G224: Fidelity Retirement
A225: =MONTH(C225) -> 10 | B225: =DAY(C225) -> 18 | C225: 44487 | D225: =LEFT(E225, FIND(" ",E225)-1) -> VENMO | E225: VENMO PAYMENT 211018 1016334480094 SEAN LEWIS | F225: -50 | G225: ZZZ
A226: =MONTH(C226) -> 10 | B226: =DAY(C226) -> 20 | C226: 44489 | D226: =LEFT(E226, FIND(" ",E226)-1) -> TRANSFER | E226: TRANSFER FROM LEWIS SHARON ON 10/20 REF # PP0CNS6J5C PURCHASE OF HOME OFFICE AND PROTECTION | F226: 377.98 | G226: Mom
A227: =MONTH(C227) -> 10 | B227: =DAY(C227) -> 20 | C227: 44489 | D227: =LEFT(E227, FIND(" ",E227)-1) -> TRANSFER | E227: TRANSFER FROM LEWIS SHARON ON 10/20 REF # PP0CNS6836 FOR LENOVO COMPUTER PURCHASE | F227: 812.12 | G227: Mom
A228: =MONTH(C228) -> 10 | B228: =DAY(C228) -> 21 | C228: 44490 | D228: =LEFT(E228, FIND(" ",E228)-1) -> VENMO | E228: VENMO PAYMENT 211021 1016376963889 SEAN LEWIS | F228: -1682.31 | G228: ZZZ
A229: =MONTH(C229) -> 10 | B229: =DAY(C229) -> 21 | C229: 44490 | D229: =LEFT(E229, FIND(" ",E229)-1) -> Nationwide | E229: Nationwide PAYROLL 01 HRP0007754254 Sean Lewis | F229: 1900.88 | G229: Nationwide
A230: =MONTH(C230) -> 10 | B230: =DAY(C230) -> 25 | C230: 44494 | D230: =LEFT(E230, FIND(" ",E230)-1) -> VENMO | E230: VENMO PAYMENT 211022 1016404945098 SEAN LEWIS | F230: -75.26 | G230: ZZZ
A231: =MONTH(C231) -> 10 | B231: =DAY(C231) -> 29 | C231: 44498 | D231: =LEFT(E231, FIND(" ",E231)-1) -> LIFETIME | E231: LIFETIME FITNESS DIRECT DEP 211029 928121133367SHS LEWIS,SEAN | F231: 21.88 | G231: Life Time
A232: =MONTH(C232) -> 11 | B232: =DAY(C232) -> 1 | C232: 44501 | D232: =LEFT(E232, FIND(" ",E232)-1) -> VENMO | E232: VENMO PAYMENT 211031 1016549315705 SEAN LEWIS | F232: -1676.72 | G232: Rent - Artisan Village
A233: =MONTH(C233) -> 11 | B233: =DAY(C233) -> 3 | C233: 44503 | D233: =LEFT(E233, FIND(" ",E233)-1) -> DISCOVER | E233: DISCOVER E-PAYMENT 211103 7328 LEWIS SEAN | F233: -1000 | G233: Credit
A234: =MONTH(C234) -> 11 | B234: =DAY(C234) -> 3 | C234: 44503 | D234: =LEFT(E234, FIND(" ",E234)-1) -> APS | E234: APS electric pmt PAYMENT 211101 5175354092 Lewis,Sean | F234: -166.33 | G234: APS
... A242: =MONTH(C242) -> 11 | B242: =DAY(C242) -> 15 | C242: 44515 | D242: =LEFT(E242, FIND(" ",E242)-1) -> ATM | E242: ATM WITHDRAWAL AUTHORIZED ON 11/14 100 W Washington St Phoenix AZ 0005789 ATM ID 2203H CARD 6634 | F242: -300 | G242: ZZZ

Sheet Discover
A1: Year | B1: Month | C1: Trans. date | D1: Post date | E1: Description | F1: Amount | G1: Category | H1: Expense Type | I1: Cumulative | J1: Association | K1: Budget Main CAT
A2: =YEAR(C2) -> 2021 | B2: =MONTH(C2) -> 1 | C2: 44197 | D2: 44197 | E2: INTERNET PAYMENT - THANK YOU | F2: -700 | G2: Payments and Credits | H2: =VLOOKUP(G2,Expense_Lookup,2,0) -> Payment | I2: 728.15
A3: =YEAR(C3) -> 2021 | B3: =MONTH(C3) -> 1 | C3: 44197 | D3: 44199 | E3: NETFLIX.COM NETFLIX.COM CA44115296471 | F3: 13.99 | G3: APP | H3: =VLOOKUP(G3,Expense_Lookup,2,0) -> Fixed | I3: =I2+F3 -> 742.14 | J3: Netflix | K3: SUBSCRIPTION
A4: =YEAR(C4) -> 2021 | B4: =MONTH(C4) -> 1 | C4: 44197 | D4: 44199 | E4: SPOTIFY P12D96D434 8777781161 NY | F4: 9.99 | G4: APP | H4: =VLOOKUP(G4,Expense_Lookup,2,0) -> Fixed | I4: =I3+F4 -> 752.13 | J4: Spotify | K4: SUBSCRIPTION | N4: Variable | O4: =SUMIFS(F:F,H:H,N4) -> 25417.25 | S4: Jan | T4: Feb | U4: Mar | V4: Apr | W4: May | X4: June | Y4: July | Z4: Aug | AA4: Sep | AB4: Oct | AC4: Nov | AD4: Dec | AE4: Yearly
A5: =YEAR(C5) -> 2021 | B5: =MONTH(C5) -> 1 | C5: 44197 | D5: 44199 | E5: WAWA 697 STAFFORD VA | F5: 18.87 | G5: Gasoline | H5: =VLOOKUP(G5,Expense_Lookup,2,0) -> Variable | I5: =I4+F5 -> 771 | K5: TRANSPORTATION | N5: Fixed | O5: =SUMIFS(F:F,H:H,N5) -> 6083.78 | Q5: {=_xlfn.UNIQUE(_xlfn._xlws.FILTER(G:G,(G:G<>0) ))} -> Category
A6: =YEAR(C6) -> 2021 | B6: =MONTH(C6) -> 1 | C6: 44201 | D6: 44201 | E6: MYFICO COM 8003194433 GA | F6: 39.95 | G6: APP | H6: =VLOOKUP(G6,Expense_Lookup,2,0) -> Fixed | I6: =I5+F6 -> 810.95 | J6: Credit Score | K6: SUBSCRIPTION | O6: =SUM(O4:O5) -> 31501.03 | Q6: Payments and Credits | R6: Payment | S6: =SUMIFS(F:F,G:G,Q6,$B:$B,1) -> -2157.38 | T6: =SUMIFS(F:F,G:G,Q6,$B:$B,2) -> -2256.47 | U6: =SUMIFS(F:F,G:G,Q6,$B:$B,3) -> -2413.62 | V6: =SUMIFS($F:$F,$G:$G,$Q6,$B:$B,4) -> -471.07 | W6: =SUMIFS($F:$F,$G:$G,$Q6,$B:$B,5) -> -2855.16 | X6: =SUMIFS($F:$F,$G:$G,$Q6,$B:$B,6) -> -3297.83 | Y6: =SUMIFS($F:$F,$G:$G,$Q6,$B:$B,7) -> -6127.09 | Z6: =SUMIFS($F:$F,$G:$G,$Q6,$B:$B,8) -> -3272.24 | AA6: =SUMIFS($F:$F,$G:$G,$Q6,$B:$B,9) -> -4605.13 | AB6: =SUMIFS($F:$F,$G:$G,$Q6,$B:$B,10) -> -1714.73 | AC6: =SUMIFS($F:$F,$G:$G,$Q6,$B:$B,11) -> -3675.51
A7: =YEAR(C7) -> 2021 | B7: =MONTH(C7) -> 1 | C7: 44201 | D7: 44201 | E7: STATE FARM INSURANCE 800-956-6310 IL | F7: 91.78 | G7: APP | H7: =VLOOKUP(G7,Expense_Lookup,2,0) -> Fixed | I7: =I6+F7 -> 902.73 | J7: State Farm | K7: TRANSPORTATION | N7: Family | Q7: APP | R7: Fixed | S7: =SUMIFS(F:F,G:G,Q7,$B:$B,1) -> 190.63 | T7: =SUMIFS(F:F,G:G,Q7,$B:$B,2) -> 250.9 | U7: =SUMIFS(F:F,G:G,Q7,$B:$B,3) -> 559.85 | V7: =SUMIFS(F:F,G:G,Q7,$B:$B,4) -> 308.43 | W7: =SUMIFS($F:$F,$G:$G,$Q7,$B:$B,5) -> 592.35 | X7: =SUMIFS($F:$F,$G:$G,$Q7,$B:$B,6) -> 579.09 | Y7: =SUMIFS($F:$F,$G:$G,$Q7,$B:$B,7) -> 395.95 | Z7: =SUMIFS($F:$F,$G:$G,$Q7,$B:$B,8) -> 655.42 | AA7: =SUMIFS($F:$F,$G:$G,$Q7,$B:$B,9) -> 616.67 | AB7: =SUMIFS($F:$F,$G:$G,$Q7,$B:$B,10) -> 790.91 | AC7: =SUMIFS($F:$F,$G:$G,$Q7,$B:$B,11) -> 152.59 | AE7: =SUM(S7:AD7) -> 5092.79
A8: =YEAR(C8) -> 2021 | B8: =MONTH(C8) -> 1 | C8: 44201 | D8: 44201 | E8: STEAMPOWERED.COM 425-952-2985 WA | F8: 19.99 | G8: Merchandise | H8: =VLOOKUP(G8,Expense_Lookup,2,0) -> Variable | I8: =I7+F8 -> 922.72 | J8: Neir Automata | K8: ENTERTAINMENT | N8: Jayelin | O8: =SUMIFS(F:F,J:J,N8)+SUMIFS('Cash Flow'!$B:$B,'Cash Flow'!$A:$A,Discover!N8)*-1 -> 910.36 | Q8: Gasoline | R8: Variable | S8: =SUMIFS(F:F,G:G,Q8,$B:$B,1) -> 67.87 | T8: =SUMIFS(F:F,G:G,Q8,$B:$B,2) -> 67.47 | U8: =SUMIFS(F:F,G:G,Q8,$B:$B,3) -> 80.06 | V8: =SUMIFS(F:F,G:G,Q8,$B:$B,4) -> 125.95 | W8: =SUMIFS($F:$F,$G:$G,$Q8,$B:$B,5) -> 115.16 | X8: =SUMIFS($F:$F,$G:$G,$Q8,$B:$B,6) -> 104.56 | Y8: =SUMIFS($F:$F,$G:$G,$Q8,$B:$B,7) -> 71.41 | Z8: =SUMIFS($F:$F,$G:$G,$Q8,$B:$B,8) -> 199.88 | AA8: =SUMIFS($F:$F,$G:$G,$Q8,$B:$B,9) -> 353.18 | AB8: =SUMIFS($F:$F,$G:$G,$Q8,$B:$B,10) -> 103 | AC8: =SUMIFS($F:$F,$G:$G,$Q8,$B:$B,11) -> 0 | AE8: =SUM(S8:AD8) -> 1288.54
A9: =YEAR(C9) -> 2021 | B9: =MONTH(C9) -> 1 | C9: 44202 | D9: 44202 | E9: LIVECAREER.COM 800652843 866-933-7587 PR | F9: 24.95 | G9: Family | H9: =VLOOKUP(G9,Expense_Lookup,2,0) -> Variable | I9: =I8+F9 -> 947.67 | J9: Jayelin | K9: MISC PAYMENTS | N9: Shevon | O9: =SUMIFS(F:F,J:J,N9)+SUMIFS('Cash Flow'!$B:$B,'Cash Flow'!$A:$A,Discover!N9)*-1 -> 1624.95 | Q9: Merchandise | R9: Variable | S9: =SUMIFS(F:F,G:G,Q9,$B:$B,1) -> 434.08 | T9: =SUMIFS(F:F,G:G,Q9,$B:$B,2) -> 262.63 | U9: =SUMIFS(F:F,G:G,Q9,$B:$B,3) -> 427.64 | V9: =SUMIFS(F:F,G:G,Q9,$B:$B,4) -> 360.76 | W9: =SUMIFS($F:$F,$G:$G,$Q9,$B:$B,5) -> 645.99 | X9: =SUMIFS($F:$F,$G:$G,$Q9,$B:$B,6) -> 1136.89 | Y9: =SUMIFS($F:$F,$G:$G,$Q9,$B:$B,7) -> 1104.67 | Z9: =SUMIFS($F:$F,$G:$G,$Q9,$B:$B,8) -> 662.17 | AA9: =SUMIFS($F:$F,$G:$G,$Q9,$B:$B,9) -> 2140.89 | AB9: =SUMIFS($F:$F,$G:$G,$Q9,$B:$B,10) -> 1531.79 | AC9: =SUMIFS($F:$F,$G:$G,$Q9,$B:$B,11) -> 266.43 | AE9: =SUM(S9:AD9) -> 8973.94
A10: =YEAR(C10) -> 2021 | B10: =MONTH(C10) -> 1 | C10: 44202 | D10: 44202 | E10: RIVER RUN SHORT PUMP HENRICO VA | F10: 30 | G10: Medical Services | H10: =VLOOKUP(G10,Expense_Lookup,2,0) -> Variable | I10: =I9+F10 -> 977.67 | K10: HEALTH | N10: Don | O10: =SUMIFS(F:F,J:J,N10)+SUMIFS('Cash Flow'!$B:$B,'Cash Flow'!$A:$A,Discover!N10)*-1 -> 297.5 | Q10: Family | R10: Variable | S10: =SUMIFS(F:F,G:G,Q10,$B:$B,1) -> 172.84 | T10: =SUMIFS(F:F,G:G,Q10,$B:$B,2) -> 71.26 | U10: =SUMIFS(F:F,G:G,Q10,$B:$B,3) -> 84.95 | V10: =SUMIFS(F:F,G:G,Q10,$B:$B,4) -> 9.95 | W10: =SUMIFS($F:$F,$G:$G,$Q10,$B:$B,5) -> 91.85 | X10: =SUMIFS($F:$F,$G:$G,$Q10,$B:$B,6) -> 0 | Y10: =SUMIFS($F:$F,$G:$G,$Q10,$B:$B,7) -> 0 | Z10: =SUMIFS($F:$F,$G:$G,$Q10,$B:$B,8) -> 0 | AA10: =SUMIFS($F:$F,$G:$G,$Q10,$B:$B,9) -> 0 | AB10: =SUMIFS($F:$F,$G:$G,$Q10,$B:$B,10) -> 0 | AC10: =SUMIFS($F:$F,$G:$G,$Q10,$B:$B,11) -> 0 | AE10: =SUM(S10:AD10) -> 430.85
A11: =YEAR(C11) -> 2021 | B11: =MONTH(C11) -> 1 | C11: 44202 | D11: 44202 | E11: THE MARKET @ 25TH RICHMOND VA | F11: 24.24 | G11: Supermarkets | H11: =VLOOKUP(G11,Expense_Lookup,2,0) -> Variable | I11: =I10+F11 -> 1001.91 | K11: DAILY LIVING | N11: Dorry | O11: =SUMIFS(F:F,J:J,N11)+SUMIFS('Cash Flow'!$B:$B,'Cash Flow'!$A:$A,Discover!N11)*-1 -> 595 | Q11: Medical Services | R11: Variable | S11: =SUMIFS(F:F,G:G,Q11,$B:$B,1) -> 70.51 | T11: =SUMIFS(F:F,G:G,Q11,$B:$B,2) -> 0 | U11: =SUMIFS(F:F,G:G,Q11,$B:$B,3) -> 0 | V11: =SUMIFS(F:F,G:G,Q11,$B:$B,4) -> 0 | W11: =SUMIFS($F:$F,$G:$G,$Q11,$B:$B,5) -> 0 | X11: =SUMIFS($F:$F,$G:$G,$Q11,$B:$B,6) -> 0 | Y11: =SUMIFS($F:$F,$G:$G,$Q11,$B:$B,7) -> 0 | Z11: =SUMIFS($F:$F,$G:$G,$Q11,$B:$B,8) -> 0 | AA11: =SUMIFS($F:$F,$G:$G,$Q11,$B:$B,9) -> 0 | AB11: =SUMIFS($F:$F,$G:$G,$Q11,$B:$B,10) -> 0 | AC11: =SUMIFS($F:$F,$G:$G,$Q11,$B:$B,11) -> 0 | AE11: =SUM(S11:AD11) -> 70.51
A12: =YEAR(C12) -> 2021 | B12: =MONTH(C12) -> 1 | C12: 44203 | D12: 44203 | E12: AMERICA'S BEST WINGS HENRICO VA | F12: 12.09 | G12: Restaurants | H12: =VLOOKUP(G12,Expense_Lookup,2,0) -> Variable | I12: =I11+F12 -> 1014 | K12: DAILY LIVING | N12: Cairo | O12: =SUMIFS(F:F,J:J,N12)+SUMIFS('Cash Flow'!$B:$B,'Cash Flow'!$A:$A,Discover!N12)*-1 -> 0 | Q12: Supermarkets | R12: Variable | S12: =SUMIFS(F:F,G:G,Q12,$B:$B,1) -> 138.14 | T12: =SUMIFS(F:F,G:G,Q12,$B:$B,2) -> 247.65 | U12: =SUMIFS(F:F,G:G,Q12,$B:$B,3) -> 132.85 | V12: =SUMIFS(F:F,G:G,Q12,$B:$B,4) -> 25.32 | W12: =SUMIFS($F:$F,$G:$G,$Q12,$B:$B,5) -> 321.42 | X12: =SUMIFS($F:$F,$G:$G,$Q12,$B:$B,6) -> 100.64 | Y12: =SUMIFS($F:$F,$G:$G,$Q12,$B:$B,7) -> 328.94 | Z12: =SUMIFS($F:$F,$G:$G,$Q12,$B:$B,8) -> 114.91 | AA12: =SUMIFS($F:$F,$G:$G,$Q12,$B:$B,9) -> 192.66 | AB12: =SUMIFS($F:$F,$G:$G,$Q12,$B:$B,10) -> 218.82 | AC12: =SUMIFS($F:$F,$G:$G,$Q12,$B:$B,11) -> 103.39 | AE12: =SUM(S12:AD12) -> 1924.74
A13: =YEAR(C13) -> 2021 | B13: =MONTH(C13) -> 1 | C13: 44203 | D13: 44203 | E13: GO DRAGON ASIAN GRILL RICHMOND VA | F13: 44 | G13: Restaurants | H13: =VLOOKUP(G13,Expense_Lookup,2,0) -> Variable | I13: =I12+F13 -> 1058 | K13: DAILY LIVING | O13: =SUM(O8:O12) -> 3427.81 | Q13: Restaurants | R13: Variable | S13: =SUMIFS(F:F,G:G,Q13,$B:$B,1) -> 117.23 | T13: =SUMIFS(F:F,G:G,Q13,$B:$B,2) -> 51.96 | U13: =SUMIFS(F:F,G:G,Q13,$B:$B,3) -> 259.85 | V13: =SUMIFS(F:F,G:G,Q13,$B:$B,4) -> 487.13 | W13: =SUMIFS($F:$F,$G:$G,$Q13,$B:$B,5) -> 247.11 | X13: =SUMIFS($F:$F,$G:$G,$Q13,$B:$B,6) -> 472.59 | Y13: =SUMIFS($F:$F,$G:$G,$Q13,$B:$B,7) -> 689.58 | Z13: =SUMIFS($F:$F,$G:$G,$Q13,$B:$B,8) -> 1021.47 | AA13: =SUMIFS($F:$F,$G:$G,$Q13,$B:$B,9) -> 1134.5 | AB13: =SUMIFS($F:$F,$G:$G,$Q13,$B:$B,10) -> 465.78 | AC13: =SUMIFS($F:$F,$G:$G,$Q13,$B:$B,11) -> 252.96 | AE13: =SUM(S13:AD13) -> 5200.16
A14: =YEAR(C14) -> 2021 | B14: =MONTH(C14) -> 1 | C14: 44203 | D14: 44203 | E14: THE MARKET @ 25TH RICHMOND VA | F14: 14.52 | G14: Supermarkets | H14: =VLOOKUP(G14,Expense_Lookup,2,0) -> Variable | I14: =I13+F14 -> 1072.52 | K14: DAILY LIVING | Q14: Services | R14: Variable | S14: =SUMIFS(F:F,G:G,Q14,$B:$B,1) -> 29.27 | T14: =SUMIFS(F:F,G:G,Q14,$B:$B,2) -> 0 | U14: =SUMIFS(F:F,G:G,Q14,$B:$B,3) -> 470 | V14: =SUMIFS(F:F,G:G,Q14,$B:$B,4) -> 98 | W14: =SUMIFS($F:$F,$G:$G,$Q14,$B:$B,5) -> 1.5 | X14: =SUMIFS($F:$F,$G:$G,$Q14,$B:$B,6) -> 213.84 | Y14: =SUMIFS($F:$F,$G:$G,$Q14,$B:$B,7) -> 1904.58 | Z14: =SUMIFS($F:$F,$G:$G,$Q14,$B:$B,8) -> 283.03 | AA14: =SUMIFS($F:$F,$G:$G,$Q14,$B:$B,9) -> 375.1 | AB14: =SUMIFS($F:$F,$G:$G,$Q14,$B:$B,10) -> 352.52 | AC14: =SUMIFS($F:$F,$G:$G,$Q14,$B:$B,11) -> 5 | AE14: =SUM(S14:AD14) -> 3732.84
A15: =YEAR(C15) -> 2021 | B15: =MONTH(C15) -> 1 | C15: 44204 | D15: 44204 | E15: CVS/PHARMACY #01988 RICHMOND VA | F15: 3.37 | G15: Family | H15: =VLOOKUP(G15,Expense_Lookup,2,0) -> Variable | I15: =I14+F15 -> 1075.89 | J15: Jayelin | K15: MISC PAYMENTS | N15: Trips | Q15: Education | R15: Variable | S15: =SUMIFS(F:F,G:G,Q15,$B:$B,1) -> 49 | T15: =SUMIFS(F:F,G:G,Q15,$B:$B,2) -> 215 | U15: =SUMIFS(F:F,G:G,Q15,$B:$B,3) -> 0 | V15: =SUMIFS(F:F,G:G,Q15,$B:$B,4) -> 0 | W15: =SUMIFS($F:$F,$G:$G,$Q15,$B:$B,5) -> 0 | X15: =SUMIFS($F:$F,$G:$G,$Q15,$B:$B,6) -> 199 | Y15: =SUMIFS($F:$F,$G:$G,$Q15,$B:$B,7) -> 0 | Z15: =SUMIFS($F:$F,$G:$G,$Q15,$B:$B,8) -> 4.8 | AA15: =SUMIFS($F:$F,$G:$G,$Q15,$B:$B,9) -> 0 | AB15: =SUMIFS($F:$F,$G:$G,$Q15,$B:$B,10) -> 0 | AC15: =SUMIFS($F:$F,$G:$G,$Q15,$B:$B,11) -> 0 | AE15: =SUM(S15:AD15) -> 467.8
A16: =YEAR(C16) -> 2021 | B16: =MONTH(C16) -> 1 | C16: 44204 | D16: 44204 | E16: LABCORP PSCC 2 800-845-6167 NC202101072171244 | F16: 40.51 | G16: Medical Services | H16: =VLOOKUP(G16,Expense_Lookup,2,0) -> Variable | I16: =I15+F16 -> 1116.4 | J16: Doctor | K16: HEALTH | N16: New York | O16: =SUMIFS(F:F,J:J,N16)+SUMIFS('Cash Flow'!$B:$B,'Cash Flow'!$A:$A,Discover!N16)*-1 -> 373.46 | Q16: Awards and Rebate Credits | R16: Payment | S16: =SUMIFS(F:F,G:G,Q16,$B:$B,1) -> -22.18 | T16: =SUMIFS(F:F,G:G,Q16,$B:$B,2) -> -14 | U16: =SUMIFS(F:F,G:G,Q16,$B:$B,3) -> -14.05 | V16: =SUMIFS(F:F,G:G,Q16,$B:$B,4) -> 0 | W16: =SUMIFS($F:$F,$G:$G,$Q16,$B:$B,5) -> 0 | X16: =SUMIFS($F:$F,$G:$G,$Q16,$B:$B,6) -> 0 | Y16: =SUMIFS($F:$F,$G:$G,$Q16,$B:$B,7) -> 0 | Z16: =SUMIFS($F:$F,$G:$G,$Q16,$B:$B,8) -> -38.86 | AA16: =SUMIFS($F:$F,$G:$G,$Q16,$B:$B,9) -> 0 | AB16: =SUMIFS($F:$F,$G:$G,$Q16,$B:$B,10) -> 0 | AC16: =SUMIFS($F:$F,$G:$G,$Q16,$B:$B,11) -> -43.38 | AE16: =SUM(S16:AD16) -> -132.47
A17: =YEAR(C17) -> 2021 | B17: =MONTH(C17) -> 1 | C17: 44205 | D17: 44205 | E17: BINGO BEER CO - GAMES PE RICHMOND VA | F17: 30 | G17: Restaurants | H17: =VLOOKUP(G17,Expense_Lookup,2,0) -> Variable | I17: =I16+F17 -> 1146.4 | J17: Akhil | K17: DAILY LIVING | N17: Brooklyn | O17: =SUMIFS(F:F,J:J,N17)+SUMIFS('Cash Flow'!$B:$B,'Cash Flow'!$A:$A,Discover!N17)*-1 -> 1983.8 | Q17: Government Services | R17: Variable | S17: =SUMIFS(F:F,G:G,Q17,$B:$B,1) -> 0 | T17: =SUMIFS(F:F,G:G,Q17,$B:$B,2) -> 40.15 | U17: =SUMIFS(F:F,G:G,Q17,$B:$B,3) -> 0 | V17: =SUMIFS(F:F,G:G,Q17,$B:$B,4) -> 0 | W17: =SUMIFS($F:$F,$G:$G,$Q17,$B:$B,5) -> 26.35 | X17: =SUMIFS($F:$F,$G:$G,$Q17,$B:$B,6) -> 195.05 | Y17: =SUMIFS($F:$F,$G:$G,$Q17,$B:$B,7) -> 194 | Z17: =SUMIFS($F:$F,$G:$G,$Q17,$B:$B,8) -> 21.51 | AA17: =SUMIFS($F:$F,$G:$G,$Q17,$B:$B,9) -> 140.91 | AB17: =SUMIFS($F:$F,$G:$G,$Q17,$B:$B,10) -> 0 | AC17: =SUMIFS($F:$F,$G:$G,$Q17,$B:$B,11) -> 138.14 | AE17: =SUM(S17:AD17) -> 756.11
A18: =YEAR(C18) -> 2021 | B18: =MONTH(C18) -> 1 | C18: 44205 | D18: 44205 | E18: WALMART SC 07032 HENRICO VA | F18: 37.5 | G18: Merchandise | H18: =VLOOKUP(G18,Expense_Lookup,2,0) -> Variable | I18: =I17+F18 -> 1183.9 | K18: PERSONAL | O18: =SUM(O16:O17) -> 2357.26 | Q18: Automotive | R18: Fixed | S18: =SUMIFS(F:F,G:G,Q18,$B:$B,1) -> 0 | T18: =SUMIFS(F:F,G:G,Q18,$B:$B,2) -> 0 | U18: =SUMIFS(F:F,G:G,Q18,$B:$B,3) -> 86.17 | V18: =SUMIFS(F:F,G:G,Q18,$B:$B,4) -> 5.65 | W18: =SUMIFS($F:$F,$G:$G,$Q18,$B:$B,5) -> 401.19 | X18: =SUMIFS($F:$F,$G:$G,$Q18,$B:$B,6) -> 0 | Y18: =SUMIFS($F:$F,$G:$G,$Q18,$B:$B,7) -> 394.26 | Z18: =SUMIFS($F:$F,$G:$G,$Q18,$B:$B,8) -> 0 | AA18: =SUMIFS($F:$F,$G:$G,$Q18,$B:$B,9) -> 110.71 | AB18: =SUMIFS($F:$F,$G:$G,$Q18,$B:$B,10) -> 0 | AC18: =SUMIFS($F:$F,$G:$G,$Q18,$B:$B,11) -> 0 | AE18: =SUM(S18:AD18) -> 997.98
A19: =YEAR(C19) -> 2021 | B19: =MONTH(C19) -> 1 | C19: 44206 | D19: 44206 | E19: APPLE.COM/BILL 866-712-7753 CAAPPLE PAY ENDING IN 4775MMW3T9K9KMA0 | F19: 14.99 | G19: APP | H19: =VLOOKUP(G19,Expense_Lookup,2,0) -> Fixed | I19: =I18+F19 -> 1198.89 | J19: HBO | K19: SUBSCRIPTION | Q19: Travel/ Entertainment | R19: Variable | S19: =SUMIFS(F:F,G:G,Q19,$B:$B,1) -> 0 | T19: =SUMIFS(F:F,G:G,Q19,$B:$B,2) -> 0 | U19: =SUMIFS(F:F,G:G,Q19,$B:$B,3) -> 101.04 | V19: =SUMIFS(F:F,G:G,Q19,$B:$B,4) -> 4.24 | W19: =SUMIFS($F:$F,$G:$G,$Q19,$B:$B,5) -> 360.05 | X19: =SUMIFS($F:$F,$G:$G,$Q19,$B:$B,6) -> 179.77 | Y19: =SUMIFS($F:$F,$G:$G,$Q19,$B:$B,7) -> 864.12 | Z19: =SUMIFS($F:$F,$G:$G,$Q19,$B:$B,8) -> 241.29 | AA19: =SUMIFS($F:$F,$G:$G,$Q19,$B:$B,9) -> 360.22 | AB19: =SUMIFS($F:$F,$G:$G,$Q19,$B:$B,10) -> 61.14 | AC19: =SUMIFS($F:$F,$G:$G,$Q19,$B:$B,11) -> 69.2 | AE19: =SUM(S19:AD19) -> 2241.07
A20: =YEAR(C20) -> 2021 | B20: =MONTH(C20) -> 1 | C20: 44206 | D20: 44206 | E20: FEDEX 782422707980 800-4633339 TN | F20: 14.47 | G20: Services | H20: =VLOOKUP(G20,Expense_Lookup,2,0) -> Variable | I20: =I19+F20 -> 1213.36 | J20: Darron | K20: MISC PAYMENTS | N20: Moving | Q20: Home Improvement | R20: Variable | S20: =SUMIFS(F:F,G:G,Q20,$B:$B,1) -> 0 | T20: =SUMIFS(F:F,G:G,Q20,$B:$B,2) -> 0 | U20: =SUMIFS(F:F,G:G,Q20,$B:$B,3) -> 0 | V20: =SUMIFS(F:F,G:G,Q20,$B:$B,4) -> 92.58 | W20: =SUMIFS($F:$F,$G:$G,$Q20,$B:$B,5) -> 54.37 | X20: =SUMIFS($F:$F,$G:$G,$Q20,$B:$B,6) -> 23.13 | Y20: =SUMIFS($F:$F,$G:$G,$Q20,$B:$B,7) -> 0 | Z20: =SUMIFS($F:$F,$G:$G,$Q20,$B:$B,8) -> 89.51 | AA20: =SUMIFS($F:$F,$G:$G,$Q20,$B:$B,9) -> 0 | AB20: =SUMIFS($F:$F,$G:$G,$Q20,$B:$B,10) -> 167.01 | AC20: =SUMIFS($F:$F,$G:$G,$Q20,$B:$B,11) -> 0 | AE20: =SUM(S20:AD20) -> 426.6
A21: =YEAR(C21) -> 2021 | B21: =MONTH(C21) -> 1 | C21: 44206 | D21: 44206 | E21: FEDEX 782422725203 800-4633339 TN | F21: 11.45 | G21: Services | H21: =VLOOKUP(G21,Expense_Lookup,2,0) -> Variable | I21: =I20+F21 -> 1224.81 | J21: Darron | K21: MISC PAYMENTS | N21: Storage | O21: =SUMIFS(F:F,J:J,N21)+SUMIFS('Cash Flow'!$B:$B,'Cash Flow'!$A:$A,Discover!N21)*-1 -> 396.27 | Q21: Car Wash | R21: Variable | S21: =SUMIFS(F:F,G:G,Q21,$B:$B,1) -> 0 | T21: =SUMIFS(F:F,G:G,Q21,$B:$B,2) -> 0 | U21: =SUMIFS(F:F,G:G,Q21,$B:$B,3) -> 0 | V21: =SUMIFS(F:F,G:G,Q21,$B:$B,4) -> 0 | W21: =SUMIFS($F:$F,$G:$G,$Q21,$B:$B,5) -> 0 | X21: =SUMIFS($F:$F,$G:$G,$Q21,$B:$B,6) -> 0 | Y21: =SUMIFS($F:$F,$G:$G,$Q21,$B:$B,7) -> 0 | Z21: =SUMIFS($F:$F,$G:$G,$Q21,$B:$B,8) -> 63.08 | AA21: =SUMIFS($F:$F,$G:$G,$Q21,$B:$B,9) -> 0 | AB21: =SUMIFS($F:$F,$G:$G,$Q21,$B:$B,10) -> 0 | AC21: =SUMIFS($F:$F,$G:$G,$Q21,$B:$B,11) -> 0 | AE21: =SUM(S21:AD21) -> 63.08
A22: =YEAR(C22) -> 2021 | B22: =MONTH(C22) -> 1 | C22: 44206 | D22: 44206 | E22: WALMART SC 07032 HENRICO VA | F22: 74.16 | G22: Merchandise | H22: =VLOOKUP(G22,Expense_Lookup,2,0) -> Variable | I22: =I21+F22 -> 1298.97 | K22: PERSONAL | N22: Arizona | O22: =SUMIFS(F:F,J:J,N22)+SUMIFS('Cash Flow'!$B:$B,'Cash Flow'!$A:$A,Discover!N22)*-1 -> 1380.63 | S22: =SUM(S6:S21) -> -909.99 | T22: =SUM(T6:T21) -> -1063.45 | U22: =SUM(U6:U21) -> -225.26 | V22: =SUM(V6:V21) -> 1046.94 | W22: =SUM(W6:W21) -> 2.18 | X22: =SUM(X6:X21) -> -93.27 | Y22: =SUM(Y6:Y21) -> -179.58 | Z22: =SUM(Z6:Z21) -> 45.97 | ... AC22: =SUM(AC6:AC21) -> -2731.18
A23: =YEAR(C23) -> 2021 | B23: =MONTH(C23) -> 1 | C23: 44207 | D23: 44207 | E23: CASH APP*SHEVON LEW 415-375-3176 CA | F23: 103 | G23: Family | H23: =VLOOKUP(G23,Expense_Lookup,2,0) -> Variable | I23: =I22+F23 -> 1401.97 | J23: Shevon | K23: MISC PAYMENTS | N23: road trip | O23: =SUMIFS(F:F,J:J,N23)+SUMIFS('Cash Flow'!$B:$B,'Cash Flow'!$A:$A,Discover!N23)*-1 -> 1213.29 | R23: Monthly Spending -> | S23: =SUM(S7:S15,S17:S21) -> 1269.57 | T23: =SUM(T7:T15,T17:T21) -> 1207.02 | U23: =SUM(U7:U15,U17:U21) -> 2202.41 | V23: =SUM(V7:V15,V17:V21) -> 1518.01 | W23: =SUM(W7:W15,W17:W21) -> 2857.34 | X23: =SUM(X7:X15,X17:X21) -> 3204.56 | Y23: =SUM(Y7:Y15,Y17:Y21) -> 5947.51 | Z23: =SUM(Z7:Z15,Z17:Z21) -> 3357.07 | ... AD23: =SUM(AD7:AD15,AD17:AD21) -> 0
A24: =YEAR(C24) -> 2021 | B24: =MONTH(C24) -> 1 | C24: 44207 | D24: 44207 | E24: PAYPAL *ETCHEDACTUA 402-935-7733 CA | F24: 49 | G24: Education | H24: =VLOOKUP(G24,Expense_Lookup,2,0) -> Variable | I24: =I23+F24 -> 1450.97 | K24: PERSONAL | O24: =SUM(O21:O22) -> 1776.9
A25: =YEAR(C25) -> 2021 | B25: =MONTH(C25) -> 1 | C25: 44208 | D25: 44208 | E25: EXXONMOBIL RICHMOND VA | F25: 23.27 | G25: Gasoline | H25: =VLOOKUP(G25,Expense_Lookup,2,0) -> Variable | I25: =I24+F25 -> 1474.24 | K25: TRANSPORTATION
A26: =YEAR(C26) -> 2021 | B26: =MONTH(C26) -> 1 | C26: 44208 | D26: 44208 | E26: FAMILY DOLLAR #5701 RICHMOND VA | F26: 3.33 | G26: Family | H26: =VLOOKUP(G26,Expense_Lookup,2,0) -> Variable | I26: =I25+F26 -> 1477.57 | J26: Jayelin | K26: MISC PAYMENTS
A27: =YEAR(C27) -> 2021 | B27: =MONTH(C27) -> 1 | C27: 44208 | D27: 44208 | E27: PAYPAL *VIZMEDIALLC 888-221-1161 CA | F27: 1.99 | G27: APP | H27: =VLOOKUP(G27,Expense_Lookup,2,0) -> Fixed | I27: =I26+F27 -> 1479.56 | J27: Manga | K27: SUBSCRIPTION
A28: =YEAR(C28) -> 2021 | B28: =MONTH(C28) -> 1 | C28: 44211 | D28: 44211 | E28: CASHBACK BONUS REDEMPTION PYMT/STMT CRDT | F28: -22.18 | G28: Awards and Rebate Credits | H28: =VLOOKUP(G28,Expense_Lookup,2,0) -> Payment | I28: =I27+F28 -> 1457.38
A29: =YEAR(C29) -> 2021 | B29: =MONTH(C29) -> 1 | C29: 44211 | D29: 44211 | E29: DIRECTPAY FULL BALANCESEE DETAILS OF YOUR NEXT DIRECTPAY BELOW | F29: -728.15 | G29: Payments and Credits | H29: =VLOOKUP(G29,Expense_Lookup,2,0) -> Payment | I29: =I28+F29 -> 729.23
A30: =YEAR(C30) -> 2021 | B30: =MONTH(C30) -> 1 | C30: 44211 | D30: 44211 | E30: INTERNET PAYMENT - THANK YOU | F30: -729.23 | G30: Payments and Credits | H30: =VLOOKUP(G30,Expense_Lookup,2,0) -> Payment | I30: =I29+F30 -> 0
A31: =YEAR(C31) -> 2021 | B31: =MONTH(C31) -> 1 | C31: 44211 | D31: 44211 | E31: MCDONALD'S F17579 RICHMOND VA | F31: 4.32 | G31: Family | H31: =VLOOKUP(G31,Expense_Lookup,2,0) -> Variable | I31: =I30+F31 -> 4.32 | J31: Jayelin | K31: MISC PAYMENTS
A32: =YEAR(C32) -> 2021 | B32: =MONTH(C32) -> 1 | C32: 44211 | D32: 44211 | E32: WALGREENS #3860 RICHMOND VA | F32: 21.19 | G32: Merchandise | H32: =VLOOKUP(G32,Expense_Lookup,2,0) -> Variable | I32: =I31+F32 -> 25.51 | J32: Draino | K32: MISC PAYMENTS
A33: =YEAR(C33) -> 2021 | B33: =MONTH(C33) -> 1 | C33: 44211 | D33: 44211 | E33: WALMART SC 07032 HENRICO VA | F33: 19.4 | G33: Merchandise | H33: =VLOOKUP(G33,Expense_Lookup,2,0) -> Variable | I33: =I32+F33 -> 44.91 | J33: Study | K33: PERSONAL
A34: =YEAR(C34) -> 2021 | B34: =MONTH(C34) -> 1 | C34: 44212 | D34: 44212 | E34: AMZN MKTP US*0H4DK7EL3 AMZN.COM/BILLWA72J9EGRQCDU | F34: 58.29 | G34: Merchandise | H34: =VLOOKUP(G34,Expense_Lookup,2,0) -> Variable | I34: =I33+F34 -> 103.2 | J34: Webcam | K34: PERSONAL
A35: =YEAR(C35) -> 2021 | B35: =MONTH(C35) -> 1 | C35: 44215 | D35: 44215 | E35: CHIPOTLE 1975 RICHMOND VA | F35: 8.23 | G35: Restaurants | H35: =VLOOKUP(G35,Expense_Lookup,2,0) -> Variable | I35: =I34+F35 -> 111.43 | K35: DAILY LIVING
A36: =YEAR(C36) -> 2021 | B36: =MONTH(C36) -> 1 | C36: 44215 | D36: 44215 | E36: CVS/PHARMACY #01988 RICHMOND VA | F36: 2.86 | G36: Family | H36: =VLOOKUP(G36,Expense_Lookup,2,0) -> Variable | I36: =I35+F36 -> 114.29 | J36: Jayelin | K36: MISC PAYMENTS
A37: =YEAR(C37) -> 2021 | B37: =MONTH(C37) -> 1 | C37: 44215 | D37: 44215 | E37: SP * ILF, LLC 8888044453 TX | F37: 99.9 | G37: Merchandise | H37: =VLOOKUP(G37,Expense_Lookup,2,0) -> Variable | I37: =I36+F37 -> 214.19 | K37: PERSONAL
A38: =YEAR(C38) -> 2021 | B38: =MONTH(C38) -> 1 | C38: 44216 | D38: 44216 | E38: THE MARKET @ 25TH RICHMOND VA | F38: 15.15 | G38: Supermarkets | H38: =VLOOKUP(G38,Expense_Lookup,2,0) -> Variable | I38: =I37+F38 -> 229.34 | K38: DAILY LIVING
A39: =YEAR(C39) -> 2021 | B39: =MONTH(C39) -> 1 | C39: 44217 | D39: 44217 | E39: KINGSISLE *PIRATE101 512-623-5983 TX00099RS900000000000000 | F39: 9.95 | G39: Family | H39: =VLOOKUP(G39,Expense_Lookup,2,0) -> Variable | I39: =I38+F39 -> 239.29 | J39: Jayelin | K39: MISC PAYMENTS
A40: =YEAR(C40) -> 2021 | B40: =MONTH(C40) -> 1 | C40: 44217 | D40: 44217 | E40: PP*PP ROKU FOR CRUNCHYR 402-935-7733 CA | F40: 7.99 | G40: APP | H40: =VLOOKUP(G40,Expense_Lookup,2,0) -> Fixed | I40: =I39+F40 -> 247.28 | J40: Crunchyroll | K40: SUBSCRIPTION
A41: =YEAR(C41) -> 2021 | B41: =MONTH(C41) -> 1 | C41: 44218 | D41: 44218 | E41: THE MARKET @ 25TH RICHMOND VA | F41: 15.61 | G41: Supermarkets | H41: =VLOOKUP(G41,Expense_Lookup,2,0) -> Variable | I41: =I40+F41 -> 262.89 | K41: DAILY LIVING
A42: =YEAR(C42) -> 2021 | B42: =MONTH(C42) -> 1 | C42: 44219 | D42: 44219 | E42: BEDBATH&BEYOND GLEN ALLEN VA | F42: 84.43 | G42: Merchandise | H42: =VLOOKUP(G42,Expense_Lookup,2,0) -> Variable | I42: =I41+F42 -> 347.32 | J42: Griddle | K42: DAILY LIVING
A43: =YEAR(C43) -> 2021 | B43: =MONTH(C43) -> 1 | C43: 44219 | D43: 44219 | E43: CITYPARKING INC 804-344-3353 VAAPPLE PAY ENDING IN 4775 | F43: 3.35 | G43: Services | H43: =VLOOKUP(G43,Expense_Lookup,2,0) -> Variable | I43: =I42+F43 -> 350.67 | J43: Akhil | K43: TRANSPORTATION
A44: =YEAR(C44) -> 2021 | B44: =MONTH(C44) -> 1 | C44: 44219 | D44: 44219 | E44: TST* 521 BISCUITS & WAFF RICHMOND VAAPPLE PAY ENDING IN 4775 | F44: 14.68 | G44: Restaurants | H44: =VLOOKUP(G44,Expense_Lookup,2,0) -> Variable | I44: =I43+F44 -> 365.35 | J44: Kaiya | K44: DAILY LIVING
A45: =YEAR(C45) -> 2021 | B45: =MONTH(C45) -> 1 | C45: 44221 | D45: 44221 | E45: EXXONMOBIL RICHMOND VA | F45: 2.76 | G45: Gasoline | H45: =VLOOKUP(G45,Expense_Lookup,2,0) -> Variable | I45: =I44+F45 -> 368.11 | K45: TRANSPORTATION
A46: =YEAR(C46) -> 2021 | B46: =MONTH(C46) -> 1 | C46: 44221 | D46: 44221 | E46: EXXONMOBIL RICHMOND VA | F46: 22.97 | G46: Gasoline | H46: =VLOOKUP(G46,Expense_Lookup,2,0) -> Variable | I46: =I45+F46 -> 391.08 | K46: TRANSPORTATION
A47: =YEAR(C47) -> 2021 | B47: =MONTH(C47) -> 1 | C47: 44222 | D47: 44222 | E47: CHIPOTLE 1975 RICHMOND VA | F47: 8.23 | G47: Restaurants | H47: =VLOOKUP(G47,Expense_Lookup,2,0) -> Variable | I47: =I46+F47 -> 399.31 | K47: DAILY LIVING
A48: =YEAR(C48) -> 2021 | B48: =MONTH(C48) -> 1 | C48: 44222 | D48: 44222 | E48: WHOLEFDS WBS#10598 RICHMOND VA | F48: 63.87 | G48: Supermarkets | H48: =VLOOKUP(G48,Expense_Lookup,2,0) -> Variable | I48: =I47+F48 -> 463.18 | K48: DAILY LIVING
A49: =YEAR(C49) -> 2021 | B49: =MONTH(C49) -> 1 | C49: 44223 | D49: 44223 | E49: CVS/PHARMACY #01988 RICHMOND VA | F49: 1.51 | G49: Family | H49: =VLOOKUP(G49,Expense_Lookup,2,0) -> Variable | I49: =I48+F49 -> 464.69 | J49: Jayelin | K49: MISC PAYMENTS
A50: =YEAR(C50) -> 2021 | B50: =MONTH(C50) -> 1 | C50: 44223 | D50: 44223 | E50: CVS/PHARMACY #01988 RICHMOND VA | F50: 2.24 | G50: Family | H50: =VLOOKUP(G50,Expense_Lookup,2,0) -> Variable | I50: =I49+F50 -> 466.93 | J50: Jayelin | K50: MISC PAYMENTS
A51: =YEAR(C51) -> 2021 | B51: =MONTH(C51) -> 1 | C51: 44223 | D51: 44223 | E51: PUBLIX #1588 RICHMOND VA | F51: 4.75 | G51: Supermarkets | H51: =VLOOKUP(G51,Expense_Lookup,2,0) -> Variable | I51: =I50+F51 -> 471.68 | K51: DAILY LIVING
A52: =YEAR(C52) -> 2021 | B52: =MONTH(C52) -> 1 | C52: 44224 | D52: 44224 | E52: ABC*CRUNCH FITNESS 888-827-9262 VAABC*CRUNCH FITNESS | F52: 9.95 | G52: APP | H52: =VLOOKUP(G52,Expense_Lookup,2,0) -> Fixed | I52: =I51+F52 -> 481.63 | J52: Crunch Fitness | K52: SUBSCRIPTION
A53: =YEAR(C53) -> 2021 | B53: =MONTH(C53) -> 1 | C53: 44226 | D53: 44226 | E53: THE MARKET @ 25TH RICHMOND VA | F53: 7.42 | G53: Family | H53: =VLOOKUP(G53,Expense_Lookup,2,0) -> Variable | I53: =I52+F53 -> 489.05 | J53: Jayelin | K53: MISC PAYMENTS
A54: =YEAR(C54) -> 2021 | B54: =MONTH(C54) -> 1 | C54: 44227 | D54: 44227 | E54: DC CHARBROILED CHICKEN RICHMOND VA | F54: 9.89 | G54: Family | H54: =VLOOKUP(G54,Expense_Lookup,2,0) -> Variable | I54: =I53+F54 -> 498.94 | J54: Jayelin | K54: MISC PAYMENTS
A55: =YEAR(C55) -> 2021 | B55: =MONTH(C55) -> 1 | C55: 44227 | D55: 44227 | E55: WALMART SC 07032 HENRICO VA | F55: 19.22 | G55: Merchandise | H55: =VLOOKUP(G55,Expense_Lookup,2,0) -> Variable | I55: =I54+F55 -> 518.16 | K55: PERSONAL
A56: =YEAR(C56) -> 2021 | B56: =MONTH(C56) -> 2 | C56: 44228 | D56: 44228 | E56: NETFLIX.COM NETFLIX.COM CA44925167830 | F56: 13.99 | G56: APP | H56: =VLOOKUP(G56,Expense_Lookup,2,0) -> Fixed | I56: =I55+F56 -> 532.15 | J56: Netflix | K56: SUBSCRIPTION
A57: =YEAR(C57) -> 2021 | B57: =MONTH(C57) -> 2 | C57: 44228 | D57: 44228 | E57: SPOTIFY P1343F2886 8777781161 NY | F57: 9.99 | G57: APP | H57: =VLOOKUP(G57,Expense_Lookup,2,0) -> Fixed | I57: =I56+F57 -> 542.14 | J57: Spotify | K57: SUBSCRIPTION
A58: =YEAR(C58) -> 2021 | B58: =MONTH(C58) -> 2 | C58: 44228 | D58: 44230 | E58: CVS/PHARMACY #01988 RICHMOND VA | F58: 15.92 | G58: Family | H58: =VLOOKUP(G58,Expense_Lookup,2,0) -> Variable | I58: =I57+F58 -> 558.06 | J58: Jayelin | K58: MISC PAYMENTS
A59: =YEAR(C59) -> 2021 | B59: =MONTH(C59) -> 2 | C59: 44229 | D59: 44230 | E59: CVS/PHARMACY #01988 RICHMOND VA | F59: 37.01 | G59: Merchandise | H59: =VLOOKUP(G59,Expense_Lookup,2,0) -> Variable | I59: =I58+F59 -> 595.07 | K59: PERSONAL
A60: =YEAR(C60) -> 2021 | B60: =MONTH(C60) -> 2 | C60: 44229 | D60: 44230 | E60: PAYPAL *DAYNEINVEST 888-221-1161 CA | F60: 10 | G60: Merchandise | H60: =VLOOKUP(G60,Expense_Lookup,2,0) -> Variable | I60: =I59+F60 -> 605.07 | J60: Masks | K60: HEALTH
A61: =YEAR(C61) -> 2021 | B61: =MONTH(C61) -> 2 | C61: 44230 | D61: 44230 | E61: STATE FARM INSURANCE 800-956-6310 IL | F61: 91.78 | G61: APP | H61: =VLOOKUP(G61,Expense_Lookup,2,0) -> Fixed | I61: =I60+F61 -> 696.85 | J61: State Farm | K61: SUBSCRIPTION
A62: =YEAR(C62) -> 2021 | B62: =MONTH(C62) -> 2 | C62: 44230 | D62: 44230 | E62: THE MARKET @ 25TH RICHMOND VA | F62: 15.09 | G62: Supermarkets | H62: =VLOOKUP(G62,Expense_Lookup,2,0) -> Variable | I62: =I61+F62 -> 711.94 | K62: DAILY LIVING
A63: =YEAR(C63) -> 2021 | B63: =MONTH(C63) -> 2 | C63: 44232 | D63: 44232 | E63: CVS/PHARMACY #01988 RICHMOND VA | F63: 1.63 | G63: Family | H63: =VLOOKUP(G63,Expense_Lookup,2,0) -> Variable | I63: =I62+F63 -> 713.57 | J63: Jayelin | K63: MISC PAYMENTS
A64: =YEAR(C64) -> 2021 | B64: =MONTH(C64) -> 2 | C64: 44232 | D64: 44232 | E64: CVS/PHARMACY #01988 RICHMOND VA | F64: 2.45 | G64: Family | H64: =VLOOKUP(G64,Expense_Lookup,2,0) -> Variable | I64: =I63+F64 -> 716.02 | J64: Jayelin | K64: MISC PAYMENTS
A65: =YEAR(C65) -> 2021 | B65: =MONTH(C65) -> 2 | C65: 44234 | D65: 44234 | E65: CHIPOTLE 1975 RICHMOND VA | F65: 9.36 | G65: Family | H65: =VLOOKUP(G65,Expense_Lookup,2,0) -> Variable | I65: =I64+F65 -> 725.38 | J65: Jayelin | K65: MISC PAYMENTS
A66: =YEAR(C66) -> 2021 | B66: =MONTH(C66) -> 2 | C66: 44237 | D66: 44237 | E66: APPLE.COM/BILL 866-712-7753 CAAPPLE PAY ENDING IN 4775MMW42NJ145A0 | F66: 3.99 | G66: Family | H66: =VLOOKUP(G66,Expense_Lookup,2,0) -> Variable | I66: =I65+F66 -> 729.37 | J66: Jayelin | K66: MISC PAYMENTS
A67: =YEAR(C67) -> 2021 | B67: =MONTH(C67) -> 2 | C67: 44237 | D67: 44237 | E67: CVS/PHARMACY #01988 RICHMOND VA | F67: 4.73 | G67: Family | H67: =VLOOKUP(G67,Expense_Lookup,2,0) -> Variable | I67: =I66+F67 -> 734.1 | J67: Jayelin | K67: MISC PAYMENTS
A68: =YEAR(C68) -> 2021 | B68: =MONTH(C68) -> 2 | C68: 44238 | D68: 44238 | E68: BIRD APP 8662052442 CA | F68: 5 | G68: Family | H68: =VLOOKUP(G68,Expense_Lookup,2,0) -> Variable | I68: =I67+F68 -> 739.1 | J68: Jayelin | K68: MISC PAYMENTS
A69: =YEAR(C69) -> 2021 | B69: =MONTH(C69) -> 2 | C69: 44238 | D69: 44238 | E69: BIRD APP 8662052442 CA | F69: 5 | G69: Family | H69: =VLOOKUP(G69,Expense_Lookup,2,0) -> Variable | I69: =I68+F69 -> 744.1 | J69: Jayelin | K69: MISC PAYMENTS
A70: =YEAR(C70) -> 2021 | B70: =MONTH(C70) -> 2 | C70: 44238 | D70: 44238 | E70: BIRD APP 8662052442 CA | F70: 5 | G70: Family | H70: =VLOOKUP(G70,Expense_Lookup,2,0) -> Variable | I70: =I69+F70 -> 749.1 | J70: Jayelin | K70: MISC PAYMENTS
A71: =YEAR(C71) -> 2021 | B71: =MONTH(C71) -> 2 | C71: 44239 | D71: 44239 | E71: CASHBACK BONUS REDEMPTION PYMT/STMT CRDT | F71: -14 | G71: Awards and Rebate Credits | H71: =VLOOKUP(G71,Expense_Lookup,2,0) -> Payment | I71: =I70+F71 -> 735.1
A72: =YEAR(C72) -> 2021 | B72: =MONTH(C72) -> 2 | C72: 44239 | D72: 44239 | E72: INTERNET PAYMENT - THANK YOU | F72: -715.37 | G72: Payments and Credits | H72: =VLOOKUP(G72,Expense_Lookup,2,0) -> Payment | I72: =I71+F72 -> 19.73
A73: =YEAR(C73) -> 2021 | B73: =MONTH(C73) -> 2 | C73: 44239 | D73: 44239 | E73: PAYPAL *VIZMEDIALLC 888-221-1161 CA | F73: 1.99 | G73: APP | H73: =VLOOKUP(G73,Expense_Lookup,2,0) -> Fixed | I73: =I72+F73 -> 21.72 | J73: Manga | K73: SUBSCRIPTION
A74: =YEAR(C74) -> 2021 | B74: =MONTH(C74) -> 2 | C74: 44241 | D74: 44241 | E74: APPLE.COM/BILL 866-712-7753 CAAPPLE PAY ENDING IN 4775MMW43JVXWTA0 | F74: 14.99 | G74: APP | H74: =VLOOKUP(G74,Expense_Lookup,2,0) -> Fixed | I74: =I73+F74 -> 36.71 | J74: HBO | K74: SUBSCRIPTION
A75: =YEAR(C75) -> 2021 | B75: =MONTH(C75) -> 2 | C75: 44241 | D75: 44241 | E75: THE MARKET @ 25TH RICHMOND VA | F75: 7.88 | G75: Supermarkets | H75: =VLOOKUP(G75,Expense_Lookup,2,0) -> Variable | I75: =I74+F75 -> 44.59 | K75: DAILY LIVING
A76: =YEAR(C76) -> 2021 | B76: =MONTH(C76) -> 2 | C76: 44241 | D76: 44241 | E76: WALMART SC 07032 HENRICO VA | F76: 48.58 | G76: Merchandise | H76: =VLOOKUP(G76,Expense_Lookup,2,0) -> Variable | I76: =I75+F76 -> 93.17 | K76: PERSONAL
A77: =YEAR(C77) -> 2021 | B77: =MONTH(C77) -> 2 | C77: 44244 | D77: 44244 | E77: TARGET RICHMOND VA | F77: 76.3 | G77: Merchandise | H77: =VLOOKUP(G77,Expense_Lookup,2,0) -> Variable | I77: =I76+F77 -> 169.47 | J77: Pants | K77: PERSONAL
A78: =YEAR(C78) -> 2021 | B78: =MONTH(C78) -> 2 | C78: 44246 | D78: 44246 | E78: PUPATELLA 2 RICHMOND VA | F78: 40.42 | G78: Restaurants | H78: =VLOOKUP(G78,Expense_Lookup,2,0) -> Variable | I78: =I77+F78 -> 209.89 | K78: DAILY LIVING
A79: =YEAR(C79) -> 2021 | B79: =MONTH(C79) -> 2 | C79: 44247 | D79: 44247 | E79: PUBLIX #1588 RICHMOND VA | F79: 135.35 | G79: Supermarkets | H79: =VLOOKUP(G79,Expense_Lookup,2,0) -> Variable | I79: =I78+F79 -> 345.24 | K79: DAILY LIVING
A80: =YEAR(C80) -> 2021 | B80: =MONTH(C80) -> 2 | C80: 44247 | D80: 44247 | E80: T-MOBILE PAYMENTS 800-937-8997 WAAPPLE PAY ENDING IN 4775T-MOBILE PAYMENTS | F80: 86.25 | G80: APP | H80: =VLOOKUP(G80,Expense_Lookup,2,0) -> Fixed | I80: =I79+F80 -> 431.49 | J80: T-Mobile | K80: SUBSCRIPTION
A81: =YEAR(C81) -> 2021 | B81: =MONTH(C81) -> 2 | C81: 44247 | D81: 44247 | E81: THE MARKET @ 25TH RICHMOND VA | F81: 10.64 | G81: Supermarkets | H81: =VLOOKUP(G81,Expense_Lookup,2,0) -> Variable | I81: =I80+F81 -> 442.13 | K81: DAILY LIVING
A82: =YEAR(C82) -> 2021 | B82: =MONTH(C82) -> 2 | C82: 44247 | D82: 44247 | E82: WWW.WOLFRAMALPHA.COM 8009653726 IL | F82: 6.99 | G82: Merchandise | H82: =VLOOKUP(G82,Expense_Lookup,2,0) -> Variable | I82: =I81+F82 -> 449.12 | J82: Study tool | K82: PERSONAL
A83: =YEAR(C83) -> 2021 | B83: =MONTH(C83) -> 2 | C83: 44248 | D83: 44248 | E83: CHIPOTLE 1975 RICHMOND VA | F83: 8.23 | G83: Family | H83: =VLOOKUP(G83,Expense_Lookup,2,0) -> Variable | I83: =I82+F83 -> 457.35 | J83: Jayelin | K83: MISC PAYMENTS
A84: =YEAR(C84) -> 2021 | B84: =MONTH(C84) -> 2 | C84: 44248 | D84: 44248 | E84: KINGSISLE *PIRATE101 512-623-5983 TX0009CTVV00000000000000 | F84: 9.95 | G84: Family | H84: =VLOOKUP(G84,Expense_Lookup,2,0) -> Variable | I84: =I83+F84 -> 467.3 | J84: Jayelin | K84: MISC PAYMENTS
A85: =YEAR(C85) -> 2021 | B85: =MONTH(C85) -> 2 | C85: 44248 | D85: 44248 | E85: PP*PP ROKU FOR CRUNCHYR 402-935-7733 CA | F85: 7.99 | G85: APP | H85: =VLOOKUP(G85,Expense_Lookup,2,0) -> Fixed | I85: =I84+F85 -> 475.29 | J85: Crunchyroll | K85: SUBSCRIPTION
A86: =YEAR(C86) -> 2021 | B86: =MONTH(C86) -> 2 | C86: 44248 | D86: 44248 | E86: SUNOCO 0113723100 RICHMOND VA | F86: 25.35 | G86: Gasoline | H86: =VLOOKUP(G86,Expense_Lookup,2,0) -> Variable | I86: =I85+F86 -> 500.64 | K86: TRANSPORTATION
A87: =YEAR(C87) -> 2021 | B87: =MONTH(C87) -> 2 | C87: 44248 | D87: 44248 | E87: WALMART SC 07032 HENRICO VA | F87: 11.64 | G87: Merchandise | H87: =VLOOKUP(G87,Expense_Lookup,2,0) -> Variable | I87: =I86+F87 -> 512.28 | K87: PERSONAL
A88: =YEAR(C88) -> 2021 | B88: =MONTH(C88) -> 2 | C88: 44248 | D88: 44248 | E88: WALMART SC 07032 HENRICO VA | F88: 20.14 | G88: Merchandise | H88: =VLOOKUP(G88,Expense_Lookup,2,0) -> Variable | I88: =I87+F88 -> 532.42 | K88: PERSONAL
A89: =YEAR(C89) -> 2021 | B89: =MONTH(C89) -> 2 | C89: 44248 | D89: 44248 | E89: WALMART SC 07032 HENRICO VA | F89: 21.14 | G89: Merchandise | H89: =VLOOKUP(G89,Expense_Lookup,2,0) -> Variable | I89: =I88+F89 -> 553.56 | K89: PERSONAL
A90: =YEAR(C90) -> 2021 | B90: =MONTH(C90) -> 2 | C90: 44250 | D90: 44250 | E90: PAYPAL *WEBULL TECH 402-935-7733 CA | F90: 1.99 | G90: APP | H90: =VLOOKUP(G90,Expense_Lookup,2,0) -> Fixed | I90: =I89+F90 -> 555.55 | J90: Webull | K90: SUBSCRIPTION
A91: =YEAR(C91) -> 2021 | B91: =MONTH(C91) -> 2 | C91: 44251 | D91: 44251 | E91: COACHING ACTUARIES 8324128532 IA | F91: 215 | G91: Education | H91: =VLOOKUP(G91,Expense_Lookup,2,0) -> Variable | I91: =I90+F91 -> 770.55 | J91: Adapt | K91: PERSONAL
A92: =YEAR(C92) -> 2021 | B92: =MONTH(C92) -> 2 | C92: 44253 | D92: 44253 | E92: INTERNET PAYMENT - THANK YOU | F92: -770.55 | G92: Payments and Credits | H92: =VLOOKUP(G92,Expense_Lookup,2,0) -> Payment | I92: =I91+F92 -> 0
A93: =YEAR(C93) -> 2021 | B93: =MONTH(C93) -> 2 | C93: 44253 | D93: 44253 | E93: DISNEYPLUS 888-905-7888 CADISNEYPLUS | F93: 6.99 | G93: Merchandise | H93: =VLOOKUP(G93,Expense_Lookup,2,0) -> Variable | I93: =I92+F93 -> 6.99 | K93: PERSONAL
A94: =YEAR(C94) -> 2021 | B94: =MONTH(C94) -> 2 | C94: 44253 | D94: 44253 | E94: INTERNET PAYMENT - THANK YOU | F94: -770.55 | G94: Payments and Credits | H94: =VLOOKUP(G94,Expense_Lookup,2,0) -> Payment | I94: =I93+F94 -> -763.56
A95: =YEAR(C95) -> 2021 | B95: =MONTH(C95) -> 2 | C95: 44253 | D95: 44253 | E95: WALMART SC 07032 HENRICO VA | F95: 13.67 | G95: Merchandise | H95: =VLOOKUP(G95,Expense_Lookup,2,0) -> Variable | I95: =I94+F95 -> -749.89 | K95: PERSONAL
A96: =YEAR(C96) -> 2021 | B96: =MONTH(C96) -> 2 | C96: 44254 | D96: 44254 | E96: APPLE.COM/BILL 866-712-7753 CAAPPLE PAY ENDING IN 4775MMW4751VM2A0 | F96: 1.99 | G96: APP | H96: =VLOOKUP(G96,Expense_Lookup,2,0) -> Fixed | I96: =I95+F96 -> -747.9 | J96: Manga | K96: SUBSCRIPTION
A97: =YEAR(C97) -> 2021 | B97: =MONTH(C97) -> 2 | C97: 44254 | D97: 44254 | E97: PAYPAL *COUPLECENTS 402-935-7733 CA | F97: 9.99 | G97: APP | H97: =VLOOKUP(G97,Expense_Lookup,2,0) -> Fixed | I97: =I96+F97 -> -737.91 | J97: Couple Cents | K97: SUBSCRIPTION
A98: =YEAR(C98) -> 2021 | B98: =MONTH(C98) -> 2 | C98: 44254 | D98: 44254 | E98: SHEETZ 267200026724498 WOODFORD VA | F98: 16.24 | G98: Gasoline | H98: =VLOOKUP(G98,Expense_Lookup,2,0) -> Variable | I98: =I97+F98 -> -721.67 | K98: TRANSPORTATION
A99: =YEAR(C99) -> 2021 | B99: =MONTH(C99) -> 2 | C99: 44254 | D99: 44254 | E99: TACO BELL #28942 DUMFRIES VA | F99: 11.54 | G99: Restaurants | H99: =VLOOKUP(G99,Expense_Lookup,2,0) -> Variable | I99: =I98+F99 -> -710.13 | K99: DAILY LIVING
A100: =YEAR(C100) -> 2021 | B100: =MONTH(C100) -> 2 | C100: 44254 | D100: 44254 | E100: WWW.CVS.COM 800-746-7287 RI | F100: 5 | G100: Merchandise | H100: =VLOOKUP(G100,Expense_Lookup,2,0) -> Variable | I100: =I99+F100 -> -705.13 | K100: PERSONAL
...

Sheet Sheet1
M1: 44533 | N1: 1962.31
J2: Vincent | K2: 742.18 | M2: 44547 | N2: 1962.31
J3: Best Buy | K3: 54.01 | M3: 44561 | N3: 1962.31
G4: Wells Fargo | H4: Discover | J4: Kim | K4: 140
G5: 1422.84 | H5: 2011.06
F6: Pay Best Buy | G6: =G5-K3 -> 1368.83
F7: Pay Vincent | G7: =G6-K2 -> 626.65
F8: Pay 15% of Discover | G8: =G7-I8 -> 324.991 | H8: =H5*0.85 -> 1709.401 | I8: =H5*0.15 -> 301.659
F9: Cashback Bonus | G9: =G8+44.4 -> 369.391
F14: -Fiscal Impact Analysis
F18: 725
F19: 1149
F20: =F19+F18 -> 1874

Sheet Subscriptions
A1: Name | B1: Sub Type | C1: Cancelled? | D1: Day | E1: Total Paid | F1: # | G1: Avg. Paid | H1: Jan | I1: Feb | J1: Mar | K1: Apr | L1: May | M1: June | N1: July | O1: Aug | P1: Sep | Q1: Oct | R1: Nov | S1: Dec
A2: {=_xlfn._xlws.SORT(_xlfn.UNIQUE(_xlfn.UNIQUE(_xlfn._xlws.FILTER(Discover!J:J, (Discover!G:G = "APP")*(Discover!J:J <>0)),1)))} -> Apple Music | B2: Monthly | C2: Yes | D2: {=AVERAGE(DAY(_xlfn.UNIQUE(_xlfn._xlws.FILTER(Discover!C:C, Discover!J:J = A2,0),1)))} -> 29 | E2: =SUMIFS(Discover!F:F,Discover!J:J,Subscriptions!A2) -> 21.18 | F2: =COUNTIFS(Discover!J:J,Subscriptions!A2,Discover!G:G,"APP") -> 2 | G2: =E2/F2 -> 10.59 | H2: =SUMIFS(Discover!$F:$F,Discover!$J:$J,Subscriptions!$A2,Discover!$B:$B,1) -> 0 | I2: =SUMIFS(Discover!$F:$F,Discover!$J:$J,Subscriptions!$A2,Discover!$B:$B,2) -> 0 | J2: =SUMIFS(Discover!$F:$F,Discover!$J:$J,Subscriptions!$A2,Discover!$B:$B,3) -> 0 | K2: =SUMIFS(Discover!$F:$F,Discover!$J:$J,Subscriptions!$A2,Discover!$B:$B,4) -> 0 | L2: =SUMIFS(Discover!$F:$F,Discover!$J:$J,Subscriptions!$A2,Discover!$B:$B,5) -> 0 | M2: =SUMIFS(Discover!$F:$F,Discover!$J:$J,Subscriptions!$A2,Discover!$B:$B,6) -> 0 | N2: =SUMIFS(Discover!$F:$F,Discover!$J:$J,Subscriptions!$A2,Discover!$B:$B,7) -> 0 | O2: =SUMIFS(Discover!$F:$F,Discover!$J:$J,Subscriptions!$A2,Discover!$B:$B,8) -> 10.59 | P2: =SUMIFS(Discover!$F:$F,Discover!$J:$J,Subscriptions!$A2,Discover!$B:$B,9) -> 10.59 | Q2: =SUMIFS(Discover!$F:$F,Discover!$J:$J,Subscriptions!$A2,Discover!$B:$B,10) -> 0 | R2: =SUMIFS(Discover!$F:$F,Discover!$J:$J,Subscriptions!$A2,Discover!$B:$B,11) -> 0 | S2: =SUMIFS(Discover!$F:$F,Discover!$J:$J,Subscriptions!$A2,Discover!$B:$B,12) -> 0
A3: Apple TV+ | B3: One time | C3: No | D3: {=AVERAGE(DAY(_xlfn.UNIQUE(_xlfn._xlws.FILTER(Discover!C:C, Discover!J:J = A3,0),1)))} -> 17 | E3: =SUMIFS(Discover!F:F,Discover!J:J,Subscriptions!A3) -> 10.58 | F3: =COUNTIFS(Discover!J:J,Subscriptions!A3,Discover!G:G,"APP") -> 2 | G3: =E3/F3 -> 5.29 | H3: =SUMIFS(Discover!$F:$F,Discover!$J:$J,Subscriptions!$A3,Discover!$B:$B,1) -> 0 | I3: =SUMIFS(Discover!$F:$F,Discover!$J:$J,Subscriptions!$A3,Discover!$B:$B,2) -> 0 | J3: =SUMIFS(Discover!$F:$F,Discover!$J:$J,Subscriptions!$A3,Discover!$B:$B,3) -> 0 | K3: =SUMIFS(Discover!$F:$F,Discover!$J:$J,Subscriptions!$A3,Discover!$B:$B,4) -> 0 | L3: =SUMIFS(Discover!$F:$F,Discover!$J:$J,Subscriptions!$A3,Discover!$B:$B,5) -> 0 | M3: =SUMIFS(Discover!$F:$F,Discover!$J:$J,Subscriptions!$A3,Discover!$B:$B,6) -> 0 | N3: =SUMIFS(Discover!$F:$F,Discover!$J:$J,Subscriptions!$A3,Discover!$B:$B,7) -> 0 | O3: =SUMIFS(Discover!$F:$F,Discover!$J:$J,Subscriptions!$A3,Discover!$B:$B,8) -> 0 | P3: =SUMIFS(Discover!$F:$F,Discover!$J:$J,Subscriptions!$A3,Discover!$B:$B,9) -> 5.29 | Q3: =SUMIFS(Discover!$F:$F,Discover!$J:$J,Subscriptions!$A3,Discover!$B:$B,10) -> 5.29 | R3: =SUMIFS(Discover!$F:$F,Discover!$J:$J,Subscriptions!$A3,Discover!$B:$B,11) -> 0 | S3: =SUMIFS(Discover!$F:$F,Discover!$J:$J,Subscriptions!$A3,Discover!$B:$B,12) -> 0
A4: Audible | B4: Monthly | C4: No | D4: {=AVERAGE(DAY(_xlfn.UNIQUE(_xlfn._xlws.FILTER(Discover!C:C, Discover!J:J = A4,0),1)))} -> 18.5 | E4: =SUMIFS(Discover!F:F,Discover!J:J,Subscriptions!A4) -> 65.2 | F4: =COUNTIFS(Discover!J:J,Subscriptions!A4,Discover!G:G,"APP") -> 4 | G4: =E4/F4 -> 16.3 | H4: =SUMIFS(Discover!$F:$F,Discover!$J:$J,Subscriptions!$A4,Discover!$B:$B,1) -> 0 | I4: =SUMIFS(Discover!$F:$F,Discover!$J:$J,Subscriptions!$A4,Discover!$B:$B,2) -> 0 | J4: =SUMIFS(Discover!$F:$F,Discover!$J:$J,Subscriptions!$A4,Discover!$B:$B,3) -> 0 | K4: =SUMIFS(Discover!$F:$F,Discover!$J:$J,Subscriptions!$A4,Discover!$B:$B,4) -> 0 | L4: =SUMIFS(Discover!$F:$F,Discover!$J:$J,Subscriptions!$A4,Discover!$B:$B,5) -> 0 | M4: =SUMIFS(Discover!$F:$F,Discover!$J:$J,Subscriptions!$A4,Discover!$B:$B,6) -> 0 | N4: =SUMIFS(Discover!$F:$F,Discover!$J:$J,Subscriptions!$A4,Discover!$B:$B,7) -> 0 | O4: =SUMIFS(Discover!$F:$F,Discover!$J:$J,Subscriptions!$A4,Discover!$B:$B,8) -> 56.52 | P4: =SUMIFS(Discover!$F:$F,Discover!$J:$J,Subscriptions!$A4,Discover!$B:$B,9) -> 8.68 | Q4: =SUMIFS(Discover!$F:$F,Discover!$J:$J,Subscriptions!$A4,Discover!$B:$B,10) -> 0 | R4: =SUMIFS(Discover!$F:$F,Discover!$J:$J,Subscriptions!$A4,Discover!$B:$B,11) -> 0 | S4: =SUMIFS(Discover!$F:$F,Discover!$J:$J,Subscriptions!$A4,Discover!$B:$B,12) -> 0
A5: Bloomberg | B5: Monthly | C5: Yes | D5: {=AVERAGE(DAY(_xlfn.UNIQUE(_xlfn._xlws.FILTER(Discover!C:C, Discover!J:J = A5,0),1)))} -> 31 | E5: =SUMIFS(Discover!F:F,Discover!J:J,Subscriptions!A5) -> 37.09 | F5: =COUNTIFS(Discover!J:J,Subscriptions!A5,Discover!G:G,"APP") -> 1 | G5: =E5/F5 -> 37.09 | H5: =SUMIFS(Discover!$F:$F,Discover!$J:$J,Subscriptions!$A5,Discover!$B:$B,1) -> 0 | I5: =SUMIFS(Discover!$F:$F,Discover!$J:$J,Subscriptions!$A5,Discover!$B:$B,2) -> 0 | J5: =SUMIFS(Discover!$F:$F,Discover!$J:$J,Subscriptions!$A5,Discover!$B:$B,3) -> 0 | K5: =SUMIFS(Discover!$F:$F,Discover!$J:$J,Subscriptions!$A5,Discover!$B:$B,4) -> 0 | L5: =SUMIFS(Discover!$F:$F,Discover!$J:$J,Subscriptions!$A5,Discover!$B:$B,5) -> 37.09 | M5: =SUMIFS(Discover!$F:$F,Discover!$J:$J,Subscriptions!$A5,Discover!$B:$B,6) -> 0 | N5: =SUMIFS(Discover!$F:$F,Discover!$J:$J,Subscriptions!$A5,Discover!$B:$B,7) -> 0 | O5: =SUMIFS(Discover!$F:$F,Discover!$J:$J,Subscriptions!$A5,Discover!$B:$B,8) -> 0 | P5: =SUMIFS(Discover!$F:$F,Discover!$J:$J,Subscriptions!$A5,Discover!$B:$B,9) -> 0 | Q5: =SUMIFS(Discover!$F:$F,Discover!$J:$J,Subscriptions!$A5,Discover!$B:$B,10) -> 0 | R5: =SUMIFS(Discover!$F:$F,Discover!$J:$J,Subscriptions!$A5,Discover!$B:$B,11) -> 0 | S5: =SUMIFS(Discover!$F:$F,Discover!$J:$J,Subscriptions!$A5,Discover!$B:$B,12) -> 0
A6: Bumble | B6: Monthly | C6: Yes | D6: {=AVERAGE(DAY(_xlfn.UNIQUE(_xlfn._xlws.FILTER(Discover!C:C, Discover!J:J = A6,0),1)))} -> 10 | E6: =SUMIFS(Discover!F:F,Discover!J:J,Subscriptions!A6) -> 84.59 | F6: =COUNTIFS(Discover!J:J,Subscriptions!A6,Discover!G:G,"APP") -> 3 | G6: =E6/F6 -> 28.196667 | H6: =SUMIFS(Discover!$F:$F,Discover!$J:$J,Subscriptions!$A6,Discover!$B:$B,1) -> 0 | I6: =SUMIFS(Discover!$F:$F,Discover!$J:$J,Subscriptions!$A6,Discover!$B:$B,2) -> 0 | J6: =SUMIFS(Discover!$F:$F,Discover!$J:$J,Subscriptions!$A6,Discover!$B:$B,3) -> 0 | K6: =SUMIFS(Discover!$F:$F,Discover!$J:$J,Subscriptions!$A6,Discover!$B:$B,4) -> 0 | L6: =SUMIFS(Discover!$F:$F,Discover!$J:$J,Subscriptions!$A6,Discover!$B:$B,5) -> 0 | M6: =SUMIFS(Discover!$F:$F,Discover!$J:$J,Subscriptions!$A6,Discover!$B:$B,6) -> 0 | N6: =SUMIFS(Discover!$F:$F,Discover!$J:$J,Subscriptions!$A6,Discover!$B:$B,7) -> 0 | O6: =SUMIFS(Discover!$F:$F,Discover!$J:$J,Subscriptions!$A6,Discover!$B:$B,8) -> 84.59 | P6: =SUMIFS(Discover!$F:$F,Discover!$J:$J,Subscriptions!$A6,Discover!$B:$B,9) -> 0 | Q6: =SUMIFS(Discover!$F:$F,Discover!$J:$J,Subscriptions!$A6,Discover!$B:$B,10) -> 0 | R6: =SUMIFS(Discover!$F:$F,Discover!$J:$J,Subscriptions!$A6,Discover!$B:$B,11) -> 0 | S6: =SUMIFS(Discover!$F:$F,Discover!$J:$J,Subscriptions!$A6,Discover!$B:$B,12) -> 0
A7: Catan Gold | B7: Monthly | C7: No | D7: {=AVERAGE(DAY(_xlfn.UNIQUE(_xlfn._xlws.FILTER(Discover!C:C, Discover!J:J = A7,0),1)))} -> 26 | E7: =SUMIFS(Discover!F:F,Discover!J:J,Subscriptions!A7) -> 14.99 | F7: =COUNTIFS(Discover!J:J,Subscriptions!A7,Discover!G:G,"APP") -> 1 | G7: =E7/F7 -> 14.99 | H7: =SUMIFS(Discover!$F:$F,Discover!$J:$J,Subscriptions!$A7,Discover!$B:$B,1) -> 0 | I7: =SUMIFS(Discover!$F:$F,Discover!$J:$J,Subscriptions!$A7,Discover!$B:$B,2) -> 0 | J7: =SUMIFS(Discover!$F:$F,Discover!$J:$J,Subscriptions!$A7,Discover!$B:$B,3) -> 14.99 | K7: =SUMIFS(Discover!$F:$F,Discover!$J:$J,Subscriptions!$A7,Discover!$B:$B,4) -> 0 | L7: =SUMIFS(Discover!$F:$F,Discover!$J:$J,Subscriptions!$A7,Discover!$B:$B,5) -> 0 | M7: =SUMIFS(Discover!$F:$F,Discover!$J:$J,Subscriptions!$A7,Discover!$B:$B,6) -> 0 | N7: =SUMIFS(Discover!$F:$F,Discover!$J:$J,Subscriptions!$A7,Discover!$B:$B,7) -> 0 | O7: =SUMIFS(Discover!$F:$F,Discover!$J:$J,Subscriptions!$A7,Discover!$B:$B,8) -> 0 | P7: =SUMIFS(Discover!$F:$F,Discover!$J:$J,Subscriptions!$A7,Discover!$B:$B,9) -> 0 | Q7: =SUMIFS(Discover!$F:$F,Discover!$J:$J,Subscriptions!$A7,Discover!$B:$B,10) -> 0 | R7: =SUMIFS(Discover!$F:$F,Discover!$J:$J,Subscriptions!$A7,Discover!$B:$B,11) -> 0 | S7: =SUMIFS(Discover!$F:$F,Discover!$J:$J,Subscriptions!$A7,Discover!$B:$B,12) -> 0
A8: Couple Cents | B8: Annual | C8: No | D8: {=AVERAGE(DAY(_xlfn.UNIQUE(_xlfn._xlws.FILTER(Discover!C:C, Discover!J:J = A8,0),1)))} -> 27 | E8: =SUMIFS(Discover!F:F,Discover!J:J,Subscriptions!A8) -> 79.92 | F8: =COUNTIFS(Discover!J:J,Subscriptions!A8,Discover!G:G,"APP") -> 7 | G8: =E8/F8 -> 11.417143 | H8: =SUMIFS(Discover!$F:$F,Discover!$J:$J,Subscriptions!$A8,Discover!$B:$B,1) -> 0 | I8: =SUMIFS(Discover!$F:$F,Discover!$J:$J,Subscriptions!$A8,Discover!$B:$B,2) -> 9.99 | J8: =SUMIFS(Discover!$F:$F,Discover!$J:$J,Subscriptions!$A8,Discover!$B:$B,3) -> 9.99 | K8: =SUMIFS(Discover!$F:$F,Discover!$J:$J,Subscriptions!$A8,Discover!$B:$B,4) -> 9.99 | L8: =SUMIFS(Discover!$F:$F,Discover!$J:$J,Subscriptions!$A8,Discover!$B:$B,5) -> 9.99 | M8: =SUMIFS(Discover!$F:$F,Discover!$J:$J,Subscriptions!$A8,Discover!$B:$B,6) -> 9.99 | N8: =SUMIFS(Discover!$F:$F,Discover!$J:$J,Subscriptions!$A8,Discover!$B:$B,7) -> 9.99 | O8: =SUMIFS(Discover!$F:$F,Discover!$J:$J,Subscriptions!$A8,Discover!$B:$B,8) -> 9.99 | P8: =SUMIFS(Discover!$F:$F,Discover!$J:$J,Subscriptions!$A8,Discover!$B:$B,9) -> 9.99 | Q8: =SUMIFS(Discover!$F:$F,Discover!$J:$J,Subscriptions!$A8,Discover!$B:$B,10) -> 0 | R8: =SUMIFS(Discover!$F:$F,Discover!$J:$J,Subscriptions!$A8,Discover!$B:$B,11) -> 0 | S8: =SUMIFS(Discover!$F:$F,Discover!$J:$J,Subscriptions!$A8,Discover!$B:$B,12) -> 0
A9: Credit Score | B9: Monthly | C9: Yes | D9: {=AVERAGE(DAY(_xlfn.UNIQUE(_xlfn._xlws.FILTER(Discover!C:C, Discover!J:J = A9,0),1)))} -> 5 | E9: =SUMIFS(Discover!F:F,Discover!J:J,Subscriptions!A9) -> 39.95 | F9: =COUNTIFS(Discover!J:J,Subscriptions!A9,Discover!G:G,"APP") -> 1 | G9: =E9/F9 -> 39.95 | H9: =SUMIFS(Discover!$F:$F,Discover!$J:$J,Subscriptions!$A9,Discover!$B:$B,1) -> 39.95 | I9: =SUMIFS(Discover!$F:$F,Discover!$J:$J,Subscriptions!$A9,Discover!$B:$B,2) -> 0 | J9: =SUMIFS(Discover!$F:$F,Discover!$J:$J,Subscriptions!$A9,Discover!$B:$B,3) -> 0 | K9: =SUMIFS(Discover!$F:$F,Discover!$J:$J,Subscriptions!$A9,Discover!$B:$B,4) -> 0 | L9: =SUMIFS(Discover!$F:$F,Discover!$J:$J,Subscriptions!$A9,Discover!$B:$B,5) -> 0 | M9: =SUMIFS(Discover!$F:$F,Discover!$J:$J,Subscriptions!$A9,Discover!$B:$B,6) -> 0 | N9: =SUMIFS(Discover!$F:$F,Discover!$J:$J,Subscriptions!$A9,Discover!$B:$B,7) -> 0 | O9: =SUMIFS(Discover!$F:$F,Discover!$J:$J,Subscriptions!$A9,Discover!$B:$B,8) -> 0 | P9: =SUMIFS(Discover!$F:$F,Discover!$J:$J,Subscriptions!$A9,Discover!$B:$B,9) -> 0 | Q9: =SUMIFS(Discover!$F:$F,Discover!$J:$J,Subscriptions!$A9,Discover!$B:$B,10) -> 0 | R9: =SUMIFS(Discover!$F:$F,Discover!$J:$J,Subscriptions!$A9,Discover!$B:$B,11) -> 0 | S9: =SUMIFS(Discover!$F:$F,Discover!$J:$J,Subscriptions!$A9,Discover!$B:$B,12) -> 0
A10: Crunch Fitness | B10: 6-Months | C10: No | D10: {=AVERAGE(DAY(_xlfn.UNIQUE(_xlfn._xlws.FILTER(Discover!C:C, Discover!J:J = A10,0),1)))} -> 28 | E10: =SUMIFS(Discover!F:F,Discover!J:J,Subscriptions!A10) -> 29.85 | F10: =COUNTIFS(Discover!J:J,Subscriptions!A10,Discover!G:G,"APP") -> 3 | G10: =E10/F10 -> 9.95 | H10: =SUMIFS(Discover!$F:$F,Discover!$J:$J,Subscriptions!$A10,Discover!$B:$B,1) -> 9.95 | I10: =SUMIFS(Discover!$F:$F,Discover!$J:$J,Subscriptions!$A10,Discover!$B:$B,2) -> 9.95 | J10: =SUMIFS(Discover!$F:$F,Discover!$J:$J,Subscriptions!$A10,Discover!$B:$B,3) -> 9.95 | K10: =SUMIFS(Discover!$F:$F,Discover!$J:$J,Subscriptions!$A10,Discover!$B:$B,4) -> 0 | L10: =SUMIFS(Discover!$F:$F,Discover!$J:$J,Subscriptions!$A10,Discover!$B:$B,5) -> 0 | M10: =SUMIFS(Discover!$F:$F,Discover!$J:$J,Subscriptions!$A10,Discover!$B:$B,6) -> 0 | N10: =SUMIFS(Discover!$F:$F,Discover!$J:$J,Subscriptions!$A10,Discover!$B:$B,7) -> 0 | O10: =SUMIFS(Discover!$F:$F,Discover!$J:$J,Subscriptions!$A10,Discover!$B:$B,8) -> 0 | P10: =SUMIFS(Discover!$F:$F,Discover!$J:$J,Subscriptions!$A10,Discover!$B:$B,9) -> 0 | Q10: =SUMIFS(Discover!$F:$F,Discover!$J:$J,Subscriptions!$A10,Discover!$B:$B,10) -> 0 | R10: =SUMIFS(Discover!$F:$F,Discover!$J:$J,Subscriptions!$A10,Discover!$B:$B,11) -> 0 | S10: =SUMIFS(Discover!$F:$F,Discover!$J:$J,Subscriptions!$A10,Discover!$B:$B,12) -> 0
A11: Crunchyroll | B11: 1 Year | C11: Yes | D11: {=AVERAGE(DAY(_xlfn.UNIQUE(_xlfn._xlws.FILTER(Discover!C:C, Discover!J:J = A11,0),1)))} -> 21.111111 | E11: =SUMIFS(Discover!F:F,Discover!J:J,Subscriptions!A11) -> 71.91 | F11: =COUNTIFS(Discover!J:J,Subscriptions!A11,Discover!G:G,"APP") -> 9 | G11: =E11/F11 -> 7.99 | H11: =SUMIFS(Discover!$F:$F,Discover!$J:$J,Subscriptions!$A11,Discover!$B:$B,1) -> 7.99 | I11: =SUMIFS(Discover!$F:$F,Discover!$J:$J,Subscriptions!$A11,Discover!$B:$B,2) -> 7.99 | J11: =SUMIFS(Discover!$F:$F,Discover!$J:$J,Subscriptions!$A11,Discover!$B:$B,3) -> 7.99 | K11: =SUMIFS(Discover!$F:$F,Discover!$J:$J,Subscriptions!$A11,Discover!$B:$B,4) -> 7.99 | L11: =SUMIFS(Discover!$F:$F,Discover!$J:$J,Subscriptions!$A11,Discover!$B:$B,5) -> 7.99 | M11: =SUMIFS(Discover!$F:$F,Discover!$J:$J,Subscriptions!$A11,Discover!$B:$B,6) -> 7.99 | N11: =SUMIFS(Discover!$F:$F,Discover!$J:$J,Subscriptions!$A11,Discover!$B:$B,7) -> 7.99 | O11: =SUMIFS(Discover!$F:$F,Discover!$J:$J,Subscriptions!$A11,Discover!$B:$B,8) -> 7.99 | P11: =SUMIFS(Discover!$F:$F,Discover!$J:$J,Subscriptions!$A11,Discover!$B:$B,9) -> 7.99 | Q11: =SUMIFS(Discover!$F:$F,Discover!$J:$J,Subscriptions!$A11,Discover!$B:$B,10) -> 0 | R11: =SUMIFS(Discover!$F:$F,Discover!$J:$J,Subscriptions!$A11,Discover!$B:$B,11) -> 0 | S11: =SUMIFS(Discover!$F:$F,Discover!$J:$J,Subscriptions!$A11,Discover!$B:$B,12) -> 0
A12: Disney | B12: 1 Month | C12: Yes | D12: {=AVERAGE(DAY(_xlfn.UNIQUE(_xlfn._xlws.FILTER(Discover!C:C, Discover!J:J = A12,0),1)))} -> 1 | E12: =SUMIFS(Discover!F:F,Discover!J:J,Subscriptions!A12) -> 69.99 | F12: =COUNTIFS(Discover!J:J,Subscriptions!A12,Discover!G:G,"APP") -> 1 | G12: =E12/F12 -> 69.99 | H12: =SUMIFS(Discover!$F:$F,Discover!$J:$J,Subscriptions!$A12,Discover!$B:$B,1) -> 0 | I12: =SUMIFS(Discover!$F:$F,Discover!$J:$J,Subscriptions!$A12,Discover!$B:$B,2) -> 0 | J12: =SUMIFS(Discover!$F:$F,Discover!$J:$J,Subscriptions!$A12,Discover!$B:$B,3) -> 69.99 | K12: =SUMIFS(Discover!$F:$F,Discover!$J:$J,Subscriptions!$A12,Discover!$B:$B,4) -> 0 | L12: =SUMIFS(Discover!$F:$F,Discover!$J:$J,Subscriptions!$A12,Discover!$B:$B,5) -> 0 | M12: =SUMIFS(Discover!$F:$F,Discover!$J:$J,Subscriptions!$A12,Discover!$B:$B,6) -> 0 | N12: =SUMIFS(Discover!$F:$F,Discover!$J:$J,Subscriptions!$A12,Discover!$B:$B,7) -> 0 | O12: =SUMIFS(Discover!$F:$F,Discover!$J:$J,Subscriptions!$A12,Discover!$B:$B,8) -> 0 | P12: =SUMIFS(Discover!$F:$F,Discover!$J:$J,Subscriptions!$A12,Discover!$B:$B,9) -> 0 | Q12: =SUMIFS(Discover!$F:$F,Discover!$J:$J,Subscriptions!$A12,Discover!$B:$B,10) -> 0 | R12: =SUMIFS(Discover!$F:$F,Discover!$J:$J,Subscriptions!$A12,Discover!$B:$B,11) -> 0 | S12: =SUMIFS(Discover!$F:$F,Discover!$J:$J,Subscriptions!$A12,Discover!$B:$B,12) -> 0
A13: Family Fitness | B13: Monthly | C13: No | D13: {=AVERAGE(DAY(_xlfn.UNIQUE(_xlfn._xlws.FILTER(Discover!C:C, Discover!J:J = A13,0),1)))} -> 6.2 | E13: =SUMIFS(Discover!F:F,Discover!J:J,Subscriptions!A13) -> 418.8 | F13: =COUNTIFS(Discover!J:J,Subscriptions!A13,Discover!G:G,"APP") -> 5 | G13: =E13/F13 -> 83.76 | H13: =SUMIFS(Discover!$F:$F,Discover!$J:$J,Subscriptions!$A13,Discover!$B:$B,1) -> 0 | I13: =SUMIFS(Discover!$F:$F,Discover!$J:$J,Subscriptions!$A13,Discover!$B:$B,2) -> 0 | J13: =SUMIFS(Discover!$F:$F,Discover!$J:$J,Subscriptions!$A13,Discover!$B:$B,3) -> 0 | K13: =SUMIFS(Discover!$F:$F,Discover!$J:$J,Subscriptions!$A13,Discover!$B:$B,4) -> 84.95 | L13: =SUMIFS(Discover!$F:$F,Discover!$J:$J,Subscriptions!$A13,Discover!$B:$B,5) -> 94.95 | M13: =SUMIFS(Discover!$F:$F,Discover!$J:$J,Subscriptions!$A13,Discover!$B:$B,6) -> 143.95 | N13: =SUMIFS(Discover!$F:$F,Discover!$J:$J,Subscriptions!$A13,Discover!$B:$B,7) -> 0 | O13: =SUMIFS(Discover!$F:$F,Discover!$J:$J,Subscriptions!$A13,Discover!$B:$B,8) -> 94.95 | P13: =SUMIFS(Discover!$F:$F,Discover!$J:$J,Subscriptions!$A13,Discover!$B:$B,9) -> 0 | Q13: =SUMIFS(Discover!$F:$F,Discover!$J:$J,Subscriptions!$A13,Discover!$B:$B,10) -> 0 | R13: =SUMIFS(Discover!$F:$F,Discover!$J:$J,Subscriptions!$A13,Discover!$B:$B,11) -> 0 | S13: =SUMIFS(Discover!$F:$F,Discover!$J:$J,Subscriptions!$A13,Discover!$B:$B,12) -> 0
A14: Final Fantasy | B14: Monthly | C14: No | D14: {=AVERAGE(DAY(_xlfn.UNIQUE(_xlfn._xlws.FILTER(Discover!C:C, Discover!J:J = A14,0),1)))} -> 9.5 | E14: =SUMIFS(Discover!F:F,Discover!J:J,Subscriptions!A14) -> 155.88 | F14: =COUNTIFS(Discover!J:J,Subscriptions!A14,Discover!G:G,"APP") -> 2 | G14: =E14/F14 -> 77.94 | H14: =SUMIFS(Discover!$F:$F,Discover!$J:$J,Subscriptions!$A14,Discover!$B:$B,1) -> 0 | I14: =SUMIFS(Discover!$F:$F,Discover!$J:$J,Subscriptions!$A14,Discover!$B:$B,2) -> 0 | J14: =SUMIFS(Discover!$F:$F,Discover!$J:$J,Subscriptions!$A14,Discover!$B:$B,3) -> 0 | K14: =SUMIFS(Discover!$F:$F,Discover!$J:$J,Subscriptions!$A14,Discover!$B:$B,4) -> 0 | L14: =SUMIFS(Discover!$F:$F,Discover!$J:$J,Subscriptions!$A14,Discover!$B:$B,5) -> 77.94 | M14: =SUMIFS(Discover!$F:$F,Discover!$J:$J,Subscriptions!$A14,Discover!$B:$B,6) -> 77.94 | N14: =SUMIFS(Discover!$F:$F,Discover!$J:$J,Subscriptions!$A14,Discover!$B:$B,7) -> 0 | O14: =SUMIFS(Discover!$F:$F,Discover!$J:$J,Subscriptions!$A14,Discover!$B:$B,8) -> 0 | P14: =SUMIFS(Discover!$F:$F,Discover!$J:$J,Subscriptions!$A14,Discover!$B:$B,9) -> 0 | Q14: =SUMIFS(Discover!$F:$F,Discover!$J:$J,Subscriptions!$A14,Discover!$B:$B,10) -> 0 | R14: =SUMIFS(Discover!$F:$F,Discover!$J:$J,Subscriptions!$A14,Discover!$B:$B,11) -> 0 | S14: =SUMIFS(Discover!$F:$F,Discover!$J:$J,Subscriptions!$A14,Discover!$B:$B,12) -> 0
A15: Finimize | E15: =SUMIFS(Discover!F:F,Discover!J:J,Subscriptions!A15) -> 79.99 | F15: =COUNTIFS(Discover!J:J,Subscriptions!A15,Discover!G:G,"APP") -> 1 | G15: =E15/F15 -> 79.99 | H15: =SUMIFS(Discover!$F:$F,Discover!$J:$J,Subscriptions!$A15,Discover!$B:$B,1) -> 0 | I15: =SUMIFS(Discover!$F:$F,Discover!$J:$J,Subscriptions!$A15,Discover!$B:$B,2) -> 0 | J15: =SUMIFS(Discover!$F:$F,Discover!$J:$J,Subscriptions!$A15,Discover!$B:$B,3) -> 79.99 | K15: =SUMIFS(Discover!$F:$F,Discover!$J:$J,Subscriptions!$A15,Discover!$B:$B,4) -> 0 | L15: =SUMIFS(Discover!$F:$F,Discover!$J:$J,Subscriptions!$A15,Discover!$B:$B,5) -> 0 | M15: =SUMIFS(Discover!$F:$F,Discover!$J:$J,Subscriptions!$A15,Discover!$B:$B,6) -> 0 | N15: =SUMIFS(Discover!$F:$F,Discover!$J:$J,Subscriptions!$A15,Discover!$B:$B,7) -> 0 | O15: =SUMIFS(Discover!$F:$F,Discover!$J:$J,Subscriptions!$A15,Discover!$B:$B,8) -> 0 | P15: =SUMIFS(Discover!$F:$F,Discover!$J:$J,Subscriptions!$A15,Discover!$B:$B,9) -> 0 | Q15: =SUMIFS(Discover!$F:$F,Discover!$J:$J,Subscriptions!$A15,Discover!$B:$B,10) -> 0 | R15: =SUMIFS(Discover!$F:$F,Discover!$J:$J,Subscriptions!$A15,Discover!$B:$B,11) -> 0 | S15: =SUMIFS(Discover!$F:$F,Discover!$J:$J,Subscriptions!$A15,Discover!$B:$B,12) -> 0
A16: fraud | B16: Monthly | C16: No | D16: {=AVERAGE(DAY(_xlfn.UNIQUE(_xlfn._xlws.FILTER(Discover!C:C, Discover!J:J = A16,0),1)))} -> 14 | E16: =SUMIFS(Discover!F:F,Discover!J:J,Subscriptions!A16) -> 3.99 | F16: =COUNTIFS(Discover!J:J,Subscriptions!A16,Discover!G:G,"APP") -> 1 | G16: =E16/F16 -> 3.99 | H16: =SUMIFS(Discover!$F:$F,Discover!$J:$J,Subscriptions!$A16,Discover!$B:$B,1) -> 0 | I16: =SUMIFS(Discover!$F:$F,Discover!$J:$J,Subscriptions!$A16,Discover!$B:$B,2) -> 0 | J16: =SUMIFS(Discover!$F:$F,Discover!$J:$J,Subscriptions!$A16,Discover!$B:$B,3) -> 0 | K16: =SUMIFS(Discover!$F:$F,Discover!$J:$J,Subscriptions!$A16,Discover!$B:$B,4) -> 0 | L16: =SUMIFS(Discover!$F:$F,Discover!$J:$J,Subscriptions!$A16,Discover!$B:$B,5) -> 0 | M16: =SUMIFS(Discover!$F:$F,Discover!$J:$J,Subscriptions!$A16,Discover!$B:$B,6) -> 0 | N16: =SUMIFS(Discover!$F:$F,Discover!$J:$J,Subscriptions!$A16,Discover!$B:$B,7) -> 0 | O16: =SUMIFS(Discover!$F:$F,Discover!$J:$J,Subscriptions!$A16,Discover!$B:$B,8) -> 3.99 | P16: =SUMIFS(Discover!$F:$F,Discover!$J:$J,Subscriptions!$A16,Discover!$B:$B,9) -> 0 | Q16: =SUMIFS(Discover!$F:$F,Discover!$J:$J,Subscriptions!$A16,Discover!$B:$B,10) -> 0 | R16: =SUMIFS(Discover!$F:$F,Discover!$J:$J,Subscriptions!$A16,Discover!$B:$B,11) -> 0 | S16: =SUMIFS(Discover!$F:$F,Discover!$J:$J,Subscriptions!$A16,Discover!$B:$B,12) -> 0
A17: Funimation | B17: Monthly | C17: No | D17: {=AVERAGE(DAY(_xlfn.UNIQUE(_xlfn._xlws.FILTER(Discover!C:C, Discover!J:J = A17,0),1)))} -> 18 | E17: =SUMIFS(Discover!F:F,Discover!J:J,Subscriptions!A17) -> 8.47 | F17: =COUNTIFS(Discover!J:J,Subscriptions!A17,Discover!G:G,"APP") -> 1 | G17: =E17/F17 -> 8.47 | H17: =SUMIFS(Discover!$F:$F,Discover!$J:$J,Subscriptions!$A17,Discover!$B:$B,1) -> 0 | I17: =SUMIFS(Discover!$F:$F,Discover!$J:$J,Subscriptions!$A17,Discover!$B:$B,2) -> 0 | J17: =SUMIFS(Discover!$F:$F,Discover!$J:$J,Subscriptions!$A17,Discover!$B:$B,3) -> 0 | K17: =SUMIFS(Discover!$F:$F,Discover!$J:$J,Subscriptions!$A17,Discover!$B:$B,4) -> 0 | L17: =SUMIFS(Discover!$F:$F,Discover!$J:$J,Subscriptions!$A17,Discover!$B:$B,5) -> 0 | M17: =SUMIFS(Discover!$F:$F,Discover!$J:$J,Subscriptions!$A17,Discover!$B:$B,6) -> 0 | N17: =SUMIFS(Discover!$F:$F,Discover!$J:$J,Subscriptions!$A17,Discover!$B:$B,7) -> 0 | O17: =SUMIFS(Discover!$F:$F,Discover!$J:$J,Subscriptions!$A17,Discover!$B:$B,8) -> 8.47 | P17: =SUMIFS(Discover!$F:$F,Discover!$J:$J,Subscriptions!$A17,Discover!$B:$B,9) -> 0 | Q17: =SUMIFS(Discover!$F:$F,Discover!$J:$J,Subscriptions!$A17,Discover!$B:$B,10) -> 0 | R17: =SUMIFS(Discover!$F:$F,Discover!$J:$J,Subscriptions!$A17,Discover!$B:$B,11) -> 0 | S17: =SUMIFS(Discover!$F:$F,Discover!$J:$J,Subscriptions!$A17,Discover!$B:$B,12) -> 0
A18: GuitarTuna | B18: Monthly | C18: No | D18: {=AVERAGE(DAY(_xlfn.UNIQUE(_xlfn._xlws.FILTER(Discover!C:C, Discover!J:J = A18,0),1)))} -> 25 | E18: =SUMIFS(Discover!F:F,Discover!J:J,Subscriptions!A18) -> 5.29 | F18: =COUNTIFS(Discover!J:J,Subscriptions!A18,Discover!G:G,"APP") -> 1 | G18: =E18/F18 -> 5.29 | H18: =SUMIFS(Discover!$F:$F,Discover!$J:$J,Subscriptions!$A18,Discover!$B:$B,1) -> 0 | I18: =SUMIFS(Discover!$F:$F,Discover!$J:$J,Subscriptions!$A18,Discover!$B:$B,2) -> 0 | J18: =SUMIFS(Discover!$F:$F,Discover!$J:$J,Subscriptions!$A18,Discover!$B:$B,3) -> 0 | K18: =SUMIFS(Discover!$F:$F,Discover!$J:$J,Subscriptions!$A18,Discover!$B:$B,4) -> 0 | L18: =SUMIFS(Discover!$F:$F,Discover!$J:$J,Subscriptions!$A18,Discover!$B:$B,5) -> 5.29 | M18: =SUMIFS(Discover!$F:$F,Discover!$J:$J,Subscriptions!$A18,Discover!$B:$B,6) -> 0 | N18: =SUMIFS(Discover!$F:$F,Discover!$J:$J,Subscriptions!$A18,Discover!$B:$B,7) -> 0 | O18: =SUMIFS(Discover!$F:$F,Discover!$J:$J,Subscriptions!$A18,Discover!$B:$B,8) -> 0 | P18: =SUMIFS(Discover!$F:$F,Discover!$J:$J,Subscriptions!$A18,Discover!$B:$B,9) -> 0 | Q18: =SUMIFS(Discover!$F:$F,Discover!$J:$J,Subscriptions!$A18,Discover!$B:$B,10) -> 0 | R18: =SUMIFS(Discover!$F:$F,Discover!$J:$J,Subscriptions!$A18,Discover!$B:$B,11) -> 0 | S18: =SUMIFS(Discover!$F:$F,Discover!$J:$J,Subscriptions!$A18,Discover!$B:$B,12) -> 0
A19: HBO | B19: Annual | C19: Yes | D19: {=AVERAGE(DAY(_xlfn.UNIQUE(_xlfn._xlws.FILTER(Discover!C:C, Discover!J:J = A19,0),1)))} -> 11.7 | E19: =SUMIFS(Discover!F:F,Discover!J:J,Subscriptions!A19) -> 156.11 | F19: =COUNTIFS(Discover!J:J,Subscriptions!A19,Discover!G:G,"APP") -> 10 | G19: =E19/F19 -> 15.611 | H19: =SUMIFS(Discover!$F:$F,Discover!$J:$J,Subscriptions!$A19,Discover!$B:$B,1) -> 14.99 | I19: =SUMIFS(Discover!$F:$F,Discover!$J:$J,Subscriptions!$A19,Discover!$B:$B,2) -> 14.99 | J19: =SUMIFS(Discover!$F:$F,Discover!$J:$J,Subscriptions!$A19,Discover!$B:$B,3) -> 14.99 | K19: =SUMIFS(Discover!$F:$F,Discover!$J:$J,Subscriptions!$A19,Discover!$B:$B,4) -> 15.89 | L19: =SUMIFS(Discover!$F:$F,Discover!$J:$J,Subscriptions!$A19,Discover!$B:$B,5) -> 15.89 | M19: =SUMIFS(Discover!$F:$F,Discover!$J:$J,Subscriptions!$A19,Discover!$B:$B,6) -> 15.89 | N19: =SUMIFS(Discover!$F:$F,Discover!$J:$J,Subscriptions!$A19,Discover!$B:$B,7) -> 15.89 | O19: =SUMIFS(Discover!$F:$F,Discover!$J:$J,Subscriptions!$A19,Discover!$B:$B,8) -> 16.01 | P19: =SUMIFS(Discover!$F:$F,Discover!$J:$J,Subscriptions!$A19,Discover!$B:$B,9) -> 15.68 | Q19: =SUMIFS(Discover!$F:$F,Discover!$J:$J,Subscriptions!$A19,Discover!$B:$B,10) -> 15.89 | R19: =SUMIFS(Discover!$F:$F,Discover!$J:$J,Subscriptions!$A19,Discover!$B:$B,11) -> 0 | S19: =SUMIFS(Discover!$F:$F,Discover!$J:$J,Subscriptions!$A19,Discover!$B:$B,12) -> 0
A20: Hulu | B20: Monthly | C20: No | D20: {=AVERAGE(DAY(_xlfn.UNIQUE(_xlfn._xlws.FILTER(Discover!C:C, Discover!J:J = A20,0),1)))} -> 3 | E20: =SUMIFS(Discover!F:F,Discover!J:J,Subscriptions!A20) -> 68.33 | F20: =COUNTIFS(Discover!J:J,Subscriptions!A20,Discover!G:G,"APP") -> 8 | G20: =E20/F20 -> 8.54125 | H20: =SUMIFS(Discover!$F:$F,Discover!$J:$J,Subscriptions!$A20,Discover!$B:$B,1) -> 0 | I20: =SUMIFS(Discover!$F:$F,Discover!$J:$J,Subscriptions!$A20,Discover!$B:$B,2) -> 0 | J20: =SUMIFS(Discover!$F:$F,Discover!$J:$J,Subscriptions!$A20,Discover!$B:$B,3) -> 0 | K20: =SUMIFS(Discover!$F:$F,Discover!$J:$J,Subscriptions!$A20,Discover!$B:$B,4) -> 0.99 | L20: =SUMIFS(Discover!$F:$F,Discover!$J:$J,Subscriptions!$A20,Discover!$B:$B,5) -> 5.99 | M20: =SUMIFS(Discover!$F:$F,Discover!$J:$J,Subscriptions!$A20,Discover!$B:$B,6) -> 0.4 | N20: =SUMIFS(Discover!$F:$F,Discover!$J:$J,Subscriptions!$A20,Discover!$B:$B,7) -> 11.99 | O20: =SUMIFS(Discover!$F:$F,Discover!$J:$J,Subscriptions!$A20,Discover!$B:$B,8) -> 11.99 | P20: =SUMIFS(Discover!$F:$F,Discover!$J:$J,Subscriptions!$A20,Discover!$B:$B,9) -> 11.99 | Q20: =SUMIFS(Discover!$F:$F,Discover!$J:$J,Subscriptions!$A20,Discover!$B:$B,10) -> 11.99 | R20: =SUMIFS(Discover!$F:$F,Discover!$J:$J,Subscriptions!$A20,Discover!$B:$B,11) -> 12.99 | S20: =SUMIFS(Discover!$F:$F,Discover!$J:$J,Subscriptions!$A20,Discover!$B:$B,12) -> 0
A21: Internet | B21: Monthly | C21: No | D21: {=AVERAGE(DAY(_xlfn.UNIQUE(_xlfn._xlws.FILTER(Discover!C:C, Discover!J:J = A21,0),1)))} -> 16 | E21: =SUMIFS(Discover!F:F,Discover!J:J,Subscriptions!A21) -> 50 | F21: =COUNTIFS(Discover!J:J,Subscriptions!A21,Discover!G:G,"APP") -> 1 | G21: =E21/F21 -> 50 | H21: =SUMIFS(Discover!$F:$F,Discover!$J:$J,Subscriptions!$A21,Discover!$B:$B,1) -> 0 | I21: =SUMIFS(Discover!$F:$F,Discover!$J:$J,Subscriptions!$A21,Discover!$B:$B,2) -> 0 | J21: =SUMIFS(Discover!$F:$F,Discover!$J:$J,Subscriptions!$A21,Discover!$B:$B,3) -> 0 | K21: =SUMIFS(Discover!$F:$F,Discover!$J:$J,Subscriptions!$A21,Discover!$B:$B,4) -> 0 | L21: =SUMIFS(Discover!$F:$F,Discover!$J:$J,Subscriptions!$A21,Discover!$B:$B,5) -> 0 | M21: =SUMIFS(Discover!$F:$F,Discover!$J:$J,Subscriptions!$A21,Discover!$B:$B,6) -> 0 | N21: =SUMIFS(Discover!$F:$F,Discover!$J:$J,Subscriptions!$A21,Discover!$B:$B,7) -> 50 | O21: =SUMIFS(Discover!$F:$F,Discover!$J:$J,Subscriptions!$A21,Discover!$B:$B,8) -> 0 | P21: =SUMIFS(Discover!$F:$F,Discover!$J:$J,Subscriptions!$A21,Discover!$B:$B,9) -> 0 | Q21: =SUMIFS(Discover!$F:$F,Discover!$J:$J,Subscriptions!$A21,Discover!$B:$B,10) -> 0 | R21: =SUMIFS(Discover!$F:$F,Discover!$J:$J,Subscriptions!$A21,Discover!$B:$B,11) -> 0 | S21: =SUMIFS(Discover!$F:$F,Discover!$J:$J,Subscriptions!$A21,Discover!$B:$B,12) -> 0
A22: Lifetime Gym | B22: Monthly | C22: Yes | D22: {=AVERAGE(DAY(_xlfn.UNIQUE(_xlfn._xlws.FILTER(Discover!C:C, Discover!J:J = A22,0),1)))} -> 25 | E22: =SUMIFS(Discover!F:F,Discover!J:J,Subscriptions!A22) -> 16.15 | F22: =COUNTIFS(Discover!J:J,Subscriptions!A22,Discover!G:G,"APP") -> 1 | G22: =E22/F22 -> 16.15 | H22: =SUMIFS(Discover!$F:$F,Discover!$J:$J,Subscriptions!$A22,Discover!$B:$B,1) -> 0 | I22: =SUMIFS(Discover!$F:$F,Discover!$J:$J,Subscriptions!$A22,Discover!$B:$B,2) -> 0 | J22: =SUMIFS(Discover!$F:$F,Discover!$J:$J,Subscriptions!$A22,Discover!$B:$B,3) -> 0 | K22: =SUMIFS(Discover!$F:$F,Discover!$J:$J,Subscriptions!$A22,Discover!$B:$B,4) -> 0 | L22: =SUMIFS(Discover!$F:$F,Discover!$J:$J,Subscriptions!$A22,Discover!$B:$B,5) -> 0 | M22: =SUMIFS(Discover!$F:$F,Discover!$J:$J,Subscriptions!$A22,Discover!$B:$B,6) -> 0 | N22: =SUMIFS(Discover!$F:$F,Discover!$J:$J,Subscriptions!$A22,Discover!$B:$B,7) -> 0 | O22: =SUMIFS(Discover!$F:$F,Discover!$J:$J,Subscriptions!$A22,Discover!$B:$B,8) -> 0 | P22: =SUMIFS(Discover!$F:$F,Discover!$J:$J,Subscriptions!$A22,Discover!$B:$B,9) -> 0 | Q22: =SUMIFS(Discover!$F:$F,Discover!$J:$J,Subscriptions!$A22,Discover!$B:$B,10) -> 16.15 | R22: =SUMIFS(Discover!$F:$F,Discover!$J:$J,Subscriptions!$A22,Discover!$B:$B,11) -> 0 | S22: =SUMIFS(Discover!$F:$F,Discover!$J:$J,Subscriptions!$A22,Discover!$B:$B,12) -> 0
A23: Manga | B23: Monthly | C23: No | D23: {=AVERAGE(DAY(_xlfn.UNIQUE(_xlfn._xlws.FILTER(Discover!C:C, Discover!J:J = A23,0),1)))} -> 13.25 | E23: =SUMIFS(Discover!F:F,Discover!J:J,Subscriptions!A23) -> 23.88 | F23: =COUNTIFS(Discover!J:J,Subscriptions!A23,Discover!G:G,"APP") -> 12 | G23: =E23/F23 -> 1.99 | H23: =SUMIFS(Discover!$F:$F,Discover!$J:$J,Subscriptions!$A23,Discover!$B:$B,1) -> 1.99 | I23: =SUMIFS(Discover!$F:$F,Discover!$J:$J,Subscriptions!$A23,Discover!$B:$B,2) -> 3.98 | J23: =SUMIFS(Discover!$F:$F,Discover!$J:$J,Subscriptions!$A23,Discover!$B:$B,3) -> 1.99 | K23: =SUMIFS(Discover!$F:$F,Discover!$J:$J,Subscriptions!$A23,Discover!$B:$B,4) -> 1.99 | L23: =SUMIFS(Discover!$F:$F,Discover!$J:$J,Subscriptions!$A23,Discover!$B:$B,5) -> 1.99 | M23: =SUMIFS(Discover!$F:$F,Discover!$J:$J,Subscriptions!$A23,Discover!$B:$B,6) -> 1.99 | N23: =SUMIFS(Discover!$F:$F,Discover!$J:$J,Subscriptions!$A23,Discover!$B:$B,7) -> 1.99 | O23: =SUMIFS(Discover!$F:$F,Discover!$J:$J,Subscriptions!$A23,Discover!$B:$B,8) -> 1.99 | P23: =SUMIFS(Discover!$F:$F,Discover!$J:$J,Subscriptions!$A23,Discover!$B:$B,9) -> 1.99 | Q23: =SUMIFS(Discover!$F:$F,Discover!$J:$J,Subscriptions!$A23,Discover!$B:$B,10) -> 1.99 | R23: =SUMIFS(Discover!$F:$F,Discover!$J:$J,Subscriptions!$A23,Discover!$B:$B,11) -> 1.99 | S23: =SUMIFS(Discover!$F:$F,Discover!$J:$J,Subscriptions!$A23,Discover!$B:$B,12) -> 0
A24: Netflix | B24: Annual | C24: No | D24: {=AVERAGE(DAY(_xlfn.UNIQUE(_xlfn._xlws.FILTER(Discover!C:C, Discover!J:J = A24,0),1)))} -> 1 | E24: =SUMIFS(Discover!F:F,Discover!J:J,Subscriptions!A24) -> 160.61 | F24: =COUNTIFS(Discover!J:J,Subscriptions!A24,Discover!G:G,"APP") -> 11 | G24: =E24/F24 -> 14.600909 | H24: =SUMIFS(Discover!$F:$F,Discover!$J:$J,Subscriptions!$A24,Discover!$B:$B,1) -> 13.99 | I24: =SUMIFS(Discover!$F:$F,Discover!$J:$J,Subscriptions!$A24,Discover!$B:$B,2) -> 13.99 | J24: =SUMIFS(Discover!$F:$F,Discover!$J:$J,Subscriptions!$A24,Discover!$B:$B,3) -> 13.99 | K24: =SUMIFS(Discover!$F:$F,Discover!$J:$J,Subscriptions!$A24,Discover!$B:$B,4) -> 14.83 | L24: =SUMIFS(Discover!$F:$F,Discover!$J:$J,Subscriptions!$A24,Discover!$B:$B,5) -> 14.83 | M24: =SUMIFS(Discover!$F:$F,Discover!$J:$J,Subscriptions!$A24,Discover!$B:$B,6) -> 14.83 | N24: =SUMIFS(Discover!$F:$F,Discover!$J:$J,Subscriptions!$A24,Discover!$B:$B,7) -> 14.83 | O24: =SUMIFS(Discover!$F:$F,Discover!$J:$J,Subscriptions!$A24,Discover!$B:$B,8) -> 14.83 | P24: =SUMIFS(Discover!$F:$F,Discover!$J:$J,Subscriptions!$A24,Discover!$B:$B,9) -> 14.83 | Q24: =SUMIFS(Discover!$F:$F,Discover!$J:$J,Subscriptions!$A24,Discover!$B:$B,10) -> 14.83 | R24: =SUMIFS(Discover!$F:$F,Discover!$J:$J,Subscriptions!$A24,Discover!$B:$B,11) -> 14.83 | S24: =SUMIFS(Discover!$F:$F,Discover!$J:$J,Subscriptions!$A24,Discover!$B:$B,12) -> 0
A25: News | B25: Monthly | C25: Yes | D25: {=AVERAGE(DAY(_xlfn.UNIQUE(_xlfn._xlws.FILTER(Discover!C:C, Discover!J:J = A25,0),1)))} -> 2 | E25: =SUMIFS(Discover!F:F,Discover!J:J,Subscriptions!A25) -> 60 | F25: =COUNTIFS(Discover!J:J,Subscriptions!A25,Discover!G:G,"APP") -> 6 | G25: =E25/F25 -> 10 | H25: =SUMIFS(Discover!$F:$F,Discover!$J:$J,Subscriptions!$A25,Discover!$B:$B,1) -> 0 | I25: =SUMIFS(Discover!$F:$F,Discover!$J:$J,Subscriptions!$A25,Discover!$B:$B,2) -> 0 | J25: =SUMIFS(Discover!$F:$F,Discover!$J:$J,Subscriptions!$A25,Discover!$B:$B,3) -> 0 | K25: =SUMIFS(Discover!$F:$F,Discover!$J:$J,Subscriptions!$A25,Discover!$B:$B,4) -> 0 | L25: =SUMIFS(Discover!$F:$F,Discover!$J:$J,Subscriptions!$A25,Discover!$B:$B,5) -> 0 | M25: =SUMIFS(Discover!$F:$F,Discover!$J:$J,Subscriptions!$A25,Discover!$B:$B,6) -> 10 | N25: =SUMIFS(Discover!$F:$F,Discover!$J:$J,Subscriptions!$A25,Discover!$B:$B,7) -> 10 | O25: =SUMIFS(Discover!$F:$F,Discover!$J:$J,Subscriptions!$A25,Discover!$B:$B,8) -> 10 | P25: =SUMIFS(Discover!$F:$F,Discover!$J:$J,Subscriptions!$A25,Discover!$B:$B,9) -> 10 | Q25: =SUMIFS(Discover!$F:$F,Discover!$J:$J,Subscriptions!$A25,Discover!$B:$B,10) -> 10 | R25: =SUMIFS(Discover!$F:$F,Discover!$J:$J,Subscriptions!$A25,Discover!$B:$B,11) -> 10 | S25: =SUMIFS(Discover!$F:$F,Discover!$J:$J,Subscriptions!$A25,Discover!$B:$B,12) -> 0
A26: oyf | B26: Monthly | C26: Yes | D26: {=AVERAGE(DAY(_xlfn.UNIQUE(_xlfn._xlws.FILTER(Discover!C:C, Discover!J:J = A26,0),1)))} -> 14.5 | E26: =SUMIFS(Discover!F:F,Discover!J:J,Subscriptions!A26) -> 102.08 | F26: =COUNTIFS(Discover!J:J,Subscriptions!A26,Discover!G:G,"APP") -> 5 | G26: =E26/F26 -> 20.416 | H26: =SUMIFS(Discover!$F:$F,Discover!$J:$J,Subscriptions!$A26,Discover!$B:$B,1) -> 0 | I26: =SUMIFS(Discover!$F:$F,Discover!$J:$J,Subscriptions!$A26,Discover!$B:$B,2) -> 0 | J26: =SUMIFS(Discover!$F:$F,Discover!$J:$J,Subscriptions!$A26,Discover!$B:$B,3) -> 0 | K26: =SUMIFS(Discover!$F:$F,Discover!$J:$J,Subscriptions!$A26,Discover!$B:$B,4) -> 0 | L26: =SUMIFS(Discover!$F:$F,Discover!$J:$J,Subscriptions!$A26,Discover!$B:$B,5) -> 0 | M26: =SUMIFS(Discover!$F:$F,Discover!$J:$J,Subscriptions!$A26,Discover!$B:$B,6) -> 47.11 | N26: =SUMIFS(Discover!$F:$F,Discover!$J:$J,Subscriptions!$A26,Discover!$B:$B,7) -> 19.99 | O26: =SUMIFS(Discover!$F:$F,Discover!$J:$J,Subscriptions!$A26,Discover!$B:$B,8) -> 4.99 | P26: =SUMIFS(Discover!$F:$F,Discover!$J:$J,Subscriptions!$A26,Discover!$B:$B,9) -> 18.99 | Q26: =SUMIFS(Discover!$F:$F,Discover!$J:$J,Subscriptions!$A26,Discover!$B:$B,10) -> 11 | R26: =SUMIFS(Discover!$F:$F,Discover!$J:$J,Subscriptions!$A26,Discover!$B:$B,11) -> 0 | S26: =SUMIFS(Discover!$F:$F,Discover!$J:$J,Subscriptions!$A26,Discover!$B:$B,12) -> 0
A27: Roadtrippers | D27: {=AVERAGE(DAY(_xlfn.UNIQUE(_xlfn._xlws.FILTER(Discover!C:C, Discover!J:J = A27,0),1)))} -> 16 | E27: =SUMIFS(Discover!F:F,Discover!J:J,Subscriptions!A27) -> 31.79 | F27: =COUNTIFS(Discover!J:J,Subscriptions!A27,Discover!G:G,"APP") -> 1 | G27: =E27/F27 -> 31.79 | H27: =SUMIFS(Discover!$F:$F,Discover!$J:$J,Subscriptions!$A27,Discover!$B:$B,1) -> 0 | I27: =SUMIFS(Discover!$F:$F,Discover!$J:$J,Subscriptions!$A27,Discover!$B:$B,2) -> 0 | J27: =SUMIFS(Discover!$F:$F,Discover!$J:$J,Subscriptions!$A27,Discover!$B:$B,3) -> 0 | K27: =SUMIFS(Discover!$F:$F,Discover!$J:$J,Subscriptions!$A27,Discover!$B:$B,4) -> 0 | L27: =SUMIFS(Discover!$F:$F,Discover!$J:$J,Subscriptions!$A27,Discover!$B:$B,5) -> 31.79 | M27: =SUMIFS(Discover!$F:$F,Discover!$J:$J,Subscriptions!$A27,Discover!$B:$B,6) -> 0 | N27: =SUMIFS(Discover!$F:$F,Discover!$J:$J,Subscriptions!$A27,Discover!$B:$B,7) -> 0 | O27: =SUMIFS(Discover!$F:$F,Discover!$J:$J,Subscriptions!$A27,Discover!$B:$B,8) -> 0 | P27: =SUMIFS(Discover!$F:$F,Discover!$J:$J,Subscriptions!$A27,Discover!$B:$B,9) -> 0 | Q27: =SUMIFS(Discover!$F:$F,Discover!$J:$J,Subscriptions!$A27,Discover!$B:$B,10) -> 0 | R27: =SUMIFS(Discover!$F:$F,Discover!$J:$J,Subscriptions!$A27,Discover!$B:$B,11) -> 0 | S27: =SUMIFS(Discover!$F:$F,Discover!$J:$J,Subscriptions!$A27,Discover!$B:$B,12) -> 0
A28: Roku | D28: {=AVERAGE(DAY(_xlfn.UNIQUE(_xlfn._xlws.FILTER(Discover!C:C, Discover!J:J = A28,0),1)))} -> 21 | E28: =SUMIFS(Discover!F:F,Discover!J:J,Subscriptions!A28) -> 7.99 | F28: =COUNTIFS(Discover!J:J,Subscriptions!A28,Discover!G:G,"APP") -> 1 | G28: =E28/F28 -> 7.99 | H28: =SUMIFS(Discover!$F:$F,Discover!$J:$J,Subscriptions!$A28,Discover!$B:$B,1) -> 0 | I28: =SUMIFS(Discover!$F:$F,Discover!$J:$J,Subscriptions!$A28,Discover!$B:$B,2) -> 0 | J28: =SUMIFS(Discover!$F:$F,Discover!$J:$J,Subscriptions!$A28,Discover!$B:$B,3) -> 0 | K28: =SUMIFS(Discover!$F:$F,Discover!$J:$J,Subscriptions!$A28,Discover!$B:$B,4) -> 0 | L28: =SUMIFS(Discover!$F:$F,Discover!$J:$J,Subscriptions!$A28,Discover!$B:$B,5) -> 0 | M28: =SUMIFS(Discover!$F:$F,Discover!$J:$J,Subscriptions!$A28,Discover!$B:$B,6) -> 0 | N28: =SUMIFS(Discover!$F:$F,Discover!$J:$J,Subscriptions!$A28,Discover!$B:$B,7) -> 0 | O28: =SUMIFS(Discover!$F:$F,Discover!$J:$J,Subscriptions!$A28,Discover!$B:$B,8) -> 0 | P28: =SUMIFS(Discover!$F:$F,Discover!$J:$J,Subscriptions!$A28,Discover!$B:$B,9) -> 0 | Q28: =SUMIFS(Discover!$F:$F,Discover!$J:$J,Subscriptions!$A28,Discover!$B:$B,10) -> 7.99 | R28: =SUMIFS(Discover!$F:$F,Discover!$J:$J,Subscriptions!$A28,Discover!$B:$B,11) -> 0 | S28: =SUMIFS(Discover!$F:$F,Discover!$J:$J,Subscriptions!$A28,Discover!$B:$B,12) -> 0
A29: Spotify | D29: {=AVERAGE(DAY(_xlfn.UNIQUE(_xlfn._xlws.FILTER(Discover!C:C, Discover!J:J = A29,0),1)))} -> 1.0909091 | E29: =SUMIFS(Discover!F:F,Discover!J:J,Subscriptions!A29) -> 109.89 | F29: =COUNTIFS(Discover!J:J,Subscriptions!A29,Discover!G:G,"APP") -> 11 | G29: =E29/F29 -> 9.99 | H29: =SUMIFS(Discover!$F:$F,Discover!$J:$J,Subscriptions!$A29,Discover!$B:$B,1) -> 9.99 | I29: =SUMIFS(Discover!$F:$F,Discover!$J:$J,Subscriptions!$A29,Discover!$B:$B,2) -> 9.99 | J29: =SUMIFS(Discover!$F:$F,Discover!$J:$J,Subscriptions!$A29,Discover!$B:$B,3) -> 9.99 | K29: =SUMIFS(Discover!$F:$F,Discover!$J:$J,Subscriptions!$A29,Discover!$B:$B,4) -> 9.99 | L29: =SUMIFS(Discover!$F:$F,Discover!$J:$J,Subscriptions!$A29,Discover!$B:$B,5) -> 9.99 | M29: =SUMIFS(Discover!$F:$F,Discover!$J:$J,Subscriptions!$A29,Discover!$B:$B,6) -> 9.99 | N29: =SUMIFS(Discover!$F:$F,Discover!$J:$J,Subscriptions!$A29,Discover!$B:$B,7) -> 9.99 | O29: =SUMIFS(Discover!$F:$F,Discover!$J:$J,Subscriptions!$A29,Discover!$B:$B,8) -> 9.99 | P29: =SUMIFS(Discover!$F:$F,Discover!$J:$J,Subscriptions!$A29,Discover!$B:$B,9) -> 9.99 | Q29: =SUMIFS(Discover!$F:$F,Discover!$J:$J,Subscriptions!$A29,Discover!$B:$B,10) -> 9.99 | R29: =SUMIFS(Discover!$F:$F,Discover!$J:$J,Subscriptions!$A29,Discover!$B:$B,11) -> 9.99 | S29: =SUMIFS(Discover!$F:$F,Discover!$J:$J,Subscriptions!$A29,Discover!$B:$B,12) -> 0
A30: State Farm | D30: {=AVERAGE(DAY(_xlfn.UNIQUE(_xlfn._xlws.FILTER(Discover!C:C, Discover!J:J = A30,0),1)))} -> 3.5454545 | E30: =SUMIFS(Discover!F:F,Discover!J:J,Subscriptions!A30) -> 969.08 | F30: =COUNTIFS(Discover!J:J,Subscriptions!A30,Discover!G:G,"APP") -> 11 | G30: =E30/F30 -> 88.098182 | H30: =SUMIFS(Discover!$F:$F,Discover!$J:$J,Subscriptions!$A30,Discover!$B:$B,1) -> 91.78 | I30: =SUMIFS(Discover!$F:$F,Discover!$J:$J,Subscriptions!$A30,Discover!$B:$B,2) -> 91.78 | J30: =SUMIFS(Discover!$F:$F,Discover!$J:$J,Subscriptions!$A30,Discover!$B:$B,3) -> 91.78 | K30: =SUMIFS(Discover!$F:$F,Discover!$J:$J,Subscriptions!$A30,Discover!$B:$B,4) -> 91.78 | L30: =SUMIFS(Discover!$F:$F,Discover!$J:$J,Subscriptions!$A30,Discover!$B:$B,5) -> 91.78 | M30: =SUMIFS(Discover!$F:$F,Discover!$J:$J,Subscriptions!$A30,Discover!$B:$B,6) -> 69.88 | N30: =SUMIFS(Discover!$F:$F,Discover!$J:$J,Subscriptions!$A30,Discover!$B:$B,7) -> 92.07 | O30: =SUMIFS(Discover!$F:$F,Discover!$J:$J,Subscriptions!$A30,Discover!$B:$B,8) -> 92.07 | P30: =SUMIFS(Discover!$F:$F,Discover!$J:$J,Subscriptions!$A30,Discover!$B:$B,9) -> 68.52 | Q30: =SUMIFS(Discover!$F:$F,Discover!$J:$J,Subscriptions!$A30,Discover!$B:$B,10) -> 84.85 | R30: =SUMIFS(Discover!$F:$F,Discover!$J:$J,Subscriptions!$A30,Discover!$B:$B,11) -> 102.79 | S30: =SUMIFS(Discover!$F:$F,Discover!$J:$J,Subscriptions!$A30,Discover!$B:$B,12) -> 0
A31: Storage | D31: {=AVERAGE(DAY(_xlfn.UNIQUE(_xlfn._xlws.FILTER(Discover!C:C, Discover!J:J = A31,0),1)))} -> 17.2 | E31: =SUMIFS(Discover!F:F,Discover!J:J,Subscriptions!A31) -> 396.27 | F31: =COUNTIFS(Discover!J:J,Subscriptions!A31,Discover!G:G,"APP") -> 3 | G31: =E31/F31 -> 132.09 | H31: =SUMIFS(Discover!$F:$F,Discover!$J:$J,Subscriptions!$A31,Discover!$B:$B,1) -> 0 | I31: =SUMIFS(Discover!$F:$F,Discover!$J:$J,Subscriptions!$A31,Discover!$B:$B,2) -> 0 | J31: =SUMIFS(Discover!$F:$F,Discover!$J:$J,Subscriptions!$A31,Discover!$B:$B,3) -> 0 | K31: =SUMIFS(Discover!$F:$F,Discover!$J:$J,Subscriptions!$A31,Discover!$B:$B,4) -> 101.4 | L31: =SUMIFS(Discover!$F:$F,Discover!$J:$J,Subscriptions!$A31,Discover!$B:$B,5) -> 216.87 | M31: =SUMIFS(Discover!$F:$F,Discover!$J:$J,Subscriptions!$A31,Discover!$B:$B,6) -> 78 | N31: =SUMIFS(Discover!$F:$F,Discover!$J:$J,Subscriptions!$A31,Discover!$B:$B,7) -> 0 | O31: =SUMIFS(Discover!$F:$F,Discover!$J:$J,Subscriptions!$A31,Discover!$B:$B,8) -> 0 | P31: =SUMIFS(Discover!$F:$F,Discover!$J:$J,Subscriptions!$A31,Discover!$B:$B,9) -> 0 | Q31: =SUMIFS(Discover!$F:$F,Discover!$J:$J,Subscriptions!$A31,Discover!$B:$B,10) -> 0 | R31: =SUMIFS(Discover!$F:$F,Discover!$J:$J,Subscriptions!$A31,Discover!$B:$B,11) -> 0 | S31: =SUMIFS(Discover!$F:$F,Discover!$J:$J,Subscriptions!$A31,Discover!$B:$B,12) -> 0
A32: Stretch Zone | D32: {=AVERAGE(DAY(_xlfn.UNIQUE(_xlfn._xlws.FILTER(Discover!C:C, Discover!J:J = A32,0),1)))} -> 25 | E32: =SUMIFS(Discover!F:F,Discover!J:J,Subscriptions!A32) -> 640 | F32: =COUNTIFS(Discover!J:J,Subscriptions!A32,Discover!G:G,"APP") -> 2 | G32: =E32/F32 -> 320 | H32: =SUMIFS(Discover!$F:$F,Discover!$J:$J,Subscriptions!$A32,Discover!$B:$B,1) -> 0 | I32: =SUMIFS(Discover!$F:$F,Discover!$J:$J,Subscriptions!$A32,Discover!$B:$B,2) -> 0 | J32: =SUMIFS(Discover!$F:$F,Discover!$J:$J,Subscriptions!$A32,Discover!$B:$B,3) -> 0 | K32: =SUMIFS(Discover!$F:$F,Discover!$J:$J,Subscriptions!$A32,Discover!$B:$B,4) -> 0 | L32: =SUMIFS(Discover!$F:$F,Discover!$J:$J,Subscriptions!$A32,Discover!$B:$B,5) -> 0 | M32: =SUMIFS(Discover!$F:$F,Discover!$J:$J,Subscriptions!$A32,Discover!$B:$B,6) -> 0 | N32: =SUMIFS(Discover!$F:$F,Discover!$J:$J,Subscriptions!$A32,Discover!$B:$B,7) -> 0 | O32: =SUMIFS(Discover!$F:$F,Discover!$J:$J,Subscriptions!$A32,Discover!$B:$B,8) -> 0 | P32: =SUMIFS(Discover!$F:$F,Discover!$J:$J,Subscriptions!$A32,Discover!$B:$B,9) -> 320 | Q32: =SUMIFS(Discover!$F:$F,Discover!$J:$J,Subscriptions!$A32,Discover!$B:$B,10) -> 320 | R32: =SUMIFS(Discover!$F:$F,Discover!$J:$J,Subscriptions!$A32,Discover!$B:$B,11) -> 0 | S32: =SUMIFS(Discover!$F:$F,Discover!$J:$J,Subscriptions!$A32,Discover!$B:$B,12) -> 0
A33: The Athletic | D33: {=AVERAGE(DAY(_xlfn.UNIQUE(_xlfn._xlws.FILTER(Discover!C:C, Discover!J:J = A33,0),1)))} -> 3 | E33: =SUMIFS(Discover!F:F,Discover!J:J,Subscriptions!A33) -> 63.59 | F33: =COUNTIFS(Discover!J:J,Subscriptions!A33,Discover!G:G,"APP") -> 1 | G33: =E33/F33 -> 63.59 | H33: =SUMIFS(Discover!$F:$F,Discover!$J:$J,Subscriptions!$A33,Discover!$B:$B,1) -> 0 | I33: =SUMIFS(Discover!$F:$F,Discover!$J:$J,Subscriptions!$A33,Discover!$B:$B,2) -> 0 | J33: =SUMIFS(Discover!$F:$F,Discover!$J:$J,Subscriptions!$A33,Discover!$B:$B,3) -> 0 | K33: =SUMIFS(Discover!$F:$F,Discover!$J:$J,Subscriptions!$A33,Discover!$B:$B,4) -> 0 | L33: =SUMIFS(Discover!$F:$F,Discover!$J:$J,Subscriptions!$A33,Discover!$B:$B,5) -> 0 | M33: =SUMIFS(Discover!$F:$F,Discover!$J:$J,Subscriptions!$A33,Discover!$B:$B,6) -> 0 | N33: =SUMIFS(Discover!$F:$F,Discover!$J:$J,Subscriptions!$A33,Discover!$B:$B,7) -> 0 | O33: =SUMIFS(Discover!$F:$F,Discover!$J:$J,Subscriptions!$A33,Discover!$B:$B,8) -> 63.59 | P33: =SUMIFS(Discover!$F:$F,Discover!$J:$J,Subscriptions!$A33,Discover!$B:$B,9) -> 0 | Q33: =SUMIFS(Discover!$F:$F,Discover!$J:$J,Subscriptions!$A33,Discover!$B:$B,10) -> 0 | R33: =SUMIFS(Discover!$F:$F,Discover!$J:$J,Subscriptions!$A33,Discover!$B:$B,11) -> 0 | S33: =SUMIFS(Discover!$F:$F,Discover!$J:$J,Subscriptions!$A33,Discover!$B:$B,12) -> 0
A34: Tinder | D34: {=AVERAGE(DAY(_xlfn.UNIQUE(_xlfn._xlws.FILTER(Discover!C:C, Discover!J:J = A34,0),1)))} -> 7 | E34: =SUMIFS(Discover!F:F,Discover!J:J,Subscriptions!A34) -> 47.68 | F34: =COUNTIFS(Discover!J:J,Subscriptions!A34,Discover!G:G,"APP") -> 2 | G34: =E34/F34 -> 23.84 | H34: =SUMIFS(Discover!$F:$F,Discover!$J:$J,Subscriptions!$A34,Discover!$B:$B,1) -> 0 | I34: =SUMIFS(Discover!$F:$F,Discover!$J:$J,Subscriptions!$A34,Discover!$B:$B,2) -> 0 | J34: =SUMIFS(Discover!$F:$F,Discover!$J:$J,Subscriptions!$A34,Discover!$B:$B,3) -> 0 | K34: =SUMIFS(Discover!$F:$F,Discover!$J:$J,Subscriptions!$A34,Discover!$B:$B,4) -> 0 | L34: =SUMIFS(Discover!$F:$F,Discover!$J:$J,Subscriptions!$A34,Discover!$B:$B,5) -> 0 | M34: =SUMIFS(Discover!$F:$F,Discover!$J:$J,Subscriptions!$A34,Discover!$B:$B,6) -> 0 | N34: =SUMIFS(Discover!$F:$F,Discover!$J:$J,Subscriptions!$A34,Discover!$B:$B,7) -> 0 | O34: =SUMIFS(Discover!$F:$F,Discover!$J:$J,Subscriptions!$A34,Discover!$B:$B,8) -> 31.79 | P34: =SUMIFS(Discover!$F:$F,Discover!$J:$J,Subscriptions!$A34,Discover!$B:$B,9) -> 15.89 | Q34: =SUMIFS(Discover!$F:$F,Discover!$J:$J,Subscriptions!$A34,Discover!$B:$B,10) -> 0 | R34: =SUMIFS(Discover!$F:$F,Discover!$J:$J,Subscriptions!$A34,Discover!$B:$B,11) -> 0 | S34: =SUMIFS(Discover!$F:$F,Discover!$J:$J,Subscriptions!$A34,Discover!$B:$B,12) -> 0
A35: T-Mobile | D35: {=AVERAGE(DAY(_xlfn.UNIQUE(_xlfn._xlws.FILTER(Discover!C:C, Discover!J:J = A35,0),1)))} -> 15 | E35: =SUMIFS(Discover!F:F,Discover!J:J,Subscriptions!A35) -> 597.5 | F35: =COUNTIFS(Discover!J:J,Subscriptions!A35,Discover!G:G,"APP") -> 7 | G35: =E35/F35 -> 85.357143 | H35: =SUMIFS(Discover!$F:$F,Discover!$J:$J,Subscriptions!$A35,Discover!$B:$B,1) -> 0 | I35: =SUMIFS(Discover!$F:$F,Discover!$J:$J,Subscriptions!$A35,Discover!$B:$B,2) -> 86.25 | J35: =SUMIFS(Discover!$F:$F,Discover!$J:$J,Subscriptions!$A35,Discover!$B:$B,3) -> 86.25 | K35: =SUMIFS(Discover!$F:$F,Discover!$J:$J,Subscriptions!$A35,Discover!$B:$B,4) -> 0 | L35: =SUMIFS(Discover!$F:$F,Discover!$J:$J,Subscriptions!$A35,Discover!$B:$B,5) -> 86.25 | M35: =SUMIFS(Discover!$F:$F,Discover!$J:$J,Subscriptions!$A35,Discover!$B:$B,6) -> 86.25 | N35: =SUMIFS(Discover!$F:$F,Discover!$J:$J,Subscriptions!$A35,Discover!$B:$B,7) -> 86.25 | O35: =SUMIFS(Discover!$F:$F,Discover!$J:$J,Subscriptions!$A35,Discover!$B:$B,8) -> 0 | P35: =SUMIFS(Discover!$F:$F,Discover!$J:$J,Subscriptions!$A35,Discover!$B:$B,9) -> 86.25 | Q35: =SUMIFS(Discover!$F:$F,Discover!$J:$J,Subscriptions!$A35,Discover!$B:$B,10) -> 80 | R35: =SUMIFS(Discover!$F:$F,Discover!$J:$J,Subscriptions!$A35,Discover!$B:$B,11) -> 0 | S35: =SUMIFS(Discover!$F:$F,Discover!$J:$J,Subscriptions!$A35,Discover!$B:$B,12) -> 0
A36: USTA | D36: {=AVERAGE(DAY(_xlfn.UNIQUE(_xlfn._xlws.FILTER(Discover!C:C, Discover!J:J = A36,0),1)))} -> 1 | E36: =SUMIFS(Discover!F:F,Discover!J:J,Subscriptions!A36) -> 44 | F36: =COUNTIFS(Discover!J:J,Subscriptions!A36,Discover!G:G,"APP") -> 1 | G36: =E36/F36 -> 44 | H36: =SUMIFS(Discover!$F:$F,Discover!$J:$J,Subscriptions!$A36,Discover!$B:$B,1) -> 0 | I36: =SUMIFS(Discover!$F:$F,Discover!$J:$J,Subscriptions!$A36,Discover!$B:$B,2) -> 0 | J36: =SUMIFS(Discover!$F:$F,Discover!$J:$J,Subscriptions!$A36,Discover!$B:$B,3) -> 0 | K36: =SUMIFS(Discover!$F:$F,Discover!$J:$J,Subscriptions!$A36,Discover!$B:$B,4) -> 0 | L36: =SUMIFS(Discover!$F:$F,Discover!$J:$J,Subscriptions!$A36,Discover!$B:$B,5) -> 44 | M36: =SUMIFS(Discover!$F:$F,Discover!$J:$J,Subscriptions!$A36,Discover!$B:$B,6) -> 0 | N36: =SUMIFS(Discover!$F:$F,Discover!$J:$J,Subscriptions!$A36,Discover!$B:$B,7) -> 0 | O36: =SUMIFS(Discover!$F:$F,Discover!$J:$J,Subscriptions!$A36,Discover!$B:$B,8) -> 0 | P36: =SUMIFS(Discover!$F:$F,Discover!$J:$J,Subscriptions!$A36,Discover!$B:$B,9) -> 0 | Q36: =SUMIFS(Discover!$F:$F,Discover!$J:$J,Subscriptions!$A36,Discover!$B:$B,10) -> 0 | R36: =SUMIFS(Discover!$F:$F,Discover!$J:$J,Subscriptions!$A36,Discover!$B:$B,11) -> 0 | S36: =SUMIFS(Discover!$F:$F,Discover!$J:$J,Subscriptions!$A36,Discover!$B:$B,12) -> 0
A37: Verizon Internet | E37: =SUMIFS(Discover!F:F,Discover!J:J,Subscriptions!A37) -> 100 | F37: =COUNTIFS(Discover!J:J,Subscriptions!A37,Discover!G:G,"APP") -> 2 | G37: =E37/F37 -> 50 | H37: =SUMIFS(Discover!$F:$F,Discover!$J:$J,Subscriptions!$A37,Discover!$B:$B,1) -> 0 | I37: =SUMIFS(Discover!$F:$F,Discover!$J:$J,Subscriptions!$A37,Discover!$B:$B,2) -> 0 | J37: =SUMIFS(Discover!$F:$F,Discover!$J:$J,Subscriptions!$A37,Discover!$B:$B,3) -> 0 | K37: =SUMIFS(Discover!$F:$F,Discover!$J:$J,Subscriptions!$A37,Discover!$B:$B,4) -> 0 | L37: =SUMIFS(Discover!$F:$F,Discover!$J:$J,Subscriptions!$A37,Discover!$B:$B,5) -> 0 | M37: =SUMIFS(Discover!$F:$F,Discover!$J:$J,Subscriptions!$A37,Discover!$B:$B,6) -> 50 | N37: =SUMIFS(Discover!$F:$F,Discover!$J:$J,Subscriptions!$A37,Discover!$B:$B,7) -> 0 | O37: =SUMIFS(Discover!$F:$F,Discover!$J:$J,Subscriptions!$A37,Discover!$B:$B,8) -> 50 | P37: =SUMIFS(Discover!$F:$F,Discover!$J:$J,Subscriptions!$A37,Discover!$B:$B,9) -> 0 | Q37: =SUMIFS(Discover!$F:$F,Discover!$J:$J,Subscriptions!$A37,Discover!$B:$B,10) -> 0 | R37: =SUMIFS(Discover!$F:$F,Discover!$J:$J,Subscriptions!$A37,Discover!$B:$B,11) -> 0 | S37: =SUMIFS(Discover!$F:$F,Discover!$J:$J,Subscriptions!$A37,Discover!$B:$B,12) -> 0
A38: Webull | E38: =SUMIFS(Discover!F:F,Discover!J:J,Subscriptions!A38) -> 7.96 | F38: =COUNTIFS(Discover!J:J,Subscriptions!A38,Discover!G:G,"APP") -> 4 | G38: =E38/F38 -> 1.99 | H38: =SUMIFS(Discover!$F:$F,Discover!$J:$J,Subscriptions!$A38,Discover!$B:$B,1) -> 0 | I38: =SUMIFS(Discover!$F:$F,Discover!$J:$J,Subscriptions!$A38,Discover!$B:$B,2) -> 1.99 | J38: =SUMIFS(Discover!$F:$F,Discover!$J:$J,Subscriptions!$A38,Discover!$B:$B,3) -> 0 | K38: =SUMIFS(Discover!$F:$F,Discover!$J:$J,Subscriptions!$A38,Discover!$B:$B,4) -> 1.99 | L38: =SUMIFS(Discover!$F:$F,Discover!$J:$J,Subscriptions!$A38,Discover!$B:$B,5) -> 1.99 | M38: =SUMIFS(Discover!$F:$F,Discover!$J:$J,Subscriptions!$A38,Discover!$B:$B,6) -> 1.99 | N38: =SUMIFS(Discover!$F:$F,Discover!$J:$J,Subscriptions!$A38,Discover!$B:$B,7) -> 0 | O38: =SUMIFS(Discover!$F:$F,Discover!$J:$J,Subscriptions!$A38,Discover!$B:$B,8) -> 0 | P38: =SUMIFS(Discover!$F:$F,Discover!$J:$J,Subscriptions!$A38,Discover!$B:$B,9) -> 0 | Q38: =SUMIFS(Discover!$F:$F,Discover!$J:$J,Subscriptions!$A38,Discover!$B:$B,10) -> 0 | R38: =SUMIFS(Discover!$F:$F,Discover!$J:$J,Subscriptions!$A38,Discover!$B:$B,11) -> 0 | S38: =SUMIFS(Discover!$F:$F,Discover!$J:$J,Subscriptions!$A38,Discover!$B:$B,12) -> 0
A39: Wolfram | E39: =SUMIFS(Discover!F:F,Discover!J:J,Subscriptions!A39) -> 13.98 | F39: =COUNTIFS(Discover!J:J,Subscriptions!A39,Discover!G:G,"APP") -> 2 | G39: =E39/F39 -> 6.99 | H39: =SUMIFS(Discover!$F:$F,Discover!$J:$J,Subscriptions!$A39,Discover!$B:$B,1) -> 0 | I39: =SUMIFS(Discover!$F:$F,Discover!$J:$J,Subscriptions!$A39,Discover!$B:$B,2) -> 0 | J39: =SUMIFS(Discover!$F:$F,Discover!$J:$J,Subscriptions!$A39,Discover!$B:$B,3) -> 6.99 | K39: =SUMIFS(Discover!$F:$F,Discover!$J:$J,Subscriptions!$A39,Discover!$B:$B,4) -> 6.99 | L39: =SUMIFS(Discover!$F:$F,Discover!$J:$J,Subscriptions!$A39,Discover!$B:$B,5) -> 0 | M39: =SUMIFS(Discover!$F:$F,Discover!$J:$J,Subscriptions!$A39,Discover!$B:$B,6) -> 0 | N39: =SUMIFS(Discover!$F:$F,Discover!$J:$J,Subscriptions!$A39,Discover!$B:$B,7) -> 0 | O39: =SUMIFS(Discover!$F:$F,Discover!$J:$J,Subscriptions!$A39,Discover!$B:$B,8) -> 0 | P39: =SUMIFS(Discover!$F:$F,Discover!$J:$J,Subscriptions!$A39,Discover!$B:$B,9) -> 0 | Q39: =SUMIFS(Discover!$F:$F,Discover!$J:$J,Subscriptions!$A39,Discover!$B:$B,10) -> 0 | R39: =SUMIFS(Discover!$F:$F,Discover!$J:$J,Subscriptions!$A39,Discover!$B:$B,11) -> 0 | S39: =SUMIFS(Discover!$F:$F,Discover!$J:$J,Subscriptions!$A39,Discover!$B:$B,12) -> 0
A40: Youtube TV | E40: =SUMIFS(Discover!F:F,Discover!J:J,Subscriptions!A40) -> 159.94 | F40: =COUNTIFS(Discover!J:J,Subscriptions!A40,Discover!G:G,"APP") -> 3 | G40: =E40/F40 -> 53.313333 | H40: =SUMIFS(Discover!$F:$F,Discover!$J:$J,Subscriptions!$A40,Discover!$B:$B,1) -> 0 | I40: =SUMIFS(Discover!$F:$F,Discover!$J:$J,Subscriptions!$A40,Discover!$B:$B,2) -> 0 | J40: =SUMIFS(Discover!$F:$F,Discover!$J:$J,Subscriptions!$A40,Discover!$B:$B,3) -> 64.99 | K40: =SUMIFS(Discover!$F:$F,Discover!$J:$J,Subscriptions!$A40,Discover!$B:$B,4) -> 0 | L40: =SUMIFS(Discover!$F:$F,Discover!$J:$J,Subscriptions!$A40,Discover!$B:$B,5) -> 0 | M40: =SUMIFS(Discover!$F:$F,Discover!$J:$J,Subscriptions!$A40,Discover!$B:$B,6) -> 0 | N40: =SUMIFS(Discover!$F:$F,Discover!$J:$J,Subscriptions!$A40,Discover!$B:$B,7) -> 0 | O40: =SUMIFS(Discover!$F:$F,Discover!$J:$J,Subscriptions!$A40,Discover!$B:$B,8) -> 0 | P40: =SUMIFS(Discover!$F:$F,Discover!$J:$J,Subscriptions!$A40,Discover!$B:$B,9) -> 0 | Q40: =SUMIFS(Discover!$F:$F,Discover!$J:$J,Subscriptions!$A40,Discover!$B:$B,10) -> 94.95 | R40: =SUMIFS(Discover!$F:$F,Discover!$J:$J,Subscriptions!$A40,Discover!$B:$B,11) -> 0 | S40: =SUMIFS(Discover!$F:$F,Discover!$J:$J,Subscriptions!$A40,Discover!$B:$B,12) -> 0
E42: =SUM(E2:E39) -> 4864.56 | G42: =SUMPRODUCT(G2:G40,E2:E40)/SUM(E2:E40) -> 98.448566 | H42: =SUM(H2:H40) -> 190.63 | I42: =SUM(I2:I40) -> 250.9 | J42: =SUM(J2:J40) -> 483.87 | K42: =SUM(K2:K40) -> 348.78 | L42: =SUM(L2:L40) -> 754.62 | M42: =SUM(M2:M40) -> 626.2 | N42: =SUM(N2:N40) -> 330.98 | O42: =SUM(O2:O40) -> 584.34 | ... S42: =SUM(S2:S40) -> 0

Sheet Cash Flow
C1: 1 | D1: 1 | E1: 1 | F1: 1 | G1: 1 | H1: 2 | I1: 2 | J1: 2 | K1: 2 | L1: 3 | M1: 3 | N1: 3 | O1: 3 | P1: 3 | Q1: 4 | R1: 4 | S1: 4 | T1: 4 | U1: 4 | V1: 5 | W1: 5 | X1: 5 | Y1: 5 | Z1: 5 | AA1: 6 | AB1: 6 | AC1: 6 | AD1: 6 | AE1: 6 | AF1: 7 | AG1: 7 | AH1: 7 | AI1: 7 | AJ1: 7 | AK1: 8 | AL1: 8 | AM1: 8 | AN1: 8 | AO1: 8 | AP1: 9 | AQ1: 9 | AR1: 9 | AS1: 9 | AT1: 9 | AU1: 10 | AV1: 10 | AW1: 10 | AX1: 10 | AY1: 10 | AZ1: 11 | BA1: 11 | BB1: 11 | BC1: 11 | BD1: 11 | BE1: 12 | BF1: 12 | BG1: 12 | BH1: 12 | BI1: 12
A2: Begin Balance | B2: 167.58 | C2: Jan | H2: Feb | L2: Mar | Q2: Apr | V2: May | AA2: Jun | AF2: Jul | AK2: Aug | AP2: Sep | AU2: Oct | AZ2: Nov | BE2: Dec
C3: 1 | D3: 8 | E3: 15 | F3: 22 | G3: 31 | H3: 5 | I3: 12 | J3: 19 | K3: 28 | L3: 5 | M3: 12 | N3: 19 | O3: 26 | P3: 31 | Q3: 2 | R3: 9 | S3: 16 | T3: 23 | U3: 30 | V3: 7 | W3: 14 | X3: 21 | Y3: 28 | Z3: 31 | AA3: 4 | AB3: 11 | AC3: 18 | AD3: 25 | AE3: 30 | AF3: 2 | AG3: 9 | AH3: 16 | AI3: 23 | AJ3: 30 | AK3: 6 | AL3: 13 | AM3: 20 | AN3: 27 | AO3: 31 | AP3: 3 | AQ3: 10 | AR3: 17 | AS3: 24 | AT3: 30 | AU3: 1 | AV3: 8 | AW3: 15 | AX3: 22 | AY3: 29 | AZ3: 5 | BA3: 12 | BB3: 19 | BC3: 26 | BD3: 30 | BE3: 3 | BF3: 10 | BG3: 17 | BH3: 24 | BI3: 31
A4: {=_xlfn._xlws.SORT(_xlfn.UNIQUE(_xlfn._xlws.FILTER('Wells Fargo'!G:G,('Wells Fargo'!G:G<>0)*('Wells Fargo'!G:G<>"Primary"))))} -> 3060 Ti GPU | B4: =SUM(C4:BI4) -> 0 | C4: =SUMIFS('Wells Fargo'!$F:$F,'Wells Fargo'!$G:$G,'Cash Flow'!$A4,'Wells Fargo'!$A:$A,C$1,'Wells Fargo'!$B:$B,"<="&'Cash Flow'!C$3) -> 0 | D4: =SUMIFS('Wells Fargo'!$F:$F,'Wells Fargo'!$G:$G,'Cash Flow'!$A4,'Wells Fargo'!$A:$A,D$1,'Wells Fargo'!$B:$B,"<="&'Cash Flow'!D$3,'Wells Fargo'!$B:$B,">"&'Cash Flow'!C$3) -> 0 | E4: =SUMIFS('Wells Fargo'!$F:$F,'Wells Fargo'!$G:$G,'Cash Flow'!$A4,'Wells Fargo'!$A:$A,E$1,'Wells Fargo'!$B:$B,"<="&'Cash Flow'!E$3,'Wells Fargo'!$B:$B,">"&'Cash Flow'!D$3) -> 0 | F4: =SUMIFS('Wells Fargo'!$F:$F,'Wells Fargo'!$G:$G,'Cash Flow'!$A4,'Wells Fargo'!$A:$A,F$1,'Wells Fargo'!$B:$B,"<="&'Cash Flow'!F$3,'Wells Fargo'!$B:$B,">"&'Cash Flow'!E$3) -> 0 | G4: =SUMIFS('Wells Fargo'!$F:$F,'Wells Fargo'!$G:$G,'Cash Flow'!$A4,'Wells Fargo'!$A:$A,G$1,'Wells Fargo'!$B:$B,"<="&'Cash Flow'!G$3,'Wells Fargo'!$B:$B,">"&'Cash Flow'!F$3) -> 0 | H4: =SUMIFS('Wells Fargo'!$F:$F,'Wells Fargo'!$G:$G,'Cash Flow'!$A4,'Wells Fargo'!$A:$A,H$1,'Wells Fargo'!$B:$B,"<="&'Cash Flow'!H$3) -> 0 | I4: =SUMIFS('Wells Fargo'!$F:$F,'Wells Fargo'!$G:$G,'Cash Flow'!$A4,'Wells Fargo'!$A:$A,I$1,'Wells Fargo'!$B:$B,"<="&'Cash Flow'!I$3,'Wells Fargo'!$B:$B,">"&'Cash Flow'!H$3) -> 0 | J4: =SUMIFS('Wells Fargo'!$F:$F,'Wells Fargo'!$G:$G,'Cash Flow'!$A4,'Wells Fargo'!$A:$A,J$1,'Wells Fargo'!$B:$B,"<="&'Cash Flow'!J$3,'Wells Fargo'!$B:$B,">"&'Cash Flow'!I$3) -> 0 | K4: =SUMIFS('Wells Fargo'!$F:$F,'Wells Fargo'!$G:$G,'Cash Flow'!$A4,'Wells Fargo'!$A:$A,K$1,'Wells Fargo'!$B:$B,"<="&'Cash Flow'!K$3,'Wells Fargo'!$B:$B,">"&'Cash Flow'!J$3) -> 0 | L4: =SUMIFS('Wells Fargo'!$F:$F,'Wells Fargo'!$G:$G,'Cash Flow'!$A4,'Wells Fargo'!$A:$A,L$1,'Wells Fargo'!$B:$B,"<="&'Cash Flow'!L$3) -> 0 | M4: =SUMIFS('Wells Fargo'!$F:$F,'Wells Fargo'!$G:$G,'Cash Flow'!$A4,'Wells Fargo'!$A:$A,M$1,'Wells Fargo'!$B:$B,"<="&'Cash Flow'!M$3,'Wells Fargo'!$B:$B,">"&'Cash Flow'!L$3) -> 0 | N4: =SUMIFS('Wells Fargo'!$F:$F,'Wells Fargo'!$G:$G,'Cash Flow'!$A4,'Wells Fargo'!$A:$A,N$1,'Wells Fargo'!$B:$B,"<="&'Cash Flow'!N$3,'Wells Fargo'!$B:$B,">"&'Cash Flow'!M$3) -> 0 | O4: =SUMIFS('Wells Fargo'!$F:$F,'Wells Fargo'!$G:$G,'Cash Flow'!$A4,'Wells Fargo'!$A:$A,O$1,'Wells Fargo'!$B:$B,"<="&'Cash Flow'!O$3,'Wells Fargo'!$B:$B,">"&'Cash Flow'!N$3) -> 0 | P4: =SUMIFS('Wells Fargo'!$F:$F,'Wells Fargo'!$G:$G,'Cash Flow'!$A4,'Wells Fargo'!$A:$A,P$1,'Wells Fargo'!$B:$B,"<="&'Cash Flow'!P$3,'Wells Fargo'!$B:$B,">"&'Cash Flow'!O$3) -> 0 | Q4: =SUMIFS('Wells Fargo'!$F:$F,'Wells Fargo'!$G:$G,'Cash Flow'!$A4,'Wells Fargo'!$A:$A,Q$1,'Wells Fargo'!$B:$B,"<="&'Cash Flow'!Q$3) -> 0 | R4: =SUMIFS('Wells Fargo'!$F:$F,'Wells Fargo'!$G:$G,'Cash Flow'!$A4,'Wells Fargo'!$A:$A,R$1,'Wells Fargo'!$B:$B,"<="&'Cash Flow'!R$3,'Wells Fargo'!$B:$B,">"&'Cash Flow'!Q$3) -> 0 | S4: =SUMIFS('Wells Fargo'!$F:$F,'Wells Fargo'!$G:$G,'Cash Flow'!$A4,'Wells Fargo'!$A:$A,S$1,'Wells Fargo'!$B:$B,"<="&'Cash Flow'!S$3,'Wells Fargo'!$B:$B,">"&'Cash Flow'!R$3) -> 0 | T4: =SUMIFS('Wells Fargo'!$F:$F,'Wells Fargo'!$G:$G,'Cash Flow'!$A4,'Wells Fargo'!$A:$A,T$1,'Wells Fargo'!$B:$B,"<="&'Cash Flow'!T$3,'Wells Fargo'!$B:$B,">"&'Cash Flow'!S$3) -> 0 | U4: =SUMIFS('Wells Fargo'!$F:$F,'Wells Fargo'!$G:$G,'Cash Flow'!$A4,'Wells Fargo'!$A:$A,U$1,'Wells Fargo'!$B:$B,"<="&'Cash Flow'!U$3,'Wells Fargo'!$B:$B,">"&'Cash Flow'!T$3) -> 0 | V4: =SUMIFS('Wells Fargo'!$F:$F,'Wells Fargo'!$G:$G,'Cash Flow'!$A4,'Wells Fargo'!$A:$A,V$1,'Wells Fargo'!$B:$B,"<="&'Cash Flow'!V$3) -> 0 | W4: =SUMIFS('Wells Fargo'!$F:$F,'Wells Fargo'!$G:$G,'Cash Flow'!$A4,'Wells Fargo'!$A:$A,W$1,'Wells Fargo'!$B:$B,"<="&'Cash Flow'!W$3,'Wells Fargo'!$B:$B,">"&'Cash Flow'!V$3) -> 0 | X4: =SUMIFS('Wells Fargo'!$F:$F,'Wells Fargo'!$G:$G,'Cash Flow'!$A4,'Wells Fargo'!$A:$A,X$1,'Wells Fargo'!$B:$B,"<="&'Cash Flow'!X$3,'Wells Fargo'!$B:$B,">"&'Cash Flow'!W$3) -> 0 | Y4: =SUMIFS('Wells Fargo'!$F:$F,'Wells Fargo'!$G:$G,'Cash Flow'!$A4,'Wells Fargo'!$A:$A,Y$1,'Wells Fargo'!$B:$B,"<="&'Cash Flow'!Y$3,'Wells Fargo'!$B:$B,">"&'Cash Flow'!X$3) -> 0 | Z4: =SUMIFS('Wells Fargo'!$F:$F,'Wells Fargo'!$G:$G,'Cash Flow'!$A4,'Wells Fargo'!$A:$A,Z$1,'Wells Fargo'!$B:$B,"<="&'Cash Flow'!Z$3,'Wells Fargo'!$B:$B,">"&'Cash Flow'!Y$3) -> 0 | AA4: =SUMIFS('Wells Fargo'!$F:$F,'Wells Fargo'!$G:$G,'Cash Flow'!$A4,'Wells Fargo'!$A:$A,AA$1,'Wells Fargo'!$B:$B,"<="&'Cash Flow'!AA$3) -> 0 | AB4: =SUMIFS('Wells Fargo'!$F:$F,'Wells Fargo'!$G:$G,'Cash Flow'!$A4,'Wells Fargo'!$A:$A,AB$1,'Wells Fargo'!$B:$B,"<="&'Cash Flow'!AB$3,'Wells Fargo'!$B:$B,">"&'Cash Flow'!AA$3) -> 0 | AC4: =SUMIFS('Wells Fargo'!$F:$F,'Wells Fargo'!$G:$G,'Cash Flow'!$A4,'Wells Fargo'!$A:$A,AC$1,'Wells Fargo'!$B:$B,"<="&'Cash Flow'!AC$3,'Wells Fargo'!$B:$B,">"&'Cash Flow'!AB$3) -> 0 | AD4: =SUMIFS('Wells Fargo'!$F:$F,'Wells Fargo'!$G:$G,'Cash Flow'!$A4,'Wells Fargo'!$A:$A,AD$1,'Wells Fargo'!$B:$B,"<="&'Cash Flow'!AD$3,'Wells Fargo'!$B:$B,">"&'Cash Flow'!AC$3) -> 0 | AE4: =SUMIFS('Wells Fargo'!$F:$F,'Wells Fargo'!$G:$G,'Cash Flow'!$A4,'Wells Fargo'!$A:$A,AE$1,'Wells Fargo'!$B:$B,"<="&'Cash Flow'!AE$3,'Wells Fargo'!$B:$B,">"&'Cash Flow'!AD$3) -> 0 | AF4: =SUMIFS('Wells Fargo'!$F:$F,'Wells Fargo'!$G:$G,'Cash Flow'!$A4,'Wells Fargo'!$A:$A,AF$1,'Wells Fargo'!$B:$B,"<="&'Cash Flow'!AF$3) -> 0 | AG4: =SUMIFS('Wells Fargo'!$F:$F,'Wells Fargo'!$G:$G,'Cash Flow'!$A4,'Wells Fargo'!$A:$A,AG$1,'Wells Fargo'!$B:$B,"<="&'Cash Flow'!AG$3,'Wells Fargo'!$B:$B,">"&'Cash Flow'!AF$3) -> 0 | AH4: =SUMIFS('Wells Fargo'!$F:$F,'Wells Fargo'!$G:$G,'Cash Flow'!$A4,'Wells Fargo'!$A:$A,AH$1,'Wells Fargo'!$B:$B,"<="&'Cash Flow'!AH$3,'Wells Fargo'!$B:$B,">"&'Cash Flow'!AG$3) -> 0 | AI4: =SUMIFS('Wells Fargo'!$F:$F,'Wells Fargo'!$G:$G,'Cash Flow'!$A4,'Wells Fargo'!$A:$A,AI$1,'Wells Fargo'!$B:$B,"<="&'Cash Flow'!AI$3,'Wells Fargo'!$B:$B,">"&'Cash Flow'!AH$3) -> 0 | AJ4: =SUMIFS('Wells Fargo'!$F:$F,'Wells Fargo'!$G:$G,'Cash Flow'!$A4,'Wells Fargo'!$A:$A,AJ$1,'Wells Fargo'!$B:$B,"<="&'Cash Flow'!AJ$3,'Wells Fargo'!$B:$B,">"&'Cash Flow'!AI$3) -> 0 | AK4: =SUMIFS('Wells Fargo'!$F:$F,'Wells Fargo'!$G:$G,'Cash Flow'!$A4,'Wells Fargo'!$A:$A,AK$1,'Wells Fargo'!$B:$B,"<="&'Cash Flow'!AK$3) -> 0 | AL4: =SUMIFS('Wells Fargo'!$F:$F,'Wells Fargo'!$G:$G,'Cash Flow'!$A4,'Wells Fargo'!$A:$A,AL$1,'Wells Fargo'!$B:$B,"<="&'Cash Flow'!AL$3,'Wells Fargo'!$B:$B,">"&'Cash Flow'!AK$3) -> 0 | AM4: =SUMIFS('Wells Fargo'!$F:$F,'Wells Fargo'!$G:$G,'Cash Flow'!$A4,'Wells Fargo'!$A:$A,AM$1,'Wells Fargo'!$B:$B,"<="&'Cash Flow'!AM$3,'Wells Fargo'!$B:$B,">"&'Cash Flow'!AL$3) -> 0 | AN4: =SUMIFS('Wells Fargo'!$F:$F,'Wells Fargo'!$G:$G,'Cash Flow'!$A4,'Wells Fargo'!$A:$A,AN$1,'Wells Fargo'!$B:$B,"<="&'Cash Flow'!AN$3,'Wells Fargo'!$B:$B,">"&'Cash Flow'!AM$3) -> 0 | AO4: =SUMIFS('Wells Fargo'!$F:$F,'Wells Fargo'!$G:$G,'Cash Flow'!$A4,'Wells Fargo'!$A:$A,AO$1,'Wells Fargo'!$B:$B,"<="&'Cash Flow'!AO$3,'Wells Fargo'!$B:$B,">"&'Cash Flow'!AN$3) -> 0 | AP4: =SUMIFS('Wells Fargo'!$F:$F,'Wells Fargo'!$G:$G,'Cash Flow'!$A4,'Wells Fargo'!$A:$A,AP$1,'Wells Fargo'!$B:$B,"<="&'Cash Flow'!AP$3) -> 0 | AQ4: =SUMIFS('Wells Fargo'!$F:$F,'Wells Fargo'!$G:$G,'Cash Flow'!$A4,'Wells Fargo'!$A:$A,AQ$1,'Wells Fargo'!$B:$B,"<="&'Cash Flow'!AQ$3,'Wells Fargo'!$B:$B,">"&'Cash Flow'!AP$3) -> 0 | AR4: =SUMIFS('Wells Fargo'!$F:$F,'Wells Fargo'!$G:$G,'Cash Flow'!$A4,'Wells Fargo'!$A:$A,AR$1,'Wells Fargo'!$B:$B,"<="&'Cash Flow'!AR$3,'Wells Fargo'!$B:$B,">"&'Cash Flow'!AQ$3) -> 0 | AS4: =SUMIFS('Wells Fargo'!$F:$F,'Wells Fargo'!$G:$G,'Cash Flow'!$A4,'Wells Fargo'!$A:$A,AS$1,'Wells Fargo'!$B:$B,"<="&'Cash Flow'!AS$3,'Wells Fargo'!$B:$B,">"&'Cash Flow'!AR$3) -> 0 | AT4: =SUMIFS('Wells Fargo'!$F:$F,'Wells Fargo'!$G:$G,'Cash Flow'!$A4,'Wells Fargo'!$A:$A,AT$1,'Wells Fargo'!$B:$B,"<="&'Cash Flow'!AT$3,'Wells Fargo'!$B:$B,">"&'Cash Flow'!AS$3) -> 0 | AU4: =SUMIFS('Wells Fargo'!$F:$F,'Wells Fargo'!$G:$G,'Cash Flow'!$A4,'Wells Fargo'!$A:$A,AU$1,'Wells Fargo'!$B:$B,"<="&'Cash Flow'!AU$3) -> 0 | AV4: =SUMIFS('Wells Fargo'!$F:$F,'Wells Fargo'!$G:$G,'Cash Flow'!$A4,'Wells Fargo'!$A:$A,AV$1,'Wells Fargo'!$B:$B,"<="&'Cash Flow'!AV$3,'Wells Fargo'!$B:$B,">"&'Cash Flow'!AU$3) -> 0 | AW4: =SUMIFS('Wells Fargo'!$F:$F,'Wells Fargo'!$G:$G,'Cash Flow'!$A4,'Wells Fargo'!$A:$A,AW$1,'Wells Fargo'!$B:$B,"<="&'Cash Flow'!AW$3,'Wells Fargo'!$B:$B,">"&'Cash Flow'!AV$3) -> 0 | AX4: =SUMIFS('Wells Fargo'!$F:$F,'Wells Fargo'!$G:$G,'Cash Flow'!$A4,'Wells Fargo'!$A:$A,AX$1,'Wells Fargo'!$B:$B,"<="&'Cash Flow'!AX$3,'Wells Fargo'!$B:$B,">"&'Cash Flow'!AW$3) -> 0 | AY4: =SUMIFS('Wells Fargo'!$F:$F,'Wells Fargo'!$G:$G,'Cash Flow'!$A4,'Wells Fargo'!$A:$A,AY$1,'Wells Fargo'!$B:$B,"<="&'Cash Flow'!AY$3,'Wells Fargo'!$B:$B,">"&'Cash Flow'!AX$3) -> 0 | AZ4: =SUMIFS('Wells Fargo'!$F:$F,'Wells Fargo'!$G:$G,'Cash Flow'!$A4,'Wells Fargo'!$A:$A,AZ$1,'Wells Fargo'!$B:$B,"<="&'Cash Flow'!AZ$3) -> 0 | BA4: =SUMIFS('Wells Fargo'!$F:$F,'Wells Fargo'!$G:$G,'Cash Flow'!$A4,'Wells Fargo'!$A:$A,BA$1,'Wells Fargo'!$B:$B,"<="&'Cash Flow'!BA$3,'Wells Fargo'!$B:$B,">"&'Cash Flow'!AZ$3) -> 0 | BB4: =SUMIFS('Wells Fargo'!$F:$F,'Wells Fargo'!$G:$G,'Cash Flow'!$A4,'Wells Fargo'!$A:$A,BB$1,'Wells Fargo'!$B:$B,"<="&'Cash Flow'!BB$3,'Wells Fargo'!$B:$B,">"&'Cash Flow'!BA$3) -> 0 | BC4: =SUMIFS('Wells Fargo'!$F:$F,'Wells Fargo'!$G:$G,'Cash Flow'!$A4,'Wells Fargo'!$A:$A,BC$1,'Wells Fargo'!$B:$B,"<="&'Cash Flow'!BC$3,'Wells Fargo'!$B:$B,">"&'Cash Flow'!BB$3) -> 0 | BD4: =SUMIFS('Wells Fargo'!$F:$F,'Wells Fargo'!$G:$G,'Cash Flow'!$A4,'Wells Fargo'!$A:$A,BD$1,'Wells Fargo'!$B:$B,"<="&'Cash Flow'!BD$3,'Wells Fargo'!$B:$B,">"&'Cash Flow'!BC$3) -> 0 | BE4: =SUMIFS('Wells Fargo'!$F:$F,'Wells Fargo'!$G:$G,'Cash Flow'!$A4,'Wells Fargo'!$A:$A,BE$1,'Wells Fargo'!$B:$B,"<="&'Cash Flow'!BE$3) -> 0 | BF4: =SUMIFS('Wells Fargo'!$F:$F,'Wells Fargo'!$G:$G,'Cash Flow'!$A4,'Wells Fargo'!$A:$A,BF$1,'Wells Fargo'!$B:$B,"<="&'Cash Flow'!BF$3,'Wells Fargo'!$B:$B,">"&'Cash Flow'!BE$3) -> 0 | BG4: =SUMIFS('Wells Fargo'!$F:$F,'Wells Fargo'!$G:$G,'Cash Flow'!$A4,'Wells Fargo'!$A:$A,BG$1,'Wells Fargo'!$B:$B,"<="&'Cash Flow'!BG$3,'Wells Fargo'!$B:$B,">"&'Cash Flow'!BF$3) -> 0 | BH4: =SUMIFS('Wells Fargo'!$F:$F,'Wells Fargo'!$G:$G,'Cash Flow'!$A4,'Wells Fargo'!$A:$A,BH$1,'Wells Fargo'!$B:$B,"<="&'Cash Flow'!BH$3,'Wells Fargo'!$B:$B,">"&'Cash Flow'!BG$3) -> 0 | BI4: =SUMIFS('Wells Fargo'!$F:$F,'Wells Fargo'!$G:$G,'Cash Flow'!$A4,'Wells Fargo'!$A:$A,BI$1,'Wells Fargo'!$B:$B,"<="&'Cash Flow'!BI$3,'Wells Fargo'!$B:$B,">"&'Cash Flow'!BH$3) -> 0
A5: 3070 GPU | B5: =SUM(C5:BI5) -> -500 | C5: =SUMIFS('Wells Fargo'!$F:$F,'Wells Fargo'!$G:$G,'Cash Flow'!$A5,'Wells Fargo'!$A:$A,C$1,'Wells Fargo'!$B:$B,"<="&'Cash Flow'!C$3) -> 0 | D5: =SUMIFS('Wells Fargo'!$F:$F,'Wells Fargo'!$G:$G,'Cash Flow'!$A5,'Wells Fargo'!$A:$A,D$1,'Wells Fargo'!$B:$B,"<="&'Cash Flow'!D$3,'Wells Fargo'!$B:$B,">"&'Cash Flow'!C$3) -> 0 | E5: =SUMIFS('Wells Fargo'!$F:$F,'Wells Fargo'!$G:$G,'Cash Flow'!$A5,'Wells Fargo'!$A:$A,E$1,'Wells Fargo'!$B:$B,"<="&'Cash Flow'!E$3,'Wells Fargo'!$B:$B,">"&'Cash Flow'!D$3) -> 0 | F5: =SUMIFS('Wells Fargo'!$F:$F,'Wells Fargo'!$G:$G,'Cash Flow'!$A5,'Wells Fargo'!$A:$A,F$1,'Wells Fargo'!$B:$B,"<="&'Cash Flow'!F$3,'Wells Fargo'!$B:$B,">"&'Cash Flow'!E$3) -> 0 | G5: =SUMIFS('Wells Fargo'!$F:$F,'Wells Fargo'!$G:$G,'Cash Flow'!$A5,'Wells Fargo'!$A:$A,G$1,'Wells Fargo'!$B:$B,"<="&'Cash Flow'!G$3,'Wells Fargo'!$B:$B,">"&'Cash Flow'!F$3) -> 0 | H5: =SUMIFS('Wells Fargo'!$F:$F,'Wells Fargo'!$G:$G,'Cash Flow'!$A5,'Wells Fargo'!$A:$A,H$1,'Wells Fargo'!$B:$B,"<="&'Cash Flow'!H$3) -> 0 | I5: =SUMIFS('Wells Fargo'!$F:$F,'Wells Fargo'!$G:$G,'Cash Flow'!$A5,'Wells Fargo'!$A:$A,I$1,'Wells Fargo'!$B:$B,"<="&'Cash Flow'!I$3,'Wells Fargo'!$B:$B,">"&'Cash Flow'!H$3) -> 0 | J5: =SUMIFS('Wells Fargo'!$F:$F,'Wells Fargo'!$G:$G,'Cash Flow'!$A5,'Wells Fargo'!$A:$A,J$1,'Wells Fargo'!$B:$B,"<="&'Cash Flow'!J$3,'Wells Fargo'!$B:$B,">"&'Cash Flow'!I$3) -> 0 | K5: =SUMIFS('Wells Fargo'!$F:$F,'Wells Fargo'!$G:$G,'Cash Flow'!$A5,'Wells Fargo'!$A:$A,K$1,'Wells Fargo'!$B:$B,"<="&'Cash Flow'!K$3,'Wells Fargo'!$B:$B,">"&'Cash Flow'!J$3) -> 0 | L5: =SUMIFS('Wells Fargo'!$F:$F,'Wells Fargo'!$G:$G,'Cash Flow'!$A5,'Wells Fargo'!$A:$A,L$1,'Wells Fargo'!$B:$B,"<="&'Cash Flow'!L$3) -> 0 | M5: =SUMIFS('Wells Fargo'!$F:$F,'Wells Fargo'!$G:$G,'Cash Flow'!$A5,'Wells Fargo'!$A:$A,M$1,'Wells Fargo'!$B:$B,"<="&'Cash Flow'!M$3,'Wells Fargo'!$B:$B,">"&'Cash Flow'!L$3) -> 0 | N5: =SUMIFS('Wells Fargo'!$F:$F,'Wells Fargo'!$G:$G,'Cash Flow'!$A5,'Wells Fargo'!$A:$A,N$1,'Wells Fargo'!$B:$B,"<="&'Cash Flow'!N$3,'Wells Fargo'!$B:$B,">"&'Cash Flow'!M$3) -> 0 | O5: =SUMIFS('Wells Fargo'!$F:$F,'Wells Fargo'!$G:$G,'Cash Flow'!$A5,'Wells Fargo'!$A:$A,O$1,'Wells Fargo'!$B:$B,"<="&'Cash Flow'!O$3,'Wells Fargo'!$B:$B,">"&'Cash Flow'!N$3) -> 0 | P5: =SUMIFS('Wells Fargo'!$F:$F,'Wells Fargo'!$G:$G,'Cash Flow'!$A5,'Wells Fargo'!$A:$A,P$1,'Wells Fargo'!$B:$B,"<="&'Cash Flow'!P$3,'Wells Fargo'!$B:$B,">"&'Cash Flow'!O$3) -> 0 | Q5: =SUMIFS('Wells Fargo'!$F:$F,'Wells Fargo'!$G:$G,'Cash Flow'!$A5,'Wells Fargo'!$A:$A,Q$1,'Wells Fargo'!$B:$B,"<="&'Cash Flow'!Q$3) -> 0 | R5: =SUMIFS('Wells Fargo'!$F:$F,'Wells Fargo'!$G:$G,'Cash Flow'!$A5,'Wells Fargo'!$A:$A,R$1,'Wells Fargo'!$B:$B,"<="&'Cash Flow'!R$3,'Wells Fargo'!$B:$B,">"&'Cash Flow'!Q$3) -> 0 | S5: =SUMIFS('Wells Fargo'!$F:$F,'Wells Fargo'!$G:$G,'Cash Flow'!$A5,'Wells Fargo'!$A:$A,S$1,'Wells Fargo'!$B:$B,"<="&'Cash Flow'!S$3,'Wells Fargo'!$B:$B,">"&'Cash Flow'!R$3) -> 0 | T5: =SUMIFS('Wells Fargo'!$F:$F,'Wells Fargo'!$G:$G,'Cash Flow'!$A5,'Wells Fargo'!$A:$A,T$1,'Wells Fargo'!$B:$B,"<="&'Cash Flow'!T$3,'Wells Fargo'!$B:$B,">"&'Cash Flow'!S$3) -> 0 | U5: =SUMIFS('Wells Fargo'!$F:$F,'Wells Fargo'!$G:$G,'Cash Flow'!$A5,'Wells Fargo'!$A:$A,U$1,'Wells Fargo'!$B:$B,"<="&'Cash Flow'!U$3,'Wells Fargo'!$B:$B,">"&'Cash Flow'!T$3) -> 0 | V5: =SUMIFS('Wells Fargo'!$F:$F,'Wells Fargo'!$G:$G,'Cash Flow'!$A5,'Wells Fargo'!$A:$A,V$1,'Wells Fargo'!$B:$B,"<="&'Cash Flow'!V$3) -> 0 | W5: =SUMIFS('Wells Fargo'!$F:$F,'Wells Fargo'!$G:$G,'Cash Flow'!$A5,'Wells Fargo'!$A:$A,W$1,'Wells Fargo'!$B:$B,"<="&'Cash Flow'!W$3,'Wells Fargo'!$B:$B,">"&'Cash Flow'!V$3) -> 0 | X5: =SUMIFS('Wells Fargo'!$F:$F,'Wells Fargo'!$G:$G,'Cash Flow'!$A5,'Wells Fargo'!$A:$A,X$1,'Wells Fargo'!$B:$B,"<="&'Cash Flow'!X$3,'Wells Fargo'!$B:$B,">"&'Cash Flow'!W$3) -> 0 | Y5: =SUMIFS('Wells Fargo'!$F:$F,'Wells Fargo'!$G:$G,'Cash Flow'!$A5,'Wells Fargo'!$A:$A,Y$1,'Wells Fargo'!$B:$B,"<="&'Cash Flow'!Y$3,'Wells Fargo'!$B:$B,">"&'Cash Flow'!X$3) -> 0 | Z5: =SUMIFS('Wells Fargo'!$F:$F,'Wells Fargo'!$G:$G,'Cash Flow'!$A5,'Wells Fargo'!$A:$A,Z$1,'Wells Fargo'!$B:$B,"<="&'Cash Flow'!Z$3,'Wells Fargo'!$B:$B,">"&'Cash Flow'!Y$3) -> 0 | AA5: =SUMIFS('Wells Fargo'!$F:$F,'Wells Fargo'!$G:$G,'Cash Flow'!$A5,'Wells Fargo'!$A:$A,AA$1,'Wells Fargo'!$B:$B,"<="&'Cash Flow'!AA$3) -> 0 | AB5: =SUMIFS('Wells Fargo'!$F:$F,'Wells Fargo'!$G:$G,'Cash Flow'!$A5,'Wells Fargo'!$A:$A,AB$1,'Wells Fargo'!$B:$B,"<="&'Cash Flow'!AB$3,'Wells Fargo'!$B:$B,">"&'Cash Flow'!AA$3) -> 0 | AC5: =SUMIFS('Wells Fargo'!$F:$F,'Wells Fargo'!$G:$G,'Cash Flow'!$A5,'Wells Fargo'!$A:$A,AC$1,'Wells Fargo'!$B:$B,"<="&'Cash Flow'!AC$3,'Wells Fargo'!$B:$B,">"&'Cash Flow'!AB$3) -> 0 | AD5: =SUMIFS('Wells Fargo'!$F:$F,'Wells Fargo'!$G:$G,'Cash Flow'!$A5,'Wells Fargo'!$A:$A,AD$1,'Wells Fargo'!$B:$B,"<="&'Cash Flow'!AD$3,'Wells Fargo'!$B:$B,">"&'Cash Flow'!AC$3) -> 0 | AE5: =SUMIFS('Wells Fargo'!$F:$F,'Wells Fargo'!$G:$G,'Cash Flow'!$A5,'Wells Fargo'!$A:$A,AE$1,'Wells Fargo'!$B:$B,"<="&'Cash Flow'!AE$3,'Wells Fargo'!$B:$B,">"&'Cash Flow'!AD$3) -> 0 | AF5: =SUMIFS('Wells Fargo'!$F:$F,'Wells Fargo'!$G:$G,'Cash Flow'!$A5,'Wells Fargo'!$A:$A,AF$1,'Wells Fargo'!$B:$B,"<="&'Cash Flow'!AF$3) -> 0 | AG5: =SUMIFS('Wells Fargo'!$F:$F,'Wells Fargo'!$G:$G,'Cash Flow'!$A5,'Wells Fargo'!$A:$A,AG$1,'Wells Fargo'!$B:$B,"<="&'Cash Flow'!AG$3,'Wells Fargo'!$B:$B,">"&'Cash Flow'!AF$3) -> 0 | AH5: =SUMIFS('Wells Fargo'!$F:$F,'Wells Fargo'!$G:$G,'Cash Flow'!$A5,'Wells Fargo'!$A:$A,AH$1,'Wells Fargo'!$B:$B,"<="&'Cash Flow'!AH$3,'Wells Fargo'!$B:$B,">"&'Cash Flow'!AG$3) -> -500 | AI5: =SUMIFS('Wells Fargo'!$F:$F,'Wells Fargo'!$G:$G,'Cash Flow'!$A5,'Wells Fargo'!$A:$A,AI$1,'Wells Fargo'!$B:$B,"<="&'Cash Flow'!AI$3,'Wells Fargo'!$B:$B,">"&'Cash Flow'!AH$3) -> 0 | AJ5: =SUMIFS('Wells Fargo'!$F:$F,'Wells Fargo'!$G:$G,'Cash Flow'!$A5,'Wells Fargo'!$A:$A,AJ$1,'Wells Fargo'!$B:$B,"<="&'Cash Flow'!AJ$3,'Wells Fargo'!$B:$B,">"&'Cash Flow'!AI$3) -> 0 | AK5: =SUMIFS('Wells Fargo'!$F:$F,'Wells Fargo'!$G:$G,'Cash Flow'!$A5,'Wells Fargo'!$A:$A,AK$1,'Wells Fargo'!$B:$B,"<="&'Cash Flow'!AK$3) -> 0 | AL5: =SUMIFS('Wells Fargo'!$F:$F,'Wells Fargo'!$G:$G,'Cash Flow'!$A5,'Wells Fargo'!$A:$A,AL$1,'Wells Fargo'!$B:$B,"<="&'Cash Flow'!AL$3,'Wells Fargo'!$B:$B,">"&'Cash Flow'!AK$3) -> 0 | AM5: =SUMIFS('Wells Fargo'!$F:$F,'Wells Fargo'!$G:$G,'Cash Flow'!$A5,'Wells Fargo'!$A:$A,AM$1,'Wells Fargo'!$B:$B,"<="&'Cash Flow'!AM$3,'Wells Fargo'!$B:$B,">"&'Cash Flow'!AL$3) -> 0 | AN5: =SUMIFS('Wells Fargo'!$F:$F,'Wells Fargo'!$G:$G,'Cash Flow'!$A5,'Wells Fargo'!$A:$A,AN$1,'Wells Fargo'!$B:$B,"<="&'Cash Flow'!AN$3,'Wells Fargo'!$B:$B,">"&'Cash Flow'!AM$3) -> 0 | AO5: =SUMIFS('Wells Fargo'!$F:$F,'Wells Fargo'!$G:$G,'Cash Flow'!$A5,'Wells Fargo'!$A:$A,AO$1,'Wells Fargo'!$B:$B,"<="&'Cash Flow'!AO$3,'Wells Fargo'!$B:$B,">"&'Cash Flow'!AN$3) -> 0 | AP5: =SUMIFS('Wells Fargo'!$F:$F,'Wells Fargo'!$G:$G,'Cash Flow'!$A5,'Wells Fargo'!$A:$A,AP$1,'Wells Fargo'!$B:$B,"<="&'Cash Flow'!AP$3) -> 0 | AQ5: =SUMIFS('Wells Fargo'!$F:$F,'Wells Fargo'!$G:$G,'Cash Flow'!$A5,'Wells Fargo'!$A:$A,AQ$1,'Wells Fargo'!$B:$B,"<="&'Cash Flow'!AQ$3,'Wells Fargo'!$B:$B,">"&'Cash Flow'!AP$3) -> 0 | AR5: =SUMIFS('Wells Fargo'!$F:$F,'Wells Fargo'!$G:$G,'Cash Flow'!$A5,'Wells Fargo'!$A:$A,AR$1,'Wells Fargo'!$B:$B,"<="&'Cash Flow'!AR$3,'Wells Fargo'!$B:$B,">"&'Cash Flow'!AQ$3) -> 0 | AS5: =SUMIFS('Wells Fargo'!$F:$F,'Wells Fargo'!$G:$G,'Cash Flow'!$A5,'Wells Fargo'!$A:$A,AS$1,'Wells Fargo'!$B:$B,"<="&'Cash Flow'!AS$3,'Wells Fargo'!$B:$B,">"&'Cash Flow'!AR$3) -> 0 | AT5: =SUMIFS('Wells Fargo'!$F:$F,'Wells Fargo'!$G:$G,'Cash Flow'!$A5,'Wells Fargo'!$A:$A,AT$1,'Wells Fargo'!$B:$B,"<="&'Cash Flow'!AT$3,'Wells Fargo'!$B:$B,">"&'Cash Flow'!AS$3) -> 0 | AU5: =SUMIFS('Wells Fargo'!$F:$F,'Wells Fargo'!$G:$G,'Cash Flow'!$A5,'Wells Fargo'!$A:$A,AU$1,'Wells Fargo'!$B:$B,"<="&'Cash Flow'!AU$3) -> 0 | AV5: =SUMIFS('Wells Fargo'!$F:$F,'Wells Fargo'!$G:$G,'Cash Flow'!$A5,'Wells Fargo'!$A:$A,AV$1,'Wells Fargo'!$B:$B,"<="&'Cash Flow'!AV$3,'Wells Fargo'!$B:$B,">"&'Cash Flow'!AU$3) -> 0 | AW5: =SUMIFS('Wells Fargo'!$F:$F,'Wells Fargo'!$G:$G,'Cash Flow'!$A5,'Wells Fargo'!$A:$A,AW$1,'Wells Fargo'!$B:$B,"<="&'Cash Flow'!AW$3,'Wells Fargo'!$B:$B,">"&'Cash Flow'!AV$3) -> 0 | AX5: =SUMIFS('Wells Fargo'!$F:$F,'Wells Fargo'!$G:$G,'Cash Flow'!$A5,'Wells Fargo'!$A:$A,AX$1,'Wells Fargo'!$B:$B,"<="&'Cash Flow'!AX$3,'Wells Fargo'!$B:$B,">"&'Cash Flow'!AW$3) -> 0 | AY5: =SUMIFS('Wells Fargo'!$F:$F,'Wells Fargo'!$G:$G,'Cash Flow'!$A5,'Wells Fargo'!$A:$A,AY$1,'Wells Fargo'!$B:$B,"<="&'Cash Flow'!AY$3,'Wells Fargo'!$B:$B,">"&'Cash Flow'!AX$3) -> 0 | AZ5: =SUMIFS('Wells Fargo'!$F:$F,'Wells Fargo'!$G:$G,'Cash Flow'!$A5,'Wells Fargo'!$A:$A,AZ$1,'Wells Fargo'!$B:$B,"<="&'Cash Flow'!AZ$3) -> 0 | BA5: =SUMIFS('Wells Fargo'!$F:$F,'Wells Fargo'!$G:$G,'Cash Flow'!$A5,'Wells Fargo'!$A:$A,BA$1,'Wells Fargo'!$B:$B,"<="&'Cash Flow'!BA$3,'Wells Fargo'!$B:$B,">"&'Cash Flow'!AZ$3) -> 0 | BB5: =SUMIFS('Wells Fargo'!$F:$F,'Wells Fargo'!$G:$G,'Cash Flow'!$A5,'Wells Fargo'!$A:$A,BB$1,'Wells Fargo'!$B:$B,"<="&'Cash Flow'!BB$3,'Wells Fargo'!$B:$B,">"&'Cash Flow'!BA$3) -> 0 | BC5: =SUMIFS('Wells Fargo'!$F:$F,'Wells Fargo'!$G:$G,'Cash Flow'!$A5,'Wells Fargo'!$A:$A,BC$1,'Wells Fargo'!$B:$B,"<="&'Cash Flow'!BC$3,'Wells Fargo'!$B:$B,">"&'Cash Flow'!BB$3) -> 0 | BD5: =SUMIFS('Wells Fargo'!$F:$F,'Wells Fargo'!$G:$G,'Cash Flow'!$A5,'Wells Fargo'!$A:$A,BD$1,'Wells Fargo'!$B:$B,"<="&'Cash Flow'!BD$3,'Wells Fargo'!$B:$B,">"&'Cash Flow'!BC$3) -> 0 | BE5: =SUMIFS('Wells Fargo'!$F:$F,'Wells Fargo'!$G:$G,'Cash Flow'!$A5,'Wells Fargo'!$A:$A,BE$1,'Wells Fargo'!$B:$B,"<="&'Cash Flow'!BE$3) -> 0 | BF5: =SUMIFS('Wells Fargo'!$F:$F,'Wells Fargo'!$G:$G,'Cash Flow'!$A5,'Wells Fargo'!$A:$A,BF$1,'Wells Fargo'!$B:$B,"<="&'Cash Flow'!BF$3,'Wells Fargo'!$B:$B,">"&'Cash Flow'!BE$3) -> 0 | BG5: =SUMIFS('Wells Fargo'!$F:$F,'Wells Fargo'!$G:$G,'Cash Flow'!$A5,'Wells Fargo'!$A:$A,BG$1,'Wells Fargo'!$B:$B,"<="&'Cash Flow'!BG$3,'Wells Fargo'!$B:$B,">"&'Cash Flow'!BF$3) -> 0 | BH5: =SUMIFS('Wells Fargo'!$F:$F,'Wells Fargo'!$G:$G,'Cash Flow'!$A5,'Wells Fargo'!$A:$A,BH$1,'Wells Fargo'!$B:$B,"<="&'Cash Flow'!BH$3,'Wells Fargo'!$B:$B,">"&'Cash Flow'!BG$3) -> 0 | BI5: =SUMIFS('Wells Fargo'!$F:$F,'Wells Fargo'!$G:$G,'Cash Flow'!$A5,'Wells Fargo'!$A:$A,BI$1,'Wells Fargo'!$B:$B,"<="&'Cash Flow'!BI$3,'Wells Fargo'!$B:$B,">"&'Cash Flow'!BH$3) -> 0
A6: 3070 GPU | B6: =SUM(C6:BI6) -> 500 | C6: =SUMIFS('Wells Fargo'!$F:$F,'Wells Fargo'!$G:$G,'Cash Flow'!$A6,'Wells Fargo'!$A:$A,C$1,'Wells Fargo'!$B:$B,"<="&'Cash Flow'!C$3) -> 0 | D6: =SUMIFS('Wells Fargo'!$F:$F,'Wells Fargo'!$G:$G,'Cash Flow'!$A6,'Wells Fargo'!$A:$A,D$1,'Wells Fargo'!$B:$B,"<="&'Cash Flow'!D$3,'Wells Fargo'!$B:$B,">"&'Cash Flow'!C$3) -> 0 | E6: =SUMIFS('Wells Fargo'!$F:$F,'Wells Fargo'!$G:$G,'Cash Flow'!$A6,'Wells Fargo'!$A:$A,E$1,'Wells Fargo'!$B:$B,"<="&'Cash Flow'!E$3,'Wells Fargo'!$B:$B,">"&'Cash Flow'!D$3) -> 0 | F6: =SUMIFS('Wells Fargo'!$F:$F,'Wells Fargo'!$G:$G,'Cash Flow'!$A6,'Wells Fargo'!$A:$A,F$1,'Wells Fargo'!$B:$B,"<="&'Cash Flow'!F$3,'Wells Fargo'!$B:$B,">"&'Cash Flow'!E$3) -> 0 | G6: =SUMIFS('Wells Fargo'!$F:$F,'Wells Fargo'!$G:$G,'Cash Flow'!$A6,'Wells Fargo'!$A:$A,G$1,'Wells Fargo'!$B:$B,"<="&'Cash Flow'!G$3,'Wells Fargo'!$B:$B,">"&'Cash Flow'!F$3) -> 0 | H6: =SUMIFS('Wells Fargo'!$F:$F,'Wells Fargo'!$G:$G,'Cash Flow'!$A6,'Wells Fargo'!$A:$A,H$1,'Wells Fargo'!$B:$B,"<="&'Cash Flow'!H$3) -> 0 | I6: =SUMIFS('Wells Fargo'!$F:$F,'Wells Fargo'!$G:$G,'Cash Flow'!$A6,'Wells Fargo'!$A:$A,I$1,'Wells Fargo'!$B:$B,"<="&'Cash Flow'!I$3,'Wells Fargo'!$B:$B,">"&'Cash Flow'!H$3) -> 0 | J6: =SUMIFS('Wells Fargo'!$F:$F,'Wells Fargo'!$G:$G,'Cash Flow'!$A6,'Wells Fargo'!$A:$A,J$1,'Wells Fargo'!$B:$B,"<="&'Cash Flow'!J$3,'Wells Fargo'!$B:$B,">"&'Cash Flow'!I$3) -> 0 | K6: =SUMIFS('Wells Fargo'!$F:$F,'Wells Fargo'!$G:$G,'Cash Flow'!$A6,'Wells Fargo'!$A:$A,K$1,'Wells Fargo'!$B:$B,"<="&'Cash Flow'!K$3,'Wells Fargo'!$B:$B,">"&'Cash Flow'!J$3) -> 0 | L6: =SUMIFS('Wells Fargo'!$F:$F,'Wells Fargo'!$G:$G,'Cash Flow'!$A6,'Wells Fargo'!$A:$A,L$1,'Wells Fargo'!$B:$B,"<="&'Cash Flow'!L$3) -> 0 | M6: =SUMIFS('Wells Fargo'!$F:$F,'Wells Fargo'!$G:$G,'Cash Flow'!$A6,'Wells Fargo'!$A:$A,M$1,'Wells Fargo'!$B:$B,"<="&'Cash Flow'!M$3,'Wells Fargo'!$B:$B,">"&'Cash Flow'!L$3) -> 0 | N6: =SUMIFS('Wells Fargo'!$F:$F,'Wells Fargo'!$G:$G,'Cash Flow'!$A6,'Wells Fargo'!$A:$A,N$1,'Wells Fargo'!$B:$B,"<="&'Cash Flow'!N$3,'Wells Fargo'!$B:$B,">"&'Cash Flow'!M$3) -> 0 | O6: =SUMIFS('Wells Fargo'!$F:$F,'Wells Fargo'!$G:$G,'Cash Flow'!$A6,'Wells Fargo'!$A:$A,O$1,'Wells Fargo'!$B:$B,"<="&'Cash Flow'!O$3,'Wells Fargo'!$B:$B,">"&'Cash Flow'!N$3) -> 0 | P6: =SUMIFS('Wells Fargo'!$F:$F,'Wells Fargo'!$G:$G,'Cash Flow'!$A6,'Wells Fargo'!$A:$A,P$1,'Wells Fargo'!$B:$B,"<="&'Cash Flow'!P$3,'Wells Fargo'!$B:$B,">"&'Cash Flow'!O$3) -> 0 | Q6: =SUMIFS('Wells Fargo'!$F:$F,'Wells Fargo'!$G:$G,'Cash Flow'!$A6,'Wells Fargo'!$A:$A,Q$1,'Wells Fargo'!$B:$B,"<="&'Cash Flow'!Q$3) -> 0 | R6: =SUMIFS('Wells Fargo'!$F:$F,'Wells Fargo'!$G:$G,'Cash Flow'!$A6,'Wells Fargo'!$A:$A,R$1,'Wells Fargo'!$B:$B,"<="&'Cash Flow'!R$3,'Wells Fargo'!$B:$B,">"&'Cash Flow'!Q$3) -> 0 | S6: =SUMIFS('Wells Fargo'!$F:$F,'Wells Fargo'!$G:$G,'Cash Flow'!$A6,'Wells Fargo'!$A:$A,S$1,'Wells Fargo'!$B:$B,"<="&'Cash Flow'!S$3,'Wells Fargo'!$B:$B,">"&'Cash Flow'!R$3) -> 0 | T6: =SUMIFS('Wells Fargo'!$F:$F,'Wells Fargo'!$G:$G,'Cash Flow'!$A6,'Wells Fargo'!$A:$A,T$1,'Wells Fargo'!$B:$B,"<="&'Cash Flow'!T$3,'Wells Fargo'!$B:$B,">"&'Cash Flow'!S$3) -> 0 | U6: =SUMIFS('Wells Fargo'!$F:$F,'Wells Fargo'!$G:$G,'Cash Flow'!$A6,'Wells Fargo'!$A:$A,U$1,'Wells Fargo'!$B:$B,"<="&'Cash Flow'!U$3,'Wells Fargo'!$B:$B,">"&'Cash Flow'!T$3) -> 0 | V6: =SUMIFS('Wells Fargo'!$F:$F,'Wells Fargo'!$G:$G,'Cash Flow'!$A6,'Wells Fargo'!$A:$A,V$1,'Wells Fargo'!$B:$B,"<="&'Cash Flow'!V$3) -> 0 | W6: =SUMIFS('Wells Fargo'!$F:$F,'Wells Fargo'!$G:$G,'Cash Flow'!$A6,'Wells Fargo'!$A:$A,W$1,'Wells Fargo'!$B:$B,"<="&'Cash Flow'!W$3,'Wells Fargo'!$B:$B,">"&'Cash Flow'!V$3) -> 0 | X6: =SUMIFS('Wells Fargo'!$F:$F,'Wells Fargo'!$G:$G,'Cash Flow'!$A6,'Wells Fargo'!$A:$A,X$1,'Wells Fargo'!$B:$B,"<="&'Cash Flow'!X$3,'Wells Fargo'!$B:$B,">"&'Cash Flow'!W$3) -> 0 | Y6: =SUMIFS('Wells Fargo'!$F:$F,'Wells Fargo'!$G:$G,'Cash Flow'!$A6,'Wells Fargo'!$A:$A,Y$1,'Wells Fargo'!$B:$B,"<="&'Cash Flow'!Y$3,'Wells Fargo'!$B:$B,">"&'Cash Flow'!X$3) -> 0 | Z6: =SUMIFS('Wells Fargo'!$F:$F,'Wells Fargo'!$G:$G,'Cash Flow'!$A6,'Wells Fargo'!$A:$A,Z$1,'Wells Fargo'!$B:$B,"<="&'Cash Flow'!Z$3,'Wells Fargo'!$B:$B,">"&'Cash Flow'!Y$3) -> 0 | AA6: =SUMIFS('Wells Fargo'!$F:$F,'Wells Fargo'!$G:$G,'Cash Flow'!$A6,'Wells Fargo'!$A:$A,AA$1,'Wells Fargo'!$B:$B,"<="&'Cash Flow'!AA$3) -> 0 | AB6: =SUMIFS('Wells Fargo'!$F:$F,'Wells Fargo'!$G:$G,'Cash Flow'!$A6,'Wells Fargo'!$A:$A,AB$1,'Wells Fargo'!$B:$B,"<="&'Cash Flow'!AB$3,'Wells Fargo'!$B:$B,">"&'Cash Flow'!AA$3) -> 0 | AC6: =SUMIFS('Wells Fargo'!$F:$F,'Wells Fargo'!$G:$G,'Cash Flow'!$A6,'Wells Fargo'!$A:$A,AC$1,'Wells Fargo'!$B:$B,"<="&'Cash Flow'!AC$3,'Wells Fargo'!$B:$B,">"&'Cash Flow'!AB$3) -> 0 | AD6: =SUMIFS('Wells Fargo'!$F:$F,'Wells Fargo'!$G:$G,'Cash Flow'!$A6,'Wells Fargo'!$A:$A,AD$1,'Wells Fargo'!$B:$B,"<="&'Cash Flow'!AD$3,'Wells Fargo'!$B:$B,">"&'Cash Flow'!AC$3) -> 0 | AE6: =SUMIFS('Wells Fargo'!$F:$F,'Wells Fargo'!$G:$G,'Cash Flow'!$A6,'Wells Fargo'!$A:$A,AE$1,'Wells Fargo'!$B:$B,"<="&'Cash Flow'!AE$3,'Wells Fargo'!$B:$B,">"&'Cash Flow'!AD$3) -> 0 | AF6: =SUMIFS('Wells Fargo'!$F:$F,'Wells Fargo'!$G:$G,'Cash Flow'!$A6,'Wells Fargo'!$A:$A,AF$1,'Wells Fargo'!$B:$B,"<="&'Cash Flow'!AF$3) -> 0 | AG6: =SUMIFS('Wells Fargo'!$F:$F,'Wells Fargo'!$G:$G,'Cash Flow'!$A6,'Wells Fargo'!$A:$A,AG$1,'Wells Fargo'!$B:$B,"<="&'Cash Flow'!AG$3,'Wells Fargo'!$B:$B,">"&'Cash Flow'!AF$3) -> 0 | AH6: =SUMIFS('Wells Fargo'!$F:$F,'Wells Fargo'!$G:$G,'Cash Flow'!$A6,'Wells Fargo'!$A:$A,AH$1,'Wells Fargo'!$B:$B,"<="&'Cash Flow'!AH$3,'Wells Fargo'!$B:$B,">"&'Cash Flow'!AG$3) -> 500 | AI6: =SUMIFS('Wells Fargo'!$F:$F,'Wells Fargo'!$G:$G,'Cash Flow'!$A6,'Wells Fargo'!$A:$A,AI$1,'Wells Fargo'!$B:$B,"<="&'Cash Flow'!AI$3,'Wells Fargo'!$B:$B,">"&'Cash Flow'!AH$3) -> 0 | AJ6: =SUMIFS('Wells Fargo'!$F:$F,'Wells Fargo'!$G:$G,'Cash Flow'!$A6,'Wells Fargo'!$A:$A,AJ$1,'Wells Fargo'!$B:$B,"<="&'Cash Flow'!AJ$3,'Wells Fargo'!$B:$B,">"&'Cash Flow'!AI$3) -> 0 | AK6: =SUMIFS('Wells Fargo'!$F:$F,'Wells Fargo'!$G:$G,'Cash Flow'!$A6,'Wells Fargo'!$A:$A,AK$1,'Wells Fargo'!$B:$B,"<="&'Cash Flow'!AK$3) -> 0 | AL6: =SUMIFS('Wells Fargo'!$F:$F,'Wells Fargo'!$G:$G,'Cash Flow'!$A6,'Wells Fargo'!$A:$A,AL$1,'Wells Fargo'!$B:$B,"<="&'Cash Flow'!AL$3,'Wells Fargo'!$B:$B,">"&'Cash Flow'!AK$3) -> 0 | AM6: =SUMIFS('Wells Fargo'!$F:$F,'Wells Fargo'!$G:$G,'Cash Flow'!$A6,'Wells Fargo'!$A:$A,AM$1,'Wells Fargo'!$B:$B,"<="&'Cash Flow'!AM$3,'Wells Fargo'!$B:$B,">"&'Cash Flow'!AL$3) -> 0 | AN6: =SUMIFS('Wells Fargo'!$F:$F,'Wells Fargo'!$G:$G,'Cash Flow'!$A6,'Wells Fargo'!$A:$A,AN$1,'Wells Fargo'!$B:$B,"<="&'Cash Flow'!AN$3,'Wells Fargo'!$B:$B,">"&'Cash Flow'!AM$3) -> 0 | AO6: =SUMIFS('Wells Fargo'!$F:$F,'Wells Fargo'!$G:$G,'Cash Flow'!$A6,'Wells Fargo'!$A:$A,AO$1,'Wells Fargo'!$B:$B,"<="&'Cash Flow'!AO$3,'Wells Fargo'!$B:$B,">"&'Cash Flow'!AN$3) -> 0 | AP6: =SUMIFS('Wells Fargo'!$F:$F,'Wells Fargo'!$G:$G,'Cash Flow'!$A6,'Wells Fargo'!$A:$A,AP$1,'Wells Fargo'!$B:$B,"<="&'Cash Flow'!AP$3) -> 0 | AQ6: =SUMIFS('Wells Fargo'!$F:$F,'Wells Fargo'!$G:$G,'Cash Flow'!$A6,'Wells Fargo'!$A:$A,AQ$1,'Wells Fargo'!$B:$B,"<="&'Cash Flow'!AQ$3,'Wells Fargo'!$B:$B,">"&'Cash Flow'!AP$3) -> 0 | AR6: =SUMIFS('Wells Fargo'!$F:$F,'Wells Fargo'!$G:$G,'Cash Flow'!$A6,'Wells Fargo'!$A:$A,AR$1,'Wells Fargo'!$B:$B,"<="&'Cash Flow'!AR$3,'Wells Fargo'!$B:$B,">"&'Cash Flow'!AQ$3) -> 0 | AS6: =SUMIFS('Wells Fargo'!$F:$F,'Wells Fargo'!$G:$G,'Cash Flow'!$A6,'Wells Fargo'!$A:$A,AS$1,'Wells Fargo'!$B:$B,"<="&'Cash Flow'!AS$3,'Wells Fargo'!$B:$B,">"&'Cash Flow'!AR$3) -> 0 | AT6: =SUMIFS('Wells Fargo'!$F:$F,'Wells Fargo'!$G:$G,'Cash Flow'!$A6,'Wells Fargo'!$A:$A,AT$1,'Wells Fargo'!$B:$B,"<="&'Cash Flow'!AT$3,'Wells Fargo'!$B:$B,">"&'Cash Flow'!AS$3) -> 0 | AU6: =SUMIFS('Wells Fargo'!$F:$F,'Wells Fargo'!$G:$G,'Cash Flow'!$A6,'Wells Fargo'!$A:$A,AU$1,'Wells Fargo'!$B:$B,"<="&'Cash Flow'!AU$3) -> 0 | AV6: =SUMIFS('Wells Fargo'!$F:$F,'Wells Fargo'!$G:$G,'Cash Flow'!$A6,'Wells Fargo'!$A:$A,AV$1,'Wells Fargo'!$B:$B,"<="&'Cash Flow'!AV$3,'Wells Fargo'!$B:$B,">"&'Cash Flow'!AU$3) -> 0 | AW6: =SUMIFS('Wells Fargo'!$F:$F,'Wells Fargo'!$G:$G,'Cash Flow'!$A6,'Wells Fargo'!$A:$A,AW$1,'Wells Fargo'!$B:$B,"<="&'Cash Flow'!AW$3,'Wells Fargo'!$B:$B,">"&'Cash Flow'!AV$3) -> 0 | AX6: =SUMIFS('Wells Fargo'!$F:$F,'Wells Fargo'!$G:$G,'Cash Flow'!$A6,'Wells Fargo'!$A:$A,AX$1,'Wells Fargo'!$B:$B,"<="&'Cash Flow'!AX$3,'Wells Fargo'!$B:$B,">"&'Cash Flow'!AW$3) -> 0 | AY6: =SUMIFS('Wells Fargo'!$F:$F,'Wells Fargo'!$G:$G,'Cash Flow'!$A6,'Wells Fargo'!$A:$A,AY$1,'Wells Fargo'!$B:$B,"<="&'Cash Flow'!AY$3,'Wells Fargo'!$B:$B,">"&'Cash Flow'!AX$3) -> 0 | AZ6: =SUMIFS('Wells Fargo'!$F:$F,'Wells Fargo'!$G:$G,'Cash Flow'!$A6,'Wells Fargo'!$A:$A,AZ$1,'Wells Fargo'!$B:$B,"<="&'Cash Flow'!AZ$3) -> 0 | BA6: =SUMIFS('Wells Fargo'!$F:$F,'Wells Fargo'!$G:$G,'Cash Flow'!$A6,'Wells Fargo'!$A:$A,BA$1,'Wells Fargo'!$B:$B,"<="&'Cash Flow'!BA$3,'Wells Fargo'!$B:$B,">"&'Cash Flow'!AZ$3) -> 0 | BB6: =SUMIFS('Wells Fargo'!$F:$F,'Wells Fargo'!$G:$G,'Cash Flow'!$A6,'Wells Fargo'!$A:$A,BB$1,'Wells Fargo'!$B:$B,"<="&'Cash Flow'!BB$3,'Wells Fargo'!$B:$B,">"&'Cash Flow'!BA$3) -> 0 | BC6: =SUMIFS('Wells Fargo'!$F:$F,'Wells Fargo'!$G:$G,'Cash Flow'!$A6,'Wells Fargo'!$A:$A,BC$1,'Wells Fargo'!$B:$B,"<="&'Cash Flow'!BC$3,'Wells Fargo'!$B:$B,">"&'Cash Flow'!BB$3) -> 0 | BD6: =SUMIFS('Wells Fargo'!$F:$F,'Wells Fargo'!$G:$G,'Cash Flow'!$A6,'Wells Fargo'!$A:$A,BD$1,'Wells Fargo'!$B:$B,"<="&'Cash Flow'!BD$3,'Wells Fargo'!$B:$B,">"&'Cash Flow'!BC$3) -> 0 | BE6: =SUMIFS('Wells Fargo'!$F:$F,'Wells Fargo'!$G:$G,'Cash Flow'!$A6,'Wells Fargo'!$A:$A,BE$1,'Wells Fargo'!$B:$B,"<="&'Cash Flow'!BE$3) -> 0 | BF6: =SUMIFS('Wells Fargo'!$F:$F,'Wells Fargo'!$G:$G,'Cash Flow'!$A6,'Wells Fargo'!$A:$A,BF$1,'Wells Fargo'!$B:$B,"<="&'Cash Flow'!BF$3,'Wells Fargo'!$B:$B,">"&'Cash Flow'!BE$3) -> 0 | BG6: =SUMIFS('Wells Fargo'!$F:$F,'Wells Fargo'!$G:$G,'Cash Flow'!$A6,'Wells Fargo'!$A:$A,BG$1,'Wells Fargo'!$B:$B,"<="&'Cash Flow'!BG$3,'Wells Fargo'!$B:$B,">"&'Cash Flow'!BF$3) -> 0 | BH6: =SUMIFS('Wells Fargo'!$F:$F,'Wells Fargo'!$G:$G,'Cash Flow'!$A6,'Wells Fargo'!$A:$A,BH$1,'Wells Fargo'!$B:$B,"<="&'Cash Flow'!BH$3,'Wells Fargo'!$B:$B,">"&'Cash Flow'!BG$3) -> 0 | BI6: =SUMIFS('Wells Fargo'!$F:$F,'Wells Fargo'!$G:$G,'Cash Flow'!$A6,'Wells Fargo'!$A:$A,BI$1,'Wells Fargo'!$B:$B,"<="&'Cash Flow'!BI$3,'Wells Fargo'!$B:$B,">"&'Cash Flow'!BH$3) -> 0
A7: Amar - Electric | B7: =SUM(C7:BI7) -> -592.54 | C7: =SUMIFS('Wells Fargo'!$F:$F,'Wells Fargo'!$G:$G,'Cash Flow'!$A7,'Wells Fargo'!$A:$A,C$1,'Wells Fargo'!$B:$B,"<="&'Cash Flow'!C$3) -> 0 | D7: =SUMIFS('Wells Fargo'!$F:$F,'Wells Fargo'!$G:$G,'Cash Flow'!$A7,'Wells Fargo'!$A:$A,D$1,'Wells Fargo'!$B:$B,"<="&'Cash Flow'!D$3,'Wells Fargo'!$B:$B,">"&'Cash Flow'!C$3) -> 0 | E7: =SUMIFS('Wells Fargo'!$F:$F,'Wells Fargo'!$G:$G,'Cash Flow'!$A7,'Wells Fargo'!$A:$A,E$1,'Wells Fargo'!$B:$B,"<="&'Cash Flow'!E$3,'Wells Fargo'!$B:$B,">"&'Cash Flow'!D$3) -> 0 | F7: =SUMIFS('Wells Fargo'!$F:$F,'Wells Fargo'!$G:$G,'Cash Flow'!$A7,'Wells Fargo'!$A:$A,F$1,'Wells Fargo'!$B:$B,"<="&'Cash Flow'!F$3,'Wells Fargo'!$B:$B,">"&'Cash Flow'!E$3) -> -78.86 | G7: =SUMIFS('Wells Fargo'!$F:$F,'Wells Fargo'!$G:$G,'Cash Flow'!$A7,'Wells Fargo'!$A:$A,G$1,'Wells Fargo'!$B:$B,"<="&'Cash Flow'!G$3,'Wells Fargo'!$B:$B,">"&'Cash Flow'!F$3) -> 0 | H7: =SUMIFS('Wells Fargo'!$F:$F,'Wells Fargo'!$G:$G,'Cash Flow'!$A7,'Wells Fargo'!$A:$A,H$1,'Wells Fargo'!$B:$B,"<="&'Cash Flow'!H$3) -> 0 | I7: =SUMIFS('Wells Fargo'!$F:$F,'Wells Fargo'!$G:$G,'Cash Flow'!$A7,'Wells Fargo'!$A:$A,I$1,'Wells Fargo'!$B:$B,"<="&'Cash Flow'!I$3,'Wells Fargo'!$B:$B,">"&'Cash Flow'!H$3) -> 0 | J7: =SUMIFS('Wells Fargo'!$F:$F,'Wells Fargo'!$G:$G,'Cash Flow'!$A7,'Wells Fargo'!$A:$A,J$1,'Wells Fargo'!$B:$B,"<="&'Cash Flow'!J$3,'Wells Fargo'!$B:$B,">"&'Cash Flow'!I$3) -> 0 | K7: =SUMIFS('Wells Fargo'!$F:$F,'Wells Fargo'!$G:$G,'Cash Flow'!$A7,'Wells Fargo'!$A:$A,K$1,'Wells Fargo'!$B:$B,"<="&'Cash Flow'!K$3,'Wells Fargo'!$B:$B,">"&'Cash Flow'!J$3) -> -81.32 | L7: =SUMIFS('Wells Fargo'!$F:$F,'Wells Fargo'!$G:$G,'Cash Flow'!$A7,'Wells Fargo'!$A:$A,L$1,'Wells Fargo'!$B:$B,"<="&'Cash Flow'!L$3) -> 0 | M7: =SUMIFS('Wells Fargo'!$F:$F,'Wells Fargo'!$G:$G,'Cash Flow'!$A7,'Wells Fargo'!$A:$A,M$1,'Wells Fargo'!$B:$B,"<="&'Cash Flow'!M$3,'Wells Fargo'!$B:$B,">"&'Cash Flow'!L$3) -> 0 | N7: =SUMIFS('Wells Fargo'!$F:$F,'Wells Fargo'!$G:$G,'Cash Flow'!$A7,'Wells Fargo'!$A:$A,N$1,'Wells Fargo'!$B:$B,"<="&'Cash Flow'!N$3,'Wells Fargo'!$B:$B,">"&'Cash Flow'!M$3) -> -39.7 | O7: =SUMIFS('Wells Fargo'!$F:$F,'Wells Fargo'!$G:$G,'Cash Flow'!$A7,'Wells Fargo'!$A:$A,O$1,'Wells Fargo'!$B:$B,"<="&'Cash Flow'!O$3,'Wells Fargo'!$B:$B,">"&'Cash Flow'!N$3) -> 0 | P7: =SUMIFS('Wells Fargo'!$F:$F,'Wells Fargo'!$G:$G,'Cash Flow'!$A7,'Wells Fargo'!$A:$A,P$1,'Wells Fargo'!$B:$B,"<="&'Cash Flow'!P$3,'Wells Fargo'!$B:$B,">"&'Cash Flow'!O$3) -> 0 | Q7: =SUMIFS('Wells Fargo'!$F:$F,'Wells Fargo'!$G:$G,'Cash Flow'!$A7,'Wells Fargo'!$A:$A,Q$1,'Wells Fargo'!$B:$B,"<="&'Cash Flow'!Q$3) -> 0 | R7: =SUMIFS('Wells Fargo'!$F:$F,'Wells Fargo'!$G:$G,'Cash Flow'!$A7,'Wells Fargo'!$A:$A,R$1,'Wells Fargo'!$B:$B,"<="&'Cash Flow'!R$3,'Wells Fargo'!$B:$B,">"&'Cash Flow'!Q$3) -> 0 | S7: =SUMIFS('Wells Fargo'!$F:$F,'Wells Fargo'!$G:$G,'Cash Flow'!$A7,'Wells Fargo'!$A:$A,S$1,'Wells Fargo'!$B:$B,"<="&'Cash Flow'!S$3,'Wells Fargo'!$B:$B,">"&'Cash Flow'!R$3) -> -138.52 | T7: =SUMIFS('Wells Fargo'!$F:$F,'Wells Fargo'!$G:$G,'Cash Flow'!$A7,'Wells Fargo'!$A:$A,T$1,'Wells Fargo'!$B:$B,"<="&'Cash Flow'!T$3,'Wells Fargo'!$B:$B,">"&'Cash Flow'!S$3) -> 0 | U7: =SUMIFS('Wells Fargo'!$F:$F,'Wells Fargo'!$G:$G,'Cash Flow'!$A7,'Wells Fargo'!$A:$A,U$1,'Wells Fargo'!$B:$B,"<="&'Cash Flow'!U$3,'Wells Fargo'!$B:$B,">"&'Cash Flow'!T$3) -> 0 | V7: =SUMIFS('Wells Fargo'!$F:$F,'Wells Fargo'!$G:$G,'Cash Flow'!$A7,'Wells Fargo'!$A:$A,V$1,'Wells Fargo'!$B:$B,"<="&'Cash Flow'!V$3) -> 0 | W7: =SUMIFS('Wells Fargo'!$F:$F,'Wells Fargo'!$G:$G,'Cash Flow'!$A7,'Wells Fargo'!$A:$A,W$1,'Wells Fargo'!$B:$B,"<="&'Cash Flow'!W$3,'Wells Fargo'!$B:$B,">"&'Cash Flow'!V$3) -> -136.14 | X7: =SUMIFS('Wells Fargo'!$F:$F,'Wells Fargo'!$G:$G,'Cash Flow'!$A7,'Wells Fargo'!$A:$A,X$1,'Wells Fargo'!$B:$B,"<="&'Cash Flow'!X$3,'Wells Fargo'!$B:$B,">"&'Cash Flow'!W$3) -> 0 | Y7: =SUMIFS('Wells Fargo'!$F:$F,'Wells Fargo'!$G:$G,'Cash Flow'!$A7,'Wells Fargo'!$A:$A,Y$1,'Wells Fargo'!$B:$B,"<="&'Cash Flow'!Y$3,'Wells Fargo'!$B:$B,">"&'Cash Flow'!X$3) -> 0 | Z7: =SUMIFS('Wells Fargo'!$F:$F,'Wells Fargo'!$G:$G,'Cash Flow'!$A7,'Wells Fargo'!$A:$A,Z$1,'Wells Fargo'!$B:$B,"<="&'Cash Flow'!Z$3,'Wells Fargo'!$B:$B,">"&'Cash Flow'!Y$3) -> 0 | AA7: =SUMIFS('Wells Fargo'!$F:$F,'Wells Fargo'!$G:$G,'Cash Flow'!$A7,'Wells Fargo'!$A:$A,AA$1,'Wells Fargo'!$B:$B,"<="&'Cash Flow'!AA$3) -> -118 | AB7: =SUMIFS('Wells Fargo'!$F:$F,'Wells Fargo'!$G:$G,'Cash Flow'!$A7,'Wells Fargo'!$A:$A,AB$1,'Wells Fargo'!$B:$B,"<="&'Cash Flow'!AB$3,'Wells Fargo'!$B:$B,">"&'Cash Flow'!AA$3) -> 0 | AC7: =SUMIFS('Wells Fargo'!$F:$F,'Wells Fargo'!$G:$G,'Cash Flow'!$A7,'Wells Fargo'!$A:$A,AC$1,'Wells Fargo'!$B:$B,"<="&'Cash Flow'!AC$3,'Wells Fargo'!$B:$B,">"&'Cash Flow'!AB$3) -> 0 | AD7: =SUMIFS('Wells Fargo'!$F:$F,'Wells Fargo'!$G:$G,'Cash Flow'!$A7,'Wells Fargo'!$A:$A,AD$1,'Wells Fargo'!$B:$B,"<="&'Cash Flow'!AD$3,'Wells Fargo'!$B:$B,">"&'Cash Flow'!AC$3) -> 0 | AE7: =SUMIFS('Wells Fargo'!$F:$F,'Wells Fargo'!$G:$G,'Cash Flow'!$A7,'Wells Fargo'!$A:$A,AE$1,'Wells Fargo'!$B:$B,"<="&'Cash Flow'!AE$3,'Wells Fargo'!$B:$B,">"&'Cash Flow'!AD$3) -> 0 | AF7: =SUMIFS('Wells Fargo'!$F:$F,'Wells Fargo'!$G:$G,'Cash Flow'!$A7,'Wells Fargo'!$A:$A,AF$1,'Wells Fargo'!$B:$B,"<="&'Cash Flow'!AF$3) -> 0 | AG7: =SUMIFS('Wells Fargo'!$F:$F,'Wells Fargo'!$G:$G,'Cash Flow'!$A7,'Wells Fargo'!$A:$A,AG$1,'Wells Fargo'!$B:$B,"<="&'Cash Flow'!AG$3,'Wells Fargo'!$B:$B,">"&'Cash Flow'!AF$3) -> 0 | AH7: =SUMIFS('Wells Fargo'!$F:$F,'Wells Fargo'!$G:$G,'Cash Flow'!$A7,'Wells Fargo'!$A:$A,AH$1,'Wells Fargo'!$B:$B,"<="&'Cash Flow'!AH$3,'Wells Fargo'!$B:$B,">"&'Cash Flow'!AG$3) -> 0 | AI7: =SUMIFS('Wells Fargo'!$F:$F,'Wells Fargo'!$G:$G,'Cash Flow'!$A7,'Wells Fargo'!$A:$A,AI$1,'Wells Fargo'!$B:$B,"<="&'Cash Flow'!AI$3,'Wells Fargo'!$B:$B,">"&'Cash Flow'!AH$3) -> 0 | AJ7: =SUMIFS('Wells Fargo'!$F:$F,'Wells Fargo'!$G:$G,'Cash Flow'!$A7,'Wells Fargo'!$A:$A,AJ$1,'Wells Fargo'!$B:$B,"<="&'Cash Flow'!AJ$3,'Wells Fargo'!$B:$B,">"&'Cash Flow'!AI$3) -> 0 | AK7: =SUMIFS('Wells Fargo'!$F:$F,'Wells Fargo'!$G:$G,'Cash Flow'!$A7,'Wells Fargo'!$A:$A,AK$1,'Wells Fargo'!$B:$B,"<="&'Cash Flow'!AK$3) -> 0 | AL7: =SUMIFS('Wells Fargo'!$F:$F,'Wells Fargo'!$G:$G,'Cash Flow'!$A7,'Wells Fargo'!$A:$A,AL$1,'Wells Fargo'!$B:$B,"<="&'Cash Flow'!AL$3,'Wells Fargo'!$B:$B,">"&'Cash Flow'!AK$3) -> 0 | AM7: =SUMIFS('Wells Fargo'!$F:$F,'Wells Fargo'!$G:$G,'Cash Flow'!$A7,'Wells Fargo'!$A:$A,AM$1,'Wells Fargo'!$B:$B,"<="&'Cash Flow'!AM$3,'Wells Fargo'!$B:$B,">"&'Cash Flow'!AL$3) -> 0 | AN7: =SUMIFS('Wells Fargo'!$F:$F,'Wells Fargo'!$G:$G,'Cash Flow'!$A7,'Wells Fargo'!$A:$A,AN$1,'Wells Fargo'!$B:$B,"<="&'Cash Flow'!AN$3,'Wells Fargo'!$B:$B,">"&'Cash Flow'!AM$3) -> 0 | AO7: =SUMIFS('Wells Fargo'!$F:$F,'Wells Fargo'!$G:$G,'Cash Flow'!$A7,'Wells Fargo'!$A:$A,AO$1,'Wells Fargo'!$B:$B,"<="&'Cash Flow'!AO$3,'Wells Fargo'!$B:$B,">"&'Cash Flow'!AN$3) -> 0 | AP7: =SUMIFS('Wells Fargo'!$F:$F,'Wells Fargo'!$G:$G,'Cash Flow'!$A7,'Wells Fargo'!$A:$A,AP$1,'Wells Fargo'!$B:$B,"<="&'Cash Flow'!AP$3) -> 0 | AQ7: =SUMIFS('Wells Fargo'!$F:$F,'Wells Fargo'!$G:$G,'Cash Flow'!$A7,'Wells Fargo'!$A:$A,AQ$1,'Wells Fargo'!$B:$B,"<="&'Cash Flow'!AQ$3,'Wells Fargo'!$B:$B,">"&'Cash Flow'!AP$3) -> 0 | AR7: =SUMIFS('Wells Fargo'!$F:$F,'Wells Fargo'!$G:$G,'Cash Flow'!$A7,'Wells Fargo'!$A:$A,AR$1,'Wells Fargo'!$B:$B,"<="&'Cash Flow'!AR$3,'Wells Fargo'!$B:$B,">"&'Cash Flow'!AQ$3) -> 0 | AS7: =SUMIFS('Wells Fargo'!$F:$F,'Wells Fargo'!$G:$G,'Cash Flow'!$A7,'Wells Fargo'!$A:$A,AS$1,'Wells Fargo'!$B:$B,"<="&'Cash Flow'!AS$3,'Wells Fargo'!$B:$B,">"&'Cash Flow'!AR$3) -> 0 | AT7: =SUMIFS('Wells Fargo'!$F:$F,'Wells Fargo'!$G:$G,'Cash Flow'!$A7,'Wells Fargo'!$A:$A,AT$1,'Wells Fargo'!$B:$B,"<="&'Cash Flow'!AT$3,'Wells Fargo'!$B:$B,">"&'Cash Flow'!AS$3) -> 0 | AU7: =SUMIFS('Wells Fargo'!$F:$F,'Wells Fargo'!$G:$G,'Cash Flow'!$A7,'Wells Fargo'!$A:$A,AU$1,'Wells Fargo'!$B:$B,"<="&'Cash Flow'!AU$3) -> 0 | AV7: =SUMIFS('Wells Fargo'!$F:$F,'Wells Fargo'!$G:$G,'Cash Flow'!$A7,'Wells Fargo'!$A:$A,AV$1,'Wells Fargo'!$B:$B,"<="&'Cash Flow'!AV$3,'Wells Fargo'!$B:$B,">"&'Cash Flow'!AU$3) -> 0 | AW7: =SUMIFS('Wells Fargo'!$F:$F,'Wells Fargo'!$G:$G,'Cash Flow'!$A7,'Wells Fargo'!$A:$A,AW$1,'Wells Fargo'!$B:$B,"<="&'Cash Flow'!AW$3,'Wells Fargo'!$B:$B,">"&'Cash Flow'!AV$3) -> 0 | AX7: =SUMIFS('Wells Fargo'!$F:$F,'Wells Fargo'!$G:$G,'Cash Flow'!$A7,'Wells Fargo'!$A:$A,AX$1,'Wells Fargo'!$B:$B,"<="&'Cash Flow'!AX$3,'Wells Fargo'!$B:$B,">"&'Cash Flow'!AW$3) -> 0 | AY7: =SUMIFS('Wells Fargo'!$F:$F,'Wells Fargo'!$G:$G,'Cash Flow'!$A7,'Wells Fargo'!$A:$A,AY$1,'Wells Fargo'!$B:$B,"<="&'Cash Flow'!AY$3,'Wells Fargo'!$B:$B,">"&'Cash Flow'!AX$3) -> 0 | AZ7: =SUMIFS('Wells Fargo'!$F:$F,'Wells Fargo'!$G:$G,'Cash Flow'!$A7,'Wells Fargo'!$A:$A,AZ$1,'Wells Fargo'!$B:$B,"<="&'Cash Flow'!AZ$3) -> 0 | BA7: =SUMIFS('Wells Fargo'!$F:$F,'Wells Fargo'!$G:$G,'Cash Flow'!$A7,'Wells Fargo'!$A:$A,BA$1,'Wells Fargo'!$B:$B,"<="&'Cash Flow'!BA$3,'Wells Fargo'!$B:$B,">"&'Cash Flow'!AZ$3) -> 0 | BB7: =SUMIFS('Wells Fargo'!$F:$F,'Wells Fargo'!$G:$G,'Cash Flow'!$A7,'Wells Fargo'!$A:$A,BB$1,'Wells Fargo'!$B:$B,"<="&'Cash Flow'!BB$3,'Wells Fargo'!$B:$B,">"&'Cash Flow'!BA$3) -> 0 | BC7: =SUMIFS('Wells Fargo'!$F:$F,'Wells Fargo'!$G:$G,'Cash Flow'!$A7,'Wells Fargo'!$A:$A,BC$1,'Wells Fargo'!$B:$B,"<="&'Cash Flow'!BC$3,'Wells Fargo'!$B:$B,">"&'Cash Flow'!BB$3) -> 0 | BD7: =SUMIFS('Wells Fargo'!$F:$F,'Wells Fargo'!$G:$G,'Cash Flow'!$A7,'Wells Fargo'!$A:$A,BD$1,'Wells Fargo'!$B:$B,"<="&'Cash Flow'!BD$3,'Wells Fargo'!$B:$B,">"&'Cash Flow'!BC$3) -> 0 | BE7: =SUMIFS('Wells Fargo'!$F:$F,'Wells Fargo'!$G:$G,'Cash Flow'!$A7,'Wells Fargo'!$A:$A,BE$1,'Wells Fargo'!$B:$B,"<="&'Cash Flow'!BE$3) -> 0 | BF7: =SUMIFS('Wells Fargo'!$F:$F,'Wells Fargo'!$G:$G,'Cash Flow'!$A7,'Wells Fargo'!$A:$A,BF$1,'Wells Fargo'!$B:$B,"<="&'Cash Flow'!BF$3,'Wells Fargo'!$B:$B,">"&'Cash Flow'!BE$3) -> 0 | BG7: =SUMIFS('Wells Fargo'!$F:$F,'Wells Fargo'!$G:$G,'Cash Flow'!$A7,'Wells Fargo'!$A:$A,BG$1,'Wells Fargo'!$B:$B,"<="&'Cash Flow'!BG$3,'Wells Fargo'!$B:$B,">"&'Cash Flow'!BF$3) -> 0 | BH7: =SUMIFS('Wells Fargo'!$F:$F,'Wells Fargo'!$G:$G,'Cash Flow'!$A7,'Wells Fargo'!$A:$A,BH$1,'Wells Fargo'!$B:$B,"<="&'Cash Flow'!BH$3,'Wells Fargo'!$B:$B,">"&'Cash Flow'!BG$3) -> 0 | BI7: =SUMIFS('Wells Fargo'!$F:$F,'Wells Fargo'!$G:$G,'Cash Flow'!$A7,'Wells Fargo'!$A:$A,BI$1,'Wells Fargo'!$B:$B,"<="&'Cash Flow'!BI$3,'Wells Fargo'!$B:$B,">"&'Cash Flow'!BH$3) -> 0
A8: Amar - Rent | B8: =SUM(C8:BI8) -> -2800 | C8: =SUMIFS('Wells Fargo'!$F:$F,'Wells Fargo'!$G:$G,'Cash Flow'!$A8,'Wells Fargo'!$A:$A,C$1,'Wells Fargo'!$B:$B,"<="&'Cash Flow'!C$3) -> 0 | D8: =SUMIFS('Wells Fargo'!$F:$F,'Wells Fargo'!$G:$G,'Cash Flow'!$A8,'Wells Fargo'!$A:$A,D$1,'Wells Fargo'!$B:$B,"<="&'Cash Flow'!D$3,'Wells Fargo'!$B:$B,">"&'Cash Flow'!C$3) -> 0 | E8: =SUMIFS('Wells Fargo'!$F:$F,'Wells Fargo'!$G:$G,'Cash Flow'!$A8,'Wells Fargo'!$A:$A,E$1,'Wells Fargo'!$B:$B,"<="&'Cash Flow'!E$3,'Wells Fargo'!$B:$B,">"&'Cash Flow'!D$3) -> 0 | F8: =SUMIFS('Wells Fargo'!$F:$F,'Wells Fargo'!$G:$G,'Cash Flow'!$A8,'Wells Fargo'!$A:$A,F$1,'Wells Fargo'!$B:$B,"<="&'Cash Flow'!F$3,'Wells Fargo'!$B:$B,">"&'Cash Flow'!E$3) -> 0 | G8: =SUMIFS('Wells Fargo'!$F:$F,'Wells Fargo'!$G:$G,'Cash Flow'!$A8,'Wells Fargo'!$A:$A,G$1,'Wells Fargo'!$B:$B,"<="&'Cash Flow'!G$3,'Wells Fargo'!$B:$B,">"&'Cash Flow'!F$3) -> -700 | H8: =SUMIFS('Wells Fargo'!$F:$F,'Wells Fargo'!$G:$G,'Cash Flow'!$A8,'Wells Fargo'!$A:$A,H$1,'Wells Fargo'!$B:$B,"<="&'Cash Flow'!H$3) -> 0 | I8: =SUMIFS('Wells Fargo'!$F:$F,'Wells Fargo'!$G:$G,'Cash Flow'!$A8,'Wells Fargo'!$A:$A,I$1,'Wells Fargo'!$B:$B,"<="&'Cash Flow'!I$3,'Wells Fargo'!$B:$B,">"&'Cash Flow'!H$3) -> 0 | J8: =SUMIFS('Wells Fargo'!$F:$F,'Wells Fargo'!$G:$G,'Cash Flow'!$A8,'Wells Fargo'!$A:$A,J$1,'Wells Fargo'!$B:$B,"<="&'Cash Flow'!J$3,'Wells Fargo'!$B:$B,">"&'Cash Flow'!I$3) -> 0 | K8: =SUMIFS('Wells Fargo'!$F:$F,'Wells Fargo'!$G:$G,'Cash Flow'!$A8,'Wells Fargo'!$A:$A,K$1,'Wells Fargo'!$B:$B,"<="&'Cash Flow'!K$3,'Wells Fargo'!$B:$B,">"&'Cash Flow'!J$3) -> -700 | L8: =SUMIFS('Wells Fargo'!$F:$F,'Wells Fargo'!$G:$G,'Cash Flow'!$A8,'Wells Fargo'!$A:$A,L$1,'Wells Fargo'!$B:$B,"<="&'Cash Flow'!L$3) -> 0 | M8: =SUMIFS('Wells Fargo'!$F:$F,'Wells Fargo'!$G:$G,'Cash Flow'!$A8,'Wells Fargo'!$A:$A,M$1,'Wells Fargo'!$B:$B,"<="&'Cash Flow'!M$3,'Wells Fargo'!$B:$B,">"&'Cash Flow'!L$3) -> 0 | N8: =SUMIFS('Wells Fargo'!$F:$F,'Wells Fargo'!$G:$G,'Cash Flow'!$A8,'Wells Fargo'!$A:$A,N$1,'Wells Fargo'!$B:$B,"<="&'Cash Flow'!N$3,'Wells Fargo'!$B:$B,">"&'Cash Flow'!M$3) -> -700 | O8: =SUMIFS('Wells Fargo'!$F:$F,'Wells Fargo'!$G:$G,'Cash Flow'!$A8,'Wells Fargo'!$A:$A,O$1,'Wells Fargo'!$B:$B,"<="&'Cash Flow'!O$3,'Wells Fargo'!$B:$B,">"&'Cash Flow'!N$3) -> 0 | P8: =SUMIFS('Wells Fargo'!$F:$F,'Wells Fargo'!$G:$G,'Cash Flow'!$A8,'Wells Fargo'!$A:$A,P$1,'Wells Fargo'!$B:$B,"<="&'Cash Flow'!P$3,'Wells Fargo'!$B:$B,">"&'Cash Flow'!O$3) -> 0 | Q8: =SUMIFS('Wells Fargo'!$F:$F,'Wells Fargo'!$G:$G,'Cash Flow'!$A8,'Wells Fargo'!$A:$A,Q$1,'Wells Fargo'!$B:$B,"<="&'Cash Flow'!Q$3) -> 0 | R8: =SUMIFS('Wells Fargo'!$F:$F,'Wells Fargo'!$G:$G,'Cash Flow'!$A8,'Wells Fargo'!$A:$A,R$1,'Wells Fargo'!$B:$B,"<="&'Cash Flow'!R$3,'Wells Fargo'!$B:$B,">"&'Cash Flow'!Q$3) -> 0 | S8: =SUMIFS('Wells Fargo'!$F:$F,'Wells Fargo'!$G:$G,'Cash Flow'!$A8,'Wells Fargo'!$A:$A,S$1,'Wells Fargo'!$B:$B,"<="&'Cash Flow'!S$3,'Wells Fargo'!$B:$B,">"&'Cash Flow'!R$3) -> 0 | T8: =SUMIFS('Wells Fargo'!$F:$F,'Wells Fargo'!$G:$G,'Cash Flow'!$A8,'Wells Fargo'!$A:$A,T$1,'Wells Fargo'!$B:$B,"<="&'Cash Flow'!T$3,'Wells Fargo'!$B:$B,">"&'Cash Flow'!S$3) -> -700 | U8: =SUMIFS('Wells Fargo'!$F:$F,'Wells Fargo'!$G:$G,'Cash Flow'!$A8,'Wells Fargo'!$A:$A,U$1,'Wells Fargo'!$B:$B,"<="&'Cash Flow'!U$3,'Wells Fargo'!$B:$B,">"&'Cash Flow'!T$3) -> 0 | V8: =SUMIFS('Wells Fargo'!$F:$F,'Wells Fargo'!$G:$G,'Cash Flow'!$A8,'Wells Fargo'!$A:$A,V$1,'Wells Fargo'!$B:$B,"<="&'Cash Flow'!V$3) -> 0 | W8: =SUMIFS('Wells Fargo'!$F:$F,'Wells Fargo'!$G:$G,'Cash Flow'!$A8,'Wells Fargo'!$A:$A,W$1,'Wells Fargo'!$B:$B,"<="&'Cash Flow'!W$3,'Wells Fargo'!$B:$B,">"&'Cash Flow'!V$3) -> 0 | X8: =SUMIFS('Wells Fargo'!$F:$F,'Wells Fargo'!$G:$G,'Cash Flow'!$A8,'Wells Fargo'!$A:$A,X$1,'Wells Fargo'!$B:$B,"<="&'Cash Flow'!X$3,'Wells Fargo'!$B:$B,">"&'Cash Flow'!W$3) -> 0 | Y8: =SUMIFS('Wells Fargo'!$F:$F,'Wells Fargo'!$G:$G,'Cash Flow'!$A8,'Wells Fargo'!$A:$A,Y$1,'Wells Fargo'!$B:$B,"<="&'Cash Flow'!Y$3,'Wells Fargo'!$B:$B,">"&'Cash Flow'!X$3) -> 0 | Z8: =SUMIFS('Wells Fargo'!$F:$F,'Wells Fargo'!$G:$G,'Cash Flow'!$A8,'Wells Fargo'!$A:$A,Z$1,'Wells Fargo'!$B:$B,"<="&'Cash Flow'!Z$3,'Wells Fargo'!$B:$B,">"&'Cash Flow'!Y$3) -> 0 | AA8: =SUMIFS('Wells Fargo'!$F:$F,'Wells Fargo'!$G:$G,'Cash Flow'!$A8,'Wells Fargo'!$A:$A,AA$1,'Wells Fargo'!$B:$B,"<="&'Cash Flow'!AA$3) -> 0 | AB8: =SUMIFS('Wells Fargo'!$F:$F,'Wells Fargo'!$G:$G,'Cash Flow'!$A8,'Wells Fargo'!$A:$A,AB$1,'Wells Fargo'!$B:$B,"<="&'Cash Flow'!AB$3,'Wells Fargo'!$B:$B,">"&'Cash Flow'!AA$3) -> 0 | AC8: =SUMIFS('Wells Fargo'!$F:$F,'Wells Fargo'!$G:$G,'Cash Flow'!$A8,'Wells Fargo'!$A:$A,AC$1,'Wells Fargo'!$B:$B,"<="&'Cash Flow'!AC$3,'Wells Fargo'!$B:$B,">"&'Cash Flow'!AB$3) -> 0 | AD8: =SUMIFS('Wells Fargo'!$F:$F,'Wells Fargo'!$G:$G,'Cash Flow'!$A8,'Wells Fargo'!$A:$A,AD$1,'Wells Fargo'!$B:$B,"<="&'Cash Flow'!AD$3,'Wells Fargo'!$B:$B,">"&'Cash Flow'!AC$3) -> 0 | AE8: =SUMIFS('Wells Fargo'!$F:$F,'Wells Fargo'!$G:$G,'Cash Flow'!$A8,'Wells Fargo'!$A:$A,AE$1,'Wells Fargo'!$B:$B,"<="&'Cash Flow'!AE$3,'Wells Fargo'!$B:$B,">"&'Cash Flow'!AD$3) -> 0 | AF8: =SUMIFS('Wells Fargo'!$F:$F,'Wells Fargo'!$G:$G,'Cash Flow'!$A8,'Wells Fargo'!$A:$A,AF$1,'Wells Fargo'!$B:$B,"<="&'Cash Flow'!AF$3) -> 0 | AG8: =SUMIFS('Wells Fargo'!$F:$F,'Wells Fargo'!$G:$G,'Cash Flow'!$A8,'Wells Fargo'!$A:$A,AG$1,'Wells Fargo'!$B:$B,"<="&'Cash Flow'!AG$3,'Wells Fargo'!$B:$B,">"&'Cash Flow'!AF$3) -> 0 | AH8: =SUMIFS('Wells Fargo'!$F:$F,'Wells Fargo'!$G:$G,'Cash Flow'!$A8,'Wells Fargo'!$A:$A,AH$1,'Wells Fargo'!$B:$B,"<="&'Cash Flow'!AH$3,'Wells Fargo'!$B:$B,">"&'Cash Flow'!AG$3) -> 0 | AI8: =SUMIFS('Wells Fargo'!$F:$F,'Wells Fargo'!$G:$G,'Cash Flow'!$A8,'Wells Fargo'!$A:$A,AI$1,'Wells Fargo'!$B:$B,"<="&'Cash Flow'!AI$3,'Wells Fargo'!$B:$B,">"&'Cash Flow'!AH$3) -> 0 | AJ8: =SUMIFS('Wells Fargo'!$F:$F,'Wells Fargo'!$G:$G,'Cash Flow'!$A8,'Wells Fargo'!$A:$A,AJ$1,'Wells Fargo'!$B:$B,"<="&'Cash Flow'!AJ$3,'Wells Fargo'!$B:$B,">"&'Cash Flow'!AI$3) -> 0 | AK8: =SUMIFS('Wells Fargo'!$F:$F,'Wells Fargo'!$G:$G,'Cash Flow'!$A8,'Wells Fargo'!$A:$A,AK$1,'Wells Fargo'!$B:$B,"<="&'Cash Flow'!AK$3) -> 0 | AL8: =SUMIFS('Wells Fargo'!$F:$F,'Wells Fargo'!$G:$G,'Cash Flow'!$A8,'Wells Fargo'!$A:$A,AL$1,'Wells Fargo'!$B:$B,"<="&'Cash Flow'!AL$3,'Wells Fargo'!$B:$B,">"&'Cash Flow'!AK$3) -> 0 | AM8: =SUMIFS('Wells Fargo'!$F:$F,'Wells Fargo'!$G:$G,'Cash Flow'!$A8,'Wells Fargo'!$A:$A,AM$1,'Wells Fargo'!$B:$B,"<="&'Cash Flow'!AM$3,'Wells Fargo'!$B:$B,">"&'Cash Flow'!AL$3) -> 0 | AN8: =SUMIFS('Wells Fargo'!$F:$F,'Wells Fargo'!$G:$G,'Cash Flow'!$A8,'Wells Fargo'!$A:$A,AN$1,'Wells Fargo'!$B:$B,"<="&'Cash Flow'!AN$3,'Wells Fargo'!$B:$B,">"&'Cash Flow'!AM$3) -> 0 | AO8: =SUMIFS('Wells Fargo'!$F:$F,'Wells Fargo'!$G:$G,'Cash Flow'!$A8,'Wells Fargo'!$A:$A,AO$1,'Wells Fargo'!$B:$B,"<="&'Cash Flow'!AO$3,'Wells Fargo'!$B:$B,">"&'Cash Flow'!AN$3) -> 0 | AP8: =SUMIFS('Wells Fargo'!$F:$F,'Wells Fargo'!$G:$G,'Cash Flow'!$A8,'Wells Fargo'!$A:$A,AP$1,'Wells Fargo'!$B:$B,"<="&'Cash Flow'!AP$3) -> 0 | AQ8: =SUMIFS('Wells Fargo'!$F:$F,'Wells Fargo'!$G:$G,'Cash Flow'!$A8,'Wells Fargo'!$A:$A,AQ$1,'Wells Fargo'!$B:$B,"<="&'Cash Flow'!AQ$3,'Wells Fargo'!$B:$B,">"&'Cash Flow'!AP$3) -> 0 | AR8: =SUMIFS('Wells Fargo'!$F:$F,'Wells Fargo'!$G:$G,'Cash Flow'!$A8,'Wells Fargo'!$A:$A,AR$1,'Wells Fargo'!$B:$B,"<="&'Cash Flow'!AR$3,'Wells Fargo'!$B:$B,">"&'Cash Flow'!AQ$3) -> 0 | AS8: =SUMIFS('Wells Fargo'!$F:$F,'Wells Fargo'!$G:$G,'Cash Flow'!$A8,'Wells Fargo'!$A:$A,AS$1,'Wells Fargo'!$B:$B,"<="&'Cash Flow'!AS$3,'Wells Fargo'!$B:$B,">"&'Cash Flow'!AR$3) -> 0 | AT8: =SUMIFS('Wells Fargo'!$F:$F,'Wells Fargo'!$G:$G,'Cash Flow'!$A8,'Wells Fargo'!$A:$A,AT$1,'Wells Fargo'!$B:$B,"<="&'Cash Flow'!AT$3,'Wells Fargo'!$B:$B,">"&'Cash Flow'!AS$3) -> 0 | AU8: =SUMIFS('Wells Fargo'!$F:$F,'Wells Fargo'!$G:$G,'Cash Flow'!$A8,'Wells Fargo'!$A:$A,AU$1,'Wells Fargo'!$B:$B,"<="&'Cash Flow'!AU$3) -> 0 | AV8: =SUMIFS('Wells Fargo'!$F:$F,'Wells Fargo'!$G:$G,'Cash Flow'!$A8,'Wells Fargo'!$A:$A,AV$1,'Wells Fargo'!$B:$B,"<="&'Cash Flow'!AV$3,'Wells Fargo'!$B:$B,">"&'Cash Flow'!AU$3) -> 0 | AW8: =SUMIFS('Wells Fargo'!$F:$F,'Wells Fargo'!$G:$G,'Cash Flow'!$A8,'Wells Fargo'!$A:$A,AW$1,'Wells Fargo'!$B:$B,"<="&'Cash Flow'!AW$3,'Wells Fargo'!$B:$B,">"&'Cash Flow'!AV$3) -> 0 | AX8: =SUMIFS('Wells Fargo'!$F:$F,'Wells Fargo'!$G:$G,'Cash Flow'!$A8,'Wells Fargo'!$A:$A,AX$1,'Wells Fargo'!$B:$B,"<="&'Cash Flow'!AX$3,'Wells Fargo'!$B:$B,">"&'Cash Flow'!AW$3) -> 0 | AY8: =SUMIFS('Wells Fargo'!$F:$F,'Wells Fargo'!$G:$G,'Cash Flow'!$A8,'Wells Fargo'!$A:$A,AY$1,'Wells Fargo'!$B:$B,"<="&'Cash Flow'!AY$3,'Wells Fargo'!$B:$B,">"&'Cash Flow'!AX$3) -> 0 | AZ8: =SUMIFS('Wells Fargo'!$F:$F,'Wells Fargo'!$G:$G,'Cash Flow'!$A8,'Wells Fargo'!$A:$A,AZ$1,'Wells Fargo'!$B:$B,"<="&'Cash Flow'!AZ$3) -> 0 | BA8: =SUMIFS('Wells Fargo'!$F:$F,'Wells Fargo'!$G:$G,'Cash Flow'!$A8,'Wells Fargo'!$A:$A,BA$1,'Wells Fargo'!$B:$B,"<="&'Cash Flow'!BA$3,'Wells Fargo'!$B:$B,">"&'Cash Flow'!AZ$3) -> 0 | BB8: =SUMIFS('Wells Fargo'!$F:$F,'Wells Fargo'!$G:$G,'Cash Flow'!$A8,'Wells Fargo'!$A:$A,BB$1,'Wells Fargo'!$B:$B,"<="&'Cash Flow'!BB$3,'Wells Fargo'!$B:$B,">"&'Cash Flow'!BA$3) -> 0 | BC8: =SUMIFS('Wells Fargo'!$F:$F,'Wells Fargo'!$G:$G,'Cash Flow'!$A8,'Wells Fargo'!$A:$A,BC$1,'Wells Fargo'!$B:$B,"<="&'Cash Flow'!BC$3,'Wells Fargo'!$B:$B,">"&'Cash Flow'!BB$3) -> 0 | BD8: =SUMIFS('Wells Fargo'!$F:$F,'Wells Fargo'!$G:$G,'Cash Flow'!$A8,'Wells Fargo'!$A:$A,BD$1,'Wells Fargo'!$B:$B,"<="&'Cash Flow'!BD$3,'Wells Fargo'!$B:$B,">"&'Cash Flow'!BC$3) -> 0 | BE8: =SUMIFS('Wells Fargo'!$F:$F,'Wells Fargo'!$G:$G,'Cash Flow'!$A8,'Wells Fargo'!$A:$A,BE$1,'Wells Fargo'!$B:$B,"<="&'Cash Flow'!BE$3) -> 0 | BF8: =SUMIFS('Wells Fargo'!$F:$F,'Wells Fargo'!$G:$G,'Cash Flow'!$A8,'Wells Fargo'!$A:$A,BF$1,'Wells Fargo'!$B:$B,"<="&'Cash Flow'!BF$3,'Wells Fargo'!$B:$B,">"&'Cash Flow'!BE$3) -> 0 | BG8: =SUMIFS('Wells Fargo'!$F:$F,'Wells Fargo'!$G:$G,'Cash Flow'!$A8,'Wells Fargo'!$A:$A,BG$1,'Wells Fargo'!$B:$B,"<="&'Cash Flow'!BG$3,'Wells Fargo'!$B:$B,">"&'Cash Flow'!BF$3) -> 0 | BH8: =SUMIFS('Wells Fargo'!$F:$F,'Wells Fargo'!$G:$G,'Cash Flow'!$A8,'Wells Fargo'!$A:$A,BH$1,'Wells Fargo'!$B:$B,"<="&'Cash Flow'!BH$3,'Wells Fargo'!$B:$B,">"&'Cash Flow'!BG$3) -> 0 | BI8: =SUMIFS('Wells Fargo'!$F:$F,'Wells Fargo'!$G:$G,'Cash Flow'!$A8,'Wells Fargo'!$A:$A,BI$1,'Wells Fargo'!$B:$B,"<="&'Cash Flow'!BI$3,'Wells Fargo'!$B:$B,">"&'Cash Flow'!BH$3) -> 0
A9: Amar - Water | B9: =SUM(C9:BI9) -> -400 | C9: =SUMIFS('Wells Fargo'!$F:$F,'Wells Fargo'!$G:$G,'Cash Flow'!$A9,'Wells Fargo'!$A:$A,C$1,'Wells Fargo'!$B:$B,"<="&'Cash Flow'!C$3) -> 0 | D9: =SUMIFS('Wells Fargo'!$F:$F,'Wells Fargo'!$G:$G,'Cash Flow'!$A9,'Wells Fargo'!$A:$A,D$1,'Wells Fargo'!$B:$B,"<="&'Cash Flow'!D$3,'Wells Fargo'!$B:$B,">"&'Cash Flow'!C$3) -> 0 | E9: =SUMIFS('Wells Fargo'!$F:$F,'Wells Fargo'!$G:$G,'Cash Flow'!$A9,'Wells Fargo'!$A:$A,E$1,'Wells Fargo'!$B:$B,"<="&'Cash Flow'!E$3,'Wells Fargo'!$B:$B,">"&'Cash Flow'!D$3) -> 0 | F9: =SUMIFS('Wells Fargo'!$F:$F,'Wells Fargo'!$G:$G,'Cash Flow'!$A9,'Wells Fargo'!$A:$A,F$1,'Wells Fargo'!$B:$B,"<="&'Cash Flow'!F$3,'Wells Fargo'!$B:$B,">"&'Cash Flow'!E$3) -> 0 | G9: =SUMIFS('Wells Fargo'!$F:$F,'Wells Fargo'!$G:$G,'Cash Flow'!$A9,'Wells Fargo'!$A:$A,G$1,'Wells Fargo'!$B:$B,"<="&'Cash Flow'!G$3,'Wells Fargo'!$B:$B,">"&'Cash Flow'!F$3) -> 0 | H9: =SUMIFS('Wells Fargo'!$F:$F,'Wells Fargo'!$G:$G,'Cash Flow'!$A9,'Wells Fargo'!$A:$A,H$1,'Wells Fargo'!$B:$B,"<="&'Cash Flow'!H$3) -> 0 | I9: =SUMIFS('Wells Fargo'!$F:$F,'Wells Fargo'!$G:$G,'Cash Flow'!$A9,'Wells Fargo'!$A:$A,I$1,'Wells Fargo'!$B:$B,"<="&'Cash Flow'!I$3,'Wells Fargo'!$B:$B,">"&'Cash Flow'!H$3) -> 0 | J9: =SUMIFS('Wells Fargo'!$F:$F,'Wells Fargo'!$G:$G,'Cash Flow'!$A9,'Wells Fargo'!$A:$A,J$1,'Wells Fargo'!$B:$B,"<="&'Cash Flow'!J$3,'Wells Fargo'!$B:$B,">"&'Cash Flow'!I$3) -> 0 | K9: =SUMIFS('Wells Fargo'!$F:$F,'Wells Fargo'!$G:$G,'Cash Flow'!$A9,'Wells Fargo'!$A:$A,K$1,'Wells Fargo'!$B:$B,"<="&'Cash Flow'!K$3,'Wells Fargo'!$B:$B,">"&'Cash Flow'!J$3) -> 0 | L9: =SUMIFS('Wells Fargo'!$F:$F,'Wells Fargo'!$G:$G,'Cash Flow'!$A9,'Wells Fargo'!$A:$A,L$1,'Wells Fargo'!$B:$B,"<="&'Cash Flow'!L$3) -> 0 | M9: =SUMIFS('Wells Fargo'!$F:$F,'Wells Fargo'!$G:$G,'Cash Flow'!$A9,'Wells Fargo'!$A:$A,M$1,'Wells Fargo'!$B:$B,"<="&'Cash Flow'!M$3,'Wells Fargo'!$B:$B,">"&'Cash Flow'!L$3) -> -150 | N9: =SUMIFS('Wells Fargo'!$F:$F,'Wells Fargo'!$G:$G,'Cash Flow'!$A9,'Wells Fargo'!$A:$A,N$1,'Wells Fargo'!$B:$B,"<="&'Cash Flow'!N$3,'Wells Fargo'!$B:$B,">"&'Cash Flow'!M$3) -> 0 | O9: =SUMIFS('Wells Fargo'!$F:$F,'Wells Fargo'!$G:$G,'Cash Flow'!$A9,'Wells Fargo'!$A:$A,O$1,'Wells Fargo'!$B:$B,"<="&'Cash Flow'!O$3,'Wells Fargo'!$B:$B,">"&'Cash Flow'!N$3) -> 0 | P9: =SUMIFS('Wells Fargo'!$F:$F,'Wells Fargo'!$G:$G,'Cash Flow'!$A9,'Wells Fargo'!$A:$A,P$1,'Wells Fargo'!$B:$B,"<="&'Cash Flow'!P$3,'Wells Fargo'!$B:$B,">"&'Cash Flow'!O$3) -> 0 | Q9: =SUMIFS('Wells Fargo'!$F:$F,'Wells Fargo'!$G:$G,'Cash Flow'!$A9,'Wells Fargo'!$A:$A,Q$1,'Wells Fargo'!$B:$B,"<="&'Cash Flow'!Q$3) -> 0 | R9: =SUMIFS('Wells Fargo'!$F:$F,'Wells Fargo'!$G:$G,'Cash Flow'!$A9,'Wells Fargo'!$A:$A,R$1,'Wells Fargo'!$B:$B,"<="&'Cash Flow'!R$3,'Wells Fargo'!$B:$B,">"&'Cash Flow'!Q$3) -> 0 | S9: =SUMIFS('Wells Fargo'!$F:$F,'Wells Fargo'!$G:$G,'Cash Flow'!$A9,'Wells Fargo'!$A:$A,S$1,'Wells Fargo'!$B:$B,"<="&'Cash Flow'!S$3,'Wells Fargo'!$B:$B,">"&'Cash Flow'!R$3) -> -100 | T9: =SUMIFS('Wells Fargo'!$F:$F,'Wells Fargo'!$G:$G,'Cash Flow'!$A9,'Wells Fargo'!$A:$A,T$1,'Wells Fargo'!$B:$B,"<="&'Cash Flow'!T$3,'Wells Fargo'!$B:$B,">"&'Cash Flow'!S$3) -> 0 | U9: =SUMIFS('Wells Fargo'!$F:$F,'Wells Fargo'!$G:$G,'Cash Flow'!$A9,'Wells Fargo'!$A:$A,U$1,'Wells Fargo'!$B:$B,"<="&'Cash Flow'!U$3,'Wells Fargo'!$B:$B,">"&'Cash Flow'!T$3) -> 0 | V9: =SUMIFS('Wells Fargo'!$F:$F,'Wells Fargo'!$G:$G,'Cash Flow'!$A9,'Wells Fargo'!$A:$A,V$1,'Wells Fargo'!$B:$B,"<="&'Cash Flow'!V$3) -> 0 | W9: =SUMIFS('Wells Fargo'!$F:$F,'Wells Fargo'!$G:$G,'Cash Flow'!$A9,'Wells Fargo'!$A:$A,W$1,'Wells Fargo'!$B:$B,"<="&'Cash Flow'!W$3,'Wells Fargo'!$B:$B,">"&'Cash Flow'!V$3) -> -150 | X9: =SUMIFS('Wells Fargo'!$F:$F,'Wells Fargo'!$G:$G,'Cash Flow'!$A9,'Wells Fargo'!$A:$A,X$1,'Wells Fargo'!$B:$B,"<="&'Cash Flow'!X$3,'Wells Fargo'!$B:$B,">"&'Cash Flow'!W$3) -> 0 | Y9: =SUMIFS('Wells Fargo'!$F:$F,'Wells Fargo'!$G:$G,'Cash Flow'!$A9,'Wells Fargo'!$A:$A,Y$1,'Wells Fargo'!$B:$B,"<="&'Cash Flow'!Y$3,'Wells Fargo'!$B:$B,">"&'Cash Flow'!X$3) -> 0 | Z9: =SUMIFS('Wells Fargo'!$F:$F,'Wells Fargo'!$G:$G,'Cash Flow'!$A9,'Wells Fargo'!$A:$A,Z$1,'Wells Fargo'!$B:$B,"<="&'Cash Flow'!Z$3,'Wells Fargo'!$B:$B,">"&'Cash Flow'!Y$3) -> 0 | AA9: =SUMIFS('Wells Fargo'!$F:$F,'Wells Fargo'!$G:$G,'Cash Flow'!$A9,'Wells Fargo'!$A:$A,AA$1,'Wells Fargo'!$B:$B,"<="&'Cash Flow'!AA$3) -> 0 | AB9: =SUMIFS('Wells Fargo'!$F:$F,'Wells Fargo'!$G:$G,'Cash Flow'!$A9,'Wells Fargo'!$A:$A,AB$1,'Wells Fargo'!$B:$B,"<="&'Cash Flow'!AB$3,'Wells Fargo'!$B:$B,">"&'Cash Flow'!AA$3) -> 0 | AC9: =SUMIFS('Wells Fargo'!$F:$F,'Wells Fargo'!$G:$G,'Cash Flow'!$A9,'Wells Fargo'!$A:$A,AC$1,'Wells Fargo'!$B:$B,"<="&'Cash Flow'!AC$3,'Wells Fargo'!$B:$B,">"&'Cash Flow'!AB$3) -> 0 | AD9: =SUMIFS('Wells Fargo'!$F:$F,'Wells Fargo'!$G:$G,'Cash Flow'!$A9,'Wells Fargo'!$A:$A,AD$1,'Wells Fargo'!$B:$B,"<="&'Cash Flow'!AD$3,'Wells Fargo'!$B:$B,">"&'Cash Flow'!AC$3) -> 0 | AE9: =SUMIFS('Wells Fargo'!$F:$F,'Wells Fargo'!$G:$G,'Cash Flow'!$A9,'Wells Fargo'!$A:$A,AE$1,'Wells Fargo'!$B:$B,"<="&'Cash Flow'!AE$3,'Wells Fargo'!$B:$B,">"&'Cash Flow'!AD$3) -> 0 | AF9: =SUMIFS('Wells Fargo'!$F:$F,'Wells Fargo'!$G:$G,'Cash Flow'!$A9,'Wells Fargo'!$A:$A,AF$1,'Wells Fargo'!$B:$B,"<="&'Cash Flow'!AF$3) -> 0 | AG9: =SUMIFS('Wells Fargo'!$F:$F,'Wells Fargo'!$G:$G,'Cash Flow'!$A9,'Wells Fargo'!$A:$A,AG$1,'Wells Fargo'!$B:$B,"<="&'Cash Flow'!AG$3,'Wells Fargo'!$B:$B,">"&'Cash Flow'!AF$3) -> 0 | AH9: =SUMIFS('Wells Fargo'!$F:$F,'Wells Fargo'!$G:$G,'Cash Flow'!$A9,'Wells Fargo'!$A:$A,AH$1,'Wells Fargo'!$B:$B,"<="&'Cash Flow'!AH$3,'Wells Fargo'!$B:$B,">"&'Cash Flow'!AG$3) -> 0 | AI9: =SUMIFS('Wells Fargo'!$F:$F,'Wells Fargo'!$G:$G,'Cash Flow'!$A9,'Wells Fargo'!$A:$A,AI$1,'Wells Fargo'!$B:$B,"<="&'Cash Flow'!AI$3,'Wells Fargo'!$B:$B,">"&'Cash Flow'!AH$3) -> 0 | AJ9: =SUMIFS('Wells Fargo'!$F:$F,'Wells Fargo'!$G:$G,'Cash Flow'!$A9,'Wells Fargo'!$A:$A,AJ$1,'Wells Fargo'!$B:$B,"<="&'Cash Flow'!AJ$3,'Wells Fargo'!$B:$B,">"&'Cash Flow'!AI$3) -> 0 | AK9: =SUMIFS('Wells Fargo'!$F:$F,'Wells Fargo'!$G:$G,'Cash Flow'!$A9,'Wells Fargo'!$A:$A,AK$1,'Wells Fargo'!$B:$B,"<="&'Cash Flow'!AK$3) -> 0 | AL9: =SUMIFS('Wells Fargo'!$F:$F,'Wells Fargo'!$G:$G,'Cash Flow'!$A9,'Wells Fargo'!$A:$A,AL$1,'Wells Fargo'!$B:$B,"<="&'Cash Flow'!AL$3,'Wells Fargo'!$B:$B,">"&'Cash Flow'!AK$3) -> 0 | AM9: =SUMIFS('Wells Fargo'!$F:$F,'Wells Fargo'!$G:$G,'Cash Flow'!$A9,'Wells Fargo'!$A:$A,AM$1,'Wells Fargo'!$B:$B,"<="&'Cash Flow'!AM$3,'Wells Fargo'!$B:$B,">"&'Cash Flow'!AL$3) -> 0 | AN9: =SUMIFS('Wells Fargo'!$F:$F,'Wells Fargo'!$G:$G,'Cash Flow'!$A9,'Wells Fargo'!$A:$A,AN$1,'Wells Fargo'!$B:$B,"<="&'Cash Flow'!AN$3,'Wells Fargo'!$B:$B,">"&'Cash Flow'!AM$3) -> 0 | AO9: =SUMIFS('Wells Fargo'!$F:$F,'Wells Fargo'!$G:$G,'Cash Flow'!$A9,'Wells Fargo'!$A:$A,AO$1,'Wells Fargo'!$B:$B,"<="&'Cash Flow'!AO$3,'Wells Fargo'!$B:$B,">"&'Cash Flow'!AN$3) -> 0 | AP9: =SUMIFS('Wells Fargo'!$F:$F,'Wells Fargo'!$G:$G,'Cash Flow'!$A9,'Wells Fargo'!$A:$A,AP$1,'Wells Fargo'!$B:$B,"<="&'Cash Flow'!AP$3) -> 0 | AQ9: =SUMIFS('Wells Fargo'!$F:$F,'Wells Fargo'!$G:$G,'Cash Flow'!$A9,'Wells Fargo'!$A:$A,AQ$1,'Wells Fargo'!$B:$B,"<="&'Cash Flow'!AQ$3,'Wells Fargo'!$B:$B,">"&'Cash Flow'!AP$3) -> 0 | AR9: =SUMIFS('Wells Fargo'!$F:$F,'Wells Fargo'!$G:$G,'Cash Flow'!$A9,'Wells Fargo'!$A:$A,AR$1,'Wells Fargo'!$B:$B,"<="&'Cash Flow'!AR$3,'Wells Fargo'!$B:$B,">"&'Cash Flow'!AQ$3) -> 0 | AS9: =SUMIFS('Wells Fargo'!$F:$F,'Wells Fargo'!$G:$G,'Cash Flow'!$A9,'Wells Fargo'!$A:$A,AS$1,'Wells Fargo'!$B:$B,"<="&'Cash Flow'!AS$3,'Wells Fargo'!$B:$B,">"&'Cash Flow'!AR$3) -> 0 | AT9: =SUMIFS('Wells Fargo'!$F:$F,'Wells Fargo'!$G:$G,'Cash Flow'!$A9,'Wells Fargo'!$A:$A,AT$1,'Wells Fargo'!$B:$B,"<="&'Cash Flow'!AT$3,'Wells Fargo'!$B:$B,">"&'Cash Flow'!AS$3) -> 0 | AU9: =SUMIFS('Wells Fargo'!$F:$F,'Wells Fargo'!$G:$G,'Cash Flow'!$A9,'Wells Fargo'!$A:$A,AU$1,'Wells Fargo'!$B:$B,"<="&'Cash Flow'!AU$3) -> 0 | AV9: =SUMIFS('Wells Fargo'!$F:$F,'Wells Fargo'!$G:$G,'Cash Flow'!$A9,'Wells Fargo'!$A:$A,AV$1,'Wells Fargo'!$B:$B,"<="&'Cash Flow'!AV$3,'Wells Fargo'!$B:$B,">"&'Cash Flow'!AU$3) -> 0 | AW9: =SUMIFS('Wells Fargo'!$F:$F,'Wells Fargo'!$G:$G,'Cash Flow'!$A9,'Wells Fargo'!$A:$A,AW$1,'Wells Fargo'!$B:$B,"<="&'Cash Flow'!AW$3,'Wells Fargo'!$B:$B,">"&'Cash Flow'!AV$3) -> 0 | AX9: =SUMIFS('Wells Fargo'!$F:$F,'Wells Fargo'!$G:$G,'Cash Flow'!$A9,'Wells Fargo'!$A:$A,AX$1,'Wells Fargo'!$B:$B,"<="&'Cash Flow'!AX$3,'Wells Fargo'!$B:$B,">"&'Cash Flow'!AW$3) -> 0 | AY9: =SUMIFS('Wells Fargo'!$F:$F,'Wells Fargo'!$G:$G,'Cash Flow'!$A9,'Wells Fargo'!$A:$A,AY$1,'Wells Fargo'!$B:$B,"<="&'Cash Flow'!AY$3,'Wells Fargo'!$B:$B,">"&'Cash Flow'!AX$3) -> 0 | AZ9: =SUMIFS('Wells Fargo'!$F:$F,'Wells Fargo'!$G:$G,'Cash Flow'!$A9,'Wells Fargo'!$A:$A,AZ$1,'Wells Fargo'!$B:$B,"<="&'Cash Flow'!AZ$3) -> 0 | BA9: =SUMIFS('Wells Fargo'!$F:$F,'Wells Fargo'!$G:$G,'Cash Flow'!$A9,'Wells Fargo'!$A:$A,BA$1,'Wells Fargo'!$B:$B,"<="&'Cash Flow'!BA$3,'Wells Fargo'!$B:$B,">"&'Cash Flow'!AZ$3) -> 0 | BB9: =SUMIFS('Wells Fargo'!$F:$F,'Wells Fargo'!$G:$G,'Cash Flow'!$A9,'Wells Fargo'!$A:$A,BB$1,'Wells Fargo'!$B:$B,"<="&'Cash Flow'!BB$3,'Wells Fargo'!$B:$B,">"&'Cash Flow'!BA$3) -> 0 | BC9: =SUMIFS('Wells Fargo'!$F:$F,'Wells Fargo'!$G:$G,'Cash Flow'!$A9,'Wells Fargo'!$A:$A,BC$1,'Wells Fargo'!$B:$B,"<="&'Cash Flow'!BC$3,'Wells Fargo'!$B:$B,">"&'Cash Flow'!BB$3) -> 0 | BD9: =SUMIFS('Wells Fargo'!$F:$F,'Wells Fargo'!$G:$G,'Cash Flow'!$A9,'Wells Fargo'!$A:$A,BD$1,'Wells Fargo'!$B:$B,"<="&'Cash Flow'!BD$3,'Wells Fargo'!$B:$B,">"&'Cash Flow'!BC$3) -> 0 | BE9: =SUMIFS('Wells Fargo'!$F:$F,'Wells Fargo'!$G:$G,'Cash Flow'!$A9,'Wells Fargo'!$A:$A,BE$1,'Wells Fargo'!$B:$B,"<="&'Cash Flow'!BE$3) -> 0 | BF9: =SUMIFS('Wells Fargo'!$F:$F,'Wells Fargo'!$G:$G,'Cash Flow'!$A9,'Wells Fargo'!$A:$A,BF$1,'Wells Fargo'!$B:$B,"<="&'Cash Flow'!BF$3,'Wells Fargo'!$B:$B,">"&'Cash Flow'!BE$3) -> 0 | BG9: =SUMIFS('Wells Fargo'!$F:$F,'Wells Fargo'!$G:$G,'Cash Flow'!$A9,'Wells Fargo'!$A:$A,BG$1,'Wells Fargo'!$B:$B,"<="&'Cash Flow'!BG$3,'Wells Fargo'!$B:$B,">"&'Cash Flow'!BF$3) -> 0 | BH9: =SUMIFS('Wells Fargo'!$F:$F,'Wells Fargo'!$G:$G,'Cash Flow'!$A9,'Wells Fargo'!$A:$A,BH$1,'Wells Fargo'!$B:$B,"<="&'Cash Flow'!BH$3,'Wells Fargo'!$B:$B,">"&'Cash Flow'!BG$3) -> 0 | BI9: =SUMIFS('Wells Fargo'!$F:$F,'Wells Fargo'!$G:$G,'Cash Flow'!$A9,'Wells Fargo'!$A:$A,BI$1,'Wells Fargo'!$B:$B,"<="&'Cash Flow'!BI$3,'Wells Fargo'!$B:$B,">"&'Cash Flow'!BH$3) -> 0
A10: Anush Rohani Shukla | B10: =SUM(C10:BI10) -> -615 | C10: =SUMIFS('Wells Fargo'!$F:$F,'Wells Fargo'!$G:$G,'Cash Flow'!$A10,'Wells Fargo'!$A:$A,C$1,'Wells Fargo'!$B:$B,"<="&'Cash Flow'!C$3) -> 0 | D10: =SUMIFS('Wells Fargo'!$F:$F,'Wells Fargo'!$G:$G,'Cash Flow'!$A10,'Wells Fargo'!$A:$A,D$1,'Wells Fargo'!$B:$B,"<="&'Cash Flow'!D$3,'Wells Fargo'!$B:$B,">"&'Cash Flow'!C$3) -> 0 | E10: =SUMIFS('Wells Fargo'!$F:$F,'Wells Fargo'!$G:$G,'Cash Flow'!$A10,'Wells Fargo'!$A:$A,E$1,'Wells Fargo'!$B:$B,"<="&'Cash Flow'!E$3,'Wells Fargo'!$B:$B,">"&'Cash Flow'!D$3) -> 0 | F10: =SUMIFS('Wells Fargo'!$F:$F,'Wells Fargo'!$G:$G,'Cash Flow'!$A10,'Wells Fargo'!$A:$A,F$1,'Wells Fargo'!$B:$B,"<="&'Cash Flow'!F$3,'Wells Fargo'!$B:$B,">"&'Cash Flow'!E$3) -> 0 | G10: =SUMIFS('Wells Fargo'!$F:$F,'Wells Fargo'!$G:$G,'Cash Flow'!$A10,'Wells Fargo'!$A:$A,G$1,'Wells Fargo'!$B:$B,"<="&'Cash Flow'!G$3,'Wells Fargo'!$B:$B,">"&'Cash Flow'!F$3) -> 0 | H10: =SUMIFS('Wells Fargo'!$F:$F,'Wells Fargo'!$G:$G,'Cash Flow'!$A10,'Wells Fargo'!$A:$A,H$1,'Wells Fargo'!$B:$B,"<="&'Cash Flow'!H$3) -> 0 | I10: =SUMIFS('Wells Fargo'!$F:$F,'Wells Fargo'!$G:$G,'Cash Flow'!$A10,'Wells Fargo'!$A:$A,I$1,'Wells Fargo'!$B:$B,"<="&'Cash Flow'!I$3,'Wells Fargo'!$B:$B,">"&'Cash Flow'!H$3) -> 0 | J10: =SUMIFS('Wells Fargo'!$F:$F,'Wells Fargo'!$G:$G,'Cash Flow'!$A10,'Wells Fargo'!$A:$A,J$1,'Wells Fargo'!$B:$B,"<="&'Cash Flow'!J$3,'Wells Fargo'!$B:$B,">"&'Cash Flow'!I$3) -> 0 | K10: =SUMIFS('Wells Fargo'!$F:$F,'Wells Fargo'!$G:$G,'Cash Flow'!$A10,'Wells Fargo'!$A:$A,K$1,'Wells Fargo'!$B:$B,"<="&'Cash Flow'!K$3,'Wells Fargo'!$B:$B,">"&'Cash Flow'!J$3) -> 0 | L10: =SUMIFS('Wells Fargo'!$F:$F,'Wells Fargo'!$G:$G,'Cash Flow'!$A10,'Wells Fargo'!$A:$A,L$1,'Wells Fargo'!$B:$B,"<="&'Cash Flow'!L$3) -> 0 | M10: =SUMIFS('Wells Fargo'!$F:$F,'Wells Fargo'!$G:$G,'Cash Flow'!$A10,'Wells Fargo'!$A:$A,M$1,'Wells Fargo'!$B:$B,"<="&'Cash Flow'!M$3,'Wells Fargo'!$B:$B,">"&'Cash Flow'!L$3) -> 0 | N10: =SUMIFS('Wells Fargo'!$F:$F,'Wells Fargo'!$G:$G,'Cash Flow'!$A10,'Wells Fargo'!$A:$A,N$1,'Wells Fargo'!$B:$B,"<="&'Cash Flow'!N$3,'Wells Fargo'!$B:$B,">"&'Cash Flow'!M$3) -> 0 | O10: =SUMIFS('Wells Fargo'!$F:$F,'Wells Fargo'!$G:$G,'Cash Flow'!$A10,'Wells Fargo'!$A:$A,O$1,'Wells Fargo'!$B:$B,"<="&'Cash Flow'!O$3,'Wells Fargo'!$B:$B,">"&'Cash Flow'!N$3) -> 0 | P10: =SUMIFS('Wells Fargo'!$F:$F,'Wells Fargo'!$G:$G,'Cash Flow'!$A10,'Wells Fargo'!$A:$A,P$1,'Wells Fargo'!$B:$B,"<="&'Cash Flow'!P$3,'Wells Fargo'!$B:$B,">"&'Cash Flow'!O$3) -> 0 | Q10: =SUMIFS('Wells Fargo'!$F:$F,'Wells Fargo'!$G:$G,'Cash Flow'!$A10,'Wells Fargo'!$A:$A,Q$1,'Wells Fargo'!$B:$B,"<="&'Cash Flow'!Q$3) -> 0 | R10: =SUMIFS('Wells Fargo'!$F:$F,'Wells Fargo'!$G:$G,'Cash Flow'!$A10,'Wells Fargo'!$A:$A,R$1,'Wells Fargo'!$B:$B,"<="&'Cash Flow'!R$3,'Wells Fargo'!$B:$B,">"&'Cash Flow'!Q$3) -> 0 | S10: =SUMIFS('Wells Fargo'!$F:$F,'Wells Fargo'!$G:$G,'Cash Flow'!$A10,'Wells Fargo'!$A:$A,S$1,'Wells Fargo'!$B:$B,"<="&'Cash Flow'!S$3,'Wells Fargo'!$B:$B,">"&'Cash Flow'!R$3) -> 0 | T10: =SUMIFS('Wells Fargo'!$F:$F,'Wells Fargo'!$G:$G,'Cash Flow'!$A10,'Wells Fargo'!$A:$A,T$1,'Wells Fargo'!$B:$B,"<="&'Cash Flow'!T$3,'Wells Fargo'!$B:$B,">"&'Cash Flow'!S$3) -> 0 | U10: =SUMIFS('Wells Fargo'!$F:$F,'Wells Fargo'!$G:$G,'Cash Flow'!$A10,'Wells Fargo'!$A:$A,U$1,'Wells Fargo'!$B:$B,"<="&'Cash Flow'!U$3,'Wells Fargo'!$B:$B,">"&'Cash Flow'!T$3) -> 0 | V10: =SUMIFS('Wells Fargo'!$F:$F,'Wells Fargo'!$G:$G,'Cash Flow'!$A10,'Wells Fargo'!$A:$A,V$1,'Wells Fargo'!$B:$B,"<="&'Cash Flow'!V$3) -> 0 | W10: =SUMIFS('Wells Fargo'!$F:$F,'Wells Fargo'!$G:$G,'Cash Flow'!$A10,'Wells Fargo'!$A:$A,W$1,'Wells Fargo'!$B:$B,"<="&'Cash Flow'!W$3,'Wells Fargo'!$B:$B,">"&'Cash Flow'!V$3) -> 0 | X10: =SUMIFS('Wells Fargo'!$F:$F,'Wells Fargo'!$G:$G,'Cash Flow'!$A10,'Wells Fargo'!$A:$A,X$1,'Wells Fargo'!$B:$B,"<="&'Cash Flow'!X$3,'Wells Fargo'!$B:$B,">"&'Cash Flow'!W$3) -> 0 | Y10: =SUMIFS('Wells Fargo'!$F:$F,'Wells Fargo'!$G:$G,'Cash Flow'!$A10,'Wells Fargo'!$A:$A,Y$1,'Wells Fargo'!$B:$B,"<="&'Cash Flow'!Y$3,'Wells Fargo'!$B:$B,">"&'Cash Flow'!X$3) -> 0 | Z10: =SUMIFS('Wells Fargo'!$F:$F,'Wells Fargo'!$G:$G,'Cash Flow'!$A10,'Wells Fargo'!$A:$A,Z$1,'Wells Fargo'!$B:$B,"<="&'Cash Flow'!Z$3,'Wells Fargo'!$B:$B,">"&'Cash Flow'!Y$3) -> 0 | AA10: =SUMIFS('Wells Fargo'!$F:$F,'Wells Fargo'!$G:$G,'Cash Flow'!$A10,'Wells Fargo'!$A:$A,AA$1,'Wells Fargo'!$B:$B,"<="&'Cash Flow'!AA$3) -> 0 | AB10: =SUMIFS('Wells Fargo'!$F:$F,'Wells Fargo'!$G:$G,'Cash Flow'!$A10,'Wells Fargo'!$A:$A,AB$1,'Wells Fargo'!$B:$B,"<="&'Cash Flow'!AB$3,'Wells Fargo'!$B:$B,">"&'Cash Flow'!AA$3) -> 0 | AC10: =SUMIFS('Wells Fargo'!$F:$F,'Wells Fargo'!$G:$G,'Cash Flow'!$A10,'Wells Fargo'!$A:$A,AC$1,'Wells Fargo'!$B:$B,"<="&'Cash Flow'!AC$3,'Wells Fargo'!$B:$B,">"&'Cash Flow'!AB$3) -> 0 | AD10: =SUMIFS('Wells Fargo'!$F:$F,'Wells Fargo'!$G:$G,'Cash Flow'!$A10,'Wells Fargo'!$A:$A,AD$1,'Wells Fargo'!$B:$B,"<="&'Cash Flow'!AD$3,'Wells Fargo'!$B:$B,">"&'Cash Flow'!AC$3) -> -615 | AE10: =SUMIFS('Wells Fargo'!$F:$F,'Wells Fargo'!$G:$G,'Cash Flow'!$A10,'Wells Fargo'!$A:$A,AE$1,'Wells Fargo'!$B:$B,"<="&'Cash Flow'!AE$3,'Wells Fargo'!$B:$B,">"&'Cash Flow'!AD$3) -> 0 | AF10: =SUMIFS('Wells Fargo'!$F:$F,'Wells Fargo'!$G:$G,'Cash Flow'!$A10,'Wells Fargo'!$A:$A,AF$1,'Wells Fargo'!$B:$B,"<="&'Cash Flow'!AF$3) -> 0 | AG10: =SUMIFS('Wells Fargo'!$F:$F,'Wells Fargo'!$G:$G,'Cash Flow'!$A10,'Wells Fargo'!$A:$A,AG$1,'Wells Fargo'!$B:$B,"<="&'Cash Flow'!AG$3,'Wells Fargo'!$B:$B,">"&'Cash Flow'!AF$3) -> 0 | AH10: =SUMIFS('Wells Fargo'!$F:$F,'Wells Fargo'!$G:$G,'Cash Flow'!$A10,'Wells Fargo'!$A:$A,AH$1,'Wells Fargo'!$B:$B,"<="&'Cash Flow'!AH$3,'Wells Fargo'!$B:$B,">"&'Cash Flow'!AG$3) -> 0 | AI10: =SUMIFS('Wells Fargo'!$F:$F,'Wells Fargo'!$G:$G,'Cash Flow'!$A10,'Wells Fargo'!$A:$A,AI$1,'Wells Fargo'!$B:$B,"<="&'Cash Flow'!AI$3,'Wells Fargo'!$B:$B,">"&'Cash Flow'!AH$3) -> 0 | AJ10: =SUMIFS('Wells Fargo'!$F:$F,'Wells Fargo'!$G:$G,'Cash Flow'!$A10,'Wells Fargo'!$A:$A,AJ$1,'Wells Fargo'!$B:$B,"<="&'Cash Flow'!AJ$3,'Wells Fargo'!$B:$B,">"&'Cash Flow'!AI$3) -> 0 | AK10: =SUMIFS('Wells Fargo'!$F:$F,'Wells Fargo'!$G:$G,'Cash Flow'!$A10,'Wells Fargo'!$A:$A,AK$1,'Wells Fargo'!$B:$B,"<="&'Cash Flow'!AK$3) -> 0 | AL10: =SUMIFS('Wells Fargo'!$F:$F,'Wells Fargo'!$G:$G,'Cash Flow'!$A10,'Wells Fargo'!$A:$A,AL$1,'Wells Fargo'!$B:$B,"<="&'Cash Flow'!AL$3,'Wells Fargo'!$B:$B,">"&'Cash Flow'!AK$3) -> 0 | AM10: =SUMIFS('Wells Fargo'!$F:$F,'Wells Fargo'!$G:$G,'Cash Flow'!$A10,'Wells Fargo'!$A:$A,AM$1,'Wells Fargo'!$B:$B,"<="&'Cash Flow'!AM$3,'Wells Fargo'!$B:$B,">"&'Cash Flow'!AL$3) -> 0 | AN10: =SUMIFS('Wells Fargo'!$F:$F,'Wells Fargo'!$G:$G,'Cash Flow'!$A10,'Wells Fargo'!$A:$A,AN$1,'Wells Fargo'!$B:$B,"<="&'Cash Flow'!AN$3,'Wells Fargo'!$B:$B,">"&'Cash Flow'!AM$3) -> 0 | AO10: =SUMIFS('Wells Fargo'!$F:$F,'Wells Fargo'!$G:$G,'Cash Flow'!$A10,'Wells Fargo'!$A:$A,AO$1,'Wells Fargo'!$B:$B,"<="&'Cash Flow'!AO$3,'Wells Fargo'!$B:$B,">"&'Cash Flow'!AN$3) -> 0 | AP10: =SUMIFS('Wells Fargo'!$F:$F,'Wells Fargo'!$G:$G,'Cash Flow'!$A10,'Wells Fargo'!$A:$A,AP$1,'Wells Fargo'!$B:$B,"<="&'Cash Flow'!AP$3) -> 0 | AQ10: =SUMIFS('Wells Fargo'!$F:$F,'Wells Fargo'!$G:$G,'Cash Flow'!$A10,'Wells Fargo'!$A:$A,AQ$1,'Wells Fargo'!$B:$B,"<="&'Cash Flow'!AQ$3,'Wells Fargo'!$B:$B,">"&'Cash Flow'!AP$3) -> 0 | AR10: =SUMIFS('Wells Fargo'!$F:$F,'Wells Fargo'!$G:$G,'Cash Flow'!$A10,'Wells Fargo'!$A:$A,AR$1,'Wells Fargo'!$B:$B,"<="&'Cash Flow'!AR$3,'Wells Fargo'!$B:$B,">"&'Cash Flow'!AQ$3) -> 0 | AS10: =SUMIFS('Wells Fargo'!$F:$F,'Wells Fargo'!$G:$G,'Cash Flow'!$A10,'Wells Fargo'!$A:$A,AS$1,'Wells Fargo'!$B:$B,"<="&'Cash Flow'!AS$3,'Wells Fargo'!$B:$B,">"&'Cash Flow'!AR$3) -> 0 | AT10: =SUMIFS('Wells Fargo'!$F:$F,'Wells Fargo'!$G:$G,'Cash Flow'!$A10,'Wells Fargo'!$A:$A,AT$1,'Wells Fargo'!$B:$B,"<="&'Cash Flow'!AT$3,'Wells Fargo'!$B:$B,">"&'Cash Flow'!AS$3) -> 0 | AU10: =SUMIFS('Wells Fargo'!$F:$F,'Wells Fargo'!$G:$G,'Cash Flow'!$A10,'Wells Fargo'!$A:$A,AU$1,'Wells Fargo'!$B:$B,"<="&'Cash Flow'!AU$3) -> 0 | AV10: =SUMIFS('Wells Fargo'!$F:$F,'Wells Fargo'!$G:$G,'Cash Flow'!$A10,'Wells Fargo'!$A:$A,AV$1,'Wells Fargo'!$B:$B,"<="&'Cash Flow'!AV$3,'Wells Fargo'!$B:$B,">"&'Cash Flow'!AU$3) -> 0 | AW10: =SUMIFS('Wells Fargo'!$F:$F,'Wells Fargo'!$G:$G,'Cash Flow'!$A10,'Wells Fargo'!$A:$A,AW$1,'Wells Fargo'!$B:$B,"<="&'Cash Flow'!AW$3,'Wells Fargo'!$B:$B,">"&'Cash Flow'!AV$3) -> 0 | AX10: =SUMIFS('Wells Fargo'!$F:$F,'Wells Fargo'!$G:$G,'Cash Flow'!$A10,'Wells Fargo'!$A:$A,AX$1,'Wells Fargo'!$B:$B,"<="&'Cash Flow'!AX$3,'Wells Fargo'!$B:$B,">"&'Cash Flow'!AW$3) -> 0 | AY10: =SUMIFS('Wells Fargo'!$F:$F,'Wells Fargo'!$G:$G,'Cash Flow'!$A10,'Wells Fargo'!$A:$A,AY$1,'Wells Fargo'!$B:$B,"<="&'Cash Flow'!AY$3,'Wells Fargo'!$B:$B,">"&'Cash Flow'!AX$3) -> 0 | AZ10: =SUMIFS('Wells Fargo'!$F:$F,'Wells Fargo'!$G:$G,'Cash Flow'!$A10,'Wells Fargo'!$A:$A,AZ$1,'Wells Fargo'!$B:$B,"<="&'Cash Flow'!AZ$3) -> 0 | BA10: =SUMIFS('Wells Fargo'!$F:$F,'Wells Fargo'!$G:$G,'Cash Flow'!$A10,'Wells Fargo'!$A:$A,BA$1,'Wells Fargo'!$B:$B,"<="&'Cash Flow'!BA$3,'Wells Fargo'!$B:$B,">"&'Cash Flow'!AZ$3) -> 0 | BB10: =SUMIFS('Wells Fargo'!$F:$F,'Wells Fargo'!$G:$G,'Cash Flow'!$A10,'Wells Fargo'!$A:$A,BB$1,'Wells Fargo'!$B:$B,"<="&'Cash Flow'!BB$3,'Wells Fargo'!$B:$B,">"&'Cash Flow'!BA$3) -> 0 | BC10: =SUMIFS('Wells Fargo'!$F:$F,'Wells Fargo'!$G:$G,'Cash Flow'!$A10,'Wells Fargo'!$A:$A,BC$1,'Wells Fargo'!$B:$B,"<="&'Cash Flow'!BC$3,'Wells Fargo'!$B:$B,">"&'Cash Flow'!BB$3) -> 0 | BD10: =SUMIFS('Wells Fargo'!$F:$F,'Wells Fargo'!$G:$G,'Cash Flow'!$A10,'Wells Fargo'!$A:$A,BD$1,'Wells Fargo'!$B:$B,"<="&'Cash Flow'!BD$3,'Wells Fargo'!$B:$B,">"&'Cash Flow'!BC$3) -> 0 | BE10: =SUMIFS('Wells Fargo'!$F:$F,'Wells Fargo'!$G:$G,'Cash Flow'!$A10,'Wells Fargo'!$A:$A,BE$1,'Wells Fargo'!$B:$B,"<="&'Cash Flow'!BE$3) -> 0 | BF10: =SUMIFS('Wells Fargo'!$F:$F,'Wells Fargo'!$G:$G,'Cash Flow'!$A10,'Wells Fargo'!$A:$A,BF$1,'Wells Fargo'!$B:$B,"<="&'Cash Flow'!BF$3,'Wells Fargo'!$B:$B,">"&'Cash Flow'!BE$3) -> 0 | BG10: =SUMIFS('Wells Fargo'!$F:$F,'Wells Fargo'!$G:$G,'Cash Flow'!$A10,'Wells Fargo'!$A:$A,BG$1,'Wells Fargo'!$B:$B,"<="&'Cash Flow'!BG$3,'Wells Fargo'!$B:$B,">"&'Cash Flow'!BF$3) -> 0 | BH10: =SUMIFS('Wells Fargo'!$F:$F,'Wells Fargo'!$G:$G,'Cash Flow'!$A10,'Wells Fargo'!$A:$A,BH$1,'Wells Fargo'!$B:$B,"<="&'Cash Flow'!BH$3,'Wells Fargo'!$B:$B,">"&'Cash Flow'!BG$3) -> 0 | BI10: =SUMIFS('Wells Fargo'!$F:$F,'Wells Fargo'!$G:$G,'Cash Flow'!$A10,'Wells Fargo'!$A:$A,BI$1,'Wells Fargo'!$B:$B,"<="&'Cash Flow'!BI$3,'Wells Fargo'!$B:$B,">"&'Cash Flow'!BH$3) -> 0
A11: APS | B11: =SUM(C11:BI11) -> -181.04 | C11: =SUMIFS('Wells Fargo'!$F:$F,'Wells Fargo'!$G:$G,'Cash Flow'!$A11,'Wells Fargo'!$A:$A,C$1,'Wells Fargo'!$B:$B,"<="&'Cash Flow'!C$3) -> 0 | D11: =SUMIFS('Wells Fargo'!$F:$F,'Wells Fargo'!$G:$G,'Cash Flow'!$A11,'Wells Fargo'!$A:$A,D$1,'Wells Fargo'!$B:$B,"<="&'Cash Flow'!D$3,'Wells Fargo'!$B:$B,">"&'Cash Flow'!C$3) -> 0 | E11: =SUMIFS('Wells Fargo'!$F:$F,'Wells Fargo'!$G:$G,'Cash Flow'!$A11,'Wells Fargo'!$A:$A,E$1,'Wells Fargo'!$B:$B,"<="&'Cash Flow'!E$3,'Wells Fargo'!$B:$B,">"&'Cash Flow'!D$3) -> 0 | F11: =SUMIFS('Wells Fargo'!$F:$F,'Wells Fargo'!$G:$G,'Cash Flow'!$A11,'Wells Fargo'!$A:$A,F$1,'Wells Fargo'!$B:$B,"<="&'Cash Flow'!F$3,'Wells Fargo'!$B:$B,">"&'Cash Flow'!E$3) -> 0 | G11: =SUMIFS('Wells Fargo'!$F:$F,'Wells Fargo'!$G:$G,'Cash Flow'!$A11,'Wells Fargo'!$A:$A,G$1,'Wells Fargo'!$B:$B,"<="&'Cash Flow'!G$3,'Wells Fargo'!$B:$B,">"&'Cash Flow'!F$3) -> 0 | H11: =SUMIFS('Wells Fargo'!$F:$F,'Wells Fargo'!$G:$G,'Cash Flow'!$A11,'Wells Fargo'!$A:$A,H$1,'Wells Fargo'!$B:$B,"<="&'Cash Flow'!H$3) -> 0 | I11: =SUMIFS('Wells Fargo'!$F:$F,'Wells Fargo'!$G:$G,'Cash Flow'!$A11,'Wells Fargo'!$A:$A,I$1,'Wells Fargo'!$B:$B,"<="&'Cash Flow'!I$3,'Wells Fargo'!$B:$B,">"&'Cash Flow'!H$3) -> 0 | J11: =SUMIFS('Wells Fargo'!$F:$F,'Wells Fargo'!$G:$G,'Cash Flow'!$A11,'Wells Fargo'!$A:$A,J$1,'Wells Fargo'!$B:$B,"<="&'Cash Flow'!J$3,'Wells Fargo'!$B:$B,">"&'Cash Flow'!I$3) -> 0 | K11: =SUMIFS('Wells Fargo'!$F:$F,'Wells Fargo'!$G:$G,'Cash Flow'!$A11,'Wells Fargo'!$A:$A,K$1,'Wells Fargo'!$B:$B,"<="&'Cash Flow'!K$3,'Wells Fargo'!$B:$B,">"&'Cash Flow'!J$3) -> 0 | L11: =SUMIFS('Wells Fargo'!$F:$F,'Wells Fargo'!$G:$G,'Cash Flow'!$A11,'Wells Fargo'!$A:$A,L$1,'Wells Fargo'!$B:$B,"<="&'Cash Flow'!L$3) -> 0 | M11: =SUMIFS('Wells Fargo'!$F:$F,'Wells Fargo'!$G:$G,'Cash Flow'!$A11,'Wells Fargo'!$A:$A,M$1,'Wells Fargo'!$B:$B,"<="&'Cash Flow'!M$3,'Wells Fargo'!$B:$B,">"&'Cash Flow'!L$3) -> 0 | N11: =SUMIFS('Wells Fargo'!$F:$F,'Wells Fargo'!$G:$G,'Cash Flow'!$A11,'Wells Fargo'!$A:$A,N$1,'Wells Fargo'!$B:$B,"<="&'Cash Flow'!N$3,'Wells Fargo'!$B:$B,">"&'Cash Flow'!M$3) -> 0 | O11: =SUMIFS('Wells Fargo'!$F:$F,'Wells Fargo'!$G:$G,'Cash Flow'!$A11,'Wells Fargo'!$A:$A,O$1,'Wells Fargo'!$B:$B,"<="&'Cash Flow'!O$3,'Wells Fargo'!$B:$B,">"&'Cash Flow'!N$3) -> 0 | P11: =SUMIFS('Wells Fargo'!$F:$F,'Wells Fargo'!$G:$G,'Cash Flow'!$A11,'Wells Fargo'!$A:$A,P$1,'Wells Fargo'!$B:$B,"<="&'Cash Flow'!P$3,'Wells Fargo'!$B:$B,">"&'Cash Flow'!O$3) -> 0 | Q11: =SUMIFS('Wells Fargo'!$F:$F,'Wells Fargo'!$G:$G,'Cash Flow'!$A11,'Wells Fargo'!$A:$A,Q$1,'Wells Fargo'!$B:$B,"<="&'Cash Flow'!Q$3) -> 0 | R11: =SUMIFS('Wells Fargo'!$F:$F,'Wells Fargo'!$G:$G,'Cash Flow'!$A11,'Wells Fargo'!$A:$A,R$1,'Wells Fargo'!$B:$B,"<="&'Cash Flow'!R$3,'Wells Fargo'!$B:$B,">"&'Cash Flow'!Q$3) -> 0 | S11: =SUMIFS('Wells Fargo'!$F:$F,'Wells Fargo'!$G:$G,'Cash Flow'!$A11,'Wells Fargo'!$A:$A,S$1,'Wells Fargo'!$B:$B,"<="&'Cash Flow'!S$3,'Wells Fargo'!$B:$B,">"&'Cash Flow'!R$3) -> 0 | T11: =SUMIFS('Wells Fargo'!$F:$F,'Wells Fargo'!$G:$G,'Cash Flow'!$A11,'Wells Fargo'!$A:$A,T$1,'Wells Fargo'!$B:$B,"<="&'Cash Flow'!T$3,'Wells Fargo'!$B:$B,">"&'Cash Flow'!S$3) -> 0 | U11: =SUMIFS('Wells Fargo'!$F:$F,'Wells Fargo'!$G:$G,'Cash Flow'!$A11,'Wells Fargo'!$A:$A,U$1,'Wells Fargo'!$B:$B,"<="&'Cash Flow'!U$3,'Wells Fargo'!$B:$B,">"&'Cash Flow'!T$3) -> 0 | V11: =SUMIFS('Wells Fargo'!$F:$F,'Wells Fargo'!$G:$G,'Cash Flow'!$A11,'Wells Fargo'!$A:$A,V$1,'Wells Fargo'!$B:$B,"<="&'Cash Flow'!V$3) -> 0 | W11: =SUMIFS('Wells Fargo'!$F:$F,'Wells Fargo'!$G:$G,'Cash Flow'!$A11,'Wells Fargo'!$A:$A,W$1,'Wells Fargo'!$B:$B,"<="&'Cash Flow'!W$3,'Wells Fargo'!$B:$B,">"&'Cash Flow'!V$3) -> 0 | X11: =SUMIFS('Wells Fargo'!$F:$F,'Wells Fargo'!$G:$G,'Cash Flow'!$A11,'Wells Fargo'!$A:$A,X$1,'Wells Fargo'!$B:$B,"<="&'Cash Flow'!X$3,'Wells Fargo'!$B:$B,">"&'Cash Flow'!W$3) -> 0 | Y11: =SUMIFS('Wells Fargo'!$F:$F,'Wells Fargo'!$G:$G,'Cash Flow'!$A11,'Wells Fargo'!$A:$A,Y$1,'Wells Fargo'!$B:$B,"<="&'Cash Flow'!Y$3,'Wells Fargo'!$B:$B,">"&'Cash Flow'!X$3) -> 0 | Z11: =SUMIFS('Wells Fargo'!$F:$F,'Wells Fargo'!$G:$G,'Cash Flow'!$A11,'Wells Fargo'!$A:$A,Z$1,'Wells Fargo'!$B:$B,"<="&'Cash Flow'!Z$3,'Wells Fargo'!$B:$B,">"&'Cash Flow'!Y$3) -> 0 | AA11: =SUMIFS('Wells Fargo'!$F:$F,'Wells Fargo'!$G:$G,'Cash Flow'!$A11,'Wells Fargo'!$A:$A,AA$1,'Wells Fargo'!$B:$B,"<="&'Cash Flow'!AA$3) -> 0 | AB11: =SUMIFS('Wells Fargo'!$F:$F,'Wells Fargo'!$G:$G,'Cash Flow'!$A11,'Wells Fargo'!$A:$A,AB$1,'Wells Fargo'!$B:$B,"<="&'Cash Flow'!AB$3,'Wells Fargo'!$B:$B,">"&'Cash Flow'!AA$3) -> 0 | AC11: =SUMIFS('Wells Fargo'!$F:$F,'Wells Fargo'!$G:$G,'Cash Flow'!$A11,'Wells Fargo'!$A:$A,AC$1,'Wells Fargo'!$B:$B,"<="&'Cash Flow'!AC$3,'Wells Fargo'!$B:$B,">"&'Cash Flow'!AB$3) -> 0 | AD11: =SUMIFS('Wells Fargo'!$F:$F,'Wells Fargo'!$G:$G,'Cash Flow'!$A11,'Wells Fargo'!$A:$A,AD$1,'Wells Fargo'!$B:$B,"<="&'Cash Flow'!AD$3,'Wells Fargo'!$B:$B,">"&'Cash Flow'!AC$3) -> 0 | AE11: =SUMIFS('Wells Fargo'!$F:$F,'Wells Fargo'!$G:$G,'Cash Flow'!$A11,'Wells Fargo'!$A:$A,AE$1,'Wells Fargo'!$B:$B,"<="&'Cash Flow'!AE$3,'Wells Fargo'!$B:$B,">"&'Cash Flow'!AD$3) -> 0 | AF11: =SUMIFS('Wells Fargo'!$F:$F,'Wells Fargo'!$G:$G,'Cash Flow'!$A11,'Wells Fargo'!$A:$A,AF$1,'Wells Fargo'!$B:$B,"<="&'Cash Flow'!AF$3) -> 0 | AG11: =SUMIFS('Wells Fargo'!$F:$F,'Wells Fargo'!$G:$G,'Cash Flow'!$A11,'Wells Fargo'!$A:$A,AG$1,'Wells Fargo'!$B:$B,"<="&'Cash Flow'!AG$3,'Wells Fargo'!$B:$B,">"&'Cash Flow'!AF$3) -> 0 | AH11: =SUMIFS('Wells Fargo'!$F:$F,'Wells Fargo'!$G:$G,'Cash Flow'!$A11,'Wells Fargo'!$A:$A,AH$1,'Wells Fargo'!$B:$B,"<="&'Cash Flow'!AH$3,'Wells Fargo'!$B:$B,">"&'Cash Flow'!AG$3) -> 0 | AI11: =SUMIFS('Wells Fargo'!$F:$F,'Wells Fargo'!$G:$G,'Cash Flow'!$A11,'Wells Fargo'!$A:$A,AI$1,'Wells Fargo'!$B:$B,"<="&'Cash Flow'!AI$3,'Wells Fargo'!$B:$B,">"&'Cash Flow'!AH$3) -> 0 | AJ11: =SUMIFS('Wells Fargo'!$F:$F,'Wells Fargo'!$G:$G,'Cash Flow'!$A11,'Wells Fargo'!$A:$A,AJ$1,'Wells Fargo'!$B:$B,"<="&'Cash Flow'!AJ$3,'Wells Fargo'!$B:$B,">"&'Cash Flow'!AI$3) -> 0 | AK11: =SUMIFS('Wells Fargo'!$F:$F,'Wells Fargo'!$G:$G,'Cash Flow'!$A11,'Wells Fargo'!$A:$A,AK$1,'Wells Fargo'!$B:$B,"<="&'Cash Flow'!AK$3) -> 0 | AL11: =SUMIFS('Wells Fargo'!$F:$F,'Wells Fargo'!$G:$G,'Cash Flow'!$A11,'Wells Fargo'!$A:$A,AL$1,'Wells Fargo'!$B:$B,"<="&'Cash Flow'!AL$3,'Wells Fargo'!$B:$B,">"&'Cash Flow'!AK$3) -> 0 | AM11: =SUMIFS('Wells Fargo'!$F:$F,'Wells Fargo'!$G:$G,'Cash Flow'!$A11,'Wells Fargo'!$A:$A,AM$1,'Wells Fargo'!$B:$B,"<="&'Cash Flow'!AM$3,'Wells Fargo'!$B:$B,">"&'Cash Flow'!AL$3) -> 0 | AN11: =SUMIFS('Wells Fargo'!$F:$F,'Wells Fargo'!$G:$G,'Cash Flow'!$A11,'Wells Fargo'!$A:$A,AN$1,'Wells Fargo'!$B:$B,"<="&'Cash Flow'!AN$3,'Wells Fargo'!$B:$B,">"&'Cash Flow'!AM$3) -> 0 | AO11: =SUMIFS('Wells Fargo'!$F:$F,'Wells Fargo'!$G:$G,'Cash Flow'!$A11,'Wells Fargo'!$A:$A,AO$1,'Wells Fargo'!$B:$B,"<="&'Cash Flow'!AO$3,'Wells Fargo'!$B:$B,">"&'Cash Flow'!AN$3) -> 0 | AP11: =SUMIFS('Wells Fargo'!$F:$F,'Wells Fargo'!$G:$G,'Cash Flow'!$A11,'Wells Fargo'!$A:$A,AP$1,'Wells Fargo'!$B:$B,"<="&'Cash Flow'!AP$3) -> 0 | AQ11: =SUMIFS('Wells Fargo'!$F:$F,'Wells Fargo'!$G:$G,'Cash Flow'!$A11,'Wells Fargo'!$A:$A,AQ$1,'Wells Fargo'!$B:$B,"<="&'Cash Flow'!AQ$3,'Wells Fargo'!$B:$B,">"&'Cash Flow'!AP$3) -> 0 | AR11: =SUMIFS('Wells Fargo'!$F:$F,'Wells Fargo'!$G:$G,'Cash Flow'!$A11,'Wells Fargo'!$A:$A,AR$1,'Wells Fargo'!$B:$B,"<="&'Cash Flow'!AR$3,'Wells Fargo'!$B:$B,">"&'Cash Flow'!AQ$3) -> 0 | AS11: =SUMIFS('Wells Fargo'!$F:$F,'Wells Fargo'!$G:$G,'Cash Flow'!$A11,'Wells Fargo'!$A:$A,AS$1,'Wells Fargo'!$B:$B,"<="&'Cash Flow'!AS$3,'Wells Fargo'!$B:$B,">"&'Cash Flow'!AR$3) -> 0 | AT11: =SUMIFS('Wells Fargo'!$F:$F,'Wells Fargo'!$G:$G,'Cash Flow'!$A11,'Wells Fargo'!$A:$A,AT$1,'Wells Fargo'!$B:$B,"<="&'Cash Flow'!AT$3,'Wells Fargo'!$B:$B,">"&'Cash Flow'!AS$3) -> 0 | AU11: =SUMIFS('Wells Fargo'!$F:$F,'Wells Fargo'!$G:$G,'Cash Flow'!$A11,'Wells Fargo'!$A:$A,AU$1,'Wells Fargo'!$B:$B,"<="&'Cash Flow'!AU$3) -> 0 | AV11: =SUMIFS('Wells Fargo'!$F:$F,'Wells Fargo'!$G:$G,'Cash Flow'!$A11,'Wells Fargo'!$A:$A,AV$1,'Wells Fargo'!$B:$B,"<="&'Cash Flow'!AV$3,'Wells Fargo'!$B:$B,">"&'Cash Flow'!AU$3) -> 0 | AW11: =SUMIFS('Wells Fargo'!$F:$F,'Wells Fargo'!$G:$G,'Cash Flow'!$A11,'Wells Fargo'!$A:$A,AW$1,'Wells Fargo'!$B:$B,"<="&'Cash Flow'!AW$3,'Wells Fargo'!$B:$B,">"&'Cash Flow'!AV$3) -> -14.71 | AX11: =SUMIFS('Wells Fargo'!$F:$F,'Wells Fargo'!$G:$G,'Cash Flow'!$A11,'Wells Fargo'!$A:$A,AX$1,'Wells Fargo'!$B:$B,"<="&'Cash Flow'!AX$3,'Wells Fargo'!$B:$B,">"&'Cash Flow'!AW$3) -> 0 | AY11: =SUMIFS('Wells Fargo'!$F:$F,'Wells Fargo'!$G:$G,'Cash Flow'!$A11,'Wells Fargo'!$A:$A,AY$1,'Wells Fargo'!$B:$B,"<="&'Cash Flow'!AY$3,'Wells Fargo'!$B:$B,">"&'Cash Flow'!AX$3) -> 0 | AZ11: =SUMIFS('Wells Fargo'!$F:$F,'Wells Fargo'!$G:$G,'Cash Flow'!$A11,'Wells Fargo'!$A:$A,AZ$1,'Wells Fargo'!$B:$B,"<="&'Cash Flow'!AZ$3) -> -166.33 | BA11: =SUMIFS('Wells Fargo'!$F:$F,'Wells Fargo'!$G:$G,'Cash Flow'!$A11,'Wells Fargo'!$A:$A,BA$1,'Wells Fargo'!$B:$B,"<="&'Cash Flow'!BA$3,'Wells Fargo'!$B:$B,">"&'Cash Flow'!AZ$3) -> 0 | BB11: =SUMIFS('Wells Fargo'!$F:$F,'Wells Fargo'!$G:$G,'Cash Flow'!$A11,'Wells Fargo'!$A:$A,BB$1,'Wells Fargo'!$B:$B,"<="&'Cash Flow'!BB$3,'Wells Fargo'!$B:$B,">"&'Cash Flow'!BA$3) -> 0 | BC11: =SUMIFS('Wells Fargo'!$F:$F,'Wells Fargo'!$G:$G,'Cash Flow'!$A11,'Wells Fargo'!$A:$A,BC$1,'Wells Fargo'!$B:$B,"<="&'Cash Flow'!BC$3,'Wells Fargo'!$B:$B,">"&'Cash Flow'!BB$3) -> 0 | BD11: =SUMIFS('Wells Fargo'!$F:$F,'Wells Fargo'!$G:$G,'Cash Flow'!$A11,'Wells Fargo'!$A:$A,BD$1,'Wells Fargo'!$B:$B,"<="&'Cash Flow'!BD$3,'Wells Fargo'!$B:$B,">"&'Cash Flow'!BC$3) -> 0 | BE11: =SUMIFS('Wells Fargo'!$F:$F,'Wells Fargo'!$G:$G,'Cash Flow'!$A11,'Wells Fargo'!$A:$A,BE$1,'Wells Fargo'!$B:$B,"<="&'Cash Flow'!BE$3) -> 0 | BF11: =SUMIFS('Wells Fargo'!$F:$F,'Wells Fargo'!$G:$G,'Cash Flow'!$A11,'Wells Fargo'!$A:$A,BF$1,'Wells Fargo'!$B:$B,"<="&'Cash Flow'!BF$3,'Wells Fargo'!$B:$B,">"&'Cash Flow'!BE$3) -> 0 | BG11: =SUMIFS('Wells Fargo'!$F:$F,'Wells Fargo'!$G:$G,'Cash Flow'!$A11,'Wells Fargo'!$A:$A,BG$1,'Wells Fargo'!$B:$B,"<="&'Cash Flow'!BG$3,'Wells Fargo'!$B:$B,">"&'Cash Flow'!BF$3) -> 0 | BH11: =SUMIFS('Wells Fargo'!$F:$F,'Wells Fargo'!$G:$G,'Cash Flow'!$A11,'Wells Fargo'!$A:$A,BH$1,'Wells Fargo'!$B:$B,"<="&'Cash Flow'!BH$3,'Wells Fargo'!$B:$B,">"&'Cash Flow'!BG$3) -> 0 | BI11: =SUMIFS('Wells Fargo'!$F:$F,'Wells Fargo'!$G:$G,'Cash Flow'!$A11,'Wells Fargo'!$A:$A,BI$1,'Wells Fargo'!$B:$B,"<="&'Cash Flow'!BI$3,'Wells Fargo'!$B:$B,">"&'Cash Flow'!BH$3) -> 0
A12: Best Buy - Credit | B12: =SUM(C12:BI12) -> -798.92 | C12: =SUMIFS('Wells Fargo'!$F:$F,'Wells Fargo'!$G:$G,'Cash Flow'!$A12,'Wells Fargo'!$A:$A,C$1,'Wells Fargo'!$B:$B,"<="&'Cash Flow'!C$3) -> 0 | D12: =SUMIFS('Wells Fargo'!$F:$F,'Wells Fargo'!$G:$G,'Cash Flow'!$A12,'Wells Fargo'!$A:$A,D$1,'Wells Fargo'!$B:$B,"<="&'Cash Flow'!D$3,'Wells Fargo'!$B:$B,">"&'Cash Flow'!C$3) -> 0 | E12: =SUMIFS('Wells Fargo'!$F:$F,'Wells Fargo'!$G:$G,'Cash Flow'!$A12,'Wells Fargo'!$A:$A,E$1,'Wells Fargo'!$B:$B,"<="&'Cash Flow'!E$3,'Wells Fargo'!$B:$B,">"&'Cash Flow'!D$3) -> 0 | F12: =SUMIFS('Wells Fargo'!$F:$F,'Wells Fargo'!$G:$G,'Cash Flow'!$A12,'Wells Fargo'!$A:$A,F$1,'Wells Fargo'!$B:$B,"<="&'Cash Flow'!F$3,'Wells Fargo'!$B:$B,">"&'Cash Flow'!E$3) -> 0 | G12: =SUMIFS('Wells Fargo'!$F:$F,'Wells Fargo'!$G:$G,'Cash Flow'!$A12,'Wells Fargo'!$A:$A,G$1,'Wells Fargo'!$B:$B,"<="&'Cash Flow'!G$3,'Wells Fargo'!$B:$B,">"&'Cash Flow'!F$3) -> 0 | H12: =SUMIFS('Wells Fargo'!$F:$F,'Wells Fargo'!$G:$G,'Cash Flow'!$A12,'Wells Fargo'!$A:$A,H$1,'Wells Fargo'!$B:$B,"<="&'Cash Flow'!H$3) -> 0 | I12: =SUMIFS('Wells Fargo'!$F:$F,'Wells Fargo'!$G:$G,'Cash Flow'!$A12,'Wells Fargo'!$A:$A,I$1,'Wells Fargo'!$B:$B,"<="&'Cash Flow'!I$3,'Wells Fargo'!$B:$B,">"&'Cash Flow'!H$3) -> 0 | J12: =SUMIFS('Wells Fargo'!$F:$F,'Wells Fargo'!$G:$G,'Cash Flow'!$A12,'Wells Fargo'!$A:$A,J$1,'Wells Fargo'!$B:$B,"<="&'Cash Flow'!J$3,'Wells Fargo'!$B:$B,">"&'Cash Flow'!I$3) -> 0 | K12: =SUMIFS('Wells Fargo'!$F:$F,'Wells Fargo'!$G:$G,'Cash Flow'!$A12,'Wells Fargo'!$A:$A,K$1,'Wells Fargo'!$B:$B,"<="&'Cash Flow'!K$3,'Wells Fargo'!$B:$B,">"&'Cash Flow'!J$3) -> 0 | L12: =SUMIFS('Wells Fargo'!$F:$F,'Wells Fargo'!$G:$G,'Cash Flow'!$A12,'Wells Fargo'!$A:$A,L$1,'Wells Fargo'!$B:$B,"<="&'Cash Flow'!L$3) -> 0 | M12: =SUMIFS('Wells Fargo'!$F:$F,'Wells Fargo'!$G:$G,'Cash Flow'!$A12,'Wells Fargo'!$A:$A,M$1,'Wells Fargo'!$B:$B,"<="&'Cash Flow'!M$3,'Wells Fargo'!$B:$B,">"&'Cash Flow'!L$3) -> 0 | N12: =SUMIFS('Wells Fargo'!$F:$F,'Wells Fargo'!$G:$G,'Cash Flow'!$A12,'Wells Fargo'!$A:$A,N$1,'Wells Fargo'!$B:$B,"<="&'Cash Flow'!N$3,'Wells Fargo'!$B:$B,">"&'Cash Flow'!M$3) -> 0 | O12: =SUMIFS('Wells Fargo'!$F:$F,'Wells Fargo'!$G:$G,'Cash Flow'!$A12,'Wells Fargo'!$A:$A,O$1,'Wells Fargo'!$B:$B,"<="&'Cash Flow'!O$3,'Wells Fargo'!$B:$B,">"&'Cash Flow'!N$3) -> 0 | P12: =SUMIFS('Wells Fargo'!$F:$F,'Wells Fargo'!$G:$G,'Cash Flow'!$A12,'Wells Fargo'!$A:$A,P$1,'Wells Fargo'!$B:$B,"<="&'Cash Flow'!P$3,'Wells Fargo'!$B:$B,">"&'Cash Flow'!O$3) -> 0 | Q12: =SUMIFS('Wells Fargo'!$F:$F,'Wells Fargo'!$G:$G,'Cash Flow'!$A12,'Wells Fargo'!$A:$A,Q$1,'Wells Fargo'!$B:$B,"<="&'Cash Flow'!Q$3) -> 0 | R12: =SUMIFS('Wells Fargo'!$F:$F,'Wells Fargo'!$G:$G,'Cash Flow'!$A12,'Wells Fargo'!$A:$A,R$1,'Wells Fargo'!$B:$B,"<="&'Cash Flow'!R$3,'Wells Fargo'!$B:$B,">"&'Cash Flow'!Q$3) -> 0 | S12: =SUMIFS('Wells Fargo'!$F:$F,'Wells Fargo'!$G:$G,'Cash Flow'!$A12,'Wells Fargo'!$A:$A,S$1,'Wells Fargo'!$B:$B,"<="&'Cash Flow'!S$3,'Wells Fargo'!$B:$B,">"&'Cash Flow'!R$3) -> 0 | T12: =SUMIFS('Wells Fargo'!$F:$F,'Wells Fargo'!$G:$G,'Cash Flow'!$A12,'Wells Fargo'!$A:$A,T$1,'Wells Fargo'!$B:$B,"<="&'Cash Flow'!T$3,'Wells Fargo'!$B:$B,">"&'Cash Flow'!S$3) -> 0 | U12: =SUMIFS('Wells Fargo'!$F:$F,'Wells Fargo'!$G:$G,'Cash Flow'!$A12,'Wells Fargo'!$A:$A,U$1,'Wells Fargo'!$B:$B,"<="&'Cash Flow'!U$3,'Wells Fargo'!$B:$B,">"&'Cash Flow'!T$3) -> 0 | V12: =SUMIFS('Wells Fargo'!$F:$F,'Wells Fargo'!$G:$G,'Cash Flow'!$A12,'Wells Fargo'!$A:$A,V$1,'Wells Fargo'!$B:$B,"<="&'Cash Flow'!V$3) -> 0 | W12: =SUMIFS('Wells Fargo'!$F:$F,'Wells Fargo'!$G:$G,'Cash Flow'!$A12,'Wells Fargo'!$A:$A,W$1,'Wells Fargo'!$B:$B,"<="&'Cash Flow'!W$3,'Wells Fargo'!$B:$B,">"&'Cash Flow'!V$3) -> 0 | X12: =SUMIFS('Wells Fargo'!$F:$F,'Wells Fargo'!$G:$G,'Cash Flow'!$A12,'Wells Fargo'!$A:$A,X$1,'Wells Fargo'!$B:$B,"<="&'Cash Flow'!X$3,'Wells Fargo'!$B:$B,">"&'Cash Flow'!W$3) -> 0 | Y12: =SUMIFS('Wells Fargo'!$F:$F,'Wells Fargo'!$G:$G,'Cash Flow'!$A12,'Wells Fargo'!$A:$A,Y$1,'Wells Fargo'!$B:$B,"<="&'Cash Flow'!Y$3,'Wells Fargo'!$B:$B,">"&'Cash Flow'!X$3) -> 0 | Z12: =SUMIFS('Wells Fargo'!$F:$F,'Wells Fargo'!$G:$G,'Cash Flow'!$A12,'Wells Fargo'!$A:$A,Z$1,'Wells Fargo'!$B:$B,"<="&'Cash Flow'!Z$3,'Wells Fargo'!$B:$B,">"&'Cash Flow'!Y$3) -> 0 | AA12: =SUMIFS('Wells Fargo'!$F:$F,'Wells Fargo'!$G:$G,'Cash Flow'!$A12,'Wells Fargo'!$A:$A,AA$1,'Wells Fargo'!$B:$B,"<="&'Cash Flow'!AA$3) -> 0 | AB12: =SUMIFS('Wells Fargo'!$F:$F,'Wells Fargo'!$G:$G,'Cash Flow'!$A12,'Wells Fargo'!$A:$A,AB$1,'Wells Fargo'!$B:$B,"<="&'Cash Flow'!AB$3,'Wells Fargo'!$B:$B,">"&'Cash Flow'!AA$3) -> 0 | AC12: =SUMIFS('Wells Fargo'!$F:$F,'Wells Fargo'!$G:$G,'Cash Flow'!$A12,'Wells Fargo'!$A:$A,AC$1,'Wells Fargo'!$B:$B,"<="&'Cash Flow'!AC$3,'Wells Fargo'!$B:$B,">"&'Cash Flow'!AB$3) -> 0 | AD12: =SUMIFS('Wells Fargo'!$F:$F,'Wells Fargo'!$G:$G,'Cash Flow'!$A12,'Wells Fargo'!$A:$A,AD$1,'Wells Fargo'!$B:$B,"<="&'Cash Flow'!AD$3,'Wells Fargo'!$B:$B,">"&'Cash Flow'!AC$3) -> 0 | AE12: =SUMIFS('Wells Fargo'!$F:$F,'Wells Fargo'!$G:$G,'Cash Flow'!$A12,'Wells Fargo'!$A:$A,AE$1,'Wells Fargo'!$B:$B,"<="&'Cash Flow'!AE$3,'Wells Fargo'!$B:$B,">"&'Cash Flow'!AD$3) -> 0 | AF12: =SUMIFS('Wells Fargo'!$F:$F,'Wells Fargo'!$G:$G,'Cash Flow'!$A12,'Wells Fargo'!$A:$A,AF$1,'Wells Fargo'!$B:$B,"<="&'Cash Flow'!AF$3) -> 0 | AG12: =SUMIFS('Wells Fargo'!$F:$F,'Wells Fargo'!$G:$G,'Cash Flow'!$A12,'Wells Fargo'!$A:$A,AG$1,'Wells Fargo'!$B:$B,"<="&'Cash Flow'!AG$3,'Wells Fargo'!$B:$B,">"&'Cash Flow'!AF$3) -> 0 | AH12: =SUMIFS('Wells Fargo'!$F:$F,'Wells Fargo'!$G:$G,'Cash Flow'!$A12,'Wells Fargo'!$A:$A,AH$1,'Wells Fargo'!$B:$B,"<="&'Cash Flow'!AH$3,'Wells Fargo'!$B:$B,">"&'Cash Flow'!AG$3) -> 0 | AI12: =SUMIFS('Wells Fargo'!$F:$F,'Wells Fargo'!$G:$G,'Cash Flow'!$A12,'Wells Fargo'!$A:$A,AI$1,'Wells Fargo'!$B:$B,"<="&'Cash Flow'!AI$3,'Wells Fargo'!$B:$B,">"&'Cash Flow'!AH$3) -> 0 | AJ12: =SUMIFS('Wells Fargo'!$F:$F,'Wells Fargo'!$G:$G,'Cash Flow'!$A12,'Wells Fargo'!$A:$A,AJ$1,'Wells Fargo'!$B:$B,"<="&'Cash Flow'!AJ$3,'Wells Fargo'!$B:$B,">"&'Cash Flow'!AI$3) -> 0 | AK12: =SUMIFS('Wells Fargo'!$F:$F,'Wells Fargo'!$G:$G,'Cash Flow'!$A12,'Wells Fargo'!$A:$A,AK$1,'Wells Fargo'!$B:$B,"<="&'Cash Flow'!AK$3) -> 0 | AL12: =SUMIFS('Wells Fargo'!$F:$F,'Wells Fargo'!$G:$G,'Cash Flow'!$A12,'Wells Fargo'!$A:$A,AL$1,'Wells Fargo'!$B:$B,"<="&'Cash Flow'!AL$3,'Wells Fargo'!$B:$B,">"&'Cash Flow'!AK$3) -> 0 | AM12: =SUMIFS('Wells Fargo'!$F:$F,'Wells Fargo'!$G:$G,'Cash Flow'!$A12,'Wells Fargo'!$A:$A,AM$1,'Wells Fargo'!$B:$B,"<="&'Cash Flow'!AM$3,'Wells Fargo'!$B:$B,">"&'Cash Flow'!AL$3) -> 0 | AN12: =SUMIFS('Wells Fargo'!$F:$F,'Wells Fargo'!$G:$G,'Cash Flow'!$A12,'Wells Fargo'!$A:$A,AN$1,'Wells Fargo'!$B:$B,"<="&'Cash Flow'!AN$3,'Wells Fargo'!$B:$B,">"&'Cash Flow'!AM$3) -> 0 | AO12: =SUMIFS('Wells Fargo'!$F:$F,'Wells Fargo'!$G:$G,'Cash Flow'!$A12,'Wells Fargo'!$A:$A,AO$1,'Wells Fargo'!$B:$B,"<="&'Cash Flow'!AO$3,'Wells Fargo'!$B:$B,">"&'Cash Flow'!AN$3) -> 0 | AP12: =SUMIFS('Wells Fargo'!$F:$F,'Wells Fargo'!$G:$G,'Cash Flow'!$A12,'Wells Fargo'!$A:$A,AP$1,'Wells Fargo'!$B:$B,"<="&'Cash Flow'!AP$3) -> 0 | AQ12: =SUMIFS('Wells Fargo'!$F:$F,'Wells Fargo'!$G:$G,'Cash Flow'!$A12,'Wells Fargo'!$A:$A,AQ$1,'Wells Fargo'!$B:$B,"<="&'Cash Flow'!AQ$3,'Wells Fargo'!$B:$B,">"&'Cash Flow'!AP$3) -> -190.78 | AR12: =SUMIFS('Wells Fargo'!$F:$F,'Wells Fargo'!$G:$G,'Cash Flow'!$A12,'Wells Fargo'!$A:$A,AR$1,'Wells Fargo'!$B:$B,"<="&'Cash Flow'!AR$3,'Wells Fargo'!$B:$B,">"&'Cash Flow'!AQ$3) -> -608.14 | AS12: =SUMIFS('Wells Fargo'!$F:$F,'Wells Fargo'!$G:$G,'Cash Flow'!$A12,'Wells Fargo'!$A:$A,AS$1,'Wells Fargo'!$B:$B,"<="&'Cash Flow'!AS$3,'Wells Fargo'!$B:$B,">"&'Cash Flow'!AR$3) -> 0 | AT12: =SUMIFS('Wells Fargo'!$F:$F,'Wells Fargo'!$G:$G,'Cash Flow'!$A12,'Wells Fargo'!$A:$A,AT$1,'Wells Fargo'!$B:$B,"<="&'Cash Flow'!AT$3,'Wells Fargo'!$B:$B,">"&'Cash Flow'!AS$3) -> 0 | AU12: =SUMIFS('Wells Fargo'!$F:$F,'Wells Fargo'!$G:$G,'Cash Flow'!$A12,'Wells Fargo'!$A:$A,AU$1,'Wells Fargo'!$B:$B,"<="&'Cash Flow'!AU$3) -> 0 | AV12: =SUMIFS('Wells Fargo'!$F:$F,'Wells Fargo'!$G:$G,'Cash Flow'!$A12,'Wells Fargo'!$A:$A,AV$1,'Wells Fargo'!$B:$B,"<="&'Cash Flow'!AV$3,'Wells Fargo'!$B:$B,">"&'Cash Flow'!AU$3) -> 0 | AW12: =SUMIFS('Wells Fargo'!$F:$F,'Wells Fargo'!$G:$G,'Cash Flow'!$A12,'Wells Fargo'!$A:$A,AW$1,'Wells Fargo'!$B:$B,"<="&'Cash Flow'!AW$3,'Wells Fargo'!$B:$B,">"&'Cash Flow'!AV$3) -> 0 | AX12: =SUMIFS('Wells Fargo'!$F:$F,'Wells Fargo'!$G:$G,'Cash Flow'!$A12,'Wells Fargo'!$A:$A,AX$1,'Wells Fargo'!$B:$B,"<="&'Cash Flow'!AX$3,'Wells Fargo'!$B:$B,">"&'Cash Flow'!AW$3) -> 0 | AY12: =SUMIFS('Wells Fargo'!$F:$F,'Wells Fargo'!$G:$G,'Cash Flow'!$A12,'Wells Fargo'!$A:$A,AY$1,'Wells Fargo'!$B:$B,"<="&'Cash Flow'!AY$3,'Wells Fargo'!$B:$B,">"&'Cash Flow'!AX$3) -> 0 | AZ12: =SUMIFS('Wells Fargo'!$F:$F,'Wells Fargo'!$G:$G,'Cash Flow'!$A12,'Wells Fargo'!$A:$A,AZ$1,'Wells Fargo'!$B:$B,"<="&'Cash Flow'!AZ$3) -> 0 | BA12: =SUMIFS('Wells Fargo'!$F:$F,'Wells Fargo'!$G:$G,'Cash Flow'!$A12,'Wells Fargo'!$A:$A,BA$1,'Wells Fargo'!$B:$B,"<="&'Cash Flow'!BA$3,'Wells Fargo'!$B:$B,">"&'Cash Flow'!AZ$3) -> 0 | BB12: =SUMIFS('Wells Fargo'!$F:$F,'Wells Fargo'!$G:$G,'Cash Flow'!$A12,'Wells Fargo'!$A:$A,BB$1,'Wells Fargo'!$B:$B,"<="&'Cash Flow'!BB$3,'Wells Fargo'!$B:$B,">"&'Cash Flow'!BA$3) -> 0 | BC12: =SUMIFS('Wells Fargo'!$F:$F,'Wells Fargo'!$G:$G,'Cash Flow'!$A12,'Wells Fargo'!$A:$A,BC$1,'Wells Fargo'!$B:$B,"<="&'Cash Flow'!BC$3,'Wells Fargo'!$B:$B,">"&'Cash Flow'!BB$3) -> 0 | BD12: =SUMIFS('Wells Fargo'!$F:$F,'Wells Fargo'!$G:$G,'Cash Flow'!$A12,'Wells Fargo'!$A:$A,BD$1,'Wells Fargo'!$B:$B,"<="&'Cash Flow'!BD$3,'Wells Fargo'!$B:$B,">"&'Cash Flow'!BC$3) -> 0 | BE12: =SUMIFS('Wells Fargo'!$F:$F,'Wells Fargo'!$G:$G,'Cash Flow'!$A12,'Wells Fargo'!$A:$A,BE$1,'Wells Fargo'!$B:$B,"<="&'Cash Flow'!BE$3) -> 0 | BF12: =SUMIFS('Wells Fargo'!$F:$F,'Wells Fargo'!$G:$G,'Cash Flow'!$A12,'Wells Fargo'!$A:$A,BF$1,'Wells Fargo'!$B:$B,"<="&'Cash Flow'!BF$3,'Wells Fargo'!$B:$B,">"&'Cash Flow'!BE$3) -> 0 | BG12: =SUMIFS('Wells Fargo'!$F:$F,'Wells Fargo'!$G:$G,'Cash Flow'!$A12,'Wells Fargo'!$A:$A,BG$1,'Wells Fargo'!$B:$B,"<="&'Cash Flow'!BG$3,'Wells Fargo'!$B:$B,">"&'Cash Flow'!BF$3) -> 0 | BH12: =SUMIFS('Wells Fargo'!$F:$F,'Wells Fargo'!$G:$G,'Cash Flow'!$A12,'Wells Fargo'!$A:$A,BH$1,'Wells Fargo'!$B:$B,"<="&'Cash Flow'!BH$3,'Wells Fargo'!$B:$B,">"&'Cash Flow'!BG$3) -> 0 | BI12: =SUMIFS('Wells Fargo'!$F:$F,'Wells Fargo'!$G:$G,'Cash Flow'!$A12,'Wells Fargo'!$A:$A,BI$1,'Wells Fargo'!$B:$B,"<="&'Cash Flow'!BI$3,'Wells Fargo'!$B:$B,">"&'Cash Flow'!BH$3) -> 0
