Workbook
Name allowance: #REF!
Name AprSun1: DATE(CalendarYear,4,1)-WEEKDAY(DATE(CalendarYear,4,1))
Name AugSun1: DATE(CalendarYear,8,1)-WEEKDAY(DATE(CalendarYear,8,1))
Name budget: '[1]Pivot (2021)'!$A$2
Name Budget: #REF!
Name CalendarYear: [0]!Year1
Name Categories: [2]!TableAssetAllocation[Category]
Name DecSun1: DATE(CalendarYear,12,1)-WEEKDAY(DATE(CalendarYear,12,1))
Name Expense_Lookup: Discover!$P:$Q
Name FebSun1: DATE(CalendarYear,2,1)-WEEKDAY(DATE(CalendarYear,2,1))
Name fixed: #REF!
Name income: #REF!
Name JanSun1: DATE(CalendarYear,1,1)-WEEKDAY(DATE(CalendarYear,1,1))
Name JulSun1: DATE(CalendarYear,7,1)-WEEKDAY(DATE(CalendarYear,7,1))
Name JunSun1: DATE(CalendarYear,6,1)-WEEKDAY(DATE(CalendarYear,6,1))
Name MarSun1: DATE(CalendarYear,3,1)-WEEKDAY(DATE(CalendarYear,3,1))
Name MaySun1: DATE(CalendarYear,5,1)-WEEKDAY(DATE(CalendarYear,5,1))
Name NovSun1: DATE(CalendarYear,11,1)-WEEKDAY(DATE(CalendarYear,11,1))
Name OctSun1: DATE(CalendarYear,10,1)-WEEKDAY(DATE(CalendarYear,10,1))
Name Robinhood: #REF!
Name SepSun1: DATE(CalendarYear,9,1)-WEEKDAY(DATE(CalendarYear,9,1))
Name StartMonth: #REF!
Name Tail_Rent: '[1]2021 Income'!#REF!
Name Title2: #REF!
Name valdate: #REF!
Name Year1: VALUE(LEFT(#REF!,4))

Sheet Wells Fargo
A1: Month | B1: Day | C1: Date | D1: Description2 | E1: Description | F1: Amount | G1: Primary
A2: =MONTH(C2) -> 1 | B2: =DAY(C2) -> 4 | C2: 44200 | D2: DISCOVER | E2: DISCOVER E-PAYMENT 210101 4732 LEWIS SEAN | F2: -700 | G2: Credit
A3: =MONTH(C3) -> 1 | B3: =DAY(C3) -> 4 | C3: 44200 | D3: IRS | E3: IRS TREAS 310 XXTAXEIP2 010421 XXXXXXXXXX00908 LEWIS, SEAN | F3: 600 | G3: Stimulus 1
A4: =MONTH(C4) -> 1 | B4: =DAY(C4) -> 15 | C4: 44211 | D4: DISCOVER | E4: DISCOVER E-PAYMENT 210115 4732 LEWIS SEAN | F4: -729.23 | G4: Credit
A5: =MONTH(C5) -> 1 | B5: =DAY(C5) -> 15 | C5: 44211 | D5: Elephant | E5: Elephant Ins PAYROLL 210113 2087 Lewis Sean | F5: 1459.65 | G5: Elephant
A6: =MONTH(C6) -> 1 | B6: =DAY(C6) -> 19 | C6: 44215 | D6: VENMO | E6: VENMO PAYMENT 5101219782 SEAN LEWIS | F6: -569.12 | G6: Vincent
A7: =MONTH(C7) -> 1 | B7: =DAY(C7) -> 19 | C7: 44215 | D7: VENMO | E7: VENMO PAYMENT 5101208453 SEAN LEWIS | F7: -78.86 | G7: Amar - Electric
A8: =MONTH(C8) -> 1 | B8: =DAY(C8) -> 19 | C8: 44215 | D8: VENMO | E8: VENMO CASHOUT 5117912825 SEAN LEWIS | F8: 150 | G8: Venmo Cash Out
A9: =MONTH(C9) -> 1 | B9: =DAY(C9) -> 21 | C9: 44217 | D9: PURCHASE | E9: PURCHASE AUTHORIZED ON 01/20 CASH APP* 8774174551 CA S461020486646597 CARD 6634 | F9: -155 | G9: Cairo
A10: =MONTH(C10) -> 1 | B10: =DAY(C10) -> 22 | C10: 44218 | D10: PURCHASE | E10: PURCHASE AUTHORIZED ON 01/21 SOCIETY OF ACTUARI 847-706-3620 IL S581021446560343 CARD 6634 | F10: -75 | G10: SOA
A11: =MONTH(C11) -> 1 | B11: =DAY(C11) -> 26 | C11: 44222 | D11: MONEY | E11: MONEY TRANSFER AUTHORIZED ON 01/26 FROM Sean Lewis VA S00581026542833832 CARD 6634 | F11: 155 | G11: Cairo
A12: =MONTH(C12) -> 1 | B12: =DAY(C12) -> 28 | C12: 44224 | D12: ROBINHOOD | E12: ROBINHOOD Funds 210127 XXXXX4480 Sean Lewis | F12: -100 | G12: Investment
A13: =MONTH(C13) -> 1 | B13: =DAY(C13) -> 28 | C13: 44224 | D13: ROBINHOOD | E13: ROBINHOOD Funds 210127 XXXXX4480 Sean Lewis | F13: -50 | G13: Investment
... A127: =MONTH(C127) -> 6 | B127: =DAY(C127) -> 17 | C127: 44364 | D127: Nationwide | E127: Nationwide PAYROLL 01 HRP0007397914 Sean Lewis | F127: 4436.57 | G127: Nationwide
A128: =MONTH(C128) -> 6 | B128: =DAY(C128) -> 18 | C128: 44365 | D128: =LEFT(E128, FIND(" ",E128)-1) -> PRINCIPAL | E128: PRINCIPAL TRUST DR CR 210617 PACT#179541394 SEAN LEWIS | F128: 3967.1 | G128: Principal retirement
A129: =MONTH(C129) -> 6 | B129: =DAY(C129) -> 18 | C129: 44365 | D129: =LEFT(E129, FIND(" ",E129)-1) -> Elephant | E129: Elephant Ins PAYROLL 210616 2087 Lewis Sean | F129: 680.02 | G129: Elephant
A130: =MONTH(C130) -> 6 | B130: =DAY(C130) -> 21 | C130: 44368 | D130: =LEFT(E130, FIND(" ",E130)-1) -> VENMO | E130: VENMO PAYMENT 210620 1014291472980 SEAN LEWIS | F130: -2738.5 | G130: Matt Bozz
A131: =MONTH(C131) -> 6 | B131: =DAY(C131) -> 21 | C131: 44368 | D131: =LEFT(E131, FIND(" ",E131)-1) -> VENMO | E131: VENMO PAYMENT 210620 1014291497592 SEAN LEWIS | F131: -615 | G131: Anush Rohani Shukla
A132: =MONTH(C132) -> 6 | B132: =DAY(C132) -> 23 | C132: 44370 | D132: =LEFT(E132, FIND(" ",E132)-1) -> DISCOVER | E132: DISCOVER E-PAYMENT 210623 7328 LEWIS SEAN | F132: -1869 | G132: Credit
A133: =MONTH(C133) -> 6 | B133: =DAY(C133) -> 23 | C133: 44370 | D133: =LEFT(E133, FIND(" ",E133)-1) -> PURCHASE | E133: PURCHASE AUTHORIZED ON 06/22 STITCH FIX STYLIN 844-386-3850 CA S581173332274659 CARD 6634 | F133: -20 | G133: Headshot
A134: =MONTH(C134) -> 6 | B134: =DAY(C134) -> 23 | C134: 44370 | D134: =LEFT(E134, FIND(" ",E134)-1) -> PRINCIPAL | E134: PRINCIPAL TRUST DR CR 210622 PACT#180033360 Sean Lewis | F134: 198.46 | G134: Principal retirement
A135: =MONTH(C135) -> 6 | B135: =DAY(C135) -> 25 | C135: 44372 | D135: =LEFT(E135, FIND(" ",E135)-1) -> PURCHASE | E135: PURCHASE AUTHORIZED ON 06/23 TST* TIO PABLO TAQ RICHMOND VA S461175013934521 CARD 6634 | F135: -58.57 | G135: Resteraunt
A136: =MONTH(C136) -> 6 | B136: =DAY(C136) -> 30 | C136: 44377 | D136: =LEFT(E136, FIND(" ",E136)-1) -> New | E136: New Manchester F WEB PMTS 063021 M7CVM7 Sean Lewis | F136: -1804.34 | G136: New Manchester - Rent
A137: =MONTH(C137) -> 7 | B137: =DAY(C137) -> 1 | C137: 44378 | D137: =LEFT(E137, FIND(" ",E137)-1) -> DISCOVER | E137: DISCOVER E-PAYMENT 210701 7328 LEWIS SEAN | F137: -871.96 | G137: Credit
A138: =MONTH(C138) -> 7 | B138: =DAY(C138) -> 1 | C138: 44378 | D138: =LEFT(E138, FIND(" ",E138)-1) -> Nationwide | E138: Nationwide PAYROLL 01 HRP0007447918 Sean Lewis | F138: 1583.62 | G138: Nationwide
A139: =MONTH(C139) -> 7 | B139: =DAY(C139) -> 6 | C139: 44383 | D139: =LEFT(E139, FIND(" ",E139)-1) -> DISCOVER | E139: DISCOVER E-PAYMENT 210705 7328 LEWIS SEAN | F139: -367.73 | G139: Credit
... A147: =MONTH(C147) -> 7 | B147: =DAY(C147) -> 7 | C147: 44384 | D147: =LEFT(E147, FIND(" ",E147)-1) -> PURCHASE | E147: PURCHASE AUTHORIZED ON 07/06 PHO QUE HUONG NUMB GLEN ALLEN VA S381187824546148 CARD 6634 | F147: -30 | G147: Resteraunt

Sheet Discover
A1: Year | B1: Month | C1: Trans. date | D1: Post date | F1: Description | G1: Amount | H1: Category | I1: Expense Type | J1: Cumulative | K1: Association
A2: =YEAR(C2) -> 2021 | B2: =MONTH(C2) -> 1 | C2: 44197 | D2: 44197 | E2: =LEFT(F2,5) -> INTER | F2: INTERNET PAYMENT - THANK YOU | G2: -700 | H2: Payments and Credits | I2: =VLOOKUP(H2,Expense_Lookup,2,0) -> Payment | J2: 728.15
A3: =YEAR(C3) -> 2021 | B3: =MONTH(C3) -> 1 | C3: 44197 | D3: 44199 | E3: =LEFT(F3,5) -> NETFL | F3: NETFLIX.COM NETFLIX.COM CA44115296471 | G3: 13.99 | H3: APP | I3: =VLOOKUP(H3,Expense_Lookup,2,0) -> Fixed | J3: =J2+G3 -> 742.14 | K3: Netflix
A4: =YEAR(C4) -> 2021 | B4: =MONTH(C4) -> 1 | C4: 44197 | D4: 44199 | E4: =LEFT(F4,5) -> SPOTI | F4: SPOTIFY P12D96D434 8777781161 NY | G4: 9.99 | H4: APP | I4: =VLOOKUP(H4,Expense_Lookup,2,0) -> Fixed | J4: =J3+G4 -> 752.13 | K4: Spotify | M4: Variable | N4: =SUMIFS(G:G,I:I,M4) -> 12045.17 | R4: Jan | S4: Feb | T4: Mar | U4: Apr | V4: May | W4: June | X4: July | Y4: Aug | Z4: Sep | AA4: Oct | AB4: Nov | AC4: Dec
A5: =YEAR(C5) -> 2021 | B5: =MONTH(C5) -> 1 | C5: 44197 | D5: 44199 | E5: =LEFT(F5,5) -> WAWA | F5: WAWA 697 STAFFORD VA | G5: 18.87 | H5: Gasoline | I5: =VLOOKUP(H5,Expense_Lookup,2,0) -> Variable | J5: =J4+G5 -> 771 | M5: Fixed | N5: =SUMIFS(G:G,I:I,M5) -> 3270.22 | P5: {=_xlfn.UNIQUE(_xlfn._xlws.FILTER(H:H,(H:H<>0) ))} -> Category
A6: =YEAR(C6) -> 2021 | B6: =MONTH(C6) -> 1 | C6: 44201 | D6: 44201 | E6: =LEFT(F6,5) -> MYFIC | F6: MYFICO COM 8003194433 GA | G6: 39.95 | H6: APP | I6: =VLOOKUP(H6,Expense_Lookup,2,0) -> Fixed | J6: =J5+G6 -> 810.95 | K6: Credit Score | N6: =SUM(N4:N5) -> 15315.39 | P6: Payments and Credits | Q6: Payment | R6: =SUMIFS(G:G,H:H,P6,$B:$B,1) -> -2157.38 | S6: =SUMIFS(G:G,H:H,P6,$B:$B,2) -> -2256.47 | T6: =SUMIFS(G:G,H:H,P6,$B:$B,3) -> -2413.62 | U6: =SUMIFS($G:$G,$H:$H,$P6,$B:$B,4) -> -471.07 | V6: =SUMIFS($G:$G,$H:$H,$P6,$B:$B,5) -> -2855.16 | W6: =SUMIFS($G:$G,$H:$H,$P6,$B:$B,6) -> -3297.83 | X6: =SUMIFS($G:$G,$H:$H,$P6,$B:$B,7) -> -3414.44
A7: =YEAR(C7) -> 2021 | B7: =MONTH(C7) -> 1 | C7: 44201 | D7: 44201 | E7: =LEFT(F7,5) -> STATE | F7: STATE FARM INSURANCE 800-956-6310 IL | G7: 91.78 | H7: APP | I7: =VLOOKUP(H7,Expense_Lookup,2,0) -> Fixed | J7: =J6+G7 -> 902.73 | K7: State Farm | M7: Family | P7: APP | Q7: Fixed | R7: =SUMIFS(G:G,H:H,P7,$B:$B,1) -> 225.53 | S7: =SUMIFS(G:G,H:H,P7,$B:$B,2) -> 260.85 | T7: =SUMIFS(G:G,H:H,P7,$B:$B,3) -> 493.82 | U7: =SUMIFS(G:G,H:H,P7,$B:$B,4) -> 318.38 | V7: =SUMIFS($G:$G,$H:$H,$P7,$B:$B,5) -> 506.1 | W7: =SUMIFS($G:$G,$H:$H,$P7,$B:$B,6) -> 579.09 | X7: =SUMIFS($G:$G,$H:$H,$P7,$B:$B,7) -> 138.88
A8: =YEAR(C8) -> 2021 | B8: =MONTH(C8) -> 1 | C8: 44201 | D8: 44201 | E8: =LEFT(F8,5) -> STEAM | F8: STEAMPOWERED.COM 425-952-2985 WA | G8: 19.99 | H8: Merchandise | I8: =VLOOKUP(H8,Expense_Lookup,2,0) -> Variable | J8: =J7+G8 -> 922.72 | K8: Neir Automata | M8: Jayelin | N8: =SUMIFS(G:G,K:K,M8)+SUMIFS('Cash Flow'!$B:$B,'Cash Flow'!$A:$A,Discover!M8)*-1 -> 700.36 | P8: Gasoline | Q8: Variable | R8: =SUMIFS(G:G,H:H,P8,$B:$B,1) -> 67.87 | S8: =SUMIFS(G:G,H:H,P8,$B:$B,2) -> 67.47 | T8: =SUMIFS(G:G,H:H,P8,$B:$B,3) -> 80.06 | U8: =SUMIFS(G:G,H:H,P8,$B:$B,4) -> 125.95 | V8: =SUMIFS($G:$G,$H:$H,$P8,$B:$B,5) -> 115.16 | W8: =SUMIFS($G:$G,$H:$H,$P8,$B:$B,6) -> 104.56 | X8: =SUMIFS($G:$G,$H:$H,$P8,$B:$B,7) -> 32.33
A9: =YEAR(C9) -> 2021 | B9: =MONTH(C9) -> 1 | C9: 44202 | D9: 44202 | E9: =LEFT(F9,5) -> LIVEC | F9: LIVECAREER.COM 800652843 866-933-7587 PR | G9: 24.95 | H9: APP | I9: =VLOOKUP(H9,Expense_Lookup,2,0) -> Fixed | J9: =J8+G9 -> 947.67 | K9: Jayelin | M9: Shevon | N9: =SUMIFS(G:G,K:K,M9)+SUMIFS('Cash Flow'!$B:$B,'Cash Flow'!$A:$A,Discover!M9)*-1 -> 514.95 | P9: Merchandise | Q9: Variable | R9: =SUMIFS(G:G,H:H,P9,$B:$B,1) -> 447.39 | S9: =SUMIFS(G:G,H:H,P9,$B:$B,2) -> 291.35 | T9: =SUMIFS(G:G,H:H,P9,$B:$B,3) -> 427.64 | U9: =SUMIFS(G:G,H:H,P9,$B:$B,4) -> 360.76 | V9: =SUMIFS($G:$G,$H:$H,$P9,$B:$B,5) -> 645.99 | W9: =SUMIFS($G:$G,$H:$H,$P9,$B:$B,6) -> 1136.89 | X9: =SUMIFS($G:$G,$H:$H,$P9,$B:$B,7) -> 742.08
A10: =YEAR(C10) -> 2021 | B10: =MONTH(C10) -> 1 | C10: 44202 | D10: 44202 | E10: =LEFT(F10,5) -> RIVER | F10: RIVER RUN SHORT PUMP HENRICO VA | G10: 30 | H10: Medical Services | I10: =VLOOKUP(H10,Expense_Lookup,2,0) -> Variable | J10: =J9+G10 -> 977.67 | M10: Don | N10: =SUMIFS(G:G,K:K,M10)+SUMIFS('Cash Flow'!$B:$B,'Cash Flow'!$A:$A,Discover!M10)*-1 -> 227.5 | P10: Medical Services | Q10: Variable | R10: =SUMIFS(G:G,H:H,P10,$B:$B,1) -> 70.51 | S10: =SUMIFS(G:G,H:H,P10,$B:$B,2) -> 0 | T10: =SUMIFS(G:G,H:H,P10,$B:$B,3) -> 0 | U10: =SUMIFS(G:G,H:H,P10,$B:$B,4) -> 0 | V10: =SUMIFS($G:$G,$H:$H,$P10,$B:$B,5) -> 0 | W10: =SUMIFS($G:$G,$H:$H,$P10,$B:$B,6) -> 0 | X10: =SUMIFS($G:$G,$H:$H,$P10,$B:$B,7) -> 0
A11: =YEAR(C11) -> 2021 | B11: =MONTH(C11) -> 1 | C11: 44202 | D11: 44202 | E11: =LEFT(F11,5) -> THE M | F11: THE MARKET @ 25TH RICHMOND VA | G11: 24.24 | H11: Supermarkets | I11: =VLOOKUP(H11,Expense_Lookup,2,0) -> Variable | J11: =J10+G11 -> 1001.91 | M11: Dorry | N11: =SUMIFS(G:G,K:K,M11)+SUMIFS('Cash Flow'!$B:$B,'Cash Flow'!$A:$A,Discover!M11)*-1 -> 355 | P11: Supermarkets | Q11: Variable | R11: =SUMIFS(G:G,H:H,P11,$B:$B,1) -> 145.56 | S11: =SUMIFS(G:G,H:H,P11,$B:$B,2) -> 247.65 | T11: =SUMIFS(G:G,H:H,P11,$B:$B,3) -> 132.85 | U11: =SUMIFS(G:G,H:H,P11,$B:$B,4) -> 25.32 | V11: =SUMIFS($G:$G,$H:$H,$P11,$B:$B,5) -> 321.42 | W11: =SUMIFS($G:$G,$H:$H,$P11,$B:$B,6) -> 100.64 | X11: =SUMIFS($G:$G,$H:$H,$P11,$B:$B,7) -> 15.6
A12: =YEAR(C12) -> 2021 | B12: =MONTH(C12) -> 1 | C12: 44203 | D12: 44203 | E12: =LEFT(F12,5) -> AMERI | F12: AMERICA'S BEST WINGS HENRICO VA | G12: 12.09 | H12: Restaurants | I12: =VLOOKUP(H12,Expense_Lookup,2,0) -> Variable | J12: =J11+G12 -> 1014 | M12: Cairo | N12: =SUMIFS(G:G,K:K,M12)+SUMIFS('Cash Flow'!$B:$B,'Cash Flow'!$A:$A,Discover!M12)*-1 -> 0 | P12: Restaurants | Q12: Variable | R12: =SUMIFS(G:G,H:H,P12,$B:$B,1) -> 131.44 | S12: =SUMIFS(G:G,H:H,P12,$B:$B,2) -> 69.55 | T12: =SUMIFS(G:G,H:H,P12,$B:$B,3) -> 314.85 | U12: =SUMIFS(G:G,H:H,P12,$B:$B,4) -> 487.13 | V12: =SUMIFS($G:$G,$H:$H,$P12,$B:$B,5) -> 247.11 | W12: =SUMIFS($G:$G,$H:$H,$P12,$B:$B,6) -> 472.59 | X12: =SUMIFS($G:$G,$H:$H,$P12,$B:$B,7) -> 354.18
A13: =YEAR(C13) -> 2021 | B13: =MONTH(C13) -> 1 | C13: 44203 | D13: 44203 | E13: =LEFT(F13,5) -> GO DR | F13: GO DRAGON ASIAN GRILL RICHMOND VA | G13: 44 | H13: Restaurants | I13: =VLOOKUP(H13,Expense_Lookup,2,0) -> Variable | J13: =J12+G13 -> 1058 | N13: =SUM(N8:N12) -> 1797.81 | P13: Services | Q13: Variable | R13: =SUMIFS(G:G,H:H,P13,$B:$B,1) -> 29.27 | S13: =SUMIFS(G:G,H:H,P13,$B:$B,2) -> 0 | T13: =SUMIFS(G:G,H:H,P13,$B:$B,3) -> 565.98 | U13: =SUMIFS(G:G,H:H,P13,$B:$B,4) -> 98 | V13: =SUMIFS($G:$G,$H:$H,$P13,$B:$B,5) -> 87.75 | W13: =SUMIFS($G:$G,$H:$H,$P13,$B:$B,6) -> 213.84 | X13: =SUMIFS($G:$G,$H:$H,$P13,$B:$B,7) -> 1380.63
A14: =YEAR(C14) -> 2021 | B14: =MONTH(C14) -> 1 | C14: 44203 | D14: 44203 | E14: =LEFT(F14,5) -> THE M | F14: THE MARKET @ 25TH RICHMOND VA | G14: 14.52 | H14: Supermarkets | I14: =VLOOKUP(H14,Expense_Lookup,2,0) -> Variable | J14: =J13+G14 -> 1072.52 | P14: Family | Q14: Variable | R14: =SUMIFS(G:G,H:H,P14,$B:$B,1) -> 103 | S14: =SUMIFS(G:G,H:H,P14,$B:$B,2) -> 0 | T14: =SUMIFS(G:G,H:H,P14,$B:$B,3) -> 0 | U14: =SUMIFS(G:G,H:H,P14,$B:$B,4) -> 0 | V14: =SUMIFS($G:$G,$H:$H,$P14,$B:$B,5) -> 0 | W14: =SUMIFS($G:$G,$H:$H,$P14,$B:$B,6) -> 0 | X14: =SUMIFS($G:$G,$H:$H,$P14,$B:$B,7) -> 0
A15: =YEAR(C15) -> 2021 | B15: =MONTH(C15) -> 1 | C15: 44204 | D15: 44204 | E15: =LEFT(F15,5) -> CVS/P | F15: CVS/PHARMACY #01988 RICHMOND VA | G15: 3.37 | H15: Merchandise | I15: =VLOOKUP(H15,Expense_Lookup,2,0) -> Variable | J15: =J14+G15 -> 1075.89 | K15: Jayelin | M15: Trips | P15: Education | Q15: Variable | R15: =SUMIFS(G:G,H:H,P15,$B:$B,1) -> 49 | S15: =SUMIFS(G:G,H:H,P15,$B:$B,2) -> 215 | T15: =SUMIFS(G:G,H:H,P15,$B:$B,3) -> 0 | U15: =SUMIFS(G:G,H:H,P15,$B:$B,4) -> 0 | V15: =SUMIFS($G:$G,$H:$H,$P15,$B:$B,5) -> 0 | W15: =SUMIFS($G:$G,$H:$H,$P15,$B:$B,6) -> 199 | X15: =SUMIFS($G:$G,$H:$H,$P15,$B:$B,7) -> 0
A16: =YEAR(C16) -> 2021 | B16: =MONTH(C16) -> 1 | C16: 44204 | D16: 44204 | E16: =LEFT(F16,5) -> LABCO | F16: LABCORP PSCC 2 800-845-6167 NC202101072171244 | G16: 40.51 | H16: Medical Services | I16: =VLOOKUP(H16,Expense_Lookup,2,0) -> Variable | J16: =J15+G16 -> 1116.4 | K16: Doctor | M16: New York | N16: =SUMIFS(G:G,K:K,M16)+SUMIFS('Cash Flow'!$B:$B,'Cash Flow'!$A:$A,Discover!M16)*-1 -> 373.46 | P16: Awards and Rebate Credits | Q16: Payment | R16: =SUMIFS(G:G,H:H,P16,$B:$B,1) -> -22.18 | S16: =SUMIFS(G:G,H:H,P16,$B:$B,2) -> -14 | T16: =SUMIFS(G:G,H:H,P16,$B:$B,3) -> -14.05 | U16: =SUMIFS(G:G,H:H,P16,$B:$B,4) -> 0 | V16: =SUMIFS($G:$G,$H:$H,$P16,$B:$B,5) -> 0 | W16: =SUMIFS($G:$G,$H:$H,$P16,$B:$B,6) -> 0 | X16: =SUMIFS($G:$G,$H:$H,$P16,$B:$B,7) -> 0
A17: =YEAR(C17) -> 2021 | B17: =MONTH(C17) -> 1 | C17: 44205 | D17: 44205 | E17: =LEFT(F17,5) -> BINGO | F17: BINGO BEER CO - GAMES PE RICHMOND VA | G17: 30 | H17: Restaurants | I17: =VLOOKUP(H17,Expense_Lookup,2,0) -> Variable | J17: =J16+G17 -> 1146.4 | K17: Akhil | M17: Brooklyn | N17: =SUMIFS(G:G,K:K,M17)+SUMIFS('Cash Flow'!$B:$B,'Cash Flow'!$A:$A,Discover!M17)*-1 -> 1983.8 | P17: Travel/ Entertainment | Q17: Variable | R17: =SUMIFS(G:G,H:H,P17,$B:$B,1) -> 0 | S17: =SUMIFS(G:G,H:H,P17,$B:$B,2) -> 15 | T17: =SUMIFS(G:G,H:H,P17,$B:$B,3) -> 101.04 | U17: =SUMIFS(G:G,H:H,P17,$B:$B,4) -> 4.24 | V17: =SUMIFS($G:$G,$H:$H,$P17,$B:$B,5) -> 360.05 | W17: =SUMIFS($G:$G,$H:$H,$P17,$B:$B,6) -> 179.77 | X17: =SUMIFS($G:$G,$H:$H,$P17,$B:$B,7) -> 399.77
A18: =YEAR(C18) -> 2021 | B18: =MONTH(C18) -> 1 | C18: 44205 | D18: 44205 | E18: =LEFT(F18,5) -> WALMA | F18: WALMART SC 07032 HENRICO VA | G18: 37.5 | H18: Merchandise | I18: =VLOOKUP(H18,Expense_Lookup,2,0) -> Variable | J18: =J17+G18 -> 1183.9 | N18: =SUM(N16:N17) -> 2357.26 | P18: Government Services | Q18: Fixed | R18: =SUMIFS(G:G,H:H,P18,$B:$B,1) -> 0 | S18: =SUMIFS(G:G,H:H,P18,$B:$B,2) -> 40.15 | T18: =SUMIFS(G:G,H:H,P18,$B:$B,3) -> 0 | U18: =SUMIFS(G:G,H:H,P18,$B:$B,4) -> 0 | V18: =SUMIFS($G:$G,$H:$H,$P18,$B:$B,5) -> 26.35 | W18: =SUMIFS($G:$G,$H:$H,$P18,$B:$B,6) -> 195.05 | X18: =SUMIFS($G:$G,$H:$H,$P18,$B:$B,7) -> 0
A19: =YEAR(C19) -> 2021 | B19: =MONTH(C19) -> 1 | C19: 44206 | D19: 44206 | E19: =LEFT(F19,5) -> APPLE | F19: APPLE.COM/BILL 866-712-7753 CAAPPLE PAY ENDING IN 4775MMW3T9K9KMA0 | G19: 14.99 | H19: APP | I19: =VLOOKUP(H19,Expense_Lookup,2,0) -> Fixed | J19: =J18+G19 -> 1198.89 | K19: HBO | P19: Automotive | Q19: Fixed | R19: =SUMIFS(G:G,H:H,P19,$B:$B,1) -> 0 | S19: =SUMIFS(G:G,H:H,P19,$B:$B,2) -> 0 | T19: =SUMIFS(G:G,H:H,P19,$B:$B,3) -> 86.17 | U19: =SUMIFS(G:G,H:H,P19,$B:$B,4) -> 5.65 | V19: =SUMIFS($G:$G,$H:$H,$P19,$B:$B,5) -> 401.19 | W19: =SUMIFS($G:$G,$H:$H,$P19,$B:$B,6) -> 0 | X19: =SUMIFS($G:$G,$H:$H,$P19,$B:$B,7) -> 0
A20: =YEAR(C20) -> 2021 | B20: =MONTH(C20) -> 1 | C20: 44206 | D20: 44206 | E20: =LEFT(F20,5) -> FEDEX | F20: FEDEX 782422707980 800-4633339 TN | G20: 14.47 | H20: Services | I20: =VLOOKUP(H20,Expense_Lookup,2,0) -> Variable | J20: =J19+G20 -> 1213.36 | K20: Darron | M20: Moving | P20: Home Improvement | Q20: Variable | R20: =SUMIFS(G:G,H:H,P20,$B:$B,1) -> 0 | S20: =SUMIFS(G:G,H:H,P20,$B:$B,2) -> 0 | T20: =SUMIFS(G:G,H:H,P20,$B:$B,3) -> 0 | U20: =SUMIFS(G:G,H:H,P20,$B:$B,4) -> 92.58 | V20: =SUMIFS($G:$G,$H:$H,$P20,$B:$B,5) -> 54.37 | W20: =SUMIFS($G:$G,$H:$H,$P20,$B:$B,6) -> 23.13 | X20: =SUMIFS($G:$G,$H:$H,$P20,$B:$B,7) -> 0
A21: =YEAR(C21) -> 2021 | B21: =MONTH(C21) -> 1 | C21: 44206 | D21: 44206 | E21: =LEFT(F21,5) -> FEDEX | F21: FEDEX 782422725203 800-4633339 TN | G21: 11.45 | H21: Services | I21: =VLOOKUP(H21,Expense_Lookup,2,0) -> Variable | J21: =J20+G21 -> 1224.81 | K21: Darron | M21: Storage | N21: =SUMIFS(G:G,K:K,M21)+SUMIFS('Cash Flow'!$B:$B,'Cash Flow'!$A:$A,Discover!M21)*-1 -> 396.27 | P21: Department Stores | Q21: Variable | R21: =SUMIFS(G:G,H:H,P21,$B:$B,1) -> 0 | S21: =SUMIFS(G:G,H:H,P21,$B:$B,2) -> 0 | T21: =SUMIFS(G:G,H:H,P21,$B:$B,3) -> 0 | U21: =SUMIFS(G:G,H:H,P21,$B:$B,4) -> 0 | V21: =SUMIFS($G:$G,$H:$H,$P21,$B:$B,5) -> 91.85 | W21: =SUMIFS($G:$G,$H:$H,$P21,$B:$B,6) -> 0 | X21: =SUMIFS($G:$G,$H:$H,$P21,$B:$B,7) -> 0
A22: =YEAR(C22) -> 2021 | B22: =MONTH(C22) -> 1 | C22: 44206 | D22: 44206 | E22: =LEFT(F22,5) -> WALMA | F22: WALMART SC 07032 HENRICO VA | G22: 74.16 | H22: Merchandise | I22: =VLOOKUP(H22,Expense_Lookup,2,0) -> Variable | J22: =J21+G22 -> 1298.97 | M22: Arizona | N22: =SUMIFS(G:G,K:K,M22)+SUMIFS('Cash Flow'!$B:$B,'Cash Flow'!$A:$A,Discover!M22)*-1 -> 1380.63 | R22: =SUM(R6:R21) -> -909.99 | S22: =SUM(S6:S21) -> -1063.45 | T22: =SUM(T6:T21) -> -225.26 | U22: =SUM(U6:U21) -> 1046.94 | V22: =SUM(V6:V21) -> 2.18 | W22: =SUM(W6:W21) -> -93.27 | X22: =SUM(X6:X21) -> -350.97
A23: =YEAR(C23) -> 2021 | B23: =MONTH(C23) -> 1 | C23: 44207 | D23: 44207 | E23: =LEFT(F23,5) -> CASH | F23: CASH APP*SHEVON LEW 415-375-3176 CA | G23: 103 | H23: Family | I23: =VLOOKUP(H23,Expense_Lookup,2,0) -> Variable | J23: =J22+G23 -> 1401.97 | K23: Shevon | N23: =SUM(N21:N22) -> 1776.9 | Q23: Monthly Spending -> | R23: =SUM(R7:R15,R17:R21) -> 1269.57 | S23: =SUM(S7:S15,S17:S21) -> 1207.02 | T23: =SUM(T7:T15,T17:T21) -> 2202.41 | U23: =SUM(U7:U15,U17:U21) -> 1518.01 | V23: =SUM(V7:V15,V17:V21) -> 2857.34 | W23: =SUM(W7:W15,W17:W21) -> 3204.56 | X23: =SUM(X7:X15,X17:X21) -> 3063.47
A24: =YEAR(C24) -> 2021 | B24: =MONTH(C24) -> 1 | C24: 44207 | D24: 44207 | E24: =LEFT(F24,5) -> PAYPA | F24: PAYPAL *ETCHEDACTUA 402-935-7733 CA | G24: 49 | H24: Education | I24: =VLOOKUP(H24,Expense_Lookup,2,0) -> Variable | J24: =J23+G24 -> 1450.97
A25: =YEAR(C25) -> 2021 | B25: =MONTH(C25) -> 1 | C25: 44208 | D25: 44208 | E25: =LEFT(F25,5) -> EXXON | F25: EXXONMOBIL RICHMOND VA | G25: 23.27 | H25: Gasoline | I25: =VLOOKUP(H25,Expense_Lookup,2,0) -> Variable | J25: =J24+G25 -> 1474.24
A26: =YEAR(C26) -> 2021 | B26: =MONTH(C26) -> 1 | C26: 44208 | D26: 44208 | E26: =LEFT(F26,5) -> FAMIL | F26: FAMILY DOLLAR #5701 RICHMOND VA | G26: 3.33 | H26: Merchandise | I26: =VLOOKUP(H26,Expense_Lookup,2,0) -> Variable | J26: =J25+G26 -> 1477.57 | K26: Jayelin
A27: =YEAR(C27) -> 2021 | B27: =MONTH(C27) -> 1 | C27: 44208 | D27: 44208 | E27: =LEFT(F27,5) -> PAYPA | F27: PAYPAL *VIZMEDIALLC 888-221-1161 CA | G27: 1.99 | H27: APP | I27: =VLOOKUP(H27,Expense_Lookup,2,0) -> Fixed | J27: =J26+G27 -> 1479.56 | K27: Manga
A28: =YEAR(C28) -> 2021 | B28: =MONTH(C28) -> 1 | C28: 44211 | D28: 44211 | E28: =LEFT(F28,5) -> CASHB | F28: CASHBACK BONUS REDEMPTION PYMT/STMT CRDT | G28: -22.18 | H28: Awards and Rebate Credits | I28: =VLOOKUP(H28,Expense_Lookup,2,0) -> Payment | J28: =J27+G28 -> 1457.38
A29: =YEAR(C29) -> 2021 | B29: =MONTH(C29) -> 1 | C29: 44211 | D29: 44211 | E29: =LEFT(F29,5) -> DIREC | F29: DIRECTPAY FULL BALANCESEE DETAILS OF YOUR NEXT DIRECTPAY BELOW | G29: -728.15 | H29: Payments and Credits | I29: =VLOOKUP(H29,Expense_Lookup,2,0) -> Payment | J29: =J28+G29 -> 729.23
A30: =YEAR(C30) -> 2021 | B30: =MONTH(C30) -> 1 | C30: 44211 | D30: 44211 | E30: =LEFT(F30,5) -> INTER | F30: INTERNET PAYMENT - THANK YOU | G30: -729.23 | H30: Payments and Credits | I30: =VLOOKUP(H30,Expense_Lookup,2,0) -> Payment | J30: =J29+G30 -> 0
A31: =YEAR(C31) -> 2021 | B31: =MONTH(C31) -> 1 | C31: 44211 | D31: 44211 | E31: =LEFT(F31,5) -> MCDON | F31: MCDONALD'S F17579 RICHMOND VA | G31: 4.32 | H31: Restaurants | I31: =VLOOKUP(H31,Expense_Lookup,2,0) -> Variable | J31: =J30+G31 -> 4.32 | K31: Jayelin
A32: =YEAR(C32) -> 2021 | B32: =MONTH(C32) -> 1 | C32: 44211 | D32: 44211 | E32: =LEFT(F32,5) -> WALGR | F32: WALGREENS #3860 RICHMOND VA | G32: 21.19 | H32: Merchandise | I32: =VLOOKUP(H32,Expense_Lookup,2,0) -> Variable | J32: =J31+G32 -> 25.51 | K32: Draino
A33: =YEAR(C33) -> 2021 | B33: =MONTH(C33) -> 1 | C33: 44211 | D33: 44211 | E33: =LEFT(F33,5) -> WALMA | F33: WALMART SC 07032 HENRICO VA | G33: 19.4 | H33: Merchandise | I33: =VLOOKUP(H33,Expense_Lookup,2,0) -> Variable | J33: =J32+G33 -> 44.91 | K33: Study
A34: =YEAR(C34) -> 2021 | B34: =MONTH(C34) -> 1 | C34: 44212 | D34: 44212 | E34: =LEFT(F34,5) -> AMZN | F34: AMZN MKTP US*0H4DK7EL3 AMZN.COM/BILLWA72J9EGRQCDU | G34: 58.29 | H34: Merchandise | I34: =VLOOKUP(H34,Expense_Lookup,2,0) -> Variable | J34: =J33+G34 -> 103.2 | K34: Webcam
A35: =YEAR(C35) -> 2021 | B35: =MONTH(C35) -> 1 | C35: 44215 | D35: 44215 | E35: =LEFT(F35,5) -> CHIPO | F35: CHIPOTLE 1975 RICHMOND VA | G35: 8.23 | H35: Restaurants | I35: =VLOOKUP(H35,Expense_Lookup,2,0) -> Variable | J35: =J34+G35 -> 111.43
A36: =YEAR(C36) -> 2021 | B36: =MONTH(C36) -> 1 | C36: 44215 | D36: 44215 | E36: =LEFT(F36,5) -> CVS/P | F36: CVS/PHARMACY #01988 RICHMOND VA | G36: 2.86 | H36: Merchandise | I36: =VLOOKUP(H36,Expense_Lookup,2,0) -> Variable | J36: =J35+G36 -> 114.29 | K36: Jayelin
A37: =YEAR(C37) -> 2021 | B37: =MONTH(C37) -> 1 | C37: 44215 | D37: 44215 | E37: =LEFT(F37,5) -> SP * | F37: SP * ILF, LLC 8888044453 TX | G37: 99.9 | H37: Merchandise | I37: =VLOOKUP(H37,Expense_Lookup,2,0) -> Variable | J37: =J36+G37 -> 214.19
A38: =YEAR(C38) -> 2021 | B38: =MONTH(C38) -> 1 | C38: 44216 | D38: 44216 | E38: =LEFT(F38,5) -> THE M | F38: THE MARKET @ 25TH RICHMOND VA | G38: 15.15 | H38: Supermarkets | I38: =VLOOKUP(H38,Expense_Lookup,2,0) -> Variable | J38: =J37+G38 -> 229.34
A39: =YEAR(C39) -> 2021 | B39: =MONTH(C39) -> 1 | C39: 44217 | D39: 44217 | E39: =LEFT(F39,5) -> KINGS | F39: KINGSISLE *PIRATE101 512-623-5983 TX00099RS900000000000000 | G39: 9.95 | H39: APP | I39: =VLOOKUP(H39,Expense_Lookup,2,0) -> Fixed | J39: =J38+G39 -> 239.29 | K39: Jayelin
A40: =YEAR(C40) -> 2021 | B40: =MONTH(C40) -> 1 | C40: 44217 | D40: 44217 | E40: =LEFT(F40,5) -> PP*PP | F40: PP*PP ROKU FOR CRUNCHYR 402-935-7733 CA | G40: 7.99 | H40: APP | I40: =VLOOKUP(H40,Expense_Lookup,2,0) -> Fixed | J40: =J39+G40 -> 247.28 | K40: Crunchyroll
A41: =YEAR(C41) -> 2021 | B41: =MONTH(C41) -> 1 | C41: 44218 | D41: 44218 | E41: =LEFT(F41,5) -> THE M | F41: THE MARKET @ 25TH RICHMOND VA | G41: 15.61 | H41: Supermarkets | I41: =VLOOKUP(H41,Expense_Lookup,2,0) -> Variable | J41: =J40+G41 -> 262.89
A42: =YEAR(C42) -> 2021 | B42: =MONTH(C42) -> 1 | C42: 44219 | D42: 44219 | E42: =LEFT(F42,5) -> BEDBA | F42: BEDBATH&BEYOND GLEN ALLEN VA | G42: 84.43 | H42: Merchandise | I42: =VLOOKUP(H42,Expense_Lookup,2,0) -> Variable | J42: =J41+G42 -> 347.32 | K42: Griddle
A43: =YEAR(C43) -> 2021 | B43: =MONTH(C43) -> 1 | C43: 44219 | D43: 44219 | E43: =LEFT(F43,5) -> CITYP | F43: CITYPARKING INC 804-344-3353 VAAPPLE PAY ENDING IN 4775 | G43: 3.35 | H43: Services | I43: =VLOOKUP(H43,Expense_Lookup,2,0) -> Variable | J43: =J42+G43 -> 350.67 | K43: Akhil
A44: =YEAR(C44) -> 2021 | B44: =MONTH(C44) -> 1 | C44: 44219 | D44: 44219 | E44: =LEFT(F44,5) -> TST* | F44: TST* 521 BISCUITS & WAFF RICHMOND VAAPPLE PAY ENDING IN 4775 | G44: 14.68 | H44: Restaurants | I44: =VLOOKUP(H44,Expense_Lookup,2,0) -> Variable | J44: =J43+G44 -> 365.35 | K44: Kaiya
A45: =YEAR(C45) -> 2021 | B45: =MONTH(C45) -> 1 | C45: 44221 | D45: 44221 | E45: =LEFT(F45,5) -> EXXON | F45: EXXONMOBIL RICHMOND VA | G45: 2.76 | H45: Gasoline | I45: =VLOOKUP(H45,Expense_Lookup,2,0) -> Variable | J45: =J44+G45 -> 368.11
A46: =YEAR(C46) -> 2021 | B46: =MONTH(C46) -> 1 | C46: 44221 | D46: 44221 | E46: =LEFT(F46,5) -> EXXON | F46: EXXONMOBIL RICHMOND VA | G46: 22.97 | H46: Gasoline | I46: =VLOOKUP(H46,Expense_Lookup,2,0) -> Variable | J46: =J45+G46 -> 391.08
A47: =YEAR(C47) -> 2021 | B47: =MONTH(C47) -> 1 | C47: 44222 | D47: 44222 | E47: =LEFT(F47,5) -> CHIPO | F47: CHIPOTLE 1975 RICHMOND VA | G47: 8.23 | H47: Restaurants | I47: =VLOOKUP(H47,Expense_Lookup,2,0) -> Variable | J47: =J46+G47 -> 399.31
A48: =YEAR(C48) -> 2021 | B48: =MONTH(C48) -> 1 | C48: 44222 | D48: 44222 | E48: =LEFT(F48,5) -> WHOLE | F48: WHOLEFDS WBS#10598 RICHMOND VA | G48: 63.87 | H48: Supermarkets | I48: =VLOOKUP(H48,Expense_Lookup,2,0) -> Variable | J48: =J47+G48 -> 463.18
A49: =YEAR(C49) -> 2021 | B49: =MONTH(C49) -> 1 | C49: 44223 | D49: 44223 | E49: =LEFT(F49,5) -> CVS/P | F49: CVS/PHARMACY #01988 RICHMOND VA | G49: 1.51 | H49: Merchandise | I49: =VLOOKUP(H49,Expense_Lookup,2,0) -> Variable | J49: =J48+G49 -> 464.69 | K49: Jayelin
A50: =YEAR(C50) -> 2021 | B50: =MONTH(C50) -> 1 | C50: 44223 | D50: 44223 | E50: =LEFT(F50,5) -> CVS/P | F50: CVS/PHARMACY #01988 RICHMOND VA | G50: 2.24 | H50: Merchandise | I50: =VLOOKUP(H50,Expense_Lookup,2,0) -> Variable | J50: =J49+G50 -> 466.93 | K50: Jayelin
A51: =YEAR(C51) -> 2021 | B51: =MONTH(C51) -> 1 | C51: 44223 | D51: 44223 | E51: =LEFT(F51,5) -> PUBLI | F51: PUBLIX #1588 RICHMOND VA | G51: 4.75 | H51: Supermarkets | I51: =VLOOKUP(H51,Expense_Lookup,2,0) -> Variable | J51: =J50+G51 -> 471.68
A52: =YEAR(C52) -> 2021 | B52: =MONTH(C52) -> 1 | C52: 44224 | D52: 44224 | E52: =LEFT(F52,5) -> ABC*C | F52: ABC*CRUNCH FITNESS 888-827-9262 VAABC*CRUNCH FITNESS | G52: 9.95 | H52: APP | I52: =VLOOKUP(H52,Expense_Lookup,2,0) -> Fixed | J52: =J51+G52 -> 481.63 | K52: Crunch Fitness
A53: =YEAR(C53) -> 2021 | B53: =MONTH(C53) -> 1 | C53: 44226 | D53: 44226 | E53: =LEFT(F53,5) -> THE M | F53: THE MARKET @ 25TH RICHMOND VA | G53: 7.42 | H53: Supermarkets | I53: =VLOOKUP(H53,Expense_Lookup,2,0) -> Variable | J53: =J52+G53 -> 489.05 | K53: Jayelin
A54: =YEAR(C54) -> 2021 | B54: =MONTH(C54) -> 1 | C54: 44227 | D54: 44227 | E54: =LEFT(F54,5) -> DC CH | F54: DC CHARBROILED CHICKEN RICHMOND VA | G54: 9.89 | H54: Restaurants | I54: =VLOOKUP(H54,Expense_Lookup,2,0) -> Variable | J54: =J53+G54 -> 498.94 | K54: Jayelin
A55: =YEAR(C55) -> 2021 | B55: =MONTH(C55) -> 1 | C55: 44227 | D55: 44227 | E55: =LEFT(F55,5) -> WALMA | F55: WALMART SC 07032 HENRICO VA | G55: 19.22 | H55: Merchandise | I55: =VLOOKUP(H55,Expense_Lookup,2,0) -> Variable | J55: =J54+G55 -> 518.16
A56: =YEAR(C56) -> 2021 | B56: =MONTH(C56) -> 2 | C56: 44228 | D56: 44228 | E56: =LEFT(F56,5) -> NETFL | F56: NETFLIX.COM NETFLIX.COM CA44925167830 | G56: 13.99 | H56: APP | I56: =VLOOKUP(H56,Expense_Lookup,2,0) -> Fixed | J56: =J55+G56 -> 532.15 | K56: Netflix
A57: =YEAR(C57) -> 2021 | B57: =MONTH(C57) -> 2 | C57: 44228 | D57: 44228 | E57: =LEFT(F57,5) -> SPOTI | F57: SPOTIFY P1343F2886 8777781161 NY | G57: 9.99 | H57: APP | I57: =VLOOKUP(H57,Expense_Lookup,2,0) -> Fixed | J57: =J56+G57 -> 542.14 | K57: Spotify
A58: =YEAR(C58) -> 2021 | B58: =MONTH(C58) -> 2 | C58: 44228 | D58: 44230 | E58: =LEFT(F58,5) -> CVS/P | F58: CVS/PHARMACY #01988 RICHMOND VA | G58: 15.92 | H58: Merchandise | I58: =VLOOKUP(H58,Expense_Lookup,2,0) -> Variable | J58: =J57+G58 -> 558.06 | K58: Jayelin
A59: =YEAR(C59) -> 2021 | B59: =MONTH(C59) -> 2 | C59: 44229 | D59: 44230 | E59: =LEFT(F59,5) -> CVS/P | F59: CVS/PHARMACY #01988 RICHMOND VA | G59: 37.01 | H59: Merchandise | I59: =VLOOKUP(H59,Expense_Lookup,2,0) -> Variable | J59: =J58+G59 -> 595.07
A60: =YEAR(C60) -> 2021 | B60: =MONTH(C60) -> 2 | C60: 44229 | D60: 44230 | E60: =LEFT(F60,5) -> PAYPA | F60: PAYPAL *DAYNEINVEST 888-221-1161 CA | G60: 10 | H60: Merchandise | I60: =VLOOKUP(H60,Expense_Lookup,2,0) -> Variable | J60: =J59+G60 -> 605.07 | K60: Masks
A61: =YEAR(C61) -> 2021 | B61: =MONTH(C61) -> 2 | C61: 44230 | D61: 44230 | E61: =LEFT(F61,5) -> STATE | F61: STATE FARM INSURANCE 800-956-6310 IL | G61: 91.78 | H61: APP | I61: =VLOOKUP(H61,Expense_Lookup,2,0) -> Fixed | J61: =J60+G61 -> 696.85 | K61: State Farm
A62: =YEAR(C62) -> 2021 | B62: =MONTH(C62) -> 2 | C62: 44230 | D62: 44230 | E62: =LEFT(F62,5) -> THE M | F62: THE MARKET @ 25TH RICHMOND VA | G62: 15.09 | H62: Supermarkets | I62: =VLOOKUP(H62,Expense_Lookup,2,0) -> Variable | J62: =J61+G62 -> 711.94
A63: =YEAR(C63) -> 2021 | B63: =MONTH(C63) -> 2 | C63: 44232 | D63: 44232 | E63: =LEFT(F63,5) -> CVS/P | F63: CVS/PHARMACY #01988 RICHMOND VA | G63: 1.63 | H63: Merchandise | I63: =VLOOKUP(H63,Expense_Lookup,2,0) -> Variable | J63: =J62+G63 -> 713.57 | K63: Jayelin
A64: =YEAR(C64) -> 2021 | B64: =MONTH(C64) -> 2 | C64: 44232 | D64: 44232 | E64: =LEFT(F64,5) -> CVS/P | F64: CVS/PHARMACY #01988 RICHMOND VA | G64: 2.45 | H64: Merchandise | I64: =VLOOKUP(H64,Expense_Lookup,2,0) -> Variable | J64: =J63+G64 -> 716.02 | K64: Jayelin
A65: =YEAR(C65) -> 2021 | B65: =MONTH(C65) -> 2 | C65: 44234 | D65: 44234 | E65: =LEFT(F65,5) -> CHIPO | F65: CHIPOTLE 1975 RICHMOND VA | G65: 9.36 | H65: Restaurants | I65: =VLOOKUP(H65,Expense_Lookup,2,0) -> Variable | J65: =J64+G65 -> 725.38 | K65: Jayelin
A66: =YEAR(C66) -> 2021 | B66: =MONTH(C66) -> 2 | C66: 44237 | D66: 44237 | E66: =LEFT(F66,5) -> APPLE | F66: APPLE.COM/BILL 866-712-7753 CAAPPLE PAY ENDING IN 4775MMW42NJ145A0 | G66: 3.99 | H66: Merchandise | I66: =VLOOKUP(H66,Expense_Lookup,2,0) -> Variable | J66: =J65+G66 -> 729.37 | K66: Jayelin
A67: =YEAR(C67) -> 2021 | B67: =MONTH(C67) -> 2 | C67: 44237 | D67: 44237 | E67: =LEFT(F67,5) -> CVS/P | F67: CVS/PHARMACY #01988 RICHMOND VA | G67: 4.73 | H67: Merchandise | I67: =VLOOKUP(H67,Expense_Lookup,2,0) -> Variable | J67: =J66+G67 -> 734.1 | K67: Jayelin
A68: =YEAR(C68) -> 2021 | B68: =MONTH(C68) -> 2 | C68: 44238 | D68: 44238 | E68: =LEFT(F68,5) -> BIRD | F68: BIRD APP 8662052442 CA | G68: 5 | H68: Travel/ Entertainment | I68: =VLOOKUP(H68,Expense_Lookup,2,0) -> Variable | J68: =J67+G68 -> 739.1 | K68: Jayelin
A69: =YEAR(C69) -> 2021 | B69: =MONTH(C69) -> 2 | C69: 44238 | D69: 44238 | E69: =LEFT(F69,5) -> BIRD | F69: BIRD APP 8662052442 CA | G69: 5 | H69: Travel/ Entertainment | I69: =VLOOKUP(H69,Expense_Lookup,2,0) -> Variable | J69: =J68+G69 -> 744.1 | K69: Jayelin
A70: =YEAR(C70) -> 2021 | B70: =MONTH(C70) -> 2 | C70: 44238 | D70: 44238 | E70: =LEFT(F70,5) -> BIRD | F70: BIRD APP 8662052442 CA | G70: 5 | H70: Travel/ Entertainment | I70: =VLOOKUP(H70,Expense_Lookup,2,0) -> Variable | J70: =J69+G70 -> 749.1 | K70: Jayelin
A71: =YEAR(C71) -> 2021 | B71: =MONTH(C71) -> 2 | C71: 44239 | D71: 44239 | E71: =LEFT(F71,5) -> CASHB | F71: CASHBACK BONUS REDEMPTION PYMT/STMT CRDT | G71: -14 | H71: Awards and Rebate Credits | I71: =VLOOKUP(H71,Expense_Lookup,2,0) -> Payment | J71: =J70+G71 -> 735.1
A72: =YEAR(C72) -> 2021 | B72: =MONTH(C72) -> 2 | C72: 44239 | D72: 44239 | E72: =LEFT(F72,5) -> INTER | F72: INTERNET PAYMENT - THANK YOU | G72: -715.37 | H72: Payments and Credits | I72: =VLOOKUP(H72,Expense_Lookup,2,0) -> Payment | J72: =J71+G72 -> 19.73
A73: =YEAR(C73) -> 2021 | B73: =MONTH(C73) -> 2 | C73: 44239 | D73: 44239 | E73: =LEFT(F73,5) -> PAYPA | F73: PAYPAL *VIZMEDIALLC 888-221-1161 CA | G73: 1.99 | H73: APP | I73: =VLOOKUP(H73,Expense_Lookup,2,0) -> Fixed | J73: =J72+G73 -> 21.72 | K73: Manga
A74: =YEAR(C74) -> 2021 | B74: =MONTH(C74) -> 2 | C74: 44241 | D74: 44241 | E74: =LEFT(F74,5) -> APPLE | F74: APPLE.COM/BILL 866-712-7753 CAAPPLE PAY ENDING IN 4775MMW43JVXWTA0 | G74: 14.99 | H74: APP | I74: =VLOOKUP(H74,Expense_Lookup,2,0) -> Fixed | J74: =J73+G74 -> 36.71 | K74: HBO
A75: =YEAR(C75) -> 2021 | B75: =MONTH(C75) -> 2 | C75: 44241 | D75: 44241 | E75: =LEFT(F75,5) -> THE M | F75: THE MARKET @ 25TH RICHMOND VA | G75: 7.88 | H75: Supermarkets | I75: =VLOOKUP(H75,Expense_Lookup,2,0) -> Variable | J75: =J74+G75 -> 44.59
A76: =YEAR(C76) -> 2021 | B76: =MONTH(C76) -> 2 | C76: 44241 | D76: 44241 | E76: =LEFT(F76,5) -> WALMA | F76: WALMART SC 07032 HENRICO VA | G76: 48.58 | H76: Merchandise | I76: =VLOOKUP(H76,Expense_Lookup,2,0) -> Variable | J76: =J75+G76 -> 93.17
A77: =YEAR(C77) -> 2021 | B77: =MONTH(C77) -> 2 | C77: 44244 | D77: 44244 | E77: =LEFT(F77,5) -> TARGE | F77: TARGET RICHMOND VA | G77: 76.3 | H77: Merchandise | I77: =VLOOKUP(H77,Expense_Lookup,2,0) -> Variable | J77: =J76+G77 -> 169.47 | K77: Pants
A78: =YEAR(C78) -> 2021 | B78: =MONTH(C78) -> 2 | C78: 44246 | D78: 44246 | E78: =LEFT(F78,5) -> PUPAT | F78: PUPATELLA 2 RICHMOND VA | G78: 40.42 | H78: Restaurants | I78: =VLOOKUP(H78,Expense_Lookup,2,0) -> Variable | J78: =J77+G78 -> 209.89
A79: =YEAR(C79) -> 2021 | B79: =MONTH(C79) -> 2 | C79: 44247 | D79: 44247 | E79: =LEFT(F79,5) -> PUBLI | F79: PUBLIX #1588 RICHMOND VA | G79: 135.35 | H79: Supermarkets | I79: =VLOOKUP(H79,Expense_Lookup,2,0) -> Variable | J79: =J78+G79 -> 345.24
A80: =YEAR(C80) -> 2021 | B80: =MONTH(C80) -> 2 | C80: 44247 | D80: 44247 | E80: =LEFT(F80,5) -> T-MOB | F80: T-MOBILE PAYMENTS 800-937-8997 WAAPPLE PAY ENDING IN 4775T-MOBILE PAYMENTS | G80: 86.25 | H80: APP | I80: =VLOOKUP(H80,Expense_Lookup,2,0) -> Fixed | J80: =J79+G80 -> 431.49 | K80: T-Mobile
A81: =YEAR(C81) -> 2021 | B81: =MONTH(C81) -> 2 | C81: 44247 | D81: 44247 | E81: =LEFT(F81,5) -> THE M | F81: THE MARKET @ 25TH RICHMOND VA | G81: 10.64 | H81: Supermarkets | I81: =VLOOKUP(H81,Expense_Lookup,2,0) -> Variable | J81: =J80+G81 -> 442.13
A82: =YEAR(C82) -> 2021 | B82: =MONTH(C82) -> 2 | C82: 44247 | D82: 44247 | E82: =LEFT(F82,5) -> WWW.W | F82: WWW.WOLFRAMALPHA.COM 8009653726 IL | G82: 6.99 | H82: Merchandise | I82: =VLOOKUP(H82,Expense_Lookup,2,0) -> Variable | J82: =J81+G82 -> 449.12 | K82: Study tool
A83: =YEAR(C83) -> 2021 | B83: =MONTH(C83) -> 2 | C83: 44248 | D83: 44248 | E83: =LEFT(F83,5) -> CHIPO | F83: CHIPOTLE 1975 RICHMOND VA | G83: 8.23 | H83: Restaurants | I83: =VLOOKUP(H83,Expense_Lookup,2,0) -> Variable | J83: =J82+G83 -> 457.35 | K83: Jayelin
A84: =YEAR(C84) -> 2021 | B84: =MONTH(C84) -> 2 | C84: 44248 | D84: 44248 | E84: =LEFT(F84,5) -> KINGS | F84: KINGSISLE *PIRATE101 512-623-5983 TX0009CTVV00000000000000 | G84: 9.95 | H84: APP | I84: =VLOOKUP(H84,Expense_Lookup,2,0) -> Fixed | J84: =J83+G84 -> 467.3 | K84: Jayelin
A85: =YEAR(C85) -> 2021 | B85: =MONTH(C85) -> 2 | C85: 44248 | D85: 44248 | E85: =LEFT(F85,5) -> PP*PP | F85: PP*PP ROKU FOR CRUNCHYR 402-935-7733 CA | G85: 7.99 | H85: APP | I85: =VLOOKUP(H85,Expense_Lookup,2,0) -> Fixed | J85: =J84+G85 -> 475.29 | K85: Crunchyroll
A86: =YEAR(C86) -> 2021 | B86: =MONTH(C86) -> 2 | C86: 44248 | D86: 44248 | E86: =LEFT(F86,5) -> SUNOC | F86: SUNOCO 0113723100 RICHMOND VA | G86: 25.35 | H86: Gasoline | I86: =VLOOKUP(H86,Expense_Lookup,2,0) -> Variable | J86: =J85+G86 -> 500.64
A87: =YEAR(C87) -> 2021 | B87: =MONTH(C87) -> 2 | C87: 44248 | D87: 44248 | E87: =LEFT(F87,5) -> WALMA | F87: WALMART SC 07032 HENRICO VA | G87: 11.64 | H87: Merchandise | I87: =VLOOKUP(H87,Expense_Lookup,2,0) -> Variable | J87: =J86+G87 -> 512.28
A88: =YEAR(C88) -> 2021 | B88: =MONTH(C88) -> 2 | C88: 44248 | D88: 44248 | E88: =LEFT(F88,5) -> WALMA | F88: WALMART SC 07032 HENRICO VA | G88: 20.14 | H88: Merchandise | I88: =VLOOKUP(H88,Expense_Lookup,2,0) -> Variable | J88: =J87+G88 -> 532.42
A89: =YEAR(C89) -> 2021 | B89: =MONTH(C89) -> 2 | C89: 44248 | D89: 44248 | E89: =LEFT(F89,5) -> WALMA | F89: WALMART SC 07032 HENRICO VA | G89: 21.14 | H89: Merchandise | I89: =VLOOKUP(H89,Expense_Lookup,2,0) -> Variable | J89: =J88+G89 -> 553.56
A90: =YEAR(C90) -> 2021 | B90: =MONTH(C90) -> 2 | C90: 44250 | D90: 44250 | E90: =LEFT(F90,5) -> PAYPA | F90: PAYPAL *WEBULL TECH 402-935-7733 CA | G90: 1.99 | H90: APP | I90: =VLOOKUP(H90,Expense_Lookup,2,0) -> Fixed | J90: =J89+G90 -> 555.55 | K90: Webull
A91: =YEAR(C91) -> 2021 | B91: =MONTH(C91) -> 2 | C91: 44251 | D91: 44251 | E91: =LEFT(F91,5) -> COACH | F91: COACHING ACTUARIES 8324128532 IA | G91: 215 | H91: Education | I91: =VLOOKUP(H91,Expense_Lookup,2,0) -> Variable | J91: =J90+G91 -> 770.55 | K91: Adapt
A92: =YEAR(C92) -> 2021 | B92: =MONTH(C92) -> 2 | C92: 44253 | D92: 44253 | E92: =LEFT(F92,5) -> INTER | F92: INTERNET PAYMENT - THANK YOU | G92: -770.55 | H92: Payments and Credits | I92: =VLOOKUP(H92,Expense_Lookup,2,0) -> Payment | J92: =J91+G92 -> 0
A93: =YEAR(C93) -> 2021 | B93: =MONTH(C93) -> 2 | C93: 44253 | D93: 44253 | E93: =LEFT(F93,5) -> DISNE | F93: DISNEYPLUS 888-905-7888 CADISNEYPLUS | G93: 6.99 | H93: Merchandise | I93: =VLOOKUP(H93,Expense_Lookup,2,0) -> Variable | J93: =J92+G93 -> 6.99
A94: =YEAR(C94) -> 2021 | B94: =MONTH(C94) -> 2 | C94: 44253 | D94: 44253 | E94: =LEFT(F94,5) -> INTER | F94: INTERNET PAYMENT - THANK YOU | G94: -770.55 | H94: Payments and Credits | I94: =VLOOKUP(H94,Expense_Lookup,2,0) -> Payment | J94: =J93+G94 -> -763.56
A95: =YEAR(C95) -> 2021 | B95: =MONTH(C95) -> 2 | C95: 44253 | D95: 44253 | E95: =LEFT(F95,5) -> WALMA | F95: WALMART SC 07032 HENRICO VA | G95: 13.67 | H95: Merchandise | I95: =VLOOKUP(H95,Expense_Lookup,2,0) -> Variable | J95: =J94+G95 -> -749.89
A96: =YEAR(C96) -> 2021 | B96: =MONTH(C96) -> 2 | C96: 44254 | D96: 44254 | E96: =LEFT(F96,5) -> APPLE | F96: APPLE.COM/BILL 866-712-7753 CAAPPLE PAY ENDING IN 4775MMW4751VM2A0 | G96: 1.99 | H96: APP | I96: =VLOOKUP(H96,Expense_Lookup,2,0) -> Fixed | J96: =J95+G96 -> -747.9 | K96: Manga
A97: =YEAR(C97) -> 2021 | B97: =MONTH(C97) -> 2 | C97: 44254 | D97: 44254 | E97: =LEFT(F97,5) -> PAYPA | F97: PAYPAL *COUPLECENTS 402-935-7733 CA | G97: 9.99 | H97: APP | I97: =VLOOKUP(H97,Expense_Lookup,2,0) -> Fixed | J97: =J96+G97 -> -737.91 | K97: Couple Cents
A98: =YEAR(C98) -> 2021 | B98: =MONTH(C98) -> 2 | C98: 44254 | D98: 44254 | E98: =LEFT(F98,5) -> SHEET | F98: SHEETZ 267200026724498 WOODFORD VA | G98: 16.24 | H98: Gasoline | I98: =VLOOKUP(H98,Expense_Lookup,2,0) -> Variable | J98: =J97+G98 -> -721.67
A99: =YEAR(C99) -> 2021 | B99: =MONTH(C99) -> 2 | C99: 44254 | D99: 44254 | E99: =LEFT(F99,5) -> TACO | F99: TACO BELL #28942 DUMFRIES VA | G99: 11.54 | H99: Restaurants | I99: =VLOOKUP(H99,Expense_Lookup,2,0) -> Variable | J99: =J98+G99 -> -710.13
A100: =YEAR(C100) -> 2021 | B100: =MONTH(C100) -> 2 | C100: 44254 | D100: 44254 | E100: =LEFT(F100,5) -> WWW.C | F100: WWW.CVS.COM 800-746-7287 RI | G100: 5 | H100: Merchandise | I100: =VLOOKUP(H100,Expense_Lookup,2,0) -> Variable | J100: =J99+G100 -> -705.13
...

Sheet Cash Flow
C1: 1 | D1: 1 | E1: 1 | F1: 1 | G1: 1 | H1: 2 | I1: 2 | J1: 2 | K1: 2 | L1: 3 | M1: 3 | N1: 3 | O1: 3 | P1: 3 | Q1: 4 | R1: 4 | S1: 4 | T1: 4 | U1: 4 | V1: 5 | W1: 5 | X1: 5 | Y1: 5 | Z1: 5 | AA1: 6 | AB1: 6 | AC1: 6 | AD1: 6 | AE1: 6 | AF1: 7 | AG1: 7 | AH1: 7 | AI1: 7 | AJ1: 7 | AK1: 8 | AL1: 8 | AM1: 8 | AN1: 8 | AO1: 8 | AP1: 9 | AQ1: 9 | AR1: 9 | AS1: 9 | AT1: 9 | AU1: 10 | AV1: 10 | AW1: 10 | AX1: 10 | AY1: 10 | AZ1: 11 | BA1: 11 | BB1: 11 | BC1: 11 | BD1: 11 | BE1: 12 | BF1: 12 | BG1: 12 | BH1: 12 | BI1: 12
A2: Begin Balance | B2: 167.58 | C2: Jan | H2: Feb | L2: Mar | Q2: Apr | V2: May | AA2: Jun | AF2: Jul | AK2: Aug | AP2: Sep | AU2: Oct | AZ2: Nov | BE2: Dec
C3: 1 | D3: 8 | E3: 15 | F3: 22 | G3: 31 | H3: 5 | I3: 12 | J3: 19 | K3: 28 | L3: 5 | M3: 12 | N3: 19 | O3: 26 | P3: 31 | Q3: 2 | R3: 9 | S3: 16 | T3: 23 | U3: 30 | V3: 7 | W3: 14 | X3: 21 | Y3: 28 | Z3: 31 | AA3: 4 | AB3: 11 | AC3: 18 | AD3: 25 | AE3: 30 | AF3: 2 | AG3: 9 | AH3: 16 | AI3: 23 | AJ3: 30 | AK3: 6 | AL3: 13 | AM3: 20 | AN3: 27 | AO3: 31 | AP3: 3 | AQ3: 10 | AR3: 17 | AS3: 24 | AT3: 30 | AU3: 1 | AV3: 8 | AW3: 15 | AX3: 22 | AY3: 29 | AZ3: 5 | BA3: 12 | BB3: 19 | BC3: 26 | BD3: 30 | BE3: 3 | BF3: 10 | BG3: 17 | BH3: 24 | BI3: 31
A4: {=_xlfn._xlws.SORT(_xlfn.UNIQUE(_xlfn._xlws.FILTER('Wells Fargo'!G:G,('Wells Fargo'!G:G<>0)*('Wells Fargo'!G:G<>"Primary"))))} -> Amar - Electric | B4: =SUM(C4:BI4) -> -592.54 | C4: =SUMIFS('Wells Fargo'!$F:$F,'Wells Fargo'!$G:$G,'Cash Flow'!$A4,'Wells Fargo'!$A:$A,C$1,'Wells Fargo'!$B:$B,"<="&'Cash Flow'!C$3) -> 0 | D4: =SUMIFS('Wells Fargo'!$F:$F,'Wells Fargo'!$G:$G,'Cash Flow'!$A4,'Wells Fargo'!$A:$A,D$1,'Wells Fargo'!$B:$B,"<="&'Cash Flow'!D$3,'Wells Fargo'!$B:$B,">"&'Cash Flow'!C$3) -> 0 | E4: =SUMIFS('Wells Fargo'!$F:$F,'Wells Fargo'!$G:$G,'Cash Flow'!$A4,'Wells Fargo'!$A:$A,E$1,'Wells Fargo'!$B:$B,"<="&'Cash Flow'!E$3,'Wells Fargo'!$B:$B,">"&'Cash Flow'!D$3) -> 0 | F4: =SUMIFS('Wells Fargo'!$F:$F,'Wells Fargo'!$G:$G,'Cash Flow'!$A4,'Wells Fargo'!$A:$A,F$1,'Wells Fargo'!$B:$B,"<="&'Cash Flow'!F$3,'Wells Fargo'!$B:$B,">"&'Cash Flow'!E$3) -> -78.86 | G4: =SUMIFS('Wells Fargo'!$F:$F,'Wells Fargo'!$G:$G,'Cash Flow'!$A4,'Wells Fargo'!$A:$A,G$1,'Wells Fargo'!$B:$B,"<="&'Cash Flow'!G$3,'Wells Fargo'!$B:$B,">"&'Cash Flow'!F$3) -> 0 | H4: =SUMIFS('Wells Fargo'!$F:$F,'Wells Fargo'!$G:$G,'Cash Flow'!$A4,'Wells Fargo'!$A:$A,H$1,'Wells Fargo'!$B:$B,"<="&'Cash Flow'!H$3) -> 0 | I4: =SUMIFS('Wells Fargo'!$F:$F,'Wells Fargo'!$G:$G,'Cash Flow'!$A4,'Wells Fargo'!$A:$A,I$1,'Wells Fargo'!$B:$B,"<="&'Cash Flow'!I$3,'Wells Fargo'!$B:$B,">"&'Cash Flow'!H$3) -> 0 | J4: =SUMIFS('Wells Fargo'!$F:$F,'Wells Fargo'!$G:$G,'Cash Flow'!$A4,'Wells Fargo'!$A:$A,J$1,'Wells Fargo'!$B:$B,"<="&'Cash Flow'!J$3,'Wells Fargo'!$B:$B,">"&'Cash Flow'!I$3) -> 0 | K4: =SUMIFS('Wells Fargo'!$F:$F,'Wells Fargo'!$G:$G,'Cash Flow'!$A4,'Wells Fargo'!$A:$A,K$1,'Wells Fargo'!$B:$B,"<="&'Cash Flow'!K$3,'Wells Fargo'!$B:$B,">"&'Cash Flow'!J$3) -> -81.32 | L4: =SUMIFS('Wells Fargo'!$F:$F,'Wells Fargo'!$G:$G,'Cash Flow'!$A4,'Wells Fargo'!$A:$A,L$1,'Wells Fargo'!$B:$B,"<="&'Cash Flow'!L$3) -> 0 | M4: =SUMIFS('Wells Fargo'!$F:$F,'Wells Fargo'!$G:$G,'Cash Flow'!$A4,'Wells Fargo'!$A:$A,M$1,'Wells Fargo'!$B:$B,"<="&'Cash Flow'!M$3,'Wells Fargo'!$B:$B,">"&'Cash Flow'!L$3) -> 0 | N4: =SUMIFS('Wells Fargo'!$F:$F,'Wells Fargo'!$G:$G,'Cash Flow'!$A4,'Wells Fargo'!$A:$A,N$1,'Wells Fargo'!$B:$B,"<="&'Cash Flow'!N$3,'Wells Fargo'!$B:$B,">"&'Cash Flow'!M$3) -> -39.7 | O4: =SUMIFS('Wells Fargo'!$F:$F,'Wells Fargo'!$G:$G,'Cash Flow'!$A4,'Wells Fargo'!$A:$A,O$1,'Wells Fargo'!$B:$B,"<="&'Cash Flow'!O$3,'Wells Fargo'!$B:$B,">"&'Cash Flow'!N$3) -> 0 | P4: =SUMIFS('Wells Fargo'!$F:$F,'Wells Fargo'!$G:$G,'Cash Flow'!$A4,'Wells Fargo'!$A:$A,P$1,'Wells Fargo'!$B:$B,"<="&'Cash Flow'!P$3,'Wells Fargo'!$B:$B,">"&'Cash Flow'!O$3) -> 0 | Q4: =SUMIFS('Wells Fargo'!$F:$F,'Wells Fargo'!$G:$G,'Cash Flow'!$A4,'Wells Fargo'!$A:$A,Q$1,'Wells Fargo'!$B:$B,"<="&'Cash Flow'!Q$3) -> 0 | R4: =SUMIFS('Wells Fargo'!$F:$F,'Wells Fargo'!$G:$G,'Cash Flow'!$A4,'Wells Fargo'!$A:$A,R$1,'Wells Fargo'!$B:$B,"<="&'Cash Flow'!R$3,'Wells Fargo'!$B:$B,">"&'Cash Flow'!Q$3) -> 0 | S4: =SUMIFS('Wells Fargo'!$F:$F,'Wells Fargo'!$G:$G,'Cash Flow'!$A4,'Wells Fargo'!$A:$A,S$1,'Wells Fargo'!$B:$B,"<="&'Cash Flow'!S$3,'Wells Fargo'!$B:$B,">"&'Cash Flow'!R$3) -> -138.52 | T4: =SUMIFS('Wells Fargo'!$F:$F,'Wells Fargo'!$G:$G,'Cash Flow'!$A4,'Wells Fargo'!$A:$A,T$1,'Wells Fargo'!$B:$B,"<="&'Cash Flow'!T$3,'Wells Fargo'!$B:$B,">"&'Cash Flow'!S$3) -> 0 | U4: =SUMIFS('Wells Fargo'!$F:$F,'Wells Fargo'!$G:$G,'Cash Flow'!$A4,'Wells Fargo'!$A:$A,U$1,'Wells Fargo'!$B:$B,"<="&'Cash Flow'!U$3,'Wells Fargo'!$B:$B,">"&'Cash Flow'!T$3) -> 0 | V4: =SUMIFS('Wells Fargo'!$F:$F,'Wells Fargo'!$G:$G,'Cash Flow'!$A4,'Wells Fargo'!$A:$A,V$1,'Wells Fargo'!$B:$B,"<="&'Cash Flow'!V$3) -> 0 | W4: =SUMIFS('Wells Fargo'!$F:$F,'Wells Fargo'!$G:$G,'Cash Flow'!$A4,'Wells Fargo'!$A:$A,W$1,'Wells Fargo'!$B:$B,"<="&'Cash Flow'!W$3,'Wells Fargo'!$B:$B,">"&'Cash Flow'!V$3) -> -136.14 | X4: =SUMIFS('Wells Fargo'!$F:$F,'Wells Fargo'!$G:$G,'Cash Flow'!$A4,'Wells Fargo'!$A:$A,X$1,'Wells Fargo'!$B:$B,"<="&'Cash Flow'!X$3,'Wells Fargo'!$B:$B,">"&'Cash Flow'!W$3) -> 0 | Y4: =SUMIFS('Wells Fargo'!$F:$F,'Wells Fargo'!$G:$G,'Cash Flow'!$A4,'Wells Fargo'!$A:$A,Y$1,'Wells Fargo'!$B:$B,"<="&'Cash Flow'!Y$3,'Wells Fargo'!$B:$B,">"&'Cash Flow'!X$3) -> 0 | Z4: =SUMIFS('Wells Fargo'!$F:$F,'Wells Fargo'!$G:$G,'Cash Flow'!$A4,'Wells Fargo'!$A:$A,Z$1,'Wells Fargo'!$B:$B,"<="&'Cash Flow'!Z$3,'Wells Fargo'!$B:$B,">"&'Cash Flow'!Y$3) -> 0 | AA4: =SUMIFS('Wells Fargo'!$F:$F,'Wells Fargo'!$G:$G,'Cash Flow'!$A4,'Wells Fargo'!$A:$A,AA$1,'Wells Fargo'!$B:$B,"<="&'Cash Flow'!AA$3) -> -118 | AB4: =SUMIFS('Wells Fargo'!$F:$F,'Wells Fargo'!$G:$G,'Cash Flow'!$A4,'Wells Fargo'!$A:$A,AB$1,'Wells Fargo'!$B:$B,"<="&'Cash Flow'!AB$3,'Wells Fargo'!$B:$B,">"&'Cash Flow'!AA$3) -> 0 | AC4: =SUMIFS('Wells Fargo'!$F:$F,'Wells Fargo'!$G:$G,'Cash Flow'!$A4,'Wells Fargo'!$A:$A,AC$1,'Wells Fargo'!$B:$B,"<="&'Cash Flow'!AC$3,'Wells Fargo'!$B:$B,">"&'Cash Flow'!AB$3) -> 0 | AD4: =SUMIFS('Wells Fargo'!$F:$F,'Wells Fargo'!$G:$G,'Cash Flow'!$A4,'Wells Fargo'!$A:$A,AD$1,'Wells Fargo'!$B:$B,"<="&'Cash Flow'!AD$3,'Wells Fargo'!$B:$B,">"&'Cash Flow'!AC$3) -> 0 | AE4: =SUMIFS('Wells Fargo'!$F:$F,'Wells Fargo'!$G:$G,'Cash Flow'!$A4,'Wells Fargo'!$A:$A,AE$1,'Wells Fargo'!$B:$B,"<="&'Cash Flow'!AE$3,'Wells Fargo'!$B:$B,">"&'Cash Flow'!AD$3) -> 0 | AF4: =SUMIFS('Wells Fargo'!$F:$F,'Wells Fargo'!$G:$G,'Cash Flow'!$A4,'Wells Fargo'!$A:$A,AF$1,'Wells Fargo'!$B:$B,"<="&'Cash Flow'!AF$3) -> 0 | AG4: =SUMIFS('Wells Fargo'!$F:$F,'Wells Fargo'!$G:$G,'Cash Flow'!$A4,'Wells Fargo'!$A:$A,AG$1,'Wells Fargo'!$B:$B,"<="&'Cash Flow'!AG$3,'Wells Fargo'!$B:$B,">"&'Cash Flow'!AF$3) -> 0 | AH4: =SUMIFS('Wells Fargo'!$F:$F,'Wells Fargo'!$G:$G,'Cash Flow'!$A4,'Wells Fargo'!$A:$A,AH$1,'Wells Fargo'!$B:$B,"<="&'Cash Flow'!AH$3,'Wells Fargo'!$B:$B,">"&'Cash Flow'!AG$3) -> 0 | AI4: =SUMIFS('Wells Fargo'!$F:$F,'Wells Fargo'!$G:$G,'Cash Flow'!$A4,'Wells Fargo'!$A:$A,AI$1,'Wells Fargo'!$B:$B,"<="&'Cash Flow'!AI$3,'Wells Fargo'!$B:$B,">"&'Cash Flow'!AH$3) -> 0 | AJ4: =SUMIFS('Wells Fargo'!$F:$F,'Wells Fargo'!$G:$G,'Cash Flow'!$A4,'Wells Fargo'!$A:$A,AJ$1,'Wells Fargo'!$B:$B,"<="&'Cash Flow'!AJ$3,'Wells Fargo'!$B:$B,">"&'Cash Flow'!AI$3) -> 0 | AK4: =SUMIFS('Wells Fargo'!$F:$F,'Wells Fargo'!$G:$G,'Cash Flow'!$A4,'Wells Fargo'!$A:$A,AK$1,'Wells Fargo'!$B:$B,"<="&'Cash Flow'!AK$3) -> 0 | AL4: =SUMIFS('Wells Fargo'!$F:$F,'Wells Fargo'!$G:$G,'Cash Flow'!$A4,'Wells Fargo'!$A:$A,AL$1,'Wells Fargo'!$B:$B,"<="&'Cash Flow'!AL$3,'Wells Fargo'!$B:$B,">"&'Cash Flow'!AK$3) -> 0 | AM4: =SUMIFS('Wells Fargo'!$F:$F,'Wells Fargo'!$G:$G,'Cash Flow'!$A4,'Wells Fargo'!$A:$A,AM$1,'Wells Fargo'!$B:$B,"<="&'Cash Flow'!AM$3,'Wells Fargo'!$B:$B,">"&'Cash Flow'!AL$3) -> 0 | AN4: =SUMIFS('Wells Fargo'!$F:$F,'Wells Fargo'!$G:$G,'Cash Flow'!$A4,'Wells Fargo'!$A:$A,AN$1,'Wells Fargo'!$B:$B,"<="&'Cash Flow'!AN$3,'Wells Fargo'!$B:$B,">"&'Cash Flow'!AM$3) -> 0 | AO4: =SUMIFS('Wells Fargo'!$F:$F,'Wells Fargo'!$G:$G,'Cash Flow'!$A4,'Wells Fargo'!$A:$A,AO$1,'Wells Fargo'!$B:$B,"<="&'Cash Flow'!AO$3,'Wells Fargo'!$B:$B,">"&'Cash Flow'!AN$3) -> 0 | AP4: =SUMIFS('Wells Fargo'!$F:$F,'Wells Fargo'!$G:$G,'Cash Flow'!$A4,'Wells Fargo'!$A:$A,AP$1,'Wells Fargo'!$B:$B,"<="&'Cash Flow'!AP$3) -> 0 | AQ4: =SUMIFS('Wells Fargo'!$F:$F,'Wells Fargo'!$G:$G,'Cash Flow'!$A4,'Wells Fargo'!$A:$A,AQ$1,'Wells Fargo'!$B:$B,"<="&'Cash Flow'!AQ$3,'Wells Fargo'!$B:$B,">"&'Cash Flow'!AP$3) -> 0 | AR4: =SUMIFS('Wells Fargo'!$F:$F,'Wells Fargo'!$G:$G,'Cash Flow'!$A4,'Wells Fargo'!$A:$A,AR$1,'Wells Fargo'!$B:$B,"<="&'Cash Flow'!AR$3,'Wells Fargo'!$B:$B,">"&'Cash Flow'!AQ$3) -> 0 | AS4: =SUMIFS('Wells Fargo'!$F:$F,'Wells Fargo'!$G:$G,'Cash Flow'!$A4,'Wells Fargo'!$A:$A,AS$1,'Wells Fargo'!$B:$B,"<="&'Cash Flow'!AS$3,'Wells Fargo'!$B:$B,">"&'Cash Flow'!AR$3) -> 0 | AT4: =SUMIFS('Wells Fargo'!$F:$F,'Wells Fargo'!$G:$G,'Cash Flow'!$A4,'Wells Fargo'!$A:$A,AT$1,'Wells Fargo'!$B:$B,"<="&'Cash Flow'!AT$3,'Wells Fargo'!$B:$B,">"&'Cash Flow'!AS$3) -> 0 | AU4: =SUMIFS('Wells Fargo'!$F:$F,'Wells Fargo'!$G:$G,'Cash Flow'!$A4,'Wells Fargo'!$A:$A,AU$1,'Wells Fargo'!$B:$B,"<="&'Cash Flow'!AU$3) -> 0 | AV4: =SUMIFS('Wells Fargo'!$F:$F,'Wells Fargo'!$G:$G,'Cash Flow'!$A4,'Wells Fargo'!$A:$A,AV$1,'Wells Fargo'!$B:$B,"<="&'Cash Flow'!AV$3,'Wells Fargo'!$B:$B,">"&'Cash Flow'!AU$3) -> 0 | AW4: =SUMIFS('Wells Fargo'!$F:$F,'Wells Fargo'!$G:$G,'Cash Flow'!$A4,'Wells Fargo'!$A:$A,AW$1,'Wells Fargo'!$B:$B,"<="&'Cash Flow'!AW$3,'Wells Fargo'!$B:$B,">"&'Cash Flow'!AV$3) -> 0 | AX4: =SUMIFS('Wells Fargo'!$F:$F,'Wells Fargo'!$G:$G,'Cash Flow'!$A4,'Wells Fargo'!$A:$A,AX$1,'Wells Fargo'!$B:$B,"<="&'Cash Flow'!AX$3,'Wells Fargo'!$B:$B,">"&'Cash Flow'!AW$3) -> 0 | AY4: =SUMIFS('Wells Fargo'!$F:$F,'Wells Fargo'!$G:$G,'Cash Flow'!$A4,'Wells Fargo'!$A:$A,AY$1,'Wells Fargo'!$B:$B,"<="&'Cash Flow'!AY$3,'Wells Fargo'!$B:$B,">"&'Cash Flow'!AX$3) -> 0 | AZ4: =SUMIFS('Wells Fargo'!$F:$F,'Wells Fargo'!$G:$G,'Cash Flow'!$A4,'Wells Fargo'!$A:$A,AZ$1,'Wells Fargo'!$B:$B,"<="&'Cash Flow'!AZ$3) -> 0 | BA4: =SUMIFS('Wells Fargo'!$F:$F,'Wells Fargo'!$G:$G,'Cash Flow'!$A4,'Wells Fargo'!$A:$A,BA$1,'Wells Fargo'!$B:$B,"<="&'Cash Flow'!BA$3,'Wells Fargo'!$B:$B,">"&'Cash Flow'!AZ$3) -> 0 | BB4: =SUMIFS('Wells Fargo'!$F:$F,'Wells Fargo'!$G:$G,'Cash Flow'!$A4,'Wells Fargo'!$A:$A,BB$1,'Wells Fargo'!$B:$B,"<="&'Cash Flow'!BB$3,'Wells Fargo'!$B:$B,">"&'Cash Flow'!BA$3) -> 0 | BC4: =SUMIFS('Wells Fargo'!$F:$F,'Wells Fargo'!$G:$G,'Cash Flow'!$A4,'Wells Fargo'!$A:$A,BC$1,'Wells Fargo'!$B:$B,"<="&'Cash Flow'!BC$3,'Wells Fargo'!$B:$B,">"&'Cash Flow'!BB$3) -> 0 | BD4: =SUMIFS('Wells Fargo'!$F:$F,'Wells Fargo'!$G:$G,'Cash Flow'!$A4,'Wells Fargo'!$A:$A,BD$1,'Wells Fargo'!$B:$B,"<="&'Cash Flow'!BD$3,'Wells Fargo'!$B:$B,">"&'Cash Flow'!BC$3) -> 0 | BE4: =SUMIFS('Wells Fargo'!$F:$F,'Wells Fargo'!$G:$G,'Cash Flow'!$A4,'Wells Fargo'!$A:$A,BE$1,'Wells Fargo'!$B:$B,"<="&'Cash Flow'!BE$3) -> 0 | BF4: =SUMIFS('Wells Fargo'!$F:$F,'Wells Fargo'!$G:$G,'Cash Flow'!$A4,'Wells Fargo'!$A:$A,BF$1,'Wells Fargo'!$B:$B,"<="&'Cash Flow'!BF$3,'Wells Fargo'!$B:$B,">"&'Cash Flow'!BE$3) -> 0 | BG4: =SUMIFS('Wells Fargo'!$F:$F,'Wells Fargo'!$G:$G,'Cash Flow'!$A4,'Wells Fargo'!$A:$A,BG$1,'Wells Fargo'!$B:$B,"<="&'Cash Flow'!BG$3,'Wells Fargo'!$B:$B,">"&'Cash Flow'!BF$3) -> 0 | BH4: =SUMIFS('Wells Fargo'!$F:$F,'Wells Fargo'!$G:$G,'Cash Flow'!$A4,'Wells Fargo'!$A:$A,BH$1,'Wells Fargo'!$B:$B,"<="&'Cash Flow'!BH$3,'Wells Fargo'!$B:$B,">"&'Cash Flow'!BG$3) -> 0 | BI4: =SUMIFS('Wells Fargo'!$F:$F,'Wells Fargo'!$G:$G,'Cash Flow'!$A4,'Wells Fargo'!$A:$A,BI$1,'Wells Fargo'!$B:$B,"<="&'Cash Flow'!BI$3,'Wells Fargo'!$B:$B,">"&'Cash Flow'!BH$3) -> 0
A5: Amar - Rent | B5: =SUM(C5:BI5) -> -2800 | C5: =SUMIFS('Wells Fargo'!$F:$F,'Wells Fargo'!$G:$G,'Cash Flow'!$A5,'Wells Fargo'!$A:$A,C$1,'Wells Fargo'!$B:$B,"<="&'Cash Flow'!C$3) -> 0 | D5: =SUMIFS('Wells Fargo'!$F:$F,'Wells Fargo'!$G:$G,'Cash Flow'!$A5,'Wells Fargo'!$A:$A,D$1,'Wells Fargo'!$B:$B,"<="&'Cash Flow'!D$3,'Wells Fargo'!$B:$B,">"&'Cash Flow'!C$3) -> 0 | E5: =SUMIFS('Wells Fargo'!$F:$F,'Wells Fargo'!$G:$G,'Cash Flow'!$A5,'Wells Fargo'!$A:$A,E$1,'Wells Fargo'!$B:$B,"<="&'Cash Flow'!E$3,'Wells Fargo'!$B:$B,">"&'Cash Flow'!D$3) -> 0 | F5: =SUMIFS('Wells Fargo'!$F:$F,'Wells Fargo'!$G:$G,'Cash Flow'!$A5,'Wells Fargo'!$A:$A,F$1,'Wells Fargo'!$B:$B,"<="&'Cash Flow'!F$3,'Wells Fargo'!$B:$B,">"&'Cash Flow'!E$3) -> 0 | G5: =SUMIFS('Wells Fargo'!$F:$F,'Wells Fargo'!$G:$G,'Cash Flow'!$A5,'Wells Fargo'!$A:$A,G$1,'Wells Fargo'!$B:$B,"<="&'Cash Flow'!G$3,'Wells Fargo'!$B:$B,">"&'Cash Flow'!F$3) -> -700 | H5: =SUMIFS('Wells Fargo'!$F:$F,'Wells Fargo'!$G:$G,'Cash Flow'!$A5,'Wells Fargo'!$A:$A,H$1,'Wells Fargo'!$B:$B,"<="&'Cash Flow'!H$3) -> 0 | I5: =SUMIFS('Wells Fargo'!$F:$F,'Wells Fargo'!$G:$G,'Cash Flow'!$A5,'Wells Fargo'!$A:$A,I$1,'Wells Fargo'!$B:$B,"<="&'Cash Flow'!I$3,'Wells Fargo'!$B:$B,">"&'Cash Flow'!H$3) -> 0 | J5: =SUMIFS('Wells Fargo'!$F:$F,'Wells Fargo'!$G:$G,'Cash Flow'!$A5,'Wells Fargo'!$A:$A,J$1,'Wells Fargo'!$B:$B,"<="&'Cash Flow'!J$3,'Wells Fargo'!$B:$B,">"&'Cash Flow'!I$3) -> 0 | K5: =SUMIFS('Wells Fargo'!$F:$F,'Wells Fargo'!$G:$G,'Cash Flow'!$A5,'Wells Fargo'!$A:$A,K$1,'Wells Fargo'!$B:$B,"<="&'Cash Flow'!K$3,'Wells Fargo'!$B:$B,">"&'Cash Flow'!J$3) -> -700 | L5: =SUMIFS('Wells Fargo'!$F:$F,'Wells Fargo'!$G:$G,'Cash Flow'!$A5,'Wells Fargo'!$A:$A,L$1,'Wells Fargo'!$B:$B,"<="&'Cash Flow'!L$3) -> 0 | M5: =SUMIFS('Wells Fargo'!$F:$F,'Wells Fargo'!$G:$G,'Cash Flow'!$A5,'Wells Fargo'!$A:$A,M$1,'Wells Fargo'!$B:$B,"<="&'Cash Flow'!M$3,'Wells Fargo'!$B:$B,">"&'Cash Flow'!L$3) -> 0 | N5: =SUMIFS('Wells Fargo'!$F:$F,'Wells Fargo'!$G:$G,'Cash Flow'!$A5,'Wells Fargo'!$A:$A,N$1,'Wells Fargo'!$B:$B,"<="&'Cash Flow'!N$3,'Wells Fargo'!$B:$B,">"&'Cash Flow'!M$3) -> -700 | O5: =SUMIFS('Wells Fargo'!$F:$F,'Wells Fargo'!$G:$G,'Cash Flow'!$A5,'Wells Fargo'!$A:$A,O$1,'Wells Fargo'!$B:$B,"<="&'Cash Flow'!O$3,'Wells Fargo'!$B:$B,">"&'Cash Flow'!N$3) -> 0 | P5: =SUMIFS('Wells Fargo'!$F:$F,'Wells Fargo'!$G:$G,'Cash Flow'!$A5,'Wells Fargo'!$A:$A,P$1,'Wells Fargo'!$B:$B,"<="&'Cash Flow'!P$3,'Wells Fargo'!$B:$B,">"&'Cash Flow'!O$3) -> 0 | Q5: =SUMIFS('Wells Fargo'!$F:$F,'Wells Fargo'!$G:$G,'Cash Flow'!$A5,'Wells Fargo'!$A:$A,Q$1,'Wells Fargo'!$B:$B,"<="&'Cash Flow'!Q$3) -> 0 | R5: =SUMIFS('Wells Fargo'!$F:$F,'Wells Fargo'!$G:$G,'Cash Flow'!$A5,'Wells Fargo'!$A:$A,R$1,'Wells Fargo'!$B:$B,"<="&'Cash Flow'!R$3,'Wells Fargo'!$B:$B,">"&'Cash Flow'!Q$3) -> 0 | S5: =SUMIFS('Wells Fargo'!$F:$F,'Wells Fargo'!$G:$G,'Cash Flow'!$A5,'Wells Fargo'!$A:$A,S$1,'Wells Fargo'!$B:$B,"<="&'Cash Flow'!S$3,'Wells Fargo'!$B:$B,">"&'Cash Flow'!R$3) -> 0 | T5: =SUMIFS('Wells Fargo'!$F:$F,'Wells Fargo'!$G:$G,'Cash Flow'!$A5,'Wells Fargo'!$A:$A,T$1,'Wells Fargo'!$B:$B,"<="&'Cash Flow'!T$3,'Wells Fargo'!$B:$B,">"&'Cash Flow'!S$3) -> -700 | U5: =SUMIFS('Wells Fargo'!$F:$F,'Wells Fargo'!$G:$G,'Cash Flow'!$A5,'Wells Fargo'!$A:$A,U$1,'Wells Fargo'!$B:$B,"<="&'Cash Flow'!U$3,'Wells Fargo'!$B:$B,">"&'Cash Flow'!T$3) -> 0 | V5: =SUMIFS('Wells Fargo'!$F:$F,'Wells Fargo'!$G:$G,'Cash Flow'!$A5,'Wells Fargo'!$A:$A,V$1,'Wells Fargo'!$B:$B,"<="&'Cash Flow'!V$3) -> 0 | W5: =SUMIFS('Wells Fargo'!$F:$F,'Wells Fargo'!$G:$G,'Cash Flow'!$A5,'Wells Fargo'!$A:$A,W$1,'Wells Fargo'!$B:$B,"<="&'Cash Flow'!W$3,'Wells Fargo'!$B:$B,">"&'Cash Flow'!V$3) -> 0 | X5: =SUMIFS('Wells Fargo'!$F:$F,'Wells Fargo'!$G:$G,'Cash Flow'!$A5,'Wells Fargo'!$A:$A,X$1,'Wells Fargo'!$B:$B,"<="&'Cash Flow'!X$3,'Wells Fargo'!$B:$B,">"&'Cash Flow'!W$3) -> 0 | Y5: =SUMIFS('Wells Fargo'!$F:$F,'Wells Fargo'!$G:$G,'Cash Flow'!$A5,'Wells Fargo'!$A:$A,Y$1,'Wells Fargo'!$B:$B,"<="&'Cash Flow'!Y$3,'Wells Fargo'!$B:$B,">"&'Cash Flow'!X$3) -> 0 | Z5: =SUMIFS('Wells Fargo'!$F:$F,'Wells Fargo'!$G:$G,'Cash Flow'!$A5,'Wells Fargo'!$A:$A,Z$1,'Wells Fargo'!$B:$B,"<="&'Cash Flow'!Z$3,'Wells Fargo'!$B:$B,">"&'Cash Flow'!Y$3) -> 0 | AA5: =SUMIFS('Wells Fargo'!$F:$F,'Wells Fargo'!$G:$G,'Cash Flow'!$A5,'Wells Fargo'!$A:$A,AA$1,'Wells Fargo'!$B:$B,"<="&'Cash Flow'!AA$3) -> 0 | AB5: =SUMIFS('Wells Fargo'!$F:$F,'Wells Fargo'!$G:$G,'Cash Flow'!$A5,'Wells Fargo'!$A:$A,AB$1,'Wells Fargo'!$B:$B,"<="&'Cash Flow'!AB$3,'Wells Fargo'!$B:$B,">"&'Cash Flow'!AA$3) -> 0 | AC5: =SUMIFS('Wells Fargo'!$F:$F,'Wells Fargo'!$G:$G,'Cash Flow'!$A5,'Wells Fargo'!$A:$A,AC$1,'Wells Fargo'!$B:$B,"<="&'Cash Flow'!AC$3,'Wells Fargo'!$B:$B,">"&'Cash Flow'!AB$3) -> 0 | AD5: =SUMIFS('Wells Fargo'!$F:$F,'Wells Fargo'!$G:$G,'Cash Flow'!$A5,'Wells Fargo'!$A:$A,AD$1,'Wells Fargo'!$B:$B,"<="&'Cash Flow'!AD$3,'Wells Fargo'!$B:$B,">"&'Cash Flow'!AC$3) -> 0 | AE5: =SUMIFS('Wells Fargo'!$F:$F,'Wells Fargo'!$G:$G,'Cash Flow'!$A5,'Wells Fargo'!$A:$A,AE$1,'Wells Fargo'!$B:$B,"<="&'Cash Flow'!AE$3,'Wells Fargo'!$B:$B,">"&'Cash Flow'!AD$3) -> 0 | AF5: =SUMIFS('Wells Fargo'!$F:$F,'Wells Fargo'!$G:$G,'Cash Flow'!$A5,'Wells Fargo'!$A:$A,AF$1,'Wells Fargo'!$B:$B,"<="&'Cash Flow'!AF$3) -> 0 | AG5: =SUMIFS('Wells Fargo'!$F:$F,'Wells Fargo'!$G:$G,'Cash Flow'!$A5,'Wells Fargo'!$A:$A,AG$1,'Wells Fargo'!$B:$B,"<="&'Cash Flow'!AG$3,'Wells Fargo'!$B:$B,">"&'Cash Flow'!AF$3) -> 0 | AH5: =SUMIFS('Wells Fargo'!$F:$F,'Wells Fargo'!$G:$G,'Cash Flow'!$A5,'Wells Fargo'!$A:$A,AH$1,'Wells Fargo'!$B:$B,"<="&'Cash Flow'!AH$3,'Wells Fargo'!$B:$B,">"&'Cash Flow'!AG$3) -> 0 | AI5: =SUMIFS('Wells Fargo'!$F:$F,'Wells Fargo'!$G:$G,'Cash Flow'!$A5,'Wells Fargo'!$A:$A,AI$1,'Wells Fargo'!$B:$B,"<="&'Cash Flow'!AI$3,'Wells Fargo'!$B:$B,">"&'Cash Flow'!AH$3) -> 0 | AJ5: =SUMIFS('Wells Fargo'!$F:$F,'Wells Fargo'!$G:$G,'Cash Flow'!$A5,'Wells Fargo'!$A:$A,AJ$1,'Wells Fargo'!$B:$B,"<="&'Cash Flow'!AJ$3,'Wells Fargo'!$B:$B,">"&'Cash Flow'!AI$3) -> 0 | AK5: =SUMIFS('Wells Fargo'!$F:$F,'Wells Fargo'!$G:$G,'Cash Flow'!$A5,'Wells Fargo'!$A:$A,AK$1,'Wells Fargo'!$B:$B,"<="&'Cash Flow'!AK$3) -> 0 | AL5: =SUMIFS('Wells Fargo'!$F:$F,'Wells Fargo'!$G:$G,'Cash Flow'!$A5,'Wells Fargo'!$A:$A,AL$1,'Wells Fargo'!$B:$B,"<="&'Cash Flow'!AL$3,'Wells Fargo'!$B:$B,">"&'Cash Flow'!AK$3) -> 0 | AM5: =SUMIFS('Wells Fargo'!$F:$F,'Wells Fargo'!$G:$G,'Cash Flow'!$A5,'Wells Fargo'!$A:$A,AM$1,'Wells Fargo'!$B:$B,"<="&'Cash Flow'!AM$3,'Wells Fargo'!$B:$B,">"&'Cash Flow'!AL$3) -> 0 | AN5: =SUMIFS('Wells Fargo'!$F:$F,'Wells Fargo'!$G:$G,'Cash Flow'!$A5,'Wells Fargo'!$A:$A,AN$1,'Wells Fargo'!$B:$B,"<="&'Cash Flow'!AN$3,'Wells Fargo'!$B:$B,">"&'Cash Flow'!AM$3) -> 0 | AO5: =SUMIFS('Wells Fargo'!$F:$F,'Wells Fargo'!$G:$G,'Cash Flow'!$A5,'Wells Fargo'!$A:$A,AO$1,'Wells Fargo'!$B:$B,"<="&'Cash Flow'!AO$3,'Wells Fargo'!$B:$B,">"&'Cash Flow'!AN$3) -> 0 | AP5: =SUMIFS('Wells Fargo'!$F:$F,'Wells Fargo'!$G:$G,'Cash Flow'!$A5,'Wells Fargo'!$A:$A,AP$1,'Wells Fargo'!$B:$B,"<="&'Cash Flow'!AP$3) -> 0 | AQ5: =SUMIFS('Wells Fargo'!$F:$F,'Wells Fargo'!$G:$G,'Cash Flow'!$A5,'Wells Fargo'!$A:$A,AQ$1,'Wells Fargo'!$B:$B,"<="&'Cash Flow'!AQ$3,'Wells Fargo'!$B:$B,">"&'Cash Flow'!AP$3) -> 0 | AR5: =SUMIFS('Wells Fargo'!$F:$F,'Wells Fargo'!$G:$G,'Cash Flow'!$A5,'Wells Fargo'!$A:$A,AR$1,'Wells Fargo'!$B:$B,"<="&'Cash Flow'!AR$3,'Wells Fargo'!$B:$B,">"&'Cash Flow'!AQ$3) -> 0 | AS5: =SUMIFS('Wells Fargo'!$F:$F,'Wells Fargo'!$G:$G,'Cash Flow'!$A5,'Wells Fargo'!$A:$A,AS$1,'Wells Fargo'!$B:$B,"<="&'Cash Flow'!AS$3,'Wells Fargo'!$B:$B,">"&'Cash Flow'!AR$3) -> 0 | AT5: =SUMIFS('Wells Fargo'!$F:$F,'Wells Fargo'!$G:$G,'Cash Flow'!$A5,'Wells Fargo'!$A:$A,AT$1,'Wells Fargo'!$B:$B,"<="&'Cash Flow'!AT$3,'Wells Fargo'!$B:$B,">"&'Cash Flow'!AS$3) -> 0 | AU5: =SUMIFS('Wells Fargo'!$F:$F,'Wells Fargo'!$G:$G,'Cash Flow'!$A5,'Wells Fargo'!$A:$A,AU$1,'Wells Fargo'!$B:$B,"<="&'Cash Flow'!AU$3) -> 0 | AV5: =SUMIFS('Wells Fargo'!$F:$F,'Wells Fargo'!$G:$G,'Cash Flow'!$A5,'Wells Fargo'!$A:$A,AV$1,'Wells Fargo'!$B:$B,"<="&'Cash Flow'!AV$3,'Wells Fargo'!$B:$B,">"&'Cash Flow'!AU$3) -> 0 | AW5: =SUMIFS('Wells Fargo'!$F:$F,'Wells Fargo'!$G:$G,'Cash Flow'!$A5,'Wells Fargo'!$A:$A,AW$1,'Wells Fargo'!$B:$B,"<="&'Cash Flow'!AW$3,'Wells Fargo'!$B:$B,">"&'Cash Flow'!AV$3) -> 0 | AX5: =SUMIFS('Wells Fargo'!$F:$F,'Wells Fargo'!$G:$G,'Cash Flow'!$A5,'Wells Fargo'!$A:$A,AX$1,'Wells Fargo'!$B:$B,"<="&'Cash Flow'!AX$3,'Wells Fargo'!$B:$B,">"&'Cash Flow'!AW$3) -> 0 | AY5: =SUMIFS('Wells Fargo'!$F:$F,'Wells Fargo'!$G:$G,'Cash Flow'!$A5,'Wells Fargo'!$A:$A,AY$1,'Wells Fargo'!$B:$B,"<="&'Cash Flow'!AY$3,'Wells Fargo'!$B:$B,">"&'Cash Flow'!AX$3) -> 0 | AZ5: =SUMIFS('Wells Fargo'!$F:$F,'Wells Fargo'!$G:$G,'Cash Flow'!$A5,'Wells Fargo'!$A:$A,AZ$1,'Wells Fargo'!$B:$B,"<="&'Cash Flow'!AZ$3) -> 0 | BA5: =SUMIFS('Wells Fargo'!$F:$F,'Wells Fargo'!$G:$G,'Cash Flow'!$A5,'Wells Fargo'!$A:$A,BA$1,'Wells Fargo'!$B:$B,"<="&'Cash Flow'!BA$3,'Wells Fargo'!$B:$B,">"&'Cash Flow'!AZ$3) -> 0 | BB5: =SUMIFS('Wells Fargo'!$F:$F,'Wells Fargo'!$G:$G,'Cash Flow'!$A5,'Wells Fargo'!$A:$A,BB$1,'Wells Fargo'!$B:$B,"<="&'Cash Flow'!BB$3,'Wells Fargo'!$B:$B,">"&'Cash Flow'!BA$3) -> 0 | BC5: =SUMIFS('Wells Fargo'!$F:$F,'Wells Fargo'!$G:$G,'Cash Flow'!$A5,'Wells Fargo'!$A:$A,BC$1,'Wells Fargo'!$B:$B,"<="&'Cash Flow'!BC$3,'Wells Fargo'!$B:$B,">"&'Cash Flow'!BB$3) -> 0 | BD5: =SUMIFS('Wells Fargo'!$F:$F,'Wells Fargo'!$G:$G,'Cash Flow'!$A5,'Wells Fargo'!$A:$A,BD$1,'Wells Fargo'!$B:$B,"<="&'Cash Flow'!BD$3,'Wells Fargo'!$B:$B,">"&'Cash Flow'!BC$3) -> 0 | BE5: =SUMIFS('Wells Fargo'!$F:$F,'Wells Fargo'!$G:$G,'Cash Flow'!$A5,'Wells Fargo'!$A:$A,BE$1,'Wells Fargo'!$B:$B,"<="&'Cash Flow'!BE$3) -> 0 | BF5: =SUMIFS('Wells Fargo'!$F:$F,'Wells Fargo'!$G:$G,'Cash Flow'!$A5,'Wells Fargo'!$A:$A,BF$1,'Wells Fargo'!$B:$B,"<="&'Cash Flow'!BF$3,'Wells Fargo'!$B:$B,">"&'Cash Flow'!BE$3) -> 0 | BG5: =SUMIFS('Wells Fargo'!$F:$F,'Wells Fargo'!$G:$G,'Cash Flow'!$A5,'Wells Fargo'!$A:$A,BG$1,'Wells Fargo'!$B:$B,"<="&'Cash Flow'!BG$3,'Wells Fargo'!$B:$B,">"&'Cash Flow'!BF$3) -> 0 | BH5: =SUMIFS('Wells Fargo'!$F:$F,'Wells Fargo'!$G:$G,'Cash Flow'!$A5,'Wells Fargo'!$A:$A,BH$1,'Wells Fargo'!$B:$B,"<="&'Cash Flow'!BH$3,'Wells Fargo'!$B:$B,">"&'Cash Flow'!BG$3) -> 0 | BI5: =SUMIFS('Wells Fargo'!$F:$F,'Wells Fargo'!$G:$G,'Cash Flow'!$A5,'Wells Fargo'!$A:$A,BI$1,'Wells Fargo'!$B:$B,"<="&'Cash Flow'!BI$3,'Wells Fargo'!$B:$B,">"&'Cash Flow'!BH$3) -> 0
A6: Amar - Water | B6: =SUM(C6:BI6) -> -400 | C6: =SUMIFS('Wells Fargo'!$F:$F,'Wells Fargo'!$G:$G,'Cash Flow'!$A6,'Wells Fargo'!$A:$A,C$1,'Wells Fargo'!$B:$B,"<="&'Cash Flow'!C$3) -> 0 | D6: =SUMIFS('Wells Fargo'!$F:$F,'Wells Fargo'!$G:$G,'Cash Flow'!$A6,'Wells Fargo'!$A:$A,D$1,'Wells Fargo'!$B:$B,"<="&'Cash Flow'!D$3,'Wells Fargo'!$B:$B,">"&'Cash Flow'!C$3) -> 0 | E6: =SUMIFS('Wells Fargo'!$F:$F,'Wells Fargo'!$G:$G,'Cash Flow'!$A6,'Wells Fargo'!$A:$A,E$1,'Wells Fargo'!$B:$B,"<="&'Cash Flow'!E$3,'Wells Fargo'!$B:$B,">"&'Cash Flow'!D$3) -> 0 | F6: =SUMIFS('Wells Fargo'!$F:$F,'Wells Fargo'!$G:$G,'Cash Flow'!$A6,'Wells Fargo'!$A:$A,F$1,'Wells Fargo'!$B:$B,"<="&'Cash Flow'!F$3,'Wells Fargo'!$B:$B,">"&'Cash Flow'!E$3) -> 0 | G6: =SUMIFS('Wells Fargo'!$F:$F,'Wells Fargo'!$G:$G,'Cash Flow'!$A6,'Wells Fargo'!$A:$A,G$1,'Wells Fargo'!$B:$B,"<="&'Cash Flow'!G$3,'Wells Fargo'!$B:$B,">"&'Cash Flow'!F$3) -> 0 | H6: =SUMIFS('Wells Fargo'!$F:$F,'Wells Fargo'!$G:$G,'Cash Flow'!$A6,'Wells Fargo'!$A:$A,H$1,'Wells Fargo'!$B:$B,"<="&'Cash Flow'!H$3) -> 0 | I6: =SUMIFS('Wells Fargo'!$F:$F,'Wells Fargo'!$G:$G,'Cash Flow'!$A6,'Wells Fargo'!$A:$A,I$1,'Wells Fargo'!$B:$B,"<="&'Cash Flow'!I$3,'Wells Fargo'!$B:$B,">"&'Cash Flow'!H$3) -> 0 | J6: =SUMIFS('Wells Fargo'!$F:$F,'Wells Fargo'!$G:$G,'Cash Flow'!$A6,'Wells Fargo'!$A:$A,J$1,'Wells Fargo'!$B:$B,"<="&'Cash Flow'!J$3,'Wells Fargo'!$B:$B,">"&'Cash Flow'!I$3) -> 0 | K6: =SUMIFS('Wells Fargo'!$F:$F,'Wells Fargo'!$G:$G,'Cash Flow'!$A6,'Wells Fargo'!$A:$A,K$1,'Wells Fargo'!$B:$B,"<="&'Cash Flow'!K$3,'Wells Fargo'!$B:$B,">"&'Cash Flow'!J$3) -> 0 | L6: =SUMIFS('Wells Fargo'!$F:$F,'Wells Fargo'!$G:$G,'Cash Flow'!$A6,'Wells Fargo'!$A:$A,L$1,'Wells Fargo'!$B:$B,"<="&'Cash Flow'!L$3) -> 0 | M6: =SUMIFS('Wells Fargo'!$F:$F,'Wells Fargo'!$G:$G,'Cash Flow'!$A6,'Wells Fargo'!$A:$A,M$1,'Wells Fargo'!$B:$B,"<="&'Cash Flow'!M$3,'Wells Fargo'!$B:$B,">"&'Cash Flow'!L$3) -> -150 | N6: =SUMIFS('Wells Fargo'!$F:$F,'Wells Fargo'!$G:$G,'Cash Flow'!$A6,'Wells Fargo'!$A:$A,N$1,'Wells Fargo'!$B:$B,"<="&'Cash Flow'!N$3,'Wells Fargo'!$B:$B,">"&'Cash Flow'!M$3) -> 0 | O6: =SUMIFS('Wells Fargo'!$F:$F,'Wells Fargo'!$G:$G,'Cash Flow'!$A6,'Wells Fargo'!$A:$A,O$1,'Wells Fargo'!$B:$B,"<="&'Cash Flow'!O$3,'Wells Fargo'!$B:$B,">"&'Cash Flow'!N$3) -> 0 | P6: =SUMIFS('Wells Fargo'!$F:$F,'Wells Fargo'!$G:$G,'Cash Flow'!$A6,'Wells Fargo'!$A:$A,P$1,'Wells Fargo'!$B:$B,"<="&'Cash Flow'!P$3,'Wells Fargo'!$B:$B,">"&'Cash Flow'!O$3) -> 0 | Q6: =SUMIFS('Wells Fargo'!$F:$F,'Wells Fargo'!$G:$G,'Cash Flow'!$A6,'Wells Fargo'!$A:$A,Q$1,'Wells Fargo'!$B:$B,"<="&'Cash Flow'!Q$3) -> 0 | R6: =SUMIFS('Wells Fargo'!$F:$F,'Wells Fargo'!$G:$G,'Cash Flow'!$A6,'Wells Fargo'!$A:$A,R$1,'Wells Fargo'!$B:$B,"<="&'Cash Flow'!R$3,'Wells Fargo'!$B:$B,">"&'Cash Flow'!Q$3) -> 0 | S6: =SUMIFS('Wells Fargo'!$F:$F,'Wells Fargo'!$G:$G,'Cash Flow'!$A6,'Wells Fargo'!$A:$A,S$1,'Wells Fargo'!$B:$B,"<="&'Cash Flow'!S$3,'Wells Fargo'!$B:$B,">"&'Cash Flow'!R$3) -> -100 | T6: =SUMIFS('Wells Fargo'!$F:$F,'Wells Fargo'!$G:$G,'Cash Flow'!$A6,'Wells Fargo'!$A:$A,T$1,'Wells Fargo'!$B:$B,"<="&'Cash Flow'!T$3,'Wells Fargo'!$B:$B,">"&'Cash Flow'!S$3) -> 0 | U6: =SUMIFS('Wells Fargo'!$F:$F,'Wells Fargo'!$G:$G,'Cash Flow'!$A6,'Wells Fargo'!$A:$A,U$1,'Wells Fargo'!$B:$B,"<="&'Cash Flow'!U$3,'Wells Fargo'!$B:$B,">"&'Cash Flow'!T$3) -> 0 | V6: =SUMIFS('Wells Fargo'!$F:$F,'Wells Fargo'!$G:$G,'Cash Flow'!$A6,'Wells Fargo'!$A:$A,V$1,'Wells Fargo'!$B:$B,"<="&'Cash Flow'!V$3) -> 0 | W6: =SUMIFS('Wells Fargo'!$F:$F,'Wells Fargo'!$G:$G,'Cash Flow'!$A6,'Wells Fargo'!$A:$A,W$1,'Wells Fargo'!$B:$B,"<="&'Cash Flow'!W$3,'Wells Fargo'!$B:$B,">"&'Cash Flow'!V$3) -> -150 | X6: =SUMIFS('Wells Fargo'!$F:$F,'Wells Fargo'!$G:$G,'Cash Flow'!$A6,'Wells Fargo'!$A:$A,X$1,'Wells Fargo'!$B:$B,"<="&'Cash Flow'!X$3,'Wells Fargo'!$B:$B,">"&'Cash Flow'!W$3) -> 0 | Y6: =SUMIFS('Wells Fargo'!$F:$F,'Wells Fargo'!$G:$G,'Cash Flow'!$A6,'Wells Fargo'!$A:$A,Y$1,'Wells Fargo'!$B:$B,"<="&'Cash Flow'!Y$3,'Wells Fargo'!$B:$B,">"&'Cash Flow'!X$3) -> 0 | Z6: =SUMIFS('Wells Fargo'!$F:$F,'Wells Fargo'!$G:$G,'Cash Flow'!$A6,'Wells Fargo'!$A:$A,Z$1,'Wells Fargo'!$B:$B,"<="&'Cash Flow'!Z$3,'Wells Fargo'!$B:$B,">"&'Cash Flow'!Y$3) -> 0 | AA6: =SUMIFS('Wells Fargo'!$F:$F,'Wells Fargo'!$G:$G,'Cash Flow'!$A6,'Wells Fargo'!$A:$A,AA$1,'Wells Fargo'!$B:$B,"<="&'Cash Flow'!AA$3) -> 0 | AB6: =SUMIFS('Wells Fargo'!$F:$F,'Wells Fargo'!$G:$G,'Cash Flow'!$A6,'Wells Fargo'!$A:$A,AB$1,'Wells Fargo'!$B:$B,"<="&'Cash Flow'!AB$3,'Wells Fargo'!$B:$B,">"&'Cash Flow'!AA$3) -> 0 | AC6: =SUMIFS('Wells Fargo'!$F:$F,'Wells Fargo'!$G:$G,'Cash Flow'!$A6,'Wells Fargo'!$A:$A,AC$1,'Wells Fargo'!$B:$B,"<="&'Cash Flow'!AC$3,'Wells Fargo'!$B:$B,">"&'Cash Flow'!AB$3) -> 0 | AD6: =SUMIFS('Wells Fargo'!$F:$F,'Wells Fargo'!$G:$G,'Cash Flow'!$A6,'Wells Fargo'!$A:$A,AD$1,'Wells Fargo'!$B:$B,"<="&'Cash Flow'!AD$3,'Wells Fargo'!$B:$B,">"&'Cash Flow'!AC$3) -> 0 | AE6: =SUMIFS('Wells Fargo'!$F:$F,'Wells Fargo'!$G:$G,'Cash Flow'!$A6,'Wells Fargo'!$A:$A,AE$1,'Wells Fargo'!$B:$B,"<="&'Cash Flow'!AE$3,'Wells Fargo'!$B:$B,">"&'Cash Flow'!AD$3) -> 0 | AF6: =SUMIFS('Wells Fargo'!$F:$F,'Wells Fargo'!$G:$G,'Cash Flow'!$A6,'Wells Fargo'!$A:$A,AF$1,'Wells Fargo'!$B:$B,"<="&'Cash Flow'!AF$3) -> 0 | AG6: =SUMIFS('Wells Fargo'!$F:$F,'Wells Fargo'!$G:$G,'Cash Flow'!$A6,'Wells Fargo'!$A:$A,AG$1,'Wells Fargo'!$B:$B,"<="&'Cash Flow'!AG$3,'Wells Fargo'!$B:$B,">"&'Cash Flow'!AF$3) -> 0 | AH6: =SUMIFS('Wells Fargo'!$F:$F,'Wells Fargo'!$G:$G,'Cash Flow'!$A6,'Wells Fargo'!$A:$A,AH$1,'Wells Fargo'!$B:$B,"<="&'Cash Flow'!AH$3,'Wells Fargo'!$B:$B,">"&'Cash Flow'!AG$3) -> 0 | AI6: =SUMIFS('Wells Fargo'!$F:$F,'Wells Fargo'!$G:$G,'Cash Flow'!$A6,'Wells Fargo'!$A:$A,AI$1,'Wells Fargo'!$B:$B,"<="&'Cash Flow'!AI$3,'Wells Fargo'!$B:$B,">"&'Cash Flow'!AH$3) -> 0 | AJ6: =SUMIFS('Wells Fargo'!$F:$F,'Wells Fargo'!$G:$G,'Cash Flow'!$A6,'Wells Fargo'!$A:$A,AJ$1,'Wells Fargo'!$B:$B,"<="&'Cash Flow'!AJ$3,'Wells Fargo'!$B:$B,">"&'Cash Flow'!AI$3) -> 0 | AK6: =SUMIFS('Wells Fargo'!$F:$F,'Wells Fargo'!$G:$G,'Cash Flow'!$A6,'Wells Fargo'!$A:$A,AK$1,'Wells Fargo'!$B:$B,"<="&'Cash Flow'!AK$3) -> 0 | AL6: =SUMIFS('Wells Fargo'!$F:$F,'Wells Fargo'!$G:$G,'Cash Flow'!$A6,'Wells Fargo'!$A:$A,AL$1,'Wells Fargo'!$B:$B,"<="&'Cash Flow'!AL$3,'Wells Fargo'!$B:$B,">"&'Cash Flow'!AK$3) -> 0 | AM6: =SUMIFS('Wells Fargo'!$F:$F,'Wells Fargo'!$G:$G,'Cash Flow'!$A6,'Wells Fargo'!$A:$A,AM$1,'Wells Fargo'!$B:$B,"<="&'Cash Flow'!AM$3,'Wells Fargo'!$B:$B,">"&'Cash Flow'!AL$3) -> 0 | AN6: =SUMIFS('Wells Fargo'!$F:$F,'Wells Fargo'!$G:$G,'Cash Flow'!$A6,'Wells Fargo'!$A:$A,AN$1,'Wells Fargo'!$B:$B,"<="&'Cash Flow'!AN$3,'Wells Fargo'!$B:$B,">"&'Cash Flow'!AM$3) -> 0 | AO6: =SUMIFS('Wells Fargo'!$F:$F,'Wells Fargo'!$G:$G,'Cash Flow'!$A6,'Wells Fargo'!$A:$A,AO$1,'Wells Fargo'!$B:$B,"<="&'Cash Flow'!AO$3,'Wells Fargo'!$B:$B,">"&'Cash Flow'!AN$3) -> 0 | AP6: =SUMIFS('Wells Fargo'!$F:$F,'Wells Fargo'!$G:$G,'Cash Flow'!$A6,'Wells Fargo'!$A:$A,AP$1,'Wells Fargo'!$B:$B,"<="&'Cash Flow'!AP$3) -> 0 | AQ6: =SUMIFS('Wells Fargo'!$F:$F,'Wells Fargo'!$G:$G,'Cash Flow'!$A6,'Wells Fargo'!$A:$A,AQ$1,'Wells Fargo'!$B:$B,"<="&'Cash Flow'!AQ$3,'Wells Fargo'!$B:$B,">"&'Cash Flow'!AP$3) -> 0 | AR6: =SUMIFS('Wells Fargo'!$F:$F,'Wells Fargo'!$G:$G,'Cash Flow'!$A6,'Wells Fargo'!$A:$A,AR$1,'Wells Fargo'!$B:$B,"<="&'Cash Flow'!AR$3,'Wells Fargo'!$B:$B,">"&'Cash Flow'!AQ$3) -> 0 | AS6: =SUMIFS('Wells Fargo'!$F:$F,'Wells Fargo'!$G:$G,'Cash Flow'!$A6,'Wells Fargo'!$A:$A,AS$1,'Wells Fargo'!$B:$B,"<="&'Cash Flow'!AS$3,'Wells Fargo'!$B:$B,">"&'Cash Flow'!AR$3) -> 0 | AT6: =SUMIFS('Wells Fargo'!$F:$F,'Wells Fargo'!$G:$G,'Cash Flow'!$A6,'Wells Fargo'!$A:$A,AT$1,'Wells Fargo'!$B:$B,"<="&'Cash Flow'!AT$3,'Wells Fargo'!$B:$B,">"&'Cash Flow'!AS$3) -> 0 | AU6: =SUMIFS('Wells Fargo'!$F:$F,'Wells Fargo'!$G:$G,'Cash Flow'!$A6,'Wells Fargo'!$A:$A,AU$1,'Wells Fargo'!$B:$B,"<="&'Cash Flow'!AU$3) -> 0 | AV6: =SUMIFS('Wells Fargo'!$F:$F,'Wells Fargo'!$G:$G,'Cash Flow'!$A6,'Wells Fargo'!$A:$A,AV$1,'Wells Fargo'!$B:$B,"<="&'Cash Flow'!AV$3,'Wells Fargo'!$B:$B,">"&'Cash Flow'!AU$3) -> 0 | AW6: =SUMIFS('Wells Fargo'!$F:$F,'Wells Fargo'!$G:$G,'Cash Flow'!$A6,'Wells Fargo'!$A:$A,AW$1,'Wells Fargo'!$B:$B,"<="&'Cash Flow'!AW$3,'Wells Fargo'!$B:$B,">"&'Cash Flow'!AV$3) -> 0 | AX6: =SUMIFS('Wells Fargo'!$F:$F,'Wells Fargo'!$G:$G,'Cash Flow'!$A6,'Wells Fargo'!$A:$A,AX$1,'Wells Fargo'!$B:$B,"<="&'Cash Flow'!AX$3,'Wells Fargo'!$B:$B,">"&'Cash Flow'!AW$3) -> 0 | AY6: =SUMIFS('Wells Fargo'!$F:$F,'Wells Fargo'!$G:$G,'Cash Flow'!$A6,'Wells Fargo'!$A:$A,AY$1,'Wells Fargo'!$B:$B,"<="&'Cash Flow'!AY$3,'Wells Fargo'!$B:$B,">"&'Cash Flow'!AX$3) -> 0 | AZ6: =SUMIFS('Wells Fargo'!$F:$F,'Wells Fargo'!$G:$G,'Cash Flow'!$A6,'Wells Fargo'!$A:$A,AZ$1,'Wells Fargo'!$B:$B,"<="&'Cash Flow'!AZ$3) -> 0 | BA6: =SUMIFS('Wells Fargo'!$F:$F,'Wells Fargo'!$G:$G,'Cash Flow'!$A6,'Wells Fargo'!$A:$A,BA$1,'Wells Fargo'!$B:$B,"<="&'Cash Flow'!BA$3,'Wells Fargo'!$B:$B,">"&'Cash Flow'!AZ$3) -> 0 | BB6: =SUMIFS('Wells Fargo'!$F:$F,'Wells Fargo'!$G:$G,'Cash Flow'!$A6,'Wells Fargo'!$A:$A,BB$1,'Wells Fargo'!$B:$B,"<="&'Cash Flow'!BB$3,'Wells Fargo'!$B:$B,">"&'Cash Flow'!BA$3) -> 0 | BC6: =SUMIFS('Wells Fargo'!$F:$F,'Wells Fargo'!$G:$G,'Cash Flow'!$A6,'Wells Fargo'!$A:$A,BC$1,'Wells Fargo'!$B:$B,"<="&'Cash Flow'!BC$3,'Wells Fargo'!$B:$B,">"&'Cash Flow'!BB$3) -> 0 | BD6: =SUMIFS('Wells Fargo'!$F:$F,'Wells Fargo'!$G:$G,'Cash Flow'!$A6,'Wells Fargo'!$A:$A,BD$1,'Wells Fargo'!$B:$B,"<="&'Cash Flow'!BD$3,'Wells Fargo'!$B:$B,">"&'Cash Flow'!BC$3) -> 0 | BE6: =SUMIFS('Wells Fargo'!$F:$F,'Wells Fargo'!$G:$G,'Cash Flow'!$A6,'Wells Fargo'!$A:$A,BE$1,'Wells Fargo'!$B:$B,"<="&'Cash Flow'!BE$3) -> 0 | BF6: =SUMIFS('Wells Fargo'!$F:$F,'Wells Fargo'!$G:$G,'Cash Flow'!$A6,'Wells Fargo'!$A:$A,BF$1,'Wells Fargo'!$B:$B,"<="&'Cash Flow'!BF$3,'Wells Fargo'!$B:$B,">"&'Cash Flow'!BE$3) -> 0 | BG6: =SUMIFS('Wells Fargo'!$F:$F,'Wells Fargo'!$G:$G,'Cash Flow'!$A6,'Wells Fargo'!$A:$A,BG$1,'Wells Fargo'!$B:$B,"<="&'Cash Flow'!BG$3,'Wells Fargo'!$B:$B,">"&'Cash Flow'!BF$3) -> 0 | BH6: =SUMIFS('Wells Fargo'!$F:$F,'Wells Fargo'!$G:$G,'Cash Flow'!$A6,'Wells Fargo'!$A:$A,BH$1,'Wells Fargo'!$B:$B,"<="&'Cash Flow'!BH$3,'Wells Fargo'!$B:$B,">"&'Cash Flow'!BG$3) -> 0 | BI6: =SUMIFS('Wells Fargo'!$F:$F,'Wells Fargo'!$G:$G,'Cash Flow'!$A6,'Wells Fargo'!$A:$A,BI$1,'Wells Fargo'!$B:$B,"<="&'Cash Flow'!BI$3,'Wells Fargo'!$B:$B,">"&'Cash Flow'!BH$3) -> 0
A7: Anush Rohani Shukla | B7: =SUM(C7:BI7) -> -615 | C7: =SUMIFS('Wells Fargo'!$F:$F,'Wells Fargo'!$G:$G,'Cash Flow'!$A7,'Wells Fargo'!$A:$A,C$1,'Wells Fargo'!$B:$B,"<="&'Cash Flow'!C$3) -> 0 | D7: =SUMIFS('Wells Fargo'!$F:$F,'Wells Fargo'!$G:$G,'Cash Flow'!$A7,'Wells Fargo'!$A:$A,D$1,'Wells Fargo'!$B:$B,"<="&'Cash Flow'!D$3,'Wells Fargo'!$B:$B,">"&'Cash Flow'!C$3) -> 0 | E7: =SUMIFS('Wells Fargo'!$F:$F,'Wells Fargo'!$G:$G,'Cash Flow'!$A7,'Wells Fargo'!$A:$A,E$1,'Wells Fargo'!$B:$B,"<="&'Cash Flow'!E$3,'Wells Fargo'!$B:$B,">"&'Cash Flow'!D$3) -> 0 | F7: =SUMIFS('Wells Fargo'!$F:$F,'Wells Fargo'!$G:$G,'Cash Flow'!$A7,'Wells Fargo'!$A:$A,F$1,'Wells Fargo'!$B:$B,"<="&'Cash Flow'!F$3,'Wells Fargo'!$B:$B,">"&'Cash Flow'!E$3) -> 0 | G7: =SUMIFS('Wells Fargo'!$F:$F,'Wells Fargo'!$G:$G,'Cash Flow'!$A7,'Wells Fargo'!$A:$A,G$1,'Wells Fargo'!$B:$B,"<="&'Cash Flow'!G$3,'Wells Fargo'!$B:$B,">"&'Cash Flow'!F$3) -> 0 | H7: =SUMIFS('Wells Fargo'!$F:$F,'Wells Fargo'!$G:$G,'Cash Flow'!$A7,'Wells Fargo'!$A:$A,H$1,'Wells Fargo'!$B:$B,"<="&'Cash Flow'!H$3) -> 0 | I7: =SUMIFS('Wells Fargo'!$F:$F,'Wells Fargo'!$G:$G,'Cash Flow'!$A7,'Wells Fargo'!$A:$A,I$1,'Wells Fargo'!$B:$B,"<="&'Cash Flow'!I$3,'Wells Fargo'!$B:$B,">"&'Cash Flow'!H$3) -> 0 | J7: =SUMIFS('Wells Fargo'!$F:$F,'Wells Fargo'!$G:$G,'Cash Flow'!$A7,'Wells Fargo'!$A:$A,J$1,'Wells Fargo'!$B:$B,"<="&'Cash Flow'!J$3,'Wells Fargo'!$B:$B,">"&'Cash Flow'!I$3) -> 0 | K7: =SUMIFS('Wells Fargo'!$F:$F,'Wells Fargo'!$G:$G,'Cash Flow'!$A7,'Wells Fargo'!$A:$A,K$1,'Wells Fargo'!$B:$B,"<="&'Cash Flow'!K$3,'Wells Fargo'!$B:$B,">"&'Cash Flow'!J$3) -> 0 | L7: =SUMIFS('Wells Fargo'!$F:$F,'Wells Fargo'!$G:$G,'Cash Flow'!$A7,'Wells Fargo'!$A:$A,L$1,'Wells Fargo'!$B:$B,"<="&'Cash Flow'!L$3) -> 0 | M7: =SUMIFS('Wells Fargo'!$F:$F,'Wells Fargo'!$G:$G,'Cash Flow'!$A7,'Wells Fargo'!$A:$A,M$1,'Wells Fargo'!$B:$B,"<="&'Cash Flow'!M$3,'Wells Fargo'!$B:$B,">"&'Cash Flow'!L$3) -> 0 | N7: =SUMIFS('Wells Fargo'!$F:$F,'Wells Fargo'!$G:$G,'Cash Flow'!$A7,'Wells Fargo'!$A:$A,N$1,'Wells Fargo'!$B:$B,"<="&'Cash Flow'!N$3,'Wells Fargo'!$B:$B,">"&'Cash Flow'!M$3) -> 0 | O7: =SUMIFS('Wells Fargo'!$F:$F,'Wells Fargo'!$G:$G,'Cash Flow'!$A7,'Wells Fargo'!$A:$A,O$1,'Wells Fargo'!$B:$B,"<="&'Cash Flow'!O$3,'Wells Fargo'!$B:$B,">"&'Cash Flow'!N$3) -> 0 | P7: =SUMIFS('Wells Fargo'!$F:$F,'Wells Fargo'!$G:$G,'Cash Flow'!$A7,'Wells Fargo'!$A:$A,P$1,'Wells Fargo'!$B:$B,"<="&'Cash Flow'!P$3,'Wells Fargo'!$B:$B,">"&'Cash Flow'!O$3) -> 0 | Q7: =SUMIFS('Wells Fargo'!$F:$F,'Wells Fargo'!$G:$G,'Cash Flow'!$A7,'Wells Fargo'!$A:$A,Q$1,'Wells Fargo'!$B:$B,"<="&'Cash Flow'!Q$3) -> 0 | R7: =SUMIFS('Wells Fargo'!$F:$F,'Wells Fargo'!$G:$G,'Cash Flow'!$A7,'Wells Fargo'!$A:$A,R$1,'Wells Fargo'!$B:$B,"<="&'Cash Flow'!R$3,'Wells Fargo'!$B:$B,">"&'Cash Flow'!Q$3) -> 0 | S7: =SUMIFS('Wells Fargo'!$F:$F,'Wells Fargo'!$G:$G,'Cash Flow'!$A7,'Wells Fargo'!$A:$A,S$1,'Wells Fargo'!$B:$B,"<="&'Cash Flow'!S$3,'Wells Fargo'!$B:$B,">"&'Cash Flow'!R$3) -> 0 | T7: =SUMIFS('Wells Fargo'!$F:$F,'Wells Fargo'!$G:$G,'Cash Flow'!$A7,'Wells Fargo'!$A:$A,T$1,'Wells Fargo'!$B:$B,"<="&'Cash Flow'!T$3,'Wells Fargo'!$B:$B,">"&'Cash Flow'!S$3) -> 0 | U7: =SUMIFS('Wells Fargo'!$F:$F,'Wells Fargo'!$G:$G,'Cash Flow'!$A7,'Wells Fargo'!$A:$A,U$1,'Wells Fargo'!$B:$B,"<="&'Cash Flow'!U$3,'Wells Fargo'!$B:$B,">"&'Cash Flow'!T$3) -> 0 | V7: =SUMIFS('Wells Fargo'!$F:$F,'Wells Fargo'!$G:$G,'Cash Flow'!$A7,'Wells Fargo'!$A:$A,V$1,'Wells Fargo'!$B:$B,"<="&'Cash Flow'!V$3) -> 0 | W7: =SUMIFS('Wells Fargo'!$F:$F,'Wells Fargo'!$G:$G,'Cash Flow'!$A7,'Wells Fargo'!$A:$A,W$1,'Wells Fargo'!$B:$B,"<="&'Cash Flow'!W$3,'Wells Fargo'!$B:$B,">"&'Cash Flow'!V$3) -> 0 | X7: =SUMIFS('Wells Fargo'!$F:$F,'Wells Fargo'!$G:$G,'Cash Flow'!$A7,'Wells Fargo'!$A:$A,X$1,'Wells Fargo'!$B:$B,"<="&'Cash Flow'!X$3,'Wells Fargo'!$B:$B,">"&'Cash Flow'!W$3) -> 0 | Y7: =SUMIFS('Wells Fargo'!$F:$F,'Wells Fargo'!$G:$G,'Cash Flow'!$A7,'Wells Fargo'!$A:$A,Y$1,'Wells Fargo'!$B:$B,"<="&'Cash Flow'!Y$3,'Wells Fargo'!$B:$B,">"&'Cash Flow'!X$3) -> 0 | Z7: =SUMIFS('Wells Fargo'!$F:$F,'Wells Fargo'!$G:$G,'Cash Flow'!$A7,'Wells Fargo'!$A:$A,Z$1,'Wells Fargo'!$B:$B,"<="&'Cash Flow'!Z$3,'Wells Fargo'!$B:$B,">"&'Cash Flow'!Y$3) -> 0 | AA7: =SUMIFS('Wells Fargo'!$F:$F,'Wells Fargo'!$G:$G,'Cash Flow'!$A7,'Wells Fargo'!$A:$A,AA$1,'Wells Fargo'!$B:$B,"<="&'Cash Flow'!AA$3) -> 0 | AB7: =SUMIFS('Wells Fargo'!$F:$F,'Wells Fargo'!$G:$G,'Cash Flow'!$A7,'Wells Fargo'!$A:$A,AB$1,'Wells Fargo'!$B:$B,"<="&'Cash Flow'!AB$3,'Wells Fargo'!$B:$B,">"&'Cash Flow'!AA$3) -> 0 | AC7: =SUMIFS('Wells Fargo'!$F:$F,'Wells Fargo'!$G:$G,'Cash Flow'!$A7,'Wells Fargo'!$A:$A,AC$1,'Wells Fargo'!$B:$B,"<="&'Cash Flow'!AC$3,'Wells Fargo'!$B:$B,">"&'Cash Flow'!AB$3) -> 0 | AD7: =SUMIFS('Wells Fargo'!$F:$F,'Wells Fargo'!$G:$G,'Cash Flow'!$A7,'Wells Fargo'!$A:$A,AD$1,'Wells Fargo'!$B:$B,"<="&'Cash Flow'!AD$3,'Wells Fargo'!$B:$B,">"&'Cash Flow'!AC$3) -> -615 | AE7: =SUMIFS('Wells Fargo'!$F:$F,'Wells Fargo'!$G:$G,'Cash Flow'!$A7,'Wells Fargo'!$A:$A,AE$1,'Wells Fargo'!$B:$B,"<="&'Cash Flow'!AE$3,'Wells Fargo'!$B:$B,">"&'Cash Flow'!AD$3) -> 0 | AF7: =SUMIFS('Wells Fargo'!$F:$F,'Wells Fargo'!$G:$G,'Cash Flow'!$A7,'Wells Fargo'!$A:$A,AF$1,'Wells Fargo'!$B:$B,"<="&'Cash Flow'!AF$3) -> 0 | AG7: =SUMIFS('Wells Fargo'!$F:$F,'Wells Fargo'!$G:$G,'Cash Flow'!$A7,'Wells Fargo'!$A:$A,AG$1,'Wells Fargo'!$B:$B,"<="&'Cash Flow'!AG$3,'Wells Fargo'!$B:$B,">"&'Cash Flow'!AF$3) -> 0 | AH7: =SUMIFS('Wells Fargo'!$F:$F,'Wells Fargo'!$G:$G,'Cash Flow'!$A7,'Wells Fargo'!$A:$A,AH$1,'Wells Fargo'!$B:$B,"<="&'Cash Flow'!AH$3,'Wells Fargo'!$B:$B,">"&'Cash Flow'!AG$3) -> 0 | AI7: =SUMIFS('Wells Fargo'!$F:$F,'Wells Fargo'!$G:$G,'Cash Flow'!$A7,'Wells Fargo'!$A:$A,AI$1,'Wells Fargo'!$B:$B,"<="&'Cash Flow'!AI$3,'Wells Fargo'!$B:$B,">"&'Cash Flow'!AH$3) -> 0 | AJ7: =SUMIFS('Wells Fargo'!$F:$F,'Wells Fargo'!$G:$G,'Cash Flow'!$A7,'Wells Fargo'!$A:$A,AJ$1,'Wells Fargo'!$B:$B,"<="&'Cash Flow'!AJ$3,'Wells Fargo'!$B:$B,">"&'Cash Flow'!AI$3) -> 0 | AK7: =SUMIFS('Wells Fargo'!$F:$F,'Wells Fargo'!$G:$G,'Cash Flow'!$A7,'Wells Fargo'!$A:$A,AK$1,'Wells Fargo'!$B:$B,"<="&'Cash Flow'!AK$3) -> 0 | AL7: =SUMIFS('Wells Fargo'!$F:$F,'Wells Fargo'!$G:$G,'Cash Flow'!$A7,'Wells Fargo'!$A:$A,AL$1,'Wells Fargo'!$B:$B,"<="&'Cash Flow'!AL$3,'Wells Fargo'!$B:$B,">"&'Cash Flow'!AK$3) -> 0 | AM7: =SUMIFS('Wells Fargo'!$F:$F,'Wells Fargo'!$G:$G,'Cash Flow'!$A7,'Wells Fargo'!$A:$A,AM$1,'Wells Fargo'!$B:$B,"<="&'Cash Flow'!AM$3,'Wells Fargo'!$B:$B,">"&'Cash Flow'!AL$3) -> 0 | AN7: =SUMIFS('Wells Fargo'!$F:$F,'Wells Fargo'!$G:$G,'Cash Flow'!$A7,'Wells Fargo'!$A:$A,AN$1,'Wells Fargo'!$B:$B,"<="&'Cash Flow'!AN$3,'Wells Fargo'!$B:$B,">"&'Cash Flow'!AM$3) -> 0 | AO7: =SUMIFS('Wells Fargo'!$F:$F,'Wells Fargo'!$G:$G,'Cash Flow'!$A7,'Wells Fargo'!$A:$A,AO$1,'Wells Fargo'!$B:$B,"<="&'Cash Flow'!AO$3,'Wells Fargo'!$B:$B,">"&'Cash Flow'!AN$3) -> 0 | AP7: =SUMIFS('Wells Fargo'!$F:$F,'Wells Fargo'!$G:$G,'Cash Flow'!$A7,'Wells Fargo'!$A:$A,AP$1,'Wells Fargo'!$B:$B,"<="&'Cash Flow'!AP$3) -> 0 | AQ7: =SUMIFS('Wells Fargo'!$F:$F,'Wells Fargo'!$G:$G,'Cash Flow'!$A7,'Wells Fargo'!$A:$A,AQ$1,'Wells Fargo'!$B:$B,"<="&'Cash Flow'!AQ$3,'Wells Fargo'!$B:$B,">"&'Cash Flow'!AP$3) -> 0 | AR7: =SUMIFS('Wells Fargo'!$F:$F,'Wells Fargo'!$G:$G,'Cash Flow'!$A7,'Wells Fargo'!$A:$A,AR$1,'Wells Fargo'!$B:$B,"<="&'Cash Flow'!AR$3,'Wells Fargo'!$B:$B,">"&'Cash Flow'!AQ$3) -> 0 | AS7: =SUMIFS('Wells Fargo'!$F:$F,'Wells Fargo'!$G:$G,'Cash Flow'!$A7,'Wells Fargo'!$A:$A,AS$1,'Wells Fargo'!$B:$B,"<="&'Cash Flow'!AS$3,'Wells Fargo'!$B:$B,">"&'Cash Flow'!AR$3) -> 0 | AT7: =SUMIFS('Wells Fargo'!$F:$F,'Wells Fargo'!$G:$G,'Cash Flow'!$A7,'Wells Fargo'!$A:$A,AT$1,'Wells Fargo'!$B:$B,"<="&'Cash Flow'!AT$3,'Wells Fargo'!$B:$B,">"&'Cash Flow'!AS$3) -> 0 | AU7: =SUMIFS('Wells Fargo'!$F:$F,'Wells Fargo'!$G:$G,'Cash Flow'!$A7,'Wells Fargo'!$A:$A,AU$1,'Wells Fargo'!$B:$B,"<="&'Cash Flow'!AU$3) -> 0 | AV7: =SUMIFS('Wells Fargo'!$F:$F,'Wells Fargo'!$G:$G,'Cash Flow'!$A7,'Wells Fargo'!$A:$A,AV$1,'Wells Fargo'!$B:$B,"<="&'Cash Flow'!AV$3,'Wells Fargo'!$B:$B,">"&'Cash Flow'!AU$3) -> 0 | AW7: =SUMIFS('Wells Fargo'!$F:$F,'Wells Fargo'!$G:$G,'Cash Flow'!$A7,'Wells Fargo'!$A:$A,AW$1,'Wells Fargo'!$B:$B,"<="&'Cash Flow'!AW$3,'Wells Fargo'!$B:$B,">"&'Cash Flow'!AV$3) -> 0 | AX7: =SUMIFS('Wells Fargo'!$F:$F,'Wells Fargo'!$G:$G,'Cash Flow'!$A7,'Wells Fargo'!$A:$A,AX$1,'Wells Fargo'!$B:$B,"<="&'Cash Flow'!AX$3,'Wells Fargo'!$B:$B,">"&'Cash Flow'!AW$3) -> 0 | AY7: =SUMIFS('Wells Fargo'!$F:$F,'Wells Fargo'!$G:$G,'Cash Flow'!$A7,'Wells Fargo'!$A:$A,AY$1,'Wells Fargo'!$B:$B,"<="&'Cash Flow'!AY$3,'Wells Fargo'!$B:$B,">"&'Cash Flow'!AX$3) -> 0 | AZ7: =SUMIFS('Wells Fargo'!$F:$F,'Wells Fargo'!$G:$G,'Cash Flow'!$A7,'Wells Fargo'!$A:$A,AZ$1,'Wells Fargo'!$B:$B,"<="&'Cash Flow'!AZ$3) -> 0 | BA7: =SUMIFS('Wells Fargo'!$F:$F,'Wells Fargo'!$G:$G,'Cash Flow'!$A7,'Wells Fargo'!$A:$A,BA$1,'Wells Fargo'!$B:$B,"<="&'Cash Flow'!BA$3,'Wells Fargo'!$B:$B,">"&'Cash Flow'!AZ$3) -> 0 | BB7: =SUMIFS('Wells Fargo'!$F:$F,'Wells Fargo'!$G:$G,'Cash Flow'!$A7,'Wells Fargo'!$A:$A,BB$1,'Wells Fargo'!$B:$B,"<="&'Cash Flow'!BB$3,'Wells Fargo'!$B:$B,">"&'Cash Flow'!BA$3) -> 0 | BC7: =SUMIFS('Wells Fargo'!$F:$F,'Wells Fargo'!$G:$G,'Cash Flow'!$A7,'Wells Fargo'!$A:$A,BC$1,'Wells Fargo'!$B:$B,"<="&'Cash Flow'!BC$3,'Wells Fargo'!$B:$B,">"&'Cash Flow'!BB$3) -> 0 | BD7: =SUMIFS('Wells Fargo'!$F:$F,'Wells Fargo'!$G:$G,'Cash Flow'!$A7,'Wells Fargo'!$A:$A,BD$1,'Wells Fargo'!$B:$B,"<="&'Cash Flow'!BD$3,'Wells Fargo'!$B:$B,">"&'Cash Flow'!BC$3) -> 0 | BE7: =SUMIFS('Wells Fargo'!$F:$F,'Wells Fargo'!$G:$G,'Cash Flow'!$A7,'Wells Fargo'!$A:$A,BE$1,'Wells Fargo'!$B:$B,"<="&'Cash Flow'!BE$3) -> 0 | BF7: =SUMIFS('Wells Fargo'!$F:$F,'Wells Fargo'!$G:$G,'Cash Flow'!$A7,'Wells Fargo'!$A:$A,BF$1,'Wells Fargo'!$B:$B,"<="&'Cash Flow'!BF$3,'Wells Fargo'!$B:$B,">"&'Cash Flow'!BE$3) -> 0 | BG7: =SUMIFS('Wells Fargo'!$F:$F,'Wells Fargo'!$G:$G,'Cash Flow'!$A7,'Wells Fargo'!$A:$A,BG$1,'Wells Fargo'!$B:$B,"<="&'Cash Flow'!BG$3,'Wells Fargo'!$B:$B,">"&'Cash Flow'!BF$3) -> 0 | BH7: =SUMIFS('Wells Fargo'!$F:$F,'Wells Fargo'!$G:$G,'Cash Flow'!$A7,'Wells Fargo'!$A:$A,BH$1,'Wells Fargo'!$B:$B,"<="&'Cash Flow'!BH$3,'Wells Fargo'!$B:$B,">"&'Cash Flow'!BG$3) -> 0 | BI7: =SUMIFS('Wells Fargo'!$F:$F,'Wells Fargo'!$G:$G,'Cash Flow'!$A7,'Wells Fargo'!$A:$A,BI$1,'Wells Fargo'!$B:$B,"<="&'Cash Flow'!BI$3,'Wells Fargo'!$B:$B,">"&'Cash Flow'!BH$3) -> 0
A8: Brooklyn | B8: =SUM(C8:BI8) -> -952.13 | C8: =SUMIFS('Wells Fargo'!$F:$F,'Wells Fargo'!$G:$G,'Cash Flow'!$A8,'Wells Fargo'!$A:$A,C$1,'Wells Fargo'!$B:$B,"<="&'Cash Flow'!C$3) -> 0 | D8: =SUMIFS('Wells Fargo'!$F:$F,'Wells Fargo'!$G:$G,'Cash Flow'!$A8,'Wells Fargo'!$A:$A,D$1,'Wells Fargo'!$B:$B,"<="&'Cash Flow'!D$3,'Wells Fargo'!$B:$B,">"&'Cash Flow'!C$3) -> 0 | E8: =SUMIFS('Wells Fargo'!$F:$F,'Wells Fargo'!$G:$G,'Cash Flow'!$A8,'Wells Fargo'!$A:$A,E$1,'Wells Fargo'!$B:$B,"<="&'Cash Flow'!E$3,'Wells Fargo'!$B:$B,">"&'Cash Flow'!D$3) -> 0 | F8: =SUMIFS('Wells Fargo'!$F:$F,'Wells Fargo'!$G:$G,'Cash Flow'!$A8,'Wells Fargo'!$A:$A,F$1,'Wells Fargo'!$B:$B,"<="&'Cash Flow'!F$3,'Wells Fargo'!$B:$B,">"&'Cash Flow'!E$3) -> 0 | G8: =SUMIFS('Wells Fargo'!$F:$F,'Wells Fargo'!$G:$G,'Cash Flow'!$A8,'Wells Fargo'!$A:$A,G$1,'Wells Fargo'!$B:$B,"<="&'Cash Flow'!G$3,'Wells Fargo'!$B:$B,">"&'Cash Flow'!F$3) -> 0 | H8: =SUMIFS('Wells Fargo'!$F:$F,'Wells Fargo'!$G:$G,'Cash Flow'!$A8,'Wells Fargo'!$A:$A,H$1,'Wells Fargo'!$B:$B,"<="&'Cash Flow'!H$3) -> 0 | I8: =SUMIFS('Wells Fargo'!$F:$F,'Wells Fargo'!$G:$G,'Cash Flow'!$A8,'Wells Fargo'!$A:$A,I$1,'Wells Fargo'!$B:$B,"<="&'Cash Flow'!I$3,'Wells Fargo'!$B:$B,">"&'Cash Flow'!H$3) -> 0 | J8: =SUMIFS('Wells Fargo'!$F:$F,'Wells Fargo'!$G:$G,'Cash Flow'!$A8,'Wells Fargo'!$A:$A,J$1,'Wells Fargo'!$B:$B,"<="&'Cash Flow'!J$3,'Wells Fargo'!$B:$B,">"&'Cash Flow'!I$3) -> 0 | K8: =SUMIFS('Wells Fargo'!$F:$F,'Wells Fargo'!$G:$G,'Cash Flow'!$A8,'Wells Fargo'!$A:$A,K$1,'Wells Fargo'!$B:$B,"<="&'Cash Flow'!K$3,'Wells Fargo'!$B:$B,">"&'Cash Flow'!J$3) -> 0 | L8: =SUMIFS('Wells Fargo'!$F:$F,'Wells Fargo'!$G:$G,'Cash Flow'!$A8,'Wells Fargo'!$A:$A,L$1,'Wells Fargo'!$B:$B,"<="&'Cash Flow'!L$3) -> 0 | M8: =SUMIFS('Wells Fargo'!$F:$F,'Wells Fargo'!$G:$G,'Cash Flow'!$A8,'Wells Fargo'!$A:$A,M$1,'Wells Fargo'!$B:$B,"<="&'Cash Flow'!M$3,'Wells Fargo'!$B:$B,">"&'Cash Flow'!L$3) -> 0 | N8: =SUMIFS('Wells Fargo'!$F:$F,'Wells Fargo'!$G:$G,'Cash Flow'!$A8,'Wells Fargo'!$A:$A,N$1,'Wells Fargo'!$B:$B,"<="&'Cash Flow'!N$3,'Wells Fargo'!$B:$B,">"&'Cash Flow'!M$3) -> 0 | O8: =SUMIFS('Wells Fargo'!$F:$F,'Wells Fargo'!$G:$G,'Cash Flow'!$A8,'Wells Fargo'!$A:$A,O$1,'Wells Fargo'!$B:$B,"<="&'Cash Flow'!O$3,'Wells Fargo'!$B:$B,">"&'Cash Flow'!N$3) -> 0 | P8: =SUMIFS('Wells Fargo'!$F:$F,'Wells Fargo'!$G:$G,'Cash Flow'!$A8,'Wells Fargo'!$A:$A,P$1,'Wells Fargo'!$B:$B,"<="&'Cash Flow'!P$3,'Wells Fargo'!$B:$B,">"&'Cash Flow'!O$3) -> 0 | Q8: =SUMIFS('Wells Fargo'!$F:$F,'Wells Fargo'!$G:$G,'Cash Flow'!$A8,'Wells Fargo'!$A:$A,Q$1,'Wells Fargo'!$B:$B,"<="&'Cash Flow'!Q$3) -> 0 | R8: =SUMIFS('Wells Fargo'!$F:$F,'Wells Fargo'!$G:$G,'Cash Flow'!$A8,'Wells Fargo'!$A:$A,R$1,'Wells Fargo'!$B:$B,"<="&'Cash Flow'!R$3,'Wells Fargo'!$B:$B,">"&'Cash Flow'!Q$3) -> 0 | S8: =SUMIFS('Wells Fargo'!$F:$F,'Wells Fargo'!$G:$G,'Cash Flow'!$A8,'Wells Fargo'!$A:$A,S$1,'Wells Fargo'!$B:$B,"<="&'Cash Flow'!S$3,'Wells Fargo'!$B:$B,">"&'Cash Flow'!R$3) -> 0 | T8: =SUMIFS('Wells Fargo'!$F:$F,'Wells Fargo'!$G:$G,'Cash Flow'!$A8,'Wells Fargo'!$A:$A,T$1,'Wells Fargo'!$B:$B,"<="&'Cash Flow'!T$3,'Wells Fargo'!$B:$B,">"&'Cash Flow'!S$3) -> 0 | U8: =SUMIFS('Wells Fargo'!$F:$F,'Wells Fargo'!$G:$G,'Cash Flow'!$A8,'Wells Fargo'!$A:$A,U$1,'Wells Fargo'!$B:$B,"<="&'Cash Flow'!U$3,'Wells Fargo'!$B:$B,">"&'Cash Flow'!T$3) -> 0 | V8: =SUMIFS('Wells Fargo'!$F:$F,'Wells Fargo'!$G:$G,'Cash Flow'!$A8,'Wells Fargo'!$A:$A,V$1,'Wells Fargo'!$B:$B,"<="&'Cash Flow'!V$3) -> 0 | W8: =SUMIFS('Wells Fargo'!$F:$F,'Wells Fargo'!$G:$G,'Cash Flow'!$A8,'Wells Fargo'!$A:$A,W$1,'Wells Fargo'!$B:$B,"<="&'Cash Flow'!W$3,'Wells Fargo'!$B:$B,">"&'Cash Flow'!V$3) -> 0 | X8: =SUMIFS('Wells Fargo'!$F:$F,'Wells Fargo'!$G:$G,'Cash Flow'!$A8,'Wells Fargo'!$A:$A,X$1,'Wells Fargo'!$B:$B,"<="&'Cash Flow'!X$3,'Wells Fargo'!$B:$B,">"&'Cash Flow'!W$3) -> 0 | Y8: =SUMIFS('Wells Fargo'!$F:$F,'Wells Fargo'!$G:$G,'Cash Flow'!$A8,'Wells Fargo'!$A:$A,Y$1,'Wells Fargo'!$B:$B,"<="&'Cash Flow'!Y$3,'Wells Fargo'!$B:$B,">"&'Cash Flow'!X$3) -> 0 | Z8: =SUMIFS('Wells Fargo'!$F:$F,'Wells Fargo'!$G:$G,'Cash Flow'!$A8,'Wells Fargo'!$A:$A,Z$1,'Wells Fargo'!$B:$B,"<="&'Cash Flow'!Z$3,'Wells Fargo'!$B:$B,">"&'Cash Flow'!Y$3) -> 0 | AA8: =SUMIFS('Wells Fargo'!$F:$F,'Wells Fargo'!$G:$G,'Cash Flow'!$A8,'Wells Fargo'!$A:$A,AA$1,'Wells Fargo'!$B:$B,"<="&'Cash Flow'!AA$3) -> 0 | AB8: =SUMIFS('Wells Fargo'!$F:$F,'Wells Fargo'!$G:$G,'Cash Flow'!$A8,'Wells Fargo'!$A:$A,AB$1,'Wells Fargo'!$B:$B,"<="&'Cash Flow'!AB$3,'Wells Fargo'!$B:$B,">"&'Cash Flow'!AA$3) -> -635.27 | AC8: =SUMIFS('Wells Fargo'!$F:$F,'Wells Fargo'!$G:$G,'Cash Flow'!$A8,'Wells Fargo'!$A:$A,AC$1,'Wells Fargo'!$B:$B,"<="&'Cash Flow'!AC$3,'Wells Fargo'!$B:$B,">"&'Cash Flow'!AB$3) -> 0 | AD8: =SUMIFS('Wells Fargo'!$F:$F,'Wells Fargo'!$G:$G,'Cash Flow'!$A8,'Wells Fargo'!$A:$A,AD$1,'Wells Fargo'!$B:$B,"<="&'Cash Flow'!AD$3,'Wells Fargo'!$B:$B,">"&'Cash Flow'!AC$3) -> 0 | AE8: =SUMIFS('Wells Fargo'!$F:$F,'Wells Fargo'!$G:$G,'Cash Flow'!$A8,'Wells Fargo'!$A:$A,AE$1,'Wells Fargo'!$B:$B,"<="&'Cash Flow'!AE$3,'Wells Fargo'!$B:$B,">"&'Cash Flow'!AD$3) -> 0 | AF8: =SUMIFS('Wells Fargo'!$F:$F,'Wells Fargo'!$G:$G,'Cash Flow'!$A8,'Wells Fargo'!$A:$A,AF$1,'Wells Fargo'!$B:$B,"<="&'Cash Flow'!AF$3) -> 0 | AG8: =SUMIFS('Wells Fargo'!$F:$F,'Wells Fargo'!$G:$G,'Cash Flow'!$A8,'Wells Fargo'!$A:$A,AG$1,'Wells Fargo'!$B:$B,"<="&'Cash Flow'!AG$3,'Wells Fargo'!$B:$B,">"&'Cash Flow'!AF$3) -> -316.86 | AH8: =SUMIFS('Wells Fargo'!$F:$F,'Wells Fargo'!$G:$G,'Cash Flow'!$A8,'Wells Fargo'!$A:$A,AH$1,'Wells Fargo'!$B:$B,"<="&'Cash Flow'!AH$3,'Wells Fargo'!$B:$B,">"&'Cash Flow'!AG$3) -> 0 | AI8: =SUMIFS('Wells Fargo'!$F:$F,'Wells Fargo'!$G:$G,'Cash Flow'!$A8,'Wells Fargo'!$A:$A,AI$1,'Wells Fargo'!$B:$B,"<="&'Cash Flow'!AI$3,'Wells Fargo'!$B:$B,">"&'Cash Flow'!AH$3) -> 0 | AJ8: =SUMIFS('Wells Fargo'!$F:$F,'Wells Fargo'!$G:$G,'Cash Flow'!$A8,'Wells Fargo'!$A:$A,AJ$1,'Wells Fargo'!$B:$B,"<="&'Cash Flow'!AJ$3,'Wells Fargo'!$B:$B,">"&'Cash Flow'!AI$3) -> 0 | AK8: =SUMIFS('Wells Fargo'!$F:$F,'Wells Fargo'!$G:$G,'Cash Flow'!$A8,'Wells Fargo'!$A:$A,AK$1,'Wells Fargo'!$B:$B,"<="&'Cash Flow'!AK$3) -> 0 | AL8: =SUMIFS('Wells Fargo'!$F:$F,'Wells Fargo'!$G:$G,'Cash Flow'!$A8,'Wells Fargo'!$A:$A,AL$1,'Wells Fargo'!$B:$B,"<="&'Cash Flow'!AL$3,'Wells Fargo'!$B:$B,">"&'Cash Flow'!AK$3) -> 0 | AM8: =SUMIFS('Wells Fargo'!$F:$F,'Wells Fargo'!$G:$G,'Cash Flow'!$A8,'Wells Fargo'!$A:$A,AM$1,'Wells Fargo'!$B:$B,"<="&'Cash Flow'!AM$3,'Wells Fargo'!$B:$B,">"&'Cash Flow'!AL$3) -> 0 | AN8: =SUMIFS('Wells Fargo'!$F:$F,'Wells Fargo'!$G:$G,'Cash Flow'!$A8,'Wells Fargo'!$A:$A,AN$1,'Wells Fargo'!$B:$B,"<="&'Cash Flow'!AN$3,'Wells Fargo'!$B:$B,">"&'Cash Flow'!AM$3) -> 0 | AO8: =SUMIFS('Wells Fargo'!$F:$F,'Wells Fargo'!$G:$G,'Cash Flow'!$A8,'Wells Fargo'!$A:$A,AO$1,'Wells Fargo'!$B:$B,"<="&'Cash Flow'!AO$3,'Wells Fargo'!$B:$B,">"&'Cash Flow'!AN$3) -> 0 | AP8: =SUMIFS('Wells Fargo'!$F:$F,'Wells Fargo'!$G:$G,'Cash Flow'!$A8,'Wells Fargo'!$A:$A,AP$1,'Wells Fargo'!$B:$B,"<="&'Cash Flow'!AP$3) -> 0 | AQ8: =SUMIFS('Wells Fargo'!$F:$F,'Wells Fargo'!$G:$G,'Cash Flow'!$A8,'Wells Fargo'!$A:$A,AQ$1,'Wells Fargo'!$B:$B,"<="&'Cash Flow'!AQ$3,'Wells Fargo'!$B:$B,">"&'Cash Flow'!AP$3) -> 0 | AR8: =SUMIFS('Wells Fargo'!$F:$F,'Wells Fargo'!$G:$G,'Cash Flow'!$A8,'Wells Fargo'!$A:$A,AR$1,'Wells Fargo'!$B:$B,"<="&'Cash Flow'!AR$3,'Wells Fargo'!$B:$B,">"&'Cash Flow'!AQ$3) -> 0 | AS8: =SUMIFS('Wells Fargo'!$F:$F,'Wells Fargo'!$G:$G,'Cash Flow'!$A8,'Wells Fargo'!$A:$A,AS$1,'Wells Fargo'!$B:$B,"<="&'Cash Flow'!AS$3,'Wells Fargo'!$B:$B,">"&'Cash Flow'!AR$3) -> 0 | AT8: =SUMIFS('Wells Fargo'!$F:$F,'Wells Fargo'!$G:$G,'Cash Flow'!$A8,'Wells Fargo'!$A:$A,AT$1,'Wells Fargo'!$B:$B,"<="&'Cash Flow'!AT$3,'Wells Fargo'!$B:$B,">"&'Cash Flow'!AS$3) -> 0 | AU8: =SUMIFS('Wells Fargo'!$F:$F,'Wells Fargo'!$G:$G,'Cash Flow'!$A8,'Wells Fargo'!$A:$A,AU$1,'Wells Fargo'!$B:$B,"<="&'Cash Flow'!AU$3) -> 0 | AV8: =SUMIFS('Wells Fargo'!$F:$F,'Wells Fargo'!$G:$G,'Cash Flow'!$A8,'Wells Fargo'!$A:$A,AV$1,'Wells Fargo'!$B:$B,"<="&'Cash Flow'!AV$3,'Wells Fargo'!$B:$B,">"&'Cash Flow'!AU$3) -> 0 | AW8: =SUMIFS('Wells Fargo'!$F:$F,'Wells Fargo'!$G:$G,'Cash Flow'!$A8,'Wells Fargo'!$A:$A,AW$1,'Wells Fargo'!$B:$B,"<="&'Cash Flow'!AW$3,'Wells Fargo'!$B:$B,">"&'Cash Flow'!AV$3) -> 0 | AX8: =SUMIFS('Wells Fargo'!$F:$F,'Wells Fargo'!$G:$G,'Cash Flow'!$A8,'Wells Fargo'!$A:$A,AX$1,'Wells Fargo'!$B:$B,"<="&'Cash Flow'!AX$3,'Wells Fargo'!$B:$B,">"&'Cash Flow'!AW$3) -> 0 | AY8: =SUMIFS('Wells Fargo'!$F:$F,'Wells Fargo'!$G:$G,'Cash Flow'!$A8,'Wells Fargo'!$A:$A,AY$1,'Wells Fargo'!$B:$B,"<="&'Cash Flow'!AY$3,'Wells Fargo'!$B:$B,">"&'Cash Flow'!AX$3) -> 0 | AZ8: =SUMIFS('Wells Fargo'!$F:$F,'Wells Fargo'!$G:$G,'Cash Flow'!$A8,'Wells Fargo'!$A:$A,AZ$1,'Wells Fargo'!$B:$B,"<="&'Cash Flow'!AZ$3) -> 0 | BA8: =SUMIFS('Wells Fargo'!$F:$F,'Wells Fargo'!$G:$G,'Cash Flow'!$A8,'Wells Fargo'!$A:$A,BA$1,'Wells Fargo'!$B:$B,"<="&'Cash Flow'!BA$3,'Wells Fargo'!$B:$B,">"&'Cash Flow'!AZ$3) -> 0 | BB8: =SUMIFS('Wells Fargo'!$F:$F,'Wells Fargo'!$G:$G,'Cash Flow'!$A8,'Wells Fargo'!$A:$A,BB$1,'Wells Fargo'!$B:$B,"<="&'Cash Flow'!BB$3,'Wells Fargo'!$B:$B,">"&'Cash Flow'!BA$3) -> 0 | BC8: =SUMIFS('Wells Fargo'!$F:$F,'Wells Fargo'!$G:$G,'Cash Flow'!$A8,'Wells Fargo'!$A:$A,BC$1,'Wells Fargo'!$B:$B,"<="&'Cash Flow'!BC$3,'Wells Fargo'!$B:$B,">"&'Cash Flow'!BB$3) -> 0 | BD8: =SUMIFS('Wells Fargo'!$F:$F,'Wells Fargo'!$G:$G,'Cash Flow'!$A8,'Wells Fargo'!$A:$A,BD$1,'Wells Fargo'!$B:$B,"<="&'Cash Flow'!BD$3,'Wells Fargo'!$B:$B,">"&'Cash Flow'!BC$3) -> 0 | BE8: =SUMIFS('Wells Fargo'!$F:$F,'Wells Fargo'!$G:$G,'Cash Flow'!$A8,'Wells Fargo'!$A:$A,BE$1,'Wells Fargo'!$B:$B,"<="&'Cash Flow'!BE$3) -> 0 | BF8: =SUMIFS('Wells Fargo'!$F:$F,'Wells Fargo'!$G:$G,'Cash Flow'!$A8,'Wells Fargo'!$A:$A,BF$1,'Wells Fargo'!$B:$B,"<="&'Cash Flow'!BF$3,'Wells Fargo'!$B:$B,">"&'Cash Flow'!BE$3) -> 0 | BG8: =SUMIFS('Wells Fargo'!$F:$F,'Wells Fargo'!$G:$G,'Cash Flow'!$A8,'Wells Fargo'!$A:$A,BG$1,'Wells Fargo'!$B:$B,"<="&'Cash Flow'!BG$3,'Wells Fargo'!$B:$B,">"&'Cash Flow'!BF$3) -> 0 | BH8: =SUMIFS('Wells Fargo'!$F:$F,'Wells Fargo'!$G:$G,'Cash Flow'!$A8,'Wells Fargo'!$A:$A,BH$1,'Wells Fargo'!$B:$B,"<="&'Cash Flow'!BH$3,'Wells Fargo'!$B:$B,">"&'Cash Flow'!BG$3) -> 0 | BI8: =SUMIFS('Wells Fargo'!$F:$F,'Wells Fargo'!$G:$G,'Cash Flow'!$A8,'Wells Fargo'!$A:$A,BI$1,'Wells Fargo'!$B:$B,"<="&'Cash Flow'!BI$3,'Wells Fargo'!$B:$B,">"&'Cash Flow'!BH$3) -> 0
A9: Cairo | B9: =SUM(C9:BI9) -> 0 | C9: =SUMIFS('Wells Fargo'!$F:$F,'Wells Fargo'!$G:$G,'Cash Flow'!$A9,'Wells Fargo'!$A:$A,C$1,'Wells Fargo'!$B:$B,"<="&'Cash Flow'!C$3) -> 0 | D9: =SUMIFS('Wells Fargo'!$F:$F,'Wells Fargo'!$G:$G,'Cash Flow'!$A9,'Wells Fargo'!$A:$A,D$1,'Wells Fargo'!$B:$B,"<="&'Cash Flow'!D$3,'Wells Fargo'!$B:$B,">"&'Cash Flow'!C$3) -> 0 | E9: =SUMIFS('Wells Fargo'!$F:$F,'Wells Fargo'!$G:$G,'Cash Flow'!$A9,'Wells Fargo'!$A:$A,E$1,'Wells Fargo'!$B:$B,"<="&'Cash Flow'!E$3,'Wells Fargo'!$B:$B,">"&'Cash Flow'!D$3) -> 0 | F9: =SUMIFS('Wells Fargo'!$F:$F,'Wells Fargo'!$G:$G,'Cash Flow'!$A9,'Wells Fargo'!$A:$A,F$1,'Wells Fargo'!$B:$B,"<="&'Cash Flow'!F$3,'Wells Fargo'!$B:$B,">"&'Cash Flow'!E$3) -> -155 | G9: =SUMIFS('Wells Fargo'!$F:$F,'Wells Fargo'!$G:$G,'Cash Flow'!$A9,'Wells Fargo'!$A:$A,G$1,'Wells Fargo'!$B:$B,"<="&'Cash Flow'!G$3,'Wells Fargo'!$B:$B,">"&'Cash Flow'!F$3) -> 155 | H9: =SUMIFS('Wells Fargo'!$F:$F,'Wells Fargo'!$G:$G,'Cash Flow'!$A9,'Wells Fargo'!$A:$A,H$1,'Wells Fargo'!$B:$B,"<="&'Cash Flow'!H$3) -> 0 | I9: =SUMIFS('Wells Fargo'!$F:$F,'Wells Fargo'!$G:$G,'Cash Flow'!$A9,'Wells Fargo'!$A:$A,I$1,'Wells Fargo'!$B:$B,"<="&'Cash Flow'!I$3,'Wells Fargo'!$B:$B,">"&'Cash Flow'!H$3) -> 0 | J9: =SUMIFS('Wells Fargo'!$F:$F,'Wells Fargo'!$G:$G,'Cash Flow'!$A9,'Wells Fargo'!$A:$A,J$1,'Wells Fargo'!$B:$B,"<="&'Cash Flow'!J$3,'Wells Fargo'!$B:$B,">"&'Cash Flow'!I$3) -> 0 | K9: =SUMIFS('Wells Fargo'!$F:$F,'Wells Fargo'!$G:$G,'Cash Flow'!$A9,'Wells Fargo'!$A:$A,K$1,'Wells Fargo'!$B:$B,"<="&'Cash Flow'!K$3,'Wells Fargo'!$B:$B,">"&'Cash Flow'!J$3) -> 0 | L9: =SUMIFS('Wells Fargo'!$F:$F,'Wells Fargo'!$G:$G,'Cash Flow'!$A9,'Wells Fargo'!$A:$A,L$1,'Wells Fargo'!$B:$B,"<="&'Cash Flow'!L$3) -> 0 | M9: =SUMIFS('Wells Fargo'!$F:$F,'Wells Fargo'!$G:$G,'Cash Flow'!$A9,'Wells Fargo'!$A:$A,M$1,'Wells Fargo'!$B:$B,"<="&'Cash Flow'!M$3,'Wells Fargo'!$B:$B,">"&'Cash Flow'!L$3) -> 0 | N9: =SUMIFS('Wells Fargo'!$F:$F,'Wells Fargo'!$G:$G,'Cash Flow'!$A9,'Wells Fargo'!$A:$A,N$1,'Wells Fargo'!$B:$B,"<="&'Cash Flow'!N$3,'Wells Fargo'!$B:$B,">"&'Cash Flow'!M$3) -> 0 | O9: =SUMIFS('Wells Fargo'!$F:$F,'Wells Fargo'!$G:$G,'Cash Flow'!$A9,'Wells Fargo'!$A:$A,O$1,'Wells Fargo'!$B:$B,"<="&'Cash Flow'!O$3,'Wells Fargo'!$B:$B,">"&'Cash Flow'!N$3) -> 0 | P9: =SUMIFS('Wells Fargo'!$F:$F,'Wells Fargo'!$G:$G,'Cash Flow'!$A9,'Wells Fargo'!$A:$A,P$1,'Wells Fargo'!$B:$B,"<="&'Cash Flow'!P$3,'Wells Fargo'!$B:$B,">"&'Cash Flow'!O$3) -> 0 | Q9: =SUMIFS('Wells Fargo'!$F:$F,'Wells Fargo'!$G:$G,'Cash Flow'!$A9,'Wells Fargo'!$A:$A,Q$1,'Wells Fargo'!$B:$B,"<="&'Cash Flow'!Q$3) -> 0 | R9: =SUMIFS('Wells Fargo'!$F:$F,'Wells Fargo'!$G:$G,'Cash Flow'!$A9,'Wells Fargo'!$A:$A,R$1,'Wells Fargo'!$B:$B,"<="&'Cash Flow'!R$3,'Wells Fargo'!$B:$B,">"&'Cash Flow'!Q$3) -> 0 | S9: =SUMIFS('Wells Fargo'!$F:$F,'Wells Fargo'!$G:$G,'Cash Flow'!$A9,'Wells Fargo'!$A:$A,S$1,'Wells Fargo'!$B:$B,"<="&'Cash Flow'!S$3,'Wells Fargo'!$B:$B,">"&'Cash Flow'!R$3) -> 0 | T9: =SUMIFS('Wells Fargo'!$F:$F,'Wells Fargo'!$G:$G,'Cash Flow'!$A9,'Wells Fargo'!$A:$A,T$1,'Wells Fargo'!$B:$B,"<="&'Cash Flow'!T$3,'Wells Fargo'!$B:$B,">"&'Cash Flow'!S$3) -> 0 | U9: =SUMIFS('Wells Fargo'!$F:$F,'Wells Fargo'!$G:$G,'Cash Flow'!$A9,'Wells Fargo'!$A:$A,U$1,'Wells Fargo'!$B:$B,"<="&'Cash Flow'!U$3,'Wells Fargo'!$B:$B,">"&'Cash Flow'!T$3) -> 0 | V9: =SUMIFS('Wells Fargo'!$F:$F,'Wells Fargo'!$G:$G,'Cash Flow'!$A9,'Wells Fargo'!$A:$A,V$1,'Wells Fargo'!$B:$B,"<="&'Cash Flow'!V$3) -> 0 | W9: =SUMIFS('Wells Fargo'!$F:$F,'Wells Fargo'!$G:$G,'Cash Flow'!$A9,'Wells Fargo'!$A:$A,W$1,'Wells Fargo'!$B:$B,"<="&'Cash Flow'!W$3,'Wells Fargo'!$B:$B,">"&'Cash Flow'!V$3) -> 0 | X9: =SUMIFS('Wells Fargo'!$F:$F,'Wells Fargo'!$G:$G,'Cash Flow'!$A9,'Wells Fargo'!$A:$A,X$1,'Wells Fargo'!$B:$B,"<="&'Cash Flow'!X$3,'Wells Fargo'!$B:$B,">"&'Cash Flow'!W$3) -> 0 | Y9: =SUMIFS('Wells Fargo'!$F:$F,'Wells Fargo'!$G:$G,'Cash Flow'!$A9,'Wells Fargo'!$A:$A,Y$1,'Wells Fargo'!$B:$B,"<="&'Cash Flow'!Y$3,'Wells Fargo'!$B:$B,">"&'Cash Flow'!X$3) -> 0 | Z9: =SUMIFS('Wells Fargo'!$F:$F,'Wells Fargo'!$G:$G,'Cash Flow'!$A9,'Wells Fargo'!$A:$A,Z$1,'Wells Fargo'!$B:$B,"<="&'Cash Flow'!Z$3,'Wells Fargo'!$B:$B,">"&'Cash Flow'!Y$3) -> 0 | AA9: =SUMIFS('Wells Fargo'!$F:$F,'Wells Fargo'!$G:$G,'Cash Flow'!$A9,'Wells Fargo'!$A:$A,AA$1,'Wells Fargo'!$B:$B,"<="&'Cash Flow'!AA$3) -> 0 | AB9: =SUMIFS('Wells Fargo'!$F:$F,'Wells Fargo'!$G:$G,'Cash Flow'!$A9,'Wells Fargo'!$A:$A,AB$1,'Wells Fargo'!$B:$B,"<="&'Cash Flow'!AB$3,'Wells Fargo'!$B:$B,">"&'Cash Flow'!AA$3) -> 0 | AC9: =SUMIFS('Wells Fargo'!$F:$F,'Wells Fargo'!$G:$G,'Cash Flow'!$A9,'Wells Fargo'!$A:$A,AC$1,'Wells Fargo'!$B:$B,"<="&'Cash Flow'!AC$3,'Wells Fargo'!$B:$B,">"&'Cash Flow'!AB$3) -> 0 | AD9: =SUMIFS('Wells Fargo'!$F:$F,'Wells Fargo'!$G:$G,'Cash Flow'!$A9,'Wells Fargo'!$A:$A,AD$1,'Wells Fargo'!$B:$B,"<="&'Cash Flow'!AD$3,'Wells Fargo'!$B:$B,">"&'Cash Flow'!AC$3) -> 0 | AE9: =SUMIFS('Wells Fargo'!$F:$F,'Wells Fargo'!$G:$G,'Cash Flow'!$A9,'Wells Fargo'!$A:$A,AE$1,'Wells Fargo'!$B:$B,"<="&'Cash Flow'!AE$3,'Wells Fargo'!$B:$B,">"&'Cash Flow'!AD$3) -> 0 | AF9: =SUMIFS('Wells Fargo'!$F:$F,'Wells Fargo'!$G:$G,'Cash Flow'!$A9,'Wells Fargo'!$A:$A,AF$1,'Wells Fargo'!$B:$B,"<="&'Cash Flow'!AF$3) -> 0 | AG9: =SUMIFS('Wells Fargo'!$F:$F,'Wells Fargo'!$G:$G,'Cash Flow'!$A9,'Wells Fargo'!$A:$A,AG$1,'Wells Fargo'!$B:$B,"<="&'Cash Flow'!AG$3,'Wells Fargo'!$B:$B,">"&'Cash Flow'!AF$3) -> 0 | AH9: =SUMIFS('Wells Fargo'!$F:$F,'Wells Fargo'!$G:$G,'Cash Flow'!$A9,'Wells Fargo'!$A:$A,AH$1,'Wells Fargo'!$B:$B,"<="&'Cash Flow'!AH$3,'Wells Fargo'!$B:$B,">"&'Cash Flow'!AG$3) -> 0 | AI9: =SUMIFS('Wells Fargo'!$F:$F,'Wells Fargo'!$G:$G,'Cash Flow'!$A9,'Wells Fargo'!$A:$A,AI$1,'Wells Fargo'!$B:$B,"<="&'Cash Flow'!AI$3,'Wells Fargo'!$B:$B,">"&'Cash Flow'!AH$3) -> 0 | AJ9: =SUMIFS('Wells Fargo'!$F:$F,'Wells Fargo'!$G:$G,'Cash Flow'!$A9,'Wells Fargo'!$A:$A,AJ$1,'Wells Fargo'!$B:$B,"<="&'Cash Flow'!AJ$3,'Wells Fargo'!$B:$B,">"&'Cash Flow'!AI$3) -> 0 | AK9: =SUMIFS('Wells Fargo'!$F:$F,'Wells Fargo'!$G:$G,'Cash Flow'!$A9,'Wells Fargo'!$A:$A,AK$1,'Wells Fargo'!$B:$B,"<="&'Cash Flow'!AK$3) -> 0 | AL9: =SUMIFS('Wells Fargo'!$F:$F,'Wells Fargo'!$G:$G,'Cash Flow'!$A9,'Wells Fargo'!$A:$A,AL$1,'Wells Fargo'!$B:$B,"<="&'Cash Flow'!AL$3,'Wells Fargo'!$B:$B,">"&'Cash Flow'!AK$3) -> 0 | AM9: =SUMIFS('Wells Fargo'!$F:$F,'Wells Fargo'!$G:$G,'Cash Flow'!$A9,'Wells Fargo'!$A:$A,AM$1,'Wells Fargo'!$B:$B,"<="&'Cash Flow'!AM$3,'Wells Fargo'!$B:$B,">"&'Cash Flow'!AL$3) -> 0 | AN9: =SUMIFS('Wells Fargo'!$F:$F,'Wells Fargo'!$G:$G,'Cash Flow'!$A9,'Wells Fargo'!$A:$A,AN$1,'Wells Fargo'!$B:$B,"<="&'Cash Flow'!AN$3,'Wells Fargo'!$B:$B,">"&'Cash Flow'!AM$3) -> 0 | AO9: =SUMIFS('Wells Fargo'!$F:$F,'Wells Fargo'!$G:$G,'Cash Flow'!$A9,'Wells Fargo'!$A:$A,AO$1,'Wells Fargo'!$B:$B,"<="&'Cash Flow'!AO$3,'Wells Fargo'!$B:$B,">"&'Cash Flow'!AN$3) -> 0 | AP9: =SUMIFS('Wells Fargo'!$F:$F,'Wells Fargo'!$G:$G,'Cash Flow'!$A9,'Wells Fargo'!$A:$A,AP$1,'Wells Fargo'!$B:$B,"<="&'Cash Flow'!AP$3) -> 0 | AQ9: =SUMIFS('Wells Fargo'!$F:$F,'Wells Fargo'!$G:$G,'Cash Flow'!$A9,'Wells Fargo'!$A:$A,AQ$1,'Wells Fargo'!$B:$B,"<="&'Cash Flow'!AQ$3,'Wells Fargo'!$B:$B,">"&'Cash Flow'!AP$3) -> 0 | AR9: =SUMIFS('Wells Fargo'!$F:$F,'Wells Fargo'!$G:$G,'Cash Flow'!$A9,'Wells Fargo'!$A:$A,AR$1,'Wells Fargo'!$B:$B,"<="&'Cash Flow'!AR$3,'Wells Fargo'!$B:$B,">"&'Cash Flow'!AQ$3) -> 0 | AS9: =SUMIFS('Wells Fargo'!$F:$F,'Wells Fargo'!$G:$G,'Cash Flow'!$A9,'Wells Fargo'!$A:$A,AS$1,'Wells Fargo'!$B:$B,"<="&'Cash Flow'!AS$3,'Wells Fargo'!$B:$B,">"&'Cash Flow'!AR$3) -> 0 | AT9: =SUMIFS('Wells Fargo'!$F:$F,'Wells Fargo'!$G:$G,'Cash Flow'!$A9,'Wells Fargo'!$A:$A,AT$1,'Wells Fargo'!$B:$B,"<="&'Cash Flow'!AT$3,'Wells Fargo'!$B:$B,">"&'Cash Flow'!AS$3) -> 0 | AU9: =SUMIFS('Wells Fargo'!$F:$F,'Wells Fargo'!$G:$G,'Cash Flow'!$A9,'Wells Fargo'!$A:$A,AU$1,'Wells Fargo'!$B:$B,"<="&'Cash Flow'!AU$3) -> 0 | AV9: =SUMIFS('Wells Fargo'!$F:$F,'Wells Fargo'!$G:$G,'Cash Flow'!$A9,'Wells Fargo'!$A:$A,AV$1,'Wells Fargo'!$B:$B,"<="&'Cash Flow'!AV$3,'Wells Fargo'!$B:$B,">"&'Cash Flow'!AU$3) -> 0 | AW9: =SUMIFS('Wells Fargo'!$F:$F,'Wells Fargo'!$G:$G,'Cash Flow'!$A9,'Wells Fargo'!$A:$A,AW$1,'Wells Fargo'!$B:$B,"<="&'Cash Flow'!AW$3,'Wells Fargo'!$B:$B,">"&'Cash Flow'!AV$3) -> 0 | AX9: =SUMIFS('Wells Fargo'!$F:$F,'Wells Fargo'!$G:$G,'Cash Flow'!$A9,'Wells Fargo'!$A:$A,AX$1,'Wells Fargo'!$B:$B,"<="&'Cash Flow'!AX$3,'Wells Fargo'!$B:$B,">"&'Cash Flow'!AW$3) -> 0 | AY9: =SUMIFS('Wells Fargo'!$F:$F,'Wells Fargo'!$G:$G,'Cash Flow'!$A9,'Wells Fargo'!$A:$A,AY$1,'Wells Fargo'!$B:$B,"<="&'Cash Flow'!AY$3,'Wells Fargo'!$B:$B,">"&'Cash Flow'!AX$3) -> 0 | AZ9: =SUMIFS('Wells Fargo'!$F:$F,'Wells Fargo'!$G:$G,'Cash Flow'!$A9,'Wells Fargo'!$A:$A,AZ$1,'Wells Fargo'!$B:$B,"<="&'Cash Flow'!AZ$3) -> 0 | BA9: =SUMIFS('Wells Fargo'!$F:$F,'Wells Fargo'!$G:$G,'Cash Flow'!$A9,'Wells Fargo'!$A:$A,BA$1,'Wells Fargo'!$B:$B,"<="&'Cash Flow'!BA$3,'Wells Fargo'!$B:$B,">"&'Cash Flow'!AZ$3) -> 0 | BB9: =SUMIFS('Wells Fargo'!$F:$F,'Wells Fargo'!$G:$G,'Cash Flow'!$A9,'Wells Fargo'!$A:$A,BB$1,'Wells Fargo'!$B:$B,"<="&'Cash Flow'!BB$3,'Wells Fargo'!$B:$B,">"&'Cash Flow'!BA$3) -> 0 | BC9: =SUMIFS('Wells Fargo'!$F:$F,'Wells Fargo'!$G:$G,'Cash Flow'!$A9,'Wells Fargo'!$A:$A,BC$1,'Wells Fargo'!$B:$B,"<="&'Cash Flow'!BC$3,'Wells Fargo'!$B:$B,">"&'Cash Flow'!BB$3) -> 0 | BD9: =SUMIFS('Wells Fargo'!$F:$F,'Wells Fargo'!$G:$G,'Cash Flow'!$A9,'Wells Fargo'!$A:$A,BD$1,'Wells Fargo'!$B:$B,"<="&'Cash Flow'!BD$3,'Wells Fargo'!$B:$B,">"&'Cash Flow'!BC$3) -> 0 | BE9: =SUMIFS('Wells Fargo'!$F:$F,'Wells Fargo'!$G:$G,'Cash Flow'!$A9,'Wells Fargo'!$A:$A,BE$1,'Wells Fargo'!$B:$B,"<="&'Cash Flow'!BE$3) -> 0 | BF9: =SUMIFS('Wells Fargo'!$F:$F,'Wells Fargo'!$G:$G,'Cash Flow'!$A9,'Wells Fargo'!$A:$A,BF$1,'Wells Fargo'!$B:$B,"<="&'Cash Flow'!BF$3,'Wells Fargo'!$B:$B,">"&'Cash Flow'!BE$3) -> 0 | BG9: =SUMIFS('Wells Fargo'!$F:$F,'Wells Fargo'!$G:$G,'Cash Flow'!$A9,'Wells Fargo'!$A:$A,BG$1,'Wells Fargo'!$B:$B,"<="&'Cash Flow'!BG$3,'Wells Fargo'!$B:$B,">"&'Cash Flow'!BF$3) -> 0 | BH9: =SUMIFS('Wells Fargo'!$F:$F,'Wells Fargo'!$G:$G,'Cash Flow'!$A9,'Wells Fargo'!$A:$A,BH$1,'Wells Fargo'!$B:$B,"<="&'Cash Flow'!BH$3,'Wells Fargo'!$B:$B,">"&'Cash Flow'!BG$3) -> 0 | BI9: =SUMIFS('Wells Fargo'!$F:$F,'Wells Fargo'!$G:$G,'Cash Flow'!$A9,'Wells Fargo'!$A:$A,BI$1,'Wells Fargo'!$B:$B,"<="&'Cash Flow'!BI$3,'Wells Fargo'!$B:$B,">"&'Cash Flow'!BH$3) -> 0
A10: Credit | B10: =SUM(C10:BI10) -> -15177.33 | C10: =SUMIFS('Wells Fargo'!$F:$F,'Wells Fargo'!$G:$G,'Cash Flow'!$A10,'Wells Fargo'!$A:$A,C$1,'Wells Fargo'!$B:$B,"<="&'Cash Flow'!C$3) -> 0 | D10: =SUMIFS('Wells Fargo'!$F:$F,'Wells Fargo'!$G:$G,'Cash Flow'!$A10,'Wells Fargo'!$A:$A,D$1,'Wells Fargo'!$B:$B,"<="&'Cash Flow'!D$3,'Wells Fargo'!$B:$B,">"&'Cash Flow'!C$3) -> -700 | E10: =SUMIFS('Wells Fargo'!$F:$F,'Wells Fargo'!$G:$G,'Cash Flow'!$A10,'Wells Fargo'!$A:$A,E$1,'Wells Fargo'!$B:$B,"<="&'Cash Flow'!E$3,'Wells Fargo'!$B:$B,">"&'Cash Flow'!D$3) -> -729.23 | F10: =SUMIFS('Wells Fargo'!$F:$F,'Wells Fargo'!$G:$G,'Cash Flow'!$A10,'Wells Fargo'!$A:$A,F$1,'Wells Fargo'!$B:$B,"<="&'Cash Flow'!F$3,'Wells Fargo'!$B:$B,">"&'Cash Flow'!E$3) -> 0 | G10: =SUMIFS('Wells Fargo'!$F:$F,'Wells Fargo'!$G:$G,'Cash Flow'!$A10,'Wells Fargo'!$A:$A,G$1,'Wells Fargo'!$B:$B,"<="&'Cash Flow'!G$3,'Wells Fargo'!$B:$B,">"&'Cash Flow'!F$3) -> 0 | H10: =SUMIFS('Wells Fargo'!$F:$F,'Wells Fargo'!$G:$G,'Cash Flow'!$A10,'Wells Fargo'!$A:$A,H$1,'Wells Fargo'!$B:$B,"<="&'Cash Flow'!H$3) -> -157.47 | I10: =SUMIFS('Wells Fargo'!$F:$F,'Wells Fargo'!$G:$G,'Cash Flow'!$A10,'Wells Fargo'!$A:$A,I$1,'Wells Fargo'!$B:$B,"<="&'Cash Flow'!I$3,'Wells Fargo'!$B:$B,">"&'Cash Flow'!H$3) -> -715.37 | J10: =SUMIFS('Wells Fargo'!$F:$F,'Wells Fargo'!$G:$G,'Cash Flow'!$A10,'Wells Fargo'!$A:$A,J$1,'Wells Fargo'!$B:$B,"<="&'Cash Flow'!J$3,'Wells Fargo'!$B:$B,">"&'Cash Flow'!I$3) -> 0 | K10: =SUMIFS('Wells Fargo'!$F:$F,'Wells Fargo'!$G:$G,'Cash Flow'!$A10,'Wells Fargo'!$A:$A,K$1,'Wells Fargo'!$B:$B,"<="&'Cash Flow'!K$3,'Wells Fargo'!$B:$B,">"&'Cash Flow'!J$3) -> -770.55 | L10: =SUMIFS('Wells Fargo'!$F:$F,'Wells Fargo'!$G:$G,'Cash Flow'!$A10,'Wells Fargo'!$A:$A,L$1,'Wells Fargo'!$B:$B,"<="&'Cash Flow'!L$3) -> 0 | M10: =SUMIFS('Wells Fargo'!$F:$F,'Wells Fargo'!$G:$G,'Cash Flow'!$A10,'Wells Fargo'!$A:$A,M$1,'Wells Fargo'!$B:$B,"<="&'Cash Flow'!M$3,'Wells Fargo'!$B:$B,">"&'Cash Flow'!L$3) -> -1160.38 | N10: =SUMIFS('Wells Fargo'!$F:$F,'Wells Fargo'!$G:$G,'Cash Flow'!$A10,'Wells Fargo'!$A:$A,N$1,'Wells Fargo'!$B:$B,"<="&'Cash Flow'!N$3,'Wells Fargo'!$B:$B,">"&'Cash Flow'!M$3) -> -521.61 | O10: =SUMIFS('Wells Fargo'!$F:$F,'Wells Fargo'!$G:$G,'Cash Flow'!$A10,'Wells Fargo'!$A:$A,O$1,'Wells Fargo'!$B:$B,"<="&'Cash Flow'!O$3,'Wells Fargo'!$B:$B,">"&'Cash Flow'!N$3) -> -264.6 | P10: =SUMIFS('Wells Fargo'!$F:$F,'Wells Fargo'!$G:$G,'Cash Flow'!$A10,'Wells Fargo'!$A:$A,P$1,'Wells Fargo'!$B:$B,"<="&'Cash Flow'!P$3,'Wells Fargo'!$B:$B,">"&'Cash Flow'!O$3) -> -465.03 | Q10: =SUMIFS('Wells Fargo'!$F:$F,'Wells Fargo'!$G:$G,'Cash Flow'!$A10,'Wells Fargo'!$A:$A,Q$1,'Wells Fargo'!$B:$B,"<="&'Cash Flow'!Q$3) -> 0 | R10: =SUMIFS('Wells Fargo'!$F:$F,'Wells Fargo'!$G:$G,'Cash Flow'!$A10,'Wells Fargo'!$A:$A,R$1,'Wells Fargo'!$B:$B,"<="&'Cash Flow'!R$3,'Wells Fargo'!$B:$B,">"&'Cash Flow'!Q$3) -> -450.02 | S10: =SUMIFS('Wells Fargo'!$F:$F,'Wells Fargo'!$G:$G,'Cash Flow'!$A10,'Wells Fargo'!$A:$A,S$1,'Wells Fargo'!$B:$B,"<="&'Cash Flow'!S$3,'Wells Fargo'!$B:$B,">"&'Cash Flow'!R$3) -> 0 | T10: =SUMIFS('Wells Fargo'!$F:$F,'Wells Fargo'!$G:$G,'Cash Flow'!$A10,'Wells Fargo'!$A:$A,T$1,'Wells Fargo'!$B:$B,"<="&'Cash Flow'!T$3,'Wells Fargo'!$B:$B,">"&'Cash Flow'!S$3) -> 0 | U10: =SUMIFS('Wells Fargo'!$F:$F,'Wells Fargo'!$G:$G,'Cash Flow'!$A10,'Wells Fargo'!$A:$A,U$1,'Wells Fargo'!$B:$B,"<="&'Cash Flow'!U$3,'Wells Fargo'!$B:$B,">"&'Cash Flow'!T$3) -> 0 | V10: =SUMIFS('Wells Fargo'!$F:$F,'Wells Fargo'!$G:$G,'Cash Flow'!$A10,'Wells Fargo'!$A:$A,V$1,'Wells Fargo'!$B:$B,"<="&'Cash Flow'!V$3) -> -1404.1 | W10: =SUMIFS('Wells Fargo'!$F:$F,'Wells Fargo'!$G:$G,'Cash Flow'!$A10,'Wells Fargo'!$A:$A,W$1,'Wells Fargo'!$B:$B,"<="&'Cash Flow'!W$3,'Wells Fargo'!$B:$B,">"&'Cash Flow'!V$3) -> 0 | X10: =SUMIFS('Wells Fargo'!$F:$F,'Wells Fargo'!$G:$G,'Cash Flow'!$A10,'Wells Fargo'!$A:$A,X$1,'Wells Fargo'!$B:$B,"<="&'Cash Flow'!X$3,'Wells Fargo'!$B:$B,">"&'Cash Flow'!W$3) -> 0 | Y10: =SUMIFS('Wells Fargo'!$F:$F,'Wells Fargo'!$G:$G,'Cash Flow'!$A10,'Wells Fargo'!$A:$A,Y$1,'Wells Fargo'!$B:$B,"<="&'Cash Flow'!Y$3,'Wells Fargo'!$B:$B,">"&'Cash Flow'!X$3) -> -1412.32 | Z10: =SUMIFS('Wells Fargo'!$F:$F,'Wells Fargo'!$G:$G,'Cash Flow'!$A10,'Wells Fargo'!$A:$A,Z$1,'Wells Fargo'!$B:$B,"<="&'Cash Flow'!Z$3,'Wells Fargo'!$B:$B,">"&'Cash Flow'!Y$3) -> 0 | AA10: =SUMIFS('Wells Fargo'!$F:$F,'Wells Fargo'!$G:$G,'Cash Flow'!$A10,'Wells Fargo'!$A:$A,AA$1,'Wells Fargo'!$B:$B,"<="&'Cash Flow'!AA$3) -> 0 | AB10: =SUMIFS('Wells Fargo'!$F:$F,'Wells Fargo'!$G:$G,'Cash Flow'!$A10,'Wells Fargo'!$A:$A,AB$1,'Wells Fargo'!$B:$B,"<="&'Cash Flow'!AB$3,'Wells Fargo'!$B:$B,">"&'Cash Flow'!AA$3) -> -1368.32 | AC10: =SUMIFS('Wells Fargo'!$F:$F,'Wells Fargo'!$G:$G,'Cash Flow'!$A10,'Wells Fargo'!$A:$A,AC$1,'Wells Fargo'!$B:$B,"<="&'Cash Flow'!AC$3,'Wells Fargo'!$B:$B,">"&'Cash Flow'!AB$3) -> 0 | AD10: =SUMIFS('Wells Fargo'!$F:$F,'Wells Fargo'!$G:$G,'Cash Flow'!$A10,'Wells Fargo'!$A:$A,AD$1,'Wells Fargo'!$B:$B,"<="&'Cash Flow'!AD$3,'Wells Fargo'!$B:$B,">"&'Cash Flow'!AC$3) -> -1869 | AE10: =SUMIFS('Wells Fargo'!$F:$F,'Wells Fargo'!$G:$G,'Cash Flow'!$A10,'Wells Fargo'!$A:$A,AE$1,'Wells Fargo'!$B:$B,"<="&'Cash Flow'!AE$3,'Wells Fargo'!$B:$B,">"&'Cash Flow'!AD$3) -> 0 | AF10: =SUMIFS('Wells Fargo'!$F:$F,'Wells Fargo'!$G:$G,'Cash Flow'!$A10,'Wells Fargo'!$A:$A,AF$1,'Wells Fargo'!$B:$B,"<="&'Cash Flow'!AF$3) -> -871.96 | AG10: =SUMIFS('Wells Fargo'!$F:$F,'Wells Fargo'!$G:$G,'Cash Flow'!$A10,'Wells Fargo'!$A:$A,AG$1,'Wells Fargo'!$B:$B,"<="&'Cash Flow'!AG$3,'Wells Fargo'!$B:$B,">"&'Cash Flow'!AF$3) -> -2317.37 | AH10: =SUMIFS('Wells Fargo'!$F:$F,'Wells Fargo'!$G:$G,'Cash Flow'!$A10,'Wells Fargo'!$A:$A,AH$1,'Wells Fargo'!$B:$B,"<="&'Cash Flow'!AH$3,'Wells Fargo'!$B:$B,">"&'Cash Flow'!AG$3) -> 0 | AI10: =SUMIFS('Wells Fargo'!$F:$F,'Wells Fargo'!$G:$G,'Cash Flow'!$A10,'Wells Fargo'!$A:$A,AI$1,'Wells Fargo'!$B:$B,"<="&'Cash Flow'!AI$3,'Wells Fargo'!$B:$B,">"&'Cash Flow'!AH$3) -> 0 | AJ10: =SUMIFS('Wells Fargo'!$F:$F,'Wells Fargo'!$G:$G,'Cash Flow'!$A10,'Wells Fargo'!$A:$A,AJ$1,'Wells Fargo'!$B:$B,"<="&'Cash Flow'!AJ$3,'Wells Fargo'!$B:$B,">"&'Cash Flow'!AI$3) -> 0 | AK10: =SUMIFS('Wells Fargo'!$F:$F,'Wells Fargo'!$G:$G,'Cash Flow'!$A10,'Wells Fargo'!$A:$A,AK$1,'Wells Fargo'!$B:$B,"<="&'Cash Flow'!AK$3) -> 0 | AL10: =SUMIFS('Wells Fargo'!$F:$F,'Wells Fargo'!$G:$G,'Cash Flow'!$A10,'Wells Fargo'!$A:$A,AL$1,'Wells Fargo'!$B:$B,"<="&'Cash Flow'!AL$3,'Wells Fargo'!$B:$B,">"&'Cash Flow'!AK$3) -> 0 | AM10: =SUMIFS('Wells Fargo'!$F:$F,'Wells Fargo'!$G:$G,'Cash Flow'!$A10,'Wells Fargo'!$A:$A,AM$1,'Wells Fargo'!$B:$B,"<="&'Cash Flow'!AM$3,'Wells Fargo'!$B:$B,">"&'Cash Flow'!AL$3) -> 0 | AN10: =SUMIFS('Wells Fargo'!$F:$F,'Wells Fargo'!$G:$G,'Cash Flow'!$A10,'Wells Fargo'!$A:$A,AN$1,'Wells Fargo'!$B:$B,"<="&'Cash Flow'!AN$3,'Wells Fargo'!$B:$B,">"&'Cash Flow'!AM$3) -> 0 | AO10: =SUMIFS('Wells Fargo'!$F:$F,'Wells Fargo'!$G:$G,'Cash Flow'!$A10,'Wells Fargo'!$A:$A,AO$1,'Wells Fargo'!$B:$B,"<="&'Cash Flow'!AO$3,'Wells Fargo'!$B:$B,">"&'Cash Flow'!AN$3) -> 0 | AP10: =SUMIFS('Wells Fargo'!$F:$F,'Wells Fargo'!$G:$G,'Cash Flow'!$A10,'Wells Fargo'!$A:$A,AP$1,'Wells Fargo'!$B:$B,"<="&'Cash Flow'!AP$3) -> 0 | AQ10: =SUMIFS('Wells Fargo'!$F:$F,'Wells Fargo'!$G:$G,'Cash Flow'!$A10,'Wells Fargo'!$A:$A,AQ$1,'Wells Fargo'!$B:$B,"<="&'Cash Flow'!AQ$3,'Wells Fargo'!$B:$B,">"&'Cash Flow'!AP$3) -> 0 | AR10: =SUMIFS('Wells Fargo'!$F:$F,'Wells Fargo'!$G:$G,'Cash Flow'!$A10,'Wells Fargo'!$A:$A,AR$1,'Wells Fargo'!$B:$B,"<="&'Cash Flow'!AR$3,'Wells Fargo'!$B:$B,">"&'Cash Flow'!AQ$3) -> 0 | AS10: =SUMIFS('Wells Fargo'!$F:$F,'Wells Fargo'!$G:$G,'Cash Flow'!$A10,'Wells Fargo'!$A:$A,AS$1,'Wells Fargo'!$B:$B,"<="&'Cash Flow'!AS$3,'Wells Fargo'!$B:$B,">"&'Cash Flow'!AR$3) -> 0 | AT10: =SUMIFS('Wells Fargo'!$F:$F,'Wells Fargo'!$G:$G,'Cash Flow'!$A10,'Wells Fargo'!$A:$A,AT$1,'Wells Fargo'!$B:$B,"<="&'Cash Flow'!AT$3,'Wells Fargo'!$B:$B,">"&'Cash Flow'!AS$3) -> 0 | AU10: =SUMIFS('Wells Fargo'!$F:$F,'Wells Fargo'!$G:$G,'Cash Flow'!$A10,'Wells Fargo'!$A:$A,AU$1,'Wells Fargo'!$B:$B,"<="&'Cash Flow'!AU$3) -> 0 | AV10: =SUMIFS('Wells Fargo'!$F:$F,'Wells Fargo'!$G:$G,'Cash Flow'!$A10,'Wells Fargo'!$A:$A,AV$1,'Wells Fargo'!$B:$B,"<="&'Cash Flow'!AV$3,'Wells Fargo'!$B:$B,">"&'Cash Flow'!AU$3) -> 0 | AW10: =SUMIFS('Wells Fargo'!$F:$F,'Wells Fargo'!$G:$G,'Cash Flow'!$A10,'Wells Fargo'!$A:$A,AW$1,'Wells Fargo'!$B:$B,"<="&'Cash Flow'!AW$3,'Wells Fargo'!$B:$B,">"&'Cash Flow'!AV$3) -> 0 | AX10: =SUMIFS('Wells Fargo'!$F:$F,'Wells Fargo'!$G:$G,'Cash Flow'!$A10,'Wells Fargo'!$A:$A,AX$1,'Wells Fargo'!$B:$B,"<="&'Cash Flow'!AX$3,'Wells Fargo'!$B:$B,">"&'Cash Flow'!AW$3) -> 0 | AY10: =SUMIFS('Wells Fargo'!$F:$F,'Wells Fargo'!$G:$G,'Cash Flow'!$A10,'Wells Fargo'!$A:$A,AY$1,'Wells Fargo'!$B:$B,"<="&'Cash Flow'!AY$3,'Wells Fargo'!$B:$B,">"&'Cash Flow'!AX$3) -> 0 | AZ10: =SUMIFS('Wells Fargo'!$F:$F,'Wells Fargo'!$G:$G,'Cash Flow'!$A10,'Wells Fargo'!$A:$A,AZ$1,'Wells Fargo'!$B:$B,"<="&'Cash Flow'!AZ$3) -> 0 | BA10: =SUMIFS('Wells Fargo'!$F:$F,'Wells Fargo'!$G:$G,'Cash Flow'!$A10,'Wells Fargo'!$A:$A,BA$1,'Wells Fargo'!$B:$B,"<="&'Cash Flow'!BA$3,'Wells Fargo'!$B:$B,">"&'Cash Flow'!AZ$3) -> 0 | BB10: =SUMIFS('Wells Fargo'!$F:$F,'Wells Fargo'!$G:$G,'Cash Flow'!$A10,'Wells Fargo'!$A:$A,BB$1,'Wells Fargo'!$B:$B,"<="&'Cash Flow'!BB$3,'Wells Fargo'!$B:$B,">"&'Cash Flow'!BA$3) -> 0 | BC10: =SUMIFS('Wells Fargo'!$F:$F,'Wells Fargo'!$G:$G,'Cash Flow'!$A10,'Wells Fargo'!$A:$A,BC$1,'Wells Fargo'!$B:$B,"<="&'Cash Flow'!BC$3,'Wells Fargo'!$B:$B,">"&'Cash Flow'!BB$3) -> 0 | BD10: =SUMIFS('Wells Fargo'!$F:$F,'Wells Fargo'!$G:$G,'Cash Flow'!$A10,'Wells Fargo'!$A:$A,BD$1,'Wells Fargo'!$B:$B,"<="&'Cash Flow'!BD$3,'Wells Fargo'!$B:$B,">"&'Cash Flow'!BC$3) -> 0 | BE10: =SUMIFS('Wells Fargo'!$F:$F,'Wells Fargo'!$G:$G,'Cash Flow'!$A10,'Wells Fargo'!$A:$A,BE$1,'Wells Fargo'!$B:$B,"<="&'Cash Flow'!BE$3) -> 0 | BF10: =SUMIFS('Wells Fargo'!$F:$F,'Wells Fargo'!$G:$G,'Cash Flow'!$A10,'Wells Fargo'!$A:$A,BF$1,'Wells Fargo'!$B:$B,"<="&'Cash Flow'!BF$3,'Wells Fargo'!$B:$B,">"&'Cash Flow'!BE$3) -> 0 | BG10: =SUMIFS('Wells Fargo'!$F:$F,'Wells Fargo'!$G:$G,'Cash Flow'!$A10,'Wells Fargo'!$A:$A,BG$1,'Wells Fargo'!$B:$B,"<="&'Cash Flow'!BG$3,'Wells Fargo'!$B:$B,">"&'Cash Flow'!BF$3) -> 0 | BH10: =SUMIFS('Wells Fargo'!$F:$F,'Wells Fargo'!$G:$G,'Cash Flow'!$A10,'Wells Fargo'!$A:$A,BH$1,'Wells Fargo'!$B:$B,"<="&'Cash Flow'!BH$3,'Wells Fargo'!$B:$B,">"&'Cash Flow'!BG$3) -> 0 | BI10: =SUMIFS('Wells Fargo'!$F:$F,'Wells Fargo'!$G:$G,'Cash Flow'!$A10,'Wells Fargo'!$A:$A,BI$1,'Wells Fargo'!$B:$B,"<="&'Cash Flow'!BI$3,'Wells Fargo'!$B:$B,">"&'Cash Flow'!BH$3) -> 0
A11: Credit Karma | B11: =SUM(C11:BI11) -> -1 | C11: =SUMIFS('Wells Fargo'!$F:$F,'Wells Fargo'!$G:$G,'Cash Flow'!$A11,'Wells Fargo'!$A:$A,C$1,'Wells Fargo'!$B:$B,"<="&'Cash Flow'!C$3) -> 0 | D11: =SUMIFS('Wells Fargo'!$F:$F,'Wells Fargo'!$G:$G,'Cash Flow'!$A11,'Wells Fargo'!$A:$A,D$1,'Wells Fargo'!$B:$B,"<="&'Cash Flow'!D$3,'Wells Fargo'!$B:$B,">"&'Cash Flow'!C$3) -> 0 | E11: =SUMIFS('Wells Fargo'!$F:$F,'Wells Fargo'!$G:$G,'Cash Flow'!$A11,'Wells Fargo'!$A:$A,E$1,'Wells Fargo'!$B:$B,"<="&'Cash Flow'!E$3,'Wells Fargo'!$B:$B,">"&'Cash Flow'!D$3) -> 0 | F11: =SUMIFS('Wells Fargo'!$F:$F,'Wells Fargo'!$G:$G,'Cash Flow'!$A11,'Wells Fargo'!$A:$A,F$1,'Wells Fargo'!$B:$B,"<="&'Cash Flow'!F$3,'Wells Fargo'!$B:$B,">"&'Cash Flow'!E$3) -> 0 | G11: =SUMIFS('Wells Fargo'!$F:$F,'Wells Fargo'!$G:$G,'Cash Flow'!$A11,'Wells Fargo'!$A:$A,G$1,'Wells Fargo'!$B:$B,"<="&'Cash Flow'!G$3,'Wells Fargo'!$B:$B,">"&'Cash Flow'!F$3) -> 0 | H11: =SUMIFS('Wells Fargo'!$F:$F,'Wells Fargo'!$G:$G,'Cash Flow'!$A11,'Wells Fargo'!$A:$A,H$1,'Wells Fargo'!$B:$B,"<="&'Cash Flow'!H$3) -> -1 | I11: =SUMIFS('Wells Fargo'!$F:$F,'Wells Fargo'!$G:$G,'Cash Flow'!$A11,'Wells Fargo'!$A:$A,I$1,'Wells Fargo'!$B:$B,"<="&'Cash Flow'!I$3,'Wells Fargo'!$B:$B,">"&'Cash Flow'!H$3) -> 0 | J11: =SUMIFS('Wells Fargo'!$F:$F,'Wells Fargo'!$G:$G,'Cash Flow'!$A11,'Wells Fargo'!$A:$A,J$1,'Wells Fargo'!$B:$B,"<="&'Cash Flow'!J$3,'Wells Fargo'!$B:$B,">"&'Cash Flow'!I$3) -> 0 | K11: =SUMIFS('Wells Fargo'!$F:$F,'Wells Fargo'!$G:$G,'Cash Flow'!$A11,'Wells Fargo'!$A:$A,K$1,'Wells Fargo'!$B:$B,"<="&'Cash Flow'!K$3,'Wells Fargo'!$B:$B,">"&'Cash Flow'!J$3) -> 0 | L11: =SUMIFS('Wells Fargo'!$F:$F,'Wells Fargo'!$G:$G,'Cash Flow'!$A11,'Wells Fargo'!$A:$A,L$1,'Wells Fargo'!$B:$B,"<="&'Cash Flow'!L$3) -> 0 | M11: =SUMIFS('Wells Fargo'!$F:$F,'Wells Fargo'!$G:$G,'Cash Flow'!$A11,'Wells Fargo'!$A:$A,M$1,'Wells Fargo'!$B:$B,"<="&'Cash Flow'!M$3,'Wells Fargo'!$B:$B,">"&'Cash Flow'!L$3) -> 0 | N11: =SUMIFS('Wells Fargo'!$F:$F,'Wells Fargo'!$G:$G,'Cash Flow'!$A11,'Wells Fargo'!$A:$A,N$1,'Wells Fargo'!$B:$B,"<="&'Cash Flow'!N$3,'Wells Fargo'!$B:$B,">"&'Cash Flow'!M$3) -> 0 | O11: =SUMIFS('Wells Fargo'!$F:$F,'Wells Fargo'!$G:$G,'Cash Flow'!$A11,'Wells Fargo'!$A:$A,O$1,'Wells Fargo'!$B:$B,"<="&'Cash Flow'!O$3,'Wells Fargo'!$B:$B,">"&'Cash Flow'!N$3) -> 0 | P11: =SUMIFS('Wells Fargo'!$F:$F,'Wells Fargo'!$G:$G,'Cash Flow'!$A11,'Wells Fargo'!$A:$A,P$1,'Wells Fargo'!$B:$B,"<="&'Cash Flow'!P$3,'Wells Fargo'!$B:$B,">"&'Cash Flow'!O$3) -> 0 | Q11: =SUMIFS('Wells Fargo'!$F:$F,'Wells Fargo'!$G:$G,'Cash Flow'!$A11,'Wells Fargo'!$A:$A,Q$1,'Wells Fargo'!$B:$B,"<="&'Cash Flow'!Q$3) -> 0 | R11: =SUMIFS('Wells Fargo'!$F:$F,'Wells Fargo'!$G:$G,'Cash Flow'!$A11,'Wells Fargo'!$A:$A,R$1,'Wells Fargo'!$B:$B,"<="&'Cash Flow'!R$3,'Wells Fargo'!$B:$B,">"&'Cash Flow'!Q$3) -> 0 | S11: =SUMIFS('Wells Fargo'!$F:$F,'Wells Fargo'!$G:$G,'Cash Flow'!$A11,'Wells Fargo'!$A:$A,S$1,'Wells Fargo'!$B:$B,"<="&'Cash Flow'!S$3,'Wells Fargo'!$B:$B,">"&'Cash Flow'!R$3) -> 0 | T11: =SUMIFS('Wells Fargo'!$F:$F,'Wells Fargo'!$G:$G,'Cash Flow'!$A11,'Wells Fargo'!$A:$A,T$1,'Wells Fargo'!$B:$B,"<="&'Cash Flow'!T$3,'Wells Fargo'!$B:$B,">"&'Cash Flow'!S$3) -> 0 | U11: =SUMIFS('Wells Fargo'!$F:$F,'Wells Fargo'!$G:$G,'Cash Flow'!$A11,'Wells Fargo'!$A:$A,U$1,'Wells Fargo'!$B:$B,"<="&'Cash Flow'!U$3,'Wells Fargo'!$B:$B,">"&'Cash Flow'!T$3) -> 0 | V11: =SUMIFS('Wells Fargo'!$F:$F,'Wells Fargo'!$G:$G,'Cash Flow'!$A11,'Wells Fargo'!$A:$A,V$1,'Wells Fargo'!$B:$B,"<="&'Cash Flow'!V$3) -> 0 | W11: =SUMIFS('Wells Fargo'!$F:$F,'Wells Fargo'!$G:$G,'Cash Flow'!$A11,'Wells Fargo'!$A:$A,W$1,'Wells Fargo'!$B:$B,"<="&'Cash Flow'!W$3,'Wells Fargo'!$B:$B,">"&'Cash Flow'!V$3) -> 0 | X11: =SUMIFS('Wells Fargo'!$F:$F,'Wells Fargo'!$G:$G,'Cash Flow'!$A11,'Wells Fargo'!$A:$A,X$1,'Wells Fargo'!$B:$B,"<="&'Cash Flow'!X$3,'Wells Fargo'!$B:$B,">"&'Cash Flow'!W$3) -> 0 | Y11: =SUMIFS('Wells Fargo'!$F:$F,'Wells Fargo'!$G:$G,'Cash Flow'!$A11,'Wells Fargo'!$A:$A,Y$1,'Wells Fargo'!$B:$B,"<="&'Cash Flow'!Y$3,'Wells Fargo'!$B:$B,">"&'Cash Flow'!X$3) -> 0 | Z11: =SUMIFS('Wells Fargo'!$F:$F,'Wells Fargo'!$G:$G,'Cash Flow'!$A11,'Wells Fargo'!$A:$A,Z$1,'Wells Fargo'!$B:$B,"<="&'Cash Flow'!Z$3,'Wells Fargo'!$B:$B,">"&'Cash Flow'!Y$3) -> 0 | AA11: =SUMIFS('Wells Fargo'!$F:$F,'Wells Fargo'!$G:$G,'Cash Flow'!$A11,'Wells Fargo'!$A:$A,AA$1,'Wells Fargo'!$B:$B,"<="&'Cash Flow'!AA$3) -> 0 | AB11: =SUMIFS('Wells Fargo'!$F:$F,'Wells Fargo'!$G:$G,'Cash Flow'!$A11,'Wells Fargo'!$A:$A,AB$1,'Wells Fargo'!$B:$B,"<="&'Cash Flow'!AB$3,'Wells Fargo'!$B:$B,">"&'Cash Flow'!AA$3) -> 0 | AC11: =SUMIFS('Wells Fargo'!$F:$F,'Wells Fargo'!$G:$G,'Cash Flow'!$A11,'Wells Fargo'!$A:$A,AC$1,'Wells Fargo'!$B:$B,"<="&'Cash Flow'!AC$3,'Wells Fargo'!$B:$B,">"&'Cash Flow'!AB$3) -> 0 | AD11: =SUMIFS('Wells Fargo'!$F:$F,'Wells Fargo'!$G:$G,'Cash Flow'!$A11,'Wells Fargo'!$A:$A,AD$1,'Wells Fargo'!$B:$B,"<="&'Cash Flow'!AD$3,'Wells Fargo'!$B:$B,">"&'Cash Flow'!AC$3) -> 0 | AE11: =SUMIFS('Wells Fargo'!$F:$F,'Wells Fargo'!$G:$G,'Cash Flow'!$A11,'Wells Fargo'!$A:$A,AE$1,'Wells Fargo'!$B:$B,"<="&'Cash Flow'!AE$3,'Wells Fargo'!$B:$B,">"&'Cash Flow'!AD$3) -> 0 | AF11: =SUMIFS('Wells Fargo'!$F:$F,'Wells Fargo'!$G:$G,'Cash Flow'!$A11,'Wells Fargo'!$A:$A,AF$1,'Wells Fargo'!$B:$B,"<="&'Cash Flow'!AF$3) -> 0 | AG11: =SUMIFS('Wells Fargo'!$F:$F,'Wells Fargo'!$G:$G,'Cash Flow'!$A11,'Wells Fargo'!$A:$A,AG$1,'Wells Fargo'!$B:$B,"<="&'Cash Flow'!AG$3,'Wells Fargo'!$B:$B,">"&'Cash Flow'!AF$3) -> 0 | AH11: =SUMIFS('Wells Fargo'!$F:$F,'Wells Fargo'!$G:$G,'Cash Flow'!$A11,'Wells Fargo'!$A:$A,AH$1,'Wells Fargo'!$B:$B,"<="&'Cash Flow'!AH$3,'Wells Fargo'!$B:$B,">"&'Cash Flow'!AG$3) -> 0 | AI11: =SUMIFS('Wells Fargo'!$F:$F,'Wells Fargo'!$G:$G,'Cash Flow'!$A11,'Wells Fargo'!$A:$A,AI$1,'Wells Fargo'!$B:$B,"<="&'Cash Flow'!AI$3,'Wells Fargo'!$B:$B,">"&'Cash Flow'!AH$3) -> 0 | AJ11: =SUMIFS('Wells Fargo'!$F:$F,'Wells Fargo'!$G:$G,'Cash Flow'!$A11,'Wells Fargo'!$A:$A,AJ$1,'Wells Fargo'!$B:$B,"<="&'Cash Flow'!AJ$3,'Wells Fargo'!$B:$B,">"&'Cash Flow'!AI$3) -> 0 | AK11: =SUMIFS('Wells Fargo'!$F:$F,'Wells Fargo'!$G:$G,'Cash Flow'!$A11,'Wells Fargo'!$A:$A,AK$1,'Wells Fargo'!$B:$B,"<="&'Cash Flow'!AK$3) -> 0 | AL11: =SUMIFS('Wells Fargo'!$F:$F,'Wells Fargo'!$G:$G,'Cash Flow'!$A11,'Wells Fargo'!$A:$A,AL$1,'Wells Fargo'!$B:$B,"<="&'Cash Flow'!AL$3,'Wells Fargo'!$B:$B,">"&'Cash Flow'!AK$3) -> 0 | AM11: =SUMIFS('Wells Fargo'!$F:$F,'Wells Fargo'!$G:$G,'Cash Flow'!$A11,'Wells Fargo'!$A:$A,AM$1,'Wells Fargo'!$B:$B,"<="&'Cash Flow'!AM$3,'Wells Fargo'!$B:$B,">"&'Cash Flow'!AL$3) -> 0 | AN11: =SUMIFS('Wells Fargo'!$F:$F,'Wells Fargo'!$G:$G,'Cash Flow'!$A11,'Wells Fargo'!$A:$A,AN$1,'Wells Fargo'!$B:$B,"<="&'Cash Flow'!AN$3,'Wells Fargo'!$B:$B,">"&'Cash Flow'!AM$3) -> 0 | AO11: =SUMIFS('Wells Fargo'!$F:$F,'Wells Fargo'!$G:$G,'Cash Flow'!$A11,'Wells Fargo'!$A:$A,AO$1,'Wells Fargo'!$B:$B,"<="&'Cash Flow'!AO$3,'Wells Fargo'!$B:$B,">"&'Cash Flow'!AN$3) -> 0 | AP11: =SUMIFS('Wells Fargo'!$F:$F,'Wells Fargo'!$G:$G,'Cash Flow'!$A11,'Wells Fargo'!$A:$A,AP$1,'Wells Fargo'!$B:$B,"<="&'Cash Flow'!AP$3) -> 0 | AQ11: =SUMIFS('Wells Fargo'!$F:$F,'Wells Fargo'!$G:$G,'Cash Flow'!$A11,'Wells Fargo'!$A:$A,AQ$1,'Wells Fargo'!$B:$B,"<="&'Cash Flow'!AQ$3,'Wells Fargo'!$B:$B,">"&'Cash Flow'!AP$3) -> 0 | AR11: =SUMIFS('Wells Fargo'!$F:$F,'Wells Fargo'!$G:$G,'Cash Flow'!$A11,'Wells Fargo'!$A:$A,AR$1,'Wells Fargo'!$B:$B,"<="&'Cash Flow'!AR$3,'Wells Fargo'!$B:$B,">"&'Cash Flow'!AQ$3) -> 0 | AS11: =SUMIFS('Wells Fargo'!$F:$F,'Wells Fargo'!$G:$G,'Cash Flow'!$A11,'Wells Fargo'!$A:$A,AS$1,'Wells Fargo'!$B:$B,"<="&'Cash Flow'!AS$3,'Wells Fargo'!$B:$B,">"&'Cash Flow'!AR$3) -> 0 | AT11: =SUMIFS('Wells Fargo'!$F:$F,'Wells Fargo'!$G:$G,'Cash Flow'!$A11,'Wells Fargo'!$A:$A,AT$1,'Wells Fargo'!$B:$B,"<="&'Cash Flow'!AT$3,'Wells Fargo'!$B:$B,">"&'Cash Flow'!AS$3) -> 0 | AU11: =SUMIFS('Wells Fargo'!$F:$F,'Wells Fargo'!$G:$G,'Cash Flow'!$A11,'Wells Fargo'!$A:$A,AU$1,'Wells Fargo'!$B:$B,"<="&'Cash Flow'!AU$3) -> 0 | AV11: =SUMIFS('Wells Fargo'!$F:$F,'Wells Fargo'!$G:$G,'Cash Flow'!$A11,'Wells Fargo'!$A:$A,AV$1,'Wells Fargo'!$B:$B,"<="&'Cash Flow'!AV$3,'Wells Fargo'!$B:$B,">"&'Cash Flow'!AU$3) -> 0 | AW11: =SUMIFS('Wells Fargo'!$F:$F,'Wells Fargo'!$G:$G,'Cash Flow'!$A11,'Wells Fargo'!$A:$A,AW$1,'Wells Fargo'!$B:$B,"<="&'Cash Flow'!AW$3,'Wells Fargo'!$B:$B,">"&'Cash Flow'!AV$3) -> 0 | AX11: =SUMIFS('Wells Fargo'!$F:$F,'Wells Fargo'!$G:$G,'Cash Flow'!$A11,'Wells Fargo'!$A:$A,AX$1,'Wells Fargo'!$B:$B,"<="&'Cash Flow'!AX$3,'Wells Fargo'!$B:$B,">"&'Cash Flow'!AW$3) -> 0 | AY11: =SUMIFS('Wells Fargo'!$F:$F,'Wells Fargo'!$G:$G,'Cash Flow'!$A11,'Wells Fargo'!$A:$A,AY$1,'Wells Fargo'!$B:$B,"<="&'Cash Flow'!AY$3,'Wells Fargo'!$B:$B,">"&'Cash Flow'!AX$3) -> 0 | AZ11: =SUMIFS('Wells Fargo'!$F:$F,'Wells Fargo'!$G:$G,'Cash Flow'!$A11,'Wells Fargo'!$A:$A,AZ$1,'Wells Fargo'!$B:$B,"<="&'Cash Flow'!AZ$3) -> 0 | BA11: =SUMIFS('Wells Fargo'!$F:$F,'Wells Fargo'!$G:$G,'Cash Flow'!$A11,'Wells Fargo'!$A:$A,BA$1,'Wells Fargo'!$B:$B,"<="&'Cash Flow'!BA$3,'Wells Fargo'!$B:$B,">"&'Cash Flow'!AZ$3) -> 0 | BB11: =SUMIFS('Wells Fargo'!$F:$F,'Wells Fargo'!$G:$G,'Cash Flow'!$A11,'Wells Fargo'!$A:$A,BB$1,'Wells Fargo'!$B:$B,"<="&'Cash Flow'!BB$3,'Wells Fargo'!$B:$B,">"&'Cash Flow'!BA$3) -> 0 | BC11: =SUMIFS('Wells Fargo'!$F:$F,'Wells Fargo'!$G:$G,'Cash Flow'!$A11,'Wells Fargo'!$A:$A,BC$1,'Wells Fargo'!$B:$B,"<="&'Cash Flow'!BC$3,'Wells Fargo'!$B:$B,">"&'Cash Flow'!BB$3) -> 0 | BD11: =SUMIFS('Wells Fargo'!$F:$F,'Wells Fargo'!$G:$G,'Cash Flow'!$A11,'Wells Fargo'!$A:$A,BD$1,'Wells Fargo'!$B:$B,"<="&'Cash Flow'!BD$3,'Wells Fargo'!$B:$B,">"&'Cash Flow'!BC$3) -> 0 | BE11: =SUMIFS('Wells Fargo'!$F:$F,'Wells Fargo'!$G:$G,'Cash Flow'!$A11,'Wells Fargo'!$A:$A,BE$1,'Wells Fargo'!$B:$B,"<="&'Cash Flow'!BE$3) -> 0 | BF11: =SUMIFS('Wells Fargo'!$F:$F,'Wells Fargo'!$G:$G,'Cash Flow'!$A11,'Wells Fargo'!$A:$A,BF$1,'Wells Fargo'!$B:$B,"<="&'Cash Flow'!BF$3,'Wells Fargo'!$B:$B,">"&'Cash Flow'!BE$3) -> 0 | BG11: =SUMIFS('Wells Fargo'!$F:$F,'Wells Fargo'!$G:$G,'Cash Flow'!$A11,'Wells Fargo'!$A:$A,BG$1,'Wells Fargo'!$B:$B,"<="&'Cash Flow'!BG$3,'Wells Fargo'!$B:$B,">"&'Cash Flow'!BF$3) -> 0 | BH11: =SUMIFS('Wells Fargo'!$F:$F,'Wells Fargo'!$G:$G,'Cash Flow'!$A11,'Wells Fargo'!$A:$A,BH$1,'Wells Fargo'!$B:$B,"<="&'Cash Flow'!BH$3,'Wells Fargo'!$B:$B,">"&'Cash Flow'!BG$3) -> 0 | BI11: =SUMIFS('Wells Fargo'!$F:$F,'Wells Fargo'!$G:$G,'Cash Flow'!$A11,'Wells Fargo'!$A:$A,BI$1,'Wells Fargo'!$B:$B,"<="&'Cash Flow'!BI$3,'Wells Fargo'!$B:$B,">"&'Cash Flow'!BH$3) -> 0
A12: Danny | B12: =SUM(C12:BI12) -> -20 | C12: =SUMIFS('Wells Fargo'!$F:$F,'Wells Fargo'!$G:$G,'Cash Flow'!$A12,'Wells Fargo'!$A:$A,C$1,'Wells Fargo'!$B:$B,"<="&'Cash Flow'!C$3) -> 0 | D12: =SUMIFS('Wells Fargo'!$F:$F,'Wells Fargo'!$G:$G,'Cash Flow'!$A12,'Wells Fargo'!$A:$A,D$1,'Wells Fargo'!$B:$B,"<="&'Cash Flow'!D$3,'Wells Fargo'!$B:$B,">"&'Cash Flow'!C$3) -> 0 | E12: =SUMIFS('Wells Fargo'!$F:$F,'Wells Fargo'!$G:$G,'Cash Flow'!$A12,'Wells Fargo'!$A:$A,E$1,'Wells Fargo'!$B:$B,"<="&'Cash Flow'!E$3,'Wells Fargo'!$B:$B,">"&'Cash Flow'!D$3) -> 0 | F12: =SUMIFS('Wells Fargo'!$F:$F,'Wells Fargo'!$G:$G,'Cash Flow'!$A12,'Wells Fargo'!$A:$A,F$1,'Wells Fargo'!$B:$B,"<="&'Cash Flow'!F$3,'Wells Fargo'!$B:$B,">"&'Cash Flow'!E$3) -> 0 | G12: =SUMIFS('Wells Fargo'!$F:$F,'Wells Fargo'!$G:$G,'Cash Flow'!$A12,'Wells Fargo'!$A:$A,G$1,'Wells Fargo'!$B:$B,"<="&'Cash Flow'!G$3,'Wells Fargo'!$B:$B,">"&'Cash Flow'!F$3) -> 0 | H12: =SUMIFS('Wells Fargo'!$F:$F,'Wells Fargo'!$G:$G,'Cash Flow'!$A12,'Wells Fargo'!$A:$A,H$1,'Wells Fargo'!$B:$B,"<="&'Cash Flow'!H$3) -> 0 | I12: =SUMIFS('Wells Fargo'!$F:$F,'Wells Fargo'!$G:$G,'Cash Flow'!$A12,'Wells Fargo'!$A:$A,I$1,'Wells Fargo'!$B:$B,"<="&'Cash Flow'!I$3,'Wells Fargo'!$B:$B,">"&'Cash Flow'!H$3) -> 0 | J12: =SUMIFS('Wells Fargo'!$F:$F,'Wells Fargo'!$G:$G,'Cash Flow'!$A12,'Wells Fargo'!$A:$A,J$1,'Wells Fargo'!$B:$B,"<="&'Cash Flow'!J$3,'Wells Fargo'!$B:$B,">"&'Cash Flow'!I$3) -> 0 | K12: =SUMIFS('Wells Fargo'!$F:$F,'Wells Fargo'!$G:$G,'Cash Flow'!$A12,'Wells Fargo'!$A:$A,K$1,'Wells Fargo'!$B:$B,"<="&'Cash Flow'!K$3,'Wells Fargo'!$B:$B,">"&'Cash Flow'!J$3) -> 0 | L12: =SUMIFS('Wells Fargo'!$F:$F,'Wells Fargo'!$G:$G,'Cash Flow'!$A12,'Wells Fargo'!$A:$A,L$1,'Wells Fargo'!$B:$B,"<="&'Cash Flow'!L$3) -> 0 | M12: =SUMIFS('Wells Fargo'!$F:$F,'Wells Fargo'!$G:$G,'Cash Flow'!$A12,'Wells Fargo'!$A:$A,M$1,'Wells Fargo'!$B:$B,"<="&'Cash Flow'!M$3,'Wells Fargo'!$B:$B,">"&'Cash Flow'!L$3) -> 0 | N12: =SUMIFS('Wells Fargo'!$F:$F,'Wells Fargo'!$G:$G,'Cash Flow'!$A12,'Wells Fargo'!$A:$A,N$1,'Wells Fargo'!$B:$B,"<="&'Cash Flow'!N$3,'Wells Fargo'!$B:$B,">"&'Cash Flow'!M$3) -> 0 | O12: =SUMIFS('Wells Fargo'!$F:$F,'Wells Fargo'!$G:$G,'Cash Flow'!$A12,'Wells Fargo'!$A:$A,O$1,'Wells Fargo'!$B:$B,"<="&'Cash Flow'!O$3,'Wells Fargo'!$B:$B,">"&'Cash Flow'!N$3) -> 0 | P12: =SUMIFS('Wells Fargo'!$F:$F,'Wells Fargo'!$G:$G,'Cash Flow'!$A12,'Wells Fargo'!$A:$A,P$1,'Wells Fargo'!$B:$B,"<="&'Cash Flow'!P$3,'Wells Fargo'!$B:$B,">"&'Cash Flow'!O$3) -> -20 | Q12: =SUMIFS('Wells Fargo'!$F:$F,'Wells Fargo'!$G:$G,'Cash Flow'!$A12,'Wells Fargo'!$A:$A,Q$1,'Wells Fargo'!$B:$B,"<="&'Cash Flow'!Q$3) -> 0 | R12: =SUMIFS('Wells Fargo'!$F:$F,'Wells Fargo'!$G:$G,'Cash Flow'!$A12,'Wells Fargo'!$A:$A,R$1,'Wells Fargo'!$B:$B,"<="&'Cash Flow'!R$3,'Wells Fargo'!$B:$B,">"&'Cash Flow'!Q$3) -> 0 | S12: =SUMIFS('Wells Fargo'!$F:$F,'Wells Fargo'!$G:$G,'Cash Flow'!$A12,'Wells Fargo'!$A:$A,S$1,'Wells Fargo'!$B:$B,"<="&'Cash Flow'!S$3,'Wells Fargo'!$B:$B,">"&'Cash Flow'!R$3) -> 0 | T12: =SUMIFS('Wells Fargo'!$F:$F,'Wells Fargo'!$G:$G,'Cash Flow'!$A12,'Wells Fargo'!$A:$A,T$1,'Wells Fargo'!$B:$B,"<="&'Cash Flow'!T$3,'Wells Fargo'!$B:$B,">"&'Cash Flow'!S$3) -> 0 | U12: =SUMIFS('Wells Fargo'!$F:$F,'Wells Fargo'!$G:$G,'Cash Flow'!$A12,'Wells Fargo'!$A:$A,U$1,'Wells Fargo'!$B:$B,"<="&'Cash Flow'!U$3,'Wells Fargo'!$B:$B,">"&'Cash Flow'!T$3) -> 0 | V12: =SUMIFS('Wells Fargo'!$F:$F,'Wells Fargo'!$G:$G,'Cash Flow'!$A12,'Wells Fargo'!$A:$A,V$1,'Wells Fargo'!$B:$B,"<="&'Cash Flow'!V$3) -> 0 | W12: =SUMIFS('Wells Fargo'!$F:$F,'Wells Fargo'!$G:$G,'Cash Flow'!$A12,'Wells Fargo'!$A:$A,W$1,'Wells Fargo'!$B:$B,"<="&'Cash Flow'!W$3,'Wells Fargo'!$B:$B,">"&'Cash Flow'!V$3) -> 0 | X12: =SUMIFS('Wells Fargo'!$F:$F,'Wells Fargo'!$G:$G,'Cash Flow'!$A12,'Wells Fargo'!$A:$A,X$1,'Wells Fargo'!$B:$B,"<="&'Cash Flow'!X$3,'Wells Fargo'!$B:$B,">"&'Cash Flow'!W$3) -> 0 | Y12: =SUMIFS('Wells Fargo'!$F:$F,'Wells Fargo'!$G:$G,'Cash Flow'!$A12,'Wells Fargo'!$A:$A,Y$1,'Wells Fargo'!$B:$B,"<="&'Cash Flow'!Y$3,'Wells Fargo'!$B:$B,">"&'Cash Flow'!X$3) -> 0 | Z12: =SUMIFS('Wells Fargo'!$F:$F,'Wells Fargo'!$G:$G,'Cash Flow'!$A12,'Wells Fargo'!$A:$A,Z$1,'Wells Fargo'!$B:$B,"<="&'Cash Flow'!Z$3,'Wells Fargo'!$B:$B,">"&'Cash Flow'!Y$3) -> 0 | AA12: =SUMIFS('Wells Fargo'!$F:$F,'Wells Fargo'!$G:$G,'Cash Flow'!$A12,'Wells Fargo'!$A:$A,AA$1,'Wells Fargo'!$B:$B,"<="&'Cash Flow'!AA$3) -> 0 | AB12: =SUMIFS('Wells Fargo'!$F:$F,'Wells Fargo'!$G:$G,'Cash Flow'!$A12,'Wells Fargo'!$A:$A,AB$1,'Wells Fargo'!$B:$B,"<="&'Cash Flow'!AB$3,'Wells Fargo'!$B:$B,">"&'Cash Flow'!AA$3) -> 0 | AC12: =SUMIFS('Wells Fargo'!$F:$F,'Wells Fargo'!$G:$G,'Cash Flow'!$A12,'Wells Fargo'!$A:$A,AC$1,'Wells Fargo'!$B:$B,"<="&'Cash Flow'!AC$3,'Wells Fargo'!$B:$B,">"&'Cash Flow'!AB$3) -> 0 | AD12: =SUMIFS('Wells Fargo'!$F:$F,'Wells Fargo'!$G:$G,'Cash Flow'!$A12,'Wells Fargo'!$A:$A,AD$1,'Wells Fargo'!$B:$B,"<="&'Cash Flow'!AD$3,'Wells Fargo'!$B:$B,">"&'Cash Flow'!AC$3) -> 0 | AE12: =SUMIFS('Wells Fargo'!$F:$F,'Wells Fargo'!$G:$G,'Cash Flow'!$A12,'Wells Fargo'!$A:$A,AE$1,'Wells Fargo'!$B:$B,"<="&'Cash Flow'!AE$3,'Wells Fargo'!$B:$B,">"&'Cash Flow'!AD$3) -> 0 | AF12: =SUMIFS('Wells Fargo'!$F:$F,'Wells Fargo'!$G:$G,'Cash Flow'!$A12,'Wells Fargo'!$A:$A,AF$1,'Wells Fargo'!$B:$B,"<="&'Cash Flow'!AF$3) -> 0 | AG12: =SUMIFS('Wells Fargo'!$F:$F,'Wells Fargo'!$G:$G,'Cash Flow'!$A12,'Wells Fargo'!$A:$A,AG$1,'Wells Fargo'!$B:$B,"<="&'Cash Flow'!AG$3,'Wells Fargo'!$B:$B,">"&'Cash Flow'!AF$3) -> 0 | AH12: =SUMIFS('Wells Fargo'!$F:$F,'Wells Fargo'!$G:$G,'Cash Flow'!$A12,'Wells Fargo'!$A:$A,AH$1,'Wells Fargo'!$B:$B,"<="&'Cash Flow'!AH$3,'Wells Fargo'!$B:$B,">"&'Cash Flow'!AG$3) -> 0 | AI12: =SUMIFS('Wells Fargo'!$F:$F,'Wells Fargo'!$G:$G,'Cash Flow'!$A12,'Wells Fargo'!$A:$A,AI$1,'Wells Fargo'!$B:$B,"<="&'Cash Flow'!AI$3,'Wells Fargo'!$B:$B,">"&'Cash Flow'!AH$3) -> 0 | AJ12: =SUMIFS('Wells Fargo'!$F:$F,'Wells Fargo'!$G:$G,'Cash Flow'!$A12,'Wells Fargo'!$A:$A,AJ$1,'Wells Fargo'!$B:$B,"<="&'Cash Flow'!AJ$3,'Wells Fargo'!$B:$B,">"&'Cash Flow'!AI$3) -> 0 | AK12: =SUMIFS('Wells Fargo'!$F:$F,'Wells Fargo'!$G:$G,'Cash Flow'!$A12,'Wells Fargo'!$A:$A,AK$1,'Wells Fargo'!$B:$B,"<="&'Cash Flow'!AK$3) -> 0 | AL12: =SUMIFS('Wells Fargo'!$F:$F,'Wells Fargo'!$G:$G,'Cash Flow'!$A12,'Wells Fargo'!$A:$A,AL$1,'Wells Fargo'!$B:$B,"<="&'Cash Flow'!AL$3,'Wells Fargo'!$B:$B,">"&'Cash Flow'!AK$3) -> 0 | AM12: =SUMIFS('Wells Fargo'!$F:$F,'Wells Fargo'!$G:$G,'Cash Flow'!$A12,'Wells Fargo'!$A:$A,AM$1,'Wells Fargo'!$B:$B,"<="&'Cash Flow'!AM$3,'Wells Fargo'!$B:$B,">"&'Cash Flow'!AL$3) -> 0 | AN12: =SUMIFS('Wells Fargo'!$F:$F,'Wells Fargo'!$G:$G,'Cash Flow'!$A12,'Wells Fargo'!$A:$A,AN$1,'Wells Fargo'!$B:$B,"<="&'Cash Flow'!AN$3,'Wells Fargo'!$B:$B,">"&'Cash Flow'!AM$3) -> 0 | AO12: =SUMIFS('Wells Fargo'!$F:$F,'Wells Fargo'!$G:$G,'Cash Flow'!$A12,'Wells Fargo'!$A:$A,AO$1,'Wells Fargo'!$B:$B,"<="&'Cash Flow'!AO$3,'Wells Fargo'!$B:$B,">"&'Cash Flow'!AN$3) -> 0 | AP12: =SUMIFS('Wells Fargo'!$F:$F,'Wells Fargo'!$G:$G,'Cash Flow'!$A12,'Wells Fargo'!$A:$A,AP$1,'Wells Fargo'!$B:$B,"<="&'Cash Flow'!AP$3) -> 0 | AQ12: =SUMIFS('Wells Fargo'!$F:$F,'Wells Fargo'!$G:$G,'Cash Flow'!$A12,'Wells Fargo'!$A:$A,AQ$1,'Wells Fargo'!$B:$B,"<="&'Cash Flow'!AQ$3,'Wells Fargo'!$B:$B,">"&'Cash Flow'!AP$3) -> 0 | AR12: =SUMIFS('Wells Fargo'!$F:$F,'Wells Fargo'!$G:$G,'Cash Flow'!$A12,'Wells Fargo'!$A:$A,AR$1,'Wells Fargo'!$B:$B,"<="&'Cash Flow'!AR$3,'Wells Fargo'!$B:$B,">"&'Cash Flow'!AQ$3) -> 0 | AS12: =SUMIFS('Wells Fargo'!$F:$F,'Wells Fargo'!$G:$G,'Cash Flow'!$A12,'Wells Fargo'!$A:$A,AS$1,'Wells Fargo'!$B:$B,"<="&'Cash Flow'!AS$3,'Wells Fargo'!$B:$B,">"&'Cash Flow'!AR$3) -> 0 | AT12: =SUMIFS('Wells Fargo'!$F:$F,'Wells Fargo'!$G:$G,'Cash Flow'!$A12,'Wells Fargo'!$A:$A,AT$1,'Wells Fargo'!$B:$B,"<="&'Cash Flow'!AT$3,'Wells Fargo'!$B:$B,">"&'Cash Flow'!AS$3) -> 0 | AU12: =SUMIFS('Wells Fargo'!$F:$F,'Wells Fargo'!$G:$G,'Cash Flow'!$A12,'Wells Fargo'!$A:$A,AU$1,'Wells Fargo'!$B:$B,"<="&'Cash Flow'!AU$3) -> 0 | AV12: =SUMIFS('Wells Fargo'!$F:$F,'Wells Fargo'!$G:$G,'Cash Flow'!$A12,'Wells Fargo'!$A:$A,AV$1,'Wells Fargo'!$B:$B,"<="&'Cash Flow'!AV$3,'Wells Fargo'!$B:$B,">"&'Cash Flow'!AU$3) -> 0 | AW12: =SUMIFS('Wells Fargo'!$F:$F,'Wells Fargo'!$G:$G,'Cash Flow'!$A12,'Wells Fargo'!$A:$A,AW$1,'Wells Fargo'!$B:$B,"<="&'Cash Flow'!AW$3,'Wells Fargo'!$B:$B,">"&'Cash Flow'!AV$3) -> 0 | AX12: =SUMIFS('Wells Fargo'!$F:$F,'Wells Fargo'!$G:$G,'Cash Flow'!$A12,'Wells Fargo'!$A:$A,AX$1,'Wells Fargo'!$B:$B,"<="&'Cash Flow'!AX$3,'Wells Fargo'!$B:$B,">"&'Cash Flow'!AW$3) -> 0 | AY12: =SUMIFS('Wells Fargo'!$F:$F,'Wells Fargo'!$G:$G,'Cash Flow'!$A12,'Wells Fargo'!$A:$A,AY$1,'Wells Fargo'!$B:$B,"<="&'Cash Flow'!AY$3,'Wells Fargo'!$B:$B,">"&'Cash Flow'!AX$3) -> 0 | AZ12: =SUMIFS('Wells Fargo'!$F:$F,'Wells Fargo'!$G:$G,'Cash Flow'!$A12,'Wells Fargo'!$A:$A,AZ$1,'Wells Fargo'!$B:$B,"<="&'Cash Flow'!AZ$3) -> 0 | BA12: =SUMIFS('Wells Fargo'!$F:$F,'Wells Fargo'!$G:$G,'Cash Flow'!$A12,'Wells Fargo'!$A:$A,BA$1,'Wells Fargo'!$B:$B,"<="&'Cash Flow'!BA$3,'Wells Fargo'!$B:$B,">"&'Cash Flow'!AZ$3) -> 0 | BB12: =SUMIFS('Wells Fargo'!$F:$F,'Wells Fargo'!$G:$G,'Cash Flow'!$A12,'Wells Fargo'!$A:$A,BB$1,'Wells Fargo'!$B:$B,"<="&'Cash Flow'!BB$3,'Wells Fargo'!$B:$B,">"&'Cash Flow'!BA$3) -> 0 | BC12: =SUMIFS('Wells Fargo'!$F:$F,'Wells Fargo'!$G:$G,'Cash Flow'!$A12,'Wells Fargo'!$A:$A,BC$1,'Wells Fargo'!$B:$B,"<="&'Cash Flow'!BC$3,'Wells Fargo'!$B:$B,">"&'Cash Flow'!BB$3) -> 0 | BD12: =SUMIFS('Wells Fargo'!$F:$F,'Wells Fargo'!$G:$G,'Cash Flow'!$A12,'Wells Fargo'!$A:$A,BD$1,'Wells Fargo'!$B:$B,"<="&'Cash Flow'!BD$3,'Wells Fargo'!$B:$B,">"&'Cash Flow'!BC$3) -> 0 | BE12: =SUMIFS('Wells Fargo'!$F:$F,'Wells Fargo'!$G:$G,'Cash Flow'!$A12,'Wells Fargo'!$A:$A,BE$1,'Wells Fargo'!$B:$B,"<="&'Cash Flow'!BE$3) -> 0 | BF12: =SUMIFS('Wells Fargo'!$F:$F,'Wells Fargo'!$G:$G,'Cash Flow'!$A12,'Wells Fargo'!$A:$A,BF$1,'Wells Fargo'!$B:$B,"<="&'Cash Flow'!BF$3,'Wells Fargo'!$B:$B,">"&'Cash Flow'!BE$3) -> 0 | BG12: =SUMIFS('Wells Fargo'!$F:$F,'Wells Fargo'!$G:$G,'Cash Flow'!$A12,'Wells Fargo'!$A:$A,BG$1,'Wells Fargo'!$B:$B,"<="&'Cash Flow'!BG$3,'Wells Fargo'!$B:$B,">"&'Cash Flow'!BF$3) -> 0 | BH12: =SUMIFS('Wells Fargo'!$F:$F,'Wells Fargo'!$G:$G,'Cash Flow'!$A12,'Wells Fargo'!$A:$A,BH$1,'Wells Fargo'!$B:$B,"<="&'Cash Flow'!BH$3,'Wells Fargo'!$B:$B,">"&'Cash Flow'!BG$3) -> 0 | BI12: =SUMIFS('Wells Fargo'!$F:$F,'Wells Fargo'!$G:$G,'Cash Flow'!$A12,'Wells Fargo'!$A:$A,BI$1,'Wells Fargo'!$B:$B,"<="&'Cash Flow'!BI$3,'Wells Fargo'!$B:$B,">"&'Cash Flow'!BH$3) -> 0
A13: Divita | B13: =SUM(C13:BI13) -> -50 | C13: =SUMIFS('Wells Fargo'!$F:$F,'Wells Fargo'!$G:$G,'Cash Flow'!$A13,'Wells Fargo'!$A:$A,C$1,'Wells Fargo'!$B:$B,"<="&'Cash Flow'!C$3) -> 0 | D13: =SUMIFS('Wells Fargo'!$F:$F,'Wells Fargo'!$G:$G,'Cash Flow'!$A13,'Wells Fargo'!$A:$A,D$1,'Wells Fargo'!$B:$B,"<="&'Cash Flow'!D$3,'Wells Fargo'!$B:$B,">"&'Cash Flow'!C$3) -> 0 | E13: =SUMIFS('Wells Fargo'!$F:$F,'Wells Fargo'!$G:$G,'Cash Flow'!$A13,'Wells Fargo'!$A:$A,E$1,'Wells Fargo'!$B:$B,"<="&'Cash Flow'!E$3,'Wells Fargo'!$B:$B,">"&'Cash Flow'!D$3) -> 0 | F13: =SUMIFS('Wells Fargo'!$F:$F,'Wells Fargo'!$G:$G,'Cash Flow'!$A13,'Wells Fargo'!$A:$A,F$1,'Wells Fargo'!$B:$B,"<="&'Cash Flow'!F$3,'Wells Fargo'!$B:$B,">"&'Cash Flow'!E$3) -> 0 | G13: =SUMIFS('Wells Fargo'!$F:$F,'Wells Fargo'!$G:$G,'Cash Flow'!$A13,'Wells Fargo'!$A:$A,G$1,'Wells Fargo'!$B:$B,"<="&'Cash Flow'!G$3,'Wells Fargo'!$B:$B,">"&'Cash Flow'!F$3) -> 0 | H13: =SUMIFS('Wells Fargo'!$F:$F,'Wells Fargo'!$G:$G,'Cash Flow'!$A13,'Wells Fargo'!$A:$A,H$1,'Wells Fargo'!$B:$B,"<="&'Cash Flow'!H$3) -> 0 | I13: =SUMIFS('Wells Fargo'!$F:$F,'Wells Fargo'!$G:$G,'Cash Flow'!$A13,'Wells Fargo'!$A:$A,I$1,'Wells Fargo'!$B:$B,"<="&'Cash Flow'!I$3,'Wells Fargo'!$B:$B,">"&'Cash Flow'!H$3) -> 0 | J13: =SUMIFS('Wells Fargo'!$F:$F,'Wells Fargo'!$G:$G,'Cash Flow'!$A13,'Wells Fargo'!$A:$A,J$1,'Wells Fargo'!$B:$B,"<="&'Cash Flow'!J$3,'Wells Fargo'!$B:$B,">"&'Cash Flow'!I$3) -> 0 | K13: =SUMIFS('Wells Fargo'!$F:$F,'Wells Fargo'!$G:$G,'Cash Flow'!$A13,'Wells Fargo'!$A:$A,K$1,'Wells Fargo'!$B:$B,"<="&'Cash Flow'!K$3,'Wells Fargo'!$B:$B,">"&'Cash Flow'!J$3) -> 0 | L13: =SUMIFS('Wells Fargo'!$F:$F,'Wells Fargo'!$G:$G,'Cash Flow'!$A13,'Wells Fargo'!$A:$A,L$1,'Wells Fargo'!$B:$B,"<="&'Cash Flow'!L$3) -> 0 | M13: =SUMIFS('Wells Fargo'!$F:$F,'Wells Fargo'!$G:$G,'Cash Flow'!$A13,'Wells Fargo'!$A:$A,M$1,'Wells Fargo'!$B:$B,"<="&'Cash Flow'!M$3,'Wells Fargo'!$B:$B,">"&'Cash Flow'!L$3) -> 0 | N13: =SUMIFS('Wells Fargo'!$F:$F,'Wells Fargo'!$G:$G,'Cash Flow'!$A13,'Wells Fargo'!$A:$A,N$1,'Wells Fargo'!$B:$B,"<="&'Cash Flow'!N$3,'Wells Fargo'!$B:$B,">"&'Cash Flow'!M$3) -> 0 | O13: =SUMIFS('Wells Fargo'!$F:$F,'Wells Fargo'!$G:$G,'Cash Flow'!$A13,'Wells Fargo'!$A:$A,O$1,'Wells Fargo'!$B:$B,"<="&'Cash Flow'!O$3,'Wells Fargo'!$B:$B,">"&'Cash Flow'!N$3) -> 0 | P13: =SUMIFS('Wells Fargo'!$F:$F,'Wells Fargo'!$G:$G,'Cash Flow'!$A13,'Wells Fargo'!$A:$A,P$1,'Wells Fargo'!$B:$B,"<="&'Cash Flow'!P$3,'Wells Fargo'!$B:$B,">"&'Cash Flow'!O$3) -> 0 | Q13: =SUMIFS('Wells Fargo'!$F:$F,'Wells Fargo'!$G:$G,'Cash Flow'!$A13,'Wells Fargo'!$A:$A,Q$1,'Wells Fargo'!$B:$B,"<="&'Cash Flow'!Q$3) -> 0 | R13: =SUMIFS('Wells Fargo'!$F:$F,'Wells Fargo'!$G:$G,'Cash Flow'!$A13,'Wells Fargo'!$A:$A,R$1,'Wells Fargo'!$B:$B,"<="&'Cash Flow'!R$3,'Wells Fargo'!$B:$B,">"&'Cash Flow'!Q$3) -> 0 | S13: =SUMIFS('Wells Fargo'!$F:$F,'Wells Fargo'!$G:$G,'Cash Flow'!$A13,'Wells Fargo'!$A:$A,S$1,'Wells Fargo'!$B:$B,"<="&'Cash Flow'!S$3,'Wells Fargo'!$B:$B,">"&'Cash Flow'!R$3) -> 0 | T13: =SUMIFS('Wells Fargo'!$F:$F,'Wells Fargo'!$G:$G,'Cash Flow'!$A13,'Wells Fargo'!$A:$A,T$1,'Wells Fargo'!$B:$B,"<="&'Cash Flow'!T$3,'Wells Fargo'!$B:$B,">"&'Cash Flow'!S$3) -> 0 | U13: =SUMIFS('Wells Fargo'!$F:$F,'Wells Fargo'!$G:$G,'Cash Flow'!$A13,'Wells Fargo'!$A:$A,U$1,'Wells Fargo'!$B:$B,"<="&'Cash Flow'!U$3,'Wells Fargo'!$B:$B,">"&'Cash Flow'!T$3) -> 0 | V13: =SUMIFS('Wells Fargo'!$F:$F,'Wells Fargo'!$G:$G,'Cash Flow'!$A13,'Wells Fargo'!$A:$A,V$1,'Wells Fargo'!$B:$B,"<="&'Cash Flow'!V$3) -> -50 | W13: =SUMIFS('Wells Fargo'!$F:$F,'Wells Fargo'!$G:$G,'Cash Flow'!$A13,'Wells Fargo'!$A:$A,W$1,'Wells Fargo'!$B:$B,"<="&'Cash Flow'!W$3,'Wells Fargo'!$B:$B,">"&'Cash Flow'!V$3) -> 0 | X13: =SUMIFS('Wells Fargo'!$F:$F,'Wells Fargo'!$G:$G,'Cash Flow'!$A13,'Wells Fargo'!$A:$A,X$1,'Wells Fargo'!$B:$B,"<="&'Cash Flow'!X$3,'Wells Fargo'!$B:$B,">"&'Cash Flow'!W$3) -> 0 | Y13: =SUMIFS('Wells Fargo'!$F:$F,'Wells Fargo'!$G:$G,'Cash Flow'!$A13,'Wells Fargo'!$A:$A,Y$1,'Wells Fargo'!$B:$B,"<="&'Cash Flow'!Y$3,'Wells Fargo'!$B:$B,">"&'Cash Flow'!X$3) -> 0 | Z13: =SUMIFS('Wells Fargo'!$F:$F,'Wells Fargo'!$G:$G,'Cash Flow'!$A13,'Wells Fargo'!$A:$A,Z$1,'Wells Fargo'!$B:$B,"<="&'Cash Flow'!Z$3,'Wells Fargo'!$B:$B,">"&'Cash Flow'!Y$3) -> 0 | AA13: =SUMIFS('Wells Fargo'!$F:$F,'Wells Fargo'!$G:$G,'Cash Flow'!$A13,'Wells Fargo'!$A:$A,AA$1,'Wells Fargo'!$B:$B,"<="&'Cash Flow'!AA$3) -> 0 | AB13: =SUMIFS('Wells Fargo'!$F:$F,'Wells Fargo'!$G:$G,'Cash Flow'!$A13,'Wells Fargo'!$A:$A,AB$1,'Wells Fargo'!$B:$B,"<="&'Cash Flow'!AB$3,'Wells Fargo'!$B:$B,">"&'Cash Flow'!AA$3) -> 0 | AC13: =SUMIFS('Wells Fargo'!$F:$F,'Wells Fargo'!$G:$G,'Cash Flow'!$A13,'Wells Fargo'!$A:$A,AC$1,'Wells Fargo'!$B:$B,"<="&'Cash Flow'!AC$3,'Wells Fargo'!$B:$B,">"&'Cash Flow'!AB$3) -> 0 | AD13: =SUMIFS('Wells Fargo'!$F:$F,'Wells Fargo'!$G:$G,'Cash Flow'!$A13,'Wells Fargo'!$A:$A,AD$1,'Wells Fargo'!$B:$B,"<="&'Cash Flow'!AD$3,'Wells Fargo'!$B:$B,">"&'Cash Flow'!AC$3) -> 0 | AE13: =SUMIFS('Wells Fargo'!$F:$F,'Wells Fargo'!$G:$G,'Cash Flow'!$A13,'Wells Fargo'!$A:$A,AE$1,'Wells Fargo'!$B:$B,"<="&'Cash Flow'!AE$3,'Wells Fargo'!$B:$B,">"&'Cash Flow'!AD$3) -> 0 | AF13: =SUMIFS('Wells Fargo'!$F:$F,'Wells Fargo'!$G:$G,'Cash Flow'!$A13,'Wells Fargo'!$A:$A,AF$1,'Wells Fargo'!$B:$B,"<="&'Cash Flow'!AF$3) -> 0 | AG13: =SUMIFS('Wells Fargo'!$F:$F,'Wells Fargo'!$G:$G,'Cash Flow'!$A13,'Wells Fargo'!$A:$A,AG$1,'Wells Fargo'!$B:$B,"<="&'Cash Flow'!AG$3,'Wells Fargo'!$B:$B,">"&'Cash Flow'!AF$3) -> 0 | AH13: =SUMIFS('Wells Fargo'!$F:$F,'Wells Fargo'!$G:$G,'Cash Flow'!$A13,'Wells Fargo'!$A:$A,AH$1,'Wells Fargo'!$B:$B,"<="&'Cash Flow'!AH$3,'Wells Fargo'!$B:$B,">"&'Cash Flow'!AG$3) -> 0 | AI13: =SUMIFS('Wells Fargo'!$F:$F,'Wells Fargo'!$G:$G,'Cash Flow'!$A13,'Wells Fargo'!$A:$A,AI$1,'Wells Fargo'!$B:$B,"<="&'Cash Flow'!AI$3,'Wells Fargo'!$B:$B,">"&'Cash Flow'!AH$3) -> 0 | AJ13: =SUMIFS('Wells Fargo'!$F:$F,'Wells Fargo'!$G:$G,'Cash Flow'!$A13,'Wells Fargo'!$A:$A,AJ$1,'Wells Fargo'!$B:$B,"<="&'Cash Flow'!AJ$3,'Wells Fargo'!$B:$B,">"&'Cash Flow'!AI$3) -> 0 | AK13: =SUMIFS('Wells Fargo'!$F:$F,'Wells Fargo'!$G:$G,'Cash Flow'!$A13,'Wells Fargo'!$A:$A,AK$1,'Wells Fargo'!$B:$B,"<="&'Cash Flow'!AK$3) -> 0 | AL13: =SUMIFS('Wells Fargo'!$F:$F,'Wells Fargo'!$G:$G,'Cash Flow'!$A13,'Wells Fargo'!$A:$A,AL$1,'Wells Fargo'!$B:$B,"<="&'Cash Flow'!AL$3,'Wells Fargo'!$B:$B,">"&'Cash Flow'!AK$3) -> 0 | AM13: =SUMIFS('Wells Fargo'!$F:$F,'Wells Fargo'!$G:$G,'Cash Flow'!$A13,'Wells Fargo'!$A:$A,AM$1,'Wells Fargo'!$B:$B,"<="&'Cash Flow'!AM$3,'Wells Fargo'!$B:$B,">"&'Cash Flow'!AL$3) -> 0 | AN13: =SUMIFS('Wells Fargo'!$F:$F,'Wells Fargo'!$G:$G,'Cash Flow'!$A13,'Wells Fargo'!$A:$A,AN$1,'Wells Fargo'!$B:$B,"<="&'Cash Flow'!AN$3,'Wells Fargo'!$B:$B,">"&'Cash Flow'!AM$3) -> 0 | AO13: =SUMIFS('Wells Fargo'!$F:$F,'Wells Fargo'!$G:$G,'Cash Flow'!$A13,'Wells Fargo'!$A:$A,AO$1,'Wells Fargo'!$B:$B,"<="&'Cash Flow'!AO$3,'Wells Fargo'!$B:$B,">"&'Cash Flow'!AN$3) -> 0 | AP13: =SUMIFS('Wells Fargo'!$F:$F,'Wells Fargo'!$G:$G,'Cash Flow'!$A13,'Wells Fargo'!$A:$A,AP$1,'Wells Fargo'!$B:$B,"<="&'Cash Flow'!AP$3) -> 0 | AQ13: =SUMIFS('Wells Fargo'!$F:$F,'Wells Fargo'!$G:$G,'Cash Flow'!$A13,'Wells Fargo'!$A:$A,AQ$1,'Wells Fargo'!$B:$B,"<="&'Cash Flow'!AQ$3,'Wells Fargo'!$B:$B,">"&'Cash Flow'!AP$3) -> 0 | AR13: =SUMIFS('Wells Fargo'!$F:$F,'Wells Fargo'!$G:$G,'Cash Flow'!$A13,'Wells Fargo'!$A:$A,AR$1,'Wells Fargo'!$B:$B,"<="&'Cash Flow'!AR$3,'Wells Fargo'!$B:$B,">"&'Cash Flow'!AQ$3) -> 0 | AS13: =SUMIFS('Wells Fargo'!$F:$F,'Wells Fargo'!$G:$G,'Cash Flow'!$A13,'Wells Fargo'!$A:$A,AS$1,'Wells Fargo'!$B:$B,"<="&'Cash Flow'!AS$3,'Wells Fargo'!$B:$B,">"&'Cash Flow'!AR$3) -> 0 | AT13: =SUMIFS('Wells Fargo'!$F:$F,'Wells Fargo'!$G:$G,'Cash Flow'!$A13,'Wells Fargo'!$A:$A,AT$1,'Wells Fargo'!$B:$B,"<="&'Cash Flow'!AT$3,'Wells Fargo'!$B:$B,">"&'Cash Flow'!AS$3) -> 0 | AU13: =SUMIFS('Wells Fargo'!$F:$F,'Wells Fargo'!$G:$G,'Cash Flow'!$A13,'Wells Fargo'!$A:$A,AU$1,'Wells Fargo'!$B:$B,"<="&'Cash Flow'!AU$3) -> 0 | AV13: =SUMIFS('Wells Fargo'!$F:$F,'Wells Fargo'!$G:$G,'Cash Flow'!$A13,'Wells Fargo'!$A:$A,AV$1,'Wells Fargo'!$B:$B,"<="&'Cash Flow'!AV$3,'Wells Fargo'!$B:$B,">"&'Cash Flow'!AU$3) -> 0 | AW13: =SUMIFS('Wells Fargo'!$F:$F,'Wells Fargo'!$G:$G,'Cash Flow'!$A13,'Wells Fargo'!$A:$A,AW$1,'Wells Fargo'!$B:$B,"<="&'Cash Flow'!AW$3,'Wells Fargo'!$B:$B,">"&'Cash Flow'!AV$3) -> 0 | AX13: =SUMIFS('Wells Fargo'!$F:$F,'Wells Fargo'!$G:$G,'Cash Flow'!$A13,'Wells Fargo'!$A:$A,AX$1,'Wells Fargo'!$B:$B,"<="&'Cash Flow'!AX$3,'Wells Fargo'!$B:$B,">"&'Cash Flow'!AW$3) -> 0 | AY13: =SUMIFS('Wells Fargo'!$F:$F,'Wells Fargo'!$G:$G,'Cash Flow'!$A13,'Wells Fargo'!$A:$A,AY$1,'Wells Fargo'!$B:$B,"<="&'Cash Flow'!AY$3,'Wells Fargo'!$B:$B,">"&'Cash Flow'!AX$3) -> 0 | AZ13: =SUMIFS('Wells Fargo'!$F:$F,'Wells Fargo'!$G:$G,'Cash Flow'!$A13,'Wells Fargo'!$A:$A,AZ$1,'Wells Fargo'!$B:$B,"<="&'Cash Flow'!AZ$3) -> 0 | BA13: =SUMIFS('Wells Fargo'!$F:$F,'Wells Fargo'!$G:$G,'Cash Flow'!$A13,'Wells Fargo'!$A:$A,BA$1,'Wells Fargo'!$B:$B,"<="&'Cash Flow'!BA$3,'Wells Fargo'!$B:$B,">"&'Cash Flow'!AZ$3) -> 0 | BB13: =SUMIFS('Wells Fargo'!$F:$F,'Wells Fargo'!$G:$G,'Cash Flow'!$A13,'Wells Fargo'!$A:$A,BB$1,'Wells Fargo'!$B:$B,"<="&'Cash Flow'!BB$3,'Wells Fargo'!$B:$B,">"&'Cash Flow'!BA$3) -> 0 | BC13: =SUMIFS('Wells Fargo'!$F:$F,'Wells Fargo'!$G:$G,'Cash Flow'!$A13,'Wells Fargo'!$A:$A,BC$1,'Wells Fargo'!$B:$B,"<="&'Cash Flow'!BC$3,'Wells Fargo'!$B:$B,">"&'Cash Flow'!BB$3) -> 0 | BD13: =SUMIFS('Wells Fargo'!$F:$F,'Wells Fargo'!$G:$G,'Cash Flow'!$A13,'Wells Fargo'!$A:$A,BD$1,'Wells Fargo'!$B:$B,"<="&'Cash Flow'!BD$3,'Wells Fargo'!$B:$B,">"&'Cash Flow'!BC$3) -> 0 | BE13: =SUMIFS('Wells Fargo'!$F:$F,'Wells Fargo'!$G:$G,'Cash Flow'!$A13,'Wells Fargo'!$A:$A,BE$1,'Wells Fargo'!$B:$B,"<="&'Cash Flow'!BE$3) -> 0 | BF13: =SUMIFS('Wells Fargo'!$F:$F,'Wells Fargo'!$G:$G,'Cash Flow'!$A13,'Wells Fargo'!$A:$A,BF$1,'Wells Fargo'!$B:$B,"<="&'Cash Flow'!BF$3,'Wells Fargo'!$B:$B,">"&'Cash Flow'!BE$3) -> 0 | BG13: =SUMIFS('Wells Fargo'!$F:$F,'Wells Fargo'!$G:$G,'Cash Flow'!$A13,'Wells Fargo'!$A:$A,BG$1,'Wells Fargo'!$B:$B,"<="&'Cash Flow'!BG$3,'Wells Fargo'!$B:$B,">"&'Cash Flow'!BF$3) -> 0 | BH13: =SUMIFS('Wells Fargo'!$F:$F,'Wells Fargo'!$G:$G,'Cash Flow'!$A13,'Wells Fargo'!$A:$A,BH$1,'Wells Fargo'!$B:$B,"<="&'Cash Flow'!BH$3,'Wells Fargo'!$B:$B,">"&'Cash Flow'!BG$3) -> 0 | BI13: =SUMIFS('Wells Fargo'!$F:$F,'Wells Fargo'!$G:$G,'Cash Flow'!$A13,'Wells Fargo'!$A:$A,BI$1,'Wells Fargo'!$B:$B,"<="&'Cash Flow'!BI$3,'Wells Fargo'!$B:$B,">"&'Cash Flow'!BH$3) -> 0
A14: Don | B14: =SUM(C14:BI14) -> -227.5 | C14: =SUMIFS('Wells Fargo'!$F:$F,'Wells Fargo'!$G:$G,'Cash Flow'!$A14,'Wells Fargo'!$A:$A,C$1,'Wells Fargo'!$B:$B,"<="&'Cash Flow'!C$3) -> 0 | D14: =SUMIFS('Wells Fargo'!$F:$F,'Wells Fargo'!$G:$G,'Cash Flow'!$A14,'Wells Fargo'!$A:$A,D$1,'Wells Fargo'!$B:$B,"<="&'Cash Flow'!D$3,'Wells Fargo'!$B:$B,">"&'Cash Flow'!C$3) -> 0 | E14: =SUMIFS('Wells Fargo'!$F:$F,'Wells Fargo'!$G:$G,'Cash Flow'!$A14,'Wells Fargo'!$A:$A,E$1,'Wells Fargo'!$B:$B,"<="&'Cash Flow'!E$3,'Wells Fargo'!$B:$B,">"&'Cash Flow'!D$3) -> 0 | F14: =SUMIFS('Wells Fargo'!$F:$F,'Wells Fargo'!$G:$G,'Cash Flow'!$A14,'Wells Fargo'!$A:$A,F$1,'Wells Fargo'!$B:$B,"<="&'Cash Flow'!F$3,'Wells Fargo'!$B:$B,">"&'Cash Flow'!E$3) -> 0 | G14: =SUMIFS('Wells Fargo'!$F:$F,'Wells Fargo'!$G:$G,'Cash Flow'!$A14,'Wells Fargo'!$A:$A,G$1,'Wells Fargo'!$B:$B,"<="&'Cash Flow'!G$3,'Wells Fargo'!$B:$B,">"&'Cash Flow'!F$3) -> 0 | H14: =SUMIFS('Wells Fargo'!$F:$F,'Wells Fargo'!$G:$G,'Cash Flow'!$A14,'Wells Fargo'!$A:$A,H$1,'Wells Fargo'!$B:$B,"<="&'Cash Flow'!H$3) -> -600 | I14: =SUMIFS('Wells Fargo'!$F:$F,'Wells Fargo'!$G:$G,'Cash Flow'!$A14,'Wells Fargo'!$A:$A,I$1,'Wells Fargo'!$B:$B,"<="&'Cash Flow'!I$3,'Wells Fargo'!$B:$B,">"&'Cash Flow'!H$3) -> 0 | J14: =SUMIFS('Wells Fargo'!$F:$F,'Wells Fargo'!$G:$G,'Cash Flow'!$A14,'Wells Fargo'!$A:$A,J$1,'Wells Fargo'!$B:$B,"<="&'Cash Flow'!J$3,'Wells Fargo'!$B:$B,">"&'Cash Flow'!I$3) -> 492.5 | K14: =SUMIFS('Wells Fargo'!$F:$F,'Wells Fargo'!$G:$G,'Cash Flow'!$A14,'Wells Fargo'!$A:$A,K$1,'Wells Fargo'!$B:$B,"<="&'Cash Flow'!K$3,'Wells Fargo'!$B:$B,">"&'Cash Flow'!J$3) -> 0 | L14: =SUMIFS('Wells Fargo'!$F:$F,'Wells Fargo'!$G:$G,'Cash Flow'!$A14,'Wells Fargo'!$A:$A,L$1,'Wells Fargo'!$B:$B,"<="&'Cash Flow'!L$3) -> 0 | M14: =SUMIFS('Wells Fargo'!$F:$F,'Wells Fargo'!$G:$G,'Cash Flow'!$A14,'Wells Fargo'!$A:$A,M$1,'Wells Fargo'!$B:$B,"<="&'Cash Flow'!M$3,'Wells Fargo'!$B:$B,">"&'Cash Flow'!L$3) -> 0 | N14: =SUMIFS('Wells Fargo'!$F:$F,'Wells Fargo'!$G:$G,'Cash Flow'!$A14,'Wells Fargo'!$A:$A,N$1,'Wells Fargo'!$B:$B,"<="&'Cash Flow'!N$3,'Wells Fargo'!$B:$B,">"&'Cash Flow'!M$3) -> 0 | O14: =SUMIFS('Wells Fargo'!$F:$F,'Wells Fargo'!$G:$G,'Cash Flow'!$A14,'Wells Fargo'!$A:$A,O$1,'Wells Fargo'!$B:$B,"<="&'Cash Flow'!O$3,'Wells Fargo'!$B:$B,">"&'Cash Flow'!N$3) -> 0 | P14: =SUMIFS('Wells Fargo'!$F:$F,'Wells Fargo'!$G:$G,'Cash Flow'!$A14,'Wells Fargo'!$A:$A,P$1,'Wells Fargo'!$B:$B,"<="&'Cash Flow'!P$3,'Wells Fargo'!$B:$B,">"&'Cash Flow'!O$3) -> 0 | Q14: =SUMIFS('Wells Fargo'!$F:$F,'Wells Fargo'!$G:$G,'Cash Flow'!$A14,'Wells Fargo'!$A:$A,Q$1,'Wells Fargo'!$B:$B,"<="&'Cash Flow'!Q$3) -> 0 | R14: =SUMIFS('Wells Fargo'!$F:$F,'Wells Fargo'!$G:$G,'Cash Flow'!$A14,'Wells Fargo'!$A:$A,R$1,'Wells Fargo'!$B:$B,"<="&'Cash Flow'!R$3,'Wells Fargo'!$B:$B,">"&'Cash Flow'!Q$3) -> 0 | S14: =SUMIFS('Wells Fargo'!$F:$F,'Wells Fargo'!$G:$G,'Cash Flow'!$A14,'Wells Fargo'!$A:$A,S$1,'Wells Fargo'!$B:$B,"<="&'Cash Flow'!S$3,'Wells Fargo'!$B:$B,">"&'Cash Flow'!R$3) -> 0 | T14: =SUMIFS('Wells Fargo'!$F:$F,'Wells Fargo'!$G:$G,'Cash Flow'!$A14,'Wells Fargo'!$A:$A,T$1,'Wells Fargo'!$B:$B,"<="&'Cash Flow'!T$3,'Wells Fargo'!$B:$B,">"&'Cash Flow'!S$3) -> 0 | U14: =SUMIFS('Wells Fargo'!$F:$F,'Wells Fargo'!$G:$G,'Cash Flow'!$A14,'Wells Fargo'!$A:$A,U$1,'Wells Fargo'!$B:$B,"<="&'Cash Flow'!U$3,'Wells Fargo'!$B:$B,">"&'Cash Flow'!T$3) -> 0 | V14: =SUMIFS('Wells Fargo'!$F:$F,'Wells Fargo'!$G:$G,'Cash Flow'!$A14,'Wells Fargo'!$A:$A,V$1,'Wells Fargo'!$B:$B,"<="&'Cash Flow'!V$3) -> 0 | W14: =SUMIFS('Wells Fargo'!$F:$F,'Wells Fargo'!$G:$G,'Cash Flow'!$A14,'Wells Fargo'!$A:$A,W$1,'Wells Fargo'!$B:$B,"<="&'Cash Flow'!W$3,'Wells Fargo'!$B:$B,">"&'Cash Flow'!V$3) -> 0 | X14: =SUMIFS('Wells Fargo'!$F:$F,'Wells Fargo'!$G:$G,'Cash Flow'!$A14,'Wells Fargo'!$A:$A,X$1,'Wells Fargo'!$B:$B,"<="&'Cash Flow'!X$3,'Wells Fargo'!$B:$B,">"&'Cash Flow'!W$3) -> 0 | Y14: =SUMIFS('Wells Fargo'!$F:$F,'Wells Fargo'!$G:$G,'Cash Flow'!$A14,'Wells Fargo'!$A:$A,Y$1,'Wells Fargo'!$B:$B,"<="&'Cash Flow'!Y$3,'Wells Fargo'!$B:$B,">"&'Cash Flow'!X$3) -> -120 | Z14: =SUMIFS('Wells Fargo'!$F:$F,'Wells Fargo'!$G:$G,'Cash Flow'!$A14,'Wells Fargo'!$A:$A,Z$1,'Wells Fargo'!$B:$B,"<="&'Cash Flow'!Z$3,'Wells Fargo'!$B:$B,">"&'Cash Flow'!Y$3) -> 0 | AA14: =SUMIFS('Wells Fargo'!$F:$F,'Wells Fargo'!$G:$G,'Cash Flow'!$A14,'Wells Fargo'!$A:$A,AA$1,'Wells Fargo'!$B:$B,"<="&'Cash Flow'!AA$3) -> 0 | AB14: =SUMIFS('Wells Fargo'!$F:$F,'Wells Fargo'!$G:$G,'Cash Flow'!$A14,'Wells Fargo'!$A:$A,AB$1,'Wells Fargo'!$B:$B,"<="&'Cash Flow'!AB$3,'Wells Fargo'!$B:$B,">"&'Cash Flow'!AA$3) -> 0 | AC14: =SUMIFS('Wells Fargo'!$F:$F,'Wells Fargo'!$G:$G,'Cash Flow'!$A14,'Wells Fargo'!$A:$A,AC$1,'Wells Fargo'!$B:$B,"<="&'Cash Flow'!AC$3,'Wells Fargo'!$B:$B,">"&'Cash Flow'!AB$3) -> 0 | AD14: =SUMIFS('Wells Fargo'!$F:$F,'Wells Fargo'!$G:$G,'Cash Flow'!$A14,'Wells Fargo'!$A:$A,AD$1,'Wells Fargo'!$B:$B,"<="&'Cash Flow'!AD$3,'Wells Fargo'!$B:$B,">"&'Cash Flow'!AC$3) -> 0 | AE14: =SUMIFS('Wells Fargo'!$F:$F,'Wells Fargo'!$G:$G,'Cash Flow'!$A14,'Wells Fargo'!$A:$A,AE$1,'Wells Fargo'!$B:$B,"<="&'Cash Flow'!AE$3,'Wells Fargo'!$B:$B,">"&'Cash Flow'!AD$3) -> 0 | AF14: =SUMIFS('Wells Fargo'!$F:$F,'Wells Fargo'!$G:$G,'Cash Flow'!$A14,'Wells Fargo'!$A:$A,AF$1,'Wells Fargo'!$B:$B,"<="&'Cash Flow'!AF$3) -> 0 | AG14: =SUMIFS('Wells Fargo'!$F:$F,'Wells Fargo'!$G:$G,'Cash Flow'!$A14,'Wells Fargo'!$A:$A,AG$1,'Wells Fargo'!$B:$B,"<="&'Cash Flow'!AG$3,'Wells Fargo'!$B:$B,">"&'Cash Flow'!AF$3) -> 0 | AH14: =SUMIFS('Wells Fargo'!$F:$F,'Wells Fargo'!$G:$G,'Cash Flow'!$A14,'Wells Fargo'!$A:$A,AH$1,'Wells Fargo'!$B:$B,"<="&'Cash Flow'!AH$3,'Wells Fargo'!$B:$B,">"&'Cash Flow'!AG$3) -> 0 | AI14: =SUMIFS('Wells Fargo'!$F:$F,'Wells Fargo'!$G:$G,'Cash Flow'!$A14,'Wells Fargo'!$A:$A,AI$1,'Wells Fargo'!$B:$B,"<="&'Cash Flow'!AI$3,'Wells Fargo'!$B:$B,">"&'Cash Flow'!AH$3) -> 0 | AJ14: =SUMIFS('Wells Fargo'!$F:$F,'Wells Fargo'!$G:$G,'Cash Flow'!$A14,'Wells Fargo'!$A:$A,AJ$1,'Wells Fargo'!$B:$B,"<="&'Cash Flow'!AJ$3,'Wells Fargo'!$B:$B,">"&'Cash Flow'!AI$3) -> 0 | AK14: =SUMIFS('Wells Fargo'!$F:$F,'Wells Fargo'!$G:$G,'Cash Flow'!$A14,'Wells Fargo'!$A:$A,AK$1,'Wells Fargo'!$B:$B,"<="&'Cash Flow'!AK$3) -> 0 | AL14: =SUMIFS('Wells Fargo'!$F:$F,'Wells Fargo'!$G:$G,'Cash Flow'!$A14,'Wells Fargo'!$A:$A,AL$1,'Wells Fargo'!$B:$B,"<="&'Cash Flow'!AL$3,'Wells Fargo'!$B:$B,">"&'Cash Flow'!AK$3) -> 0 | AM14: =SUMIFS('Wells Fargo'!$F:$F,'Wells Fargo'!$G:$G,'Cash Flow'!$A14,'Wells Fargo'!$A:$A,AM$1,'Wells Fargo'!$B:$B,"<="&'Cash Flow'!AM$3,'Wells Fargo'!$B:$B,">"&'Cash Flow'!AL$3) -> 0 | AN14: =SUMIFS('Wells Fargo'!$F:$F,'Wells Fargo'!$G:$G,'Cash Flow'!$A14,'Wells Fargo'!$A:$A,AN$1,'Wells Fargo'!$B:$B,"<="&'Cash Flow'!AN$3,'Wells Fargo'!$B:$B,">"&'Cash Flow'!AM$3) -> 0 | AO14: =SUMIFS('Wells Fargo'!$F:$F,'Wells Fargo'!$G:$G,'Cash Flow'!$A14,'Wells Fargo'!$A:$A,AO$1,'Wells Fargo'!$B:$B,"<="&'Cash Flow'!AO$3,'Wells Fargo'!$B:$B,">"&'Cash Flow'!AN$3) -> 0 | AP14: =SUMIFS('Wells Fargo'!$F:$F,'Wells Fargo'!$G:$G,'Cash Flow'!$A14,'Wells Fargo'!$A:$A,AP$1,'Wells Fargo'!$B:$B,"<="&'Cash Flow'!AP$3) -> 0 | AQ14: =SUMIFS('Wells Fargo'!$F:$F,'Wells Fargo'!$G:$G,'Cash Flow'!$A14,'Wells Fargo'!$A:$A,AQ$1,'Wells Fargo'!$B:$B,"<="&'Cash Flow'!AQ$3,'Wells Fargo'!$B:$B,">"&'Cash Flow'!AP$3) -> 0 | AR14: =SUMIFS('Wells Fargo'!$F:$F,'Wells Fargo'!$G:$G,'Cash Flow'!$A14,'Wells Fargo'!$A:$A,AR$1,'Wells Fargo'!$B:$B,"<="&'Cash Flow'!AR$3,'Wells Fargo'!$B:$B,">"&'Cash Flow'!AQ$3) -> 0 | AS14: =SUMIFS('Wells Fargo'!$F:$F,'Wells Fargo'!$G:$G,'Cash Flow'!$A14,'Wells Fargo'!$A:$A,AS$1,'Wells Fargo'!$B:$B,"<="&'Cash Flow'!AS$3,'Wells Fargo'!$B:$B,">"&'Cash Flow'!AR$3) -> 0 | AT14: =SUMIFS('Wells Fargo'!$F:$F,'Wells Fargo'!$G:$G,'Cash Flow'!$A14,'Wells Fargo'!$A:$A,AT$1,'Wells Fargo'!$B:$B,"<="&'Cash Flow'!AT$3,'Wells Fargo'!$B:$B,">"&'Cash Flow'!AS$3) -> 0 | AU14: =SUMIFS('Wells Fargo'!$F:$F,'Wells Fargo'!$G:$G,'Cash Flow'!$A14,'Wells Fargo'!$A:$A,AU$1,'Wells Fargo'!$B:$B,"<="&'Cash Flow'!AU$3) -> 0 | AV14: =SUMIFS('Wells Fargo'!$F:$F,'Wells Fargo'!$G:$G,'Cash Flow'!$A14,'Wells Fargo'!$A:$A,AV$1,'Wells Fargo'!$B:$B,"<="&'Cash Flow'!AV$3,'Wells Fargo'!$B:$B,">"&'Cash Flow'!AU$3) -> 0 | AW14: =SUMIFS('Wells Fargo'!$F:$F,'Wells Fargo'!$G:$G,'Cash Flow'!$A14,'Wells Fargo'!$A:$A,AW$1,'Wells Fargo'!$B:$B,"<="&'Cash Flow'!AW$3,'Wells Fargo'!$B:$B,">"&'Cash Flow'!AV$3) -> 0 | AX14: =SUMIFS('Wells Fargo'!$F:$F,'Wells Fargo'!$G:$G,'Cash Flow'!$A14,'Wells Fargo'!$A:$A,AX$1,'Wells Fargo'!$B:$B,"<="&'Cash Flow'!AX$3,'Wells Fargo'!$B:$B,">"&'Cash Flow'!AW$3) -> 0 | AY14: =SUMIFS('Wells Fargo'!$F:$F,'Wells Fargo'!$G:$G,'Cash Flow'!$A14,'Wells Fargo'!$A:$A,AY$1,'Wells Fargo'!$B:$B,"<="&'Cash Flow'!AY$3,'Wells Fargo'!$B:$B,">"&'Cash Flow'!AX$3) -> 0 | AZ14: =SUMIFS('Wells Fargo'!$F:$F,'Wells Fargo'!$G:$G,'Cash Flow'!$A14,'Wells Fargo'!$A:$A,AZ$1,'Wells Fargo'!$B:$B,"<="&'Cash Flow'!AZ$3) -> 0 | BA14: =SUMIFS('Wells Fargo'!$F:$F,'Wells Fargo'!$G:$G,'Cash Flow'!$A14,'Wells Fargo'!$A:$A,BA$1,'Wells Fargo'!$B:$B,"<="&'Cash Flow'!BA$3,'Wells Fargo'!$B:$B,">"&'Cash Flow'!AZ$3) -> 0 | BB14: =SUMIFS('Wells Fargo'!$F:$F,'Wells Fargo'!$G:$G,'Cash Flow'!$A14,'Wells Fargo'!$A:$A,BB$1,'Wells Fargo'!$B:$B,"<="&'Cash Flow'!BB$3,'Wells Fargo'!$B:$B,">"&'Cash Flow'!BA$3) -> 0 | BC14: =SUMIFS('Wells Fargo'!$F:$F,'Wells Fargo'!$G:$G,'Cash Flow'!$A14,'Wells Fargo'!$A:$A,BC$1,'Wells Fargo'!$B:$B,"<="&'Cash Flow'!BC$3,'Wells Fargo'!$B:$B,">"&'Cash Flow'!BB$3) -> 0 | BD14: =SUMIFS('Wells Fargo'!$F:$F,'Wells Fargo'!$G:$G,'Cash Flow'!$A14,'Wells Fargo'!$A:$A,BD$1,'Wells Fargo'!$B:$B,"<="&'Cash Flow'!BD$3,'Wells Fargo'!$B:$B,">"&'Cash Flow'!BC$3) -> 0 | BE14: =SUMIFS('Wells Fargo'!$F:$F,'Wells Fargo'!$G:$G,'Cash Flow'!$A14,'Wells Fargo'!$A:$A,BE$1,'Wells Fargo'!$B:$B,"<="&'Cash Flow'!BE$3) -> 0 | BF14: =SUMIFS('Wells Fargo'!$F:$F,'Wells Fargo'!$G:$G,'Cash Flow'!$A14,'Wells Fargo'!$A:$A,BF$1,'Wells Fargo'!$B:$B,"<="&'Cash Flow'!BF$3,'Wells Fargo'!$B:$B,">"&'Cash Flow'!BE$3) -> 0 | BG14: =SUMIFS('Wells Fargo'!$F:$F,'Wells Fargo'!$G:$G,'Cash Flow'!$A14,'Wells Fargo'!$A:$A,BG$1,'Wells Fargo'!$B:$B,"<="&'Cash Flow'!BG$3,'Wells Fargo'!$B:$B,">"&'Cash Flow'!BF$3) -> 0 | BH14: =SUMIFS('Wells Fargo'!$F:$F,'Wells Fargo'!$G:$G,'Cash Flow'!$A14,'Wells Fargo'!$A:$A,BH$1,'Wells Fargo'!$B:$B,"<="&'Cash Flow'!BH$3,'Wells Fargo'!$B:$B,">"&'Cash Flow'!BG$3) -> 0 | BI14: =SUMIFS('Wells Fargo'!$F:$F,'Wells Fargo'!$G:$G,'Cash Flow'!$A14,'Wells Fargo'!$A:$A,BI$1,'Wells Fargo'!$B:$B,"<="&'Cash Flow'!BI$3,'Wells Fargo'!$B:$B,">"&'Cash Flow'!BH$3) -> 0
A15: Dorry | B15: =SUM(C15:BI15) -> -300 | C15: =SUMIFS('Wells Fargo'!$F:$F,'Wells Fargo'!$G:$G,'Cash Flow'!$A15,'Wells Fargo'!$A:$A,C$1,'Wells Fargo'!$B:$B,"<="&'Cash Flow'!C$3) -> 0 | D15: =SUMIFS('Wells Fargo'!$F:$F,'Wells Fargo'!$G:$G,'Cash Flow'!$A15,'Wells Fargo'!$A:$A,D$1,'Wells Fargo'!$B:$B,"<="&'Cash Flow'!D$3,'Wells Fargo'!$B:$B,">"&'Cash Flow'!C$3) -> 0 | E15: =SUMIFS('Wells Fargo'!$F:$F,'Wells Fargo'!$G:$G,'Cash Flow'!$A15,'Wells Fargo'!$A:$A,E$1,'Wells Fargo'!$B:$B,"<="&'Cash Flow'!E$3,'Wells Fargo'!$B:$B,">"&'Cash Flow'!D$3) -> 0 | F15: =SUMIFS('Wells Fargo'!$F:$F,'Wells Fargo'!$G:$G,'Cash Flow'!$A15,'Wells Fargo'!$A:$A,F$1,'Wells Fargo'!$B:$B,"<="&'Cash Flow'!F$3,'Wells Fargo'!$B:$B,">"&'Cash Flow'!E$3) -> 0 | G15: =SUMIFS('Wells Fargo'!$F:$F,'Wells Fargo'!$G:$G,'Cash Flow'!$A15,'Wells Fargo'!$A:$A,G$1,'Wells Fargo'!$B:$B,"<="&'Cash Flow'!G$3,'Wells Fargo'!$B:$B,">"&'Cash Flow'!F$3) -> 0 | H15: =SUMIFS('Wells Fargo'!$F:$F,'Wells Fargo'!$G:$G,'Cash Flow'!$A15,'Wells Fargo'!$A:$A,H$1,'Wells Fargo'!$B:$B,"<="&'Cash Flow'!H$3) -> 0 | I15: =SUMIFS('Wells Fargo'!$F:$F,'Wells Fargo'!$G:$G,'Cash Flow'!$A15,'Wells Fargo'!$A:$A,I$1,'Wells Fargo'!$B:$B,"<="&'Cash Flow'!I$3,'Wells Fargo'!$B:$B,">"&'Cash Flow'!H$3) -> 0 | J15: =SUMIFS('Wells Fargo'!$F:$F,'Wells Fargo'!$G:$G,'Cash Flow'!$A15,'Wells Fargo'!$A:$A,J$1,'Wells Fargo'!$B:$B,"<="&'Cash Flow'!J$3,'Wells Fargo'!$B:$B,">"&'Cash Flow'!I$3) -> 0 | K15: =SUMIFS('Wells Fargo'!$F:$F,'Wells Fargo'!$G:$G,'Cash Flow'!$A15,'Wells Fargo'!$A:$A,K$1,'Wells Fargo'!$B:$B,"<="&'Cash Flow'!K$3,'Wells Fargo'!$B:$B,">"&'Cash Flow'!J$3) -> 0 | L15: =SUMIFS('Wells Fargo'!$F:$F,'Wells Fargo'!$G:$G,'Cash Flow'!$A15,'Wells Fargo'!$A:$A,L$1,'Wells Fargo'!$B:$B,"<="&'Cash Flow'!L$3) -> 0 | M15: =SUMIFS('Wells Fargo'!$F:$F,'Wells Fargo'!$G:$G,'Cash Flow'!$A15,'Wells Fargo'!$A:$A,M$1,'Wells Fargo'!$B:$B,"<="&'Cash Flow'!M$3,'Wells Fargo'!$B:$B,">"&'Cash Flow'!L$3) -> 0 | N15: =SUMIFS('Wells Fargo'!$F:$F,'Wells Fargo'!$G:$G,'Cash Flow'!$A15,'Wells Fargo'!$A:$A,N$1,'Wells Fargo'!$B:$B,"<="&'Cash Flow'!N$3,'Wells Fargo'!$B:$B,">"&'Cash Flow'!M$3) -> 0 | O15: =SUMIFS('Wells Fargo'!$F:$F,'Wells Fargo'!$G:$G,'Cash Flow'!$A15,'Wells Fargo'!$A:$A,O$1,'Wells Fargo'!$B:$B,"<="&'Cash Flow'!O$3,'Wells Fargo'!$B:$B,">"&'Cash Flow'!N$3) -> 0 | P15: =SUMIFS('Wells Fargo'!$F:$F,'Wells Fargo'!$G:$G,'Cash Flow'!$A15,'Wells Fargo'!$A:$A,P$1,'Wells Fargo'!$B:$B,"<="&'Cash Flow'!P$3,'Wells Fargo'!$B:$B,">"&'Cash Flow'!O$3) -> 0 | Q15: =SUMIFS('Wells Fargo'!$F:$F,'Wells Fargo'!$G:$G,'Cash Flow'!$A15,'Wells Fargo'!$A:$A,Q$1,'Wells Fargo'!$B:$B,"<="&'Cash Flow'!Q$3) -> 0 | R15: =SUMIFS('Wells Fargo'!$F:$F,'Wells Fargo'!$G:$G,'Cash Flow'!$A15,'Wells Fargo'!$A:$A,R$1,'Wells Fargo'!$B:$B,"<="&'Cash Flow'!R$3,'Wells Fargo'!$B:$B,">"&'Cash Flow'!Q$3) -> 0 | S15: =SUMIFS('Wells Fargo'!$F:$F,'Wells Fargo'!$G:$G,'Cash Flow'!$A15,'Wells Fargo'!$A:$A,S$1,'Wells Fargo'!$B:$B,"<="&'Cash Flow'!S$3,'Wells Fargo'!$B:$B,">"&'Cash Flow'!R$3) -> -250 | T15: =SUMIFS('Wells Fargo'!$F:$F,'Wells Fargo'!$G:$G,'Cash Flow'!$A15,'Wells Fargo'!$A:$A,T$1,'Wells Fargo'!$B:$B,"<="&'Cash Flow'!T$3,'Wells Fargo'!$B:$B,">"&'Cash Flow'!S$3) -> 0 | U15: =SUMIFS('Wells Fargo'!$F:$F,'Wells Fargo'!$G:$G,'Cash Flow'!$A15,'Wells Fargo'!$A:$A,U$1,'Wells Fargo'!$B:$B,"<="&'Cash Flow'!U$3,'Wells Fargo'!$B:$B,">"&'Cash Flow'!T$3) -> -50 | V15: =SUMIFS('Wells Fargo'!$F:$F,'Wells Fargo'!$G:$G,'Cash Flow'!$A15,'Wells Fargo'!$A:$A,V$1,'Wells Fargo'!$B:$B,"<="&'Cash Flow'!V$3) -> 0 | W15: =SUMIFS('Wells Fargo'!$F:$F,'Wells Fargo'!$G:$G,'Cash Flow'!$A15,'Wells Fargo'!$A:$A,W$1,'Wells Fargo'!$B:$B,"<="&'Cash Flow'!W$3,'Wells Fargo'!$B:$B,">"&'Cash Flow'!V$3) -> 0 | X15: =SUMIFS('Wells Fargo'!$F:$F,'Wells Fargo'!$G:$G,'Cash Flow'!$A15,'Wells Fargo'!$A:$A,X$1,'Wells Fargo'!$B:$B,"<="&'Cash Flow'!X$3,'Wells Fargo'!$B:$B,">"&'Cash Flow'!W$3) -> 0 | Y15: =SUMIFS('Wells Fargo'!$F:$F,'Wells Fargo'!$G:$G,'Cash Flow'!$A15,'Wells Fargo'!$A:$A,Y$1,'Wells Fargo'!$B:$B,"<="&'Cash Flow'!Y$3,'Wells Fargo'!$B:$B,">"&'Cash Flow'!X$3) -> 0 | Z15: =SUMIFS('Wells Fargo'!$F:$F,'Wells Fargo'!$G:$G,'Cash Flow'!$A15,'Wells Fargo'!$A:$A,Z$1,'Wells Fargo'!$B:$B,"<="&'Cash Flow'!Z$3,'Wells Fargo'!$B:$B,">"&'Cash Flow'!Y$3) -> 0 | AA15: =SUMIFS('Wells Fargo'!$F:$F,'Wells Fargo'!$G:$G,'Cash Flow'!$A15,'Wells Fargo'!$A:$A,AA$1,'Wells Fargo'!$B:$B,"<="&'Cash Flow'!AA$3) -> 0 | AB15: =SUMIFS('Wells Fargo'!$F:$F,'Wells Fargo'!$G:$G,'Cash Flow'!$A15,'Wells Fargo'!$A:$A,AB$1,'Wells Fargo'!$B:$B,"<="&'Cash Flow'!AB$3,'Wells Fargo'!$B:$B,">"&'Cash Flow'!AA$3) -> 0 | AC15: =SUMIFS('Wells Fargo'!$F:$F,'Wells Fargo'!$G:$G,'Cash Flow'!$A15,'Wells Fargo'!$A:$A,AC$1,'Wells Fargo'!$B:$B,"<="&'Cash Flow'!AC$3,'Wells Fargo'!$B:$B,">"&'Cash Flow'!AB$3) -> 0 | AD15: =SUMIFS('Wells Fargo'!$F:$F,'Wells Fargo'!$G:$G,'Cash Flow'!$A15,'Wells Fargo'!$A:$A,AD$1,'Wells Fargo'!$B:$B,"<="&'Cash Flow'!AD$3,'Wells Fargo'!$B:$B,">"&'Cash Flow'!AC$3) -> 0 | AE15: =SUMIFS('Wells Fargo'!$F:$F,'Wells Fargo'!$G:$G,'Cash Flow'!$A15,'Wells Fargo'!$A:$A,AE$1,'Wells Fargo'!$B:$B,"<="&'Cash Flow'!AE$3,'Wells Fargo'!$B:$B,">"&'Cash Flow'!AD$3) -> 0 | AF15: =SUMIFS('Wells Fargo'!$F:$F,'Wells Fargo'!$G:$G,'Cash Flow'!$A15,'Wells Fargo'!$A:$A,AF$1,'Wells Fargo'!$B:$B,"<="&'Cash Flow'!AF$3) -> 0 | AG15: =SUMIFS('Wells Fargo'!$F:$F,'Wells Fargo'!$G:$G,'Cash Flow'!$A15,'Wells Fargo'!$A:$A,AG$1,'Wells Fargo'!$B:$B,"<="&'Cash Flow'!AG$3,'Wells Fargo'!$B:$B,">"&'Cash Flow'!AF$3) -> 0 | AH15: =SUMIFS('Wells Fargo'!$F:$F,'Wells Fargo'!$G:$G,'Cash Flow'!$A15,'Wells Fargo'!$A:$A,AH$1,'Wells Fargo'!$B:$B,"<="&'Cash Flow'!AH$3,'Wells Fargo'!$B:$B,">"&'Cash Flow'!AG$3) -> 0 | AI15: =SUMIFS('Wells Fargo'!$F:$F,'Wells Fargo'!$G:$G,'Cash Flow'!$A15,'Wells Fargo'!$A:$A,AI$1,'Wells Fargo'!$B:$B,"<="&'Cash Flow'!AI$3,'Wells Fargo'!$B:$B,">"&'Cash Flow'!AH$3) -> 0 | AJ15: =SUMIFS('Wells Fargo'!$F:$F,'Wells Fargo'!$G:$G,'Cash Flow'!$A15,'Wells Fargo'!$A:$A,AJ$1,'Wells Fargo'!$B:$B,"<="&'Cash Flow'!AJ$3,'Wells Fargo'!$B:$B,">"&'Cash Flow'!AI$3) -> 0 | AK15: =SUMIFS('Wells Fargo'!$F:$F,'Wells Fargo'!$G:$G,'Cash Flow'!$A15,'Wells Fargo'!$A:$A,AK$1,'Wells Fargo'!$B:$B,"<="&'Cash Flow'!AK$3) -> 0 | AL15: =SUMIFS('Wells Fargo'!$F:$F,'Wells Fargo'!$G:$G,'Cash Flow'!$A15,'Wells Fargo'!$A:$A,AL$1,'Wells Fargo'!$B:$B,"<="&'Cash Flow'!AL$3,'Wells Fargo'!$B:$B,">"&'Cash Flow'!AK$3) -> 0 | AM15: =SUMIFS('Wells Fargo'!$F:$F,'Wells Fargo'!$G:$G,'Cash Flow'!$A15,'Wells Fargo'!$A:$A,AM$1,'Wells Fargo'!$B:$B,"<="&'Cash Flow'!AM$3,'Wells Fargo'!$B:$B,">"&'Cash Flow'!AL$3) -> 0 | AN15: =SUMIFS('Wells Fargo'!$F:$F,'Wells Fargo'!$G:$G,'Cash Flow'!$A15,'Wells Fargo'!$A:$A,AN$1,'Wells Fargo'!$B:$B,"<="&'Cash Flow'!AN$3,'Wells Fargo'!$B:$B,">"&'Cash Flow'!AM$3) -> 0 | AO15: =SUMIFS('Wells Fargo'!$F:$F,'Wells Fargo'!$G:$G,'Cash Flow'!$A15,'Wells Fargo'!$A:$A,AO$1,'Wells Fargo'!$B:$B,"<="&'Cash Flow'!AO$3,'Wells Fargo'!$B:$B,">"&'Cash Flow'!AN$3) -> 0 | AP15: =SUMIFS('Wells Fargo'!$F:$F,'Wells Fargo'!$G:$G,'Cash Flow'!$A15,'Wells Fargo'!$A:$A,AP$1,'Wells Fargo'!$B:$B,"<="&'Cash Flow'!AP$3) -> 0 | AQ15: =SUMIFS('Wells Fargo'!$F:$F,'Wells Fargo'!$G:$G,'Cash Flow'!$A15,'Wells Fargo'!$A:$A,AQ$1,'Wells Fargo'!$B:$B,"<="&'Cash Flow'!AQ$3,'Wells Fargo'!$B:$B,">"&'Cash Flow'!AP$3) -> 0 | AR15: =SUMIFS('Wells Fargo'!$F:$F,'Wells Fargo'!$G:$G,'Cash Flow'!$A15,'Wells Fargo'!$A:$A,AR$1,'Wells Fargo'!$B:$B,"<="&'Cash Flow'!AR$3,'Wells Fargo'!$B:$B,">"&'Cash Flow'!AQ$3) -> 0 | AS15: =SUMIFS('Wells Fargo'!$F:$F,'Wells Fargo'!$G:$G,'Cash Flow'!$A15,'Wells Fargo'!$A:$A,AS$1,'Wells Fargo'!$B:$B,"<="&'Cash Flow'!AS$3,'Wells Fargo'!$B:$B,">"&'Cash Flow'!AR$3) -> 0 | AT15: =SUMIFS('Wells Fargo'!$F:$F,'Wells Fargo'!$G:$G,'Cash Flow'!$A15,'Wells Fargo'!$A:$A,AT$1,'Wells Fargo'!$B:$B,"<="&'Cash Flow'!AT$3,'Wells Fargo'!$B:$B,">"&'Cash Flow'!AS$3) -> 0 | AU15: =SUMIFS('Wells Fargo'!$F:$F,'Wells Fargo'!$G:$G,'Cash Flow'!$A15,'Wells Fargo'!$A:$A,AU$1,'Wells Fargo'!$B:$B,"<="&'Cash Flow'!AU$3) -> 0 | AV15: =SUMIFS('Wells Fargo'!$F:$F,'Wells Fargo'!$G:$G,'Cash Flow'!$A15,'Wells Fargo'!$A:$A,AV$1,'Wells Fargo'!$B:$B,"<="&'Cash Flow'!AV$3,'Wells Fargo'!$B:$B,">"&'Cash Flow'!AU$3) -> 0 | AW15: =SUMIFS('Wells Fargo'!$F:$F,'Wells Fargo'!$G:$G,'Cash Flow'!$A15,'Wells Fargo'!$A:$A,AW$1,'Wells Fargo'!$B:$B,"<="&'Cash Flow'!AW$3,'Wells Fargo'!$B:$B,">"&'Cash Flow'!AV$3) -> 0 | AX15: =SUMIFS('Wells Fargo'!$F:$F,'Wells Fargo'!$G:$G,'Cash Flow'!$A15,'Wells Fargo'!$A:$A,AX$1,'Wells Fargo'!$B:$B,"<="&'Cash Flow'!AX$3,'Wells Fargo'!$B:$B,">"&'Cash Flow'!AW$3) -> 0 | AY15: =SUMIFS('Wells Fargo'!$F:$F,'Wells Fargo'!$G:$G,'Cash Flow'!$A15,'Wells Fargo'!$A:$A,AY$1,'Wells Fargo'!$B:$B,"<="&'Cash Flow'!AY$3,'Wells Fargo'!$B:$B,">"&'Cash Flow'!AX$3) -> 0 | AZ15: =SUMIFS('Wells Fargo'!$F:$F,'Wells Fargo'!$G:$G,'Cash Flow'!$A15,'Wells Fargo'!$A:$A,AZ$1,'Wells Fargo'!$B:$B,"<="&'Cash Flow'!AZ$3) -> 0 | BA15: =SUMIFS('Wells Fargo'!$F:$F,'Wells Fargo'!$G:$G,'Cash Flow'!$A15,'Wells Fargo'!$A:$A,BA$1,'Wells Fargo'!$B:$B,"<="&'Cash Flow'!BA$3,'Wells Fargo'!$B:$B,">"&'Cash Flow'!AZ$3) -> 0 | BB15: =SUMIFS('Wells Fargo'!$F:$F,'Wells Fargo'!$G:$G,'Cash Flow'!$A15,'Wells Fargo'!$A:$A,BB$1,'Wells Fargo'!$B:$B,"<="&'Cash Flow'!BB$3,'Wells Fargo'!$B:$B,">"&'Cash Flow'!BA$3) -> 0 | BC15: =SUMIFS('Wells Fargo'!$F:$F,'Wells Fargo'!$G:$G,'Cash Flow'!$A15,'Wells Fargo'!$A:$A,BC$1,'Wells Fargo'!$B:$B,"<="&'Cash Flow'!BC$3,'Wells Fargo'!$B:$B,">"&'Cash Flow'!BB$3) -> 0 | BD15: =SUMIFS('Wells Fargo'!$F:$F,'Wells Fargo'!$G:$G,'Cash Flow'!$A15,'Wells Fargo'!$A:$A,BD$1,'Wells Fargo'!$B:$B,"<="&'Cash Flow'!BD$3,'Wells Fargo'!$B:$B,">"&'Cash Flow'!BC$3) -> 0 | BE15: =SUMIFS('Wells Fargo'!$F:$F,'Wells Fargo'!$G:$G,'Cash Flow'!$A15,'Wells Fargo'!$A:$A,BE$1,'Wells Fargo'!$B:$B,"<="&'Cash Flow'!BE$3) -> 0 | BF15: =SUMIFS('Wells Fargo'!$F:$F,'Wells Fargo'!$G:$G,'Cash Flow'!$A15,'Wells Fargo'!$A:$A,BF$1,'Wells Fargo'!$B:$B,"<="&'Cash Flow'!BF$3,'Wells Fargo'!$B:$B,">"&'Cash Flow'!BE$3) -> 0 | BG15: =SUMIFS('Wells Fargo'!$F:$F,'Wells Fargo'!$G:$G,'Cash Flow'!$A15,'Wells Fargo'!$A:$A,BG$1,'Wells Fargo'!$B:$B,"<="&'Cash Flow'!BG$3,'Wells Fargo'!$B:$B,">"&'Cash Flow'!BF$3) -> 0 | BH15: =SUMIFS('Wells Fargo'!$F:$F,'Wells Fargo'!$G:$G,'Cash Flow'!$A15,'Wells Fargo'!$A:$A,BH$1,'Wells Fargo'!$B:$B,"<="&'Cash Flow'!BH$3,'Wells Fargo'!$B:$B,">"&'Cash Flow'!BG$3) -> 0 | BI15: =SUMIFS('Wells Fargo'!$F:$F,'Wells Fargo'!$G:$G,'Cash Flow'!$A15,'Wells Fargo'!$A:$A,BI$1,'Wells Fargo'!$B:$B,"<="&'Cash Flow'!BI$3,'Wells Fargo'!$B:$B,">"&'Cash Flow'!BH$3) -> 0
A16: Elephant | B16: =SUM(C16:BI16) -> 15895.41 | C16: =SUMIFS('Wells Fargo'!$F:$F,'Wells Fargo'!$G:$G,'Cash Flow'!$A16,'Wells Fargo'!$A:$A,C$1,'Wells Fargo'!$B:$B,"<="&'Cash Flow'!C$3) -> 0 | D16: =SUMIFS('Wells Fargo'!$F:$F,'Wells Fargo'!$G:$G,'Cash Flow'!$A16,'Wells Fargo'!$A:$A,D$1,'Wells Fargo'!$B:$B,"<="&'Cash Flow'!D$3,'Wells Fargo'!$B:$B,">"&'Cash Flow'!C$3) -> 0 | E16: =SUMIFS('Wells Fargo'!$F:$F,'Wells Fargo'!$G:$G,'Cash Flow'!$A16,'Wells Fargo'!$A:$A,E$1,'Wells Fargo'!$B:$B,"<="&'Cash Flow'!E$3,'Wells Fargo'!$B:$B,">"&'Cash Flow'!D$3) -> 1459.65 | F16: =SUMIFS('Wells Fargo'!$F:$F,'Wells Fargo'!$G:$G,'Cash Flow'!$A16,'Wells Fargo'!$A:$A,F$1,'Wells Fargo'!$B:$B,"<="&'Cash Flow'!F$3,'Wells Fargo'!$B:$B,">"&'Cash Flow'!E$3) -> 0 | G16: =SUMIFS('Wells Fargo'!$F:$F,'Wells Fargo'!$G:$G,'Cash Flow'!$A16,'Wells Fargo'!$A:$A,G$1,'Wells Fargo'!$B:$B,"<="&'Cash Flow'!G$3,'Wells Fargo'!$B:$B,">"&'Cash Flow'!F$3) -> 1459.64 | H16: =SUMIFS('Wells Fargo'!$F:$F,'Wells Fargo'!$G:$G,'Cash Flow'!$A16,'Wells Fargo'!$A:$A,H$1,'Wells Fargo'!$B:$B,"<="&'Cash Flow'!H$3) -> 0 | I16: =SUMIFS('Wells Fargo'!$F:$F,'Wells Fargo'!$G:$G,'Cash Flow'!$A16,'Wells Fargo'!$A:$A,I$1,'Wells Fargo'!$B:$B,"<="&'Cash Flow'!I$3,'Wells Fargo'!$B:$B,">"&'Cash Flow'!H$3) -> 1809.65 | J16: =SUMIFS('Wells Fargo'!$F:$F,'Wells Fargo'!$G:$G,'Cash Flow'!$A16,'Wells Fargo'!$A:$A,J$1,'Wells Fargo'!$B:$B,"<="&'Cash Flow'!J$3,'Wells Fargo'!$B:$B,">"&'Cash Flow'!I$3) -> 0 | K16: =SUMIFS('Wells Fargo'!$F:$F,'Wells Fargo'!$G:$G,'Cash Flow'!$A16,'Wells Fargo'!$A:$A,K$1,'Wells Fargo'!$B:$B,"<="&'Cash Flow'!K$3,'Wells Fargo'!$B:$B,">"&'Cash Flow'!J$3) -> 1459.65 | L16: =SUMIFS('Wells Fargo'!$F:$F,'Wells Fargo'!$G:$G,'Cash Flow'!$A16,'Wells Fargo'!$A:$A,L$1,'Wells Fargo'!$B:$B,"<="&'Cash Flow'!L$3) -> 0 | M16: =SUMIFS('Wells Fargo'!$F:$F,'Wells Fargo'!$G:$G,'Cash Flow'!$A16,'Wells Fargo'!$A:$A,M$1,'Wells Fargo'!$B:$B,"<="&'Cash Flow'!M$3,'Wells Fargo'!$B:$B,">"&'Cash Flow'!L$3) -> 1459.64 | N16: =SUMIFS('Wells Fargo'!$F:$F,'Wells Fargo'!$G:$G,'Cash Flow'!$A16,'Wells Fargo'!$A:$A,N$1,'Wells Fargo'!$B:$B,"<="&'Cash Flow'!N$3,'Wells Fargo'!$B:$B,">"&'Cash Flow'!M$3) -> 0 | O16: =SUMIFS('Wells Fargo'!$F:$F,'Wells Fargo'!$G:$G,'Cash Flow'!$A16,'Wells Fargo'!$A:$A,O$1,'Wells Fargo'!$B:$B,"<="&'Cash Flow'!O$3,'Wells Fargo'!$B:$B,">"&'Cash Flow'!N$3) -> 1457.82 | P16: =SUMIFS('Wells Fargo'!$F:$F,'Wells Fargo'!$G:$G,'Cash Flow'!$A16,'Wells Fargo'!$A:$A,P$1,'Wells Fargo'!$B:$B,"<="&'Cash Flow'!P$3,'Wells Fargo'!$B:$B,">"&'Cash Flow'!O$3) -> 0 | Q16: =SUMIFS('Wells Fargo'!$F:$F,'Wells Fargo'!$G:$G,'Cash Flow'!$A16,'Wells Fargo'!$A:$A,Q$1,'Wells Fargo'!$B:$B,"<="&'Cash Flow'!Q$3) -> 0 | R16: =SUMIFS('Wells Fargo'!$F:$F,'Wells Fargo'!$G:$G,'Cash Flow'!$A16,'Wells Fargo'!$A:$A,R$1,'Wells Fargo'!$B:$B,"<="&'Cash Flow'!R$3,'Wells Fargo'!$B:$B,">"&'Cash Flow'!Q$3) -> 1242.82 | S16: =SUMIFS('Wells Fargo'!$F:$F,'Wells Fargo'!$G:$G,'Cash Flow'!$A16,'Wells Fargo'!$A:$A,S$1,'Wells Fargo'!$B:$B,"<="&'Cash Flow'!S$3,'Wells Fargo'!$B:$B,">"&'Cash Flow'!R$3) -> 0 | T16: =SUMIFS('Wells Fargo'!$F:$F,'Wells Fargo'!$G:$G,'Cash Flow'!$A16,'Wells Fargo'!$A:$A,T$1,'Wells Fargo'!$B:$B,"<="&'Cash Flow'!T$3,'Wells Fargo'!$B:$B,">"&'Cash Flow'!S$3) -> 1174.51 | U16: =SUMIFS('Wells Fargo'!$F:$F,'Wells Fargo'!$G:$G,'Cash Flow'!$A16,'Wells Fargo'!$A:$A,U$1,'Wells Fargo'!$B:$B,"<="&'Cash Flow'!U$3,'Wells Fargo'!$B:$B,">"&'Cash Flow'!T$3) -> 0 | V16: =SUMIFS('Wells Fargo'!$F:$F,'Wells Fargo'!$G:$G,'Cash Flow'!$A16,'Wells Fargo'!$A:$A,V$1,'Wells Fargo'!$B:$B,"<="&'Cash Flow'!V$3) -> 1174.52 | W16: =SUMIFS('Wells Fargo'!$F:$F,'Wells Fargo'!$G:$G,'Cash Flow'!$A16,'Wells Fargo'!$A:$A,W$1,'Wells Fargo'!$B:$B,"<="&'Cash Flow'!W$3,'Wells Fargo'!$B:$B,">"&'Cash Flow'!V$3) -> 0 | X16: =SUMIFS('Wells Fargo'!$F:$F,'Wells Fargo'!$G:$G,'Cash Flow'!$A16,'Wells Fargo'!$A:$A,X$1,'Wells Fargo'!$B:$B,"<="&'Cash Flow'!X$3,'Wells Fargo'!$B:$B,">"&'Cash Flow'!W$3) -> 1342.98 | Y16: =SUMIFS('Wells Fargo'!$F:$F,'Wells Fargo'!$G:$G,'Cash Flow'!$A16,'Wells Fargo'!$A:$A,Y$1,'Wells Fargo'!$B:$B,"<="&'Cash Flow'!Y$3,'Wells Fargo'!$B:$B,">"&'Cash Flow'!X$3) -> 0 | Z16: =SUMIFS('Wells Fargo'!$F:$F,'Wells Fargo'!$G:$G,'Cash Flow'!$A16,'Wells Fargo'!$A:$A,Z$1,'Wells Fargo'!$B:$B,"<="&'Cash Flow'!Z$3,'Wells Fargo'!$B:$B,">"&'Cash Flow'!Y$3) -> 0 | AA16: =SUMIFS('Wells Fargo'!$F:$F,'Wells Fargo'!$G:$G,'Cash Flow'!$A16,'Wells Fargo'!$A:$A,AA$1,'Wells Fargo'!$B:$B,"<="&'Cash Flow'!AA$3) -> 1174.51 | AB16: =SUMIFS('Wells Fargo'!$F:$F,'Wells Fargo'!$G:$G,'Cash Flow'!$A16,'Wells Fargo'!$A:$A,AB$1,'Wells Fargo'!$B:$B,"<="&'Cash Flow'!AB$3,'Wells Fargo'!$B:$B,">"&'Cash Flow'!AA$3) -> 0 | AC16: =SUMIFS('Wells Fargo'!$F:$F,'Wells Fargo'!$G:$G,'Cash Flow'!$A16,'Wells Fargo'!$A:$A,AC$1,'Wells Fargo'!$B:$B,"<="&'Cash Flow'!AC$3,'Wells Fargo'!$B:$B,">"&'Cash Flow'!AB$3) -> 680.02 | AD16: =SUMIFS('Wells Fargo'!$F:$F,'Wells Fargo'!$G:$G,'Cash Flow'!$A16,'Wells Fargo'!$A:$A,AD$1,'Wells Fargo'!$B:$B,"<="&'Cash Flow'!AD$3,'Wells Fargo'!$B:$B,">"&'Cash Flow'!AC$3) -> 0 | AE16: =SUMIFS('Wells Fargo'!$F:$F,'Wells Fargo'!$G:$G,'Cash Flow'!$A16,'Wells Fargo'!$A:$A,AE$1,'Wells Fargo'!$B:$B,"<="&'Cash Flow'!AE$3,'Wells Fargo'!$B:$B,">"&'Cash Flow'!AD$3) -> 0 | AF16: =SUMIFS('Wells Fargo'!$F:$F,'Wells Fargo'!$G:$G,'Cash Flow'!$A16,'Wells Fargo'!$A:$A,AF$1,'Wells Fargo'!$B:$B,"<="&'Cash Flow'!AF$3) -> 0 | AG16: =SUMIFS('Wells Fargo'!$F:$F,'Wells Fargo'!$G:$G,'Cash Flow'!$A16,'Wells Fargo'!$A:$A,AG$1,'Wells Fargo'!$B:$B,"<="&'Cash Flow'!AG$3,'Wells Fargo'!$B:$B,">"&'Cash Flow'!AF$3) -> 0 | AH16: =SUMIFS('Wells Fargo'!$F:$F,'Wells Fargo'!$G:$G,'Cash Flow'!$A16,'Wells Fargo'!$A:$A,AH$1,'Wells Fargo'!$B:$B,"<="&'Cash Flow'!AH$3,'Wells Fargo'!$B:$B,">"&'Cash Flow'!AG$3) -> 0 | AI16: =SUMIFS('Wells Fargo'!$F:$F,'Wells Fargo'!$G:$G,'Cash Flow'!$A16,'Wells Fargo'!$A:$A,AI$1,'Wells Fargo'!$B:$B,"<="&'Cash Flow'!AI$3,'Wells Fargo'!$B:$B,">"&'Cash Flow'!AH$3) -> 0 | AJ16: =SUMIFS('Wells Fargo'!$F:$F,'Wells Fargo'!$G:$G,'Cash Flow'!$A16,'Wells Fargo'!$A:$A,AJ$1,'Wells Fargo'!$B:$B,"<="&'Cash Flow'!AJ$3,'Wells Fargo'!$B:$B,">"&'Cash Flow'!AI$3) -> 0 | AK16: =SUMIFS('Wells Fargo'!$F:$F,'Wells Fargo'!$G:$G,'Cash Flow'!$A16,'Wells Fargo'!$A:$A,AK$1,'Wells Fargo'!$B:$B,"<="&'Cash Flow'!AK$3) -> 0 | AL16: =SUMIFS('Wells Fargo'!$F:$F,'Wells Fargo'!$G:$G,'Cash Flow'!$A16,'Wells Fargo'!$A:$A,AL$1,'Wells Fargo'!$B:$B,"<="&'Cash Flow'!AL$3,'Wells Fargo'!$B:$B,">"&'Cash Flow'!AK$3) -> 0 | AM16: =SUMIFS('Wells Fargo'!$F:$F,'Wells Fargo'!$G:$G,'Cash Flow'!$A16,'Wells Fargo'!$A:$A,AM$1,'Wells Fargo'!$B:$B,"<="&'Cash Flow'!AM$3,'Wells Fargo'!$B:$B,">"&'Cash Flow'!AL$3) -> 0 | AN16: =SUMIFS('Wells Fargo'!$F:$F,'Wells Fargo'!$G:$G,'Cash Flow'!$A16,'Wells Fargo'!$A:$A,AN$1,'Wells Fargo'!$B:$B,"<="&'Cash Flow'!AN$3,'Wells Fargo'!$B:$B,">"&'Cash Flow'!AM$3) -> 0 | AO16: =SUMIFS('Wells Fargo'!$F:$F,'Wells Fargo'!$G:$G,'Cash Flow'!$A16,'Wells Fargo'!$A:$A,AO$1,'Wells Fargo'!$B:$B,"<="&'Cash Flow'!AO$3,'Wells Fargo'!$B:$B,">"&'Cash Flow'!AN$3) -> 0 | AP16: =SUMIFS('Wells Fargo'!$F:$F,'Wells Fargo'!$G:$G,'Cash Flow'!$A16,'Wells Fargo'!$A:$A,AP$1,'Wells Fargo'!$B:$B,"<="&'Cash Flow'!AP$3) -> 0 | AQ16: =SUMIFS('Wells Fargo'!$F:$F,'Wells Fargo'!$G:$G,'Cash Flow'!$A16,'Wells Fargo'!$A:$A,AQ$1,'Wells Fargo'!$B:$B,"<="&'Cash Flow'!AQ$3,'Wells Fargo'!$B:$B,">"&'Cash Flow'!AP$3) -> 0 | AR16: =SUMIFS('Wells Fargo'!$F:$F,'Wells Fargo'!$G:$G,'Cash Flow'!$A16,'Wells Fargo'!$A:$A,AR$1,'Wells Fargo'!$B:$B,"<="&'Cash Flow'!AR$3,'Wells Fargo'!$B:$B,">"&'Cash Flow'!AQ$3) -> 0 | AS16: =SUMIFS('Wells Fargo'!$F:$F,'Wells Fargo'!$G:$G,'Cash Flow'!$A16,'Wells Fargo'!$A:$A,AS$1,'Wells Fargo'!$B:$B,"<="&'Cash Flow'!AS$3,'Wells Fargo'!$B:$B,">"&'Cash Flow'!AR$3) -> 0 | AT16: =SUMIFS('Wells Fargo'!$F:$F,'Wells Fargo'!$G:$G,'Cash Flow'!$A16,'Wells Fargo'!$A:$A,AT$1,'Wells Fargo'!$B:$B,"<="&'Cash Flow'!AT$3,'Wells Fargo'!$B:$B,">"&'Cash Flow'!AS$3) -> 0 | AU16: =SUMIFS('Wells Fargo'!$F:$F,'Wells Fargo'!$G:$G,'Cash Flow'!$A16,'Wells Fargo'!$A:$A,AU$1,'Wells Fargo'!$B:$B,"<="&'Cash Flow'!AU$3) -> 0 | AV16: =SUMIFS('Wells Fargo'!$F:$F,'Wells Fargo'!$G:$G,'Cash Flow'!$A16,'Wells Fargo'!$A:$A,AV$1,'Wells Fargo'!$B:$B,"<="&'Cash Flow'!AV$3,'Wells Fargo'!$B:$B,">"&'Cash Flow'!AU$3) -> 0 | AW16: =SUMIFS('Wells Fargo'!$F:$F,'Wells Fargo'!$G:$G,'Cash Flow'!$A16,'Wells Fargo'!$A:$A,AW$1,'Wells Fargo'!$B:$B,"<="&'Cash Flow'!AW$3,'Wells Fargo'!$B:$B,">"&'Cash Flow'!AV$3) -> 0 | AX16: =SUMIFS('Wells Fargo'!$F:$F,'Wells Fargo'!$G:$G,'Cash Flow'!$A16,'Wells Fargo'!$A:$A,AX$1,'Wells Fargo'!$B:$B,"<="&'Cash Flow'!AX$3,'Wells Fargo'!$B:$B,">"&'Cash Flow'!AW$3) -> 0 | AY16: =SUMIFS('Wells Fargo'!$F:$F,'Wells Fargo'!$G:$G,'Cash Flow'!$A16,'Wells Fargo'!$A:$A,AY$1,'Wells Fargo'!$B:$B,"<="&'Cash Flow'!AY$3,'Wells Fargo'!$B:$B,">"&'Cash Flow'!AX$3) -> 0 | AZ16: =SUMIFS('Wells Fargo'!$F:$F,'Wells Fargo'!$G:$G,'Cash Flow'!$A16,'Wells Fargo'!$A:$A,AZ$1,'Wells Fargo'!$B:$B,"<="&'Cash Flow'!AZ$3) -> 0 | BA16: =SUMIFS('Wells Fargo'!$F:$F,'Wells Fargo'!$G:$G,'Cash Flow'!$A16,'Wells Fargo'!$A:$A,BA$1,'Wells Fargo'!$B:$B,"<="&'Cash Flow'!BA$3,'Wells Fargo'!$B:$B,">"&'Cash Flow'!AZ$3) -> 0 | BB16: =SUMIFS('Wells Fargo'!$F:$F,'Wells Fargo'!$G:$G,'Cash Flow'!$A16,'Wells Fargo'!$A:$A,BB$1,'Wells Fargo'!$B:$B,"<="&'Cash Flow'!BB$3,'Wells Fargo'!$B:$B,">"&'Cash Flow'!BA$3) -> 0 | BC16: =SUMIFS('Wells Fargo'!$F:$F,'Wells Fargo'!$G:$G,'Cash Flow'!$A16,'Wells Fargo'!$A:$A,BC$1,'Wells Fargo'!$B:$B,"<="&'Cash Flow'!BC$3,'Wells Fargo'!$B:$B,">"&'Cash Flow'!BB$3) -> 0 | BD16: =SUMIFS('Wells Fargo'!$F:$F,'Wells Fargo'!$G:$G,'Cash Flow'!$A16,'Wells Fargo'!$A:$A,BD$1,'Wells Fargo'!$B:$B,"<="&'Cash Flow'!BD$3,'Wells Fargo'!$B:$B,">"&'Cash Flow'!BC$3) -> 0 | BE16: =SUMIFS('Wells Fargo'!$F:$F,'Wells Fargo'!$G:$G,'Cash Flow'!$A16,'Wells Fargo'!$A:$A,BE$1,'Wells Fargo'!$B:$B,"<="&'Cash Flow'!BE$3) -> 0 | BF16: =SUMIFS('Wells Fargo'!$F:$F,'Wells Fargo'!$G:$G,'Cash Flow'!$A16,'Wells Fargo'!$A:$A,BF$1,'Wells Fargo'!$B:$B,"<="&'Cash Flow'!BF$3,'Wells Fargo'!$B:$B,">"&'Cash Flow'!BE$3) -> 0 | BG16: =SUMIFS('Wells Fargo'!$F:$F,'Wells Fargo'!$G:$G,'Cash Flow'!$A16,'Wells Fargo'!$A:$A,BG$1,'Wells Fargo'!$B:$B,"<="&'Cash Flow'!BG$3,'Wells Fargo'!$B:$B,">"&'Cash Flow'!BF$3) -> 0 | BH16: =SUMIFS('Wells Fargo'!$F:$F,'Wells Fargo'!$G:$G,'Cash Flow'!$A16,'Wells Fargo'!$A:$A,BH$1,'Wells Fargo'!$B:$B,"<="&'Cash Flow'!BH$3,'Wells Fargo'!$B:$B,">"&'Cash Flow'!BG$3) -> 0 | BI16: =SUMIFS('Wells Fargo'!$F:$F,'Wells Fargo'!$G:$G,'Cash Flow'!$A16,'Wells Fargo'!$A:$A,BI$1,'Wells Fargo'!$B:$B,"<="&'Cash Flow'!BI$3,'Wells Fargo'!$B:$B,">"&'Cash Flow'!BH$3) -> 0
... A40: Stimulus 2 | B40: =SUM(C40:BI40) -> 2800 | C40: =SUMIFS('Wells Fargo'!$F:$F,'Wells Fargo'!$G:$G,'Cash Flow'!$A40,'Wells Fargo'!$A:$A,C$1,'Wells Fargo'!$B:$B,"<="&'Cash Flow'!C$3) -> 0 | D40: =SUMIFS('Wells Fargo'!$F:$F,'Wells Fargo'!$G:$G,'Cash Flow'!$A40,'Wells Fargo'!$A:$A,D$1,'Wells Fargo'!$B:$B,"<="&'Cash Flow'!D$3,'Wells Fargo'!$B:$B,">"&'Cash Flow'!C$3) -> 0 | E40: =SUMIFS('Wells Fargo'!$F:$F,'Wells Fargo'!$G:$G,'Cash Flow'!$A40,'Wells Fargo'!$A:$A,E$1,'Wells Fargo'!$B:$B,"<="&'Cash Flow'!E$3,'Wells Fargo'!$B:$B,">"&'Cash Flow'!D$3) -> 0 | F40: =SUMIFS('Wells Fargo'!$F:$F,'Wells Fargo'!$G:$G,'Cash Flow'!$A40,'Wells Fargo'!$A:$A,F$1,'Wells Fargo'!$B:$B,"<="&'Cash Flow'!F$3,'Wells Fargo'!$B:$B,">"&'Cash Flow'!E$3) -> 0 | G40: =SUMIFS('Wells Fargo'!$F:$F,'Wells Fargo'!$G:$G,'Cash Flow'!$A40,'Wells Fargo'!$A:$A,G$1,'Wells Fargo'!$B:$B,"<="&'Cash Flow'!G$3,'Wells Fargo'!$B:$B,">"&'Cash Flow'!F$3) -> 0 | H40: =SUMIFS('Wells Fargo'!$F:$F,'Wells Fargo'!$G:$G,'Cash Flow'!$A40,'Wells Fargo'!$A:$A,H$1,'Wells Fargo'!$B:$B,"<="&'Cash Flow'!H$3) -> 0 | I40: =SUMIFS('Wells Fargo'!$F:$F,'Wells Fargo'!$G:$G,'Cash Flow'!$A40,'Wells Fargo'!$A:$A,I$1,'Wells Fargo'!$B:$B,"<="&'Cash Flow'!I$3,'Wells Fargo'!$B:$B,">"&'Cash Flow'!H$3) -> 0 | J40: =SUMIFS('Wells Fargo'!$F:$F,'Wells Fargo'!$G:$G,'Cash Flow'!$A40,'Wells Fargo'!$A:$A,J$1,'Wells Fargo'!$B:$B,"<="&'Cash Flow'!J$3,'Wells Fargo'!$B:$B,">"&'Cash Flow'!I$3) -> 0 | K40: =SUMIFS('Wells Fargo'!$F:$F,'Wells Fargo'!$G:$G,'Cash Flow'!$A40,'Wells Fargo'!$A:$A,K$1,'Wells Fargo'!$B:$B,"<="&'Cash Flow'!K$3,'Wells Fargo'!$B:$B,">"&'Cash Flow'!J$3) -> 0 | L40: =SUMIFS('Wells Fargo'!$F:$F,'Wells Fargo'!$G:$G,'Cash Flow'!$A40,'Wells Fargo'!$A:$A,L$1,'Wells Fargo'!$B:$B,"<="&'Cash Flow'!L$3) -> 0 | M40: =SUMIFS('Wells Fargo'!$F:$F,'Wells Fargo'!$G:$G,'Cash Flow'!$A40,'Wells Fargo'!$A:$A,M$1,'Wells Fargo'!$B:$B,"<="&'Cash Flow'!M$3,'Wells Fargo'!$B:$B,">"&'Cash Flow'!L$3) -> 0 | N40: =SUMIFS('Wells Fargo'!$F:$F,'Wells Fargo'!$G:$G,'Cash Flow'!$A40,'Wells Fargo'!$A:$A,N$1,'Wells Fargo'!$B:$B,"<="&'Cash Flow'!N$3,'Wells Fargo'!$B:$B,">"&'Cash Flow'!M$3) -> 2800 | O40: =SUMIFS('Wells Fargo'!$F:$F,'Wells Fargo'!$G:$G,'Cash Flow'!$A40,'Wells Fargo'!$A:$A,O$1,'Wells Fargo'!$B:$B,"<="&'Cash Flow'!O$3,'Wells Fargo'!$B:$B,">"&'Cash Flow'!N$3) -> 0 | P40: =SUMIFS('Wells Fargo'!$F:$F,'Wells Fargo'!$G:$G,'Cash Flow'!$A40,'Wells Fargo'!$A:$A,P$1,'Wells Fargo'!$B:$B,"<="&'Cash Flow'!P$3,'Wells Fargo'!$B:$B,">"&'Cash Flow'!O$3) -> 0 | Q40: =SUMIFS('Wells Fargo'!$F:$F,'Wells Fargo'!$G:$G,'Cash Flow'!$A40,'Wells Fargo'!$A:$A,Q$1,'Wells Fargo'!$B:$B,"<="&'Cash Flow'!Q$3) -> 0 | R40: =SUMIFS('Wells Fargo'!$F:$F,'Wells Fargo'!$G:$G,'Cash Flow'!$A40,'Wells Fargo'!$A:$A,R$1,'Wells Fargo'!$B:$B,"<="&'Cash Flow'!R$3,'Wells Fargo'!$B:$B,">"&'Cash Flow'!Q$3) -> 0 | S40: =SUMIFS('Wells Fargo'!$F:$F,'Wells Fargo'!$G:$G,'Cash Flow'!$A40,'Wells Fargo'!$A:$A,S$1,'Wells Fargo'!$B:$B,"<="&'Cash Flow'!S$3,'Wells Fargo'!$B:$B,">"&'Cash Flow'!R$3) -> 0 | T40: =SUMIFS('Wells Fargo'!$F:$F,'Wells Fargo'!$G:$G,'Cash Flow'!$A40,'Wells Fargo'!$A:$A,T$1,'Wells Fargo'!$B:$B,"<="&'Cash Flow'!T$3,'Wells Fargo'!$B:$B,">"&'Cash Flow'!S$3) -> 0 | U40: =SUMIFS('Wells Fargo'!$F:$F,'Wells Fargo'!$G:$G,'Cash Flow'!$A40,'Wells Fargo'!$A:$A,U$1,'Wells Fargo'!$B:$B,"<="&'Cash Flow'!U$3,'Wells Fargo'!$B:$B,">"&'Cash Flow'!T$3) -> 0 | V40: =SUMIFS('Wells Fargo'!$F:$F,'Wells Fargo'!$G:$G,'Cash Flow'!$A40,'Wells Fargo'!$A:$A,V$1,'Wells Fargo'!$B:$B,"<="&'Cash Flow'!V$3) -> 0 | W40: =SUMIFS('Wells Fargo'!$F:$F,'Wells Fargo'!$G:$G,'Cash Flow'!$A40,'Wells Fargo'!$A:$A,W$1,'Wells Fargo'!$B:$B,"<="&'Cash Flow'!W$3,'Wells Fargo'!$B:$B,">"&'Cash Flow'!V$3) -> 0 | X40: =SUMIFS('Wells Fargo'!$F:$F,'Wells Fargo'!$G:$G,'Cash Flow'!$A40,'Wells Fargo'!$A:$A,X$1,'Wells Fargo'!$B:$B,"<="&'Cash Flow'!X$3,'Wells Fargo'!$B:$B,">"&'Cash Flow'!W$3) -> 0 | Y40: =SUMIFS('Wells Fargo'!$F:$F,'Wells Fargo'!$G:$G,'Cash Flow'!$A40,'Wells Fargo'!$A:$A,Y$1,'Wells Fargo'!$B:$B,"<="&'Cash Flow'!Y$3,'Wells Fargo'!$B:$B,">"&'Cash Flow'!X$3) -> 0 | Z40: =SUMIFS('Wells Fargo'!$F:$F,'Wells Fargo'!$G:$G,'Cash Flow'!$A40,'Wells Fargo'!$A:$A,Z$1,'Wells Fargo'!$B:$B,"<="&'Cash Flow'!Z$3,'Wells Fargo'!$B:$B,">"&'Cash Flow'!Y$3) -> 0 | AA40: =SUMIFS('Wells Fargo'!$F:$F,'Wells Fargo'!$G:$G,'Cash Flow'!$A40,'Wells Fargo'!$A:$A,AA$1,'Wells Fargo'!$B:$B,"<="&'Cash Flow'!AA$3) -> 0 | AB40: =SUMIFS('Wells Fargo'!$F:$F,'Wells Fargo'!$G:$G,'Cash Flow'!$A40,'Wells Fargo'!$A:$A,AB$1,'Wells Fargo'!$B:$B,"<="&'Cash Flow'!AB$3,'Wells Fargo'!$B:$B,">"&'Cash Flow'!AA$3) -> 0 | AC40: =SUMIFS('Wells Fargo'!$F:$F,'Wells Fargo'!$G:$G,'Cash Flow'!$A40,'Wells Fargo'!$A:$A,AC$1,'Wells Fargo'!$B:$B,"<="&'Cash Flow'!AC$3,'Wells Fargo'!$B:$B,">"&'Cash Flow'!AB$3) -> 0 | AD40: =SUMIFS('Wells Fargo'!$F:$F,'Wells Fargo'!$G:$G,'Cash Flow'!$A40,'Wells Fargo'!$A:$A,AD$1,'Wells Fargo'!$B:$B,"<="&'Cash Flow'!AD$3,'Wells Fargo'!$B:$B,">"&'Cash Flow'!AC$3) -> 0 | AE40: =SUMIFS('Wells Fargo'!$F:$F,'Wells Fargo'!$G:$G,'Cash Flow'!$A40,'Wells Fargo'!$A:$A,AE$1,'Wells Fargo'!$B:$B,"<="&'Cash Flow'!AE$3,'Wells Fargo'!$B:$B,">"&'Cash Flow'!AD$3) -> 0 | AF40: =SUMIFS('Wells Fargo'!$F:$F,'Wells Fargo'!$G:$G,'Cash Flow'!$A40,'Wells Fargo'!$A:$A,AF$1,'Wells Fargo'!$B:$B,"<="&'Cash Flow'!AF$3) -> 0 | AG40: =SUMIFS('Wells Fargo'!$F:$F,'Wells Fargo'!$G:$G,'Cash Flow'!$A40,'Wells Fargo'!$A:$A,AG$1,'Wells Fargo'!$B:$B,"<="&'Cash Flow'!AG$3,'Wells Fargo'!$B:$B,">"&'Cash Flow'!AF$3) -> 0 | AH40: =SUMIFS('Wells Fargo'!$F:$F,'Wells Fargo'!$G:$G,'Cash Flow'!$A40,'Wells Fargo'!$A:$A,AH$1,'Wells Fargo'!$B:$B,"<="&'Cash Flow'!AH$3,'Wells Fargo'!$B:$B,">"&'Cash Flow'!AG$3) -> 0 | AI40: =SUMIFS('Wells Fargo'!$F:$F,'Wells Fargo'!$G:$G,'Cash Flow'!$A40,'Wells Fargo'!$A:$A,AI$1,'Wells Fargo'!$B:$B,"<="&'Cash Flow'!AI$3,'Wells Fargo'!$B:$B,">"&'Cash Flow'!AH$3) -> 0 | AJ40: =SUMIFS('Wells Fargo'!$F:$F,'Wells Fargo'!$G:$G,'Cash Flow'!$A40,'Wells Fargo'!$A:$A,AJ$1,'Wells Fargo'!$B:$B,"<="&'Cash Flow'!AJ$3,'Wells Fargo'!$B:$B,">"&'Cash Flow'!AI$3) -> 0 | AK40: =SUMIFS('Wells Fargo'!$F:$F,'Wells Fargo'!$G:$G,'Cash Flow'!$A40,'Wells Fargo'!$A:$A,AK$1,'Wells Fargo'!$B:$B,"<="&'Cash Flow'!AK$3) -> 0 | AL40: =SUMIFS('Wells Fargo'!$F:$F,'Wells Fargo'!$G:$G,'Cash Flow'!$A40,'Wells Fargo'!$A:$A,AL$1,'Wells Fargo'!$B:$B,"<="&'Cash Flow'!AL$3,'Wells Fargo'!$B:$B,">"&'Cash Flow'!AK$3) -> 0 | AM40: =SUMIFS('Wells Fargo'!$F:$F,'Wells Fargo'!$G:$G,'Cash Flow'!$A40,'Wells Fargo'!$A:$A,AM$1,'Wells Fargo'!$B:$B,"<="&'Cash Flow'!AM$3,'Wells Fargo'!$B:$B,">"&'Cash Flow'!AL$3) -> 0 | AN40: =SUMIFS('Wells Fargo'!$F:$F,'Wells Fargo'!$G:$G,'Cash Flow'!$A40,'Wells Fargo'!$A:$A,AN$1,'Wells Fargo'!$B:$B,"<="&'Cash Flow'!AN$3,'Wells Fargo'!$B:$B,">"&'Cash Flow'!AM$3) -> 0 | AO40: =SUMIFS('Wells Fargo'!$F:$F,'Wells Fargo'!$G:$G,'Cash Flow'!$A40,'Wells Fargo'!$A:$A,AO$1,'Wells Fargo'!$B:$B,"<="&'Cash Flow'!AO$3,'Wells Fargo'!$B:$B,">"&'Cash Flow'!AN$3) -> 0 | AP40: =SUMIFS('Wells Fargo'!$F:$F,'Wells Fargo'!$G:$G,'Cash Flow'!$A40,'Wells Fargo'!$A:$A,AP$1,'Wells Fargo'!$B:$B,"<="&'Cash Flow'!AP$3) -> 0 | AQ40: =SUMIFS('Wells Fargo'!$F:$F,'Wells Fargo'!$G:$G,'Cash Flow'!$A40,'Wells Fargo'!$A:$A,AQ$1,'Wells Fargo'!$B:$B,"<="&'Cash Flow'!AQ$3,'Wells Fargo'!$B:$B,">"&'Cash Flow'!AP$3) -> 0 | AR40: =SUMIFS('Wells Fargo'!$F:$F,'Wells Fargo'!$G:$G,'Cash Flow'!$A40,'Wells Fargo'!$A:$A,AR$1,'Wells Fargo'!$B:$B,"<="&'Cash Flow'!AR$3,'Wells Fargo'!$B:$B,">"&'Cash Flow'!AQ$3) -> 0 | AS40: =SUMIFS('Wells Fargo'!$F:$F,'Wells Fargo'!$G:$G,'Cash Flow'!$A40,'Wells Fargo'!$A:$A,AS$1,'Wells Fargo'!$B:$B,"<="&'Cash Flow'!AS$3,'Wells Fargo'!$B:$B,">"&'Cash Flow'!AR$3) -> 0 | AT40: =SUMIFS('Wells Fargo'!$F:$F,'Wells Fargo'!$G:$G,'Cash Flow'!$A40,'Wells Fargo'!$A:$A,AT$1,'Wells Fargo'!$B:$B,"<="&'Cash Flow'!AT$3,'Wells Fargo'!$B:$B,">"&'Cash Flow'!AS$3) -> 0 | AU40: =SUMIFS('Wells Fargo'!$F:$F,'Wells Fargo'!$G:$G,'Cash Flow'!$A40,'Wells Fargo'!$A:$A,AU$1,'Wells Fargo'!$B:$B,"<="&'Cash Flow'!AU$3) -> 0 | AV40: =SUMIFS('Wells Fargo'!$F:$F,'Wells Fargo'!$G:$G,'Cash Flow'!$A40,'Wells Fargo'!$A:$A,AV$1,'Wells Fargo'!$B:$B,"<="&'Cash Flow'!AV$3,'Wells Fargo'!$B:$B,">"&'Cash Flow'!AU$3) -> 0 | AW40: =SUMIFS('Wells Fargo'!$F:$F,'Wells Fargo'!$G:$G,'Cash Flow'!$A40,'Wells Fargo'!$A:$A,AW$1,'Wells Fargo'!$B:$B,"<="&'Cash Flow'!AW$3,'Wells Fargo'!$B:$B,">"&'Cash Flow'!AV$3) -> 0 | AX40: =SUMIFS('Wells Fargo'!$F:$F,'Wells Fargo'!$G:$G,'Cash Flow'!$A40,'Wells Fargo'!$A:$A,AX$1,'Wells Fargo'!$B:$B,"<="&'Cash Flow'!AX$3,'Wells Fargo'!$B:$B,">"&'Cash Flow'!AW$3) -> 0 | AY40: =SUMIFS('Wells Fargo'!$F:$F,'Wells Fargo'!$G:$G,'Cash Flow'!$A40,'Wells Fargo'!$A:$A,AY$1,'Wells Fargo'!$B:$B,"<="&'Cash Flow'!AY$3,'Wells Fargo'!$B:$B,">"&'Cash Flow'!AX$3) -> 0 | AZ40: =SUMIFS('Wells Fargo'!$F:$F,'Wells Fargo'!$G:$G,'Cash Flow'!$A40,'Wells Fargo'!$A:$A,AZ$1,'Wells Fargo'!$B:$B,"<="&'Cash Flow'!AZ$3) -> 0 | BA40: =SUMIFS('Wells Fargo'!$F:$F,'Wells Fargo'!$G:$G,'Cash Flow'!$A40,'Wells Fargo'!$A:$A,BA$1,'Wells Fargo'!$B:$B,"<="&'Cash Flow'!BA$3,'Wells Fargo'!$B:$B,">"&'Cash Flow'!AZ$3) -> 0 | BB40: =SUMIFS('Wells Fargo'!$F:$F,'Wells Fargo'!$G:$G,'Cash Flow'!$A40,'Wells Fargo'!$A:$A,BB$1,'Wells Fargo'!$B:$B,"<="&'Cash Flow'!BB$3,'Wells Fargo'!$B:$B,">"&'Cash Flow'!BA$3) -> 0 | BC40: =SUMIFS('Wells Fargo'!$F:$F,'Wells Fargo'!$G:$G,'Cash Flow'!$A40,'Wells Fargo'!$A:$A,BC$1,'Wells Fargo'!$B:$B,"<="&'Cash Flow'!BC$3,'Wells Fargo'!$B:$B,">"&'Cash Flow'!BB$3) -> 0 | BD40: =SUMIFS('Wells Fargo'!$F:$F,'Wells Fargo'!$G:$G,'Cash Flow'!$A40,'Wells Fargo'!$A:$A,BD$1,'Wells Fargo'!$B:$B,"<="&'Cash Flow'!BD$3,'Wells Fargo'!$B:$B,">"&'Cash Flow'!BC$3) -> 0 | BE40: =SUMIFS('Wells Fargo'!$F:$F,'Wells Fargo'!$G:$G,'Cash Flow'!$A40,'Wells Fargo'!$A:$A,BE$1,'Wells Fargo'!$B:$B,"<="&'Cash Flow'!BE$3) -> 0 | BF40: =SUMIFS('Wells Fargo'!$F:$F,'Wells Fargo'!$G:$G,'Cash Flow'!$A40,'Wells Fargo'!$A:$A,BF$1,'Wells Fargo'!$B:$B,"<="&'Cash Flow'!BF$3,'Wells Fargo'!$B:$B,">"&'Cash Flow'!BE$3) -> 0 | BG40: =SUMIFS('Wells Fargo'!$F:$F,'Wells Fargo'!$G:$G,'Cash Flow'!$A40,'Wells Fargo'!$A:$A,BG$1,'Wells Fargo'!$B:$B,"<="&'Cash Flow'!BG$3,'Wells Fargo'!$B:$B,">"&'Cash Flow'!BF$3) -> 0 | BH40: =SUMIFS('Wells Fargo'!$F:$F,'Wells Fargo'!$G:$G,'Cash Flow'!$A40,'Wells Fargo'!$A:$A,BH$1,'Wells Fargo'!$B:$B,"<="&'Cash Flow'!BH$3,'Wells Fargo'!$B:$B,">"&'Cash Flow'!BG$3) -> 0 | BI40: =SUMIFS('Wells Fargo'!$F:$F,'Wells Fargo'!$G:$G,'Cash Flow'!$A40,'Wells Fargo'!$A:$A,BI$1,'Wells Fargo'!$B:$B,"<="&'Cash Flow'!BI$3,'Wells Fargo'!$B:$B,">"&'Cash Flow'!BH$3) -> 0
A41: Stranger | B41: =SUM(B4:B40) -> 1283.71 | C41: =SUMIFS('Wells Fargo'!$F:$F,'Wells Fargo'!$G:$G,'Cash Flow'!$A41,'Wells Fargo'!$A:$A,C$1,'Wells Fargo'!$B:$B,"<="&'Cash Flow'!C$3) -> 0 | D41: =SUMIFS('Wells Fargo'!$F:$F,'Wells Fargo'!$G:$G,'Cash Flow'!$A41,'Wells Fargo'!$A:$A,D$1,'Wells Fargo'!$B:$B,"<="&'Cash Flow'!D$3,'Wells Fargo'!$B:$B,">"&'Cash Flow'!C$3) -> 0 | E41: =SUMIFS('Wells Fargo'!$F:$F,'Wells Fargo'!$G:$G,'Cash Flow'!$A41,'Wells Fargo'!$A:$A,E$1,'Wells Fargo'!$B:$B,"<="&'Cash Flow'!E$3,'Wells Fargo'!$B:$B,">"&'Cash Flow'!D$3) -> 0 | F41: =SUMIFS('Wells Fargo'!$F:$F,'Wells Fargo'!$G:$G,'Cash Flow'!$A41,'Wells Fargo'!$A:$A,F$1,'Wells Fargo'!$B:$B,"<="&'Cash Flow'!F$3,'Wells Fargo'!$B:$B,">"&'Cash Flow'!E$3) -> 0 | G41: =SUMIFS('Wells Fargo'!$F:$F,'Wells Fargo'!$G:$G,'Cash Flow'!$A41,'Wells Fargo'!$A:$A,G$1,'Wells Fargo'!$B:$B,"<="&'Cash Flow'!G$3,'Wells Fargo'!$B:$B,">"&'Cash Flow'!F$3) -> 0 | H41: =SUMIFS('Wells Fargo'!$F:$F,'Wells Fargo'!$G:$G,'Cash Flow'!$A41,'Wells Fargo'!$A:$A,H$1,'Wells Fargo'!$B:$B,"<="&'Cash Flow'!H$3) -> 0 | I41: =SUMIFS('Wells Fargo'!$F:$F,'Wells Fargo'!$G:$G,'Cash Flow'!$A41,'Wells Fargo'!$A:$A,I$1,'Wells Fargo'!$B:$B,"<="&'Cash Flow'!I$3,'Wells Fargo'!$B:$B,">"&'Cash Flow'!H$3) -> 0 | J41: =SUMIFS('Wells Fargo'!$F:$F,'Wells Fargo'!$G:$G,'Cash Flow'!$A41,'Wells Fargo'!$A:$A,J$1,'Wells Fargo'!$B:$B,"<="&'Cash Flow'!J$3,'Wells Fargo'!$B:$B,">"&'Cash Flow'!I$3) -> 0 | K41: =SUMIFS('Wells Fargo'!$F:$F,'Wells Fargo'!$G:$G,'Cash Flow'!$A41,'Wells Fargo'!$A:$A,K$1,'Wells Fargo'!$B:$B,"<="&'Cash Flow'!K$3,'Wells Fargo'!$B:$B,">"&'Cash Flow'!J$3) -> 0 | L41: =SUMIFS('Wells Fargo'!$F:$F,'Wells Fargo'!$G:$G,'Cash Flow'!$A41,'Wells Fargo'!$A:$A,L$1,'Wells Fargo'!$B:$B,"<="&'Cash Flow'!L$3) -> 0 | M41: =SUMIFS('Wells Fargo'!$F:$F,'Wells Fargo'!$G:$G,'Cash Flow'!$A41,'Wells Fargo'!$A:$A,M$1,'Wells Fargo'!$B:$B,"<="&'Cash Flow'!M$3,'Wells Fargo'!$B:$B,">"&'Cash Flow'!L$3) -> 0 | N41: =SUMIFS('Wells Fargo'!$F:$F,'Wells Fargo'!$G:$G,'Cash Flow'!$A41,'Wells Fargo'!$A:$A,N$1,'Wells Fargo'!$B:$B,"<="&'Cash Flow'!N$3,'Wells Fargo'!$B:$B,">"&'Cash Flow'!M$3) -> 0 | O41: =SUMIFS('Wells Fargo'!$F:$F,'Wells Fargo'!$G:$G,'Cash Flow'!$A41,'Wells Fargo'!$A:$A,O$1,'Wells Fargo'!$B:$B,"<="&'Cash Flow'!O$3,'Wells Fargo'!$B:$B,">"&'Cash Flow'!N$3) -> 0 | P41: =SUMIFS('Wells Fargo'!$F:$F,'Wells Fargo'!$G:$G,'Cash Flow'!$A41,'Wells Fargo'!$A:$A,P$1,'Wells Fargo'!$B:$B,"<="&'Cash Flow'!P$3,'Wells Fargo'!$B:$B,">"&'Cash Flow'!O$3) -> 0 | Q41: =SUMIFS('Wells Fargo'!$F:$F,'Wells Fargo'!$G:$G,'Cash Flow'!$A41,'Wells Fargo'!$A:$A,Q$1,'Wells Fargo'!$B:$B,"<="&'Cash Flow'!Q$3) -> 0 | R41: =SUMIFS('Wells Fargo'!$F:$F,'Wells Fargo'!$G:$G,'Cash Flow'!$A41,'Wells Fargo'!$A:$A,R$1,'Wells Fargo'!$B:$B,"<="&'Cash Flow'!R$3,'Wells Fargo'!$B:$B,">"&'Cash Flow'!Q$3) -> 0 | S41: =SUMIFS('Wells Fargo'!$F:$F,'Wells Fargo'!$G:$G,'Cash Flow'!$A41,'Wells Fargo'!$A:$A,S$1,'Wells Fargo'!$B:$B,"<="&'Cash Flow'!S$3,'Wells Fargo'!$B:$B,">"&'Cash Flow'!R$3) -> 0 | T41: =SUMIFS('Wells Fargo'!$F:$F,'Wells Fargo'!$G:$G,'Cash Flow'!$A41,'Wells Fargo'!$A:$A,T$1,'Wells Fargo'!$B:$B,"<="&'Cash Flow'!T$3,'Wells Fargo'!$B:$B,">"&'Cash Flow'!S$3) -> 0 | U41: =SUMIFS('Wells Fargo'!$F:$F,'Wells Fargo'!$G:$G,'Cash Flow'!$A41,'Wells Fargo'!$A:$A,U$1,'Wells Fargo'!$B:$B,"<="&'Cash Flow'!U$3,'Wells Fargo'!$B:$B,">"&'Cash Flow'!T$3) -> 0 | V41: =SUMIFS('Wells Fargo'!$F:$F,'Wells Fargo'!$G:$G,'Cash Flow'!$A41,'Wells Fargo'!$A:$A,V$1,'Wells Fargo'!$B:$B,"<="&'Cash Flow'!V$3) -> 0 | W41: =SUMIFS('Wells Fargo'!$F:$F,'Wells Fargo'!$G:$G,'Cash Flow'!$A41,'Wells Fargo'!$A:$A,W$1,'Wells Fargo'!$B:$B,"<="&'Cash Flow'!W$3,'Wells Fargo'!$B:$B,">"&'Cash Flow'!V$3) -> 0 | X41: =SUMIFS('Wells Fargo'!$F:$F,'Wells Fargo'!$G:$G,'Cash Flow'!$A41,'Wells Fargo'!$A:$A,X$1,'Wells Fargo'!$B:$B,"<="&'Cash Flow'!X$3,'Wells Fargo'!$B:$B,">"&'Cash Flow'!W$3) -> 0 | Y41: =SUMIFS('Wells Fargo'!$F:$F,'Wells Fargo'!$G:$G,'Cash Flow'!$A41,'Wells Fargo'!$A:$A,Y$1,'Wells Fargo'!$B:$B,"<="&'Cash Flow'!Y$3,'Wells Fargo'!$B:$B,">"&'Cash Flow'!X$3) -> -50 | Z41: =SUMIFS('Wells Fargo'!$F:$F,'Wells Fargo'!$G:$G,'Cash Flow'!$A41,'Wells Fargo'!$A:$A,Z$1,'Wells Fargo'!$B:$B,"<="&'Cash Flow'!Z$3,'Wells Fargo'!$B:$B,">"&'Cash Flow'!Y$3) -> 0 | AA41: =SUMIFS('Wells Fargo'!$F:$F,'Wells Fargo'!$G:$G,'Cash Flow'!$A41,'Wells Fargo'!$A:$A,AA$1,'Wells Fargo'!$B:$B,"<="&'Cash Flow'!AA$3) -> 0 | AB41: =SUMIFS('Wells Fargo'!$F:$F,'Wells Fargo'!$G:$G,'Cash Flow'!$A41,'Wells Fargo'!$A:$A,AB$1,'Wells Fargo'!$B:$B,"<="&'Cash Flow'!AB$3,'Wells Fargo'!$B:$B,">"&'Cash Flow'!AA$3) -> 0 | AC41: =SUMIFS('Wells Fargo'!$F:$F,'Wells Fargo'!$G:$G,'Cash Flow'!$A41,'Wells Fargo'!$A:$A,AC$1,'Wells Fargo'!$B:$B,"<="&'Cash Flow'!AC$3,'Wells Fargo'!$B:$B,">"&'Cash Flow'!AB$3) -> 0 | AD41: =SUMIFS('Wells Fargo'!$F:$F,'Wells Fargo'!$G:$G,'Cash Flow'!$A41,'Wells Fargo'!$A:$A,AD$1,'Wells Fargo'!$B:$B,"<="&'Cash Flow'!AD$3,'Wells Fargo'!$B:$B,">"&'Cash Flow'!AC$3) -> 0 | AE41: =SUMIFS('Wells Fargo'!$F:$F,'Wells Fargo'!$G:$G,'Cash Flow'!$A41,'Wells Fargo'!$A:$A,AE$1,'Wells Fargo'!$B:$B,"<="&'Cash Flow'!AE$3,'Wells Fargo'!$B:$B,">"&'Cash Flow'!AD$3) -> 0 | AF41: =SUMIFS('Wells Fargo'!$F:$F,'Wells Fargo'!$G:$G,'Cash Flow'!$A41,'Wells Fargo'!$A:$A,AF$1,'Wells Fargo'!$B:$B,"<="&'Cash Flow'!AF$3) -> 0 | AG41: =SUMIFS('Wells Fargo'!$F:$F,'Wells Fargo'!$G:$G,'Cash Flow'!$A41,'Wells Fargo'!$A:$A,AG$1,'Wells Fargo'!$B:$B,"<="&'Cash Flow'!AG$3,'Wells Fargo'!$B:$B,">"&'Cash Flow'!AF$3) -> 0 | AH41: =SUMIFS('Wells Fargo'!$F:$F,'Wells Fargo'!$G:$G,'Cash Flow'!$A41,'Wells Fargo'!$A:$A,AH$1,'Wells Fargo'!$B:$B,"<="&'Cash Flow'!AH$3,'Wells Fargo'!$B:$B,">"&'Cash Flow'!AG$3) -> 0 | AI41: =SUMIFS('Wells Fargo'!$F:$F,'Wells Fargo'!$G:$G,'Cash Flow'!$A41,'Wells Fargo'!$A:$A,AI$1,'Wells Fargo'!$B:$B,"<="&'Cash Flow'!AI$3,'Wells Fargo'!$B:$B,">"&'Cash Flow'!AH$3) -> 0 | AJ41: =SUMIFS('Wells Fargo'!$F:$F,'Wells Fargo'!$G:$G,'Cash Flow'!$A41,'Wells Fargo'!$A:$A,AJ$1,'Wells Fargo'!$B:$B,"<="&'Cash Flow'!AJ$3,'Wells Fargo'!$B:$B,">"&'Cash Flow'!AI$3) -> 0 | AK41: =SUMIFS('Wells Fargo'!$F:$F,'Wells Fargo'!$G:$G,'Cash Flow'!$A41,'Wells Fargo'!$A:$A,AK$1,'Wells Fargo'!$B:$B,"<="&'Cash Flow'!AK$3) -> 0 | AL41: =SUMIFS('Wells Fargo'!$F:$F,'Wells Fargo'!$G:$G,'Cash Flow'!$A41,'Wells Fargo'!$A:$A,AL$1,'Wells Fargo'!$B:$B,"<="&'Cash Flow'!AL$3,'Wells Fargo'!$B:$B,">"&'Cash Flow'!AK$3) -> 0 | AM41: =SUMIFS('Wells Fargo'!$F:$F,'Wells Fargo'!$G:$G,'Cash Flow'!$A41,'Wells Fargo'!$A:$A,AM$1,'Wells Fargo'!$B:$B,"<="&'Cash Flow'!AM$3,'Wells Fargo'!$B:$B,">"&'Cash Flow'!AL$3) -> 0 | AN41: =SUMIFS('Wells Fargo'!$F:$F,'Wells Fargo'!$G:$G,'Cash Flow'!$A41,'Wells Fargo'!$A:$A,AN$1,'Wells Fargo'!$B:$B,"<="&'Cash Flow'!AN$3,'Wells Fargo'!$B:$B,">"&'Cash Flow'!AM$3) -> 0 | AO41: =SUMIFS('Wells Fargo'!$F:$F,'Wells Fargo'!$G:$G,'Cash Flow'!$A41,'Wells Fargo'!$A:$A,AO$1,'Wells Fargo'!$B:$B,"<="&'Cash Flow'!AO$3,'Wells Fargo'!$B:$B,">"&'Cash Flow'!AN$3) -> 0 | AP41: =SUMIFS('Wells Fargo'!$F:$F,'Wells Fargo'!$G:$G,'Cash Flow'!$A41,'Wells Fargo'!$A:$A,AP$1,'Wells Fargo'!$B:$B,"<="&'Cash Flow'!AP$3) -> 0 | AQ41: =SUMIFS('Wells Fargo'!$F:$F,'Wells Fargo'!$G:$G,'Cash Flow'!$A41,'Wells Fargo'!$A:$A,AQ$1,'Wells Fargo'!$B:$B,"<="&'Cash Flow'!AQ$3,'Wells Fargo'!$B:$B,">"&'Cash Flow'!AP$3) -> 0 | AR41: =SUMIFS('Wells Fargo'!$F:$F,'Wells Fargo'!$G:$G,'Cash Flow'!$A41,'Wells Fargo'!$A:$A,AR$1,'Wells Fargo'!$B:$B,"<="&'Cash Flow'!AR$3,'Wells Fargo'!$B:$B,">"&'Cash Flow'!AQ$3) -> 0 | AS41: =SUMIFS('Wells Fargo'!$F:$F,'Wells Fargo'!$G:$G,'Cash Flow'!$A41,'Wells Fargo'!$A:$A,AS$1,'Wells Fargo'!$B:$B,"<="&'Cash Flow'!AS$3,'Wells Fargo'!$B:$B,">"&'Cash Flow'!AR$3) -> 0 | AT41: =SUMIFS('Wells Fargo'!$F:$F,'Wells Fargo'!$G:$G,'Cash Flow'!$A41,'Wells Fargo'!$A:$A,AT$1,'Wells Fargo'!$B:$B,"<="&'Cash Flow'!AT$3,'Wells Fargo'!$B:$B,">"&'Cash Flow'!AS$3) -> 0 | AU41: =SUMIFS('Wells Fargo'!$F:$F,'Wells Fargo'!$G:$G,'Cash Flow'!$A41,'Wells Fargo'!$A:$A,AU$1,'Wells Fargo'!$B:$B,"<="&'Cash Flow'!AU$3) -> 0 | AV41: =SUMIFS('Wells Fargo'!$F:$F,'Wells Fargo'!$G:$G,'Cash Flow'!$A41,'Wells Fargo'!$A:$A,AV$1,'Wells Fargo'!$B:$B,"<="&'Cash Flow'!AV$3,'Wells Fargo'!$B:$B,">"&'Cash Flow'!AU$3) -> 0 | AW41: =SUMIFS('Wells Fargo'!$F:$F,'Wells Fargo'!$G:$G,'Cash Flow'!$A41,'Wells Fargo'!$A:$A,AW$1,'Wells Fargo'!$B:$B,"<="&'Cash Flow'!AW$3,'Wells Fargo'!$B:$B,">"&'Cash Flow'!AV$3) -> 0 | AX41: =SUMIFS('Wells Fargo'!$F:$F,'Wells Fargo'!$G:$G,'Cash Flow'!$A41,'Wells Fargo'!$A:$A,AX$1,'Wells Fargo'!$B:$B,"<="&'Cash Flow'!AX$3,'Wells Fargo'!$B:$B,">"&'Cash Flow'!AW$3) -> 0 | AY41: =SUMIFS('Wells Fargo'!$F:$F,'Wells Fargo'!$G:$G,'Cash Flow'!$A41,'Wells Fargo'!$A:$A,AY$1,'Wells Fargo'!$B:$B,"<="&'Cash Flow'!AY$3,'Wells Fargo'!$B:$B,">"&'Cash Flow'!AX$3) -> 0 | AZ41: =SUMIFS('Wells Fargo'!$F:$F,'Wells Fargo'!$G:$G,'Cash Flow'!$A41,'Wells Fargo'!$A:$A,AZ$1,'Wells Fargo'!$B:$B,"<="&'Cash Flow'!AZ$3) -> 0 | BA41: =SUMIFS('Wells Fargo'!$F:$F,'Wells Fargo'!$G:$G,'Cash Flow'!$A41,'Wells Fargo'!$A:$A,BA$1,'Wells Fargo'!$B:$B,"<="&'Cash Flow'!BA$3,'Wells Fargo'!$B:$B,">"&'Cash Flow'!AZ$3) -> 0 | BB41: =SUMIFS('Wells Fargo'!$F:$F,'Wells Fargo'!$G:$G,'Cash Flow'!$A41,'Wells Fargo'!$A:$A,BB$1,'Wells Fargo'!$B:$B,"<="&'Cash Flow'!BB$3,'Wells Fargo'!$B:$B,">"&'Cash Flow'!BA$3) -> 0 | BC41: =SUMIFS('Wells Fargo'!$F:$F,'Wells Fargo'!$G:$G,'Cash Flow'!$A41,'Wells Fargo'!$A:$A,BC$1,'Wells Fargo'!$B:$B,"<="&'Cash Flow'!BC$3,'Wells Fargo'!$B:$B,">"&'Cash Flow'!BB$3) -> 0 | BD41: =SUMIFS('Wells Fargo'!$F:$F,'Wells Fargo'!$G:$G,'Cash Flow'!$A41,'Wells Fargo'!$A:$A,BD$1,'Wells Fargo'!$B:$B,"<="&'Cash Flow'!BD$3,'Wells Fargo'!$B:$B,">"&'Cash Flow'!BC$3) -> 0 | BE41: =SUMIFS('Wells Fargo'!$F:$F,'Wells Fargo'!$G:$G,'Cash Flow'!$A41,'Wells Fargo'!$A:$A,BE$1,'Wells Fargo'!$B:$B,"<="&'Cash Flow'!BE$3) -> 0 | BF41: =SUMIFS('Wells Fargo'!$F:$F,'Wells Fargo'!$G:$G,'Cash Flow'!$A41,'Wells Fargo'!$A:$A,BF$1,'Wells Fargo'!$B:$B,"<="&'Cash Flow'!BF$3,'Wells Fargo'!$B:$B,">"&'Cash Flow'!BE$3) -> 0 | BG41: =SUMIFS('Wells Fargo'!$F:$F,'Wells Fargo'!$G:$G,'Cash Flow'!$A41,'Wells Fargo'!$A:$A,BG$1,'Wells Fargo'!$B:$B,"<="&'Cash Flow'!BG$3,'Wells Fargo'!$B:$B,">"&'Cash Flow'!BF$3) -> 0 | BH41: =SUMIFS('Wells Fargo'!$F:$F,'Wells Fargo'!$G:$G,'Cash Flow'!$A41,'Wells Fargo'!$A:$A,BH$1,'Wells Fargo'!$B:$B,"<="&'Cash Flow'!BH$3,'Wells Fargo'!$B:$B,">"&'Cash Flow'!BG$3) -> 0 | BI41: =SUMIFS('Wells Fargo'!$F:$F,'Wells Fargo'!$G:$G,'Cash Flow'!$A41,'Wells Fargo'!$A:$A,BI$1,'Wells Fargo'!$B:$B,"<="&'Cash Flow'!BI$3,'Wells Fargo'!$B:$B,">"&'Cash Flow'!BH$3) -> 0
