Workbook
Name allowance: Summary!$J$16
Name AprSun1: DATE('Income Calendar'!CalendarYear,4,1)-WEEKDAY(DATE('Income Calendar'!CalendarYear,4,1))
Name AprSun1: DATE(CalendarYear,4,1)-WEEKDAY(DATE(CalendarYear,4,1))
Name AugSun1: DATE('Income Calendar'!CalendarYear,8,1)-WEEKDAY(DATE('Income Calendar'!CalendarYear,8,1))
Name AugSun1: DATE(CalendarYear,8,1)-WEEKDAY(DATE(CalendarYear,8,1))
Name Budget: Summary!$J$11
Name CalendarYear: 'Income Calendar'!Year1
Name CalendarYear: 'Expense Calendar'!Year1
Name DecSun1: DATE('Income Calendar'!CalendarYear,12,1)-WEEKDAY(DATE('Income Calendar'!CalendarYear,12,1))
Name DecSun1: DATE(CalendarYear,12,1)-WEEKDAY(DATE(CalendarYear,12,1))
Name FebSun1: DATE('Income Calendar'!CalendarYear,2,1)-WEEKDAY(DATE('Income Calendar'!CalendarYear,2,1))
Name FebSun1: DATE(CalendarYear,2,1)-WEEKDAY(DATE(CalendarYear,2,1))
Name fixed: fixed_expenses4[#All]
Name fixed: fixed_expenses[#All]
Name income: 'Income Calendar'!$N$3
Name JanSun1: DATE('Income Calendar'!CalendarYear,1,1)-WEEKDAY(DATE('Income Calendar'!CalendarYear,1,1))
Name JanSun1: DATE(CalendarYear,1,1)-WEEKDAY(DATE(CalendarYear,1,1))
Name JulSun1: DATE('Income Calendar'!CalendarYear,7,1)-WEEKDAY(DATE('Income Calendar'!CalendarYear,7,1))
Name JulSun1: DATE(CalendarYear,7,1)-WEEKDAY(DATE(CalendarYear,7,1))
Name JunSun1: DATE('Income Calendar'!CalendarYear,6,1)-WEEKDAY(DATE('Income Calendar'!CalendarYear,6,1))
Name JunSun1: DATE(CalendarYear,6,1)-WEEKDAY(DATE(CalendarYear,6,1))
Name MarSun1: DATE('Income Calendar'!CalendarYear,3,1)-WEEKDAY(DATE('Income Calendar'!CalendarYear,3,1))
Name MarSun1: DATE(CalendarYear,3,1)-WEEKDAY(DATE(CalendarYear,3,1))
Name MaySun1: DATE('Income Calendar'!CalendarYear,5,1)-WEEKDAY(DATE('Income Calendar'!CalendarYear,5,1))
Name MaySun1: DATE(CalendarYear,5,1)-WEEKDAY(DATE(CalendarYear,5,1))
Name Month1: 'Expense Calendar'!$B$3
Name Month1: 'Income Calendar'!$B$3
Name NovSun1: DATE('Income Calendar'!CalendarYear,11,1)-WEEKDAY(DATE('Income Calendar'!CalendarYear,11,1))
Name NovSun1: DATE(CalendarYear,11,1)-WEEKDAY(DATE(CalendarYear,11,1))
Name OctSun1: DATE('Income Calendar'!CalendarYear,10,1)-WEEKDAY(DATE('Income Calendar'!CalendarYear,10,1))
Name OctSun1: DATE(CalendarYear,10,1)-WEEKDAY(DATE(CalendarYear,10,1))
Name SepSun1: DATE('Income Calendar'!CalendarYear,9,1)-WEEKDAY(DATE('Income Calendar'!CalendarYear,9,1))
Name SepSun1: DATE(CalendarYear,9,1)-WEEKDAY(DATE(CalendarYear,9,1))
Name StartMonth: 'Income Calendar'!$B$4
Name StartMonth: 'Expense Calendar'!$B$4
Name Year1: VALUE(LEFT('Expense Calendar'!$B$1,4))
Name Year1: VALUE(LEFT('Income Calendar'!$B$1,4))

Sheet Summary
A1: lynnangelcontracting@gmail.com | AJ1: *No bills can be due after the 28th due to February
B2: Jan | I2: 1 | J2: =I2+1 -> 2 | K2: =J2+1 -> 3 | L2: =K2+1 -> 4 | M2: =L2+1 -> 5 | N2: =M2+1 -> 6 | O2: =N2+1 -> 7 | P2: =O2+1 -> 8 | Q2: =P2+1 -> 9 | ... AM2: =AL2+1 -> 31
B3: Begin Cash Flow | C3: Income | D3: Fixed Expenses | E3: End Cash Flow | K3: Rent | W3: Paul Phone Bill | AB3: Lynn Phone Bill
A4: ='Expense Calendar'!B6 -> 27 | C4: ='Income Calendar'!P13 -> 800 | D4: ='Expense Calendar'!P13 -> 0 | E4: =C4-D4 -> 800 | W4: Electric
A5: ='Expense Calendar'!B15 -> 3 | B5: =E4 -> 800 | C5: ='Income Calendar'!P22 -> 800 | D5: ='Expense Calendar'!P22 -> 1200 | E5: =C5-D5+B5 -> 400
A6: ='Expense Calendar'!B24 -> 10 | B6: =E5 -> 400 | C6: ='Income Calendar'!P31 -> 800 | D6: ='Expense Calendar'!P31 -> 110 | E6: =C6-D6+B6 -> 1090
A7: ='Expense Calendar'!B33 -> 17 | B7: =E6 -> 1090 | C7: ='Income Calendar'!P40 -> 1570 | D7: ='Expense Calendar'!P40 -> 0 | E7: =C7-D7+B7 -> 2660
A8: ='Expense Calendar'!B42 -> 24 | B8: =E7 -> 2660 | C8: ='Income Calendar'!P49 -> 800 | D8: ='Expense Calendar'!P49 -> 0 | E8: =C8-D8+B8 -> 3460
A9: ='Expense Calendar'!B51 -> 31 | B9: =E8 -> 3460 | C9: ='Income Calendar'!P58 -> 0 | D9: ='Expense Calendar'!P58 -> 0 | E9: =C9-D9+B9 -> 3460
B10: FEB | E10: =E9 -> 3460 | F10: *What cash do we have in our bank right now? (Feb ) | J10: Budget | K10: Leftover (Cash) | L10: Income | M10: % Income
B11: Begin Cash Flow | C11: Income | D11: Fixed Expenses | E11: End Cash Flow | F11: Varibale Expense | G11: Savings | I11: Projected Weekly | J11: 200 | K11: =E97 -> 28882 | L11: =income -> 62420 | M11: =K11/L11 -> 0.46270426
A12: ='Expense Calendar'!B64 -> 31 | B12: =E10 -> 3460 | C12: ='Income Calendar'!P71 -> 1570 | D12: ='Expense Calendar'!P71 -> 1432 | E12: =C12-D12+B12 -> 3598 | F12: =-1*Budget -> -200 | G12: =allowance*-1 -> -50 | I12: Standard | J12: 524.2449 | K12: =L11*0.2 -> 12484 | M12: =K12/L11 -> 0.2
A13: ='Expense Calendar'!B73 -> 7 | B13: =E12+F12+G12 -> 3348 | C13: ='Income Calendar'!P80 -> 800 | D13: ='Expense Calendar'!P80 -> 0 | E13: =C13-D13+B13 -> 4148 | F13: =-1*Budget -> -200 | G13: =allowance*-1 -> -50 | I13: Monthly | J13: =Budget*4 -> 800
A14: ='Expense Calendar'!B82 -> 14 | B14: =E13+F13+G13 -> 3898 | C14: ='Income Calendar'!P89 -> 1570 | D14: ='Expense Calendar'!P89 -> 342 | E14: =C14-D14+B14 -> 5126 | F14: =-1*Budget -> -200 | G14: =allowance*-1 -> -50
A15: ='Expense Calendar'!B91 -> 21 | B15: =E14+F14+G14 -> 4876 | C15: ='Income Calendar'!P98 -> 800 | D15: ='Expense Calendar'!P98 -> 0 | E15: =C15-D15+B15 -> 5676 | F15: =-1*Budget -> -200 | G15: =allowance*-1 -> -50 | J15: Savings | K15: Total
A16: ='Expense Calendar'!B100 -> 28 | B16: =E15+F15+G15 -> 5426 | C16: ='Income Calendar'!P107 -> 0 | D16: ='Expense Calendar'!P107 -> 0 | E16: =C16-D16+B16 -> 5426 | I16: Weekly | J16: 50 | K16: =SUM(G12:G17,G20:G25,G28:G33,G36:G41,G44:G49,G52:G57,G60:G65,G68:G73,G76:G81,G84:G89,G92:G97)*-1 -> 2450 | L16: *without interest
A17: ='Expense Calendar'!B109 -> 7 | B17: =E16+F16+G16 -> 5426 | C17: ='Income Calendar'!P116 -> 0 | D17: ='Expense Calendar'!P116 -> 0 | E17: =C17-D17+B17 -> 5426 | K17: current interest rate | L17: 0.0005 | M17: Bank of America
B18: MAR
B19: Begin Cash Flow | C19: Income | D19: Fixed Expenses | E19: End Cash Flow | F19: Varibale Expense | G19: Savings
A20: ='Expense Calendar'!B122 -> 28 | C20: ='Income Calendar'!P129 -> 1570 | D20: ='Expense Calendar'!P129 -> 1432 | E20: =C20-D20+E17 -> 5564 | F20: =-1*Budget -> -200 | G20: =allowance*-1 -> -50
A21: ='Expense Calendar'!B131 -> 7 | B21: =E20+F20+G20 -> 5314 | C21: ='Income Calendar'!P138 -> 800 | D21: ='Expense Calendar'!P138 -> 0 | E21: =C21-D21+B21 -> 6114 | F21: =-1*Budget -> -200 | G21: =allowance*-1 -> -50
A22: ='Expense Calendar'!B140 -> 14 | B22: =E21+F21+G21 -> 5864 | C22: ='Income Calendar'!P147 -> 1570 | D22: ='Expense Calendar'!P147 -> 342 | E22: =C22-D22+B22 -> 7092 | F22: =-1*Budget -> -200 | G22: =allowance*-1 -> -50
A23: ='Expense Calendar'!B149 -> 21 | B23: =E22+F22+G22 -> 6842 | C23: ='Income Calendar'!P156 -> 800 | D23: ='Expense Calendar'!P156 -> 0 | E23: =C23-D23+B23 -> 7642 | F23: =-1*Budget -> -200 | G23: =allowance*-1 -> -50
A24: ='Expense Calendar'!B158 -> 28 | B24: =E23+F23+G23 -> 7392 | C24: ='Income Calendar'!P165 -> 0 | D24: ='Expense Calendar'!P165 -> 0 | E24: =C24-D24+B24 -> 7392
A25: ='Expense Calendar'!B167 -> 4 | B25: =E24+F24+G24 -> 7392 | C25: ='Income Calendar'!P174 -> 0 | D25: ='Expense Calendar'!P174 -> 0 | E25: =C25-D25+B25 -> 7392
B26: APR
B27: Begin Cash Flow | C27: Income | D27: Fixed Expenses | E27: End Cash Flow | F27: Varibale Expense | G27: Savings
A28: ='Expense Calendar'!B180 -> 28 | C28: ='Income Calendar'!P187 -> 1570 | D28: ='Expense Calendar'!P187 -> 1432 | E28: =C28-D28+E25 -> 7530 | F28: =-1*Budget -> -200 | G28: =allowance*-1 -> -50
A29: ='Expense Calendar'!B189 -> 4 | B29: =E28+F28+G28 -> 7280 | C29: ='Income Calendar'!P196 -> 800 | D29: ='Expense Calendar'!P196 -> 0 | E29: =C29-D29+B29 -> 8080 | F29: =-1*Budget -> -200 | G29: =allowance*-1 -> -50
A30: ='Expense Calendar'!B198 -> 11 | B30: =E29+F29+G29 -> 7830 | C30: ='Income Calendar'!P205 -> 1570 | D30: ='Expense Calendar'!P205 -> 342 | E30: =C30-D30+B30 -> 9058 | F30: =-1*Budget -> -200 | G30: =allowance*-1 -> -50
A31: ='Expense Calendar'!B207 -> 18 | B31: =E30+F30+G30 -> 8808 | C31: ='Income Calendar'!P214 -> 800 | D31: ='Expense Calendar'!P214 -> 0 | E31: =C31-D31+B31 -> 9608 | F31: =-1*Budget -> -200 | G31: =allowance*-1 -> -50
A32: ='Expense Calendar'!B216 -> 25 | B32: =E31+F31+G31 -> 9358 | C32: ='Income Calendar'!P223 -> 1570 | D32: ='Expense Calendar'!P223 -> 232 | E32: =C32-D32+B32 -> 10696 | F32: =-1*Budget -> -200 | G32: =allowance*-1 -> -50
A33: ='Expense Calendar'!B225 -> 2 | B33: =E32+F32+G32 -> 10446 | C33: ='Income Calendar'!P232 -> 0 | D33: ='Expense Calendar'!P232 -> 0 | E33: =C33-D33+B33 -> 10446
B34: MAY
B35: Begin Cash Flow | C35: Income | D35: Fixed Expenses | E35: End Cash Flow | F35: Varibale Expense | G35: Savings
A36: ='Expense Calendar'!B238 -> 25 | C36: ='Income Calendar'!P245 -> 0 | D36: ='Expense Calendar'!P245 -> 0 | E36: =C36-D36+E33 -> 10446 | F36: =-1*Budget -> -200 | G36: =allowance*-1 -> -50
A37: ='Expense Calendar'!B247 -> 2 | B37: =E36+F36+G36 -> 10196 | C37: ='Income Calendar'!P254 -> 1570 | D37: ='Expense Calendar'!P254 -> 1200 | E37: =C37-D37+B37 -> 10566 | F37: =-1*Budget -> -200 | G37: =allowance*-1 -> -50
A38: ='Expense Calendar'!B256 -> 9 | B38: =E37+F37+G37 -> 10316 | C38: ='Income Calendar'!P263 -> 800 | D38: ='Expense Calendar'!P263 -> 342 | E38: =C38-D38+B38 -> 10774 | F38: =-1*Budget -> -200 | G38: =allowance*-1 -> -50
A39: ='Expense Calendar'!B265 -> 16 | B39: =E38+F38+G38 -> 10524 | C39: ='Income Calendar'!P272 -> 1570 | D39: ='Expense Calendar'!P272 -> 0 | E39: =C39-D39+B39 -> 12094 | F39: =-1*Budget -> -200 | G39: =allowance*-1 -> -50
A40: ='Expense Calendar'!B274 -> 23 | B40: =E39+F39+G39 -> 11844 | C40: ='Income Calendar'!P281 -> 800 | D40: ='Expense Calendar'!P281 -> 232 | E40: =C40-D40+B40 -> 12412 | F40: =-1*Budget -> -200 | G40: =allowance*-1 -> -50
A41: ='Expense Calendar'!B283 -> 30 | B41: =E40+F40+G40 -> 12162 | C41: ='Income Calendar'!P290 -> 0 | D41: ='Expense Calendar'!P290 -> 0 | E41: =C41-D41+B41 -> 12162
B42: JUNE
B43: Begin Cash Flow | C43: Income | D43: Fixed Expenses | E43: End Cash Flow | F43: Varibale Expense | G43: Savings | H43: Trip Expense
A44: ='Expense Calendar'!B296 -> 30 | C44: ='Income Calendar'!P303 -> 1570 | D44: ='Expense Calendar'!P303 -> 1200 | E44: =C44-D44+E41 -> 12532 | F44: =-1*Budget -> -200 | G44: =allowance*-1 -> -50
A45: ='Expense Calendar'!B305 -> 6 | B45: =E44+F44+G44 -> 12282 | C45: ='Income Calendar'!P312 -> 800 | D45: ='Expense Calendar'!P312 -> 232 | E45: =C45-D45+B45 -> 12850 | F45: =-1*Budget -> -200 | G45: =allowance*-1 -> -50
A46: ='Expense Calendar'!B314 -> 13 | B46: =E45+F45+G45 -> 12600 | C46: ='Income Calendar'!P321 -> 1570 | D46: ='Expense Calendar'!P321 -> 110 | E46: =C46-D46+B46 -> 14060 | F46: =-1*Budget -> -200 | G46: =allowance*-1 -> -50
A47: ='Expense Calendar'!B323 -> 20 | B47: =E46+F46+G46 -> 13810 | C47: ='Income Calendar'!P330 -> 800 | D47: ='Expense Calendar'!P330 -> 232 | E47: =C47-D47+B47 -> 14378 | F47: =-1*Budget -> -200 | G47: =allowance*-1 -> -50 | H47: 0 | I47: *Birthday
A48: ='Expense Calendar'!B332 -> 27 | B48: =E47+F47+G47+H47 -> 14128 | C48: ='Income Calendar'!P339 -> 0 | D48: ='Expense Calendar'!P339 -> 0 | E48: =C48-D48+B48 -> 14128
A49: ='Expense Calendar'!B341 -> 4 | B49: =E48+F48+G48 -> 14128 | C49: ='Income Calendar'!P348 -> 0 | D49: ='Expense Calendar'!P348 -> 0 | E49: =C49-D49+B49 -> 14128
B50: JULY
B51: Begin Cash Flow | C51: Income | D51: Fixed Expenses | E51: End Cash Flow | F51: Varibale Expense | G51: Savings
A52: ='Expense Calendar'!B354 -> 27 | C52: ='Income Calendar'!P361 -> 1570 | D52: ='Expense Calendar'!P361 -> 1200 | E52: =C52-D52+E49 -> 14498 | F52: =-1*Budget -> -200 | G52: =allowance*-1 -> -50
A53: ='Expense Calendar'!B363 -> 4 | B53: =E52+F52+G52 -> 14248 | C53: ='Income Calendar'!P370 -> 800 | D53: ='Expense Calendar'!P370 -> 232 | E53: =C53-D53+B53 -> 14816 | F53: =-1*Budget -> -200 | G53: =allowance*-1 -> -50
A54: ='Expense Calendar'!B372 -> 11 | B54: =E53+F53+G53 -> 14566 | C54: ='Income Calendar'!P379 -> 1570 | D54: ='Expense Calendar'!P379 -> 110 | E54: =C54-D54+B54 -> 16026 | F54: =-1*Budget -> -200 | G54: =allowance*-1 -> -50
A55: ='Expense Calendar'!B381 -> 18 | B55: =E54+F54+G54 -> 15776 | C55: ='Income Calendar'!P388 -> 800 | D55: ='Expense Calendar'!P388 -> 232 | E55: =C55-D55+B55 -> 16344 | F55: =-1*Budget -> -200 | G55: =allowance*-1 -> -50
A56: ='Expense Calendar'!B390 -> 25 | B56: =E55+F55+G55 -> 16094 | C56: ='Income Calendar'!P397 -> 1570 | D56: ='Expense Calendar'!P397 -> 0 | E56: =C56-D56+B56 -> 17664 | F56: =-1*Budget -> -200 | G56: =allowance*-1 -> -50
A57: ='Expense Calendar'!B399 -> 1 | B57: =E56+F56+G56 -> 17414 | C57: ='Income Calendar'!P406 -> 0 | D57: ='Expense Calendar'!P406 -> 0 | E57: =C57-D57+B57 -> 17414
B58: AUG
B59: Begin Cash Flow | C59: Income | D59: Fixed Expenses | E59: End Cash Flow | F59: Varibale Expense | G59: Savings
A60: ='Expense Calendar'!B412 -> 1 | C60: ='Income Calendar'!P419 -> 800 | D60: ='Expense Calendar'!P419 -> 1432 | E60: =C60-D60+E57 -> 16782 | F60: =-1*Budget -> -200 | G60: =allowance*-1 -> -50
A61: ='Expense Calendar'!B421 -> 8 | B61: =E60+F60+G60 -> 16532 | C61: ='Income Calendar'!P428 -> 1570 | D61: ='Expense Calendar'!P428 -> 0 | E61: =C61-D61+B61 -> 18102 | F61: =-1*Budget -> -200 | G61: =allowance*-1 -> -50
A62: ='Expense Calendar'!B430 -> 15 | B62: =E61+F61+G61 -> 17852 | C62: ='Income Calendar'!P437 -> 800 | D62: ='Expense Calendar'!P437 -> 342 | E62: =C62-D62+B62 -> 18310 | F62: =-1*Budget -> -200 | G62: =allowance*-1 -> -50
A63: ='Expense Calendar'!B439 -> 22 | B63: =E62+F62+G62 -> 18060 | C63: ='Income Calendar'!P446 -> 1570 | D63: ='Expense Calendar'!P446 -> 0 | E63: =C63-D63+B63 -> 19630 | F63: =-1*Budget -> -200 | G63: =allowance*-1 -> -50
A64: ='Expense Calendar'!B448 -> 29 | B64: =E63+F63+G63 -> 19380 | C64: ='Income Calendar'!P455 -> 0 | D64: ='Expense Calendar'!P455 -> 0 | E64: =C64-D64+B64 -> 19380
A65: ='Expense Calendar'!B457 -> 5 | B65: =E64+F64+G64 -> 19380 | C65: ='Income Calendar'!P464 -> 0 | D65: ='Expense Calendar'!P464 -> 0 | E65: =C65-D65+B65 -> 19380
B66: SEP
B67: Begin Cash Flow | C67: Income | D67: Fixed Expenses | E67: End Cash Flow | F67: Varibale Expense | G67: Savings
A68: ='Expense Calendar'!B470 -> 29 | C68: ='Income Calendar'!P477 -> 800 | D68: ='Expense Calendar'!P477 -> 1432 | E68: =C68-D68+E65 -> 18748 | F68: =-1*Budget -> -200 | G68: =allowance*-1 -> -50
A69: ='Expense Calendar'!B479 -> 5 | B69: =E68+F68+G68 -> 18498 | C69: ='Income Calendar'!P486 -> 1570 | D69: ='Expense Calendar'!P486 -> 0 | E69: =C69-D69+B69 -> 20068 | F69: =-1*Budget -> -200 | G69: =allowance*-1 -> -50
A70: ='Expense Calendar'!B488 -> 12 | B70: =E69+F69+G69 -> 19818 | C70: ='Income Calendar'!P495 -> 800 | D70: ='Expense Calendar'!P495 -> 342 | E70: =C70-D70+B70 -> 20276 | F70: =-1*Budget -> -200 | G70: =allowance*-1 -> -50
A71: ='Expense Calendar'!B497 -> 19 | B71: =E70+F70+G70 -> 20026 | C71: ='Income Calendar'!P504 -> 1570 | D71: ='Expense Calendar'!P504 -> 0 | E71: =C71-D71+B71 -> 21596 | F71: =-1*Budget -> -200 | G71: =allowance*-1 -> -50
A72: ='Expense Calendar'!B506 -> 26 | B72: =E71+F71+G71 -> 21346 | C72: ='Income Calendar'!P513 -> 0 | D72: ='Expense Calendar'!P513 -> 0 | E72: =C72-D72+B72 -> 21346
A73: ='Expense Calendar'!B515 -> 3 | B73: =E72+F72+G72 -> 21346 | C73: ='Income Calendar'!P522 -> 0 | D73: ='Expense Calendar'!P522 -> 0 | E73: =C73-D73+B73 -> 21346
B74: OCT
B75: Begin Cash Flow | C75: Income | D75: Fixed Expenses | E75: End Cash Flow | F75: Varibale Expense | G75: Savings
C76: ='Income Calendar'!P535 -> 800 | D76: ='Expense Calendar'!P535 -> 232 | E76: =C76-D76+E73 -> 21914 | F76: =-1*Budget -> -200 | G76: =allowance*-1 -> -50
B77: =E76+F76+G76 -> 21664 | C77: ='Income Calendar'!P544 -> 1570 | D77: ='Expense Calendar'!P544 -> 1200 | E77: =C77-D77+B77 -> 22034 | F77: =-1*Budget -> -200 | G77: =allowance*-1 -> -50
B78: =E77+F77+G77 -> 21784 | C78: ='Income Calendar'!P553 -> 800 | D78: ='Expense Calendar'!P553 -> 342 | E78: =C78-D78+B78 -> 22242 | F78: =-1*Budget -> -200 | G78: =allowance*-1 -> -50
B79: =E78+F78+G78 -> 21992 | C79: ='Income Calendar'!P562 -> 1570 | D79: ='Expense Calendar'!P562 -> 0 | E79: =C79-D79+B79 -> 23562 | F79: =-1*Budget -> -200 | G79: =allowance*-1 -> -50
B80: =E79+F79+G79 -> 23312 | C80: ='Income Calendar'!P571 -> 800 | D80: ='Expense Calendar'!P571 -> 232 | E80: =C80-D80+B80 -> 23880 | F80: =-1*Budget -> -200 | G80: =allowance*-1 -> -50
B81: =E80+F80+G80 -> 23630 | C81: ='Income Calendar'!P580 -> 0 | D81: ='Expense Calendar'!P580 -> 0 | E81: =C81-D81+B81 -> 23630
B82: NOV
B83: Begin Cash Flow | C83: Income | D83: Fixed Expenses | E83: End Cash Flow | F83: Varibale Expense | G83: Savings
C84: ='Income Calendar'!P593 -> 1570 | D84: ='Expense Calendar'!P593 -> 1200 | E84: =C84-D84+E81 -> 24000 | F84: =-1*Budget -> -200 | G84: =allowance*-1 -> -50
B85: =E84+F84+G84 -> 23750 | C85: ='Income Calendar'!P602 -> 800 | D85: ='Expense Calendar'!P602 -> 232 | E85: =C85-D85+B85 -> 24318 | F85: =-1*Budget -> -200 | G85: =allowance*-1 -> -50
B86: =E85+F85+G85 -> 24068 | C86: ='Income Calendar'!P611 -> 1570 | D86: ='Expense Calendar'!P611 -> 110 | E86: =C86-D86+B86 -> 25528 | F86: =-1*Budget -> -200 | G86: =allowance*-1 -> -50
B87: =E86+F86+G86 -> 25278 | C87: ='Income Calendar'!P620 -> 800 | D87: ='Expense Calendar'!P620 -> 232 | E87: =C87-D87+B87 -> 25846 | F87: =-1*Budget -> -200 | G87: =allowance*-1 -> -50
B88: =E87+F87+G87 -> 25596 | C88: ='Income Calendar'!P629 -> 0 | D88: ='Expense Calendar'!P629 -> 0 | E88: =C88-D88+B88 -> 25596
B89: =E88+F88+G88 -> 25596 | C89: ='Income Calendar'!P638 -> 0 | D89: ='Expense Calendar'!P638 -> 0 | E89: =C89-D89+B89 -> 25596
B90: DEC
B91: Begin Cash Flow | C91: Income | D91: Fixed Expenses | E91: End Cash Flow | F91: Varibale Expense | G91: Savings
C92: ='Income Calendar'!P651 -> 1570 | D92: ='Expense Calendar'!P651 -> 1200 | E92: =C92-D92+E89 -> 25966 | F92: =-1*Budget -> -200 | G92: =allowance*-1 -> -50
B93: =E92+F92+G92 -> 25716 | C93: ='Income Calendar'!P660 -> 800 | D93: ='Expense Calendar'!P660 -> 232 | E93: =C93-D93+B93 -> 26284 | F93: =-1*Budget -> -200 | G93: =allowance*-1 -> -50
B94: =E93+F93+G93 -> 26034 | C94: ='Income Calendar'!P669 -> 1570 | D94: ='Expense Calendar'!P669 -> 110 | E94: =C94-D94+B94 -> 27494 | F94: =-1*Budget -> -200 | G94: =allowance*-1 -> -50
B95: =E94+F94+G94 -> 27244 | C95: ='Income Calendar'!P678 -> 800 | D95: ='Expense Calendar'!P678 -> 232 | E95: =C95-D95+B95 -> 27812 | F95: =-1*Budget -> -200 | G95: =allowance*-1 -> -50
B96: =E95+F95+G95 -> 27562 | C96: ='Income Calendar'!P687 -> 1570 | D96: ='Expense Calendar'!P687 -> 0 | E96: =C96-D96+B96 -> 29132 | F96: =-1*Budget -> -200 | G96: =allowance*-1 -> -50
B97: =E96+F96+G96 -> 28882 | C97: ='Income Calendar'!P696 -> 0 | D97: ='Expense Calendar'!P696 -> 0 | E97: =C97-D97+B97 -> 28882

Sheet Expense Calendar
B1: =YEAR(TODAY()) -> 2021 | C1: EXPENSE CALENDAR
A2: January label is in cell at right, Monthly Total label in cell L2, Grand Total label in N2, and Tip in G2. | B2: JANUARY | G2: TIP: Change the year in cell B1 to update the calendar year. | L2: MONTHLY TOTAL | N2: GRAND TOTAL
A3: Monthly Total is auto calculated in cell L3 and Grand Total in N3. | F3: =IFERROR(WEEKDAY(DATEVALUE(B2&" 1, "&Year1)),"") -> 6 | L3: =SUM(P13,P22,P31,P40,P49,P58) -> 1310 | N3: =SUM(P:P) -> 21288
A4: January calendar is in cells B5 through O58. | B4: 1 | D4: 2 | F4: 3 | H4: 4 | J4: 5 | L4: 6 | N4: 7
A5: Weekdays are in cells at right, cells B5 through N5, and Weekly Total label in cell P5. | B5: SUNDAY | D5: MONDAY | E5: =IF(WEEKDAY(DATEVALUE(Month1&" 1, "&Year1))=COLUMN(#REF!),1,IF(LEN(C5)>0,C5+1,"")) -> #VALUE! | F5: TUESDAY | G5: =IF(WEEKDAY(DATEVALUE(Month1&" 1, "&Year1))=COLUMN(#REF!),1,IF(LEN(E5)>0,E5+1,"")) -> #VALUE! | H5: WEDNESDAY | I5: =IF(WEEKDAY(DATEVALUE(Month1&" 1, "&Year1))=COLUMN(#REF!),1,IF(LEN(G5)>0,G5+1,"")) -> #VALUE! | J5: THURSDAY | K5: =IF(WEEKDAY(DATEVALUE(Month1&" 1, "&Year1))=COLUMN(#REF!),1,IF(LEN(I5)>0,I5+1,"")) -> #VALUE! | L5: FRIDAY | M5: =IF(WEEKDAY(DATEVALUE(Month1&" 1, "&Year1))=COLUMN(#REF!),1,IF(LEN(K5)>0,K5+1,"")) -> #VALUE! | N5: SATURDAY | O5: =IF(WEEKDAY(DATEVALUE(Month1&" 1, "&Year1))=COLUMN(#REF!),1,IF(LEN(M5)>0,M5+1,"")) -> #VALUE! | P5: WEEKLY TOTAL | T5: Description | U5: Amount | V5: Included
A6: Calendar dates are in cells at right, cells B6 through O6. If it doesn’t start with number 1, then it is date of previous month. | B6: =DAY(IF(DAY(JanSun1)=1,JanSun1-6,JanSun1+1)) -> 27 | D6: =DAY(IF(DAY(JanSun1)=1,JanSun1-5,JanSun1+2)) -> 28 | F6: =DAY(IF(DAY(JanSun1)=1,JanSun1-4,JanSun1+3)) -> 29 | H6: =DAY(IF(DAY(JanSun1)=1,JanSun1-3,JanSun1+4)) -> 30 | J6: =DAY(IF(DAY(JanSun1)=1,JanSun1-2,JanSun1+5)) -> 31 | L6: =DAY(IF(DAY(JanSun1)=1,JanSun1-1,JanSun1+6)) -> 1 | N6: =DAY(IF(DAY(JanSun1)=1,JanSun1,JanSun1+7)) -> 2 | T6: Paul Phone Bill | U6: 60
A7: Description and Amount labels are in cells at right, cells B7 through O7. | B7: DESCRIPTION | C7: AMOUNT | D7: DESCRIPTION | E7: AMOUNT | F7: DESCRIPTION | G7: AMOUNT | H7: DESCRIPTION | I7: AMOUNT | J7: DESCRIPTION | K7: AMOUNT | L7: DESCRIPTION | M7: AMOUNT | N7: DESCRIPTION | O7: AMOUNT | T7: Cairo Phone Bill | U7: 115 | V7: *Disney Plus, Hulu, Espn, Kids Phone
A8: Enter Description and Amount of each expense in cells at right, cells B8 through O12. Next instruction is in cell A13. | B8: =IF(HLOOKUP(B6,Summary!$I$2:$AM$7,2,0)=0,"",HLOOKUP(B6,Summary!$I$2:$AM$7,2,0)) | C8: =IFERROR(VLOOKUP(B8,fixed_expenses[],2,0),"") | D8: =IF(HLOOKUP(D6,Summary!$I$2:$AM$7,2,0)=0,"",HLOOKUP(D6,Summary!$I$2:$AM$7,2,0)) | E8: =IFERROR(VLOOKUP(D8,fixed_expenses[],2,0),"") | F8: =IF(HLOOKUP(F6,Summary!$I$2:$AM$7,2,0)=0,"",HLOOKUP(F6,Summary!$I$2:$AM$7,2,0)) | G8: =IFERROR(VLOOKUP(F8,fixed_expenses[],2,0),"") | H8: =IF(HLOOKUP(H6,Summary!$I$2:$AM$7,2,0)=0,"",HLOOKUP(H6,Summary!$I$2:$AM$7,2,0)) | I8: =IFERROR(VLOOKUP(H8,fixed_expenses[],2,0),"") | J8: =IF(HLOOKUP(J6,Summary!$I$2:$AM$7,2,0)=0,"",HLOOKUP(J6,Summary!$I$2:$AM$7,2,0)) | K8: =IFERROR(VLOOKUP(J8,fixed_expenses[],2,0),"") | L8: =IF(HLOOKUP(L6,Summary!$I$2:$AM$7,2,0)=0,"",HLOOKUP(L6,Summary!$I$2:$AM$7,2,0)) | M8: =IFERROR(VLOOKUP(L8,fixed_expenses[],2,0),"") | N8: =IF(HLOOKUP(N6,Summary!$I$2:$AM$7,2,0)=0,"",HLOOKUP(N6,Summary!$I$2:$AM$7,2,0)) | O8: =IFERROR(VLOOKUP(N8,fixed_expenses[],2,0),"") | T8: Electric | U8: 50
B9: =IF(HLOOKUP(B6,Summary!$I$2:$AM$7,3,0)=0,"",HLOOKUP(B6,Summary!$I$2:$AM$7,3,0)) | C9: =IFERROR(VLOOKUP(B9,fixed_expenses[],2,0),"") | D9: =IF(HLOOKUP(D6,Summary!$I$2:$AM$7,3,0)=0,"",HLOOKUP(D6,Summary!$I$2:$AM$7,3,0)) | E9: =IFERROR(VLOOKUP(D9,fixed_expenses[],2,0),"") | F9: =IF(HLOOKUP(F6,Summary!$I$2:$AM$7,3,0)=0,"",HLOOKUP(F6,Summary!$I$2:$AM$7,3,0)) | G9: =IFERROR(VLOOKUP(F9,fixed_expenses[],2,0),"") | H9: =IF(HLOOKUP(H6,Summary!$I$2:$AM$7,3,0)=0,"",HLOOKUP(H6,Summary!$I$2:$AM$7,3,0)) | I9: =IFERROR(VLOOKUP(H9,fixed_expenses[],2,0),"") | J9: =IF(HLOOKUP(J6,Summary!$I$2:$AM$7,3,0)=0,"",HLOOKUP(J6,Summary!$I$2:$AM$7,3,0)) | K9: =IFERROR(VLOOKUP(J9,fixed_expenses[],2,0),"") | L9: =IF(HLOOKUP(L6,Summary!$I$2:$AM$7,3,0)=0,"",HLOOKUP(L6,Summary!$I$2:$AM$7,3,0)) | M9: =IFERROR(VLOOKUP(L9,fixed_expenses[],2,0),"") | N9: =IF(HLOOKUP(N6,Summary!$I$2:$AM$7,3,0)=0,"",HLOOKUP(N6,Summary!$I$2:$AM$7,3,0)) | O9: =IFERROR(VLOOKUP(N9,fixed_expenses[],2,0),"") | T9: Rent | U9: 1200
B10: =IF(HLOOKUP(B6,Summary!$I$2:$AM$7,4,0)=0,"",HLOOKUP(B6,Summary!$I$2:$AM$7,4,0)) | C10: =IFERROR(VLOOKUP(B10,fixed_expenses[],2,0),"") | D10: =IF(HLOOKUP(D6,Summary!$I$2:$AM$7,4,0)=0,"",HLOOKUP(D6,Summary!$I$2:$AM$7,4,0)) | E10: =IFERROR(VLOOKUP(D10,fixed_expenses[],2,0),"") | F10: =IF(HLOOKUP(F6,Summary!$I$2:$AM$7,4,0)=0,"",HLOOKUP(F6,Summary!$I$2:$AM$7,4,0)) | G10: =IFERROR(VLOOKUP(F10,fixed_expenses[],2,0),"") | H10: =IF(HLOOKUP(H6,Summary!$I$2:$AM$7,4,0)=0,"",HLOOKUP(H6,Summary!$I$2:$AM$7,4,0)) | I10: =IFERROR(VLOOKUP(H10,fixed_expenses[],2,0),"") | J10: =IF(HLOOKUP(J6,Summary!$I$2:$AM$7,4,0)=0,"",HLOOKUP(J6,Summary!$I$2:$AM$7,4,0)) | K10: =IFERROR(VLOOKUP(J10,fixed_expenses[],2,0),"") | L10: =IF(HLOOKUP(L6,Summary!$I$2:$AM$7,4,0)=0,"",HLOOKUP(L6,Summary!$I$2:$AM$7,4,0)) | M10: =IFERROR(VLOOKUP(L10,fixed_expenses[],2,0),"") | N10: =IF(HLOOKUP(N6,Summary!$I$2:$AM$7,4,0)=0,"",HLOOKUP(N6,Summary!$I$2:$AM$7,4,0)) | O10: =IFERROR(VLOOKUP(N10,fixed_expenses[],2,0),"") | T10: Car | U10: 232
B11: =IF(HLOOKUP(B6,Summary!$I$2:$AM$7,5,0)=0,"",HLOOKUP(B6,Summary!$I$2:$AM$7,5,0)) | C11: =IFERROR(VLOOKUP(B11,fixed_expenses[],2,0),"") | D11: =IF(HLOOKUP(D6,Summary!$I$2:$AM$7,5,0)=0,"",HLOOKUP(D6,Summary!$I$2:$AM$7,5,0)) | E11: =IFERROR(VLOOKUP(D11,fixed_expenses[],2,0),"") | F11: =IF(HLOOKUP(F6,Summary!$I$2:$AM$7,5,0)=0,"",HLOOKUP(F6,Summary!$I$2:$AM$7,5,0)) | G11: =IFERROR(VLOOKUP(F11,fixed_expenses[],2,0),"") | H11: =IF(HLOOKUP(H6,Summary!$I$2:$AM$7,5,0)=0,"",HLOOKUP(H6,Summary!$I$2:$AM$7,5,0)) | I11: =IFERROR(VLOOKUP(H11,fixed_expenses[],2,0),"") | J11: =IF(HLOOKUP(J6,Summary!$I$2:$AM$7,5,0)=0,"",HLOOKUP(J6,Summary!$I$2:$AM$7,5,0)) | K11: =IFERROR(VLOOKUP(J11,fixed_expenses[],2,0),"") | L11: =IF(HLOOKUP(L6,Summary!$I$2:$AM$7,5,0)=0,"",HLOOKUP(L6,Summary!$I$2:$AM$7,5,0)) | M11: =IFERROR(VLOOKUP(L11,fixed_expenses[],2,0),"") | N11: =IF(HLOOKUP(N6,Summary!$I$2:$AM$7,5,0)=0,"",HLOOKUP(N6,Summary!$I$2:$AM$7,5,0)) | O11: =IFERROR(VLOOKUP(N11,fixed_expenses[],2,0),"")
B12: =IF(HLOOKUP(B6,Summary!$I$2:$AM$7,6,0)=0,"",HLOOKUP(B6,Summary!$I$2:$AM$7,6,0)) | C12: =IFERROR(VLOOKUP(B12,fixed_expenses[],2,0),"") | D12: =IF(HLOOKUP(D6,Summary!$I$2:$AM$7,6,0)=0,"",HLOOKUP(D6,Summary!$I$2:$AM$7,6,0)) | E12: =IFERROR(VLOOKUP(D12,fixed_expenses[],2,0),"") | F12: =IF(HLOOKUP(F6,Summary!$I$2:$AM$7,6,0)=0,"",HLOOKUP(F6,Summary!$I$2:$AM$7,6,0)) | G12: =IFERROR(VLOOKUP(F12,fixed_expenses[],2,0),"") | H12: =IF(HLOOKUP(H6,Summary!$I$2:$AM$7,6,0)=0,"",HLOOKUP(H6,Summary!$I$2:$AM$7,6,0)) | I12: =IFERROR(VLOOKUP(H12,fixed_expenses[],2,0),"") | J12: =IF(HLOOKUP(J6,Summary!$I$2:$AM$7,6,0)=0,"",HLOOKUP(J6,Summary!$I$2:$AM$7,6,0)) | K12: =IFERROR(VLOOKUP(J12,fixed_expenses[],2,0),"") | L12: =IF(HLOOKUP(L6,Summary!$I$2:$AM$7,6,0)=0,"",HLOOKUP(L6,Summary!$I$2:$AM$7,6,0)) | M12: =IFERROR(VLOOKUP(L12,fixed_expenses[],2,0),"") | N12: =IF(HLOOKUP(N6,Summary!$I$2:$AM$7,6,0)=0,"",HLOOKUP(N6,Summary!$I$2:$AM$7,6,0)) | O12: =IFERROR(VLOOKUP(N12,fixed_expenses[],2,0),"")
A13: Total is auto calculated for each day and week in cell at right, cells C13 through P13. Next instruction is in cell A15. | B13: TOTAL | C13: =SUM(C8:C12) -> 0 | E13: =SUM(E8:E12) -> 0 | G13: =SUM(G8:G12) -> 0 | I13: =SUM(I8:I12) -> 0 | K13: =SUM(K8:K12) -> 0 | M13: =SUM(M8:M12) -> 0 | O13: =SUM(O8:O12) -> 0 | P13: =SUMIF(B6:N6,"<8",C13:O13) -> 0
A15: Calendar dates are in cells at right, cells B15 through O15. | B15: =N6+1 -> 3 | D15: =B15+1 -> 4 | F15: =D15+1 -> 5 | H15: =F15+1 -> 6 | J15: =H15+1 -> 7 | L15: =J15+1 -> 8 | N15: =L15+1 -> 9
A16: Description and Amount labels are in cells at right, cells B16 through O16. | B16: DESCRIPTION | C16: AMOUNT | D16: DESCRIPTION | E16: AMOUNT | F16: DESCRIPTION | G16: AMOUNT | H16: DESCRIPTION | I16: AMOUNT | J16: DESCRIPTION | K16: AMOUNT | L16: DESCRIPTION | M16: AMOUNT | N16: DESCRIPTION | O16: AMOUNT
A17: Enter Description and Amount of each expense in cells at right, cells B17 through O21. Next instruction is in cell A22. | B17: =IF(HLOOKUP(B15,Summary!$I$2:$AM$7,2,0)=0,"",HLOOKUP(B15,Summary!$I$2:$AM$7,2,0)) -> Rent | C17: =IFERROR(VLOOKUP(B17,fixed_expenses[],2,0),"") -> 1200 | D17: =IF(HLOOKUP(D15,Summary!$I$2:$AM$7,2,0)=0,"",HLOOKUP(D15,Summary!$I$2:$AM$7,2,0)) | E17: =IFERROR(VLOOKUP(D17,fixed_expenses[],2,0),"") | F17: =IF(HLOOKUP(F15,Summary!$I$2:$AM$7,2,0)=0,"",HLOOKUP(F15,Summary!$I$2:$AM$7,2,0)) | G17: =IFERROR(VLOOKUP(F17,fixed_expenses[],2,0),"") | H17: =IF(HLOOKUP(H15,Summary!$I$2:$AM$7,2,0)=0,"",HLOOKUP(H15,Summary!$I$2:$AM$7,2,0)) | I17: =IFERROR(VLOOKUP(H17,fixed_expenses[],2,0),"") | J17: =IF(HLOOKUP(J15,Summary!$I$2:$AM$7,2,0)=0,"",HLOOKUP(J15,Summary!$I$2:$AM$7,2,0)) | K17: =IFERROR(VLOOKUP(J17,fixed_expenses[],2,0),"") | L17: =IF(HLOOKUP(L15,Summary!$I$2:$AM$7,2,0)=0,"",HLOOKUP(L15,Summary!$I$2:$AM$7,2,0)) | M17: =IFERROR(VLOOKUP(L17,fixed_expenses[],2,0),"") | N17: =IF(HLOOKUP(N15,Summary!$I$2:$AM$7,2,0)=0,"",HLOOKUP(N15,Summary!$I$2:$AM$7,2,0)) | O17: =IFERROR(VLOOKUP(N17,fixed_expenses[],2,0),"")
B18: =IF(HLOOKUP(B15,Summary!$I$2:$AM$7,3,0)=0,"",HLOOKUP(B15,Summary!$I$2:$AM$7,3,0)) | C18: =IFERROR(VLOOKUP(B18,fixed_expenses[],2,0),"") | D18: =IF(HLOOKUP(D15,Summary!$I$2:$AM$7,3,0)=0,"",HLOOKUP(D15,Summary!$I$2:$AM$7,3,0)) | E18: =IFERROR(VLOOKUP(D18,fixed_expenses[],2,0),"") | F18: =IF(HLOOKUP(F15,Summary!$I$2:$AM$7,3,0)=0,"",HLOOKUP(F15,Summary!$I$2:$AM$7,3,0)) | G18: =IFERROR(VLOOKUP(F18,fixed_expenses[],2,0),"") | H18: =IF(HLOOKUP(H15,Summary!$I$2:$AM$7,3,0)=0,"",HLOOKUP(H15,Summary!$I$2:$AM$7,3,0)) | I18: =IFERROR(VLOOKUP(H18,fixed_expenses[],2,0),"") | J18: =IF(HLOOKUP(J15,Summary!$I$2:$AM$7,3,0)=0,"",HLOOKUP(J15,Summary!$I$2:$AM$7,3,0)) | K18: =IFERROR(VLOOKUP(J18,fixed_expenses[],2,0),"") | L18: =IF(HLOOKUP(L15,Summary!$I$2:$AM$7,3,0)=0,"",HLOOKUP(L15,Summary!$I$2:$AM$7,3,0)) | M18: =IFERROR(VLOOKUP(L18,fixed_expenses[],2,0),"") | N18: =IF(HLOOKUP(N15,Summary!$I$2:$AM$7,3,0)=0,"",HLOOKUP(N15,Summary!$I$2:$AM$7,3,0)) | O18: =IFERROR(VLOOKUP(N18,fixed_expenses[],2,0),"")
B19: =IF(HLOOKUP(B15,Summary!$I$2:$AM$7,4,0)=0,"",HLOOKUP(B15,Summary!$I$2:$AM$7,4,0)) | C19: =IFERROR(VLOOKUP(B19,fixed_expenses[],2,0),"") | D19: =IF(HLOOKUP(D15,Summary!$I$2:$AM$7,4,0)=0,"",HLOOKUP(D15,Summary!$I$2:$AM$7,4,0)) | E19: =IFERROR(VLOOKUP(D19,fixed_expenses[],2,0),"") | F19: =IF(HLOOKUP(F15,Summary!$I$2:$AM$7,4,0)=0,"",HLOOKUP(F15,Summary!$I$2:$AM$7,4,0)) | G19: =IFERROR(VLOOKUP(F19,fixed_expenses[],2,0),"") | H19: =IF(HLOOKUP(H15,Summary!$I$2:$AM$7,4,0)=0,"",HLOOKUP(H15,Summary!$I$2:$AM$7,4,0)) | I19: =IFERROR(VLOOKUP(H19,fixed_expenses[],2,0),"") | J19: =IF(HLOOKUP(J15,Summary!$I$2:$AM$7,4,0)=0,"",HLOOKUP(J15,Summary!$I$2:$AM$7,4,0)) | K19: =IFERROR(VLOOKUP(J19,fixed_expenses[],2,0),"") | L19: =IF(HLOOKUP(L15,Summary!$I$2:$AM$7,4,0)=0,"",HLOOKUP(L15,Summary!$I$2:$AM$7,4,0)) | M19: =IFERROR(VLOOKUP(L19,fixed_expenses[],2,0),"") | N19: =IF(HLOOKUP(N15,Summary!$I$2:$AM$7,4,0)=0,"",HLOOKUP(N15,Summary!$I$2:$AM$7,4,0)) | O19: =IFERROR(VLOOKUP(N19,fixed_expenses[],2,0),"")
B20: =IF(HLOOKUP(B15,Summary!$I$2:$AM$7,5,0)=0,"",HLOOKUP(B15,Summary!$I$2:$AM$7,5,0)) | C20: =IFERROR(VLOOKUP(B20,fixed_expenses[],2,0),"") | D20: =IF(HLOOKUP(D15,Summary!$I$2:$AM$7,5,0)=0,"",HLOOKUP(D15,Summary!$I$2:$AM$7,5,0)) | E20: =IFERROR(VLOOKUP(D20,fixed_expenses[],2,0),"") | F20: =IF(HLOOKUP(F15,Summary!$I$2:$AM$7,5,0)=0,"",HLOOKUP(F15,Summary!$I$2:$AM$7,5,0)) | G20: =IFERROR(VLOOKUP(F20,fixed_expenses[],2,0),"") | H20: =IF(HLOOKUP(H15,Summary!$I$2:$AM$7,5,0)=0,"",HLOOKUP(H15,Summary!$I$2:$AM$7,5,0)) | I20: =IFERROR(VLOOKUP(H20,fixed_expenses[],2,0),"") | J20: =IF(HLOOKUP(J15,Summary!$I$2:$AM$7,5,0)=0,"",HLOOKUP(J15,Summary!$I$2:$AM$7,5,0)) | K20: =IFERROR(VLOOKUP(J20,fixed_expenses[],2,0),"") | L20: =IF(HLOOKUP(L15,Summary!$I$2:$AM$7,5,0)=0,"",HLOOKUP(L15,Summary!$I$2:$AM$7,5,0)) | M20: =IFERROR(VLOOKUP(L20,fixed_expenses[],2,0),"") | N20: =IF(HLOOKUP(N15,Summary!$I$2:$AM$7,5,0)=0,"",HLOOKUP(N15,Summary!$I$2:$AM$7,5,0)) | O20: =IFERROR(VLOOKUP(N20,fixed_expenses[],2,0),"")
B21: =IF(HLOOKUP(B15,Summary!$I$2:$AM$7,6,0)=0,"",HLOOKUP(B15,Summary!$I$2:$AM$7,6,0)) | C21: =IFERROR(VLOOKUP(B21,fixed_expenses[],2,0),"") | D21: =IF(HLOOKUP(D15,Summary!$I$2:$AM$7,6,0)=0,"",HLOOKUP(D15,Summary!$I$2:$AM$7,6,0)) | E21: =IFERROR(VLOOKUP(D21,fixed_expenses[],2,0),"") | F21: =IF(HLOOKUP(F15,Summary!$I$2:$AM$7,6,0)=0,"",HLOOKUP(F15,Summary!$I$2:$AM$7,6,0)) | G21: =IFERROR(VLOOKUP(F21,fixed_expenses[],2,0),"") | H21: =IF(HLOOKUP(H15,Summary!$I$2:$AM$7,6,0)=0,"",HLOOKUP(H15,Summary!$I$2:$AM$7,6,0)) | I21: =IFERROR(VLOOKUP(H21,fixed_expenses[],2,0),"") | J21: =IF(HLOOKUP(J15,Summary!$I$2:$AM$7,6,0)=0,"",HLOOKUP(J15,Summary!$I$2:$AM$7,6,0)) | K21: =IFERROR(VLOOKUP(J21,fixed_expenses[],2,0),"") | L21: =IF(HLOOKUP(L15,Summary!$I$2:$AM$7,6,0)=0,"",HLOOKUP(L15,Summary!$I$2:$AM$7,6,0)) | M21: =IFERROR(VLOOKUP(L21,fixed_expenses[],2,0),"") | N21: =IF(HLOOKUP(N15,Summary!$I$2:$AM$7,6,0)=0,"",HLOOKUP(N15,Summary!$I$2:$AM$7,6,0)) | O21: =IFERROR(VLOOKUP(N21,fixed_expenses[],2,0),"")
A22: Total is auto calculated for each day and week in cell at right, cells C22 through P22. Next instruction is in cell A24. | B22: TOTAL | C22: =SUM(C17:C21) -> 1200 | E22: =SUM(E17:E21) -> 0 | G22: =SUM(G17:G21) -> 0 | I22: =SUM(I17:I21) -> 0 | K22: =SUM(K17:K21) -> 0 | M22: =SUM(M17:M21) -> 0 | O22: =SUM(O17:O21) -> 0 | P22: =SUM(C22,E22,G22,I22,K22,M22,O22) -> 1200
A24: Calendar dates are in cells at right, cells B24 through O24. | B24: =N15+1 -> 10 | D24: =B24+1 -> 11 | F24: =D24+1 -> 12 | H24: =F24+1 -> 13 | J24: =H24+1 -> 14 | L24: =J24+1 -> 15 | N24: =L24+1 -> 16
A25: Description and Amount labels are in cells at right, cells B25 through O25. | B25: DESCRIPTION | C25: AMOUNT | D25: DESCRIPTION | E25: AMOUNT | F25: DESCRIPTION | G25: AMOUNT | H25: DESCRIPTION | I25: AMOUNT | J25: DESCRIPTION | K25: AMOUNT | L25: DESCRIPTION | M25: AMOUNT | N25: DESCRIPTION | O25: AMOUNT
A26: Enter Description and Amount of each expense in cells at right, cells B26 through O30. Next instruction is in cell A31. | B26: =IF(HLOOKUP(B24,Summary!$I$2:$AM$7,2,0)=0,"",HLOOKUP(B24,Summary!$I$2:$AM$7,2,0)) | C26: =IFERROR(VLOOKUP(B26,fixed_expenses[],2,0),"") | D26: =IF(HLOOKUP(D24,Summary!$I$2:$AM$7,2,0)=0,"",HLOOKUP(D24,Summary!$I$2:$AM$7,2,0)) | E26: =IFERROR(VLOOKUP(D26,fixed_expenses[],2,0),"") | F26: =IF(HLOOKUP(F24,Summary!$I$2:$AM$7,2,0)=0,"",HLOOKUP(F24,Summary!$I$2:$AM$7,2,0)) | G26: =IFERROR(VLOOKUP(F26,fixed_expenses[],2,0),"") | H26: =IF(HLOOKUP(H24,Summary!$I$2:$AM$7,2,0)=0,"",HLOOKUP(H24,Summary!$I$2:$AM$7,2,0)) | I26: =IFERROR(VLOOKUP(H26,fixed_expenses[],2,0),"") | J26: =IF(HLOOKUP(J24,Summary!$I$2:$AM$7,2,0)=0,"",HLOOKUP(J24,Summary!$I$2:$AM$7,2,0)) | K26: =IFERROR(VLOOKUP(J26,fixed_expenses[],2,0),"") | L26: =IF(HLOOKUP(L24,Summary!$I$2:$AM$7,2,0)=0,"",HLOOKUP(L24,Summary!$I$2:$AM$7,2,0)) -> Paul Phone Bill | M26: =IFERROR(VLOOKUP(L26,fixed_expenses[],2,0),"") -> 60 | N26: =IF(HLOOKUP(N24,Summary!$I$2:$AM$7,2,0)=0,"",HLOOKUP(N24,Summary!$I$2:$AM$7,2,0)) | O26: =IFERROR(VLOOKUP(N26,fixed_expenses[],2,0),"")
B27: =IF(HLOOKUP(B24,Summary!$I$2:$AM$7,3,0)=0,"",HLOOKUP(B24,Summary!$I$2:$AM$7,3,0)) | C27: =IFERROR(VLOOKUP(B27,fixed_expenses[],2,0),"") | D27: =IF(HLOOKUP(D24,Summary!$I$2:$AM$7,3,0)=0,"",HLOOKUP(D24,Summary!$I$2:$AM$7,3,0)) | E27: =IFERROR(VLOOKUP(D27,fixed_expenses[],2,0),"") | F27: =IF(HLOOKUP(F24,Summary!$I$2:$AM$7,3,0)=0,"",HLOOKUP(F24,Summary!$I$2:$AM$7,3,0)) | G27: =IFERROR(VLOOKUP(F27,fixed_expenses[],2,0),"") | H27: =IF(HLOOKUP(H24,Summary!$I$2:$AM$7,3,0)=0,"",HLOOKUP(H24,Summary!$I$2:$AM$7,3,0)) | I27: =IFERROR(VLOOKUP(H27,fixed_expenses[],2,0),"") | J27: =IF(HLOOKUP(J24,Summary!$I$2:$AM$7,3,0)=0,"",HLOOKUP(J24,Summary!$I$2:$AM$7,3,0)) | K27: =IFERROR(VLOOKUP(J27,fixed_expenses[],2,0),"") | L27: =IF(HLOOKUP(L24,Summary!$I$2:$AM$7,3,0)=0,"",HLOOKUP(L24,Summary!$I$2:$AM$7,3,0)) -> Electric | M27: =IFERROR(VLOOKUP(L27,fixed_expenses[],2,0),"") -> 50 | N27: =IF(HLOOKUP(N24,Summary!$I$2:$AM$7,3,0)=0,"",HLOOKUP(N24,Summary!$I$2:$AM$7,3,0)) | O27: =IFERROR(VLOOKUP(N27,fixed_expenses[],2,0),"")
B28: =IF(HLOOKUP(B24,Summary!$I$2:$AM$7,4,0)=0,"",HLOOKUP(B24,Summary!$I$2:$AM$7,4,0)) | C28: =IFERROR(VLOOKUP(B28,fixed_expenses[],2,0),"") | D28: =IF(HLOOKUP(D24,Summary!$I$2:$AM$7,4,0)=0,"",HLOOKUP(D24,Summary!$I$2:$AM$7,4,0)) | E28: =IFERROR(VLOOKUP(D28,fixed_expenses[],2,0),"") | F28: =IF(HLOOKUP(F24,Summary!$I$2:$AM$7,4,0)=0,"",HLOOKUP(F24,Summary!$I$2:$AM$7,4,0)) | G28: =IFERROR(VLOOKUP(F28,fixed_expenses[],2,0),"") | H28: =IF(HLOOKUP(H24,Summary!$I$2:$AM$7,4,0)=0,"",HLOOKUP(H24,Summary!$I$2:$AM$7,4,0)) | I28: =IFERROR(VLOOKUP(H28,fixed_expenses[],2,0),"") | J28: =IF(HLOOKUP(J24,Summary!$I$2:$AM$7,4,0)=0,"",HLOOKUP(J24,Summary!$I$2:$AM$7,4,0)) | K28: =IFERROR(VLOOKUP(J28,fixed_expenses[],2,0),"") | L28: =IF(HLOOKUP(L24,Summary!$I$2:$AM$7,4,0)=0,"",HLOOKUP(L24,Summary!$I$2:$AM$7,4,0)) | M28: =IFERROR(VLOOKUP(L28,fixed_expenses[],2,0),"") | N28: =IF(HLOOKUP(N24,Summary!$I$2:$AM$7,4,0)=0,"",HLOOKUP(N24,Summary!$I$2:$AM$7,4,0)) | O28: =IFERROR(VLOOKUP(N28,fixed_expenses[],2,0),"")
B29: =IF(HLOOKUP(B24,Summary!$I$2:$AM$7,5,0)=0,"",HLOOKUP(B24,Summary!$I$2:$AM$7,5,0)) | C29: =IFERROR(VLOOKUP(B29,fixed_expenses[],2,0),"") | D29: =IF(HLOOKUP(D24,Summary!$I$2:$AM$7,5,0)=0,"",HLOOKUP(D24,Summary!$I$2:$AM$7,5,0)) | E29: =IFERROR(VLOOKUP(D29,fixed_expenses[],2,0),"") | F29: =IF(HLOOKUP(F24,Summary!$I$2:$AM$7,5,0)=0,"",HLOOKUP(F24,Summary!$I$2:$AM$7,5,0)) | G29: =IFERROR(VLOOKUP(F29,fixed_expenses[],2,0),"") | H29: =IF(HLOOKUP(H24,Summary!$I$2:$AM$7,5,0)=0,"",HLOOKUP(H24,Summary!$I$2:$AM$7,5,0)) | I29: =IFERROR(VLOOKUP(H29,fixed_expenses[],2,0),"") | J29: =IF(HLOOKUP(J24,Summary!$I$2:$AM$7,5,0)=0,"",HLOOKUP(J24,Summary!$I$2:$AM$7,5,0)) | K29: =IFERROR(VLOOKUP(J29,fixed_expenses[],2,0),"") | L29: =IF(HLOOKUP(L24,Summary!$I$2:$AM$7,5,0)=0,"",HLOOKUP(L24,Summary!$I$2:$AM$7,5,0)) | M29: =IFERROR(VLOOKUP(L29,fixed_expenses[],2,0),"") | N29: =IF(HLOOKUP(N24,Summary!$I$2:$AM$7,5,0)=0,"",HLOOKUP(N24,Summary!$I$2:$AM$7,5,0)) | O29: =IFERROR(VLOOKUP(N29,fixed_expenses[],2,0),"")
B30: =IF(HLOOKUP(B24,Summary!$I$2:$AM$7,6,0)=0,"",HLOOKUP(B24,Summary!$I$2:$AM$7,6,0)) | C30: =IFERROR(VLOOKUP(B30,fixed_expenses[],2,0),"") | D30: =IF(HLOOKUP(D24,Summary!$I$2:$AM$7,6,0)=0,"",HLOOKUP(D24,Summary!$I$2:$AM$7,6,0)) | E30: =IFERROR(VLOOKUP(D30,fixed_expenses[],2,0),"") | F30: =IF(HLOOKUP(F24,Summary!$I$2:$AM$7,6,0)=0,"",HLOOKUP(F24,Summary!$I$2:$AM$7,6,0)) | G30: =IFERROR(VLOOKUP(F30,fixed_expenses[],2,0),"") | H30: =IF(HLOOKUP(H24,Summary!$I$2:$AM$7,6,0)=0,"",HLOOKUP(H24,Summary!$I$2:$AM$7,6,0)) | I30: =IFERROR(VLOOKUP(H30,fixed_expenses[],2,0),"") | J30: =IF(HLOOKUP(J24,Summary!$I$2:$AM$7,6,0)=0,"",HLOOKUP(J24,Summary!$I$2:$AM$7,6,0)) | K30: =IFERROR(VLOOKUP(J30,fixed_expenses[],2,0),"") | L30: =IF(HLOOKUP(L24,Summary!$I$2:$AM$7,6,0)=0,"",HLOOKUP(L24,Summary!$I$2:$AM$7,6,0)) | M30: =IFERROR(VLOOKUP(L30,fixed_expenses[],2,0),"") | N30: =IF(HLOOKUP(N24,Summary!$I$2:$AM$7,6,0)=0,"",HLOOKUP(N24,Summary!$I$2:$AM$7,6,0)) | O30: =IFERROR(VLOOKUP(N30,fixed_expenses[],2,0),"")
A31: Total is auto calculated for each day and week in cell at right, cells C31 through P31. Next instruction is in cell A33. | B31: TOTAL | C31: =SUM(C26:C30) -> 0 | E31: =SUM(E26:E30) -> 0 | G31: =SUM(G26:G30) -> 0 | I31: =SUM(I26:I30) -> 0 | K31: =SUM(K26:K30) -> 0 | M31: =SUM(M26:M30) -> 110 | O31: =SUM(O26:O30) -> 0 | P31: =SUM(C31,E31,G31,I31,K31,M31,O31) -> 110
A33: Calendar dates are in cells at right, cells B33 through O33. | B33: =N24+1 -> 17 | D33: =B33+1 -> 18 | F33: =D33+1 -> 19 | H33: =F33+1 -> 20 | J33: =H33+1 -> 21 | L33: =J33+1 -> 22 | N33: =L33+1 -> 23
A34: Description and Amount labels are in cells at right, cells B34 through O34. | B34: DESCRIPTION | C34: AMOUNT | D34: DESCRIPTION | E34: AMOUNT | F34: DESCRIPTION | G34: AMOUNT | H34: DESCRIPTION | I34: AMOUNT | J34: DESCRIPTION | K34: AMOUNT | L34: DESCRIPTION | M34: AMOUNT | N34: DESCRIPTION | O34: AMOUNT
A35: Enter Description and Amount of each expense in cells at right, cells B35 through O39. Next instruction is in cell A40. | B35: =IF(HLOOKUP(B33,Summary!$I$2:$AM$7,2,0)=0,"",HLOOKUP(B33,Summary!$I$2:$AM$7,2,0)) | C35: =IFERROR(VLOOKUP(B35,fixed_expenses[],2,0),"") | D35: =IF(HLOOKUP(D33,Summary!$I$2:$AM$7,2,0)=0,"",HLOOKUP(D33,Summary!$I$2:$AM$7,2,0)) | E35: =IFERROR(VLOOKUP(D35,fixed_expenses[],2,0),"") | F35: =IF(HLOOKUP(F33,Summary!$I$2:$AM$7,2,0)=0,"",HLOOKUP(F33,Summary!$I$2:$AM$7,2,0)) | G35: =IFERROR(VLOOKUP(F35,fixed_expenses[],2,0),"") | H35: =IF(HLOOKUP(H33,Summary!$I$2:$AM$7,2,0)=0,"",HLOOKUP(H33,Summary!$I$2:$AM$7,2,0)) -> Lynn Phone Bill | I35: =IFERROR(VLOOKUP(H35,fixed_expenses[],2,0),"") | J35: =IF(HLOOKUP(J33,Summary!$I$2:$AM$7,2,0)=0,"",HLOOKUP(J33,Summary!$I$2:$AM$7,2,0)) | K35: =IFERROR(VLOOKUP(J35,fixed_expenses[],2,0),"") | L35: =IF(HLOOKUP(L33,Summary!$I$2:$AM$7,2,0)=0,"",HLOOKUP(L33,Summary!$I$2:$AM$7,2,0)) | M35: =IFERROR(VLOOKUP(L35,fixed_expenses[],2,0),"") | N35: =IF(HLOOKUP(N33,Summary!$I$2:$AM$7,2,0)=0,"",HLOOKUP(N33,Summary!$I$2:$AM$7,2,0)) | O35: =IFERROR(VLOOKUP(N35,fixed_expenses[],2,0),"")
B36: =IF(HLOOKUP(B33,Summary!$I$2:$AM$7,3,0)=0,"",HLOOKUP(B33,Summary!$I$2:$AM$7,3,0)) | C36: =IFERROR(VLOOKUP(B36,fixed_expenses[],2,0),"") | D36: =IF(HLOOKUP(D33,Summary!$I$2:$AM$7,3,0)=0,"",HLOOKUP(D33,Summary!$I$2:$AM$7,3,0)) | E36: =IFERROR(VLOOKUP(D36,fixed_expenses[],2,0),"") | F36: =IF(HLOOKUP(F33,Summary!$I$2:$AM$7,3,0)=0,"",HLOOKUP(F33,Summary!$I$2:$AM$7,3,0)) | G36: =IFERROR(VLOOKUP(F36,fixed_expenses[],2,0),"") | H36: =IF(HLOOKUP(H33,Summary!$I$2:$AM$7,3,0)=0,"",HLOOKUP(H33,Summary!$I$2:$AM$7,3,0)) | I36: =IFERROR(VLOOKUP(H36,fixed_expenses[],2,0),"") | J36: =IF(HLOOKUP(J33,Summary!$I$2:$AM$7,3,0)=0,"",HLOOKUP(J33,Summary!$I$2:$AM$7,3,0)) | K36: =IFERROR(VLOOKUP(J36,fixed_expenses[],2,0),"") | L36: =IF(HLOOKUP(L33,Summary!$I$2:$AM$7,3,0)=0,"",HLOOKUP(L33,Summary!$I$2:$AM$7,3,0)) | M36: =IFERROR(VLOOKUP(L36,fixed_expenses[],2,0),"") | N36: =IF(HLOOKUP(N33,Summary!$I$2:$AM$7,3,0)=0,"",HLOOKUP(N33,Summary!$I$2:$AM$7,3,0)) | O36: =IFERROR(VLOOKUP(N36,fixed_expenses[],2,0),"")
B37: =IF(HLOOKUP(B33,Summary!$I$2:$AM$7,4,0)=0,"",HLOOKUP(B33,Summary!$I$2:$AM$7,4,0)) | C37: =IFERROR(VLOOKUP(B37,fixed_expenses[],2,0),"") | D37: =IF(HLOOKUP(D33,Summary!$I$2:$AM$7,4,0)=0,"",HLOOKUP(D33,Summary!$I$2:$AM$7,4,0)) | E37: =IFERROR(VLOOKUP(D37,fixed_expenses[],2,0),"") | F37: =IF(HLOOKUP(F33,Summary!$I$2:$AM$7,4,0)=0,"",HLOOKUP(F33,Summary!$I$2:$AM$7,4,0)) | G37: =IFERROR(VLOOKUP(F37,fixed_expenses[],2,0),"") | H37: =IF(HLOOKUP(H33,Summary!$I$2:$AM$7,4,0)=0,"",HLOOKUP(H33,Summary!$I$2:$AM$7,4,0)) | I37: =IFERROR(VLOOKUP(H37,fixed_expenses[],2,0),"") | J37: =IF(HLOOKUP(J33,Summary!$I$2:$AM$7,4,0)=0,"",HLOOKUP(J33,Summary!$I$2:$AM$7,4,0)) | K37: =IFERROR(VLOOKUP(J37,fixed_expenses[],2,0),"") | L37: =IF(HLOOKUP(L33,Summary!$I$2:$AM$7,4,0)=0,"",HLOOKUP(L33,Summary!$I$2:$AM$7,4,0)) | M37: =IFERROR(VLOOKUP(L37,fixed_expenses[],2,0),"") | N37: =IF(HLOOKUP(N33,Summary!$I$2:$AM$7,4,0)=0,"",HLOOKUP(N33,Summary!$I$2:$AM$7,4,0)) | O37: =IFERROR(VLOOKUP(N37,fixed_expenses[],2,0),"")
B38: =IF(HLOOKUP(B33,Summary!$I$2:$AM$7,5,0)=0,"",HLOOKUP(B33,Summary!$I$2:$AM$7,5,0)) | C38: =IFERROR(VLOOKUP(B38,fixed_expenses[],2,0),"") | D38: =IF(HLOOKUP(D33,Summary!$I$2:$AM$7,5,0)=0,"",HLOOKUP(D33,Summary!$I$2:$AM$7,5,0)) | E38: =IFERROR(VLOOKUP(D38,fixed_expenses[],2,0),"") | F38: =IF(HLOOKUP(F33,Summary!$I$2:$AM$7,5,0)=0,"",HLOOKUP(F33,Summary!$I$2:$AM$7,5,0)) | G38: =IFERROR(VLOOKUP(F38,fixed_expenses[],2,0),"") | H38: =IF(HLOOKUP(H33,Summary!$I$2:$AM$7,5,0)=0,"",HLOOKUP(H33,Summary!$I$2:$AM$7,5,0)) | I38: =IFERROR(VLOOKUP(H38,fixed_expenses[],2,0),"") | J38: =IF(HLOOKUP(J33,Summary!$I$2:$AM$7,5,0)=0,"",HLOOKUP(J33,Summary!$I$2:$AM$7,5,0)) | K38: =IFERROR(VLOOKUP(J38,fixed_expenses[],2,0),"") | L38: =IF(HLOOKUP(L33,Summary!$I$2:$AM$7,5,0)=0,"",HLOOKUP(L33,Summary!$I$2:$AM$7,5,0)) | M38: =IFERROR(VLOOKUP(L38,fixed_expenses[],2,0),"") | N38: =IF(HLOOKUP(N33,Summary!$I$2:$AM$7,5,0)=0,"",HLOOKUP(N33,Summary!$I$2:$AM$7,5,0)) | O38: =IFERROR(VLOOKUP(N38,fixed_expenses[],2,0),"")
B39: =IF(HLOOKUP(B33,Summary!$I$2:$AM$7,6,0)=0,"",HLOOKUP(B33,Summary!$I$2:$AM$7,6,0)) | C39: =IFERROR(VLOOKUP(B39,fixed_expenses[],2,0),"") | D39: =IF(HLOOKUP(D33,Summary!$I$2:$AM$7,6,0)=0,"",HLOOKUP(D33,Summary!$I$2:$AM$7,6,0)) | E39: =IFERROR(VLOOKUP(D39,fixed_expenses[],2,0),"") | F39: =IF(HLOOKUP(F33,Summary!$I$2:$AM$7,6,0)=0,"",HLOOKUP(F33,Summary!$I$2:$AM$7,6,0)) | G39: =IFERROR(VLOOKUP(F39,fixed_expenses[],2,0),"") | H39: =IF(HLOOKUP(H33,Summary!$I$2:$AM$7,6,0)=0,"",HLOOKUP(H33,Summary!$I$2:$AM$7,6,0)) | I39: =IFERROR(VLOOKUP(H39,fixed_expenses[],2,0),"") | J39: =IF(HLOOKUP(J33,Summary!$I$2:$AM$7,6,0)=0,"",HLOOKUP(J33,Summary!$I$2:$AM$7,6,0)) | K39: =IFERROR(VLOOKUP(J39,fixed_expenses[],2,0),"") | L39: =IF(HLOOKUP(L33,Summary!$I$2:$AM$7,6,0)=0,"",HLOOKUP(L33,Summary!$I$2:$AM$7,6,0)) | M39: =IFERROR(VLOOKUP(L39,fixed_expenses[],2,0),"") | N39: =IF(HLOOKUP(N33,Summary!$I$2:$AM$7,6,0)=0,"",HLOOKUP(N33,Summary!$I$2:$AM$7,6,0)) | O39: =IFERROR(VLOOKUP(N39,fixed_expenses[],2,0),"")
A40: Total is auto calculated for each day and week in cell at right, cells C40 through P40. Next instruction is in cell A42. | B40: TOTAL | C40: =SUM(C35:C39) -> 0 | E40: =SUM(E35:E39) -> 0 | G40: =SUM(G35:G39) -> 0 | I40: =SUM(I35:I39) -> 0 | K40: =SUM(K35:K39) -> 0 | M40: =SUM(M35:M39) -> 0 | O40: =SUM(O35:O39) -> 0 | P40: =SUM(C40,E40,G40,I40,K40,M40,O40) -> 0
A42: Calendar dates are in cells at right, cells B42 through O42. | B42: =DAY(IF(DAY(JanSun1)=1,JanSun1+22,JanSun1+29)) -> 24 | D42: =DAY(IF(DAY(JanSun1)=1,JanSun1+23,JanSun1+30)) -> 25 | F42: =DAY(IF(DAY(JanSun1)=1,JanSun1+24,JanSun1+31)) -> 26 | H42: =DAY(IF(DAY(JanSun1)=1,JanSun1+25,JanSun1+32)) -> 27 | J42: =DAY(IF(DAY(JanSun1)=1,JanSun1+26,JanSun1+33)) -> 28 | L42: =DAY(IF(DAY(JanSun1)=1,JanSun1+27,JanSun1+34)) -> 29 | N42: =DAY(IF(DAY(JanSun1)=1,JanSun1+28,JanSun1+35)) -> 30
A43: Description and Amount labels are in cells at right, cells B43 through O43. | B43: DESCRIPTION | C43: AMOUNT | D43: DESCRIPTION | E43: AMOUNT | F43: DESCRIPTION | G43: AMOUNT | H43: DESCRIPTION | I43: AMOUNT | J43: DESCRIPTION | K43: AMOUNT | L43: DESCRIPTION | M43: AMOUNT | N43: DESCRIPTION | O43: AMOUNT
A44: Enter Description and Amount of each expense in cells at right, cells B44 through O48. Next instruction is in cell A49. | B44: =IF(HLOOKUP(B42,Summary!$I$2:$AM$7,2,0)=0,"",HLOOKUP(B42,Summary!$I$2:$AM$7,2,0)) | C44: =IFERROR(VLOOKUP(B44,fixed_expenses[],2,0),"") | D44: =IF(HLOOKUP(D42,Summary!$I$2:$AM$7,2,0)=0,"",HLOOKUP(D42,Summary!$I$2:$AM$7,2,0)) | E44: =IFERROR(VLOOKUP(D44,fixed_expenses[],2,0),"") | F44: =IF(HLOOKUP(F42,Summary!$I$2:$AM$7,2,0)=0,"",HLOOKUP(F42,Summary!$I$2:$AM$7,2,0)) | G44: =IFERROR(VLOOKUP(F44,fixed_expenses[],2,0),"") | H44: =IF(HLOOKUP(H42,Summary!$I$2:$AM$7,2,0)=0,"",HLOOKUP(H42,Summary!$I$2:$AM$7,2,0)) | I44: =IFERROR(VLOOKUP(H44,fixed_expenses[],2,0),"") | J44: =IF(HLOOKUP(J42,Summary!$I$2:$AM$7,2,0)=0,"",HLOOKUP(J42,Summary!$I$2:$AM$7,2,0)) | K44: =IFERROR(VLOOKUP(J44,fixed_expenses[],2,0),"") | L44: =IF(HLOOKUP(L42,Summary!$I$2:$AM$7,2,0)=0,"",HLOOKUP(L42,Summary!$I$2:$AM$7,2,0)) | M44: =IFERROR(VLOOKUP(L44,fixed_expenses[],2,0),"") | N44: =IF(HLOOKUP(N42,Summary!$I$2:$AM$7,2,0)=0,"",HLOOKUP(N42,Summary!$I$2:$AM$7,2,0)) | O44: =IFERROR(VLOOKUP(N44,fixed_expenses[],2,0),"")
B45: =IF(HLOOKUP(B42,Summary!$I$2:$AM$7,3,0)=0,"",HLOOKUP(B42,Summary!$I$2:$AM$7,3,0)) | C45: =IFERROR(VLOOKUP(B45,fixed_expenses[],2,0),"") | D45: =IF(HLOOKUP(D42,Summary!$I$2:$AM$7,3,0)=0,"",HLOOKUP(D42,Summary!$I$2:$AM$7,3,0)) | E45: =IFERROR(VLOOKUP(D45,fixed_expenses[],2,0),"") | F45: =IF(HLOOKUP(F42,Summary!$I$2:$AM$7,3,0)=0,"",HLOOKUP(F42,Summary!$I$2:$AM$7,3,0)) | G45: =IFERROR(VLOOKUP(F45,fixed_expenses[],2,0),"") | H45: =IF(HLOOKUP(H42,Summary!$I$2:$AM$7,3,0)=0,"",HLOOKUP(H42,Summary!$I$2:$AM$7,3,0)) | I45: =IFERROR(VLOOKUP(H45,fixed_expenses[],2,0),"") | J45: =IF(HLOOKUP(J42,Summary!$I$2:$AM$7,3,0)=0,"",HLOOKUP(J42,Summary!$I$2:$AM$7,3,0)) | K45: =IFERROR(VLOOKUP(J45,fixed_expenses[],2,0),"") | L45: =IF(HLOOKUP(L42,Summary!$I$2:$AM$7,3,0)=0,"",HLOOKUP(L42,Summary!$I$2:$AM$7,3,0)) | M45: =IFERROR(VLOOKUP(L45,fixed_expenses[],2,0),"") | N45: =IF(HLOOKUP(N42,Summary!$I$2:$AM$7,3,0)=0,"",HLOOKUP(N42,Summary!$I$2:$AM$7,3,0)) | O45: =IFERROR(VLOOKUP(N45,fixed_expenses[],2,0),"")
B46: =IF(HLOOKUP(B42,Summary!$I$2:$AM$7,4,0)=0,"",HLOOKUP(B42,Summary!$I$2:$AM$7,4,0)) | C46: =IFERROR(VLOOKUP(B46,fixed_expenses[],2,0),"") | D46: =IF(HLOOKUP(D42,Summary!$I$2:$AM$7,4,0)=0,"",HLOOKUP(D42,Summary!$I$2:$AM$7,4,0)) | E46: =IFERROR(VLOOKUP(D46,fixed_expenses[],2,0),"") | F46: =IF(HLOOKUP(F42,Summary!$I$2:$AM$7,4,0)=0,"",HLOOKUP(F42,Summary!$I$2:$AM$7,4,0)) | G46: =IFERROR(VLOOKUP(F46,fixed_expenses[],2,0),"") | H46: =IF(HLOOKUP(H42,Summary!$I$2:$AM$7,4,0)=0,"",HLOOKUP(H42,Summary!$I$2:$AM$7,4,0)) | I46: =IFERROR(VLOOKUP(H46,fixed_expenses[],2,0),"") | J46: =IF(HLOOKUP(J42,Summary!$I$2:$AM$7,4,0)=0,"",HLOOKUP(J42,Summary!$I$2:$AM$7,4,0)) | K46: =IFERROR(VLOOKUP(J46,fixed_expenses[],2,0),"") | L46: =IF(HLOOKUP(L42,Summary!$I$2:$AM$7,4,0)=0,"",HLOOKUP(L42,Summary!$I$2:$AM$7,4,0)) | M46: =IFERROR(VLOOKUP(L46,fixed_expenses[],2,0),"") | N46: =IF(HLOOKUP(N42,Summary!$I$2:$AM$7,4,0)=0,"",HLOOKUP(N42,Summary!$I$2:$AM$7,4,0)) | O46: =IFERROR(VLOOKUP(N46,fixed_expenses[],2,0),"")
B47: =IF(HLOOKUP(B42,Summary!$I$2:$AM$7,5,0)=0,"",HLOOKUP(B42,Summary!$I$2:$AM$7,5,0)) | C47: =IFERROR(VLOOKUP(B47,fixed_expenses[],2,0),"") | D47: =IF(HLOOKUP(D42,Summary!$I$2:$AM$7,5,0)=0,"",HLOOKUP(D42,Summary!$I$2:$AM$7,5,0)) | E47: =IFERROR(VLOOKUP(D47,fixed_expenses[],2,0),"") | F47: =IF(HLOOKUP(F42,Summary!$I$2:$AM$7,5,0)=0,"",HLOOKUP(F42,Summary!$I$2:$AM$7,5,0)) | G47: =IFERROR(VLOOKUP(F47,fixed_expenses[],2,0),"") | H47: =IF(HLOOKUP(H42,Summary!$I$2:$AM$7,5,0)=0,"",HLOOKUP(H42,Summary!$I$2:$AM$7,5,0)) | I47: =IFERROR(VLOOKUP(H47,fixed_expenses[],2,0),"") | J47: =IF(HLOOKUP(J42,Summary!$I$2:$AM$7,5,0)=0,"",HLOOKUP(J42,Summary!$I$2:$AM$7,5,0)) | K47: =IFERROR(VLOOKUP(J47,fixed_expenses[],2,0),"") | L47: =IF(HLOOKUP(L42,Summary!$I$2:$AM$7,5,0)=0,"",HLOOKUP(L42,Summary!$I$2:$AM$7,5,0)) | M47: =IFERROR(VLOOKUP(L47,fixed_expenses[],2,0),"") | N47: =IF(HLOOKUP(N42,Summary!$I$2:$AM$7,5,0)=0,"",HLOOKUP(N42,Summary!$I$2:$AM$7,5,0)) | O47: =IFERROR(VLOOKUP(N47,fixed_expenses[],2,0),"")
B48: =IF(HLOOKUP(B42,Summary!$I$2:$AM$7,6,0)=0,"",HLOOKUP(B42,Summary!$I$2:$AM$7,6,0)) | C48: =IFERROR(VLOOKUP(B48,fixed_expenses[],2,0),"") | D48: =IF(HLOOKUP(D42,Summary!$I$2:$AM$7,6,0)=0,"",HLOOKUP(D42,Summary!$I$2:$AM$7,6,0)) | E48: =IFERROR(VLOOKUP(D48,fixed_expenses[],2,0),"") | F48: =IF(HLOOKUP(F42,Summary!$I$2:$AM$7,6,0)=0,"",HLOOKUP(F42,Summary!$I$2:$AM$7,6,0)) | G48: =IFERROR(VLOOKUP(F48,fixed_expenses[],2,0),"") | H48: =IF(HLOOKUP(H42,Summary!$I$2:$AM$7,6,0)=0,"",HLOOKUP(H42,Summary!$I$2:$AM$7,6,0)) | I48: =IFERROR(VLOOKUP(H48,fixed_expenses[],2,0),"") | J48: =IF(HLOOKUP(J42,Summary!$I$2:$AM$7,6,0)=0,"",HLOOKUP(J42,Summary!$I$2:$AM$7,6,0)) | K48: =IFERROR(VLOOKUP(J48,fixed_expenses[],2,0),"") | L48: =IF(HLOOKUP(L42,Summary!$I$2:$AM$7,6,0)=0,"",HLOOKUP(L42,Summary!$I$2:$AM$7,6,0)) | M48: =IFERROR(VLOOKUP(L48,fixed_expenses[],2,0),"") | N48: =IF(HLOOKUP(N42,Summary!$I$2:$AM$7,6,0)=0,"",HLOOKUP(N42,Summary!$I$2:$AM$7,6,0)) | O48: =IFERROR(VLOOKUP(N48,fixed_expenses[],2,0),"")
A49: Total is auto calculated for each day and week in cell at right, cells C49 through P49. Next instruction is in cell A51. | B49: TOTAL | C49: =SUM(C44:C48) -> 0 | E49: =SUM(E44:E48) -> 0 | G49: =SUM(G44:G48) -> 0 | I49: =SUM(I44:I48) -> 0 | K49: =SUM(K44:K48) -> 0 | M49: =SUM(M44:M48) -> 0 | O49: =SUM(O44:O48) -> 0 | P49: =SUMIF(B42:N42,">="&15,C49:O49) -> 0
A51: Calendar dates are in cells at right, cells B51 through O51. | B51: =DAY(IF(DAY(JanSun1)=1,JanSun1+29,JanSun1+36)) -> 31 | D51: =DAY(IF(DAY(JanSun1)=1,JanSun1+30,JanSun1+37)) -> 1 | F51: =DAY(IF(DAY(JanSun1)=1,JanSun1+31,JanSun1+38)) -> 2 | H51: =DAY(IF(DAY(JanSun1)=1,JanSun1+32,JanSun1+39)) -> 3 | J51: =DAY(IF(DAY(JanSun1)=1,JanSun1+33,JanSun1+40)) -> 4 | L51: =DAY(IF(DAY(JanSun1)=1,JanSun1+34,JanSun1+41)) -> 5 | N51: =DAY(IF(DAY(JanSun1)=1,JanSun1+35,JanSun1+42)) -> 6
A52: Description and Amount labels are in cells at right, cells B52 through O52. | B52: DESCRIPTION | C52: AMOUNT | D52: DESCRIPTION | E52: AMOUNT | F52: DESCRIPTION | G52: AMOUNT | H52: DESCRIPTION | I52: AMOUNT | J52: DESCRIPTION | K52: AMOUNT | L52: DESCRIPTION | M52: AMOUNT | N52: DESCRIPTION | O52: AMOUNT
A53: Enter Description and Amount of each expense in cells at right, cells B53 through O57. Next instruction is in cell A58. | B53: =IF(HLOOKUP(B51,Summary!$I$2:$AM$7,2,0)=0,"",HLOOKUP(B51,Summary!$I$2:$AM$7,2,0)) | C53: =IFERROR(VLOOKUP(B53,fixed_expenses[],2,0),"") | D53: =IF(HLOOKUP(D51,Summary!$I$2:$AM$7,2,0)=0,"",HLOOKUP(D51,Summary!$I$2:$AM$7,2,0)) | E53: =IFERROR(VLOOKUP(D53,fixed_expenses[],2,0),"") | F53: =IF(HLOOKUP(F51,Summary!$I$2:$AM$7,2,0)=0,"",HLOOKUP(F51,Summary!$I$2:$AM$7,2,0)) | G53: =IFERROR(VLOOKUP(F53,fixed_expenses[],2,0),"") | H53: =IF(HLOOKUP(H51,Summary!$I$2:$AM$7,2,0)=0,"",HLOOKUP(H51,Summary!$I$2:$AM$7,2,0)) -> Rent | I53: =IFERROR(VLOOKUP(H53,fixed_expenses[],2,0),"") -> 1200 | J53: =IF(HLOOKUP(J51,Summary!$I$2:$AM$7,2,0)=0,"",HLOOKUP(J51,Summary!$I$2:$AM$7,2,0)) | K53: =IFERROR(VLOOKUP(J53,fixed_expenses[],2,0),"") | L53: =IF(HLOOKUP(L51,Summary!$I$2:$AM$7,2,0)=0,"",HLOOKUP(L51,Summary!$I$2:$AM$7,2,0)) | M53: =IFERROR(VLOOKUP(L53,fixed_expenses[],2,0),"") | N53: =IF(HLOOKUP(N51,Summary!$I$2:$AM$7,2,0)=0,"",HLOOKUP(N51,Summary!$I$2:$AM$7,2,0)) | O53: =IFERROR(VLOOKUP(N53,fixed_expenses[],2,0),"")
B54: =IF(HLOOKUP(B51,Summary!$I$2:$AM$7,3,0)=0,"",HLOOKUP(B51,Summary!$I$2:$AM$7,3,0)) | C54: =IFERROR(VLOOKUP(B54,fixed_expenses[],2,0),"") | D54: =IF(HLOOKUP(D51,Summary!$I$2:$AM$7,3,0)=0,"",HLOOKUP(D51,Summary!$I$2:$AM$7,3,0)) | E54: =IFERROR(VLOOKUP(D54,fixed_expenses[],2,0),"") | F54: =IF(HLOOKUP(F51,Summary!$I$2:$AM$7,3,0)=0,"",HLOOKUP(F51,Summary!$I$2:$AM$7,3,0)) | G54: =IFERROR(VLOOKUP(F54,fixed_expenses[],2,0),"") | H54: =IF(HLOOKUP(H51,Summary!$I$2:$AM$7,3,0)=0,"",HLOOKUP(H51,Summary!$I$2:$AM$7,3,0)) | I54: =IFERROR(VLOOKUP(H54,fixed_expenses[],2,0),"") | J54: =IF(HLOOKUP(J51,Summary!$I$2:$AM$7,3,0)=0,"",HLOOKUP(J51,Summary!$I$2:$AM$7,3,0)) | K54: =IFERROR(VLOOKUP(J54,fixed_expenses[],2,0),"") | L54: =IF(HLOOKUP(L51,Summary!$I$2:$AM$7,3,0)=0,"",HLOOKUP(L51,Summary!$I$2:$AM$7,3,0)) | M54: =IFERROR(VLOOKUP(L54,fixed_expenses[],2,0),"") | N54: =IF(HLOOKUP(N51,Summary!$I$2:$AM$7,3,0)=0,"",HLOOKUP(N51,Summary!$I$2:$AM$7,3,0)) | O54: =IFERROR(VLOOKUP(N54,fixed_expenses[],2,0),"")
B55: =IF(HLOOKUP(B51,Summary!$I$2:$AM$7,4,0)=0,"",HLOOKUP(B51,Summary!$I$2:$AM$7,4,0)) | C55: =IFERROR(VLOOKUP(B55,fixed_expenses[],2,0),"") | D55: =IF(HLOOKUP(D51,Summary!$I$2:$AM$7,4,0)=0,"",HLOOKUP(D51,Summary!$I$2:$AM$7,4,0)) | E55: =IFERROR(VLOOKUP(D55,fixed_expenses[],2,0),"") | F55: =IF(HLOOKUP(F51,Summary!$I$2:$AM$7,4,0)=0,"",HLOOKUP(F51,Summary!$I$2:$AM$7,4,0)) | G55: =IFERROR(VLOOKUP(F55,fixed_expenses[],2,0),"") | H55: =IF(HLOOKUP(H51,Summary!$I$2:$AM$7,4,0)=0,"",HLOOKUP(H51,Summary!$I$2:$AM$7,4,0)) | I55: =IFERROR(VLOOKUP(H55,fixed_expenses[],2,0),"") | J55: =IF(HLOOKUP(J51,Summary!$I$2:$AM$7,4,0)=0,"",HLOOKUP(J51,Summary!$I$2:$AM$7,4,0)) | K55: =IFERROR(VLOOKUP(J55,fixed_expenses[],2,0),"") | L55: =IF(HLOOKUP(L51,Summary!$I$2:$AM$7,4,0)=0,"",HLOOKUP(L51,Summary!$I$2:$AM$7,4,0)) | M55: =IFERROR(VLOOKUP(L55,fixed_expenses[],2,0),"") | N55: =IF(HLOOKUP(N51,Summary!$I$2:$AM$7,4,0)=0,"",HLOOKUP(N51,Summary!$I$2:$AM$7,4,0)) | O55: =IFERROR(VLOOKUP(N55,fixed_expenses[],2,0),"")
B56: =IF(HLOOKUP(B51,Summary!$I$2:$AM$7,5,0)=0,"",HLOOKUP(B51,Summary!$I$2:$AM$7,5,0)) | C56: =IFERROR(VLOOKUP(B56,fixed_expenses[],2,0),"") | D56: =IF(HLOOKUP(D51,Summary!$I$2:$AM$7,5,0)=0,"",HLOOKUP(D51,Summary!$I$2:$AM$7,5,0)) | E56: =IFERROR(VLOOKUP(D56,fixed_expenses[],2,0),"") | F56: =IF(HLOOKUP(F51,Summary!$I$2:$AM$7,5,0)=0,"",HLOOKUP(F51,Summary!$I$2:$AM$7,5,0)) | G56: =IFERROR(VLOOKUP(F56,fixed_expenses[],2,0),"") | H56: =IF(HLOOKUP(H51,Summary!$I$2:$AM$7,5,0)=0,"",HLOOKUP(H51,Summary!$I$2:$AM$7,5,0)) | I56: =IFERROR(VLOOKUP(H56,fixed_expenses[],2,0),"") | J56: =IF(HLOOKUP(J51,Summary!$I$2:$AM$7,5,0)=0,"",HLOOKUP(J51,Summary!$I$2:$AM$7,5,0)) | K56: =IFERROR(VLOOKUP(J56,fixed_expenses[],2,0),"") | L56: =IF(HLOOKUP(L51,Summary!$I$2:$AM$7,5,0)=0,"",HLOOKUP(L51,Summary!$I$2:$AM$7,5,0)) | M56: =IFERROR(VLOOKUP(L56,fixed_expenses[],2,0),"") | N56: =IF(HLOOKUP(N51,Summary!$I$2:$AM$7,5,0)=0,"",HLOOKUP(N51,Summary!$I$2:$AM$7,5,0)) | O56: =IFERROR(VLOOKUP(N56,fixed_expenses[],2,0),"")
B57: =IF(HLOOKUP(B51,Summary!$I$2:$AM$7,6,0)=0,"",HLOOKUP(B51,Summary!$I$2:$AM$7,6,0)) | C57: =IFERROR(VLOOKUP(B57,fixed_expenses[],2,0),"") | D57: =IF(HLOOKUP(D51,Summary!$I$2:$AM$7,6,0)=0,"",HLOOKUP(D51,Summary!$I$2:$AM$7,6,0)) | E57: =IFERROR(VLOOKUP(D57,fixed_expenses[],2,0),"") | F57: =IF(HLOOKUP(F51,Summary!$I$2:$AM$7,6,0)=0,"",HLOOKUP(F51,Summary!$I$2:$AM$7,6,0)) | G57: =IFERROR(VLOOKUP(F57,fixed_expenses[],2,0),"") | H57: =IF(HLOOKUP(H51,Summary!$I$2:$AM$7,6,0)=0,"",HLOOKUP(H51,Summary!$I$2:$AM$7,6,0)) | I57: =IFERROR(VLOOKUP(H57,fixed_expenses[],2,0),"") | J57: =IF(HLOOKUP(J51,Summary!$I$2:$AM$7,6,0)=0,"",HLOOKUP(J51,Summary!$I$2:$AM$7,6,0)) | K57: =IFERROR(VLOOKUP(J57,fixed_expenses[],2,0),"") | L57: =IF(HLOOKUP(L51,Summary!$I$2:$AM$7,6,0)=0,"",HLOOKUP(L51,Summary!$I$2:$AM$7,6,0)) | M57: =IFERROR(VLOOKUP(L57,fixed_expenses[],2,0),"") | N57: =IF(HLOOKUP(N51,Summary!$I$2:$AM$7,6,0)=0,"",HLOOKUP(N51,Summary!$I$2:$AM$7,6,0)) | O57: =IFERROR(VLOOKUP(N57,fixed_expenses[],2,0),"")
A58: Total is auto calculated for each day and week in cell at right, cells C58 through P58. Next instruction is in cell A60. | B58: TOTAL | C58: =SUM(C53:C57) -> 0 | E58: =SUM(E53:E57) -> 0 | G58: =SUM(G53:G57) -> 0 | I58: =SUM(I53:I57) -> 1200 | K58: =SUM(K53:K57) -> 0 | M58: =SUM(M53:M57) -> 0 | O58: =SUM(O53:O57) -> 0 | P58: =SUMIF(B51:N51,">="&15,C58:O58) -> 0
A60: February label is in cell at right, Monthly Total label in cell L60, and Grand Total label in N60. | B60: FEBRUARY | L60: MONTHLY TOTAL | N60: GRAND TOTAL
A61: Monthly Total is auto calculated in cell L61 and Grand Total in N61. | F61: =IFERROR(WEEKDAY(DATEVALUE(B60&" 1, "&Year1)),"") -> 2 | L61: =SUM(P71,P80,P89,P98,P107,P116) -> 1774 | N61: =SUM(P:P) -> 21288
A62: February calendar is in cells B63 through O116. | B62: 1 | D62: 2 | F62: 3 | H62: 4 | J62: 5 | L62: 6 | N62: 7
A63: Weekdays are in cells at right, cells B63 through N63, and Weekly Total label in cell P63. | B63: SUNDAY | D63: MONDAY | E63: =IF(WEEKDAY(DATEVALUE(Month1&" 1, "&Year1))=COLUMN(#REF!),1,IF(LEN(C63)>0,C63+1,"")) -> #VALUE! | F63: TUESDAY | G63: =IF(WEEKDAY(DATEVALUE(Month1&" 1, "&Year1))=COLUMN(#REF!),1,IF(LEN(E63)>0,E63+1,"")) -> #VALUE! | H63: WEDNESDAY | I63: =IF(WEEKDAY(DATEVALUE(Month1&" 1, "&Year1))=COLUMN(#REF!),1,IF(LEN(G63)>0,G63+1,"")) -> #VALUE! | J63: THURSDAY | K63: =IF(WEEKDAY(DATEVALUE(Month1&" 1, "&Year1))=COLUMN(#REF!),1,IF(LEN(I63)>0,I63+1,"")) -> #VALUE! | L63: FRIDAY | M63: =IF(WEEKDAY(DATEVALUE(Month1&" 1, "&Year1))=COLUMN(#REF!),1,IF(LEN(K63)>0,K63+1,"")) -> #VALUE! | N63: SATURDAY | O63: =IF(WEEKDAY(DATEVALUE(Month1&" 1, "&Year1))=COLUMN(#REF!),1,IF(LEN(M63)>0,M63+1,"")) -> #VALUE! | P63: WEEKLY TOTAL
A64: Calendar dates are in cells at right, cells B64 through O64. If it doesn’t start with number 1, then it is date of previous month. | B64: =DAY(IF(DAY(FebSun1)=1,FebSun1-6,FebSun1+1)) -> 31 | D64: =DAY(IF(DAY(FebSun1)=1,FebSun1-5,FebSun1+2)) -> 1 | F64: =DAY(IF(DAY(FebSun1)=1,FebSun1-4,FebSun1+3)) -> 2 | H64: =DAY(IF(DAY(FebSun1)=1,FebSun1-3,FebSun1+4)) -> 3 | J64: =DAY(IF(DAY(FebSun1)=1,FebSun1-2,FebSun1+5)) -> 4 | L64: =DAY(IF(DAY(FebSun1)=1,FebSun1-1,FebSun1+6)) -> 5 | N64: =DAY(IF(DAY(FebSun1)=1,FebSun1,FebSun1+7)) -> 6
A65: Description and Amount labels are in cells at right, cells B65 through O65. | B65: DESCRIPTION | C65: AMOUNT | D65: DESCRIPTION | E65: AMOUNT | F65: DESCRIPTION | G65: AMOUNT | H65: DESCRIPTION | I65: AMOUNT | J65: DESCRIPTION | K65: AMOUNT | L65: DESCRIPTION | M65: AMOUNT | N65: DESCRIPTION | O65: AMOUNT
A66: Enter Description and Amount of each expense in cells at right, cells B66 through O70. Next instruction is in cell A71. | B66: =IF(HLOOKUP(B64,Summary!$I$2:$AM$7,2,0)=0,"",HLOOKUP(B64,Summary!$I$2:$AM$7,2,0)) | C66: =IFERROR(VLOOKUP(B66,fixed_expenses[],2,0),"") | D66: =IF(HLOOKUP(D64,Summary!$I$2:$AM$7,2,0)=0,"",HLOOKUP(D64,Summary!$I$2:$AM$7,2,0)) | E66: =IFERROR(VLOOKUP(D66,fixed_expenses[],2,0),"") | F66: =IF(HLOOKUP(F64,Summary!$I$2:$AM$7,2,0)=0,"",HLOOKUP(F64,Summary!$I$2:$AM$7,2,0)) | G66: =IFERROR(VLOOKUP(F66,fixed_expenses[],2,0),"") | H66: =IF(HLOOKUP(H64,Summary!$I$2:$AM$7,2,0)=0,"",HLOOKUP(H64,Summary!$I$2:$AM$7,2,0)) -> Rent | I66: =IFERROR(VLOOKUP(H66,fixed_expenses[],2,0),"") -> 1200 | J66: =IF(HLOOKUP(J64,Summary!$I$2:$AM$7,2,0)=0,"",HLOOKUP(J64,Summary!$I$2:$AM$7,2,0)) | K66: =IFERROR(VLOOKUP(J66,fixed_expenses[],2,0),"") | L66: Car | M66: =IFERROR(VLOOKUP(L66,fixed_expenses[],2,0),"") -> 232 | N66: =IF(HLOOKUP(N64,Summary!$I$2:$AM$7,2,0)=0,"",HLOOKUP(N64,Summary!$I$2:$AM$7,2,0)) | O66: =IFERROR(VLOOKUP(N66,fixed_expenses[],2,0),"")
B67: =IF(HLOOKUP(B64,Summary!$I$2:$AM$7,3,0)=0,"",HLOOKUP(B64,Summary!$I$2:$AM$7,3,0)) | C67: =IFERROR(VLOOKUP(B67,fixed_expenses[],2,0),"") | D67: =IF(HLOOKUP(D64,Summary!$I$2:$AM$7,3,0)=0,"",HLOOKUP(D64,Summary!$I$2:$AM$7,3,0)) | E67: =IFERROR(VLOOKUP(D67,fixed_expenses[],2,0),"") | F67: =IF(HLOOKUP(F64,Summary!$I$2:$AM$7,3,0)=0,"",HLOOKUP(F64,Summary!$I$2:$AM$7,3,0)) | G67: =IFERROR(VLOOKUP(F67,fixed_expenses[],2,0),"") | H67: =IF(HLOOKUP(H64,Summary!$I$2:$AM$7,3,0)=0,"",HLOOKUP(H64,Summary!$I$2:$AM$7,3,0)) | I67: =IFERROR(VLOOKUP(H67,fixed_expenses[],2,0),"") | J67: =IF(HLOOKUP(J64,Summary!$I$2:$AM$7,3,0)=0,"",HLOOKUP(J64,Summary!$I$2:$AM$7,3,0)) | K67: =IFERROR(VLOOKUP(J67,fixed_expenses[],2,0),"") | L67: =IF(HLOOKUP(L64,Summary!$I$2:$AM$7,3,0)=0,"",HLOOKUP(L64,Summary!$I$2:$AM$7,3,0)) | M67: =IFERROR(VLOOKUP(L67,fixed_expenses[],2,0),"") | N67: =IF(HLOOKUP(N64,Summary!$I$2:$AM$7,3,0)=0,"",HLOOKUP(N64,Summary!$I$2:$AM$7,3,0)) | O67: =IFERROR(VLOOKUP(N67,fixed_expenses[],2,0),"")
B68: =IF(HLOOKUP(B64,Summary!$I$2:$AM$7,4,0)=0,"",HLOOKUP(B64,Summary!$I$2:$AM$7,4,0)) | C68: =IFERROR(VLOOKUP(B68,fixed_expenses[],2,0),"") | D68: =IF(HLOOKUP(D64,Summary!$I$2:$AM$7,4,0)=0,"",HLOOKUP(D64,Summary!$I$2:$AM$7,4,0)) | E68: =IFERROR(VLOOKUP(D68,fixed_expenses[],2,0),"") | F68: =IF(HLOOKUP(F64,Summary!$I$2:$AM$7,4,0)=0,"",HLOOKUP(F64,Summary!$I$2:$AM$7,4,0)) | G68: =IFERROR(VLOOKUP(F68,fixed_expenses[],2,0),"") | H68: =IF(HLOOKUP(H64,Summary!$I$2:$AM$7,4,0)=0,"",HLOOKUP(H64,Summary!$I$2:$AM$7,4,0)) | I68: =IFERROR(VLOOKUP(H68,fixed_expenses[],2,0),"") | J68: =IF(HLOOKUP(J64,Summary!$I$2:$AM$7,4,0)=0,"",HLOOKUP(J64,Summary!$I$2:$AM$7,4,0)) | K68: =IFERROR(VLOOKUP(J68,fixed_expenses[],2,0),"") | L68: =IF(HLOOKUP(L64,Summary!$I$2:$AM$7,4,0)=0,"",HLOOKUP(L64,Summary!$I$2:$AM$7,4,0)) | M68: =IFERROR(VLOOKUP(L68,fixed_expenses[],2,0),"") | N68: =IF(HLOOKUP(N64,Summary!$I$2:$AM$7,4,0)=0,"",HLOOKUP(N64,Summary!$I$2:$AM$7,4,0)) | O68: =IFERROR(VLOOKUP(N68,fixed_expenses[],2,0),"")
B69: =IF(HLOOKUP(B64,Summary!$I$2:$AM$7,5,0)=0,"",HLOOKUP(B64,Summary!$I$2:$AM$7,5,0)) | C69: =IFERROR(VLOOKUP(B69,fixed_expenses[],2,0),"") | D69: =IF(HLOOKUP(D64,Summary!$I$2:$AM$7,5,0)=0,"",HLOOKUP(D64,Summary!$I$2:$AM$7,5,0)) | E69: =IFERROR(VLOOKUP(D69,fixed_expenses[],2,0),"") | F69: =IF(HLOOKUP(F64,Summary!$I$2:$AM$7,5,0)=0,"",HLOOKUP(F64,Summary!$I$2:$AM$7,5,0)) | G69: =IFERROR(VLOOKUP(F69,fixed_expenses[],2,0),"") | H69: =IF(HLOOKUP(H64,Summary!$I$2:$AM$7,5,0)=0,"",HLOOKUP(H64,Summary!$I$2:$AM$7,5,0)) | I69: =IFERROR(VLOOKUP(H69,fixed_expenses[],2,0),"") | J69: =IF(HLOOKUP(J64,Summary!$I$2:$AM$7,5,0)=0,"",HLOOKUP(J64,Summary!$I$2:$AM$7,5,0)) | K69: =IFERROR(VLOOKUP(J69,fixed_expenses[],2,0),"") | L69: =IF(HLOOKUP(L64,Summary!$I$2:$AM$7,5,0)=0,"",HLOOKUP(L64,Summary!$I$2:$AM$7,5,0)) | M69: =IFERROR(VLOOKUP(L69,fixed_expenses[],2,0),"") | N69: =IF(HLOOKUP(N64,Summary!$I$2:$AM$7,5,0)=0,"",HLOOKUP(N64,Summary!$I$2:$AM$7,5,0)) | O69: =IFERROR(VLOOKUP(N69,fixed_expenses[],2,0),"")
B70: =IF(HLOOKUP(B64,Summary!$I$2:$AM$7,6,0)=0,"",HLOOKUP(B64,Summary!$I$2:$AM$7,6,0)) | C70: =IFERROR(VLOOKUP(B70,fixed_expenses[],2,0),"") | D70: =IF(HLOOKUP(D64,Summary!$I$2:$AM$7,6,0)=0,"",HLOOKUP(D64,Summary!$I$2:$AM$7,6,0)) | E70: =IFERROR(VLOOKUP(D70,fixed_expenses[],2,0),"") | F70: =IF(HLOOKUP(F64,Summary!$I$2:$AM$7,6,0)=0,"",HLOOKUP(F64,Summary!$I$2:$AM$7,6,0)) | G70: =IFERROR(VLOOKUP(F70,fixed_expenses[],2,0),"") | H70: =IF(HLOOKUP(H64,Summary!$I$2:$AM$7,6,0)=0,"",HLOOKUP(H64,Summary!$I$2:$AM$7,6,0)) | I70: =IFERROR(VLOOKUP(H70,fixed_expenses[],2,0),"") | J70: =IF(HLOOKUP(J64,Summary!$I$2:$AM$7,6,0)=0,"",HLOOKUP(J64,Summary!$I$2:$AM$7,6,0)) | K70: =IFERROR(VLOOKUP(J70,fixed_expenses[],2,0),"") | L70: =IF(HLOOKUP(L64,Summary!$I$2:$AM$7,6,0)=0,"",HLOOKUP(L64,Summary!$I$2:$AM$7,6,0)) | M70: =IFERROR(VLOOKUP(L70,fixed_expenses[],2,0),"") | N70: =IF(HLOOKUP(N64,Summary!$I$2:$AM$7,6,0)=0,"",HLOOKUP(N64,Summary!$I$2:$AM$7,6,0)) | O70: =IFERROR(VLOOKUP(N70,fixed_expenses[],2,0),"")
A71: Total is auto calculated for each day and week in cell at right, cells C71 through P71. Next instruction is in cell A73. | B71: TOTAL | C71: =SUM(C66:C70) -> 0 | E71: =SUM(E66:E70) -> 0 | G71: =SUM(G66:G70) -> 0 | I71: =SUM(I66:I70) -> 1200 | K71: =SUM(K66:K70) -> 0 | M71: =SUM(M66:M70) -> 232 | O71: =SUM(O66:O70) -> 0 | P71: =SUMIF(B64:N64,"<8",C71:O71) -> 1432
A73: Calendar dates are in cells at right, cells B73 through O73. | B73: =N64+1 -> 7 | D73: =B73+1 -> 8 | F73: =D73+1 -> 9 | H73: =F73+1 -> 10 | J73: =H73+1 -> 11 | L73: =J73+1 -> 12 | N73: =L73+1 -> 13
A74: Description and Amount labels are in cells at right, cells B74 through O74. | B74: DESCRIPTION | C74: AMOUNT | D74: DESCRIPTION | E74: AMOUNT | F74: DESCRIPTION | G74: AMOUNT | H74: DESCRIPTION | I74: AMOUNT | J74: DESCRIPTION | K74: AMOUNT | L74: DESCRIPTION | M74: AMOUNT | N74: DESCRIPTION | O74: AMOUNT
A75: Enter Description and Amount of each expense in cells at right, cells B75 through O79. Next instruction is in cell A80. | B75: =IF(HLOOKUP(B73,Summary!$I$2:$AM$7,2,0)=0,"",HLOOKUP(B73,Summary!$I$2:$AM$7,2,0)) | C75: =IFERROR(VLOOKUP(B75,fixed_expenses[],2,0),"") | D75: =IF(HLOOKUP(D73,Summary!$I$2:$AM$7,2,0)=0,"",HLOOKUP(D73,Summary!$I$2:$AM$7,2,0)) | E75: =IFERROR(VLOOKUP(D75,fixed_expenses[],2,0),"") | F75: =IF(HLOOKUP(F73,Summary!$I$2:$AM$7,2,0)=0,"",HLOOKUP(F73,Summary!$I$2:$AM$7,2,0)) | G75: =IFERROR(VLOOKUP(F75,fixed_expenses[],2,0),"") | H75: =IF(HLOOKUP(H73,Summary!$I$2:$AM$7,2,0)=0,"",HLOOKUP(H73,Summary!$I$2:$AM$7,2,0)) | I75: =IFERROR(VLOOKUP(H75,fixed_expenses[],2,0),"") | J75: =IF(HLOOKUP(J73,Summary!$I$2:$AM$7,2,0)=0,"",HLOOKUP(J73,Summary!$I$2:$AM$7,2,0)) | K75: =IFERROR(VLOOKUP(J75,fixed_expenses[],2,0),"") | L75: =IF(HLOOKUP(L73,Summary!$I$2:$AM$7,2,0)=0,"",HLOOKUP(L73,Summary!$I$2:$AM$7,2,0)) | M75: =IFERROR(VLOOKUP(L75,fixed_expenses[],2,0),"") | N75: =IF(HLOOKUP(N73,Summary!$I$2:$AM$7,2,0)=0,"",HLOOKUP(N73,Summary!$I$2:$AM$7,2,0)) | O75: =IFERROR(VLOOKUP(N75,fixed_expenses[],2,0),"")
B76: =IF(HLOOKUP(B73,Summary!$I$2:$AM$7,3,0)=0,"",HLOOKUP(B73,Summary!$I$2:$AM$7,3,0)) | C76: =IFERROR(VLOOKUP(B76,fixed_expenses[],2,0),"") | D76: =IF(HLOOKUP(D73,Summary!$I$2:$AM$7,3,0)=0,"",HLOOKUP(D73,Summary!$I$2:$AM$7,3,0)) | E76: =IFERROR(VLOOKUP(D76,fixed_expenses[],2,0),"") | F76: =IF(HLOOKUP(F73,Summary!$I$2:$AM$7,3,0)=0,"",HLOOKUP(F73,Summary!$I$2:$AM$7,3,0)) | G76: =IFERROR(VLOOKUP(F76,fixed_expenses[],2,0),"") | H76: =IF(HLOOKUP(H73,Summary!$I$2:$AM$7,3,0)=0,"",HLOOKUP(H73,Summary!$I$2:$AM$7,3,0)) | I76: =IFERROR(VLOOKUP(H76,fixed_expenses[],2,0),"") | J76: =IF(HLOOKUP(J73,Summary!$I$2:$AM$7,3,0)=0,"",HLOOKUP(J73,Summary!$I$2:$AM$7,3,0)) | K76: =IFERROR(VLOOKUP(J76,fixed_expenses[],2,0),"") | L76: =IF(HLOOKUP(L73,Summary!$I$2:$AM$7,3,0)=0,"",HLOOKUP(L73,Summary!$I$2:$AM$7,3,0)) | M76: =IFERROR(VLOOKUP(L76,fixed_expenses[],2,0),"") | N76: =IF(HLOOKUP(N73,Summary!$I$2:$AM$7,3,0)=0,"",HLOOKUP(N73,Summary!$I$2:$AM$7,3,0)) | O76: =IFERROR(VLOOKUP(N76,fixed_expenses[],2,0),"")
B77: =IF(HLOOKUP(B73,Summary!$I$2:$AM$7,4,0)=0,"",HLOOKUP(B73,Summary!$I$2:$AM$7,4,0)) | C77: =IFERROR(VLOOKUP(B77,fixed_expenses[],2,0),"") | D77: =IF(HLOOKUP(D73,Summary!$I$2:$AM$7,4,0)=0,"",HLOOKUP(D73,Summary!$I$2:$AM$7,4,0)) | E77: =IFERROR(VLOOKUP(D77,fixed_expenses[],2,0),"") | F77: =IF(HLOOKUP(F73,Summary!$I$2:$AM$7,4,0)=0,"",HLOOKUP(F73,Summary!$I$2:$AM$7,4,0)) | G77: =IFERROR(VLOOKUP(F77,fixed_expenses[],2,0),"") | H77: =IF(HLOOKUP(H73,Summary!$I$2:$AM$7,4,0)=0,"",HLOOKUP(H73,Summary!$I$2:$AM$7,4,0)) | I77: =IFERROR(VLOOKUP(H77,fixed_expenses[],2,0),"") | J77: =IF(HLOOKUP(J73,Summary!$I$2:$AM$7,4,0)=0,"",HLOOKUP(J73,Summary!$I$2:$AM$7,4,0)) | K77: =IFERROR(VLOOKUP(J77,fixed_expenses[],2,0),"") | L77: =IF(HLOOKUP(L73,Summary!$I$2:$AM$7,4,0)=0,"",HLOOKUP(L73,Summary!$I$2:$AM$7,4,0)) | M77: =IFERROR(VLOOKUP(L77,fixed_expenses[],2,0),"") | N77: =IF(HLOOKUP(N73,Summary!$I$2:$AM$7,4,0)=0,"",HLOOKUP(N73,Summary!$I$2:$AM$7,4,0)) | O77: =IFERROR(VLOOKUP(N77,fixed_expenses[],2,0),"")
B78: =IF(HLOOKUP(B73,Summary!$I$2:$AM$7,5,0)=0,"",HLOOKUP(B73,Summary!$I$2:$AM$7,5,0)) | C78: =IFERROR(VLOOKUP(B78,fixed_expenses[],2,0),"") | D78: =IF(HLOOKUP(D73,Summary!$I$2:$AM$7,5,0)=0,"",HLOOKUP(D73,Summary!$I$2:$AM$7,5,0)) | E78: =IFERROR(VLOOKUP(D78,fixed_expenses[],2,0),"") | F78: =IF(HLOOKUP(F73,Summary!$I$2:$AM$7,5,0)=0,"",HLOOKUP(F73,Summary!$I$2:$AM$7,5,0)) | G78: =IFERROR(VLOOKUP(F78,fixed_expenses[],2,0),"") | H78: =IF(HLOOKUP(H73,Summary!$I$2:$AM$7,5,0)=0,"",HLOOKUP(H73,Summary!$I$2:$AM$7,5,0)) | I78: =IFERROR(VLOOKUP(H78,fixed_expenses[],2,0),"") | J78: =IF(HLOOKUP(J73,Summary!$I$2:$AM$7,5,0)=0,"",HLOOKUP(J73,Summary!$I$2:$AM$7,5,0)) | K78: =IFERROR(VLOOKUP(J78,fixed_expenses[],2,0),"") | L78: =IF(HLOOKUP(L73,Summary!$I$2:$AM$7,5,0)=0,"",HLOOKUP(L73,Summary!$I$2:$AM$7,5,0)) | M78: =IFERROR(VLOOKUP(L78,fixed_expenses[],2,0),"") | N78: =IF(HLOOKUP(N73,Summary!$I$2:$AM$7,5,0)=0,"",HLOOKUP(N73,Summary!$I$2:$AM$7,5,0)) | O78: =IFERROR(VLOOKUP(N78,fixed_expenses[],2,0),"")
B79: =IF(HLOOKUP(B73,Summary!$I$2:$AM$7,6,0)=0,"",HLOOKUP(B73,Summary!$I$2:$AM$7,6,0)) | C79: =IFERROR(VLOOKUP(B79,fixed_expenses[],2,0),"") | D79: =IF(HLOOKUP(D73,Summary!$I$2:$AM$7,6,0)=0,"",HLOOKUP(D73,Summary!$I$2:$AM$7,6,0)) | E79: =IFERROR(VLOOKUP(D79,fixed_expenses[],2,0),"") | F79: =IF(HLOOKUP(F73,Summary!$I$2:$AM$7,6,0)=0,"",HLOOKUP(F73,Summary!$I$2:$AM$7,6,0)) | G79: =IFERROR(VLOOKUP(F79,fixed_expenses[],2,0),"") | H79: =IF(HLOOKUP(H73,Summary!$I$2:$AM$7,6,0)=0,"",HLOOKUP(H73,Summary!$I$2:$AM$7,6,0)) | I79: =IFERROR(VLOOKUP(H79,fixed_expenses[],2,0),"") | J79: =IF(HLOOKUP(J73,Summary!$I$2:$AM$7,6,0)=0,"",HLOOKUP(J73,Summary!$I$2:$AM$7,6,0)) | K79: =IFERROR(VLOOKUP(J79,fixed_expenses[],2,0),"") | L79: =IF(HLOOKUP(L73,Summary!$I$2:$AM$7,6,0)=0,"",HLOOKUP(L73,Summary!$I$2:$AM$7,6,0)) | M79: =IFERROR(VLOOKUP(L79,fixed_expenses[],2,0),"") | N79: =IF(HLOOKUP(N73,Summary!$I$2:$AM$7,6,0)=0,"",HLOOKUP(N73,Summary!$I$2:$AM$7,6,0)) | O79: =IFERROR(VLOOKUP(N79,fixed_expenses[],2,0),"")
A80: Total is auto calculated for each day and week in cell at right, cells C80 through P80. Next instruction is in cell A82. | B80: TOTAL | C80: =SUM(C75:C79) -> 0 | E80: =SUM(E75:E79) -> 0 | G80: =SUM(G75:G79) -> 0 | I80: =SUM(I75:I79) -> 0 | K80: =SUM(K75:K79) -> 0 | M80: =SUM(M75:M79) -> 0 | O80: =SUM(O75:O79) -> 0 | P80: =SUM(C80,E80,G80,I80,K80,M80,O80) -> 0
A82: Calendar dates are in cells at right, cells B82 through O82. | B82: =N73+1 -> 14 | D82: =B82+1 -> 15 | F82: =D82+1 -> 16 | H82: =F82+1 -> 17 | J82: =H82+1 -> 18 | L82: =J82+1 -> 19 | N82: =L82+1 -> 20
A83: Description and Amount labels are in cells at right, cells B83 through O83. | B83: DESCRIPTION | C83: AMOUNT | D83: DESCRIPTION | E83: AMOUNT | F83: DESCRIPTION | G83: AMOUNT | H83: DESCRIPTION | I83: AMOUNT | J83: DESCRIPTION | K83: AMOUNT | L83: DESCRIPTION | M83: AMOUNT | N83: DESCRIPTION | O83: AMOUNT
A84: Enter Description and Amount of each expense in cells at right, cells B84 through O88. Next instruction is in cell A89. | B84: =IF(HLOOKUP(B82,Summary!$I$2:$AM$7,2,0)=0,"",HLOOKUP(B82,Summary!$I$2:$AM$7,2,0)) | C84: =IFERROR(VLOOKUP(B84,fixed_expenses[],2,0),"") | D84: =IF(HLOOKUP(D82,Summary!$I$2:$AM$7,2,0)=0,"",HLOOKUP(D82,Summary!$I$2:$AM$7,2,0)) -> Paul Phone Bill | E84: =IFERROR(VLOOKUP(D84,fixed_expenses[],2,0),"") -> 60 | F84: =IF(HLOOKUP(F82,Summary!$I$2:$AM$7,2,0)=0,"",HLOOKUP(F82,Summary!$I$2:$AM$7,2,0)) | G84: =IFERROR(VLOOKUP(F84,fixed_expenses[],2,0),"") | H84: =IF(HLOOKUP(H82,Summary!$I$2:$AM$7,2,0)=0,"",HLOOKUP(H82,Summary!$I$2:$AM$7,2,0)) | I84: =IFERROR(VLOOKUP(H84,fixed_expenses[],2,0),"") | J84: =IF(HLOOKUP(J82,Summary!$I$2:$AM$7,2,0)=0,"",HLOOKUP(J82,Summary!$I$2:$AM$7,2,0)) | K84: =IFERROR(VLOOKUP(J84,fixed_expenses[],2,0),"") | L84: Car | M84: =IFERROR(VLOOKUP(L84,fixed_expenses[],2,0),"") -> 232 | N84: =IF(HLOOKUP(N82,Summary!$I$2:$AM$7,2,0)=0,"",HLOOKUP(N82,Summary!$I$2:$AM$7,2,0)) -> Lynn Phone Bill | O84: =IFERROR(VLOOKUP(N84,fixed_expenses[],2,0),"")
B85: =IF(HLOOKUP(B82,Summary!$I$2:$AM$7,3,0)=0,"",HLOOKUP(B82,Summary!$I$2:$AM$7,3,0)) | C85: =IFERROR(VLOOKUP(B85,fixed_expenses[],2,0),"") | D85: =IF(HLOOKUP(D82,Summary!$I$2:$AM$7,3,0)=0,"",HLOOKUP(D82,Summary!$I$2:$AM$7,3,0)) -> Electric | E85: =IFERROR(VLOOKUP(D85,fixed_expenses[],2,0),"") -> 50 | F85: =IF(HLOOKUP(F82,Summary!$I$2:$AM$7,3,0)=0,"",HLOOKUP(F82,Summary!$I$2:$AM$7,3,0)) | G85: =IFERROR(VLOOKUP(F85,fixed_expenses[],2,0),"") | H85: =IF(HLOOKUP(H82,Summary!$I$2:$AM$7,3,0)=0,"",HLOOKUP(H82,Summary!$I$2:$AM$7,3,0)) | I85: =IFERROR(VLOOKUP(H85,fixed_expenses[],2,0),"") | J85: =IF(HLOOKUP(J82,Summary!$I$2:$AM$7,3,0)=0,"",HLOOKUP(J82,Summary!$I$2:$AM$7,3,0)) | K85: =IFERROR(VLOOKUP(J85,fixed_expenses[],2,0),"") | L85: =IF(HLOOKUP(L82,Summary!$I$2:$AM$7,3,0)=0,"",HLOOKUP(L82,Summary!$I$2:$AM$7,3,0)) | M85: =IFERROR(VLOOKUP(L85,fixed_expenses[],2,0),"") | N85: =IF(HLOOKUP(N82,Summary!$I$2:$AM$7,3,0)=0,"",HLOOKUP(N82,Summary!$I$2:$AM$7,3,0)) | O85: =IFERROR(VLOOKUP(N85,fixed_expenses[],2,0),"")
B86: =IF(HLOOKUP(B82,Summary!$I$2:$AM$7,4,0)=0,"",HLOOKUP(B82,Summary!$I$2:$AM$7,4,0)) | C86: =IFERROR(VLOOKUP(B86,fixed_expenses[],2,0),"") | D86: =IF(HLOOKUP(D82,Summary!$I$2:$AM$7,4,0)=0,"",HLOOKUP(D82,Summary!$I$2:$AM$7,4,0)) | E86: =IFERROR(VLOOKUP(D86,fixed_expenses[],2,0),"") | F86: =IF(HLOOKUP(F82,Summary!$I$2:$AM$7,4,0)=0,"",HLOOKUP(F82,Summary!$I$2:$AM$7,4,0)) | G86: =IFERROR(VLOOKUP(F86,fixed_expenses[],2,0),"") | H86: =IF(HLOOKUP(H82,Summary!$I$2:$AM$7,4,0)=0,"",HLOOKUP(H82,Summary!$I$2:$AM$7,4,0)) | I86: =IFERROR(VLOOKUP(H86,fixed_expenses[],2,0),"") | J86: =IF(HLOOKUP(J82,Summary!$I$2:$AM$7,4,0)=0,"",HLOOKUP(J82,Summary!$I$2:$AM$7,4,0)) | K86: =IFERROR(VLOOKUP(J86,fixed_expenses[],2,0),"") | L86: =IF(HLOOKUP(L82,Summary!$I$2:$AM$7,4,0)=0,"",HLOOKUP(L82,Summary!$I$2:$AM$7,4,0)) | M86: =IFERROR(VLOOKUP(L86,fixed_expenses[],2,0),"") | N86: =IF(HLOOKUP(N82,Summary!$I$2:$AM$7,4,0)=0,"",HLOOKUP(N82,Summary!$I$2:$AM$7,4,0)) | O86: =IFERROR(VLOOKUP(N86,fixed_expenses[],2,0),"")
B87: =IF(HLOOKUP(B82,Summary!$I$2:$AM$7,5,0)=0,"",HLOOKUP(B82,Summary!$I$2:$AM$7,5,0)) | C87: =IFERROR(VLOOKUP(B87,fixed_expenses[],2,0),"") | D87: =IF(HLOOKUP(D82,Summary!$I$2:$AM$7,5,0)=0,"",HLOOKUP(D82,Summary!$I$2:$AM$7,5,0)) | E87: =IFERROR(VLOOKUP(D87,fixed_expenses[],2,0),"") | F87: =IF(HLOOKUP(F82,Summary!$I$2:$AM$7,5,0)=0,"",HLOOKUP(F82,Summary!$I$2:$AM$7,5,0)) | G87: =IFERROR(VLOOKUP(F87,fixed_expenses[],2,0),"") | H87: =IF(HLOOKUP(H82,Summary!$I$2:$AM$7,5,0)=0,"",HLOOKUP(H82,Summary!$I$2:$AM$7,5,0)) | I87: =IFERROR(VLOOKUP(H87,fixed_expenses[],2,0),"") | J87: =IF(HLOOKUP(J82,Summary!$I$2:$AM$7,5,0)=0,"",HLOOKUP(J82,Summary!$I$2:$AM$7,5,0)) | K87: =IFERROR(VLOOKUP(J87,fixed_expenses[],2,0),"") | L87: =IF(HLOOKUP(L82,Summary!$I$2:$AM$7,5,0)=0,"",HLOOKUP(L82,Summary!$I$2:$AM$7,5,0)) | M87: =IFERROR(VLOOKUP(L87,fixed_expenses[],2,0),"") | N87: =IF(HLOOKUP(N82,Summary!$I$2:$AM$7,5,0)=0,"",HLOOKUP(N82,Summary!$I$2:$AM$7,5,0)) | O87: =IFERROR(VLOOKUP(N87,fixed_expenses[],2,0),"")
B88: =IF(HLOOKUP(B82,Summary!$I$2:$AM$7,6,0)=0,"",HLOOKUP(B82,Summary!$I$2:$AM$7,6,0)) | C88: =IFERROR(VLOOKUP(B88,fixed_expenses[],2,0),"") | D88: =IF(HLOOKUP(D82,Summary!$I$2:$AM$7,6,0)=0,"",HLOOKUP(D82,Summary!$I$2:$AM$7,6,0)) | E88: =IFERROR(VLOOKUP(D88,fixed_expenses[],2,0),"") | F88: =IF(HLOOKUP(F82,Summary!$I$2:$AM$7,6,0)=0,"",HLOOKUP(F82,Summary!$I$2:$AM$7,6,0)) | G88: =IFERROR(VLOOKUP(F88,fixed_expenses[],2,0),"") | H88: =IF(HLOOKUP(H82,Summary!$I$2:$AM$7,6,0)=0,"",HLOOKUP(H82,Summary!$I$2:$AM$7,6,0)) | I88: =IFERROR(VLOOKUP(H88,fixed_expenses[],2,0),"") | J88: =IF(HLOOKUP(J82,Summary!$I$2:$AM$7,6,0)=0,"",HLOOKUP(J82,Summary!$I$2:$AM$7,6,0)) | K88: =IFERROR(VLOOKUP(J88,fixed_expenses[],2,0),"") | L88: =IF(HLOOKUP(L82,Summary!$I$2:$AM$7,6,0)=0,"",HLOOKUP(L82,Summary!$I$2:$AM$7,6,0)) | M88: =IFERROR(VLOOKUP(L88,fixed_expenses[],2,0),"") | N88: =IF(HLOOKUP(N82,Summary!$I$2:$AM$7,6,0)=0,"",HLOOKUP(N82,Summary!$I$2:$AM$7,6,0)) | O88: =IFERROR(VLOOKUP(N88,fixed_expenses[],2,0),"")
A89: Total is auto calculated for each day and week in cell at right, cells C89 through P89. Next instruction is in cell A91. | B89: TOTAL | C89: =SUM(C84:C88) -> 0 | E89: =SUM(E84:E88) -> 110 | G89: =SUM(G84:G88) -> 0 | I89: =SUM(I84:I88) -> 0 | K89: =SUM(K84:K88) -> 0 | M89: =SUM(M84:M88) -> 232 | O89: =SUM(O84:O88) -> 0 | P89: =SUM(C89,E89,G89,I89,K89,M89,O89) -> 342
A91: Calendar dates are in cells at right, cells B91 through O91. | B91: =N82+1 -> 21 | D91: =B91+1 -> 22 | F91: =D91+1 -> 23 | H91: =F91+1 -> 24 | J91: =H91+1 -> 25 | L91: =J91+1 -> 26 | N91: =L91+1 -> 27
A92: Description and Amount labels are in cells at right, cells B92 through O92. | B92: DESCRIPTION | C92: AMOUNT | D92: DESCRIPTION | E92: AMOUNT | F92: DESCRIPTION | G92: AMOUNT | H92: DESCRIPTION | I92: AMOUNT | J92: DESCRIPTION | K92: AMOUNT | L92: DESCRIPTION | M92: AMOUNT | N92: DESCRIPTION | O92: AMOUNT
A93: Enter Description and Amount of each expense in cells at right, cells B93 through O97. Next instruction is in cell A98. | B93: =IF(HLOOKUP(B91,Summary!$I$2:$AM$7,2,0)=0,"",HLOOKUP(B91,Summary!$I$2:$AM$7,2,0)) | C93: =IFERROR(VLOOKUP(B93,fixed_expenses[],2,0),"") | D93: =IF(HLOOKUP(D91,Summary!$I$2:$AM$7,2,0)=0,"",HLOOKUP(D91,Summary!$I$2:$AM$7,2,0)) | E93: =IFERROR(VLOOKUP(D93,fixed_expenses[],2,0),"") | F93: =IF(HLOOKUP(F91,Summary!$I$2:$AM$7,2,0)=0,"",HLOOKUP(F91,Summary!$I$2:$AM$7,2,0)) | G93: =IFERROR(VLOOKUP(F93,fixed_expenses[],2,0),"") | H93: =IF(HLOOKUP(H91,Summary!$I$2:$AM$7,2,0)=0,"",HLOOKUP(H91,Summary!$I$2:$AM$7,2,0)) | I93: =IFERROR(VLOOKUP(H93,fixed_expenses[],2,0),"") | J93: =IF(HLOOKUP(J91,Summary!$I$2:$AM$7,2,0)=0,"",HLOOKUP(J91,Summary!$I$2:$AM$7,2,0)) | K93: =IFERROR(VLOOKUP(J93,fixed_expenses[],2,0),"") | L93: =IF(HLOOKUP(L91,Summary!$I$2:$AM$7,2,0)=0,"",HLOOKUP(L91,Summary!$I$2:$AM$7,2,0)) | M93: =IFERROR(VLOOKUP(L93,fixed_expenses[],2,0),"") | N93: =IF(HLOOKUP(N91,Summary!$I$2:$AM$7,2,0)=0,"",HLOOKUP(N91,Summary!$I$2:$AM$7,2,0)) | O93: =IFERROR(VLOOKUP(N93,fixed_expenses[],2,0),"")
B94: =IF(HLOOKUP(B91,Summary!$I$2:$AM$7,3,0)=0,"",HLOOKUP(B91,Summary!$I$2:$AM$7,3,0)) | C94: =IFERROR(VLOOKUP(B94,fixed_expenses[],2,0),"") | D94: =IF(HLOOKUP(D91,Summary!$I$2:$AM$7,3,0)=0,"",HLOOKUP(D91,Summary!$I$2:$AM$7,3,0)) | E94: =IFERROR(VLOOKUP(D94,fixed_expenses[],2,0),"") | F94: =IF(HLOOKUP(F91,Summary!$I$2:$AM$7,3,0)=0,"",HLOOKUP(F91,Summary!$I$2:$AM$7,3,0)) | G94: =IFERROR(VLOOKUP(F94,fixed_expenses[],2,0),"") | H94: =IF(HLOOKUP(H91,Summary!$I$2:$AM$7,3,0)=0,"",HLOOKUP(H91,Summary!$I$2:$AM$7,3,0)) | I94: =IFERROR(VLOOKUP(H94,fixed_expenses[],2,0),"") | J94: =IF(HLOOKUP(J91,Summary!$I$2:$AM$7,3,0)=0,"",HLOOKUP(J91,Summary!$I$2:$AM$7,3,0)) | K94: =IFERROR(VLOOKUP(J94,fixed_expenses[],2,0),"") | L94: =IF(HLOOKUP(L91,Summary!$I$2:$AM$7,3,0)=0,"",HLOOKUP(L91,Summary!$I$2:$AM$7,3,0)) | M94: =IFERROR(VLOOKUP(L94,fixed_expenses[],2,0),"") | N94: =IF(HLOOKUP(N91,Summary!$I$2:$AM$7,3,0)=0,"",HLOOKUP(N91,Summary!$I$2:$AM$7,3,0)) | O94: =IFERROR(VLOOKUP(N94,fixed_expenses[],2,0),"")
B95: =IF(HLOOKUP(B91,Summary!$I$2:$AM$7,4,0)=0,"",HLOOKUP(B91,Summary!$I$2:$AM$7,4,0)) | C95: =IFERROR(VLOOKUP(B95,fixed_expenses[],2,0),"") | D95: =IF(HLOOKUP(D91,Summary!$I$2:$AM$7,4,0)=0,"",HLOOKUP(D91,Summary!$I$2:$AM$7,4,0)) | E95: =IFERROR(VLOOKUP(D95,fixed_expenses[],2,0),"") | F95: =IF(HLOOKUP(F91,Summary!$I$2:$AM$7,4,0)=0,"",HLOOKUP(F91,Summary!$I$2:$AM$7,4,0)) | G95: =IFERROR(VLOOKUP(F95,fixed_expenses[],2,0),"") | H95: =IF(HLOOKUP(H91,Summary!$I$2:$AM$7,4,0)=0,"",HLOOKUP(H91,Summary!$I$2:$AM$7,4,0)) | I95: =IFERROR(VLOOKUP(H95,fixed_expenses[],2,0),"") | J95: =IF(HLOOKUP(J91,Summary!$I$2:$AM$7,4,0)=0,"",HLOOKUP(J91,Summary!$I$2:$AM$7,4,0)) | K95: =IFERROR(VLOOKUP(J95,fixed_expenses[],2,0),"") | L95: =IF(HLOOKUP(L91,Summary!$I$2:$AM$7,4,0)=0,"",HLOOKUP(L91,Summary!$I$2:$AM$7,4,0)) | M95: =IFERROR(VLOOKUP(L95,fixed_expenses[],2,0),"") | N95: =IF(HLOOKUP(N91,Summary!$I$2:$AM$7,4,0)=0,"",HLOOKUP(N91,Summary!$I$2:$AM$7,4,0)) | O95: =IFERROR(VLOOKUP(N95,fixed_expenses[],2,0),"")
B96: =IF(HLOOKUP(B91,Summary!$I$2:$AM$7,5,0)=0,"",HLOOKUP(B91,Summary!$I$2:$AM$7,5,0)) | C96: =IFERROR(VLOOKUP(B96,fixed_expenses[],2,0),"") | D96: =IF(HLOOKUP(D91,Summary!$I$2:$AM$7,5,0)=0,"",HLOOKUP(D91,Summary!$I$2:$AM$7,5,0)) | E96: =IFERROR(VLOOKUP(D96,fixed_expenses[],2,0),"") | F96: =IF(HLOOKUP(F91,Summary!$I$2:$AM$7,5,0)=0,"",HLOOKUP(F91,Summary!$I$2:$AM$7,5,0)) | G96: =IFERROR(VLOOKUP(F96,fixed_expenses[],2,0),"") | H96: =IF(HLOOKUP(H91,Summary!$I$2:$AM$7,5,0)=0,"",HLOOKUP(H91,Summary!$I$2:$AM$7,5,0)) | I96: =IFERROR(VLOOKUP(H96,fixed_expenses[],2,0),"") | J96: =IF(HLOOKUP(J91,Summary!$I$2:$AM$7,5,0)=0,"",HLOOKUP(J91,Summary!$I$2:$AM$7,5,0)) | K96: =IFERROR(VLOOKUP(J96,fixed_expenses[],2,0),"") | L96: =IF(HLOOKUP(L91,Summary!$I$2:$AM$7,5,0)=0,"",HLOOKUP(L91,Summary!$I$2:$AM$7,5,0)) | M96: =IFERROR(VLOOKUP(L96,fixed_expenses[],2,0),"") | N96: =IF(HLOOKUP(N91,Summary!$I$2:$AM$7,5,0)=0,"",HLOOKUP(N91,Summary!$I$2:$AM$7,5,0)) | O96: =IFERROR(VLOOKUP(N96,fixed_expenses[],2,0),"")
B97: =IF(HLOOKUP(B91,Summary!$I$2:$AM$7,6,0)=0,"",HLOOKUP(B91,Summary!$I$2:$AM$7,6,0)) | C97: =IFERROR(VLOOKUP(B97,fixed_expenses[],2,0),"") | D97: =IF(HLOOKUP(D91,Summary!$I$2:$AM$7,6,0)=0,"",HLOOKUP(D91,Summary!$I$2:$AM$7,6,0)) | E97: =IFERROR(VLOOKUP(D97,fixed_expenses[],2,0),"") | F97: =IF(HLOOKUP(F91,Summary!$I$2:$AM$7,6,0)=0,"",HLOOKUP(F91,Summary!$I$2:$AM$7,6,0)) | G97: =IFERROR(VLOOKUP(F97,fixed_expenses[],2,0),"") | H97: =IF(HLOOKUP(H91,Summary!$I$2:$AM$7,6,0)=0,"",HLOOKUP(H91,Summary!$I$2:$AM$7,6,0)) | I97: =IFERROR(VLOOKUP(H97,fixed_expenses[],2,0),"") | J97: =IF(HLOOKUP(J91,Summary!$I$2:$AM$7,6,0)=0,"",HLOOKUP(J91,Summary!$I$2:$AM$7,6,0)) | K97: =IFERROR(VLOOKUP(J97,fixed_expenses[],2,0),"") | L97: =IF(HLOOKUP(L91,Summary!$I$2:$AM$7,6,0)=0,"",HLOOKUP(L91,Summary!$I$2:$AM$7,6,0)) | M97: =IFERROR(VLOOKUP(L97,fixed_expenses[],2,0),"") | N97: =IF(HLOOKUP(N91,Summary!$I$2:$AM$7,6,0)=0,"",HLOOKUP(N91,Summary!$I$2:$AM$7,6,0)) | O97: =IFERROR(VLOOKUP(N97,fixed_expenses[],2,0),"")
A98: Total is auto calculated for each day and week in cell at right, cells C98 through P98. Next instruction is in cell A100. | B98: TOTAL | C98: =SUM(C93:C97) -> 0 | E98: =SUM(E93:E97) -> 0 | G98: =SUM(G93:G97) -> 0 | I98: =SUM(I93:I97) -> 0 | K98: =SUM(K93:K97) -> 0 | M98: =SUM(M93:M97) -> 0 | O98: =SUM(O93:O97) -> 0 | P98: =SUM(C98,E98,G98,I98,K98,M98,O98) -> 0
A100: Calendar dates are in cells at right, cells B100 through O100. | B100: =DAY(IF(DAY(FebSun1)=1,FebSun1+22,FebSun1+29)) -> 28 | D100: =DAY(IF(DAY(FebSun1)=1,FebSun1+23,FebSun1+30)) -> 1 | F100: =DAY(IF(DAY(FebSun1)=1,FebSun1+24,FebSun1+31)) -> 2 | H100: =DAY(IF(DAY(FebSun1)=1,FebSun1+25,FebSun1+32)) -> 3 | J100: =DAY(IF(DAY(FebSun1)=1,FebSun1+26,FebSun1+33)) -> 4 | L100: =DAY(IF(DAY(FebSun1)=1,FebSun1+27,FebSun1+34)) -> 5 | N100: =DAY(IF(DAY(FebSun1)=1,FebSun1+28,FebSun1+35)) -> 6
A101: Description and Amount labels are in cells at right, cells B101 through O101. | B101: DESCRIPTION | C101: AMOUNT | D101: DESCRIPTION | E101: AMOUNT | F101: DESCRIPTION | G101: AMOUNT | H101: DESCRIPTION | I101: AMOUNT | J101: DESCRIPTION | K101: AMOUNT | L101: DESCRIPTION | M101: AMOUNT | N101: DESCRIPTION | O101: AMOUNT
A102: Enter Description and Amount of each expense in cells at right, cells B102 through O106. Next instruction is in cell A107. | B102: =IF(HLOOKUP(B100,Summary!$I$2:$AM$7,2,0)=0,"",HLOOKUP(B100,Summary!$I$2:$AM$7,2,0)) | C102: =IFERROR(VLOOKUP(B102,fixed_expenses[],2,0),"") | D102: =IF(HLOOKUP(D100,Summary!$I$2:$AM$7,2,0)=0,"",HLOOKUP(D100,Summary!$I$2:$AM$7,2,0)) | E102: =IFERROR(VLOOKUP(D102,fixed_expenses[],2,0),"") | F102: =IF(HLOOKUP(F100,Summary!$I$2:$AM$7,2,0)=0,"",HLOOKUP(F100,Summary!$I$2:$AM$7,2,0)) | G102: =IFERROR(VLOOKUP(F102,fixed_expenses[],2,0),"") | H102: =IF(HLOOKUP(H100,Summary!$I$2:$AM$7,2,0)=0,"",HLOOKUP(H100,Summary!$I$2:$AM$7,2,0)) -> Rent | I102: =IFERROR(VLOOKUP(H102,fixed_expenses[],2,0),"") -> 1200 | J102: =IF(HLOOKUP(J100,Summary!$I$2:$AM$7,2,0)=0,"",HLOOKUP(J100,Summary!$I$2:$AM$7,2,0)) | K102: =IFERROR(VLOOKUP(J102,fixed_expenses[],2,0),"") | L102: =IF(HLOOKUP(L100,Summary!$I$2:$AM$7,2,0)=0,"",HLOOKUP(L100,Summary!$I$2:$AM$7,2,0)) | M102: =IFERROR(VLOOKUP(L102,fixed_expenses[],2,0),"") | N102: =IF(HLOOKUP(N100,Summary!$I$2:$AM$7,2,0)=0,"",HLOOKUP(N100,Summary!$I$2:$AM$7,2,0)) | O102: =IFERROR(VLOOKUP(N102,fixed_expenses[],2,0),"")
B103: =IF(HLOOKUP(B100,Summary!$I$2:$AM$7,3,0)=0,"",HLOOKUP(B100,Summary!$I$2:$AM$7,3,0)) | C103: =IFERROR(VLOOKUP(B103,fixed_expenses[],2,0),"") | D103: =IF(HLOOKUP(D100,Summary!$I$2:$AM$7,3,0)=0,"",HLOOKUP(D100,Summary!$I$2:$AM$7,3,0)) | E103: =IFERROR(VLOOKUP(D103,fixed_expenses[],2,0),"") | F103: =IF(HLOOKUP(F100,Summary!$I$2:$AM$7,3,0)=0,"",HLOOKUP(F100,Summary!$I$2:$AM$7,3,0)) | G103: =IFERROR(VLOOKUP(F103,fixed_expenses[],2,0),"") | H103: =IF(HLOOKUP(H100,Summary!$I$2:$AM$7,3,0)=0,"",HLOOKUP(H100,Summary!$I$2:$AM$7,3,0)) | I103: =IFERROR(VLOOKUP(H103,fixed_expenses[],2,0),"") | J103: =IF(HLOOKUP(J100,Summary!$I$2:$AM$7,3,0)=0,"",HLOOKUP(J100,Summary!$I$2:$AM$7,3,0)) | K103: =IFERROR(VLOOKUP(J103,fixed_expenses[],2,0),"") | L103: =IF(HLOOKUP(L100,Summary!$I$2:$AM$7,3,0)=0,"",HLOOKUP(L100,Summary!$I$2:$AM$7,3,0)) | M103: =IFERROR(VLOOKUP(L103,fixed_expenses[],2,0),"") | N103: =IF(HLOOKUP(N100,Summary!$I$2:$AM$7,3,0)=0,"",HLOOKUP(N100,Summary!$I$2:$AM$7,3,0)) | O103: =IFERROR(VLOOKUP(N103,fixed_expenses[],2,0),"")
B104: =IF(HLOOKUP(B100,Summary!$I$2:$AM$7,4,0)=0,"",HLOOKUP(B100,Summary!$I$2:$AM$7,4,0)) | C104: =IFERROR(VLOOKUP(B104,fixed_expenses[],2,0),"") | D104: =IF(HLOOKUP(D100,Summary!$I$2:$AM$7,4,0)=0,"",HLOOKUP(D100,Summary!$I$2:$AM$7,4,0)) | E104: =IFERROR(VLOOKUP(D104,fixed_expenses[],2,0),"") | F104: =IF(HLOOKUP(F100,Summary!$I$2:$AM$7,4,0)=0,"",HLOOKUP(F100,Summary!$I$2:$AM$7,4,0)) | G104: =IFERROR(VLOOKUP(F104,fixed_expenses[],2,0),"") | H104: =IF(HLOOKUP(H100,Summary!$I$2:$AM$7,4,0)=0,"",HLOOKUP(H100,Summary!$I$2:$AM$7,4,0)) | I104: =IFERROR(VLOOKUP(H104,fixed_expenses[],2,0),"") | J104: =IF(HLOOKUP(J100,Summary!$I$2:$AM$7,4,0)=0,"",HLOOKUP(J100,Summary!$I$2:$AM$7,4,0)) | K104: =IFERROR(VLOOKUP(J104,fixed_expenses[],2,0),"") | L104: =IF(HLOOKUP(L100,Summary!$I$2:$AM$7,4,0)=0,"",HLOOKUP(L100,Summary!$I$2:$AM$7,4,0)) | M104: =IFERROR(VLOOKUP(L104,fixed_expenses[],2,0),"") | N104: =IF(HLOOKUP(N100,Summary!$I$2:$AM$7,4,0)=0,"",HLOOKUP(N100,Summary!$I$2:$AM$7,4,0)) | O104: =IFERROR(VLOOKUP(N104,fixed_expenses[],2,0),"")
B105: =IF(HLOOKUP(B100,Summary!$I$2:$AM$7,5,0)=0,"",HLOOKUP(B100,Summary!$I$2:$AM$7,5,0)) | C105: =IFERROR(VLOOKUP(B105,fixed_expenses[],2,0),"") | D105: =IF(HLOOKUP(D100,Summary!$I$2:$AM$7,5,0)=0,"",HLOOKUP(D100,Summary!$I$2:$AM$7,5,0)) | E105: =IFERROR(VLOOKUP(D105,fixed_expenses[],2,0),"") | F105: =IF(HLOOKUP(F100,Summary!$I$2:$AM$7,5,0)=0,"",HLOOKUP(F100,Summary!$I$2:$AM$7,5,0)) | G105: =IFERROR(VLOOKUP(F105,fixed_expenses[],2,0),"") | H105: =IF(HLOOKUP(H100,Summary!$I$2:$AM$7,5,0)=0,"",HLOOKUP(H100,Summary!$I$2:$AM$7,5,0)) | I105: =IFERROR(VLOOKUP(H105,fixed_expenses[],2,0),"") | J105: =IF(HLOOKUP(J100,Summary!$I$2:$AM$7,5,0)=0,"",HLOOKUP(J100,Summary!$I$2:$AM$7,5,0)) | K105: =IFERROR(VLOOKUP(J105,fixed_expenses[],2,0),"") | L105: =IF(HLOOKUP(L100,Summary!$I$2:$AM$7,5,0)=0,"",HLOOKUP(L100,Summary!$I$2:$AM$7,5,0)) | M105: =IFERROR(VLOOKUP(L105,fixed_expenses[],2,0),"") | N105: =IF(HLOOKUP(N100,Summary!$I$2:$AM$7,5,0)=0,"",HLOOKUP(N100,Summary!$I$2:$AM$7,5,0)) | O105: =IFERROR(VLOOKUP(N105,fixed_expenses[],2,0),"")
B106: =IF(HLOOKUP(B100,Summary!$I$2:$AM$7,6,0)=0,"",HLOOKUP(B100,Summary!$I$2:$AM$7,6,0)) | C106: =IFERROR(VLOOKUP(B106,fixed_expenses[],2,0),"") | D106: =IF(HLOOKUP(D100,Summary!$I$2:$AM$7,6,0)=0,"",HLOOKUP(D100,Summary!$I$2:$AM$7,6,0)) | E106: =IFERROR(VLOOKUP(D106,fixed_expenses[],2,0),"") | F106: =IF(HLOOKUP(F100,Summary!$I$2:$AM$7,6,0)=0,"",HLOOKUP(F100,Summary!$I$2:$AM$7,6,0)) | G106: =IFERROR(VLOOKUP(F106,fixed_expenses[],2,0),"") | H106: =IF(HLOOKUP(H100,Summary!$I$2:$AM$7,6,0)=0,"",HLOOKUP(H100,Summary!$I$2:$AM$7,6,0)) | I106: =IFERROR(VLOOKUP(H106,fixed_expenses[],2,0),"") | J106: =IF(HLOOKUP(J100,Summary!$I$2:$AM$7,6,0)=0,"",HLOOKUP(J100,Summary!$I$2:$AM$7,6,0)) | K106: =IFERROR(VLOOKUP(J106,fixed_expenses[],2,0),"") | L106: =IF(HLOOKUP(L100,Summary!$I$2:$AM$7,6,0)=0,"",HLOOKUP(L100,Summary!$I$2:$AM$7,6,0)) | M106: =IFERROR(VLOOKUP(L106,fixed_expenses[],2,0),"") | N106: =IF(HLOOKUP(N100,Summary!$I$2:$AM$7,6,0)=0,"",HLOOKUP(N100,Summary!$I$2:$AM$7,6,0)) | O106: =IFERROR(VLOOKUP(N106,fixed_expenses[],2,0),"")
A107: Total is auto calculated for each day and week in cell at right, cells C107 through P107. Next instruction is in cell A109. | B107: TOTAL | C107: =SUM(C102:C106) -> 0 | E107: =SUM(E102:E106) -> 0 | G107: =SUM(G102:G106) -> 0 | I107: =SUM(I102:I106) -> 1200 | K107: =SUM(K102:K106) -> 0 | M107: =SUM(M102:M106) -> 0 | O107: =SUM(O102:O106) -> 0 | P107: =SUMIF(B100:N100,">="&15,C107:O107) -> 0
A109: Calendar dates are in cells at right, cells B109 through O109. | B109: =DAY(IF(DAY(FebSun1)=1,FebSun1+29,FebSun1+36)) -> 7 | D109: =DAY(IF(DAY(FebSun1)=1,FebSun1+30,FebSun1+37)) -> 8 | F109: =DAY(IF(DAY(FebSun1)=1,FebSun1+31,FebSun1+38)) -> 9 | H109: =DAY(IF(DAY(FebSun1)=1,FebSun1+32,FebSun1+39)) -> 10 | J109: =DAY(IF(DAY(FebSun1)=1,FebSun1+33,FebSun1+40)) -> 11 | L109: =DAY(IF(DAY(FebSun1)=1,FebSun1+34,FebSun1+41)) -> 12 | N109: =DAY(IF(DAY(FebSun1)=1,FebSun1+35,FebSun1+42)) -> 13
A110: Description and Amount labels are in cells at right, cells B110 through O110. | B110: DESCRIPTION | C110: AMOUNT | D110: DESCRIPTION | E110: AMOUNT | F110: DESCRIPTION | G110: AMOUNT | H110: DESCRIPTION | I110: AMOUNT | J110: DESCRIPTION | K110: AMOUNT | L110: DESCRIPTION | M110: AMOUNT | N110: DESCRIPTION | O110: AMOUNT
A111: Enter Description and Amount of each expense in cells at right, cells B111 through O115. Next instruction is in cell A116. | B111: =IF(HLOOKUP(B109,Summary!$I$2:$AM$7,2,0)=0,"",HLOOKUP(B109,Summary!$I$2:$AM$7,2,0)) | C111: =IFERROR(VLOOKUP(B111,fixed_expenses[],2,0),"") | D111: =IF(HLOOKUP(D109,Summary!$I$2:$AM$7,2,0)=0,"",HLOOKUP(D109,Summary!$I$2:$AM$7,2,0)) | E111: =IFERROR(VLOOKUP(D111,fixed_expenses[],2,0),"") | F111: =IF(HLOOKUP(F109,Summary!$I$2:$AM$7,2,0)=0,"",HLOOKUP(F109,Summary!$I$2:$AM$7,2,0)) | G111: =IFERROR(VLOOKUP(F111,fixed_expenses[],2,0),"") | H111: =IF(HLOOKUP(H109,Summary!$I$2:$AM$7,2,0)=0,"",HLOOKUP(H109,Summary!$I$2:$AM$7,2,0)) | I111: =IFERROR(VLOOKUP(H111,fixed_expenses[],2,0),"") | J111: =IF(HLOOKUP(J109,Summary!$I$2:$AM$7,2,0)=0,"",HLOOKUP(J109,Summary!$I$2:$AM$7,2,0)) | K111: =IFERROR(VLOOKUP(J111,fixed_expenses[],2,0),"") | L111: =IF(HLOOKUP(L109,Summary!$I$2:$AM$7,2,0)=0,"",HLOOKUP(L109,Summary!$I$2:$AM$7,2,0)) | M111: =IFERROR(VLOOKUP(L111,fixed_expenses[],2,0),"") | N111: =IF(HLOOKUP(N109,Summary!$I$2:$AM$7,2,0)=0,"",HLOOKUP(N109,Summary!$I$2:$AM$7,2,0)) | O111: =IFERROR(VLOOKUP(N111,fixed_expenses[],2,0),"")
...

Sheet Income Calendar
B1: =YEAR(TODAY()) -> 2021 | C1: EXPENSE CALENDAR
A2: January label is in cell at right, Monthly Total label in cell L2, Grand Total label in N2, and Tip in G2. | B2: JANUARY | G2: TIP: Change the year in cell B1 to update the calendar year. | L2: MONTHLY TOTAL | N2: GRAND TOTAL
A3: Monthly Total is auto calculated in cell L3 and Grand Total in N3. | F3: =IFERROR(WEEKDAY(DATEVALUE(B2&" 1, "&Year1)),"") -> 6 | L3: =SUM(P13,P22,P31,P40,P49,P58) -> 4770 | N3: =SUM(P:P) -> 62420
A4: January calendar is in cells B5 through O58. | B4: 1 | D4: 2 | F4: 3 | H4: 4 | J4: 5 | L4: 6 | N4: 7
A5: Weekdays are in cells at right, cells B5 through N5, and Weekly Total label in cell P5. | B5: SUNDAY | D5: MONDAY | E5: =IF(WEEKDAY(DATEVALUE(Month1&" 1, "&Year1))=COLUMN(#REF!),1,IF(LEN(C5)>0,C5+1,"")) -> #VALUE! | F5: TUESDAY | G5: =IF(WEEKDAY(DATEVALUE(Month1&" 1, "&Year1))=COLUMN(#REF!),1,IF(LEN(E5)>0,E5+1,"")) -> #VALUE! | H5: WEDNESDAY | I5: =IF(WEEKDAY(DATEVALUE(Month1&" 1, "&Year1))=COLUMN(#REF!),1,IF(LEN(G5)>0,G5+1,"")) -> #VALUE! | J5: THURSDAY | K5: =IF(WEEKDAY(DATEVALUE(Month1&" 1, "&Year1))=COLUMN(#REF!),1,IF(LEN(I5)>0,I5+1,"")) -> #VALUE! | L5: FRIDAY | M5: =IF(WEEKDAY(DATEVALUE(Month1&" 1, "&Year1))=COLUMN(#REF!),1,IF(LEN(K5)>0,K5+1,"")) -> #VALUE! | N5: SATURDAY | O5: =IF(WEEKDAY(DATEVALUE(Month1&" 1, "&Year1))=COLUMN(#REF!),1,IF(LEN(M5)>0,M5+1,"")) -> #VALUE! | P5: WEEKLY TOTAL | T5: Description | U5: Amount
A6: Calendar dates are in cells at right, cells B6 through O6. If it doesn’t start with number 1, then it is date of previous month. | B6: =DAY(IF(DAY(JanSun1)=1,JanSun1-6,JanSun1+1)) -> 27 | D6: =DAY(IF(DAY(JanSun1)=1,JanSun1-5,JanSun1+2)) -> 28 | F6: =DAY(IF(DAY(JanSun1)=1,JanSun1-4,JanSun1+3)) -> 29 | H6: =DAY(IF(DAY(JanSun1)=1,JanSun1-3,JanSun1+4)) -> 30 | J6: =DAY(IF(DAY(JanSun1)=1,JanSun1-2,JanSun1+5)) -> 31 | L6: =DAY(IF(DAY(JanSun1)=1,JanSun1-1,JanSun1+6)) -> 1 | N6: =DAY(IF(DAY(JanSun1)=1,JanSun1,JanSun1+7)) -> 2 | T6: Paul Income | U6: 800
A7: Description and Amount labels are in cells at right, cells B7 through O7. | B7: DESCRIPTION | C7: AMOUNT | D7: DESCRIPTION | E7: AMOUNT | F7: DESCRIPTION | G7: AMOUNT | H7: DESCRIPTION | I7: AMOUNT | J7: DESCRIPTION | K7: AMOUNT | L7: DESCRIPTION | M7: AMOUNT | N7: DESCRIPTION | O7: AMOUNT | T7: Lynn Income | U7: 770
A8: Enter Description and Amount of each expense in cells at right, cells B8 through O12. Next instruction is in cell A13. | C8: =IFERROR(VLOOKUP(B8,fixed_expenses4[],2,0),"") | E8: =IFERROR(VLOOKUP(D8,fixed_expenses4[],2,0),"") | G8: =IFERROR(VLOOKUP(F8,fixed_expenses4[],2,0),"") | I8: =IFERROR(VLOOKUP(H8,fixed_expenses4[],2,0),"") | K8: =IFERROR(VLOOKUP(J8,fixed_expenses4[],2,0),"") | L8: Paul Income | M8: =IFERROR(VLOOKUP(L8,fixed_expenses4[],2,0),"") -> 800 | O8: =IFERROR(VLOOKUP(N8,fixed_expenses4[],2,0),"")
C9: =IFERROR(VLOOKUP(B9,fixed_expenses4[],2,0),"") | E9: =IFERROR(VLOOKUP(D9,fixed_expenses4[],2,0),"") | G9: =IFERROR(VLOOKUP(F9,fixed_expenses4[],2,0),"") | I9: =IFERROR(VLOOKUP(H9,fixed_expenses4[],2,0),"") | K9: =IFERROR(VLOOKUP(J9,fixed_expenses4[],2,0),"") | M9: =IFERROR(VLOOKUP(L9,fixed_expenses4[],2,0),"") | O9: =IFERROR(VLOOKUP(N9,fixed_expenses4[],2,0),"")
C10: =IFERROR(VLOOKUP(B10,fixed_expenses4[],2,0),"") | E10: =IFERROR(VLOOKUP(D10,fixed_expenses4[],2,0),"") | G10: =IFERROR(VLOOKUP(F10,fixed_expenses4[],2,0),"") | I10: =IFERROR(VLOOKUP(H10,fixed_expenses4[],2,0),"") | K10: =IFERROR(VLOOKUP(J10,fixed_expenses4[],2,0),"") | M10: =IFERROR(VLOOKUP(L10,fixed_expenses4[],2,0),"") | O10: =IFERROR(VLOOKUP(N10,fixed_expenses4[],2,0),"")
C11: =IFERROR(VLOOKUP(B11,fixed_expenses4[],2,0),"") | E11: =IFERROR(VLOOKUP(D11,fixed_expenses4[],2,0),"") | G11: =IFERROR(VLOOKUP(F11,fixed_expenses4[],2,0),"") | I11: =IFERROR(VLOOKUP(H11,fixed_expenses4[],2,0),"") | K11: =IFERROR(VLOOKUP(J11,fixed_expenses4[],2,0),"") | M11: =IFERROR(VLOOKUP(L11,fixed_expenses4[],2,0),"") | O11: =IFERROR(VLOOKUP(N11,fixed_expenses4[],2,0),"")
C12: =IFERROR(VLOOKUP(B12,fixed_expenses4[],2,0),"") | E12: =IFERROR(VLOOKUP(D12,fixed_expenses4[],2,0),"") | G12: =IFERROR(VLOOKUP(F12,fixed_expenses4[],2,0),"") | I12: =IFERROR(VLOOKUP(H12,fixed_expenses4[],2,0),"") | K12: =IFERROR(VLOOKUP(J12,fixed_expenses4[],2,0),"") | M12: =IFERROR(VLOOKUP(L12,fixed_expenses4[],2,0),"") | O12: =IFERROR(VLOOKUP(N12,fixed_expenses4[],2,0),"")
A13: Total is auto calculated for each day and week in cell at right, cells C13 through P13. Next instruction is in cell A15. | B13: TOTAL | C13: =SUM(C8:C12) -> 0 | E13: =SUM(E8:E12) -> 0 | G13: =SUM(G8:G12) -> 0 | I13: =SUM(I8:I12) -> 0 | K13: =SUM(K8:K12) -> 0 | M13: =SUM(M8:M12) -> 800 | O13: =SUM(O8:O12) -> 0 | P13: =SUMIF(B6:N6,"<8",C13:O13) -> 800
A15: Calendar dates are in cells at right, cells B15 through O15. | B15: =N6+1 -> 3 | D15: =B15+1 -> 4 | F15: =D15+1 -> 5 | H15: =F15+1 -> 6 | J15: =H15+1 -> 7 | L15: =J15+1 -> 8 | N15: =L15+1 -> 9
A16: Description and Amount labels are in cells at right, cells B16 through O16. | B16: DESCRIPTION | C16: AMOUNT | D16: DESCRIPTION | E16: AMOUNT | F16: DESCRIPTION | G16: AMOUNT | H16: DESCRIPTION | I16: AMOUNT | J16: DESCRIPTION | K16: AMOUNT | L16: DESCRIPTION | M16: AMOUNT | N16: DESCRIPTION | O16: AMOUNT
A17: Enter Description and Amount of each expense in cells at right, cells B17 through O21. Next instruction is in cell A22. | C17: =IFERROR(VLOOKUP(B17,fixed_expenses4[],2,0),"") | E17: =IFERROR(VLOOKUP(D17,fixed_expenses4[],2,0),"") | G17: =IFERROR(VLOOKUP(F17,fixed_expenses4[],2,0),"") | I17: =IFERROR(VLOOKUP(H17,fixed_expenses4[],2,0),"") | K17: =IFERROR(VLOOKUP(J17,fixed_expenses4[],2,0),"") | L17: Paul Income | M17: =IFERROR(VLOOKUP(L17,fixed_expenses4[],2,0),"") -> 800 | O17: =IFERROR(VLOOKUP(N17,fixed_expenses4[],2,0),"")
C18: =IFERROR(VLOOKUP(B18,fixed_expenses4[],2,0),"") | E18: =IFERROR(VLOOKUP(D18,fixed_expenses4[],2,0),"") | G18: =IFERROR(VLOOKUP(F18,fixed_expenses4[],2,0),"") | I18: =IFERROR(VLOOKUP(H18,fixed_expenses4[],2,0),"") | K18: =IFERROR(VLOOKUP(J18,fixed_expenses4[],2,0),"") | M18: =IFERROR(VLOOKUP(L18,fixed_expenses4[],2,0),"") | O18: =IFERROR(VLOOKUP(N18,fixed_expenses4[],2,0),"")
C19: =IFERROR(VLOOKUP(B19,fixed_expenses4[],2,0),"") | E19: =IFERROR(VLOOKUP(D19,fixed_expenses4[],2,0),"") | G19: =IFERROR(VLOOKUP(F19,fixed_expenses4[],2,0),"") | I19: =IFERROR(VLOOKUP(H19,fixed_expenses4[],2,0),"") | K19: =IFERROR(VLOOKUP(J19,fixed_expenses4[],2,0),"") | M19: =IFERROR(VLOOKUP(L19,fixed_expenses4[],2,0),"") | O19: =IFERROR(VLOOKUP(N19,fixed_expenses4[],2,0),"")
C20: =IFERROR(VLOOKUP(B20,fixed_expenses4[],2,0),"") | E20: =IFERROR(VLOOKUP(D20,fixed_expenses4[],2,0),"") | G20: =IFERROR(VLOOKUP(F20,fixed_expenses4[],2,0),"") | I20: =IFERROR(VLOOKUP(H20,fixed_expenses4[],2,0),"") | K20: =IFERROR(VLOOKUP(J20,fixed_expenses4[],2,0),"") | M20: =IFERROR(VLOOKUP(L20,fixed_expenses4[],2,0),"") | O20: =IFERROR(VLOOKUP(N20,fixed_expenses4[],2,0),"")
C21: =IFERROR(VLOOKUP(B21,fixed_expenses4[],2,0),"") | E21: =IFERROR(VLOOKUP(D21,fixed_expenses4[],2,0),"") | G21: =IFERROR(VLOOKUP(F21,fixed_expenses4[],2,0),"") | I21: =IFERROR(VLOOKUP(H21,fixed_expenses4[],2,0),"") | K21: =IFERROR(VLOOKUP(J21,fixed_expenses4[],2,0),"") | M21: =IFERROR(VLOOKUP(L21,fixed_expenses4[],2,0),"") | O21: =IFERROR(VLOOKUP(N21,fixed_expenses4[],2,0),"")
A22: Total is auto calculated for each day and week in cell at right, cells C22 through P22. Next instruction is in cell A24. | B22: TOTAL | C22: =SUM(C17:C21) -> 0 | E22: =SUM(E17:E21) -> 0 | G22: =SUM(G17:G21) -> 0 | I22: =SUM(I17:I21) -> 0 | K22: =SUM(K17:K21) -> 0 | M22: =SUM(M17:M21) -> 800 | O22: =SUM(O17:O21) -> 0 | P22: =SUM(C22,E22,G22,I22,K22,M22,O22) -> 800
A24: Calendar dates are in cells at right, cells B24 through O24. | B24: =N15+1 -> 10 | D24: =B24+1 -> 11 | F24: =D24+1 -> 12 | H24: =F24+1 -> 13 | J24: =H24+1 -> 14 | L24: =J24+1 -> 15 | N24: =L24+1 -> 16
A25: Description and Amount labels are in cells at right, cells B25 through O25. | B25: DESCRIPTION | C25: AMOUNT | D25: DESCRIPTION | E25: AMOUNT | F25: DESCRIPTION | G25: AMOUNT | H25: DESCRIPTION | I25: AMOUNT | J25: DESCRIPTION | K25: AMOUNT | L25: DESCRIPTION | M25: AMOUNT | N25: DESCRIPTION | O25: AMOUNT
A26: Enter Description and Amount of each expense in cells at right, cells B26 through O30. Next instruction is in cell A31. | C26: =IFERROR(VLOOKUP(B26,fixed_expenses4[],2,0),"") | E26: =IFERROR(VLOOKUP(D26,fixed_expenses4[],2,0),"") | G26: =IFERROR(VLOOKUP(F26,fixed_expenses4[],2,0),"") | I26: =IFERROR(VLOOKUP(H26,fixed_expenses4[],2,0),"") | K26: =IFERROR(VLOOKUP(J26,fixed_expenses4[],2,0),"") | L26: Paul Income | M26: =IFERROR(VLOOKUP(L26,fixed_expenses4[],2,0),"") -> 800 | O26: =IFERROR(VLOOKUP(N26,fixed_expenses4[],2,0),"")
C27: =IFERROR(VLOOKUP(B27,fixed_expenses4[],2,0),"") | E27: =IFERROR(VLOOKUP(D27,fixed_expenses4[],2,0),"") | G27: =IFERROR(VLOOKUP(F27,fixed_expenses4[],2,0),"") | I27: =IFERROR(VLOOKUP(H27,fixed_expenses4[],2,0),"") | K27: =IFERROR(VLOOKUP(J27,fixed_expenses4[],2,0),"") | M27: =IFERROR(VLOOKUP(L27,fixed_expenses4[],2,0),"") | O27: =IFERROR(VLOOKUP(N27,fixed_expenses4[],2,0),"")
C28: =IFERROR(VLOOKUP(B28,fixed_expenses4[],2,0),"") | E28: =IFERROR(VLOOKUP(D28,fixed_expenses4[],2,0),"") | G28: =IFERROR(VLOOKUP(F28,fixed_expenses4[],2,0),"") | I28: =IFERROR(VLOOKUP(H28,fixed_expenses4[],2,0),"") | K28: =IFERROR(VLOOKUP(J28,fixed_expenses4[],2,0),"") | M28: =IFERROR(VLOOKUP(L28,fixed_expenses4[],2,0),"") | O28: =IFERROR(VLOOKUP(N28,fixed_expenses4[],2,0),"")
C29: =IFERROR(VLOOKUP(B29,fixed_expenses4[],2,0),"") | E29: =IFERROR(VLOOKUP(D29,fixed_expenses4[],2,0),"") | G29: =IFERROR(VLOOKUP(F29,fixed_expenses4[],2,0),"") | I29: =IFERROR(VLOOKUP(H29,fixed_expenses4[],2,0),"") | K29: =IFERROR(VLOOKUP(J29,fixed_expenses4[],2,0),"") | M29: =IFERROR(VLOOKUP(L29,fixed_expenses4[],2,0),"") | O29: =IFERROR(VLOOKUP(N29,fixed_expenses4[],2,0),"")
C30: =IFERROR(VLOOKUP(B30,fixed_expenses4[],2,0),"") | E30: =IFERROR(VLOOKUP(D30,fixed_expenses4[],2,0),"") | G30: =IFERROR(VLOOKUP(F30,fixed_expenses4[],2,0),"") | I30: =IFERROR(VLOOKUP(H30,fixed_expenses4[],2,0),"") | K30: =IFERROR(VLOOKUP(J30,fixed_expenses4[],2,0),"") | M30: =IFERROR(VLOOKUP(L30,fixed_expenses4[],2,0),"") | O30: =IFERROR(VLOOKUP(N30,fixed_expenses4[],2,0),"")
A31: Total is auto calculated for each day and week in cell at right, cells C31 through P31. Next instruction is in cell A33. | B31: TOTAL | C31: =SUM(C26:C30) -> 0 | E31: =SUM(E26:E30) -> 0 | G31: =SUM(G26:G30) -> 0 | I31: =SUM(I26:I30) -> 0 | K31: =SUM(K26:K30) -> 0 | M31: =SUM(M26:M30) -> 800 | O31: =SUM(O26:O30) -> 0 | P31: =SUM(C31,E31,G31,I31,K31,M31,O31) -> 800
A33: Calendar dates are in cells at right, cells B33 through O33. | B33: =N24+1 -> 17 | D33: =B33+1 -> 18 | F33: =D33+1 -> 19 | H33: =F33+1 -> 20 | J33: =H33+1 -> 21 | L33: =J33+1 -> 22 | N33: =L33+1 -> 23
A34: Description and Amount labels are in cells at right, cells B34 through O34. | B34: DESCRIPTION | C34: AMOUNT | D34: DESCRIPTION | E34: AMOUNT | F34: DESCRIPTION | G34: AMOUNT | H34: DESCRIPTION | I34: AMOUNT | J34: DESCRIPTION | K34: AMOUNT | L34: DESCRIPTION | M34: AMOUNT | N34: DESCRIPTION | O34: AMOUNT
A35: Enter Description and Amount of each expense in cells at right, cells B35 through O39. Next instruction is in cell A40. | C35: =IFERROR(VLOOKUP(B35,fixed_expenses4[],2,0),"") | E35: =IFERROR(VLOOKUP(D35,fixed_expenses4[],2,0),"") | G35: =IFERROR(VLOOKUP(F35,fixed_expenses4[],2,0),"") | I35: =IFERROR(VLOOKUP(H35,fixed_expenses4[],2,0),"") | K35: =IFERROR(VLOOKUP(J35,fixed_expenses4[],2,0),"") | L35: Paul Income | M35: =IFERROR(VLOOKUP(L35,fixed_expenses4[],2,0),"") -> 800 | O35: =IFERROR(VLOOKUP(N35,fixed_expenses4[],2,0),"")
C36: =IFERROR(VLOOKUP(B36,fixed_expenses4[],2,0),"") | E36: =IFERROR(VLOOKUP(D36,fixed_expenses4[],2,0),"") | G36: =IFERROR(VLOOKUP(F36,fixed_expenses4[],2,0),"") | I36: =IFERROR(VLOOKUP(H36,fixed_expenses4[],2,0),"") | K36: =IFERROR(VLOOKUP(J36,fixed_expenses4[],2,0),"") | L36: Lynn Income | M36: =IFERROR(VLOOKUP(L36,fixed_expenses4[],2,0),"") -> 770 | O36: =IFERROR(VLOOKUP(N36,fixed_expenses4[],2,0),"")
C37: =IFERROR(VLOOKUP(B37,fixed_expenses4[],2,0),"") | E37: =IFERROR(VLOOKUP(D37,fixed_expenses4[],2,0),"") | G37: =IFERROR(VLOOKUP(F37,fixed_expenses4[],2,0),"") | I37: =IFERROR(VLOOKUP(H37,fixed_expenses4[],2,0),"") | K37: =IFERROR(VLOOKUP(J37,fixed_expenses4[],2,0),"") | M37: =IFERROR(VLOOKUP(L37,fixed_expenses4[],2,0),"") | O37: =IFERROR(VLOOKUP(N37,fixed_expenses4[],2,0),"")
C38: =IFERROR(VLOOKUP(B38,fixed_expenses4[],2,0),"") | E38: =IFERROR(VLOOKUP(D38,fixed_expenses4[],2,0),"") | G38: =IFERROR(VLOOKUP(F38,fixed_expenses4[],2,0),"") | I38: =IFERROR(VLOOKUP(H38,fixed_expenses4[],2,0),"") | K38: =IFERROR(VLOOKUP(J38,fixed_expenses4[],2,0),"") | M38: =IFERROR(VLOOKUP(L38,fixed_expenses4[],2,0),"") | O38: =IFERROR(VLOOKUP(N38,fixed_expenses4[],2,0),"")
C39: =IFERROR(VLOOKUP(B39,fixed_expenses4[],2,0),"") | E39: =IFERROR(VLOOKUP(D39,fixed_expenses4[],2,0),"") | G39: =IFERROR(VLOOKUP(F39,fixed_expenses4[],2,0),"") | I39: =IFERROR(VLOOKUP(H39,fixed_expenses4[],2,0),"") | K39: =IFERROR(VLOOKUP(J39,fixed_expenses4[],2,0),"") | M39: =IFERROR(VLOOKUP(L39,fixed_expenses4[],2,0),"") | O39: =IFERROR(VLOOKUP(N39,fixed_expenses4[],2,0),"")
A40: Total is auto calculated for each day and week in cell at right, cells C40 through P40. Next instruction is in cell A42. | B40: TOTAL | C40: =SUM(C35:C39) -> 0 | E40: =SUM(E35:E39) -> 0 | G40: =SUM(G35:G39) -> 0 | I40: =SUM(I35:I39) -> 0 | K40: =SUM(K35:K39) -> 0 | M40: =SUM(M35:M39) -> 1570 | O40: =SUM(O35:O39) -> 0 | P40: =SUM(C40,E40,G40,I40,K40,M40,O40) -> 1570
A42: Calendar dates are in cells at right, cells B42 through O42. | B42: =DAY(IF(DAY(JanSun1)=1,JanSun1+22,JanSun1+29)) -> 24 | D42: =DAY(IF(DAY(JanSun1)=1,JanSun1+23,JanSun1+30)) -> 25 | F42: =DAY(IF(DAY(JanSun1)=1,JanSun1+24,JanSun1+31)) -> 26 | H42: =DAY(IF(DAY(JanSun1)=1,JanSun1+25,JanSun1+32)) -> 27 | J42: =DAY(IF(DAY(JanSun1)=1,JanSun1+26,JanSun1+33)) -> 28 | L42: =DAY(IF(DAY(JanSun1)=1,JanSun1+27,JanSun1+34)) -> 29 | N42: =DAY(IF(DAY(JanSun1)=1,JanSun1+28,JanSun1+35)) -> 30
A43: Description and Amount labels are in cells at right, cells B43 through O43. | B43: DESCRIPTION | C43: AMOUNT | D43: DESCRIPTION | E43: AMOUNT | F43: DESCRIPTION | G43: AMOUNT | H43: DESCRIPTION | I43: AMOUNT | J43: DESCRIPTION | K43: AMOUNT | L43: DESCRIPTION | M43: AMOUNT | N43: DESCRIPTION | O43: AMOUNT
A44: Enter Description and Amount of each expense in cells at right, cells B44 through O48. Next instruction is in cell A49. | C44: =IFERROR(VLOOKUP(B44,fixed_expenses4[],2,0),"") | E44: =IFERROR(VLOOKUP(D44,fixed_expenses4[],2,0),"") | G44: =IFERROR(VLOOKUP(F44,fixed_expenses4[],2,0),"") | I44: =IFERROR(VLOOKUP(H44,fixed_expenses4[],2,0),"") | K44: =IFERROR(VLOOKUP(J44,fixed_expenses4[],2,0),"") | L44: Paul Income | M44: =IFERROR(VLOOKUP(L44,fixed_expenses4[],2,0),"") -> 800 | O44: =IFERROR(VLOOKUP(N44,fixed_expenses4[],2,0),"")
C45: =IFERROR(VLOOKUP(B45,fixed_expenses4[],2,0),"") | E45: =IFERROR(VLOOKUP(D45,fixed_expenses4[],2,0),"") | G45: =IFERROR(VLOOKUP(F45,fixed_expenses4[],2,0),"") | I45: =IFERROR(VLOOKUP(H45,fixed_expenses4[],2,0),"") | K45: =IFERROR(VLOOKUP(J45,fixed_expenses4[],2,0),"") | M45: =IFERROR(VLOOKUP(L45,fixed_expenses4[],2,0),"") | O45: =IFERROR(VLOOKUP(N45,fixed_expenses4[],2,0),"")
C46: =IFERROR(VLOOKUP(B46,fixed_expenses4[],2,0),"") | E46: =IFERROR(VLOOKUP(D46,fixed_expenses4[],2,0),"") | G46: =IFERROR(VLOOKUP(F46,fixed_expenses4[],2,0),"") | I46: =IFERROR(VLOOKUP(H46,fixed_expenses4[],2,0),"") | K46: =IFERROR(VLOOKUP(J46,fixed_expenses4[],2,0),"") | M46: =IFERROR(VLOOKUP(L46,fixed_expenses4[],2,0),"") | O46: =IFERROR(VLOOKUP(N46,fixed_expenses4[],2,0),"")
C47: =IFERROR(VLOOKUP(B47,fixed_expenses4[],2,0),"") | E47: =IFERROR(VLOOKUP(D47,fixed_expenses4[],2,0),"") | G47: =IFERROR(VLOOKUP(F47,fixed_expenses4[],2,0),"") | I47: =IFERROR(VLOOKUP(H47,fixed_expenses4[],2,0),"") | K47: =IFERROR(VLOOKUP(J47,fixed_expenses4[],2,0),"") | M47: =IFERROR(VLOOKUP(L47,fixed_expenses4[],2,0),"") | O47: =IFERROR(VLOOKUP(N47,fixed_expenses4[],2,0),"")
C48: =IFERROR(VLOOKUP(B48,fixed_expenses4[],2,0),"") | E48: =IFERROR(VLOOKUP(D48,fixed_expenses4[],2,0),"") | G48: =IFERROR(VLOOKUP(F48,fixed_expenses4[],2,0),"") | I48: =IFERROR(VLOOKUP(H48,fixed_expenses4[],2,0),"") | K48: =IFERROR(VLOOKUP(J48,fixed_expenses4[],2,0),"") | M48: =IFERROR(VLOOKUP(L48,fixed_expenses4[],2,0),"") | O48: =IFERROR(VLOOKUP(N48,fixed_expenses4[],2,0),"")
A49: Total is auto calculated for each day and week in cell at right, cells C49 through P49. Next instruction is in cell A51. | B49: TOTAL | C49: =SUM(C44:C48) -> 0 | E49: =SUM(E44:E48) -> 0 | G49: =SUM(G44:G48) -> 0 | I49: =SUM(I44:I48) -> 0 | K49: =SUM(K44:K48) -> 0 | M49: =SUM(M44:M48) -> 800 | O49: =SUM(O44:O48) -> 0 | P49: =SUMIF(B42:N42,">="&15,C49:O49) -> 800
A51: Calendar dates are in cells at right, cells B51 through O51. | B51: =DAY(IF(DAY(JanSun1)=1,JanSun1+29,JanSun1+36)) -> 31 | D51: =DAY(IF(DAY(JanSun1)=1,JanSun1+30,JanSun1+37)) -> 1 | F51: =DAY(IF(DAY(JanSun1)=1,JanSun1+31,JanSun1+38)) -> 2 | H51: =DAY(IF(DAY(JanSun1)=1,JanSun1+32,JanSun1+39)) -> 3 | J51: =DAY(IF(DAY(JanSun1)=1,JanSun1+33,JanSun1+40)) -> 4 | L51: =DAY(IF(DAY(JanSun1)=1,JanSun1+34,JanSun1+41)) -> 5 | N51: =DAY(IF(DAY(JanSun1)=1,JanSun1+35,JanSun1+42)) -> 6
A52: Description and Amount labels are in cells at right, cells B52 through O52. | B52: DESCRIPTION | C52: AMOUNT | D52: DESCRIPTION | E52: AMOUNT | F52: DESCRIPTION | G52: AMOUNT | H52: DESCRIPTION | I52: AMOUNT | J52: DESCRIPTION | K52: AMOUNT | L52: DESCRIPTION | M52: AMOUNT | N52: DESCRIPTION | O52: AMOUNT
A53: Enter Description and Amount of each expense in cells at right, cells B53 through O57. Next instruction is in cell A58. | C53: =IFERROR(VLOOKUP(B53,fixed_expenses4[],2,0),"") | E53: =IFERROR(VLOOKUP(D53,fixed_expenses4[],2,0),"") | G53: =IFERROR(VLOOKUP(F53,fixed_expenses4[],2,0),"") | I53: =IFERROR(VLOOKUP(H53,fixed_expenses4[],2,0),"") | K53: =IFERROR(VLOOKUP(J53,fixed_expenses4[],2,0),"") | M53: =IFERROR(VLOOKUP(L53,fixed_expenses4[],2,0),"") | O53: =IFERROR(VLOOKUP(N53,fixed_expenses4[],2,0),"")
C54: =IFERROR(VLOOKUP(B54,fixed_expenses4[],2,0),"") | E54: =IFERROR(VLOOKUP(D54,fixed_expenses4[],2,0),"") | G54: =IFERROR(VLOOKUP(F54,fixed_expenses4[],2,0),"") | I54: =IFERROR(VLOOKUP(H54,fixed_expenses4[],2,0),"") | K54: =IFERROR(VLOOKUP(J54,fixed_expenses4[],2,0),"") | M54: =IFERROR(VLOOKUP(L54,fixed_expenses4[],2,0),"") | O54: =IFERROR(VLOOKUP(N54,fixed_expenses4[],2,0),"")
C55: =IFERROR(VLOOKUP(B55,fixed_expenses4[],2,0),"") | E55: =IFERROR(VLOOKUP(D55,fixed_expenses4[],2,0),"") | G55: =IFERROR(VLOOKUP(F55,fixed_expenses4[],2,0),"") | I55: =IFERROR(VLOOKUP(H55,fixed_expenses4[],2,0),"") | K55: =IFERROR(VLOOKUP(J55,fixed_expenses4[],2,0),"") | M55: =IFERROR(VLOOKUP(L55,fixed_expenses4[],2,0),"") | O55: =IFERROR(VLOOKUP(N55,fixed_expenses4[],2,0),"")
C56: =IFERROR(VLOOKUP(B56,fixed_expenses4[],2,0),"") | E56: =IFERROR(VLOOKUP(D56,fixed_expenses4[],2,0),"") | G56: =IFERROR(VLOOKUP(F56,fixed_expenses4[],2,0),"") | I56: =IFERROR(VLOOKUP(H56,fixed_expenses4[],2,0),"") | K56: =IFERROR(VLOOKUP(J56,fixed_expenses4[],2,0),"") | M56: =IFERROR(VLOOKUP(L56,fixed_expenses4[],2,0),"") | O56: =IFERROR(VLOOKUP(N56,fixed_expenses4[],2,0),"")
C57: =IFERROR(VLOOKUP(B57,fixed_expenses4[],2,0),"") | E57: =IFERROR(VLOOKUP(D57,fixed_expenses4[],2,0),"") | G57: =IFERROR(VLOOKUP(F57,fixed_expenses4[],2,0),"") | I57: =IFERROR(VLOOKUP(H57,fixed_expenses4[],2,0),"") | K57: =IFERROR(VLOOKUP(J57,fixed_expenses4[],2,0),"") | M57: =IFERROR(VLOOKUP(L57,fixed_expenses4[],2,0),"") | O57: =IFERROR(VLOOKUP(N57,fixed_expenses4[],2,0),"")
A58: Total is auto calculated for each day and week in cell at right, cells C58 through P58. Next instruction is in cell A60. | B58: TOTAL | C58: =SUM(C53:C57) -> 0 | E58: =SUM(E53:E57) -> 0 | G58: =SUM(G53:G57) -> 0 | I58: =SUM(I53:I57) -> 0 | K58: =SUM(K53:K57) -> 0 | M58: =SUM(M53:M57) -> 0 | O58: =SUM(O53:O57) -> 0 | P58: =SUMIF(B51:N51,">="&15,C58:O58) -> 0
A60: February label is in cell at right, Monthly Total label in cell L60, and Grand Total label in N60. | B60: FEBRUARY | L60: MONTHLY TOTAL | N60: GRAND TOTAL
A61: Monthly Total is auto calculated in cell L61 and Grand Total in N61. | F61: =IFERROR(WEEKDAY(DATEVALUE(B60&" 1, "&Year1)),"") -> 2 | L61: =SUM(P71,P80,P89,P98,P107,P116) -> 4740 | N61: =SUM(P:P) -> 62420
A62: February calendar is in cells B63 through O116. | B62: 1 | D62: 2 | F62: 3 | H62: 4 | J62: 5 | L62: 6 | N62: 7
A63: Weekdays are in cells at right, cells B63 through N63, and Weekly Total label in cell P63. | B63: SUNDAY | D63: MONDAY | E63: =IF(WEEKDAY(DATEVALUE(Month1&" 1, "&Year1))=COLUMN(#REF!),1,IF(LEN(C63)>0,C63+1,"")) -> #VALUE! | F63: TUESDAY | G63: =IF(WEEKDAY(DATEVALUE(Month1&" 1, "&Year1))=COLUMN(#REF!),1,IF(LEN(E63)>0,E63+1,"")) -> #VALUE! | H63: WEDNESDAY | I63: =IF(WEEKDAY(DATEVALUE(Month1&" 1, "&Year1))=COLUMN(#REF!),1,IF(LEN(G63)>0,G63+1,"")) -> #VALUE! | J63: THURSDAY | K63: =IF(WEEKDAY(DATEVALUE(Month1&" 1, "&Year1))=COLUMN(#REF!),1,IF(LEN(I63)>0,I63+1,"")) -> #VALUE! | L63: FRIDAY | M63: =IF(WEEKDAY(DATEVALUE(Month1&" 1, "&Year1))=COLUMN(#REF!),1,IF(LEN(K63)>0,K63+1,"")) -> #VALUE! | N63: SATURDAY | O63: =IF(WEEKDAY(DATEVALUE(Month1&" 1, "&Year1))=COLUMN(#REF!),1,IF(LEN(M63)>0,M63+1,"")) -> #VALUE! | P63: WEEKLY TOTAL
A64: Calendar dates are in cells at right, cells B64 through O64. If it doesn’t start with number 1, then it is date of previous month. | B64: =DAY(IF(DAY(FebSun1)=1,FebSun1-6,FebSun1+1)) -> 31 | D64: =DAY(IF(DAY(FebSun1)=1,FebSun1-5,FebSun1+2)) -> 1 | F64: =DAY(IF(DAY(FebSun1)=1,FebSun1-4,FebSun1+3)) -> 2 | H64: =DAY(IF(DAY(FebSun1)=1,FebSun1-3,FebSun1+4)) -> 3 | J64: =DAY(IF(DAY(FebSun1)=1,FebSun1-2,FebSun1+5)) -> 4 | L64: =DAY(IF(DAY(FebSun1)=1,FebSun1-1,FebSun1+6)) -> 5 | N64: =DAY(IF(DAY(FebSun1)=1,FebSun1,FebSun1+7)) -> 6
A65: Description and Amount labels are in cells at right, cells B65 through O65. | B65: DESCRIPTION | C65: AMOUNT | D65: DESCRIPTION | E65: AMOUNT | F65: DESCRIPTION | G65: AMOUNT | H65: DESCRIPTION | I65: AMOUNT | J65: DESCRIPTION | K65: AMOUNT | L65: DESCRIPTION | M65: AMOUNT | N65: DESCRIPTION | O65: AMOUNT
A66: Enter Description and Amount of each expense in cells at right, cells B66 through O70. Next instruction is in cell A71. | C66: =IFERROR(VLOOKUP(B66,fixed_expenses4[],2,0),"") | E66: =IFERROR(VLOOKUP(D66,fixed_expenses4[],2,0),"") | G66: =IFERROR(VLOOKUP(F66,fixed_expenses4[],2,0),"") | I66: =IFERROR(VLOOKUP(H66,fixed_expenses4[],2,0),"") | K66: =IFERROR(VLOOKUP(J66,fixed_expenses4[],2,0),"") | L66: Paul Income | M66: =IFERROR(VLOOKUP(L66,fixed_expenses4[],2,0),"") -> 800 | O66: =IFERROR(VLOOKUP(N66,fixed_expenses4[],2,0),"")
C67: =IFERROR(VLOOKUP(B67,fixed_expenses4[],2,0),"") | E67: =IFERROR(VLOOKUP(D67,fixed_expenses4[],2,0),"") | G67: =IFERROR(VLOOKUP(F67,fixed_expenses4[],2,0),"") | I67: =IFERROR(VLOOKUP(H67,fixed_expenses4[],2,0),"") | K67: =IFERROR(VLOOKUP(J67,fixed_expenses4[],2,0),"") | L67: Lynn Income | M67: =IFERROR(VLOOKUP(L67,fixed_expenses4[],2,0),"") -> 770 | O67: =IFERROR(VLOOKUP(N67,fixed_expenses4[],2,0),"")
C68: =IFERROR(VLOOKUP(B68,fixed_expenses4[],2,0),"") | E68: =IFERROR(VLOOKUP(D68,fixed_expenses4[],2,0),"") | G68: =IFERROR(VLOOKUP(F68,fixed_expenses4[],2,0),"") | I68: =IFERROR(VLOOKUP(H68,fixed_expenses4[],2,0),"") | K68: =IFERROR(VLOOKUP(J68,fixed_expenses4[],2,0),"") | M68: =IFERROR(VLOOKUP(L68,fixed_expenses4[],2,0),"") | O68: =IFERROR(VLOOKUP(N68,fixed_expenses4[],2,0),"")
C69: =IFERROR(VLOOKUP(B69,fixed_expenses4[],2,0),"") | E69: =IFERROR(VLOOKUP(D69,fixed_expenses4[],2,0),"") | G69: =IFERROR(VLOOKUP(F69,fixed_expenses4[],2,0),"") | I69: =IFERROR(VLOOKUP(H69,fixed_expenses4[],2,0),"") | K69: =IFERROR(VLOOKUP(J69,fixed_expenses4[],2,0),"") | M69: =IFERROR(VLOOKUP(L69,fixed_expenses4[],2,0),"") | O69: =IFERROR(VLOOKUP(N69,fixed_expenses4[],2,0),"")
C70: =IFERROR(VLOOKUP(B70,fixed_expenses4[],2,0),"") | E70: =IFERROR(VLOOKUP(D70,fixed_expenses4[],2,0),"") | G70: =IFERROR(VLOOKUP(F70,fixed_expenses4[],2,0),"") | I70: =IFERROR(VLOOKUP(H70,fixed_expenses4[],2,0),"") | K70: =IFERROR(VLOOKUP(J70,fixed_expenses4[],2,0),"") | M70: =IFERROR(VLOOKUP(L70,fixed_expenses4[],2,0),"") | O70: =IFERROR(VLOOKUP(N70,fixed_expenses4[],2,0),"")
A71: Total is auto calculated for each day and week in cell at right, cells C71 through P71. Next instruction is in cell A73. | B71: TOTAL | C71: =SUM(C66:C70) -> 0 | E71: =SUM(E66:E70) -> 0 | G71: =SUM(G66:G70) -> 0 | I71: =SUM(I66:I70) -> 0 | K71: =SUM(K66:K70) -> 0 | M71: =SUM(M66:M70) -> 1570 | O71: =SUM(O66:O70) -> 0 | P71: =SUMIF(B64:N64,"<8",C71:O71) -> 1570
A73: Calendar dates are in cells at right, cells B73 through O73. | B73: =N64+1 -> 7 | D73: =B73+1 -> 8 | F73: =D73+1 -> 9 | H73: =F73+1 -> 10 | J73: =H73+1 -> 11 | L73: =J73+1 -> 12 | N73: =L73+1 -> 13
A74: Description and Amount labels are in cells at right, cells B74 through O74. | B74: DESCRIPTION | C74: AMOUNT | D74: DESCRIPTION | E74: AMOUNT | F74: DESCRIPTION | G74: AMOUNT | H74: DESCRIPTION | I74: AMOUNT | J74: DESCRIPTION | K74: AMOUNT | L74: DESCRIPTION | M74: AMOUNT | N74: DESCRIPTION | O74: AMOUNT
A75: Enter Description and Amount of each expense in cells at right, cells B75 through O79. Next instruction is in cell A80. | C75: =IFERROR(VLOOKUP(B75,fixed_expenses4[],2,0),"") | E75: =IFERROR(VLOOKUP(D75,fixed_expenses4[],2,0),"") | G75: =IFERROR(VLOOKUP(F75,fixed_expenses4[],2,0),"") | I75: =IFERROR(VLOOKUP(H75,fixed_expenses4[],2,0),"") | K75: =IFERROR(VLOOKUP(J75,fixed_expenses4[],2,0),"") | L75: Paul Income | M75: =IFERROR(VLOOKUP(L75,fixed_expenses4[],2,0),"") -> 800 | O75: =IFERROR(VLOOKUP(N75,fixed_expenses4[],2,0),"")
C76: =IFERROR(VLOOKUP(B76,fixed_expenses4[],2,0),"") | E76: =IFERROR(VLOOKUP(D76,fixed_expenses4[],2,0),"") | G76: =IFERROR(VLOOKUP(F76,fixed_expenses4[],2,0),"") | I76: =IFERROR(VLOOKUP(H76,fixed_expenses4[],2,0),"") | K76: =IFERROR(VLOOKUP(J76,fixed_expenses4[],2,0),"") | M76: =IFERROR(VLOOKUP(L76,fixed_expenses4[],2,0),"") | O76: =IFERROR(VLOOKUP(N76,fixed_expenses4[],2,0),"")
C77: =IFERROR(VLOOKUP(B77,fixed_expenses4[],2,0),"") | E77: =IFERROR(VLOOKUP(D77,fixed_expenses4[],2,0),"") | G77: =IFERROR(VLOOKUP(F77,fixed_expenses4[],2,0),"") | I77: =IFERROR(VLOOKUP(H77,fixed_expenses4[],2,0),"") | K77: =IFERROR(VLOOKUP(J77,fixed_expenses4[],2,0),"") | M77: =IFERROR(VLOOKUP(L77,fixed_expenses4[],2,0),"") | O77: =IFERROR(VLOOKUP(N77,fixed_expenses4[],2,0),"")
C78: =IFERROR(VLOOKUP(B78,fixed_expenses4[],2,0),"") | E78: =IFERROR(VLOOKUP(D78,fixed_expenses4[],2,0),"") | G78: =IFERROR(VLOOKUP(F78,fixed_expenses4[],2,0),"") | I78: =IFERROR(VLOOKUP(H78,fixed_expenses4[],2,0),"") | K78: =IFERROR(VLOOKUP(J78,fixed_expenses4[],2,0),"") | M78: =IFERROR(VLOOKUP(L78,fixed_expenses4[],2,0),"") | O78: =IFERROR(VLOOKUP(N78,fixed_expenses4[],2,0),"")
C79: =IFERROR(VLOOKUP(B79,fixed_expenses4[],2,0),"") | E79: =IFERROR(VLOOKUP(D79,fixed_expenses4[],2,0),"") | G79: =IFERROR(VLOOKUP(F79,fixed_expenses4[],2,0),"") | I79: =IFERROR(VLOOKUP(H79,fixed_expenses4[],2,0),"") | K79: =IFERROR(VLOOKUP(J79,fixed_expenses4[],2,0),"") | M79: =IFERROR(VLOOKUP(L79,fixed_expenses4[],2,0),"") | O79: =IFERROR(VLOOKUP(N79,fixed_expenses4[],2,0),"")
A80: Total is auto calculated for each day and week in cell at right, cells C80 through P80. Next instruction is in cell A82. | B80: TOTAL | C80: =SUM(C75:C79) -> 0 | E80: =SUM(E75:E79) -> 0 | G80: =SUM(G75:G79) -> 0 | I80: =SUM(I75:I79) -> 0 | K80: =SUM(K75:K79) -> 0 | M80: =SUM(M75:M79) -> 800 | O80: =SUM(O75:O79) -> 0 | P80: =SUM(C80,E80,G80,I80,K80,M80,O80) -> 800
A82: Calendar dates are in cells at right, cells B82 through O82. | B82: =N73+1 -> 14 | D82: =B82+1 -> 15 | F82: =D82+1 -> 16 | H82: =F82+1 -> 17 | J82: =H82+1 -> 18 | L82: =J82+1 -> 19 | N82: =L82+1 -> 20
A83: Description and Amount labels are in cells at right, cells B83 through O83. | B83: DESCRIPTION | C83: AMOUNT | D83: DESCRIPTION | E83: AMOUNT | F83: DESCRIPTION | G83: AMOUNT | H83: DESCRIPTION | I83: AMOUNT | J83: DESCRIPTION | K83: AMOUNT | L83: DESCRIPTION | M83: AMOUNT | N83: DESCRIPTION | O83: AMOUNT
A84: Enter Description and Amount of each expense in cells at right, cells B84 through O88. Next instruction is in cell A89. | C84: =IFERROR(VLOOKUP(B84,fixed_expenses4[],2,0),"") | E84: =IFERROR(VLOOKUP(D84,fixed_expenses4[],2,0),"") | G84: =IFERROR(VLOOKUP(F84,fixed_expenses4[],2,0),"") | I84: =IFERROR(VLOOKUP(H84,fixed_expenses4[],2,0),"") | K84: =IFERROR(VLOOKUP(J84,fixed_expenses4[],2,0),"") | L84: Paul Income | M84: =IFERROR(VLOOKUP(L84,fixed_expenses4[],2,0),"") -> 800 | O84: =IFERROR(VLOOKUP(N84,fixed_expenses4[],2,0),"")
C85: =IFERROR(VLOOKUP(B85,fixed_expenses4[],2,0),"") | E85: =IFERROR(VLOOKUP(D85,fixed_expenses4[],2,0),"") | G85: =IFERROR(VLOOKUP(F85,fixed_expenses4[],2,0),"") | I85: =IFERROR(VLOOKUP(H85,fixed_expenses4[],2,0),"") | K85: =IFERROR(VLOOKUP(J85,fixed_expenses4[],2,0),"") | L85: Lynn Income | M85: =IFERROR(VLOOKUP(L85,fixed_expenses4[],2,0),"") -> 770 | O85: =IFERROR(VLOOKUP(N85,fixed_expenses4[],2,0),"")
C86: =IFERROR(VLOOKUP(B86,fixed_expenses4[],2,0),"") | E86: =IFERROR(VLOOKUP(D86,fixed_expenses4[],2,0),"") | G86: =IFERROR(VLOOKUP(F86,fixed_expenses4[],2,0),"") | I86: =IFERROR(VLOOKUP(H86,fixed_expenses4[],2,0),"") | K86: =IFERROR(VLOOKUP(J86,fixed_expenses4[],2,0),"") | M86: =IFERROR(VLOOKUP(L86,fixed_expenses4[],2,0),"") | O86: =IFERROR(VLOOKUP(N86,fixed_expenses4[],2,0),"")
C87: =IFERROR(VLOOKUP(B87,fixed_expenses4[],2,0),"") | E87: =IFERROR(VLOOKUP(D87,fixed_expenses4[],2,0),"") | G87: =IFERROR(VLOOKUP(F87,fixed_expenses4[],2,0),"") | I87: =IFERROR(VLOOKUP(H87,fixed_expenses4[],2,0),"") | K87: =IFERROR(VLOOKUP(J87,fixed_expenses4[],2,0),"") | M87: =IFERROR(VLOOKUP(L87,fixed_expenses4[],2,0),"") | O87: =IFERROR(VLOOKUP(N87,fixed_expenses4[],2,0),"")
C88: =IFERROR(VLOOKUP(B88,fixed_expenses4[],2,0),"") | E88: =IFERROR(VLOOKUP(D88,fixed_expenses4[],2,0),"") | G88: =IFERROR(VLOOKUP(F88,fixed_expenses4[],2,0),"") | I88: =IFERROR(VLOOKUP(H88,fixed_expenses4[],2,0),"") | K88: =IFERROR(VLOOKUP(J88,fixed_expenses4[],2,0),"") | M88: =IFERROR(VLOOKUP(L88,fixed_expenses4[],2,0),"") | O88: =IFERROR(VLOOKUP(N88,fixed_expenses4[],2,0),"")
A89: Total is auto calculated for each day and week in cell at right, cells C89 through P89. Next instruction is in cell A91. | B89: TOTAL | C89: =SUM(C84:C88) -> 0 | E89: =SUM(E84:E88) -> 0 | G89: =SUM(G84:G88) -> 0 | I89: =SUM(I84:I88) -> 0 | K89: =SUM(K84:K88) -> 0 | M89: =SUM(M84:M88) -> 1570 | O89: =SUM(O84:O88) -> 0 | P89: =SUM(C89,E89,G89,I89,K89,M89,O89) -> 1570
A91: Calendar dates are in cells at right, cells B91 through O91. | B91: =N82+1 -> 21 | D91: =B91+1 -> 22 | F91: =D91+1 -> 23 | H91: =F91+1 -> 24 | J91: =H91+1 -> 25 | L91: =J91+1 -> 26 | N91: =L91+1 -> 27
A92: Description and Amount labels are in cells at right, cells B92 through O92. | B92: DESCRIPTION | C92: AMOUNT | D92: DESCRIPTION | E92: AMOUNT | F92: DESCRIPTION | G92: AMOUNT | H92: DESCRIPTION | I92: AMOUNT | J92: DESCRIPTION | K92: AMOUNT | L92: DESCRIPTION | M92: AMOUNT | N92: DESCRIPTION | O92: AMOUNT
A93: Enter Description and Amount of each expense in cells at right, cells B93 through O97. Next instruction is in cell A98. | C93: =IFERROR(VLOOKUP(B93,fixed_expenses4[],2,0),"") | E93: =IFERROR(VLOOKUP(D93,fixed_expenses4[],2,0),"") | G93: =IFERROR(VLOOKUP(F93,fixed_expenses4[],2,0),"") | I93: =IFERROR(VLOOKUP(H93,fixed_expenses4[],2,0),"") | K93: =IFERROR(VLOOKUP(J93,fixed_expenses4[],2,0),"") | L93: Paul Income | M93: =IFERROR(VLOOKUP(L93,fixed_expenses4[],2,0),"") -> 800 | O93: =IFERROR(VLOOKUP(N93,fixed_expenses4[],2,0),"")
C94: =IFERROR(VLOOKUP(B94,fixed_expenses4[],2,0),"") | E94: =IFERROR(VLOOKUP(D94,fixed_expenses4[],2,0),"") | G94: =IFERROR(VLOOKUP(F94,fixed_expenses4[],2,0),"") | I94: =IFERROR(VLOOKUP(H94,fixed_expenses4[],2,0),"") | K94: =IFERROR(VLOOKUP(J94,fixed_expenses4[],2,0),"") | M94: =IFERROR(VLOOKUP(L94,fixed_expenses4[],2,0),"") | O94: =IFERROR(VLOOKUP(N94,fixed_expenses4[],2,0),"")
C95: =IFERROR(VLOOKUP(B95,fixed_expenses4[],2,0),"") | E95: =IFERROR(VLOOKUP(D95,fixed_expenses4[],2,0),"") | G95: =IFERROR(VLOOKUP(F95,fixed_expenses4[],2,0),"") | I95: =IFERROR(VLOOKUP(H95,fixed_expenses4[],2,0),"") | K95: =IFERROR(VLOOKUP(J95,fixed_expenses4[],2,0),"") | M95: =IFERROR(VLOOKUP(L95,fixed_expenses4[],2,0),"") | O95: =IFERROR(VLOOKUP(N95,fixed_expenses4[],2,0),"")
C96: =IFERROR(VLOOKUP(B96,fixed_expenses4[],2,0),"") | E96: =IFERROR(VLOOKUP(D96,fixed_expenses4[],2,0),"") | G96: =IFERROR(VLOOKUP(F96,fixed_expenses4[],2,0),"") | I96: =IFERROR(VLOOKUP(H96,fixed_expenses4[],2,0),"") | K96: =IFERROR(VLOOKUP(J96,fixed_expenses4[],2,0),"") | M96: =IFERROR(VLOOKUP(L96,fixed_expenses4[],2,0),"") | O96: =IFERROR(VLOOKUP(N96,fixed_expenses4[],2,0),"")
C97: =IFERROR(VLOOKUP(B97,fixed_expenses4[],2,0),"") | E97: =IFERROR(VLOOKUP(D97,fixed_expenses4[],2,0),"") | G97: =IFERROR(VLOOKUP(F97,fixed_expenses4[],2,0),"") | I97: =IFERROR(VLOOKUP(H97,fixed_expenses4[],2,0),"") | K97: =IFERROR(VLOOKUP(J97,fixed_expenses4[],2,0),"") | M97: =IFERROR(VLOOKUP(L97,fixed_expenses4[],2,0),"") | O97: =IFERROR(VLOOKUP(N97,fixed_expenses4[],2,0),"")
A98: Total is auto calculated for each day and week in cell at right, cells C98 through P98. Next instruction is in cell A100. | B98: TOTAL | C98: =SUM(C93:C97) -> 0 | E98: =SUM(E93:E97) -> 0 | G98: =SUM(G93:G97) -> 0 | I98: =SUM(I93:I97) -> 0 | K98: =SUM(K93:K97) -> 0 | M98: =SUM(M93:M97) -> 800 | O98: =SUM(O93:O97) -> 0 | P98: =SUM(C98,E98,G98,I98,K98,M98,O98) -> 800
A100: Calendar dates are in cells at right, cells B100 through O100. | B100: =DAY(IF(DAY(FebSun1)=1,FebSun1+22,FebSun1+29)) -> 28 | D100: =DAY(IF(DAY(FebSun1)=1,FebSun1+23,FebSun1+30)) -> 1 | F100: =DAY(IF(DAY(FebSun1)=1,FebSun1+24,FebSun1+31)) -> 2 | H100: =DAY(IF(DAY(FebSun1)=1,FebSun1+25,FebSun1+32)) -> 3 | J100: =DAY(IF(DAY(FebSun1)=1,FebSun1+26,FebSun1+33)) -> 4 | L100: =DAY(IF(DAY(FebSun1)=1,FebSun1+27,FebSun1+34)) -> 5 | N100: =DAY(IF(DAY(FebSun1)=1,FebSun1+28,FebSun1+35)) -> 6
A101: Description and Amount labels are in cells at right, cells B101 through O101. | B101: DESCRIPTION | C101: AMOUNT | D101: DESCRIPTION | E101: AMOUNT | F101: DESCRIPTION | G101: AMOUNT | H101: DESCRIPTION | I101: AMOUNT | J101: DESCRIPTION | K101: AMOUNT | L101: DESCRIPTION | M101: AMOUNT | N101: DESCRIPTION | O101: AMOUNT
A102: Enter Description and Amount of each expense in cells at right, cells B102 through O106. Next instruction is in cell A107. | C102: =IFERROR(VLOOKUP(B102,fixed_expenses4[],2,0),"") | E102: =IFERROR(VLOOKUP(D102,fixed_expenses4[],2,0),"") | G102: =IFERROR(VLOOKUP(F102,fixed_expenses4[],2,0),"") | I102: =IFERROR(VLOOKUP(H102,fixed_expenses4[],2,0),"") | K102: =IFERROR(VLOOKUP(J102,fixed_expenses4[],2,0),"") | M102: =IFERROR(VLOOKUP(L102,fixed_expenses4[],2,0),"") | O102: =IFERROR(VLOOKUP(N102,fixed_expenses4[],2,0),"")
C103: =IFERROR(VLOOKUP(B103,fixed_expenses4[],2,0),"") | E103: =IFERROR(VLOOKUP(D103,fixed_expenses4[],2,0),"") | G103: =IFERROR(VLOOKUP(F103,fixed_expenses4[],2,0),"") | I103: =IFERROR(VLOOKUP(H103,fixed_expenses4[],2,0),"") | K103: =IFERROR(VLOOKUP(J103,fixed_expenses4[],2,0),"") | M103: =IFERROR(VLOOKUP(L103,fixed_expenses4[],2,0),"") | O103: =IFERROR(VLOOKUP(N103,fixed_expenses4[],2,0),"")
C104: =IFERROR(VLOOKUP(B104,fixed_expenses4[],2,0),"") | E104: =IFERROR(VLOOKUP(D104,fixed_expenses4[],2,0),"") | G104: =IFERROR(VLOOKUP(F104,fixed_expenses4[],2,0),"") | I104: =IFERROR(VLOOKUP(H104,fixed_expenses4[],2,0),"") | K104: =IFERROR(VLOOKUP(J104,fixed_expenses4[],2,0),"") | M104: =IFERROR(VLOOKUP(L104,fixed_expenses4[],2,0),"") | O104: =IFERROR(VLOOKUP(N104,fixed_expenses4[],2,0),"")
C105: =IFERROR(VLOOKUP(B105,fixed_expenses4[],2,0),"") | E105: =IFERROR(VLOOKUP(D105,fixed_expenses4[],2,0),"") | G105: =IFERROR(VLOOKUP(F105,fixed_expenses4[],2,0),"") | I105: =IFERROR(VLOOKUP(H105,fixed_expenses4[],2,0),"") | K105: =IFERROR(VLOOKUP(J105,fixed_expenses4[],2,0),"") | M105: =IFERROR(VLOOKUP(L105,fixed_expenses4[],2,0),"") | O105: =IFERROR(VLOOKUP(N105,fixed_expenses4[],2,0),"")
C106: =IFERROR(VLOOKUP(B106,fixed_expenses4[],2,0),"") | E106: =IFERROR(VLOOKUP(D106,fixed_expenses4[],2,0),"") | G106: =IFERROR(VLOOKUP(F106,fixed_expenses4[],2,0),"") | I106: =IFERROR(VLOOKUP(H106,fixed_expenses4[],2,0),"") | K106: =IFERROR(VLOOKUP(J106,fixed_expenses4[],2,0),"") | M106: =IFERROR(VLOOKUP(L106,fixed_expenses4[],2,0),"") | O106: =IFERROR(VLOOKUP(N106,fixed_expenses4[],2,0),"")
A107: Total is auto calculated for each day and week in cell at right, cells C107 through P107. Next instruction is in cell A109. | B107: TOTAL | C107: =SUM(C102:C106) -> 0 | E107: =SUM(E102:E106) -> 0 | G107: =SUM(G102:G106) -> 0 | I107: =SUM(I102:I106) -> 0 | K107: =SUM(K102:K106) -> 0 | M107: =SUM(M102:M106) -> 0 | O107: =SUM(O102:O106) -> 0 | P107: =SUMIF(B100:N100,">="&15,C107:O107) -> 0
A109: Calendar dates are in cells at right, cells B109 through O109. | B109: =DAY(IF(DAY(FebSun1)=1,FebSun1+29,FebSun1+36)) -> 7 | D109: =DAY(IF(DAY(FebSun1)=1,FebSun1+30,FebSun1+37)) -> 8 | F109: =DAY(IF(DAY(FebSun1)=1,FebSun1+31,FebSun1+38)) -> 9 | H109: =DAY(IF(DAY(FebSun1)=1,FebSun1+32,FebSun1+39)) -> 10 | J109: =DAY(IF(DAY(FebSun1)=1,FebSun1+33,FebSun1+40)) -> 11 | L109: =DAY(IF(DAY(FebSun1)=1,FebSun1+34,FebSun1+41)) -> 12 | N109: =DAY(IF(DAY(FebSun1)=1,FebSun1+35,FebSun1+42)) -> 13
A110: Description and Amount labels are in cells at right, cells B110 through O110. | B110: DESCRIPTION | C110: AMOUNT | D110: DESCRIPTION | E110: AMOUNT | F110: DESCRIPTION | G110: AMOUNT | H110: DESCRIPTION | I110: AMOUNT | J110: DESCRIPTION | K110: AMOUNT | L110: DESCRIPTION | M110: AMOUNT | N110: DESCRIPTION | O110: AMOUNT
A111: Enter Description and Amount of each expense in cells at right, cells B111 through O115. Next instruction is in cell A116. | C111: =IFERROR(VLOOKUP(B111,fixed_expenses4[],2,0),"") | E111: =IFERROR(VLOOKUP(D111,fixed_expenses4[],2,0),"") | G111: =IFERROR(VLOOKUP(F111,fixed_expenses4[],2,0),"") | I111: =IFERROR(VLOOKUP(H111,fixed_expenses4[],2,0),"") | K111: =IFERROR(VLOOKUP(J111,fixed_expenses4[],2,0),"") | M111: =IFERROR(VLOOKUP(L111,fixed_expenses4[],2,0),"") | O111: =IFERROR(VLOOKUP(N111,fixed_expenses4[],2,0),"")
...
