Workbook

Sheet Discover Data
B1: Trans. Date | C1: Post Date | D1: Description | E1: Amount | F1: Category | G1: Short_Desc | H1: Date | I1: Reoccurring_Flag | J1: Category_2 | K1: CumAmount | N1: 01/2022 | O1: 02/2022 | P1: 03/2022 | Q1: 04/2022 | R1: 05/2022 | S1: 06/2022 | T1: 07/2022
A2: 0 | B2: 44562 | C2: 44562 | D2: Balance | E2: 3581.67 | F2: Balance | G2: Balance | K2: =dis_table[[#This Row],[Amount]] -> 3581.67 | M2: Automotive | N2: =SUMIFS(dis_table[Amount],dis_table[Category],$M2,dis_table[Date],N$1) -> 42.34 | O2: =SUMIFS(dis_table[Amount],dis_table[Category],$M2,dis_table[Date],O$1) -> 0 | P2: =SUMIFS(dis_table[Amount],dis_table[Category],$M2,dis_table[Date],P$1) -> 0 | Q2: =SUMIFS(dis_table[Amount],dis_table[Category],$M2,dis_table[Date],Q$1) -> 0 | R2: =SUMIFS(dis_table[Amount],dis_table[Category],$M2,dis_table[Date],R$1) -> 0 | S2: =SUMIFS(dis_table[Amount],dis_table[Category],$M2,dis_table[Date],S$1) -> 0 | T2: =SUMIFS(dis_table[Amount],dis_table[Category],$M2,dis_table[Date],T$1) -> 0
A3: 1 | B3: 44562 | C3: 44562 | D3: JIMMY JOHNS - 2500 PHOENIX AZ | E3: 18.02 | F3: Restaurants | G3: fast_food | H3: 01/2022 | I3: No | J3: Food | K3: =K2+dis_table[[#This Row],[Amount]] -> 3599.69 | M3: Education | N3: =SUMIFS(dis_table[Amount],dis_table[Category],$M3,dis_table[Date],N$1) -> 0 | O3: =SUMIFS(dis_table[Amount],dis_table[Category],$M3,dis_table[Date],O$1) -> 0 | P3: =SUMIFS(dis_table[Amount],dis_table[Category],$M3,dis_table[Date],P$1) -> 0 | Q3: =SUMIFS(dis_table[Amount],dis_table[Category],$M3,dis_table[Date],Q$1) -> 21.71 | R3: =SUMIFS(dis_table[Amount],dis_table[Category],$M3,dis_table[Date],R$1) -> 0 | S3: =SUMIFS(dis_table[Amount],dis_table[Category],$M3,dis_table[Date],S$1) -> 298 | T3: =SUMIFS(dis_table[Amount],dis_table[Category],$M3,dis_table[Date],T$1) -> 100.25
A4: 2 | B4: 44562 | C4: 44562 | D4: OLIVE GARDE00064212140 PHOENIX AZ | E4: 60 | F4: Restaurants | G4: restaurant | H4: 01/2022 | I4: No | J4: Food | K4: =K3+dis_table[[#This Row],[Amount]] -> 3659.69 | M4: Gasoline | N4: =SUMIFS(dis_table[Amount],dis_table[Category],$M4,dis_table[Date],N$1) -> 92.41 | O4: =SUMIFS(dis_table[Amount],dis_table[Category],$M4,dis_table[Date],O$1) -> 0 | P4: =SUMIFS(dis_table[Amount],dis_table[Category],$M4,dis_table[Date],P$1) -> 342.53 | Q4: =SUMIFS(dis_table[Amount],dis_table[Category],$M4,dis_table[Date],Q$1) -> 3.59 | R4: =SUMIFS(dis_table[Amount],dis_table[Category],$M4,dis_table[Date],R$1) -> 73.21 | S4: =SUMIFS(dis_table[Amount],dis_table[Category],$M4,dis_table[Date],S$1) -> 11.8 | T4: =SUMIFS(dis_table[Amount],dis_table[Category],$M4,dis_table[Date],T$1) -> 198.64
A5: 3 | B5: 44563 | C5: 44563 | D5: INTERNET PAYMENT - THANK YOU | E5: -1800 | F5: Payments and Credits | G5: payment | H5: 01/2022 | I5: No | K5: =K4+dis_table[[#This Row],[Amount]] -> 1859.69 | M5: Government Services | N5: =SUMIFS(dis_table[Amount],dis_table[Category],$M5,dis_table[Date],N$1) -> 0 | O5: =SUMIFS(dis_table[Amount],dis_table[Category],$M5,dis_table[Date],O$1) -> 0 | P5: =SUMIFS(dis_table[Amount],dis_table[Category],$M5,dis_table[Date],P$1) -> 35 | Q5: =SUMIFS(dis_table[Amount],dis_table[Category],$M5,dis_table[Date],Q$1) -> 0 | R5: =SUMIFS(dis_table[Amount],dis_table[Category],$M5,dis_table[Date],R$1) -> 0 | S5: =SUMIFS(dis_table[Amount],dis_table[Category],$M5,dis_table[Date],S$1) -> 0 | T5: =SUMIFS(dis_table[Amount],dis_table[Category],$M5,dis_table[Date],T$1) -> 0
A6: 4 | B6: 44562 | C6: 44564 | D6: NETFLIX.COM NETFLIX.COM CAITEM TRANSFERRED FROM PREV ACCOUNT | E6: 14.83 | F6: Merchandise | G6: netflix | H6: 01/2022 | I6: Yes | J6: Recreation_Entertainment | K6: =K5+dis_table[[#This Row],[Amount]] -> 1874.52 | M6: Home Improvement | N6: =SUMIFS(dis_table[Amount],dis_table[Category],$M6,dis_table[Date],N$1) -> 0 | O6: =SUMIFS(dis_table[Amount],dis_table[Category],$M6,dis_table[Date],O$1) -> 0 | P6: =SUMIFS(dis_table[Amount],dis_table[Category],$M6,dis_table[Date],P$1) -> 0 | Q6: =SUMIFS(dis_table[Amount],dis_table[Category],$M6,dis_table[Date],Q$1) -> 0 | R6: =SUMIFS(dis_table[Amount],dis_table[Category],$M6,dis_table[Date],R$1) -> 0 | S6: =SUMIFS(dis_table[Amount],dis_table[Category],$M6,dis_table[Date],S$1) -> 0 | T6: =SUMIFS(dis_table[Amount],dis_table[Category],$M6,dis_table[Date],T$1) -> 38.1
A7: 5 | B7: 44562 | C7: 44564 | D7: SPOTIFY P18D298A28 8777781161 NYITEM TRANSFERRED FROM PREV ACCOUNT | E7: 9.99 | F7: Merchandise | G7: spotify | H7: 01/2022 | I7: Yes | J7: Recreation_Entertainment | K7: =K6+dis_table[[#This Row],[Amount]] -> 1884.51 | M7: Interest | N7: =SUMIFS(dis_table[Amount],dis_table[Category],$M7,dis_table[Date],N$1) -> 0 | O7: =SUMIFS(dis_table[Amount],dis_table[Category],$M7,dis_table[Date],O$1) -> 0 | P7: =SUMIFS(dis_table[Amount],dis_table[Category],$M7,dis_table[Date],P$1) -> 0 | Q7: =SUMIFS(dis_table[Amount],dis_table[Category],$M7,dis_table[Date],Q$1) -> 0 | R7: =SUMIFS(dis_table[Amount],dis_table[Category],$M7,dis_table[Date],R$1) -> 50.48 | S7: =SUMIFS(dis_table[Amount],dis_table[Category],$M7,dis_table[Date],S$1) -> 99.24 | T7: =SUMIFS(dis_table[Amount],dis_table[Category],$M7,dis_table[Date],T$1) -> 99.19
A8: 6 | B8: 44563 | C8: 44564 | D8: KRYSTAL AND SAAGAR 2025317527 DCITEM TRANSFERRED FROM PREV ACCOUNT | E8: 10 | F8: Merchandise | G8: breaking_points | H8: 01/2022 | I8: Yes | J8: Recreation_Entertainment | K8: =K7+dis_table[[#This Row],[Amount]] -> 1894.51 | M8: Medical Services | N8: =SUMIFS(dis_table[Amount],dis_table[Category],$M8,dis_table[Date],N$1) -> 0 | O8: =SUMIFS(dis_table[Amount],dis_table[Category],$M8,dis_table[Date],O$1) -> 0 | P8: =SUMIFS(dis_table[Amount],dis_table[Category],$M8,dis_table[Date],P$1) -> 432 | Q8: =SUMIFS(dis_table[Amount],dis_table[Category],$M8,dis_table[Date],Q$1) -> 0 | R8: =SUMIFS(dis_table[Amount],dis_table[Category],$M8,dis_table[Date],R$1) -> 37.5 | S8: =SUMIFS(dis_table[Amount],dis_table[Category],$M8,dis_table[Date],S$1) -> 0 | T8: =SUMIFS(dis_table[Amount],dis_table[Category],$M8,dis_table[Date],T$1) -> 0
A9: 7 | B9: 44564 | C9: 44564 | D9: PAYPAL *HULU 402-935-7733 CA | E9: 12.99 | F9: Services | G9: hulu | H9: 01/2022 | I9: Yes | J9: Recreation_Entertainment | K9: =K8+dis_table[[#This Row],[Amount]] -> 1907.5 | M9: Merchandise | N9: =SUMIFS(dis_table[Amount],dis_table[Category],$M9,dis_table[Date],N$1) -> 802.23 | O9: =SUMIFS(dis_table[Amount],dis_table[Category],$M9,dis_table[Date],O$1) -> 473.95 | P9: =SUMIFS(dis_table[Amount],dis_table[Category],$M9,dis_table[Date],P$1) -> 1208.91 | Q9: =SUMIFS(dis_table[Amount],dis_table[Category],$M9,dis_table[Date],Q$1) -> 1041.03 | R9: =SUMIFS(dis_table[Amount],dis_table[Category],$M9,dis_table[Date],R$1) -> 1359.53 | S9: =SUMIFS(dis_table[Amount],dis_table[Category],$M9,dis_table[Date],S$1) -> 900.1 | T9: =SUMIFS(dis_table[Amount],dis_table[Category],$M9,dis_table[Date],T$1) -> 1110.46
A10: 8 | B10: 44565 | C10: 44565 | D10: AUTOZONE #2768 PHOENIX AZ | E10: 42.34 | F10: Automotive | G10: car | H10: 01/2022 | I10: No | J10: Utilities | K10: =K9+dis_table[[#This Row],[Amount]] -> 1949.84 | M10: Restaurants | N10: =SUMIFS(dis_table[Amount],dis_table[Category],$M10,dis_table[Date],N$1) -> 388.66 | O10: =SUMIFS(dis_table[Amount],dis_table[Category],$M10,dis_table[Date],O$1) -> 115.83 | P10: =SUMIFS(dis_table[Amount],dis_table[Category],$M10,dis_table[Date],P$1) -> 1073.85 | Q10: =SUMIFS(dis_table[Amount],dis_table[Category],$M10,dis_table[Date],Q$1) -> 575.54 | R10: =SUMIFS(dis_table[Amount],dis_table[Category],$M10,dis_table[Date],R$1) -> 770.3 | S10: =SUMIFS(dis_table[Amount],dis_table[Category],$M10,dis_table[Date],S$1) -> 478.24 | T10: =SUMIFS(dis_table[Amount],dis_table[Category],$M10,dis_table[Date],T$1) -> 441.53
A11: 9 | B11: 44565 | C11: 44565 | D11: STATE FARM INSURANCE 800-956-6310 ILITEM TRANSFERRED FROM PREV ACCOUNT | E11: 79.38 | F11: Merchandise | G11: state_farm | H11: 01/2022 | I11: Yes | J11: Insurance | K11: =K10+dis_table[[#This Row],[Amount]] -> 2029.22 | M11: Services | N11: =SUMIFS(dis_table[Amount],dis_table[Category],$M11,dis_table[Date],N$1) -> 497.44 | O11: =SUMIFS(dis_table[Amount],dis_table[Category],$M11,dis_table[Date],O$1) -> 132.57 | P11: =SUMIFS(dis_table[Amount],dis_table[Category],$M11,dis_table[Date],P$1) -> 378.81 | Q11: =SUMIFS(dis_table[Amount],dis_table[Category],$M11,dis_table[Date],Q$1) -> 78.88 | R11: =SUMIFS(dis_table[Amount],dis_table[Category],$M11,dis_table[Date],R$1) -> 138.95 | S11: =SUMIFS(dis_table[Amount],dis_table[Category],$M11,dis_table[Date],S$1) -> 134.85 | T11: =SUMIFS(dis_table[Amount],dis_table[Category],$M11,dis_table[Date],T$1) -> 246.78
A12: 10 | B12: 44566 | C12: 44566 | D12: MCDONALD'S F20697 PHOENIX AZAPPLE PAY ENDING IN 4775 | E12: 8 | F12: Restaurants | G12: fast_food | H12: 01/2022 | I12: No | J12: Food | K12: =K11+dis_table[[#This Row],[Amount]] -> 2037.22 | M12: Supermarkets | N12: =SUMIFS(dis_table[Amount],dis_table[Category],$M12,dis_table[Date],N$1) -> 151.27 | O12: =SUMIFS(dis_table[Amount],dis_table[Category],$M12,dis_table[Date],O$1) -> 132.46 | P12: =SUMIFS(dis_table[Amount],dis_table[Category],$M12,dis_table[Date],P$1) -> 12.27 | Q12: =SUMIFS(dis_table[Amount],dis_table[Category],$M12,dis_table[Date],Q$1) -> 459.72 | R12: =SUMIFS(dis_table[Amount],dis_table[Category],$M12,dis_table[Date],R$1) -> 46.36 | S12: =SUMIFS(dis_table[Amount],dis_table[Category],$M12,dis_table[Date],S$1) -> 181.77 | T12: =SUMIFS(dis_table[Amount],dis_table[Category],$M12,dis_table[Date],T$1) -> 294.14
A13: 11 | B13: 44569 | C13: 44569 | D13: 3856 EL POLLO LOCO PHOENIX AZ | E13: 29.93 | F13: Restaurants | G13: fast_food | H13: 01/2022 | I13: No | J13: Food | K13: =K12+dis_table[[#This Row],[Amount]] -> 2067.15 | M13: Travel/ Entertainment | N13: =SUMIFS(dis_table[Amount],dis_table[Category],$M13,dis_table[Date],N$1) -> 217.36 | O13: =SUMIFS(dis_table[Amount],dis_table[Category],$M13,dis_table[Date],O$1) -> 608.72 | P13: =SUMIFS(dis_table[Amount],dis_table[Category],$M13,dis_table[Date],P$1) -> 422 | Q13: =SUMIFS(dis_table[Amount],dis_table[Category],$M13,dis_table[Date],Q$1) -> 409.8 | R13: =SUMIFS(dis_table[Amount],dis_table[Category],$M13,dis_table[Date],R$1) -> 1511.29 | S13: =SUMIFS(dis_table[Amount],dis_table[Category],$M13,dis_table[Date],S$1) -> 1230.06 | T13: =SUMIFS(dis_table[Amount],dis_table[Category],$M13,dis_table[Date],T$1) -> 418.69
A14: 12 | B14: 44569 | C14: 44569 | D14: DRI*NVIDIA STORE NVIDIA.COM MNITEM TRANSFERRED FROM PREV ACCOUNT | E14: 4.99 | F14: Merchandise | G14: nvidia | H14: 01/2022 | I14: Yes | J14: Recreation_Entertainment | K14: =K13+dis_table[[#This Row],[Amount]] -> 2072.14 | M14: Balance | N14: =SUM(N2:N13) -> 2191.71 | O14: =SUM(O2:O13) -> 1463.53 | P14: =SUM(P2:P13) -> 3905.37 | Q14: =SUM(Q2:Q13) -> 2590.27 | R14: =SUM(R2:R13) -> 3987.62 | S14: =SUM(S2:S13) -> 3334.06 | T14: =SUM(T2:T13) -> 2947.78
A15: 13 | B15: 44570 | C15: 44570 | D15: SAFEWAY #2651 PHOENIX AZ | E15: 32.58 | F15: Supermarkets | G15: groceries | H15: 01/2022 | I15: No | J15: Food | K15: =K14+dis_table[[#This Row],[Amount]] -> 2104.72 | M15: Payments and Credits | N15: =SUMIFS(dis_table[Amount],dis_table[Category],$M15,dis_table[Date],N$1) -> -3994.92 | O15: =SUMIFS(dis_table[Amount],dis_table[Category],$M15,dis_table[Date],O$1) -> -2509.43 | P15: =SUMIFS(dis_table[Amount],dis_table[Category],$M15,dis_table[Date],P$1) -> -1969.1 | Q15: =SUMIFS(dis_table[Amount],dis_table[Category],$M15,dis_table[Date],Q$1) -> -934.85 | R15: =SUMIFS(dis_table[Amount],dis_table[Category],$M15,dis_table[Date],R$1) -> -2000 | S15: =SUMIFS(dis_table[Amount],dis_table[Category],$M15,dis_table[Date],S$1) -> -4008 | T15: =SUMIFS(dis_table[Amount],dis_table[Category],$M15,dis_table[Date],T$1) -> -2601
A16: 14 | B16: 44570 | C16: 44570 | D16: PAYPAL *HEARSTMAGAZ 402-935-7733 CA | E16: 20 | F16: Merchandise | G16: pay_wall | H16: 01/2022 | I16: Yes | J16: Recreation_Entertainment | K16: =K15+dis_table[[#This Row],[Amount]] -> 2124.72 | M16: Awards and Rebate Credits | N16: =SUMIFS(dis_table[Amount],dis_table[Category],$M16,dis_table[Date],N$1) -> -29.08 | O16: =SUMIFS(dis_table[Amount],dis_table[Category],$M16,dis_table[Date],O$1) -> -29.29 | P16: =SUMIFS(dis_table[Amount],dis_table[Category],$M16,dis_table[Date],P$1) -> 0 | Q16: =SUMIFS(dis_table[Amount],dis_table[Category],$M16,dis_table[Date],Q$1) -> -65.15 | R16: =SUMIFS(dis_table[Amount],dis_table[Category],$M16,dis_table[Date],R$1) -> -41.23 | S16: =SUMIFS(dis_table[Amount],dis_table[Category],$M16,dis_table[Date],S$1) -> 0 | T16: =SUMIFS(dis_table[Amount],dis_table[Category],$M16,dis_table[Date],T$1) -> 0
A17: 15 | B17: 44570 | C17: 44570 | D17: SAFEWAY #2651 PHOENIX AZ | E17: 2.49 | F17: Supermarkets | G17: groceries | H17: 01/2022 | I17: No | J17: Food | K17: =K16+dis_table[[#This Row],[Amount]] -> 2127.21
A18: 16 | B18: 44570 | C18: 44570 | D18: SAFEWAY #2651 PHOENIX AZ | E18: 36.72 | F18: Supermarkets | G18: groceries | H18: 01/2022 | I18: No | J18: Food | K18: =K17+dis_table[[#This Row],[Amount]] -> 2163.93 | N18: 01/2022 | O18: 02/2022 | P18: 03/2022 | Q18: 04/2022 | R18: 05/2022 | S18: 06/2022 | T18: 07/2022
A19: 17 | B19: 44571 | C19: 44571 | D19: AMZN MKTP US*BP5036MA3 AMZN.COM/BILLWAITEM TRANSFERRED FROM PREV ACCOUNT | E19: 49.98 | F19: Merchandise | G19: amazon | H19: 01/2022 | I19: No | K19: =K18+dis_table[[#This Row],[Amount]] -> 2213.91 | M19: =M14 -> Balance | N19: 3659.69 | O19: =O14 -> 1463.53 | P19: =P14 -> 3905.37 | Q19: =Q14 -> 2590.27 | R19: =R14 -> 3987.62 | S19: =S14 -> 3334.06 | T19: =T14 -> 2947.78
A20: 18 | B20: 44571 | C20: 44571 | D20: MCDONALD'S F20697 PHOENIX AZ | E20: 10.09 | F20: Restaurants | G20: fast_food | H20: 01/2022 | I20: No | J20: Food | K20: =K19+dis_table[[#This Row],[Amount]] -> 2224 | M20: =M15 -> Payments and Credits | N20: =N15*-1 -> 3994.92 | O20: =O15*-1 -> 2509.43 | P20: =P15*-1 -> 1969.1 | Q20: =Q15*-1 -> 934.85 | R20: =R15*-1 -> 2000 | S20: =S15*-1 -> 4008 | T20: =T15*-1 -> 2601
A21: 19 | B21: 44572 | C21: 44572 | D21: LIFE TIME ATHLETIC 279 PHOENIX AZ01118R | E21: 210 | F21: Travel/ Entertainment | G21: gym | H21: 01/2022 | I21: No | J21: Personal_Spending | K21: =K20+dis_table[[#This Row],[Amount]] -> 2434
A22: 20 | B22: 44573 | C22: 44573 | D22: CVS/PHARMACY #09252 SCOTTSDALE AZAPPLE PAY ENDING IN 4775 | E22: 19.8 | F22: Merchandise | G22: conv_store | H22: 01/2022 | I22: No | J22: Personal_Spending | K22: =K21+dis_table[[#This Row],[Amount]] -> 2453.8
A23: 21 | B23: 44573 | C23: 44573 | D23: CAFE RIO 0084 SCOTTSDALE SCOTTSDALE AZ | E23: 15.1 | F23: Restaurants | G23: fast_food | H23: 01/2022 | I23: No | J23: Food | K23: =K22+dis_table[[#This Row],[Amount]] -> 2468.9
A24: 22 | B24: 44574 | C24: 44574 | D24: INTERNET PAYMENT - THANK YOU | E24: -2194.92 | F24: Payments and Credits | G24: payment | H24: 01/2022 | I24: No | K24: =K23+dis_table[[#This Row],[Amount]] -> 273.98
A25: 23 | B25: 44574 | C25: 44574 | D25: CIRCLE K 01930 YUMA AZ01374R | E25: 30.89 | F25: Gasoline | G25: gas_station | H25: 01/2022 | I25: No | J25: Transportation | K25: =K24+dis_table[[#This Row],[Amount]] -> 304.87
A26: 24 | B26: 44574 | C26: 44574 | D26: CASHBACK BONUS REDEMPTION PYMT/STMT CRDT | E26: -29.08 | F26: Awards and Rebate Credits | G26: cashback_bonus | H26: 01/2022 | I26: No | K26: =K25+dis_table[[#This Row],[Amount]] -> 275.79
A27: 25 | B27: 44575 | C27: 44575 | D27: MCDONALDS 20697 PHOENIX AZ | E27: 6.29 | F27: Restaurants | G27: fast_food | H27: 01/2022 | I27: No | J27: Food | K27: =K26+dis_table[[#This Row],[Amount]] -> 282.08
A28: 26 | B28: 44575 | C28: 44575 | D28: APPLE.COM/BILL 866-712-7753 CAAPPLE PAY ENDING IN 4775MMW7SF5QV8A0 | E28: 15.89 | F28: Merchandise | G28: hbo | H28: 01/2022 | I28: Yes | J28: Recreation_Entertainment | K28: =K27+dis_table[[#This Row],[Amount]] -> 297.97
A29: 27 | B29: 44576 | C29: 44576 | D29: THE CRACK SHACK LITTLE I SAN DIEGO CA | E29: 52.41 | F29: Restaurants | G29: restaurant | H29: 01/2022 | I29: No | J29: Food | K29: =K28+dis_table[[#This Row],[Amount]] -> 350.38
A30: 28 | B30: 44576 | C30: 44576 | D30: TACOS EL GORDO - CHULA V CHULA VISTA CA | E30: 21.49 | F30: Restaurants | G30: fast_food | H30: 01/2022 | I30: No | J30: Food | K30: =K29+dis_table[[#This Row],[Amount]] -> 371.87
A31: 29 | B31: 44576 | C31: 44576 | D31: RALPHS # 0212 SAN DIEGO CA | E31: 35.02 | F31: Supermarkets | G31: groceries | H31: 01/2022 | I31: No | J31: Food | K31: =K30+dis_table[[#This Row],[Amount]] -> 406.89
A32: 30 | B32: 44577 | C32: 44577 | D32: ZOO TICKETS AND TOURS SAN DIEGO CA0001000185182201161649 | E32: 62 | F32: Services | G32: zoo | H32: 01/2022 | I32: No | J32: Recreation_Entertainment | K32: =K31+dis_table[[#This Row],[Amount]] -> 468.89
A33: 31 | B33: 44577 | C33: 44577 | D33: APPLE.COM/BILL 111-111-1111 CAAPPLE PAY ENDING IN 4775 | E33: 26.49 | F33: Merchandise | G33: unsure | H33: 01/2022 | I33: No | J33: Misc | K33: =K32+dis_table[[#This Row],[Amount]] -> 495.38
A34: 32 | B34: 44578 | C34: 44578 | D34: 7-ELEVEN 21028 EL CENTRO CAAPPLE PAY ENDING IN 4775 | E34: 2.99 | F34: Gasoline | G34: conv_store | H34: 01/2022 | I34: No | J34: Personal_Spending | K34: =K33+dis_table[[#This Row],[Amount]] -> 498.37
A35: 33 | B35: 44578 | C35: 44578 | D35: CHEVRON 0207812 YUMA AZ00207812 1200537 R | E35: 24.15 | F35: Gasoline | G35: gas_station | H35: 01/2022 | I35: No | J35: Transportation | K35: =K34+dis_table[[#This Row],[Amount]] -> 522.52
A36: 34 | B36: 44578 | C36: 44578 | D36: BURGER KING #25911 YUMA AZ | E36: 12.68 | F36: Restaurants | G36: fast_food | H36: 01/2022 | I36: No | J36: Food | K36: =K35+dis_table[[#This Row],[Amount]] -> 535.2
A37: 35 | B37: 44578 | C37: 44578 | D37: TMOBILE*AUTO PAY 800-937-8997 WAITEM TRANSFERRED FROM PREV ACCOUNT | E37: 70 | F37: Merchandise | G37: cell_phone | H37: 01/2022 | I37: Yes | J37: Utilities | K37: =K36+dis_table[[#This Row],[Amount]] -> 605.2
A38: 36 | B38: 44579 | C38: 44579 | D38: APPLE.COM/BILL 866-712-7753 CAAPPLE PAY ENDING IN 4775MMW7VVNMDVA0 | E38: 5.29 | F38: Merchandise | G38: apple_tv | H38: 01/2022 | I38: Yes | J38: Recreation_Entertainment | K38: =K37+dis_table[[#This Row],[Amount]] -> 610.49
... A48: 46 | B48: 44583 | C48: 44583 | D48: OCOTILLO VILLAGE HEALTH CHANDLER AZ | E48: 7.36 | F48: Travel/ Entertainment | G48: fast_food | H48: 01/2022 | I48: No | J48: Food | K48: =K47+dis_table[[#This Row],[Amount]] -> 1058.76
A49: 47 | B49: 44583 | C49: 44583 | D49: AMZN MKTP US*FL5G52C63 AMZN.COM/BILLWAITEM TRANSFERRED FROM PREV ACCOUNT | E49: 32.98 | F49: Merchandise | G49: amazon | H49: 01/2022 | I49: No | K49: =K48+dis_table[[#This Row],[Amount]] -> 1091.74
A50: 48 | B50: 44583 | C50: 44583 | D50: AMZN MKTP US*VD9Y872T3 AMZN.COM/BILLWAITEM TRANSFERRED FROM PREV ACCOUNT | E50: 29.99 | F50: Merchandise | G50: amazon | H50: 01/2022 | I50: No | K50: =K49+dis_table[[#This Row],[Amount]] -> 1121.73
A51: 49 | B51: 44583 | C51: 44583 | D51: AMZN MKTP US*YX9X26H73 AMZN.COM/BILLWAITEM TRANSFERRED FROM PREV ACCOUNT | E51: 22.79 | F51: Merchandise | G51: amazon | H51: 01/2022 | I51: No | K51: =K50+dis_table[[#This Row],[Amount]] -> 1144.52
A52: 50 | B52: 44584 | C52: 44584 | D52: PAYPAL *GRAMMARLY ZDYBC 402-935-7733 CA | E52: 30 | F52: Merchandise | G52: grammarly | H52: 01/2022 | I52: Yes | J52: Recreation_Entertainment | K52: =K51+dis_table[[#This Row],[Amount]] -> 1174.52
A53: 51 | B53: 44586 | C53: 44586 | D53: CLR*STRETCHZONE480687187 480-687-1874 TITEM TRANSFERRED FROM PREV ACCOUNT | E53: 79 | F53: Merchandise | G53: stretch_zone | H53: 01/2022 | I53: Yes | J53: Personal_Spending | K53: =K52+dis_table[[#This Row],[Amount]] -> 1253.52
A54: 52 | B54: 44587 | C54: 44587 | D54: STAPLES 00103929105 PHOENIX AZ | E54: 2.17 | F54: Merchandise | G54: staples | H54: 01/2022 | I54: No | J54: Personal_Spending | K54: =K53+dis_table[[#This Row],[Amount]] -> 1255.69
A55: 53 | B55: 44587 | C55: 44587 | D55: STAPLES 00103929105 PHOENIX AZ | E55: 1.87 | F55: Merchandise | G55: staples | H55: 01/2022 | I55: No | J55: Personal_Spending | K55: =K54+dis_table[[#This Row],[Amount]] -> 1257.56
A56: 54 | B56: 44587 | C56: 44587 | D56: PAYPAL *INTERACTIVE 402-935-7733 CA | E56: 210 | F56: Services | G56: learning | H56: 01/2022 | I56: No | J56: Personal_Spending | K56: =K55+dis_table[[#This Row],[Amount]] -> 1467.56
A57: 55 | B57: 44587 | C57: 44587 | D57: PAYPAL *INTERACTIVE 402-935-7733 CA | E57: 30 | F57: Services | G57: learning | H57: 01/2022 | I57: No | J57: Personal_Spending | K57: =K56+dis_table[[#This Row],[Amount]] -> 1497.56
A58: 56 | B58: 44587 | C58: 44587 | D58: MCDONALD'S F20697 PHOENIX AZ | E58: 9 | F58: Restaurants | G58: fast_food | H58: 01/2022 | I58: No | J58: Food | K58: =K57+dis_table[[#This Row],[Amount]] -> 1506.56
A59: 57 | B59: 44589 | C59: 44589 | D59: STAPLES 00103929105 PHOENIX AZ | E59: 5.67 | F59: Merchandise | G59: staples | H59: 01/2022 | I59: No | J59: Personal_Spending | K59: =K58+dis_table[[#This Row],[Amount]] -> 1512.23
A60: 58 | B60: 44589 | C60: 44589 | D60: STAPLES 00103929105 PHOENIX AZ | E60: 4.15 | F60: Merchandise | G60: staples | H60: 01/2022 | I60: No | J60: Personal_Spending | K60: =K59+dis_table[[#This Row],[Amount]] -> 1516.38
A61: 59 | B61: 44589 | C61: 44589 | D61: SQ *NORA ASIAN FRESH PHOENIX AZ0002305843015128013485 | E61: 24.36 | F61: Restaurants | G61: fast_food | H61: 01/2022 | I61: No | J61: Food | K61: =K60+dis_table[[#This Row],[Amount]] -> 1540.74
A62: 60 | B62: 44589 | C62: 44589 | D62: MCDONALD'S F20697 PHOENIX AZ | E62: 6.83 | F62: Restaurants | G62: fast_food | H62: 01/2022 | I62: No | J62: Food | K62: =K61+dis_table[[#This Row],[Amount]] -> 1547.57
A63: 61 | B63: 44589 | C63: 44589 | D63: STAPLES 00103929105 PHOENIX AZ | E63: 6.86 | F63: Merchandise | G63: staples | H63: 01/2022 | I63: No | J63: Personal_Spending | K63: =K62+dis_table[[#This Row],[Amount]] -> 1554.43
... A84: 82 | B84: 44600 | C84: 44600 | D84: JIMMY JOHNS - 2500 - ECO PHOENIX AZAPPLE PAY ENDING IN 4775 | E84: 4.66 | F84: Restaurants | G84: fast_food | H84: 02/2022 | I84: No | J84: Food | K84: =K83+dis_table[[#This Row],[Amount]] -> 2388.94
A85: 83 | B85: 44602 | C85: 44602 | D85: INTERNET PAYMENT - THANK YOU | E85: -1733.33 | F85: Payments and Credits | G85: payment | H85: 02/2022 | I85: No | K85: =K84+dis_table[[#This Row],[Amount]] -> 655.61
A86: 84 | B86: 44602 | C86: 44602 | D86: APPLE.COM/BILL 866-712-7753 CAAPPLE PAY ENDING IN 4775MMW8436DXMA0 | E86: 15.89 | F86: Merchandise | G86: hbo | H86: 02/2022 | I86: Yes | J86: Recreation_Entertainment | K86: =K85+dis_table[[#This Row],[Amount]] -> 671.5
A87: 85 | B87: 44603 | C87: 44603 | D87: CLR*STRETCHZONE480687187 480-687-1874 TITEM TRANSFERRED FROM PREV ACCOUNT | E87: -5 | F87: Payments and Credits | G87: stretch_zone | H87: 02/2022 | I87: Yes | J87: Personal_Spending | K87: =K86+dis_table[[#This Row],[Amount]] -> 666.5
A88: 86 | B88: 44604 | C88: 44604 | D88: AMZN MKTP US*9T8VU3NC3 AMZN.COM/BILLWAITEM TRANSFERRED FROM PREV ACCOUNT | E88: 9.2 | F88: Merchandise | G88: amazon | H88: 02/2022 | I88: No | K88: =K87+dis_table[[#This Row],[Amount]] -> 675.7
A89: 87 | B89: 44605 | C89: 44605 | D89: AMZN MKTP US*RX32S1F23 AMZN.COM/BILLWAITEM TRANSFERRED FROM PREV ACCOUNT | E89: 14.11 | F89: Merchandise | G89: amazon | H89: 02/2022 | I89: No | K89: =K88+dis_table[[#This Row],[Amount]] -> 689.81
A90: 88 | B90: 44605 | C90: 44605 | D90: JIMMY JOHNS - 2500 - ECO PHOENIX AZAPPLE PAY ENDING IN 4775 | E90: 20 | F90: Restaurants | G90: fast_food | H90: 02/2022 | I90: No | J90: Food | K90: =K89+dis_table[[#This Row],[Amount]] -> 709.81
A91: 89 | B91: 44605 | C91: 44605 | D91: APPLE.COM/BILL 111-111-1111 CAAPPLE PAY ENDING IN 4775 | E91: 14.99 | F91: Merchandise | G91: nba_league_pass | H91: 02/2022 | I91: Yes | J91: Recreation_Entertainment | K91: =K90+dis_table[[#This Row],[Amount]] -> 724.8
A92: 90 | B92: 44606 | C92: 44606 | D92: JIMMY JOHNS - 2500 - ECO PHOENIX AZAPPLE PAY ENDING IN 4775 | E92: 26.59 | F92: Restaurants | G92: fast_food | H92: 02/2022 | I92: No | J92: Food | K92: =K91+dis_table[[#This Row],[Amount]] -> 751.39
A93: 91 | B93: 44607 | C93: 44607 | D93: AF*REAL PROPERTY MANA. 866-648-1536 CA | E93: 49 | F93: Services | G93: dad | H93: 02/2022 | I93: No | J93: People | K93: =K92+dis_table[[#This Row],[Amount]] -> 800.39
A94: 92 | B94: 44608 | C94: 44608 | D94: CCBILL.COM 888-5969279 AZITEM TRANSFERRED FROM PREV ACCOUNT | E94: 12 | F94: Merchandise | G94: onlyfans | H94: 02/2022 | I94: No | J94: Recreation_Entertainment | K94: =K93+dis_table[[#This Row],[Amount]] -> 812.39
A95: 93 | B95: 44609 | C95: 44609 | D95: TMOBILE*AUTO PAY 800-937-8997 WAITEM TRANSFERRED FROM PREV ACCOUNT | E95: 70 | F95: Merchandise | G95: cell_phone | H95: 02/2022 | I95: Yes | J95: Utilities | K95: =K94+dis_table[[#This Row],[Amount]] -> 882.39
A96: 94 | B96: 44611 | C96: 44611 | D96: APPLE.COM/BILL 866-712-7753 CAAPPLE PAY ENDING IN 4775MMW86H07HVA0 | E96: 5.29 | F96: Merchandise | G96: apple_tv | H96: 02/2022 | I96: Yes | J96: Recreation_Entertainment | K96: =K95+dis_table[[#This Row],[Amount]] -> 887.68
A97: 95 | B97: 44612 | C97: 44612 | D97: CASHBACK BONUS REDEMPTION PYMT/STMT CRDT | E97: -29.29 | F97: Awards and Rebate Credits | G97: cashback_bonus | H97: 02/2022 | I97: No | K97: =K96+dis_table[[#This Row],[Amount]] -> 858.39
A98: 96 | B98: 44612 | C98: 44612 | D98: GOOGLE *YOUTUBE TV G.CO/HELPPAY#CAP0HR9LUQ | E98: 70.58 | F98: Services | G98: youtube_tv | H98: 02/2022 | I98: Yes | J98: Recreation_Entertainment | K98: =K97+dis_table[[#This Row],[Amount]] -> 928.97
A99: 97 | B99: 44612 | C99: 44612 | D99: INTERNET PAYMENT - THANK YOU | E99: -771.1 | F99: Payments and Credits | G99: payment | H99: 02/2022 | I99: No | K99: =K98+dis_table[[#This Row],[Amount]] -> 157.87
A100: 98 | B100: 44613 | C100: 44613 | D100: CCBILL.COM 888-5969279 AZITEM TRANSFERRED FROM PREV ACCOUNT | E100: 11 | F100: Merchandise | G100: onlyfans | H100: 02/2022 | I100: No | J100: Recreation_Entertainment | K100: =K99+dis_table[[#This Row],[Amount]] -> 168.87
A101: 99 | B101: 44615 | C101: 44615 | D101: PAYPAL *GRAMMARLY A0Q7H 402-935-7733 CA | E101: 30 | F101: Merchandise | G101: grammarly | H101: 02/2022 | I101: Yes | J101: Recreation_Entertainment | K101: =K100+dis_table[[#This Row],[Amount]] -> 198.87
A102: 100 | B102: 44616 | C102: 44616 | D102: CAVASSON EASTSIDE CAFE SCOTTSDALE AZ | E102: 14.16 | F102: Restaurants | G102: work_lunch | H102: 02/2022 | I102: No | J102: Food | K102: =K101+dis_table[[#This Row],[Amount]] -> 213.03
A103: 101 | B103: 44616 | C103: 44616 | D103: CAVASSON EASTSIDE CAFE SCOTTSDALE AZ | E103: 1.62 | F103: Restaurants | G103: work_lunch | H103: 02/2022 | I103: No | J103: Food | K103: =K102+dis_table[[#This Row],[Amount]] -> 214.65
A104: 102 | B104: 44617 | C104: 44617 | D104: WALMART SC 04232 PHOENIX AZ | E104: 126.7 | F104: Merchandise | G104: walmart | H104: 02/2022 | I104: No | J104: Personal_Spending | K104: =K103+dis_table[[#This Row],[Amount]] -> 341.35
A105: 103 | B105: 44617 | C105: 44617 | D105: PAYPAL *FRONTGATETX INN 402-935-7733 CA | E105: 130.18 | F105: Travel/ Entertainment | G105: music_festival | H105: 02/2022 | I105: No | J105: Recreation_Entertainment | K105: =K104+dis_table[[#This Row],[Amount]] -> 471.53
A106: 104 | B106: 44617 | C106: 44617 | D106: ALBERTSONS #0966 SCOTTSDALE AZ | E106: 9.32 | F106: Supermarkets | G106: groceries | H106: 02/2022 | I106: No | J106: Food | K106: =K105+dis_table[[#This Row],[Amount]] -> 480.85
A107: 105 | B107: 44618 | C107: 44618 | D107: CHARLIE'S PHOENIX PHOENIX AZ | E107: 18 | F107: Restaurants | G107: restaurant | H107: 02/2022 | I107: No | J107: Food | K107: =K106+dis_table[[#This Row],[Amount]] -> 498.85
A108: 106 | B108: 44618 | C108: 44618 | D108: PAYPAL *SPORTPLANLT 402-935-7733 CA | E108: 29.99 | F108: Merchandise | G108: pay_wall | H108: 02/2022 | I108: Yes | J108: Recreation_Entertainment | K108: =K107+dis_table[[#This Row],[Amount]] -> 528.84
A109: 107 | B109: 44619 | C109: 44619 | D109: BR: INNINGS FEST AUSTIN TX | E109: 18.89 | F109: Travel/ Entertainment | G109: music_festival | H109: 02/2022 | I109: No | J109: Recreation_Entertainment | K109: =K108+dis_table[[#This Row],[Amount]] -> 547.73
A110: 108 | B110: 44619 | C110: 44619 | D110: BR: INNINGS FEST AUSTIN TX | E110: 31.02 | F110: Travel/ Entertainment | G110: music_festival | H110: 02/2022 | I110: No | J110: Recreation_Entertainment | K110: =K109+dis_table[[#This Row],[Amount]] -> 578.75
A111: 109 | B111: 44619 | C111: 44619 | D111: BR: INNINGS FEST AUSTIN TX | E111: 41.37 | F111: Travel/ Entertainment | G111: music_festival | H111: 02/2022 | I111: No | J111: Recreation_Entertainment | K111: =K110+dis_table[[#This Row],[Amount]] -> 620.12
... A130: 128 | B130: 44624 | C130: 44624 | D130: SHOWTIME 888-965-7469 NY | E130: 11.94 | F130: Merchandise | G130: live_event | H130: 03/2022 | I130: No | J130: Recreation_Entertainment | K130: =K129+dis_table[[#This Row],[Amount]] -> 1103.16
A131: 129 | B131: 44625 | C131: 44625 | D131: AMZN MKTP US*1W4E475R0 AMZN.COM/BILLWAITEM TRANSFERRED FROM PREV ACCOUNT | E131: 21.22 | F131: Merchandise | G131: amazon | H131: 03/2022 | I131: No | K131: =K130+dis_table[[#This Row],[Amount]] -> 1124.38
A132: 130 | B132: 44626 | C132: 44626 | D132: TST* WOW WOW HAWAIIAN LE PHOENIX AZ | E132: 6.02 | F132: Restaurants | G132: fast_food | H132: 03/2022 | I132: No | J132: Food | K132: =K131+dis_table[[#This Row],[Amount]] -> 1130.4
A133: 131 | B133: 44626 | C133: 44626 | D133: ST JOHN VIANNEY GIFT SHO SEDONA AZ | E133: 42 | F133: Merchandise | G133: dad | H133: 03/2022 | I133: No | J133: People | K133: =K132+dis_table[[#This Row],[Amount]] -> 1172.4
A134: 132 | B134: 44626 | C134: 44626 | D134: ROTTEN JOHNNY S SEDONA AZ | E134: 25 | F134: Restaurants | G134: restaurant | H134: 03/2022 | I134: No | J134: Food | K134: =K133+dis_table[[#This Row],[Amount]] -> 1197.4
A135: 133 | B135: 44626 | C135: 44626 | D135: REI #56 PARADISE VAL PHOENIX AZ0927610560271410 | E135: 277.61 | F135: Merchandise | G135: clothing | H135: 03/2022 | I135: No | J135: Personal_Spending | K135: =K134+dis_table[[#This Row],[Amount]] -> 1475.01
A136: 134 | B136: 44627 | C136: 44627 | D136: WABA HAIR SUPPLY #5 PHOENIX AZ | E136: 47.51 | F136: Merchandise | G136: hair_supplies | H136: 03/2022 | I136: No | J136: Personal_Spending | K136: =K135+dis_table[[#This Row],[Amount]] -> 1522.52
A137: 135 | B137: 44627 | C137: 44627 | D137: WHATABURGER 1223 TEMPE AZ51 | E137: 12.52 | F137: Restaurants | G137: fast_food | H137: 03/2022 | I137: No | J137: Food | K137: =K136+dis_table[[#This Row],[Amount]] -> 1535.04
A138: 136 | B138: 44628 | C138: 44628 | D138: SEE TICKETS *BAHAMAS - G 323-908-0607 CASEE TICKETS *BAHAMAS - G | E138: 77.66 | F138: Travel/ Entertainment | G138: concerts | H138: 03/2022 | I138: No | J138: Recreation_Entertainment | K138: =K137+dis_table[[#This Row],[Amount]] -> 1612.7
A139: 137 | B139: 44628 | C139: 44628 | D139: SKYHARBORPARKINGTERM3 PHOENIX AZ00899R | E139: 4 | F139: Services | G139: parking | H139: 03/2022 | I139: No | J139: Transportation | K139: =K138+dis_table[[#This Row],[Amount]] -> 1616.7
A140: 138 | B140: 44628 | C140: 44628 | D140: SEE TICKETS *RITT MOMNEY 323-908-0607 CASEE TICKETS *RITT MOMNEY | E140: 80.64 | F140: Travel/ Entertainment | G140: concert | H140: 03/2022 | I140: No | J140: Recreation_Entertainment | K140: =K139+dis_table[[#This Row],[Amount]] -> 1697.34
A141: 139 | B141: 44628 | C141: 44628 | D141: DRI*NVIDIA STORE NVIDIA.COM MNITEM TRANSFERRED FROM PREV ACCOUNT | E141: 4.99 | F141: Merchandise | G141: nvidia | H141: 03/2022 | I141: Yes | J141: Recreation_Entertainment | K141: =K140+dis_table[[#This Row],[Amount]] -> 1702.33
A142: 140 | B142: 44629 | C142: 44629 | D142: PIER 54 TEMPE AZ | E142: 35 | F142: Restaurants | G142: restaurant | H142: 03/2022 | I142: No | J142: Food | K142: =K141+dis_table[[#This Row],[Amount]] -> 1737.33
A143: 141 | B143: 44629 | C143: 44629 | D143: TACOS HUICHO #3 PHOENIX AZ | E143: 51.8 | F143: Restaurants | G143: fast_food | H143: 03/2022 | I143: No | J143: Food | K143: =K142+dis_table[[#This Row],[Amount]] -> 1789.13
... A148: 146 | B148: 44630 | C148: 44630 | D148: GRAND CYN NP-NGVC FLAGSTAFF AZ | E148: 35 | F148: Government Services | G148: museum | H148: 03/2022 | I148: No | J148: Recreation_Entertainment | K148: =K147+dis_table[[#This Row],[Amount]] -> 1926.76
A149: 147 | B149: 44630 | C149: 44630 | D149: INTERNET PAYMENT - THANK YOU | E149: -734.55 | F149: Payments and Credits | G149: payment | H149: 03/2022 | I149: No | K149: =K148+dis_table[[#This Row],[Amount]] -> 1192.21
A150: 148 | B150: 44630 | C150: 44630 | D150: LOVE'S TRAVEL STOPS #7 MAYER AZ | E150: 5.19 | F150: Gasoline | G150: gas_station | H150: 03/2022 | I150: No | J150: Transportation | K150: =K149+dis_table[[#This Row],[Amount]] -> 1197.4
A151: 149 | B151: 44630 | C151: 44630 | D151: DUNKIN #346591 PHOENIX AZ | E151: 21.12 | F151: Restaurants | G151: fast_food | H151: 03/2022 | I151: No | J151: Food | K151: =K150+dis_table[[#This Row],[Amount]] -> 1218.52
...

Sheet Discover Account
A1: Date | B1: Payment | C1: CumAmount
A2: 01/2022 | C2: 3599.69
A3: 01/2022 | C3: 3659.69
A4: 01/2022 | B4: -1800 | C4: 1859.69
A5: 01/2022 | C5: 1874.52
A6: 01/2022 | C6: 1884.51
A7: 01/2022 | C7: 1894.51
A8: 01/2022 | C8: 1907.5
A9: 01/2022 | C9: 1949.84
A10: 01/2022 | C10: 2029.22
A11: 01/2022 | C11: 2037.22
A12: 01/2022 | C12: 2067.15
A13: 01/2022 | C13: 2072.14
A14: 01/2022 | C14: 2104.72
A15: 01/2022 | C15: 2124.72
A16: 01/2022 | C16: 2127.21
... A22: 01/2022 | C22: 2468.9
A23: 01/2022 | B23: -2194.92 | C23: 273.98
A24: 01/2022 | C24: 304.87
A25: 01/2022 | B25: -29.08 | C25: 275.79
A26: 01/2022 | C26: 282.08
A27: 01/2022 | C27: 297.97
A28: 01/2022 | C28: 350.38
A29: 01/2022 | C29: 371.87
A30: 01/2022 | C30: 406.89
A31: 01/2022 | C31: 468.89
A32: 01/2022 | C32: 495.38
A33: 01/2022 | C33: 498.37
A34: 01/2022 | C34: 522.52
A35: 01/2022 | C35: 535.2
A36: 01/2022 | C36: 605.2
A37: 01/2022 | C37: 610.49
... A83: 02/2022 | C83: 2388.94
A84: 02/2022 | B84: -1733.33 | C84: 655.61
A85: 02/2022 | C85: 671.5
A86: 02/2022 | B86: -5 | C86: 666.5
A87: 02/2022 | C87: 675.7
A88: 02/2022 | C88: 689.81
A89: 02/2022 | C89: 709.81
A90: 02/2022 | C90: 724.8
A91: 02/2022 | C91: 751.39
A92: 02/2022 | C92: 800.39
A93: 02/2022 | C93: 812.39
A94: 02/2022 | C94: 882.39
A95: 02/2022 | C95: 887.68
A96: 02/2022 | B96: -29.29 | C96: 858.39
A97: 02/2022 | C97: 928.97
A98: 02/2022 | B98: -771.1 | C98: 157.87
A99: 02/2022 | C99: 168.87
A100: 02/2022 | C100: 198.87
A101: 02/2022 | C101: 213.03
A102: 02/2022 | C102: 214.65
A103: 02/2022 | C103: 341.35
A104: 02/2022 | C104: 471.53
A105: 02/2022 | C105: 480.85
A106: 02/2022 | C106: 498.85
A107: 02/2022 | C107: 528.84
A108: 02/2022 | C108: 547.73
A109: 02/2022 | C109: 578.75
A110: 02/2022 | C110: 620.12
... A147: 03/2022 | C147: 1926.76
A148: 03/2022 | B148: -734.55 | C148: 1192.21
A149: 03/2022 | C149: 1197.4
A150: 03/2022 | C150: 1218.52
A151: 03/2022 | C151: 1229.11
A152: 03/2022 | C152: 1245
A153: 03/2022 | C153: 1278.13
A154: 03/2022 | C154: 1308.13
A155: 03/2022 | C155: 1369.91
A156: 03/2022 | C156: 1423.91
A157: 03/2022 | C157: 1445.91
A158: 03/2022 | C158: 1457.41
A159: 03/2022 | C159: 1537.31
A160: 03/2022 | C160: 1545.84
... A185: 03/2022 | C185: 2798.51
A186: 03/2022 | B186: -734.55 | C186: 2063.96
A187: 03/2022 | C187: 2074.37
A188: 03/2022 | C188: 2313.6
A189: 03/2022 | C189: 2345.13
A190: 03/2022 | C190: 2360.13
A191: 03/2022 | B191: -500 | C191: 1860.13
A192: 03/2022 | C192: 2252.13
A193: 03/2022 | C193: 2296.33
A194: 03/2022 | C194: 2306.33
A195: 03/2022 | C195: 2318.33
A196: 03/2022 | C196: 2322.14
A197: 03/2022 | C197: 2338.14
A198: 03/2022 | C198: 2357.26
A199: 03/2022 | C199: 2381.83
A200: 03/2022 | C200: 2423.64
A201: 03/2022 | C201: 2500.64
A202: 03/2022 | C202: 2530.47
A203: 03/2022 | C203: 2610.46
... A217: 04/2022 | C217: 3068.74
A218: 04/2022 | B218: -934.85 | C218: 2133.89
A219: 04/2022 | B219: -65.15 | C219: 2068.74
A220: 04/2022 | C220: 2118.74
A221: 04/2022 | C221: 2123.73
A222: 04/2022 | C222: 2147.08
A223: 04/2022 | C223: 2159.72
...

Sheet Care Credit
A1: Transaction Date | B1: Post Date | C1: Description | D1: Amount | E1: Short_Desc | F1: Date | G1: Category_2
A2: 44571 | B2: 44571 | C2: 8534812QVLH06N92F WESTERN DENTAL OF ARIZONAPHOENIX AZ | D2: 2286 | E2: Dental | F2: =MONTH(A2)&"/"&YEAR(A2) -> 1/2022 | G2: Medical
A3: 44574 | B3: 44574 | C3: 8534812QX019L6GDK PAYMENT - THANK YOU | D3: -1000 | E3: Payment | F3: =MONTH(A3)&"/"&YEAR(A3) -> 1/2022
A4: 44599 | B4: 44599 | C4: Card Security 1-800-815-4051 | D4: 21.35 | E4: Security | F4: =MONTH(A4)&"/"&YEAR(A4) -> 2/2022 | G4: Medical
A5: 44602 | B5: 44602 | C5: 8534812DT01Q3QH69 PAYMENT - THANK YOU | D5: -307.35 | E5: Payment | F5: =MONTH(A5)&"/"&YEAR(A5) -> 2/2022
A6: 44611 | B6: 44611 | C6: 8534812E301QZ55AX PAYMENT - THANK YOU | D6: -1000 | E6: Payment | F6: =MONTH(A6)&"/"&YEAR(A6) -> 2/2022
A7: 44645 | B7: 44645 | C7: 8534812F6LK8M1WZE BANNER SURGERY CENTER CAMPHOENIX AZ | D7: 2121.16 | E7: Surgery | F7: =MONTH(A7)&"/"&YEAR(A7) -> 3/2022 | G7: Medical
A8: 44658 | B8: 44658 | C8: 8534812FH01H6BNDY PAYMENT - THANK YOU | D8: -1000 | E8: Payment | F8: =MONTH(A8)&"/"&YEAR(A8) -> 4/2022
A9: 44659 | B9: 44659 | C9: Card Security 1-800-815-4051 | D9: 18.61 | E9: Security | F9: =MONTH(A9)&"/"&YEAR(A9) -> 4/2022
A10: 44677 | B10: 44677 | C10: 8534812G501JT48VE PAYMENT - THANK YOU | D10: -139.77 | E10: Payment | F10: =MONTH(A10)&"/"&YEAR(A10) -> 4/2022
A11: 44686 | B11: 44686 | C11: 8534812GD01KKWEH4 PAYMENT - THANK YOU | D11: -1000 | E11: Payment | F11: =MONTH(A11)&"/"&YEAR(A11) -> 5/2022
A12: 44760 | B12: 44760 | C12: 8534812JRLK8M1WZF BANNER SURGERY CENTER CAMPHOENIX AZ | D12: -504.86 | E12: refund | F12: =MONTH(A12)&"/"&YEAR(A12) -> 7/2022
A13: 44763 | B13: 44763 | C13: F907200JU000CB202 CREDIT BALANCE I KETTERING OH | D13: 504.86 | E13: Refund | F13: =MONTH(A13)&"/"&YEAR(A13) -> 7/2022 | G13: Medical

Sheet Best Buy
A1: Transaction Date | B1: Amount | C1: Description | D1: Category | E1: Short_Desc | F1: Date | G1: Category_2
A2: 44697 | B2: 582.53 | C2: COACHING ACTUARIES WWW.COACHINGAIA | D2: sale | E2: learning | F2: =MONTH(A2)&"/"&YEAR(A2) -> 5/2022 | G2: Personal_Spending
A3: 44714 | B3: -974.91 | C3: ONLINE PAYMENT DEERFIELD IL | D3: payment | E3: payment | F3: =MONTH(A3)&"/"&YEAR(A3) -> 6/2022
A4: 44702 | B4: 12 | C4: SEASCAPE GOLF CLUB APTOS CA | D4: sale | E4: golf | F4: =MONTH(A4)&"/"&YEAR(A4) -> 5/2022 | G4: Recreation_Entertainment
A5: 44702 | B5: 9.6 | C5: SEASCAPE GOLF CLUB APTOS CA | D5: sale | E5: golf | F5: =MONTH(A5)&"/"&YEAR(A5) -> 5/2022 | G5: Recreation_Entertainment
A6: 44702 | B6: 26.14 | C6: SEASCAPE GOLF CLUB APTOS CA | D6: sale | E6: golf | F6: =MONTH(A6)&"/"&YEAR(A6) -> 5/2022 | G6: Recreation_Entertainment
A7: 44702 | B7: 299.8 | C7: TST* Laili Restaurant Santa Cruz CA | D7: sale | E7: golf | F7: =MONTH(A7)&"/"&YEAR(A7) -> 5/2022 | G7: Recreation_Entertainment
A8: 44703 | B8: 32 | C8: MELOMELO KAVA BAR - SANT SANTA CRUZ CA | D8: sale | E8: resteraunt | F8: =MONTH(A8)&"/"&YEAR(A8) -> 5/2022 | G8: Food
A9: 44703 | B9: 12.84 | C9: SQ *HMB COFFEE CO Half Moon BayCA | D9: sale | E9: coffee | F9: =MONTH(A9)&"/"&YEAR(A9) -> 5/2022 | G9: Food

Sheet Wells Fargo
A1: Trans Date | B1: Debit_Amount | C1: Amount | D1: Description | E1: Short_Desc | F1: Date | G1: Category_2
A2: 44564 | B2: -1800 | C2: =IF(SIGN(B2)=-1, B2*-1, B2) -> 1800 | D2: DISCOVER E-PAYMENT 220102 4618 LEWIS SEAN | E2: discover | F2: =MONTH(A2)&"/"&YEAR(A2) -> 1/2022 | G2: credit
A3: 44564 | B3: -241.99 | C3: =IF(SIGN(B3)=-1, B3*-1, B3) -> 241.99 | D3: BEST BUY PAYMENT 220102 610633785460241 SEAN LEWIS | E3: best_buy | F3: =MONTH(A3)&"/"&YEAR(A3) -> 1/2022 | G3: credit
A4: 44564 | B4: -10 | C4: =IF(SIGN(B4)=-1, B4*-1, B4) -> 10 | D4: PAYPAL INST XFER 220101 LOUISCK SEAN LEWIS | E4: comedy | F4: =MONTH(A4)&"/"&YEAR(A4) -> 1/2022 | G4: =IFERROR(VLOOKUP('Wells Fargo'!E159,dis_table[[#All],[Short_Desc]:[CumAmount]],4,0),0) -> 0
A5: 44564 | B5: 194 | C5: =IF(SIGN(B5)=-1, B5*-1, B5) -> 194 | D5: ATM CASH DEPOSIT ON 01/02 3002 N Central Ave Phoenix AZ 0003743 ATM ID 5449B CARD 6634 | E5: atm | F5: =MONTH(A5)&"/"&YEAR(A5) -> 1/2022 | G5: 0
A6: 44564 | B6: -485 | C6: =IF(SIGN(B6)=-1, B6*-1, B6) -> 485 | D6: TRANSFER TO LEWIS SHARON ON 01/03 REF #PP0D9295LZ XXXXXXXXX5267 | E6: mom | F6: =MONTH(A6)&"/"&YEAR(A6) -> 1/2022 | G6: People
A7: 44564 | B7: 477.73 | C7: =IF(SIGN(B7)=-1, B7*-1, B7) -> 477.73 | D7: RTP from VENMO on 01/03 Ref#20220103021000021P1BRJPM00530020747 | E7: Vincent | F7: =MONTH(A7)&"/"&YEAR(A7) -> 1/2022 | G7: People
A8: 44568 | B8: 30.89 | C8: =IF(SIGN(B8)=-1, B8*-1, B8) -> 30.89 | D8: VENMO CASHOUT 220107 1017829933941 SEAN LEWIS | E8: Vincent | F8: =MONTH(A8)&"/"&YEAR(A8) -> 1/2022 | G8: Utilities
A9: 44568 | B9: 23.27 | C9: =IF(SIGN(B9)=-1, B9*-1, B9) -> 23.27 | D9: LIFETIME FITNESS DIRECT DEP 220107 558079861456SHS LEWIS,SEAN | E9: gym | F9: =MONTH(A9)&"/"&YEAR(A9) -> 1/2022 | G9: =IFERROR(VLOOKUP('Wells Fargo'!E156,dis_table[[#All],[Short_Desc]:[CumAmount]],4,0),0) -> 0
A10: 44571 | B10: 234.58 | C10: =IF(SIGN(B10)=-1, B10*-1, B10) -> 234.58 | D10: VENMO CASHOUT 220110 1017875354612 SEAN LEWIS | E10: Melanie | F10: =MONTH(A10)&"/"&YEAR(A10) -> 1/2022 | G10: Utilities
A11: 44571 | B11: 50 | C11: =IF(SIGN(B11)=-1, B11*-1, B11) -> 50 | D11: VENMO CASHOUT 220110 1017874602288 SEAN LEWIS | E11: Kabir | F11: =MONTH(A11)&"/"&YEAR(A11) -> 1/2022 | G11: Recreation_Entertainment
A12: 44572 | B12: -100 | C12: =IF(SIGN(B12)=-1, B12*-1, B12) -> 100 | D12: PURCHASE AUTHORIZED ON 01/10 CASH APP*CYANFACE 8774174551 CA S462010765413680 CARD 6634 | E12: Jayelin | F12: =MONTH(A12)&"/"&YEAR(A12) -> 1/2022 | G12: People
A13: 44574 | B13: -2194.92 | C13: =IF(SIGN(B13)=-1, B13*-1, B13) -> 2194.92 | D13: DISCOVER E-PAYMENT 220113 4618 LEWIS SEAN | E13: discover | F13: =MONTH(A13)&"/"&YEAR(A13) -> 1/2022 | G13: credit
A14: 44574 | B14: 3898.5 | C14: =IF(SIGN(B14)=-1, B14*-1, B14) -> 3898.5 | D14: Nationwide PAYROLL 01 HRP0007983168 Sean Lewis | E14: nationwide | F14: =MONTH(A14)&"/"&YEAR(A14) -> 1/2022 | G14: income
A15: 44575 | B15: -1000 | C15: =IF(SIGN(B15)=-1, B15*-1, B15) -> 1000 | D15: Synchrony Bank CC PYMT JAN 13 601918368630042 SEAN LEWIS | E15: care_credit | F15: =MONTH(A15)&"/"&YEAR(A15) -> 1/2022 | G15: credit
A16: 44575 | B16: -2.5 | C16: =IF(SIGN(B16)=-1, B16*-1, B16) -> 2.5 | D16: NON-WELLS FARGO ATM TRANSACTION FEE | E16: atm | F16: =MONTH(A16)&"/"&YEAR(A16) -> 1/2022 | G16: =IFERROR(VLOOKUP('Wells Fargo'!E148,dis_table[[#All],[Short_Desc]:[CumAmount]],4,0),0) -> 0
A17: 44575 | B17: -103.5 | C17: =IF(SIGN(B17)=-1, B17*-1, B17) -> 103.5 | D17: NON-WF ATM WITHDRAWAL AUTHORIZED ON 01/14 666 W E ST SAN DIEGO CA 382015019310845 ATM ID CA0961 CARD 6634 | E17: atm | F17: =MONTH(A17)&"/"&YEAR(A17) -> 1/2022 | G17: 0
A18: 44579 | B18: -48.5 | C18: =IF(SIGN(B18)=-1, B18*-1, B18) -> 48.5 | D18: NON-WF ATM WITHDRAWAL AUTHORIZED ON 01/16 4645 DE SOTO ST SAN DIEGO CA 582017109140029 ATM ID L631055 CARD 6634 | E18: atm | F18: =MONTH(A18)&"/"&YEAR(A18) -> 1/2022 | G18: =IFERROR(VLOOKUP('Wells Fargo'!E140,dis_table[[#All],[Short_Desc]:[CumAmount]],4,0),0) -> 0
A19: 44579 | B19: -2.5 | C19: =IF(SIGN(B19)=-1, B19*-1, B19) -> 2.5 | D19: NON-WELLS FARGO ATM TRANSACTION FEE | E19: atm | F19: =MONTH(A19)&"/"&YEAR(A19) -> 1/2022 | G19: =IFERROR(VLOOKUP('Wells Fargo'!E144,dis_table[[#All],[Short_Desc]:[CumAmount]],4,0),0) -> 0
A20: 44579 | B20: -10 | C20: =IF(SIGN(B20)=-1, B20*-1, B20) -> 10 | D20: PURCHASE AUTHORIZED ON 01/16 CASH APP*VALLEY 8774174551 CA S382017149175934 CARD 6634 | E20: fast_food | F20: =MONTH(A20)&"/"&YEAR(A20) -> 1/2022 | G20: =IFERROR(VLOOKUP('Wells Fargo'!E137,dis_table[[#All],[Short_Desc]:[CumAmount]],4,0),0) -> Misc
A21: 44579 | B21: -20 | C21: =IF(SIGN(B21)=-1, B21*-1, B21) -> 20 | D21: PURCHASE AUTHORIZED ON 01/16 CASH APP*DARIUS CA 8774174551 CA S382017148849842 CARD 6634 | E21: fast_food | F21: =MONTH(A21)&"/"&YEAR(A21) -> 1/2022 | G21: =IFERROR(VLOOKUP('Wells Fargo'!E138,dis_table[[#All],[Short_Desc]:[CumAmount]],4,0),0) -> Personal_Spending
A22: 44579 | B22: -2.5 | C22: =IF(SIGN(B22)=-1, B22*-1, B22) -> 2.5 | D22: NON-WELLS FARGO ATM TRANSACTION FEE | E22: atm | F22: =MONTH(A22)&"/"&YEAR(A22) -> 1/2022 | G22: =IFERROR(VLOOKUP('Wells Fargo'!E139,dis_table[[#All],[Short_Desc]:[CumAmount]],4,0),0) -> People
A23: 44579 | B23: -54.04 | C23: =IF(SIGN(B23)=-1, B23*-1, B23) -> 54.04 | D23: PURCHASE AUTHORIZED ON 01/16 CHEVRON 0094991 SAN DIEGO CA S382017053945491 CARD 6634 | E23: gas_station | F23: =MONTH(A23)&"/"&YEAR(A23) -> 1/2022 | G23: =IFERROR(VLOOKUP('Wells Fargo'!E141,dis_table[[#All],[Short_Desc]:[CumAmount]],4,0),0) -> 0
A24: 44579 | B24: -21.54 | C24: =IF(SIGN(B24)=-1, B24*-1, B24) -> 21.54 | D24: PURCHASE AUTHORIZED ON 01/16 SD ZOO CINNAMON TR SAN DIEGO CA S382017034170694 CARD 6634 | E24: zoo | F24: =MONTH(A24)&"/"&YEAR(A24) -> 1/2022 | G24: =IFERROR(VLOOKUP('Wells Fargo'!E142,dis_table[[#All],[Short_Desc]:[CumAmount]],4,0),0) -> 0
A25: 44579 | B25: -6.99 | C25: =IF(SIGN(B25)=-1, B25*-1, B25) -> 6.99 | D25: PURCHASE AUTHORIZED ON 01/16 SD ZOO CANYON CAFE SAN DIEGO CA S582016817636715 CARD 6634 | E25: zoo | F25: =MONTH(A25)&"/"&YEAR(A25) -> 1/2022 | G25: =IFERROR(VLOOKUP('Wells Fargo'!E143,dis_table[[#All],[Short_Desc]:[CumAmount]],4,0),0) -> People
A26: 44579 | B26: -42.75 | C26: =IF(SIGN(B26)=-1, B26*-1, B26) -> 42.75 | D26: NON-WF ATM WITHDRAWAL AUTHORIZED ON 01/16 3710 VOLTAIRE ST. STE 1 SAN DIEGO CA 582016595373620 ATM ID P459681 CARD 6634 | E26: atm | F26: =MONTH(A26)&"/"&YEAR(A26) -> 1/2022 | G26: =IFERROR(VLOOKUP('Wells Fargo'!E145,dis_table[[#All],[Short_Desc]:[CumAmount]],4,0),0) -> 0
A27: 44579 | B27: -40 | C27: =IF(SIGN(B27)=-1, B27*-1, B27) -> 40 | D27: PURCHASE AUTHORIZED ON 01/15 BALLAST POINT LITT SAN DIEGO CA S302015831911176 CARD 6634 | E27: restaurant | F27: =MONTH(A27)&"/"&YEAR(A27) -> 1/2022 | G27: Food
A28: 44579 | B28: -576.01 | C28: =IF(SIGN(B28)=-1, B28*-1, B28) -> 576.01 | D28: VENMO PAYMENT 220117 1018001608819 SEAN LEWIS | E28: Kabir | F28: =MONTH(A28)&"/"&YEAR(A28) -> 1/2022 | G28: Recreation_Entertainment
A29: 44579 | B29: -68.33 | C29: =IF(SIGN(B29)=-1, B29*-1, B29) -> 68.33 | D29: VENMO PAYMENT 220117 1018001751483 SEAN LEWIS | E29: Logan | F29: =MONTH(A29)&"/"&YEAR(A29) -> 1/2022 | G29: Recreation_Entertainment
A30: 44585 | B30: -70 | C30: =IF(SIGN(B30)=-1, B30*-1, B30) -> 70 | D30: VENMO PAYMENT 220122 1018085063025 SEAN LEWIS | E30: Jon | F30: =MONTH(A30)&"/"&YEAR(A30) -> 1/2022 | G30: Personal_Spending
A31: 44588 | B31: -1866.67 | C31: =IF(SIGN(B31)=-1, B31*-1, B31) -> 1866.67 | D31: VENMO PAYMENT 220127 1018168964129 SEAN LEWIS | E31: rent | F31: =MONTH(A31)&"/"&YEAR(A31) -> 1/2022 | G31: Housing
A32: 44588 | B32: 933.33 | C32: =IF(SIGN(B32)=-1, B32*-1, B32) -> 933.33 | D32: VENMO CASHOUT 220127 1018164349212 SEAN LEWIS | E32: Vincent | F32: =MONTH(A32)&"/"&YEAR(A32) -> 1/2022 | G32: Housing
A33: 44588 | B33: 1718.36 | C33: =IF(SIGN(B33)=-1, B33*-1, B33) -> 1718.36 | D33: Nationwide PAYROLL 01 HRP0008024211 Sean Lewis | E33: nationwide | F33: =MONTH(A33)&"/"&YEAR(A33) -> 1/2022 | G33: income
A34: 44592 | B34: -120 | C34: =IF(SIGN(B34)=-1, B34*-1, B34) -> 120 | D34: TRANSFER TO LEWIS DON ON 01/31 REF #PP0Q7YVDF7 XXXXXX7932 | E34: Don | F34: =MONTH(A34)&"/"&YEAR(A34) -> 1/2022 | G34: People
A35: 44592 | B35: -20 | C35: =IF(SIGN(B35)=-1, B35*-1, B35) -> 20 | D35: TRANSFER TO LEWIS SHARON ON 01/31 REF #PP0Q7YX7VJ XXXXXXXXX5267 | E35: mom | F35: =MONTH(A35)&"/"&YEAR(A35) -> 1/2022 | G35: People
A36: 44592 | B36: -29 | C36: =IF(SIGN(B36)=-1, B36*-1, B36) -> 29 | D36: VENMO PAYMENT 220129 1018202156945 SEAN LEWIS | E36: Nick | F36: =MONTH(A36)&"/"&YEAR(A36) -> 1/2022 | G36: Recreation_Entertainment
A37: 44599 | B37: 120 | C37: =IF(SIGN(B37)=-1, B37*-1, B37) -> 120 | D37: ZELLE FROM LEWIS JUSTINA ON 02/05 REF # PP0Q8BDL92 | E37: Don | F37: =MONTH(A37)&"/"&YEAR(A37) -> 2/2022 | G37: People
A38: 44602 | B38: -1733.33 | C38: =IF(SIGN(B38)=-1, B38*-1, B38) -> 1733.33 | D38: DISCOVER E-PAYMENT 220210 4618 LEWIS SEAN | E38: discover | F38: =MONTH(A38)&"/"&YEAR(A38) -> 2/2022 | G38: =IFERROR(VLOOKUP('Wells Fargo'!E122,dis_table[[#All],[Short_Desc]:[CumAmount]],4,0),0) -> 0
A39: 44602 | B39: -70 | C39: =IF(SIGN(B39)=-1, B39*-1, B39) -> 70 | D39: VENMO PAYMENT 220210 1018415472279 SEAN LEWIS | E39: Kim | F39: =MONTH(A39)&"/"&YEAR(A39) -> 2/2022 | G39: Personal_Spending
A40: 44602 | B40: 662.38 | C40: =IF(SIGN(B40)=-1, B40*-1, B40) -> 662.38 | D40: VENMO CASHOUT 220210 1018420729744 SEAN LEWIS | E40: Vincent | F40: =MONTH(A40)&"/"&YEAR(A40) -> 2/2022 | G40: Housing
A41: 44602 | B41: 68.58 | C41: =IF(SIGN(B41)=-1, B41*-1, B41) -> 68.58 | D41: VENMO CASHOUT 220210 1018412598097 SEAN LEWIS | E41: Melanie | F41: =MONTH(A41)&"/"&YEAR(A41) -> 2/2022 | G41: Utilities
A42: 44602 | B42: 1718.36 | C42: =IF(SIGN(B42)=-1, B42*-1, B42) -> 1718.36 | D42: Nationwide PAYROLL 01 HRP0008036323 Sean Lewis | E42: nationwide | F42: =MONTH(A42)&"/"&YEAR(A42) -> 2/2022 | G42: income
A43: 44603 | B43: -70 | C43: =IF(SIGN(B43)=-1, B43*-1, B43) -> 70 | D43: VENMO PAYMENT 220211 1018433632129 SEAN LEWIS | E43: Jon | F43: =MONTH(A43)&"/"&YEAR(A43) -> 2/2022 | G43: Personal_Spending
A44: 44603 | B44: -307.35 | C44: =IF(SIGN(B44)=-1, B44*-1, B44) -> 307.35 | D44: Synchrony Bank CC PYMT FEB 10 601918368630042 SEAN LEWIS | E44: care_credit | F44: =MONTH(A44)&"/"&YEAR(A44) -> 2/2022 | G44: credit
A45: 44606 | B45: -100 | C45: =IF(SIGN(B45)=-1, B45*-1, B45) -> 100 | D45: ATM WITHDRAWAL AUTHORIZED ON 02/13 4402 E Thomas Rd Phoenix AZ 0008953 ATM ID 5743H CARD 6634 | E45: atm | F45: =MONTH(A45)&"/"&YEAR(A45) -> 2/2022 | G45: =IFERROR(VLOOKUP('Wells Fargo'!E119,dis_table[[#All],[Short_Desc]:[CumAmount]],4,0),0) -> 0
A46: 44610 | B46: -70 | C46: =IF(SIGN(B46)=-1, B46*-1, B46) -> 70 | D46: VENMO PAYMENT 220218 1018555740013 SEAN LEWIS | E46: Jon | F46: =MONTH(A46)&"/"&YEAR(A46) -> 2/2022 | G46: Personal_Spending
A47: 44614 | B47: -205.75 | C47: =IF(SIGN(B47)=-1, B47*-1, B47) -> 205.75 | D47: APS electric pmt PAYMENT 220217 5175354092 Autopay | E47: aps | F47: =MONTH(A47)&"/"&YEAR(A47) -> 2/2022 | G47: Utilities
A48: 44614 | B48: -1000 | C48: =IF(SIGN(B48)=-1, B48*-1, B48) -> 1000 | D48: Synchrony Bank CC PYMT FEB 19 601918368630042 SEAN LEWIS | E48: care_credit | F48: =MONTH(A48)&"/"&YEAR(A48) -> 2/2022 | G48: credit
A49: 44614 | B49: -771.1 | C49: =IF(SIGN(B49)=-1, B49*-1, B49) -> 771.1 | D49: DISCOVER E-PAYMENT 220220 4618 LEWIS SEAN | E49: discover | F49: =MONTH(A49)&"/"&YEAR(A49) -> 2/2022 | G49: =IFERROR(VLOOKUP('Wells Fargo'!E115,dis_table[[#All],[Short_Desc]:[CumAmount]],4,0),0) -> 0
A50: 44614 | B50: 520.85 | C50: =IF(SIGN(B50)=-1, B50*-1, B50) -> 520.85 | D50: TPG PRODUCTS SBTPG LLC 220218 ETRVW3GLLOEOPDY SEAN LEWIS | E50: taxes | F50: =MONTH(A50)&"/"&YEAR(A50) -> 2/2022 | G50: income
A51: 44614 | B51: 1257 | C51: =IF(SIGN(B51)=-1, B51*-1, B51) -> 1257 | D51: AZ DEPT OF REV Tax Refund 220218 XXXXX0268 LEWIS SEAN | E51: taxes | F51: =MONTH(A51)&"/"&YEAR(A51) -> 2/2022 | G51: income
A52: 44614 | B52: -189.21 | C52: =IF(SIGN(B52)=-1, B52*-1, B52) -> 189.21 | D52: VENMO PAYMENT 220222 1018622300513 SEAN LEWIS | E52: Vincent | F52: =MONTH(A52)&"/"&YEAR(A52) -> 2/2022 | G52: People
A53: 44616 | B53: 2176.22 | C53: =IF(SIGN(B53)=-1, B53*-1, B53) -> 2176.22 | D53: Nationwide PAYROLL 01 HRP0008091792 Sean Lewis | E53: nationwide | F53: =MONTH(A53)&"/"&YEAR(A53) -> 2/2022 | G53: income
A54: 44616 | B54: 100 | C54: =IF(SIGN(B54)=-1, B54*-1, B54) -> 100 | D54: TD AMERITRADE ACH OUT a9KLOZ6PQR LEWIS SEAN | E54: td_ameritrade | F54: =MONTH(A54)&"/"&YEAR(A54) -> 2/2022 | G54: income
A55: 44617 | B55: 1424 | C55: =IF(SIGN(B55)=-1, B55*-1, B55) -> 1424 | D55: VA DEPT TAXATION VASTTAXRFD 220217 XXXXX0268 LEWIS, SEAN E | E55: taxes | F55: =MONTH(A55)&"/"&YEAR(A55) -> 2/2022 | G55: income
A56: 44617 | B56: -1400 | C56: =IF(SIGN(B56)=-1, B56*-1, B56) -> 1400 | D56: VENMO PAYMENT 220225 1018674378710 SEAN LEWIS | E56: Vincent | F56: =MONTH(A56)&"/"&YEAR(A56) -> 2/2022 | G56: People
A57: 44620 | B57: -1866.67 | C57: =IF(SIGN(B57)=-1, B57*-1, B57) -> 1866.67 | D57: VENMO PAYMENT 220226 1018692237447 SEAN LEWIS | E57: rent | F57: =MONTH(A57)&"/"&YEAR(A57) -> 2/2022 | G57: Housing
A58: 44620 | B58: -2.5 | C58: =IF(SIGN(B58)=-1, B58*-1, B58) -> 2.5 | D58: NON-WELLS FARGO ATM TRANSACTION FEE | E58: atm | F58: =MONTH(A58)&"/"&YEAR(A58) -> 2/2022 | G58: =IFERROR(VLOOKUP('Wells Fargo'!E105,dis_table[[#All],[Short_Desc]:[CumAmount]],4,0),0) -> 0
A59: 44620 | B59: -42 | C59: =IF(SIGN(B59)=-1, B59*-1, B59) -> 42 | D59: NON-WF ATM WITHDRAWAL AUTHORIZED ON 02/25 727 W CAMELBACK RD PHOENIX AZ 382057136740734 ATM ID P304339 CARD 6634 | E59: atm | F59: =MONTH(A59)&"/"&YEAR(A59) -> 2/2022 | G59: =IFERROR(VLOOKUP('Wells Fargo'!E106,dis_table[[#All],[Short_Desc]:[CumAmount]],4,0),0) -> 0
A60: 44620 | B60: 485 | C60: =IF(SIGN(B60)=-1, B60*-1, B60) -> 485 | D60: TRANSFER FROM LEWIS SHARON ON 02/26 REF # PP0Q9F5QXB THANK YOU | E60: mom | F60: =MONTH(A60)&"/"&YEAR(A60) -> 2/2022 | G60: People
A61: 44620 | B61: -485 | C61: =IF(SIGN(B61)=-1, B61*-1, B61) -> 485 | D61: VENMO PAYMENT 220226 1018692186925 SEAN LEWIS | E61: Vincent | F61: =MONTH(A61)&"/"&YEAR(A61) -> 2/2022 | G61: People
A62: 44621 | B62: -62 | C62: =IF(SIGN(B62)=-1, B62*-1, B62) -> 62 | D62: VENMO PAYMENT 220301 1018758856961 SEAN LEWIS | E62: Vincent | F62: =MONTH(A62)&"/"&YEAR(A62) -> 3/2022 | G62: Utilities
A63: 44630 | B63: -734.55 | C63: =IF(SIGN(B63)=-1, B63*-1, B63) -> 734.55 | D63: DISCOVER E-PAYMENT 220310 4618 LEWIS SEAN | E63: discover | F63: =MONTH(A63)&"/"&YEAR(A63) -> 3/2022 | G63: credit
A64: 44630 | B64: 2240.07 | C64: =IF(SIGN(B64)=-1, B64*-1, B64) -> 2240.07 | D64: Nationwide PAYROLL 01 HRP0008137116 Sean Lewis | E64: nationwide | F64: =MONTH(A64)&"/"&YEAR(A64) -> 3/2022 | G64: income
A65: 44630 | B65: -1500 | C65: =IF(SIGN(B65)=-1, B65*-1, B65) -> 1500 | D65: VENMO PAYMENT 220310 1018915574100 SEAN LEWIS | E65: Vincent | F65: =MONTH(A65)&"/"&YEAR(A65) -> 3/2022 | G65: People
A66: 44638 | B66: -60 | C66: =IF(SIGN(B66)=-1, B66*-1, B66) -> 60 | D66: PURCHASE AUTHORIZED ON 03/17 CASH APP*SHEVON LE 8774174551 CA S302076796250975 CARD 6634 | E66: Shevon | F66: =MONTH(A66)&"/"&YEAR(A66) -> 3/2022 | G66: People
A67: 44641 | B67: 33 | C67: =IF(SIGN(B67)=-1, B67*-1, B67) -> 33 | D67: ZELLE FROM ERNEST NOCHE ON 03/20 REF # BACU6FMEIILK | E67: Michael | F67: =MONTH(A67)&"/"&YEAR(A67) -> 3/2022 | G67: Food
A68: 44641 | B68: 137.51 | C68: =IF(SIGN(B68)=-1, B68*-1, B68) -> 137.51 | D68: VENMO CASHOUT 220321 1019111739464 SEAN LEWIS | E68: Venmo | F68: =MONTH(A68)&"/"&YEAR(A68) -> 3/2022 | G68: People
A69: 44642 | B69: -734.55 | C69: =IF(SIGN(B69)=-1, B69*-1, B69) -> 734.55 | D69: DISCOVER E-PAYMENT 220322 4618 LEWIS SEAN | E69: discover | F69: =MONTH(A69)&"/"&YEAR(A69) -> 3/2022 | G69: credit
A70: 44642 | B70: -146.17 | C70: =IF(SIGN(B70)=-1, B70*-1, B70) -> 146.17 | D70: APS electric pmt PAYMENT 220318 5175354092 Autopay | E70: aps | F70: =MONTH(A70)&"/"&YEAR(A70) -> 3/2022 | G70: Utilities
A71: 44642 | B71: -43.16 | C71: =IF(SIGN(B71)=-1, B71*-1, B71) -> 43.16 | D71: PURCHASE AUTHORIZED ON 03/22 SHELL SERVICE STATION PHOENIX AZ P302081522144554 CARD 6634 | E71: gas_station | F71: =MONTH(A71)&"/"&YEAR(A71) -> 3/2022 | G71: =IFERROR(VLOOKUP('Wells Fargo'!E94,dis_table[[#All],[Short_Desc]:[CumAmount]],4,0),0) -> 0
A72: 44642 | B72: 66 | C72: =IF(SIGN(B72)=-1, B72*-1, B72) -> 66 | D72: VENMO CASHOUT 220322 1019125273986 SEAN LEWIS | E72: Vincent | F72: =MONTH(A72)&"/"&YEAR(A72) -> 3/2022 | G72: People
A73: 44644 | B73: -1400 | C73: =IF(SIGN(B73)=-1, B73*-1, B73) -> 1400 | D73: VENMO PAYMENT 220324 1019164077845 SEAN LEWIS | E73: rent | F73: =MONTH(A73)&"/"&YEAR(A73) -> 3/2022 | G73: Housing
A74: 44644 | B74: -500 | C74: =IF(SIGN(B74)=-1, B74*-1, B74) -> 500 | D74: DISCOVER E-PAYMENT 220324 4618 LEWIS SEAN | E74: discover | F74: =MONTH(A74)&"/"&YEAR(A74) -> 3/2022 | G74: credit
A75: 44644 | B75: 2240.07 | C75: =IF(SIGN(B75)=-1, B75*-1, B75) -> 2240.07 | D75: Nationwide PAYROLL 01 HRP0008178715 Sean Lewis | E75: nationwide | F75: =MONTH(A75)&"/"&YEAR(A75) -> 3/2022 | G75: income
A76: 44645 | B76: -52 | C76: =IF(SIGN(B76)=-1, B76*-1, B76) -> 52 | D76: VENMO PAYMENT 220325 1019189845192 SEAN LEWIS | E76: Nick | F76: =MONTH(A76)&"/"&YEAR(A76) -> 3/2022 | G76: Recreation_Entertainment
A77: 44648 | B77: -5 | C77: =IF(SIGN(B77)=-1, B77*-1, B77) -> 5 | D77: PURCHASE AUTHORIZED ON 03/26 CASH APP*ENGAGETM 8774174551 CA S382085824280328 CARD 6634 | E77: Dorry | F77: =MONTH(A77)&"/"&YEAR(A77) -> 3/2022 | G77: People
A78: 44648 | B78: -100 | C78: =IF(SIGN(B78)=-1, B78*-1, B78) -> 100 | D78: PURCHASE AUTHORIZED ON 03/25 CASH APP*CYANFACE 8774174551 CA S302084480194424 CARD 6634 | E78: jayelin | F78: =MONTH(A78)&"/"&YEAR(A78) -> 3/2022 | G78: People
A79: 44649 | B79: -70.65 | C79: =IF(SIGN(B79)=-1, B79*-1, B79) -> 70.65 | D79: VENMO PAYMENT 220329 1019258605951 SEAN LEWIS | E79: Melanie | F79: =MONTH(A79)&"/"&YEAR(A79) -> 3/2022 | G79: Utilities
A80: 44649 | B80: 49.32 | C80: =IF(SIGN(B80)=-1, B80*-1, B80) -> 49.32 | D80: VENMO CASHOUT 220329 1019258957091 SEAN LEWIS | E80: Melanie | F80: =MONTH(A80)&"/"&YEAR(A80) -> 3/2022 | G80: Utilities
A81: 44649 | B81: 87.4 | C81: =IF(SIGN(B81)=-1, B81*-1, B81) -> 87.4 | D81: VENMO CASHOUT 220329 1019257034036 SEAN LEWIS | E81: Venmo | F81: =MONTH(A81)&"/"&YEAR(A81) -> 3/2022 | G81: People
A82: 44651 | B82: -10 | C82: =IF(SIGN(B82)=-1, B82*-1, B82) -> 10 | D82: PURCHASE AUTHORIZED ON 03/30 CASH APP*CYANFACE 8774174551 CA S462090143040686 CARD 6634 | E82: Jayelin | F82: =MONTH(A82)&"/"&YEAR(A82) -> 3/2022 | G82: People
A83: 44652 | B83: -45 | C83: =IF(SIGN(B83)=-1, B83*-1, B83) -> 45 | D83: PURCHASE AUTHORIZED ON 03/31 CASH APP*CYANFACE 8774174551 CA S582090834603593 CARD 6634 | E83: Jayelin | F83: =MONTH(A83)&"/"&YEAR(A83) -> 4/2022 | G83: People
A84: 44655 | B84: -8 | C84: =IF(SIGN(B84)=-1, B84*-1, B84) -> 8 | D84: PURCHASE AUTHORIZED ON 04/01 CASH APP*CYANFACE 8774174551 CA S302091792116789 CARD 6634 | E84: Jayelin | F84: =MONTH(A84)&"/"&YEAR(A84) -> 4/2022 | G84: People
A85: 44655 | B85: -38.71 | C85: =IF(SIGN(B85)=-1, B85*-1, B85) -> 38.71 | D85: PURCHASE AUTHORIZED ON 04/02 SAFEWAY #2651 PHOENIX AZ P462092686408975 CARD 6634 | E85: groceries | F85: =MONTH(A85)&"/"&YEAR(A85) -> 4/2022 | G85: =IFERROR(VLOOKUP('Wells Fargo'!E79,dis_table[[#All],[Short_Desc]:[CumAmount]],4,0),0) -> 0
A86: 44655 | B86: -100 | C86: =IF(SIGN(B86)=-1, B86*-1, B86) -> 100 | D86: TRANSFER TO LEWIS SHARON ON 04/03 REF #PP0QCJCLVN XXXXXXXXX5267 | E86: mom | F86: =MONTH(A86)&"/"&YEAR(A86) -> 4/2022 | G86: People
A87: 44656 | B87: -5.41 | C87: =IF(SIGN(B87)=-1, B87*-1, B87) -> 5.41 | D87: PURCHASE AUTHORIZED ON 04/04 Whitepages 800-9529005 WA S382095014545576 CARD 6634 | E87: unsure | F87: =MONTH(A87)&"/"&YEAR(A87) -> 4/2022 | G87: =IFERROR(VLOOKUP('Wells Fargo'!E76,dis_table[[#All],[Short_Desc]:[CumAmount]],4,0),0) -> 0
A88: 44656 | B88: -10.78 | C88: =IF(SIGN(B88)=-1, B88*-1, B88) -> 10.78 | D88: PURCHASE AUTHORIZED ON 04/04 Whitepages 800-9529005 WA S382095010925055 CARD 6634 | E88: unsure | F88: =MONTH(A88)&"/"&YEAR(A88) -> 4/2022 | G88: =IFERROR(VLOOKUP('Wells Fargo'!E77,dis_table[[#All],[Short_Desc]:[CumAmount]],4,0),0) -> 0
A89: 44657 | B89: -40 | C89: =IF(SIGN(B89)=-1, B89*-1, B89) -> 40 | D89: PURCHASE AUTHORIZED ON 04/05 CASH APP*CYANFACE 8774174551 CA S382096070149787 CARD 6634 | E89: Jayelin | F89: =MONTH(A89)&"/"&YEAR(A89) -> 4/2022 | G89: People
A90: 44658 | B90: -934.85 | C90: =IF(SIGN(B90)=-1, B90*-1, B90) -> 934.85 | D90: DISCOVER E-PAYMENT 220407 4618 LEWIS SEAN | E90: discover | F90: =MONTH(A90)&"/"&YEAR(A90) -> 4/2022 | G90: credit
A91: 44658 | B91: 2240.08 | C91: =IF(SIGN(B91)=-1, B91*-1, B91) -> 2240.08 | D91: Nationwide PAYROLL 01 HRP0008210841 Sean Lewis | E91: nationwide | F91: =MONTH(A91)&"/"&YEAR(A91) -> 4/2022 | G91: income
A92: 44659 | B92: -35 | C92: =IF(SIGN(B92)=-1, B92*-1, B92) -> 35 | D92: ZELLE TO ZAZUETA CARMEN ON 04/08 REF #PP0QCS8FDR | E92: Carmen | F92: =MONTH(A92)&"/"&YEAR(A92) -> 4/2022 | G92: People
A93: 44659 | B93: -1000 | C93: =IF(SIGN(B93)=-1, B93*-1, B93) -> 1000 | D93: Synchrony Bank CC PYMT APR 07 601918368630042 SEAN LEWIS | E93: care_credit | F93: =MONTH(A93)&"/"&YEAR(A93) -> 4/2022 | G93: credit
A94: 44659 | B94: -200 | C94: =IF(SIGN(B94)=-1, B94*-1, B94) -> 200 | D94: TRANSFER TO LEWIS SHARON ON 04/08 REF #PP0QCT2JQH XXXXXXXXX5267 | E94: mom | F94: =MONTH(A94)&"/"&YEAR(A94) -> 4/2022 | G94: People
A95: 44666 | B95: -50 | C95: =IF(SIGN(B95)=-1, B95*-1, B95) -> 50 | D95: VENMO PAYMENT 220415 1019571055773 SEAN LEWIS | E95: aps | F95: =MONTH(A95)&"/"&YEAR(A95) -> 4/2022 | G95: Utilities
A96: 44666 | B96: 63 | C96: =IF(SIGN(B96)=-1, B96*-1, B96) -> 63 | D96: TICKETMASTER RES 0414-TH002 200051625122116 SEAN LEWIS | E96: ticket_sale | F96: =MONTH(A96)&"/"&YEAR(A96) -> 4/2022 | G96: income
A97: 44671 | B97: -147.97 | C97: =IF(SIGN(B97)=-1, B97*-1, B97) -> 147.97 | D97: APS electric pmt PAYMENT 220418 5175354092 Autopay | E97: aps | F97: =MONTH(A97)&"/"&YEAR(A97) -> 4/2022 | G97: Utilities
A98: 44672 | B98: -1400 | C98: =IF(SIGN(B98)=-1, B98*-1, B98) -> 1400 | D98: VENMO PAYMENT 220421 1019665215805 SEAN LEWIS | E98: rent | F98: =MONTH(A98)&"/"&YEAR(A98) -> 4/2022 | G98: Housing
A99: 44672 | B99: 2240.07 | C99: =IF(SIGN(B99)=-1, B99*-1, B99) -> 2240.07 | D99: Nationwide PAYROLL 01 HRP0008262709 Sean Lewis | E99: nationwide | F99: =MONTH(A99)&"/"&YEAR(A99) -> 4/2022 | G99: income
A100: 44676 | B100: -59 | C100: =IF(SIGN(B100)=-1, B100*-1, B100) -> 59 | D100: VENMO PAYMENT 220425 1019749370210 SEAN LEWIS | E100: Maricela | F100: =MONTH(A100)&"/"&YEAR(A100) -> 4/2022 | G100: Recreation_Entertainment
...

Sheet AMEX
A1: Date | B1: Description | C1: Amount | D1: Category
A2: 02/03/2022 | B2: LIFE TIME CAFE 132Q3KATY AZ | C2: 17.81 | D2: Restaurant-Bar & Café
A3: 02/04/2022 | B3: HACHI RAMEN 0000 TEMPE AZ | C3: 32.41 | D3: Restaurant-Restaurant
A4: 02/04/2022 | B4: THE HOME DEPOT TEMPE AZ | C4: 26.04 | D4: Merchandise & Supplies-Hardware Supplies
A5: 02/05/2022 | B5: UNITED STATES PROFESORLANDO FL | C5: 378.17 | D5: Entertainment-Associations
A6: 02/06/2022 | B6: BOSA DONUTS AHWATUKEPHOENIX AZ | C6: 5 | D6: Restaurant-Restaurant
A7: 02/06/2022 | B7: TARGET PHOENIX SPECTPHOENIX AZ | C7: 152.8 | D7: Merchandise & Supplies-Wholesale Stores
A8: 02/06/2022 | B8: TST* WOW WOW HAWAIIAPHOENIX AZ | C8: 15.7 | D8: Restaurant-Restaurant
A9: 02/06/2022 | B9: UNION 76 09480716 PHOENIX AZ | C9: 37.4 | D9: Transportation-Fuel
A10: 02/08/2022 | B10: TACOS HUICHO #2 0000PHOENIX AZ | C10: 40.87 | D10: Restaurant-Restaurant
A11: 02/09/2022 | B11: WALGREENS PHOENIX AZ | C11: 3.19 | D11: Merchandise & Supplies-Pharmacies
A12: 02/10/2022 | B12: PHOENIX TENNIS CENTEPHOENIX AZ | C12: 4.33 | D12: Other-Miscellaneous
A13: 02/10/2022 | B13: TCKTWEB*CARIBOUWITHSSAN FRANCISCO CA | C13: 67 | D13: Entertainment-General Events
... A68: 07/17/2022 | B68: VHLV- LODGING 021770LAS VEGAS NV | C68: 112.87 | D68: Travel-Lodging

Sheet June Trips
A1: Trans Date | B1: Description | C1: Individual Amount | D1: Shared Amount | E1: Split Amount | F1: Amount | G1: Date | H1: Short_Desc | I1: Category_2
A2: 44725 | B2: Aldi | D2: 11.71 | E2: =D2/2 -> 5.855 | F2: =E2+C2 -> 5.855 | G2: =MONTH(A2)&"/"&YEAR(A2) -> 6/2022 | H2: groceries | I2: =VLOOKUP(Table5[[#This Row],[Short_Desc]],dis_table[[#All],[Short_Desc]:[CumAmount]],4,0) -> Food
A3: 44727 | B3: Uber | D3: 42.54 | E3: =D3/2 -> 21.27 | F3: =E3+C3 -> 21.27 | G3: =MONTH(A3)&"/"&YEAR(A3) -> 6/2022 | H3: ride_share | I3: =VLOOKUP(Table5[[#This Row],[Short_Desc]],dis_table[[#All],[Short_Desc]:[CumAmount]],4,0) -> Transportation
A4: 44729 | B4: Hilton Shulas Resturant | C4: 5.3 | F4: =E4+C4 -> 5.3 | G4: =MONTH(A4)&"/"&YEAR(A4) -> 6/2022 | H4: restaurant | I4: =VLOOKUP(Table5[[#This Row],[Short_Desc]],dis_table[[#All],[Short_Desc]:[CumAmount]],4,0) -> Food
A5: 44731 | B5: Amtrak Northeast Cafe | C5: 18.5 | F5: =E5+C5 -> 18.5 | G5: =MONTH(A5)&"/"&YEAR(A5) -> 6/2022 | H5: fast_food | I5: =VLOOKUP(Table5[[#This Row],[Short_Desc]],dis_table[[#All],[Short_Desc]:[CumAmount]],4,0) -> Food
A6: 44731 | B6: Macdonalds | D6: 23.62 | E6: =D6/2 -> 11.81 | F6: =E6+C6 -> 11.81 | G6: =MONTH(A6)&"/"&YEAR(A6) -> 6/2022 | H6: fast_food | I6: =VLOOKUP(Table5[[#This Row],[Short_Desc]],dis_table[[#All],[Short_Desc]:[CumAmount]],4,0) -> Food
A7: 44731 | B7: Hilton | D7: 497.04 | E7: =D7/2 -> 248.52 | F7: =E7+C7 -> 248.52 | G7: =MONTH(A7)&"/"&YEAR(A7) -> 6/2022 | H7: hotel | I7: Recreation_Entertainment
A8: 44732 | B8: Uber | D8: 56.52 | E8: =D8/2 -> 28.26 | F8: =E8+C8 -> 28.26 | G8: =MONTH(A8)&"/"&YEAR(A8) -> 6/2022 | H8: ride_share | I8: =VLOOKUP(Table5[[#This Row],[Short_Desc]],dis_table[[#All],[Short_Desc]:[CumAmount]],4,0) -> Transportation
A9: 44732 | B9: Uber | D9: 12.97 | E9: =D9/2 -> 6.485 | F9: =E9+C9 -> 6.485 | G9: =MONTH(A9)&"/"&YEAR(A9) -> 6/2022 | H9: ride_share | I9: =VLOOKUP(Table5[[#This Row],[Short_Desc]],dis_table[[#All],[Short_Desc]:[CumAmount]],4,0) -> Transportation
A10: 44732 | B10: Republic | D10: 85 | E10: =D10/2 -> 42.5 | F10: =E10+C10 -> 42.5 | G10: =MONTH(A10)&"/"&YEAR(A10) -> 6/2022 | H10: restaurant | I10: =VLOOKUP(Table5[[#This Row],[Short_Desc]],dis_table[[#All],[Short_Desc]:[CumAmount]],4,0) -> Food
A11: 44732 | B11: Trip Advisor (underground tour) | D11: 58.06 | E11: =D11/2 -> 29.03 | F11: =E11+C11 -> 29.03 | G11: =MONTH(A11)&"/"&YEAR(A11) -> 6/2022 | H11: tour | I11: Recreation_Entertainment
A12: 44734 | B12: Hurry Curry of Tokyo | D12: 33.08 | E12: =D12/2 -> 16.54 | F12: =E12+C12 -> 16.54 | G12: =MONTH(A12)&"/"&YEAR(A12) -> 6/2022 | H12: restaurant | I12: =VLOOKUP(Table5[[#This Row],[Short_Desc]],dis_table[[#All],[Short_Desc]:[CumAmount]],4,0) -> Food
A13: 44735 | B13: La Parisienne French Bakery | D13: 26.22 | E13: =D13/2 -> 13.11 | F13: =E13+C13 -> 13.11 | G13: =MONTH(A13)&"/"&YEAR(A13) -> 6/2022 | H13: restaurant | I13: =VLOOKUP(Table5[[#This Row],[Short_Desc]],dis_table[[#All],[Short_Desc]:[CumAmount]],4,0) -> Food
A14: 44736 | B14: UW food Services | C14: 14.37 | F14: =E14+C14 -> 14.37 | G14: =MONTH(A14)&"/"&YEAR(A14) -> 6/2022 | H14: fast_food | I14: =VLOOKUP(Table5[[#This Row],[Short_Desc]],dis_table[[#All],[Short_Desc]:[CumAmount]],4,0) -> Food
A15: 44736 | B15: What the Pho Xpress | D15: 32.82 | E15: =D15/2 -> 16.41 | F15: =E15+C15 -> 16.41 | G15: =MONTH(A15)&"/"&YEAR(A15) -> 6/2022 | H15: restaurant | I15: =VLOOKUP(Table5[[#This Row],[Short_Desc]],dis_table[[#All],[Short_Desc]:[CumAmount]],4,0) -> Food
A16: 44736 | B16: Macy's (Luggage) | C16: 711.25 | F16: =E16+C16 -> 711.25 | G16: =MONTH(A16)&"/"&YEAR(A16) -> 6/2022 | H16: luggage | I16: Personal_Spending
A17: 44736 | B17: Umi Sake House | D17: 145.54 | E17: =D17/2 -> 72.77 | F17: =E17+C17 -> 72.77 | G17: =MONTH(A17)&"/"&YEAR(A17) -> 6/2022 | H17: restaurant | I17: =VLOOKUP(Table5[[#This Row],[Short_Desc]],dis_table[[#All],[Short_Desc]:[CumAmount]],4,0) -> Food
A18: 44738 | B18: Pho Viet Anh | D18: 44 | E18: =D18/2 -> 22 | F18: =E18+C18 -> 22 | G18: =MONTH(A18)&"/"&YEAR(A18) -> 6/2022 | H18: restaurant | I18: =VLOOKUP(Table5[[#This Row],[Short_Desc]],dis_table[[#All],[Short_Desc]:[CumAmount]],4,0) -> Food
A19: 44738 | B19: Hyatt House Space Needle | D19: 1751.05 | E19: =D19/2 -> 875.525 | F19: =E19+C19 -> 875.525 | G19: =MONTH(A19)&"/"&YEAR(A19) -> 6/2022 | H19: hotel | I19: Recreation_Entertainment
A20: 44739 | B20: Traveluro - Hampton Inn | D20: 116 | E20: =D20/2 -> 58 | F20: =E20+C20 -> 58 | G20: =MONTH(A20)&"/"&YEAR(A20) -> 6/2022 | H20: hotel | I20: Recreation_Entertainment
A21: 44740 | B21: Pitamore | D21: 25.71 | E21: =D21/2 -> 12.855 | F21: =E21+C21 -> 12.855 | G21: =MONTH(A21)&"/"&YEAR(A21) -> 6/2022 | H21: restaurant | I21: =VLOOKUP(Table5[[#This Row],[Short_Desc]],dis_table[[#All],[Short_Desc]:[CumAmount]],4,0) -> Food
A22: 44741 | B22: Ramen Utsuke | D22: 34.7 | E22: =D22/2 -> 17.35 | F22: =E22+C22 -> 17.35 | G22: =MONTH(A22)&"/"&YEAR(A22) -> 6/2022 | H22: restaurant | I22: =VLOOKUP(Table5[[#This Row],[Short_Desc]],dis_table[[#All],[Short_Desc]:[CumAmount]],4,0) -> Food
A23: 44741 | B23: CVS Pharmacy | D23: 19.88 | E23: =D23/2 -> 9.94 | F23: =E23+C23 -> 9.94 | G23: =MONTH(A23)&"/"&YEAR(A23) -> 6/2022 | H23: conv_store | I23: =VLOOKUP(Table5[[#This Row],[Short_Desc]],dis_table[[#All],[Short_Desc]:[CumAmount]],4,0) -> Personal_Spending
A24: 44741 | B24: Uber Eats | D24: 41.7 | E24: =D24/2 -> 20.85 | F24: =E24+C24 -> 20.85 | G24: =MONTH(A24)&"/"&YEAR(A24) -> 6/2022 | H24: fast_food | I24: =VLOOKUP(Table5[[#This Row],[Short_Desc]],dis_table[[#All],[Short_Desc]:[CumAmount]],4,0) -> Food
A25: 44741 | B25: Hotel Tonight - Kimton Hotel Monaco Baltimore | D25: 478 | E25: =D25/2 -> 239 | F25: =E25+C25 -> 239 | G25: =MONTH(A25)&"/"&YEAR(A25) -> 6/2022 | H25: hotel | I25: Recreation_Entertainment
A26: 44742 | B26: CVS Pharmacy | D26: 46.45 | E26: =D26/2 -> 23.225 | F26: =E26+C26 -> 23.225 | G26: =MONTH(A26)&"/"&YEAR(A26) -> 6/2022 | H26: conv_store | I26: =VLOOKUP(Table5[[#This Row],[Short_Desc]],dis_table[[#All],[Short_Desc]:[CumAmount]],4,0) -> Personal_Spending
A27: 44742 | B27: Corner Baker Inner Harbor | D27: 21.28 | E27: =D27/2 -> 10.64 | F27: =E27+C27 -> 10.64 | G27: =MONTH(A27)&"/"&YEAR(A27) -> 6/2022 | H27: restaurant | I27: =VLOOKUP(Table5[[#This Row],[Short_Desc]],dis_table[[#All],[Short_Desc]:[CumAmount]],4,0) -> Food
A28: 44742 | B28: Dalesios Restaurant of Little Italy | D28: 50.88 | E28: =D28/2 -> 25.44 | F28: =E28+C28 -> 25.44 | G28: =MONTH(A28)&"/"&YEAR(A28) -> 6/2022 | H28: restaurant | I28: =VLOOKUP(Table5[[#This Row],[Short_Desc]],dis_table[[#All],[Short_Desc]:[CumAmount]],4,0) -> Food
A29: 44743 | B29: Uber Eats - kumari restaurant | D29: 53.5 | E29: =D29/2 -> 26.75 | F29: =E29+C29 -> 26.75 | G29: =MONTH(A29)&"/"&YEAR(A29) -> 7/2022 | H29: fast_food | I29: =VLOOKUP(Table5[[#This Row],[Short_Desc]],dis_table[[#All],[Short_Desc]:[CumAmount]],4,0) -> Food
A30: 44743 | B30: Chipotle | D30: 20.41 | E30: =D30/2 -> 10.205 | F30: =E30+C30 -> 10.205 | G30: =MONTH(A30)&"/"&YEAR(A30) -> 7/2022 | H30: fast_food | I30: =VLOOKUP(Table5[[#This Row],[Short_Desc]],dis_table[[#All],[Short_Desc]:[CumAmount]],4,0) -> Food
A31: 44744 | B31: Uber Eats | D31: 38.5 | E31: =D31/2 -> 19.25 | F31: =E31+C31 -> 19.25 | G31: =MONTH(A31)&"/"&YEAR(A31) -> 7/2022 | H31: fast_food | I31: =VLOOKUP(Table5[[#This Row],[Short_Desc]],dis_table[[#All],[Short_Desc]:[CumAmount]],4,0) -> Food
A32: 44745 | B32: Uber | D32: 95.86 | E32: =D32/2 -> 47.93 | F32: =E32+C32 -> 47.93 | G32: =MONTH(A32)&"/"&YEAR(A32) -> 7/2022 | H32: ride_share | I32: =VLOOKUP(Table5[[#This Row],[Short_Desc]],dis_table[[#All],[Short_Desc]:[CumAmount]],4,0) -> Transportation
A33: 44745 | B33: Kimpton Hotel (Mini Bar) | C33: 9.54 | F33: =E33+C33 -> 9.54 | G33: =MONTH(A33)&"/"&YEAR(A33) -> 7/2022 | H33: conv_store | I33: =VLOOKUP(Table5[[#This Row],[Short_Desc]],dis_table[[#All],[Short_Desc]:[CumAmount]],4,0) -> Personal_Spending
F34: =SUBTOTAL(109,Table5[Amount]) -> 2690.48

Sheet Accounts
B2: Balance | C2: Limit | D2: Available Credit | E2: Monthly Payment | F2: Due Date
A3: Discover | B3: 6077.24 | C3: 7900 | D3: =C3-B3 -> 1822.76 | E3: 120 | F3: 28 | G3: =B3/E3 -> 50.643667
A4: Care Credit | B4: 0 | C4: 7550 | D4: =C4-B4 -> 7550 | F4: 2
A5: Best Buy | B5: 554.09 | C5: 4997 | D5: =C5-B5 -> 4442.91 | F5: 14
A6: Amex | B6: 505.36 | F6: 2
A7: Student Loan | B7: 22430.56 | E7: 348
A8: Vincent Debt | B8: =Table5[[#Totals],[Amount]] -> 2690.48
A12: Income | B12: 44771 | C12: =B12+14 -> 44785 | D12: =C12+14 -> 44799 | E12: =D12+14 -> 44813 | F12: =E12+14 -> 44827 | G12: =F12+14 -> 44841 | H12: =G12+14 -> 44855 | I12: =H12+14 -> 44869 | J12: =I12+14 -> 44883 | ... M12: =L12+14 -> 44925
A13: Nationwide | B13: 2482.89 | C13: 2482.89 | D13: 2482.89 | E13: 2482.89 | F13: 2482.89 | G13: 2482.89 | H13: 2482.89 | I13: 2482.89 | J13: 2482.89 | K13: 2482.89 | L13: 2482.89 | M13: 2482.89 | N13: =SUM(B13:M13) -> 29794.68
A14: surgery refund | B14: 504.86
A15: deposit | G15: 550
B16: =SUM(B13:B15) -> 2987.75 | C16: =SUM(C13:C15)+B28 -> 2993.4 | D16: =SUM(D13:D15)+C28 -> 2916.84 | E16: =SUM(E13:E15)+D28 -> 2999.73 | F16: =SUM(F13:F15)+E28 -> 2944.524 | G16: =SUM(G13:G15)+F28 -> 3439.318 | H16: =SUM(H13:H15)+G28 -> 3026.112 | I16: =SUM(I13:I15)+H28 -> 2970.906 | J16: =SUM(J13:J15)+I28 -> 2857.7 | ... M16: =SUM(M13:M15)+L28 -> 5048.37
A18: Payments
A19: rent | B19: 1400 | D19: 1400 | G19: 710 | I19: 710 | K19: 710
A20: Discover | B20: 1077.24 | C20: 1500 | D20: 1000 | E20: 2000 | F20: 2000 | G20: 1300 | H20: 2000 | I20: 1000 | J20: 2000 | K20: 1200 | L20: 1000 | M20: 1000
A21: Care Credit | B21: 0 | C21: 0 | D21: 0 | E21: 0 | F21: 0 | G21: 0 | H21: 0 | I21: 0 | J21: 0 | K21: 0 | L21: 0 | M21: 0
A22: Best Buy | C22: 554.09 | D22: 0 | E22: 0 | F22: 0 | G22: 0 | H22: 0 | I22: 0 | J22: 0 | K22: 0 | L22: 0 | M22: 0
A23: Amex | C23: 505.36 | D23: 0 | E23: 0 | F23: 0 | G23: 0 | H23: 0 | I23: 0 | J23: 0 | K23: 0 | L23: 0 | M23: 0
A24: Student Loan | G24: =$E$7 -> 348 | I24: =$E$7 -> 348 | K24: =$E$7 -> 348
A25: Vincent Debt | E25: =B8/5 -> 538.096 | F25: 538.096 | G25: 538.096 | H25: 538.096 | I25: 538.096
B26: =SUM(B19:B25) -> 2477.24 | C26: =SUM(C19:C25) -> 2559.45 | D26: =SUM(D19:D25) -> 2400 | E26: =SUM(E19:E25) -> 2538.096 | F26: =SUM(F19:F25) -> 2538.096 | G26: =SUM(G19:G25) -> 2896.096 | H26: =SUM(H19:H25) -> 2538.096 | I26: =SUM(I19:I25) -> 2596.096 | ... M26: =SUM(M19:M25) -> 1000
B28: =B16-B26 -> 510.51 | C28: =C16-C26 -> 433.95 | D28: =D16-D26 -> 516.84 | E28: =E16-E26 -> 461.634 | F28: =F16-F26 -> 406.428 | G28: =G16-G26 -> 543.222 | H28: =H16-H26 -> 488.016 | I28: =I16-I26 -> 374.81 | ... M28: =M16-M26 -> 4048.37
A30: Discover Balance Watch
A31: Starting Balance | B31: =B3 -> 6077.24 | C31: =B34 -> 6000 | D31: =C34 -> 5500 | E31: =D34 -> 5500 | F31: =E34 -> 4500 | G31: =F34 -> 3500 | H31: =G34 -> 3200 | I31: =H34 -> 2200 | J31: =I34 -> 2200 | ... M31: =L34 -> 1000
A32: After Payment | B32: =B31-B20 -> 5000 | C32: =C31-C20 -> 4500 | D32: =D31-D20 -> 4500 | E32: =E31-E20 -> 3500 | F32: =F31-F20 -> 2500 | G32: =G31-G20 -> 2200 | H32: =H31-H20 -> 1200 | I32: =I31-I20 -> 1200 | ... M32: =M31-M20 -> 0
A33: Est. Spending | B33: 1000 | C33: 1000 | D33: 1000 | E33: 1000 | F33: 1000 | G33: 1000 | H33: 1000 | I33: 1000 | J33: 1000 | K33: 1000 | L33: 1000 | M33: 1000
A34: Ending Balance | B34: =B32+B33 -> 6000 | C34: =C32+C33 -> 5500 | D34: =D32+D33 -> 5500 | E34: =E32+E33 -> 4500 | F34: =F32+F33 -> 3500 | G34: =G32+G33 -> 3200 | H34: =H32+H33 -> 2200 | I34: =I32+I33 -> 2200 | ... M34: =M32+M33 -> 1000

Sheet Category Summary
B2: All Accounts | C2: 01/2022 | D2: 02/2022 | E2: 03/2022 | F2: 04/2022 | G2: 05/2022 | H2: 06/2022 | I2: 07/2022 | J2: Total
B3: Food | C3: =SUMIFS(dis_table[Amount],dis_table[Category_2],'Category Summary'!$B3,dis_table[Date],'Category Summary'!C$2) +SUMIFS(cc_table[Amount],cc_table[Category_2],'Category Summary'!$B3,cc_table[Date],'Category Summary'!C$2) + SUMIFS(bb_table[Amount],bb_table[Category_2],'Category Summary'!$B3,bb_table[Date],'Category Summary'!C$2) + SUMIFS(Table5[Amount],Table5[Category_2],'Category Summary'!$B3,Table5[Date],'Category Summary'!C$2)+C18*-1 -> 587.29 | D3: =SUMIFS(dis_table[Amount],dis_table[Category_2],'Category Summary'!$B3,dis_table[Date],'Category Summary'!D$2) +SUMIFS(cc_table[Amount],cc_table[Category_2],'Category Summary'!$B3,cc_table[Date],'Category Summary'!D$2) + SUMIFS(bb_table[Amount],bb_table[Category_2],'Category Summary'!$B3,bb_table[Date],'Category Summary'!D$2) + SUMIFS(Table5[Amount],Table5[Category_2],'Category Summary'!$B3,Table5[Date],'Category Summary'!D$2)+D18*-1 -> 248.29 | E3: =SUMIFS(dis_table[Amount],dis_table[Category_2],'Category Summary'!$B3,dis_table[Date],'Category Summary'!E$2) +SUMIFS(cc_table[Amount],cc_table[Category_2],'Category Summary'!$B3,cc_table[Date],'Category Summary'!E$2) + SUMIFS(bb_table[Amount],bb_table[Category_2],'Category Summary'!$B3,bb_table[Date],'Category Summary'!E$2) + SUMIFS(Table5[Amount],Table5[Category_2],'Category Summary'!$B3,Table5[Date],'Category Summary'!E$2)+E18*-1 -> 1231.25 | F3: =SUMIFS(dis_table[Amount],dis_table[Category_2],'Category Summary'!$B3,dis_table[Date],'Category Summary'!F$2) +SUMIFS(cc_table[Amount],cc_table[Category_2],'Category Summary'!$B3,cc_table[Date],'Category Summary'!F$2) + SUMIFS(bb_table[Amount],bb_table[Category_2],'Category Summary'!$B3,bb_table[Date],'Category Summary'!F$2) + SUMIFS(Table5[Amount],Table5[Category_2],'Category Summary'!$B3,Table5[Date],'Category Summary'!F$2)+F18*-1 -> 945.31 | G3: =SUMIFS(dis_table[Amount],dis_table[Category_2],'Category Summary'!$B3,dis_table[Date],'Category Summary'!G$2) +SUMIFS(cc_table[Amount],cc_table[Category_2],'Category Summary'!$B3,cc_table[Date],'Category Summary'!G$2) + SUMIFS(bb_table[Amount],bb_table[Category_2],'Category Summary'!$B3,bb_table[Date],'Category Summary'!G$2) + SUMIFS(Table5[Amount],Table5[Category_2],'Category Summary'!$B3,Table5[Date],'Category Summary'!G$2)+G18*-1 -> 766.29 | H3: =SUMIFS(dis_table[Amount],dis_table[Category_2],'Category Summary'!$B3,dis_table[Date],'Category Summary'!H$2) +SUMIFS(cc_table[Amount],cc_table[Category_2],'Category Summary'!$B3,cc_table[Date],'Category Summary'!H$2) + SUMIFS(bb_table[Amount],bb_table[Category_2],'Category Summary'!$B3,bb_table[Date],'Category Summary'!H$2) + SUMIFS(Table5[Amount],Table5[Category_2],'Category Summary'!$B3,Table5[Date],'Category Summary'!H$2)+H18*-1 -> 945.77 | I3: =SUMIFS(dis_table[Amount],dis_table[Category_2],'Category Summary'!$B3,dis_table[Date],'Category Summary'!I$2) +SUMIFS(cc_table[Amount],cc_table[Category_2],'Category Summary'!$B3,cc_table[Date],'Category Summary'!I$2) + SUMIFS(bb_table[Amount],bb_table[Category_2],'Category Summary'!$B3,bb_table[Date],'Category Summary'!I$2) + SUMIFS(Table5[Amount],Table5[Category_2],'Category Summary'!$B3,Table5[Date],'Category Summary'!I$2)+I18*-1 -> 735.445 | J3: =SUM(C3:I3) -> 5459.645 | K3: =J3/$J$27 -> 0.14862668
B4: Recreation_Entertainment | C4: =SUMIFS(dis_table[Amount],dis_table[Category_2],'Category Summary'!$B4,dis_table[Date],'Category Summary'!C$2) +SUMIFS(cc_table[Amount],cc_table[Category_2],'Category Summary'!$B4,cc_table[Date],'Category Summary'!C$2) + SUMIFS(bb_table[Amount],bb_table[Category_2],'Category Summary'!$B4,bb_table[Date],'Category Summary'!C$2) + SUMIFS(Table5[Amount],Table5[Category_2],'Category Summary'!$B4,Table5[Date],'Category Summary'!C$2)+C19*-1 -> 849.09 | D4: =SUMIFS(dis_table[Amount],dis_table[Category_2],'Category Summary'!$B4,dis_table[Date],'Category Summary'!D$2) +SUMIFS(cc_table[Amount],cc_table[Category_2],'Category Summary'!$B4,cc_table[Date],'Category Summary'!D$2) + SUMIFS(bb_table[Amount],bb_table[Category_2],'Category Summary'!$B4,bb_table[Date],'Category Summary'!D$2) + SUMIFS(Table5[Amount],Table5[Category_2],'Category Summary'!$B4,Table5[Date],'Category Summary'!D$2)+D19*-1 -> 528.66 | E4: =SUMIFS(dis_table[Amount],dis_table[Category_2],'Category Summary'!$B4,dis_table[Date],'Category Summary'!E$2) +SUMIFS(cc_table[Amount],cc_table[Category_2],'Category Summary'!$B4,cc_table[Date],'Category Summary'!E$2) + SUMIFS(bb_table[Amount],bb_table[Category_2],'Category Summary'!$B4,bb_table[Date],'Category Summary'!E$2) + SUMIFS(Table5[Amount],Table5[Category_2],'Category Summary'!$B4,Table5[Date],'Category Summary'!E$2)+E19*-1 -> 887.47 | F4: =SUMIFS(dis_table[Amount],dis_table[Category_2],'Category Summary'!$B4,dis_table[Date],'Category Summary'!F$2) +SUMIFS(cc_table[Amount],cc_table[Category_2],'Category Summary'!$B4,cc_table[Date],'Category Summary'!F$2) + SUMIFS(bb_table[Amount],bb_table[Category_2],'Category Summary'!$B4,bb_table[Date],'Category Summary'!F$2) + SUMIFS(Table5[Amount],Table5[Category_2],'Category Summary'!$B4,Table5[Date],'Category Summary'!F$2)+F19*-1 -> 695.02 | G4: =SUMIFS(dis_table[Amount],dis_table[Category_2],'Category Summary'!$B4,dis_table[Date],'Category Summary'!G$2) +SUMIFS(cc_table[Amount],cc_table[Category_2],'Category Summary'!$B4,cc_table[Date],'Category Summary'!G$2) + SUMIFS(bb_table[Amount],bb_table[Category_2],'Category Summary'!$B4,bb_table[Date],'Category Summary'!G$2) + SUMIFS(Table5[Amount],Table5[Category_2],'Category Summary'!$B4,Table5[Date],'Category Summary'!G$2)+G19*-1 -> 2111.44 | H4: =SUMIFS(dis_table[Amount],dis_table[Category_2],'Category Summary'!$B4,dis_table[Date],'Category Summary'!H$2) +SUMIFS(cc_table[Amount],cc_table[Category_2],'Category Summary'!$B4,cc_table[Date],'Category Summary'!H$2) + SUMIFS(bb_table[Amount],bb_table[Category_2],'Category Summary'!$B4,bb_table[Date],'Category Summary'!H$2) + SUMIFS(Table5[Amount],Table5[Category_2],'Category Summary'!$B4,Table5[Date],'Category Summary'!H$2)+H19*-1 -> 2665.935 | I4: =SUMIFS(dis_table[Amount],dis_table[Category_2],'Category Summary'!$B4,dis_table[Date],'Category Summary'!I$2) +SUMIFS(cc_table[Amount],cc_table[Category_2],'Category Summary'!$B4,cc_table[Date],'Category Summary'!I$2) + SUMIFS(bb_table[Amount],bb_table[Category_2],'Category Summary'!$B4,bb_table[Date],'Category Summary'!I$2) + SUMIFS(Table5[Amount],Table5[Category_2],'Category Summary'!$B4,Table5[Date],'Category Summary'!I$2)+I19*-1 -> 739.41 | J4: =SUM(C4:I4) -> 8477.025 | K4: =J4/$J$27 -> 0.23076813
B5: Personal_Spending | C5: =SUMIFS(dis_table[Amount],dis_table[Category_2],'Category Summary'!$B5,dis_table[Date],'Category Summary'!C$2) +SUMIFS(cc_table[Amount],cc_table[Category_2],'Category Summary'!$B5,cc_table[Date],'Category Summary'!C$2) + SUMIFS(bb_table[Amount],bb_table[Category_2],'Category Summary'!$B5,bb_table[Date],'Category Summary'!C$2) + SUMIFS(Table5[Amount],Table5[Category_2],'Category Summary'!$B5,Table5[Date],'Category Summary'!C$2)+C20*-1 -> 826.7 | D5: =SUMIFS(dis_table[Amount],dis_table[Category_2],'Category Summary'!$B5,dis_table[Date],'Category Summary'!D$2) +SUMIFS(cc_table[Amount],cc_table[Category_2],'Category Summary'!$B5,cc_table[Date],'Category Summary'!D$2) + SUMIFS(bb_table[Amount],bb_table[Category_2],'Category Summary'!$B5,bb_table[Date],'Category Summary'!D$2) + SUMIFS(Table5[Amount],Table5[Category_2],'Category Summary'!$B5,Table5[Date],'Category Summary'!D$2)+D20*-1 -> 336.7 | E5: =SUMIFS(dis_table[Amount],dis_table[Category_2],'Category Summary'!$B5,dis_table[Date],'Category Summary'!E$2) +SUMIFS(cc_table[Amount],cc_table[Category_2],'Category Summary'!$B5,cc_table[Date],'Category Summary'!E$2) + SUMIFS(bb_table[Amount],bb_table[Category_2],'Category Summary'!$B5,bb_table[Date],'Category Summary'!E$2) + SUMIFS(Table5[Amount],Table5[Category_2],'Category Summary'!$B5,Table5[Date],'Category Summary'!E$2)+E20*-1 -> 726.89 | F5: =SUMIFS(dis_table[Amount],dis_table[Category_2],'Category Summary'!$B5,dis_table[Date],'Category Summary'!F$2) +SUMIFS(cc_table[Amount],cc_table[Category_2],'Category Summary'!$B5,cc_table[Date],'Category Summary'!F$2) + SUMIFS(bb_table[Amount],bb_table[Category_2],'Category Summary'!$B5,bb_table[Date],'Category Summary'!F$2) + SUMIFS(Table5[Amount],Table5[Category_2],'Category Summary'!$B5,Table5[Date],'Category Summary'!F$2)+F20*-1 -> 185.98 | G5: =SUMIFS(dis_table[Amount],dis_table[Category_2],'Category Summary'!$B5,dis_table[Date],'Category Summary'!G$2) +SUMIFS(cc_table[Amount],cc_table[Category_2],'Category Summary'!$B5,cc_table[Date],'Category Summary'!G$2) + SUMIFS(bb_table[Amount],bb_table[Category_2],'Category Summary'!$B5,bb_table[Date],'Category Summary'!G$2) + SUMIFS(Table5[Amount],Table5[Category_2],'Category Summary'!$B5,Table5[Date],'Category Summary'!G$2)+G20*-1 -> 1010.83 | H5: =SUMIFS(dis_table[Amount],dis_table[Category_2],'Category Summary'!$B5,dis_table[Date],'Category Summary'!H$2) +SUMIFS(cc_table[Amount],cc_table[Category_2],'Category Summary'!$B5,cc_table[Date],'Category Summary'!H$2) + SUMIFS(bb_table[Amount],bb_table[Category_2],'Category Summary'!$B5,bb_table[Date],'Category Summary'!H$2) + SUMIFS(Table5[Amount],Table5[Category_2],'Category Summary'!$B5,Table5[Date],'Category Summary'!H$2)+H20*-1 -> 1392.525 | I5: =SUMIFS(dis_table[Amount],dis_table[Category_2],'Category Summary'!$B5,dis_table[Date],'Category Summary'!I$2) +SUMIFS(cc_table[Amount],cc_table[Category_2],'Category Summary'!$B5,cc_table[Date],'Category Summary'!I$2) + SUMIFS(bb_table[Amount],bb_table[Category_2],'Category Summary'!$B5,bb_table[Date],'Category Summary'!I$2) + SUMIFS(Table5[Amount],Table5[Category_2],'Category Summary'!$B5,Table5[Date],'Category Summary'!I$2)+I20*-1 -> 416.79 | J5: =SUM(C5:I5) -> 4896.415 | K5: =J5/$J$27 -> 0.133294
B6: Transportation | C6: =SUMIFS(dis_table[Amount],dis_table[Category_2],'Category Summary'!$B6,dis_table[Date],'Category Summary'!C$2) +SUMIFS(cc_table[Amount],cc_table[Category_2],'Category Summary'!$B6,cc_table[Date],'Category Summary'!C$2) + SUMIFS(bb_table[Amount],bb_table[Category_2],'Category Summary'!$B6,bb_table[Date],'Category Summary'!C$2) + SUMIFS(Table5[Amount],Table5[Category_2],'Category Summary'!$B6,Table5[Date],'Category Summary'!C$2)+C21*-1 -> 145.57 | D6: =SUMIFS(dis_table[Amount],dis_table[Category_2],'Category Summary'!$B6,dis_table[Date],'Category Summary'!D$2) +SUMIFS(cc_table[Amount],cc_table[Category_2],'Category Summary'!$B6,cc_table[Date],'Category Summary'!D$2) + SUMIFS(bb_table[Amount],bb_table[Category_2],'Category Summary'!$B6,bb_table[Date],'Category Summary'!D$2) + SUMIFS(Table5[Amount],Table5[Category_2],'Category Summary'!$B6,Table5[Date],'Category Summary'!D$2)+D21*-1 -> 333.19 | E6: =SUMIFS(dis_table[Amount],dis_table[Category_2],'Category Summary'!$B6,dis_table[Date],'Category Summary'!E$2) +SUMIFS(cc_table[Amount],cc_table[Category_2],'Category Summary'!$B6,cc_table[Date],'Category Summary'!E$2) + SUMIFS(bb_table[Amount],bb_table[Category_2],'Category Summary'!$B6,bb_table[Date],'Category Summary'!E$2) + SUMIFS(Table5[Amount],Table5[Category_2],'Category Summary'!$B6,Table5[Date],'Category Summary'!E$2)+E21*-1 -> 307.96 | F6: =SUMIFS(dis_table[Amount],dis_table[Category_2],'Category Summary'!$B6,dis_table[Date],'Category Summary'!F$2) +SUMIFS(cc_table[Amount],cc_table[Category_2],'Category Summary'!$B6,cc_table[Date],'Category Summary'!F$2) + SUMIFS(bb_table[Amount],bb_table[Category_2],'Category Summary'!$B6,bb_table[Date],'Category Summary'!F$2) + SUMIFS(Table5[Amount],Table5[Category_2],'Category Summary'!$B6,Table5[Date],'Category Summary'!F$2)+F21*-1 -> 316.07 | G6: =SUMIFS(dis_table[Amount],dis_table[Category_2],'Category Summary'!$B6,dis_table[Date],'Category Summary'!G$2) +SUMIFS(cc_table[Amount],cc_table[Category_2],'Category Summary'!$B6,cc_table[Date],'Category Summary'!G$2) + SUMIFS(bb_table[Amount],bb_table[Category_2],'Category Summary'!$B6,bb_table[Date],'Category Summary'!G$2) + SUMIFS(Table5[Amount],Table5[Category_2],'Category Summary'!$B6,Table5[Date],'Category Summary'!G$2)+G21*-1 -> 682.91 | H6: =SUMIFS(dis_table[Amount],dis_table[Category_2],'Category Summary'!$B6,dis_table[Date],'Category Summary'!H$2) +SUMIFS(cc_table[Amount],cc_table[Category_2],'Category Summary'!$B6,cc_table[Date],'Category Summary'!H$2) + SUMIFS(bb_table[Amount],bb_table[Category_2],'Category Summary'!$B6,bb_table[Date],'Category Summary'!H$2) + SUMIFS(Table5[Amount],Table5[Category_2],'Category Summary'!$B6,Table5[Date],'Category Summary'!H$2)+H21*-1 -> 511.855 | I6: =SUMIFS(dis_table[Amount],dis_table[Category_2],'Category Summary'!$B6,dis_table[Date],'Category Summary'!I$2) +SUMIFS(cc_table[Amount],cc_table[Category_2],'Category Summary'!$B6,cc_table[Date],'Category Summary'!I$2) + SUMIFS(bb_table[Amount],bb_table[Category_2],'Category Summary'!$B6,bb_table[Date],'Category Summary'!I$2) + SUMIFS(Table5[Amount],Table5[Category_2],'Category Summary'!$B6,Table5[Date],'Category Summary'!I$2)+I21*-1 -> 838.13 | J6: =SUM(C6:I6) -> 3135.685 | K6: =J6/$J$27 -> 0.085362042
B7: Misc | C7: =SUMIFS(dis_table[Amount],dis_table[Category_2],'Category Summary'!$B7,dis_table[Date],'Category Summary'!C$2) +SUMIFS(cc_table[Amount],cc_table[Category_2],'Category Summary'!$B7,cc_table[Date],'Category Summary'!C$2) + SUMIFS(bb_table[Amount],bb_table[Category_2],'Category Summary'!$B7,bb_table[Date],'Category Summary'!C$2) + SUMIFS(Table5[Amount],Table5[Category_2],'Category Summary'!$B7,Table5[Date],'Category Summary'!C$2)+C22*-1 -> 36.49 | D7: =SUMIFS(dis_table[Amount],dis_table[Category_2],'Category Summary'!$B7,dis_table[Date],'Category Summary'!D$2) +SUMIFS(cc_table[Amount],cc_table[Category_2],'Category Summary'!$B7,cc_table[Date],'Category Summary'!D$2) + SUMIFS(bb_table[Amount],bb_table[Category_2],'Category Summary'!$B7,bb_table[Date],'Category Summary'!D$2) + SUMIFS(Table5[Amount],Table5[Category_2],'Category Summary'!$B7,Table5[Date],'Category Summary'!D$2)+D22*-1 -> 0 | E7: =SUMIFS(dis_table[Amount],dis_table[Category_2],'Category Summary'!$B7,dis_table[Date],'Category Summary'!E$2) +SUMIFS(cc_table[Amount],cc_table[Category_2],'Category Summary'!$B7,cc_table[Date],'Category Summary'!E$2) + SUMIFS(bb_table[Amount],bb_table[Category_2],'Category Summary'!$B7,bb_table[Date],'Category Summary'!E$2) + SUMIFS(Table5[Amount],Table5[Category_2],'Category Summary'!$B7,Table5[Date],'Category Summary'!E$2)+E22*-1 -> 0 | F7: =SUMIFS(dis_table[Amount],dis_table[Category_2],'Category Summary'!$B7,dis_table[Date],'Category Summary'!F$2) +SUMIFS(cc_table[Amount],cc_table[Category_2],'Category Summary'!$B7,cc_table[Date],'Category Summary'!F$2) + SUMIFS(bb_table[Amount],bb_table[Category_2],'Category Summary'!$B7,bb_table[Date],'Category Summary'!F$2) + SUMIFS(Table5[Amount],Table5[Category_2],'Category Summary'!$B7,Table5[Date],'Category Summary'!F$2)+F22*-1 -> 16 | G7: =SUMIFS(dis_table[Amount],dis_table[Category_2],'Category Summary'!$B7,dis_table[Date],'Category Summary'!G$2) +SUMIFS(cc_table[Amount],cc_table[Category_2],'Category Summary'!$B7,cc_table[Date],'Category Summary'!G$2) + SUMIFS(bb_table[Amount],bb_table[Category_2],'Category Summary'!$B7,bb_table[Date],'Category Summary'!G$2) + SUMIFS(Table5[Amount],Table5[Category_2],'Category Summary'!$B7,Table5[Date],'Category Summary'!G$2)+G22*-1 -> 9.75 | H7: =SUMIFS(dis_table[Amount],dis_table[Category_2],'Category Summary'!$B7,dis_table[Date],'Category Summary'!H$2) +SUMIFS(cc_table[Amount],cc_table[Category_2],'Category Summary'!$B7,cc_table[Date],'Category Summary'!H$2) + SUMIFS(bb_table[Amount],bb_table[Category_2],'Category Summary'!$B7,bb_table[Date],'Category Summary'!H$2) + SUMIFS(Table5[Amount],Table5[Category_2],'Category Summary'!$B7,Table5[Date],'Category Summary'!H$2)+H22*-1 -> 83 | I7: =SUMIFS(dis_table[Amount],dis_table[Category_2],'Category Summary'!$B7,dis_table[Date],'Category Summary'!I$2) +SUMIFS(cc_table[Amount],cc_table[Category_2],'Category Summary'!$B7,cc_table[Date],'Category Summary'!I$2) + SUMIFS(bb_table[Amount],bb_table[Category_2],'Category Summary'!$B7,bb_table[Date],'Category Summary'!I$2) + SUMIFS(Table5[Amount],Table5[Category_2],'Category Summary'!$B7,Table5[Date],'Category Summary'!I$2)+I22*-1 -> 5.1 | J7: =SUM(C7:I7) -> 150.34 | K7: =J7/$J$27 -> 0.0040926718
B8: Utilities | C8: =SUMIFS(dis_table[Amount],dis_table[Category_2],'Category Summary'!$B8,dis_table[Date],'Category Summary'!C$2) +SUMIFS(cc_table[Amount],cc_table[Category_2],'Category Summary'!$B8,cc_table[Date],'Category Summary'!C$2) + SUMIFS(bb_table[Amount],bb_table[Category_2],'Category Summary'!$B8,bb_table[Date],'Category Summary'!C$2) + SUMIFS(Table5[Amount],Table5[Category_2],'Category Summary'!$B8,Table5[Date],'Category Summary'!C$2)+C23*-1 -> 29.32 | D8: =SUMIFS(dis_table[Amount],dis_table[Category_2],'Category Summary'!$B8,dis_table[Date],'Category Summary'!D$2) +SUMIFS(cc_table[Amount],cc_table[Category_2],'Category Summary'!$B8,cc_table[Date],'Category Summary'!D$2) + SUMIFS(bb_table[Amount],bb_table[Category_2],'Category Summary'!$B8,bb_table[Date],'Category Summary'!D$2) + SUMIFS(Table5[Amount],Table5[Category_2],'Category Summary'!$B8,Table5[Date],'Category Summary'!D$2)+D23*-1 -> 207.17 | E8: =SUMIFS(dis_table[Amount],dis_table[Category_2],'Category Summary'!$B8,dis_table[Date],'Category Summary'!E$2) +SUMIFS(cc_table[Amount],cc_table[Category_2],'Category Summary'!$B8,cc_table[Date],'Category Summary'!E$2) + SUMIFS(bb_table[Amount],bb_table[Category_2],'Category Summary'!$B8,bb_table[Date],'Category Summary'!E$2) + SUMIFS(Table5[Amount],Table5[Category_2],'Category Summary'!$B8,Table5[Date],'Category Summary'!E$2)+E23*-1 -> 299.5 | F8: =SUMIFS(dis_table[Amount],dis_table[Category_2],'Category Summary'!$B8,dis_table[Date],'Category Summary'!F$2) +SUMIFS(cc_table[Amount],cc_table[Category_2],'Category Summary'!$B8,cc_table[Date],'Category Summary'!F$2) + SUMIFS(bb_table[Amount],bb_table[Category_2],'Category Summary'!$B8,bb_table[Date],'Category Summary'!F$2) + SUMIFS(Table5[Amount],Table5[Category_2],'Category Summary'!$B8,Table5[Date],'Category Summary'!F$2)+F23*-1 -> 267.97 | G8: =SUMIFS(dis_table[Amount],dis_table[Category_2],'Category Summary'!$B8,dis_table[Date],'Category Summary'!G$2) +SUMIFS(cc_table[Amount],cc_table[Category_2],'Category Summary'!$B8,cc_table[Date],'Category Summary'!G$2) + SUMIFS(bb_table[Amount],bb_table[Category_2],'Category Summary'!$B8,bb_table[Date],'Category Summary'!G$2) + SUMIFS(Table5[Amount],Table5[Category_2],'Category Summary'!$B8,Table5[Date],'Category Summary'!G$2)+G23*-1 -> 263.04 | H8: =SUMIFS(dis_table[Amount],dis_table[Category_2],'Category Summary'!$B8,dis_table[Date],'Category Summary'!H$2) +SUMIFS(cc_table[Amount],cc_table[Category_2],'Category Summary'!$B8,cc_table[Date],'Category Summary'!H$2) + SUMIFS(bb_table[Amount],bb_table[Category_2],'Category Summary'!$B8,bb_table[Date],'Category Summary'!H$2) + SUMIFS(Table5[Amount],Table5[Category_2],'Category Summary'!$B8,Table5[Date],'Category Summary'!H$2)+H23*-1 -> 341.77 | I8: =SUMIFS(dis_table[Amount],dis_table[Category_2],'Category Summary'!$B8,dis_table[Date],'Category Summary'!I$2) +SUMIFS(cc_table[Amount],cc_table[Category_2],'Category Summary'!$B8,cc_table[Date],'Category Summary'!I$2) + SUMIFS(bb_table[Amount],bb_table[Category_2],'Category Summary'!$B8,bb_table[Date],'Category Summary'!I$2) + SUMIFS(Table5[Amount],Table5[Category_2],'Category Summary'!$B8,Table5[Date],'Category Summary'!I$2)+I23*-1 -> 272.46 | J8: =SUM(C8:I8) -> 1681.23 | K8: =J8/$J$27 -> 0.045767743
B9: Insurance | C9: =SUMIFS(dis_table[Amount],dis_table[Category_2],'Category Summary'!$B9,dis_table[Date],'Category Summary'!C$2) +SUMIFS(cc_table[Amount],cc_table[Category_2],'Category Summary'!$B9,cc_table[Date],'Category Summary'!C$2) + SUMIFS(bb_table[Amount],bb_table[Category_2],'Category Summary'!$B9,bb_table[Date],'Category Summary'!C$2) + SUMIFS(Table5[Amount],Table5[Category_2],'Category Summary'!$B9,Table5[Date],'Category Summary'!C$2) -> 79.38 | D9: =SUMIFS(dis_table[Amount],dis_table[Category_2],'Category Summary'!$B9,dis_table[Date],'Category Summary'!D$2) +SUMIFS(cc_table[Amount],cc_table[Category_2],'Category Summary'!$B9,cc_table[Date],'Category Summary'!D$2) + SUMIFS(bb_table[Amount],bb_table[Category_2],'Category Summary'!$B9,bb_table[Date],'Category Summary'!D$2) + SUMIFS(Table5[Amount],Table5[Category_2],'Category Summary'!$B9,Table5[Date],'Category Summary'!D$2) -> 79.38 | E9: =SUMIFS(dis_table[Amount],dis_table[Category_2],'Category Summary'!$B9,dis_table[Date],'Category Summary'!E$2) +SUMIFS(cc_table[Amount],cc_table[Category_2],'Category Summary'!$B9,cc_table[Date],'Category Summary'!E$2) + SUMIFS(bb_table[Amount],bb_table[Category_2],'Category Summary'!$B9,bb_table[Date],'Category Summary'!E$2) + SUMIFS(Table5[Amount],Table5[Category_2],'Category Summary'!$B9,Table5[Date],'Category Summary'!E$2) -> 79.38 | F9: =SUMIFS(dis_table[Amount],dis_table[Category_2],'Category Summary'!$B9,dis_table[Date],'Category Summary'!F$2) +SUMIFS(cc_table[Amount],cc_table[Category_2],'Category Summary'!$B9,cc_table[Date],'Category Summary'!F$2) + SUMIFS(bb_table[Amount],bb_table[Category_2],'Category Summary'!$B9,bb_table[Date],'Category Summary'!F$2) + SUMIFS(Table5[Amount],Table5[Category_2],'Category Summary'!$B9,Table5[Date],'Category Summary'!F$2) -> 79.38 | G9: =SUMIFS(dis_table[Amount],dis_table[Category_2],'Category Summary'!$B9,dis_table[Date],'Category Summary'!G$2) +SUMIFS(cc_table[Amount],cc_table[Category_2],'Category Summary'!$B9,cc_table[Date],'Category Summary'!G$2) + SUMIFS(bb_table[Amount],bb_table[Category_2],'Category Summary'!$B9,bb_table[Date],'Category Summary'!G$2) + SUMIFS(Table5[Amount],Table5[Category_2],'Category Summary'!$B9,Table5[Date],'Category Summary'!G$2) -> 79.38 | H9: =SUMIFS(dis_table[Amount],dis_table[Category_2],'Category Summary'!$B9,dis_table[Date],'Category Summary'!H$2) +SUMIFS(cc_table[Amount],cc_table[Category_2],'Category Summary'!$B9,cc_table[Date],'Category Summary'!H$2) + SUMIFS(bb_table[Amount],bb_table[Category_2],'Category Summary'!$B9,bb_table[Date],'Category Summary'!H$2) + SUMIFS(Table5[Amount],Table5[Category_2],'Category Summary'!$B9,Table5[Date],'Category Summary'!H$2) -> 79.38 | I9: =SUMIFS(dis_table[Amount],dis_table[Category_2],'Category Summary'!$B9,dis_table[Date],'Category Summary'!I$2) +SUMIFS(cc_table[Amount],cc_table[Category_2],'Category Summary'!$B9,cc_table[Date],'Category Summary'!I$2) + SUMIFS(bb_table[Amount],bb_table[Category_2],'Category Summary'!$B9,bb_table[Date],'Category Summary'!I$2) + SUMIFS(Table5[Amount],Table5[Category_2],'Category Summary'!$B9,Table5[Date],'Category Summary'!I$2) -> 79.66 | J9: =SUM(C9:I9) -> 555.94 | K9: =J9/$J$27 -> 0.015134229
B10: People | C10: =SUMIFS(dis_table[Amount],dis_table[Category_2],'Category Summary'!$B10,dis_table[Date],'Category Summary'!C$2) +SUMIFS(cc_table[Amount],cc_table[Category_2],'Category Summary'!$B10,cc_table[Date],'Category Summary'!C$2) + SUMIFS(bb_table[Amount],bb_table[Category_2],'Category Summary'!$B10,bb_table[Date],'Category Summary'!C$2) + SUMIFS(Table5[Amount],Table5[Category_2],'Category Summary'!$B10,Table5[Date],'Category Summary'!C$2)+C24*-1 -> 256.76 | D10: =SUMIFS(dis_table[Amount],dis_table[Category_2],'Category Summary'!$B10,dis_table[Date],'Category Summary'!D$2) +SUMIFS(cc_table[Amount],cc_table[Category_2],'Category Summary'!$B10,cc_table[Date],'Category Summary'!D$2) + SUMIFS(bb_table[Amount],bb_table[Category_2],'Category Summary'!$B10,bb_table[Date],'Category Summary'!D$2) + SUMIFS(Table5[Amount],Table5[Category_2],'Category Summary'!$B10,Table5[Date],'Category Summary'!D$2)+D24*-1 -> 1518.21 | E10: =SUMIFS(dis_table[Amount],dis_table[Category_2],'Category Summary'!$B10,dis_table[Date],'Category Summary'!E$2) +SUMIFS(cc_table[Amount],cc_table[Category_2],'Category Summary'!$B10,cc_table[Date],'Category Summary'!E$2) + SUMIFS(bb_table[Amount],bb_table[Category_2],'Category Summary'!$B10,bb_table[Date],'Category Summary'!E$2) + SUMIFS(Table5[Amount],Table5[Category_2],'Category Summary'!$B10,Table5[Date],'Category Summary'!E$2)+E24*-1 -> 1552.29 | F10: =SUMIFS(dis_table[Amount],dis_table[Category_2],'Category Summary'!$B10,dis_table[Date],'Category Summary'!F$2) +SUMIFS(cc_table[Amount],cc_table[Category_2],'Category Summary'!$B10,cc_table[Date],'Category Summary'!F$2) + SUMIFS(bb_table[Amount],bb_table[Category_2],'Category Summary'!$B10,bb_table[Date],'Category Summary'!F$2) + SUMIFS(Table5[Amount],Table5[Category_2],'Category Summary'!$B10,Table5[Date],'Category Summary'!F$2)+F24*-1 -> 668 | G10: =SUMIFS(dis_table[Amount],dis_table[Category_2],'Category Summary'!$B10,dis_table[Date],'Category Summary'!G$2) +SUMIFS(cc_table[Amount],cc_table[Category_2],'Category Summary'!$B10,cc_table[Date],'Category Summary'!G$2) + SUMIFS(bb_table[Amount],bb_table[Category_2],'Category Summary'!$B10,bb_table[Date],'Category Summary'!G$2) + SUMIFS(Table5[Amount],Table5[Category_2],'Category Summary'!$B10,Table5[Date],'Category Summary'!G$2)+G24*-1 -> 468.47 | H10: =SUMIFS(dis_table[Amount],dis_table[Category_2],'Category Summary'!$B10,dis_table[Date],'Category Summary'!H$2) +SUMIFS(cc_table[Amount],cc_table[Category_2],'Category Summary'!$B10,cc_table[Date],'Category Summary'!H$2) + SUMIFS(bb_table[Amount],bb_table[Category_2],'Category Summary'!$B10,bb_table[Date],'Category Summary'!H$2) + SUMIFS(Table5[Amount],Table5[Category_2],'Category Summary'!$B10,Table5[Date],'Category Summary'!H$2)+H24*-1 -> 66.07 | I10: =SUMIFS(dis_table[Amount],dis_table[Category_2],'Category Summary'!$B10,dis_table[Date],'Category Summary'!I$2) +SUMIFS(cc_table[Amount],cc_table[Category_2],'Category Summary'!$B10,cc_table[Date],'Category Summary'!I$2) + SUMIFS(bb_table[Amount],bb_table[Category_2],'Category Summary'!$B10,bb_table[Date],'Category Summary'!I$2) + SUMIFS(Table5[Amount],Table5[Category_2],'Category Summary'!$B10,Table5[Date],'Category Summary'!I$2)+I24*-1 -> 151.5 | J10: =SUM(C10:I10) -> 4681.3 | K10: =J10/$J$27 -> 0.12743797
B11: Medical | C11: =SUMIFS(dis_table[Amount],dis_table[Category_2],'Category Summary'!$B11,dis_table[Date],'Category Summary'!C$2) +SUMIFS(cc_table[Amount],cc_table[Category_2],'Category Summary'!$B11,cc_table[Date],'Category Summary'!C$2) + SUMIFS(bb_table[Amount],bb_table[Category_2],'Category Summary'!$B11,bb_table[Date],'Category Summary'!C$2) + SUMIFS(Table5[Amount],Table5[Category_2],'Category Summary'!$B11,Table5[Date],'Category Summary'!C$2) -> 2286 | D11: =SUMIFS(dis_table[Amount],dis_table[Category_2],'Category Summary'!$B11,dis_table[Date],'Category Summary'!D$2) +SUMIFS(cc_table[Amount],cc_table[Category_2],'Category Summary'!$B11,cc_table[Date],'Category Summary'!D$2) + SUMIFS(bb_table[Amount],bb_table[Category_2],'Category Summary'!$B11,bb_table[Date],'Category Summary'!D$2) + SUMIFS(Table5[Amount],Table5[Category_2],'Category Summary'!$B11,Table5[Date],'Category Summary'!D$2) -> 21.35 | E11: =SUMIFS(dis_table[Amount],dis_table[Category_2],'Category Summary'!$B11,dis_table[Date],'Category Summary'!E$2) +SUMIFS(cc_table[Amount],cc_table[Category_2],'Category Summary'!$B11,cc_table[Date],'Category Summary'!E$2) + SUMIFS(bb_table[Amount],bb_table[Category_2],'Category Summary'!$B11,bb_table[Date],'Category Summary'!E$2) + SUMIFS(Table5[Amount],Table5[Category_2],'Category Summary'!$B11,Table5[Date],'Category Summary'!E$2) -> 2553.16 | F11: =SUMIFS(dis_table[Amount],dis_table[Category_2],'Category Summary'!$B11,dis_table[Date],'Category Summary'!F$2) +SUMIFS(cc_table[Amount],cc_table[Category_2],'Category Summary'!$B11,cc_table[Date],'Category Summary'!F$2) + SUMIFS(bb_table[Amount],bb_table[Category_2],'Category Summary'!$B11,bb_table[Date],'Category Summary'!F$2) + SUMIFS(Table5[Amount],Table5[Category_2],'Category Summary'!$B11,Table5[Date],'Category Summary'!F$2) -> 0 | G11: =SUMIFS(dis_table[Amount],dis_table[Category_2],'Category Summary'!$B11,dis_table[Date],'Category Summary'!G$2) +SUMIFS(cc_table[Amount],cc_table[Category_2],'Category Summary'!$B11,cc_table[Date],'Category Summary'!G$2) + SUMIFS(bb_table[Amount],bb_table[Category_2],'Category Summary'!$B11,bb_table[Date],'Category Summary'!G$2) + SUMIFS(Table5[Amount],Table5[Category_2],'Category Summary'!$B11,Table5[Date],'Category Summary'!G$2) -> 0 | H11: =SUMIFS(dis_table[Amount],dis_table[Category_2],'Category Summary'!$B11,dis_table[Date],'Category Summary'!H$2) +SUMIFS(cc_table[Amount],cc_table[Category_2],'Category Summary'!$B11,cc_table[Date],'Category Summary'!H$2) + SUMIFS(bb_table[Amount],bb_table[Category_2],'Category Summary'!$B11,bb_table[Date],'Category Summary'!H$2) + SUMIFS(Table5[Amount],Table5[Category_2],'Category Summary'!$B11,Table5[Date],'Category Summary'!H$2) -> 0 | I11: =SUMIFS(dis_table[Amount],dis_table[Category_2],'Category Summary'!$B11,dis_table[Date],'Category Summary'!I$2) +SUMIFS(cc_table[Amount],cc_table[Category_2],'Category Summary'!$B11,cc_table[Date],'Category Summary'!I$2) + SUMIFS(bb_table[Amount],bb_table[Category_2],'Category Summary'!$B11,bb_table[Date],'Category Summary'!I$2) + SUMIFS(Table5[Amount],Table5[Category_2],'Category Summary'!$B11,Table5[Date],'Category Summary'!I$2) -> 504.86 | J11: =SUM(C11:I11) -> 5365.37 | K11: =J11/$J$27 -> 0.14606025
B12: Housing | C12: =SUMIFS(dis_table[Amount],dis_table[Category_2],'Category Summary'!$B12,dis_table[Date],'Category Summary'!C$2) +SUMIFS(cc_table[Amount],cc_table[Category_2],'Category Summary'!$B12,cc_table[Date],'Category Summary'!C$2) + SUMIFS(bb_table[Amount],bb_table[Category_2],'Category Summary'!$B12,bb_table[Date],'Category Summary'!C$2) + SUMIFS(Table5[Amount],Table5[Category_2],'Category Summary'!$B12,Table5[Date],'Category Summary'!C$2)+C25*-1 -> 933.34 | D12: =SUMIFS(dis_table[Amount],dis_table[Category_2],'Category Summary'!$B12,dis_table[Date],'Category Summary'!D$2) +SUMIFS(cc_table[Amount],cc_table[Category_2],'Category Summary'!$B12,cc_table[Date],'Category Summary'!D$2) + SUMIFS(bb_table[Amount],bb_table[Category_2],'Category Summary'!$B12,bb_table[Date],'Category Summary'!D$2) + SUMIFS(Table5[Amount],Table5[Category_2],'Category Summary'!$B12,Table5[Date],'Category Summary'!D$2)+D25*-1 -> 1204.29 | E12: =SUMIFS(dis_table[Amount],dis_table[Category_2],'Category Summary'!$B12,dis_table[Date],'Category Summary'!E$2) +SUMIFS(cc_table[Amount],cc_table[Category_2],'Category Summary'!$B12,cc_table[Date],'Category Summary'!E$2) + SUMIFS(bb_table[Amount],bb_table[Category_2],'Category Summary'!$B12,bb_table[Date],'Category Summary'!E$2) + SUMIFS(Table5[Amount],Table5[Category_2],'Category Summary'!$B12,Table5[Date],'Category Summary'!E$2)+E25*-1 -> 1400 | F12: =SUMIFS(dis_table[Amount],dis_table[Category_2],'Category Summary'!$B12,dis_table[Date],'Category Summary'!F$2) +SUMIFS(cc_table[Amount],cc_table[Category_2],'Category Summary'!$B12,cc_table[Date],'Category Summary'!F$2) + SUMIFS(bb_table[Amount],bb_table[Category_2],'Category Summary'!$B12,bb_table[Date],'Category Summary'!F$2) + SUMIFS(Table5[Amount],Table5[Category_2],'Category Summary'!$B12,Table5[Date],'Category Summary'!F$2)+F25*-1 -> 1463.66 | G12: =SUMIFS(dis_table[Amount],dis_table[Category_2],'Category Summary'!$B12,dis_table[Date],'Category Summary'!G$2) +SUMIFS(cc_table[Amount],cc_table[Category_2],'Category Summary'!$B12,cc_table[Date],'Category Summary'!G$2) + SUMIFS(bb_table[Amount],bb_table[Category_2],'Category Summary'!$B12,bb_table[Date],'Category Summary'!G$2) + SUMIFS(Table5[Amount],Table5[Category_2],'Category Summary'!$B12,Table5[Date],'Category Summary'!G$2)+G25*-1 -> 1400 | H12: =SUMIFS(dis_table[Amount],dis_table[Category_2],'Category Summary'!$B12,dis_table[Date],'Category Summary'!H$2) +SUMIFS(cc_table[Amount],cc_table[Category_2],'Category Summary'!$B12,cc_table[Date],'Category Summary'!H$2) + SUMIFS(bb_table[Amount],bb_table[Category_2],'Category Summary'!$B12,bb_table[Date],'Category Summary'!H$2) + SUMIFS(Table5[Amount],Table5[Category_2],'Category Summary'!$B12,Table5[Date],'Category Summary'!H$2)+H25*-1 -> 1400 | I12: =SUMIFS(dis_table[Amount],dis_table[Category_2],'Category Summary'!$B12,dis_table[Date],'Category Summary'!I$2) +SUMIFS(cc_table[Amount],cc_table[Category_2],'Category Summary'!$B12,cc_table[Date],'Category Summary'!I$2) + SUMIFS(bb_table[Amount],bb_table[Category_2],'Category Summary'!$B12,bb_table[Date],'Category Summary'!I$2) + SUMIFS(Table5[Amount],Table5[Category_2],'Category Summary'!$B12,Table5[Date],'Category Summary'!I$2)+I25*-1 -> 38.1 | J12: =SUM(C12:I12) -> 7839.39 | K12: =J12/$J$27 -> 0.21340994
B13: Total | C13: =SUM(C3:C12) -> 6029.94 | D13: =SUM(D3:D12) -> 4477.24 | E13: =SUM(E3:E12) -> 9037.9 | F13: =SUM(F3:F12) -> 4637.39 | G13: =SUM(G3:G12) -> 6792.11 | H13: =SUM(H3:H12) -> 7486.305 | I13: =SUM(I3:I12) -> 3781.455 | J13: =SUM(J3:J12) -> 42242.34 | K13: =SUM(K3:K12) -> 1.1499537
B17: Debit Accounts | C17: 01/2022 | D17: 02/2022 | E17: 03/2022 | F17: 04/2022 | G17: 05/2022 | H17: 06/2022 | I17: 07/2022 | J17: Total
B18: Food | C18: =SUMIFS(wf_table[Debit_Amount],wf_table[Category_2],'Category Summary'!$B18,wf_table[Date],'Category Summary'!C$17) -> -40 | D18: =SUMIFS(wf_table[Debit_Amount],wf_table[Category_2],'Category Summary'!$B18,wf_table[Date],'Category Summary'!D$17) -> 0 | E18: =SUMIFS(wf_table[Debit_Amount],wf_table[Category_2],'Category Summary'!$B18,wf_table[Date],'Category Summary'!E$17) -> 33 | F18: =SUMIFS(wf_table[Debit_Amount],wf_table[Category_2],'Category Summary'!$B18,wf_table[Date],'Category Summary'!F$17) -> 0 | G18: =SUMIFS(wf_table[Debit_Amount],wf_table[Category_2],'Category Summary'!$B18,wf_table[Date],'Category Summary'!G$17) -> 0 | H18: =SUMIFS(wf_table[Debit_Amount],wf_table[Category_2],'Category Summary'!$B18,wf_table[Date],'Category Summary'!H$17) -> 0 | I18: =SUMIFS(wf_table[Debit_Amount],wf_table[Category_2],'Category Summary'!$B18,wf_table[Date],'Category Summary'!I$17) -> 0 | J18: =SUM(C18:I18) -> -7
B19: Recreation_Entertainment | C19: =SUMIFS(wf_table[Debit_Amount],wf_table[Category_2],'Category Summary'!$B19,wf_table[Date],'Category Summary'!C$17) -> -623.34 | D19: =SUMIFS(wf_table[Debit_Amount],wf_table[Category_2],'Category Summary'!$B19,wf_table[Date],'Category Summary'!D$17) -> 0 | E19: =SUMIFS(wf_table[Debit_Amount],wf_table[Category_2],'Category Summary'!$B19,wf_table[Date],'Category Summary'!E$17) -> -52 | F19: =SUMIFS(wf_table[Debit_Amount],wf_table[Category_2],'Category Summary'!$B19,wf_table[Date],'Category Summary'!F$17) -> -59 | G19: =SUMIFS(wf_table[Debit_Amount],wf_table[Category_2],'Category Summary'!$B19,wf_table[Date],'Category Summary'!G$17) -> -276.83 | H19: =SUMIFS(wf_table[Debit_Amount],wf_table[Category_2],'Category Summary'!$B19,wf_table[Date],'Category Summary'!H$17) -> 0 | I19: =SUMIFS(wf_table[Debit_Amount],wf_table[Category_2],'Category Summary'!$B19,wf_table[Date],'Category Summary'!I$17) -> -25.48 | J19: =SUM(C19:I19) -> -1036.65
B20: Personal_Spending | C20: =SUMIFS(wf_table[Debit_Amount],wf_table[Category_2],'Category Summary'!$B20,wf_table[Date],'Category Summary'!C$17) -> -90 | D20: =SUMIFS(wf_table[Debit_Amount],wf_table[Category_2],'Category Summary'!$B20,wf_table[Date],'Category Summary'!D$17) -> -210 | E20: =SUMIFS(wf_table[Debit_Amount],wf_table[Category_2],'Category Summary'!$B20,wf_table[Date],'Category Summary'!E$17) -> 0 | F20: =SUMIFS(wf_table[Debit_Amount],wf_table[Category_2],'Category Summary'!$B20,wf_table[Date],'Category Summary'!F$17) -> 0 | G20: =SUMIFS(wf_table[Debit_Amount],wf_table[Category_2],'Category Summary'!$B20,wf_table[Date],'Category Summary'!G$17) -> 0 | H20: =SUMIFS(wf_table[Debit_Amount],wf_table[Category_2],'Category Summary'!$B20,wf_table[Date],'Category Summary'!H$17) -> 0 | I20: =SUMIFS(wf_table[Debit_Amount],wf_table[Category_2],'Category Summary'!$B20,wf_table[Date],'Category Summary'!I$17) -> 0 | J20: =SUM(C20:I20) -> -300
B21: Transportation | C21: =SUMIFS(wf_table[Debit_Amount],wf_table[Category_2],'Category Summary'!$B21,wf_table[Date],'Category Summary'!C$17) -> 0 | D21: =SUMIFS(wf_table[Debit_Amount],wf_table[Category_2],'Category Summary'!$B21,wf_table[Date],'Category Summary'!D$17) -> 0 | E21: =SUMIFS(wf_table[Debit_Amount],wf_table[Category_2],'Category Summary'!$B21,wf_table[Date],'Category Summary'!E$17) -> 0 | F21: =SUMIFS(wf_table[Debit_Amount],wf_table[Category_2],'Category Summary'!$B21,wf_table[Date],'Category Summary'!F$17) -> 0 | G21: =SUMIFS(wf_table[Debit_Amount],wf_table[Category_2],'Category Summary'!$B21,wf_table[Date],'Category Summary'!G$17) -> 0 | H21: =SUMIFS(wf_table[Debit_Amount],wf_table[Category_2],'Category Summary'!$B21,wf_table[Date],'Category Summary'!H$17) -> 0 | I21: =SUMIFS(wf_table[Debit_Amount],wf_table[Category_2],'Category Summary'!$B21,wf_table[Date],'Category Summary'!I$17) -> -64 | J21: =SUM(C21:I21) -> -64
B22: Misc | C22: =SUMIFS(wf_table[Debit_Amount],wf_table[Category_2],'Category Summary'!$B22,wf_table[Date],'Category Summary'!C$17) -> -10 | D22: =SUMIFS(wf_table[Debit_Amount],wf_table[Category_2],'Category Summary'!$B22,wf_table[Date],'Category Summary'!D$17) -> 0 | E22: =SUMIFS(wf_table[Debit_Amount],wf_table[Category_2],'Category Summary'!$B22,wf_table[Date],'Category Summary'!E$17) -> 0 | F22: =SUMIFS(wf_table[Debit_Amount],wf_table[Category_2],'Category Summary'!$B22,wf_table[Date],'Category Summary'!F$17) -> 0 | G22: =SUMIFS(wf_table[Debit_Amount],wf_table[Category_2],'Category Summary'!$B22,wf_table[Date],'Category Summary'!G$17) -> 0 | H22: =SUMIFS(wf_table[Debit_Amount],wf_table[Category_2],'Category Summary'!$B22,wf_table[Date],'Category Summary'!H$17) -> 0 | I22: =SUMIFS(wf_table[Debit_Amount],wf_table[Category_2],'Category Summary'!$B22,wf_table[Date],'Category Summary'!I$17) -> 0 | J22: =SUM(C22:I22) -> -10
B23: Utilities | C23: =SUMIFS(wf_table[Debit_Amount],wf_table[Category_2],'Category Summary'!$B23,wf_table[Date],'Category Summary'!C$17) -> 265.47 | D23: =SUMIFS(wf_table[Debit_Amount],wf_table[Category_2],'Category Summary'!$B23,wf_table[Date],'Category Summary'!D$17) -> -137.17 | E23: =SUMIFS(wf_table[Debit_Amount],wf_table[Category_2],'Category Summary'!$B23,wf_table[Date],'Category Summary'!E$17) -> -229.5 | F23: =SUMIFS(wf_table[Debit_Amount],wf_table[Category_2],'Category Summary'!$B23,wf_table[Date],'Category Summary'!F$17) -> -197.97 | G23: =SUMIFS(wf_table[Debit_Amount],wf_table[Category_2],'Category Summary'!$B23,wf_table[Date],'Category Summary'!G$17) -> -193.04 | H23: =SUMIFS(wf_table[Debit_Amount],wf_table[Category_2],'Category Summary'!$B23,wf_table[Date],'Category Summary'!H$17) -> -271.77 | I23: =SUMIFS(wf_table[Debit_Amount],wf_table[Category_2],'Category Summary'!$B23,wf_table[Date],'Category Summary'!I$17) -> -202.46 | J23: =SUM(C23:I23) -> -966.44
B24: People | C24: =SUMIFS(wf_table[Debit_Amount],wf_table[Category_2],'Category Summary'!$B24,wf_table[Date],'Category Summary'!C$17) -> -256.76 | D24: =SUMIFS(wf_table[Debit_Amount],wf_table[Category_2],'Category Summary'!$B24,wf_table[Date],'Category Summary'!D$17) -> -1469.21 | E24: =SUMIFS(wf_table[Debit_Amount],wf_table[Category_2],'Category Summary'!$B24,wf_table[Date],'Category Summary'!E$17) -> -1384.09 | F24: =SUMIFS(wf_table[Debit_Amount],wf_table[Category_2],'Category Summary'!$B24,wf_table[Date],'Category Summary'!F$17) -> -668 | G24: =SUMIFS(wf_table[Debit_Amount],wf_table[Category_2],'Category Summary'!$B24,wf_table[Date],'Category Summary'!G$17) -> -468.47 | H24: =SUMIFS(wf_table[Debit_Amount],wf_table[Category_2],'Category Summary'!$B24,wf_table[Date],'Category Summary'!H$17) -> -66.07 | I24: =SUMIFS(wf_table[Debit_Amount],wf_table[Category_2],'Category Summary'!$B24,wf_table[Date],'Category Summary'!I$17) -> -100 | J24: =SUM(C24:I24) -> -4412.6
B25: Housing | C25: =SUMIFS(wf_table[Debit_Amount],wf_table[Category_2],'Category Summary'!$B25,wf_table[Date],'Category Summary'!C$17) -> -933.34 | D25: =SUMIFS(wf_table[Debit_Amount],wf_table[Category_2],'Category Summary'!$B25,wf_table[Date],'Category Summary'!D$17) -> -1204.29 | E25: =SUMIFS(wf_table[Debit_Amount],wf_table[Category_2],'Category Summary'!$B25,wf_table[Date],'Category Summary'!E$17) -> -1400 | F25: =SUMIFS(wf_table[Debit_Amount],wf_table[Category_2],'Category Summary'!$B25,wf_table[Date],'Category Summary'!F$17) -> -1400 | G25: =SUMIFS(wf_table[Debit_Amount],wf_table[Category_2],'Category Summary'!$B25,wf_table[Date],'Category Summary'!G$17) -> -1400 | H25: =SUMIFS(wf_table[Debit_Amount],wf_table[Category_2],'Category Summary'!$B25,wf_table[Date],'Category Summary'!H$17) -> -1400 | I25: =SUMIFS(wf_table[Debit_Amount],wf_table[Category_2],'Category Summary'!$B25,wf_table[Date],'Category Summary'!I$17) -> 0 | J25: =SUM(C25:I25) -> -7737.63
B26: credit | C26: =SUMIFS(wf_table[Debit_Amount],wf_table[Category_2],'Category Summary'!$B26,wf_table[Date],'Category Summary'!C$17) -> -5236.91 | D26: =SUMIFS(wf_table[Debit_Amount],wf_table[Category_2],'Category Summary'!$B26,wf_table[Date],'Category Summary'!D$17) -> -1307.35 | E26: =SUMIFS(wf_table[Debit_Amount],wf_table[Category_2],'Category Summary'!$B26,wf_table[Date],'Category Summary'!E$17) -> -1969.1 | F26: =SUMIFS(wf_table[Debit_Amount],wf_table[Category_2],'Category Summary'!$B26,wf_table[Date],'Category Summary'!F$17) -> -2074.62 | G26: =SUMIFS(wf_table[Debit_Amount],wf_table[Category_2],'Category Summary'!$B26,wf_table[Date],'Category Summary'!G$17) -> -3000 | H26: =SUMIFS(wf_table[Debit_Amount],wf_table[Category_2],'Category Summary'!$B26,wf_table[Date],'Category Summary'!H$17) -> -4974.91 | I26: =SUMIFS(wf_table[Debit_Amount],wf_table[Category_2],'Category Summary'!$B26,wf_table[Date],'Category Summary'!I$17) -> -2600 | J26: =SUM(C26:I26) -> -21162.89
B27: income | C27: =SUMIFS(wf_table[Debit_Amount],wf_table[Category_2],'Category Summary'!$B27,wf_table[Date],'Category Summary'!C$17) -> 5616.86 | D27: =SUMIFS(wf_table[Debit_Amount],wf_table[Category_2],'Category Summary'!$B27,wf_table[Date],'Category Summary'!D$17) -> 7196.43 | E27: =SUMIFS(wf_table[Debit_Amount],wf_table[Category_2],'Category Summary'!$B27,wf_table[Date],'Category Summary'!E$17) -> 4480.14 | F27: =SUMIFS(wf_table[Debit_Amount],wf_table[Category_2],'Category Summary'!$B27,wf_table[Date],'Category Summary'!F$17) -> 4543.15 | G27: =SUMIFS(wf_table[Debit_Amount],wf_table[Category_2],'Category Summary'!$B27,wf_table[Date],'Category Summary'!G$17) -> 4965.79 | H27: =SUMIFS(wf_table[Debit_Amount],wf_table[Category_2],'Category Summary'!$B27,wf_table[Date],'Category Summary'!H$17) -> 7448.69 | I27: =SUMIFS(wf_table[Debit_Amount],wf_table[Category_2],'Category Summary'!$B27,wf_table[Date],'Category Summary'!I$17) -> 2482.89 | J27: =SUM(C27:I27) -> 36733.95
C28: =SUM(C18:C27) -> -1308.02 | D28: =SUM(D18:D27) -> 2868.41 | E28: =SUM(E18:E27) -> -521.55 | F28: =SUM(F18:F27) -> 143.56 | G28: =SUM(G18:G27) -> -372.55 | H28: =SUM(H18:H27) -> 735.94 | I28: =SUM(I18:I27) -> -509.05 | J28: =J27-J13 -> -5508.39

Sheet People Summary
C1: 01/2022 | D1: 02/2022 | E1: 03/2022 | F1: 04/2022 | G1: 05/2022 | H1: 06/2022 | I1: 07/2022 | J1: Total
B2: mom | C2: =SUMIFS(wf_table[Debit_Amount],wf_table[Short_Desc],'People Summary'!$B2,wf_table[Date],'People Summary'!C$1,wf_table[Category_2],"People" ) -> -505 | D2: =SUMIFS(wf_table[Debit_Amount],wf_table[Short_Desc],'People Summary'!$B2,wf_table[Date],'People Summary'!D$1,wf_table[Category_2],"People" ) -> 485 | E2: =SUMIFS(wf_table[Debit_Amount],wf_table[Short_Desc],'People Summary'!$B2,wf_table[Date],'People Summary'!E$1,wf_table[Category_2],"People" ) -> 0 | F2: =SUMIFS(wf_table[Debit_Amount],wf_table[Short_Desc],'People Summary'!$B2,wf_table[Date],'People Summary'!F$1,wf_table[Category_2],"People" ) -> -430 | G2: =SUMIFS(wf_table[Debit_Amount],wf_table[Short_Desc],'People Summary'!$B2,wf_table[Date],'People Summary'!G$1,wf_table[Category_2],"People" ) -> -500 | H2: =SUMIFS(wf_table[Debit_Amount],wf_table[Short_Desc],'People Summary'!$B2,wf_table[Date],'People Summary'!H$1,wf_table[Category_2],"People" ) -> 400 | I2: =SUMIFS(wf_table[Debit_Amount],wf_table[Short_Desc],'People Summary'!$B2,wf_table[Date],'People Summary'!I$1,wf_table[Category_2],"People" ) -> -100 | J2: =SUM(C2:I2) -> -650
B3: Vincent | C3: =SUMIFS(wf_table[Debit_Amount],wf_table[Short_Desc],'People Summary'!$B3,wf_table[Date],'People Summary'!C$1,wf_table[Category_2],"People" ) -> 477.73 | D3: =SUMIFS(wf_table[Debit_Amount],wf_table[Short_Desc],'People Summary'!$B3,wf_table[Date],'People Summary'!D$1,wf_table[Category_2],"People" ) -> -2074.21 | E3: =SUMIFS(wf_table[Debit_Amount],wf_table[Short_Desc],'People Summary'!$B3,wf_table[Date],'People Summary'!E$1,wf_table[Category_2],"People" ) -> -1434 | F3: =SUMIFS(wf_table[Debit_Amount],wf_table[Short_Desc],'People Summary'!$B3,wf_table[Date],'People Summary'!F$1,wf_table[Category_2],"People" ) -> 0 | G3: =SUMIFS(wf_table[Debit_Amount],wf_table[Short_Desc],'People Summary'!$B3,wf_table[Date],'People Summary'!G$1,wf_table[Category_2],"People" ) -> 0 | H3: =SUMIFS(wf_table[Debit_Amount],wf_table[Short_Desc],'People Summary'!$B3,wf_table[Date],'People Summary'!H$1,wf_table[Category_2],"People" ) -> -186.07 | I3: =SUMIFS(wf_table[Debit_Amount],wf_table[Short_Desc],'People Summary'!$B3,wf_table[Date],'People Summary'!I$1,wf_table[Category_2],"People" ) -> 0 | J3: =SUM(C3:I3) -> -3216.55
B4: Kabir | C4: =SUMIFS(wf_table[Debit_Amount],wf_table[Short_Desc],'People Summary'!$B4,wf_table[Date],'People Summary'!C$1,wf_table[Category_2],"People" ) -> 0 | D4: =SUMIFS(wf_table[Debit_Amount],wf_table[Short_Desc],'People Summary'!$B4,wf_table[Date],'People Summary'!D$1,wf_table[Category_2],"People" ) -> 0 | E4: =SUMIFS(wf_table[Debit_Amount],wf_table[Short_Desc],'People Summary'!$B4,wf_table[Date],'People Summary'!E$1,wf_table[Category_2],"People" ) -> 0 | F4: =SUMIFS(wf_table[Debit_Amount],wf_table[Short_Desc],'People Summary'!$B4,wf_table[Date],'People Summary'!F$1,wf_table[Category_2],"People" ) -> 0 | G4: =SUMIFS(wf_table[Debit_Amount],wf_table[Short_Desc],'People Summary'!$B4,wf_table[Date],'People Summary'!G$1,wf_table[Category_2],"People" ) -> 0 | H4: =SUMIFS(wf_table[Debit_Amount],wf_table[Short_Desc],'People Summary'!$B4,wf_table[Date],'People Summary'!H$1,wf_table[Category_2],"People" ) -> 0 | I4: =SUMIFS(wf_table[Debit_Amount],wf_table[Short_Desc],'People Summary'!$B4,wf_table[Date],'People Summary'!I$1,wf_table[Category_2],"People" ) -> 0 | J4: =SUM(C4:I4) -> 0
B5: Jayelin | C5: =SUMIFS(wf_table[Debit_Amount],wf_table[Short_Desc],'People Summary'!$B5,wf_table[Date],'People Summary'!C$1,wf_table[Category_2],"People" ) -> -100 | D5: =SUMIFS(wf_table[Debit_Amount],wf_table[Short_Desc],'People Summary'!$B5,wf_table[Date],'People Summary'!D$1,wf_table[Category_2],"People" ) -> 0 | E5: =SUMIFS(wf_table[Debit_Amount],wf_table[Short_Desc],'People Summary'!$B5,wf_table[Date],'People Summary'!E$1,wf_table[Category_2],"People" ) -> -110 | F5: =SUMIFS(wf_table[Debit_Amount],wf_table[Short_Desc],'People Summary'!$B5,wf_table[Date],'People Summary'!F$1,wf_table[Category_2],"People" ) -> -93 | G5: =SUMIFS(wf_table[Debit_Amount],wf_table[Short_Desc],'People Summary'!$B5,wf_table[Date],'People Summary'!G$1,wf_table[Category_2],"People" ) -> -40 | H5: =SUMIFS(wf_table[Debit_Amount],wf_table[Short_Desc],'People Summary'!$B5,wf_table[Date],'People Summary'!H$1,wf_table[Category_2],"People" ) -> 0 | I5: =SUMIFS(wf_table[Debit_Amount],wf_table[Short_Desc],'People Summary'!$B5,wf_table[Date],'People Summary'!I$1,wf_table[Category_2],"People" ) -> 0 | J5: =SUM(C5:I5) -> -343
B6: Logan | C6: =SUMIFS(wf_table[Debit_Amount],wf_table[Short_Desc],'People Summary'!$B6,wf_table[Date],'People Summary'!C$1,wf_table[Category_2],"People" ) -> 0 | D6: =SUMIFS(wf_table[Debit_Amount],wf_table[Short_Desc],'People Summary'!$B6,wf_table[Date],'People Summary'!D$1,wf_table[Category_2],"People" ) -> 0 | E6: =SUMIFS(wf_table[Debit_Amount],wf_table[Short_Desc],'People Summary'!$B6,wf_table[Date],'People Summary'!E$1,wf_table[Category_2],"People" ) -> 0 | F6: =SUMIFS(wf_table[Debit_Amount],wf_table[Short_Desc],'People Summary'!$B6,wf_table[Date],'People Summary'!F$1,wf_table[Category_2],"People" ) -> 0 | G6: =SUMIFS(wf_table[Debit_Amount],wf_table[Short_Desc],'People Summary'!$B6,wf_table[Date],'People Summary'!G$1,wf_table[Category_2],"People" ) -> 0 | H6: =SUMIFS(wf_table[Debit_Amount],wf_table[Short_Desc],'People Summary'!$B6,wf_table[Date],'People Summary'!H$1,wf_table[Category_2],"People" ) -> 0 | I6: =SUMIFS(wf_table[Debit_Amount],wf_table[Short_Desc],'People Summary'!$B6,wf_table[Date],'People Summary'!I$1,wf_table[Category_2],"People" ) -> 0 | J6: =SUM(C6:I6) -> 0
B7: atm | C7: =SUMIFS(wf_table[Debit_Amount],wf_table[Short_Desc],'People Summary'!$B7,wf_table[Date],'People Summary'!C$1,wf_table[Category_2],"People" ) -> -2.5 | D7: =SUMIFS(wf_table[Debit_Amount],wf_table[Short_Desc],'People Summary'!$B7,wf_table[Date],'People Summary'!D$1,wf_table[Category_2],"People" ) -> 0 | E7: =SUMIFS(wf_table[Debit_Amount],wf_table[Short_Desc],'People Summary'!$B7,wf_table[Date],'People Summary'!E$1,wf_table[Category_2],"People" ) -> 0 | F7: =SUMIFS(wf_table[Debit_Amount],wf_table[Short_Desc],'People Summary'!$B7,wf_table[Date],'People Summary'!F$1,wf_table[Category_2],"People" ) -> 0 | G7: =SUMIFS(wf_table[Debit_Amount],wf_table[Short_Desc],'People Summary'!$B7,wf_table[Date],'People Summary'!G$1,wf_table[Category_2],"People" ) -> 0 | H7: =SUMIFS(wf_table[Debit_Amount],wf_table[Short_Desc],'People Summary'!$B7,wf_table[Date],'People Summary'!H$1,wf_table[Category_2],"People" ) -> 0 | I7: =SUMIFS(wf_table[Debit_Amount],wf_table[Short_Desc],'People Summary'!$B7,wf_table[Date],'People Summary'!I$1,wf_table[Category_2],"People" ) -> 0 | J7: =SUM(C7:I7) -> -2.5
B8: Nick | C8: =SUMIFS(wf_table[Debit_Amount],wf_table[Short_Desc],'People Summary'!$B8,wf_table[Date],'People Summary'!C$1,wf_table[Category_2],"People" ) -> 0 | D8: =SUMIFS(wf_table[Debit_Amount],wf_table[Short_Desc],'People Summary'!$B8,wf_table[Date],'People Summary'!D$1,wf_table[Category_2],"People" ) -> 0 | E8: =SUMIFS(wf_table[Debit_Amount],wf_table[Short_Desc],'People Summary'!$B8,wf_table[Date],'People Summary'!E$1,wf_table[Category_2],"People" ) -> 0 | F8: =SUMIFS(wf_table[Debit_Amount],wf_table[Short_Desc],'People Summary'!$B8,wf_table[Date],'People Summary'!F$1,wf_table[Category_2],"People" ) -> 0 | G8: =SUMIFS(wf_table[Debit_Amount],wf_table[Short_Desc],'People Summary'!$B8,wf_table[Date],'People Summary'!G$1,wf_table[Category_2],"People" ) -> 0 | H8: =SUMIFS(wf_table[Debit_Amount],wf_table[Short_Desc],'People Summary'!$B8,wf_table[Date],'People Summary'!H$1,wf_table[Category_2],"People" ) -> 0 | I8: =SUMIFS(wf_table[Debit_Amount],wf_table[Short_Desc],'People Summary'!$B8,wf_table[Date],'People Summary'!I$1,wf_table[Category_2],"People" ) -> 0 | J8: =SUM(C8:I8) -> 0
B9: Shevon | C9: =SUMIFS(wf_table[Debit_Amount],wf_table[Short_Desc],'People Summary'!$B9,wf_table[Date],'People Summary'!C$1,wf_table[Category_2],"People" ) -> 0 | D9: =SUMIFS(wf_table[Debit_Amount],wf_table[Short_Desc],'People Summary'!$B9,wf_table[Date],'People Summary'!D$1,wf_table[Category_2],"People" ) -> 0 | E9: =SUMIFS(wf_table[Debit_Amount],wf_table[Short_Desc],'People Summary'!$B9,wf_table[Date],'People Summary'!E$1,wf_table[Category_2],"People" ) -> -60 | F9: =SUMIFS(wf_table[Debit_Amount],wf_table[Short_Desc],'People Summary'!$B9,wf_table[Date],'People Summary'!F$1,wf_table[Category_2],"People" ) -> 0 | G9: =SUMIFS(wf_table[Debit_Amount],wf_table[Short_Desc],'People Summary'!$B9,wf_table[Date],'People Summary'!G$1,wf_table[Category_2],"People" ) -> 0 | H9: =SUMIFS(wf_table[Debit_Amount],wf_table[Short_Desc],'People Summary'!$B9,wf_table[Date],'People Summary'!H$1,wf_table[Category_2],"People" ) -> -50 | I9: =SUMIFS(wf_table[Debit_Amount],wf_table[Short_Desc],'People Summary'!$B9,wf_table[Date],'People Summary'!I$1,wf_table[Category_2],"People" ) -> 0 | J9: =SUM(C9:I9) -> -110
B10: Venmo | C10: =SUMIFS(wf_table[Debit_Amount],wf_table[Short_Desc],'People Summary'!$B10,wf_table[Date],'People Summary'!C$1,wf_table[Category_2],"People" ) -> 0 | D10: =SUMIFS(wf_table[Debit_Amount],wf_table[Short_Desc],'People Summary'!$B10,wf_table[Date],'People Summary'!D$1,wf_table[Category_2],"People" ) -> 0 | E10: =SUMIFS(wf_table[Debit_Amount],wf_table[Short_Desc],'People Summary'!$B10,wf_table[Date],'People Summary'!E$1,wf_table[Category_2],"People" ) -> 224.91 | F10: =SUMIFS(wf_table[Debit_Amount],wf_table[Short_Desc],'People Summary'!$B10,wf_table[Date],'People Summary'!F$1,wf_table[Category_2],"People" ) -> 0 | G10: =SUMIFS(wf_table[Debit_Amount],wf_table[Short_Desc],'People Summary'!$B10,wf_table[Date],'People Summary'!G$1,wf_table[Category_2],"People" ) -> 66.01 | H10: =SUMIFS(wf_table[Debit_Amount],wf_table[Short_Desc],'People Summary'!$B10,wf_table[Date],'People Summary'!H$1,wf_table[Category_2],"People" ) -> 0 | I10: =SUMIFS(wf_table[Debit_Amount],wf_table[Short_Desc],'People Summary'!$B10,wf_table[Date],'People Summary'!I$1,wf_table[Category_2],"People" ) -> 0 | J10: =SUM(C10:I10) -> 290.92
B11: Michael | C11: =SUMIFS(wf_table[Debit_Amount],wf_table[Short_Desc],'People Summary'!$B11,wf_table[Date],'People Summary'!C$1,wf_table[Category_2],"People" ) -> 0 | D11: =SUMIFS(wf_table[Debit_Amount],wf_table[Short_Desc],'People Summary'!$B11,wf_table[Date],'People Summary'!D$1,wf_table[Category_2],"People" ) -> 0 | E11: =SUMIFS(wf_table[Debit_Amount],wf_table[Short_Desc],'People Summary'!$B11,wf_table[Date],'People Summary'!E$1,wf_table[Category_2],"People" ) -> 0 | F11: =SUMIFS(wf_table[Debit_Amount],wf_table[Short_Desc],'People Summary'!$B11,wf_table[Date],'People Summary'!F$1,wf_table[Category_2],"People" ) -> 0 | G11: =SUMIFS(wf_table[Debit_Amount],wf_table[Short_Desc],'People Summary'!$B11,wf_table[Date],'People Summary'!G$1,wf_table[Category_2],"People" ) -> 0 | H11: =SUMIFS(wf_table[Debit_Amount],wf_table[Short_Desc],'People Summary'!$B11,wf_table[Date],'People Summary'!H$1,wf_table[Category_2],"People" ) -> 0 | I11: =SUMIFS(wf_table[Debit_Amount],wf_table[Short_Desc],'People Summary'!$B11,wf_table[Date],'People Summary'!I$1,wf_table[Category_2],"People" ) -> 0 | J11: =SUM(C11:I11) -> 0
B12: Dorry | C12: =SUMIFS(wf_table[Debit_Amount],wf_table[Short_Desc],'People Summary'!$B12,wf_table[Date],'People Summary'!C$1,wf_table[Category_2],"People" ) -> 0 | D12: =SUMIFS(wf_table[Debit_Amount],wf_table[Short_Desc],'People Summary'!$B12,wf_table[Date],'People Summary'!D$1,wf_table[Category_2],"People" ) -> 0 | E12: =SUMIFS(wf_table[Debit_Amount],wf_table[Short_Desc],'People Summary'!$B12,wf_table[Date],'People Summary'!E$1,wf_table[Category_2],"People" ) -> -5 | F12: =SUMIFS(wf_table[Debit_Amount],wf_table[Short_Desc],'People Summary'!$B12,wf_table[Date],'People Summary'!F$1,wf_table[Category_2],"People" ) -> -110 | G12: =SUMIFS(wf_table[Debit_Amount],wf_table[Short_Desc],'People Summary'!$B12,wf_table[Date],'People Summary'!G$1,wf_table[Category_2],"People" ) -> 0 | H12: =SUMIFS(wf_table[Debit_Amount],wf_table[Short_Desc],'People Summary'!$B12,wf_table[Date],'People Summary'!H$1,wf_table[Category_2],"People" ) -> -120 | I12: =SUMIFS(wf_table[Debit_Amount],wf_table[Short_Desc],'People Summary'!$B12,wf_table[Date],'People Summary'!I$1,wf_table[Category_2],"People" ) -> 0 | J12: =SUM(C12:I12) -> -235
B13: Carmen | C13: =SUMIFS(wf_table[Debit_Amount],wf_table[Short_Desc],'People Summary'!$B13,wf_table[Date],'People Summary'!C$1,wf_table[Category_2],"People" ) -> 0 | D13: =SUMIFS(wf_table[Debit_Amount],wf_table[Short_Desc],'People Summary'!$B13,wf_table[Date],'People Summary'!D$1,wf_table[Category_2],"People" ) -> 0 | E13: =SUMIFS(wf_table[Debit_Amount],wf_table[Short_Desc],'People Summary'!$B13,wf_table[Date],'People Summary'!E$1,wf_table[Category_2],"People" ) -> 0 | F13: =SUMIFS(wf_table[Debit_Amount],wf_table[Short_Desc],'People Summary'!$B13,wf_table[Date],'People Summary'!F$1,wf_table[Category_2],"People" ) -> -35 | G13: =SUMIFS(wf_table[Debit_Amount],wf_table[Short_Desc],'People Summary'!$B13,wf_table[Date],'People Summary'!G$1,wf_table[Category_2],"People" ) -> 0 | H13: =SUMIFS(wf_table[Debit_Amount],wf_table[Short_Desc],'People Summary'!$B13,wf_table[Date],'People Summary'!H$1,wf_table[Category_2],"People" ) -> 0 | I13: =SUMIFS(wf_table[Debit_Amount],wf_table[Short_Desc],'People Summary'!$B13,wf_table[Date],'People Summary'!I$1,wf_table[Category_2],"People" ) -> 0 | J13: =SUM(C13:I13) -> -35
... B17: Don | C17: =SUMIFS(wf_table[Debit_Amount],wf_table[Short_Desc],'People Summary'!$B17,wf_table[Date],'People Summary'!C$1,wf_table[Category_2],"People" ) -> -120 | D17: =SUMIFS(wf_table[Debit_Amount],wf_table[Short_Desc],'People Summary'!$B17,wf_table[Date],'People Summary'!D$1,wf_table[Category_2],"People" ) -> 120 | E17: =SUMIFS(wf_table[Debit_Amount],wf_table[Short_Desc],'People Summary'!$B17,wf_table[Date],'People Summary'!E$1,wf_table[Category_2],"People" ) -> 0 | F17: =SUMIFS(wf_table[Debit_Amount],wf_table[Short_Desc],'People Summary'!$B17,wf_table[Date],'People Summary'!F$1,wf_table[Category_2],"People" ) -> 0 | G17: =SUMIFS(wf_table[Debit_Amount],wf_table[Short_Desc],'People Summary'!$B17,wf_table[Date],'People Summary'!G$1,wf_table[Category_2],"People" ) -> 0 | H17: =SUMIFS(wf_table[Debit_Amount],wf_table[Short_Desc],'People Summary'!$B17,wf_table[Date],'People Summary'!H$1,wf_table[Category_2],"People" ) -> -110 | I17: =SUMIFS(wf_table[Debit_Amount],wf_table[Short_Desc],'People Summary'!$B17,wf_table[Date],'People Summary'!I$1,wf_table[Category_2],"People" ) -> 0 | J17: =SUM(C17:I17) -> -110
C18: =SUM(C2:C17) -> -249.77 | D18: =SUM(D2:D17) -> -1469.21 | E18: =SUM(E2:E17) -> -1384.09 | F18: =SUM(F2:F17) -> -668 | G18: =SUM(G2:G17) -> -550.99 | H18: =SUM(H2:H17) -> -66.07 | I18: =SUM(I2:I17) -> -100 | J18: =SUM(J2:J17) -> -4488.13

Sheet Short Desc Summary
A2: Category | B2: Short Desc | C2: Reoccurring Flag | D2: 01/2022 | E2: 02/2022 | F2: 03/2022 | G2: 04/2022 | H2: 05/2022 | I2: 06/2022 | J2: 07/2022
A3: =VLOOKUP(B3,dis_table[[#All],[Short_Desc]:[Category_2]],4,0) -> 0 | B3: Balance | C3: =VLOOKUP(B3,dis_table[[#All],[Short_Desc]:[Reoccurring_Flag]],3,0) -> 0 | D3: =SUMIFS(dis_table[Amount],dis_table[Short_Desc],'Short Desc Summary'!$B3,dis_table[Date],'Short Desc Summary'!D$2) +SUMIFS(cc_table[Amount],cc_table[Short_Desc],'Short Desc Summary'!$B3,cc_table[Date],'Short Desc Summary'!D$2) +SUMIFS(bb_table[Amount],bb_table[Short_Desc],'Short Desc Summary'!$B3,bb_table[Date],'Short Desc Summary'!D$2) -> 0 | E3: =SUMIFS(dis_table[Amount],dis_table[Short_Desc],'Short Desc Summary'!$B3,dis_table[Date],'Short Desc Summary'!E$2) +SUMIFS(cc_table[Amount],cc_table[Short_Desc],'Short Desc Summary'!$B3,cc_table[Date],'Short Desc Summary'!E$2) +SUMIFS(bb_table[Amount],bb_table[Short_Desc],'Short Desc Summary'!$B3,bb_table[Date],'Short Desc Summary'!E$2) -> 0 | F3: =SUMIFS(dis_table[Amount],dis_table[Short_Desc],'Short Desc Summary'!$B3,dis_table[Date],'Short Desc Summary'!F$2) +SUMIFS(cc_table[Amount],cc_table[Short_Desc],'Short Desc Summary'!$B3,cc_table[Date],'Short Desc Summary'!F$2) +SUMIFS(bb_table[Amount],bb_table[Short_Desc],'Short Desc Summary'!$B3,bb_table[Date],'Short Desc Summary'!F$2) -> 0 | G3: =SUMIFS(dis_table[Amount],dis_table[Short_Desc],'Short Desc Summary'!$B3,dis_table[Date],'Short Desc Summary'!G$2) +SUMIFS(cc_table[Amount],cc_table[Short_Desc],'Short Desc Summary'!$B3,cc_table[Date],'Short Desc Summary'!G$2) +SUMIFS(bb_table[Amount],bb_table[Short_Desc],'Short Desc Summary'!$B3,bb_table[Date],'Short Desc Summary'!G$2) -> 0 | H3: =SUMIFS(dis_table[Amount],dis_table[Short_Desc],'Short Desc Summary'!$B3,dis_table[Date],'Short Desc Summary'!H$2) +SUMIFS(cc_table[Amount],cc_table[Short_Desc],'Short Desc Summary'!$B3,cc_table[Date],'Short Desc Summary'!H$2) +SUMIFS(bb_table[Amount],bb_table[Short_Desc],'Short Desc Summary'!$B3,bb_table[Date],'Short Desc Summary'!H$2) -> 0 | I3: =SUMIFS(dis_table[Amount],dis_table[Short_Desc],'Short Desc Summary'!$B3,dis_table[Date],'Short Desc Summary'!I$2) +SUMIFS(cc_table[Amount],cc_table[Short_Desc],'Short Desc Summary'!$B3,cc_table[Date],'Short Desc Summary'!I$2) +SUMIFS(bb_table[Amount],bb_table[Short_Desc],'Short Desc Summary'!$B3,bb_table[Date],'Short Desc Summary'!I$2) -> 0 | J3: =SUMIFS(dis_table[Amount],dis_table[Short_Desc],'Short Desc Summary'!$B3,dis_table[Date],'Short Desc Summary'!J$2) +SUMIFS(cc_table[Amount],cc_table[Short_Desc],'Short Desc Summary'!$B3,cc_table[Date],'Short Desc Summary'!J$2) +SUMIFS(bb_table[Amount],bb_table[Short_Desc],'Short Desc Summary'!$B3,bb_table[Date],'Short Desc Summary'!J$2) -> 0
A4: =VLOOKUP(B4,dis_table[[#All],[Short_Desc]:[Category_2]],4,0) -> 0 | B4: amazon | C4: =VLOOKUP(B4,dis_table[[#All],[Short_Desc]:[Reoccurring_Flag]],3,0) -> No | D4: =SUMIFS(dis_table[Amount],dis_table[Short_Desc],'Short Desc Summary'!$B4,dis_table[Date],'Short Desc Summary'!D$2) +SUMIFS(cc_table[Amount],cc_table[Short_Desc],'Short Desc Summary'!$B4,cc_table[Date],'Short Desc Summary'!D$2) +SUMIFS(bb_table[Amount],bb_table[Short_Desc],'Short Desc Summary'!$B4,bb_table[Date],'Short Desc Summary'!D$2) -> 135.74 | E4: =SUMIFS(dis_table[Amount],dis_table[Short_Desc],'Short Desc Summary'!$B4,dis_table[Date],'Short Desc Summary'!E$2) +SUMIFS(cc_table[Amount],cc_table[Short_Desc],'Short Desc Summary'!$B4,cc_table[Date],'Short Desc Summary'!E$2) +SUMIFS(bb_table[Amount],bb_table[Short_Desc],'Short Desc Summary'!$B4,bb_table[Date],'Short Desc Summary'!E$2) -> 23.31 | F4: =SUMIFS(dis_table[Amount],dis_table[Short_Desc],'Short Desc Summary'!$B4,dis_table[Date],'Short Desc Summary'!F$2) +SUMIFS(cc_table[Amount],cc_table[Short_Desc],'Short Desc Summary'!$B4,cc_table[Date],'Short Desc Summary'!F$2) +SUMIFS(bb_table[Amount],bb_table[Short_Desc],'Short Desc Summary'!$B4,bb_table[Date],'Short Desc Summary'!F$2) -> 21.22 | G4: =SUMIFS(dis_table[Amount],dis_table[Short_Desc],'Short Desc Summary'!$B4,dis_table[Date],'Short Desc Summary'!G$2) +SUMIFS(cc_table[Amount],cc_table[Short_Desc],'Short Desc Summary'!$B4,cc_table[Date],'Short Desc Summary'!G$2) +SUMIFS(bb_table[Amount],bb_table[Short_Desc],'Short Desc Summary'!$B4,bb_table[Date],'Short Desc Summary'!G$2) -> 277.85 | H4: =SUMIFS(dis_table[Amount],dis_table[Short_Desc],'Short Desc Summary'!$B4,dis_table[Date],'Short Desc Summary'!H$2) +SUMIFS(cc_table[Amount],cc_table[Short_Desc],'Short Desc Summary'!$B4,cc_table[Date],'Short Desc Summary'!H$2) +SUMIFS(bb_table[Amount],bb_table[Short_Desc],'Short Desc Summary'!$B4,bb_table[Date],'Short Desc Summary'!H$2) -> 458.28 | I4: =SUMIFS(dis_table[Amount],dis_table[Short_Desc],'Short Desc Summary'!$B4,dis_table[Date],'Short Desc Summary'!I$2) +SUMIFS(cc_table[Amount],cc_table[Short_Desc],'Short Desc Summary'!$B4,cc_table[Date],'Short Desc Summary'!I$2) +SUMIFS(bb_table[Amount],bb_table[Short_Desc],'Short Desc Summary'!$B4,bb_table[Date],'Short Desc Summary'!I$2) -> 55.16 | J4: =SUMIFS(dis_table[Amount],dis_table[Short_Desc],'Short Desc Summary'!$B4,dis_table[Date],'Short Desc Summary'!J$2) +SUMIFS(cc_table[Amount],cc_table[Short_Desc],'Short Desc Summary'!$B4,cc_table[Date],'Short Desc Summary'!J$2) +SUMIFS(bb_table[Amount],bb_table[Short_Desc],'Short Desc Summary'!$B4,bb_table[Date],'Short Desc Summary'!J$2) -> 76.61
A5: =VLOOKUP(B5,dis_table[[#All],[Short_Desc]:[Category_2]],4,0) -> 0 | B5: payment | C5: =VLOOKUP(B5,dis_table[[#All],[Short_Desc]:[Reoccurring_Flag]],3,0) -> No | D5: =SUMIFS(dis_table[Amount],dis_table[Short_Desc],'Short Desc Summary'!$B5,dis_table[Date],'Short Desc Summary'!D$2) +SUMIFS(cc_table[Amount],cc_table[Short_Desc],'Short Desc Summary'!$B5,cc_table[Date],'Short Desc Summary'!D$2) +SUMIFS(bb_table[Amount],bb_table[Short_Desc],'Short Desc Summary'!$B5,bb_table[Date],'Short Desc Summary'!D$2) -> -4994.92 | E5: =SUMIFS(dis_table[Amount],dis_table[Short_Desc],'Short Desc Summary'!$B5,dis_table[Date],'Short Desc Summary'!E$2) +SUMIFS(cc_table[Amount],cc_table[Short_Desc],'Short Desc Summary'!$B5,cc_table[Date],'Short Desc Summary'!E$2) +SUMIFS(bb_table[Amount],bb_table[Short_Desc],'Short Desc Summary'!$B5,bb_table[Date],'Short Desc Summary'!E$2) -> -3811.78 | F5: =SUMIFS(dis_table[Amount],dis_table[Short_Desc],'Short Desc Summary'!$B5,dis_table[Date],'Short Desc Summary'!F$2) +SUMIFS(cc_table[Amount],cc_table[Short_Desc],'Short Desc Summary'!$B5,cc_table[Date],'Short Desc Summary'!F$2) +SUMIFS(bb_table[Amount],bb_table[Short_Desc],'Short Desc Summary'!$B5,bb_table[Date],'Short Desc Summary'!F$2) -> -1969.1 | G5: =SUMIFS(dis_table[Amount],dis_table[Short_Desc],'Short Desc Summary'!$B5,dis_table[Date],'Short Desc Summary'!G$2) +SUMIFS(cc_table[Amount],cc_table[Short_Desc],'Short Desc Summary'!$B5,cc_table[Date],'Short Desc Summary'!G$2) +SUMIFS(bb_table[Amount],bb_table[Short_Desc],'Short Desc Summary'!$B5,bb_table[Date],'Short Desc Summary'!G$2) -> -2074.62 | H5: =SUMIFS(dis_table[Amount],dis_table[Short_Desc],'Short Desc Summary'!$B5,dis_table[Date],'Short Desc Summary'!H$2) +SUMIFS(cc_table[Amount],cc_table[Short_Desc],'Short Desc Summary'!$B5,cc_table[Date],'Short Desc Summary'!H$2) +SUMIFS(bb_table[Amount],bb_table[Short_Desc],'Short Desc Summary'!$B5,bb_table[Date],'Short Desc Summary'!H$2) -> -3000 | I5: =SUMIFS(dis_table[Amount],dis_table[Short_Desc],'Short Desc Summary'!$B5,dis_table[Date],'Short Desc Summary'!I$2) +SUMIFS(cc_table[Amount],cc_table[Short_Desc],'Short Desc Summary'!$B5,cc_table[Date],'Short Desc Summary'!I$2) +SUMIFS(bb_table[Amount],bb_table[Short_Desc],'Short Desc Summary'!$B5,bb_table[Date],'Short Desc Summary'!I$2) -> -4974.91 | J5: =SUMIFS(dis_table[Amount],dis_table[Short_Desc],'Short Desc Summary'!$B5,dis_table[Date],'Short Desc Summary'!J$2) +SUMIFS(cc_table[Amount],cc_table[Short_Desc],'Short Desc Summary'!$B5,cc_table[Date],'Short Desc Summary'!J$2) +SUMIFS(bb_table[Amount],bb_table[Short_Desc],'Short Desc Summary'!$B5,bb_table[Date],'Short Desc Summary'!J$2) -> -2600
A6: =VLOOKUP(B6,dis_table[[#All],[Short_Desc]:[Category_2]],4,0) -> 0 | B6: cashback_bonus | C6: =VLOOKUP(B6,dis_table[[#All],[Short_Desc]:[Reoccurring_Flag]],3,0) -> No | D6: =SUMIFS(dis_table[Amount],dis_table[Short_Desc],'Short Desc Summary'!$B6,dis_table[Date],'Short Desc Summary'!D$2) +SUMIFS(cc_table[Amount],cc_table[Short_Desc],'Short Desc Summary'!$B6,cc_table[Date],'Short Desc Summary'!D$2) +SUMIFS(bb_table[Amount],bb_table[Short_Desc],'Short Desc Summary'!$B6,bb_table[Date],'Short Desc Summary'!D$2) -> -29.08 | E6: =SUMIFS(dis_table[Amount],dis_table[Short_Desc],'Short Desc Summary'!$B6,dis_table[Date],'Short Desc Summary'!E$2) +SUMIFS(cc_table[Amount],cc_table[Short_Desc],'Short Desc Summary'!$B6,cc_table[Date],'Short Desc Summary'!E$2) +SUMIFS(bb_table[Amount],bb_table[Short_Desc],'Short Desc Summary'!$B6,bb_table[Date],'Short Desc Summary'!E$2) -> -29.29 | F6: =SUMIFS(dis_table[Amount],dis_table[Short_Desc],'Short Desc Summary'!$B6,dis_table[Date],'Short Desc Summary'!F$2) +SUMIFS(cc_table[Amount],cc_table[Short_Desc],'Short Desc Summary'!$B6,cc_table[Date],'Short Desc Summary'!F$2) +SUMIFS(bb_table[Amount],bb_table[Short_Desc],'Short Desc Summary'!$B6,bb_table[Date],'Short Desc Summary'!F$2) -> 0 | G6: =SUMIFS(dis_table[Amount],dis_table[Short_Desc],'Short Desc Summary'!$B6,dis_table[Date],'Short Desc Summary'!G$2) +SUMIFS(cc_table[Amount],cc_table[Short_Desc],'Short Desc Summary'!$B6,cc_table[Date],'Short Desc Summary'!G$2) +SUMIFS(bb_table[Amount],bb_table[Short_Desc],'Short Desc Summary'!$B6,bb_table[Date],'Short Desc Summary'!G$2) -> -65.15 | H6: =SUMIFS(dis_table[Amount],dis_table[Short_Desc],'Short Desc Summary'!$B6,dis_table[Date],'Short Desc Summary'!H$2) +SUMIFS(cc_table[Amount],cc_table[Short_Desc],'Short Desc Summary'!$B6,cc_table[Date],'Short Desc Summary'!H$2) +SUMIFS(bb_table[Amount],bb_table[Short_Desc],'Short Desc Summary'!$B6,bb_table[Date],'Short Desc Summary'!H$2) -> -41.23 | I6: =SUMIFS(dis_table[Amount],dis_table[Short_Desc],'Short Desc Summary'!$B6,dis_table[Date],'Short Desc Summary'!I$2) +SUMIFS(cc_table[Amount],cc_table[Short_Desc],'Short Desc Summary'!$B6,cc_table[Date],'Short Desc Summary'!I$2) +SUMIFS(bb_table[Amount],bb_table[Short_Desc],'Short Desc Summary'!$B6,bb_table[Date],'Short Desc Summary'!I$2) -> 0 | J6: =SUMIFS(dis_table[Amount],dis_table[Short_Desc],'Short Desc Summary'!$B6,dis_table[Date],'Short Desc Summary'!J$2) +SUMIFS(cc_table[Amount],cc_table[Short_Desc],'Short Desc Summary'!$B6,cc_table[Date],'Short Desc Summary'!J$2) +SUMIFS(bb_table[Amount],bb_table[Short_Desc],'Short Desc Summary'!$B6,bb_table[Date],'Short Desc Summary'!J$2) -> 0
A7: =VLOOKUP(B7,dis_table[[#All],[Short_Desc]:[Category_2]],4,0) -> 0 | B7: interest | C7: =VLOOKUP(B7,dis_table[[#All],[Short_Desc]:[Reoccurring_Flag]],3,0) -> No | D7: =SUMIFS(dis_table[Amount],dis_table[Short_Desc],'Short Desc Summary'!$B7,dis_table[Date],'Short Desc Summary'!D$2) +SUMIFS(cc_table[Amount],cc_table[Short_Desc],'Short Desc Summary'!$B7,cc_table[Date],'Short Desc Summary'!D$2) +SUMIFS(bb_table[Amount],bb_table[Short_Desc],'Short Desc Summary'!$B7,bb_table[Date],'Short Desc Summary'!D$2) -> 0 | E7: =SUMIFS(dis_table[Amount],dis_table[Short_Desc],'Short Desc Summary'!$B7,dis_table[Date],'Short Desc Summary'!E$2) +SUMIFS(cc_table[Amount],cc_table[Short_Desc],'Short Desc Summary'!$B7,cc_table[Date],'Short Desc Summary'!E$2) +SUMIFS(bb_table[Amount],bb_table[Short_Desc],'Short Desc Summary'!$B7,bb_table[Date],'Short Desc Summary'!E$2) -> 0 | F7: =SUMIFS(dis_table[Amount],dis_table[Short_Desc],'Short Desc Summary'!$B7,dis_table[Date],'Short Desc Summary'!F$2) +SUMIFS(cc_table[Amount],cc_table[Short_Desc],'Short Desc Summary'!$B7,cc_table[Date],'Short Desc Summary'!F$2) +SUMIFS(bb_table[Amount],bb_table[Short_Desc],'Short Desc Summary'!$B7,bb_table[Date],'Short Desc Summary'!F$2) -> 0 | G7: =SUMIFS(dis_table[Amount],dis_table[Short_Desc],'Short Desc Summary'!$B7,dis_table[Date],'Short Desc Summary'!G$2) +SUMIFS(cc_table[Amount],cc_table[Short_Desc],'Short Desc Summary'!$B7,cc_table[Date],'Short Desc Summary'!G$2) +SUMIFS(bb_table[Amount],bb_table[Short_Desc],'Short Desc Summary'!$B7,bb_table[Date],'Short Desc Summary'!G$2) -> 0 | H7: =SUMIFS(dis_table[Amount],dis_table[Short_Desc],'Short Desc Summary'!$B7,dis_table[Date],'Short Desc Summary'!H$2) +SUMIFS(cc_table[Amount],cc_table[Short_Desc],'Short Desc Summary'!$B7,cc_table[Date],'Short Desc Summary'!H$2) +SUMIFS(bb_table[Amount],bb_table[Short_Desc],'Short Desc Summary'!$B7,bb_table[Date],'Short Desc Summary'!H$2) -> 50.48 | I7: =SUMIFS(dis_table[Amount],dis_table[Short_Desc],'Short Desc Summary'!$B7,dis_table[Date],'Short Desc Summary'!I$2) +SUMIFS(cc_table[Amount],cc_table[Short_Desc],'Short Desc Summary'!$B7,cc_table[Date],'Short Desc Summary'!I$2) +SUMIFS(bb_table[Amount],bb_table[Short_Desc],'Short Desc Summary'!$B7,bb_table[Date],'Short Desc Summary'!I$2) -> 99.24 | J7: =SUMIFS(dis_table[Amount],dis_table[Short_Desc],'Short Desc Summary'!$B7,dis_table[Date],'Short Desc Summary'!J$2) +SUMIFS(cc_table[Amount],cc_table[Short_Desc],'Short Desc Summary'!$B7,cc_table[Date],'Short Desc Summary'!J$2) +SUMIFS(bb_table[Amount],bb_table[Short_Desc],'Short Desc Summary'!$B7,bb_table[Date],'Short Desc Summary'!J$2) -> 99.19
A8: =VLOOKUP(B8,dis_table[[#All],[Short_Desc]:[Category_2]],4,0) -> Food | B8: fast_food | C8: =VLOOKUP(B8,dis_table[[#All],[Short_Desc]:[Reoccurring_Flag]],3,0) -> No | D8: =SUMIFS(dis_table[Amount],dis_table[Short_Desc],'Short Desc Summary'!$B8,dis_table[Date],'Short Desc Summary'!D$2) +SUMIFS(cc_table[Amount],cc_table[Short_Desc],'Short Desc Summary'!$B8,cc_table[Date],'Short Desc Summary'!D$2) +SUMIFS(bb_table[Amount],bb_table[Short_Desc],'Short Desc Summary'!$B8,bb_table[Date],'Short Desc Summary'!D$2) -> 180.99 | E8: =SUMIFS(dis_table[Amount],dis_table[Short_Desc],'Short Desc Summary'!$B8,dis_table[Date],'Short Desc Summary'!E$2) +SUMIFS(cc_table[Amount],cc_table[Short_Desc],'Short Desc Summary'!$B8,cc_table[Date],'Short Desc Summary'!E$2) +SUMIFS(bb_table[Amount],bb_table[Short_Desc],'Short Desc Summary'!$B8,bb_table[Date],'Short Desc Summary'!E$2) -> 82.05 | F8: =SUMIFS(dis_table[Amount],dis_table[Short_Desc],'Short Desc Summary'!$B8,dis_table[Date],'Short Desc Summary'!F$2) +SUMIFS(cc_table[Amount],cc_table[Short_Desc],'Short Desc Summary'!$B8,cc_table[Date],'Short Desc Summary'!F$2) +SUMIFS(bb_table[Amount],bb_table[Short_Desc],'Short Desc Summary'!$B8,bb_table[Date],'Short Desc Summary'!F$2) -> 432.69 | G8: =SUMIFS(dis_table[Amount],dis_table[Short_Desc],'Short Desc Summary'!$B8,dis_table[Date],'Short Desc Summary'!G$2) +SUMIFS(cc_table[Amount],cc_table[Short_Desc],'Short Desc Summary'!$B8,cc_table[Date],'Short Desc Summary'!G$2) +SUMIFS(bb_table[Amount],bb_table[Short_Desc],'Short Desc Summary'!$B8,bb_table[Date],'Short Desc Summary'!G$2) -> 291.46 | H8: =SUMIFS(dis_table[Amount],dis_table[Short_Desc],'Short Desc Summary'!$B8,dis_table[Date],'Short Desc Summary'!H$2) +SUMIFS(cc_table[Amount],cc_table[Short_Desc],'Short Desc Summary'!$B8,cc_table[Date],'Short Desc Summary'!H$2) +SUMIFS(bb_table[Amount],bb_table[Short_Desc],'Short Desc Summary'!$B8,bb_table[Date],'Short Desc Summary'!H$2) -> 227.61 | I8: =SUMIFS(dis_table[Amount],dis_table[Short_Desc],'Short Desc Summary'!$B8,dis_table[Date],'Short Desc Summary'!I$2) +SUMIFS(cc_table[Amount],cc_table[Short_Desc],'Short Desc Summary'!$B8,cc_table[Date],'Short Desc Summary'!I$2) +SUMIFS(bb_table[Amount],bb_table[Short_Desc],'Short Desc Summary'!$B8,bb_table[Date],'Short Desc Summary'!I$2) -> 102.18 | J8: =SUMIFS(dis_table[Amount],dis_table[Short_Desc],'Short Desc Summary'!$B8,dis_table[Date],'Short Desc Summary'!J$2) +SUMIFS(cc_table[Amount],cc_table[Short_Desc],'Short Desc Summary'!$B8,cc_table[Date],'Short Desc Summary'!J$2) +SUMIFS(bb_table[Amount],bb_table[Short_Desc],'Short Desc Summary'!$B8,bb_table[Date],'Short Desc Summary'!J$2) -> 173.65
A9: =VLOOKUP(B9,dis_table[[#All],[Short_Desc]:[Category_2]],4,0) -> Food | B9: restaurant | C9: =VLOOKUP(B9,dis_table[[#All],[Short_Desc]:[Reoccurring_Flag]],3,0) -> No | D9: =SUMIFS(dis_table[Amount],dis_table[Short_Desc],'Short Desc Summary'!$B9,dis_table[Date],'Short Desc Summary'!D$2) +SUMIFS(cc_table[Amount],cc_table[Short_Desc],'Short Desc Summary'!$B9,cc_table[Date],'Short Desc Summary'!D$2) +SUMIFS(bb_table[Amount],bb_table[Short_Desc],'Short Desc Summary'!$B9,bb_table[Date],'Short Desc Summary'!D$2) -> 202.41 | E9: =SUMIFS(dis_table[Amount],dis_table[Short_Desc],'Short Desc Summary'!$B9,dis_table[Date],'Short Desc Summary'!E$2) +SUMIFS(cc_table[Amount],cc_table[Short_Desc],'Short Desc Summary'!$B9,cc_table[Date],'Short Desc Summary'!E$2) +SUMIFS(bb_table[Amount],bb_table[Short_Desc],'Short Desc Summary'!$B9,bb_table[Date],'Short Desc Summary'!E$2) -> 18 | F9: =SUMIFS(dis_table[Amount],dis_table[Short_Desc],'Short Desc Summary'!$B9,dis_table[Date],'Short Desc Summary'!F$2) +SUMIFS(cc_table[Amount],cc_table[Short_Desc],'Short Desc Summary'!$B9,cc_table[Date],'Short Desc Summary'!F$2) +SUMIFS(bb_table[Amount],bb_table[Short_Desc],'Short Desc Summary'!$B9,bb_table[Date],'Short Desc Summary'!F$2) -> 796.13 | G9: =SUMIFS(dis_table[Amount],dis_table[Short_Desc],'Short Desc Summary'!$B9,dis_table[Date],'Short Desc Summary'!G$2) +SUMIFS(cc_table[Amount],cc_table[Short_Desc],'Short Desc Summary'!$B9,cc_table[Date],'Short Desc Summary'!G$2) +SUMIFS(bb_table[Amount],bb_table[Short_Desc],'Short Desc Summary'!$B9,bb_table[Date],'Short Desc Summary'!G$2) -> 243.61 | H9: =SUMIFS(dis_table[Amount],dis_table[Short_Desc],'Short Desc Summary'!$B9,dis_table[Date],'Short Desc Summary'!H$2) +SUMIFS(cc_table[Amount],cc_table[Short_Desc],'Short Desc Summary'!$B9,cc_table[Date],'Short Desc Summary'!H$2) +SUMIFS(bb_table[Amount],bb_table[Short_Desc],'Short Desc Summary'!$B9,bb_table[Date],'Short Desc Summary'!H$2) -> 324.04 | I9: =SUMIFS(dis_table[Amount],dis_table[Short_Desc],'Short Desc Summary'!$B9,dis_table[Date],'Short Desc Summary'!I$2) +SUMIFS(cc_table[Amount],cc_table[Short_Desc],'Short Desc Summary'!$B9,cc_table[Date],'Short Desc Summary'!I$2) +SUMIFS(bb_table[Amount],bb_table[Short_Desc],'Short Desc Summary'!$B9,bb_table[Date],'Short Desc Summary'!I$2) -> 319.96 | J9: =SUMIFS(dis_table[Amount],dis_table[Short_Desc],'Short Desc Summary'!$B9,dis_table[Date],'Short Desc Summary'!J$2) +SUMIFS(cc_table[Amount],cc_table[Short_Desc],'Short Desc Summary'!$B9,cc_table[Date],'Short Desc Summary'!J$2) +SUMIFS(bb_table[Amount],bb_table[Short_Desc],'Short Desc Summary'!$B9,bb_table[Date],'Short Desc Summary'!J$2) -> 191.83
A10: =VLOOKUP(B10,dis_table[[#All],[Short_Desc]:[Category_2]],4,0) -> Food | B10: groceries | C10: =VLOOKUP(B10,dis_table[[#All],[Short_Desc]:[Reoccurring_Flag]],3,0) -> No | D10: =SUMIFS(dis_table[Amount],dis_table[Short_Desc],'Short Desc Summary'!$B10,dis_table[Date],'Short Desc Summary'!D$2) +SUMIFS(cc_table[Amount],cc_table[Short_Desc],'Short Desc Summary'!$B10,cc_table[Date],'Short Desc Summary'!D$2) +SUMIFS(bb_table[Amount],bb_table[Short_Desc],'Short Desc Summary'!$B10,bb_table[Date],'Short Desc Summary'!D$2) -> 151.27 | E10: =SUMIFS(dis_table[Amount],dis_table[Short_Desc],'Short Desc Summary'!$B10,dis_table[Date],'Short Desc Summary'!E$2) +SUMIFS(cc_table[Amount],cc_table[Short_Desc],'Short Desc Summary'!$B10,cc_table[Date],'Short Desc Summary'!E$2) +SUMIFS(bb_table[Amount],bb_table[Short_Desc],'Short Desc Summary'!$B10,bb_table[Date],'Short Desc Summary'!E$2) -> 132.46 | F10: =SUMIFS(dis_table[Amount],dis_table[Short_Desc],'Short Desc Summary'!$B10,dis_table[Date],'Short Desc Summary'!F$2) +SUMIFS(cc_table[Amount],cc_table[Short_Desc],'Short Desc Summary'!$B10,cc_table[Date],'Short Desc Summary'!F$2) +SUMIFS(bb_table[Amount],bb_table[Short_Desc],'Short Desc Summary'!$B10,bb_table[Date],'Short Desc Summary'!F$2) -> 12.27 | G10: =SUMIFS(dis_table[Amount],dis_table[Short_Desc],'Short Desc Summary'!$B10,dis_table[Date],'Short Desc Summary'!G$2) +SUMIFS(cc_table[Amount],cc_table[Short_Desc],'Short Desc Summary'!$B10,cc_table[Date],'Short Desc Summary'!G$2) +SUMIFS(bb_table[Amount],bb_table[Short_Desc],'Short Desc Summary'!$B10,bb_table[Date],'Short Desc Summary'!G$2) -> 410.24 | H10: =SUMIFS(dis_table[Amount],dis_table[Short_Desc],'Short Desc Summary'!$B10,dis_table[Date],'Short Desc Summary'!H$2) +SUMIFS(cc_table[Amount],cc_table[Short_Desc],'Short Desc Summary'!$B10,cc_table[Date],'Short Desc Summary'!H$2) +SUMIFS(bb_table[Amount],bb_table[Short_Desc],'Short Desc Summary'!$B10,bb_table[Date],'Short Desc Summary'!H$2) -> 0 | I10: =SUMIFS(dis_table[Amount],dis_table[Short_Desc],'Short Desc Summary'!$B10,dis_table[Date],'Short Desc Summary'!I$2) +SUMIFS(cc_table[Amount],cc_table[Short_Desc],'Short Desc Summary'!$B10,cc_table[Date],'Short Desc Summary'!I$2) +SUMIFS(bb_table[Amount],bb_table[Short_Desc],'Short Desc Summary'!$B10,bb_table[Date],'Short Desc Summary'!I$2) -> 166.91 | J10: =SUMIFS(dis_table[Amount],dis_table[Short_Desc],'Short Desc Summary'!$B10,dis_table[Date],'Short Desc Summary'!J$2) +SUMIFS(cc_table[Amount],cc_table[Short_Desc],'Short Desc Summary'!$B10,cc_table[Date],'Short Desc Summary'!J$2) +SUMIFS(bb_table[Amount],bb_table[Short_Desc],'Short Desc Summary'!$B10,bb_table[Date],'Short Desc Summary'!J$2) -> 288.96
A11: =VLOOKUP(B11,dis_table[[#All],[Short_Desc]:[Category_2]],4,0) -> Food | B11: work_lunch | C11: =VLOOKUP(B11,dis_table[[#All],[Short_Desc]:[Reoccurring_Flag]],3,0) -> No | D11: =SUMIFS(dis_table[Amount],dis_table[Short_Desc],'Short Desc Summary'!$B11,dis_table[Date],'Short Desc Summary'!D$2) +SUMIFS(cc_table[Amount],cc_table[Short_Desc],'Short Desc Summary'!$B11,cc_table[Date],'Short Desc Summary'!D$2) +SUMIFS(bb_table[Amount],bb_table[Short_Desc],'Short Desc Summary'!$B11,bb_table[Date],'Short Desc Summary'!D$2) -> 12.62 | E11: =SUMIFS(dis_table[Amount],dis_table[Short_Desc],'Short Desc Summary'!$B11,dis_table[Date],'Short Desc Summary'!E$2) +SUMIFS(cc_table[Amount],cc_table[Short_Desc],'Short Desc Summary'!$B11,cc_table[Date],'Short Desc Summary'!E$2) +SUMIFS(bb_table[Amount],bb_table[Short_Desc],'Short Desc Summary'!$B11,bb_table[Date],'Short Desc Summary'!E$2) -> 15.78 | F11: =SUMIFS(dis_table[Amount],dis_table[Short_Desc],'Short Desc Summary'!$B11,dis_table[Date],'Short Desc Summary'!F$2) +SUMIFS(cc_table[Amount],cc_table[Short_Desc],'Short Desc Summary'!$B11,cc_table[Date],'Short Desc Summary'!F$2) +SUMIFS(bb_table[Amount],bb_table[Short_Desc],'Short Desc Summary'!$B11,bb_table[Date],'Short Desc Summary'!F$2) -> 13.16 | G11: =SUMIFS(dis_table[Amount],dis_table[Short_Desc],'Short Desc Summary'!$B11,dis_table[Date],'Short Desc Summary'!G$2) +SUMIFS(cc_table[Amount],cc_table[Short_Desc],'Short Desc Summary'!$B11,cc_table[Date],'Short Desc Summary'!G$2) +SUMIFS(bb_table[Amount],bb_table[Short_Desc],'Short Desc Summary'!$B11,bb_table[Date],'Short Desc Summary'!G$2) -> 0 | H11: =SUMIFS(dis_table[Amount],dis_table[Short_Desc],'Short Desc Summary'!$B11,dis_table[Date],'Short Desc Summary'!H$2) +SUMIFS(cc_table[Amount],cc_table[Short_Desc],'Short Desc Summary'!$B11,cc_table[Date],'Short Desc Summary'!H$2) +SUMIFS(bb_table[Amount],bb_table[Short_Desc],'Short Desc Summary'!$B11,bb_table[Date],'Short Desc Summary'!H$2) -> 0 | I11: =SUMIFS(dis_table[Amount],dis_table[Short_Desc],'Short Desc Summary'!$B11,dis_table[Date],'Short Desc Summary'!I$2) +SUMIFS(cc_table[Amount],cc_table[Short_Desc],'Short Desc Summary'!$B11,cc_table[Date],'Short Desc Summary'!I$2) +SUMIFS(bb_table[Amount],bb_table[Short_Desc],'Short Desc Summary'!$B11,bb_table[Date],'Short Desc Summary'!I$2) -> 0 | J11: =SUMIFS(dis_table[Amount],dis_table[Short_Desc],'Short Desc Summary'!$B11,dis_table[Date],'Short Desc Summary'!J$2) +SUMIFS(cc_table[Amount],cc_table[Short_Desc],'Short Desc Summary'!$B11,cc_table[Date],'Short Desc Summary'!J$2) +SUMIFS(bb_table[Amount],bb_table[Short_Desc],'Short Desc Summary'!$B11,bb_table[Date],'Short Desc Summary'!J$2) -> 24.8
A12: =VLOOKUP(B12,dis_table[[#All],[Short_Desc]:[Category_2]],4,0) -> Food | B12: coffee | C12: =VLOOKUP(B12,dis_table[[#All],[Short_Desc]:[Reoccurring_Flag]],3,0) -> No | D12: =SUMIFS(dis_table[Amount],dis_table[Short_Desc],'Short Desc Summary'!$B12,dis_table[Date],'Short Desc Summary'!D$2) +SUMIFS(cc_table[Amount],cc_table[Short_Desc],'Short Desc Summary'!$B12,cc_table[Date],'Short Desc Summary'!D$2) +SUMIFS(bb_table[Amount],bb_table[Short_Desc],'Short Desc Summary'!$B12,bb_table[Date],'Short Desc Summary'!D$2) -> 0 | E12: =SUMIFS(dis_table[Amount],dis_table[Short_Desc],'Short Desc Summary'!$B12,dis_table[Date],'Short Desc Summary'!E$2) +SUMIFS(cc_table[Amount],cc_table[Short_Desc],'Short Desc Summary'!$B12,cc_table[Date],'Short Desc Summary'!E$2) +SUMIFS(bb_table[Amount],bb_table[Short_Desc],'Short Desc Summary'!$B12,bb_table[Date],'Short Desc Summary'!E$2) -> 0 | F12: =SUMIFS(dis_table[Amount],dis_table[Short_Desc],'Short Desc Summary'!$B12,dis_table[Date],'Short Desc Summary'!F$2) +SUMIFS(cc_table[Amount],cc_table[Short_Desc],'Short Desc Summary'!$B12,cc_table[Date],'Short Desc Summary'!F$2) +SUMIFS(bb_table[Amount],bb_table[Short_Desc],'Short Desc Summary'!$B12,bb_table[Date],'Short Desc Summary'!F$2) -> 10 | G12: =SUMIFS(dis_table[Amount],dis_table[Short_Desc],'Short Desc Summary'!$B12,dis_table[Date],'Short Desc Summary'!G$2) +SUMIFS(cc_table[Amount],cc_table[Short_Desc],'Short Desc Summary'!$B12,cc_table[Date],'Short Desc Summary'!G$2) +SUMIFS(bb_table[Amount],bb_table[Short_Desc],'Short Desc Summary'!$B12,bb_table[Date],'Short Desc Summary'!G$2) -> 0 | H12: =SUMIFS(dis_table[Amount],dis_table[Short_Desc],'Short Desc Summary'!$B12,dis_table[Date],'Short Desc Summary'!H$2) +SUMIFS(cc_table[Amount],cc_table[Short_Desc],'Short Desc Summary'!$B12,cc_table[Date],'Short Desc Summary'!H$2) +SUMIFS(bb_table[Amount],bb_table[Short_Desc],'Short Desc Summary'!$B12,bb_table[Date],'Short Desc Summary'!H$2) -> 182.64 | I12: =SUMIFS(dis_table[Amount],dis_table[Short_Desc],'Short Desc Summary'!$B12,dis_table[Date],'Short Desc Summary'!I$2) +SUMIFS(cc_table[Amount],cc_table[Short_Desc],'Short Desc Summary'!$B12,cc_table[Date],'Short Desc Summary'!I$2) +SUMIFS(bb_table[Amount],bb_table[Short_Desc],'Short Desc Summary'!$B12,bb_table[Date],'Short Desc Summary'!I$2) -> 30.42 | J12: =SUMIFS(dis_table[Amount],dis_table[Short_Desc],'Short Desc Summary'!$B12,dis_table[Date],'Short Desc Summary'!J$2) +SUMIFS(cc_table[Amount],cc_table[Short_Desc],'Short Desc Summary'!$B12,cc_table[Date],'Short Desc Summary'!J$2) +SUMIFS(bb_table[Amount],bb_table[Short_Desc],'Short Desc Summary'!$B12,bb_table[Date],'Short Desc Summary'!J$2) -> 0
A13: =VLOOKUP(B13,dis_table[[#All],[Short_Desc]:[Category_2]],4,0) -> Housing | B13: home | C13: =VLOOKUP(B13,dis_table[[#All],[Short_Desc]:[Reoccurring_Flag]],3,0) -> No | D13: =SUMIFS(dis_table[Amount],dis_table[Short_Desc],'Short Desc Summary'!$B13,dis_table[Date],'Short Desc Summary'!D$2) +SUMIFS(cc_table[Amount],cc_table[Short_Desc],'Short Desc Summary'!$B13,cc_table[Date],'Short Desc Summary'!D$2) +SUMIFS(bb_table[Amount],bb_table[Short_Desc],'Short Desc Summary'!$B13,bb_table[Date],'Short Desc Summary'!D$2) -> 0 | E13: =SUMIFS(dis_table[Amount],dis_table[Short_Desc],'Short Desc Summary'!$B13,dis_table[Date],'Short Desc Summary'!E$2) +SUMIFS(cc_table[Amount],cc_table[Short_Desc],'Short Desc Summary'!$B13,cc_table[Date],'Short Desc Summary'!E$2) +SUMIFS(bb_table[Amount],bb_table[Short_Desc],'Short Desc Summary'!$B13,bb_table[Date],'Short Desc Summary'!E$2) -> 0 | F13: =SUMIFS(dis_table[Amount],dis_table[Short_Desc],'Short Desc Summary'!$B13,dis_table[Date],'Short Desc Summary'!F$2) +SUMIFS(cc_table[Amount],cc_table[Short_Desc],'Short Desc Summary'!$B13,cc_table[Date],'Short Desc Summary'!F$2) +SUMIFS(bb_table[Amount],bb_table[Short_Desc],'Short Desc Summary'!$B13,bb_table[Date],'Short Desc Summary'!F$2) -> 0 | G13: =SUMIFS(dis_table[Amount],dis_table[Short_Desc],'Short Desc Summary'!$B13,dis_table[Date],'Short Desc Summary'!G$2) +SUMIFS(cc_table[Amount],cc_table[Short_Desc],'Short Desc Summary'!$B13,cc_table[Date],'Short Desc Summary'!G$2) +SUMIFS(bb_table[Amount],bb_table[Short_Desc],'Short Desc Summary'!$B13,bb_table[Date],'Short Desc Summary'!G$2) -> 63.66 | H13: =SUMIFS(dis_table[Amount],dis_table[Short_Desc],'Short Desc Summary'!$B13,dis_table[Date],'Short Desc Summary'!H$2) +SUMIFS(cc_table[Amount],cc_table[Short_Desc],'Short Desc Summary'!$B13,cc_table[Date],'Short Desc Summary'!H$2) +SUMIFS(bb_table[Amount],bb_table[Short_Desc],'Short Desc Summary'!$B13,bb_table[Date],'Short Desc Summary'!H$2) -> 0 | I13: =SUMIFS(dis_table[Amount],dis_table[Short_Desc],'Short Desc Summary'!$B13,dis_table[Date],'Short Desc Summary'!I$2) +SUMIFS(cc_table[Amount],cc_table[Short_Desc],'Short Desc Summary'!$B13,cc_table[Date],'Short Desc Summary'!I$2) +SUMIFS(bb_table[Amount],bb_table[Short_Desc],'Short Desc Summary'!$B13,bb_table[Date],'Short Desc Summary'!I$2) -> 0 | J13: =SUMIFS(dis_table[Amount],dis_table[Short_Desc],'Short Desc Summary'!$B13,dis_table[Date],'Short Desc Summary'!J$2) +SUMIFS(cc_table[Amount],cc_table[Short_Desc],'Short Desc Summary'!$B13,cc_table[Date],'Short Desc Summary'!J$2) +SUMIFS(bb_table[Amount],bb_table[Short_Desc],'Short Desc Summary'!$B13,bb_table[Date],'Short Desc Summary'!J$2) -> 0
A14: =VLOOKUP(B14,dis_table[[#All],[Short_Desc]:[Category_2]],4,0) -> Housing | B14: home_supplies | C14: =VLOOKUP(B14,dis_table[[#All],[Short_Desc]:[Reoccurring_Flag]],3,0) -> No | D14: =SUMIFS(dis_table[Amount],dis_table[Short_Desc],'Short Desc Summary'!$B14,dis_table[Date],'Short Desc Summary'!D$2) +SUMIFS(cc_table[Amount],cc_table[Short_Desc],'Short Desc Summary'!$B14,cc_table[Date],'Short Desc Summary'!D$2) +SUMIFS(bb_table[Amount],bb_table[Short_Desc],'Short Desc Summary'!$B14,bb_table[Date],'Short Desc Summary'!D$2) -> 0 | E14: =SUMIFS(dis_table[Amount],dis_table[Short_Desc],'Short Desc Summary'!$B14,dis_table[Date],'Short Desc Summary'!E$2) +SUMIFS(cc_table[Amount],cc_table[Short_Desc],'Short Desc Summary'!$B14,cc_table[Date],'Short Desc Summary'!E$2) +SUMIFS(bb_table[Amount],bb_table[Short_Desc],'Short Desc Summary'!$B14,bb_table[Date],'Short Desc Summary'!E$2) -> 0 | F14: =SUMIFS(dis_table[Amount],dis_table[Short_Desc],'Short Desc Summary'!$B14,dis_table[Date],'Short Desc Summary'!F$2) +SUMIFS(cc_table[Amount],cc_table[Short_Desc],'Short Desc Summary'!$B14,cc_table[Date],'Short Desc Summary'!F$2) +SUMIFS(bb_table[Amount],bb_table[Short_Desc],'Short Desc Summary'!$B14,bb_table[Date],'Short Desc Summary'!F$2) -> 0 | G14: =SUMIFS(dis_table[Amount],dis_table[Short_Desc],'Short Desc Summary'!$B14,dis_table[Date],'Short Desc Summary'!G$2) +SUMIFS(cc_table[Amount],cc_table[Short_Desc],'Short Desc Summary'!$B14,cc_table[Date],'Short Desc Summary'!G$2) +SUMIFS(bb_table[Amount],bb_table[Short_Desc],'Short Desc Summary'!$B14,bb_table[Date],'Short Desc Summary'!G$2) -> 0 | H14: =SUMIFS(dis_table[Amount],dis_table[Short_Desc],'Short Desc Summary'!$B14,dis_table[Date],'Short Desc Summary'!H$2) +SUMIFS(cc_table[Amount],cc_table[Short_Desc],'Short Desc Summary'!$B14,cc_table[Date],'Short Desc Summary'!H$2) +SUMIFS(bb_table[Amount],bb_table[Short_Desc],'Short Desc Summary'!$B14,bb_table[Date],'Short Desc Summary'!H$2) -> 0 | I14: =SUMIFS(dis_table[Amount],dis_table[Short_Desc],'Short Desc Summary'!$B14,dis_table[Date],'Short Desc Summary'!I$2) +SUMIFS(cc_table[Amount],cc_table[Short_Desc],'Short Desc Summary'!$B14,cc_table[Date],'Short Desc Summary'!I$2) +SUMIFS(bb_table[Amount],bb_table[Short_Desc],'Short Desc Summary'!$B14,bb_table[Date],'Short Desc Summary'!I$2) -> 0 | J14: =SUMIFS(dis_table[Amount],dis_table[Short_Desc],'Short Desc Summary'!$B14,dis_table[Date],'Short Desc Summary'!J$2) +SUMIFS(cc_table[Amount],cc_table[Short_Desc],'Short Desc Summary'!$B14,cc_table[Date],'Short Desc Summary'!J$2) +SUMIFS(bb_table[Amount],bb_table[Short_Desc],'Short Desc Summary'!$B14,bb_table[Date],'Short Desc Summary'!J$2) -> 38.1
... A16: =VLOOKUP(B16,dis_table[[#All],[Short_Desc]:[Category_2]],4,0) -> Medical | B16: medical | C16: =VLOOKUP(B16,dis_table[[#All],[Short_Desc]:[Reoccurring_Flag]],3,0) -> No | D16: =SUMIFS(dis_table[Amount],dis_table[Short_Desc],'Short Desc Summary'!$B16,dis_table[Date],'Short Desc Summary'!D$2) +SUMIFS(cc_table[Amount],cc_table[Short_Desc],'Short Desc Summary'!$B16,cc_table[Date],'Short Desc Summary'!D$2) +SUMIFS(bb_table[Amount],bb_table[Short_Desc],'Short Desc Summary'!$B16,bb_table[Date],'Short Desc Summary'!D$2) -> 0 | E16: =SUMIFS(dis_table[Amount],dis_table[Short_Desc],'Short Desc Summary'!$B16,dis_table[Date],'Short Desc Summary'!E$2) +SUMIFS(cc_table[Amount],cc_table[Short_Desc],'Short Desc Summary'!$B16,cc_table[Date],'Short Desc Summary'!E$2) +SUMIFS(bb_table[Amount],bb_table[Short_Desc],'Short Desc Summary'!$B16,bb_table[Date],'Short Desc Summary'!E$2) -> 0 | F16: =SUMIFS(dis_table[Amount],dis_table[Short_Desc],'Short Desc Summary'!$B16,dis_table[Date],'Short Desc Summary'!F$2) +SUMIFS(cc_table[Amount],cc_table[Short_Desc],'Short Desc Summary'!$B16,cc_table[Date],'Short Desc Summary'!F$2) +SUMIFS(bb_table[Amount],bb_table[Short_Desc],'Short Desc Summary'!$B16,bb_table[Date],'Short Desc Summary'!F$2) -> 432 | G16: =SUMIFS(dis_table[Amount],dis_table[Short_Desc],'Short Desc Summary'!$B16,dis_table[Date],'Short Desc Summary'!G$2) +SUMIFS(cc_table[Amount],cc_table[Short_Desc],'Short Desc Summary'!$B16,cc_table[Date],'Short Desc Summary'!G$2) +SUMIFS(bb_table[Amount],bb_table[Short_Desc],'Short Desc Summary'!$B16,bb_table[Date],'Short Desc Summary'!G$2) -> 0 | H16: =SUMIFS(dis_table[Amount],dis_table[Short_Desc],'Short Desc Summary'!$B16,dis_table[Date],'Short Desc Summary'!H$2) +SUMIFS(cc_table[Amount],cc_table[Short_Desc],'Short Desc Summary'!$B16,cc_table[Date],'Short Desc Summary'!H$2) +SUMIFS(bb_table[Amount],bb_table[Short_Desc],'Short Desc Summary'!$B16,bb_table[Date],'Short Desc Summary'!H$2) -> 0 | I16: =SUMIFS(dis_table[Amount],dis_table[Short_Desc],'Short Desc Summary'!$B16,dis_table[Date],'Short Desc Summary'!I$2) +SUMIFS(cc_table[Amount],cc_table[Short_Desc],'Short Desc Summary'!$B16,cc_table[Date],'Short Desc Summary'!I$2) +SUMIFS(bb_table[Amount],bb_table[Short_Desc],'Short Desc Summary'!$B16,bb_table[Date],'Short Desc Summary'!I$2) -> 0 | J16: =SUMIFS(dis_table[Amount],dis_table[Short_Desc],'Short Desc Summary'!$B16,dis_table[Date],'Short Desc Summary'!J$2) +SUMIFS(cc_table[Amount],cc_table[Short_Desc],'Short Desc Summary'!$B16,cc_table[Date],'Short Desc Summary'!J$2) +SUMIFS(bb_table[Amount],bb_table[Short_Desc],'Short Desc Summary'!$B16,bb_table[Date],'Short Desc Summary'!J$2) -> 0
A17: =VLOOKUP(B17,cc_table[[#All],[Short_Desc]:[Category_2]],3,0) -> Medical | B17: Dental | C17: No | D17: =SUMIFS(dis_table[Amount],dis_table[Short_Desc],'Short Desc Summary'!$B17,dis_table[Date],'Short Desc Summary'!D$2) +SUMIFS(cc_table[Amount],cc_table[Short_Desc],'Short Desc Summary'!$B17,cc_table[Date],'Short Desc Summary'!D$2) +SUMIFS(bb_table[Amount],bb_table[Short_Desc],'Short Desc Summary'!$B17,bb_table[Date],'Short Desc Summary'!D$2) -> 2286 | E17: =SUMIFS(dis_table[Amount],dis_table[Short_Desc],'Short Desc Summary'!$B17,dis_table[Date],'Short Desc Summary'!E$2) +SUMIFS(cc_table[Amount],cc_table[Short_Desc],'Short Desc Summary'!$B17,cc_table[Date],'Short Desc Summary'!E$2) +SUMIFS(bb_table[Amount],bb_table[Short_Desc],'Short Desc Summary'!$B17,bb_table[Date],'Short Desc Summary'!E$2) -> 0 | F17: =SUMIFS(dis_table[Amount],dis_table[Short_Desc],'Short Desc Summary'!$B17,dis_table[Date],'Short Desc Summary'!F$2) +SUMIFS(cc_table[Amount],cc_table[Short_Desc],'Short Desc Summary'!$B17,cc_table[Date],'Short Desc Summary'!F$2) +SUMIFS(bb_table[Amount],bb_table[Short_Desc],'Short Desc Summary'!$B17,bb_table[Date],'Short Desc Summary'!F$2) -> 0 | G17: =SUMIFS(dis_table[Amount],dis_table[Short_Desc],'Short Desc Summary'!$B17,dis_table[Date],'Short Desc Summary'!G$2) +SUMIFS(cc_table[Amount],cc_table[Short_Desc],'Short Desc Summary'!$B17,cc_table[Date],'Short Desc Summary'!G$2) +SUMIFS(bb_table[Amount],bb_table[Short_Desc],'Short Desc Summary'!$B17,bb_table[Date],'Short Desc Summary'!G$2) -> 0 | H17: =SUMIFS(dis_table[Amount],dis_table[Short_Desc],'Short Desc Summary'!$B17,dis_table[Date],'Short Desc Summary'!H$2) +SUMIFS(cc_table[Amount],cc_table[Short_Desc],'Short Desc Summary'!$B17,cc_table[Date],'Short Desc Summary'!H$2) +SUMIFS(bb_table[Amount],bb_table[Short_Desc],'Short Desc Summary'!$B17,bb_table[Date],'Short Desc Summary'!H$2) -> 0 | I17: =SUMIFS(dis_table[Amount],dis_table[Short_Desc],'Short Desc Summary'!$B17,dis_table[Date],'Short Desc Summary'!I$2) +SUMIFS(cc_table[Amount],cc_table[Short_Desc],'Short Desc Summary'!$B17,cc_table[Date],'Short Desc Summary'!I$2) +SUMIFS(bb_table[Amount],bb_table[Short_Desc],'Short Desc Summary'!$B17,bb_table[Date],'Short Desc Summary'!I$2) -> 0 | J17: =SUMIFS(dis_table[Amount],dis_table[Short_Desc],'Short Desc Summary'!$B17,dis_table[Date],'Short Desc Summary'!J$2) +SUMIFS(cc_table[Amount],cc_table[Short_Desc],'Short Desc Summary'!$B17,cc_table[Date],'Short Desc Summary'!J$2) +SUMIFS(bb_table[Amount],bb_table[Short_Desc],'Short Desc Summary'!$B17,bb_table[Date],'Short Desc Summary'!J$2) -> 0
A18: =VLOOKUP(B18,cc_table[[#All],[Short_Desc]:[Category_2]],3,0) -> Medical | B18: Surgery | C18: No | D18: =SUMIFS(dis_table[Amount],dis_table[Short_Desc],'Short Desc Summary'!$B18,dis_table[Date],'Short Desc Summary'!D$2) +SUMIFS(cc_table[Amount],cc_table[Short_Desc],'Short Desc Summary'!$B18,cc_table[Date],'Short Desc Summary'!D$2) +SUMIFS(bb_table[Amount],bb_table[Short_Desc],'Short Desc Summary'!$B18,bb_table[Date],'Short Desc Summary'!D$2) -> 0 | E18: =SUMIFS(dis_table[Amount],dis_table[Short_Desc],'Short Desc Summary'!$B18,dis_table[Date],'Short Desc Summary'!E$2) +SUMIFS(cc_table[Amount],cc_table[Short_Desc],'Short Desc Summary'!$B18,cc_table[Date],'Short Desc Summary'!E$2) +SUMIFS(bb_table[Amount],bb_table[Short_Desc],'Short Desc Summary'!$B18,bb_table[Date],'Short Desc Summary'!E$2) -> 0 | F18: =SUMIFS(dis_table[Amount],dis_table[Short_Desc],'Short Desc Summary'!$B18,dis_table[Date],'Short Desc Summary'!F$2) +SUMIFS(cc_table[Amount],cc_table[Short_Desc],'Short Desc Summary'!$B18,cc_table[Date],'Short Desc Summary'!F$2) +SUMIFS(bb_table[Amount],bb_table[Short_Desc],'Short Desc Summary'!$B18,bb_table[Date],'Short Desc Summary'!F$2) -> 2121.16 | G18: =SUMIFS(dis_table[Amount],dis_table[Short_Desc],'Short Desc Summary'!$B18,dis_table[Date],'Short Desc Summary'!G$2) +SUMIFS(cc_table[Amount],cc_table[Short_Desc],'Short Desc Summary'!$B18,cc_table[Date],'Short Desc Summary'!G$2) +SUMIFS(bb_table[Amount],bb_table[Short_Desc],'Short Desc Summary'!$B18,bb_table[Date],'Short Desc Summary'!G$2) -> 0 | H18: =SUMIFS(dis_table[Amount],dis_table[Short_Desc],'Short Desc Summary'!$B18,dis_table[Date],'Short Desc Summary'!H$2) +SUMIFS(cc_table[Amount],cc_table[Short_Desc],'Short Desc Summary'!$B18,cc_table[Date],'Short Desc Summary'!H$2) +SUMIFS(bb_table[Amount],bb_table[Short_Desc],'Short Desc Summary'!$B18,bb_table[Date],'Short Desc Summary'!H$2) -> 0 | I18: =SUMIFS(dis_table[Amount],dis_table[Short_Desc],'Short Desc Summary'!$B18,dis_table[Date],'Short Desc Summary'!I$2) +SUMIFS(cc_table[Amount],cc_table[Short_Desc],'Short Desc Summary'!$B18,cc_table[Date],'Short Desc Summary'!I$2) +SUMIFS(bb_table[Amount],bb_table[Short_Desc],'Short Desc Summary'!$B18,bb_table[Date],'Short Desc Summary'!I$2) -> 0 | J18: =SUMIFS(dis_table[Amount],dis_table[Short_Desc],'Short Desc Summary'!$B18,dis_table[Date],'Short Desc Summary'!J$2) +SUMIFS(cc_table[Amount],cc_table[Short_Desc],'Short Desc Summary'!$B18,cc_table[Date],'Short Desc Summary'!J$2) +SUMIFS(bb_table[Amount],bb_table[Short_Desc],'Short Desc Summary'!$B18,bb_table[Date],'Short Desc Summary'!J$2) -> 0
A19: =VLOOKUP(B19,dis_table[[#All],[Short_Desc]:[Category_2]],4,0) -> Misc | B19: unsure | C19: =VLOOKUP(B19,dis_table[[#All],[Short_Desc]:[Reoccurring_Flag]],3,0) -> No | D19: =SUMIFS(dis_table[Amount],dis_table[Short_Desc],'Short Desc Summary'!$B19,dis_table[Date],'Short Desc Summary'!D$2) +SUMIFS(cc_table[Amount],cc_table[Short_Desc],'Short Desc Summary'!$B19,cc_table[Date],'Short Desc Summary'!D$2) +SUMIFS(bb_table[Amount],bb_table[Short_Desc],'Short Desc Summary'!$B19,bb_table[Date],'Short Desc Summary'!D$2) -> 26.49 | E19: =SUMIFS(dis_table[Amount],dis_table[Short_Desc],'Short Desc Summary'!$B19,dis_table[Date],'Short Desc Summary'!E$2) +SUMIFS(cc_table[Amount],cc_table[Short_Desc],'Short Desc Summary'!$B19,cc_table[Date],'Short Desc Summary'!E$2) +SUMIFS(bb_table[Amount],bb_table[Short_Desc],'Short Desc Summary'!$B19,bb_table[Date],'Short Desc Summary'!E$2) -> 0 | F19: =SUMIFS(dis_table[Amount],dis_table[Short_Desc],'Short Desc Summary'!$B19,dis_table[Date],'Short Desc Summary'!F$2) +SUMIFS(cc_table[Amount],cc_table[Short_Desc],'Short Desc Summary'!$B19,cc_table[Date],'Short Desc Summary'!F$2) +SUMIFS(bb_table[Amount],bb_table[Short_Desc],'Short Desc Summary'!$B19,bb_table[Date],'Short Desc Summary'!F$2) -> 0 | G19: =SUMIFS(dis_table[Amount],dis_table[Short_Desc],'Short Desc Summary'!$B19,dis_table[Date],'Short Desc Summary'!G$2) +SUMIFS(cc_table[Amount],cc_table[Short_Desc],'Short Desc Summary'!$B19,cc_table[Date],'Short Desc Summary'!G$2) +SUMIFS(bb_table[Amount],bb_table[Short_Desc],'Short Desc Summary'!$B19,bb_table[Date],'Short Desc Summary'!G$2) -> 16 | H19: =SUMIFS(dis_table[Amount],dis_table[Short_Desc],'Short Desc Summary'!$B19,dis_table[Date],'Short Desc Summary'!H$2) +SUMIFS(cc_table[Amount],cc_table[Short_Desc],'Short Desc Summary'!$B19,cc_table[Date],'Short Desc Summary'!H$2) +SUMIFS(bb_table[Amount],bb_table[Short_Desc],'Short Desc Summary'!$B19,bb_table[Date],'Short Desc Summary'!H$2) -> 9.75 | I19: =SUMIFS(dis_table[Amount],dis_table[Short_Desc],'Short Desc Summary'!$B19,dis_table[Date],'Short Desc Summary'!I$2) +SUMIFS(cc_table[Amount],cc_table[Short_Desc],'Short Desc Summary'!$B19,cc_table[Date],'Short Desc Summary'!I$2) +SUMIFS(bb_table[Amount],bb_table[Short_Desc],'Short Desc Summary'!$B19,bb_table[Date],'Short Desc Summary'!I$2) -> 83 | J19: =SUMIFS(dis_table[Amount],dis_table[Short_Desc],'Short Desc Summary'!$B19,dis_table[Date],'Short Desc Summary'!J$2) +SUMIFS(cc_table[Amount],cc_table[Short_Desc],'Short Desc Summary'!$B19,cc_table[Date],'Short Desc Summary'!J$2) +SUMIFS(bb_table[Amount],bb_table[Short_Desc],'Short Desc Summary'!$B19,bb_table[Date],'Short Desc Summary'!J$2) -> 0
A20: =VLOOKUP(B20,dis_table[[#All],[Short_Desc]:[Category_2]],4,0) -> Misc | B20: vending | C20: =VLOOKUP(B20,dis_table[[#All],[Short_Desc]:[Reoccurring_Flag]],3,0) -> No | D20: =SUMIFS(dis_table[Amount],dis_table[Short_Desc],'Short Desc Summary'!$B20,dis_table[Date],'Short Desc Summary'!D$2) +SUMIFS(cc_table[Amount],cc_table[Short_Desc],'Short Desc Summary'!$B20,cc_table[Date],'Short Desc Summary'!D$2) +SUMIFS(bb_table[Amount],bb_table[Short_Desc],'Short Desc Summary'!$B20,bb_table[Date],'Short Desc Summary'!D$2) -> 0 | E20: =SUMIFS(dis_table[Amount],dis_table[Short_Desc],'Short Desc Summary'!$B20,dis_table[Date],'Short Desc Summary'!E$2) +SUMIFS(cc_table[Amount],cc_table[Short_Desc],'Short Desc Summary'!$B20,cc_table[Date],'Short Desc Summary'!E$2) +SUMIFS(bb_table[Amount],bb_table[Short_Desc],'Short Desc Summary'!$B20,bb_table[Date],'Short Desc Summary'!E$2) -> 0 | F20: =SUMIFS(dis_table[Amount],dis_table[Short_Desc],'Short Desc Summary'!$B20,dis_table[Date],'Short Desc Summary'!F$2) +SUMIFS(cc_table[Amount],cc_table[Short_Desc],'Short Desc Summary'!$B20,cc_table[Date],'Short Desc Summary'!F$2) +SUMIFS(bb_table[Amount],bb_table[Short_Desc],'Short Desc Summary'!$B20,bb_table[Date],'Short Desc Summary'!F$2) -> 0 | G20: =SUMIFS(dis_table[Amount],dis_table[Short_Desc],'Short Desc Summary'!$B20,dis_table[Date],'Short Desc Summary'!G$2) +SUMIFS(cc_table[Amount],cc_table[Short_Desc],'Short Desc Summary'!$B20,cc_table[Date],'Short Desc Summary'!G$2) +SUMIFS(bb_table[Amount],bb_table[Short_Desc],'Short Desc Summary'!$B20,bb_table[Date],'Short Desc Summary'!G$2) -> 0 | H20: =SUMIFS(dis_table[Amount],dis_table[Short_Desc],'Short Desc Summary'!$B20,dis_table[Date],'Short Desc Summary'!H$2) +SUMIFS(cc_table[Amount],cc_table[Short_Desc],'Short Desc Summary'!$B20,cc_table[Date],'Short Desc Summary'!H$2) +SUMIFS(bb_table[Amount],bb_table[Short_Desc],'Short Desc Summary'!$B20,bb_table[Date],'Short Desc Summary'!H$2) -> 0 | I20: =SUMIFS(dis_table[Amount],dis_table[Short_Desc],'Short Desc Summary'!$B20,dis_table[Date],'Short Desc Summary'!I$2) +SUMIFS(cc_table[Amount],cc_table[Short_Desc],'Short Desc Summary'!$B20,cc_table[Date],'Short Desc Summary'!I$2) +SUMIFS(bb_table[Amount],bb_table[Short_Desc],'Short Desc Summary'!$B20,bb_table[Date],'Short Desc Summary'!I$2) -> 0 | J20: =SUMIFS(dis_table[Amount],dis_table[Short_Desc],'Short Desc Summary'!$B20,dis_table[Date],'Short Desc Summary'!J$2) +SUMIFS(cc_table[Amount],cc_table[Short_Desc],'Short Desc Summary'!$B20,cc_table[Date],'Short Desc Summary'!J$2) +SUMIFS(bb_table[Amount],bb_table[Short_Desc],'Short Desc Summary'!$B20,bb_table[Date],'Short Desc Summary'!J$2) -> 5.1
A21: =VLOOKUP(B21,dis_table[[#All],[Short_Desc]:[Category_2]],4,0) -> People | B21: dad | C21: =VLOOKUP(B21,dis_table[[#All],[Short_Desc]:[Reoccurring_Flag]],3,0) -> No | D21: =SUMIFS(dis_table[Amount],dis_table[Short_Desc],'Short Desc Summary'!$B21,dis_table[Date],'Short Desc Summary'!D$2) +SUMIFS(cc_table[Amount],cc_table[Short_Desc],'Short Desc Summary'!$B21,cc_table[Date],'Short Desc Summary'!D$2) +SUMIFS(bb_table[Amount],bb_table[Short_Desc],'Short Desc Summary'!$B21,bb_table[Date],'Short Desc Summary'!D$2) -> 0 | E21: =SUMIFS(dis_table[Amount],dis_table[Short_Desc],'Short Desc Summary'!$B21,dis_table[Date],'Short Desc Summary'!E$2) +SUMIFS(cc_table[Amount],cc_table[Short_Desc],'Short Desc Summary'!$B21,cc_table[Date],'Short Desc Summary'!E$2) +SUMIFS(bb_table[Amount],bb_table[Short_Desc],'Short Desc Summary'!$B21,bb_table[Date],'Short Desc Summary'!E$2) -> 49 | F21: =SUMIFS(dis_table[Amount],dis_table[Short_Desc],'Short Desc Summary'!$B21,dis_table[Date],'Short Desc Summary'!F$2) +SUMIFS(cc_table[Amount],cc_table[Short_Desc],'Short Desc Summary'!$B21,cc_table[Date],'Short Desc Summary'!F$2) +SUMIFS(bb_table[Amount],bb_table[Short_Desc],'Short Desc Summary'!$B21,bb_table[Date],'Short Desc Summary'!F$2) -> 42 | G21: =SUMIFS(dis_table[Amount],dis_table[Short_Desc],'Short Desc Summary'!$B21,dis_table[Date],'Short Desc Summary'!G$2) +SUMIFS(cc_table[Amount],cc_table[Short_Desc],'Short Desc Summary'!$B21,cc_table[Date],'Short Desc Summary'!G$2) +SUMIFS(bb_table[Amount],bb_table[Short_Desc],'Short Desc Summary'!$B21,bb_table[Date],'Short Desc Summary'!G$2) -> 0 | H21: =SUMIFS(dis_table[Amount],dis_table[Short_Desc],'Short Desc Summary'!$B21,dis_table[Date],'Short Desc Summary'!H$2) +SUMIFS(cc_table[Amount],cc_table[Short_Desc],'Short Desc Summary'!$B21,cc_table[Date],'Short Desc Summary'!H$2) +SUMIFS(bb_table[Amount],bb_table[Short_Desc],'Short Desc Summary'!$B21,bb_table[Date],'Short Desc Summary'!H$2) -> 0 | I21: =SUMIFS(dis_table[Amount],dis_table[Short_Desc],'Short Desc Summary'!$B21,dis_table[Date],'Short Desc Summary'!I$2) +SUMIFS(cc_table[Amount],cc_table[Short_Desc],'Short Desc Summary'!$B21,cc_table[Date],'Short Desc Summary'!I$2) +SUMIFS(bb_table[Amount],bb_table[Short_Desc],'Short Desc Summary'!$B21,bb_table[Date],'Short Desc Summary'!I$2) -> 0 | J21: =SUMIFS(dis_table[Amount],dis_table[Short_Desc],'Short Desc Summary'!$B21,dis_table[Date],'Short Desc Summary'!J$2) +SUMIFS(cc_table[Amount],cc_table[Short_Desc],'Short Desc Summary'!$B21,cc_table[Date],'Short Desc Summary'!J$2) +SUMIFS(bb_table[Amount],bb_table[Short_Desc],'Short Desc Summary'!$B21,bb_table[Date],'Short Desc Summary'!J$2) -> 0
A22: =VLOOKUP(B22,dis_table[[#All],[Short_Desc]:[Category_2]],4,0) -> People | B22: tahjei | C22: =VLOOKUP(B22,dis_table[[#All],[Short_Desc]:[Reoccurring_Flag]],3,0) -> No | D22: =SUMIFS(dis_table[Amount],dis_table[Short_Desc],'Short Desc Summary'!$B22,dis_table[Date],'Short Desc Summary'!D$2) +SUMIFS(cc_table[Amount],cc_table[Short_Desc],'Short Desc Summary'!$B22,cc_table[Date],'Short Desc Summary'!D$2) +SUMIFS(bb_table[Amount],bb_table[Short_Desc],'Short Desc Summary'!$B22,bb_table[Date],'Short Desc Summary'!D$2) -> 0 | E22: =SUMIFS(dis_table[Amount],dis_table[Short_Desc],'Short Desc Summary'!$B22,dis_table[Date],'Short Desc Summary'!E$2) +SUMIFS(cc_table[Amount],cc_table[Short_Desc],'Short Desc Summary'!$B22,cc_table[Date],'Short Desc Summary'!E$2) +SUMIFS(bb_table[Amount],bb_table[Short_Desc],'Short Desc Summary'!$B22,bb_table[Date],'Short Desc Summary'!E$2) -> 0 | F22: =SUMIFS(dis_table[Amount],dis_table[Short_Desc],'Short Desc Summary'!$B22,dis_table[Date],'Short Desc Summary'!F$2) +SUMIFS(cc_table[Amount],cc_table[Short_Desc],'Short Desc Summary'!$B22,cc_table[Date],'Short Desc Summary'!F$2) +SUMIFS(bb_table[Amount],bb_table[Short_Desc],'Short Desc Summary'!$B22,bb_table[Date],'Short Desc Summary'!F$2) -> 126.2 | G22: =SUMIFS(dis_table[Amount],dis_table[Short_Desc],'Short Desc Summary'!$B22,dis_table[Date],'Short Desc Summary'!G$2) +SUMIFS(cc_table[Amount],cc_table[Short_Desc],'Short Desc Summary'!$B22,cc_table[Date],'Short Desc Summary'!G$2) +SUMIFS(bb_table[Amount],bb_table[Short_Desc],'Short Desc Summary'!$B22,bb_table[Date],'Short Desc Summary'!G$2) -> 0 | H22: =SUMIFS(dis_table[Amount],dis_table[Short_Desc],'Short Desc Summary'!$B22,dis_table[Date],'Short Desc Summary'!H$2) +SUMIFS(cc_table[Amount],cc_table[Short_Desc],'Short Desc Summary'!$B22,cc_table[Date],'Short Desc Summary'!H$2) +SUMIFS(bb_table[Amount],bb_table[Short_Desc],'Short Desc Summary'!$B22,bb_table[Date],'Short Desc Summary'!H$2) -> 0 | I22: =SUMIFS(dis_table[Amount],dis_table[Short_Desc],'Short Desc Summary'!$B22,dis_table[Date],'Short Desc Summary'!I$2) +SUMIFS(cc_table[Amount],cc_table[Short_Desc],'Short Desc Summary'!$B22,cc_table[Date],'Short Desc Summary'!I$2) +SUMIFS(bb_table[Amount],bb_table[Short_Desc],'Short Desc Summary'!$B22,bb_table[Date],'Short Desc Summary'!I$2) -> 0 | J22: =SUMIFS(dis_table[Amount],dis_table[Short_Desc],'Short Desc Summary'!$B22,dis_table[Date],'Short Desc Summary'!J$2) +SUMIFS(cc_table[Amount],cc_table[Short_Desc],'Short Desc Summary'!$B22,cc_table[Date],'Short Desc Summary'!J$2) +SUMIFS(bb_table[Amount],bb_table[Short_Desc],'Short Desc Summary'!$B22,bb_table[Date],'Short Desc Summary'!J$2) -> 0
A23: =VLOOKUP(B23,dis_table[[#All],[Short_Desc]:[Category_2]],4,0) -> People | B23: don | C23: =VLOOKUP(B23,dis_table[[#All],[Short_Desc]:[Reoccurring_Flag]],3,0) -> No | D23: =SUMIFS(dis_table[Amount],dis_table[Short_Desc],'Short Desc Summary'!$B23,dis_table[Date],'Short Desc Summary'!D$2) +SUMIFS(cc_table[Amount],cc_table[Short_Desc],'Short Desc Summary'!$B23,cc_table[Date],'Short Desc Summary'!D$2) +SUMIFS(bb_table[Amount],bb_table[Short_Desc],'Short Desc Summary'!$B23,bb_table[Date],'Short Desc Summary'!D$2) -> 0 | E23: =SUMIFS(dis_table[Amount],dis_table[Short_Desc],'Short Desc Summary'!$B23,dis_table[Date],'Short Desc Summary'!E$2) +SUMIFS(cc_table[Amount],cc_table[Short_Desc],'Short Desc Summary'!$B23,cc_table[Date],'Short Desc Summary'!E$2) +SUMIFS(bb_table[Amount],bb_table[Short_Desc],'Short Desc Summary'!$B23,bb_table[Date],'Short Desc Summary'!E$2) -> 0 | F23: =SUMIFS(dis_table[Amount],dis_table[Short_Desc],'Short Desc Summary'!$B23,dis_table[Date],'Short Desc Summary'!F$2) +SUMIFS(cc_table[Amount],cc_table[Short_Desc],'Short Desc Summary'!$B23,cc_table[Date],'Short Desc Summary'!F$2) +SUMIFS(bb_table[Amount],bb_table[Short_Desc],'Short Desc Summary'!$B23,bb_table[Date],'Short Desc Summary'!F$2) -> 0 | G23: =SUMIFS(dis_table[Amount],dis_table[Short_Desc],'Short Desc Summary'!$B23,dis_table[Date],'Short Desc Summary'!G$2) +SUMIFS(cc_table[Amount],cc_table[Short_Desc],'Short Desc Summary'!$B23,cc_table[Date],'Short Desc Summary'!G$2) +SUMIFS(bb_table[Amount],bb_table[Short_Desc],'Short Desc Summary'!$B23,bb_table[Date],'Short Desc Summary'!G$2) -> 0 | H23: =SUMIFS(dis_table[Amount],dis_table[Short_Desc],'Short Desc Summary'!$B23,dis_table[Date],'Short Desc Summary'!H$2) +SUMIFS(cc_table[Amount],cc_table[Short_Desc],'Short Desc Summary'!$B23,cc_table[Date],'Short Desc Summary'!H$2) +SUMIFS(bb_table[Amount],bb_table[Short_Desc],'Short Desc Summary'!$B23,bb_table[Date],'Short Desc Summary'!H$2) -> 0 | I23: =SUMIFS(dis_table[Amount],dis_table[Short_Desc],'Short Desc Summary'!$B23,dis_table[Date],'Short Desc Summary'!I$2) +SUMIFS(cc_table[Amount],cc_table[Short_Desc],'Short Desc Summary'!$B23,cc_table[Date],'Short Desc Summary'!I$2) +SUMIFS(bb_table[Amount],bb_table[Short_Desc],'Short Desc Summary'!$B23,bb_table[Date],'Short Desc Summary'!I$2) -> 0 | J23: =SUMIFS(dis_table[Amount],dis_table[Short_Desc],'Short Desc Summary'!$B23,dis_table[Date],'Short Desc Summary'!J$2) +SUMIFS(cc_table[Amount],cc_table[Short_Desc],'Short Desc Summary'!$B23,cc_table[Date],'Short Desc Summary'!J$2) +SUMIFS(bb_table[Amount],bb_table[Short_Desc],'Short Desc Summary'!$B23,bb_table[Date],'Short Desc Summary'!J$2) -> 51.5
A24: =VLOOKUP(B24,dis_table[[#All],[Short_Desc]:[Category_2]],4,0) -> Personal_Spending | B24: gym | C24: =VLOOKUP(B24,dis_table[[#All],[Short_Desc]:[Reoccurring_Flag]],3,0) -> No | D24: =SUMIFS(dis_table[Amount],dis_table[Short_Desc],'Short Desc Summary'!$B24,dis_table[Date],'Short Desc Summary'!D$2) +SUMIFS(cc_table[Amount],cc_table[Short_Desc],'Short Desc Summary'!$B24,cc_table[Date],'Short Desc Summary'!D$2) +SUMIFS(bb_table[Amount],bb_table[Short_Desc],'Short Desc Summary'!$B24,bb_table[Date],'Short Desc Summary'!D$2) -> 210 | E24: =SUMIFS(dis_table[Amount],dis_table[Short_Desc],'Short Desc Summary'!$B24,dis_table[Date],'Short Desc Summary'!E$2) +SUMIFS(cc_table[Amount],cc_table[Short_Desc],'Short Desc Summary'!$B24,cc_table[Date],'Short Desc Summary'!E$2) +SUMIFS(bb_table[Amount],bb_table[Short_Desc],'Short Desc Summary'!$B24,bb_table[Date],'Short Desc Summary'!E$2) -> 0 | F24: =SUMIFS(dis_table[Amount],dis_table[Short_Desc],'Short Desc Summary'!$B24,dis_table[Date],'Short Desc Summary'!F$2) +SUMIFS(cc_table[Amount],cc_table[Short_Desc],'Short Desc Summary'!$B24,cc_table[Date],'Short Desc Summary'!F$2) +SUMIFS(bb_table[Amount],bb_table[Short_Desc],'Short Desc Summary'!$B24,bb_table[Date],'Short Desc Summary'!F$2) -> 0 | G24: =SUMIFS(dis_table[Amount],dis_table[Short_Desc],'Short Desc Summary'!$B24,dis_table[Date],'Short Desc Summary'!G$2) +SUMIFS(cc_table[Amount],cc_table[Short_Desc],'Short Desc Summary'!$B24,cc_table[Date],'Short Desc Summary'!G$2) +SUMIFS(bb_table[Amount],bb_table[Short_Desc],'Short Desc Summary'!$B24,bb_table[Date],'Short Desc Summary'!G$2) -> 0 | H24: =SUMIFS(dis_table[Amount],dis_table[Short_Desc],'Short Desc Summary'!$B24,dis_table[Date],'Short Desc Summary'!H$2) +SUMIFS(cc_table[Amount],cc_table[Short_Desc],'Short Desc Summary'!$B24,cc_table[Date],'Short Desc Summary'!H$2) +SUMIFS(bb_table[Amount],bb_table[Short_Desc],'Short Desc Summary'!$B24,bb_table[Date],'Short Desc Summary'!H$2) -> 0 | I24: =SUMIFS(dis_table[Amount],dis_table[Short_Desc],'Short Desc Summary'!$B24,dis_table[Date],'Short Desc Summary'!I$2) +SUMIFS(cc_table[Amount],cc_table[Short_Desc],'Short Desc Summary'!$B24,cc_table[Date],'Short Desc Summary'!I$2) +SUMIFS(bb_table[Amount],bb_table[Short_Desc],'Short Desc Summary'!$B24,bb_table[Date],'Short Desc Summary'!I$2) -> 0 | J24: =SUMIFS(dis_table[Amount],dis_table[Short_Desc],'Short Desc Summary'!$B24,dis_table[Date],'Short Desc Summary'!J$2) +SUMIFS(cc_table[Amount],cc_table[Short_Desc],'Short Desc Summary'!$B24,cc_table[Date],'Short Desc Summary'!J$2) +SUMIFS(bb_table[Amount],bb_table[Short_Desc],'Short Desc Summary'!$B24,bb_table[Date],'Short Desc Summary'!J$2) -> 15.77
A25: =VLOOKUP(B25,dis_table[[#All],[Short_Desc]:[Category_2]],4,0) -> Personal_Spending | B25: conv_store | C25: =VLOOKUP(B25,dis_table[[#All],[Short_Desc]:[Reoccurring_Flag]],3,0) -> No | D25: =SUMIFS(dis_table[Amount],dis_table[Short_Desc],'Short Desc Summary'!$B25,dis_table[Date],'Short Desc Summary'!D$2) +SUMIFS(cc_table[Amount],cc_table[Short_Desc],'Short Desc Summary'!$B25,cc_table[Date],'Short Desc Summary'!D$2) +SUMIFS(bb_table[Amount],bb_table[Short_Desc],'Short Desc Summary'!$B25,bb_table[Date],'Short Desc Summary'!D$2) -> 33.1 | E25: =SUMIFS(dis_table[Amount],dis_table[Short_Desc],'Short Desc Summary'!$B25,dis_table[Date],'Short Desc Summary'!E$2) +SUMIFS(cc_table[Amount],cc_table[Short_Desc],'Short Desc Summary'!$B25,cc_table[Date],'Short Desc Summary'!E$2) +SUMIFS(bb_table[Amount],bb_table[Short_Desc],'Short Desc Summary'!$B25,bb_table[Date],'Short Desc Summary'!E$2) -> 0 | F25: =SUMIFS(dis_table[Amount],dis_table[Short_Desc],'Short Desc Summary'!$B25,dis_table[Date],'Short Desc Summary'!F$2) +SUMIFS(cc_table[Amount],cc_table[Short_Desc],'Short Desc Summary'!$B25,cc_table[Date],'Short Desc Summary'!F$2) +SUMIFS(bb_table[Amount],bb_table[Short_Desc],'Short Desc Summary'!$B25,bb_table[Date],'Short Desc Summary'!F$2) -> 64.73 | G25: =SUMIFS(dis_table[Amount],dis_table[Short_Desc],'Short Desc Summary'!$B25,dis_table[Date],'Short Desc Summary'!G$2) +SUMIFS(cc_table[Amount],cc_table[Short_Desc],'Short Desc Summary'!$B25,cc_table[Date],'Short Desc Summary'!G$2) +SUMIFS(bb_table[Amount],bb_table[Short_Desc],'Short Desc Summary'!$B25,bb_table[Date],'Short Desc Summary'!G$2) -> 24.02 | H25: =SUMIFS(dis_table[Amount],dis_table[Short_Desc],'Short Desc Summary'!$B25,dis_table[Date],'Short Desc Summary'!H$2) +SUMIFS(cc_table[Amount],cc_table[Short_Desc],'Short Desc Summary'!$B25,cc_table[Date],'Short Desc Summary'!H$2) +SUMIFS(bb_table[Amount],bb_table[Short_Desc],'Short Desc Summary'!$B25,bb_table[Date],'Short Desc Summary'!H$2) -> 17.52 | I25: =SUMIFS(dis_table[Amount],dis_table[Short_Desc],'Short Desc Summary'!$B25,dis_table[Date],'Short Desc Summary'!I$2) +SUMIFS(cc_table[Amount],cc_table[Short_Desc],'Short Desc Summary'!$B25,cc_table[Date],'Short Desc Summary'!I$2) +SUMIFS(bb_table[Amount],bb_table[Short_Desc],'Short Desc Summary'!$B25,bb_table[Date],'Short Desc Summary'!I$2) -> 137.36 | J25: =SUMIFS(dis_table[Amount],dis_table[Short_Desc],'Short Desc Summary'!$B25,dis_table[Date],'Short Desc Summary'!J$2) +SUMIFS(cc_table[Amount],cc_table[Short_Desc],'Short Desc Summary'!$B25,cc_table[Date],'Short Desc Summary'!J$2) +SUMIFS(bb_table[Amount],bb_table[Short_Desc],'Short Desc Summary'!$B25,bb_table[Date],'Short Desc Summary'!J$2) -> 55.35
A26: =VLOOKUP(B26,dis_table[[#All],[Short_Desc]:[Category_2]],4,0) -> Personal_Spending | B26: target | C26: =VLOOKUP(B26,dis_table[[#All],[Short_Desc]:[Reoccurring_Flag]],3,0) -> No | D26: =SUMIFS(dis_table[Amount],dis_table[Short_Desc],'Short Desc Summary'!$B26,dis_table[Date],'Short Desc Summary'!D$2) +SUMIFS(cc_table[Amount],cc_table[Short_Desc],'Short Desc Summary'!$B26,cc_table[Date],'Short Desc Summary'!D$2) +SUMIFS(bb_table[Amount],bb_table[Short_Desc],'Short Desc Summary'!$B26,bb_table[Date],'Short Desc Summary'!D$2) -> 153.88 | E26: =SUMIFS(dis_table[Amount],dis_table[Short_Desc],'Short Desc Summary'!$B26,dis_table[Date],'Short Desc Summary'!E$2) +SUMIFS(cc_table[Amount],cc_table[Short_Desc],'Short Desc Summary'!$B26,cc_table[Date],'Short Desc Summary'!E$2) +SUMIFS(bb_table[Amount],bb_table[Short_Desc],'Short Desc Summary'!$B26,bb_table[Date],'Short Desc Summary'!E$2) -> 0 | F26: =SUMIFS(dis_table[Amount],dis_table[Short_Desc],'Short Desc Summary'!$B26,dis_table[Date],'Short Desc Summary'!F$2) +SUMIFS(cc_table[Amount],cc_table[Short_Desc],'Short Desc Summary'!$B26,cc_table[Date],'Short Desc Summary'!F$2) +SUMIFS(bb_table[Amount],bb_table[Short_Desc],'Short Desc Summary'!$B26,bb_table[Date],'Short Desc Summary'!F$2) -> 0 | G26: =SUMIFS(dis_table[Amount],dis_table[Short_Desc],'Short Desc Summary'!$B26,dis_table[Date],'Short Desc Summary'!G$2) +SUMIFS(cc_table[Amount],cc_table[Short_Desc],'Short Desc Summary'!$B26,cc_table[Date],'Short Desc Summary'!G$2) +SUMIFS(bb_table[Amount],bb_table[Short_Desc],'Short Desc Summary'!$B26,bb_table[Date],'Short Desc Summary'!G$2) -> 47.34 | H26: =SUMIFS(dis_table[Amount],dis_table[Short_Desc],'Short Desc Summary'!$B26,dis_table[Date],'Short Desc Summary'!H$2) +SUMIFS(cc_table[Amount],cc_table[Short_Desc],'Short Desc Summary'!$B26,cc_table[Date],'Short Desc Summary'!H$2) +SUMIFS(bb_table[Amount],bb_table[Short_Desc],'Short Desc Summary'!$B26,bb_table[Date],'Short Desc Summary'!H$2) -> 211.57 | I26: =SUMIFS(dis_table[Amount],dis_table[Short_Desc],'Short Desc Summary'!$B26,dis_table[Date],'Short Desc Summary'!I$2) +SUMIFS(cc_table[Amount],cc_table[Short_Desc],'Short Desc Summary'!$B26,cc_table[Date],'Short Desc Summary'!I$2) +SUMIFS(bb_table[Amount],bb_table[Short_Desc],'Short Desc Summary'!$B26,bb_table[Date],'Short Desc Summary'!I$2) -> 0 | J26: =SUMIFS(dis_table[Amount],dis_table[Short_Desc],'Short Desc Summary'!$B26,dis_table[Date],'Short Desc Summary'!J$2) +SUMIFS(cc_table[Amount],cc_table[Short_Desc],'Short Desc Summary'!$B26,cc_table[Date],'Short Desc Summary'!J$2) +SUMIFS(bb_table[Amount],bb_table[Short_Desc],'Short Desc Summary'!$B26,bb_table[Date],'Short Desc Summary'!J$2) -> 29.06
A27: =VLOOKUP(B27,dis_table[[#All],[Short_Desc]:[Category_2]],4,0) -> Personal_Spending | B27: stretch_zone | C27: =VLOOKUP(B27,dis_table[[#All],[Short_Desc]:[Reoccurring_Flag]],3,0) -> Yes | D27: =SUMIFS(dis_table[Amount],dis_table[Short_Desc],'Short Desc Summary'!$B27,dis_table[Date],'Short Desc Summary'!D$2) +SUMIFS(cc_table[Amount],cc_table[Short_Desc],'Short Desc Summary'!$B27,cc_table[Date],'Short Desc Summary'!D$2) +SUMIFS(bb_table[Amount],bb_table[Short_Desc],'Short Desc Summary'!$B27,bb_table[Date],'Short Desc Summary'!D$2) -> 79 | E27: =SUMIFS(dis_table[Amount],dis_table[Short_Desc],'Short Desc Summary'!$B27,dis_table[Date],'Short Desc Summary'!E$2) +SUMIFS(cc_table[Amount],cc_table[Short_Desc],'Short Desc Summary'!$B27,cc_table[Date],'Short Desc Summary'!E$2) +SUMIFS(bb_table[Amount],bb_table[Short_Desc],'Short Desc Summary'!$B27,bb_table[Date],'Short Desc Summary'!E$2) -> 0 | F27: =SUMIFS(dis_table[Amount],dis_table[Short_Desc],'Short Desc Summary'!$B27,dis_table[Date],'Short Desc Summary'!F$2) +SUMIFS(cc_table[Amount],cc_table[Short_Desc],'Short Desc Summary'!$B27,cc_table[Date],'Short Desc Summary'!F$2) +SUMIFS(bb_table[Amount],bb_table[Short_Desc],'Short Desc Summary'!$B27,bb_table[Date],'Short Desc Summary'!F$2) -> 0 | G27: =SUMIFS(dis_table[Amount],dis_table[Short_Desc],'Short Desc Summary'!$B27,dis_table[Date],'Short Desc Summary'!G$2) +SUMIFS(cc_table[Amount],cc_table[Short_Desc],'Short Desc Summary'!$B27,cc_table[Date],'Short Desc Summary'!G$2) +SUMIFS(bb_table[Amount],bb_table[Short_Desc],'Short Desc Summary'!$B27,bb_table[Date],'Short Desc Summary'!G$2) -> 0 | H27: =SUMIFS(dis_table[Amount],dis_table[Short_Desc],'Short Desc Summary'!$B27,dis_table[Date],'Short Desc Summary'!H$2) +SUMIFS(cc_table[Amount],cc_table[Short_Desc],'Short Desc Summary'!$B27,cc_table[Date],'Short Desc Summary'!H$2) +SUMIFS(bb_table[Amount],bb_table[Short_Desc],'Short Desc Summary'!$B27,bb_table[Date],'Short Desc Summary'!H$2) -> 0 | I27: =SUMIFS(dis_table[Amount],dis_table[Short_Desc],'Short Desc Summary'!$B27,dis_table[Date],'Short Desc Summary'!I$2) +SUMIFS(cc_table[Amount],cc_table[Short_Desc],'Short Desc Summary'!$B27,cc_table[Date],'Short Desc Summary'!I$2) +SUMIFS(bb_table[Amount],bb_table[Short_Desc],'Short Desc Summary'!$B27,bb_table[Date],'Short Desc Summary'!I$2) -> 0 | J27: =SUMIFS(dis_table[Amount],dis_table[Short_Desc],'Short Desc Summary'!$B27,dis_table[Date],'Short Desc Summary'!J$2) +SUMIFS(cc_table[Amount],cc_table[Short_Desc],'Short Desc Summary'!$B27,cc_table[Date],'Short Desc Summary'!J$2) +SUMIFS(bb_table[Amount],bb_table[Short_Desc],'Short Desc Summary'!$B27,bb_table[Date],'Short Desc Summary'!J$2) -> 0
A28: =VLOOKUP(B28,dis_table[[#All],[Short_Desc]:[Category_2]],4,0) -> Personal_Spending | B28: staples | C28: =VLOOKUP(B28,dis_table[[#All],[Short_Desc]:[Reoccurring_Flag]],3,0) -> No | D28: =SUMIFS(dis_table[Amount],dis_table[Short_Desc],'Short Desc Summary'!$B28,dis_table[Date],'Short Desc Summary'!D$2) +SUMIFS(cc_table[Amount],cc_table[Short_Desc],'Short Desc Summary'!$B28,cc_table[Date],'Short Desc Summary'!D$2) +SUMIFS(bb_table[Amount],bb_table[Short_Desc],'Short Desc Summary'!$B28,bb_table[Date],'Short Desc Summary'!D$2) -> 20.72 | E28: =SUMIFS(dis_table[Amount],dis_table[Short_Desc],'Short Desc Summary'!$B28,dis_table[Date],'Short Desc Summary'!E$2) +SUMIFS(cc_table[Amount],cc_table[Short_Desc],'Short Desc Summary'!$B28,cc_table[Date],'Short Desc Summary'!E$2) +SUMIFS(bb_table[Amount],bb_table[Short_Desc],'Short Desc Summary'!$B28,bb_table[Date],'Short Desc Summary'!E$2) -> 0 | F28: =SUMIFS(dis_table[Amount],dis_table[Short_Desc],'Short Desc Summary'!$B28,dis_table[Date],'Short Desc Summary'!F$2) +SUMIFS(cc_table[Amount],cc_table[Short_Desc],'Short Desc Summary'!$B28,cc_table[Date],'Short Desc Summary'!F$2) +SUMIFS(bb_table[Amount],bb_table[Short_Desc],'Short Desc Summary'!$B28,bb_table[Date],'Short Desc Summary'!F$2) -> 17.59 | G28: =SUMIFS(dis_table[Amount],dis_table[Short_Desc],'Short Desc Summary'!$B28,dis_table[Date],'Short Desc Summary'!G$2) +SUMIFS(cc_table[Amount],cc_table[Short_Desc],'Short Desc Summary'!$B28,cc_table[Date],'Short Desc Summary'!G$2) +SUMIFS(bb_table[Amount],bb_table[Short_Desc],'Short Desc Summary'!$B28,bb_table[Date],'Short Desc Summary'!G$2) -> 0 | H28: =SUMIFS(dis_table[Amount],dis_table[Short_Desc],'Short Desc Summary'!$B28,dis_table[Date],'Short Desc Summary'!H$2) +SUMIFS(cc_table[Amount],cc_table[Short_Desc],'Short Desc Summary'!$B28,cc_table[Date],'Short Desc Summary'!H$2) +SUMIFS(bb_table[Amount],bb_table[Short_Desc],'Short Desc Summary'!$B28,bb_table[Date],'Short Desc Summary'!H$2) -> 0 | I28: =SUMIFS(dis_table[Amount],dis_table[Short_Desc],'Short Desc Summary'!$B28,dis_table[Date],'Short Desc Summary'!I$2) +SUMIFS(cc_table[Amount],cc_table[Short_Desc],'Short Desc Summary'!$B28,cc_table[Date],'Short Desc Summary'!I$2) +SUMIFS(bb_table[Amount],bb_table[Short_Desc],'Short Desc Summary'!$B28,bb_table[Date],'Short Desc Summary'!I$2) -> 0 | J28: =SUMIFS(dis_table[Amount],dis_table[Short_Desc],'Short Desc Summary'!$B28,dis_table[Date],'Short Desc Summary'!J$2) +SUMIFS(cc_table[Amount],cc_table[Short_Desc],'Short Desc Summary'!$B28,cc_table[Date],'Short Desc Summary'!J$2) +SUMIFS(bb_table[Amount],bb_table[Short_Desc],'Short Desc Summary'!$B28,bb_table[Date],'Short Desc Summary'!J$2) -> 0
