Workbook
Name Categories: OFFSET(Categories_deprecated_2jdI!$J$7,0,0,COUNTIF(Categories_deprecated_2jdI!$J$7:$J$44,"<>"&"--"),1)
Name CategoryIdentifiers: Categories!$B$8:$B$100
Name CategoryNames: Categories!$C$8:$C$100
Name FrequencyKey: RecurringExpenses!$X$8:$X$11
Name FrequencyValue: RecurringExpenses!$Y$8:$Y$11
Name HiddenCategoriesCategoryNames: _xlfn.ANCHORARRAY(HiddenCategories!$B$2)
Name HiddenCategoriesSubcategoryNames: HiddenCategories!$C$2:$C$100
Name HiddenCategoriesSubcategoryNamesRows: HiddenCategories!$C$2:$CX$100
Name Months: OFFSET(Snapshot!$V$7,0,0,COUNTIF(Snapshot!$V$7:$V$200,"<>"&"--"),1)
Name snapshot_month: Snapshot!$Q$4
Name SubcategoryNames: Categories!$I$8:$I$100
Name user_custom_categories: Categories_deprecated_2jdI!$C$25:$E$44

Sheet Transactions
B2: Transactions
B3: Transactions from your added accounts are automatically imported here. Click Update in the task pane to import more transactions. Edit the Merchant and Category columns to better reflect where and how you spend your money.
B6: Date | C6: Merchant | D6: Category | E6: Subcategory | F6: Amount $ | G6: Account | H6: Account Number | I6: Institution | J6: Transaction_ID | K6: Account_ID | L6: Institution_ID | M6: Category Type | N6: Date_Day | O6: Date_Month | P6: Date_Year | Q6: Beginning of Week | R6: Month
B7: 44302 | C7: Atm Cash Withdrawal Aspen | D7: Transfer | F7: -200 | J7: 985572e216794b238fa7213245412ee0 | K7: 0ced1dbbb4a747578f3268aacbdce68e | L7: 0223204f73754797a10ae9c56a61ed0d | M7: {=IFERROR(INDEX(CategoriesTable[Category type],MATCH(Table1[[#This Row],[Category]],CategoriesTable[Category name],0),0),"")} -> Transfer | N7: 16 | O7: =MONTH(Table1[[#This Row],[Date]]) -> 4 | P7: 2021 | Q7: =IF(ISBLANK(Table1[[#This Row],[Date]]),"",Table1[[#This Row],[Date]]-WEEKDAY(Table1[[#This Row],[Date]],2)+1) -> 44298 | R7: =IF(ISBLANK(Table1[[#This Row],[Date]]),"",DATE(Table1[[#This Row],[Date_Year]],Table1[[#This Row],[Date_Month]],1)) -> 44287
B8: 44301 | C8: Electronic Debit Transamerica Ins | D8: Bills/Utilities | F8: -10.9 | J8: 8f8a985455a44a4ea7676fcc75a84c51 | K8: 0ced1dbbb4a747578f3268aacbdce68e | L8: 0223204f73754797a10ae9c56a61ed0d | M8: {=IFERROR(INDEX(CategoriesTable[Category type],MATCH(Table1[[#This Row],[Category]],CategoriesTable[Category name],0),0),"")} -> Expense | N8: 15 | O8: =MONTH(Table1[[#This Row],[Date]]) -> 4 | P8: 2021 | Q8: =IF(ISBLANK(Table1[[#This Row],[Date]]),"",Table1[[#This Row],[Date]]-WEEKDAY(Table1[[#This Row],[Date]],2)+1) -> 44298 | R8: =IF(ISBLANK(Table1[[#This Row],[Date]]),"",DATE(Table1[[#This Row],[Date_Year]],Table1[[#This Row],[Date_Month]],1)) -> 44287
B9: 44294 | C9: XBOX Live | D9: Entertainment | F9: -10.59 | J9: 5eba4e9093fe4a9f99d838f562920cbd | K9: 0ced1dbbb4a747578f3268aacbdce68e | L9: 0223204f73754797a10ae9c56a61ed0d | M9: {=IFERROR(INDEX(CategoriesTable[Category type],MATCH(Table1[[#This Row],[Category]],CategoriesTable[Category name],0),0),"")} -> Expense | N9: 8 | O9: =MONTH(Table1[[#This Row],[Date]]) -> 4 | P9: 2021 | Q9: =IF(ISBLANK(Table1[[#This Row],[Date]]),"",Table1[[#This Row],[Date]]-WEEKDAY(Table1[[#This Row],[Date]],2)+1) -> 44291 | R9: =IF(ISBLANK(Table1[[#This Row],[Date]]),"",DATE(Table1[[#This Row],[Date_Year]],Table1[[#This Row],[Date_Month]],1)) -> 44287
B10: 44292 | C10: Verizon | D10: Bills/Utilities | F10: -326.03 | J10: ee49fc1d1a9243b58afc9b778fb8afac | K10: 0ced1dbbb4a747578f3268aacbdce68e | L10: 0223204f73754797a10ae9c56a61ed0d | M10: {=IFERROR(INDEX(CategoriesTable[Category type],MATCH(Table1[[#This Row],[Category]],CategoriesTable[Category name],0),0),"")} -> Expense | N10: 6 | O10: =MONTH(Table1[[#This Row],[Date]]) -> 4 | P10: 2021 | Q10: =IF(ISBLANK(Table1[[#This Row],[Date]]),"",Table1[[#This Row],[Date]]-WEEKDAY(Table1[[#This Row],[Date]],2)+1) -> 44291 | R10: =IF(ISBLANK(Table1[[#This Row],[Date]]),"",DATE(Table1[[#This Row],[Date_Year]],Table1[[#This Row],[Date_Month]],1)) -> 44287
B11: 44291 | C11: Atm Cash Withdrawal Aspen | D11: Transfer | F11: -160 | J11: 539dad513aac4b72a195f704cd2d6ca4 | K11: 0ced1dbbb4a747578f3268aacbdce68e | L11: 0223204f73754797a10ae9c56a61ed0d | M11: {=IFERROR(INDEX(CategoriesTable[Category type],MATCH(Table1[[#This Row],[Category]],CategoriesTable[Category name],0),0),"")} -> Transfer | N11: 5 | O11: =MONTH(Table1[[#This Row],[Date]]) -> 4 | P11: 2021 | Q11: =IF(ISBLANK(Table1[[#This Row],[Date]]),"",Table1[[#This Row],[Date]]-WEEKDAY(Table1[[#This Row],[Date]],2)+1) -> 44291 | R11: =IF(ISBLANK(Table1[[#This Row],[Date]]),"",DATE(Table1[[#This Row],[Date_Year]],Table1[[#This Row],[Date_Month]],1)) -> 44287
B12: 44291 | C12: Netflix | D12: Bills/Utilities | F12: -19.07 | J12: ede53e3ac5064dc1a5c3dad531e6647b | K12: 0ced1dbbb4a747578f3268aacbdce68e | L12: 0223204f73754797a10ae9c56a61ed0d | M12: {=IFERROR(INDEX(CategoriesTable[Category type],MATCH(Table1[[#This Row],[Category]],CategoriesTable[Category name],0),0),"")} -> Expense | N12: 5 | O12: =MONTH(Table1[[#This Row],[Date]]) -> 4 | P12: 2021 | Q12: =IF(ISBLANK(Table1[[#This Row],[Date]]),"",Table1[[#This Row],[Date]]-WEEKDAY(Table1[[#This Row],[Date]],2)+1) -> 44291 | R12: =IF(ISBLANK(Table1[[#This Row],[Date]]),"",DATE(Table1[[#This Row],[Date_Year]],Table1[[#This Row],[Date_Month]],1)) -> 44287
B13: 44289 | C13: Cinnabon | D13: Restaurants/Dining | F13: -25.97 | J13: 4dd1e4b6530548948e5422244c00fed8 | K13: 0ced1dbbb4a747578f3268aacbdce68e | L13: 0223204f73754797a10ae9c56a61ed0d | M13: {=IFERROR(INDEX(CategoriesTable[Category type],MATCH(Table1[[#This Row],[Category]],CategoriesTable[Category name],0),0),"")} -> Expense | N13: 3 | O13: =MONTH(Table1[[#This Row],[Date]]) -> 4 | P13: 2021 | Q13: =IF(ISBLANK(Table1[[#This Row],[Date]]),"",Table1[[#This Row],[Date]]-WEEKDAY(Table1[[#This Row],[Date]],2)+1) -> 44284 | R13: =IF(ISBLANK(Table1[[#This Row],[Date]]),"",DATE(Table1[[#This Row],[Date_Year]],Table1[[#This Row],[Date_Month]],1)) -> 44287
B14: 44288 | C14: CVS Care Pass | D14: Shopping | F14: -5.3 | J14: 6a91c9cd36f142ed96634e1f701a58f6 | K14: 0ced1dbbb4a747578f3268aacbdce68e | L14: 0223204f73754797a10ae9c56a61ed0d | M14: {=IFERROR(INDEX(CategoriesTable[Category type],MATCH(Table1[[#This Row],[Category]],CategoriesTable[Category name],0),0),"")} -> Expense | N14: 2 | O14: =MONTH(Table1[[#This Row],[Date]]) -> 4 | P14: 2021 | Q14: =IF(ISBLANK(Table1[[#This Row],[Date]]),"",Table1[[#This Row],[Date]]-WEEKDAY(Table1[[#This Row],[Date]],2)+1) -> 44284 | R14: =IF(ISBLANK(Table1[[#This Row],[Date]]),"",DATE(Table1[[#This Row],[Date_Year]],Table1[[#This Row],[Date_Month]],1)) -> 44287
B15: 44288 | C15: 7 Eleven | D15: Restaurants/Dining | F15: -16.76 | J15: fd7d2fd0c9ca4bd9ab4782bc4771e628 | K15: 0ced1dbbb4a747578f3268aacbdce68e | L15: 0223204f73754797a10ae9c56a61ed0d | M15: {=IFERROR(INDEX(CategoriesTable[Category type],MATCH(Table1[[#This Row],[Category]],CategoriesTable[Category name],0),0),"")} -> Expense | N15: 2 | O15: =MONTH(Table1[[#This Row],[Date]]) -> 4 | P15: 2021 | Q15: =IF(ISBLANK(Table1[[#This Row],[Date]]),"",Table1[[#This Row],[Date]]-WEEKDAY(Table1[[#This Row],[Date]],2)+1) -> 44284 | R15: =IF(ISBLANK(Table1[[#This Row],[Date]]),"",DATE(Table1[[#This Row],[Date_Year]],Table1[[#This Row],[Date_Month]],1)) -> 44287
B16: 44288 | C16: Point Of Sale Debit | D16: Auto/Transport | F16: -2500 | J16: 3821a77aaba34a279fe744b4121cce26 | K16: 0ced1dbbb4a747578f3268aacbdce68e | L16: 0223204f73754797a10ae9c56a61ed0d | M16: {=IFERROR(INDEX(CategoriesTable[Category type],MATCH(Table1[[#This Row],[Category]],CategoriesTable[Category name],0),0),"")} -> Expense | N16: 2 | O16: =MONTH(Table1[[#This Row],[Date]]) -> 4 | P16: 2021 | Q16: =IF(ISBLANK(Table1[[#This Row],[Date]]),"",Table1[[#This Row],[Date]]-WEEKDAY(Table1[[#This Row],[Date]],2)+1) -> 44284 | R16: =IF(ISBLANK(Table1[[#This Row],[Date]]),"",DATE(Table1[[#This Row],[Date_Year]],Table1[[#This Row],[Date_Month]],1)) -> 44287
B17: 44287 | C17: Amercican Home Shield | D17: Bills/Utilities | F17: -54.99 | J17: 7b73ea380fe54ba8b6cf0298c5a4e78a | K17: 0ced1dbbb4a747578f3268aacbdce68e | L17: 0223204f73754797a10ae9c56a61ed0d | M17: {=IFERROR(INDEX(CategoriesTable[Category type],MATCH(Table1[[#This Row],[Category]],CategoriesTable[Category name],0),0),"")} -> Expense | N17: 1 | O17: =MONTH(Table1[[#This Row],[Date]]) -> 4 | P17: 2021 | Q17: =IF(ISBLANK(Table1[[#This Row],[Date]]),"",Table1[[#This Row],[Date]]-WEEKDAY(Table1[[#This Row],[Date]],2)+1) -> 44284 | R17: =IF(ISBLANK(Table1[[#This Row],[Date]]),"",DATE(Table1[[#This Row],[Date_Year]],Table1[[#This Row],[Date_Month]],1)) -> 44287
B18: 44287 | C18: Electronic Credit TreasXxciv Serv | D18: Income | F18: 4433.04 | J18: 54e8ad2e0b5345eb9ae1a55dd18e6af1 | K18: 0ced1dbbb4a747578f3268aacbdce68e | L18: 0223204f73754797a10ae9c56a61ed0d | M18: {=IFERROR(INDEX(CategoriesTable[Category type],MATCH(Table1[[#This Row],[Category]],CategoriesTable[Category name],0),0),"")} -> Income | N18: 1 | O18: =MONTH(Table1[[#This Row],[Date]]) -> 4 | P18: 2021 | Q18: =IF(ISBLANK(Table1[[#This Row],[Date]]),"",Table1[[#This Row],[Date]]-WEEKDAY(Table1[[#This Row],[Date]],2)+1) -> 44284 | R18: =IF(ISBLANK(Table1[[#This Row],[Date]]),"",DATE(Table1[[#This Row],[Date_Year]],Table1[[#This Row],[Date_Month]],1)) -> 44287
... B1250: 43763 | C1250: Check Card Purchase Subway | D1250: Restaurants/Dining | F1250: -16.39 | J1250: 73ee7a71ccf94f14b5b1fcbc03c88b9a | K1250: 0ced1dbbb4a747578f3268aacbdce68e | L1250: 0223204f73754797a10ae9c56a61ed0d | M1250: {=IFERROR(INDEX(CategoriesTable[Category type],MATCH(Table1[[#This Row],[Category]],CategoriesTable[Category name],0),0),"")} -> Expense | N1250: 25 | O1250: =MONTH(Table1[[#This Row],[Date]]) -> 10 | P1250: 2019 | Q1250: =IF(ISBLANK(Table1[[#This Row],[Date]]),"",Table1[[#This Row],[Date]]-WEEKDAY(Table1[[#This Row],[Date]],2)+1) -> 43759 | R1250: =IF(ISBLANK(Table1[[#This Row],[Date]]),"",DATE(Table1[[#This Row],[Date_Year]],Table1[[#This Row],[Date_Month]],1)) -> 43739
M1251: {=IFERROR(INDEX(CategoriesTable[Category type],MATCH(Table1[[#This Row],[Category]],CategoriesTable[Category name],0),0),"")} | N1251: =DAY(Table1[[#This Row],[Date]]) -> 0 | O1251: =MONTH(Table1[[#This Row],[Date]]) -> 1 | P1251: =YEAR(Table1[[#This Row],[Date]]) -> 1900 | Q1251: =IF(ISBLANK(Table1[[#This Row],[Date]]),"",Table1[[#This Row],[Date]]-WEEKDAY(Table1[[#This Row],[Date]],2)+1) | R1251: =IF(ISBLANK(Table1[[#This Row],[Date]]),"",DATE(Table1[[#This Row],[Date_Year]],Table1[[#This Row],[Date_Month]],1))
L1252: {=IFERROR(INDEX(CategoriesTableLegacy[Category Type],MATCH(Table1[[#This Row],[Category]],CategoriesTableLegacy[Category Name],0),0),"")}

Sheet Spotify
A1: Spotify
A2: 44281 | B2: Spotify | C2: Bills/Utilities | E2: -10.59
A3: 44253 | B3: Spotify | C3: Bills/Utilities | E3: -9.99
A4: 44222 | B4: Spotify | C4: Bills/Utilities | E4: -9.99
A5: 44191 | B5: Spotify | C5: Bills/Utilities | E5: -9.99
A6: 44161 | B6: Spotify | C6: Bills/Utilities | E6: -9.99
A7: 44130 | B7: Spotify | C7: Bills/Utilities | E7: -9.99
A8: 44100 | B8: Spotify | C8: Bills/Utilities | E8: -9.99
A9: 44069 | B9: Spotify | C9: Bills/Utilities | E9: -9.99
A10: 44039 | B10: Spotify | C10: Fees/Charges | E10: -36
A11: 44008 | B11: Spotify | C11: Bills/Utilities | E11: -9.99
A12: 43977 | B12: Spotify | C12: Bills/Utilities | E12: -9.99
A13: 43947 | B13: Spotify | C13: Bills/Utilities | E13: -9.99
A14: 43916 | B14: Spotify | C14: Bills/Utilities | E14: -9.99

Sheet Verizon
A2: 44262 | B2: Verizon Wireless | C2: Bills/Utilities | E2: -123.2
A3: 44233 | B3: Verizon Wireless | C3: Bills/Utilities | E3: -123.2
A4: 44198 | B4: Verizon Wireless | C4: Bills/Utilities | E4: -123.02
A5: 44171 | B5: Verizon Wireless | C5: Bills/Utilities | E5: -123.02
A6: 44143 | B6: Verizon Wireless | C6: Bills/Utilities | E6: -123.02

Sheet Amazon Prime
A1: Amazon Prime
A2: 44255 | B2: Amazon Prime | C2: Shopping | E2: -12.99 | G2: Username:
A3: 44227 | B3: Amazon Prime | C3: Shopping | E3: -12.99 | G3: Password:
A4: 44196 | B4: Amazon Prime | C4: Shopping | E4: -12.99
A5: 44165 | B5: Amazon Prime | C5: Shopping | E5: -12.99
A6: 44135 | B6: Amazon Prime | C6: Shopping | E6: -12.99
A7: 44104 | B7: Amazon Prime | C7: Shopping | E7: -12.99
A8: 44074 | B8: Amazon Prime | C8: Shopping | E8: -12.99
A9: 44046 | B9: Amazon Prime | C9: Shopping | E9: -12.99
A10: 44012 | B10: Amazon Prime | C10: Shopping | E10: -12.99
A11: 43982 | B11: Amazon Prime | C11: Shopping | E11: -12.99
A12: 43951 | B12: Amazon Prime | C12: Shopping | E12: -12.99
A13: 43921 | B13: Amazon Prime | C13: Shopping | E13: -12.99
A14: 43890 | B14: Amazon Prime | C14: Shopping | E14: -12.99
A15: 43861 | B15: Amazon Prime | C15: Shopping | E15: -12.99
... A18: 43769 | B18: Amazon Prime | C18: Shopping | E18: -12.99

Sheet Shen Life
M1: Shen Life Insurance
M2: 44279 | N2: Electronic Debit Shen Life | O2: Bills/Utilities | Q2: -40.28
M3: 44251 | N3: Electronic Debit Shen Life | O3: Bills/Utilities | Q3: -40.28
M4: 44218 | N4: Electronic Debit Shen Life | O4: Bills/Utilities | Q4: -40.28
M5: 44188 | N5: Electronic Debit Shen Life | O5: Bills/Utilities | Q5: -40.28
M6: 44159 | N6: Electronic Debit Shen Life | O6: Bills/Utilities | Q6: -40.28
M7: 44126 | N7: Electronic Debit Shen Life | O7: Bills/Utilities | Q7: -40.28
M8: 44097 | N8: Electronic Debit Shen Life | O8: Bills/Utilities | Q8: -40.28
M9: 44067 | N9: Electronic Debit Shen Life | O9: Bills/Utilities | Q9: -40.28
M10: 44034 | N10: Electronic Debit Shen Life | O10: Bills/Utilities | Q10: -40.28
M11: 44006 | N11: Electronic Debit Shen Life | O11: Bills/Utilities | Q11: -40.28
M12: 43973 | N12: Electronic Debit Shen Life | O12: Bills/Utilities | Q12: -40.28
M13: 43943 | N13: Electronic Debit Shen Life | O13: Bills/Utilities | Q13: -40.28
... M18: 43791 | N18: Electronic Debit Shen Life | O18: Bills/Utilities | Q18: -40.28

Sheet Paymentus
K1: 44275 | L1: Check Card Purchase Paymentus | M1: Professional Services | O1: -3.95
K2: 44251 | L2: Check Card Purchase Paymentus | M2: Professional Services | O2: -3.95
K3: 44175 | L3: Check Card Purchase Paymentus | M3: Professional Services | O3: -3.95
K4: 44159 | L4: Check Card Purchase Paymentus | M4: Professional Services | O4: -3.95

Sheet TransAmerica
A1: TransAmerica Life Insurance
A2: 44301 | B2: Electronic Debit Transamerica Ins | C2: Bills/Utilities | E2: -10.9 | F2: =YEAR(A2) -> 2021 | I2: 2019 | J2: =SUMIFS(E:E,F:F,I2) -> -975.8
A3: 44284 | B3: Electronic Debit Tran Life | C3: Bills/Utilities | E3: -344.72 | F3: =YEAR(A3) -> 2021 | I3: 2020 | J3: =SUMIFS(E:E,F:F,I3) -> -3762.4
A4: 44272 | B4: Electronic Debit Transamerica Ins | C4: Bills/Utilities | E4: -10.9 | F4: =YEAR(A4) -> 2021 | I4: 2021 | J4: =SUMIFS(E:E,F:F,I4) -> -1077.76
A5: 44256 | B5: Electronic Debit Tran Life | C5: Bills/Utilities | E5: -344.72 | F5: =YEAR(A5) -> 2021
A6: 44245 | B6: Electronic Debit Transamerica Ins | C6: Bills/Utilities | E6: -10.9 | F6: =YEAR(A6) -> 2021
A7: 44223 | B7: Electronic Debit Tran Life | C7: Bills/Utilities | E7: -344.72 | F7: =YEAR(A7) -> 2021
A8: 44211 | B8: Electronic Debit Transamerica Ins | C8: Bills/Utilities | E8: -10.9 | F8: =YEAR(A8) -> 2021
A9: 44195 | B9: Electronic Debit Tran Life | C9: Bills/Utilities | E9: -344.72 | F9: =YEAR(A9) -> 2020
A10: 44181 | B10: Electronic Debit Transamerica Ins | C10: Bills/Utilities | E10: -10.9 | F10: =YEAR(A10) -> 2020
A11: 44165 | B11: Electronic Debit Tran Life | C11: Bills/Utilities | E11: -344.72 | F11: =YEAR(A11) -> 2020
A12: 44153 | B12: Electronic Debit Transamerica Ins | C12: Bills/Utilities | E12: -10.9 | F12: =YEAR(A12) -> 2020
A13: 44132 | B13: Electronic Debit Tran Life | C13: Bills/Utilities | E13: -344.72 | F13: =YEAR(A13) -> 2020
A14: 44119 | B14: Electronic Debit Transamerica Ins | C14: Bills/Utilities | E14: -10.9 | F14: =YEAR(A14) -> 2020
A15: 44103 | B15: Electronic Debit Transamerica Tpl | C15: Bills/Utilities | E15: -344.72 | F15: =YEAR(A15) -> 2020
A16: 44090 | B16: Electronic Debit Transamerica Ins | C16: Bills/Utilities | E16: -10.9 | F16: =YEAR(A16) -> 2020
... A36: 43767 | B36: Electronic Debit Transamerica Tpl | C36: Bills/Utilities | E36: -318 | F36: =YEAR(A36) -> 2019

Sheet RecurringExpenses
C2: Recurring Expenses
C3: Money in Excel automatically identifies which transactions are recurring. If any recurring expenses are missing, input them into empty rows. Our system will use 1) Merchant, 2) Amount $, 3) and Frequency to search for these transactions in the future and monitor prices.
C7: Most Costly Recurring Expenses | H7: Recurring Expenses Details | X7: FREQUENCY KEY
C8: Merchant | D8: Annual Cost | G8: Id | H8: Merchant | I8: Amount $ | J8: Frequency | K8: YTD/Annual Cost | L8: Price Change $ | M8: Last Date Paid | N8: Upcoming Pay Date | O8: Sum from Trans | P8: Upcoming Days | Q8: Rank_Days | R8: Rank_Annual | S8: User Added | T8: Column1 | X8: Weekly | Y8: 52
C9: {=IFERROR(INDEX(RecurringExp[Merchant],MATCH($B19,RecurringExp[Rank_Annual],0),0),"")} -> Verizon | D9: {=IFERROR(INDEX(RecurringExp[YTD/Annual Cost],MATCH($B19,RecurringExp[Rank_Annual],0),0),NA())} -> 1248.02 | G9: 10356f54718044df8b62308dc482e640 | H9: Electronic Debit Tran Life | I9: 344.72 | J9: Monthly | K9: =IFERROR(IF(ISBLANK(RecurringExp[[#This Row],[Amount $]]),"",IF(RecurringExp[[#This Row],[Sum from Trans]]<>"",RecurringExp[[#This Row],[Sum from Trans]],RecurringExp[[#This Row],[Amount $]]*_xlfn.XLOOKUP(RecurringExp[[#This Row],[Frequency]],FrequencyKey,FrequencyValue))),"") -> 1034.16 | L9: 0 | M9: 44284 | N9: 44309 | O9: =IF(SUMIFS(Table1[Amount $],Table1[Merchant],RecurringExp[[#This Row],[Merchant]],Table1[Date_Year],YEAR(TODAY()))*-1=0,"",SUMIFS(Table1[Amount $],Table1[Merchant],RecurringExp[[#This Row],[Merchant]],Table1[Date_Year],YEAR(TODAY()))*-1) -> 1034.16 | P9: =IF(ISBLANK(RecurringExp[[#This Row],[Upcoming Pay Date]]),"",IF(RecurringExp[[#This Row],[Upcoming Pay Date]]-TODAY()<0,"",IF(RecurringExp[[#This Row],[Upcoming Pay Date]]-TODAY()>30,"",RecurringExp[[#This Row],[Upcoming Pay Date]]-TODAY()))) -> 6 | Q9: =IFERROR(RANK(RecurringExp[[#This Row],[Upcoming Days]],RecurringExp[Upcoming Days],1)+COUNTIF(RecurringExp[[#This Row],[Upcoming Days]]:RecurringExp[[#This Row],[Upcoming Days]],RecurringExp[[#This Row],[Upcoming Days]])-1,"") -> 3 | R9: =IFERROR(RANK(RecurringExp[[#This Row],[YTD/Annual Cost]],RecurringExp[YTD/Annual Cost],0)+COUNTIF(RecurringExp[[#This Row],[YTD/Annual Cost]]:RecurringExp[[#This Row],[YTD/Annual Cost]],RecurringExp[[#This Row],[YTD/Annual Cost]])-1,"") -> 2 | S9: FALSE | X9: Monthly | Y9: 12
C10: {=IFERROR(INDEX(RecurringExp[Merchant],MATCH($B20,RecurringExp[Rank_Annual],0),0),"")} -> Electronic Debit Tran Life | D10: {=IFERROR(INDEX(RecurringExp[YTD/Annual Cost],MATCH($B20,RecurringExp[Rank_Annual],0),0),NA())} -> 1034.16 | G10: f5004c8526f74da69afb1ec3bc1654f3 | H10: Check Card Purchase Credit | I10: 226 | J10: Monthly | K10: =IFERROR(IF(ISBLANK(RecurringExp[[#This Row],[Amount $]]),"",IF(RecurringExp[[#This Row],[Sum from Trans]]<>"",RecurringExp[[#This Row],[Sum from Trans]],RecurringExp[[#This Row],[Amount $]]*_xlfn.XLOOKUP(RecurringExp[[#This Row],[Frequency]],FrequencyKey,FrequencyValue))),"") -> 452 | L10: -0.5 | M10: 44275 | N10: 44304 | O10: =IF(SUMIFS(Table1[Amount $],Table1[Merchant],RecurringExp[[#This Row],[Merchant]],Table1[Date_Year],YEAR(TODAY()))*-1=0,"",SUMIFS(Table1[Amount $],Table1[Merchant],RecurringExp[[#This Row],[Merchant]],Table1[Date_Year],YEAR(TODAY()))*-1) -> 452 | P10: =IF(ISBLANK(RecurringExp[[#This Row],[Upcoming Pay Date]]),"",IF(RecurringExp[[#This Row],[Upcoming Pay Date]]-TODAY()<0,"",IF(RecurringExp[[#This Row],[Upcoming Pay Date]]-TODAY()>30,"",RecurringExp[[#This Row],[Upcoming Pay Date]]-TODAY()))) -> 1 | Q10: =IFERROR(RANK(RecurringExp[[#This Row],[Upcoming Days]],RecurringExp[Upcoming Days],1)+COUNTIF(RecurringExp[[#This Row],[Upcoming Days]]:RecurringExp[[#This Row],[Upcoming Days]],RecurringExp[[#This Row],[Upcoming Days]])-1,"") -> 1 | R10: =IFERROR(RANK(RecurringExp[[#This Row],[YTD/Annual Cost]],RecurringExp[YTD/Annual Cost],0)+COUNTIF(RecurringExp[[#This Row],[YTD/Annual Cost]]:RecurringExp[[#This Row],[YTD/Annual Cost]],RecurringExp[[#This Row],[YTD/Annual Cost]])-1,"") -> 4 | S10: FALSE | X10: Quarterly | Y10: 4
C11: {=IFERROR(INDEX(RecurringExp[Merchant],MATCH($B21,RecurringExp[Rank_Annual],0),0),"")} -> Pepco | D11: {=IFERROR(INDEX(RecurringExp[YTD/Annual Cost],MATCH($B21,RecurringExp[Rank_Annual],0),0),NA())} -> 473.95 | G11: f95ec81a473c48febed64722b3cd4567 | H11: Electronic Debit Shen Life | I11: 40.28 | J11: Monthly | K11: =IFERROR(IF(ISBLANK(RecurringExp[[#This Row],[Amount $]]),"",IF(RecurringExp[[#This Row],[Sum from Trans]]<>"",RecurringExp[[#This Row],[Sum from Trans]],RecurringExp[[#This Row],[Amount $]]*_xlfn.XLOOKUP(RecurringExp[[#This Row],[Frequency]],FrequencyKey,FrequencyValue))),"") -> 120.84 | L11: 0 | M11: 44279 | N11: 44307 | O11: =IF(SUMIFS(Table1[Amount $],Table1[Merchant],RecurringExp[[#This Row],[Merchant]],Table1[Date_Year],YEAR(TODAY()))*-1=0,"",SUMIFS(Table1[Amount $],Table1[Merchant],RecurringExp[[#This Row],[Merchant]],Table1[Date_Year],YEAR(TODAY()))*-1) -> 120.84 | P11: =IF(ISBLANK(RecurringExp[[#This Row],[Upcoming Pay Date]]),"",IF(RecurringExp[[#This Row],[Upcoming Pay Date]]-TODAY()<0,"",IF(RecurringExp[[#This Row],[Upcoming Pay Date]]-TODAY()>30,"",RecurringExp[[#This Row],[Upcoming Pay Date]]-TODAY()))) -> 4 | Q11: =IFERROR(RANK(RecurringExp[[#This Row],[Upcoming Days]],RecurringExp[Upcoming Days],1)+COUNTIF(RecurringExp[[#This Row],[Upcoming Days]]:RecurringExp[[#This Row],[Upcoming Days]],RecurringExp[[#This Row],[Upcoming Days]])-1,"") -> 2 | R11: =IFERROR(RANK(RecurringExp[[#This Row],[YTD/Annual Cost]],RecurringExp[YTD/Annual Cost],0)+COUNTIF(RecurringExp[[#This Row],[YTD/Annual Cost]]:RecurringExp[[#This Row],[YTD/Annual Cost]],RecurringExp[[#This Row],[YTD/Annual Cost]])-1,"") -> 7 | S11: FALSE | X11: Annual | Y11: 1
C12: {=IFERROR(INDEX(RecurringExp[Merchant],MATCH($B22,RecurringExp[Rank_Annual],0),0),"")} -> Check Card Purchase Credit | D12: {=IFERROR(INDEX(RecurringExp[YTD/Annual Cost],MATCH($B22,RecurringExp[Rank_Annual],0),0),NA())} -> 452 | G12: 97ac467f47ed4d2587fe9463fa2b1d99 | H12: Amazon Prime | I12: 12.99 | J12: Monthly | K12: =IFERROR(IF(ISBLANK(RecurringExp[[#This Row],[Amount $]]),"",IF(RecurringExp[[#This Row],[Sum from Trans]]<>"",RecurringExp[[#This Row],[Sum from Trans]],RecurringExp[[#This Row],[Amount $]]*_xlfn.XLOOKUP(RecurringExp[[#This Row],[Frequency]],FrequencyKey,FrequencyValue))),"") -> 25.98 | L12: 0 | M12: 44255 | N12: 44282 | O12: =IF(SUMIFS(Table1[Amount $],Table1[Merchant],RecurringExp[[#This Row],[Merchant]],Table1[Date_Year],YEAR(TODAY()))*-1=0,"",SUMIFS(Table1[Amount $],Table1[Merchant],RecurringExp[[#This Row],[Merchant]],Table1[Date_Year],YEAR(TODAY()))*-1) -> 25.98 | P12: =IF(ISBLANK(RecurringExp[[#This Row],[Upcoming Pay Date]]),"",IF(RecurringExp[[#This Row],[Upcoming Pay Date]]-TODAY()<0,"",IF(RecurringExp[[#This Row],[Upcoming Pay Date]]-TODAY()>30,"",RecurringExp[[#This Row],[Upcoming Pay Date]]-TODAY()))) | Q12: =IFERROR(RANK(RecurringExp[[#This Row],[Upcoming Days]],RecurringExp[Upcoming Days],1)+COUNTIF(RecurringExp[[#This Row],[Upcoming Days]]:RecurringExp[[#This Row],[Upcoming Days]],RecurringExp[[#This Row],[Upcoming Days]])-1,"") | R12: =IFERROR(RANK(RecurringExp[[#This Row],[YTD/Annual Cost]],RecurringExp[YTD/Annual Cost],0)+COUNTIF(RecurringExp[[#This Row],[YTD/Annual Cost]]:RecurringExp[[#This Row],[YTD/Annual Cost]],RecurringExp[[#This Row],[YTD/Annual Cost]])-1,"") -> 14 | S12: FALSE
C13: {=IFERROR(INDEX(RecurringExp[Merchant],MATCH($B23,RecurringExp[Rank_Annual],0),0),"")} -> Verizon Wireless | D13: {=IFERROR(INDEX(RecurringExp[YTD/Annual Cost],MATCH($B23,RecurringExp[Rank_Annual],0),0),NA())} -> 369.42 | G13: 733e186ad45c41c18cdbd0db71529383 | H13: Electronic Debit Transamerica Ins | I13: 10.9 | J13: Monthly | K13: =IFERROR(IF(ISBLANK(RecurringExp[[#This Row],[Amount $]]),"",IF(RecurringExp[[#This Row],[Sum from Trans]]<>"",RecurringExp[[#This Row],[Sum from Trans]],RecurringExp[[#This Row],[Amount $]]*_xlfn.XLOOKUP(RecurringExp[[#This Row],[Frequency]],FrequencyKey,FrequencyValue))),"") -> 43.6 | L13: 0 | M13: 44301 | N13: 44328 | O13: =IF(SUMIFS(Table1[Amount $],Table1[Merchant],RecurringExp[[#This Row],[Merchant]],Table1[Date_Year],YEAR(TODAY()))*-1=0,"",SUMIFS(Table1[Amount $],Table1[Merchant],RecurringExp[[#This Row],[Merchant]],Table1[Date_Year],YEAR(TODAY()))*-1) -> 43.6 | P13: =IF(ISBLANK(RecurringExp[[#This Row],[Upcoming Pay Date]]),"",IF(RecurringExp[[#This Row],[Upcoming Pay Date]]-TODAY()<0,"",IF(RecurringExp[[#This Row],[Upcoming Pay Date]]-TODAY()>30,"",RecurringExp[[#This Row],[Upcoming Pay Date]]-TODAY()))) -> 25 | Q13: =IFERROR(RANK(RecurringExp[[#This Row],[Upcoming Days]],RecurringExp[Upcoming Days],1)+COUNTIF(RecurringExp[[#This Row],[Upcoming Days]]:RecurringExp[[#This Row],[Upcoming Days]],RecurringExp[[#This Row],[Upcoming Days]])-1,"") -> 4 | R13: =IFERROR(RANK(RecurringExp[[#This Row],[YTD/Annual Cost]],RecurringExp[YTD/Annual Cost],0)+COUNTIF(RecurringExp[[#This Row],[YTD/Annual Cost]]:RecurringExp[[#This Row],[YTD/Annual Cost]],RecurringExp[[#This Row],[YTD/Annual Cost]])-1,"") -> 10 | S13: FALSE
G14: bae3166a432246f8a5f5bfe277a884d0 | H14: Netflix | I14: 19.07 | J14: Monthly | K14: =IFERROR(IF(ISBLANK(RecurringExp[[#This Row],[Amount $]]),"",IF(RecurringExp[[#This Row],[Sum from Trans]]<>"",RecurringExp[[#This Row],[Sum from Trans]],RecurringExp[[#This Row],[Amount $]]*_xlfn.XLOOKUP(RecurringExp[[#This Row],[Frequency]],FrequencyKey,FrequencyValue))),"") -> 73.04 | L14: 15.12 | M14: 44267 | N14: 44297 | O14: =IF(SUMIFS(Table1[Amount $],Table1[Merchant],RecurringExp[[#This Row],[Merchant]],Table1[Date_Year],YEAR(TODAY()))*-1=0,"",SUMIFS(Table1[Amount $],Table1[Merchant],RecurringExp[[#This Row],[Merchant]],Table1[Date_Year],YEAR(TODAY()))*-1) -> 73.04 | P14: =IF(ISBLANK(RecurringExp[[#This Row],[Upcoming Pay Date]]),"",IF(RecurringExp[[#This Row],[Upcoming Pay Date]]-TODAY()<0,"",IF(RecurringExp[[#This Row],[Upcoming Pay Date]]-TODAY()>30,"",RecurringExp[[#This Row],[Upcoming Pay Date]]-TODAY()))) | Q14: =IFERROR(RANK(RecurringExp[[#This Row],[Upcoming Days]],RecurringExp[Upcoming Days],1)+COUNTIF(RecurringExp[[#This Row],[Upcoming Days]]:RecurringExp[[#This Row],[Upcoming Days]],RecurringExp[[#This Row],[Upcoming Days]])-1,"") | R14: =IFERROR(RANK(RecurringExp[[#This Row],[YTD/Annual Cost]],RecurringExp[YTD/Annual Cost],0)+COUNTIF(RecurringExp[[#This Row],[YTD/Annual Cost]]:RecurringExp[[#This Row],[YTD/Annual Cost]],RecurringExp[[#This Row],[YTD/Annual Cost]])-1,"") -> 9 | S14: FALSE
G15: a36684c6cc8a402e8c2cf99a8e29b8a0 | H15: Verizon | I15: 326.03 | J15: Monthly | K15: =IFERROR(IF(ISBLANK(RecurringExp[[#This Row],[Amount $]]),"",IF(RecurringExp[[#This Row],[Sum from Trans]]<>"",RecurringExp[[#This Row],[Sum from Trans]],RecurringExp[[#This Row],[Amount $]]*_xlfn.XLOOKUP(RecurringExp[[#This Row],[Frequency]],FrequencyKey,FrequencyValue))),"") -> 1248.02 | L15: 326.03 | M15: 44267 | N15: 44297 | O15: =IF(SUMIFS(Table1[Amount $],Table1[Merchant],RecurringExp[[#This Row],[Merchant]],Table1[Date_Year],YEAR(TODAY()))*-1=0,"",SUMIFS(Table1[Amount $],Table1[Merchant],RecurringExp[[#This Row],[Merchant]],Table1[Date_Year],YEAR(TODAY()))*-1) -> 1248.02 | P15: =IF(ISBLANK(RecurringExp[[#This Row],[Upcoming Pay Date]]),"",IF(RecurringExp[[#This Row],[Upcoming Pay Date]]-TODAY()<0,"",IF(RecurringExp[[#This Row],[Upcoming Pay Date]]-TODAY()>30,"",RecurringExp[[#This Row],[Upcoming Pay Date]]-TODAY()))) | Q15: =IFERROR(RANK(RecurringExp[[#This Row],[Upcoming Days]],RecurringExp[Upcoming Days],1)+COUNTIF(RecurringExp[[#This Row],[Upcoming Days]]:RecurringExp[[#This Row],[Upcoming Days]],RecurringExp[[#This Row],[Upcoming Days]])-1,"") | R15: =IFERROR(RANK(RecurringExp[[#This Row],[YTD/Annual Cost]],RecurringExp[YTD/Annual Cost],0)+COUNTIF(RecurringExp[[#This Row],[YTD/Annual Cost]]:RecurringExp[[#This Row],[YTD/Annual Cost]],RecurringExp[[#This Row],[YTD/Annual Cost]])-1,"") -> 1 | S15: TRUE
G16: 44d8b5f616c94a5abb1bba30de4f123c | H16: Verizon Wireless | I16: 123.02 | J16: Monthly | K16: =IFERROR(IF(ISBLANK(RecurringExp[[#This Row],[Amount $]]),"",IF(RecurringExp[[#This Row],[Sum from Trans]]<>"",RecurringExp[[#This Row],[Sum from Trans]],RecurringExp[[#This Row],[Amount $]]*_xlfn.XLOOKUP(RecurringExp[[#This Row],[Frequency]],FrequencyKey,FrequencyValue))),"") -> 369.42 | L16: 123.02 | M16: 44268 | N16: 44298 | O16: =IF(SUMIFS(Table1[Amount $],Table1[Merchant],RecurringExp[[#This Row],[Merchant]],Table1[Date_Year],YEAR(TODAY()))*-1=0,"",SUMIFS(Table1[Amount $],Table1[Merchant],RecurringExp[[#This Row],[Merchant]],Table1[Date_Year],YEAR(TODAY()))*-1) -> 369.42 | P16: =IF(ISBLANK(RecurringExp[[#This Row],[Upcoming Pay Date]]),"",IF(RecurringExp[[#This Row],[Upcoming Pay Date]]-TODAY()<0,"",IF(RecurringExp[[#This Row],[Upcoming Pay Date]]-TODAY()>30,"",RecurringExp[[#This Row],[Upcoming Pay Date]]-TODAY()))) | Q16: =IFERROR(RANK(RecurringExp[[#This Row],[Upcoming Days]],RecurringExp[Upcoming Days],1)+COUNTIF(RecurringExp[[#This Row],[Upcoming Days]]:RecurringExp[[#This Row],[Upcoming Days]],RecurringExp[[#This Row],[Upcoming Days]])-1,"") | R16: =IFERROR(RANK(RecurringExp[[#This Row],[YTD/Annual Cost]],RecurringExp[YTD/Annual Cost],0)+COUNTIF(RecurringExp[[#This Row],[YTD/Annual Cost]]:RecurringExp[[#This Row],[YTD/Annual Cost]],RecurringExp[[#This Row],[YTD/Annual Cost]])-1,"") -> 5 | S16: TRUE
C17: Upcoming Due Dates | G17: 3a7b9681a72246a7b6d8c44c0037c119 | H17: Spotify | I17: 9.99 | J17: Monthly | K17: =IFERROR(IF(ISBLANK(RecurringExp[[#This Row],[Amount $]]),"",IF(RecurringExp[[#This Row],[Sum from Trans]]<>"",RecurringExp[[#This Row],[Sum from Trans]],RecurringExp[[#This Row],[Amount $]]*_xlfn.XLOOKUP(RecurringExp[[#This Row],[Frequency]],FrequencyKey,FrequencyValue))),"") -> 30.57 | L17: 9.99 | O17: =IF(SUMIFS(Table1[Amount $],Table1[Merchant],RecurringExp[[#This Row],[Merchant]],Table1[Date_Year],YEAR(TODAY()))*-1=0,"",SUMIFS(Table1[Amount $],Table1[Merchant],RecurringExp[[#This Row],[Merchant]],Table1[Date_Year],YEAR(TODAY()))*-1) -> 30.57 | P17: =IF(ISBLANK(RecurringExp[[#This Row],[Upcoming Pay Date]]),"",IF(RecurringExp[[#This Row],[Upcoming Pay Date]]-TODAY()<0,"",IF(RecurringExp[[#This Row],[Upcoming Pay Date]]-TODAY()>30,"",RecurringExp[[#This Row],[Upcoming Pay Date]]-TODAY()))) | Q17: =IFERROR(RANK(RecurringExp[[#This Row],[Upcoming Days]],RecurringExp[Upcoming Days],1)+COUNTIF(RecurringExp[[#This Row],[Upcoming Days]]:RecurringExp[[#This Row],[Upcoming Days]],RecurringExp[[#This Row],[Upcoming Days]])-1,"") | R17: =IFERROR(RANK(RecurringExp[[#This Row],[YTD/Annual Cost]],RecurringExp[YTD/Annual Cost],0)+COUNTIF(RecurringExp[[#This Row],[YTD/Annual Cost]]:RecurringExp[[#This Row],[YTD/Annual Cost]],RecurringExp[[#This Row],[YTD/Annual Cost]])-1,"") -> 12 | S17: TRUE
C18: Merchant | D18: $ Amount | E18: Days to Pay | G18: 9fd9623113b14378b3151d18e87991ca | H18: Xbox Live | I18: 9.99 | J18: Monthly | K18: =IFERROR(IF(ISBLANK(RecurringExp[[#This Row],[Amount $]]),"",IF(RecurringExp[[#This Row],[Sum from Trans]]<>"",RecurringExp[[#This Row],[Sum from Trans]],RecurringExp[[#This Row],[Amount $]]*_xlfn.XLOOKUP(RecurringExp[[#This Row],[Frequency]],FrequencyKey,FrequencyValue))),"") -> 40.56 | L18: 9.99 | O18: =IF(SUMIFS(Table1[Amount $],Table1[Merchant],RecurringExp[[#This Row],[Merchant]],Table1[Date_Year],YEAR(TODAY()))*-1=0,"",SUMIFS(Table1[Amount $],Table1[Merchant],RecurringExp[[#This Row],[Merchant]],Table1[Date_Year],YEAR(TODAY()))*-1) -> 40.56 | P18: =IF(ISBLANK(RecurringExp[[#This Row],[Upcoming Pay Date]]),"",IF(RecurringExp[[#This Row],[Upcoming Pay Date]]-TODAY()<0,"",IF(RecurringExp[[#This Row],[Upcoming Pay Date]]-TODAY()>30,"",RecurringExp[[#This Row],[Upcoming Pay Date]]-TODAY()))) | Q18: =IFERROR(RANK(RecurringExp[[#This Row],[Upcoming Days]],RecurringExp[Upcoming Days],1)+COUNTIF(RecurringExp[[#This Row],[Upcoming Days]]:RecurringExp[[#This Row],[Upcoming Days]],RecurringExp[[#This Row],[Upcoming Days]])-1,"") | R18: =IFERROR(RANK(RecurringExp[[#This Row],[YTD/Annual Cost]],RecurringExp[YTD/Annual Cost],0)+COUNTIF(RecurringExp[[#This Row],[YTD/Annual Cost]]:RecurringExp[[#This Row],[YTD/Annual Cost]],RecurringExp[[#This Row],[YTD/Annual Cost]])-1,"") -> 11 | S18: TRUE
B19: 1 | C19: =IFERROR(INDEX(RecurringExp[Merchant],MATCH($B19,RecurringExp[Rank_Days],0),0),"") -> Check Card Purchase Credit | D19: {=IFERROR(INDEX(RecurringExp[Amount $],MATCH($B19,RecurringExp[Rank_Days],0),0),"")} -> 226 | E19: {=IFERROR(IF(INDEX(RecurringExp[Upcoming Days],MATCH($B19,RecurringExp[Rank_Days],0),0)=0,"Today",INDEX(RecurringExp[Upcoming Days],MATCH($B19,RecurringExp[Rank_Days],0),0)),"")} -> 1 | G19: 1fcc54d44edd46dabe6a9e1f754e9b91 | H19: Door Dash Pass | I19: 9.99 | J19: Monthly | K19: =IFERROR(IF(ISBLANK(RecurringExp[[#This Row],[Amount $]]),"",IF(RecurringExp[[#This Row],[Sum from Trans]]<>"",RecurringExp[[#This Row],[Sum from Trans]],RecurringExp[[#This Row],[Amount $]]*_xlfn.XLOOKUP(RecurringExp[[#This Row],[Frequency]],FrequencyKey,FrequencyValue))),"") -> 29.97 | L19: 9.99 | O19: =IF(SUMIFS(Table1[Amount $],Table1[Merchant],RecurringExp[[#This Row],[Merchant]],Table1[Date_Year],YEAR(TODAY()))*-1=0,"",SUMIFS(Table1[Amount $],Table1[Merchant],RecurringExp[[#This Row],[Merchant]],Table1[Date_Year],YEAR(TODAY()))*-1) -> 29.97 | P19: =IF(ISBLANK(RecurringExp[[#This Row],[Upcoming Pay Date]]),"",IF(RecurringExp[[#This Row],[Upcoming Pay Date]]-TODAY()<0,"",IF(RecurringExp[[#This Row],[Upcoming Pay Date]]-TODAY()>30,"",RecurringExp[[#This Row],[Upcoming Pay Date]]-TODAY()))) | Q19: =IFERROR(RANK(RecurringExp[[#This Row],[Upcoming Days]],RecurringExp[Upcoming Days],1)+COUNTIF(RecurringExp[[#This Row],[Upcoming Days]]:RecurringExp[[#This Row],[Upcoming Days]],RecurringExp[[#This Row],[Upcoming Days]])-1,"") | R19: =IFERROR(RANK(RecurringExp[[#This Row],[YTD/Annual Cost]],RecurringExp[YTD/Annual Cost],0)+COUNTIF(RecurringExp[[#This Row],[YTD/Annual Cost]]:RecurringExp[[#This Row],[YTD/Annual Cost]],RecurringExp[[#This Row],[YTD/Annual Cost]])-1,"") -> 13 | S19: TRUE
B20: 2 | C20: =IFERROR(INDEX(RecurringExp[Merchant],MATCH($B21,RecurringExp[Rank_Days],0),0),"") -> Electronic Debit Tran Life | D20: {=IFERROR(INDEX(RecurringExp[Amount $],MATCH($B21,RecurringExp[Rank_Days],0),0),"")} -> 344.72 | E20: {=IFERROR(IF(INDEX(RecurringExp[Upcoming Days],MATCH($B21,RecurringExp[Rank_Days],0),0)=0,"Today",INDEX(RecurringExp[Upcoming Days],MATCH($B21,RecurringExp[Rank_Days],0),0)),"")} -> 6 | G20: 78cd7f00d91d4a11b62fc27c980e85e0 | H20: Amercican Home Shield | I20: 54.99 | J20: Monthly | K20: =IFERROR(IF(ISBLANK(RecurringExp[[#This Row],[Amount $]]),"",IF(RecurringExp[[#This Row],[Sum from Trans]]<>"",RecurringExp[[#This Row],[Sum from Trans]],RecurringExp[[#This Row],[Amount $]]*_xlfn.XLOOKUP(RecurringExp[[#This Row],[Frequency]],FrequencyKey,FrequencyValue))),"") -> 109.98 | L20: 54.99 | O20: =IF(SUMIFS(Table1[Amount $],Table1[Merchant],RecurringExp[[#This Row],[Merchant]],Table1[Date_Year],YEAR(TODAY()))*-1=0,"",SUMIFS(Table1[Amount $],Table1[Merchant],RecurringExp[[#This Row],[Merchant]],Table1[Date_Year],YEAR(TODAY()))*-1) -> 109.98 | P20: =IF(ISBLANK(RecurringExp[[#This Row],[Upcoming Pay Date]]),"",IF(RecurringExp[[#This Row],[Upcoming Pay Date]]-TODAY()<0,"",IF(RecurringExp[[#This Row],[Upcoming Pay Date]]-TODAY()>30,"",RecurringExp[[#This Row],[Upcoming Pay Date]]-TODAY()))) | Q20: =IFERROR(RANK(RecurringExp[[#This Row],[Upcoming Days]],RecurringExp[Upcoming Days],1)+COUNTIF(RecurringExp[[#This Row],[Upcoming Days]]:RecurringExp[[#This Row],[Upcoming Days]],RecurringExp[[#This Row],[Upcoming Days]])-1,"") | R20: =IFERROR(RANK(RecurringExp[[#This Row],[YTD/Annual Cost]],RecurringExp[YTD/Annual Cost],0)+COUNTIF(RecurringExp[[#This Row],[YTD/Annual Cost]]:RecurringExp[[#This Row],[YTD/Annual Cost]],RecurringExp[[#This Row],[YTD/Annual Cost]])-1,"") -> 8 | S20: TRUE
B21: 3 | C21: =IFERROR(INDEX(RecurringExp[Merchant],MATCH($B22,RecurringExp[Rank_Days],0),0),"") -> Electronic Debit Transamerica Ins | D21: {=IFERROR(INDEX(RecurringExp[Amount $],MATCH($B22,RecurringExp[Rank_Days],0),0),"")} -> 10.9 | E21: {=IFERROR(IF(INDEX(RecurringExp[Upcoming Days],MATCH($B22,RecurringExp[Rank_Days],0),0)=0,"Today",INDEX(RecurringExp[Upcoming Days],MATCH($B22,RecurringExp[Rank_Days],0),0)),"")} -> 25 | G21: bba6eb3df4614aa195dc047d4eae2f58 | H21: CVS Care Pass | I21: 5.3 | J21: Monthly | K21: =IFERROR(IF(ISBLANK(RecurringExp[[#This Row],[Amount $]]),"",IF(RecurringExp[[#This Row],[Sum from Trans]]<>"",RecurringExp[[#This Row],[Sum from Trans]],RecurringExp[[#This Row],[Amount $]]*_xlfn.XLOOKUP(RecurringExp[[#This Row],[Frequency]],FrequencyKey,FrequencyValue))),"") -> 21.2 | L21: 5.3 | O21: =IF(SUMIFS(Table1[Amount $],Table1[Merchant],RecurringExp[[#This Row],[Merchant]],Table1[Date_Year],YEAR(TODAY()))*-1=0,"",SUMIFS(Table1[Amount $],Table1[Merchant],RecurringExp[[#This Row],[Merchant]],Table1[Date_Year],YEAR(TODAY()))*-1) -> 21.2 | P21: =IF(ISBLANK(RecurringExp[[#This Row],[Upcoming Pay Date]]),"",IF(RecurringExp[[#This Row],[Upcoming Pay Date]]-TODAY()<0,"",IF(RecurringExp[[#This Row],[Upcoming Pay Date]]-TODAY()>30,"",RecurringExp[[#This Row],[Upcoming Pay Date]]-TODAY()))) | Q21: =IFERROR(RANK(RecurringExp[[#This Row],[Upcoming Days]],RecurringExp[Upcoming Days],1)+COUNTIF(RecurringExp[[#This Row],[Upcoming Days]]:RecurringExp[[#This Row],[Upcoming Days]],RecurringExp[[#This Row],[Upcoming Days]])-1,"") | R21: =IFERROR(RANK(RecurringExp[[#This Row],[YTD/Annual Cost]],RecurringExp[YTD/Annual Cost],0)+COUNTIF(RecurringExp[[#This Row],[YTD/Annual Cost]]:RecurringExp[[#This Row],[YTD/Annual Cost]],RecurringExp[[#This Row],[YTD/Annual Cost]])-1,"") -> 15 | S21: TRUE
B22: 4 | C22: =IFERROR(INDEX(RecurringExp[Merchant],MATCH($B23,RecurringExp[Rank_Days],0),0),"") | D22: {=IFERROR(INDEX(RecurringExp[Amount $],MATCH($B23,RecurringExp[Rank_Days],0),0),"")} | E22: {=IFERROR(IF(INDEX(RecurringExp[Upcoming Days],MATCH($B23,RecurringExp[Rank_Days],0),0)=0,"Today",INDEX(RecurringExp[Upcoming Days],MATCH($B23,RecurringExp[Rank_Days],0),0)),"")} | H22: T Mobile | I22: 65.92 | J22: Monthly | K22: =IFERROR(IF(ISBLANK(RecurringExp[[#This Row],[Amount $]]),"",IF(RecurringExp[[#This Row],[Sum from Trans]]<>"",RecurringExp[[#This Row],[Sum from Trans]],RecurringExp[[#This Row],[Amount $]]*_xlfn.XLOOKUP(RecurringExp[[#This Row],[Frequency]],FrequencyKey,FrequencyValue))),"") -> 197.69 | O22: =IF(SUMIFS(Table1[Amount $],Table1[Merchant],RecurringExp[[#This Row],[Merchant]],Table1[Date_Year],YEAR(TODAY()))*-1=0,"",SUMIFS(Table1[Amount $],Table1[Merchant],RecurringExp[[#This Row],[Merchant]],Table1[Date_Year],YEAR(TODAY()))*-1) -> 197.69 | P22: =IF(ISBLANK(RecurringExp[[#This Row],[Upcoming Pay Date]]),"",IF(RecurringExp[[#This Row],[Upcoming Pay Date]]-TODAY()<0,"",IF(RecurringExp[[#This Row],[Upcoming Pay Date]]-TODAY()>30,"",RecurringExp[[#This Row],[Upcoming Pay Date]]-TODAY()))) | Q22: =IFERROR(RANK(RecurringExp[[#This Row],[Upcoming Days]],RecurringExp[Upcoming Days],1)+COUNTIF(RecurringExp[[#This Row],[Upcoming Days]]:RecurringExp[[#This Row],[Upcoming Days]],RecurringExp[[#This Row],[Upcoming Days]])-1,"") | R22: =IFERROR(RANK(RecurringExp[[#This Row],[YTD/Annual Cost]],RecurringExp[YTD/Annual Cost],0)+COUNTIF(RecurringExp[[#This Row],[YTD/Annual Cost]]:RecurringExp[[#This Row],[YTD/Annual Cost]],RecurringExp[[#This Row],[YTD/Annual Cost]])-1,"") -> 6
B23: 5 | H23: Pepco | I23: 473.95 | J23: Unknown | K23: =IFERROR(IF(ISBLANK(RecurringExp[[#This Row],[Amount $]]),"",IF(RecurringExp[[#This Row],[Sum from Trans]]<>"",RecurringExp[[#This Row],[Sum from Trans]],RecurringExp[[#This Row],[Amount $]]*_xlfn.XLOOKUP(RecurringExp[[#This Row],[Frequency]],FrequencyKey,FrequencyValue))),"") -> 473.95 | O23: =IF(SUMIFS(Table1[Amount $],Table1[Merchant],RecurringExp[[#This Row],[Merchant]],Table1[Date_Year],YEAR(TODAY()))*-1=0,"",SUMIFS(Table1[Amount $],Table1[Merchant],RecurringExp[[#This Row],[Merchant]],Table1[Date_Year],YEAR(TODAY()))*-1) -> 473.95 | P23: =IF(ISBLANK(RecurringExp[[#This Row],[Upcoming Pay Date]]),"",IF(RecurringExp[[#This Row],[Upcoming Pay Date]]-TODAY()<0,"",IF(RecurringExp[[#This Row],[Upcoming Pay Date]]-TODAY()>30,"",RecurringExp[[#This Row],[Upcoming Pay Date]]-TODAY()))) | Q23: =IFERROR(RANK(RecurringExp[[#This Row],[Upcoming Days]],RecurringExp[Upcoming Days],1)+COUNTIF(RecurringExp[[#This Row],[Upcoming Days]]:RecurringExp[[#This Row],[Upcoming Days]],RecurringExp[[#This Row],[Upcoming Days]])-1,"") | R23: =IFERROR(RANK(RecurringExp[[#This Row],[YTD/Annual Cost]],RecurringExp[YTD/Annual Cost],0)+COUNTIF(RecurringExp[[#This Row],[YTD/Annual Cost]]:RecurringExp[[#This Row],[YTD/Annual Cost]],RecurringExp[[#This Row],[YTD/Annual Cost]])-1,"") -> 3 | T23: 2109
H24: JC Penny | I24: 155 | J24: Unknown | K24: =IFERROR(IF(ISBLANK(RecurringExp[[#This Row],[Amount $]]),"",IF(RecurringExp[[#This Row],[Sum from Trans]]<>"",RecurringExp[[#This Row],[Sum from Trans]],RecurringExp[[#This Row],[Amount $]]*_xlfn.XLOOKUP(RecurringExp[[#This Row],[Frequency]],FrequencyKey,FrequencyValue))),"") | O24: =IF(SUMIFS(Table1[Amount $],Table1[Merchant],RecurringExp[[#This Row],[Merchant]],Table1[Date_Year],YEAR(TODAY()))*-1=0,"",SUMIFS(Table1[Amount $],Table1[Merchant],RecurringExp[[#This Row],[Merchant]],Table1[Date_Year],YEAR(TODAY()))*-1) | P24: =IF(ISBLANK(RecurringExp[[#This Row],[Upcoming Pay Date]]),"",IF(RecurringExp[[#This Row],[Upcoming Pay Date]]-TODAY()<0,"",IF(RecurringExp[[#This Row],[Upcoming Pay Date]]-TODAY()>30,"",RecurringExp[[#This Row],[Upcoming Pay Date]]-TODAY()))) | Q24: =IFERROR(RANK(RecurringExp[[#This Row],[Upcoming Days]],RecurringExp[Upcoming Days],1)+COUNTIF(RecurringExp[[#This Row],[Upcoming Days]]:RecurringExp[[#This Row],[Upcoming Days]],RecurringExp[[#This Row],[Upcoming Days]])-1,"") | R24: =IFERROR(RANK(RecurringExp[[#This Row],[YTD/Annual Cost]],RecurringExp[YTD/Annual Cost],0)+COUNTIF(RecurringExp[[#This Row],[YTD/Annual Cost]]:RecurringExp[[#This Row],[YTD/Annual Cost]],RecurringExp[[#This Row],[YTD/Annual Cost]])-1,"")
H25: Kohls | I25: 95 | J25: Unknown | K25: =IFERROR(IF(ISBLANK(RecurringExp[[#This Row],[Amount $]]),"",IF(RecurringExp[[#This Row],[Sum from Trans]]<>"",RecurringExp[[#This Row],[Sum from Trans]],RecurringExp[[#This Row],[Amount $]]*_xlfn.XLOOKUP(RecurringExp[[#This Row],[Frequency]],FrequencyKey,FrequencyValue))),"") | O25: =IF(SUMIFS(Table1[Amount $],Table1[Merchant],RecurringExp[[#This Row],[Merchant]],Table1[Date_Year],YEAR(TODAY()))*-1=0,"",SUMIFS(Table1[Amount $],Table1[Merchant],RecurringExp[[#This Row],[Merchant]],Table1[Date_Year],YEAR(TODAY()))*-1) | P25: =IF(ISBLANK(RecurringExp[[#This Row],[Upcoming Pay Date]]),"",IF(RecurringExp[[#This Row],[Upcoming Pay Date]]-TODAY()<0,"",IF(RecurringExp[[#This Row],[Upcoming Pay Date]]-TODAY()>30,"",RecurringExp[[#This Row],[Upcoming Pay Date]]-TODAY()))) | Q25: =IFERROR(RANK(RecurringExp[[#This Row],[Upcoming Days]],RecurringExp[Upcoming Days],1)+COUNTIF(RecurringExp[[#This Row],[Upcoming Days]]:RecurringExp[[#This Row],[Upcoming Days]],RecurringExp[[#This Row],[Upcoming Days]])-1,"") | R25: =IFERROR(RANK(RecurringExp[[#This Row],[YTD/Annual Cost]],RecurringExp[YTD/Annual Cost],0)+COUNTIF(RecurringExp[[#This Row],[YTD/Annual Cost]]:RecurringExp[[#This Row],[YTD/Annual Cost]],RecurringExp[[#This Row],[YTD/Annual Cost]])-1,"")
K26: =IFERROR(IF(ISBLANK(RecurringExp[[#This Row],[Amount $]]),"",IF(RecurringExp[[#This Row],[Sum from Trans]]<>"",RecurringExp[[#This Row],[Sum from Trans]],RecurringExp[[#This Row],[Amount $]]*_xlfn.XLOOKUP(RecurringExp[[#This Row],[Frequency]],FrequencyKey,FrequencyValue))),"") | O26: =IF(SUMIFS(Table1[Amount $],Table1[Merchant],RecurringExp[[#This Row],[Merchant]],Table1[Date_Year],YEAR(TODAY()))*-1=0,"",SUMIFS(Table1[Amount $],Table1[Merchant],RecurringExp[[#This Row],[Merchant]],Table1[Date_Year],YEAR(TODAY()))*-1) | P26: =IF(ISBLANK(RecurringExp[[#This Row],[Upcoming Pay Date]]),"",IF(RecurringExp[[#This Row],[Upcoming Pay Date]]-TODAY()<0,"",IF(RecurringExp[[#This Row],[Upcoming Pay Date]]-TODAY()>30,"",RecurringExp[[#This Row],[Upcoming Pay Date]]-TODAY()))) | Q26: =IFERROR(RANK(RecurringExp[[#This Row],[Upcoming Days]],RecurringExp[Upcoming Days],1)+COUNTIF(RecurringExp[[#This Row],[Upcoming Days]]:RecurringExp[[#This Row],[Upcoming Days]],RecurringExp[[#This Row],[Upcoming Days]])-1,"") | R26: =IFERROR(RANK(RecurringExp[[#This Row],[YTD/Annual Cost]],RecurringExp[YTD/Annual Cost],0)+COUNTIF(RecurringExp[[#This Row],[YTD/Annual Cost]]:RecurringExp[[#This Row],[YTD/Annual Cost]],RecurringExp[[#This Row],[YTD/Annual Cost]])-1,"")
K27: =IFERROR(IF(ISBLANK(RecurringExp[[#This Row],[Amount $]]),"",IF(RecurringExp[[#This Row],[Sum from Trans]]<>"",RecurringExp[[#This Row],[Sum from Trans]],RecurringExp[[#This Row],[Amount $]]*_xlfn.XLOOKUP(RecurringExp[[#This Row],[Frequency]],FrequencyKey,FrequencyValue))),"") | O27: =IF(SUMIFS(Table1[Amount $],Table1[Merchant],RecurringExp[[#This Row],[Merchant]],Table1[Date_Year],YEAR(TODAY()))*-1=0,"",SUMIFS(Table1[Amount $],Table1[Merchant],RecurringExp[[#This Row],[Merchant]],Table1[Date_Year],YEAR(TODAY()))*-1) | P27: =IF(ISBLANK(RecurringExp[[#This Row],[Upcoming Pay Date]]),"",IF(RecurringExp[[#This Row],[Upcoming Pay Date]]-TODAY()<0,"",IF(RecurringExp[[#This Row],[Upcoming Pay Date]]-TODAY()>30,"",RecurringExp[[#This Row],[Upcoming Pay Date]]-TODAY()))) | Q27: =IFERROR(RANK(RecurringExp[[#This Row],[Upcoming Days]],RecurringExp[Upcoming Days],1)+COUNTIF(RecurringExp[[#This Row],[Upcoming Days]]:RecurringExp[[#This Row],[Upcoming Days]],RecurringExp[[#This Row],[Upcoming Days]])-1,"") | R27: =IFERROR(RANK(RecurringExp[[#This Row],[YTD/Annual Cost]],RecurringExp[YTD/Annual Cost],0)+COUNTIF(RecurringExp[[#This Row],[YTD/Annual Cost]]:RecurringExp[[#This Row],[YTD/Annual Cost]],RecurringExp[[#This Row],[YTD/Annual Cost]])-1,"")
K28: =IFERROR(IF(ISBLANK(RecurringExp[[#This Row],[Amount $]]),"",IF(RecurringExp[[#This Row],[Sum from Trans]]<>"",RecurringExp[[#This Row],[Sum from Trans]],RecurringExp[[#This Row],[Amount $]]*_xlfn.XLOOKUP(RecurringExp[[#This Row],[Frequency]],FrequencyKey,FrequencyValue))),"") | O28: =IF(SUMIFS(Table1[Amount $],Table1[Merchant],RecurringExp[[#This Row],[Merchant]],Table1[Date_Year],YEAR(TODAY()))*-1=0,"",SUMIFS(Table1[Amount $],Table1[Merchant],RecurringExp[[#This Row],[Merchant]],Table1[Date_Year],YEAR(TODAY()))*-1) | P28: =IF(ISBLANK(RecurringExp[[#This Row],[Upcoming Pay Date]]),"",IF(RecurringExp[[#This Row],[Upcoming Pay Date]]-TODAY()<0,"",IF(RecurringExp[[#This Row],[Upcoming Pay Date]]-TODAY()>30,"",RecurringExp[[#This Row],[Upcoming Pay Date]]-TODAY()))) | Q28: =IFERROR(RANK(RecurringExp[[#This Row],[Upcoming Days]],RecurringExp[Upcoming Days],1)+COUNTIF(RecurringExp[[#This Row],[Upcoming Days]]:RecurringExp[[#This Row],[Upcoming Days]],RecurringExp[[#This Row],[Upcoming Days]])-1,"") | R28: =IFERROR(RANK(RecurringExp[[#This Row],[YTD/Annual Cost]],RecurringExp[YTD/Annual Cost],0)+COUNTIF(RecurringExp[[#This Row],[YTD/Annual Cost]]:RecurringExp[[#This Row],[YTD/Annual Cost]],RecurringExp[[#This Row],[YTD/Annual Cost]])-1,"")
K29: =IFERROR(IF(ISBLANK(RecurringExp[[#This Row],[Amount $]]),"",IF(RecurringExp[[#This Row],[Sum from Trans]]<>"",RecurringExp[[#This Row],[Sum from Trans]],RecurringExp[[#This Row],[Amount $]]*_xlfn.XLOOKUP(RecurringExp[[#This Row],[Frequency]],FrequencyKey,FrequencyValue))),"") | O29: =IF(SUMIFS(Table1[Amount $],Table1[Merchant],RecurringExp[[#This Row],[Merchant]],Table1[Date_Year],YEAR(TODAY()))*-1=0,"",SUMIFS(Table1[Amount $],Table1[Merchant],RecurringExp[[#This Row],[Merchant]],Table1[Date_Year],YEAR(TODAY()))*-1) | P29: =IF(ISBLANK(RecurringExp[[#This Row],[Upcoming Pay Date]]),"",IF(RecurringExp[[#This Row],[Upcoming Pay Date]]-TODAY()<0,"",IF(RecurringExp[[#This Row],[Upcoming Pay Date]]-TODAY()>30,"",RecurringExp[[#This Row],[Upcoming Pay Date]]-TODAY()))) | Q29: =IFERROR(RANK(RecurringExp[[#This Row],[Upcoming Days]],RecurringExp[Upcoming Days],1)+COUNTIF(RecurringExp[[#This Row],[Upcoming Days]]:RecurringExp[[#This Row],[Upcoming Days]],RecurringExp[[#This Row],[Upcoming Days]])-1,"") | R29: =IFERROR(RANK(RecurringExp[[#This Row],[YTD/Annual Cost]],RecurringExp[YTD/Annual Cost],0)+COUNTIF(RecurringExp[[#This Row],[YTD/Annual Cost]]:RecurringExp[[#This Row],[YTD/Annual Cost]],RecurringExp[[#This Row],[YTD/Annual Cost]])-1,"")
K30: =IFERROR(IF(ISBLANK(RecurringExp[[#This Row],[Amount $]]),"",IF(RecurringExp[[#This Row],[Sum from Trans]]<>"",RecurringExp[[#This Row],[Sum from Trans]],RecurringExp[[#This Row],[Amount $]]*_xlfn.XLOOKUP(RecurringExp[[#This Row],[Frequency]],FrequencyKey,FrequencyValue))),"") | O30: =IF(SUMIFS(Table1[Amount $],Table1[Merchant],RecurringExp[[#This Row],[Merchant]],Table1[Date_Year],YEAR(TODAY()))*-1=0,"",SUMIFS(Table1[Amount $],Table1[Merchant],RecurringExp[[#This Row],[Merchant]],Table1[Date_Year],YEAR(TODAY()))*-1) | P30: =IF(ISBLANK(RecurringExp[[#This Row],[Upcoming Pay Date]]),"",IF(RecurringExp[[#This Row],[Upcoming Pay Date]]-TODAY()<0,"",IF(RecurringExp[[#This Row],[Upcoming Pay Date]]-TODAY()>30,"",RecurringExp[[#This Row],[Upcoming Pay Date]]-TODAY()))) | Q30: =IFERROR(RANK(RecurringExp[[#This Row],[Upcoming Days]],RecurringExp[Upcoming Days],1)+COUNTIF(RecurringExp[[#This Row],[Upcoming Days]]:RecurringExp[[#This Row],[Upcoming Days]],RecurringExp[[#This Row],[Upcoming Days]])-1,"") | R30: =IFERROR(RANK(RecurringExp[[#This Row],[YTD/Annual Cost]],RecurringExp[YTD/Annual Cost],0)+COUNTIF(RecurringExp[[#This Row],[YTD/Annual Cost]]:RecurringExp[[#This Row],[YTD/Annual Cost]],RecurringExp[[#This Row],[YTD/Annual Cost]])-1,"")
K31: =IFERROR(IF(ISBLANK(RecurringExp[[#This Row],[Amount $]]),"",IF(RecurringExp[[#This Row],[Sum from Trans]]<>"",RecurringExp[[#This Row],[Sum from Trans]],RecurringExp[[#This Row],[Amount $]]*_xlfn.XLOOKUP(RecurringExp[[#This Row],[Frequency]],FrequencyKey,FrequencyValue))),"") | O31: =IF(SUMIFS(Table1[Amount $],Table1[Merchant],RecurringExp[[#This Row],[Merchant]],Table1[Date_Year],YEAR(TODAY()))*-1=0,"",SUMIFS(Table1[Amount $],Table1[Merchant],RecurringExp[[#This Row],[Merchant]],Table1[Date_Year],YEAR(TODAY()))*-1) | P31: =IF(ISBLANK(RecurringExp[[#This Row],[Upcoming Pay Date]]),"",IF(RecurringExp[[#This Row],[Upcoming Pay Date]]-TODAY()<0,"",IF(RecurringExp[[#This Row],[Upcoming Pay Date]]-TODAY()>30,"",RecurringExp[[#This Row],[Upcoming Pay Date]]-TODAY()))) | Q31: =IFERROR(RANK(RecurringExp[[#This Row],[Upcoming Days]],RecurringExp[Upcoming Days],1)+COUNTIF(RecurringExp[[#This Row],[Upcoming Days]]:RecurringExp[[#This Row],[Upcoming Days]],RecurringExp[[#This Row],[Upcoming Days]])-1,"") | R31: =IFERROR(RANK(RecurringExp[[#This Row],[YTD/Annual Cost]],RecurringExp[YTD/Annual Cost],0)+COUNTIF(RecurringExp[[#This Row],[YTD/Annual Cost]]:RecurringExp[[#This Row],[YTD/Annual Cost]],RecurringExp[[#This Row],[YTD/Annual Cost]])-1,"")

Sheet Snapshot
C2: Snapshot | Q2: Choose month below
C4: See your spending trends month over month with easy to read graphs. To switch months, click on the blue date box to the right. | Q4: June 2020 | W4: =_xlfn.XLOOKUP(TEXT(Q4,"mmmm yyyy"),$V$7:$V$200,$W$7:$W$200) -> 43983 | Y4: Monthly Summary | AC4: Category | AD4: Count | AE4: Rank | AF4: Order | AG4: Category | AH4: $ | AJ4: Display Axis | AK4: Current Mon. | AL4: $ | AM4: =TEXT(AK6,"MMMM")&" Spending" -> June Spending | AN4: Max Date | AO4: Last Mon. | AP4: $ | AQ4: =TEXT(AO6,"MMMM")&" Spending" -> May Spending | AR4: Max Date | AT4: Merchants | AU4: $ | AV4: Trans Count | AW4: Trans Rank | AX4: $ Rank
V6: Input | W6: Month Filter | Y6: =TEXT(ABS(Z9),"$#,##0")&" "&IF(Z7>Z8,"less was spent compared to last month","more was spent compared to last month") -> $321 less was spent compared to last month | AC6: {=_xlfn.UNIQUE(INDEX(_xlfn._xlws.FILTER(CategoriesTable[],(CategoriesTable[Category type]="expense")*(NOT(CategoriesTable[ID]=0)),""),0,2),FALSE)} -> Auto/Transport | AD6: =SUMIFS(Table1[Amount $],Table1[Category],Snapshot!AC6,Table1[Month],Snapshot!$W$4)*-1 -> 0 | AE6: =RANK(AD6,$AD$6:$AD$35,0)+COUNTIF(AD6:$AD$6,AD6)-1 -> 10 | AF6: 1 | AG6: {=IF(INDEX($AD$6:$AD$35,MATCH(AF6,$AE$6:$AE$35,0),0)=0,"",INDEX($AC$6:$AC$35,MATCH(AF6,$AE$6:$AE$35,0),0))} -> Bills/Utilities | AH6: {=IF(INDEX($AD$6:$AD$35,MATCH(AF6,$AE$6:$AE$35,0),0)=0,0,INDEX($AD$6:$AD$35,MATCH(AF6,$AE$6:$AE$35,0),0))} -> 1881.32 | AJ6: =DATE(2000,1,1) -> 36526 | AK6: =DATE(YEAR(W4),MONTH(W4),DAY(W4)) -> 43983 | AL6: =SUMIFS(Table1[Amount $],Table1[Category Type],"Expense",Table1[Date],Snapshot!AK6)*-1 -> 50.16 | AM6: =IF(AK6>TODAY(),NA(),SUM(AL6:$AL$6)) -> 50.16 | AN6: =IF(OR(AK6=EOMONTH($AK$6,0),AK6=TODAY()),AM6,NA()) -> #N/A | AO6: =DATE(YEAR(AK6),MONTH(AK6)-1,DAY(AK6)) -> 43952 | AP6: =SUMIFS(Table1[Amount $],Table1[Category Type],"Expense",Table1[Date],Snapshot!AO6)*-1 -> 500 | AQ6: =IF(AO6<=EOMONTH($AO$6,0),SUM(AP$6:$AP6),NA()) -> 500 | AR6: =IF(AO6=EOMONTH($AO$6,0),AQ6,NA()) -> #N/A | AT6: {=_xlfn.UNIQUE(_xlfn._xlws.FILTER(Table1[Merchant],(Table1[Merchant]<>"")*(Table1[Amount $]<0)*(Table1[Month]=Snapshot!$W$4)*(Table1[Category Type]="Expense")))} -> Amazon Prime | AU6: =IF(ISBLANK(AT6),"",SUMIFS(Table1[Amount $],Table1[Merchant],Snapshot!AT6,Table1[Month],Snapshot!$W$4)*-1) -> 12.99 | AV6: =IF(ISBLANK(AT6),"",COUNTIFS(Table1[Merchant],Snapshot!AT6,Table1[Month],Snapshot!$W$4)) -> 1 | AW6: =IFERROR(RANK(AV6,$AV$6:$AV$200)+COUNTIF($AV$6:AV6,AV6)-1,"") -> 8 | AX6: =IFERROR(RANK(AU6,$AU$6:$AU$200)+COUNTIF($AU$6:AU6,AU6)-1,"") -> 25
D7: Current vs. previous month spending | M7: This month's top spending categories | V7: =IF(ISBLANK(W7),"--",TEXT(W7,"mmmm")&" "&TEXT(W7,"YYYY")) -> April 2021 | W7: {=_xlfn._xlws.SORT(_xlfn.UNIQUE(_xlfn._xlws.FILTER(Table1[Month],Table1[Month]<>"",)),1,-1)} -> 44287 | Y7: =IFERROR(TEXT(AO6,"mmmm"),"--") -> May | Z7: =SUMIFS(Table1[Amount $],Table1[Category Type],"Expense",Table1[Month],DATE(YEAR(Snapshot!$W$4),MONTH(Snapshot!$W$4)-1,DAY(Snapshot!$W$4)))*-1 -> 4475.64 | AC7: Bills/Utilities | AD7: =SUMIFS(Table1[Amount $],Table1[Category],Snapshot!AC7,Table1[Month],Snapshot!$W$4)*-1 -> 1881.32 | AE7: =RANK(AD7,$AD$6:$AD$35,0)+COUNTIF(AD$6:$AD7,AD7)-1 -> 1 | AF7: 2 | AG7: {=IF(INDEX($AD$6:$AD$35,MATCH(AF7,$AE$6:$AE$35,0),0)=0,"",INDEX($AC$6:$AC$35,MATCH(AF7,$AE$6:$AE$35,0),0))} -> Shopping | AH7: {=IF(INDEX($AD$6:$AD$35,MATCH(AF7,$AE$6:$AE$35,0),0)=0,0,INDEX($AD$6:$AD$35,MATCH(AF7,$AE$6:$AE$35,0),0))} -> 573.13 | AJ7: =DATE(YEAR(AJ6),MONTH(AJ6),DAY(AJ6)+1) -> 36527 | AK7: =IF(MONTH(AK6)=MONTH(DATE(YEAR(AK6),MONTH(AK6),DAY(AK6)+1)),DATE(YEAR(AK6),MONTH(AK6),DAY(AK6)+1),NA()) -> 43984 | AL7: =SUMIFS(Table1[Amount $],Table1[Category Type],"Expense",Table1[Date],Snapshot!AK7)*-1 -> 149.93 | AM7: =IF(AK7>TODAY(),NA(),SUM(AL$6:$AL7)) -> 200.09 | AN7: =IF(OR(AK7=EOMONTH($AK$6,0),AK7=TODAY()),AM7,NA()) -> #N/A | AO7: =IF(MONTH(AO6)=MONTH(DATE(YEAR(AO6),MONTH(AO6),DAY(AO6)+1)),DATE(YEAR(AO6),MONTH(AO6),DAY(AO6)+1),NA()) -> 43953 | AP7: =SUMIFS(Table1[Amount $],Table1[Category Type],"Expense",Table1[Date],Snapshot!AO7)*-1 -> 77.58 | AQ7: =IF(AO7<=EOMONTH($AO$6,0),SUM(AP$6:$AP7),NA()) -> 577.58 | AR7: =IF(AO7=EOMONTH($AO$6,0),AQ7,NA()) -> #N/A | AT7: Electronic Debit Transamerica Tpl | AU7: =IF(ISBLANK(AT7),"",SUMIFS(Table1[Amount $],Table1[Merchant],Snapshot!AT7,Table1[Month],Snapshot!$W$4)*-1) -> 318 | AV7: =IF(ISBLANK(AT7),"",COUNTIFS(Table1[Merchant],Snapshot!AT7,Table1[Month],Snapshot!$W$4)) -> 1 | AW7: =IFERROR(RANK(AV7,$AV$6:$AV$200)+COUNTIF($AV$6:AV7,AV7)-1,"") -> 9 | AX7: =IFERROR(RANK(AU7,$AU$6:$AU$200)+COUNTIF($AU$6:AU7,AU7)-1,"") -> 5
D8: =Y6 -> $321 less was spent compared to last month | M8: =Q10&" accounts for "&TEXT(S10/S22,"0%")&" of money spent this month" -> Bills/Utilities accounts for 45% of money spent this month | V8: =IF(ISBLANK(W8),"--",TEXT(W8,"mmmm")&" "&TEXT(W8,"YYYY")) -> March 2021 | W8: 44256 | Y8: =IFERROR(TEXT(AK6,"mmmm"),"--") -> June | Z8: =SUMIFS(Table1[Amount $],Table1[Category Type],"Expense",Table1[Month],Snapshot!$W$4)*-1 -> 4154.17 | AC8: Entertainment | AD8: =SUMIFS(Table1[Amount $],Table1[Category],Snapshot!AC8,Table1[Month],Snapshot!$W$4)*-1 -> 32.38 | AE8: =RANK(AD8,$AD$6:$AD$35,0)+COUNTIF(AD$6:$AD8,AD8)-1 -> 7 | AF8: 3 | AG8: {=IF(INDEX($AD$6:$AD$35,MATCH(AF8,$AE$6:$AE$35,0),0)=0,"",INDEX($AC$6:$AC$35,MATCH(AF8,$AE$6:$AE$35,0),0))} -> Restaurants/Dining | AH8: {=IF(INDEX($AD$6:$AD$35,MATCH(AF8,$AE$6:$AE$35,0),0)=0,0,INDEX($AD$6:$AD$35,MATCH(AF8,$AE$6:$AE$35,0),0))} -> 562.29 | AJ8: =DATE(YEAR(AJ7),MONTH(AJ7),DAY(AJ7)+1) -> 36528 | AK8: =IF(MONTH(AK7)=MONTH(DATE(YEAR(AK7),MONTH(AK7),DAY(AK7)+1)),DATE(YEAR(AK7),MONTH(AK7),DAY(AK7)+1),NA()) -> 43985 | AL8: =SUMIFS(Table1[Amount $],Table1[Category Type],"Expense",Table1[Date],Snapshot!AK8)*-1 -> 109.44 | AM8: =IF(AK8>TODAY(),NA(),SUM(AL$6:$AL8)) -> 309.53 | AN8: =IF(OR(AK8=EOMONTH($AK$6,0),AK8=TODAY()),AM8,NA()) -> #N/A | AO8: =IF(MONTH(AO7)=MONTH(DATE(YEAR(AO7),MONTH(AO7),DAY(AO7)+1)),DATE(YEAR(AO7),MONTH(AO7),DAY(AO7)+1),NA()) -> 43954 | AP8: =SUMIFS(Table1[Amount $],Table1[Category Type],"Expense",Table1[Date],Snapshot!AO8)*-1 -> 0 | AQ8: =IF(AO8<=EOMONTH($AO$6,0),SUM(AP$6:$AP8),NA()) -> 577.58 | AR8: =IF(AO8=EOMONTH($AO$6,0),AQ8,NA()) -> #N/A | AT8: Overdraft Item Fee For | AU8: =IF(ISBLANK(AT8),"",SUMIFS(Table1[Amount $],Table1[Merchant],Snapshot!AT8,Table1[Month],Snapshot!$W$4)*-1) -> 180 | AV8: =IF(ISBLANK(AT8),"",COUNTIFS(Table1[Merchant],Snapshot!AT8,Table1[Month],Snapshot!$W$4)) -> 5 | AW8: =IFERROR(RANK(AV8,$AV$6:$AV$200)+COUNTIF($AV$6:AV8,AV8)-1,"") -> 2 | AX8: =IFERROR(RANK(AU8,$AU$6:$AU$200)+COUNTIF($AU$6:AU8,AU8)-1,"") -> 10
V9: =IF(ISBLANK(W9),"--",TEXT(W9,"mmmm")&" "&TEXT(W9,"YYYY")) -> February 2021 | W9: 44228 | Y9: Difference | Z9: =Z8-Z7 -> -321.47 | AC9: Fees/Charges | AD9: =SUMIFS(Table1[Amount $],Table1[Category],Snapshot!AC9,Table1[Month],Snapshot!$W$4)*-1 -> 325.95 | AE9: =RANK(AD9,$AD$6:$AD$35,0)+COUNTIF(AD$6:$AD9,AD9)-1 -> 5 | AF9: 4 | AG9: {=IF(INDEX($AD$6:$AD$35,MATCH(AF9,$AE$6:$AE$35,0),0)=0,"",INDEX($AC$6:$AC$35,MATCH(AF9,$AE$6:$AE$35,0),0))} -> Professional Services | AH9: {=IF(INDEX($AD$6:$AD$35,MATCH(AF9,$AE$6:$AE$35,0),0)=0,0,INDEX($AD$6:$AD$35,MATCH(AF9,$AE$6:$AE$35,0),0))} -> 500 | AJ9: =DATE(YEAR(AJ8),MONTH(AJ8),DAY(AJ8)+1) -> 36529 | AK9: =IF(MONTH(AK8)=MONTH(DATE(YEAR(AK8),MONTH(AK8),DAY(AK8)+1)),DATE(YEAR(AK8),MONTH(AK8),DAY(AK8)+1),NA()) -> 43986 | AL9: =SUMIFS(Table1[Amount $],Table1[Category Type],"Expense",Table1[Date],Snapshot!AK9)*-1 -> 90.9 | AM9: =IF(AK9>TODAY(),NA(),SUM(AL$6:$AL9)) -> 400.43 | AN9: =IF(OR(AK9=EOMONTH($AK$6,0),AK9=TODAY()),AM9,NA()) -> #N/A | AO9: =IF(MONTH(AO8)=MONTH(DATE(YEAR(AO8),MONTH(AO8),DAY(AO8)+1)),DATE(YEAR(AO8),MONTH(AO8),DAY(AO8)+1),NA()) -> 43955 | AP9: =SUMIFS(Table1[Amount $],Table1[Category Type],"Expense",Table1[Date],Snapshot!AO9)*-1 -> 0 | AQ9: =IF(AO9<=EOMONTH($AO$6,0),SUM(AP$6:$AP9),NA()) -> 577.58 | AR9: =IF(AO9=EOMONTH($AO$6,0),AQ9,NA()) -> #N/A | AT9: Overdraft Protection Transfer Fee | AU9: =IF(ISBLANK(AT9),"",SUMIFS(Table1[Amount $],Table1[Merchant],Snapshot!AT9,Table1[Month],Snapshot!$W$4)*-1) -> 12.5 | AV9: =IF(ISBLANK(AT9),"",COUNTIFS(Table1[Merchant],Snapshot!AT9,Table1[Month],Snapshot!$W$4)) -> 1 | AW9: =IFERROR(RANK(AV9,$AV$6:$AV$200)+COUNTIF($AV$6:AV9,AV9)-1,"") -> 10 | AX9: =IFERROR(RANK(AU9,$AU$6:$AU$200)+COUNTIF($AU$6:AU9,AU9)-1,"") -> 26
Q10: {=INDEX($AG$6:$AG$11,MATCH(1,$AF$6:$AF$11,0),0)} -> Bills/Utilities | S10: {=INDEX($AH$6:$AH$11,MATCH(1,$AF$6:$AF$11,0),0)} -> 1881.32 | V10: =IF(ISBLANK(W10),"--",TEXT(W10,"mmmm")&" "&TEXT(W10,"YYYY")) -> January 2021 | W10: 44197 | AC10: Groceries | AD10: =SUMIFS(Table1[Amount $],Table1[Category],Snapshot!AC10,Table1[Month],Snapshot!$W$4)*-1 -> 23.28 | AE10: =RANK(AD10,$AD$6:$AD$35,0)+COUNTIF(AD$6:$AD10,AD10)-1 -> 8 | AF10: 5 | AG10: {=IF(INDEX($AD$6:$AD$35,MATCH(AF10,$AE$6:$AE$35,0),0)=0,"",INDEX($AC$6:$AC$35,MATCH(AF10,$AE$6:$AE$35,0),0))} -> Fees/Charges | AH10: {=IF(INDEX($AD$6:$AD$35,MATCH(AF10,$AE$6:$AE$35,0),0)=0,0,INDEX($AD$6:$AD$35,MATCH(AF10,$AE$6:$AE$35,0),0))} -> 325.95 | AJ10: =DATE(YEAR(AJ9),MONTH(AJ9),DAY(AJ9)+1) -> 36530 | AK10: =IF(MONTH(AK9)=MONTH(DATE(YEAR(AK9),MONTH(AK9),DAY(AK9)+1)),DATE(YEAR(AK9),MONTH(AK9),DAY(AK9)+1),NA()) -> 43987 | AL10: =SUMIFS(Table1[Amount $],Table1[Category Type],"Expense",Table1[Date],Snapshot!AK10)*-1 -> 15.99 | AM10: =IF(AK10>TODAY(),NA(),SUM(AL$6:$AL10)) -> 416.42 | AN10: =IF(OR(AK10=EOMONTH($AK$6,0),AK10=TODAY()),AM10,NA()) -> #N/A | AO10: =IF(MONTH(AO9)=MONTH(DATE(YEAR(AO9),MONTH(AO9),DAY(AO9)+1)),DATE(YEAR(AO9),MONTH(AO9),DAY(AO9)+1),NA()) -> 43956 | AP10: =SUMIFS(Table1[Amount $],Table1[Category Type],"Expense",Table1[Date],Snapshot!AO10)*-1 -> 66.73 | AQ10: =IF(AO10<=EOMONTH($AO$6,0),SUM(AP$6:$AP10),NA()) -> 644.31 | AR10: =IF(AO10=EOMONTH($AO$6,0),AQ10,NA()) -> #N/A | AT10: Extended Overdraft Fee | AU10: =IF(ISBLANK(AT10),"",SUMIFS(Table1[Amount $],Table1[Merchant],Snapshot!AT10,Table1[Month],Snapshot!$W$4)*-1) -> 36 | AV10: =IF(ISBLANK(AT10),"",COUNTIFS(Table1[Merchant],Snapshot!AT10,Table1[Month],Snapshot!$W$4)) -> 1 | AW10: =IFERROR(RANK(AV10,$AV$6:$AV$200)+COUNTIF($AV$6:AV10,AV10)-1,"") -> 11 | AX10: =IFERROR(RANK(AU10,$AU$6:$AU$200)+COUNTIF($AU$6:AU10,AU10)-1,"") -> 18
V11: =IF(ISBLANK(W11),"--",TEXT(W11,"mmmm")&" "&TEXT(W11,"YYYY")) -> December 2020 | W11: 44166 | AC11: Health/Fitness | AD11: =SUMIFS(Table1[Amount $],Table1[Category],Snapshot!AC11,Table1[Month],Snapshot!$W$4)*-1 -> 0 | AE11: =RANK(AD11,$AD$6:$AD$35,0)+COUNTIF(AD$6:$AD11,AD11)-1 -> 11 | AF11: 6 | AG11: =IF(SUM(AH6:AH10)=SUM(AD6:AD35),"","All Other Categories") -> All Other Categories | AH11: =SUM(AD6:AD35)-SUM(AH6:AH10) -> 311.48 | AJ11: =DATE(YEAR(AJ10),MONTH(AJ10),DAY(AJ10)+1) -> 36531 | AK11: =IF(MONTH(AK10)=MONTH(DATE(YEAR(AK10),MONTH(AK10),DAY(AK10)+1)),DATE(YEAR(AK10),MONTH(AK10),DAY(AK10)+1),NA()) -> 43988 | AL11: =SUMIFS(Table1[Amount $],Table1[Category Type],"Expense",Table1[Date],Snapshot!AK11)*-1 -> 221.72 | AM11: =IF(AK11>TODAY(),NA(),SUM(AL$6:$AL11)) -> 638.14 | AN11: =IF(OR(AK11=EOMONTH($AK$6,0),AK11=TODAY()),AM11,NA()) -> #N/A | AO11: =IF(MONTH(AO10)=MONTH(DATE(YEAR(AO10),MONTH(AO10),DAY(AO10)+1)),DATE(YEAR(AO10),MONTH(AO10),DAY(AO10)+1),NA()) -> 43957 | AP11: =SUMIFS(Table1[Amount $],Table1[Category Type],"Expense",Table1[Date],Snapshot!AO11)*-1 -> 465.77 | AQ11: =IF(AO11<=EOMONTH($AO$6,0),SUM(AP$6:$AP11),NA()) -> 1110.08 | AR11: =IF(AO11=EOMONTH($AO$6,0),AQ11,NA()) -> #N/A | AT11: Returned Item Fee For | AU11: =IF(ISBLANK(AT11),"",SUMIFS(Table1[Amount $],Table1[Merchant],Snapshot!AT11,Table1[Month],Snapshot!$W$4)*-1) -> 36 | AV11: =IF(ISBLANK(AT11),"",COUNTIFS(Table1[Merchant],Snapshot!AT11,Table1[Month],Snapshot!$W$4)) -> 1 | AW11: =IFERROR(RANK(AV11,$AV$6:$AV$200)+COUNTIF($AV$6:AV11,AV11)-1,"") -> 12 | AX11: =IFERROR(RANK(AU11,$AU$6:$AU$200)+COUNTIF($AU$6:AU11,AU11)-1,"") -> 19
Q12: {=INDEX($AG$6:$AG$11,MATCH(2,$AF$6:$AF$11,0),0)} -> Shopping | S12: {=INDEX($AH$6:$AH$11,MATCH(2,$AF$6:$AF$11,0),0)} -> 573.13 | V12: =IF(ISBLANK(W12),"--",TEXT(W12,"mmmm")&" "&TEXT(W12,"YYYY")) -> November 2020 | W12: 44136 | AC12: Home | AD12: =SUMIFS(Table1[Amount $],Table1[Category],Snapshot!AC12,Table1[Month],Snapshot!$W$4)*-1 -> 0 | AE12: =RANK(AD12,$AD$6:$AD$35,0)+COUNTIF(AD$6:$AD12,AD12)-1 -> 12 | AG12: Total | AH12: =SUM(AH6:AH11) -> 4154.17 | AJ12: =DATE(YEAR(AJ11),MONTH(AJ11),DAY(AJ11)+1) -> 36532 | AK12: =IF(MONTH(AK11)=MONTH(DATE(YEAR(AK11),MONTH(AK11),DAY(AK11)+1)),DATE(YEAR(AK11),MONTH(AK11),DAY(AK11)+1),NA()) -> 43989 | AL12: =SUMIFS(Table1[Amount $],Table1[Category Type],"Expense",Table1[Date],Snapshot!AK12)*-1 -> 0 | AM12: =IF(AK12>TODAY(),NA(),SUM(AL$6:$AL12)) -> 638.14 | AN12: =IF(OR(AK12=EOMONTH($AK$6,0),AK12=TODAY()),AM12,NA()) -> #N/A | AO12: =IF(MONTH(AO11)=MONTH(DATE(YEAR(AO11),MONTH(AO11),DAY(AO11)+1)),DATE(YEAR(AO11),MONTH(AO11),DAY(AO11)+1),NA()) -> 43958 | AP12: =SUMIFS(Table1[Amount $],Table1[Category Type],"Expense",Table1[Date],Snapshot!AO12)*-1 -> 600.62 | AQ12: =IF(AO12<=EOMONTH($AO$6,0),SUM(AP$6:$AP12),NA()) -> 1710.7 | AR12: =IF(AO12=EOMONTH($AO$6,0),AQ12,NA()) -> #N/A | AT12: Spotify | AU12: =IF(ISBLANK(AT12),"",SUMIFS(Table1[Amount $],Table1[Merchant],Snapshot!AT12,Table1[Month],Snapshot!$W$4)*-1) -> 9.99 | AV12: =IF(ISBLANK(AT12),"",COUNTIFS(Table1[Merchant],Snapshot!AT12,Table1[Month],Snapshot!$W$4)) -> 1 | AW12: =IFERROR(RANK(AV12,$AV$6:$AV$200)+COUNTIF($AV$6:AV12,AV12)-1,"") -> 13 | AX12: =IFERROR(RANK(AU12,$AU$6:$AU$200)+COUNTIF($AU$6:AU12,AU12)-1,"") -> 29
V13: =IF(ISBLANK(W13),"--",TEXT(W13,"mmmm")&" "&TEXT(W13,"YYYY")) -> October 2020 | W13: 44105 | AC13: Misc | AD13: =SUMIFS(Table1[Amount $],Table1[Category],Snapshot!AC13,Table1[Month],Snapshot!$W$4)*-1 -> 0 | AE13: =RANK(AD13,$AD$6:$AD$35,0)+COUNTIF(AD$6:$AD13,AD13)-1 -> 13 | AJ13: =DATE(YEAR(AJ12),MONTH(AJ12),DAY(AJ12)+1) -> 36533 | AK13: =IF(MONTH(AK12)=MONTH(DATE(YEAR(AK12),MONTH(AK12),DAY(AK12)+1)),DATE(YEAR(AK12),MONTH(AK12),DAY(AK12)+1),NA()) -> 43990 | AL13: =SUMIFS(Table1[Amount $],Table1[Category Type],"Expense",Table1[Date],Snapshot!AK13)*-1 -> 609.79 | AM13: =IF(AK13>TODAY(),NA(),SUM(AL$6:$AL13)) -> 1247.93 | AN13: =IF(OR(AK13=EOMONTH($AK$6,0),AK13=TODAY()),AM13,NA()) -> #N/A | AO13: =IF(MONTH(AO12)=MONTH(DATE(YEAR(AO12),MONTH(AO12),DAY(AO12)+1)),DATE(YEAR(AO12),MONTH(AO12),DAY(AO12)+1),NA()) -> 43959 | AP13: =SUMIFS(Table1[Amount $],Table1[Category Type],"Expense",Table1[Date],Snapshot!AO13)*-1 -> 201.95 | AQ13: =IF(AO13<=EOMONTH($AO$6,0),SUM(AP$6:$AP13),NA()) -> 1912.65 | AR13: =IF(AO13=EOMONTH($AO$6,0),AQ13,NA()) -> #N/A | AT13: Jcpenney | AU13: =IF(ISBLANK(AT13),"",SUMIFS(Table1[Amount $],Table1[Merchant],Snapshot!AT13,Table1[Month],Snapshot!$W$4)*-1) -> 36 | AV13: =IF(ISBLANK(AT13),"",COUNTIFS(Table1[Merchant],Snapshot!AT13,Table1[Month],Snapshot!$W$4)) -> 1 | AW13: =IFERROR(RANK(AV13,$AV$6:$AV$200)+COUNTIF($AV$6:AV13,AV13)-1,"") -> 14 | AX13: =IFERROR(RANK(AU13,$AU$6:$AU$200)+COUNTIF($AU$6:AU13,AU13)-1,"") -> 20
Q14: {=INDEX($AG$6:$AG$11,MATCH(3,$AF$6:$AF$11,0),0)} -> Restaurants/Dining | S14: {=INDEX($AH$6:$AH$11,MATCH(3,$AF$6:$AF$11,0),0)} -> 562.29 | V14: =IF(ISBLANK(W14),"--",TEXT(W14,"mmmm")&" "&TEXT(W14,"YYYY")) -> September 2020 | W14: 44075 | AC14: Mortgage/Rent | AD14: =SUMIFS(Table1[Amount $],Table1[Category],Snapshot!AC14,Table1[Month],Snapshot!$W$4)*-1 -> 239.82 | AE14: =RANK(AD14,$AD$6:$AD$35,0)+COUNTIF(AD$6:$AD14,AD14)-1 -> 6 | AJ14: =DATE(YEAR(AJ13),MONTH(AJ13),DAY(AJ13)+1) -> 36534 | AK14: =IF(MONTH(AK13)=MONTH(DATE(YEAR(AK13),MONTH(AK13),DAY(AK13)+1)),DATE(YEAR(AK13),MONTH(AK13),DAY(AK13)+1),NA()) -> 43991 | AL14: =SUMIFS(Table1[Amount $],Table1[Category Type],"Expense",Table1[Date],Snapshot!AK14)*-1 -> 0 | AM14: =IF(AK14>TODAY(),NA(),SUM(AL$6:$AL14)) -> 1247.93 | AN14: =IF(OR(AK14=EOMONTH($AK$6,0),AK14=TODAY()),AM14,NA()) -> #N/A | AO14: =IF(MONTH(AO13)=MONTH(DATE(YEAR(AO13),MONTH(AO13),DAY(AO13)+1)),DATE(YEAR(AO13),MONTH(AO13),DAY(AO13)+1),NA()) -> 43960 | AP14: =SUMIFS(Table1[Amount $],Table1[Category Type],"Expense",Table1[Date],Snapshot!AO14)*-1 -> 192.2 | AQ14: =IF(AO14<=EOMONTH($AO$6,0),SUM(AP$6:$AP14),NA()) -> 2104.85 | AR14: =IF(AO14=EOMONTH($AO$6,0),AQ14,NA()) -> #N/A | AT14: Mcdonald's | AU14: =IF(ISBLANK(AT14),"",SUMIFS(Table1[Amount $],Table1[Merchant],Snapshot!AT14,Table1[Month],Snapshot!$W$4)*-1) -> 127.83 | AV14: =IF(ISBLANK(AT14),"",COUNTIFS(Table1[Merchant],Snapshot!AT14,Table1[Month],Snapshot!$W$4)) -> 5 | AW14: =IFERROR(RANK(AV14,$AV$6:$AV$200)+COUNTIF($AV$6:AV14,AV14)-1,"") -> 3 | AX14: =IFERROR(RANK(AU14,$AU$6:$AU$200)+COUNTIF($AU$6:AU14,AU14)-1,"") -> 13
V15: =IF(ISBLANK(W15),"--",TEXT(W15,"mmmm")&" "&TEXT(W15,"YYYY")) -> August 2020 | W15: 44044 | AC15: Payment | AD15: =SUMIFS(Table1[Amount $],Table1[Category],Snapshot!AC15,Table1[Month],Snapshot!$W$4)*-1 -> 16 | AE15: =RANK(AD15,$AD$6:$AD$35,0)+COUNTIF(AD$6:$AD15,AD15)-1 -> 9 | AJ15: =DATE(YEAR(AJ14),MONTH(AJ14),DAY(AJ14)+1) -> 36535 | AK15: =IF(MONTH(AK14)=MONTH(DATE(YEAR(AK14),MONTH(AK14),DAY(AK14)+1)),DATE(YEAR(AK14),MONTH(AK14),DAY(AK14)+1),NA()) -> 43992 | AL15: =SUMIFS(Table1[Amount $],Table1[Category Type],"Expense",Table1[Date],Snapshot!AK15)*-1 -> 0 | AM15: =IF(AK15>TODAY(),NA(),SUM(AL$6:$AL15)) -> 1247.93 | AN15: =IF(OR(AK15=EOMONTH($AK$6,0),AK15=TODAY()),AM15,NA()) -> #N/A | AO15: =IF(MONTH(AO14)=MONTH(DATE(YEAR(AO14),MONTH(AO14),DAY(AO14)+1)),DATE(YEAR(AO14),MONTH(AO14),DAY(AO14)+1),NA()) -> 43961 | AP15: =SUMIFS(Table1[Amount $],Table1[Category Type],"Expense",Table1[Date],Snapshot!AO15)*-1 -> 42.77 | AQ15: =IF(AO15<=EOMONTH($AO$6,0),SUM(AP$6:$AP15),NA()) -> 2147.62 | AR15: =IF(AO15=EOMONTH($AO$6,0),AQ15,NA()) -> #N/A | AT15: Electronic Debit Shen Life | AU15: =IF(ISBLANK(AT15),"",SUMIFS(Table1[Amount $],Table1[Merchant],Snapshot!AT15,Table1[Month],Snapshot!$W$4)*-1) -> 40.28 | AV15: =IF(ISBLANK(AT15),"",COUNTIFS(Table1[Merchant],Snapshot!AT15,Table1[Month],Snapshot!$W$4)) -> 1 | AW15: =IFERROR(RANK(AV15,$AV$6:$AV$200)+COUNTIF($AV$6:AV15,AV15)-1,"") -> 15 | AX15: =IFERROR(RANK(AU15,$AU$6:$AU$200)+COUNTIF($AU$6:AU15,AU15)-1,"") -> 17
Q16: {=INDEX($AG$6:$AG$11,MATCH(4,$AF$6:$AF$11,0),0)} -> Professional Services | S16: {=INDEX($AH$6:$AH$11,MATCH(4,$AF$6:$AF$11,0),0)} -> 500 | V16: =IF(ISBLANK(W16),"--",TEXT(W16,"mmmm")&" "&TEXT(W16,"YYYY")) -> July 2020 | W16: 44013 | AC16: Professional Services | AD16: =SUMIFS(Table1[Amount $],Table1[Category],Snapshot!AC16,Table1[Month],Snapshot!$W$4)*-1 -> 500 | AE16: =RANK(AD16,$AD$6:$AD$35,0)+COUNTIF(AD$6:$AD16,AD16)-1 -> 4 | AJ16: =DATE(YEAR(AJ15),MONTH(AJ15),DAY(AJ15)+1) -> 36536 | AK16: =IF(MONTH(AK15)=MONTH(DATE(YEAR(AK15),MONTH(AK15),DAY(AK15)+1)),DATE(YEAR(AK15),MONTH(AK15),DAY(AK15)+1),NA()) -> 43993 | AL16: =SUMIFS(Table1[Amount $],Table1[Category Type],"Expense",Table1[Date],Snapshot!AK16)*-1 -> 501.95 | AM16: =IF(AK16>TODAY(),NA(),SUM(AL$6:$AL16)) -> 1749.88 | AN16: =IF(OR(AK16=EOMONTH($AK$6,0),AK16=TODAY()),AM16,NA()) -> #N/A | AO16: =IF(MONTH(AO15)=MONTH(DATE(YEAR(AO15),MONTH(AO15),DAY(AO15)+1)),DATE(YEAR(AO15),MONTH(AO15),DAY(AO15)+1),NA()) -> 43962 | AP16: =SUMIFS(Table1[Amount $],Table1[Category Type],"Expense",Table1[Date],Snapshot!AO16)*-1 -> 139.79 | AQ16: =IF(AO16<=EOMONTH($AO$6,0),SUM(AP$6:$AP16),NA()) -> 2287.41 | AR16: =IF(AO16=EOMONTH($AO$6,0),AQ16,NA()) -> #N/A | AT16: Check Card Purchase Doordash | AU16: =IF(ISBLANK(AT16),"",SUMIFS(Table1[Amount $],Table1[Merchant],Snapshot!AT16,Table1[Month],Snapshot!$W$4)*-1) -> 386.67 | AV16: =IF(ISBLANK(AT16),"",COUNTIFS(Table1[Merchant],Snapshot!AT16,Table1[Month],Snapshot!$W$4)) -> 7 | AW16: =IFERROR(RANK(AV16,$AV$6:$AV$200)+COUNTIF($AV$6:AV16,AV16)-1,"") -> 1 | AX16: =IFERROR(RANK(AU16,$AU$6:$AU$200)+COUNTIF($AU$6:AU16,AU16)-1,"") -> 3
V17: =IF(ISBLANK(W17),"--",TEXT(W17,"mmmm")&" "&TEXT(W17,"YYYY")) -> June 2020 | W17: 43983 | AC17: Restaurants/Dining | AD17: =SUMIFS(Table1[Amount $],Table1[Category],Snapshot!AC17,Table1[Month],Snapshot!$W$4)*-1 -> 562.29 | AE17: =RANK(AD17,$AD$6:$AD$35,0)+COUNTIF(AD$6:$AD17,AD17)-1 -> 3 | AJ17: =DATE(YEAR(AJ16),MONTH(AJ16),DAY(AJ16)+1) -> 36537 | AK17: =IF(MONTH(AK16)=MONTH(DATE(YEAR(AK16),MONTH(AK16),DAY(AK16)+1)),DATE(YEAR(AK16),MONTH(AK16),DAY(AK16)+1),NA()) -> 43994 | AL17: =SUMIFS(Table1[Amount $],Table1[Category Type],"Expense",Table1[Date],Snapshot!AK17)*-1 -> 343.58 | AM17: =IF(AK17>TODAY(),NA(),SUM(AL$6:$AL17)) -> 2093.46 | AN17: =IF(OR(AK17=EOMONTH($AK$6,0),AK17=TODAY()),AM17,NA()) -> #N/A | AO17: =IF(MONTH(AO16)=MONTH(DATE(YEAR(AO16),MONTH(AO16),DAY(AO16)+1)),DATE(YEAR(AO16),MONTH(AO16),DAY(AO16)+1),NA()) -> 43963 | AP17: =SUMIFS(Table1[Amount $],Table1[Category Type],"Expense",Table1[Date],Snapshot!AO17)*-1 -> 30.91 | AQ17: =IF(AO17<=EOMONTH($AO$6,0),SUM(AP$6:$AP17),NA()) -> 2318.32 | AR17: =IF(AO17=EOMONTH($AO$6,0),AQ17,NA()) -> #N/A | AT17: Cvs | AU17: =IF(ISBLANK(AT17),"",SUMIFS(Table1[Amount $],Table1[Merchant],Snapshot!AT17,Table1[Month],Snapshot!$W$4)*-1) -> 132.35 | AV17: =IF(ISBLANK(AT17),"",COUNTIFS(Table1[Merchant],Snapshot!AT17,Table1[Month],Snapshot!$W$4)) -> 1 | AW17: =IFERROR(RANK(AV17,$AV$6:$AV$200)+COUNTIF($AV$6:AV17,AV17)-1,"") -> 16 | AX17: =IFERROR(RANK(AU17,$AU$6:$AU$200)+COUNTIF($AU$6:AU17,AU17)-1,"") -> 12
Q18: {=INDEX($AG$6:$AG$11,MATCH(5,$AF$6:$AF$11,0),0)} -> Fees/Charges | S18: {=INDEX($AH$6:$AH$11,MATCH(5,$AF$6:$AF$11,0),0)} -> 325.95 | V18: =IF(ISBLANK(W18),"--",TEXT(W18,"mmmm")&" "&TEXT(W18,"YYYY")) -> May 2020 | W18: 43952 | AC18: Shopping | AD18: =SUMIFS(Table1[Amount $],Table1[Category],Snapshot!AC18,Table1[Month],Snapshot!$W$4)*-1 -> 573.13 | AE18: =RANK(AD18,$AD$6:$AD$35,0)+COUNTIF(AD$6:$AD18,AD18)-1 -> 2 | AJ18: =DATE(YEAR(AJ17),MONTH(AJ17),DAY(AJ17)+1) -> 36538 | AK18: =IF(MONTH(AK17)=MONTH(DATE(YEAR(AK17),MONTH(AK17),DAY(AK17)+1)),DATE(YEAR(AK17),MONTH(AK17),DAY(AK17)+1),NA()) -> 43995 | AL18: =SUMIFS(Table1[Amount $],Table1[Category Type],"Expense",Table1[Date],Snapshot!AK18)*-1 -> 36.04 | AM18: =IF(AK18>TODAY(),NA(),SUM(AL$6:$AL18)) -> 2129.5 | AN18: =IF(OR(AK18=EOMONTH($AK$6,0),AK18=TODAY()),AM18,NA()) -> #N/A | AO18: =IF(MONTH(AO17)=MONTH(DATE(YEAR(AO17),MONTH(AO17),DAY(AO17)+1)),DATE(YEAR(AO17),MONTH(AO17),DAY(AO17)+1),NA()) -> 43964 | AP18: =SUMIFS(Table1[Amount $],Table1[Category Type],"Expense",Table1[Date],Snapshot!AO18)*-1 -> 65.79 | AQ18: =IF(AO18<=EOMONTH($AO$6,0),SUM(AP$6:$AP18),NA()) -> 2384.11 | AR18: =IF(AO18=EOMONTH($AO$6,0),AQ18,NA()) -> #N/A | AT18: Electronic Debit Schwan S | AU18: =IF(ISBLANK(AT18),"",SUMIFS(Table1[Amount $],Table1[Merchant],Snapshot!AT18,Table1[Month],Snapshot!$W$4)*-1) -> 205.07 | AV18: =IF(ISBLANK(AT18),"",COUNTIFS(Table1[Merchant],Snapshot!AT18,Table1[Month],Snapshot!$W$4)) -> 2 | AW18: =IFERROR(RANK(AV18,$AV$6:$AV$200)+COUNTIF($AV$6:AV18,AV18)-1,"") -> 5 | AX18: =IFERROR(RANK(AU18,$AU$6:$AU$200)+COUNTIF($AU$6:AU18,AU18)-1,"") -> 8
V19: =IF(ISBLANK(W19),"--",TEXT(W19,"mmmm")&" "&TEXT(W19,"YYYY")) -> April 2020 | W19: 43922 | AC19: Travel | AD19: =SUMIFS(Table1[Amount $],Table1[Category],Snapshot!AC19,Table1[Month],Snapshot!$W$4)*-1 -> 0 | AE19: =RANK(AD19,$AD$6:$AD$35,0)+COUNTIF(AD$6:$AD19,AD19)-1 -> 14 | AJ19: =DATE(YEAR(AJ18),MONTH(AJ18),DAY(AJ18)+1) -> 36539 | AK19: =IF(MONTH(AK18)=MONTH(DATE(YEAR(AK18),MONTH(AK18),DAY(AK18)+1)),DATE(YEAR(AK18),MONTH(AK18),DAY(AK18)+1),NA()) -> 43996 | AL19: =SUMIFS(Table1[Amount $],Table1[Category Type],"Expense",Table1[Date],Snapshot!AK19)*-1 -> 0 | AM19: =IF(AK19>TODAY(),NA(),SUM(AL$6:$AL19)) -> 2129.5 | AN19: =IF(OR(AK19=EOMONTH($AK$6,0),AK19=TODAY()),AM19,NA()) -> #N/A | AO19: =IF(MONTH(AO18)=MONTH(DATE(YEAR(AO18),MONTH(AO18),DAY(AO18)+1)),DATE(YEAR(AO18),MONTH(AO18),DAY(AO18)+1),NA()) -> 43965 | AP19: =SUMIFS(Table1[Amount $],Table1[Category Type],"Expense",Table1[Date],Snapshot!AO19)*-1 -> 127.88 | AQ19: =IF(AO19<=EOMONTH($AO$6,0),SUM(AP$6:$AP19),NA()) -> 2511.99 | AR19: =IF(AO19=EOMONTH($AO$6,0),AQ19,NA()) -> #N/A | AT19: Electronic Debit Td Auto | AU19: =IF(ISBLANK(AT19),"",SUMIFS(Table1[Amount $],Table1[Merchant],Snapshot!AT19,Table1[Month],Snapshot!$W$4)*-1) -> 239.82 | AV19: =IF(ISBLANK(AT19),"",COUNTIFS(Table1[Merchant],Snapshot!AT19,Table1[Month],Snapshot!$W$4)) -> 1 | AW19: =IFERROR(RANK(AV19,$AV$6:$AV$200)+COUNTIF($AV$6:AV19,AV19)-1,"") -> 17 | AX19: =IFERROR(RANK(AU19,$AU$6:$AU$200)+COUNTIF($AU$6:AU19,AU19)-1,"") -> 7
Q20: {=INDEX($AG$6:$AG$11,MATCH(6,$AF$6:$AF$11,0),0)} -> All Other Categories | S20: {=INDEX($AH$6:$AH$11,MATCH(6,$AF$6:$AF$11,0),0)} -> 311.48 | V20: =IF(ISBLANK(W20),"--",TEXT(W20,"mmmm")&" "&TEXT(W20,"YYYY")) -> March 2020 | W20: 43891 | AC20: Uncategorized | AD20: =SUMIFS(Table1[Amount $],Table1[Category],Snapshot!AC20,Table1[Month],Snapshot!$W$4)*-1 -> 0 | AE20: =RANK(AD20,$AD$6:$AD$35,0)+COUNTIF(AD$6:$AD20,AD20)-1 -> 15 | AJ20: =DATE(YEAR(AJ19),MONTH(AJ19),DAY(AJ19)+1) -> 36540 | AK20: =IF(MONTH(AK19)=MONTH(DATE(YEAR(AK19),MONTH(AK19),DAY(AK19)+1)),DATE(YEAR(AK19),MONTH(AK19),DAY(AK19)+1),NA()) -> 43997 | AL20: =SUMIFS(Table1[Amount $],Table1[Category Type],"Expense",Table1[Date],Snapshot!AK20)*-1 -> 331.03 | AM20: =IF(AK20>TODAY(),NA(),SUM(AL$6:$AL20)) -> 2460.53 | AN20: =IF(OR(AK20=EOMONTH($AK$6,0),AK20=TODAY()),AM20,NA()) -> #N/A | AO20: =IF(MONTH(AO19)=MONTH(DATE(YEAR(AO19),MONTH(AO19),DAY(AO19)+1)),DATE(YEAR(AO19),MONTH(AO19),DAY(AO19)+1),NA()) -> 43966 | AP20: =SUMIFS(Table1[Amount $],Table1[Category Type],"Expense",Table1[Date],Snapshot!AO20)*-1 -> 52.59 | AQ20: =IF(AO20<=EOMONTH($AO$6,0),SUM(AP$6:$AP20),NA()) -> 2564.58 | AR20: =IF(AO20=EOMONTH($AO$6,0),AQ20,NA()) -> #N/A | AT20: Point Of Sale Debit | AU20: =IF(ISBLANK(AT20),"",SUMIFS(Table1[Amount $],Table1[Merchant],Snapshot!AT20,Table1[Month],Snapshot!$W$4)*-1) -> 186.72 | AV20: =IF(ISBLANK(AT20),"",COUNTIFS(Table1[Merchant],Snapshot!AT20,Table1[Month],Snapshot!$W$4)) -> 4 | AW20: =IFERROR(RANK(AV20,$AV$6:$AV$200)+COUNTIF($AV$6:AV20,AV20)-1,"") -> 4 | AX20: =IFERROR(RANK(AU20,$AU$6:$AU$200)+COUNTIF($AU$6:AU20,AU20)-1,"") -> 9
V21: =IF(ISBLANK(W21),"--",TEXT(W21,"mmmm")&" "&TEXT(W21,"YYYY")) -> February 2020 | W21: 43862 | AC21: Apps | AD21: =SUMIFS(Table1[Amount $],Table1[Category],Snapshot!AC21,Table1[Month],Snapshot!$W$4)*-1 -> 0 | AE21: =RANK(AD21,$AD$6:$AD$35,0)+COUNTIF(AD$6:$AD21,AD21)-1 -> 16 | AJ21: =DATE(YEAR(AJ20),MONTH(AJ20),DAY(AJ20)+1) -> 36541 | AK21: =IF(MONTH(AK20)=MONTH(DATE(YEAR(AK20),MONTH(AK20),DAY(AK20)+1)),DATE(YEAR(AK20),MONTH(AK20),DAY(AK20)+1),NA()) -> 43998 | AL21: =SUMIFS(Table1[Amount $],Table1[Category Type],"Expense",Table1[Date],Snapshot!AK21)*-1 -> 138.35 | AM21: =IF(AK21>TODAY(),NA(),SUM(AL$6:$AL21)) -> 2598.88 | AN21: =IF(OR(AK21=EOMONTH($AK$6,0),AK21=TODAY()),AM21,NA()) -> #N/A | AO21: =IF(MONTH(AO20)=MONTH(DATE(YEAR(AO20),MONTH(AO20),DAY(AO20)+1)),DATE(YEAR(AO20),MONTH(AO20),DAY(AO20)+1),NA()) -> 43967 | AP21: =SUMIFS(Table1[Amount $],Table1[Category Type],"Expense",Table1[Date],Snapshot!AO21)*-1 -> 0 | AQ21: =IF(AO21<=EOMONTH($AO$6,0),SUM(AP$6:$AP21),NA()) -> 2564.58 | AR21: =IF(AO21=EOMONTH($AO$6,0),AQ21,NA()) -> #N/A | AT21: Check Card Purchase Subway | AU21: =IF(ISBLANK(AT21),"",SUMIFS(Table1[Amount $],Table1[Merchant],Snapshot!AT21,Table1[Month],Snapshot!$W$4)*-1) -> 12.19 | AV21: =IF(ISBLANK(AT21),"",COUNTIFS(Table1[Merchant],Snapshot!AT21,Table1[Month],Snapshot!$W$4)) -> 1 | AW21: =IFERROR(RANK(AV21,$AV$6:$AV$200)+COUNTIF($AV$6:AV21,AV21)-1,"") -> 18 | AX21: =IFERROR(RANK(AU21,$AU$6:$AU$200)+COUNTIF($AU$6:AU21,AU21)-1,"") -> 27
P22: Total spending | S22: =S10+S12+S14+S16+S18+S20 -> 4154.17 | V22: =IF(ISBLANK(W22),"--",TEXT(W22,"mmmm")&" "&TEXT(W22,"YYYY")) -> January 2020 | W22: 43831 | AC22: Education | AD22: =SUMIFS(Table1[Amount $],Table1[Category],Snapshot!AC22,Table1[Month],Snapshot!$W$4)*-1 -> 0 | AE22: =RANK(AD22,$AD$6:$AD$35,0)+COUNTIF(AD$6:$AD22,AD22)-1 -> 17 | AJ22: =DATE(YEAR(AJ21),MONTH(AJ21),DAY(AJ21)+1) -> 36542 | AK22: =IF(MONTH(AK21)=MONTH(DATE(YEAR(AK21),MONTH(AK21),DAY(AK21)+1)),DATE(YEAR(AK21),MONTH(AK21),DAY(AK21)+1),NA()) -> 43999 | AL22: =SUMIFS(Table1[Amount $],Table1[Category Type],"Expense",Table1[Date],Snapshot!AK22)*-1 -> 10.9 | AM22: =IF(AK22>TODAY(),NA(),SUM(AL$6:$AL22)) -> 2609.78 | AN22: =IF(OR(AK22=EOMONTH($AK$6,0),AK22=TODAY()),AM22,NA()) -> #N/A | AO22: =IF(MONTH(AO21)=MONTH(DATE(YEAR(AO21),MONTH(AO21),DAY(AO21)+1)),DATE(YEAR(AO21),MONTH(AO21),DAY(AO21)+1),NA()) -> 43968 | AP22: =SUMIFS(Table1[Amount $],Table1[Category Type],"Expense",Table1[Date],Snapshot!AO22)*-1 -> 43.11 | AQ22: =IF(AO22<=EOMONTH($AO$6,0),SUM(AP$6:$AP22),NA()) -> 2607.69 | AR22: =IF(AO22=EOMONTH($AO$6,0),AQ22,NA()) -> #N/A | AT22: T Mobile | AU22: =IF(ISBLANK(AT22),"",SUMIFS(Table1[Amount $],Table1[Merchant],Snapshot!AT22,Table1[Month],Snapshot!$W$4)*-1) -> 75.92 | AV22: =IF(ISBLANK(AT22),"",COUNTIFS(Table1[Merchant],Snapshot!AT22,Table1[Month],Snapshot!$W$4)) -> 1 | AW22: =IFERROR(RANK(AV22,$AV$6:$AV$200)+COUNTIF($AV$6:AV22,AV22)-1,"") -> 19 | AX22: =IFERROR(RANK(AU22,$AU$6:$AU$200)+COUNTIF($AU$6:AU22,AU22)-1,"") -> 16
V23: =IF(ISBLANK(W23),"--",TEXT(W23,"mmmm")&" "&TEXT(W23,"YYYY")) -> December 2019 | W23: 43800 | AC23: Government | AD23: =SUMIFS(Table1[Amount $],Table1[Category],Snapshot!AC23,Table1[Month],Snapshot!$W$4)*-1 -> 0 | AE23: =RANK(AD23,$AD$6:$AD$35,0)+COUNTIF(AD$6:$AD23,AD23)-1 -> 18 | AJ23: =DATE(YEAR(AJ22),MONTH(AJ22),DAY(AJ22)+1) -> 36543 | AK23: =IF(MONTH(AK22)=MONTH(DATE(YEAR(AK22),MONTH(AK22),DAY(AK22)+1)),DATE(YEAR(AK22),MONTH(AK22),DAY(AK22)+1),NA()) -> 44000 | AL23: =SUMIFS(Table1[Amount $],Table1[Category Type],"Expense",Table1[Date],Snapshot!AK23)*-1 -> 75.92 | AM23: =IF(AK23>TODAY(),NA(),SUM(AL$6:$AL23)) -> 2685.7 | AN23: =IF(OR(AK23=EOMONTH($AK$6,0),AK23=TODAY()),AM23,NA()) -> #N/A | AO23: =IF(MONTH(AO22)=MONTH(DATE(YEAR(AO22),MONTH(AO22),DAY(AO22)+1)),DATE(YEAR(AO22),MONTH(AO22),DAY(AO22)+1),NA()) -> 43969 | AP23: =SUMIFS(Table1[Amount $],Table1[Category Type],"Expense",Table1[Date],Snapshot!AO23)*-1 -> 155.77 | AQ23: =IF(AO23<=EOMONTH($AO$6,0),SUM(AP$6:$AP23),NA()) -> 2763.46 | AR23: =IF(AO23=EOMONTH($AO$6,0),AQ23,NA()) -> #N/A | AT23: Electronic Debit Transamerica Ins | AU23: =IF(ISBLANK(AT23),"",SUMIFS(Table1[Amount $],Table1[Merchant],Snapshot!AT23,Table1[Month],Snapshot!$W$4)*-1) -> 10.9 | AV23: =IF(ISBLANK(AT23),"",COUNTIFS(Table1[Merchant],Snapshot!AT23,Table1[Month],Snapshot!$W$4)) -> 1 | AW23: =IFERROR(RANK(AV23,$AV$6:$AV$200)+COUNTIF($AV$6:AV23,AV23)-1,"") -> 20 | AX23: =IFERROR(RANK(AU23,$AU$6:$AU$200)+COUNTIF($AU$6:AU23,AU23)-1,"") -> 28
V24: =IF(ISBLANK(W24),"--",TEXT(W24,"mmmm")&" "&TEXT(W24,"YYYY")) -> November 2019 | W24: 43770 | AC24: Loan | AD24: =SUMIFS(Table1[Amount $],Table1[Category],Snapshot!AC24,Table1[Month],Snapshot!$W$4)*-1 -> 0 | AE24: =RANK(AD24,$AD$6:$AD$35,0)+COUNTIF(AD$6:$AD24,AD24)-1 -> 19 | AJ24: =DATE(YEAR(AJ23),MONTH(AJ23),DAY(AJ23)+1) -> 36544 | AK24: =IF(MONTH(AK23)=MONTH(DATE(YEAR(AK23),MONTH(AK23),DAY(AK23)+1)),DATE(YEAR(AK23),MONTH(AK23),DAY(AK23)+1),NA()) -> 44001 | AL24: =SUMIFS(Table1[Amount $],Table1[Category Type],"Expense",Table1[Date],Snapshot!AK24)*-1 -> 0 | AM24: =IF(AK24>TODAY(),NA(),SUM(AL$6:$AL24)) -> 2685.7 | AN24: =IF(OR(AK24=EOMONTH($AK$6,0),AK24=TODAY()),AM24,NA()) -> #N/A | AO24: =IF(MONTH(AO23)=MONTH(DATE(YEAR(AO23),MONTH(AO23),DAY(AO23)+1)),DATE(YEAR(AO23),MONTH(AO23),DAY(AO23)+1),NA()) -> 43970 | AP24: =SUMIFS(Table1[Amount $],Table1[Category Type],"Expense",Table1[Date],Snapshot!AO24)*-1 -> 37.68 | AQ24: =IF(AO24<=EOMONTH($AO$6,0),SUM(AP$6:$AP24),NA()) -> 2801.14 | AR24: =IF(AO24=EOMONTH($AO$6,0),AQ24,NA()) -> #N/A | AT24: Electronic Debit Aft A | AU24: =IF(ISBLANK(AT24),"",SUMIFS(Table1[Amount $],Table1[Merchant],Snapshot!AT24,Table1[Month],Snapshot!$W$4)*-1) -> 79.85 | AV24: =IF(ISBLANK(AT24),"",COUNTIFS(Table1[Merchant],Snapshot!AT24,Table1[Month],Snapshot!$W$4)) -> 1 | AW24: =IFERROR(RANK(AV24,$AV$6:$AV$200)+COUNTIF($AV$6:AV24,AV24)-1,"") -> 21 | AX24: =IFERROR(RANK(AU24,$AU$6:$AU$200)+COUNTIF($AU$6:AU24,AU24)-1,"") -> 15
V25: =IF(ISBLANK(W25),"--",TEXT(W25,"mmmm")&" "&TEXT(W25,"YYYY")) -> October 2019 | W25: 43739 | AD25: =SUMIFS(Table1[Amount $],Table1[Category],Snapshot!AC25,Table1[Month],Snapshot!$W$4)*-1 -> 0 | AE25: =RANK(AD25,$AD$6:$AD$35,0)+COUNTIF(AD$6:$AD25,AD25)-1 -> 20 | AJ25: =DATE(YEAR(AJ24),MONTH(AJ24),DAY(AJ24)+1) -> 36545 | AK25: =IF(MONTH(AK24)=MONTH(DATE(YEAR(AK24),MONTH(AK24),DAY(AK24)+1)),DATE(YEAR(AK24),MONTH(AK24),DAY(AK24)+1),NA()) -> 44002 | AL25: =SUMIFS(Table1[Amount $],Table1[Category Type],"Expense",Table1[Date],Snapshot!AK25)*-1 -> 53.22 | AM25: =IF(AK25>TODAY(),NA(),SUM(AL$6:$AL25)) -> 2738.92 | AN25: =IF(OR(AK25=EOMONTH($AK$6,0),AK25=TODAY()),AM25,NA()) -> #N/A | AO25: =IF(MONTH(AO24)=MONTH(DATE(YEAR(AO24),MONTH(AO24),DAY(AO24)+1)),DATE(YEAR(AO24),MONTH(AO24),DAY(AO24)+1),NA()) -> 43971 | AP25: =SUMIFS(Table1[Amount $],Table1[Category Type],"Expense",Table1[Date],Snapshot!AO25)*-1 -> 0 | AQ25: =IF(AO25<=EOMONTH($AO$6,0),SUM(AP$6:$AP25),NA()) -> 2801.14 | AR25: =IF(AO25=EOMONTH($AO$6,0),AQ25,NA()) -> #N/A | AT25: Electronic Debit Washington Gas | AU25: =IF(ISBLANK(AT25),"",SUMIFS(Table1[Amount $],Table1[Merchant],Snapshot!AT25,Table1[Month],Snapshot!$W$4)*-1) -> 297.75 | AV25: =IF(ISBLANK(AT25),"",COUNTIFS(Table1[Merchant],Snapshot!AT25,Table1[Month],Snapshot!$W$4)) -> 1 | AW25: =IFERROR(RANK(AV25,$AV$6:$AV$200)+COUNTIF($AV$6:AV25,AV25)-1,"") -> 22 | AX25: =IFERROR(RANK(AU25,$AU$6:$AU$200)+COUNTIF($AU$6:AU25,AU25)-1,"") -> 6
V26: =IF(ISBLANK(W26),"--",TEXT(W26,"mmmm")&" "&TEXT(W26,"YYYY")) -> -- | AD26: =SUMIFS(Table1[Amount $],Table1[Category],Snapshot!AC26,Table1[Month],Snapshot!$W$4)*-1 -> 0 | AE26: =RANK(AD26,$AD$6:$AD$35,0)+COUNTIF(AD$6:$AD26,AD26)-1 -> 21 | AJ26: =DATE(YEAR(AJ25),MONTH(AJ25),DAY(AJ25)+1) -> 36546 | AK26: =IF(MONTH(AK25)=MONTH(DATE(YEAR(AK25),MONTH(AK25),DAY(AK25)+1)),DATE(YEAR(AK25),MONTH(AK25),DAY(AK25)+1),NA()) -> 44003 | AL26: =SUMIFS(Table1[Amount $],Table1[Category Type],"Expense",Table1[Date],Snapshot!AK26)*-1 -> 53.44 | AM26: =IF(AK26>TODAY(),NA(),SUM(AL$6:$AL26)) -> 2792.36 | AN26: =IF(OR(AK26=EOMONTH($AK$6,0),AK26=TODAY()),AM26,NA()) -> #N/A | AO26: =IF(MONTH(AO25)=MONTH(DATE(YEAR(AO25),MONTH(AO25),DAY(AO25)+1)),DATE(YEAR(AO25),MONTH(AO25),DAY(AO25)+1),NA()) -> 43972 | AP26: =SUMIFS(Table1[Amount $],Table1[Category Type],"Expense",Table1[Date],Snapshot!AO26)*-1 -> 0 | AQ26: =IF(AO26<=EOMONTH($AO$6,0),SUM(AP$6:$AP26),NA()) -> 2801.14 | AR26: =IF(AO26=EOMONTH($AO$6,0),AQ26,NA()) -> #N/A | AT26: Electronic Debit Potomac Elec | AU26: =IF(ISBLANK(AT26),"",SUMIFS(Table1[Amount $],Table1[Merchant],Snapshot!AT26,Table1[Month],Snapshot!$W$4)*-1) -> 343.58 | AV26: =IF(ISBLANK(AT26),"",COUNTIFS(Table1[Merchant],Snapshot!AT26,Table1[Month],Snapshot!$W$4)) -> 1 | AW26: =IFERROR(RANK(AV26,$AV$6:$AV$200)+COUNTIF($AV$6:AV26,AV26)-1,"") -> 23 | AX26: =IFERROR(RANK(AU26,$AU$6:$AU$200)+COUNTIF($AU$6:AU26,AU26)-1,"") -> 4
D27: Cumulative spending throughout month | V27: =IF(ISBLANK(W27),"--",TEXT(W27,"mmmm")&" "&TEXT(W27,"YYYY")) -> -- | AD27: =SUMIFS(Table1[Amount $],Table1[Category],Snapshot!AC27,Table1[Month],Snapshot!$W$4)*-1 -> 0 | AE27: =RANK(AD27,$AD$6:$AD$35,0)+COUNTIF(AD$6:$AD27,AD27)-1 -> 22 | AJ27: =DATE(YEAR(AJ26),MONTH(AJ26),DAY(AJ26)+1) -> 36547 | AK27: =IF(MONTH(AK26)=MONTH(DATE(YEAR(AK26),MONTH(AK26),DAY(AK26)+1)),DATE(YEAR(AK26),MONTH(AK26),DAY(AK26)+1),NA()) -> 44004 | AL27: =SUMIFS(Table1[Amount $],Table1[Category Type],"Expense",Table1[Date],Snapshot!AK27)*-1 -> 602.4 | AM27: =IF(AK27>TODAY(),NA(),SUM(AL$6:$AL27)) -> 3394.76 | AN27: =IF(OR(AK27=EOMONTH($AK$6,0),AK27=TODAY()),AM27,NA()) -> #N/A | AO27: =IF(MONTH(AO26)=MONTH(DATE(YEAR(AO26),MONTH(AO26),DAY(AO26)+1)),DATE(YEAR(AO26),MONTH(AO26),DAY(AO26)+1),NA()) -> 43973 | AP27: =SUMIFS(Table1[Amount $],Table1[Category Type],"Expense",Table1[Date],Snapshot!AO27)*-1 -> 92.55 | AQ27: =IF(AO27<=EOMONTH($AO$6,0),SUM(AP$6:$AP27),NA()) -> 2893.69 | AR27: =IF(AO27=EOMONTH($AO$6,0),AQ27,NA()) -> #N/A | AT27: Check Card Purchase Avedon | AU27: =IF(ISBLANK(AT27),"",SUMIFS(Table1[Amount $],Table1[Merchant],Snapshot!AT27,Table1[Month],Snapshot!$W$4)*-1) -> 500 | AV27: =IF(ISBLANK(AT27),"",COUNTIFS(Table1[Merchant],Snapshot!AT27,Table1[Month],Snapshot!$W$4)) -> 1 | AW27: =IFERROR(RANK(AV27,$AV$6:$AV$200)+COUNTIF($AV$6:AV27,AV27)-1,"") -> 24 | AX27: =IFERROR(RANK(AU27,$AU$6:$AU$200)+COUNTIF($AU$6:AU27,AU27)-1,"") -> 2
D28: =IFERROR(IF(AND(MONTH(W4)=MONTH(TODAY()),YEAR(W4)=YEAR(TODAY())),AK39,AK42),"") -> Compared to May, you spent $321 less | V28: =IF(ISBLANK(W28),"--",TEXT(W28,"mmmm")&" "&TEXT(W28,"YYYY")) -> -- | AD28: =SUMIFS(Table1[Amount $],Table1[Category],Snapshot!AC28,Table1[Month],Snapshot!$W$4)*-1 -> 0 | AE28: =RANK(AD28,$AD$6:$AD$35,0)+COUNTIF(AD$6:$AD28,AD28)-1 -> 23 | AJ28: =DATE(YEAR(AJ27),MONTH(AJ27),DAY(AJ27)+1) -> 36548 | AK28: =IF(MONTH(AK27)=MONTH(DATE(YEAR(AK27),MONTH(AK27),DAY(AK27)+1)),DATE(YEAR(AK27),MONTH(AK27),DAY(AK27)+1),NA()) -> 44005 | AL28: =SUMIFS(Table1[Amount $],Table1[Category Type],"Expense",Table1[Date],Snapshot!AK28)*-1 -> 72 | AM28: =IF(AK28>TODAY(),NA(),SUM(AL$6:$AL28)) -> 3466.76 | AN28: =IF(OR(AK28=EOMONTH($AK$6,0),AK28=TODAY()),AM28,NA()) -> #N/A | AO28: =IF(MONTH(AO27)=MONTH(DATE(YEAR(AO27),MONTH(AO27),DAY(AO27)+1)),DATE(YEAR(AO27),MONTH(AO27),DAY(AO27)+1),NA()) -> 43974 | AP28: =SUMIFS(Table1[Amount $],Table1[Category Type],"Expense",Table1[Date],Snapshot!AO28)*-1 -> 40.67 | AQ28: =IF(AO28<=EOMONTH($AO$6,0),SUM(AP$6:$AP28),NA()) -> 2934.36 | AR28: =IF(AO28=EOMONTH($AO$6,0),AQ28,NA()) -> #N/A | AT28: Electronic Debit Pmntus Svc | AU28: =IF(ISBLANK(AT28),"",SUMIFS(Table1[Amount $],Table1[Merchant],Snapshot!AT28,Table1[Month],Snapshot!$W$4)*-1) -> 1.95 | AV28: =IF(ISBLANK(AT28),"",COUNTIFS(Table1[Merchant],Snapshot!AT28,Table1[Month],Snapshot!$W$4)) -> 1 | AW28: =IFERROR(RANK(AV28,$AV$6:$AV$200)+COUNTIF($AV$6:AV28,AV28)-1,"") -> 25 | AX28: =IFERROR(RANK(AU28,$AU$6:$AU$200)+COUNTIF($AU$6:AU28,AU28)-1,"") -> 31
V29: =IF(ISBLANK(W29),"--",TEXT(W29,"mmmm")&" "&TEXT(W29,"YYYY")) -> -- | AD29: =SUMIFS(Table1[Amount $],Table1[Category],Snapshot!AC29,Table1[Month],Snapshot!$W$4)*-1 -> 0 | AE29: =RANK(AD29,$AD$6:$AD$35,0)+COUNTIF(AD$6:$AD29,AD29)-1 -> 24 | AJ29: =DATE(YEAR(AJ28),MONTH(AJ28),DAY(AJ28)+1) -> 36549 | AK29: =IF(MONTH(AK28)=MONTH(DATE(YEAR(AK28),MONTH(AK28),DAY(AK28)+1)),DATE(YEAR(AK28),MONTH(AK28),DAY(AK28)+1),NA()) -> 44006 | AL29: =SUMIFS(Table1[Amount $],Table1[Category Type],"Expense",Table1[Date],Snapshot!AK29)*-1 -> 117.93 | AM29: =IF(AK29>TODAY(),NA(),SUM(AL$6:$AL29)) -> 3584.69 | AN29: =IF(OR(AK29=EOMONTH($AK$6,0),AK29=TODAY()),AM29,NA()) -> #N/A | AO29: =IF(MONTH(AO28)=MONTH(DATE(YEAR(AO28),MONTH(AO28),DAY(AO28)+1)),DATE(YEAR(AO28),MONTH(AO28),DAY(AO28)+1),NA()) -> 43975 | AP29: =SUMIFS(Table1[Amount $],Table1[Category Type],"Expense",Table1[Date],Snapshot!AO29)*-1 -> 43.85 | AQ29: =IF(AO29<=EOMONTH($AO$6,0),SUM(AP$6:$AP29),NA()) -> 2978.21 | AR29: =IF(AO29=EOMONTH($AO$6,0),AQ29,NA()) -> #N/A | AT29: Electronic Debit Billmatrix Billpayfee | AU29: =IF(ISBLANK(AT29),"",SUMIFS(Table1[Amount $],Table1[Merchant],Snapshot!AT29,Table1[Month],Snapshot!$W$4)*-1) -> 3.5 | AV29: =IF(ISBLANK(AT29),"",COUNTIFS(Table1[Merchant],Snapshot!AT29,Table1[Month],Snapshot!$W$4)) -> 1 | AW29: =IFERROR(RANK(AV29,$AV$6:$AV$200)+COUNTIF($AV$6:AV29,AV29)-1,"") -> 26 | AX29: =IFERROR(RANK(AU29,$AU$6:$AU$200)+COUNTIF($AU$6:AU29,AU29)-1,"") -> 30
V30: =IF(ISBLANK(W30),"--",TEXT(W30,"mmmm")&" "&TEXT(W30,"YYYY")) -> -- | AD30: =SUMIFS(Table1[Amount $],Table1[Category],Snapshot!AC30,Table1[Month],Snapshot!$W$4)*-1 -> 0 | AE30: =RANK(AD30,$AD$6:$AD$35,0)+COUNTIF(AD$6:$AD30,AD30)-1 -> 25 | AJ30: =DATE(YEAR(AJ29),MONTH(AJ29),DAY(AJ29)+1) -> 36550 | AK30: =IF(MONTH(AK29)=MONTH(DATE(YEAR(AK29),MONTH(AK29),DAY(AK29)+1)),DATE(YEAR(AK29),MONTH(AK29),DAY(AK29)+1),NA()) -> 44007 | AL30: =SUMIFS(Table1[Amount $],Table1[Category Type],"Expense",Table1[Date],Snapshot!AK30)*-1 -> 108 | AM30: =IF(AK30>TODAY(),NA(),SUM(AL$6:$AL30)) -> 3692.69 | AN30: =IF(OR(AK30=EOMONTH($AK$6,0),AK30=TODAY()),AM30,NA()) -> #N/A | AO30: =IF(MONTH(AO29)=MONTH(DATE(YEAR(AO29),MONTH(AO29),DAY(AO29)+1)),DATE(YEAR(AO29),MONTH(AO29),DAY(AO29)+1),NA()) -> 43976 | AP30: =SUMIFS(Table1[Amount $],Table1[Category Type],"Expense",Table1[Date],Snapshot!AO30)*-1 -> 110.21 | AQ30: =IF(AO30<=EOMONTH($AO$6,0),SUM(AP$6:$AP30),NA()) -> 3088.42 | AR30: =IF(AO30=EOMONTH($AO$6,0),AQ30,NA()) -> #N/A | AT30: Electronic Debit Fis Verizon | AU30: =IF(ISBLANK(AT30),"",SUMIFS(Table1[Amount $],Table1[Merchant],Snapshot!AT30,Table1[Month],Snapshot!$W$4)*-1) -> 515.23 | AV30: =IF(ISBLANK(AT30),"",COUNTIFS(Table1[Merchant],Snapshot!AT30,Table1[Month],Snapshot!$W$4)) -> 1 | AW30: =IFERROR(RANK(AV30,$AV$6:$AV$200)+COUNTIF($AV$6:AV30,AV30)-1,"") -> 27 | AX30: =IFERROR(RANK(AU30,$AU$6:$AU$200)+COUNTIF($AU$6:AU30,AU30)-1,"") -> 1
V31: =IF(ISBLANK(W31),"--",TEXT(W31,"mmmm")&" "&TEXT(W31,"YYYY")) -> -- | AD31: =SUMIFS(Table1[Amount $],Table1[Category],Snapshot!AC31,Table1[Month],Snapshot!$W$4)*-1 -> 0 | AE31: =RANK(AD31,$AD$6:$AD$35,0)+COUNTIF(AD$6:$AD31,AD31)-1 -> 26 | AJ31: =DATE(YEAR(AJ30),MONTH(AJ30),DAY(AJ30)+1) -> 36551 | AK31: =IF(MONTH(AK30)=MONTH(DATE(YEAR(AK30),MONTH(AK30),DAY(AK30)+1)),DATE(YEAR(AK30),MONTH(AK30),DAY(AK30)+1),NA()) -> 44008 | AL31: =SUMIFS(Table1[Amount $],Table1[Category Type],"Expense",Table1[Date],Snapshot!AK31)*-1 -> 94.49 | AM31: =IF(AK31>TODAY(),NA(),SUM(AL$6:$AL31)) -> 3787.18 | AN31: =IF(OR(AK31=EOMONTH($AK$6,0),AK31=TODAY()),AM31,NA()) -> #N/A | AO31: =IF(MONTH(AO30)=MONTH(DATE(YEAR(AO30),MONTH(AO30),DAY(AO30)+1)),DATE(YEAR(AO30),MONTH(AO30),DAY(AO30)+1),NA()) -> 43977 | AP31: =SUMIFS(Table1[Amount $],Table1[Category Type],"Expense",Table1[Date],Snapshot!AO31)*-1 -> 391.33 | AQ31: =IF(AO31<=EOMONTH($AO$6,0),SUM(AP$6:$AP31),NA()) -> 3479.75 | AR31: =IF(AO31=EOMONTH($AO$6,0),AQ31,NA()) -> #N/A | AT31: Check Card Purchase Ammodern | AU31: =IF(ISBLANK(AT31),"",SUMIFS(Table1[Amount $],Table1[Merchant],Snapshot!AT31,Table1[Month],Snapshot!$W$4)*-1) -> 173.83 | AV31: =IF(ISBLANK(AT31),"",COUNTIFS(Table1[Merchant],Snapshot!AT31,Table1[Month],Snapshot!$W$4)) -> 1 | AW31: =IFERROR(RANK(AV31,$AV$6:$AV$200)+COUNTIF($AV$6:AV31,AV31)-1,"") -> 28 | AX31: =IFERROR(RANK(AU31,$AU$6:$AU$200)+COUNTIF($AU$6:AU31,AU31)-1,"") -> 11
V32: =IF(ISBLANK(W32),"--",TEXT(W32,"mmmm")&" "&TEXT(W32,"YYYY")) -> -- | AD32: =SUMIFS(Table1[Amount $],Table1[Category],Snapshot!AC32,Table1[Month],Snapshot!$W$4)*-1 -> 0 | AE32: =RANK(AD32,$AD$6:$AD$35,0)+COUNTIF(AD$6:$AD32,AD32)-1 -> 27 | AJ32: =DATE(YEAR(AJ31),MONTH(AJ31),DAY(AJ31)+1) -> 36552 | AK32: =IF(MONTH(AK31)=MONTH(DATE(YEAR(AK31),MONTH(AK31),DAY(AK31)+1)),DATE(YEAR(AK31),MONTH(AK31),DAY(AK31)+1),NA()) -> 44009 | AL32: =SUMIFS(Table1[Amount $],Table1[Category Type],"Expense",Table1[Date],Snapshot!AK32)*-1 -> 0 | AM32: =IF(AK32>TODAY(),NA(),SUM(AL$6:$AL32)) -> 3787.18 | AN32: =IF(OR(AK32=EOMONTH($AK$6,0),AK32=TODAY()),AM32,NA()) -> #N/A | AO32: =IF(MONTH(AO31)=MONTH(DATE(YEAR(AO31),MONTH(AO31),DAY(AO31)+1)),DATE(YEAR(AO31),MONTH(AO31),DAY(AO31)+1),NA()) -> 43978 | AP32: =SUMIFS(Table1[Amount $],Table1[Category Type],"Expense",Table1[Date],Snapshot!AO32)*-1 -> 232.59 | AQ32: =IF(AO32<=EOMONTH($AO$6,0),SUM(AP$6:$AP32),NA()) -> 3712.34 | AR32: =IF(AO32=EOMONTH($AO$6,0),AQ32,NA()) -> #N/A | AT32: Ihop | AU32: =IF(ISBLANK(AT32),"",SUMIFS(Table1[Amount $],Table1[Merchant],Snapshot!AT32,Table1[Month],Snapshot!$W$4)*-1) -> 89.82 | AV32: =IF(ISBLANK(AT32),"",COUNTIFS(Table1[Merchant],Snapshot!AT32,Table1[Month],Snapshot!$W$4)) -> 2 | AW32: =IFERROR(RANK(AV32,$AV$6:$AV$200)+COUNTIF($AV$6:AV32,AV32)-1,"") -> 6 | AX32: =IFERROR(RANK(AU32,$AU$6:$AU$200)+COUNTIF($AU$6:AU32,AU32)-1,"") -> 14
V33: =IF(ISBLANK(W33),"--",TEXT(W33,"mmmm")&" "&TEXT(W33,"YYYY")) -> -- | AD33: =SUMIFS(Table1[Amount $],Table1[Category],Snapshot!AC33,Table1[Month],Snapshot!$W$4)*-1 -> 0 | AE33: =RANK(AD33,$AD$6:$AD$35,0)+COUNTIF(AD$6:$AD33,AD33)-1 -> 28 | AJ33: =DATE(YEAR(AJ32),MONTH(AJ32),DAY(AJ32)+1) -> 36553 | AK33: =IF(MONTH(AK32)=MONTH(DATE(YEAR(AK32),MONTH(AK32),DAY(AK32)+1)),DATE(YEAR(AK32),MONTH(AK32),DAY(AK32)+1),NA()) -> 44010 | AL33: =SUMIFS(Table1[Amount $],Table1[Category Type],"Expense",Table1[Date],Snapshot!AK33)*-1 -> 0 | AM33: =IF(AK33>TODAY(),NA(),SUM(AL$6:$AL33)) -> 3787.18 | AN33: =IF(OR(AK33=EOMONTH($AK$6,0),AK33=TODAY()),AM33,NA()) -> #N/A | AO33: =IF(MONTH(AO32)=MONTH(DATE(YEAR(AO32),MONTH(AO32),DAY(AO32)+1)),DATE(YEAR(AO32),MONTH(AO32),DAY(AO32)+1),NA()) -> 43979 | AP33: =SUMIFS(Table1[Amount $],Table1[Category Type],"Expense",Table1[Date],Snapshot!AO33)*-1 -> 570.2 | AQ33: =IF(AO33<=EOMONTH($AO$6,0),SUM(AP$6:$AP33),NA()) -> 4282.54 | AR33: =IF(AO33=EOMONTH($AO$6,0),AQ33,NA()) -> #N/A | AT33: Netflix | AU33: =IF(ISBLANK(AT33),"",SUMIFS(Table1[Amount $],Table1[Merchant],Snapshot!AT33,Table1[Month],Snapshot!$W$4)*-1) -> 15.99 | AV33: =IF(ISBLANK(AT33),"",COUNTIFS(Table1[Merchant],Snapshot!AT33,Table1[Month],Snapshot!$W$4)) -> 1 | AW33: =IFERROR(RANK(AV33,$AV$6:$AV$200)+COUNTIF($AV$6:AV33,AV33)-1,"") -> 29 | AX33: =IFERROR(RANK(AU33,$AU$6:$AU$200)+COUNTIF($AU$6:AU33,AU33)-1,"") -> 24
V34: =IF(ISBLANK(W34),"--",TEXT(W34,"mmmm")&" "&TEXT(W34,"YYYY")) -> -- | AD34: =SUMIFS(Table1[Amount $],Table1[Category],Snapshot!AC34,Table1[Month],Snapshot!$W$4)*-1 -> 0 | AE34: =RANK(AD34,$AD$6:$AD$35,0)+COUNTIF(AD$6:$AD34,AD34)-1 -> 29 | AJ34: =DATE(YEAR(AJ33),MONTH(AJ33),DAY(AJ33)+1) -> 36554 | AK34: =IF(MONTH(AK33)=MONTH(DATE(YEAR(AK33),MONTH(AK33),DAY(AK33)+1)),DATE(YEAR(AK33),MONTH(AK33),DAY(AK33)+1),NA()) -> 44011 | AL34: =SUMIFS(Table1[Amount $],Table1[Category Type],"Expense",Table1[Date],Snapshot!AK34)*-1 -> 354 | AM34: =IF(AK34>TODAY(),NA(),SUM(AL$6:$AL34)) -> 4141.18 | AN34: =IF(OR(AK34=EOMONTH($AK$6,0),AK34=TODAY()),AM34,NA()) -> #N/A | AO34: =IF(MONTH(AO33)=MONTH(DATE(YEAR(AO33),MONTH(AO33),DAY(AO33)+1)),DATE(YEAR(AO33),MONTH(AO33),DAY(AO33)+1),NA()) -> 43980 | AP34: =SUMIFS(Table1[Amount $],Table1[Category Type],"Expense",Table1[Date],Snapshot!AO34)*-1 -> 37.29 | AQ34: =IF(AO34<=EOMONTH($AO$6,0),SUM(AP$6:$AP34),NA()) -> 4319.83 | AR34: =IF(AO34=EOMONTH($AO$6,0),AQ34,NA()) -> #N/A | AT34: 7 Eleven | AU34: =IF(ISBLANK(AT34),"",SUMIFS(Table1[Amount $],Table1[Merchant],Snapshot!AT34,Table1[Month],Snapshot!$W$4)*-1) -> 23.28 | AV34: =IF(ISBLANK(AT34),"",COUNTIFS(Table1[Merchant],Snapshot!AT34,Table1[Month],Snapshot!$W$4)) -> 1 | AW34: =IFERROR(RANK(AV34,$AV$6:$AV$200)+COUNTIF($AV$6:AV34,AV34)-1,"") -> 30 | AX34: =IFERROR(RANK(AU34,$AU$6:$AU$200)+COUNTIF($AU$6:AU34,AU34)-1,"") -> 22
V35: =IF(ISBLANK(W35),"--",TEXT(W35,"mmmm")&" "&TEXT(W35,"YYYY")) -> -- | AD35: =SUMIFS(Table1[Amount $],Table1[Category],Snapshot!AC35,Table1[Month],Snapshot!$W$4)*-1 -> 0 | AE35: =RANK(AD35,$AD$6:$AD$35,0)+COUNTIF(AD$6:$AD35,AD35)-1 -> 30 | AJ35: =DATE(YEAR(AJ34),MONTH(AJ34),DAY(AJ34)+1) -> 36555 | AK35: =IF(MONTH(AK34)=MONTH(DATE(YEAR(AK34),MONTH(AK34),DAY(AK34)+1)),DATE(YEAR(AK34),MONTH(AK34),DAY(AK34)+1),NA()) -> 44012 | AL35: =SUMIFS(Table1[Amount $],Table1[Category Type],"Expense",Table1[Date],Snapshot!AK35)*-1 -> 12.99 | AM35: =IF(AK35>TODAY(),NA(),SUM(AL$6:$AL35)) -> 4154.17 | AN35: =IF(OR(AK35=EOMONTH($AK$6,0),AK35=TODAY()),AM35,NA()) -> 4154.17 | AO35: =IF(MONTH(AO34)=MONTH(DATE(YEAR(AO34),MONTH(AO34),DAY(AO34)+1)),DATE(YEAR(AO34),MONTH(AO34),DAY(AO34)+1),NA()) -> 43981 | AP35: =SUMIFS(Table1[Amount $],Table1[Category Type],"Expense",Table1[Date],Snapshot!AO35)*-1 -> 98.88 | AQ35: =IF(AO35<=EOMONTH($AO$6,0),SUM(AP$6:$AP35),NA()) -> 4418.71 | AR35: =IF(AO35=EOMONTH($AO$6,0),AQ35,NA()) -> #N/A | AT35: Check Card Purchase Kfc | AU35: =IF(ISBLANK(AT35),"",SUMIFS(Table1[Amount $],Table1[Merchant],Snapshot!AT35,Table1[Month],Snapshot!$W$4)*-1) -> 17.78 | AV35: =IF(ISBLANK(AT35),"",COUNTIFS(Table1[Merchant],Snapshot!AT35,Table1[Month],Snapshot!$W$4)) -> 1 | AW35: =IFERROR(RANK(AV35,$AV$6:$AV$200)+COUNTIF($AV$6:AV35,AV35)-1,"") -> 31 | AX35: =IFERROR(RANK(AU35,$AU$6:$AU$200)+COUNTIF($AU$6:AU35,AU35)-1,"") -> 23
V36: =IF(ISBLANK(W36),"--",TEXT(W36,"mmmm")&" "&TEXT(W36,"YYYY")) -> -- | AJ36: =DATE(YEAR(AJ35),MONTH(AJ35),DAY(AJ35)+1) -> 36556 | AK36: =IF(MONTH(AK35)=MONTH(DATE(YEAR(AK35),MONTH(AK35),DAY(AK35)+1)),DATE(YEAR(AK35),MONTH(AK35),DAY(AK35)+1),NA()) -> #N/A | AL36: =SUMIFS(Table1[Amount $],Table1[Category Type],"Expense",Table1[Date],Snapshot!AK36)*-1 -> 0 | AM36: =IF(AK36>TODAY(),NA(),SUM(AL$6:$AL36)) -> #N/A | AN36: =IF(OR(AK36=EOMONTH($AK$6,0),AK36=TODAY()),AM36,NA()) -> #N/A | AO36: =IF(MONTH(AO35)=MONTH(DATE(YEAR(AO35),MONTH(AO35),DAY(AO35)+1)),DATE(YEAR(AO35),MONTH(AO35),DAY(AO35)+1),NA()) -> 43982 | AP36: =SUMIFS(Table1[Amount $],Table1[Category Type],"Expense",Table1[Date],Snapshot!AO36)*-1 -> 56.93 | AQ36: =IF(AO36<=EOMONTH($AO$6,0),SUM(AP$6:$AP36),NA()) -> 4475.64 | AR36: =IF(AO36=EOMONTH($AO$6,0),AQ36,NA()) -> 4475.64 | AT36: Recurring Check Card Purchase | AU36: =IF(ISBLANK(AT36),"",SUMIFS(Table1[Amount $],Table1[Merchant],Snapshot!AT36,Table1[Month],Snapshot!$W$4)*-1) -> 32.38 | AV36: =IF(ISBLANK(AT36),"",COUNTIFS(Table1[Merchant],Snapshot!AT36,Table1[Month],Snapshot!$W$4)) -> 2 | AW36: =IFERROR(RANK(AV36,$AV$6:$AV$200)+COUNTIF($AV$6:AV36,AV36)-1,"") -> 7 | AX36: =IFERROR(RANK(AU36,$AU$6:$AU$200)+COUNTIF($AU$6:AU36,AU36)-1,"") -> 21
V37: =IF(ISBLANK(W37),"--",TEXT(W37,"mmmm")&" "&TEXT(W37,"YYYY")) -> -- | AU37: =IF(ISBLANK(AT37),"",SUMIFS(Table1[Amount $],Table1[Merchant],Snapshot!AT37,Table1[Month],Snapshot!$W$4)*-1) | AV37: =IF(ISBLANK(AT37),"",COUNTIFS(Table1[Merchant],Snapshot!AT37,Table1[Month],Snapshot!$W$4)) | AW37: =IFERROR(RANK(AV37,$AV$6:$AV$200)+COUNTIF($AV$6:AV37,AV37)-1,"") | AX37: =IFERROR(RANK(AU37,$AU$6:$AU$200)+COUNTIF($AU$6:AU37,AU37)-1,"")
V38: =IF(ISBLANK(W38),"--",TEXT(W38,"mmmm")&" "&TEXT(W38,"YYYY")) -> -- | AK38: =TODAY() -> 44303 | AM38: {=INDEX(AM6:AM36,MATCH(AK38,AK6:AK36,0),0)} -> #N/A | AO38: =DATE(YEAR(AK38),MONTH(AK38)-1,DAY(AK38)) -> 44272 | AQ38: {=INDEX(AQ6:AQ36,MATCH(AO38,AO6:AO36,0),0)} -> #N/A | AU38: =IF(ISBLANK(AT38),"",SUMIFS(Table1[Amount $],Table1[Merchant],Snapshot!AT38,Table1[Month],Snapshot!$W$4)*-1) | AV38: =IF(ISBLANK(AT38),"",COUNTIFS(Table1[Merchant],Snapshot!AT38,Table1[Month],Snapshot!$W$4)) | AW38: =IFERROR(RANK(AV38,$AV$6:$AV$200)+COUNTIF($AV$6:AV38,AV38)-1,"") | AX38: =IFERROR(RANK(AU38,$AU$6:$AU$200)+COUNTIF($AU$6:AU38,AU38)-1,"")
V39: =IF(ISBLANK(W39),"--",TEXT(W39,"mmmm")&" "&TEXT(W39,"YYYY")) -> -- | AK39: =IF(AM38>AQ38,"Spent "&TEXT(AM38-AQ38,"$#,##0")&" more","Spent "&TEXT((AM38-AQ38)*-1,"$#,##0")&" less")&" than this time last month" -> #N/A | AU39: =IF(ISBLANK(AT39),"",SUMIFS(Table1[Amount $],Table1[Merchant],Snapshot!AT39,Table1[Month],Snapshot!$W$4)*-1) | AV39: =IF(ISBLANK(AT39),"",COUNTIFS(Table1[Merchant],Snapshot!AT39,Table1[Month],Snapshot!$W$4)) | AW39: =IFERROR(RANK(AV39,$AV$6:$AV$200)+COUNTIF($AV$6:AV39,AV39)-1,"") | AX39: =IFERROR(RANK(AU39,$AU$6:$AU$200)+COUNTIF($AU$6:AU39,AU39)-1,"")
V40: =IF(ISBLANK(W40),"--",TEXT(W40,"mmmm")&" "&TEXT(W40,"YYYY")) -> -- | AU40: =IF(ISBLANK(AT40),"",SUMIFS(Table1[Amount $],Table1[Merchant],Snapshot!AT40,Table1[Month],Snapshot!$W$4)*-1) | AV40: =IF(ISBLANK(AT40),"",COUNTIFS(Table1[Merchant],Snapshot!AT40,Table1[Month],Snapshot!$W$4)) | AW40: =IFERROR(RANK(AV40,$AV$6:$AV$200)+COUNTIF($AV$6:AV40,AV40)-1,"") | AX40: =IFERROR(RANK(AU40,$AU$6:$AU$200)+COUNTIF($AU$6:AU40,AU40)-1,"")
V41: =IF(ISBLANK(W41),"--",TEXT(W41,"mmmm")&" "&TEXT(W41,"YYYY")) -> -- | AK41: =IFERROR(MAX(AK6:AK36),IFERROR(AK35,IF(AK34,AK33))) -> 44012 | AM41: {=INDEX(AM6:AM36,MATCH(AK41,AK6:AK36,0),0)} -> 4154.17 | AO41: =IFERROR(MAX(AO6:AO36),IFERROR(AO35,IF(AO34,AO33))) -> 43982 | AQ41: {=INDEX(AQ6:AQ36,MATCH(AO41,AO6:AO36,0),0)} -> 4475.64 | AU41: =IF(ISBLANK(AT41),"",SUMIFS(Table1[Amount $],Table1[Merchant],Snapshot!AT41,Table1[Month],Snapshot!$W$4)*-1) | AV41: =IF(ISBLANK(AT41),"",COUNTIFS(Table1[Merchant],Snapshot!AT41,Table1[Month],Snapshot!$W$4)) | AW41: =IFERROR(RANK(AV41,$AV$6:$AV$200)+COUNTIF($AV$6:AV41,AV41)-1,"") | AX41: =IFERROR(RANK(AU41,$AU$6:$AU$200)+COUNTIF($AU$6:AU41,AU41)-1,"")
V42: =IF(ISBLANK(W42),"--",TEXT(W42,"mmmm")&" "&TEXT(W42,"YYYY")) -> -- | AK42: ="Compared to "&TEXT(AO6,"mmmm")&", you "&IF(AM41>AQ41,"spent "&TEXT(AM41-AQ41,"$#,##0")&" more","spent "&TEXT((AM41-AQ41)*-1,"$#,##0")&" less") -> Compared to May, you spent $321 less | AU42: =IF(ISBLANK(AT42),"",SUMIFS(Table1[Amount $],Table1[Merchant],Snapshot!AT42,Table1[Month],Snapshot!$W$4)*-1) | AV42: =IF(ISBLANK(AT42),"",COUNTIFS(Table1[Merchant],Snapshot!AT42,Table1[Month],Snapshot!$W$4)) | AW42: =IFERROR(RANK(AV42,$AV$6:$AV$200)+COUNTIF($AV$6:AV42,AV42)-1,"") | AX42: =IFERROR(RANK(AU42,$AU$6:$AU$200)+COUNTIF($AU$6:AU42,AU42)-1,"")
V43: =IF(ISBLANK(W43),"--",TEXT(W43,"mmmm")&" "&TEXT(W43,"YYYY")) -> -- | AU43: =IF(ISBLANK(AT43),"",SUMIFS(Table1[Amount $],Table1[Merchant],Snapshot!AT43,Table1[Month],Snapshot!$W$4)*-1) | AV43: =IF(ISBLANK(AT43),"",COUNTIFS(Table1[Merchant],Snapshot!AT43,Table1[Month],Snapshot!$W$4)) | AW43: =IFERROR(RANK(AV43,$AV$6:$AV$200)+COUNTIF($AV$6:AV43,AV43)-1,"") | AX43: =IFERROR(RANK(AU43,$AU$6:$AU$200)+COUNTIF($AU$6:AU43,AU43)-1,"")
D44: Frequented merchants | M44: Merchants where the most was spent | V44: =IF(ISBLANK(W44),"--",TEXT(W44,"mmmm")&" "&TEXT(W44,"YYYY")) -> -- | AU44: =IF(ISBLANK(AT44),"",SUMIFS(Table1[Amount $],Table1[Merchant],Snapshot!AT44,Table1[Month],Snapshot!$W$4)*-1) | AV44: =IF(ISBLANK(AT44),"",COUNTIFS(Table1[Merchant],Snapshot!AT44,Table1[Month],Snapshot!$W$4)) | AW44: =IFERROR(RANK(AV44,$AV$6:$AV$200)+COUNTIF($AV$6:AV44,AV44)-1,"") | AX44: =IFERROR(RANK(AU44,$AU$6:$AU$200)+COUNTIF($AU$6:AU44,AU44)-1,"")
V45: =IF(ISBLANK(W45),"--",TEXT(W45,"mmmm")&" "&TEXT(W45,"YYYY")) -> -- | AU45: =IF(ISBLANK(AT45),"",SUMIFS(Table1[Amount $],Table1[Merchant],Snapshot!AT45,Table1[Month],Snapshot!$W$4)*-1) | AV45: =IF(ISBLANK(AT45),"",COUNTIFS(Table1[Merchant],Snapshot!AT45,Table1[Month],Snapshot!$W$4)) | AW45: =IFERROR(RANK(AV45,$AV$6:$AV$200)+COUNTIF($AV$6:AV45,AV45)-1,"") | AX45: =IFERROR(RANK(AU45,$AU$6:$AU$200)+COUNTIF($AU$6:AU45,AU45)-1,"")
D46: Merchant | G46: Count | I46: Total cost | M46: Merchant | Q46: Category | S46: Total cost | V46: =IF(ISBLANK(W46),"--",TEXT(W46,"mmmm")&" "&TEXT(W46,"YYYY")) -> -- | AU46: =IF(ISBLANK(AT46),"",SUMIFS(Table1[Amount $],Table1[Merchant],Snapshot!AT46,Table1[Month],Snapshot!$W$4)*-1) | AV46: =IF(ISBLANK(AT46),"",COUNTIFS(Table1[Merchant],Snapshot!AT46,Table1[Month],Snapshot!$W$4)) | AW46: =IFERROR(RANK(AV46,$AV$6:$AV$200)+COUNTIF($AV$6:AV46,AV46)-1,"") | AX46: =IFERROR(RANK(AU46,$AU$6:$AU$200)+COUNTIF($AU$6:AU46,AU46)-1,"")
B47: 1 | D47: {=IFERROR(INDEX($AT:$AT,MATCH($B47,$AW:$AW,0),0),"")} -> Check Card Purchase Doordash | G47: {=IF(IFERROR(INDEX($AV:$AV,MATCH($B47,$AW:$AW,0),0),"")=0,"",IFERROR(INDEX($AV:$AV,MATCH($B47,$AW:$AW,0),0),""))} -> 7 | I47: {=IF(IFERROR(INDEX($AU:$AU,MATCH($B47,$AW:$AW,0),0),"")=0,"",IFERROR(INDEX($AU:$AU,MATCH($B47,$AW:$AW,0),0),""))} -> 386.67 | M47: {=IFERROR(INDEX($AT:$AT,MATCH($B47,$AX:$AX,0),0),"")} -> Electronic Debit Fis Verizon | Q47: {=IFERROR(INDEX(Table1[Category],MATCH(Snapshot!M47,Table1[Merchant],0),0),"")} -> Bills/Utilities | S47: {=IF(IFERROR(INDEX($AU:$AU,MATCH($B47,$AX:$AX,0),0),"")=0,"",IFERROR(INDEX($AU:$AU,MATCH($B47,$AX:$AX,0),0),""))} -> 515.23 | V47: =IF(ISBLANK(W47),"--",TEXT(W47,"mmmm")&" "&TEXT(W47,"YYYY")) -> -- | AU47: =IF(ISBLANK(AT47),"",SUMIFS(Table1[Amount $],Table1[Merchant],Snapshot!AT47,Table1[Month],Snapshot!$W$4)*-1) | AV47: =IF(ISBLANK(AT47),"",COUNTIFS(Table1[Merchant],Snapshot!AT47,Table1[Month],Snapshot!$W$4)) | AW47: =IFERROR(RANK(AV47,$AV$6:$AV$200)+COUNTIF($AV$6:AV47,AV47)-1,"") | AX47: =IFERROR(RANK(AU47,$AU$6:$AU$200)+COUNTIF($AU$6:AU47,AU47)-1,"")
B48: =B47+1 -> 2 | D48: {=IFERROR(INDEX($AT:$AT,MATCH($B48,$AW:$AW,0),0),"")} -> Overdraft Item Fee For | G48: {=IF(IFERROR(INDEX($AV:$AV,MATCH($B48,$AW:$AW,0),0),"")=0,"",IFERROR(INDEX($AV:$AV,MATCH($B48,$AW:$AW,0),0),""))} -> 5 | I48: {=IF(IFERROR(INDEX($AU:$AU,MATCH($B48,$AW:$AW,0),0),"")=0,"",IFERROR(INDEX($AU:$AU,MATCH($B48,$AW:$AW,0),0),""))} -> 180 | M48: {=IFERROR(INDEX($AT:$AT,MATCH($B48,$AX:$AX,0),0),"")} -> Check Card Purchase Avedon | Q48: {=IFERROR(INDEX(Table1[Category],MATCH(Snapshot!M48,Table1[Merchant],0),0),"")} -> Professional Services | S48: {=IF(IFERROR(INDEX($AU:$AU,MATCH($B48,$AX:$AX,0),0),"")=0,"",IFERROR(INDEX($AU:$AU,MATCH($B48,$AX:$AX,0),0),""))} -> 500 | V48: =IF(ISBLANK(W48),"--",TEXT(W48,"mmmm")&" "&TEXT(W48,"YYYY")) -> -- | AU48: =IF(ISBLANK(AT48),"",SUMIFS(Table1[Amount $],Table1[Merchant],Snapshot!AT48,Table1[Month],Snapshot!$W$4)*-1) | AV48: =IF(ISBLANK(AT48),"",COUNTIFS(Table1[Merchant],Snapshot!AT48,Table1[Month],Snapshot!$W$4)) | AW48: =IFERROR(RANK(AV48,$AV$6:$AV$200)+COUNTIF($AV$6:AV48,AV48)-1,"") | AX48: =IFERROR(RANK(AU48,$AU$6:$AU$200)+COUNTIF($AU$6:AU48,AU48)-1,"")
B49: =B48+1 -> 3 | D49: {=IFERROR(INDEX($AT:$AT,MATCH($B49,$AW:$AW,0),0),"")} -> Mcdonald's | G49: {=IF(IFERROR(INDEX($AV:$AV,MATCH($B49,$AW:$AW,0),0),"")=0,"",IFERROR(INDEX($AV:$AV,MATCH($B49,$AW:$AW,0),0),""))} -> 5 | I49: {=IF(IFERROR(INDEX($AU:$AU,MATCH($B49,$AW:$AW,0),0),"")=0,"",IFERROR(INDEX($AU:$AU,MATCH($B49,$AW:$AW,0),0),""))} -> 127.83 | M49: {=IFERROR(INDEX($AT:$AT,MATCH($B49,$AX:$AX,0),0),"")} -> Check Card Purchase Doordash | Q49: {=IFERROR(INDEX(Table1[Category],MATCH(Snapshot!M49,Table1[Merchant],0),0),"")} -> Restaurants/Dining | S49: {=IF(IFERROR(INDEX($AU:$AU,MATCH($B49,$AX:$AX,0),0),"")=0,"",IFERROR(INDEX($AU:$AU,MATCH($B49,$AX:$AX,0),0),""))} -> 386.67 | V49: =IF(ISBLANK(W49),"--",TEXT(W49,"mmmm")&" "&TEXT(W49,"YYYY")) -> -- | AU49: =IF(ISBLANK(AT49),"",SUMIFS(Table1[Amount $],Table1[Merchant],Snapshot!AT49,Table1[Month],Snapshot!$W$4)*-1) | AV49: =IF(ISBLANK(AT49),"",COUNTIFS(Table1[Merchant],Snapshot!AT49,Table1[Month],Snapshot!$W$4)) | AW49: =IFERROR(RANK(AV49,$AV$6:$AV$200)+COUNTIF($AV$6:AV49,AV49)-1,"") | AX49: =IFERROR(RANK(AU49,$AU$6:$AU$200)+COUNTIF($AU$6:AU49,AU49)-1,"")
B50: =B49+1 -> 4 | D50: {=IFERROR(INDEX($AT:$AT,MATCH($B50,$AW:$AW,0),0),"")} -> Point Of Sale Debit | G50: {=IF(IFERROR(INDEX($AV:$AV,MATCH($B50,$AW:$AW,0),0),"")=0,"",IFERROR(INDEX($AV:$AV,MATCH($B50,$AW:$AW,0),0),""))} -> 4 | I50: {=IF(IFERROR(INDEX($AU:$AU,MATCH($B50,$AW:$AW,0),0),"")=0,"",IFERROR(INDEX($AU:$AU,MATCH($B50,$AW:$AW,0),0),""))} -> 186.72 | M50: {=IFERROR(INDEX($AT:$AT,MATCH($B50,$AX:$AX,0),0),"")} -> Electronic Debit Potomac Elec | Q50: {=IFERROR(INDEX(Table1[Category],MATCH(Snapshot!M50,Table1[Merchant],0),0),"")} -> Bills/Utilities | S50: {=IF(IFERROR(INDEX($AU:$AU,MATCH($B50,$AX:$AX,0),0),"")=0,"",IFERROR(INDEX($AU:$AU,MATCH($B50,$AX:$AX,0),0),""))} -> 343.58 | V50: =IF(ISBLANK(W50),"--",TEXT(W50,"mmmm")&" "&TEXT(W50,"YYYY")) -> -- | AU50: =IF(ISBLANK(AT50),"",SUMIFS(Table1[Amount $],Table1[Merchant],Snapshot!AT50,Table1[Month],Snapshot!$W$4)*-1) | AV50: =IF(ISBLANK(AT50),"",COUNTIFS(Table1[Merchant],Snapshot!AT50,Table1[Month],Snapshot!$W$4)) | AW50: =IFERROR(RANK(AV50,$AV$6:$AV$200)+COUNTIF($AV$6:AV50,AV50)-1,"") | AX50: =IFERROR(RANK(AU50,$AU$6:$AU$200)+COUNTIF($AU$6:AU50,AU50)-1,"")
B51: =B50+1 -> 5 | D51: {=IFERROR(INDEX($AT:$AT,MATCH($B51,$AW:$AW,0),0),"")} -> Electronic Debit Schwan S | G51: {=IF(IFERROR(INDEX($AV:$AV,MATCH($B51,$AW:$AW,0),0),"")=0,"",IFERROR(INDEX($AV:$AV,MATCH($B51,$AW:$AW,0),0),""))} -> 2 | I51: {=IF(IFERROR(INDEX($AU:$AU,MATCH($B51,$AW:$AW,0),0),"")=0,"",IFERROR(INDEX($AU:$AU,MATCH($B51,$AW:$AW,0),0),""))} -> 205.07 | M51: {=IFERROR(INDEX($AT:$AT,MATCH($B51,$AX:$AX,0),0),"")} -> Electronic Debit Transamerica Tpl | Q51: {=IFERROR(INDEX(Table1[Category],MATCH(Snapshot!M51,Table1[Merchant],0),0),"")} -> Bills/Utilities | S51: {=IF(IFERROR(INDEX($AU:$AU,MATCH($B51,$AX:$AX,0),0),"")=0,"",IFERROR(INDEX($AU:$AU,MATCH($B51,$AX:$AX,0),0),""))} -> 318 | V51: =IF(ISBLANK(W51),"--",TEXT(W51,"mmmm")&" "&TEXT(W51,"YYYY")) -> -- | AU51: =IF(ISBLANK(AT51),"",SUMIFS(Table1[Amount $],Table1[Merchant],Snapshot!AT51,Table1[Month],Snapshot!$W$4)*-1) | AV51: =IF(ISBLANK(AT51),"",COUNTIFS(Table1[Merchant],Snapshot!AT51,Table1[Month],Snapshot!$W$4)) | AW51: =IFERROR(RANK(AV51,$AV$6:$AV$200)+COUNTIF($AV$6:AV51,AV51)-1,"") | AX51: =IFERROR(RANK(AU51,$AU$6:$AU$200)+COUNTIF($AU$6:AU51,AU51)-1,"")
B52: =B51+1 -> 6 | D52: {=IFERROR(INDEX($AT:$AT,MATCH($B52,$AW:$AW,0),0),"")} -> Ihop | G52: {=IF(IFERROR(INDEX($AV:$AV,MATCH($B52,$AW:$AW,0),0),"")=0,"",IFERROR(INDEX($AV:$AV,MATCH($B52,$AW:$AW,0),0),""))} -> 2 | I52: {=IF(IFERROR(INDEX($AU:$AU,MATCH($B52,$AW:$AW,0),0),"")=0,"",IFERROR(INDEX($AU:$AU,MATCH($B52,$AW:$AW,0),0),""))} -> 89.82 | M52: {=IFERROR(INDEX($AT:$AT,MATCH($B52,$AX:$AX,0),0),"")} -> Electronic Debit Washington Gas | Q52: {=IFERROR(INDEX(Table1[Category],MATCH(Snapshot!M52,Table1[Merchant],0),0),"")} -> Bills/Utilities | S52: {=IF(IFERROR(INDEX($AU:$AU,MATCH($B52,$AX:$AX,0),0),"")=0,"",IFERROR(INDEX($AU:$AU,MATCH($B52,$AX:$AX,0),0),""))} -> 297.75 | V52: =IF(ISBLANK(W52),"--",TEXT(W52,"mmmm")&" "&TEXT(W52,"YYYY")) -> -- | AU52: =IF(ISBLANK(AT52),"",SUMIFS(Table1[Amount $],Table1[Merchant],Snapshot!AT52,Table1[Month],Snapshot!$W$4)*-1) | AV52: =IF(ISBLANK(AT52),"",COUNTIFS(Table1[Merchant],Snapshot!AT52,Table1[Month],Snapshot!$W$4)) | AW52: =IFERROR(RANK(AV52,$AV$6:$AV$200)+COUNTIF($AV$6:AV52,AV52)-1,"") | AX52: =IFERROR(RANK(AU52,$AU$6:$AU$200)+COUNTIF($AU$6:AU52,AU52)-1,"")
B53: =B52+1 -> 7 | D53: {=IFERROR(INDEX($AT:$AT,MATCH($B53,$AW:$AW,0),0),"")} -> Recurring Check Card Purchase | G53: {=IF(IFERROR(INDEX($AV:$AV,MATCH($B53,$AW:$AW,0),0),"")=0,"",IFERROR(INDEX($AV:$AV,MATCH($B53,$AW:$AW,0),0),""))} -> 2 | I53: {=IF(IFERROR(INDEX($AU:$AU,MATCH($B53,$AW:$AW,0),0),"")=0,"",IFERROR(INDEX($AU:$AU,MATCH($B53,$AW:$AW,0),0),""))} -> 32.38 | M53: {=IFERROR(INDEX($AT:$AT,MATCH($B53,$AX:$AX,0),0),"")} -> Electronic Debit Td Auto | Q53: {=IFERROR(INDEX(Table1[Category],MATCH(Snapshot!M53,Table1[Merchant],0),0),"")} -> Mortgage/Rent | S53: {=IF(IFERROR(INDEX($AU:$AU,MATCH($B53,$AX:$AX,0),0),"")=0,"",IFERROR(INDEX($AU:$AU,MATCH($B53,$AX:$AX,0),0),""))} -> 239.82 | V53: =IF(ISBLANK(W53),"--",TEXT(W53,"mmmm")&" "&TEXT(W53,"YYYY")) -> -- | AU53: =IF(ISBLANK(AT53),"",SUMIFS(Table1[Amount $],Table1[Merchant],Snapshot!AT53,Table1[Month],Snapshot!$W$4)*-1) | AV53: =IF(ISBLANK(AT53),"",COUNTIFS(Table1[Merchant],Snapshot!AT53,Table1[Month],Snapshot!$W$4)) | AW53: =IFERROR(RANK(AV53,$AV$6:$AV$200)+COUNTIF($AV$6:AV53,AV53)-1,"") | AX53: =IFERROR(RANK(AU53,$AU$6:$AU$200)+COUNTIF($AU$6:AU53,AU53)-1,"")
B54: =B53+1 -> 8 | D54: {=IFERROR(INDEX($AT:$AT,MATCH($B54,$AW:$AW,0),0),"")} -> Amazon Prime | G54: {=IF(IFERROR(INDEX($AV:$AV,MATCH($B54,$AW:$AW,0),0),"")=0,"",IFERROR(INDEX($AV:$AV,MATCH($B54,$AW:$AW,0),0),""))} -> 1 | I54: {=IF(IFERROR(INDEX($AU:$AU,MATCH($B54,$AW:$AW,0),0),"")=0,"",IFERROR(INDEX($AU:$AU,MATCH($B54,$AW:$AW,0),0),""))} -> 12.99 | M54: {=IFERROR(INDEX($AT:$AT,MATCH($B54,$AX:$AX,0),0),"")} -> Electronic Debit Schwan S | Q54: {=IFERROR(INDEX(Table1[Category],MATCH(Snapshot!M54,Table1[Merchant],0),0),"")} -> Shopping | S54: {=IF(IFERROR(INDEX($AU:$AU,MATCH($B54,$AX:$AX,0),0),"")=0,"",IFERROR(INDEX($AU:$AU,MATCH($B54,$AX:$AX,0),0),""))} -> 205.07 | V54: =IF(ISBLANK(W54),"--",TEXT(W54,"mmmm")&" "&TEXT(W54,"YYYY")) -> -- | AU54: =IF(ISBLANK(AT54),"",SUMIFS(Table1[Amount $],Table1[Merchant],Snapshot!AT54,Table1[Month],Snapshot!$W$4)*-1) | AV54: =IF(ISBLANK(AT54),"",COUNTIFS(Table1[Merchant],Snapshot!AT54,Table1[Month],Snapshot!$W$4)) | AW54: =IFERROR(RANK(AV54,$AV$6:$AV$200)+COUNTIF($AV$6:AV54,AV54)-1,"") | AX54: =IFERROR(RANK(AU54,$AU$6:$AU$200)+COUNTIF($AU$6:AU54,AU54)-1,"")
B55: =B54+1 -> 9 | D55: {=IFERROR(INDEX($AT:$AT,MATCH($B55,$AW:$AW,0),0),"")} -> Electronic Debit Transamerica Tpl | G55: {=IF(IFERROR(INDEX($AV:$AV,MATCH($B55,$AW:$AW,0),0),"")=0,"",IFERROR(INDEX($AV:$AV,MATCH($B55,$AW:$AW,0),0),""))} -> 1 | I55: {=IF(IFERROR(INDEX($AU:$AU,MATCH($B55,$AW:$AW,0),0),"")=0,"",IFERROR(INDEX($AU:$AU,MATCH($B55,$AW:$AW,0),0),""))} -> 318 | M55: {=IFERROR(INDEX($AT:$AT,MATCH($B55,$AX:$AX,0),0),"")} -> Point Of Sale Debit | Q55: {=IFERROR(INDEX(Table1[Category],MATCH(Snapshot!M55,Table1[Merchant],0),0),"")} -> Auto/Transport | S55: {=IF(IFERROR(INDEX($AU:$AU,MATCH($B55,$AX:$AX,0),0),"")=0,"",IFERROR(INDEX($AU:$AU,MATCH($B55,$AX:$AX,0),0),""))} -> 186.72 | V55: =IF(ISBLANK(W55),"--",TEXT(W55,"mmmm")&" "&TEXT(W55,"YYYY")) -> -- | AU55: =IF(ISBLANK(AT55),"",SUMIFS(Table1[Amount $],Table1[Merchant],Snapshot!AT55,Table1[Month],Snapshot!$W$4)*-1) | AV55: =IF(ISBLANK(AT55),"",COUNTIFS(Table1[Merchant],Snapshot!AT55,Table1[Month],Snapshot!$W$4)) | AW55: =IFERROR(RANK(AV55,$AV$6:$AV$200)+COUNTIF($AV$6:AV55,AV55)-1,"") | AX55: =IFERROR(RANK(AU55,$AU$6:$AU$200)+COUNTIF($AU$6:AU55,AU55)-1,"")
B56: =B55+1 -> 10 | D56: {=IFERROR(INDEX($AT:$AT,MATCH($B56,$AW:$AW,0),0),"")} -> Overdraft Protection Transfer Fee | G56: {=IF(IFERROR(INDEX($AV:$AV,MATCH($B56,$AW:$AW,0),0),"")=0,"",IFERROR(INDEX($AV:$AV,MATCH($B56,$AW:$AW,0),0),""))} -> 1 | I56: {=IF(IFERROR(INDEX($AU:$AU,MATCH($B56,$AW:$AW,0),0),"")=0,"",IFERROR(INDEX($AU:$AU,MATCH($B56,$AW:$AW,0),0),""))} -> 12.5 | M56: {=IFERROR(INDEX($AT:$AT,MATCH($B56,$AX:$AX,0),0),"")} -> Overdraft Item Fee For | Q56: {=IFERROR(INDEX(Table1[Category],MATCH(Snapshot!M56,Table1[Merchant],0),0),"")} -> Fees/Charges | S56: {=IF(IFERROR(INDEX($AU:$AU,MATCH($B56,$AX:$AX,0),0),"")=0,"",IFERROR(INDEX($AU:$AU,MATCH($B56,$AX:$AX,0),0),""))} -> 180 | V56: =IF(ISBLANK(W56),"--",TEXT(W56,"mmmm")&" "&TEXT(W56,"YYYY")) -> -- | AU56: =IF(ISBLANK(AT56),"",SUMIFS(Table1[Amount $],Table1[Merchant],Snapshot!AT56,Table1[Month],Snapshot!$W$4)*-1) | AV56: =IF(ISBLANK(AT56),"",COUNTIFS(Table1[Merchant],Snapshot!AT56,Table1[Month],Snapshot!$W$4)) | AW56: =IFERROR(RANK(AV56,$AV$6:$AV$200)+COUNTIF($AV$6:AV56,AV56)-1,"") | AX56: =IFERROR(RANK(AU56,$AU$6:$AU$200)+COUNTIF($AU$6:AU56,AU56)-1,"")
V57: =IF(ISBLANK(W57),"--",TEXT(W57,"mmmm")&" "&TEXT(W57,"YYYY")) -> -- | AU57: =IF(ISBLANK(AT57),"",SUMIFS(Table1[Amount $],Table1[Merchant],Snapshot!AT57,Table1[Month],Snapshot!$W$4)*-1) | AV57: =IF(ISBLANK(AT57),"",COUNTIFS(Table1[Merchant],Snapshot!AT57,Table1[Month],Snapshot!$W$4)) | AW57: =IFERROR(RANK(AV57,$AV$6:$AV$200)+COUNTIF($AV$6:AV57,AV57)-1,"") | AX57: =IFERROR(RANK(AU57,$AU$6:$AU$200)+COUNTIF($AU$6:AU57,AU57)-1,"")
V58: =IF(ISBLANK(W58),"--",TEXT(W58,"mmmm")&" "&TEXT(W58,"YYYY")) -> -- | AU58: =IF(ISBLANK(AT58),"",SUMIFS(Table1[Amount $],Table1[Merchant],Snapshot!AT58,Table1[Month],Snapshot!$W$4)*-1) | AV58: =IF(ISBLANK(AT58),"",COUNTIFS(Table1[Merchant],Snapshot!AT58,Table1[Month],Snapshot!$W$4)) | AW58: =IFERROR(RANK(AV58,$AV$6:$AV$200)+COUNTIF($AV$6:AV58,AV58)-1,"") | AX58: =IFERROR(RANK(AU58,$AU$6:$AU$200)+COUNTIF($AU$6:AU58,AU58)-1,"")
V59: =IF(ISBLANK(W59),"--",TEXT(W59,"mmmm")&" "&TEXT(W59,"YYYY")) -> -- | AU59: =IF(ISBLANK(AT59),"",SUMIFS(Table1[Amount $],Table1[Merchant],Snapshot!AT59,Table1[Month],Snapshot!$W$4)*-1) | AV59: =IF(ISBLANK(AT59),"",COUNTIFS(Table1[Merchant],Snapshot!AT59,Table1[Month],Snapshot!$W$4)) | AW59: =IFERROR(RANK(AV59,$AV$6:$AV$200)+COUNTIF($AV$6:AV59,AV59)-1,"") | AX59: =IFERROR(RANK(AU59,$AU$6:$AU$200)+COUNTIF($AU$6:AU59,AU59)-1,"")
V60: =IF(ISBLANK(W60),"--",TEXT(W60,"mmmm")&" "&TEXT(W60,"YYYY")) -> -- | AU60: =IF(ISBLANK(AT60),"",SUMIFS(Table1[Amount $],Table1[Merchant],Snapshot!AT60,Table1[Month],Snapshot!$W$4)*-1) | AV60: =IF(ISBLANK(AT60),"",COUNTIFS(Table1[Merchant],Snapshot!AT60,Table1[Month],Snapshot!$W$4)) | AW60: =IFERROR(RANK(AV60,$AV$6:$AV$200)+COUNTIF($AV$6:AV60,AV60)-1,"") | AX60: =IFERROR(RANK(AU60,$AU$6:$AU$200)+COUNTIF($AU$6:AU60,AU60)-1,"")
V61: =IF(ISBLANK(W61),"--",TEXT(W61,"mmmm")&" "&TEXT(W61,"YYYY")) -> -- | AU61: =IF(ISBLANK(AT61),"",SUMIFS(Table1[Amount $],Table1[Merchant],Snapshot!AT61,Table1[Month],Snapshot!$W$4)*-1) | AV61: =IF(ISBLANK(AT61),"",COUNTIFS(Table1[Merchant],Snapshot!AT61,Table1[Month],Snapshot!$W$4)) | AW61: =IFERROR(RANK(AV61,$AV$6:$AV$200)+COUNTIF($AV$6:AV61,AV61)-1,"") | AX61: =IFERROR(RANK(AU61,$AU$6:$AU$200)+COUNTIF($AU$6:AU61,AU61)-1,"")
V62: =IF(ISBLANK(W62),"--",TEXT(W62,"mmmm")&" "&TEXT(W62,"YYYY")) -> -- | AU62: =IF(ISBLANK(AT62),"",SUMIFS(Table1[Amount $],Table1[Merchant],Snapshot!AT62,Table1[Month],Snapshot!$W$4)*-1) | AV62: =IF(ISBLANK(AT62),"",COUNTIFS(Table1[Merchant],Snapshot!AT62,Table1[Month],Snapshot!$W$4)) | AW62: =IFERROR(RANK(AV62,$AV$6:$AV$200)+COUNTIF($AV$6:AV62,AV62)-1,"") | AX62: =IFERROR(RANK(AU62,$AU$6:$AU$200)+COUNTIF($AU$6:AU62,AU62)-1,"")
V63: =IF(ISBLANK(W63),"--",TEXT(W63,"mmmm")&" "&TEXT(W63,"YYYY")) -> -- | AU63: =IF(ISBLANK(AT63),"",SUMIFS(Table1[Amount $],Table1[Merchant],Snapshot!AT63,Table1[Month],Snapshot!$W$4)*-1) | AV63: =IF(ISBLANK(AT63),"",COUNTIFS(Table1[Merchant],Snapshot!AT63,Table1[Month],Snapshot!$W$4)) | AW63: =IFERROR(RANK(AV63,$AV$6:$AV$200)+COUNTIF($AV$6:AV63,AV63)-1,"") | AX63: =IFERROR(RANK(AU63,$AU$6:$AU$200)+COUNTIF($AU$6:AU63,AU63)-1,"")
V64: =IF(ISBLANK(W64),"--",TEXT(W64,"mmmm")&" "&TEXT(W64,"YYYY")) -> -- | AU64: =IF(ISBLANK(AT64),"",SUMIFS(Table1[Amount $],Table1[Merchant],Snapshot!AT64,Table1[Month],Snapshot!$W$4)*-1) | AV64: =IF(ISBLANK(AT64),"",COUNTIFS(Table1[Merchant],Snapshot!AT64,Table1[Month],Snapshot!$W$4)) | AW64: =IFERROR(RANK(AV64,$AV$6:$AV$200)+COUNTIF($AV$6:AV64,AV64)-1,"") | AX64: =IFERROR(RANK(AU64,$AU$6:$AU$200)+COUNTIF($AU$6:AU64,AU64)-1,"")
V65: =IF(ISBLANK(W65),"--",TEXT(W65,"mmmm")&" "&TEXT(W65,"YYYY")) -> -- | AU65: =IF(ISBLANK(AT65),"",SUMIFS(Table1[Amount $],Table1[Merchant],Snapshot!AT65,Table1[Month],Snapshot!$W$4)*-1) | AV65: =IF(ISBLANK(AT65),"",COUNTIFS(Table1[Merchant],Snapshot!AT65,Table1[Month],Snapshot!$W$4)) | AW65: =IFERROR(RANK(AV65,$AV$6:$AV$200)+COUNTIF($AV$6:AV65,AV65)-1,"") | AX65: =IFERROR(RANK(AU65,$AU$6:$AU$200)+COUNTIF($AU$6:AU65,AU65)-1,"")
V66: =IF(ISBLANK(W66),"--",TEXT(W66,"mmmm")&" "&TEXT(W66,"YYYY")) -> -- | AU66: =IF(ISBLANK(AT66),"",SUMIFS(Table1[Amount $],Table1[Merchant],Snapshot!AT66,Table1[Month],Snapshot!$W$4)*-1) | AV66: =IF(ISBLANK(AT66),"",COUNTIFS(Table1[Merchant],Snapshot!AT66,Table1[Month],Snapshot!$W$4)) | AW66: =IFERROR(RANK(AV66,$AV$6:$AV$200)+COUNTIF($AV$6:AV66,AV66)-1,"") | AX66: =IFERROR(RANK(AU66,$AU$6:$AU$200)+COUNTIF($AU$6:AU66,AU66)-1,"")
V67: =IF(ISBLANK(W67),"--",TEXT(W67,"mmmm")&" "&TEXT(W67,"YYYY")) -> -- | AU67: =IF(ISBLANK(AT67),"",SUMIFS(Table1[Amount $],Table1[Merchant],Snapshot!AT67,Table1[Month],Snapshot!$W$4)*-1) | AV67: =IF(ISBLANK(AT67),"",COUNTIFS(Table1[Merchant],Snapshot!AT67,Table1[Month],Snapshot!$W$4)) | AW67: =IFERROR(RANK(AV67,$AV$6:$AV$200)+COUNTIF($AV$6:AV67,AV67)-1,"") | AX67: =IFERROR(RANK(AU67,$AU$6:$AU$200)+COUNTIF($AU$6:AU67,AU67)-1,"")
V68: =IF(ISBLANK(W68),"--",TEXT(W68,"mmmm")&" "&TEXT(W68,"YYYY")) -> -- | AU68: =IF(ISBLANK(AT68),"",SUMIFS(Table1[Amount $],Table1[Merchant],Snapshot!AT68,Table1[Month],Snapshot!$W$4)*-1) | AV68: =IF(ISBLANK(AT68),"",COUNTIFS(Table1[Merchant],Snapshot!AT68,Table1[Month],Snapshot!$W$4)) | AW68: =IFERROR(RANK(AV68,$AV$6:$AV$200)+COUNTIF($AV$6:AV68,AV68)-1,"") | AX68: =IFERROR(RANK(AU68,$AU$6:$AU$200)+COUNTIF($AU$6:AU68,AU68)-1,"")
... V200: =IF(ISBLANK(W200),"--",TEXT(W200,"mmmm")&" "&TEXT(W200,"YYYY")) -> -- | AU200: =IF(ISBLANK(AT200),"",SUMIFS(Table1[Amount $],Table1[Merchant],Snapshot!AT200,Table1[Month],Snapshot!$W$4)*-1) | AV200: =IF(ISBLANK(AT200),"",COUNTIFS(Table1[Merchant],Snapshot!AT200,Table1[Month],Snapshot!$W$4)) | AW200: =IFERROR(RANK(AV200,$AV$6:$AV$200)+COUNTIF($AV$6:AV200,AV200)-1,"") | AX200: =IFERROR(RANK(AU200,$AU$6:$AU$200)+COUNTIF($AU$6:AU200,AU200)-1,"")

Sheet Categories_deprecated_2jdI
B2: Categories
B3: Create and edit categories in the blue cells (below the default categories) to fit your specific financial needs. Make transactions glanceable across every sheet.
G5: Categories
C6: Id | D6: Category Name | E6: Category Type | G6: Yes / No | H6: Count | I6: Order | J6: Full Categories | K6: Clean Categories
B7: Default categories These categories cannot be edited. | D7: Income | E7: Income | G7: =IF(COUNTA(CategoriesTableLegacy[[#This Row],[Category Name]:[Category Type]])=2,"YES","") -> YES | H7: =IF(G7="","",COUNTIF($G$7:G7,"YES")) -> 1 | I7: =IF(ROW()-6>MAX($H$7:$H$44),"--",ROW()-6) -> 1 | J7: {=IFERROR(INDEX(CategoriesTableLegacy[Category Name],MATCH(I7,$H$7:$H$44,0),0),"--")} -> Income | K7: {=OFFSET(Categories_deprecated_2jdI!$J$7,0,0,COUNTIF(Categories_deprecated_2jdI!$J$7:$J$44,"<>"&"--"),1)} -> Income
D8: Refund | E8: Transfer | G8: =IF(COUNTA(CategoriesTableLegacy[[#This Row],[Category Name]:[Category Type]])=2,"YES","") -> YES | H8: =IF(G8="","",COUNTIF($G$7:G8,"YES")) -> 2 | I8: =IF(ROW()-6>MAX($H$7:$H$44),"--",ROW()-6) -> 2 | J8: {=IFERROR(INDEX(CategoriesTableLegacy[Category Name],MATCH(I8,$H$7:$H$44,0),0),"--")} -> Refund | K8: Refund
D9: Transfer | E9: Transfer | G9: =IF(COUNTA(CategoriesTableLegacy[[#This Row],[Category Name]:[Category Type]])=2,"YES","") -> YES | H9: =IF(G9="","",COUNTIF($G$7:G9,"YES")) -> 3 | I9: =IF(ROW()-6>MAX($H$7:$H$44),"--",ROW()-6) -> 3 | J9: {=IFERROR(INDEX(CategoriesTableLegacy[Category Name],MATCH(I9,$H$7:$H$44,0),0),"--")} -> Transfer | K9: Transfer
D10: Auto/Transport | E10: Expense | G10: =IF(COUNTA(CategoriesTableLegacy[[#This Row],[Category Name]:[Category Type]])=2,"YES","") -> YES | H10: =IF(G10="","",COUNTIF($G$7:G10,"YES")) -> 4 | I10: =IF(ROW()-6>MAX($H$7:$H$44),"--",ROW()-6) -> 4 | J10: {=IFERROR(INDEX(CategoriesTableLegacy[Category Name],MATCH(I10,$H$7:$H$44,0),0),"--")} -> Auto/Transport | K10: Auto/Transport
D11: Bills/Utilities | E11: Expense | G11: =IF(COUNTA(CategoriesTableLegacy[[#This Row],[Category Name]:[Category Type]])=2,"YES","") -> YES | H11: =IF(G11="","",COUNTIF($G$7:G11,"YES")) -> 5 | I11: =IF(ROW()-6>MAX($H$7:$H$44),"--",ROW()-6) -> 5 | J11: {=IFERROR(INDEX(CategoriesTableLegacy[Category Name],MATCH(I11,$H$7:$H$44,0),0),"--")} -> Bills/Utilities | K11: Bills/Utilities
D12: Entertainment | E12: Expense | G12: =IF(COUNTA(CategoriesTableLegacy[[#This Row],[Category Name]:[Category Type]])=2,"YES","") -> YES | H12: =IF(G12="","",COUNTIF($G$7:G12,"YES")) -> 6 | I12: =IF(ROW()-6>MAX($H$7:$H$44),"--",ROW()-6) -> 6 | J12: {=IFERROR(INDEX(CategoriesTableLegacy[Category Name],MATCH(I12,$H$7:$H$44,0),0),"--")} -> Entertainment | K12: Entertainment
D13: Fees/Charges | E13: Expense | G13: =IF(COUNTA(CategoriesTableLegacy[[#This Row],[Category Name]:[Category Type]])=2,"YES","") -> YES | H13: =IF(G13="","",COUNTIF($G$7:G13,"YES")) -> 7 | I13: =IF(ROW()-6>MAX($H$7:$H$44),"--",ROW()-6) -> 7 | J13: {=IFERROR(INDEX(CategoriesTableLegacy[Category Name],MATCH(I13,$H$7:$H$44,0),0),"--")} -> Fees/Charges | K13: Fees/Charges
D14: Groceries | E14: Expense | G14: =IF(COUNTA(CategoriesTableLegacy[[#This Row],[Category Name]:[Category Type]])=2,"YES","") -> YES | H14: =IF(G14="","",COUNTIF($G$7:G14,"YES")) -> 8 | I14: =IF(ROW()-6>MAX($H$7:$H$44),"--",ROW()-6) -> 8 | J14: {=IFERROR(INDEX(CategoriesTableLegacy[Category Name],MATCH(I14,$H$7:$H$44,0),0),"--")} -> Groceries | K14: Groceries
D15: Health/Fitness | E15: Expense | G15: =IF(COUNTA(CategoriesTableLegacy[[#This Row],[Category Name]:[Category Type]])=2,"YES","") -> YES | H15: =IF(G15="","",COUNTIF($G$7:G15,"YES")) -> 9 | I15: =IF(ROW()-6>MAX($H$7:$H$44),"--",ROW()-6) -> 9 | J15: {=IFERROR(INDEX(CategoriesTableLegacy[Category Name],MATCH(I15,$H$7:$H$44,0),0),"--")} -> Health/Fitness | K15: Health/Fitness
D16: Home | E16: Expense | G16: =IF(COUNTA(CategoriesTableLegacy[[#This Row],[Category Name]:[Category Type]])=2,"YES","") -> YES | H16: =IF(G16="","",COUNTIF($G$7:G16,"YES")) -> 10 | I16: =IF(ROW()-6>MAX($H$7:$H$44),"--",ROW()-6) -> 10 | J16: {=IFERROR(INDEX(CategoriesTableLegacy[Category Name],MATCH(I16,$H$7:$H$44,0),0),"--")} -> Home | K16: Home
D17: Misc | E17: Expense | G17: =IF(COUNTA(CategoriesTableLegacy[[#This Row],[Category Name]:[Category Type]])=2,"YES","") -> YES | H17: =IF(G17="","",COUNTIF($G$7:G17,"YES")) -> 11 | I17: =IF(ROW()-6>MAX($H$7:$H$44),"--",ROW()-6) -> 11 | J17: {=IFERROR(INDEX(CategoriesTableLegacy[Category Name],MATCH(I17,$H$7:$H$44,0),0),"--")} -> Misc | K17: Misc
D18: Mortgage/Rent | E18: Expense | G18: =IF(COUNTA(CategoriesTableLegacy[[#This Row],[Category Name]:[Category Type]])=2,"YES","") -> YES | H18: =IF(G18="","",COUNTIF($G$7:G18,"YES")) -> 12 | I18: =IF(ROW()-6>MAX($H$7:$H$44),"--",ROW()-6) -> 12 | J18: {=IFERROR(INDEX(CategoriesTableLegacy[Category Name],MATCH(I18,$H$7:$H$44,0),0),"--")} -> Mortgage/Rent | K18: Mortgage/Rent
D19: Payment | E19: Expense | G19: =IF(COUNTA(CategoriesTableLegacy[[#This Row],[Category Name]:[Category Type]])=2,"YES","") -> YES | H19: =IF(G19="","",COUNTIF($G$7:G19,"YES")) -> 13 | I19: =IF(ROW()-6>MAX($H$7:$H$44),"--",ROW()-6) -> 13 | J19: {=IFERROR(INDEX(CategoriesTableLegacy[Category Name],MATCH(I19,$H$7:$H$44,0),0),"--")} -> Payment | K19: Payment
... D24: Uncategorized | E24: Expense | G24: =IF(COUNTA(CategoriesTableLegacy[[#This Row],[Category Name]:[Category Type]])=2,"YES","") -> YES | H24: =IF(G24="","",COUNTIF($G$7:G24,"YES")) -> 18 | I24: =IF(ROW()-6>MAX($H$7:$H$44),"--",ROW()-6) -> 18 | J24: {=IFERROR(INDEX(CategoriesTableLegacy[Category Name],MATCH(I24,$H$7:$H$44,0),0),"--")} -> Uncategorized | K24: Uncategorized
B25: Custom categories Add your own categories in column D and set the category type in column E. We'll remove duplicate categories automatically. | G25: =IF(COUNTA(CategoriesTableLegacy[[#This Row],[Category Name]:[Category Type]])=2,"YES","") | H25: =IF(G25="","",COUNTIF($G$7:G25,"YES")) | I25: =IF(ROW()-6>MAX($H$7:$H$44),"--",ROW()-6) -> -- | J25: {=IFERROR(INDEX(CategoriesTableLegacy[Category Name],MATCH(I25,$H$7:$H$44,0),0),"--")} -> --
G26: =IF(COUNTA(CategoriesTableLegacy[[#This Row],[Category Name]:[Category Type]])=2,"YES","") | H26: =IF(G26="","",COUNTIF($G$7:G26,"YES")) | I26: =IF(ROW()-6>MAX($H$7:$H$44),"--",ROW()-6) -> -- | J26: {=IFERROR(INDEX(CategoriesTableLegacy[Category Name],MATCH(I26,$H$7:$H$44,0),0),"--")} -> --
G27: =IF(COUNTA(CategoriesTableLegacy[[#This Row],[Category Name]:[Category Type]])=2,"YES","") | H27: =IF(G27="","",COUNTIF($G$7:G27,"YES")) | I27: =IF(ROW()-6>MAX($H$7:$H$44),"--",ROW()-6) -> -- | J27: {=IFERROR(INDEX(CategoriesTableLegacy[Category Name],MATCH(I27,$H$7:$H$44,0),0),"--")} -> --
G28: =IF(COUNTA(CategoriesTableLegacy[[#This Row],[Category Name]:[Category Type]])=2,"YES","") | H28: =IF(G28="","",COUNTIF($G$7:G28,"YES")) | I28: =IF(ROW()-6>MAX($H$7:$H$44),"--",ROW()-6) -> -- | J28: {=IFERROR(INDEX(CategoriesTableLegacy[Category Name],MATCH(I28,$H$7:$H$44,0),0),"--")} -> --
G29: =IF(COUNTA(CategoriesTableLegacy[[#This Row],[Category Name]:[Category Type]])=2,"YES","") | H29: =IF(G29="","",COUNTIF($G$7:G29,"YES")) | I29: =IF(ROW()-6>MAX($H$7:$H$44),"--",ROW()-6) -> -- | J29: {=IFERROR(INDEX(CategoriesTableLegacy[Category Name],MATCH(I29,$H$7:$H$44,0),0),"--")} -> --
G30: =IF(COUNTA(CategoriesTableLegacy[[#This Row],[Category Name]:[Category Type]])=2,"YES","") | H30: =IF(G30="","",COUNTIF($G$7:G30,"YES")) | I30: =IF(ROW()-6>MAX($H$7:$H$44),"--",ROW()-6) -> -- | J30: {=IFERROR(INDEX(CategoriesTableLegacy[Category Name],MATCH(I30,$H$7:$H$44,0),0),"--")} -> --
G31: =IF(COUNTA(CategoriesTableLegacy[[#This Row],[Category Name]:[Category Type]])=2,"YES","") | H31: =IF(G31="","",COUNTIF($G$7:G31,"YES")) | I31: =IF(ROW()-6>MAX($H$7:$H$44),"--",ROW()-6) -> -- | J31: {=IFERROR(INDEX(CategoriesTableLegacy[Category Name],MATCH(I31,$H$7:$H$44,0),0),"--")} -> --
G32: =IF(COUNTA(CategoriesTableLegacy[[#This Row],[Category Name]:[Category Type]])=2,"YES","") | H32: =IF(G32="","",COUNTIF($G$7:G32,"YES")) | I32: =IF(ROW()-6>MAX($H$7:$H$44),"--",ROW()-6) -> -- | J32: {=IFERROR(INDEX(CategoriesTableLegacy[Category Name],MATCH(I32,$H$7:$H$44,0),0),"--")} -> --
G33: =IF(COUNTA(CategoriesTableLegacy[[#This Row],[Category Name]:[Category Type]])=2,"YES","") | H33: =IF(G33="","",COUNTIF($G$7:G33,"YES")) | I33: =IF(ROW()-6>MAX($H$7:$H$44),"--",ROW()-6) -> -- | J33: {=IFERROR(INDEX(CategoriesTableLegacy[Category Name],MATCH(I33,$H$7:$H$44,0),0),"--")} -> --
G34: =IF(COUNTA(CategoriesTableLegacy[[#This Row],[Category Name]:[Category Type]])=2,"YES","") | H34: =IF(G34="","",COUNTIF($G$7:G34,"YES")) | I34: =IF(ROW()-6>MAX($H$7:$H$44),"--",ROW()-6) -> -- | J34: {=IFERROR(INDEX(CategoriesTableLegacy[Category Name],MATCH(I34,$H$7:$H$44,0),0),"--")} -> --
G35: =IF(COUNTA(CategoriesTableLegacy[[#This Row],[Category Name]:[Category Type]])=2,"YES","") | H35: =IF(G35="","",COUNTIF($G$7:G35,"YES")) | I35: =IF(ROW()-6>MAX($H$7:$H$44),"--",ROW()-6) -> -- | J35: {=IFERROR(INDEX(CategoriesTableLegacy[Category Name],MATCH(I35,$H$7:$H$44,0),0),"--")} -> --
G36: =IF(COUNTA(CategoriesTableLegacy[[#This Row],[Category Name]:[Category Type]])=2,"YES","") | H36: =IF(G36="","",COUNTIF($G$7:G36,"YES")) | I36: =IF(ROW()-6>MAX($H$7:$H$44),"--",ROW()-6) -> -- | J36: {=IFERROR(INDEX(CategoriesTableLegacy[Category Name],MATCH(I36,$H$7:$H$44,0),0),"--")} -> --
G37: =IF(COUNTA(CategoriesTableLegacy[[#This Row],[Category Name]:[Category Type]])=2,"YES","") | H37: =IF(G37="","",COUNTIF($G$7:G37,"YES")) | I37: =IF(ROW()-6>MAX($H$7:$H$44),"--",ROW()-6) -> -- | J37: {=IFERROR(INDEX(CategoriesTableLegacy[Category Name],MATCH(I37,$H$7:$H$44,0),0),"--")} -> --
... G44: =IF(COUNTA(CategoriesTableLegacy[[#This Row],[Category Name]:[Category Type]])=2,"YES","") | H44: =IF(G44="","",COUNTIF($G$7:G44,"YES")) | I44: =IF(ROW()-6>MAX($H$7:$H$44),"--",ROW()-6) -> -- | J44: {=IFERROR(INDEX(CategoriesTableLegacy[Category Name],MATCH(I44,$H$7:$H$44,0),0),"--")} -> --

Sheet Categories
B2: Categories
C3: Add custom categories and subcategories below, then assign them to your transactions in the transactions sheet. You can only edit or delete the categories and subcategories you've added.
C5: Categories | H5: Subcategories
C6: Add custom categories in the empty rows below the default categories. Make sure to select expenses, income, or transfers under category type. | H6: To add custom subcategories in the table below, select a category from the dropdown menu and add the related subcategory in the next column.
B7: ID | C7: Category name | D7: Category type | E7: Default | G7: ID | H7: Category name | I7: Subcategory name | J7: Category ID
B8: 89f91b72f72a4dd68a16b583d4720595 | C8: Auto/Transport | D8: Expense | E8: TRUE | G8: 01a08ee0780d41da979351ef7694e331 | H8: Auto/Transport | I8: Gas | J8: =IF(NOT(_xlfn.XLOOKUP(SubcategoriesTable[[#This Row],[Category name]],CategoriesTable[Category name],CategoriesTable[ID])=0),_xlfn.XLOOKUP(SubcategoriesTable[[#This Row],[Category name]],CategoriesTable[Category name],CategoriesTable[ID]),"") -> 89f91b72f72a4dd68a16b583d4720595
B9: 4144f48502914015b998277a326fcedc | C9: Bills/Utilities | D9: Expense | E9: TRUE | J9: =IF(NOT(_xlfn.XLOOKUP(SubcategoriesTable[[#This Row],[Category name]],CategoriesTable[Category name],CategoriesTable[ID])=0),_xlfn.XLOOKUP(SubcategoriesTable[[#This Row],[Category name]],CategoriesTable[Category name],CategoriesTable[ID]),"")
B10: ca8ac7c19b84437194c3fe5508eb8bda | C10: Entertainment | D10: Expense | E10: TRUE | J10: =IF(NOT(_xlfn.XLOOKUP(SubcategoriesTable[[#This Row],[Category name]],CategoriesTable[Category name],CategoriesTable[ID])=0),_xlfn.XLOOKUP(SubcategoriesTable[[#This Row],[Category name]],CategoriesTable[Category name],CategoriesTable[ID]),"")
B11: de9b1d2511bc45a9bb2d484aa9e33b31 | C11: Fees/Charges | D11: Expense | E11: TRUE | J11: =IF(NOT(_xlfn.XLOOKUP(SubcategoriesTable[[#This Row],[Category name]],CategoriesTable[Category name],CategoriesTable[ID])=0),_xlfn.XLOOKUP(SubcategoriesTable[[#This Row],[Category name]],CategoriesTable[Category name],CategoriesTable[ID]),"")
B12: 9fa283df10474311b55af8d4cf39d146 | C12: Groceries | D12: Expense | E12: TRUE | J12: =IF(NOT(_xlfn.XLOOKUP(SubcategoriesTable[[#This Row],[Category name]],CategoriesTable[Category name],CategoriesTable[ID])=0),_xlfn.XLOOKUP(SubcategoriesTable[[#This Row],[Category name]],CategoriesTable[Category name],CategoriesTable[ID]),"")
B13: 1c7ed344fd3c47f1b0c4926eb05c305c | C13: Health/Fitness | D13: Expense | E13: TRUE | J13: =IF(NOT(_xlfn.XLOOKUP(SubcategoriesTable[[#This Row],[Category name]],CategoriesTable[Category name],CategoriesTable[ID])=0),_xlfn.XLOOKUP(SubcategoriesTable[[#This Row],[Category name]],CategoriesTable[Category name],CategoriesTable[ID]),"")
B14: cc336735a5324e28bf4f3414f7548cf1 | C14: Home | D14: Expense | E14: TRUE | J14: =IF(NOT(_xlfn.XLOOKUP(SubcategoriesTable[[#This Row],[Category name]],CategoriesTable[Category name],CategoriesTable[ID])=0),_xlfn.XLOOKUP(SubcategoriesTable[[#This Row],[Category name]],CategoriesTable[Category name],CategoriesTable[ID]),"")
B15: fabfe582932d48b78ac2846c1ec3d43f | C15: Income | D15: Income | E15: TRUE | J15: =IF(NOT(_xlfn.XLOOKUP(SubcategoriesTable[[#This Row],[Category name]],CategoriesTable[Category name],CategoriesTable[ID])=0),_xlfn.XLOOKUP(SubcategoriesTable[[#This Row],[Category name]],CategoriesTable[Category name],CategoriesTable[ID]),"")
B16: 013119218f2e4bdd86aa9097992873f8 | C16: Misc | D16: Expense | E16: TRUE | J16: =IF(NOT(_xlfn.XLOOKUP(SubcategoriesTable[[#This Row],[Category name]],CategoriesTable[Category name],CategoriesTable[ID])=0),_xlfn.XLOOKUP(SubcategoriesTable[[#This Row],[Category name]],CategoriesTable[Category name],CategoriesTable[ID]),"")
B17: 0c9f3488736a4d97bd78b9c29fbb29fb | C17: Mortgage/Rent | D17: Expense | E17: TRUE | J17: =IF(NOT(_xlfn.XLOOKUP(SubcategoriesTable[[#This Row],[Category name]],CategoriesTable[Category name],CategoriesTable[ID])=0),_xlfn.XLOOKUP(SubcategoriesTable[[#This Row],[Category name]],CategoriesTable[Category name],CategoriesTable[ID]),"")
B18: 0613345f0a8b4edfb294d0fdc6fe7382 | C18: Payment | D18: Expense | E18: TRUE | J18: =IF(NOT(_xlfn.XLOOKUP(SubcategoriesTable[[#This Row],[Category name]],CategoriesTable[Category name],CategoriesTable[ID])=0),_xlfn.XLOOKUP(SubcategoriesTable[[#This Row],[Category name]],CategoriesTable[Category name],CategoriesTable[ID]),"")
B19: 31cc220e25c84daf9b641cfb0e376681 | C19: Professional Services | D19: Expense | E19: TRUE | J19: =IF(NOT(_xlfn.XLOOKUP(SubcategoriesTable[[#This Row],[Category name]],CategoriesTable[Category name],CategoriesTable[ID])=0),_xlfn.XLOOKUP(SubcategoriesTable[[#This Row],[Category name]],CategoriesTable[Category name],CategoriesTable[ID]),"")
B20: 23fe5da83519415dae0687f037d51b09 | C20: Refund | D20: Transfer | E20: TRUE | J20: =IF(NOT(_xlfn.XLOOKUP(SubcategoriesTable[[#This Row],[Category name]],CategoriesTable[Category name],CategoriesTable[ID])=0),_xlfn.XLOOKUP(SubcategoriesTable[[#This Row],[Category name]],CategoriesTable[Category name],CategoriesTable[ID]),"")
... B30: 7376689a73f04ecd8b60a33ff72eca9f | C30: Loan | D30: Expense | E30: FALSE | J30: =IF(NOT(_xlfn.XLOOKUP(SubcategoriesTable[[#This Row],[Category name]],CategoriesTable[Category name],CategoriesTable[ID])=0),_xlfn.XLOOKUP(SubcategoriesTable[[#This Row],[Category name]],CategoriesTable[Category name],CategoriesTable[ID]),"")
C31: Insurance | J31: =IF(NOT(_xlfn.XLOOKUP(SubcategoriesTable[[#This Row],[Category name]],CategoriesTable[Category name],CategoriesTable[ID])=0),_xlfn.XLOOKUP(SubcategoriesTable[[#This Row],[Category name]],CategoriesTable[Category name],CategoriesTable[ID]),"")
J32: =IF(NOT(_xlfn.XLOOKUP(SubcategoriesTable[[#This Row],[Category name]],CategoriesTable[Category name],CategoriesTable[ID])=0),_xlfn.XLOOKUP(SubcategoriesTable[[#This Row],[Category name]],CategoriesTable[Category name],CategoriesTable[ID]),"")
J33: =IF(NOT(_xlfn.XLOOKUP(SubcategoriesTable[[#This Row],[Category name]],CategoriesTable[Category name],CategoriesTable[ID])=0),_xlfn.XLOOKUP(SubcategoriesTable[[#This Row],[Category name]],CategoriesTable[Category name],CategoriesTable[ID]),"")
J34: =IF(NOT(_xlfn.XLOOKUP(SubcategoriesTable[[#This Row],[Category name]],CategoriesTable[Category name],CategoriesTable[ID])=0),_xlfn.XLOOKUP(SubcategoriesTable[[#This Row],[Category name]],CategoriesTable[Category name],CategoriesTable[ID]),"")
J35: =IF(NOT(_xlfn.XLOOKUP(SubcategoriesTable[[#This Row],[Category name]],CategoriesTable[Category name],CategoriesTable[ID])=0),_xlfn.XLOOKUP(SubcategoriesTable[[#This Row],[Category name]],CategoriesTable[Category name],CategoriesTable[ID]),"")
J36: =IF(NOT(_xlfn.XLOOKUP(SubcategoriesTable[[#This Row],[Category name]],CategoriesTable[Category name],CategoriesTable[ID])=0),_xlfn.XLOOKUP(SubcategoriesTable[[#This Row],[Category name]],CategoriesTable[Category name],CategoriesTable[ID]),"")
J37: =IF(NOT(_xlfn.XLOOKUP(SubcategoriesTable[[#This Row],[Category name]],CategoriesTable[Category name],CategoriesTable[ID])=0),_xlfn.XLOOKUP(SubcategoriesTable[[#This Row],[Category name]],CategoriesTable[Category name],CategoriesTable[ID]),"")
J38: =IF(NOT(_xlfn.XLOOKUP(SubcategoriesTable[[#This Row],[Category name]],CategoriesTable[Category name],CategoriesTable[ID])=0),_xlfn.XLOOKUP(SubcategoriesTable[[#This Row],[Category name]],CategoriesTable[Category name],CategoriesTable[ID]),"")
J39: =IF(NOT(_xlfn.XLOOKUP(SubcategoriesTable[[#This Row],[Category name]],CategoriesTable[Category name],CategoriesTable[ID])=0),_xlfn.XLOOKUP(SubcategoriesTable[[#This Row],[Category name]],CategoriesTable[Category name],CategoriesTable[ID]),"")
J40: =IF(NOT(_xlfn.XLOOKUP(SubcategoriesTable[[#This Row],[Category name]],CategoriesTable[Category name],CategoriesTable[ID])=0),_xlfn.XLOOKUP(SubcategoriesTable[[#This Row],[Category name]],CategoriesTable[Category name],CategoriesTable[ID]),"")
J41: =IF(NOT(_xlfn.XLOOKUP(SubcategoriesTable[[#This Row],[Category name]],CategoriesTable[Category name],CategoriesTable[ID])=0),_xlfn.XLOOKUP(SubcategoriesTable[[#This Row],[Category name]],CategoriesTable[Category name],CategoriesTable[ID]),"")
J42: =IF(NOT(_xlfn.XLOOKUP(SubcategoriesTable[[#This Row],[Category name]],CategoriesTable[Category name],CategoriesTable[ID])=0),_xlfn.XLOOKUP(SubcategoriesTable[[#This Row],[Category name]],CategoriesTable[Category name],CategoriesTable[ID]),"")
J43: =IF(NOT(_xlfn.XLOOKUP(SubcategoriesTable[[#This Row],[Category name]],CategoriesTable[Category name],CategoriesTable[ID])=0),_xlfn.XLOOKUP(SubcategoriesTable[[#This Row],[Category name]],CategoriesTable[Category name],CategoriesTable[ID]),"")
... J100: =IF(NOT(_xlfn.XLOOKUP(SubcategoriesTable[[#This Row],[Category name]],CategoriesTable[Category name],CategoriesTable[ID])=0),_xlfn.XLOOKUP(SubcategoriesTable[[#This Row],[Category name]],CategoriesTable[Category name],CategoriesTable[ID]),"")

Sheet HiddenCategories
B1: Category | C1: Subcategories
B2: {=_xlfn.UNIQUE(_xlfn._xlws.FILTER(CategoryNames, CategoryNames<>"",),FALSE,FALSE)} -> Auto/Transport | C2: {=IFERROR(TRANSPOSE(INDEX(_xlfn._xlws.FILTER(INDIRECT("SubcategoriesTable[Subcategory name]"),INDIRECT("SubcategoriesTable[Category name]")=$B2),,)),_xlfn.CONCAT("No subcategories for"," ", $B2))} -> Gas
B3: Bills/Utilities | C3: {=IFERROR(TRANSPOSE(INDEX(_xlfn._xlws.FILTER(INDIRECT("SubcategoriesTable[Subcategory name]"),INDIRECT("SubcategoriesTable[Category name]")=$B3),,)),_xlfn.CONCAT("No subcategories for"," ", $B3))} -> No subcategories for Bills/Utilities
B4: Entertainment | C4: {=IFERROR(TRANSPOSE(INDEX(_xlfn._xlws.FILTER(INDIRECT("SubcategoriesTable[Subcategory name]"),INDIRECT("SubcategoriesTable[Category name]")=$B4),,)),_xlfn.CONCAT("No subcategories for"," ", $B4))} -> No subcategories for Entertainment
B5: Fees/Charges | C5: {=IFERROR(TRANSPOSE(INDEX(_xlfn._xlws.FILTER(INDIRECT("SubcategoriesTable[Subcategory name]"),INDIRECT("SubcategoriesTable[Category name]")=$B5),,)),_xlfn.CONCAT("No subcategories for"," ", $B5))} -> No subcategories for Fees/Charges
B6: Groceries | C6: {=IFERROR(TRANSPOSE(INDEX(_xlfn._xlws.FILTER(INDIRECT("SubcategoriesTable[Subcategory name]"),INDIRECT("SubcategoriesTable[Category name]")=$B6),,)),_xlfn.CONCAT("No subcategories for"," ", $B6))} -> No subcategories for Groceries
B7: Health/Fitness | C7: {=IFERROR(TRANSPOSE(INDEX(_xlfn._xlws.FILTER(INDIRECT("SubcategoriesTable[Subcategory name]"),INDIRECT("SubcategoriesTable[Category name]")=$B7),,)),_xlfn.CONCAT("No subcategories for"," ", $B7))} -> No subcategories for Health/Fitness
B8: Home | C8: {=IFERROR(TRANSPOSE(INDEX(_xlfn._xlws.FILTER(INDIRECT("SubcategoriesTable[Subcategory name]"),INDIRECT("SubcategoriesTable[Category name]")=$B8),,)),_xlfn.CONCAT("No subcategories for"," ", $B8))} -> No subcategories for Home
B9: Income | C9: {=IFERROR(TRANSPOSE(INDEX(_xlfn._xlws.FILTER(INDIRECT("SubcategoriesTable[Subcategory name]"),INDIRECT("SubcategoriesTable[Category name]")=$B9),,)),_xlfn.CONCAT("No subcategories for"," ", $B9))} -> No subcategories for Income
B10: Misc | C10: {=IFERROR(TRANSPOSE(INDEX(_xlfn._xlws.FILTER(INDIRECT("SubcategoriesTable[Subcategory name]"),INDIRECT("SubcategoriesTable[Category name]")=$B10),,)),_xlfn.CONCAT("No subcategories for"," ", $B10))} -> No subcategories for Misc
B11: Mortgage/Rent | C11: {=IFERROR(TRANSPOSE(INDEX(_xlfn._xlws.FILTER(INDIRECT("SubcategoriesTable[Subcategory name]"),INDIRECT("SubcategoriesTable[Category name]")=$B11),,)),_xlfn.CONCAT("No subcategories for"," ", $B11))} -> No subcategories for Mortgage/Rent
B12: Payment | C12: {=IFERROR(TRANSPOSE(INDEX(_xlfn._xlws.FILTER(INDIRECT("SubcategoriesTable[Subcategory name]"),INDIRECT("SubcategoriesTable[Category name]")=$B12),,)),_xlfn.CONCAT("No subcategories for"," ", $B12))} -> No subcategories for Payment
B13: Professional Services | C13: {=IFERROR(TRANSPOSE(INDEX(_xlfn._xlws.FILTER(INDIRECT("SubcategoriesTable[Subcategory name]"),INDIRECT("SubcategoriesTable[Category name]")=$B13),,)),_xlfn.CONCAT("No subcategories for"," ", $B13))} -> No subcategories for Professional Services
B14: Refund | C14: {=IFERROR(TRANSPOSE(INDEX(_xlfn._xlws.FILTER(INDIRECT("SubcategoriesTable[Subcategory name]"),INDIRECT("SubcategoriesTable[Category name]")=$B14),,)),_xlfn.CONCAT("No subcategories for"," ", $B14))} -> No subcategories for Refund
... B25: Insurance | C25: {=IFERROR(TRANSPOSE(INDEX(_xlfn._xlws.FILTER(INDIRECT("SubcategoriesTable[Subcategory name]"),INDIRECT("SubcategoriesTable[Category name]")=$B25),,)),_xlfn.CONCAT("No subcategories for"," ", $B25))} -> No subcategories for Insurance
C26: {=IFERROR(TRANSPOSE(INDEX(_xlfn._xlws.FILTER(INDIRECT("SubcategoriesTable[Subcategory name]"),INDIRECT("SubcategoriesTable[Category name]")=$B26),,)),_xlfn.CONCAT("No subcategories for"," ", $B26))} -> 0 | D26: 0 | E26: 0 | F26: 0 | G26: 0 | H26: 0 | I26: 0 | J26: 0 | K26: 0 | L26: 0 | M26: 0 | N26: 0 | O26: 0 | P26: 0 | Q26: 0 | R26: 0 | S26: 0 | T26: 0 | U26: 0 | V26: 0 | W26: 0 | X26: 0 | Y26: 0 | Z26: 0 | AA26: 0 | AB26: 0 | AC26: 0 | AD26: 0 | AE26: 0 | AF26: 0 | AG26: 0 | AH26: 0 | AI26: 0 | AJ26: 0 | AK26: 0 | AL26: 0 | AM26: 0 | AN26: 0 | AO26: 0 | AP26: 0 | AQ26: 0 | AR26: 0 | AS26: 0 | AT26: 0 | AU26: 0 | AV26: 0 | AW26: 0 | AX26: 0 | AY26: 0 | AZ26: 0 | BA26: 0 | BB26: 0 | BC26: 0 | BD26: 0 | BE26: 0 | BF26: 0 | BG26: 0 | BH26: 0 | BI26: 0 | BJ26: 0 | BK26: 0 | BL26: 0 | BM26: 0 | BN26: 0 | BO26: 0 | BP26: 0 | BQ26: 0 | BR26: 0 | BS26: 0 | BT26: 0 | BU26: 0 | BV26: 0 | BW26: 0 | BX26: 0 | BY26: 0 | BZ26: 0 | CA26: 0 | CB26: 0 | CC26: 0 | CD26: 0 | CE26: 0 | CF26: 0 | CG26: 0 | CH26: 0 | CI26: 0 | CJ26: 0 | CK26: 0 | CL26: 0 | CM26: 0 | CN26: 0 | CO26: 0 | CP26: 0
C27: {=IFERROR(TRANSPOSE(INDEX(_xlfn._xlws.FILTER(INDIRECT("SubcategoriesTable[Subcategory name]"),INDIRECT("SubcategoriesTable[Category name]")=$B27),,)),_xlfn.CONCAT("No subcategories for"," ", $B27))} -> 0 | D27: 0 | E27: 0 | F27: 0 | G27: 0 | H27: 0 | I27: 0 | J27: 0 | K27: 0 | L27: 0 | M27: 0 | N27: 0 | O27: 0 | P27: 0 | Q27: 0 | R27: 0 | S27: 0 | T27: 0 | U27: 0 | V27: 0 | W27: 0 | X27: 0 | Y27: 0 | Z27: 0 | AA27: 0 | AB27: 0 | AC27: 0 | AD27: 0 | AE27: 0 | AF27: 0 | AG27: 0 | AH27: 0 | AI27: 0 | AJ27: 0 | AK27: 0 | AL27: 0 | AM27: 0 | AN27: 0 | AO27: 0 | AP27: 0 | AQ27: 0 | AR27: 0 | AS27: 0 | AT27: 0 | AU27: 0 | AV27: 0 | AW27: 0 | AX27: 0 | AY27: 0 | AZ27: 0 | BA27: 0 | BB27: 0 | BC27: 0 | BD27: 0 | BE27: 0 | BF27: 0 | BG27: 0 | BH27: 0 | BI27: 0 | BJ27: 0 | BK27: 0 | BL27: 0 | BM27: 0 | BN27: 0 | BO27: 0 | BP27: 0 | BQ27: 0 | BR27: 0 | BS27: 0 | BT27: 0 | BU27: 0 | BV27: 0 | BW27: 0 | BX27: 0 | BY27: 0 | BZ27: 0 | CA27: 0 | CB27: 0 | CC27: 0 | CD27: 0 | CE27: 0 | CF27: 0 | CG27: 0 | CH27: 0 | CI27: 0 | CJ27: 0 | CK27: 0 | CL27: 0 | CM27: 0 | CN27: 0 | CO27: 0 | CP27: 0
C28: {=IFERROR(TRANSPOSE(INDEX(_xlfn._xlws.FILTER(INDIRECT("SubcategoriesTable[Subcategory name]"),INDIRECT("SubcategoriesTable[Category name]")=$B28),,)),_xlfn.CONCAT("No subcategories for"," ", $B28))} -> 0 | D28: 0 | E28: 0 | F28: 0 | G28: 0 | H28: 0 | I28: 0 | J28: 0 | K28: 0 | L28: 0 | M28: 0 | N28: 0 | O28: 0 | P28: 0 | Q28: 0 | R28: 0 | S28: 0 | T28: 0 | U28: 0 | V28: 0 | W28: 0 | X28: 0 | Y28: 0 | Z28: 0 | AA28: 0 | AB28: 0 | AC28: 0 | AD28: 0 | AE28: 0 | AF28: 0 | AG28: 0 | AH28: 0 | AI28: 0 | AJ28: 0 | AK28: 0 | AL28: 0 | AM28: 0 | AN28: 0 | AO28: 0 | AP28: 0 | AQ28: 0 | AR28: 0 | AS28: 0 | AT28: 0 | AU28: 0 | AV28: 0 | AW28: 0 | AX28: 0 | AY28: 0 | AZ28: 0 | BA28: 0 | BB28: 0 | BC28: 0 | BD28: 0 | BE28: 0 | BF28: 0 | BG28: 0 | BH28: 0 | BI28: 0 | BJ28: 0 | BK28: 0 | BL28: 0 | BM28: 0 | BN28: 0 | BO28: 0 | BP28: 0 | BQ28: 0 | BR28: 0 | BS28: 0 | BT28: 0 | BU28: 0 | BV28: 0 | BW28: 0 | BX28: 0 | BY28: 0 | BZ28: 0 | CA28: 0 | CB28: 0 | CC28: 0 | CD28: 0 | CE28: 0 | CF28: 0 | CG28: 0 | CH28: 0 | CI28: 0 | CJ28: 0 | CK28: 0 | CL28: 0 | CM28: 0 | CN28: 0 | CO28: 0 | CP28: 0
C29: {=IFERROR(TRANSPOSE(INDEX(_xlfn._xlws.FILTER(INDIRECT("SubcategoriesTable[Subcategory name]"),INDIRECT("SubcategoriesTable[Category name]")=$B29),,)),_xlfn.CONCAT("No subcategories for"," ", $B29))} -> 0 | D29: 0 | E29: 0 | F29: 0 | G29: 0 | H29: 0 | I29: 0 | J29: 0 | K29: 0 | L29: 0 | M29: 0 | N29: 0 | O29: 0 | P29: 0 | Q29: 0 | R29: 0 | S29: 0 | T29: 0 | U29: 0 | V29: 0 | W29: 0 | X29: 0 | Y29: 0 | Z29: 0 | AA29: 0 | AB29: 0 | AC29: 0 | AD29: 0 | AE29: 0 | AF29: 0 | AG29: 0 | AH29: 0 | AI29: 0 | AJ29: 0 | AK29: 0 | AL29: 0 | AM29: 0 | AN29: 0 | AO29: 0 | AP29: 0 | AQ29: 0 | AR29: 0 | AS29: 0 | AT29: 0 | AU29: 0 | AV29: 0 | AW29: 0 | AX29: 0 | AY29: 0 | AZ29: 0 | BA29: 0 | BB29: 0 | BC29: 0 | BD29: 0 | BE29: 0 | BF29: 0 | BG29: 0 | BH29: 0 | BI29: 0 | BJ29: 0 | BK29: 0 | BL29: 0 | BM29: 0 | BN29: 0 | BO29: 0 | BP29: 0 | BQ29: 0 | BR29: 0 | BS29: 0 | BT29: 0 | BU29: 0 | BV29: 0 | BW29: 0 | BX29: 0 | BY29: 0 | BZ29: 0 | CA29: 0 | CB29: 0 | CC29: 0 | CD29: 0 | CE29: 0 | CF29: 0 | CG29: 0 | CH29: 0 | CI29: 0 | CJ29: 0 | CK29: 0 | CL29: 0 | CM29: 0 | CN29: 0 | CO29: 0 | CP29: 0
C30: {=IFERROR(TRANSPOSE(INDEX(_xlfn._xlws.FILTER(INDIRECT("SubcategoriesTable[Subcategory name]"),INDIRECT("SubcategoriesTable[Category name]")=$B30),,)),_xlfn.CONCAT("No subcategories for"," ", $B30))} -> 0 | D30: 0 | E30: 0 | F30: 0 | G30: 0 | H30: 0 | I30: 0 | J30: 0 | K30: 0 | L30: 0 | M30: 0 | N30: 0 | O30: 0 | P30: 0 | Q30: 0 | R30: 0 | S30: 0 | T30: 0 | U30: 0 | V30: 0 | W30: 0 | X30: 0 | Y30: 0 | Z30: 0 | AA30: 0 | AB30: 0 | AC30: 0 | AD30: 0 | AE30: 0 | AF30: 0 | AG30: 0 | AH30: 0 | AI30: 0 | AJ30: 0 | AK30: 0 | AL30: 0 | AM30: 0 | AN30: 0 | AO30: 0 | AP30: 0 | AQ30: 0 | AR30: 0 | AS30: 0 | AT30: 0 | AU30: 0 | AV30: 0 | AW30: 0 | AX30: 0 | AY30: 0 | AZ30: 0 | BA30: 0 | BB30: 0 | BC30: 0 | BD30: 0 | BE30: 0 | BF30: 0 | BG30: 0 | BH30: 0 | BI30: 0 | BJ30: 0 | BK30: 0 | BL30: 0 | BM30: 0 | BN30: 0 | BO30: 0 | BP30: 0 | BQ30: 0 | BR30: 0 | BS30: 0 | BT30: 0 | BU30: 0 | BV30: 0 | BW30: 0 | BX30: 0 | BY30: 0 | BZ30: 0 | CA30: 0 | CB30: 0 | CC30: 0 | CD30: 0 | CE30: 0 | CF30: 0 | CG30: 0 | CH30: 0 | CI30: 0 | CJ30: 0 | CK30: 0 | CL30: 0 | CM30: 0 | CN30: 0 | CO30: 0 | CP30: 0
C31: {=IFERROR(TRANSPOSE(INDEX(_xlfn._xlws.FILTER(INDIRECT("SubcategoriesTable[Subcategory name]"),INDIRECT("SubcategoriesTable[Category name]")=$B31),,)),_xlfn.CONCAT("No subcategories for"," ", $B31))} -> 0 | D31: 0 | E31: 0 | F31: 0 | G31: 0 | H31: 0 | I31: 0 | J31: 0 | K31: 0 | L31: 0 | M31: 0 | N31: 0 | O31: 0 | P31: 0 | Q31: 0 | R31: 0 | S31: 0 | T31: 0 | U31: 0 | V31: 0 | W31: 0 | X31: 0 | Y31: 0 | Z31: 0 | AA31: 0 | AB31: 0 | AC31: 0 | AD31: 0 | AE31: 0 | AF31: 0 | AG31: 0 | AH31: 0 | AI31: 0 | AJ31: 0 | AK31: 0 | AL31: 0 | AM31: 0 | AN31: 0 | AO31: 0 | AP31: 0 | AQ31: 0 | AR31: 0 | AS31: 0 | AT31: 0 | AU31: 0 | AV31: 0 | AW31: 0 | AX31: 0 | AY31: 0 | AZ31: 0 | BA31: 0 | BB31: 0 | BC31: 0 | BD31: 0 | BE31: 0 | BF31: 0 | BG31: 0 | BH31: 0 | BI31: 0 | BJ31: 0 | BK31: 0 | BL31: 0 | BM31: 0 | BN31: 0 | BO31: 0 | BP31: 0 | BQ31: 0 | BR31: 0 | BS31: 0 | BT31: 0 | BU31: 0 | BV31: 0 | BW31: 0 | BX31: 0 | BY31: 0 | BZ31: 0 | CA31: 0 | CB31: 0 | CC31: 0 | CD31: 0 | CE31: 0 | CF31: 0 | CG31: 0 | CH31: 0 | CI31: 0 | CJ31: 0 | CK31: 0 | CL31: 0 | CM31: 0 | CN31: 0 | CO31: 0 | CP31: 0
C32: {=IFERROR(TRANSPOSE(INDEX(_xlfn._xlws.FILTER(INDIRECT("SubcategoriesTable[Subcategory name]"),INDIRECT("SubcategoriesTable[Category name]")=$B32),,)),_xlfn.CONCAT("No subcategories for"," ", $B32))} -> 0 | D32: 0 | E32: 0 | F32: 0 | G32: 0 | H32: 0 | I32: 0 | J32: 0 | K32: 0 | L32: 0 | M32: 0 | N32: 0 | O32: 0 | P32: 0 | Q32: 0 | R32: 0 | S32: 0 | T32: 0 | U32: 0 | V32: 0 | W32: 0 | X32: 0 | Y32: 0 | Z32: 0 | AA32: 0 | AB32: 0 | AC32: 0 | AD32: 0 | AE32: 0 | AF32: 0 | AG32: 0 | AH32: 0 | AI32: 0 | AJ32: 0 | AK32: 0 | AL32: 0 | AM32: 0 | AN32: 0 | AO32: 0 | AP32: 0 | AQ32: 0 | AR32: 0 | AS32: 0 | AT32: 0 | AU32: 0 | AV32: 0 | AW32: 0 | AX32: 0 | AY32: 0 | AZ32: 0 | BA32: 0 | BB32: 0 | BC32: 0 | BD32: 0 | BE32: 0 | BF32: 0 | BG32: 0 | BH32: 0 | BI32: 0 | BJ32: 0 | BK32: 0 | BL32: 0 | BM32: 0 | BN32: 0 | BO32: 0 | BP32: 0 | BQ32: 0 | BR32: 0 | BS32: 0 | BT32: 0 | BU32: 0 | BV32: 0 | BW32: 0 | BX32: 0 | BY32: 0 | BZ32: 0 | CA32: 0 | CB32: 0 | CC32: 0 | CD32: 0 | CE32: 0 | CF32: 0 | CG32: 0 | CH32: 0 | CI32: 0 | CJ32: 0 | CK32: 0 | CL32: 0 | CM32: 0 | CN32: 0 | CO32: 0 | CP32: 0
C33: {=IFERROR(TRANSPOSE(INDEX(_xlfn._xlws.FILTER(INDIRECT("SubcategoriesTable[Subcategory name]"),INDIRECT("SubcategoriesTable[Category name]")=$B33),,)),_xlfn.CONCAT("No subcategories for"," ", $B33))} -> 0 | D33: 0 | E33: 0 | F33: 0 | G33: 0 | H33: 0 | I33: 0 | J33: 0 | K33: 0 | L33: 0 | M33: 0 | N33: 0 | O33: 0 | P33: 0 | Q33: 0 | R33: 0 | S33: 0 | T33: 0 | U33: 0 | V33: 0 | W33: 0 | X33: 0 | Y33: 0 | Z33: 0 | AA33: 0 | AB33: 0 | AC33: 0 | AD33: 0 | AE33: 0 | AF33: 0 | AG33: 0 | AH33: 0 | AI33: 0 | AJ33: 0 | AK33: 0 | AL33: 0 | AM33: 0 | AN33: 0 | AO33: 0 | AP33: 0 | AQ33: 0 | AR33: 0 | AS33: 0 | AT33: 0 | AU33: 0 | AV33: 0 | AW33: 0 | AX33: 0 | AY33: 0 | AZ33: 0 | BA33: 0 | BB33: 0 | BC33: 0 | BD33: 0 | BE33: 0 | BF33: 0 | BG33: 0 | BH33: 0 | BI33: 0 | BJ33: 0 | BK33: 0 | BL33: 0 | BM33: 0 | BN33: 0 | BO33: 0 | BP33: 0 | BQ33: 0 | BR33: 0 | BS33: 0 | BT33: 0 | BU33: 0 | BV33: 0 | BW33: 0 | BX33: 0 | BY33: 0 | BZ33: 0 | CA33: 0 | CB33: 0 | CC33: 0 | CD33: 0 | CE33: 0 | CF33: 0 | CG33: 0 | CH33: 0 | CI33: 0 | CJ33: 0 | CK33: 0 | CL33: 0 | CM33: 0 | CN33: 0 | CO33: 0 | CP33: 0
C34: {=IFERROR(TRANSPOSE(INDEX(_xlfn._xlws.FILTER(INDIRECT("SubcategoriesTable[Subcategory name]"),INDIRECT("SubcategoriesTable[Category name]")=$B34),,)),_xlfn.CONCAT("No subcategories for"," ", $B34))} -> 0 | D34: 0 | E34: 0 | F34: 0 | G34: 0 | H34: 0 | I34: 0 | J34: 0 | K34: 0 | L34: 0 | M34: 0 | N34: 0 | O34: 0 | P34: 0 | Q34: 0 | R34: 0 | S34: 0 | T34: 0 | U34: 0 | V34: 0 | W34: 0 | X34: 0 | Y34: 0 | Z34: 0 | AA34: 0 | AB34: 0 | AC34: 0 | AD34: 0 | AE34: 0 | AF34: 0 | AG34: 0 | AH34: 0 | AI34: 0 | AJ34: 0 | AK34: 0 | AL34: 0 | AM34: 0 | AN34: 0 | AO34: 0 | AP34: 0 | AQ34: 0 | AR34: 0 | AS34: 0 | AT34: 0 | AU34: 0 | AV34: 0 | AW34: 0 | AX34: 0 | AY34: 0 | AZ34: 0 | BA34: 0 | BB34: 0 | BC34: 0 | BD34: 0 | BE34: 0 | BF34: 0 | BG34: 0 | BH34: 0 | BI34: 0 | BJ34: 0 | BK34: 0 | BL34: 0 | BM34: 0 | BN34: 0 | BO34: 0 | BP34: 0 | BQ34: 0 | BR34: 0 | BS34: 0 | BT34: 0 | BU34: 0 | BV34: 0 | BW34: 0 | BX34: 0 | BY34: 0 | BZ34: 0 | CA34: 0 | CB34: 0 | CC34: 0 | CD34: 0 | CE34: 0 | CF34: 0 | CG34: 0 | CH34: 0 | CI34: 0 | CJ34: 0 | CK34: 0 | CL34: 0 | CM34: 0 | CN34: 0 | CO34: 0 | CP34: 0
C35: {=IFERROR(TRANSPOSE(INDEX(_xlfn._xlws.FILTER(INDIRECT("SubcategoriesTable[Subcategory name]"),INDIRECT("SubcategoriesTable[Category name]")=$B35),,)),_xlfn.CONCAT("No subcategories for"," ", $B35))} -> 0 | D35: 0 | E35: 0 | F35: 0 | G35: 0 | H35: 0 | I35: 0 | J35: 0 | K35: 0 | L35: 0 | M35: 0 | N35: 0 | O35: 0 | P35: 0 | Q35: 0 | R35: 0 | S35: 0 | T35: 0 | U35: 0 | V35: 0 | W35: 0 | X35: 0 | Y35: 0 | Z35: 0 | AA35: 0 | AB35: 0 | AC35: 0 | AD35: 0 | AE35: 0 | AF35: 0 | AG35: 0 | AH35: 0 | AI35: 0 | AJ35: 0 | AK35: 0 | AL35: 0 | AM35: 0 | AN35: 0 | AO35: 0 | AP35: 0 | AQ35: 0 | AR35: 0 | AS35: 0 | AT35: 0 | AU35: 0 | AV35: 0 | AW35: 0 | AX35: 0 | AY35: 0 | AZ35: 0 | BA35: 0 | BB35: 0 | BC35: 0 | BD35: 0 | BE35: 0 | BF35: 0 | BG35: 0 | BH35: 0 | BI35: 0 | BJ35: 0 | BK35: 0 | BL35: 0 | BM35: 0 | BN35: 0 | BO35: 0 | BP35: 0 | BQ35: 0 | BR35: 0 | BS35: 0 | BT35: 0 | BU35: 0 | BV35: 0 | BW35: 0 | BX35: 0 | BY35: 0 | BZ35: 0 | CA35: 0 | CB35: 0 | CC35: 0 | CD35: 0 | CE35: 0 | CF35: 0 | CG35: 0 | CH35: 0 | CI35: 0 | CJ35: 0 | CK35: 0 | CL35: 0 | CM35: 0 | CN35: 0 | CO35: 0 | CP35: 0
C36: {=IFERROR(TRANSPOSE(INDEX(_xlfn._xlws.FILTER(INDIRECT("SubcategoriesTable[Subcategory name]"),INDIRECT("SubcategoriesTable[Category name]")=$B36),,)),_xlfn.CONCAT("No subcategories for"," ", $B36))} -> 0 | D36: 0 | E36: 0 | F36: 0 | G36: 0 | H36: 0 | I36: 0 | J36: 0 | K36: 0 | L36: 0 | M36: 0 | N36: 0 | O36: 0 | P36: 0 | Q36: 0 | R36: 0 | S36: 0 | T36: 0 | U36: 0 | V36: 0 | W36: 0 | X36: 0 | Y36: 0 | Z36: 0 | AA36: 0 | AB36: 0 | AC36: 0 | AD36: 0 | AE36: 0 | AF36: 0 | AG36: 0 | AH36: 0 | AI36: 0 | AJ36: 0 | AK36: 0 | AL36: 0 | AM36: 0 | AN36: 0 | AO36: 0 | AP36: 0 | AQ36: 0 | AR36: 0 | AS36: 0 | AT36: 0 | AU36: 0 | AV36: 0 | AW36: 0 | AX36: 0 | AY36: 0 | AZ36: 0 | BA36: 0 | BB36: 0 | BC36: 0 | BD36: 0 | BE36: 0 | BF36: 0 | BG36: 0 | BH36: 0 | BI36: 0 | BJ36: 0 | BK36: 0 | BL36: 0 | BM36: 0 | BN36: 0 | BO36: 0 | BP36: 0 | BQ36: 0 | BR36: 0 | BS36: 0 | BT36: 0 | BU36: 0 | BV36: 0 | BW36: 0 | BX36: 0 | BY36: 0 | BZ36: 0 | CA36: 0 | CB36: 0 | CC36: 0 | CD36: 0 | CE36: 0 | CF36: 0 | CG36: 0 | CH36: 0 | CI36: 0 | CJ36: 0 | CK36: 0 | CL36: 0 | CM36: 0 | CN36: 0 | CO36: 0 | CP36: 0
C37: {=IFERROR(TRANSPOSE(INDEX(_xlfn._xlws.FILTER(INDIRECT("SubcategoriesTable[Subcategory name]"),INDIRECT("SubcategoriesTable[Category name]")=$B37),,)),_xlfn.CONCAT("No subcategories for"," ", $B37))} -> 0 | D37: 0 | E37: 0 | F37: 0 | G37: 0 | H37: 0 | I37: 0 | J37: 0 | K37: 0 | L37: 0 | M37: 0 | N37: 0 | O37: 0 | P37: 0 | Q37: 0 | R37: 0 | S37: 0 | T37: 0 | U37: 0 | V37: 0 | W37: 0 | X37: 0 | Y37: 0 | Z37: 0 | AA37: 0 | AB37: 0 | AC37: 0 | AD37: 0 | AE37: 0 | AF37: 0 | AG37: 0 | AH37: 0 | AI37: 0 | AJ37: 0 | AK37: 0 | AL37: 0 | AM37: 0 | AN37: 0 | AO37: 0 | AP37: 0 | AQ37: 0 | AR37: 0 | AS37: 0 | AT37: 0 | AU37: 0 | AV37: 0 | AW37: 0 | AX37: 0 | AY37: 0 | AZ37: 0 | BA37: 0 | BB37: 0 | BC37: 0 | BD37: 0 | BE37: 0 | BF37: 0 | BG37: 0 | BH37: 0 | BI37: 0 | BJ37: 0 | BK37: 0 | BL37: 0 | BM37: 0 | BN37: 0 | BO37: 0 | BP37: 0 | BQ37: 0 | BR37: 0 | BS37: 0 | BT37: 0 | BU37: 0 | BV37: 0 | BW37: 0 | BX37: 0 | BY37: 0 | BZ37: 0 | CA37: 0 | CB37: 0 | CC37: 0 | CD37: 0 | CE37: 0 | CF37: 0 | CG37: 0 | CH37: 0 | CI37: 0 | CJ37: 0 | CK37: 0 | CL37: 0 | CM37: 0 | CN37: 0 | CO37: 0 | CP37: 0
... C100: {=IFERROR(TRANSPOSE(INDEX(_xlfn._xlws.FILTER(INDIRECT("SubcategoriesTable[Subcategory name]"),INDIRECT("SubcategoriesTable[Category name]")=$B100),,)),_xlfn.CONCAT("No subcategories for"," ", $B100))} -> 0 | D100: 0 | E100: 0 | F100: 0 | G100: 0 | H100: 0 | I100: 0 | J100: 0 | K100: 0 | L100: 0 | M100: 0 | N100: 0 | O100: 0 | P100: 0 | Q100: 0 | R100: 0 | S100: 0 | T100: 0 | U100: 0 | V100: 0 | W100: 0 | X100: 0 | Y100: 0 | Z100: 0 | AA100: 0 | AB100: 0 | AC100: 0 | AD100: 0 | AE100: 0 | AF100: 0 | AG100: 0 | AH100: 0 | AI100: 0 | AJ100: 0 | AK100: 0 | AL100: 0 | AM100: 0 | AN100: 0 | AO100: 0 | AP100: 0 | AQ100: 0 | AR100: 0 | AS100: 0 | AT100: 0 | AU100: 0 | AV100: 0 | AW100: 0 | AX100: 0 | AY100: 0 | AZ100: 0 | BA100: 0 | BB100: 0 | BC100: 0 | BD100: 0 | BE100: 0 | BF100: 0 | BG100: 0 | BH100: 0 | BI100: 0 | BJ100: 0 | BK100: 0 | BL100: 0 | BM100: 0 | BN100: 0 | BO100: 0 | BP100: 0 | BQ100: 0 | BR100: 0 | BS100: 0 | BT100: 0 | BU100: 0 | BV100: 0 | BW100: 0 | BX100: 0 | BY100: 0 | BZ100: 0 | CA100: 0 | CB100: 0 | CC100: 0 | CD100: 0 | CE100: 0 | CF100: 0 | CG100: 0 | CH100: 0 | CI100: 0 | CJ100: 0 | CK100: 0 | CL100: 0 | CM100: 0 | CN100: 0 | CO100: 0 | CP100: 0

Sheet Institutions
A1: ID | B1: Institution name | C1: Institution nickname | E1: ID | F1: Institution ID | G1: Account# | H1: Account name | I1: Account nickname
A2: 0223204f73754797a10ae9c56a61ed0d | B2: SunTrust - Online Banking | C2: SunTrust - Online Banking | E2: 0ced1dbbb4a747578f3268aacbdce68e | F2: 0223204f73754797a10ae9c56a61ed0d | G2: 5413 | H2: Checking | I2: Checking
A3: 90bb019b232a41839a8b1ee417c22781 | B3: TD Ameritrade | C3: TD Ameritrade | E3: 21141238982c4fb29d514707963012ad | F3: 90bb019b232a41839a8b1ee417c22781 | G3: 4951 | H3: Brokerage Account - 4951 | I3: Brokerage Account - 4951
A4: 8bea4ec256a4491cb9bcafd4029691c5 | B4: Wells Fargo | C4: Wells Fargo | E4: 3f579d95c4b947338c4b835b7035b14c | F4: 8bea4ec256a4491cb9bcafd4029691c5 | G4: 4636 | H4: EVERYDAY CHECKING | I4: EVERYDAY CHECKING
A5: 1047e720dc9c4e08a5a78dcd4ad86b97 | B5: Robinhood | C5: Robinhood | E5: 36960db26bba4391860647c82c94f97b | F5: 1047e720dc9c4e08a5a78dcd4ad86b97 | G5: 4480 | H5: Checking - 4480 | I5: Checking - 4480
A6: 6dc51233b6fb471d952c564dcf5dce13 | B6: Discover | C6: Discover | E6: 4e6bb00cf0324f5aa6b6988462123810 | F6: 1047e720dc9c4e08a5a78dcd4ad86b97 | G6: 4480 | H6: Brokerage Account - 4480 | I6: Brokerage Account - 4480
A7: ea384fdcbf004c91a2b37c336a74368a | B7: Principal Financial Group - Participant Logon | C7: Principal Financial Group - Participant Logon | E7: c0ea6fc12dab42a6995744767fe779bd | F7: 6dc51233b6fb471d952c564dcf5dce13 | G7: 7328 | H7: Discover it chrome Card | I7: Discover it chrome Card
E8: febeaf892c0d42ca953f873555a77366 | F8: ea384fdcbf004c91a2b37c336a74368a | G8: 5568 | H8: Sean Lewis | I8: Sean Lewis
