Workbook
Name Allowance: #REF!
Name AprSun1: DATE(CalendarYear,4,1)-WEEKDAY(DATE(CalendarYear,4,1))
Name AugSun1: DATE(CalendarYear,8,1)-WEEKDAY(DATE(CalendarYear,8,1))
Name BaseTRSHH: '[1]Base Rate Schedules'!$F$32:$H$38
Name Box2c: #REF!
Name CalendarYear: [0]!Year1
Name Categories: OFFSET(#REF!,0,0,COUNTIF(#REF!,"<>"&"--"),1)
Name CategoryIdentifiers: [2]Categories!$B$8:$B$273
Name CategoryNames: #REF!
Name CategoryNames: [2]Categories!$C$8:$C$273
Name DecSun1: DATE(CalendarYear,12,1)-WEEKDAY(DATE(CalendarYear,12,1))
Name Essential: #REF!
Name Expense_Lookup: [3]Discover!$S:$T
Name FebSun1: DATE(CalendarYear,2,1)-WEEKDAY(DATE(CalendarYear,2,1))
Name FilStat19: #REF!
Name FilStat20: #REF!
Name HiddenCategoriesCategoryNames: _xlfn.ANCHORARRAY([2]HiddenCategories!$B$2)
Name HWRSHH: #REF!
Name HWRSMJ: #REF!
Name HWRSS: #REF!
Name JanSun1: DATE(CalendarYear,1,1)-WEEKDAY(DATE(CalendarYear,1,1))
Name JulSun1: DATE(CalendarYear,7,1)-WEEKDAY(DATE(CalendarYear,7,1))
Name JunSun1: DATE(CalendarYear,6,1)-WEEKDAY(DATE(CalendarYear,6,1))
Name LastCol: COUNTA('[3]PERSONAL BUDGET - WIP'!$4:$4)+1
Name MarSun1: DATE(CalendarYear,3,1)-WEEKDAY(DATE(CalendarYear,3,1))
Name MaySun1: DATE(CalendarYear,5,1)-WEEKDAY(DATE(CalendarYear,5,1))
Name MonthlyBudgetAvailableDates: _xlfn.ANCHORARRAY([2]MonthlyBudgetHidden!$C$2)
Name MonthlyBudgetNearestTransactionDate: [2]MonthlyBudgetHidden!$C$2
Name MonthlyBudgetUnusedCategoryNames: _xlfn.ANCHORARRAY([2]MonthlyBudgetHidden!$G$2)
Name MonthlyBudgetUsedCategoryNames: _xlfn.ANCHORARRAY([2]MonthlyBudgetHidden!$E$2)
Name MonthlyBudgetValidCategoryNames: _xlfn.ANCHORARRAY([2]MonthlyBudgetHidden!$D$2)
Name Months: OFFSET([2]Snapshot!$V$7,0,0,COUNTIF([2]Snapshot!$V$7:$V$200,"<>"&"--"),1)
Name Non_Essential: #REF!
Name NovSun1: DATE(CalendarYear,11,1)-WEEKDAY(DATE(CalendarYear,11,1))
Name OctSun1: DATE(CalendarYear,10,1)-WEEKDAY(DATE(CalendarYear,10,1))
Name PayFreq: #REF!
Name PrintArea_SET: OFFSET('[3]PERSONAL BUDGET - WIP'!$C$2,,,MATCH(REPT("z",255),'[3]PERSONAL BUDGET - WIP'!$C:$C),LastCol)
Name SDHH: #REF!
Name SDMJ: #REF!
Name SDS: #REF!
Name SepSun1: DATE(CalendarYear,9,1)-WEEKDAY(DATE(CalendarYear,9,1))
Name SubcategoryNames: [2]Categories!$I$8:$I$251
Name TRSHH: #REF!
Name TRSMJ: #REF!
Name TRSS: #REF!
Name Update12p: #REF!
Name Update22p: #REF!
Name Update24p: #REF!
Name Update32p: #REF!
Name Update35p: #REF!
Name Update37p: #REF!
Name UpdateWA: #REF!
Name user_custom_categories: #REF!
Name Version: #REF!
Name WRSHH: #REF!
Name WRSHH2020: #REF!
Name WRSMJ: #REF!
Name WRSMJ2020: #REF!
Name WRSS: #REF!
Name WRSS2020: #REF!

Sheet Sheet1
A1: Period | B1: Earnings | C1: Pre Tax Deductions | D1: Employee Taxes | E1: Post Tax Deductions | F1: Net Pay
A2: 05/31/2021 - 06/13/2021 (Bi-Weekly (Payroll)) | B2: 6798.37 | C2: 0 | D2: 2361.8 | E2: 0 | F2: 4436.57
A3: 06/14/2021 - 06/27/2021 (Bi-Weekly (Payroll)) | B3: 3024.86 | C3: 147.16 | D3: 833.26 | E3: 460.82 | F3: 1583.62
A4: 06/28/2021 - 07/11/2021 (Bi-Weekly (Payroll)) | B4: 3024.86 | C4: 147.16 | D4: 833.27 | E4: 460.82 | F4: 1583.61
A5: 07/12/2021 - 07/25/2021 (Bi-Weekly (Payroll)) | B5: 3024.86 | C5: 147.16 | D5: 833.22 | E5: 310.82 | F5: 1733.66
A6: 07/26/2021 - 08/08/2021 (Bi-Weekly (Payroll)) | B6: 3024.86 | C6: 147.16 | D6: 833.23 | E6: 10.82 | F6: 2033.65
A7: 08/09/2021 - 08/22/2021 (Bi-Weekly (Payroll)) | B7: 3024.86 | C7: 147.16 | D7: 833.23 | E7: 10.82 | F7: 2033.65
A8: 08/23/2021 - 09/05/2021 (Bi-Weekly (Payroll)) | B8: 3024.86 | C8: 147.16 | D8: 833.22 | E8: 10.82 | F8: 2033.66
A9: 09/06/2021 - 09/19/2021 (Bi-Weekly (Payroll)) | B9: 3024.86 | C9: 147.16 | D9: 687.54 | E9: 10.82 | F9: 2179.34
A10: 09/20/2021 - 10/03/2021 (Bi-Weekly (Payroll)) | B10: 3024.86 | C10: 147.16 | D10: 687.54 | E10: 160.82 | F10: 2029.34
A11: 10/04/2021 - 10/17/2021 (Bi-Weekly (Payroll)) | B11: 3249.6 | C11: 147.16 | D11: 762.27 | E11: 439.29 | F11: 1900.88
A12: 10/18/2021 - 10/31/2021 (Bi-Weekly (Payroll)) | B12: 3024.86 | C12: 147.16 | D12: 687.54 | E12: 289.29 | F12: 1900.87
A13: 11/01/2021 - 11/14/2021 (Bi-Weekly (Payroll)) | B13: 3024.86 | C13: 147.16 | D13: 687.53 | E13: 289.29 | F13: 1900.88
... A17: Totals | B17: 50648.08 | C17: 2882.39 | D17: 13150.37 | E17: 2602.3 | F17: 32013.02

Sheet Income
B1: 05/31/2021 - 06/13/2021 (Bi-Weekly (Payroll)) | C1: 06/14/2021 - 06/27/2021 (Bi-Weekly (Payroll)) | D1: 06/28/2021 - 07/11/2021 (Bi-Weekly (Payroll)) | E1: 07/12/2021 - 07/25/2021 (Bi-Weekly (Payroll)) | F1: 07/26/2021 - 08/08/2021 (Bi-Weekly (Payroll)) | G1: 08/09/2021 - 08/22/2021 (Bi-Weekly (Payroll)) | H1: 08/23/2021 - 09/05/2021 (Bi-Weekly (Payroll)) | I1: 09/06/2021 - 09/19/2021 (Bi-Weekly (Payroll)) | J1: 09/20/2021 - 10/03/2021 (Bi-Weekly (Payroll)) | K1: 10/04/2021 - 10/17/2021 (Bi-Weekly (Payroll)) | L1: 10/18/2021 - 10/31/2021 (Bi-Weekly (Payroll)) | M1: 11/01/2021 - 11/14/2021 (Bi-Weekly (Payroll)) | N1: 11/15/2021 - 11/28/2021 (Bi-Weekly (Payroll)) | O1: 11/29/2021 - 12/12/2021 (Bi-Weekly (Payroll)) | P1: 12/13/2021 - 12/26/2021 (Bi-Weekly (Payroll)) | Q1: 12/27/2021 - 01/09/2022 (Bi-Weekly (Payroll)) | R1: 01/10/2022 - 01/23/2022 (Bi-Weekly (Payroll)) | S1: 01/24/2021 - 02/06/2021 (Bi-Weekly (Payroll)) | T1: 02/07/2022 - 02/20/2022 (Bi-Weekly (Payroll)) | U1: 02/07/2022 - 03/06/2022 (Bi-Weekly (Payroll)) | V1: 03/07/2022 - 03/20/2022 (Bi-Weekly (Payroll)) | W1: 03/20/2022 - 04/03/2022 (Bi-Weekly (Payroll)) | X1: 04/04/2022 - 04/17/2022 (Bi-Weekly (Payroll)) | Y1: 04/18/2022 - 05/02/2022 (Bi-Weekly (Payroll)) | Z1: 05/02/2022 - 05/15/2022 (Bi-Weekly (Payroll)) | AA1: 05/16/2022 - 05/29/2022 (Bi-Weekly (Payroll)) | AB1: 05/30/2022 - 06/12/2022 (Bi-Weekly (Payroll)) | AC1: 06/13/2022 - 06/26/2022 (Bi-Weekly (Payroll)) | AD1: 06/27/2022 - 07/10/2022 (Bi-Weekly (Payroll)) | AE1: 07/11/2022 - 07/24/2022 (Bi-Weekly (Payroll)) | AF1: Projection
A2: Earnings
A3: Bonus - Non Discretionary | J3: 0 | K3: 0 | L3: 0 | M3: 0 | N3: 0 | O3: 0 | P3: 1200 | Q3: 3143
A4: Grossed Up Earnings | B4: 4098.37 | K4: 224.74
A5: LTD Benefit Credit | B5: 0 | C5: 4.86 | D5: 4.86 | E5: 4.86 | F5: 4.86 | G5: 4.86 | H5: 4.86 | I5: 4.86 | J5: 4.86 | K5: 4.86 | L5: 4.86 | M5: 4.86 | N5: 4.86 | O5: 4.86 | P5: 4.86 | Q5: 4.86 | R5: 4.98 | S5: 4.98 | T5: 4.98 | U5: 5.14 | V5: 5.14 | W5: 5.14 | X5: 5.14 | Y5: 5.73 | Z5: 5.73 | AA5: 5.73 | AB5: 5.73 | AC5: 5.73 | AD5: 5.73 | AE5: 5.73 | AF5: 5.73
A6: My Health Completion Credit | B6: 0 | C6: 20 | D6: 20 | E6: 20 | F6: 20 | G6: 20 | H6: 20 | I6: 20 | J6: 20 | K6: 20 | L6: 20 | M6: 20 | N6: 20 | O6: 20 | P6: 20 | Q6: 20 | R6: 20 | S6: 20 | T6: 20 | U6: 20 | V6: 20 | W6: 20 | X6: 20 | Y6: 20 | Z6: 20 | AA6: 20 | AB6: 20 | AC6: 20 | AD6: 20 | AE6: 20 | AF6: 20
A7: Regular | B7: 2700 | C7: 3000 | D7: 3000 | E7: 3000 | F7: 3000 | G7: 3000 | H7: 3000 | I7: 3000 | J7: 3000 | K7: 3000 | L7: 3000 | M7: 3000 | N7: 3000 | O7: 3000 | P7: 3076.93 | Q7: 3076.93 | R7: 3076.93 | S7: 3076.93 | T7: 3076.93 | U7: 3173.08 | V7: 3173.08 | W7: 3173.08 | X7: 3173.08 | Y7: 3538.47 | Z7: 3538.47 | AA7: 3538.47 | AB7: 3538.47 | AC7: 3538.47 | AD7: 3538.47 | AE7: 3538.47 | AF7: 3538.47
A8: Pre Tax Deductions
A9: Group Accident Coverage | R9: 0.82 | S9: 0.82 | T9: 0.82 | U9: 0.84 | V9: 0.84 | W9: 0.84 | X9: 0.84 | Y9: 0.94 | Z9: 0.94 | AA9: 0.94 | AB9: 0.94 | AC9: 0.94 | AD9: 0.94 | AE9: 0.94 | AF9: 0.94
A10: Health Savings Account | B10: 0 | C10: 54.77 | D10: 54.77 | E10: 54.77 | F10: 54.77 | G10: 54.77 | H10: 54.77 | I10: 54.77 | J10: 54.77 | K10: 54.77 | L10: 54.77 | M10: 54.77 | N10: 54.77 | O10: 54.77 | P10: 54.77 | Q10: 111.15 | R10: 111.15 | S10: 111.15 | T10: 111.15 | U10: 111.15 | V10: 111.15 | W10: 111.15 | X10: 111.15 | Y10: 111.15 | Z10: 111.15 | AA10: 111.15 | AB10: 111.15 | AC10: 111.15 | AD10: 111.15 | AE10: 111.15 | AF10: 111.15
A11: Medical Coverage | B11: 0 | C11: 87 | D11: 87 | E11: 87 | F11: 87 | G11: 87 | H11: 87 | I11: 87 | J11: 87 | K11: 87 | L11: 87 | M11: 87 | N11: 87 | O11: 87 | P11: 87 | Q11: 66 | R11: 66 | S11: 66 | T11: 66 | U11: 66 | V11: 66 | W11: 66 | X11: 66 | Y11: 66 | Z11: 66 | AA11: 66 | AB11: 66 | AC11: 66 | AD11: 66 | AE11: 66 | AF11: 66
A12: Supplemental Accident Coverage | B12: 0 | C12: 1.6 | D12: 1.6 | E12: 1.6 | F12: 1.6 | G12: 1.6 | H12: 1.6 | I12: 1.6 | J12: 1.6 | K12: 1.6 | L12: 1.6 | M12: 1.6 | N12: 1.6 | O12: 1.6 | P12: 1.6 | Q12: 1.7 | R12: 1.7 | S12: 1.7 | T12: 1.7 | U12: 1.7 | V12: 1.7 | W12: 1.7 | X12: 1.7 | Y12: 1.7 | Z12: 1.7 | AA12: 1.7 | AB12: 1.7 | AC12: 1.7 | AD12: 1.7 | AE12: 1.7 | AF12: 1.7
A13: Vision Coverage | B13: 0 | C13: 3.79 | D13: 3.79 | E13: 3.79 | F13: 3.79 | G13: 3.79 | H13: 3.79 | I13: 3.79 | J13: 3.79 | K13: 3.79 | L13: 3.79 | M13: 3.79 | N13: 3.79 | O13: 3.79 | P13: 3.79 | Q13: 3.79 | R13: 3.79 | S13: 3.79 | T13: 3.79 | U13: 3.79 | V13: 3.79 | W13: 3.79 | X13: 3.79 | Y13: 3.79 | Z13: 3.79 | AA13: 3.79 | AB13: 3.79 | AC13: 3.79 | AD13: 3.79 | AE13: 3.79 | AF13: 3.79
A14: Nationwide Savings Plan | B14: 0 | C14: 0 | D14: 0 | E14: 0 | F14: 0 | G14: 0 | H14: 0 | I14: 0 | J14: 0 | K14: 0 | L14: 0 | M14: 0 | N14: 240 | O14: 240 | P14: 342.15 | Q14: =Q7*Q39 -> 0 | R14: 615.39 | S14: 615.39 | T14: 0 | U14: 0 | V14: 0 | W14: 0 | X14: 0 | Y14: 0 | Z14: 0 | AA14: 0 | AB14: 0 | AC14: 0 | AD14: 0 | AE14: 0 | AF14: =AF7*0.15 -> 530.7705 | AG14: =S14-AF14 -> 84.6195
A15: Federal and FICA Taxable Wages | B15: =SUM(B4:B7)-SUM(B10:B13) -> 6798.37 | C15: =SUM(C4:C7)-SUM(C10:C13) -> 2877.7 | D15: =SUM(D4:D7)-SUM(D10:D13) -> 2877.7 | E15: =SUM(E4:E7)-SUM(E10:E13) -> 2877.7 | F15: =SUM(F4:F7)-SUM(F10:F13) -> 2877.7 | G15: =SUM(G4:G7)-SUM(G10:G13) -> 2877.7 | H15: =SUM(H4:H7)-SUM(H10:H13) -> 2877.7 | I15: =SUM(I4:I7)-SUM(I10:I13) -> 2877.7 | ... M15: =SUM(M4:M7)-SUM(M10:M13) -> 2877.7 | N15: =SUM(N3:N7)-SUM(N10:N14) -> 2637.7 | O15: =SUM(O3:O7)-SUM(O10:O14) -> 2637.7 | P15: =SUM(P3:P7)-SUM(P10:P14) -> 3812.48 | Q15: =SUM(Q3:Q7)-SUM(Q10:Q14) -> 6062.15 | R15: =SUM(R3:R7)-SUM(R9:R13)+1.42 -> 2919.87 | S15: =SUM(S3:S7)-SUM(S9:S13)+1.42 -> 2919.87 | T15: =SUM(T3:T7)-SUM(T9:T14)+1.42 -> 2919.87 | U15: =SUM(U3:U7)-SUM(U9:U14)+1.55 -> 3016.29 | V15: =SUM(V3:V7)-SUM(V9:V14)+1.55 -> 3016.29 | W15: =SUM(W3:W7)-SUM(W9:W14)+1.55 -> 3016.29 | X15: =SUM(X3:X7)-SUM(X9:X14)+1.55 -> 3016.29 | Y15: =SUM(Y3:Y7)-SUM(Y9:Y14)+1.92 -> 3382.54 | Z15: =SUM(Z3:Z7)-SUM(Z9:Z14)+1.92 -> 3382.54 | AA15: =SUM(AA3:AA7)-SUM(AA9:AA14)+1.92 -> 3382.54 | AB15: =SUM(AB3:AB7)-SUM(AB9:AB14)+1.92 -> 3382.54 | AC15: =SUM(AC3:AC7)-SUM(AC9:AC14)+1.92 -> 3382.54 | AD15: =SUM(AD3:AD7)-SUM(AD9:AD14)+1.92 -> 3382.54 | AE15: =SUM(AE3:AE7)-SUM(AE9:AE14)+1.92 -> 3382.54 | AF15: =SUM(AF3:AF7)-SUM(AF9:AF13)+1.92 -> 3382.54
A16: Taxes
A17: OASDI | B17: 421.5 | C17: 178.5 | D17: 178.5 | E17: 178.5 | F17: 178.5 | G17: 178.5 | H17: 178.5 | I17: 178.5 | J17: 178.5 | K17: 192.44 | L17: 178.5 | M17: 178.5 | N17: 178.5 | O17: 178.5 | P17: 257.67 | Q17: 375.97432 | R17: 181.03 | S17: 181.03 | T17: 181.03 | U17: 187.01 | V17: 187.01 | W17: 187.01 | X17: 187.01 | Y17: 209.72 | Z17: 209.72 | AA17: 209.72 | AB17: 209.72 | AC17: 209.72 | AD17: 209.72 | AE17: 209.72 | AF17: =$AF$15*AE33 -> 209.72
A18: Medicare | B18: 98.58 | C18: 41.74 | D18: 41.75 | E18: 41.74 | F18: 41.75 | G18: 41.75 | H18: 41.74 | I18: 41.75 | J18: 41.75 | K18: 45 | L18: 41.75 | M18: 41.74 | N18: 41.75 | O18: 41.74 | P18: 60.27 | Q18: 87.941834 | R18: 42.34 | S18: 42.34 | T18: 42.33 | U18: 43.74 | V18: 43.74 | W18: 43.73 | X18: 43.74 | Y18: 49.05 | Z18: 49.04 | AA18: 49.04 | AB18: 49.05 | AC18: 49.04 | AD18: 49.05 | AE18: 49.04 | AF18: =$AF$15*AE34 -> 49.04
A19: Federal | B19: 1225.93 | C19: 363.68 | D19: 363.68 | E19: 363.64 | F19: 363.64 | G19: 363.64 | H19: 363.64 | I19: 363.64 | J19: 363.64 | K19: 413.09 | L19: 363.64 | M19: 363.64 | N19: 310.84 | O19: 310.84 | P19: 569.29 | Q19: 1079.0506 | R19: 228.8 | S19: 228.8 | T19: 364.18 | U19: 385.39 | V19: 385.39 | W19: 385.39 | X19: 385.39 | Y19: 465.96 | Z19: 465.96 | AA19: 465.96 | AB19: 465.96 | AC19: 465.96 | AD19: 465.96 | AE19: 465.96 | AF19: =$AF$15*AE35 -> 465.96
A20: State Tax (VA) | B20: 371.05 | C20: 145.69 | D20: 145.69 | E20: 145.69 | F20: 145.69 | G20: 145.69 | H20: 145.69
A21: State Tax (AZ) | B21: 244.74 | C21: 103.65 | D21: 103.65 | E21: 103.65 | F21: 103.65 | G21: 103.65 | H21: 103.65 | I21: 103.65 | J21: 103.65 | K21: 111.74 | L21: 103.65 | M21: 103.65 | N21: 95.01 | O21: 95.01 | P21: 137.3 | Q21: 218.2374 | R21: 82.96 | S21: 82.96 | T21: 105.12 | U21: 108.59 | V21: 108.59 | W21: 108.59 | X21: 108.59 | Y21: 121.77 | Z21: 121.77 | AA21: 121.77 | AB21: 121.77 | AC21: 121.77 | AD21: 121.77 | AE21: 121.77 | AF21: =AE37*(AF15-AF14) -> 102.66249
A22: Post Tax Deductions
A23: Life Insurance Coverage | B23: 0 | C23: 1.13 | D23: 1.13 | E23: 1.13 | F23: 1.13 | G23: 1.13 | H23: 1.13 | I23: 1.13 | J23: 1.13 | K23: 1.13 | L23: 1.13 | M23: 1.13 | N23: 1.13 | O23: 1.13 | P23: 1.13 | Q23: 1.16 | R23: 1.16 | S23: 1.16 | T23: 1.16 | U23: 1.22 | V23: 1.22 | W23: 1.22 | X23: 1.22 | Y23: 1.33 | Z23: 1.33 | AA23: 1.33 | AB23: 1.33 | AC23: 1.33 | AD23: 1.33 | AE23: 1.33 | AF23: 1.33
A24: Long Term Disability Coverage | B24: 0 | C24: 9.69 | D24: 9.69 | E24: 9.69 | F24: 9.69 | G24: 9.69 | H24: 9.69 | I24: 9.69 | J24: 9.69 | K24: 9.69 | L24: 9.69 | M24: 9.69 | N24: 9.69 | O24: 9.69 | P24: 9.69 | Q24: 9.94 | R24: 9.94 | S24: 9.94 | T24: 9.94 | U24: 10.25 | V24: 10.25 | W24: 10.25 | X24: 10.25 | Y24: 11.43 | Z24: 11.43 | AA24: 11.43 | AB24: 11.43 | AC24: 11.43 | AD24: 11.43 | AE24: 11.43 | AF24: 11.43
A25: NSP AfterTax Deduction NonRoth | C25: 450 | D25: 450 | E25: 300
A26: Bravo Award - No Cash Net | K26: 150
A27: Charitable Giving | K27: 38.47 | L27: 38.47 | M27: 38.47 | N27: 38.47 | O27: 38.47 | P27: 38.47 | Q27: 38.47 | R27: 38.47 | S27: 38.47 | T27: 38.47 | U27: 38.47 | V27: 38.47 | W27: 38.47 | X27: 38.47 | Y27: 38.47 | Z27: 38.47 | AA27: 38.47 | AB27: 38.47 | AC27: 38.47 | AD27: 38.47 | AE27: 38.47 | AF27: 38.47
A28: Roth 401k Deduction - ROTH | J28: 150 | K28: 240 | L28: 240 | M28: 240
A30: Net Income | B30: =B15-SUM(B17:B21)-SUM(B23:B28) -> 4436.57 | C30: =C15-SUM(C17:C21)-SUM(C23:C28) -> 1583.62 | D30: =D15-SUM(D17:D21)-SUM(D23:D28) -> 1583.61 | E30: =E15-SUM(E17:E21)-SUM(E23:E28) -> 1733.66 | F30: =F15-SUM(F17:F21)-SUM(F23:F28) -> 2033.65 | G30: =G15-SUM(G17:G21)-SUM(G23:G28) -> 2033.65 | H30: =H15-SUM(H17:H21)-SUM(H23:H28) -> 2033.66 | I30: =I15-SUM(I17:I21)-SUM(I23:I28) -> 2179.34 | ... Q30: =Q15-SUM(Q17:Q21)-SUM(Q23:Q28) -> 4251.3758 | R30: =R15-SUM(R17:R21)-SUM(R23:R28)-R14-1.55 -> 1718.23 | S30: =S15-SUM(S17:S21)-SUM(S23:S28)-S14-1.55 -> 1718.23 | T30: =T15-SUM(T17:T21)-SUM(T23:T28)-1.42 -> 2176.22 | U30: =U15-SUM(U17:U21)-SUM(U23:U28)-1.55 -> 2240.07 | V30: =V15-SUM(V17:V21)-SUM(V23:V28)-1.55 -> 2240.07 | W30: =W15-SUM(W17:W21)-SUM(W23:W28)-1.55 -> 2240.08 | X30: =X15-SUM(X17:X21)-SUM(X23:X28)-1.55 -> 2240.07 | Y30: =Y15-SUM(Y17:Y21)-SUM(Y23:Y28)-1.92 -> 2482.89 | Z30: =Z15-SUM(Z17:Z21)-SUM(Z23:Z28)-1.92 -> 2482.9 | AA30: =AA15-SUM(AA17:AA21)-SUM(AA23:AA28)-1.92 -> 2482.9 | AB30: =AB15-SUM(AB17:AB21)-SUM(AB23:AB28)-1.92 -> 2482.89 | AC30: =AC15-SUM(AC17:AC21)-SUM(AC23:AC28)-1.92 -> 2482.9 | AD30: =AD15-SUM(AD17:AD21)-SUM(AD23:AD28)-1.92 -> 2482.89 | AE30: =AE15-SUM(AE17:AE21)-SUM(AE23:AE28)-1.92 -> 2482.9 | AF30: =AF15-SUM(AF17:AF21)-SUM(AF23:AF28)-1.92-AF14 -> 1971.237
A32: Taxes
A33: OASDI | B33: =B17/B$15 -> 0.062000156 | C33: =C17/C$15 -> 0.062028703 | D33: =D17/D$15 -> 0.062028703 | E33: =E17/E$15 -> 0.062028703 | F33: =F17/F$15 -> 0.062028703 | G33: =G17/G$15 -> 0.062028703 | H33: =H17/H$15 -> 0.062028703 | I33: =I17/I$15 -> 0.062028703 | ... AF33: =AF17/AF$15 -> 0.062000745
A34: Medicare | B34: =B18/B$15 -> 0.014500535 | C34: =C18/C$15 -> 0.014504639 | D34: =D18/D$15 -> 0.014508114 | E34: =E18/E$15 -> 0.014504639 | F34: =F18/F$15 -> 0.014508114 | G34: =G18/G$15 -> 0.014508114 | H34: =H18/H$15 -> 0.014504639 | I34: =I18/I$15 -> 0.014508114 | ... AF34: =AF18/AF$15 -> 0.014497981
A35: Federal | B35: =B19/B$15 -> 0.18032705 | C35: =C19/C$15 -> 0.12637871 | D35: =D19/D$15 -> 0.12637871 | E35: =E19/E$15 -> 0.12636481 | F35: =F19/F$15 -> 0.12636481 | G35: =G19/G$15 -> 0.12636481 | H35: =H19/H$15 -> 0.12636481 | I35: =I19/I$15 -> 0.12636481 | ... AF35: =AF19/AF$15 -> 0.13775447
A36: State Tax (VA) | B36: =B20/B$15 -> 0.054579259 | C36: =C20/C$15 -> 0.050627237 | D36: =D20/D$15 -> 0.050627237 | E36: =E20/E$15 -> 0.050627237 | F36: =F20/F$15 -> 0.050627237 | G36: =G20/G$15 -> 0.050627237 | H36: =H20/H$15 -> 0.050627237 | I36: =I20/I$15 -> 0 | ... AF36: =AF20/AF$15 -> 0
A37: State Tax (AZ) | B37: =B21/(B$15-B14) -> 0.035999806 | C37: =C21/(C$15-C14) -> 0.036018348 | D37: =D21/(D$15-D14) -> 0.036018348 | E37: =E21/(E$15-E14) -> 0.036018348 | F37: =F21/(F$15-F14) -> 0.036018348 | G37: =G21/(G$15-G14) -> 0.036018348 | H37: =H21/(H$15-H14) -> 0.036018348 | I37: =I21/(I$15-I14) -> 0.036018348 | ... AF37: =AF21/(AF$15-AF14) -> 0.035999574
A38: Nationwide Savings Plan | B38: =B14/B7 -> 0 | C38: =C14/C7 -> 0 | D38: =D14/D7 -> 0 | E38: =E14/E7 -> 0 | F38: =F14/F7 -> 0 | G38: =G14/G7 -> 0 | H38: =H14/H7 -> 0 | I38: =I14/I7 -> 0 | ... AF38: =AF14/AF7 -> 0.15
A39: Roth | B39: =B28/B7 -> 0 | C39: =C28/C7 -> 0 | D39: =D28/D7 -> 0 | E39: =E28/E7 -> 0 | F39: =F28/F7 -> 0 | G39: =G28/G7 -> 0 | H39: =H28/H7 -> 0 | I39: =I28/I7 -> 0 | ... AF39: =AF28/AF7 -> 0
R40: =0.2*R7 -> 615.386 | S40: =0.2*S7 -> 615.386 | T40: =0.2*T7 -> 615.386 | U40: =0.2*U7 -> 634.616 | V40: =0.2*V7 -> 634.616 | W40: =0.2*W7 -> 634.616 | X40: =0.2*X7 -> 634.616 | Y40: =0.15*Y7 -> 530.7705 | Z40: =0.15*Z7 -> 530.7705 | AA40: =0.15*AA7 -> 530.7705 | AB40: =0.15*AB7 -> 530.7705 | AC40: =0.15*AC7 -> 530.7705 | AD40: =0.15*AD7 -> 530.7705 | AE40: =0.15*AE7 -> 530.7705 | AF40: =0.15*AF7 -> 530.7705
S41: =S30/S15 -> 0.58846113
AF42: =2000-AF30 -> 28.762988

Sheet Federal Tax Estimate
A1: Table 3 | D1: Semiannually | E1: Quarterly | F1: Monthly | G1: Semimonthly | H1: Biweekly | I1: Weekly | J1: Daily | P1: 363.68
D2: 2 | E2: 4 | F2: 12 | G2: 24 | H2: 26 | I2: 52 | J2: 260
B4: Step 1. | D4: Adjust the employee's payment amount
D5: 1a | E5: Enter the employee’s total taxable wages this payroll period | L5: 1a | M5: =Income!Q15 -> 6062.15
D6: 1b | E6: Enter the number of pay periods you have per year (see Table 3) | L6: 1b | M6: =H2 -> 26
D7: 1c | E7: Multiply the amount on line 1a by the number on line 1b | L7: 1c | M7: =M6*M5 -> 157615.9
C9: If the employee HAS submitted a Form W-4 for 2020 or later, figure the Adjusted Annual Wage Amount as follows:
D10: 1d | E10: Enter the amount from Step 4(a) of the employee's Form W-4 | L10: 1d | M10: 0
D11: 1e | E11: Add lines 1c and 1d | L11: 1e | M11: =M10+M7 -> 157615.9
D12: 1f | E12: Enter the amount from Step 4(b) of the employee's Form W-4 | L12: 1f | M12: 0
D13: 1g | E13: If the box in Step 2 of Form W-4 is checked, enter -0-. If the box is not checked, enter $12,900 if the taxpayer is married filing jointly or $8,600 otherwise | L13: 1g | M13: 0
D14: 1h | E14: Add lines 1f and 1g | L14: 1h | M14: 0
D15: 1i | E15: Subtract line 1h from line 1e. If zero or less, enter -0-. This is the Adjusted Annual Wage Amount | L15: 1i | M15: =M11 -> 157615.9
C17: If the employee HAS NOT submitted a Form W-4 for 2020 or later, figure the Adjusted Annual Wage Amount as follows:
D18: 1j | E18: Enter the number of allowances claimed on the employee's most recent Form W-4 | L18: 1j
D19: 1k | E19: Multiply line 1j by $4,300 | L19: 1k
D20: 1l | E20: Subtract line 1k from line 1c. If zero or less, enter -0-. This is the Adjusted Annual Wage Amount | L20: 1l
B22: Step 2. | D22: Figure the Tentative Withholding Amount
D23: based on the employee's Adjusted Annual Wage Amount; filing status (Step 1(c) of the 2020 or later Form W-4) or marital status (line 3 of Form W-4 from 2019 or earlier); and whether the box in Step 2 of 2020 or later Form W-4 is checked.
D24: Note. Don't use the Head of Household table if the Form W-4 is from 2019 or earlier.
D26: 2a | E26: Enter the employee's Adjusted Annual Wage Amount from line 1i or 1l above | L26: 2a | M26: =M15 -> 157615.9
D27: 2b | E27: Find the row in the appropriate Annual Percentage Method table in which the amount on line 2a is at least the amount in column A but less than the amount in column B, then enter here the amount from column A of that row | L27: 2b | M27: =VLOOKUP(1,'Tax Table'!A3:F10,2,0) -> 102025
D28: 2c | E28: Enter the amount from column C of that row | L28: 2c | M28: =VLOOKUP(1,'Tax Table'!A3:F10,4,0) -> 15213.5
D29: 2d | E29: Enter the percentage from column D of that row | L29: 2d | M29: =VLOOKUP(1,'Tax Table'!A3:F10,5,0) -> 0.24
D30: 2e | E30: Subtract line 2b from line 2a | L30: 2e | M30: =M26-M27 -> 55590.9
D31: 2f | E31: Multiply the amount on line 2e by the percentage on line 2d | L31: 2f | M31: =M30*M29 -> 13341.816
D32: 2g | E32: Add lines 2c and 2f | L32: 2g | M32: =M31+M28 -> 28555.316
D33: 2h | E33: Divide the amount on line 2g by the number of pay periods on line 1b. This is the Tentative Withholding Amount | L33: 2h | M33: =M32/M6 -> 1098.2814
B35: Step 3. | D35: Account for tax credits
D36: 3a | E36: If the employee's Form W-4 is from 2020 or later, enter the amount from Step 3 of that form; otherwise, enter -0- | L36: 3a | M36: 500
D37: 3b | E37: Divide the amount on line 3a by the number of pay periods on line 1b | L37: 3b | M37: =M36/M6 -> 19.230769
D38: 3c | E38: Subtract line 3b from line 2h. If zero or less, enter -0- | L38: 3c | M38: =M33-M37 -> 1079.0506
B40: Step 4. | D40: Figure the final amount to withhold
D41: 4a | E41: Enter the additional amount to withhold from the employee’s Form W-4 (Step 4(c) of the 2020 or later form or line 6 on earlier forms) | L41: 4a | M41: 0
D42: 4b | E42: Add lines 3c and 4a. This is the amount to withhold from the employee’s wages this pay period | M42: =M38-M41 -> 1079.0506

Sheet Tax Table
B1: A | C1: B | D1: C | E1: D | F1: E
B2: Single or Married Filing Separately
A3: =IF(AND('Federal Tax Estimate'!$M$15>='Tax Table'!B3,'Federal Tax Estimate'!$M$15<='Tax Table'!C3),1,0) -> 0 | B3: 0 | C3: 6475 | D3: 0 | E3: 0 | F3: 0
A4: =IF(AND('Federal Tax Estimate'!$M$15>='Tax Table'!B4,'Federal Tax Estimate'!$M$15<='Tax Table'!C4),1,0) -> 0 | B4: 12950 | C4: =B5 -> 23225 | D4: 0 | E4: 0.1 | F4: 6475
A5: =IF(AND('Federal Tax Estimate'!$M$15>='Tax Table'!B5,'Federal Tax Estimate'!$M$15<='Tax Table'!C5),1,0) -> 0 | B5: 23225 | C5: =B6 -> 54725 | D5: 1027.5 | E5: 0.12 | F5: 11613
A6: =IF(AND('Federal Tax Estimate'!$M$15>='Tax Table'!B6,'Federal Tax Estimate'!$M$15<='Tax Table'!C6),1,0) -> 0 | B6: 54725 | C6: =B7 -> 102025 | D6: 4807.5 | E6: 0.22 | F6: 27363
A7: =IF(AND('Federal Tax Estimate'!$M$15>='Tax Table'!B7,'Federal Tax Estimate'!$M$15<='Tax Table'!C7),1,0) -> 1 | B7: 102025 | C7: =B8 -> 183000 | D7: 15213.5 | E7: 0.24 | F7: 51013
A8: =IF(AND('Federal Tax Estimate'!$M$15>='Tax Table'!B8,'Federal Tax Estimate'!$M$15<='Tax Table'!C8),1,0) -> 0 | B8: 183000 | C8: =B9 -> 228900 | D8: 34647.5 | E8: 0.32 | F8: 91500
A9: =IF(AND('Federal Tax Estimate'!$M$15>='Tax Table'!B9,'Federal Tax Estimate'!$M$15<='Tax Table'!C9),1,0) -> 0 | B9: 228900 | C9: =B10 -> 552850 | D9: 49335.5 | E9: 0.35 | F9: 114450
A10: =IF(AND('Federal Tax Estimate'!$M$15>='Tax Table'!B10,'Federal Tax Estimate'!$M$15<='Tax Table'!C10),1,0) -> 0 | B10: 552850 | D10: 162718 | E10: 0.37 | F10: 276425
B12: Head of Household
B13: 0 | C13: 9700 | D13: 0 | E13: 0 | F13: 0
B14: 9700 | C14: 17025 | D14: 0 | E14: 0.1 | F14: 9700
B15: 17025 | C15: 37650 | D15: 732.5 | E15: 0.12 | F15: 17025
B16: 37650 | C16: 54225 | D16: 3207.5 | E16: 0.22 | F16: 37650
B17: 54225 | C17: 94725 | D17: 6854 | E17: 0.24 | F17: 54225
B18: 94725 | C18: 117675 | D18: 16574 | E18: 0.32 | F18: 94725
B19: 117675 | C19: 279650 | D19: 23918 | E19: 0.35 | F19: 117675
B20: 279650 | D20: 80609.25 | E20: 0.37 | F20: 279650
