Workbook

Sheet Discover Data
B1: Trans. Date | C1: Post Date | D1: Description | E1: Amount | F1: Category | G1: Short_Desc | H1: Date | I1: Reoccurring_Flag | J1: Category_2 | K1: CumAmount | N1: 01/2022 | O1: 02/2022 | P1: 03/2022 | Q1: 04/2022 | R1: 05/2022 | S1: 06/2022 | T1: 07/2022 | U1: 08/2022 | V1: 09/2022 | W1: 10/2022 | X1: 11/2022 | Y1: 12/2022
A2: 0 | B2: 01/01/2022 | C2: 01/01/2022 | D2: Balance | E2: 3581.67 | F2: Balance | G2: Balance | K2: 3581.67 | M2: Automotive | N2: =SUMIFS(dis_table[Amount],dis_table[Category],$M2,dis_table[Date],N$1) -> 42.34 | O2: =SUMIFS(dis_table[Amount],dis_table[Category],$M2,dis_table[Date],O$1) -> 0 | P2: =SUMIFS(dis_table[Amount],dis_table[Category],$M2,dis_table[Date],P$1) -> 0 | Q2: =SUMIFS(dis_table[Amount],dis_table[Category],$M2,dis_table[Date],Q$1) -> 0 | R2: =SUMIFS(dis_table[Amount],dis_table[Category],$M2,dis_table[Date],R$1) -> 0 | S2: =SUMIFS(dis_table[Amount],dis_table[Category],$M2,dis_table[Date],S$1) -> 0 | T2: =SUMIFS(dis_table[Amount],dis_table[Category],$M2,dis_table[Date],T$1) -> 21 | U2: =SUMIFS(dis_table[Amount],dis_table[Category],$M2,dis_table[Date],U$1) -> 130.33 | ... Y2: =SUMIFS(dis_table[Amount],dis_table[Category],$M2,dis_table[Date],Y$1) -> 0
A3: 1 | B3: 01/01/2022 | C3: 01/01/2022 | D3: JIMMY JOHNS - 2500 PHOENIX AZ | E3: 18.02 | F3: Restaurants | G3: fast_food | H3: 01/2022 | I3: No | J3: Food | K3: 3599.69 | M3: Education | N3: =SUMIFS(dis_table[Amount],dis_table[Category],$M3,dis_table[Date],N$1) -> 0 | O3: =SUMIFS(dis_table[Amount],dis_table[Category],$M3,dis_table[Date],O$1) -> 0 | P3: =SUMIFS(dis_table[Amount],dis_table[Category],$M3,dis_table[Date],P$1) -> 0 | Q3: =SUMIFS(dis_table[Amount],dis_table[Category],$M3,dis_table[Date],Q$1) -> 21.71 | R3: =SUMIFS(dis_table[Amount],dis_table[Category],$M3,dis_table[Date],R$1) -> 0 | S3: =SUMIFS(dis_table[Amount],dis_table[Category],$M3,dis_table[Date],S$1) -> 298 | T3: =SUMIFS(dis_table[Amount],dis_table[Category],$M3,dis_table[Date],T$1) -> 100.25 | U3: =SUMIFS(dis_table[Amount],dis_table[Category],$M3,dis_table[Date],U$1) -> 33 | ... Y3: =SUMIFS(dis_table[Amount],dis_table[Category],$M3,dis_table[Date],Y$1) -> 0
A4: 2 | B4: 01/01/2022 | C4: 01/01/2022 | D4: OLIVE GARDE00064212140 PHOENIX AZ | E4: 60 | F4: Restaurants | G4: restaurant | H4: 01/2022 | I4: No | J4: Food | K4: 3659.69 | M4: Gasoline | N4: =SUMIFS(dis_table[Amount],dis_table[Category],$M4,dis_table[Date],N$1) -> 92.41 | O4: =SUMIFS(dis_table[Amount],dis_table[Category],$M4,dis_table[Date],O$1) -> 0 | P4: =SUMIFS(dis_table[Amount],dis_table[Category],$M4,dis_table[Date],P$1) -> 342.53 | Q4: =SUMIFS(dis_table[Amount],dis_table[Category],$M4,dis_table[Date],Q$1) -> 3.59 | R4: =SUMIFS(dis_table[Amount],dis_table[Category],$M4,dis_table[Date],R$1) -> 73.21 | S4: =SUMIFS(dis_table[Amount],dis_table[Category],$M4,dis_table[Date],S$1) -> 11.8 | T4: =SUMIFS(dis_table[Amount],dis_table[Category],$M4,dis_table[Date],T$1) -> 229.64 | U4: =SUMIFS(dis_table[Amount],dis_table[Category],$M4,dis_table[Date],U$1) -> 0 | ... Y4: =SUMIFS(dis_table[Amount],dis_table[Category],$M4,dis_table[Date],Y$1) -> 0
A5: 3 | B5: 01/01/2022 | C5: 01/03/2022 | D5: NETFLIX.COM NETFLIX.COM CAITEM TRANSFERRED FROM PREV ACCOUNT | E5: 14.83 | F5: Merchandise | G5: netflix | H5: 01/2022 | I5: Yes | J5: Recreation_Entertainment | K5: 3674.52 | M5: Government Services | N5: =SUMIFS(dis_table[Amount],dis_table[Category],$M5,dis_table[Date],N$1) -> 0 | O5: =SUMIFS(dis_table[Amount],dis_table[Category],$M5,dis_table[Date],O$1) -> 0 | P5: =SUMIFS(dis_table[Amount],dis_table[Category],$M5,dis_table[Date],P$1) -> 35 | Q5: =SUMIFS(dis_table[Amount],dis_table[Category],$M5,dis_table[Date],Q$1) -> 0 | R5: =SUMIFS(dis_table[Amount],dis_table[Category],$M5,dis_table[Date],R$1) -> 0 | S5: =SUMIFS(dis_table[Amount],dis_table[Category],$M5,dis_table[Date],S$1) -> 0 | T5: =SUMIFS(dis_table[Amount],dis_table[Category],$M5,dis_table[Date],T$1) -> 0 | U5: =SUMIFS(dis_table[Amount],dis_table[Category],$M5,dis_table[Date],U$1) -> 0 | ... Y5: =SUMIFS(dis_table[Amount],dis_table[Category],$M5,dis_table[Date],Y$1) -> 0
A6: 4 | B6: 01/01/2022 | C6: 01/03/2022 | D6: SPOTIFY P18D298A28 8777781161 NYITEM TRANSFERRED FROM PREV ACCOUNT | E6: 9.99 | F6: Merchandise | G6: spotify | H6: 01/2022 | I6: Yes | J6: Recreation_Entertainment | K6: 3684.51 | M6: Home Improvement | N6: =SUMIFS(dis_table[Amount],dis_table[Category],$M6,dis_table[Date],N$1) -> 0 | O6: =SUMIFS(dis_table[Amount],dis_table[Category],$M6,dis_table[Date],O$1) -> 0 | P6: =SUMIFS(dis_table[Amount],dis_table[Category],$M6,dis_table[Date],P$1) -> 0 | Q6: =SUMIFS(dis_table[Amount],dis_table[Category],$M6,dis_table[Date],Q$1) -> 0 | R6: =SUMIFS(dis_table[Amount],dis_table[Category],$M6,dis_table[Date],R$1) -> 0 | S6: =SUMIFS(dis_table[Amount],dis_table[Category],$M6,dis_table[Date],S$1) -> 0 | T6: =SUMIFS(dis_table[Amount],dis_table[Category],$M6,dis_table[Date],T$1) -> 49.46 | U6: =SUMIFS(dis_table[Amount],dis_table[Category],$M6,dis_table[Date],U$1) -> 197.48 | ... Y6: =SUMIFS(dis_table[Amount],dis_table[Category],$M6,dis_table[Date],Y$1) -> 0
A7: 5 | B7: 01/02/2022 | C7: 01/02/2022 | D7: INTERNET PAYMENT - THANK YOU | E7: -1800 | F7: Payments and Credits | G7: payment | H7: 01/2022 | I7: No | J7: Payment_and_Interest | K7: 1884.51 | M7: Interest | N7: =SUMIFS(dis_table[Amount],dis_table[Category],$M7,dis_table[Date],N$1) -> 0 | O7: =SUMIFS(dis_table[Amount],dis_table[Category],$M7,dis_table[Date],O$1) -> 0 | P7: =SUMIFS(dis_table[Amount],dis_table[Category],$M7,dis_table[Date],P$1) -> 0 | Q7: =SUMIFS(dis_table[Amount],dis_table[Category],$M7,dis_table[Date],Q$1) -> 0 | R7: =SUMIFS(dis_table[Amount],dis_table[Category],$M7,dis_table[Date],R$1) -> 50.48 | S7: =SUMIFS(dis_table[Amount],dis_table[Category],$M7,dis_table[Date],S$1) -> 99.24 | T7: =SUMIFS(dis_table[Amount],dis_table[Category],$M7,dis_table[Date],T$1) -> 99.19 | U7: =SUMIFS(dis_table[Amount],dis_table[Category],$M7,dis_table[Date],U$1) -> 61.69 | ... Y7: =SUMIFS(dis_table[Amount],dis_table[Category],$M7,dis_table[Date],Y$1) -> 0
A8: 6 | B8: 01/02/2022 | C8: 01/03/2022 | D8: KRYSTAL AND SAAGAR 2025317527 DCITEM TRANSFERRED FROM PREV ACCOUNT | E8: 10 | F8: Merchandise | G8: breaking_points | H8: 01/2022 | I8: Yes | J8: Recreation_Entertainment | K8: 1894.51 | M8: Medical Services | N8: =SUMIFS(dis_table[Amount],dis_table[Category],$M8,dis_table[Date],N$1) -> 0 | O8: =SUMIFS(dis_table[Amount],dis_table[Category],$M8,dis_table[Date],O$1) -> 0 | P8: =SUMIFS(dis_table[Amount],dis_table[Category],$M8,dis_table[Date],P$1) -> 432 | Q8: =SUMIFS(dis_table[Amount],dis_table[Category],$M8,dis_table[Date],Q$1) -> 0 | R8: =SUMIFS(dis_table[Amount],dis_table[Category],$M8,dis_table[Date],R$1) -> 37.5 | S8: =SUMIFS(dis_table[Amount],dis_table[Category],$M8,dis_table[Date],S$1) -> 0 | T8: =SUMIFS(dis_table[Amount],dis_table[Category],$M8,dis_table[Date],T$1) -> 0 | U8: =SUMIFS(dis_table[Amount],dis_table[Category],$M8,dis_table[Date],U$1) -> 0 | ... Y8: =SUMIFS(dis_table[Amount],dis_table[Category],$M8,dis_table[Date],Y$1) -> 0
A9: 7 | B9: 01/03/2022 | C9: 01/03/2022 | D9: PAYPAL *HULU 402-935-7733 CA | E9: 12.99 | F9: Services | G9: hulu | H9: 01/2022 | I9: Yes | J9: Recreation_Entertainment | K9: 1907.5 | M9: Merchandise | N9: =SUMIFS(dis_table[Amount],dis_table[Category],$M9,dis_table[Date],N$1) -> 802.23 | O9: =SUMIFS(dis_table[Amount],dis_table[Category],$M9,dis_table[Date],O$1) -> 473.95 | P9: =SUMIFS(dis_table[Amount],dis_table[Category],$M9,dis_table[Date],P$1) -> 1208.91 | Q9: =SUMIFS(dis_table[Amount],dis_table[Category],$M9,dis_table[Date],Q$1) -> 1041.03 | R9: =SUMIFS(dis_table[Amount],dis_table[Category],$M9,dis_table[Date],R$1) -> 1359.53 | S9: =SUMIFS(dis_table[Amount],dis_table[Category],$M9,dis_table[Date],S$1) -> 900.1 | T9: =SUMIFS(dis_table[Amount],dis_table[Category],$M9,dis_table[Date],T$1) -> 1381.63 | U9: =SUMIFS(dis_table[Amount],dis_table[Category],$M9,dis_table[Date],U$1) -> 796.45 | ... Y9: =SUMIFS(dis_table[Amount],dis_table[Category],$M9,dis_table[Date],Y$1) -> 0
A10: 8 | B10: 01/04/2022 | C10: 01/04/2022 | D10: AUTOZONE #2768 PHOENIX AZ | E10: 42.34 | F10: Automotive | G10: car | H10: 01/2022 | I10: No | J10: Utilities | K10: 1949.84 | M10: Restaurants | N10: =SUMIFS(dis_table[Amount],dis_table[Category],$M10,dis_table[Date],N$1) -> 388.66 | O10: =SUMIFS(dis_table[Amount],dis_table[Category],$M10,dis_table[Date],O$1) -> 115.83 | P10: =SUMIFS(dis_table[Amount],dis_table[Category],$M10,dis_table[Date],P$1) -> 1073.85 | Q10: =SUMIFS(dis_table[Amount],dis_table[Category],$M10,dis_table[Date],Q$1) -> 575.54 | R10: =SUMIFS(dis_table[Amount],dis_table[Category],$M10,dis_table[Date],R$1) -> 770.3 | S10: =SUMIFS(dis_table[Amount],dis_table[Category],$M10,dis_table[Date],S$1) -> 478.24 | T10: =SUMIFS(dis_table[Amount],dis_table[Category],$M10,dis_table[Date],T$1) -> 801.09 | U10: =SUMIFS(dis_table[Amount],dis_table[Category],$M10,dis_table[Date],U$1) -> 643.66 | ... Y10: =SUMIFS(dis_table[Amount],dis_table[Category],$M10,dis_table[Date],Y$1) -> 0
A11: 9 | B11: 01/04/2022 | C11: 01/04/2022 | D11: STATE FARM INSURANCE 800-956-6310 ILITEM TRANSFERRED FROM PREV ACCOUNT | E11: 79.38 | F11: Merchandise | G11: state_farm | H11: 01/2022 | I11: Yes | J11: Insurance | K11: 2029.22 | M11: Services | N11: =SUMIFS(dis_table[Amount],dis_table[Category],$M11,dis_table[Date],N$1) -> 497.44 | O11: =SUMIFS(dis_table[Amount],dis_table[Category],$M11,dis_table[Date],O$1) -> 132.57 | P11: =SUMIFS(dis_table[Amount],dis_table[Category],$M11,dis_table[Date],P$1) -> 378.81 | Q11: =SUMIFS(dis_table[Amount],dis_table[Category],$M11,dis_table[Date],Q$1) -> 78.88 | R11: =SUMIFS(dis_table[Amount],dis_table[Category],$M11,dis_table[Date],R$1) -> 138.95 | S11: =SUMIFS(dis_table[Amount],dis_table[Category],$M11,dis_table[Date],S$1) -> 134.85 | T11: =SUMIFS(dis_table[Amount],dis_table[Category],$M11,dis_table[Date],T$1) -> 246.78 | U11: =SUMIFS(dis_table[Amount],dis_table[Category],$M11,dis_table[Date],U$1) -> 35.85 | ... Y11: =SUMIFS(dis_table[Amount],dis_table[Category],$M11,dis_table[Date],Y$1) -> 0
A12: 10 | B12: 01/05/2022 | C12: 01/05/2022 | D12: MCDONALD'S F20697 PHOENIX AZAPPLE PAY ENDING IN 4775 | E12: 8 | F12: Restaurants | G12: fast_food | H12: 01/2022 | I12: No | J12: Food | K12: 2037.22 | M12: Supermarkets | N12: =SUMIFS(dis_table[Amount],dis_table[Category],$M12,dis_table[Date],N$1) -> 151.27 | O12: =SUMIFS(dis_table[Amount],dis_table[Category],$M12,dis_table[Date],O$1) -> 132.46 | P12: =SUMIFS(dis_table[Amount],dis_table[Category],$M12,dis_table[Date],P$1) -> 12.27 | Q12: =SUMIFS(dis_table[Amount],dis_table[Category],$M12,dis_table[Date],Q$1) -> 459.72 | R12: =SUMIFS(dis_table[Amount],dis_table[Category],$M12,dis_table[Date],R$1) -> 46.36 | S12: =SUMIFS(dis_table[Amount],dis_table[Category],$M12,dis_table[Date],S$1) -> 181.77 | T12: =SUMIFS(dis_table[Amount],dis_table[Category],$M12,dis_table[Date],T$1) -> 372.82 | U12: =SUMIFS(dis_table[Amount],dis_table[Category],$M12,dis_table[Date],U$1) -> 220.27 | ... Y12: =SUMIFS(dis_table[Amount],dis_table[Category],$M12,dis_table[Date],Y$1) -> 0
A13: 11 | B13: 01/08/2022 | C13: 01/08/2022 | D13: 3856 EL POLLO LOCO PHOENIX AZ | E13: 29.93 | F13: Restaurants | G13: fast_food | H13: 01/2022 | I13: No | J13: Food | K13: 2067.15 | M13: Travel/ Entertainment | N13: =SUMIFS(dis_table[Amount],dis_table[Category],$M13,dis_table[Date],N$1) -> 217.36 | O13: =SUMIFS(dis_table[Amount],dis_table[Category],$M13,dis_table[Date],O$1) -> 608.72 | P13: =SUMIFS(dis_table[Amount],dis_table[Category],$M13,dis_table[Date],P$1) -> 422 | Q13: =SUMIFS(dis_table[Amount],dis_table[Category],$M13,dis_table[Date],Q$1) -> 409.8 | R13: =SUMIFS(dis_table[Amount],dis_table[Category],$M13,dis_table[Date],R$1) -> 1511.29 | S13: =SUMIFS(dis_table[Amount],dis_table[Category],$M13,dis_table[Date],S$1) -> 1230.06 | T13: =SUMIFS(dis_table[Amount],dis_table[Category],$M13,dis_table[Date],T$1) -> 418.69 | U13: =SUMIFS(dis_table[Amount],dis_table[Category],$M13,dis_table[Date],U$1) -> 32.04 | ... Y13: =SUMIFS(dis_table[Amount],dis_table[Category],$M13,dis_table[Date],Y$1) -> 0
A14: 12 | B14: 01/08/2022 | C14: 01/08/2022 | D14: DRI*NVIDIA STORE NVIDIA.COM MNITEM TRANSFERRED FROM PREV ACCOUNT | E14: 4.99 | F14: Merchandise | G14: nvidia | H14: 01/2022 | I14: Yes | J14: Recreation_Entertainment | K14: 2072.14 | M14: Balance | N14: =SUM(N2:N13) -> 2191.71 | O14: =SUM(O2:O13) -> 1463.53 | P14: =SUM(P2:P13) -> 3905.37 | Q14: =SUM(Q2:Q13) -> 2590.27 | R14: =SUM(R2:R13) -> 3987.62 | S14: =SUM(S2:S13) -> 3334.06 | T14: =SUM(T2:T13) -> 3720.55 | U14: =SUM(U2:U13) -> 2150.77 | ... Y14: =SUM(Y2:Y13) -> 0
A15: 13 | B15: 01/09/2022 | C15: 01/09/2022 | D15: SAFEWAY #2651 PHOENIX AZ | E15: 36.72 | F15: Supermarkets | G15: groceries | H15: 01/2022 | I15: No | J15: Food | K15: 2108.86 | M15: Payments and Credits | N15: =SUMIFS(dis_table[Amount],dis_table[Category],$M15,dis_table[Date],N$1) -> -3994.92 | O15: =SUMIFS(dis_table[Amount],dis_table[Category],$M15,dis_table[Date],O$1) -> -2509.43 | P15: =SUMIFS(dis_table[Amount],dis_table[Category],$M15,dis_table[Date],P$1) -> -1969.1 | Q15: =SUMIFS(dis_table[Amount],dis_table[Category],$M15,dis_table[Date],Q$1) -> -934.85 | R15: =SUMIFS(dis_table[Amount],dis_table[Category],$M15,dis_table[Date],R$1) -> -2000 | S15: =SUMIFS(dis_table[Amount],dis_table[Category],$M15,dis_table[Date],S$1) -> -4008 | T15: =SUMIFS(dis_table[Amount],dis_table[Category],$M15,dis_table[Date],T$1) -> -8859.68 | U15: =SUMIFS(dis_table[Amount],dis_table[Category],$M15,dis_table[Date],U$1) -> -1792.5 | ... Y15: =SUMIFS(dis_table[Amount],dis_table[Category],$M15,dis_table[Date],Y$1) -> 0
A16: 14 | B16: 01/09/2022 | C16: 01/09/2022 | D16: SAFEWAY #2651 PHOENIX AZ | E16: 32.58 | F16: Supermarkets | G16: groceries | H16: 01/2022 | I16: No | J16: Food | K16: 2141.44 | M16: Awards and Rebate Credits | N16: =SUMIFS(dis_table[Amount],dis_table[Category],$M16,dis_table[Date],N$1) -> -29.08 | O16: =SUMIFS(dis_table[Amount],dis_table[Category],$M16,dis_table[Date],O$1) -> -29.29 | P16: =SUMIFS(dis_table[Amount],dis_table[Category],$M16,dis_table[Date],P$1) -> 0 | Q16: =SUMIFS(dis_table[Amount],dis_table[Category],$M16,dis_table[Date],Q$1) -> -65.15 | R16: =SUMIFS(dis_table[Amount],dis_table[Category],$M16,dis_table[Date],R$1) -> -41.23 | S16: =SUMIFS(dis_table[Amount],dis_table[Category],$M16,dis_table[Date],S$1) -> 0 | T16: =SUMIFS(dis_table[Amount],dis_table[Category],$M16,dis_table[Date],T$1) -> -81.42 | U16: =SUMIFS(dis_table[Amount],dis_table[Category],$M16,dis_table[Date],U$1) -> -53.05 | ... Y16: =SUMIFS(dis_table[Amount],dis_table[Category],$M16,dis_table[Date],Y$1) -> 0
A17: 15 | B17: 01/09/2022 | C17: 01/09/2022 | D17: PAYPAL *HEARSTMAGAZ 402-935-7733 CA | E17: 20 | F17: Merchandise | G17: pay_wall | H17: 01/2022 | I17: Yes | J17: Recreation_Entertainment | K17: 2161.44
A18: 16 | B18: 01/09/2022 | C18: 01/09/2022 | D18: SAFEWAY #2651 PHOENIX AZ | E18: 2.49 | F18: Supermarkets | G18: groceries | H18: 01/2022 | I18: No | J18: Food | K18: 2163.93 | N18: 01/2022 | O18: 02/2022 | P18: 03/2022 | Q18: 04/2022 | R18: 05/2022 | S18: 06/2022 | T18: 07/2022 | U18: 08/2022 | V18: 09/2022 | W18: 10/2022 | X18: 11/2022 | Y18: 12/2022
A19: 17 | B19: 01/10/2022 | C19: 01/10/2022 | D19: AMZN MKTP US*BP5036MA3 AMZN.COM/BILLWAITEM TRANSFERRED FROM PREV ACCOUNT | E19: 49.98 | F19: Merchandise | G19: amazon | H19: 01/2022 | I19: No | J19: Personal_Spending | K19: 2213.91 | M19: =M14 -> Balance | N19: 3659.69 | O19: =O14 -> 1463.53 | P19: =P14 -> 3905.37 | Q19: =Q14 -> 2590.27 | R19: =R14 -> 3987.62 | S19: =S14 -> 3334.06 | T19: =T14 -> 3720.55 | U19: =U14 -> 2150.77 | V19: =V14 -> 3625.55 | ... Y19: =Y14 -> 0
A20: 18 | B20: 01/10/2022 | C20: 01/10/2022 | D20: MCDONALD'S F20697 PHOENIX AZ | E20: 10.09 | F20: Restaurants | G20: fast_food | H20: 01/2022 | I20: No | J20: Food | K20: 2224 | M20: =M15 -> Payments and Credits | N20: =N15*-1 -> 3994.92 | O20: =O15*-1 -> 2509.43 | P20: =P15*-1 -> 1969.1 | Q20: =Q15*-1 -> 934.85 | R20: =R15*-1 -> 2000 | S20: =S15*-1 -> 4008 | T20: =T15*-1 -> 8859.68 | U20: =U15*-1 -> 1792.5 | ... Y20: =Y15*-1 -> 0
A21: 19 | B21: 01/11/2022 | C21: 01/11/2022 | D21: LIFE TIME ATHLETIC 279 PHOENIX AZ01118R | E21: 210 | F21: Travel/ Entertainment | G21: gym | H21: 01/2022 | I21: No | J21: Personal_Spending | K21: 2434
A22: 20 | B22: 01/12/2022 | C22: 01/12/2022 | D22: CAFE RIO 0084 SCOTTSDALE SCOTTSDALE AZ | E22: 15.1 | F22: Restaurants | G22: fast_food | H22: 01/2022 | I22: No | J22: Food | K22: 2449.1
A23: 21 | B23: 01/12/2022 | C23: 01/12/2022 | D23: CVS/PHARMACY #09252 SCOTTSDALE AZAPPLE PAY ENDING IN 4775 | E23: 19.8 | F23: Merchandise | G23: conv_store | H23: 01/2022 | I23: No | J23: Personal_Spending | K23: 2468.9
A24: 22 | B24: 01/13/2022 | C24: 01/13/2022 | D24: INTERNET PAYMENT - THANK YOU | E24: -2194.92 | F24: Payments and Credits | G24: payment | H24: 01/2022 | I24: No | J24: Payment_and_Interest | K24: 273.98
A25: 23 | B25: 01/13/2022 | C25: 01/13/2022 | D25: CASHBACK BONUS REDEMPTION PYMT/STMT CRDT | E25: -29.08 | F25: Awards and Rebate Credits | G25: cashback_bonus | H25: 01/2022 | I25: No | J25: Payment_and_Interest | K25: 244.9
A26: 24 | B26: 01/13/2022 | C26: 01/13/2022 | D26: CIRCLE K 01930 YUMA AZ01374R | E26: 30.89 | F26: Gasoline | G26: gas_station | H26: 01/2022 | I26: No | J26: Transportation | K26: 275.79
A27: 25 | B27: 01/14/2022 | C27: 01/14/2022 | D27: MCDONALDS 20697 PHOENIX AZ | E27: 6.29 | F27: Restaurants | G27: fast_food | H27: 01/2022 | I27: No | J27: Food | K27: 282.08
A28: 26 | B28: 01/14/2022 | C28: 02/03/2022 | D28: SEVEN MILE CASINO RESTAU CHULA VISTA CA | E28: 60 | F28: Restaurants | G28: restaurant | H28: 01/2022 | I28: No | J28: Food | K28: 342.08
A29: 27 | B29: 01/14/2022 | C29: 01/14/2022 | D29: APPLE.COM/BILL 866-712-7753 CAAPPLE PAY ENDING IN 4775MMW7SF5QV8A0 | E29: 15.89 | F29: Merchandise | G29: hbo | H29: 01/2022 | I29: Yes | J29: Recreation_Entertainment | K29: 357.97
A30: 28 | B30: 01/15/2022 | C30: 01/15/2022 | D30: RALPHS # 0212 SAN DIEGO CA | E30: 35.02 | F30: Supermarkets | G30: groceries | H30: 01/2022 | I30: No | J30: Food | K30: 392.99
A31: 29 | B31: 01/15/2022 | C31: 01/15/2022 | D31: TACOS EL GORDO - CHULA V CHULA VISTA CA | E31: 21.49 | F31: Restaurants | G31: fast_food | H31: 01/2022 | I31: No | J31: Food | K31: 414.48
A32: 30 | B32: 01/15/2022 | C32: 01/15/2022 | D32: THE CRACK SHACK LITTLE I SAN DIEGO CA | E32: 52.41 | F32: Restaurants | G32: restaurant | H32: 01/2022 | I32: No | J32: Food | K32: 466.89
... A739: 737 | B739: 09/14/2022 | C739: 09/14/2022 | D739: TST* RISE PIZZERIA BURLINGAME CA00049860008560623466AA | E739: 37 | F739: Restaurants | G739: restaurant | H739: 09/2022 | I739: No | J739: Food | K739: 668.05
A740: 738 | B740: 09/15/2022 | C740: 09/15/2022 | D740: APPLE.COM/US 800-676-2775 CAW1217133334A263446652 | E740: 53.72 | F740: Merchandise | H740: 09/2022 | I740: No | K740: 721.77
A741: 739 | B741: 09/15/2022 | C741: 09/15/2022 | D741: HAN SUNG BBQ SANTA CLARA CA | E741: 42 | F741: Restaurants | G741: restaurant | H741: 09/2022 | I741: No | J741: Food | K741: 763.77
A742: 740 | B742: 09/16/2022 | C742: 09/16/2022 | D742: FLIGHTS BURLINGAME CA | E742: 102.7 | F742: Restaurants | G742: restaurant | H742: 09/2022 | I742: No | J742: Food | K742: 866.47
A743: 741 | B743: 09/17/2022 | C743: 09/17/2022 | D743: TMOBILE*AUTO PAY 800-937-8997 WAITEM TRANSFERRED FROM PREV ACCOUNT | E743: 70 | F743: Merchandise | G743: cell_phone | H743: 09/2022 | I743: No | J743: Utilities | K743: 936.47
A744: 742 | B744: 09/17/2022 | C744: 09/17/2022 | D744: TARGET 00011221091 SAN MATEO CA | E744: 27.89 | F744: Supermarkets | G744: target | H744: 09/2022 | I744: No | J744: Personal_Spending | K744: 964.36
A745: 743 | B745: 09/17/2022 | C745: 09/17/2022 | D745: CKE*SOM TUM STATION SAN SAN MATEO CA | E745: 14.83 | F745: Restaurants | G745: restaurant | H745: 09/2022 | I745: No | J745: Food | K745: 979.19
A746: 744 | B746: 09/17/2022 | C746: 09/17/2022 | D746: APPLE.COM/BILL 111-111-1111 CAAPPLE PAY ENDING IN 4775 | E746: 5.29 | F746: Merchandise | G746: apple_tv | H746: 09/2022 | I746: Yes | J746: Recreation_Entertainment | K746: 984.48
A747: 745 | B747: 09/17/2022 | C747: 09/17/2022 | D747: AMZN MKTP US*1M04898F1 AMZN.COM/BILLWA4A83VGAFU9G | E747: 110.21 | F747: Merchandise | G747: amazon | H747: 09/2022 | I747: No | J747: Personal_Spending | K747: 1094.69
A748: 746 | B748: 09/18/2022 | C748: 09/18/2022 | D748: DEAN'S PRODUCE. SAN MATEO CA | E748: 34.52 | F748: Supermarkets | G748: groceries | H748: 09/2022 | I748: No | J748: Food | K748: 1129.21
A749: 747 | B749: 09/18/2022 | C749: 09/18/2022 | D749: INTERNET PAYMENT - THANK YOU | E749: -763.77 | F749: Payments and Credits | G749: payment | H749: 09/2022 | I749: No | J749: Payment_and_Interest | K749: 365.44
A750: 748 | B750: 09/18/2022 | C750: 09/18/2022 | D750: WHOLEFDS SMT 10150 SAN MATEO CA | E750: 15.59 | F750: Supermarkets | G750: groceries | H750: 09/2022 | I750: No | J750: Food | K750: 381.03
A751: 749 | B751: 09/19/2022 | C751: 09/19/2022 | D751: AMZN MKTP US*1M1M978J0 AMZN.COM/BILLWA61WE70JX48J | E751: 21.48 | F751: Merchandise | G751: amazon | H751: 09/2022 | I751: No | J751: Personal_Spending | K751: 402.51
A752: 750 | B752: 09/19/2022 | C752: 09/19/2022 | D752: AMZN MKTP US*1M2YJ8EV2 AMZN.COM/BILLWA5D6111DW1IM | E752: 58.12 | F752: Merchandise | G752: amazon | H752: 09/2022 | I752: No | J752: Personal_Spending | K752: 460.63
... A778: 776 | B778: 10/04/2022 | C778: 10/04/2022 | D778: STATE FARM INSURANCE 800-956-6310 ILITEM TRANSFERRED FROM PREV ACCOUNT | E778: 80.08 | F778: Merchandise | G778: state_farm | H778: 10/2022 | I778: Yes | J778: Insurance | K778: 658.31
A779: 777 | B779: 10/05/2022 | C779: 10/05/2022 | D779: APPLE.COM/BILL 866-712-7753 CAAPPLE PAY ENDING IN 4775MMWBSMLKDVA0 | E779: 76.31 | F779: Merchandise | H779: 10/2022 | I779: No | K779: 734.62
A780: 778 | B780: 10/05/2022 | C780: 10/05/2022 | D780: BRUNDAVAN INDIAN CUISINE SANTA CLARA CA | E780: 41.86 | F780: Restaurants | G780: restaurant | H780: 10/2022 | I780: No | J780: Food | K780: 776.48
A781: 779 | B781: 10/06/2022 | C781: 10/06/2022 | D781: APPLE.COM/BILL 866-712-7753 CAMMWBSNX4S3A0 | E781: 9.99 | F781: Merchandise | H781: 10/2022 | I781: No | K781: 786.47
A782: 780 | B782: 10/07/2022 | C782: 10/07/2022 | D782: APPLE.COM/US 800-676-2775 CAW1217133334A285573915 | E782: 553.89 | F782: Merchandise | H782: 10/2022 | I782: No | K782: 1340.36
A783: 781 | B783: 10/07/2022 | C783: 10/07/2022 | D783: CCBILL.COM 888-5969279 AZ | E783: 6.37 | F783: Merchandise | G783: onlyfans | H783: 10/2022 | I783: No | J783: Recreation_Entertainment | K783: 1346.73
A784: 782 | B784: 10/08/2022 | C784: 10/08/2022 | D784: CREPEVINE (BURLINGAME) BURLINGAME CA | E784: 12.52 | F784: Restaurants | G784: restaurant | H784: 10/2022 | I784: No | J784: Food | K784: 1359.25
A785: 783 | B785: 10/08/2022 | C785: 10/08/2022 | D785: INTERNET PAYMENT - THANK YOU | E785: -1340.36 | F785: Payments and Credits | G785: payment | H785: 10/2022 | I785: No | J785: Payment_and_Interest | K785: 18.89
A786: 784 | B786: 10/09/2022 | C786: 10/09/2022 | D786: SQ *ROYAL DONUT BURLINGAME CA0001152921512011595126 | E786: 17.1 | F786: Restaurants | G786: restaurant | H786: 10/2022 | I786: No | J786: Food | K786: 35.99
A787: 785 | B787: 10/09/2022 | C787: 10/09/2022 | D787: PANDA EXPRESS #907 BURLINGAME CA | E787: 11 | F787: Restaurants | G787: fast_food | H787: 10/2022 | I787: No | J787: Food | K787: 46.99
A788: 786 | B788: 10/09/2022 | C788: 10/09/2022 | D788: GOOGLE *YOUTUBE TV G.CO/HELPPAY#CAP0MWK7CI | E788: 64.99 | F788: Services | G788: youtube_tv | H788: 10/2022 | I788: Yes | J788: Recreation_Entertainment | K788: 111.98
A789: 787 | B789: 10/10/2022 | C789: 10/10/2022 | D789: BEST BUY 00001404295 SAN CARLOS CA | E789: 255.92 | F789: Merchandise | G789: electronics | H789: 10/2022 | I789: No | J789: Recreation_Entertainment | K789: 367.9
A790: 788 | B790: 10/10/2022 | C790: 10/10/2022 | D790: IN N OUT BURGER 257 SAN CARLOS CA | E790: 8.64 | F790: Restaurants | G790: fast_food | H790: 10/2022 | I790: No | J790: Food | K790: 376.54
A791: 789 | B791: 10/10/2022 | C791: 10/10/2022 | D791: OFFICE DEPOT #558 SAN CARLOS CA | E791: 64.52 | F791: Merchandise | G791: home_supplies | H791: 10/2022 | I791: No | J791: Housing | K791: 441.06
A792: 790 | B792: 10/11/2022 | C792: 10/11/2022 | D792: APPLE.COM/BILL 866-712-7753 CAAPPLE PAY ENDING IN 4775MMWBSYVSW8A0 | E792: 15.89 | F792: Merchandise | G792: hbo | H792: 10/2022 | I792: Yes | J792: Recreation_Entertainment | K792: 456.95
A793: 791 | B793: 10/11/2022 | C793: 10/11/2022 | D793: BEST BUY 00001404295 SAN CARLOS CA | E793: 114.8 | F793: Merchandise | G793: electronics | H793: 10/2022 | I793: No | J793: Recreation_Entertainment | K793: 571.75
A794: 792 | B794: 10/11/2022 | C794: 10/11/2022 | D794: CVS/PHARMACY #09940 SAN MATEO CA | E794: 27.17 | F794: Merchandise | G794: conv_store | H794: 10/2022 | I794: No | J794: Personal_Spending | K794: 598.92
... A825: 823 | B825: 10/23/2022 | C825: 10/23/2022 | D825: GREEN TORTOISE HOSTEL SEATTLE WA | E825: 138.53 | F825: Travel/ Entertainment | G825: hostel | H825: 10/2022 | I825: No | J825: Housing | K825: 426.99
A826: 824 | B826: 10/23/2022 | C826: 10/23/2022 | D826: ATI5235-013224201 310-627-2866 CA | E826: 54.45 | F826: Travel/ Entertainment | H826: 10/2022 | I826: No | K826: 481.44
A827: 825 | B827: 10/23/2022 | C827: 10/23/2022 | D827: AMC 0880 PACIFIC PLACE SEATTLE WA | E827: 19.72 | F827: Travel/ Entertainment | G827: movies | H827: 10/2022 | I827: No | J827: Recreation_Entertainment | K827: 501.16
A828: 826 | B828: 10/23/2022 | C828: 10/23/2022 | D828: 712 GARAGE LANES 8003425 SEATTLE WA | E828: 120.27 | F828: Travel/ Entertainment | G828: bowling | H828: 10/2022 | I828: No | J828: Recreation_Entertainment | K828: 621.43
A829: 827 | B829: 10/23/2022 | C829: 10/23/2022 | D829: 712 GARAGE LANES 8003425 SEATTLE WA | E829: 46.46 | F829: Travel/ Entertainment | G829: bowling | H829: 10/2022 | I829: No | J829: Recreation_Entertainment | K829: 667.89
A830: 828 | B830: 10/23/2022 | C830: 10/23/2022 | D830: ORCA SEATTLE WA | E830: 69 | F830: Travel/ Entertainment | G830: bus_fare | H830: 10/2022 | I830: No | J830: Transportation | K830: 736.89
A831: 829 | B831: 10/24/2022 | C831: 10/24/2022 | D831: WWW.WEWORK.COM 6467604450 NY | E831: 29 | F831: Services | G831: professional | H831: 10/2022 | I831: No | J831: Personal_Spending | K831: 765.89
A832: 830 | B832: 10/24/2022 | C832: 10/24/2022 | D832: UBER TRIP 866-576-1039 CAAPPLE PAY ENDING IN 1455 | E832: 21.99 | F832: Travel/ Entertainment | G832: ride_share | H832: 10/2022 | I832: No | J832: Transportation | K832: 787.88
A833: 831 | B833: 10/24/2022 | C833: 10/24/2022 | D833: UBER TRIP 866-576-1039 CAAPPLE PAY ENDING IN 1455 | E833: 15.9 | F833: Travel/ Entertainment | G833: ride_share | H833: 10/2022 | I833: No | J833: Transportation | K833: 803.78
A834: 832 | B834: 10/24/2022 | C834: 10/24/2022 | D834: TARGET 00027862091 SEATTLE WA | E834: 7.93 | F834: Supermarkets | G834: target | H834: 10/2022 | I834: No | J834: Personal_Spending | K834: 811.71
A835: 833 | B835: 10/24/2022 | C835: 10/24/2022 | D835: KJ'S BAR SEATTLE WA02402R | E835: 11.04 | F835: Restaurants | G835: restaurant | H835: 10/2022 | I835: No | J835: Food | K835: 822.75
A836: 834 | B836: 10/24/2022 | C836: 10/24/2022 | D836: CHUKAR CHERRY COMPANY SEATTLE WA | E836: 13.5 | F836: Merchandise | G836: restaurant | H836: 10/2022 | I836: No | J836: Food | K836: 836.25
A837: 835 | B837: 10/24/2022 | C837: 10/24/2022 | D837: AYTTHAYA THAI SEATTLE WA | E837: 55.75 | F837: Restaurants | G837: restaurant | H837: 10/2022 | I837: No | J837: Food | K837: 892
A838: 836 | B838: 10/24/2022 | C838: 10/24/2022 | D838: MOD PIZZA DWNT SEATTLE SEATTLE WA02433R | E838: 32.7 | F838: Restaurants | G838: fast_food | H838: 10/2022 | I838: No | J838: Food | K838: 924.7
... A882: 880 | B882: 11/05/2022 | C882: 11/05/2022 | D882: ANCHOR PUBLIC TAPS SAN FRANCISCOCA | E882: 8.4 | F882: Restaurants | G882: restaurant | H882: 11/2022 | I882: No | J882: Food | K882: 556.71
A883: 881 | B883: 11/06/2022 | C883: 11/06/2022 | D883: APPLE.COM/BILL 866-712-7753 CAMMWBVG39H4A0 | E883: 9.99 | F883: Merchandise | H883: 11/2022 | I883: No | K883: 566.7
A884: 882 | B884: 11/07/2022 | C884: 11/07/2022 | D884: WHOLEFDS SMT 10150 SAN MATEO CA | E884: 16.59 | F884: Supermarkets | G884: groceries | H884: 11/2022 | I884: No | J884: Food | K884: 583.29
A885: 883 | B885: 11/07/2022 | C885: 11/07/2022 | D885: HABIT SAN MATEO #50 SAN MATEO CA | E885: 15.67 | F885: Restaurants | G885: restaurant | H885: 11/2022 | I885: No | J885: Food | K885: 598.96
A886: 884 | B886: 11/08/2022 | C886: 11/08/2022 | D886: NBA*SACRAMENTO KINGS 916-928-3683 CAMICD58A500-ERBAN | E886: 158 | F886: Travel/ Entertainment | G886: restaurant | H886: 11/2022 | I886: No | J886: Food | K886: 756.96
A887: 885 | B887: 11/09/2022 | C887: 11/09/2022 | D887: AMZN MKTP US*HB4TE31U0 AMZN.COM/BILLWA4JBTMKBCPJP | E887: 117.27 | F887: Merchandise | G887: amazon | H887: 11/2022 | I887: No | J887: Personal_Spending | K887: 874.23
A888: 886 | B888: 11/09/2022 | C888: 11/09/2022 | D888: ATI49980-11090430 310-627-2866 CAAPPLE PAY ENDING IN 1455 | E888: 71.67 | F888: Travel/ Entertainment | H888: 11/2022 | I888: No | K888: 945.9
A889: 887 | B889: 11/09/2022 | C889: 11/09/2022 | D889: BEST BUY 00008730295 COLMA CA | E889: 36.46 | F889: Merchandise | G889: electronics | H889: 11/2022 | I889: No | J889: Recreation_Entertainment | K889: 982.36
A890: 888 | B890: 11/09/2022 | C890: 11/09/2022 | D890: FUEL 24 7 WESTBOROUGH SAN FRANCISCOCA | E890: 48.65 | F890: Gasoline | G890: gas_station | H890: 11/2022 | I890: No | J890: Transportation | K890: 1031.01
A891: 889 | B891: 11/09/2022 | C891: 11/09/2022 | D891: GOOGLE *YOUTUBE TV G.CO/HELPPAY#CAP0NDWKX1 | E891: 64.99 | F891: Services | G891: youtube_tv | H891: 11/2022 | I891: Yes | J891: Recreation_Entertainment | K891: 1096
A892: 890 | B892: 11/09/2022 | C892: 11/09/2022 | D892: STORE*TEA PLUS NOODLES 6506819470 CA | E892: 16.75 | F892: Restaurants | G892: restaurant | H892: 11/2022 | I892: No | J892: Food | K892: 1112.75
A893: 891 | B893: 11/10/2022 | C893: 11/10/2022 | D893: WALGREENS #12257 BURLINGAME CA | E893: 30.28 | F893: Merchandise | G893: conv_store | H893: 11/2022 | I893: No | J893: Personal_Spending | K893: 1143.03
A894: 892 | B894: 11/11/2022 | C894: 11/11/2022 | D894: MAIDO STATIONERY - SJ SAN JOSE CA | E894: 37.12 | F894: Merchandise | G894: home_supplies | H894: 11/2022 | I894: No | J894: Housing | K894: 1180.15
A895: 893 | B895: 11/11/2022 | C895: 11/11/2022 | D895: SQ *SALT & STRAW SAN JOSE CA0001152921512150964054 | E895: 7.74 | F895: Restaurants | G895: restaurant | H895: 11/2022 | I895: No | J895: Food | K895: 1187.89
A896: 894 | B896: 11/11/2022 | C896: 11/11/2022 | D896: COCOLA SAN JOSE CA | E896: 6.12 | F896: Restaurants | G896: restaurant | H896: 11/2022 | I896: No | J896: Food | K896: 1194.01
A897: 895 | B897: 11/11/2022 | C897: 11/11/2022 | D897: APPLE.COM/BILL 866-712-7753 CAAPPLE PAY ENDING IN 1455MMWBVKBT8NA0 | E897: 37.09 | F897: Merchandise | H897: 11/2022 | I897: No | K897: 1231.1
A898: 896 | B898: 11/11/2022 | C898: 11/11/2022 | D898: APPLE.COM/BILL 866-712-7753 CAAPPLE PAY ENDING IN 1455MMWBVKWJ8QA0 | E898: 26.49 | F898: Merchandise | G898: unsure | H898: 11/2022 | I898: No | J898: Misc | K898: 1257.59
A899: 897 | B899: 11/11/2022 | C899: 11/11/2022 | D899: CINEPOLIS SAN MATEO SAN MATEO CA01177R | E899: 31.79 | F899: Restaurants | G899: movies | H899: 11/2022 | I899: No | J899: Recreation_Entertainment | K899: 1289.38
A900: 898 | B900: 11/12/2022 | C900: 11/12/2022 | D900: AMZN MKTP US*HB60245D1 AMZN.COM/BILLWATZSMW0BB17N | E900: 29.59 | F900: Merchandise | G900: amazon | H900: 11/2022 | I900: No | J900: Personal_Spending | K900: 1318.97
A901: 899 | B901: 11/12/2022 | C901: 11/12/2022 | D901: PAYPAL *COURSE HERO 402-935-7733 CA | E901: 119.4 | F901: Services | G901: learning | H901: 11/2022 | I901: No | J901: Personal_Spending | K901: 1438.37
A902: 900 | B902: 11/13/2022 | C902: 11/13/2022 | D902: PANDA EXPRESS #907 P 800-877-8988 CAAPPLE PAY ENDING IN 1455 | E902: 11.78 | F902: Restaurants | G902: fast_food | H902: 11/2022 | I902: No | J902: Food | K902: 1450.15
A903: 901 | B903: 11/14/2022 | C903: 11/14/2022 | D903: HYATT REG PHOENIX F&B PHOENIX AZ | E903: 15.37 | F903: Restaurants | G903: restaurant | H903: 11/2022 | I903: No | J903: Food | K903: 1465.52
A904: 902 | B904: 11/14/2022 | C904: 11/14/2022 | D904: SKYLINE NEWS AND GIFTS SAN FRANCISCOCA | E904: 8.35 | F904: Merchandise | G904: airport | H904: 11/2022 | I904: No | J904: Transportation | K904: 1473.87
...

Sheet Discover Account
A1: Date | B1: Payment | C1: CumAmount
A2: 01/2022 | C2: 3581.67
A3: 01/2022 | C3: 3599.69
A4: 01/2022 | B4: -1800 | C4: 3659.69
A5: 01/2022 | C5: 3674.52
A6: 01/2022 | C6: 3684.51
A7: 01/2022 | C7: 3694.6
A8: 01/2022 | C8: 3744.58
A9: 01/2022 | C9: 3954.58
A10: 01/2022 | C10: 3974.38
A11: 01/2022 | C11: 3989.48
A12: 01/2022 | C12: 1794.56
A13: 01/2022 | C13: 1825.45
A14: 01/2022 | C14: 1796.37
A15: 01/2022 | C15: 1856.37
A16: 01/2022 | C16: 1862.66
... A32: 01/2022 | C32: 2573.73
A33: 01/2022 | B33: =(C32-C33)*-1 -> -1800 | C33: 773.73
A34: 01/2022 | C34: 786.72
A35: 01/2022 | C35: 797.72
A36: 01/2022 | C36: 802.71
A37: 01/2022 | C37: 835.15
A38: 01/2022 | C38: 841.98
A39: 01/2022 | C39: 849.34
A40: 01/2022 | C40: 879.33
A41: 01/2022 | C41: 902.12
A42: 01/2022 | C42: 935.1
A43: 01/2022 | C43: 965.1
A44: 01/2022 | C44: 1044.1
A45: 01/2022 | C45: 1074.1
... A74: 02/2022 | C74: 1897.34
A75: 02/2022 | B75: =(C74-C75)*-1 -> -1733.33 | C75: 164.01
A76: 02/2022 | C76: 179.9
A77: 02/2022 | B77: =(C76-C77)*-1 -> -5 | C77: 174.9
A78: 02/2022 | C78: 184.1
A79: 02/2022 | C79: 204.1
A80: 02/2022 | C80: 218.21
A81: 02/2022 | C81: 233.2
A82: 02/2022 | C82: 259.79
A83: 02/2022 | C83: 308.79
A84: 02/2022 | C84: 320.79
A85: 02/2022 | C85: 390.79
A86: 02/2022 | C86: 396.08
A87: 02/2022 | C87: 406.08
A88: 02/2022 | B88: =(C87-C88)*-1 -> -771.1 | C88: -365.02
A89: 02/2022 | B89: =(C88-C89)*-1 -> -29.29 | C89: -394.31
A90: 02/2022 | C90: -323.73
A91: 02/2022 | C91: -312.73
A92: 02/2022 | C92: -282.73
A93: 02/2022 | C93: -268.57
A94: 02/2022 | C94: -266.95
A95: 02/2022 | C95: -140.25
A96: 02/2022 | C96: -10.07
A97: 02/2022 | C97: -0.75
A98: 02/2022 | C98: 17.25
A99: 02/2022 | C99: 47.24
A100: 02/2022 | C100: 52.18
A101: 02/2022 | C101: 101.31
... A119: 03/2022 | C119: 778.55
A120: 03/2022 | B120: =(C119-C120)*-1 -> -734.55 | C120: 44
A121: 03/2022 | C121: 79
A122: 03/2022 | C122: 100.12
A123: 03/2022 | C123: 125.04
A124: 03/2022 | C124: 130.17
A125: 03/2022 | C125: 162.75
A126: 03/2022 | C126: 178.64
A127: 03/2022 | C127: 189.23
A128: 03/2022 | C128: 229.23
A129: 03/2022 | C129: 234.42
A130: 03/2022 | C130: 267.55
A131: 03/2022 | C131: 297.55
A132: 03/2022 | C132: 359.33
... A165: 03/2022 | C165: 1865.08
A166: 03/2022 | B166: =(C165-C166)*-1 -> -734.55 | C166: 1130.53
A167: 03/2022 | C167: 1369.76
A168: 03/2022 | C168: 1401.29
A169: 03/2022 | C169: 1416.29
A170: 03/2022 | C170: 1426.7
A171: 03/2022 | B171: =(C170-C171)*-1 -> -500 | C171: 926.7
A172: 03/2022 | C172: 1318.7
A173: 03/2022 | C173: 1337.82
A174: 03/2022 | C174: 1353.82
A175: 03/2022 | C175: 1365.82
A176: 03/2022 | C176: 1375.82
A177: 03/2022 | C177: 1420.02
A178: 03/2022 | C178: 1423.83
A179: 03/2022 | C179: 1448.4
A180: 03/2022 | C180: 1525.4
A181: 03/2022 | C181: 1567.21
A182: 03/2022 | C182: 1580.3
A183: 03/2022 | C183: 1617.87
... A285: 04/2022 | C285: 4844.63
A286: 04/2022 | B286: =(C285-C286)*-1 -> -934.85 | C286: 3909.78
A287: 04/2022 | B287: =(C286-C287)*-1 -> -65.15 | C287: 3844.63
A288: 04/2022 | C288: 3894.63
A289: 04/2022 | C289: 3953.15
A290: 04/2022 | C290: 3958.14
A291: 04/2022 | C291: 3981.49
A292: 04/2022 | C292: 3994.13
A293: 04/2022 | C293: 3999.66
...

Sheet Care Credit
A1: Transaction Date | B1: Post Date | C1: Description | D1: Amount | E1: Short_Desc | F1: Date | G1: Category_2
A2: 44571 | B2: 44571 | C2: 8534812QVLH06N92F WESTERN DENTAL OF ARIZONAPHOENIX AZ | D2: 2286 | E2: Dental | F2: =MONTH(A2)&"/"&YEAR(A2) -> 1/2022 | G2: Medical
A3: 44574 | B3: 44574 | C3: 8534812QX019L6GDK PAYMENT - THANK YOU | D3: -1000 | E3: Payment | F3: =MONTH(A3)&"/"&YEAR(A3) -> 1/2022
A4: 44599 | B4: 44599 | C4: Card Security 1-800-815-4051 | D4: 21.35 | E4: Security | F4: =MONTH(A4)&"/"&YEAR(A4) -> 2/2022 | G4: Medical
A5: 44602 | B5: 44602 | C5: 8534812DT01Q3QH69 PAYMENT - THANK YOU | D5: -307.35 | E5: Payment | F5: =MONTH(A5)&"/"&YEAR(A5) -> 2/2022
A6: 44611 | B6: 44611 | C6: 8534812E301QZ55AX PAYMENT - THANK YOU | D6: -1000 | E6: Payment | F6: =MONTH(A6)&"/"&YEAR(A6) -> 2/2022
A7: 44645 | B7: 44645 | C7: 8534812F6LK8M1WZE BANNER SURGERY CENTER CAMPHOENIX AZ | D7: 2121.16 | E7: Surgery | F7: =MONTH(A7)&"/"&YEAR(A7) -> 3/2022 | G7: Medical
A8: 44658 | B8: 44658 | C8: 8534812FH01H6BNDY PAYMENT - THANK YOU | D8: -1000 | E8: Payment | F8: =MONTH(A8)&"/"&YEAR(A8) -> 4/2022
A9: 44659 | B9: 44659 | C9: Card Security 1-800-815-4051 | D9: 18.61 | E9: Security | F9: =MONTH(A9)&"/"&YEAR(A9) -> 4/2022
A10: 44677 | B10: 44677 | C10: 8534812G501JT48VE PAYMENT - THANK YOU | D10: -139.77 | E10: Payment | F10: =MONTH(A10)&"/"&YEAR(A10) -> 4/2022
A11: 44686 | B11: 44686 | C11: 8534812GD01KKWEH4 PAYMENT - THANK YOU | D11: -1000 | E11: Payment | F11: =MONTH(A11)&"/"&YEAR(A11) -> 5/2022
A12: 44760 | B12: 44760 | C12: 8534812JRLK8M1WZF BANNER SURGERY CENTER CAMPHOENIX AZ | D12: -504.86 | E12: refund | F12: =MONTH(A12)&"/"&YEAR(A12) -> 7/2022
A13: 44763 | B13: 44763 | C13: F907200JU000CB202 CREDIT BALANCE I KETTERING OH | D13: 504.86 | E13: Refund | F13: =MONTH(A13)&"/"&YEAR(A13) -> 7/2022 | G13: Medical

Sheet Best Buy
A1: Transaction Date | B1: Amount | C1: Description | D1: Category | E1: Short_Desc | F1: Date | G1: Category_2
A2: 44697 | B2: 582.53 | C2: COACHING ACTUARIES WWW.COACHINGAIA | D2: sale | E2: learning | F2: =MONTH(A2)&"/"&YEAR(A2) -> 5/2022 | G2: Personal_Spending
A3: 44714 | B3: -974.91 | C3: ONLINE PAYMENT DEERFIELD IL | D3: payment | E3: payment | F3: =MONTH(A3)&"/"&YEAR(A3) -> 6/2022
A4: 44702 | B4: 12 | C4: SEASCAPE GOLF CLUB APTOS CA | D4: sale | E4: golf | F4: =MONTH(A4)&"/"&YEAR(A4) -> 5/2022 | G4: Recreation_Entertainment
A5: 44702 | B5: 9.6 | C5: SEASCAPE GOLF CLUB APTOS CA | D5: sale | E5: golf | F5: =MONTH(A5)&"/"&YEAR(A5) -> 5/2022 | G5: Recreation_Entertainment
A6: 44702 | B6: 26.14 | C6: SEASCAPE GOLF CLUB APTOS CA | D6: sale | E6: golf | F6: =MONTH(A6)&"/"&YEAR(A6) -> 5/2022 | G6: Recreation_Entertainment
A7: 44702 | B7: 299.8 | C7: TST* Laili Restaurant Santa Cruz CA | D7: sale | E7: golf | F7: =MONTH(A7)&"/"&YEAR(A7) -> 5/2022 | G7: Recreation_Entertainment
A8: 44703 | B8: 32 | C8: MELOMELO KAVA BAR - SANT SANTA CRUZ CA | D8: sale | E8: resteraunt | F8: =MONTH(A8)&"/"&YEAR(A8) -> 5/2022 | G8: Food
A9: 44703 | B9: 12.84 | C9: SQ *HMB COFFEE CO Half Moon BayCA | D9: sale | E9: coffee | F9: =MONTH(A9)&"/"&YEAR(A9) -> 5/2022 | G9: Food

Sheet Wells Fargo
A1: Trans Date | B1: Debit_Amount | C1: Amount | D1: Description | E1: Short_Desc | F1: Date | G1: Category_2
A2: 44564 | B2: -1800 | C2: =IF(SIGN(B2)=-1, B2*-1, B2) -> 1800 | D2: DISCOVER E-PAYMENT 220102 4618 LEWIS SEAN | E2: discover | F2: =MONTH(A2)&"/"&YEAR(A2) -> 1/2022 | G2: credit
A3: 44564 | B3: -241.99 | C3: =IF(SIGN(B3)=-1, B3*-1, B3) -> 241.99 | D3: BEST BUY PAYMENT 220102 610633785460241 SEAN LEWIS | E3: best_buy | F3: =MONTH(A3)&"/"&YEAR(A3) -> 1/2022 | G3: credit
A4: 44564 | B4: -10 | C4: =IF(SIGN(B4)=-1, B4*-1, B4) -> 10 | D4: PAYPAL INST XFER 220101 LOUISCK SEAN LEWIS | E4: comedy | F4: =MONTH(A4)&"/"&YEAR(A4) -> 1/2022 | G4: =IFERROR(VLOOKUP('Wells Fargo'!E159,dis_table[[#All],[Short_Desc]:[CumAmount]],4,0),0) -> 0
A5: 44564 | B5: 194 | C5: =IF(SIGN(B5)=-1, B5*-1, B5) -> 194 | D5: ATM CASH DEPOSIT ON 01/02 3002 N Central Ave Phoenix AZ 0003743 ATM ID 5449B CARD 6634 | E5: atm | F5: =MONTH(A5)&"/"&YEAR(A5) -> 1/2022 | G5: 0
A6: 44564 | B6: -485 | C6: =IF(SIGN(B6)=-1, B6*-1, B6) -> 485 | D6: TRANSFER TO LEWIS SHARON ON 01/03 REF #PP0D9295LZ XXXXXXXXX5267 | E6: mom | F6: =MONTH(A6)&"/"&YEAR(A6) -> 1/2022 | G6: People
A7: 44564 | B7: 477.73 | C7: =IF(SIGN(B7)=-1, B7*-1, B7) -> 477.73 | D7: RTP from VENMO on 01/03 Ref#20220103021000021P1BRJPM00530020747 | E7: Vincent | F7: =MONTH(A7)&"/"&YEAR(A7) -> 1/2022 | G7: People
A8: 44568 | B8: 30.89 | C8: =IF(SIGN(B8)=-1, B8*-1, B8) -> 30.89 | D8: VENMO CASHOUT 220107 1017829933941 SEAN LEWIS | E8: Vincent | F8: =MONTH(A8)&"/"&YEAR(A8) -> 1/2022 | G8: Utilities
A9: 44568 | B9: 23.27 | C9: =IF(SIGN(B9)=-1, B9*-1, B9) -> 23.27 | D9: LIFETIME FITNESS DIRECT DEP 220107 558079861456SHS LEWIS,SEAN | E9: gym | F9: =MONTH(A9)&"/"&YEAR(A9) -> 1/2022 | G9: =IFERROR(VLOOKUP('Wells Fargo'!E156,dis_table[[#All],[Short_Desc]:[CumAmount]],4,0),0) -> 0
A10: 44571 | B10: 234.58 | C10: =IF(SIGN(B10)=-1, B10*-1, B10) -> 234.58 | D10: VENMO CASHOUT 220110 1017875354612 SEAN LEWIS | E10: Melanie | F10: =MONTH(A10)&"/"&YEAR(A10) -> 1/2022 | G10: Utilities
A11: 44571 | B11: 50 | C11: =IF(SIGN(B11)=-1, B11*-1, B11) -> 50 | D11: VENMO CASHOUT 220110 1017874602288 SEAN LEWIS | E11: Kabir | F11: =MONTH(A11)&"/"&YEAR(A11) -> 1/2022 | G11: Recreation_Entertainment
A12: 44572 | B12: -100 | C12: =IF(SIGN(B12)=-1, B12*-1, B12) -> 100 | D12: PURCHASE AUTHORIZED ON 01/10 CASH APP*CYANFACE 8774174551 CA S462010765413680 CARD 6634 | E12: Jayelin | F12: =MONTH(A12)&"/"&YEAR(A12) -> 1/2022 | G12: People
A13: 44574 | B13: -2194.92 | C13: =IF(SIGN(B13)=-1, B13*-1, B13) -> 2194.92 | D13: DISCOVER E-PAYMENT 220113 4618 LEWIS SEAN | E13: discover | F13: =MONTH(A13)&"/"&YEAR(A13) -> 1/2022 | G13: credit
A14: 44574 | B14: 3898.5 | C14: =IF(SIGN(B14)=-1, B14*-1, B14) -> 3898.5 | D14: Nationwide PAYROLL 01 HRP0007983168 Sean Lewis | E14: nationwide | F14: =MONTH(A14)&"/"&YEAR(A14) -> 1/2022 | G14: income
A15: 44575 | B15: -1000 | C15: =IF(SIGN(B15)=-1, B15*-1, B15) -> 1000 | D15: Synchrony Bank CC PYMT JAN 13 601918368630042 SEAN LEWIS | E15: care_credit | F15: =MONTH(A15)&"/"&YEAR(A15) -> 1/2022 | G15: credit
A16: 44575 | B16: -2.5 | C16: =IF(SIGN(B16)=-1, B16*-1, B16) -> 2.5 | D16: NON-WELLS FARGO ATM TRANSACTION FEE | E16: atm | F16: =MONTH(A16)&"/"&YEAR(A16) -> 1/2022 | G16: =IFERROR(VLOOKUP('Wells Fargo'!E148,dis_table[[#All],[Short_Desc]:[CumAmount]],4,0),0) -> 0
A17: 44575 | B17: -103.5 | C17: =IF(SIGN(B17)=-1, B17*-1, B17) -> 103.5 | D17: NON-WF ATM WITHDRAWAL AUTHORIZED ON 01/14 666 W E ST SAN DIEGO CA 382015019310845 ATM ID CA0961 CARD 6634 | E17: atm | F17: =MONTH(A17)&"/"&YEAR(A17) -> 1/2022 | G17: 0
A18: 44579 | B18: -48.5 | C18: =IF(SIGN(B18)=-1, B18*-1, B18) -> 48.5 | D18: NON-WF ATM WITHDRAWAL AUTHORIZED ON 01/16 4645 DE SOTO ST SAN DIEGO CA 582017109140029 ATM ID L631055 CARD 6634 | E18: atm | F18: =MONTH(A18)&"/"&YEAR(A18) -> 1/2022 | G18: =IFERROR(VLOOKUP('Wells Fargo'!E140,dis_table[[#All],[Short_Desc]:[CumAmount]],4,0),0) -> 0
A19: 44579 | B19: -2.5 | C19: =IF(SIGN(B19)=-1, B19*-1, B19) -> 2.5 | D19: NON-WELLS FARGO ATM TRANSACTION FEE | E19: atm | F19: =MONTH(A19)&"/"&YEAR(A19) -> 1/2022 | G19: =IFERROR(VLOOKUP('Wells Fargo'!E144,dis_table[[#All],[Short_Desc]:[CumAmount]],4,0),0) -> 0
A20: 44579 | B20: -10 | C20: =IF(SIGN(B20)=-1, B20*-1, B20) -> 10 | D20: PURCHASE AUTHORIZED ON 01/16 CASH APP*VALLEY 8774174551 CA S382017149175934 CARD 6634 | E20: fast_food | F20: =MONTH(A20)&"/"&YEAR(A20) -> 1/2022 | G20: =IFERROR(VLOOKUP('Wells Fargo'!E137,dis_table[[#All],[Short_Desc]:[CumAmount]],4,0),0) -> Misc
A21: 44579 | B21: -20 | C21: =IF(SIGN(B21)=-1, B21*-1, B21) -> 20 | D21: PURCHASE AUTHORIZED ON 01/16 CASH APP*DARIUS CA 8774174551 CA S382017148849842 CARD 6634 | E21: fast_food | F21: =MONTH(A21)&"/"&YEAR(A21) -> 1/2022 | G21: =IFERROR(VLOOKUP('Wells Fargo'!E138,dis_table[[#All],[Short_Desc]:[CumAmount]],4,0),0) -> Personal_Spending
A22: 44579 | B22: -2.5 | C22: =IF(SIGN(B22)=-1, B22*-1, B22) -> 2.5 | D22: NON-WELLS FARGO ATM TRANSACTION FEE | E22: atm | F22: =MONTH(A22)&"/"&YEAR(A22) -> 1/2022 | G22: =IFERROR(VLOOKUP('Wells Fargo'!E139,dis_table[[#All],[Short_Desc]:[CumAmount]],4,0),0) -> People
A23: 44579 | B23: -54.04 | C23: =IF(SIGN(B23)=-1, B23*-1, B23) -> 54.04 | D23: PURCHASE AUTHORIZED ON 01/16 CHEVRON 0094991 SAN DIEGO CA S382017053945491 CARD 6634 | E23: gas_station | F23: =MONTH(A23)&"/"&YEAR(A23) -> 1/2022 | G23: =IFERROR(VLOOKUP('Wells Fargo'!E141,dis_table[[#All],[Short_Desc]:[CumAmount]],4,0),0) -> 0
A24: 44579 | B24: -21.54 | C24: =IF(SIGN(B24)=-1, B24*-1, B24) -> 21.54 | D24: PURCHASE AUTHORIZED ON 01/16 SD ZOO CINNAMON TR SAN DIEGO CA S382017034170694 CARD 6634 | E24: zoo | F24: =MONTH(A24)&"/"&YEAR(A24) -> 1/2022 | G24: =IFERROR(VLOOKUP('Wells Fargo'!E142,dis_table[[#All],[Short_Desc]:[CumAmount]],4,0),0) -> 0
A25: 44579 | B25: -6.99 | C25: =IF(SIGN(B25)=-1, B25*-1, B25) -> 6.99 | D25: PURCHASE AUTHORIZED ON 01/16 SD ZOO CANYON CAFE SAN DIEGO CA S582016817636715 CARD 6634 | E25: zoo | F25: =MONTH(A25)&"/"&YEAR(A25) -> 1/2022 | G25: =IFERROR(VLOOKUP('Wells Fargo'!E143,dis_table[[#All],[Short_Desc]:[CumAmount]],4,0),0) -> People
A26: 44579 | B26: -42.75 | C26: =IF(SIGN(B26)=-1, B26*-1, B26) -> 42.75 | D26: NON-WF ATM WITHDRAWAL AUTHORIZED ON 01/16 3710 VOLTAIRE ST. STE 1 SAN DIEGO CA 582016595373620 ATM ID P459681 CARD 6634 | E26: atm | F26: =MONTH(A26)&"/"&YEAR(A26) -> 1/2022 | G26: =IFERROR(VLOOKUP('Wells Fargo'!E145,dis_table[[#All],[Short_Desc]:[CumAmount]],4,0),0) -> 0
A27: 44579 | B27: -40 | C27: =IF(SIGN(B27)=-1, B27*-1, B27) -> 40 | D27: PURCHASE AUTHORIZED ON 01/15 BALLAST POINT LITT SAN DIEGO CA S302015831911176 CARD 6634 | E27: restaurant | F27: =MONTH(A27)&"/"&YEAR(A27) -> 1/2022 | G27: Food
A28: 44579 | B28: -576.01 | C28: =IF(SIGN(B28)=-1, B28*-1, B28) -> 576.01 | D28: VENMO PAYMENT 220117 1018001608819 SEAN LEWIS | E28: Kabir | F28: =MONTH(A28)&"/"&YEAR(A28) -> 1/2022 | G28: Recreation_Entertainment
A29: 44579 | B29: -68.33 | C29: =IF(SIGN(B29)=-1, B29*-1, B29) -> 68.33 | D29: VENMO PAYMENT 220117 1018001751483 SEAN LEWIS | E29: Logan | F29: =MONTH(A29)&"/"&YEAR(A29) -> 1/2022 | G29: Recreation_Entertainment
A30: 44585 | B30: -70 | C30: =IF(SIGN(B30)=-1, B30*-1, B30) -> 70 | D30: VENMO PAYMENT 220122 1018085063025 SEAN LEWIS | E30: Jon | F30: =MONTH(A30)&"/"&YEAR(A30) -> 1/2022 | G30: Personal_Spending
A31: 44588 | B31: -1866.67 | C31: =IF(SIGN(B31)=-1, B31*-1, B31) -> 1866.67 | D31: VENMO PAYMENT 220127 1018168964129 SEAN LEWIS | E31: rent | F31: =MONTH(A31)&"/"&YEAR(A31) -> 1/2022 | G31: Housing
A32: 44588 | B32: 933.33 | C32: =IF(SIGN(B32)=-1, B32*-1, B32) -> 933.33 | D32: VENMO CASHOUT 220127 1018164349212 SEAN LEWIS | E32: Vincent | F32: =MONTH(A32)&"/"&YEAR(A32) -> 1/2022 | G32: Housing
A33: 44588 | B33: 1718.36 | C33: =IF(SIGN(B33)=-1, B33*-1, B33) -> 1718.36 | D33: Nationwide PAYROLL 01 HRP0008024211 Sean Lewis | E33: nationwide | F33: =MONTH(A33)&"/"&YEAR(A33) -> 1/2022 | G33: income
A34: 44592 | B34: -120 | C34: =IF(SIGN(B34)=-1, B34*-1, B34) -> 120 | D34: TRANSFER TO LEWIS DON ON 01/31 REF #PP0Q7YVDF7 XXXXXX7932 | E34: Don | F34: =MONTH(A34)&"/"&YEAR(A34) -> 1/2022 | G34: People
A35: 44592 | B35: -20 | C35: =IF(SIGN(B35)=-1, B35*-1, B35) -> 20 | D35: TRANSFER TO LEWIS SHARON ON 01/31 REF #PP0Q7YX7VJ XXXXXXXXX5267 | E35: mom | F35: =MONTH(A35)&"/"&YEAR(A35) -> 1/2022 | G35: People
A36: 44592 | B36: -29 | C36: =IF(SIGN(B36)=-1, B36*-1, B36) -> 29 | D36: VENMO PAYMENT 220129 1018202156945 SEAN LEWIS | E36: Nick | F36: =MONTH(A36)&"/"&YEAR(A36) -> 1/2022 | G36: Recreation_Entertainment
A37: 44599 | B37: 120 | C37: =IF(SIGN(B37)=-1, B37*-1, B37) -> 120 | D37: ZELLE FROM LEWIS JUSTINA ON 02/05 REF # PP0Q8BDL92 | E37: Don | F37: =MONTH(A37)&"/"&YEAR(A37) -> 2/2022 | G37: People
A38: 44602 | B38: -1733.33 | C38: =IF(SIGN(B38)=-1, B38*-1, B38) -> 1733.33 | D38: DISCOVER E-PAYMENT 220210 4618 LEWIS SEAN | E38: discover | F38: =MONTH(A38)&"/"&YEAR(A38) -> 2/2022 | G38: =IFERROR(VLOOKUP('Wells Fargo'!E122,dis_table[[#All],[Short_Desc]:[CumAmount]],4,0),0) -> 0
A39: 44602 | B39: -70 | C39: =IF(SIGN(B39)=-1, B39*-1, B39) -> 70 | D39: VENMO PAYMENT 220210 1018415472279 SEAN LEWIS | E39: Kim | F39: =MONTH(A39)&"/"&YEAR(A39) -> 2/2022 | G39: Personal_Spending
A40: 44602 | B40: 662.38 | C40: =IF(SIGN(B40)=-1, B40*-1, B40) -> 662.38 | D40: VENMO CASHOUT 220210 1018420729744 SEAN LEWIS | E40: Vincent | F40: =MONTH(A40)&"/"&YEAR(A40) -> 2/2022 | G40: Housing
A41: 44602 | B41: 68.58 | C41: =IF(SIGN(B41)=-1, B41*-1, B41) -> 68.58 | D41: VENMO CASHOUT 220210 1018412598097 SEAN LEWIS | E41: Melanie | F41: =MONTH(A41)&"/"&YEAR(A41) -> 2/2022 | G41: Utilities
A42: 44602 | B42: 1718.36 | C42: =IF(SIGN(B42)=-1, B42*-1, B42) -> 1718.36 | D42: Nationwide PAYROLL 01 HRP0008036323 Sean Lewis | E42: nationwide | F42: =MONTH(A42)&"/"&YEAR(A42) -> 2/2022 | G42: income
A43: 44603 | B43: -70 | C43: =IF(SIGN(B43)=-1, B43*-1, B43) -> 70 | D43: VENMO PAYMENT 220211 1018433632129 SEAN LEWIS | E43: Jon | F43: =MONTH(A43)&"/"&YEAR(A43) -> 2/2022 | G43: Personal_Spending
A44: 44603 | B44: -307.35 | C44: =IF(SIGN(B44)=-1, B44*-1, B44) -> 307.35 | D44: Synchrony Bank CC PYMT FEB 10 601918368630042 SEAN LEWIS | E44: care_credit | F44: =MONTH(A44)&"/"&YEAR(A44) -> 2/2022 | G44: credit
A45: 44606 | B45: -100 | C45: =IF(SIGN(B45)=-1, B45*-1, B45) -> 100 | D45: ATM WITHDRAWAL AUTHORIZED ON 02/13 4402 E Thomas Rd Phoenix AZ 0008953 ATM ID 5743H CARD 6634 | E45: atm | F45: =MONTH(A45)&"/"&YEAR(A45) -> 2/2022 | G45: =IFERROR(VLOOKUP('Wells Fargo'!E119,dis_table[[#All],[Short_Desc]:[CumAmount]],4,0),0) -> 0
A46: 44610 | B46: -70 | C46: =IF(SIGN(B46)=-1, B46*-1, B46) -> 70 | D46: VENMO PAYMENT 220218 1018555740013 SEAN LEWIS | E46: Jon | F46: =MONTH(A46)&"/"&YEAR(A46) -> 2/2022 | G46: Personal_Spending
A47: 44614 | B47: -205.75 | C47: =IF(SIGN(B47)=-1, B47*-1, B47) -> 205.75 | D47: APS electric pmt PAYMENT 220217 5175354092 Autopay | E47: aps | F47: =MONTH(A47)&"/"&YEAR(A47) -> 2/2022 | G47: Utilities
A48: 44614 | B48: -1000 | C48: =IF(SIGN(B48)=-1, B48*-1, B48) -> 1000 | D48: Synchrony Bank CC PYMT FEB 19 601918368630042 SEAN LEWIS | E48: care_credit | F48: =MONTH(A48)&"/"&YEAR(A48) -> 2/2022 | G48: credit
A49: 44614 | B49: -771.1 | C49: =IF(SIGN(B49)=-1, B49*-1, B49) -> 771.1 | D49: DISCOVER E-PAYMENT 220220 4618 LEWIS SEAN | E49: discover | F49: =MONTH(A49)&"/"&YEAR(A49) -> 2/2022 | G49: =IFERROR(VLOOKUP('Wells Fargo'!E115,dis_table[[#All],[Short_Desc]:[CumAmount]],4,0),0) -> People
A50: 44614 | B50: 520.85 | C50: =IF(SIGN(B50)=-1, B50*-1, B50) -> 520.85 | D50: TPG PRODUCTS SBTPG LLC 220218 ETRVW3GLLOEOPDY SEAN LEWIS | E50: taxes | F50: =MONTH(A50)&"/"&YEAR(A50) -> 2/2022 | G50: income
A51: 44614 | B51: 1257 | C51: =IF(SIGN(B51)=-1, B51*-1, B51) -> 1257 | D51: AZ DEPT OF REV Tax Refund 220218 XXXXX0268 LEWIS SEAN | E51: taxes | F51: =MONTH(A51)&"/"&YEAR(A51) -> 2/2022 | G51: income
A52: 44614 | B52: -189.21 | C52: =IF(SIGN(B52)=-1, B52*-1, B52) -> 189.21 | D52: VENMO PAYMENT 220222 1018622300513 SEAN LEWIS | E52: Vincent | F52: =MONTH(A52)&"/"&YEAR(A52) -> 2/2022 | G52: People
A53: 44616 | B53: 2176.22 | C53: =IF(SIGN(B53)=-1, B53*-1, B53) -> 2176.22 | D53: Nationwide PAYROLL 01 HRP0008091792 Sean Lewis | E53: nationwide | F53: =MONTH(A53)&"/"&YEAR(A53) -> 2/2022 | G53: income
A54: 44616 | B54: 100 | C54: =IF(SIGN(B54)=-1, B54*-1, B54) -> 100 | D54: TD AMERITRADE ACH OUT a9KLOZ6PQR LEWIS SEAN | E54: td_ameritrade | F54: =MONTH(A54)&"/"&YEAR(A54) -> 2/2022 | G54: income
A55: 44617 | B55: 1424 | C55: =IF(SIGN(B55)=-1, B55*-1, B55) -> 1424 | D55: VA DEPT TAXATION VASTTAXRFD 220217 XXXXX0268 LEWIS, SEAN E | E55: taxes | F55: =MONTH(A55)&"/"&YEAR(A55) -> 2/2022 | G55: income
A56: 44617 | B56: -1400 | C56: =IF(SIGN(B56)=-1, B56*-1, B56) -> 1400 | D56: VENMO PAYMENT 220225 1018674378710 SEAN LEWIS | E56: Vincent | F56: =MONTH(A56)&"/"&YEAR(A56) -> 2/2022 | G56: People
A57: 44620 | B57: -1866.67 | C57: =IF(SIGN(B57)=-1, B57*-1, B57) -> 1866.67 | D57: VENMO PAYMENT 220226 1018692237447 SEAN LEWIS | E57: rent | F57: =MONTH(A57)&"/"&YEAR(A57) -> 2/2022 | G57: Housing
A58: 44620 | B58: -2.5 | C58: =IF(SIGN(B58)=-1, B58*-1, B58) -> 2.5 | D58: NON-WELLS FARGO ATM TRANSACTION FEE | E58: atm | F58: =MONTH(A58)&"/"&YEAR(A58) -> 2/2022 | G58: =IFERROR(VLOOKUP('Wells Fargo'!E105,dis_table[[#All],[Short_Desc]:[CumAmount]],4,0),0) -> 0
A59: 44620 | B59: -42 | C59: =IF(SIGN(B59)=-1, B59*-1, B59) -> 42 | D59: NON-WF ATM WITHDRAWAL AUTHORIZED ON 02/25 727 W CAMELBACK RD PHOENIX AZ 382057136740734 ATM ID P304339 CARD 6634 | E59: atm | F59: =MONTH(A59)&"/"&YEAR(A59) -> 2/2022 | G59: =IFERROR(VLOOKUP('Wells Fargo'!E106,dis_table[[#All],[Short_Desc]:[CumAmount]],4,0),0) -> 0
A60: 44620 | B60: 485 | C60: =IF(SIGN(B60)=-1, B60*-1, B60) -> 485 | D60: TRANSFER FROM LEWIS SHARON ON 02/26 REF # PP0Q9F5QXB THANK YOU | E60: mom | F60: =MONTH(A60)&"/"&YEAR(A60) -> 2/2022 | G60: People
A61: 44620 | B61: -485 | C61: =IF(SIGN(B61)=-1, B61*-1, B61) -> 485 | D61: VENMO PAYMENT 220226 1018692186925 SEAN LEWIS | E61: Vincent | F61: =MONTH(A61)&"/"&YEAR(A61) -> 2/2022 | G61: People
A62: 44621 | B62: -62 | C62: =IF(SIGN(B62)=-1, B62*-1, B62) -> 62 | D62: VENMO PAYMENT 220301 1018758856961 SEAN LEWIS | E62: Vincent | F62: =MONTH(A62)&"/"&YEAR(A62) -> 3/2022 | G62: Utilities
A63: 44630 | B63: -734.55 | C63: =IF(SIGN(B63)=-1, B63*-1, B63) -> 734.55 | D63: DISCOVER E-PAYMENT 220310 4618 LEWIS SEAN | E63: discover | F63: =MONTH(A63)&"/"&YEAR(A63) -> 3/2022 | G63: credit
A64: 44630 | B64: 2240.07 | C64: =IF(SIGN(B64)=-1, B64*-1, B64) -> 2240.07 | D64: Nationwide PAYROLL 01 HRP0008137116 Sean Lewis | E64: nationwide | F64: =MONTH(A64)&"/"&YEAR(A64) -> 3/2022 | G64: income
A65: 44630 | B65: -1500 | C65: =IF(SIGN(B65)=-1, B65*-1, B65) -> 1500 | D65: VENMO PAYMENT 220310 1018915574100 SEAN LEWIS | E65: Vincent | F65: =MONTH(A65)&"/"&YEAR(A65) -> 3/2022 | G65: People
A66: 44638 | B66: -60 | C66: =IF(SIGN(B66)=-1, B66*-1, B66) -> 60 | D66: PURCHASE AUTHORIZED ON 03/17 CASH APP*SHEVON LE 8774174551 CA S302076796250975 CARD 6634 | E66: Shevon | F66: =MONTH(A66)&"/"&YEAR(A66) -> 3/2022 | G66: People
A67: 44641 | B67: 33 | C67: =IF(SIGN(B67)=-1, B67*-1, B67) -> 33 | D67: ZELLE FROM ERNEST NOCHE ON 03/20 REF # BACU6FMEIILK | E67: Michael | F67: =MONTH(A67)&"/"&YEAR(A67) -> 3/2022 | G67: Food
A68: 44641 | B68: 137.51 | C68: =IF(SIGN(B68)=-1, B68*-1, B68) -> 137.51 | D68: VENMO CASHOUT 220321 1019111739464 SEAN LEWIS | E68: Venmo | F68: =MONTH(A68)&"/"&YEAR(A68) -> 3/2022 | G68: People
A69: 44642 | B69: -734.55 | C69: =IF(SIGN(B69)=-1, B69*-1, B69) -> 734.55 | D69: DISCOVER E-PAYMENT 220322 4618 LEWIS SEAN | E69: discover | F69: =MONTH(A69)&"/"&YEAR(A69) -> 3/2022 | G69: credit
A70: 44642 | B70: -146.17 | C70: =IF(SIGN(B70)=-1, B70*-1, B70) -> 146.17 | D70: APS electric pmt PAYMENT 220318 5175354092 Autopay | E70: aps | F70: =MONTH(A70)&"/"&YEAR(A70) -> 3/2022 | G70: Utilities
A71: 44642 | B71: -43.16 | C71: =IF(SIGN(B71)=-1, B71*-1, B71) -> 43.16 | D71: PURCHASE AUTHORIZED ON 03/22 SHELL SERVICE STATION PHOENIX AZ P302081522144554 CARD 6634 | E71: gas_station | F71: =MONTH(A71)&"/"&YEAR(A71) -> 3/2022 | G71: =IFERROR(VLOOKUP('Wells Fargo'!E94,dis_table[[#All],[Short_Desc]:[CumAmount]],4,0),0) -> 0
A72: 44642 | B72: 66 | C72: =IF(SIGN(B72)=-1, B72*-1, B72) -> 66 | D72: VENMO CASHOUT 220322 1019125273986 SEAN LEWIS | E72: Vincent | F72: =MONTH(A72)&"/"&YEAR(A72) -> 3/2022 | G72: People
A73: 44644 | B73: -1400 | C73: =IF(SIGN(B73)=-1, B73*-1, B73) -> 1400 | D73: VENMO PAYMENT 220324 1019164077845 SEAN LEWIS | E73: rent | F73: =MONTH(A73)&"/"&YEAR(A73) -> 3/2022 | G73: Housing
A74: 44644 | B74: -500 | C74: =IF(SIGN(B74)=-1, B74*-1, B74) -> 500 | D74: DISCOVER E-PAYMENT 220324 4618 LEWIS SEAN | E74: discover | F74: =MONTH(A74)&"/"&YEAR(A74) -> 3/2022 | G74: credit
A75: 44644 | B75: 2240.07 | C75: =IF(SIGN(B75)=-1, B75*-1, B75) -> 2240.07 | D75: Nationwide PAYROLL 01 HRP0008178715 Sean Lewis | E75: nationwide | F75: =MONTH(A75)&"/"&YEAR(A75) -> 3/2022 | G75: income
A76: 44645 | B76: -52 | C76: =IF(SIGN(B76)=-1, B76*-1, B76) -> 52 | D76: VENMO PAYMENT 220325 1019189845192 SEAN LEWIS | E76: Nick | F76: =MONTH(A76)&"/"&YEAR(A76) -> 3/2022 | G76: Recreation_Entertainment
A77: 44648 | B77: -5 | C77: =IF(SIGN(B77)=-1, B77*-1, B77) -> 5 | D77: PURCHASE AUTHORIZED ON 03/26 CASH APP*ENGAGETM 8774174551 CA S382085824280328 CARD 6634 | E77: Dorry | F77: =MONTH(A77)&"/"&YEAR(A77) -> 3/2022 | G77: People
A78: 44648 | B78: -100 | C78: =IF(SIGN(B78)=-1, B78*-1, B78) -> 100 | D78: PURCHASE AUTHORIZED ON 03/25 CASH APP*CYANFACE 8774174551 CA S302084480194424 CARD 6634 | E78: jayelin | F78: =MONTH(A78)&"/"&YEAR(A78) -> 3/2022 | G78: People
A79: 44649 | B79: -70.65 | C79: =IF(SIGN(B79)=-1, B79*-1, B79) -> 70.65 | D79: VENMO PAYMENT 220329 1019258605951 SEAN LEWIS | E79: Melanie | F79: =MONTH(A79)&"/"&YEAR(A79) -> 3/2022 | G79: Utilities
A80: 44649 | B80: 49.32 | C80: =IF(SIGN(B80)=-1, B80*-1, B80) -> 49.32 | D80: VENMO CASHOUT 220329 1019258957091 SEAN LEWIS | E80: Melanie | F80: =MONTH(A80)&"/"&YEAR(A80) -> 3/2022 | G80: Utilities
A81: 44649 | B81: 87.4 | C81: =IF(SIGN(B81)=-1, B81*-1, B81) -> 87.4 | D81: VENMO CASHOUT 220329 1019257034036 SEAN LEWIS | E81: Venmo | F81: =MONTH(A81)&"/"&YEAR(A81) -> 3/2022 | G81: People
A82: 44651 | B82: -10 | C82: =IF(SIGN(B82)=-1, B82*-1, B82) -> 10 | D82: PURCHASE AUTHORIZED ON 03/30 CASH APP*CYANFACE 8774174551 CA S462090143040686 CARD 6634 | E82: Jayelin | F82: =MONTH(A82)&"/"&YEAR(A82) -> 3/2022 | G82: People
A83: 44652 | B83: -45 | C83: =IF(SIGN(B83)=-1, B83*-1, B83) -> 45 | D83: PURCHASE AUTHORIZED ON 03/31 CASH APP*CYANFACE 8774174551 CA S582090834603593 CARD 6634 | E83: Jayelin | F83: =MONTH(A83)&"/"&YEAR(A83) -> 4/2022 | G83: People
A84: 44655 | B84: -8 | C84: =IF(SIGN(B84)=-1, B84*-1, B84) -> 8 | D84: PURCHASE AUTHORIZED ON 04/01 CASH APP*CYANFACE 8774174551 CA S302091792116789 CARD 6634 | E84: Jayelin | F84: =MONTH(A84)&"/"&YEAR(A84) -> 4/2022 | G84: People
A85: 44655 | B85: -38.71 | C85: =IF(SIGN(B85)=-1, B85*-1, B85) -> 38.71 | D85: PURCHASE AUTHORIZED ON 04/02 SAFEWAY #2651 PHOENIX AZ P462092686408975 CARD 6634 | E85: groceries | F85: =MONTH(A85)&"/"&YEAR(A85) -> 4/2022 | G85: =IFERROR(VLOOKUP('Wells Fargo'!E79,dis_table[[#All],[Short_Desc]:[CumAmount]],4,0),0) -> 0
A86: 44655 | B86: -100 | C86: =IF(SIGN(B86)=-1, B86*-1, B86) -> 100 | D86: TRANSFER TO LEWIS SHARON ON 04/03 REF #PP0QCJCLVN XXXXXXXXX5267 | E86: mom | F86: =MONTH(A86)&"/"&YEAR(A86) -> 4/2022 | G86: People
A87: 44656 | B87: -5.41 | C87: =IF(SIGN(B87)=-1, B87*-1, B87) -> 5.41 | D87: PURCHASE AUTHORIZED ON 04/04 Whitepages 800-9529005 WA S382095014545576 CARD 6634 | E87: unsure | F87: =MONTH(A87)&"/"&YEAR(A87) -> 4/2022 | G87: =IFERROR(VLOOKUP('Wells Fargo'!E76,dis_table[[#All],[Short_Desc]:[CumAmount]],4,0),0) -> 0
A88: 44656 | B88: -10.78 | C88: =IF(SIGN(B88)=-1, B88*-1, B88) -> 10.78 | D88: PURCHASE AUTHORIZED ON 04/04 Whitepages 800-9529005 WA S382095010925055 CARD 6634 | E88: unsure | F88: =MONTH(A88)&"/"&YEAR(A88) -> 4/2022 | G88: =IFERROR(VLOOKUP('Wells Fargo'!E77,dis_table[[#All],[Short_Desc]:[CumAmount]],4,0),0) -> 0
A89: 44657 | B89: -40 | C89: =IF(SIGN(B89)=-1, B89*-1, B89) -> 40 | D89: PURCHASE AUTHORIZED ON 04/05 CASH APP*CYANFACE 8774174551 CA S382096070149787 CARD 6634 | E89: Jayelin | F89: =MONTH(A89)&"/"&YEAR(A89) -> 4/2022 | G89: People
A90: 44658 | B90: -934.85 | C90: =IF(SIGN(B90)=-1, B90*-1, B90) -> 934.85 | D90: DISCOVER E-PAYMENT 220407 4618 LEWIS SEAN | E90: discover | F90: =MONTH(A90)&"/"&YEAR(A90) -> 4/2022 | G90: credit
A91: 44658 | B91: 2240.08 | C91: =IF(SIGN(B91)=-1, B91*-1, B91) -> 2240.08 | D91: Nationwide PAYROLL 01 HRP0008210841 Sean Lewis | E91: nationwide | F91: =MONTH(A91)&"/"&YEAR(A91) -> 4/2022 | G91: income
A92: 44659 | B92: -35 | C92: =IF(SIGN(B92)=-1, B92*-1, B92) -> 35 | D92: ZELLE TO ZAZUETA CARMEN ON 04/08 REF #PP0QCS8FDR | E92: Carmen | F92: =MONTH(A92)&"/"&YEAR(A92) -> 4/2022 | G92: People
A93: 44659 | B93: -1000 | C93: =IF(SIGN(B93)=-1, B93*-1, B93) -> 1000 | D93: Synchrony Bank CC PYMT APR 07 601918368630042 SEAN LEWIS | E93: care_credit | F93: =MONTH(A93)&"/"&YEAR(A93) -> 4/2022 | G93: credit
A94: 44659 | B94: -200 | C94: =IF(SIGN(B94)=-1, B94*-1, B94) -> 200 | D94: TRANSFER TO LEWIS SHARON ON 04/08 REF #PP0QCT2JQH XXXXXXXXX5267 | E94: mom | F94: =MONTH(A94)&"/"&YEAR(A94) -> 4/2022 | G94: People
A95: 44666 | B95: -50 | C95: =IF(SIGN(B95)=-1, B95*-1, B95) -> 50 | D95: VENMO PAYMENT 220415 1019571055773 SEAN LEWIS | E95: aps | F95: =MONTH(A95)&"/"&YEAR(A95) -> 4/2022 | G95: Utilities
A96: 44666 | B96: 63 | C96: =IF(SIGN(B96)=-1, B96*-1, B96) -> 63 | D96: TICKETMASTER RES 0414-TH002 200051625122116 SEAN LEWIS | E96: ticket_sale | F96: =MONTH(A96)&"/"&YEAR(A96) -> 4/2022 | G96: income
A97: 44671 | B97: -147.97 | C97: =IF(SIGN(B97)=-1, B97*-1, B97) -> 147.97 | D97: APS electric pmt PAYMENT 220418 5175354092 Autopay | E97: aps | F97: =MONTH(A97)&"/"&YEAR(A97) -> 4/2022 | G97: Utilities
A98: 44672 | B98: -1400 | C98: =IF(SIGN(B98)=-1, B98*-1, B98) -> 1400 | D98: VENMO PAYMENT 220421 1019665215805 SEAN LEWIS | E98: rent | F98: =MONTH(A98)&"/"&YEAR(A98) -> 4/2022 | G98: Housing
A99: 44672 | B99: 2240.07 | C99: =IF(SIGN(B99)=-1, B99*-1, B99) -> 2240.07 | D99: Nationwide PAYROLL 01 HRP0008262709 Sean Lewis | E99: nationwide | F99: =MONTH(A99)&"/"&YEAR(A99) -> 4/2022 | G99: income
A100: 44676 | B100: -59 | C100: =IF(SIGN(B100)=-1, B100*-1, B100) -> 59 | D100: VENMO PAYMENT 220425 1019749370210 SEAN LEWIS | E100: Maricela | F100: =MONTH(A100)&"/"&YEAR(A100) -> 4/2022 | G100: Recreation_Entertainment
...

Sheet AMEX
A1: Date | B1: Description | C1: Amount | D1: Category
A2: 02/03/2022 | B2: LIFE TIME CAFE 132Q3KATY AZ | C2: 17.81 | D2: Restaurant-Bar & Café
A3: 02/04/2022 | B3: HACHI RAMEN 0000 TEMPE AZ | C3: 32.41 | D3: Restaurant-Restaurant
A4: 02/04/2022 | B4: THE HOME DEPOT TEMPE AZ | C4: 26.04 | D4: Merchandise & Supplies-Hardware Supplies
A5: 02/05/2022 | B5: UNITED STATES PROFESORLANDO FL | C5: 378.17 | D5: Entertainment-Associations
A6: 02/06/2022 | B6: BOSA DONUTS AHWATUKEPHOENIX AZ | C6: 5 | D6: Restaurant-Restaurant
A7: 02/06/2022 | B7: TARGET PHOENIX SPECTPHOENIX AZ | C7: 152.8 | D7: Merchandise & Supplies-Wholesale Stores
A8: 02/06/2022 | B8: TST* WOW WOW HAWAIIAPHOENIX AZ | C8: 15.7 | D8: Restaurant-Restaurant
A9: 02/06/2022 | B9: UNION 76 09480716 PHOENIX AZ | C9: 37.4 | D9: Transportation-Fuel
A10: 02/08/2022 | B10: TACOS HUICHO #2 0000PHOENIX AZ | C10: 40.87 | D10: Restaurant-Restaurant
A11: 02/09/2022 | B11: WALGREENS PHOENIX AZ | C11: 3.19 | D11: Merchandise & Supplies-Pharmacies
A12: 02/10/2022 | B12: PHOENIX TENNIS CENTEPHOENIX AZ | C12: 4.33 | D12: Other-Miscellaneous
A13: 02/10/2022 | B13: TCKTWEB*CARIBOUWITHSSAN FRANCISCO CA | C13: 67 | D13: Entertainment-General Events
... A68: 07/17/2022 | B68: VHLV- LODGING 021770LAS VEGAS NV | C68: 112.87 | D68: Travel-Lodging

Sheet June Trips
A1: Trans Date | B1: Description | C1: Individual Amount | D1: Shared Amount | E1: Split Amount | F1: Amount | G1: Date | H1: Short_Desc | I1: Category_2
A2: 44725 | B2: Aldi | D2: 11.71 | E2: =D2/2 -> 5.855 | F2: =E2+C2 -> 5.855 | G2: =MONTH(A2)&"/"&YEAR(A2) -> 6/2022 | H2: groceries | I2: =VLOOKUP(Table5[[#This Row],[Short_Desc]],dis_table[[#All],[Short_Desc]:[CumAmount]],4,0) -> Food
A3: 44727 | B3: Uber | D3: 42.54 | E3: =D3/2 -> 21.27 | F3: =E3+C3 -> 21.27 | G3: =MONTH(A3)&"/"&YEAR(A3) -> 6/2022 | H3: ride_share | I3: =VLOOKUP(Table5[[#This Row],[Short_Desc]],dis_table[[#All],[Short_Desc]:[CumAmount]],4,0) -> Transportation
A4: 44729 | B4: Hilton Shulas Resturant | C4: 5.3 | F4: =E4+C4 -> 5.3 | G4: =MONTH(A4)&"/"&YEAR(A4) -> 6/2022 | H4: restaurant | I4: =VLOOKUP(Table5[[#This Row],[Short_Desc]],dis_table[[#All],[Short_Desc]:[CumAmount]],4,0) -> Food
A5: 44731 | B5: Amtrak Northeast Cafe | C5: 18.5 | F5: =E5+C5 -> 18.5 | G5: =MONTH(A5)&"/"&YEAR(A5) -> 6/2022 | H5: fast_food | I5: =VLOOKUP(Table5[[#This Row],[Short_Desc]],dis_table[[#All],[Short_Desc]:[CumAmount]],4,0) -> Food
A6: 44731 | B6: Macdonalds | D6: 23.62 | E6: =D6/2 -> 11.81 | F6: =E6+C6 -> 11.81 | G6: =MONTH(A6)&"/"&YEAR(A6) -> 6/2022 | H6: fast_food | I6: =VLOOKUP(Table5[[#This Row],[Short_Desc]],dis_table[[#All],[Short_Desc]:[CumAmount]],4,0) -> Food
A7: 44731 | B7: Hilton | D7: 497.04 | E7: =D7/2 -> 248.52 | F7: =E7+C7 -> 248.52 | G7: =MONTH(A7)&"/"&YEAR(A7) -> 6/2022 | H7: hotel | I7: Recreation_Entertainment
A8: 44732 | B8: Uber | D8: 56.52 | E8: =D8/2 -> 28.26 | F8: =E8+C8 -> 28.26 | G8: =MONTH(A8)&"/"&YEAR(A8) -> 6/2022 | H8: ride_share | I8: =VLOOKUP(Table5[[#This Row],[Short_Desc]],dis_table[[#All],[Short_Desc]:[CumAmount]],4,0) -> Transportation
A9: 44732 | B9: Uber | D9: 12.97 | E9: =D9/2 -> 6.485 | F9: =E9+C9 -> 6.485 | G9: =MONTH(A9)&"/"&YEAR(A9) -> 6/2022 | H9: ride_share | I9: =VLOOKUP(Table5[[#This Row],[Short_Desc]],dis_table[[#All],[Short_Desc]:[CumAmount]],4,0) -> Transportation
A10: 44732 | B10: Republic | D10: 85 | E10: =D10/2 -> 42.5 | F10: =E10+C10 -> 42.5 | G10: =MONTH(A10)&"/"&YEAR(A10) -> 6/2022 | H10: restaurant | I10: =VLOOKUP(Table5[[#This Row],[Short_Desc]],dis_table[[#All],[Short_Desc]:[CumAmount]],4,0) -> Food
A11: 44732 | B11: Trip Advisor (underground tour) | D11: 58.06 | E11: =D11/2 -> 29.03 | F11: =E11+C11 -> 29.03 | G11: =MONTH(A11)&"/"&YEAR(A11) -> 6/2022 | H11: tour | I11: Recreation_Entertainment
A12: 44734 | B12: Hurry Curry of Tokyo | D12: 33.08 | E12: =D12/2 -> 16.54 | F12: =E12+C12 -> 16.54 | G12: =MONTH(A12)&"/"&YEAR(A12) -> 6/2022 | H12: restaurant | I12: =VLOOKUP(Table5[[#This Row],[Short_Desc]],dis_table[[#All],[Short_Desc]:[CumAmount]],4,0) -> Food
A13: 44735 | B13: La Parisienne French Bakery | D13: 26.22 | E13: =D13/2 -> 13.11 | F13: =E13+C13 -> 13.11 | G13: =MONTH(A13)&"/"&YEAR(A13) -> 6/2022 | H13: restaurant | I13: =VLOOKUP(Table5[[#This Row],[Short_Desc]],dis_table[[#All],[Short_Desc]:[CumAmount]],4,0) -> Food
A14: 44736 | B14: UW food Services | C14: 14.37 | F14: =E14+C14 -> 14.37 | G14: =MONTH(A14)&"/"&YEAR(A14) -> 6/2022 | H14: fast_food | I14: =VLOOKUP(Table5[[#This Row],[Short_Desc]],dis_table[[#All],[Short_Desc]:[CumAmount]],4,0) -> Food
A15: 44736 | B15: What the Pho Xpress | D15: 32.82 | E15: =D15/2 -> 16.41 | F15: =E15+C15 -> 16.41 | G15: =MONTH(A15)&"/"&YEAR(A15) -> 6/2022 | H15: restaurant | I15: =VLOOKUP(Table5[[#This Row],[Short_Desc]],dis_table[[#All],[Short_Desc]:[CumAmount]],4,0) -> Food
A16: 44736 | B16: Macy's (Luggage) | C16: 711.25 | F16: =E16+C16 -> 711.25 | G16: =MONTH(A16)&"/"&YEAR(A16) -> 6/2022 | H16: luggage | I16: Personal_Spending
A17: 44736 | B17: Umi Sake House | D17: 145.54 | E17: =D17/2 -> 72.77 | F17: =E17+C17 -> 72.77 | G17: =MONTH(A17)&"/"&YEAR(A17) -> 6/2022 | H17: restaurant | I17: =VLOOKUP(Table5[[#This Row],[Short_Desc]],dis_table[[#All],[Short_Desc]:[CumAmount]],4,0) -> Food
A18: 44738 | B18: Pho Viet Anh | D18: 44 | E18: =D18/2 -> 22 | F18: =E18+C18 -> 22 | G18: =MONTH(A18)&"/"&YEAR(A18) -> 6/2022 | H18: restaurant | I18: =VLOOKUP(Table5[[#This Row],[Short_Desc]],dis_table[[#All],[Short_Desc]:[CumAmount]],4,0) -> Food
A19: 44738 | B19: Hyatt House Space Needle | D19: 1751.05 | E19: =D19/2 -> 875.525 | F19: =E19+C19 -> 875.525 | G19: =MONTH(A19)&"/"&YEAR(A19) -> 6/2022 | H19: hotel | I19: Recreation_Entertainment
A20: 44739 | B20: Traveluro - Hampton Inn | D20: 116 | E20: =D20/2 -> 58 | F20: =E20+C20 -> 58 | G20: =MONTH(A20)&"/"&YEAR(A20) -> 6/2022 | H20: hotel | I20: Recreation_Entertainment
A21: 44740 | B21: Pitamore | D21: 25.71 | E21: =D21/2 -> 12.855 | F21: =E21+C21 -> 12.855 | G21: =MONTH(A21)&"/"&YEAR(A21) -> 6/2022 | H21: restaurant | I21: =VLOOKUP(Table5[[#This Row],[Short_Desc]],dis_table[[#All],[Short_Desc]:[CumAmount]],4,0) -> Food
A22: 44741 | B22: Ramen Utsuke | D22: 34.7 | E22: =D22/2 -> 17.35 | F22: =E22+C22 -> 17.35 | G22: =MONTH(A22)&"/"&YEAR(A22) -> 6/2022 | H22: restaurant | I22: =VLOOKUP(Table5[[#This Row],[Short_Desc]],dis_table[[#All],[Short_Desc]:[CumAmount]],4,0) -> Food
A23: 44741 | B23: CVS Pharmacy | D23: 19.88 | E23: =D23/2 -> 9.94 | F23: =E23+C23 -> 9.94 | G23: =MONTH(A23)&"/"&YEAR(A23) -> 6/2022 | H23: conv_store | I23: =VLOOKUP(Table5[[#This Row],[Short_Desc]],dis_table[[#All],[Short_Desc]:[CumAmount]],4,0) -> Personal_Spending
A24: 44741 | B24: Uber Eats | D24: 41.7 | E24: =D24/2 -> 20.85 | F24: =E24+C24 -> 20.85 | G24: =MONTH(A24)&"/"&YEAR(A24) -> 6/2022 | H24: fast_food | I24: =VLOOKUP(Table5[[#This Row],[Short_Desc]],dis_table[[#All],[Short_Desc]:[CumAmount]],4,0) -> Food
A25: 44741 | B25: Hotel Tonight - Kimton Hotel Monaco Baltimore | D25: 478 | E25: =D25/2 -> 239 | F25: =E25+C25 -> 239 | G25: =MONTH(A25)&"/"&YEAR(A25) -> 6/2022 | H25: hotel | I25: Recreation_Entertainment
A26: 44742 | B26: CVS Pharmacy | D26: 46.45 | E26: =D26/2 -> 23.225 | F26: =E26+C26 -> 23.225 | G26: =MONTH(A26)&"/"&YEAR(A26) -> 6/2022 | H26: conv_store | I26: =VLOOKUP(Table5[[#This Row],[Short_Desc]],dis_table[[#All],[Short_Desc]:[CumAmount]],4,0) -> Personal_Spending
A27: 44742 | B27: Corner Baker Inner Harbor | D27: 21.28 | E27: =D27/2 -> 10.64 | F27: =E27+C27 -> 10.64 | G27: =MONTH(A27)&"/"&YEAR(A27) -> 6/2022 | H27: restaurant | I27: =VLOOKUP(Table5[[#This Row],[Short_Desc]],dis_table[[#All],[Short_Desc]:[CumAmount]],4,0) -> Food
A28: 44742 | B28: Dalesios Restaurant of Little Italy | D28: 50.88 | E28: =D28/2 -> 25.44 | F28: =E28+C28 -> 25.44 | G28: =MONTH(A28)&"/"&YEAR(A28) -> 6/2022 | H28: restaurant | I28: =VLOOKUP(Table5[[#This Row],[Short_Desc]],dis_table[[#All],[Short_Desc]:[CumAmount]],4,0) -> Food
A29: 44743 | B29: Uber Eats - kumari restaurant | D29: 53.5 | E29: =D29/2 -> 26.75 | F29: =E29+C29 -> 26.75 | G29: =MONTH(A29)&"/"&YEAR(A29) -> 7/2022 | H29: fast_food | I29: =VLOOKUP(Table5[[#This Row],[Short_Desc]],dis_table[[#All],[Short_Desc]:[CumAmount]],4,0) -> Food
A30: 44743 | B30: Chipotle | D30: 20.41 | E30: =D30/2 -> 10.205 | F30: =E30+C30 -> 10.205 | G30: =MONTH(A30)&"/"&YEAR(A30) -> 7/2022 | H30: fast_food | I30: =VLOOKUP(Table5[[#This Row],[Short_Desc]],dis_table[[#All],[Short_Desc]:[CumAmount]],4,0) -> Food
A31: 44744 | B31: Uber Eats | D31: 38.5 | E31: =D31/2 -> 19.25 | F31: =E31+C31 -> 19.25 | G31: =MONTH(A31)&"/"&YEAR(A31) -> 7/2022 | H31: fast_food | I31: =VLOOKUP(Table5[[#This Row],[Short_Desc]],dis_table[[#All],[Short_Desc]:[CumAmount]],4,0) -> Food
A32: 44745 | B32: Uber | D32: 95.86 | E32: =D32/2 -> 47.93 | F32: =E32+C32 -> 47.93 | G32: =MONTH(A32)&"/"&YEAR(A32) -> 7/2022 | H32: ride_share | I32: =VLOOKUP(Table5[[#This Row],[Short_Desc]],dis_table[[#All],[Short_Desc]:[CumAmount]],4,0) -> Transportation
A33: 44745 | B33: Kimpton Hotel (Mini Bar) | C33: 9.54 | F33: =E33+C33 -> 9.54 | G33: =MONTH(A33)&"/"&YEAR(A33) -> 7/2022 | H33: conv_store | I33: =VLOOKUP(Table5[[#This Row],[Short_Desc]],dis_table[[#All],[Short_Desc]:[CumAmount]],4,0) -> Personal_Spending
F34: =SUBTOTAL(109,Table5[Amount]) -> 2690.48

Sheet Accounts
B2: Balance | C2: Limit | D2: Available Credit | E2: Monthly Payment | F2: Due Date
A3: Discover | B3: 6077.24 | C3: 7900 | D3: =C3-B3 -> 1822.76 | E3: 120 | F3: 28 | G3: =B3/E3 -> 50.643667
A4: Care Credit | B4: 0 | C4: 7550 | D4: =C4-B4 -> 7550 | F4: 2
A5: Best Buy | B5: 554.09 | C5: 4997 | D5: =C5-B5 -> 4442.91 | F5: 14
A6: Amex | B6: 505.36 | F6: 2
A7: Student Loan | B7: 22430.56 | E7: 348
A8: Vincent Debt | B8: =Table5[[#Totals],[Amount]] -> 2690.48
A12: Income | B12: 44771 | C12: =B12+14 -> 44785 | D12: =C12+14 -> 44799 | E12: =D12+14 -> 44813 | F12: =E12+14 -> 44827 | G12: =F12+14 -> 44841 | H12: =G12+14 -> 44855 | I12: =H12+14 -> 44869 | J12: =I12+14 -> 44883 | ... M12: =L12+14 -> 44925
A13: Nationwide | B13: 2482.89 | C13: 2482.89 | D13: 2482.89 | E13: 2482.89 | F13: 2482.89 | G13: 2482.89 | H13: 2482.89 | I13: 2482.89 | J13: 2482.89 | K13: 2482.89 | L13: 2482.89 | M13: 2482.89 | N13: =SUM(B13:M13) -> 29794.68
A14: surgery refund | B14: 504.86
A15: deposit | G15: 550
B16: =SUM(B13:B15) -> 2987.75 | C16: =SUM(C13:C15)+B28 -> 2993.4 | D16: =SUM(D13:D15)+C28 -> 2916.84 | E16: =SUM(E13:E15)+D28 -> 2999.73 | F16: =SUM(F13:F15)+E28 -> 2944.524 | G16: =SUM(G13:G15)+F28 -> 3439.318 | H16: =SUM(H13:H15)+G28 -> 3026.112 | I16: =SUM(I13:I15)+H28 -> 2970.906 | J16: =SUM(J13:J15)+I28 -> 2857.7 | ... M16: =SUM(M13:M15)+L28 -> 5048.37
A18: Payments
A19: rent | B19: 1400 | D19: 1400 | G19: 710 | I19: 710 | K19: 710
A20: Discover | B20: 1077.24 | C20: 1500 | D20: 1000 | E20: 2000 | F20: 2000 | G20: 1300 | H20: 2000 | I20: 1000 | J20: 2000 | K20: 1200 | L20: 1000 | M20: 1000
A21: Care Credit | B21: 0 | C21: 0 | D21: 0 | E21: 0 | F21: 0 | G21: 0 | H21: 0 | I21: 0 | J21: 0 | K21: 0 | L21: 0 | M21: 0
A22: Best Buy | C22: 554.09 | D22: 0 | E22: 0 | F22: 0 | G22: 0 | H22: 0 | I22: 0 | J22: 0 | K22: 0 | L22: 0 | M22: 0
A23: Amex | C23: 505.36 | D23: 0 | E23: 0 | F23: 0 | G23: 0 | H23: 0 | I23: 0 | J23: 0 | K23: 0 | L23: 0 | M23: 0
A24: Student Loan | G24: =$E$7 -> 348 | I24: =$E$7 -> 348 | K24: =$E$7 -> 348
A25: Vincent Debt | E25: =B8/5 -> 538.096 | F25: 538.096 | G25: 538.096 | H25: 538.096 | I25: 538.096
B26: =SUM(B19:B25) -> 2477.24 | C26: =SUM(C19:C25) -> 2559.45 | D26: =SUM(D19:D25) -> 2400 | E26: =SUM(E19:E25) -> 2538.096 | F26: =SUM(F19:F25) -> 2538.096 | G26: =SUM(G19:G25) -> 2896.096 | H26: =SUM(H19:H25) -> 2538.096 | I26: =SUM(I19:I25) -> 2596.096 | ... M26: =SUM(M19:M25) -> 1000
B28: =B16-B26 -> 510.51 | C28: =C16-C26 -> 433.95 | D28: =D16-D26 -> 516.84 | E28: =E16-E26 -> 461.634 | F28: =F16-F26 -> 406.428 | G28: =G16-G26 -> 543.222 | H28: =H16-H26 -> 488.016 | I28: =I16-I26 -> 374.81 | ... M28: =M16-M26 -> 4048.37
A30: Discover Balance Watch
A31: Starting Balance | B31: =B3 -> 6077.24 | C31: =B34 -> 6000 | D31: =C34 -> 5500 | E31: =D34 -> 5500 | F31: =E34 -> 4500 | G31: =F34 -> 3500 | H31: =G34 -> 3200 | I31: =H34 -> 2200 | J31: =I34 -> 2200 | ... M31: =L34 -> 1000
A32: After Payment | B32: =B31-B20 -> 5000 | C32: =C31-C20 -> 4500 | D32: =D31-D20 -> 4500 | E32: =E31-E20 -> 3500 | F32: =F31-F20 -> 2500 | G32: =G31-G20 -> 2200 | H32: =H31-H20 -> 1200 | I32: =I31-I20 -> 1200 | ... M32: =M31-M20 -> 0
A33: Est. Spending | B33: 1000 | C33: 1000 | D33: 1000 | E33: 1000 | F33: 1000 | G33: 1000 | H33: 1000 | I33: 1000 | J33: 1000 | K33: 1000 | L33: 1000 | M33: 1000
A34: Ending Balance | B34: =B32+B33 -> 6000 | C34: =C32+C33 -> 5500 | D34: =D32+D33 -> 5500 | E34: =E32+E33 -> 4500 | F34: =F32+F33 -> 3500 | G34: =G32+G33 -> 3200 | H34: =H32+H33 -> 2200 | I34: =I32+I33 -> 2200 | ... M34: =M32+M33 -> 1000

Sheet Category Summary
B2: All Accounts | C2: 01/2022 | D2: 02/2022 | E2: 03/2022 | F2: 04/2022 | G2: 05/2022 | H2: 06/2022 | I2: 07/2022 | J2: 08/2022 | K2: 09/2022 | L2: 10/2022 | M2: 11/2022 | N2: 12/2022 | O2: Total
B3: Food | C3: =SUMIFS(dis_table[Amount],dis_table[Category_2],'Category Summary'!$B3,dis_table[Date],'Category Summary'!C$2) +SUMIFS(cc_table[Amount],cc_table[Category_2],'Category Summary'!$B3,cc_table[Date],'Category Summary'!C$2) + SUMIFS(bb_table[Amount],bb_table[Category_2],'Category Summary'!$B3,bb_table[Date],'Category Summary'!C$2) + SUMIFS(Table5[Amount],Table5[Category_2],'Category Summary'!$B3,Table5[Date],'Category Summary'!C$2)+C18*-1 -> 587.29 | D3: =SUMIFS(dis_table[Amount],dis_table[Category_2],'Category Summary'!$B3,dis_table[Date],'Category Summary'!D$2) +SUMIFS(cc_table[Amount],cc_table[Category_2],'Category Summary'!$B3,cc_table[Date],'Category Summary'!D$2) + SUMIFS(bb_table[Amount],bb_table[Category_2],'Category Summary'!$B3,bb_table[Date],'Category Summary'!D$2) + SUMIFS(Table5[Amount],Table5[Category_2],'Category Summary'!$B3,Table5[Date],'Category Summary'!D$2)+D18*-1 -> 248.29 | E3: =SUMIFS(dis_table[Amount],dis_table[Category_2],'Category Summary'!$B3,dis_table[Date],'Category Summary'!E$2) +SUMIFS(cc_table[Amount],cc_table[Category_2],'Category Summary'!$B3,cc_table[Date],'Category Summary'!E$2) + SUMIFS(bb_table[Amount],bb_table[Category_2],'Category Summary'!$B3,bb_table[Date],'Category Summary'!E$2) + SUMIFS(Table5[Amount],Table5[Category_2],'Category Summary'!$B3,Table5[Date],'Category Summary'!E$2)+E18*-1 -> 1231.25 | F3: =SUMIFS(dis_table[Amount],dis_table[Category_2],'Category Summary'!$B3,dis_table[Date],'Category Summary'!F$2) +SUMIFS(cc_table[Amount],cc_table[Category_2],'Category Summary'!$B3,cc_table[Date],'Category Summary'!F$2) + SUMIFS(bb_table[Amount],bb_table[Category_2],'Category Summary'!$B3,bb_table[Date],'Category Summary'!F$2) + SUMIFS(Table5[Amount],Table5[Category_2],'Category Summary'!$B3,Table5[Date],'Category Summary'!F$2)+F18*-1 -> 945.31 | G3: =SUMIFS(dis_table[Amount],dis_table[Category_2],'Category Summary'!$B3,dis_table[Date],'Category Summary'!G$2) +SUMIFS(cc_table[Amount],cc_table[Category_2],'Category Summary'!$B3,cc_table[Date],'Category Summary'!G$2) + SUMIFS(bb_table[Amount],bb_table[Category_2],'Category Summary'!$B3,bb_table[Date],'Category Summary'!G$2) + SUMIFS(Table5[Amount],Table5[Category_2],'Category Summary'!$B3,Table5[Date],'Category Summary'!G$2)+G18*-1 -> 766.29 | H3: =SUMIFS(dis_table[Amount],dis_table[Category_2],'Category Summary'!$B3,dis_table[Date],'Category Summary'!H$2) +SUMIFS(cc_table[Amount],cc_table[Category_2],'Category Summary'!$B3,cc_table[Date],'Category Summary'!H$2) + SUMIFS(bb_table[Amount],bb_table[Category_2],'Category Summary'!$B3,bb_table[Date],'Category Summary'!H$2) + SUMIFS(Table5[Amount],Table5[Category_2],'Category Summary'!$B3,Table5[Date],'Category Summary'!H$2)+H18*-1 -> 945.77 | I3: =SUMIFS(dis_table[Amount],dis_table[Category_2],'Category Summary'!$B3,dis_table[Date],'Category Summary'!I$2) +SUMIFS(cc_table[Amount],cc_table[Category_2],'Category Summary'!$B3,cc_table[Date],'Category Summary'!I$2) + SUMIFS(bb_table[Amount],bb_table[Category_2],'Category Summary'!$B3,bb_table[Date],'Category Summary'!I$2) + SUMIFS(Table5[Amount],Table5[Category_2],'Category Summary'!$B3,Table5[Date],'Category Summary'!I$2)+I18*-1 -> 1137.425 | J3: =SUMIFS(dis_table[Amount],dis_table[Category_2],'Category Summary'!$B3,dis_table[Date],'Category Summary'!J$2) +SUMIFS(cc_table[Amount],cc_table[Category_2],'Category Summary'!$B3,cc_table[Date],'Category Summary'!J$2) + SUMIFS(bb_table[Amount],bb_table[Category_2],'Category Summary'!$B3,bb_table[Date],'Category Summary'!J$2) + SUMIFS(Table5[Amount],Table5[Category_2],'Category Summary'!$B3,Table5[Date],'Category Summary'!J$2)+J18*-1 -> 795.71 | ... M3: =SUMIFS(dis_table[Amount],dis_table[Category_2],'Category Summary'!$B3,dis_table[Date],'Category Summary'!M$2) +SUMIFS(cc_table[Amount],cc_table[Category_2],'Category Summary'!$B3,cc_table[Date],'Category Summary'!M$2) + SUMIFS(bb_table[Amount],bb_table[Category_2],'Category Summary'!$B3,bb_table[Date],'Category Summary'!M$2) + SUMIFS(Table5[Amount],Table5[Category_2],'Category Summary'!$B3,Table5[Date],'Category Summary'!M$2)+M18*-1 -> 649.85 | N3: =SUMIFS(dis_table[Category_2],dis_table[Amount],'Category Summary'!$B3,dis_table[Post Date],'Category Summary'!N$2) +SUMIFS(cc_table[Post Date],cc_table[Short_Desc],'Category Summary'!$B3,cc_table[Amount],'Category Summary'!N$2) + SUMIFS(bb_table[Category_2],bb_table[Short_Desc],'Category Summary'!$B3,bb_table[Category],'Category Summary'!N$2) + SUMIFS(Table5[Description],Table5[Split Amount],'Category Summary'!$B3,Table5[Individual Amount],'Category Summary'!N$2)+N18*-1 -> 0 | O3: =SUM(C3:N3) -> 8880.035 | P3: =O3/$O$27 -> 0.22643417
B4: Recreation_Entertainment | C4: =SUMIFS(dis_table[Amount],dis_table[Category_2],'Category Summary'!$B4,dis_table[Date],'Category Summary'!C$2) +SUMIFS(cc_table[Amount],cc_table[Category_2],'Category Summary'!$B4,cc_table[Date],'Category Summary'!C$2) + SUMIFS(bb_table[Amount],bb_table[Category_2],'Category Summary'!$B4,bb_table[Date],'Category Summary'!C$2) + SUMIFS(Table5[Amount],Table5[Category_2],'Category Summary'!$B4,Table5[Date],'Category Summary'!C$2)+C19*-1 -> 849.09 | D4: =SUMIFS(dis_table[Amount],dis_table[Category_2],'Category Summary'!$B4,dis_table[Date],'Category Summary'!D$2) +SUMIFS(cc_table[Amount],cc_table[Category_2],'Category Summary'!$B4,cc_table[Date],'Category Summary'!D$2) + SUMIFS(bb_table[Amount],bb_table[Category_2],'Category Summary'!$B4,bb_table[Date],'Category Summary'!D$2) + SUMIFS(Table5[Amount],Table5[Category_2],'Category Summary'!$B4,Table5[Date],'Category Summary'!D$2)+D19*-1 -> 528.66 | E4: =SUMIFS(dis_table[Amount],dis_table[Category_2],'Category Summary'!$B4,dis_table[Date],'Category Summary'!E$2) +SUMIFS(cc_table[Amount],cc_table[Category_2],'Category Summary'!$B4,cc_table[Date],'Category Summary'!E$2) + SUMIFS(bb_table[Amount],bb_table[Category_2],'Category Summary'!$B4,bb_table[Date],'Category Summary'!E$2) + SUMIFS(Table5[Amount],Table5[Category_2],'Category Summary'!$B4,Table5[Date],'Category Summary'!E$2)+E19*-1 -> 887.47 | F4: =SUMIFS(dis_table[Amount],dis_table[Category_2],'Category Summary'!$B4,dis_table[Date],'Category Summary'!F$2) +SUMIFS(cc_table[Amount],cc_table[Category_2],'Category Summary'!$B4,cc_table[Date],'Category Summary'!F$2) + SUMIFS(bb_table[Amount],bb_table[Category_2],'Category Summary'!$B4,bb_table[Date],'Category Summary'!F$2) + SUMIFS(Table5[Amount],Table5[Category_2],'Category Summary'!$B4,Table5[Date],'Category Summary'!F$2)+F19*-1 -> 695.02 | G4: =SUMIFS(dis_table[Amount],dis_table[Category_2],'Category Summary'!$B4,dis_table[Date],'Category Summary'!G$2) +SUMIFS(cc_table[Amount],cc_table[Category_2],'Category Summary'!$B4,cc_table[Date],'Category Summary'!G$2) + SUMIFS(bb_table[Amount],bb_table[Category_2],'Category Summary'!$B4,bb_table[Date],'Category Summary'!G$2) + SUMIFS(Table5[Amount],Table5[Category_2],'Category Summary'!$B4,Table5[Date],'Category Summary'!G$2)+G19*-1 -> 2111.44 | H4: =SUMIFS(dis_table[Amount],dis_table[Category_2],'Category Summary'!$B4,dis_table[Date],'Category Summary'!H$2) +SUMIFS(cc_table[Amount],cc_table[Category_2],'Category Summary'!$B4,cc_table[Date],'Category Summary'!H$2) + SUMIFS(bb_table[Amount],bb_table[Category_2],'Category Summary'!$B4,bb_table[Date],'Category Summary'!H$2) + SUMIFS(Table5[Amount],Table5[Category_2],'Category Summary'!$B4,Table5[Date],'Category Summary'!H$2)+H19*-1 -> 2665.935 | I4: =SUMIFS(dis_table[Amount],dis_table[Category_2],'Category Summary'!$B4,dis_table[Date],'Category Summary'!I$2) +SUMIFS(cc_table[Amount],cc_table[Category_2],'Category Summary'!$B4,cc_table[Date],'Category Summary'!I$2) + SUMIFS(bb_table[Amount],bb_table[Category_2],'Category Summary'!$B4,bb_table[Date],'Category Summary'!I$2) + SUMIFS(Table5[Amount],Table5[Category_2],'Category Summary'!$B4,Table5[Date],'Category Summary'!I$2)+I19*-1 -> 879.96 | J4: =SUMIFS(dis_table[Amount],dis_table[Category_2],'Category Summary'!$B4,dis_table[Date],'Category Summary'!J$2) +SUMIFS(cc_table[Amount],cc_table[Category_2],'Category Summary'!$B4,cc_table[Date],'Category Summary'!J$2) + SUMIFS(bb_table[Amount],bb_table[Category_2],'Category Summary'!$B4,bb_table[Date],'Category Summary'!J$2) + SUMIFS(Table5[Amount],Table5[Category_2],'Category Summary'!$B4,Table5[Date],'Category Summary'!J$2)+J19*-1 -> 91.71 | ... M4: =SUMIFS(dis_table[Amount],dis_table[Category_2],'Category Summary'!$B4,dis_table[Date],'Category Summary'!M$2) +SUMIFS(cc_table[Amount],cc_table[Category_2],'Category Summary'!$B4,cc_table[Date],'Category Summary'!M$2) + SUMIFS(bb_table[Amount],bb_table[Category_2],'Category Summary'!$B4,bb_table[Date],'Category Summary'!M$2) + SUMIFS(Table5[Amount],Table5[Category_2],'Category Summary'!$B4,Table5[Date],'Category Summary'!M$2)+M19*-1 -> 205.88 | N4: =SUMIFS(dis_table[Category_2],dis_table[Amount],'Category Summary'!$B4,dis_table[Post Date],'Category Summary'!N$2) +SUMIFS(cc_table[Post Date],cc_table[Short_Desc],'Category Summary'!$B4,cc_table[Amount],'Category Summary'!N$2) + SUMIFS(bb_table[Category_2],bb_table[Short_Desc],'Category Summary'!$B4,bb_table[Category],'Category Summary'!N$2) + SUMIFS(Table5[Description],Table5[Split Amount],'Category Summary'!$B4,Table5[Individual Amount],'Category Summary'!N$2)+N19*-1 -> 0 | O4: =SUM(C4:N4) -> 10122.405 | P4: =O4/$O$27 -> 0.25811367
B5: Personal_Spending | C5: =SUMIFS(dis_table[Amount],dis_table[Category_2],'Category Summary'!$B5,dis_table[Date],'Category Summary'!C$2) +SUMIFS(cc_table[Amount],cc_table[Category_2],'Category Summary'!$B5,cc_table[Date],'Category Summary'!C$2) + SUMIFS(bb_table[Amount],bb_table[Category_2],'Category Summary'!$B5,bb_table[Date],'Category Summary'!C$2) + SUMIFS(Table5[Amount],Table5[Category_2],'Category Summary'!$B5,Table5[Date],'Category Summary'!C$2)+C20*-1 -> 962.44 | D5: =SUMIFS(dis_table[Amount],dis_table[Category_2],'Category Summary'!$B5,dis_table[Date],'Category Summary'!D$2) +SUMIFS(cc_table[Amount],cc_table[Category_2],'Category Summary'!$B5,cc_table[Date],'Category Summary'!D$2) + SUMIFS(bb_table[Amount],bb_table[Category_2],'Category Summary'!$B5,bb_table[Date],'Category Summary'!D$2) + SUMIFS(Table5[Amount],Table5[Category_2],'Category Summary'!$B5,Table5[Date],'Category Summary'!D$2)+D20*-1 -> 360.01 | E5: =SUMIFS(dis_table[Amount],dis_table[Category_2],'Category Summary'!$B5,dis_table[Date],'Category Summary'!E$2) +SUMIFS(cc_table[Amount],cc_table[Category_2],'Category Summary'!$B5,cc_table[Date],'Category Summary'!E$2) + SUMIFS(bb_table[Amount],bb_table[Category_2],'Category Summary'!$B5,bb_table[Date],'Category Summary'!E$2) + SUMIFS(Table5[Amount],Table5[Category_2],'Category Summary'!$B5,Table5[Date],'Category Summary'!E$2)+E20*-1 -> 748.11 | F5: =SUMIFS(dis_table[Amount],dis_table[Category_2],'Category Summary'!$B5,dis_table[Date],'Category Summary'!F$2) +SUMIFS(cc_table[Amount],cc_table[Category_2],'Category Summary'!$B5,cc_table[Date],'Category Summary'!F$2) + SUMIFS(bb_table[Amount],bb_table[Category_2],'Category Summary'!$B5,bb_table[Date],'Category Summary'!F$2) + SUMIFS(Table5[Amount],Table5[Category_2],'Category Summary'!$B5,Table5[Date],'Category Summary'!F$2)+F20*-1 -> 463.83 | G5: =SUMIFS(dis_table[Amount],dis_table[Category_2],'Category Summary'!$B5,dis_table[Date],'Category Summary'!G$2) +SUMIFS(cc_table[Amount],cc_table[Category_2],'Category Summary'!$B5,cc_table[Date],'Category Summary'!G$2) + SUMIFS(bb_table[Amount],bb_table[Category_2],'Category Summary'!$B5,bb_table[Date],'Category Summary'!G$2) + SUMIFS(Table5[Amount],Table5[Category_2],'Category Summary'!$B5,Table5[Date],'Category Summary'!G$2)+G20*-1 -> 1469.11 | H5: =SUMIFS(dis_table[Amount],dis_table[Category_2],'Category Summary'!$B5,dis_table[Date],'Category Summary'!H$2) +SUMIFS(cc_table[Amount],cc_table[Category_2],'Category Summary'!$B5,cc_table[Date],'Category Summary'!H$2) + SUMIFS(bb_table[Amount],bb_table[Category_2],'Category Summary'!$B5,bb_table[Date],'Category Summary'!H$2) + SUMIFS(Table5[Amount],Table5[Category_2],'Category Summary'!$B5,Table5[Date],'Category Summary'!H$2)+H20*-1 -> 1447.685 | I5: =SUMIFS(dis_table[Amount],dis_table[Category_2],'Category Summary'!$B5,dis_table[Date],'Category Summary'!I$2) +SUMIFS(cc_table[Amount],cc_table[Category_2],'Category Summary'!$B5,cc_table[Date],'Category Summary'!I$2) + SUMIFS(bb_table[Amount],bb_table[Category_2],'Category Summary'!$B5,bb_table[Date],'Category Summary'!I$2) + SUMIFS(Table5[Amount],Table5[Category_2],'Category Summary'!$B5,Table5[Date],'Category Summary'!I$2)+I20*-1 -> 660.28 | J5: =SUMIFS(dis_table[Amount],dis_table[Category_2],'Category Summary'!$B5,dis_table[Date],'Category Summary'!J$2) +SUMIFS(cc_table[Amount],cc_table[Category_2],'Category Summary'!$B5,cc_table[Date],'Category Summary'!J$2) + SUMIFS(bb_table[Amount],bb_table[Category_2],'Category Summary'!$B5,bb_table[Date],'Category Summary'!J$2) + SUMIFS(Table5[Amount],Table5[Category_2],'Category Summary'!$B5,Table5[Date],'Category Summary'!J$2)+J20*-1 -> 516.82 | ... M5: =SUMIFS(dis_table[Amount],dis_table[Category_2],'Category Summary'!$B5,dis_table[Date],'Category Summary'!M$2) +SUMIFS(cc_table[Amount],cc_table[Category_2],'Category Summary'!$B5,cc_table[Date],'Category Summary'!M$2) + SUMIFS(bb_table[Amount],bb_table[Category_2],'Category Summary'!$B5,bb_table[Date],'Category Summary'!M$2) + SUMIFS(Table5[Amount],Table5[Category_2],'Category Summary'!$B5,Table5[Date],'Category Summary'!M$2)+M20*-1 -> 465.36 | N5: =SUMIFS(dis_table[Category_2],dis_table[Amount],'Category Summary'!$B5,dis_table[Post Date],'Category Summary'!N$2) +SUMIFS(cc_table[Post Date],cc_table[Short_Desc],'Category Summary'!$B5,cc_table[Amount],'Category Summary'!N$2) + SUMIFS(bb_table[Category_2],bb_table[Short_Desc],'Category Summary'!$B5,bb_table[Category],'Category Summary'!N$2) + SUMIFS(Table5[Description],Table5[Split Amount],'Category Summary'!$B5,Table5[Individual Amount],'Category Summary'!N$2)+N20*-1 -> 0 | O5: =SUM(C5:N5) -> 8236.735 | P5: =O5/$O$27 -> 0.21003051
B6: Transportation | C6: =SUMIFS(dis_table[Amount],dis_table[Category_2],'Category Summary'!$B6,dis_table[Date],'Category Summary'!C$2) +SUMIFS(cc_table[Amount],cc_table[Category_2],'Category Summary'!$B6,cc_table[Date],'Category Summary'!C$2) + SUMIFS(bb_table[Amount],bb_table[Category_2],'Category Summary'!$B6,bb_table[Date],'Category Summary'!C$2) + SUMIFS(Table5[Amount],Table5[Category_2],'Category Summary'!$B6,Table5[Date],'Category Summary'!C$2)+C21*-1 -> 145.57 | D6: =SUMIFS(dis_table[Amount],dis_table[Category_2],'Category Summary'!$B6,dis_table[Date],'Category Summary'!D$2) +SUMIFS(cc_table[Amount],cc_table[Category_2],'Category Summary'!$B6,cc_table[Date],'Category Summary'!D$2) + SUMIFS(bb_table[Amount],bb_table[Category_2],'Category Summary'!$B6,bb_table[Date],'Category Summary'!D$2) + SUMIFS(Table5[Amount],Table5[Category_2],'Category Summary'!$B6,Table5[Date],'Category Summary'!D$2)+D21*-1 -> 333.19 | E6: =SUMIFS(dis_table[Amount],dis_table[Category_2],'Category Summary'!$B6,dis_table[Date],'Category Summary'!E$2) +SUMIFS(cc_table[Amount],cc_table[Category_2],'Category Summary'!$B6,cc_table[Date],'Category Summary'!E$2) + SUMIFS(bb_table[Amount],bb_table[Category_2],'Category Summary'!$B6,bb_table[Date],'Category Summary'!E$2) + SUMIFS(Table5[Amount],Table5[Category_2],'Category Summary'!$B6,Table5[Date],'Category Summary'!E$2)+E21*-1 -> 307.96 | F6: =SUMIFS(dis_table[Amount],dis_table[Category_2],'Category Summary'!$B6,dis_table[Date],'Category Summary'!F$2) +SUMIFS(cc_table[Amount],cc_table[Category_2],'Category Summary'!$B6,cc_table[Date],'Category Summary'!F$2) + SUMIFS(bb_table[Amount],bb_table[Category_2],'Category Summary'!$B6,bb_table[Date],'Category Summary'!F$2) + SUMIFS(Table5[Amount],Table5[Category_2],'Category Summary'!$B6,Table5[Date],'Category Summary'!F$2)+F21*-1 -> 316.07 | G6: =SUMIFS(dis_table[Amount],dis_table[Category_2],'Category Summary'!$B6,dis_table[Date],'Category Summary'!G$2) +SUMIFS(cc_table[Amount],cc_table[Category_2],'Category Summary'!$B6,cc_table[Date],'Category Summary'!G$2) + SUMIFS(bb_table[Amount],bb_table[Category_2],'Category Summary'!$B6,bb_table[Date],'Category Summary'!G$2) + SUMIFS(Table5[Amount],Table5[Category_2],'Category Summary'!$B6,Table5[Date],'Category Summary'!G$2)+G21*-1 -> 682.91 | H6: =SUMIFS(dis_table[Amount],dis_table[Category_2],'Category Summary'!$B6,dis_table[Date],'Category Summary'!H$2) +SUMIFS(cc_table[Amount],cc_table[Category_2],'Category Summary'!$B6,cc_table[Date],'Category Summary'!H$2) + SUMIFS(bb_table[Amount],bb_table[Category_2],'Category Summary'!$B6,bb_table[Date],'Category Summary'!H$2) + SUMIFS(Table5[Amount],Table5[Category_2],'Category Summary'!$B6,Table5[Date],'Category Summary'!H$2)+H21*-1 -> 511.855 | I6: =SUMIFS(dis_table[Amount],dis_table[Category_2],'Category Summary'!$B6,dis_table[Date],'Category Summary'!I$2) +SUMIFS(cc_table[Amount],cc_table[Category_2],'Category Summary'!$B6,cc_table[Date],'Category Summary'!I$2) + SUMIFS(bb_table[Amount],bb_table[Category_2],'Category Summary'!$B6,bb_table[Date],'Category Summary'!I$2) + SUMIFS(Table5[Amount],Table5[Category_2],'Category Summary'!$B6,Table5[Date],'Category Summary'!I$2)+I21*-1 -> 869.13 | J6: =SUMIFS(dis_table[Amount],dis_table[Category_2],'Category Summary'!$B6,dis_table[Date],'Category Summary'!J$2) +SUMIFS(cc_table[Amount],cc_table[Category_2],'Category Summary'!$B6,cc_table[Date],'Category Summary'!J$2) + SUMIFS(bb_table[Amount],bb_table[Category_2],'Category Summary'!$B6,bb_table[Date],'Category Summary'!J$2) + SUMIFS(Table5[Amount],Table5[Category_2],'Category Summary'!$B6,Table5[Date],'Category Summary'!J$2)+J21*-1 -> 32.04 | ... M6: =SUMIFS(dis_table[Amount],dis_table[Category_2],'Category Summary'!$B6,dis_table[Date],'Category Summary'!M$2) +SUMIFS(cc_table[Amount],cc_table[Category_2],'Category Summary'!$B6,cc_table[Date],'Category Summary'!M$2) + SUMIFS(bb_table[Amount],bb_table[Category_2],'Category Summary'!$B6,bb_table[Date],'Category Summary'!M$2) + SUMIFS(Table5[Amount],Table5[Category_2],'Category Summary'!$B6,Table5[Date],'Category Summary'!M$2)+M21*-1 -> 67.9 | N6: =SUMIFS(dis_table[Category_2],dis_table[Amount],'Category Summary'!$B6,dis_table[Post Date],'Category Summary'!N$2) +SUMIFS(cc_table[Post Date],cc_table[Short_Desc],'Category Summary'!$B6,cc_table[Amount],'Category Summary'!N$2) + SUMIFS(bb_table[Category_2],bb_table[Short_Desc],'Category Summary'!$B6,bb_table[Category],'Category Summary'!N$2) + SUMIFS(Table5[Description],Table5[Split Amount],'Category Summary'!$B6,Table5[Individual Amount],'Category Summary'!N$2)+N21*-1 -> 0 | O6: =SUM(C6:N6) -> 4216.455 | P6: =O6/$O$27 -> 0.10751641
B7: Misc | C7: =SUMIFS(dis_table[Amount],dis_table[Category_2],'Category Summary'!$B7,dis_table[Date],'Category Summary'!C$2) +SUMIFS(cc_table[Amount],cc_table[Category_2],'Category Summary'!$B7,cc_table[Date],'Category Summary'!C$2) + SUMIFS(bb_table[Amount],bb_table[Category_2],'Category Summary'!$B7,bb_table[Date],'Category Summary'!C$2) + SUMIFS(Table5[Amount],Table5[Category_2],'Category Summary'!$B7,Table5[Date],'Category Summary'!C$2)+C22*-1 -> 36.49 | D7: =SUMIFS(dis_table[Amount],dis_table[Category_2],'Category Summary'!$B7,dis_table[Date],'Category Summary'!D$2) +SUMIFS(cc_table[Amount],cc_table[Category_2],'Category Summary'!$B7,cc_table[Date],'Category Summary'!D$2) + SUMIFS(bb_table[Amount],bb_table[Category_2],'Category Summary'!$B7,bb_table[Date],'Category Summary'!D$2) + SUMIFS(Table5[Amount],Table5[Category_2],'Category Summary'!$B7,Table5[Date],'Category Summary'!D$2)+D22*-1 -> 0 | E7: =SUMIFS(dis_table[Amount],dis_table[Category_2],'Category Summary'!$B7,dis_table[Date],'Category Summary'!E$2) +SUMIFS(cc_table[Amount],cc_table[Category_2],'Category Summary'!$B7,cc_table[Date],'Category Summary'!E$2) + SUMIFS(bb_table[Amount],bb_table[Category_2],'Category Summary'!$B7,bb_table[Date],'Category Summary'!E$2) + SUMIFS(Table5[Amount],Table5[Category_2],'Category Summary'!$B7,Table5[Date],'Category Summary'!E$2)+E22*-1 -> 0 | F7: =SUMIFS(dis_table[Amount],dis_table[Category_2],'Category Summary'!$B7,dis_table[Date],'Category Summary'!F$2) +SUMIFS(cc_table[Amount],cc_table[Category_2],'Category Summary'!$B7,cc_table[Date],'Category Summary'!F$2) + SUMIFS(bb_table[Amount],bb_table[Category_2],'Category Summary'!$B7,bb_table[Date],'Category Summary'!F$2) + SUMIFS(Table5[Amount],Table5[Category_2],'Category Summary'!$B7,Table5[Date],'Category Summary'!F$2)+F22*-1 -> 16 | G7: =SUMIFS(dis_table[Amount],dis_table[Category_2],'Category Summary'!$B7,dis_table[Date],'Category Summary'!G$2) +SUMIFS(cc_table[Amount],cc_table[Category_2],'Category Summary'!$B7,cc_table[Date],'Category Summary'!G$2) + SUMIFS(bb_table[Amount],bb_table[Category_2],'Category Summary'!$B7,bb_table[Date],'Category Summary'!G$2) + SUMIFS(Table5[Amount],Table5[Category_2],'Category Summary'!$B7,Table5[Date],'Category Summary'!G$2)+G22*-1 -> 9.75 | H7: =SUMIFS(dis_table[Amount],dis_table[Category_2],'Category Summary'!$B7,dis_table[Date],'Category Summary'!H$2) +SUMIFS(cc_table[Amount],cc_table[Category_2],'Category Summary'!$B7,cc_table[Date],'Category Summary'!H$2) + SUMIFS(bb_table[Amount],bb_table[Category_2],'Category Summary'!$B7,bb_table[Date],'Category Summary'!H$2) + SUMIFS(Table5[Amount],Table5[Category_2],'Category Summary'!$B7,Table5[Date],'Category Summary'!H$2)+H22*-1 -> 83 | I7: =SUMIFS(dis_table[Amount],dis_table[Category_2],'Category Summary'!$B7,dis_table[Date],'Category Summary'!I$2) +SUMIFS(cc_table[Amount],cc_table[Category_2],'Category Summary'!$B7,cc_table[Date],'Category Summary'!I$2) + SUMIFS(bb_table[Amount],bb_table[Category_2],'Category Summary'!$B7,bb_table[Date],'Category Summary'!I$2) + SUMIFS(Table5[Amount],Table5[Category_2],'Category Summary'!$B7,Table5[Date],'Category Summary'!I$2)+I22*-1 -> 5.1 | J7: =SUMIFS(dis_table[Amount],dis_table[Category_2],'Category Summary'!$B7,dis_table[Date],'Category Summary'!J$2) +SUMIFS(cc_table[Amount],cc_table[Category_2],'Category Summary'!$B7,cc_table[Date],'Category Summary'!J$2) + SUMIFS(bb_table[Amount],bb_table[Category_2],'Category Summary'!$B7,bb_table[Date],'Category Summary'!J$2) + SUMIFS(Table5[Amount],Table5[Category_2],'Category Summary'!$B7,Table5[Date],'Category Summary'!J$2)+J22*-1 -> 39.79 | ... M7: =SUMIFS(dis_table[Amount],dis_table[Category_2],'Category Summary'!$B7,dis_table[Date],'Category Summary'!M$2) +SUMIFS(cc_table[Amount],cc_table[Category_2],'Category Summary'!$B7,cc_table[Date],'Category Summary'!M$2) + SUMIFS(bb_table[Amount],bb_table[Category_2],'Category Summary'!$B7,bb_table[Date],'Category Summary'!M$2) + SUMIFS(Table5[Amount],Table5[Category_2],'Category Summary'!$B7,Table5[Date],'Category Summary'!M$2)+M22*-1 -> 51.11 | N7: =SUMIFS(dis_table[Category_2],dis_table[Amount],'Category Summary'!$B7,dis_table[Post Date],'Category Summary'!N$2) +SUMIFS(cc_table[Post Date],cc_table[Short_Desc],'Category Summary'!$B7,cc_table[Amount],'Category Summary'!N$2) + SUMIFS(bb_table[Category_2],bb_table[Short_Desc],'Category Summary'!$B7,bb_table[Category],'Category Summary'!N$2) + SUMIFS(Table5[Description],Table5[Split Amount],'Category Summary'!$B7,Table5[Individual Amount],'Category Summary'!N$2)+N22*-1 -> 0 | O7: =SUM(C7:N7) -> 1444.69 | P7: =O7/$O$27 -> 0.036838502
B8: Utilities | C8: =SUMIFS(dis_table[Amount],dis_table[Category_2],'Category Summary'!$B8,dis_table[Date],'Category Summary'!C$2) +SUMIFS(cc_table[Amount],cc_table[Category_2],'Category Summary'!$B8,cc_table[Date],'Category Summary'!C$2) + SUMIFS(bb_table[Amount],bb_table[Category_2],'Category Summary'!$B8,bb_table[Date],'Category Summary'!C$2) + SUMIFS(Table5[Amount],Table5[Category_2],'Category Summary'!$B8,Table5[Date],'Category Summary'!C$2)+C23*-1 -> 29.32 | D8: =SUMIFS(dis_table[Amount],dis_table[Category_2],'Category Summary'!$B8,dis_table[Date],'Category Summary'!D$2) +SUMIFS(cc_table[Amount],cc_table[Category_2],'Category Summary'!$B8,cc_table[Date],'Category Summary'!D$2) + SUMIFS(bb_table[Amount],bb_table[Category_2],'Category Summary'!$B8,bb_table[Date],'Category Summary'!D$2) + SUMIFS(Table5[Amount],Table5[Category_2],'Category Summary'!$B8,Table5[Date],'Category Summary'!D$2)+D23*-1 -> 207.17 | E8: =SUMIFS(dis_table[Amount],dis_table[Category_2],'Category Summary'!$B8,dis_table[Date],'Category Summary'!E$2) +SUMIFS(cc_table[Amount],cc_table[Category_2],'Category Summary'!$B8,cc_table[Date],'Category Summary'!E$2) + SUMIFS(bb_table[Amount],bb_table[Category_2],'Category Summary'!$B8,bb_table[Date],'Category Summary'!E$2) + SUMIFS(Table5[Amount],Table5[Category_2],'Category Summary'!$B8,Table5[Date],'Category Summary'!E$2)+E23*-1 -> 299.5 | F8: =SUMIFS(dis_table[Amount],dis_table[Category_2],'Category Summary'!$B8,dis_table[Date],'Category Summary'!F$2) +SUMIFS(cc_table[Amount],cc_table[Category_2],'Category Summary'!$B8,cc_table[Date],'Category Summary'!F$2) + SUMIFS(bb_table[Amount],bb_table[Category_2],'Category Summary'!$B8,bb_table[Date],'Category Summary'!F$2) + SUMIFS(Table5[Amount],Table5[Category_2],'Category Summary'!$B8,Table5[Date],'Category Summary'!F$2)+F23*-1 -> 267.97 | G8: =SUMIFS(dis_table[Amount],dis_table[Category_2],'Category Summary'!$B8,dis_table[Date],'Category Summary'!G$2) +SUMIFS(cc_table[Amount],cc_table[Category_2],'Category Summary'!$B8,cc_table[Date],'Category Summary'!G$2) + SUMIFS(bb_table[Amount],bb_table[Category_2],'Category Summary'!$B8,bb_table[Date],'Category Summary'!G$2) + SUMIFS(Table5[Amount],Table5[Category_2],'Category Summary'!$B8,Table5[Date],'Category Summary'!G$2)+G23*-1 -> 263.04 | H8: =SUMIFS(dis_table[Amount],dis_table[Category_2],'Category Summary'!$B8,dis_table[Date],'Category Summary'!H$2) +SUMIFS(cc_table[Amount],cc_table[Category_2],'Category Summary'!$B8,cc_table[Date],'Category Summary'!H$2) + SUMIFS(bb_table[Amount],bb_table[Category_2],'Category Summary'!$B8,bb_table[Date],'Category Summary'!H$2) + SUMIFS(Table5[Amount],Table5[Category_2],'Category Summary'!$B8,Table5[Date],'Category Summary'!H$2)+H23*-1 -> 341.77 | I8: =SUMIFS(dis_table[Amount],dis_table[Category_2],'Category Summary'!$B8,dis_table[Date],'Category Summary'!I$2) +SUMIFS(cc_table[Amount],cc_table[Category_2],'Category Summary'!$B8,cc_table[Date],'Category Summary'!I$2) + SUMIFS(bb_table[Amount],bb_table[Category_2],'Category Summary'!$B8,bb_table[Date],'Category Summary'!I$2) + SUMIFS(Table5[Amount],Table5[Category_2],'Category Summary'!$B8,Table5[Date],'Category Summary'!I$2)+I23*-1 -> 293.46 | J8: =SUMIFS(dis_table[Amount],dis_table[Category_2],'Category Summary'!$B8,dis_table[Date],'Category Summary'!J$2) +SUMIFS(cc_table[Amount],cc_table[Category_2],'Category Summary'!$B8,cc_table[Date],'Category Summary'!J$2) + SUMIFS(bb_table[Amount],bb_table[Category_2],'Category Summary'!$B8,bb_table[Date],'Category Summary'!J$2) + SUMIFS(Table5[Amount],Table5[Category_2],'Category Summary'!$B8,Table5[Date],'Category Summary'!J$2)+J23*-1 -> 200.33 | ... M8: =SUMIFS(dis_table[Amount],dis_table[Category_2],'Category Summary'!$B8,dis_table[Date],'Category Summary'!M$2) +SUMIFS(cc_table[Amount],cc_table[Category_2],'Category Summary'!$B8,cc_table[Date],'Category Summary'!M$2) + SUMIFS(bb_table[Amount],bb_table[Category_2],'Category Summary'!$B8,bb_table[Date],'Category Summary'!M$2) + SUMIFS(Table5[Amount],Table5[Category_2],'Category Summary'!$B8,Table5[Date],'Category Summary'!M$2)+M23*-1 -> 161.6 | N8: =SUMIFS(dis_table[Category_2],dis_table[Amount],'Category Summary'!$B8,dis_table[Post Date],'Category Summary'!N$2) +SUMIFS(cc_table[Post Date],cc_table[Short_Desc],'Category Summary'!$B8,cc_table[Amount],'Category Summary'!N$2) + SUMIFS(bb_table[Category_2],bb_table[Short_Desc],'Category Summary'!$B8,bb_table[Category],'Category Summary'!N$2) + SUMIFS(Table5[Description],Table5[Split Amount],'Category Summary'!$B8,Table5[Individual Amount],'Category Summary'!N$2)+N23*-1 -> 0 | O8: =SUM(C8:N8) -> 2572.79 | P8: =O8/$O$27 -> 0.065604198
B9: Insurance | C9: =SUMIFS(dis_table[Amount],dis_table[Category_2],'Category Summary'!$B9,dis_table[Date],'Category Summary'!C$2) +SUMIFS(cc_table[Amount],cc_table[Category_2],'Category Summary'!$B9,cc_table[Date],'Category Summary'!C$2) + SUMIFS(bb_table[Amount],bb_table[Category_2],'Category Summary'!$B9,bb_table[Date],'Category Summary'!C$2) + SUMIFS(Table5[Amount],Table5[Category_2],'Category Summary'!$B9,Table5[Date],'Category Summary'!C$2) -> 79.38 | D9: =SUMIFS(dis_table[Amount],dis_table[Category_2],'Category Summary'!$B9,dis_table[Date],'Category Summary'!D$2) +SUMIFS(cc_table[Amount],cc_table[Category_2],'Category Summary'!$B9,cc_table[Date],'Category Summary'!D$2) + SUMIFS(bb_table[Amount],bb_table[Category_2],'Category Summary'!$B9,bb_table[Date],'Category Summary'!D$2) + SUMIFS(Table5[Amount],Table5[Category_2],'Category Summary'!$B9,Table5[Date],'Category Summary'!D$2) -> 79.38 | E9: =SUMIFS(dis_table[Amount],dis_table[Category_2],'Category Summary'!$B9,dis_table[Date],'Category Summary'!E$2) +SUMIFS(cc_table[Amount],cc_table[Category_2],'Category Summary'!$B9,cc_table[Date],'Category Summary'!E$2) + SUMIFS(bb_table[Amount],bb_table[Category_2],'Category Summary'!$B9,bb_table[Date],'Category Summary'!E$2) + SUMIFS(Table5[Amount],Table5[Category_2],'Category Summary'!$B9,Table5[Date],'Category Summary'!E$2) -> 79.38 | F9: =SUMIFS(dis_table[Amount],dis_table[Category_2],'Category Summary'!$B9,dis_table[Date],'Category Summary'!F$2) +SUMIFS(cc_table[Amount],cc_table[Category_2],'Category Summary'!$B9,cc_table[Date],'Category Summary'!F$2) + SUMIFS(bb_table[Amount],bb_table[Category_2],'Category Summary'!$B9,bb_table[Date],'Category Summary'!F$2) + SUMIFS(Table5[Amount],Table5[Category_2],'Category Summary'!$B9,Table5[Date],'Category Summary'!F$2) -> 79.38 | G9: =SUMIFS(dis_table[Amount],dis_table[Category_2],'Category Summary'!$B9,dis_table[Date],'Category Summary'!G$2) +SUMIFS(cc_table[Amount],cc_table[Category_2],'Category Summary'!$B9,cc_table[Date],'Category Summary'!G$2) + SUMIFS(bb_table[Amount],bb_table[Category_2],'Category Summary'!$B9,bb_table[Date],'Category Summary'!G$2) + SUMIFS(Table5[Amount],Table5[Category_2],'Category Summary'!$B9,Table5[Date],'Category Summary'!G$2) -> 79.38 | H9: =SUMIFS(dis_table[Amount],dis_table[Category_2],'Category Summary'!$B9,dis_table[Date],'Category Summary'!H$2) +SUMIFS(cc_table[Amount],cc_table[Category_2],'Category Summary'!$B9,cc_table[Date],'Category Summary'!H$2) + SUMIFS(bb_table[Amount],bb_table[Category_2],'Category Summary'!$B9,bb_table[Date],'Category Summary'!H$2) + SUMIFS(Table5[Amount],Table5[Category_2],'Category Summary'!$B9,Table5[Date],'Category Summary'!H$2) -> 79.38 | I9: =SUMIFS(dis_table[Amount],dis_table[Category_2],'Category Summary'!$B9,dis_table[Date],'Category Summary'!I$2) +SUMIFS(cc_table[Amount],cc_table[Category_2],'Category Summary'!$B9,cc_table[Date],'Category Summary'!I$2) + SUMIFS(bb_table[Amount],bb_table[Category_2],'Category Summary'!$B9,bb_table[Date],'Category Summary'!I$2) + SUMIFS(Table5[Amount],Table5[Category_2],'Category Summary'!$B9,Table5[Date],'Category Summary'!I$2) -> 79.66 | J9: =SUMIFS(dis_table[Amount],dis_table[Category_2],'Category Summary'!$B9,dis_table[Date],'Category Summary'!J$2) +SUMIFS(cc_table[Amount],cc_table[Category_2],'Category Summary'!$B9,cc_table[Date],'Category Summary'!J$2) + SUMIFS(bb_table[Amount],bb_table[Category_2],'Category Summary'!$B9,bb_table[Date],'Category Summary'!J$2) + SUMIFS(Table5[Amount],Table5[Category_2],'Category Summary'!$B9,Table5[Date],'Category Summary'!J$2)+J24*-1 -> 79.66 | K9: =SUMIFS(dis_table[Amount],dis_table[Category_2],'Category Summary'!$B9,dis_table[Date],'Category Summary'!K$2) +SUMIFS(cc_table[Amount],cc_table[Category_2],'Category Summary'!$B9,cc_table[Date],'Category Summary'!K$2) + SUMIFS(bb_table[Amount],bb_table[Category_2],'Category Summary'!$B9,bb_table[Date],'Category Summary'!K$2) + SUMIFS(Table5[Amount],Table5[Category_2],'Category Summary'!$B9,Table5[Date],'Category Summary'!K$2)+K24*-1 -> 80.08 | L9: =SUMIFS(dis_table[Amount],dis_table[Category_2],'Category Summary'!$B9,dis_table[Date],'Category Summary'!L$2) +SUMIFS(cc_table[Amount],cc_table[Category_2],'Category Summary'!$B9,cc_table[Date],'Category Summary'!L$2) + SUMIFS(bb_table[Amount],bb_table[Category_2],'Category Summary'!$B9,bb_table[Date],'Category Summary'!L$2) + SUMIFS(Table5[Amount],Table5[Category_2],'Category Summary'!$B9,Table5[Date],'Category Summary'!L$2)+L24*-1 -> 80.08 | M9: =SUMIFS(dis_table[Amount],dis_table[Category_2],'Category Summary'!$B9,dis_table[Date],'Category Summary'!M$2) +SUMIFS(cc_table[Amount],cc_table[Category_2],'Category Summary'!$B9,cc_table[Date],'Category Summary'!M$2) + SUMIFS(bb_table[Amount],bb_table[Category_2],'Category Summary'!$B9,bb_table[Date],'Category Summary'!M$2) + SUMIFS(Table5[Amount],Table5[Category_2],'Category Summary'!$B9,Table5[Date],'Category Summary'!M$2)+M24*-1 -> 80.08 | N9: =SUMIFS(dis_table[Category_2],dis_table[Amount],'Category Summary'!$B9,dis_table[Post Date],'Category Summary'!N$2) +SUMIFS(cc_table[Post Date],cc_table[Short_Desc],'Category Summary'!$B9,cc_table[Amount],'Category Summary'!N$2) + SUMIFS(bb_table[Category_2],bb_table[Short_Desc],'Category Summary'!$B9,bb_table[Category],'Category Summary'!N$2) + SUMIFS(Table5[Description],Table5[Split Amount],'Category Summary'!$B9,Table5[Individual Amount],'Category Summary'!N$2) -> 0 | O9: =SUM(C9:N9) -> 875.84 | P9: =O9/$O$27 -> 0.022333257
B10: People | C10: =SUMIFS(dis_table[Amount],dis_table[Category_2],'Category Summary'!$B10,dis_table[Date],'Category Summary'!C$2) +SUMIFS(cc_table[Amount],cc_table[Category_2],'Category Summary'!$B10,cc_table[Date],'Category Summary'!C$2) + SUMIFS(bb_table[Amount],bb_table[Category_2],'Category Summary'!$B10,bb_table[Date],'Category Summary'!C$2) + SUMIFS(Table5[Amount],Table5[Category_2],'Category Summary'!$B10,Table5[Date],'Category Summary'!C$2)+C24*-1 -> 256.76 | D10: =SUMIFS(dis_table[Amount],dis_table[Category_2],'Category Summary'!$B10,dis_table[Date],'Category Summary'!D$2) +SUMIFS(cc_table[Amount],cc_table[Category_2],'Category Summary'!$B10,cc_table[Date],'Category Summary'!D$2) + SUMIFS(bb_table[Amount],bb_table[Category_2],'Category Summary'!$B10,bb_table[Date],'Category Summary'!D$2) + SUMIFS(Table5[Amount],Table5[Category_2],'Category Summary'!$B10,Table5[Date],'Category Summary'!D$2)+D24*-1 -> 2289.31 | E10: =SUMIFS(dis_table[Amount],dis_table[Category_2],'Category Summary'!$B10,dis_table[Date],'Category Summary'!E$2) +SUMIFS(cc_table[Amount],cc_table[Category_2],'Category Summary'!$B10,cc_table[Date],'Category Summary'!E$2) + SUMIFS(bb_table[Amount],bb_table[Category_2],'Category Summary'!$B10,bb_table[Date],'Category Summary'!E$2) + SUMIFS(Table5[Amount],Table5[Category_2],'Category Summary'!$B10,Table5[Date],'Category Summary'!E$2)+E24*-1 -> 1552.29 | F10: =SUMIFS(dis_table[Amount],dis_table[Category_2],'Category Summary'!$B10,dis_table[Date],'Category Summary'!F$2) +SUMIFS(cc_table[Amount],cc_table[Category_2],'Category Summary'!$B10,cc_table[Date],'Category Summary'!F$2) + SUMIFS(bb_table[Amount],bb_table[Category_2],'Category Summary'!$B10,bb_table[Date],'Category Summary'!F$2) + SUMIFS(Table5[Amount],Table5[Category_2],'Category Summary'!$B10,Table5[Date],'Category Summary'!F$2)+F24*-1 -> 668 | G10: =SUMIFS(dis_table[Amount],dis_table[Category_2],'Category Summary'!$B10,dis_table[Date],'Category Summary'!G$2) +SUMIFS(cc_table[Amount],cc_table[Category_2],'Category Summary'!$B10,cc_table[Date],'Category Summary'!G$2) + SUMIFS(bb_table[Amount],bb_table[Category_2],'Category Summary'!$B10,bb_table[Date],'Category Summary'!G$2) + SUMIFS(Table5[Amount],Table5[Category_2],'Category Summary'!$B10,Table5[Date],'Category Summary'!G$2)+G24*-1 -> 468.47 | H10: =SUMIFS(dis_table[Amount],dis_table[Category_2],'Category Summary'!$B10,dis_table[Date],'Category Summary'!H$2) +SUMIFS(cc_table[Amount],cc_table[Category_2],'Category Summary'!$B10,cc_table[Date],'Category Summary'!H$2) + SUMIFS(bb_table[Amount],bb_table[Category_2],'Category Summary'!$B10,bb_table[Date],'Category Summary'!H$2) + SUMIFS(Table5[Amount],Table5[Category_2],'Category Summary'!$B10,Table5[Date],'Category Summary'!H$2)+H24*-1 -> 66.07 | I10: =SUMIFS(dis_table[Amount],dis_table[Category_2],'Category Summary'!$B10,dis_table[Date],'Category Summary'!I$2) +SUMIFS(cc_table[Amount],cc_table[Category_2],'Category Summary'!$B10,cc_table[Date],'Category Summary'!I$2) + SUMIFS(bb_table[Amount],bb_table[Category_2],'Category Summary'!$B10,bb_table[Date],'Category Summary'!I$2) + SUMIFS(Table5[Amount],Table5[Category_2],'Category Summary'!$B10,Table5[Date],'Category Summary'!I$2)+I24*-1 -> 51.5 | J10: =SUMIFS(dis_table[Amount],dis_table[Category_2],'Category Summary'!$B10,dis_table[Date],'Category Summary'!J$2) +SUMIFS(cc_table[Amount],cc_table[Category_2],'Category Summary'!$B10,cc_table[Date],'Category Summary'!J$2) + SUMIFS(bb_table[Amount],bb_table[Category_2],'Category Summary'!$B10,bb_table[Date],'Category Summary'!J$2) + SUMIFS(Table5[Amount],Table5[Category_2],'Category Summary'!$B10,Table5[Date],'Category Summary'!J$2)+J25*-1 -> 25.75 | K10: =SUMIFS(dis_table[Amount],dis_table[Category_2],'Category Summary'!$B10,dis_table[Date],'Category Summary'!K$2) +SUMIFS(cc_table[Amount],cc_table[Category_2],'Category Summary'!$B10,cc_table[Date],'Category Summary'!K$2) + SUMIFS(bb_table[Amount],bb_table[Category_2],'Category Summary'!$B10,bb_table[Date],'Category Summary'!K$2) + SUMIFS(Table5[Amount],Table5[Category_2],'Category Summary'!$B10,Table5[Date],'Category Summary'!K$2)+K25*-1 -> 0 | L10: =SUMIFS(dis_table[Amount],dis_table[Category_2],'Category Summary'!$B10,dis_table[Date],'Category Summary'!L$2) +SUMIFS(cc_table[Amount],cc_table[Category_2],'Category Summary'!$B10,cc_table[Date],'Category Summary'!L$2) + SUMIFS(bb_table[Amount],bb_table[Category_2],'Category Summary'!$B10,bb_table[Date],'Category Summary'!L$2) + SUMIFS(Table5[Amount],Table5[Category_2],'Category Summary'!$B10,Table5[Date],'Category Summary'!L$2)+L25*-1 -> 0 | M10: =SUMIFS(dis_table[Amount],dis_table[Category_2],'Category Summary'!$B10,dis_table[Date],'Category Summary'!M$2) +SUMIFS(cc_table[Amount],cc_table[Category_2],'Category Summary'!$B10,cc_table[Date],'Category Summary'!M$2) + SUMIFS(bb_table[Amount],bb_table[Category_2],'Category Summary'!$B10,bb_table[Date],'Category Summary'!M$2) + SUMIFS(Table5[Amount],Table5[Category_2],'Category Summary'!$B10,Table5[Date],'Category Summary'!M$2)+M25*-1 -> 103 | N10: =SUMIFS(dis_table[Category_2],dis_table[Amount],'Category Summary'!$B10,dis_table[Post Date],'Category Summary'!N$2) +SUMIFS(cc_table[Post Date],cc_table[Short_Desc],'Category Summary'!$B10,cc_table[Amount],'Category Summary'!N$2) + SUMIFS(bb_table[Category_2],bb_table[Short_Desc],'Category Summary'!$B10,bb_table[Category],'Category Summary'!N$2) + SUMIFS(Table5[Description],Table5[Split Amount],'Category Summary'!$B10,Table5[Individual Amount],'Category Summary'!N$2)+N24*-1 -> 0 | O10: =SUM(C10:N10) -> 5481.15 | P10: =O10/$O$27 -> 0.13976518
B11: Medical | C11: =SUMIFS(dis_table[Amount],dis_table[Category_2],'Category Summary'!$B11,dis_table[Date],'Category Summary'!C$2) +SUMIFS(cc_table[Amount],cc_table[Category_2],'Category Summary'!$B11,cc_table[Date],'Category Summary'!C$2) + SUMIFS(bb_table[Amount],bb_table[Category_2],'Category Summary'!$B11,bb_table[Date],'Category Summary'!C$2) + SUMIFS(Table5[Amount],Table5[Category_2],'Category Summary'!$B11,Table5[Date],'Category Summary'!C$2) -> 2286 | D11: =SUMIFS(dis_table[Amount],dis_table[Category_2],'Category Summary'!$B11,dis_table[Date],'Category Summary'!D$2) +SUMIFS(cc_table[Amount],cc_table[Category_2],'Category Summary'!$B11,cc_table[Date],'Category Summary'!D$2) + SUMIFS(bb_table[Amount],bb_table[Category_2],'Category Summary'!$B11,bb_table[Date],'Category Summary'!D$2) + SUMIFS(Table5[Amount],Table5[Category_2],'Category Summary'!$B11,Table5[Date],'Category Summary'!D$2) -> 21.35 | E11: =SUMIFS(dis_table[Amount],dis_table[Category_2],'Category Summary'!$B11,dis_table[Date],'Category Summary'!E$2) +SUMIFS(cc_table[Amount],cc_table[Category_2],'Category Summary'!$B11,cc_table[Date],'Category Summary'!E$2) + SUMIFS(bb_table[Amount],bb_table[Category_2],'Category Summary'!$B11,bb_table[Date],'Category Summary'!E$2) + SUMIFS(Table5[Amount],Table5[Category_2],'Category Summary'!$B11,Table5[Date],'Category Summary'!E$2) -> 2553.16 | F11: =SUMIFS(dis_table[Amount],dis_table[Category_2],'Category Summary'!$B11,dis_table[Date],'Category Summary'!F$2) +SUMIFS(cc_table[Amount],cc_table[Category_2],'Category Summary'!$B11,cc_table[Date],'Category Summary'!F$2) + SUMIFS(bb_table[Amount],bb_table[Category_2],'Category Summary'!$B11,bb_table[Date],'Category Summary'!F$2) + SUMIFS(Table5[Amount],Table5[Category_2],'Category Summary'!$B11,Table5[Date],'Category Summary'!F$2) -> 0 | G11: =SUMIFS(dis_table[Amount],dis_table[Category_2],'Category Summary'!$B11,dis_table[Date],'Category Summary'!G$2) +SUMIFS(cc_table[Amount],cc_table[Category_2],'Category Summary'!$B11,cc_table[Date],'Category Summary'!G$2) + SUMIFS(bb_table[Amount],bb_table[Category_2],'Category Summary'!$B11,bb_table[Date],'Category Summary'!G$2) + SUMIFS(Table5[Amount],Table5[Category_2],'Category Summary'!$B11,Table5[Date],'Category Summary'!G$2) -> 0 | H11: =SUMIFS(dis_table[Amount],dis_table[Category_2],'Category Summary'!$B11,dis_table[Date],'Category Summary'!H$2) +SUMIFS(cc_table[Amount],cc_table[Category_2],'Category Summary'!$B11,cc_table[Date],'Category Summary'!H$2) + SUMIFS(bb_table[Amount],bb_table[Category_2],'Category Summary'!$B11,bb_table[Date],'Category Summary'!H$2) + SUMIFS(Table5[Amount],Table5[Category_2],'Category Summary'!$B11,Table5[Date],'Category Summary'!H$2) -> 0 | I11: =SUMIFS(dis_table[Amount],dis_table[Category_2],'Category Summary'!$B11,dis_table[Date],'Category Summary'!I$2) +SUMIFS(cc_table[Amount],cc_table[Category_2],'Category Summary'!$B11,cc_table[Date],'Category Summary'!I$2) + SUMIFS(bb_table[Amount],bb_table[Category_2],'Category Summary'!$B11,bb_table[Date],'Category Summary'!I$2) + SUMIFS(Table5[Amount],Table5[Category_2],'Category Summary'!$B11,Table5[Date],'Category Summary'!I$2) -> 504.86 | J11: =SUMIFS(dis_table[Amount],dis_table[Category_2],'Category Summary'!$B11,dis_table[Date],'Category Summary'!J$2) +SUMIFS(cc_table[Amount],cc_table[Category_2],'Category Summary'!$B11,cc_table[Date],'Category Summary'!J$2) + SUMIFS(bb_table[Amount],bb_table[Category_2],'Category Summary'!$B11,bb_table[Date],'Category Summary'!J$2) + SUMIFS(Table5[Amount],Table5[Category_2],'Category Summary'!$B11,Table5[Date],'Category Summary'!J$2)+J26*-1 -> 0 | K11: =SUMIFS(dis_table[Amount],dis_table[Category_2],'Category Summary'!$B11,dis_table[Date],'Category Summary'!K$2) +SUMIFS(cc_table[Amount],cc_table[Category_2],'Category Summary'!$B11,cc_table[Date],'Category Summary'!K$2) + SUMIFS(bb_table[Amount],bb_table[Category_2],'Category Summary'!$B11,bb_table[Date],'Category Summary'!K$2) + SUMIFS(Table5[Amount],Table5[Category_2],'Category Summary'!$B11,Table5[Date],'Category Summary'!K$2)+K26*-1 -> 85.76 | L11: =SUMIFS(dis_table[Amount],dis_table[Category_2],'Category Summary'!$B11,dis_table[Date],'Category Summary'!L$2) +SUMIFS(cc_table[Amount],cc_table[Category_2],'Category Summary'!$B11,cc_table[Date],'Category Summary'!L$2) + SUMIFS(bb_table[Amount],bb_table[Category_2],'Category Summary'!$B11,bb_table[Date],'Category Summary'!L$2) + SUMIFS(Table5[Amount],Table5[Category_2],'Category Summary'!$B11,Table5[Date],'Category Summary'!L$2)+L26*-1 -> 0 | M11: =SUMIFS(dis_table[Amount],dis_table[Category_2],'Category Summary'!$B11,dis_table[Date],'Category Summary'!M$2) +SUMIFS(cc_table[Amount],cc_table[Category_2],'Category Summary'!$B11,cc_table[Date],'Category Summary'!M$2) + SUMIFS(bb_table[Amount],bb_table[Category_2],'Category Summary'!$B11,bb_table[Date],'Category Summary'!M$2) + SUMIFS(Table5[Amount],Table5[Category_2],'Category Summary'!$B11,Table5[Date],'Category Summary'!M$2)+M26*-1 -> 0 | N11: =SUMIFS(dis_table[Category_2],dis_table[Amount],'Category Summary'!$B11,dis_table[Post Date],'Category Summary'!N$2) +SUMIFS(cc_table[Post Date],cc_table[Short_Desc],'Category Summary'!$B11,cc_table[Amount],'Category Summary'!N$2) + SUMIFS(bb_table[Category_2],bb_table[Short_Desc],'Category Summary'!$B11,bb_table[Category],'Category Summary'!N$2) + SUMIFS(Table5[Description],Table5[Split Amount],'Category Summary'!$B11,Table5[Individual Amount],'Category Summary'!N$2) -> 0 | O11: =SUM(C11:N11) -> 5451.13 | P11: =O11/$O$27 -> 0.13899969
B12: Housing | C12: =SUMIFS(dis_table[Amount],dis_table[Category_2],'Category Summary'!$B12,dis_table[Date],'Category Summary'!C$2) +SUMIFS(cc_table[Amount],cc_table[Category_2],'Category Summary'!$B12,cc_table[Date],'Category Summary'!C$2) + SUMIFS(bb_table[Amount],bb_table[Category_2],'Category Summary'!$B12,bb_table[Date],'Category Summary'!C$2) + SUMIFS(Table5[Amount],Table5[Category_2],'Category Summary'!$B12,Table5[Date],'Category Summary'!C$2)+C25*-1 -> 933.34 | D12: =SUMIFS(dis_table[Amount],dis_table[Category_2],'Category Summary'!$B12,dis_table[Date],'Category Summary'!D$2) +SUMIFS(cc_table[Amount],cc_table[Category_2],'Category Summary'!$B12,cc_table[Date],'Category Summary'!D$2) + SUMIFS(bb_table[Amount],bb_table[Category_2],'Category Summary'!$B12,bb_table[Date],'Category Summary'!D$2) + SUMIFS(Table5[Amount],Table5[Category_2],'Category Summary'!$B12,Table5[Date],'Category Summary'!D$2)+D25*-1 -> 1204.29 | E12: =SUMIFS(dis_table[Amount],dis_table[Category_2],'Category Summary'!$B12,dis_table[Date],'Category Summary'!E$2) +SUMIFS(cc_table[Amount],cc_table[Category_2],'Category Summary'!$B12,cc_table[Date],'Category Summary'!E$2) + SUMIFS(bb_table[Amount],bb_table[Category_2],'Category Summary'!$B12,bb_table[Date],'Category Summary'!E$2) + SUMIFS(Table5[Amount],Table5[Category_2],'Category Summary'!$B12,Table5[Date],'Category Summary'!E$2)+E25*-1 -> 1400 | F12: =SUMIFS(dis_table[Amount],dis_table[Category_2],'Category Summary'!$B12,dis_table[Date],'Category Summary'!F$2) +SUMIFS(cc_table[Amount],cc_table[Category_2],'Category Summary'!$B12,cc_table[Date],'Category Summary'!F$2) + SUMIFS(bb_table[Amount],bb_table[Category_2],'Category Summary'!$B12,bb_table[Date],'Category Summary'!F$2) + SUMIFS(Table5[Amount],Table5[Category_2],'Category Summary'!$B12,Table5[Date],'Category Summary'!F$2)+F25*-1 -> 1463.66 | G12: =SUMIFS(dis_table[Amount],dis_table[Category_2],'Category Summary'!$B12,dis_table[Date],'Category Summary'!G$2) +SUMIFS(cc_table[Amount],cc_table[Category_2],'Category Summary'!$B12,cc_table[Date],'Category Summary'!G$2) + SUMIFS(bb_table[Amount],bb_table[Category_2],'Category Summary'!$B12,bb_table[Date],'Category Summary'!G$2) + SUMIFS(Table5[Amount],Table5[Category_2],'Category Summary'!$B12,Table5[Date],'Category Summary'!G$2)+G25*-1 -> 1400 | H12: =SUMIFS(dis_table[Amount],dis_table[Category_2],'Category Summary'!$B12,dis_table[Date],'Category Summary'!H$2) +SUMIFS(cc_table[Amount],cc_table[Category_2],'Category Summary'!$B12,cc_table[Date],'Category Summary'!H$2) + SUMIFS(bb_table[Amount],bb_table[Category_2],'Category Summary'!$B12,bb_table[Date],'Category Summary'!H$2) + SUMIFS(Table5[Amount],Table5[Category_2],'Category Summary'!$B12,Table5[Date],'Category Summary'!H$2)+H25*-1 -> 1400 | I12: =SUMIFS(dis_table[Amount],dis_table[Category_2],'Category Summary'!$B12,dis_table[Date],'Category Summary'!I$2) +SUMIFS(cc_table[Amount],cc_table[Category_2],'Category Summary'!$B12,cc_table[Date],'Category Summary'!I$2) + SUMIFS(bb_table[Amount],bb_table[Category_2],'Category Summary'!$B12,bb_table[Date],'Category Summary'!I$2) + SUMIFS(Table5[Amount],Table5[Category_2],'Category Summary'!$B12,Table5[Date],'Category Summary'!I$2)+I25*-1 -> 1449.46 | J12: =SUMIFS(dis_table[Amount],dis_table[Category_2],'Category Summary'!$B12,dis_table[Date],'Category Summary'!J$2) +SUMIFS(cc_table[Amount],cc_table[Category_2],'Category Summary'!$B12,cc_table[Date],'Category Summary'!J$2) + SUMIFS(bb_table[Amount],bb_table[Category_2],'Category Summary'!$B12,bb_table[Date],'Category Summary'!J$2) + SUMIFS(Table5[Amount],Table5[Category_2],'Category Summary'!$B12,Table5[Date],'Category Summary'!J$2)+J27*-1 -> 197.48 | K12: =SUMIFS(dis_table[Amount],dis_table[Category_2],'Category Summary'!$B12,dis_table[Date],'Category Summary'!K$2) +SUMIFS(cc_table[Amount],cc_table[Category_2],'Category Summary'!$B12,cc_table[Date],'Category Summary'!K$2) + SUMIFS(bb_table[Amount],bb_table[Category_2],'Category Summary'!$B12,bb_table[Date],'Category Summary'!K$2) + SUMIFS(Table5[Amount],Table5[Category_2],'Category Summary'!$B12,Table5[Date],'Category Summary'!K$2)+K27*-1 -> 0 | L12: =SUMIFS(dis_table[Amount],dis_table[Category_2],'Category Summary'!$B12,dis_table[Date],'Category Summary'!L$2) +SUMIFS(cc_table[Amount],cc_table[Category_2],'Category Summary'!$B12,cc_table[Date],'Category Summary'!L$2) + SUMIFS(bb_table[Amount],bb_table[Category_2],'Category Summary'!$B12,bb_table[Date],'Category Summary'!L$2) + SUMIFS(Table5[Amount],Table5[Category_2],'Category Summary'!$B12,Table5[Date],'Category Summary'!L$2)+L27*-1 -> 210.25 | M12: =SUMIFS(dis_table[Amount],dis_table[Category_2],'Category Summary'!$B12,dis_table[Date],'Category Summary'!M$2) +SUMIFS(cc_table[Amount],cc_table[Category_2],'Category Summary'!$B12,cc_table[Date],'Category Summary'!M$2) + SUMIFS(bb_table[Amount],bb_table[Category_2],'Category Summary'!$B12,bb_table[Date],'Category Summary'!M$2) + SUMIFS(Table5[Amount],Table5[Category_2],'Category Summary'!$B12,Table5[Date],'Category Summary'!M$2)+M27*-1 -> 37.12 | N12: =SUMIFS(dis_table[Category_2],dis_table[Amount],'Category Summary'!$B12,dis_table[Post Date],'Category Summary'!N$2) +SUMIFS(cc_table[Post Date],cc_table[Short_Desc],'Category Summary'!$B12,cc_table[Amount],'Category Summary'!N$2) + SUMIFS(bb_table[Category_2],bb_table[Short_Desc],'Category Summary'!$B12,bb_table[Category],'Category Summary'!N$2) + SUMIFS(Table5[Description],Table5[Split Amount],'Category Summary'!$B12,Table5[Individual Amount],'Category Summary'!N$2)+N25*-1 -> 0 | O12: =SUM(C12:N12) -> 9695.6 | P12: =O12/$O$27 -> 0.24723046
B13: Total | C13: =SUM(C3:C12) -> 6165.68 | D13: =SUM(D3:D12) -> 5271.65 | E13: =SUM(E3:E12) -> 9059.12 | F13: =SUM(F3:F12) -> 4915.24 | G13: =SUM(G3:G12) -> 7250.39 | H13: =SUM(H3:H12) -> 7541.465 | I13: =SUM(I3:I12) -> 5930.835 | J13: =SUM(J3:J12) -> 1979.29 | ... P13: =SUM(P3:P12) -> 1.4528661
B17: Debit Accounts | C17: 01/2022 | D17: 02/2022 | E17: 03/2022 | F17: 04/2022 | G17: 05/2022 | H17: 06/2022 | I17: 07/2022 | J17: 08/2022 | K17: 09/2022 | L17: 10/2022 | M17: 11/2022 | N17: 12/2022 | O17: Total
B18: Food | C18: =SUMIFS(wf_table[Debit_Amount],wf_table[Category_2],'Category Summary'!$B18,wf_table[Date],'Category Summary'!C$17) -> -40 | D18: =SUMIFS(wf_table[Debit_Amount],wf_table[Category_2],'Category Summary'!$B18,wf_table[Date],'Category Summary'!D$17) -> 0 | E18: =SUMIFS(wf_table[Debit_Amount],wf_table[Category_2],'Category Summary'!$B18,wf_table[Date],'Category Summary'!E$17) -> 33 | F18: =SUMIFS(wf_table[Debit_Amount],wf_table[Category_2],'Category Summary'!$B18,wf_table[Date],'Category Summary'!F$17) -> 0 | G18: =SUMIFS(wf_table[Debit_Amount],wf_table[Category_2],'Category Summary'!$B18,wf_table[Date],'Category Summary'!G$17) -> 0 | H18: =SUMIFS(wf_table[Debit_Amount],wf_table[Category_2],'Category Summary'!$B18,wf_table[Date],'Category Summary'!H$17) -> 0 | I18: =SUMIFS(wf_table[Debit_Amount],wf_table[Category_2],'Category Summary'!$B18,wf_table[Date],'Category Summary'!I$17) -> 0 | J18: =SUMIFS(wf_table[Amount],wf_table[Trans Date],'Category Summary'!$B18,wf_table[Category_2],'Category Summary'!J$17) -> 0 | K18: =SUMIFS(wf_table[Description],wf_table[Debit_Amount],'Category Summary'!$B18,wf_table[Trans Date],'Category Summary'!K$17) -> 0 | L18: =SUMIFS(wf_table[Short_Desc],wf_table[Amount],'Category Summary'!$B18,wf_table[Debit_Amount],'Category Summary'!L$17) -> 0 | M18: =SUMIFS(wf_table[Date],wf_table[Description],'Category Summary'!$B18,wf_table[Amount],'Category Summary'!M$17) -> 0 | N18: =SUMIFS(wf_table[Category_2],wf_table[Short_Desc],'Category Summary'!$B18,wf_table[Description],'Category Summary'!N$17) -> 0 | O18: =SUM(C18:I18) -> -7
B19: Recreation_Entertainment | C19: =SUMIFS(wf_table[Debit_Amount],wf_table[Category_2],'Category Summary'!$B19,wf_table[Date],'Category Summary'!C$17) -> -623.34 | D19: =SUMIFS(wf_table[Debit_Amount],wf_table[Category_2],'Category Summary'!$B19,wf_table[Date],'Category Summary'!D$17) -> 0 | E19: =SUMIFS(wf_table[Debit_Amount],wf_table[Category_2],'Category Summary'!$B19,wf_table[Date],'Category Summary'!E$17) -> -52 | F19: =SUMIFS(wf_table[Debit_Amount],wf_table[Category_2],'Category Summary'!$B19,wf_table[Date],'Category Summary'!F$17) -> -59 | G19: =SUMIFS(wf_table[Debit_Amount],wf_table[Category_2],'Category Summary'!$B19,wf_table[Date],'Category Summary'!G$17) -> -276.83 | H19: =SUMIFS(wf_table[Debit_Amount],wf_table[Category_2],'Category Summary'!$B19,wf_table[Date],'Category Summary'!H$17) -> 0 | I19: =SUMIFS(wf_table[Debit_Amount],wf_table[Category_2],'Category Summary'!$B19,wf_table[Date],'Category Summary'!I$17) -> -25.48 | J19: =SUMIFS(wf_table[Amount],wf_table[Trans Date],'Category Summary'!$B19,wf_table[Category_2],'Category Summary'!J$17) -> 0 | K19: =SUMIFS(wf_table[Description],wf_table[Debit_Amount],'Category Summary'!$B19,wf_table[Trans Date],'Category Summary'!K$17) -> 0 | L19: =SUMIFS(wf_table[Short_Desc],wf_table[Amount],'Category Summary'!$B19,wf_table[Debit_Amount],'Category Summary'!L$17) -> 0 | M19: =SUMIFS(wf_table[Date],wf_table[Description],'Category Summary'!$B19,wf_table[Amount],'Category Summary'!M$17) -> 0 | N19: =SUMIFS(wf_table[Category_2],wf_table[Short_Desc],'Category Summary'!$B19,wf_table[Description],'Category Summary'!N$17) -> 0 | O19: =SUM(C19:I19) -> -1036.65
B20: Personal_Spending | C20: =SUMIFS(wf_table[Debit_Amount],wf_table[Category_2],'Category Summary'!$B20,wf_table[Date],'Category Summary'!C$17) -> -90 | D20: =SUMIFS(wf_table[Debit_Amount],wf_table[Category_2],'Category Summary'!$B20,wf_table[Date],'Category Summary'!D$17) -> -210 | E20: =SUMIFS(wf_table[Debit_Amount],wf_table[Category_2],'Category Summary'!$B20,wf_table[Date],'Category Summary'!E$17) -> 0 | F20: =SUMIFS(wf_table[Debit_Amount],wf_table[Category_2],'Category Summary'!$B20,wf_table[Date],'Category Summary'!F$17) -> 0 | G20: =SUMIFS(wf_table[Debit_Amount],wf_table[Category_2],'Category Summary'!$B20,wf_table[Date],'Category Summary'!G$17) -> 0 | H20: =SUMIFS(wf_table[Debit_Amount],wf_table[Category_2],'Category Summary'!$B20,wf_table[Date],'Category Summary'!H$17) -> 0 | I20: =SUMIFS(wf_table[Debit_Amount],wf_table[Category_2],'Category Summary'!$B20,wf_table[Date],'Category Summary'!I$17) -> 0 | J20: =SUMIFS(wf_table[Amount],wf_table[Trans Date],'Category Summary'!$B20,wf_table[Category_2],'Category Summary'!J$17) -> 0 | K20: =SUMIFS(wf_table[Description],wf_table[Debit_Amount],'Category Summary'!$B20,wf_table[Trans Date],'Category Summary'!K$17) -> 0 | L20: =SUMIFS(wf_table[Short_Desc],wf_table[Amount],'Category Summary'!$B20,wf_table[Debit_Amount],'Category Summary'!L$17) -> 0 | M20: =SUMIFS(wf_table[Date],wf_table[Description],'Category Summary'!$B20,wf_table[Amount],'Category Summary'!M$17) -> 0 | N20: =SUMIFS(wf_table[Category_2],wf_table[Short_Desc],'Category Summary'!$B20,wf_table[Description],'Category Summary'!N$17) -> 0 | O20: =SUM(C20:I20) -> -300
B21: Transportation | C21: =SUMIFS(wf_table[Debit_Amount],wf_table[Category_2],'Category Summary'!$B21,wf_table[Date],'Category Summary'!C$17) -> 0 | D21: =SUMIFS(wf_table[Debit_Amount],wf_table[Category_2],'Category Summary'!$B21,wf_table[Date],'Category Summary'!D$17) -> 0 | E21: =SUMIFS(wf_table[Debit_Amount],wf_table[Category_2],'Category Summary'!$B21,wf_table[Date],'Category Summary'!E$17) -> 0 | F21: =SUMIFS(wf_table[Debit_Amount],wf_table[Category_2],'Category Summary'!$B21,wf_table[Date],'Category Summary'!F$17) -> 0 | G21: =SUMIFS(wf_table[Debit_Amount],wf_table[Category_2],'Category Summary'!$B21,wf_table[Date],'Category Summary'!G$17) -> 0 | H21: =SUMIFS(wf_table[Debit_Amount],wf_table[Category_2],'Category Summary'!$B21,wf_table[Date],'Category Summary'!H$17) -> 0 | I21: =SUMIFS(wf_table[Debit_Amount],wf_table[Category_2],'Category Summary'!$B21,wf_table[Date],'Category Summary'!I$17) -> -64 | J21: =SUMIFS(wf_table[Amount],wf_table[Trans Date],'Category Summary'!$B21,wf_table[Category_2],'Category Summary'!J$17) -> 0 | K21: =SUMIFS(wf_table[Description],wf_table[Debit_Amount],'Category Summary'!$B21,wf_table[Trans Date],'Category Summary'!K$17) -> 0 | L21: =SUMIFS(wf_table[Short_Desc],wf_table[Amount],'Category Summary'!$B21,wf_table[Debit_Amount],'Category Summary'!L$17) -> 0 | M21: =SUMIFS(wf_table[Date],wf_table[Description],'Category Summary'!$B21,wf_table[Amount],'Category Summary'!M$17) -> 0 | N21: =SUMIFS(wf_table[Category_2],wf_table[Short_Desc],'Category Summary'!$B21,wf_table[Description],'Category Summary'!N$17) -> 0 | O21: =SUM(C21:I21) -> -64
B22: Misc | C22: =SUMIFS(wf_table[Debit_Amount],wf_table[Category_2],'Category Summary'!$B22,wf_table[Date],'Category Summary'!C$17) -> -10 | D22: =SUMIFS(wf_table[Debit_Amount],wf_table[Category_2],'Category Summary'!$B22,wf_table[Date],'Category Summary'!D$17) -> 0 | E22: =SUMIFS(wf_table[Debit_Amount],wf_table[Category_2],'Category Summary'!$B22,wf_table[Date],'Category Summary'!E$17) -> 0 | F22: =SUMIFS(wf_table[Debit_Amount],wf_table[Category_2],'Category Summary'!$B22,wf_table[Date],'Category Summary'!F$17) -> 0 | G22: =SUMIFS(wf_table[Debit_Amount],wf_table[Category_2],'Category Summary'!$B22,wf_table[Date],'Category Summary'!G$17) -> 0 | H22: =SUMIFS(wf_table[Debit_Amount],wf_table[Category_2],'Category Summary'!$B22,wf_table[Date],'Category Summary'!H$17) -> 0 | I22: =SUMIFS(wf_table[Debit_Amount],wf_table[Category_2],'Category Summary'!$B22,wf_table[Date],'Category Summary'!I$17) -> 0 | J22: =SUMIFS(wf_table[Amount],wf_table[Trans Date],'Category Summary'!$B22,wf_table[Category_2],'Category Summary'!J$17) -> 0 | K22: =SUMIFS(wf_table[Description],wf_table[Debit_Amount],'Category Summary'!$B22,wf_table[Trans Date],'Category Summary'!K$17) -> 0 | L22: =SUMIFS(wf_table[Short_Desc],wf_table[Amount],'Category Summary'!$B22,wf_table[Debit_Amount],'Category Summary'!L$17) -> 0 | M22: =SUMIFS(wf_table[Date],wf_table[Description],'Category Summary'!$B22,wf_table[Amount],'Category Summary'!M$17) -> 0 | N22: =SUMIFS(wf_table[Category_2],wf_table[Short_Desc],'Category Summary'!$B22,wf_table[Description],'Category Summary'!N$17) -> 0 | O22: =SUM(C22:I22) -> -10
B23: Utilities | C23: =SUMIFS(wf_table[Debit_Amount],wf_table[Category_2],'Category Summary'!$B23,wf_table[Date],'Category Summary'!C$17) -> 265.47 | D23: =SUMIFS(wf_table[Debit_Amount],wf_table[Category_2],'Category Summary'!$B23,wf_table[Date],'Category Summary'!D$17) -> -137.17 | E23: =SUMIFS(wf_table[Debit_Amount],wf_table[Category_2],'Category Summary'!$B23,wf_table[Date],'Category Summary'!E$17) -> -229.5 | F23: =SUMIFS(wf_table[Debit_Amount],wf_table[Category_2],'Category Summary'!$B23,wf_table[Date],'Category Summary'!F$17) -> -197.97 | G23: =SUMIFS(wf_table[Debit_Amount],wf_table[Category_2],'Category Summary'!$B23,wf_table[Date],'Category Summary'!G$17) -> -193.04 | H23: =SUMIFS(wf_table[Debit_Amount],wf_table[Category_2],'Category Summary'!$B23,wf_table[Date],'Category Summary'!H$17) -> -271.77 | I23: =SUMIFS(wf_table[Debit_Amount],wf_table[Category_2],'Category Summary'!$B23,wf_table[Date],'Category Summary'!I$17) -> -202.46 | J23: =SUMIFS(wf_table[Amount],wf_table[Trans Date],'Category Summary'!$B23,wf_table[Category_2],'Category Summary'!J$17) -> 0 | K23: =SUMIFS(wf_table[Description],wf_table[Debit_Amount],'Category Summary'!$B23,wf_table[Trans Date],'Category Summary'!K$17) -> 0 | L23: =SUMIFS(wf_table[Short_Desc],wf_table[Amount],'Category Summary'!$B23,wf_table[Debit_Amount],'Category Summary'!L$17) -> 0 | M23: =SUMIFS(wf_table[Date],wf_table[Description],'Category Summary'!$B23,wf_table[Amount],'Category Summary'!M$17) -> 0 | N23: =SUMIFS(wf_table[Category_2],wf_table[Short_Desc],'Category Summary'!$B23,wf_table[Description],'Category Summary'!N$17) -> 0 | O23: =SUM(C23:I23) -> -966.44
B24: People | C24: =SUMIFS(wf_table[Debit_Amount],wf_table[Category_2],'Category Summary'!$B24,wf_table[Date],'Category Summary'!C$17) -> -256.76 | D24: =SUMIFS(wf_table[Debit_Amount],wf_table[Category_2],'Category Summary'!$B24,wf_table[Date],'Category Summary'!D$17) -> -2240.31 | E24: =SUMIFS(wf_table[Debit_Amount],wf_table[Category_2],'Category Summary'!$B24,wf_table[Date],'Category Summary'!E$17) -> -1384.09 | F24: =SUMIFS(wf_table[Debit_Amount],wf_table[Category_2],'Category Summary'!$B24,wf_table[Date],'Category Summary'!F$17) -> -668 | G24: =SUMIFS(wf_table[Debit_Amount],wf_table[Category_2],'Category Summary'!$B24,wf_table[Date],'Category Summary'!G$17) -> -468.47 | H24: =SUMIFS(wf_table[Debit_Amount],wf_table[Category_2],'Category Summary'!$B24,wf_table[Date],'Category Summary'!H$17) -> -66.07 | I24: =SUMIFS(wf_table[Debit_Amount],wf_table[Category_2],'Category Summary'!$B24,wf_table[Date],'Category Summary'!I$17) -> 0 | J24: =SUMIFS(wf_table[Amount],wf_table[Trans Date],'Category Summary'!$B24,wf_table[Category_2],'Category Summary'!J$17) -> 0 | K24: =SUMIFS(wf_table[Description],wf_table[Debit_Amount],'Category Summary'!$B24,wf_table[Trans Date],'Category Summary'!K$17) -> 0 | L24: =SUMIFS(wf_table[Short_Desc],wf_table[Amount],'Category Summary'!$B24,wf_table[Debit_Amount],'Category Summary'!L$17) -> 0 | M24: =SUMIFS(wf_table[Date],wf_table[Description],'Category Summary'!$B24,wf_table[Amount],'Category Summary'!M$17) -> 0 | N24: =SUMIFS(wf_table[Category_2],wf_table[Short_Desc],'Category Summary'!$B24,wf_table[Description],'Category Summary'!N$17) -> 0 | O24: =SUM(C24:I24) -> -5083.7
B25: Housing | C25: =SUMIFS(wf_table[Debit_Amount],wf_table[Category_2],'Category Summary'!$B25,wf_table[Date],'Category Summary'!C$17) -> -933.34 | D25: =SUMIFS(wf_table[Debit_Amount],wf_table[Category_2],'Category Summary'!$B25,wf_table[Date],'Category Summary'!D$17) -> -1204.29 | E25: =SUMIFS(wf_table[Debit_Amount],wf_table[Category_2],'Category Summary'!$B25,wf_table[Date],'Category Summary'!E$17) -> -1400 | F25: =SUMIFS(wf_table[Debit_Amount],wf_table[Category_2],'Category Summary'!$B25,wf_table[Date],'Category Summary'!F$17) -> -1400 | G25: =SUMIFS(wf_table[Debit_Amount],wf_table[Category_2],'Category Summary'!$B25,wf_table[Date],'Category Summary'!G$17) -> -1400 | H25: =SUMIFS(wf_table[Debit_Amount],wf_table[Category_2],'Category Summary'!$B25,wf_table[Date],'Category Summary'!H$17) -> -1400 | I25: =SUMIFS(wf_table[Debit_Amount],wf_table[Category_2],'Category Summary'!$B25,wf_table[Date],'Category Summary'!I$17) -> -1400 | J25: =SUMIFS(wf_table[Amount],wf_table[Trans Date],'Category Summary'!$B25,wf_table[Category_2],'Category Summary'!J$17) -> 0 | K25: =SUMIFS(wf_table[Description],wf_table[Debit_Amount],'Category Summary'!$B25,wf_table[Trans Date],'Category Summary'!K$17) -> 0 | L25: =SUMIFS(wf_table[Short_Desc],wf_table[Amount],'Category Summary'!$B25,wf_table[Debit_Amount],'Category Summary'!L$17) -> 0 | M25: =SUMIFS(wf_table[Date],wf_table[Description],'Category Summary'!$B25,wf_table[Amount],'Category Summary'!M$17) -> 0 | N25: =SUMIFS(wf_table[Category_2],wf_table[Short_Desc],'Category Summary'!$B25,wf_table[Description],'Category Summary'!N$17) -> 0 | O25: =SUM(C25:I25) -> -9137.63
B26: credit | C26: =SUMIFS(wf_table[Debit_Amount],wf_table[Category_2],'Category Summary'!$B26,wf_table[Date],'Category Summary'!C$17) -> -5236.91 | D26: =SUMIFS(wf_table[Debit_Amount],wf_table[Category_2],'Category Summary'!$B26,wf_table[Date],'Category Summary'!D$17) -> -1307.35 | E26: =SUMIFS(wf_table[Debit_Amount],wf_table[Category_2],'Category Summary'!$B26,wf_table[Date],'Category Summary'!E$17) -> -1969.1 | F26: =SUMIFS(wf_table[Debit_Amount],wf_table[Category_2],'Category Summary'!$B26,wf_table[Date],'Category Summary'!F$17) -> -2074.62 | G26: =SUMIFS(wf_table[Debit_Amount],wf_table[Category_2],'Category Summary'!$B26,wf_table[Date],'Category Summary'!G$17) -> -3000 | H26: =SUMIFS(wf_table[Debit_Amount],wf_table[Category_2],'Category Summary'!$B26,wf_table[Date],'Category Summary'!H$17) -> -4974.91 | I26: =SUMIFS(wf_table[Debit_Amount],wf_table[Category_2],'Category Summary'!$B26,wf_table[Date],'Category Summary'!I$17) -> -3600 | J26: =SUMIFS(wf_table[Amount],wf_table[Trans Date],'Category Summary'!$B26,wf_table[Category_2],'Category Summary'!J$17) -> 0 | K26: =SUMIFS(wf_table[Description],wf_table[Debit_Amount],'Category Summary'!$B26,wf_table[Trans Date],'Category Summary'!K$17) -> 0 | L26: =SUMIFS(wf_table[Short_Desc],wf_table[Amount],'Category Summary'!$B26,wf_table[Debit_Amount],'Category Summary'!L$17) -> 0 | M26: =SUMIFS(wf_table[Date],wf_table[Description],'Category Summary'!$B26,wf_table[Amount],'Category Summary'!M$17) -> 0 | N26: =SUMIFS(wf_table[Category_2],wf_table[Short_Desc],'Category Summary'!$B26,wf_table[Description],'Category Summary'!N$17) -> 0 | O26: =SUM(C26:I26) -> -22162.89
B27: income | C27: =SUMIFS(wf_table[Debit_Amount],wf_table[Category_2],'Category Summary'!$B27,wf_table[Date],'Category Summary'!C$17) -> 5616.86 | D27: =SUMIFS(wf_table[Debit_Amount],wf_table[Category_2],'Category Summary'!$B27,wf_table[Date],'Category Summary'!D$17) -> 7196.43 | E27: =SUMIFS(wf_table[Debit_Amount],wf_table[Category_2],'Category Summary'!$B27,wf_table[Date],'Category Summary'!E$17) -> 4480.14 | F27: =SUMIFS(wf_table[Debit_Amount],wf_table[Category_2],'Category Summary'!$B27,wf_table[Date],'Category Summary'!F$17) -> 4543.15 | G27: =SUMIFS(wf_table[Debit_Amount],wf_table[Category_2],'Category Summary'!$B27,wf_table[Date],'Category Summary'!G$17) -> 4965.79 | H27: =SUMIFS(wf_table[Debit_Amount],wf_table[Category_2],'Category Summary'!$B27,wf_table[Date],'Category Summary'!H$17) -> 7448.69 | I27: =SUMIFS(wf_table[Debit_Amount],wf_table[Category_2],'Category Summary'!$B27,wf_table[Date],'Category Summary'!I$17) -> 4965.79 | J27: =SUMIFS(wf_table[Amount],wf_table[Trans Date],'Category Summary'!$B27,wf_table[Category_2],'Category Summary'!J$17) -> 0 | K27: =SUMIFS(wf_table[Description],wf_table[Debit_Amount],'Category Summary'!$B27,wf_table[Trans Date],'Category Summary'!K$17) -> 0 | L27: =SUMIFS(wf_table[Short_Desc],wf_table[Amount],'Category Summary'!$B27,wf_table[Debit_Amount],'Category Summary'!L$17) -> 0 | M27: =SUMIFS(wf_table[Date],wf_table[Description],'Category Summary'!$B27,wf_table[Amount],'Category Summary'!M$17) -> 0 | N27: =SUMIFS(wf_table[Category_2],wf_table[Short_Desc],'Category Summary'!$B27,wf_table[Description],'Category Summary'!N$17) -> 0 | O27: =SUM(C27:I27) -> 39216.85
C28: =SUM(C18:C27) -> -1308.02 | D28: =SUM(D18:D27) -> 2097.31 | E28: =SUM(E18:E27) -> -521.55 | F28: =SUM(F18:F27) -> 143.56 | G28: =SUM(G18:G27) -> -372.55 | H28: =SUM(H18:H27) -> 735.94 | I28: =SUM(I18:I27) -> -326.15 | J28: =SUM(J18:J27) -> 0 | ... N28: =SUM(N18:N27) -> 0 | O28: =O27-O13 -> -17759.98

Sheet Cat Sum
A3: Sum of Amount | B3: Column Labels
A4: Row Labels | B4: 01/2022 | C4: 02/2022 | D4: 03/2022 | E4: 04/2022 | F4: 05/2022 | G4: 06/2022 | H4: 07/2022 | I4: 08/2022 | J4: 09/2022 | K4: 10/2022 | L4: 11/2022 | M4: Grand Total
A5: Food | B5: 547.29 | C5: 248.29 | D5: 1264.25 | E5: 945.31 | F5: 721.45 | G5: 619.47 | H5: 1081.22 | I5: 795.71 | J5: 816.43 | K5: 756.42 | L5: 649.85 | M5: 8445.69
A6: Housing | E6: 63.66 | H6: 49.46 | I6: 197.48 | K6: 210.25 | L6: 37.12 | M6: 557.97
A7: Insurance | B7: 79.38 | C7: 79.38 | D7: 79.38 | E7: 79.38 | F7: 79.38 | G7: 79.38 | H7: 79.66 | I7: 79.66 | J7: 80.08 | K7: 80.08 | L7: 80.08 | M7: 875.84
A8: Medical | D8: 432 | J8: 85.76 | M8: 517.76
A9: Misc | B9: 26.49 | E9: 16 | F9: 9.75 | G9: 83 | H9: 5.1 | I9: 39.79 | J9: 1203.45 | L9: 51.11 | M9: 1434.69
A10: People | C10: 49 | D10: 168.2 | H10: 51.5 | I10: 25.75 | L10: 103 | M10: 397.45
A11: Personal_Spending | B11: 872.44 | C11: 150.01 | D11: 748.11 | E11: 463.83 | F11: 886.58 | G11: 703.27 | H11: 650.74 | I11: 516.82 | J11: 414.19 | K11: 728.9 | L11: 465.36 | M11: 6600.25
A12: Recreation_Entertainment | B12: 225.75 | C12: 528.66 | D12: 835.47 | E12: 636.02 | F12: 1487.07 | G12: 1215.86 | H12: 854.48 | I12: 91.71 | J12: 310.69 | K12: 896.55 | L12: 205.88 | M12: 7288.14
A13: Transportation | B13: 145.57 | C13: 333.19 | D13: 307.96 | E13: 316.07 | F13: 682.91 | G13: 455.84 | H13: 757.2 | I13: 32.04 | J13: 384.2 | K13: 565.63 | L13: 67.9 | M13: 4048.51
A14: Utilities | B14: 294.79 | C14: 70 | D14: 70 | E14: 70 | F14: 70 | G14: 70 | H14: 91 | I14: 200.33 | J14: 277.03 | K14: 231.6 | L14: 161.6 | M14: 1606.35
A15: Grand Total | B15: 2191.71 | C15: 1458.53 | D15: 3905.37 | E15: 2590.27 | F15: 3937.14 | G15: 3226.82 | H15: 3620.36 | I15: 1979.29 | J15: 3571.83 | K15: 3469.43 | L15: 1821.9 | M15: 31772.65
A21: Sum of Debit_Amount | B21: Column Labels
A22: Row Labels | B22: 1/2022 | C22: 2/2022 | D22: 3/2022 | E22: 4/2022 | F22: 5/2022 | G22: 6/2022 | H22: 7/2022 | I22: 8/2022 | J22: Grand Total
A23: credit | B23: -5236.91 | C23: -1307.35 | D23: -1969.1 | E23: -2074.62 | F23: -3000 | G23: -4974.91 | H23: -3600 | I23: -1230.83 | J23: -23393.72
A24: Food | B24: -40 | D24: 33 | J24: -7
A25: Housing | B25: -933.34 | C25: -1204.29 | D25: -1400 | E25: -1400 | F25: -1400 | G25: -1400 | H25: -1400 | I25: -1073.34 | J25: -10210.97
A26: income | B26: 5616.86 | C26: 7196.43 | D26: 4480.14 | E26: 4543.15 | F26: 4965.79 | G26: 7448.69 | H26: 4965.79 | I26: 4435.02 | J26: 43651.87
A27: Misc | B27: -10 | J27: -10
A28: People | B28: -256.76 | C28: -2240.31 | D28: -1384.09 | E28: -668 | F28: -468.47 | G28: -66.07 | H28: 0 | I28: -1000 | J28: -6083.7
A29: Personal_Spending | B29: -90 | C29: -210 | J29: -300
A30: Recreation_Entertainment | B30: -623.34 | D30: -52 | E30: -59 | F30: -276.83 | H30: -25.48 | I30: -25.48 | J30: -1062.13
A31: Transportation | H31: -64 | J31: -64
A32: Utilities | B32: 265.47 | C32: -137.17 | D32: -229.5 | E32: -197.97 | F32: -193.04 | G32: -271.77 | H32: -202.46 | I32: -278.59 | J32: -1245.03
A33: Grand Total | B33: -1308.02 | C33: 2097.31 | D33: -521.55 | E33: 143.56 | F33: -372.55 | G33: 735.94 | H33: -326.15 | I33: 826.78 | J33: 1275.32

Sheet People Summary
A1: Category_2 | B1: People
A3: Sum of Amount | B3: Date
A4: Short_Desc | B4: 02/2022 | C4: 03/2022 | D4: 07/2022 | E4: 08/2022 | F4: 11/2022 | G4: Grand Total
A5: dad | B5: 49 | C5: 42 | G5: 91
A6: don | D6: 51.5 | G6: 51.5
A7: Jayelin | E7: 25.75 | F7: 103 | G7: 128.75
A8: tahjei | C8: 126.2 | G8: 126.2
A9: Grand Total | B9: 49 | C9: 168.2 | D9: 51.5 | E9: 25.75 | F9: 103 | G9: 397.45
A15: Category_2 | B15: People
A17: Sum of Amount | B17: Column Labels
A18: Row Labels | B18: 1/2022 | C18: 2/2022 | D18: 3/2022 | E18: 4/2022 | F18: 5/2022 | G18: 6/2022 | H18: 7/2022 | I18: 8/2022 | J18: Grand Total
A19: Amanda | F19: 77 | J19: 77
A20: atm | B20: 2.5 | J20: 2.5
A21: Carmen | E21: 35 | J21: 35
A22: discover | C22: 771.1 | J22: 771.1
A23: Don | B23: 120 | C23: 120 | G23: 110 | J23: 350
A24: Dorry | D24: 5 | E24: 110 | G24: 120 | J24: 235
A25: Jayelin | B25: 100 | D25: 110 | E25: 93 | F25: 40 | J25: 343
A26: mom | B26: 505 | C26: 485 | E26: 430 | F26: 500 | G26: 800 | H26: 200 | J26: 2920
A27: refund | F27: 82.52 | J27: 82.52
A28: Shevon | D28: 60 | G28: 50 | J28: 110
A29: Venmo | D29: 224.91 | F29: 66.01 | J29: 290.92
A30: Vincent | B30: 477.73 | C30: 2074.21 | D30: 1566 | G30: 186.07 | J30: 4304.01
A31: zoo | B31: 6.99 | J31: 6.99
A32: tahjei | I32: 1000 | J32: 1000
A33: Grand Total | B33: 1212.22 | C33: 3450.31 | D33: 1965.91 | E33: 668 | F33: 765.53 | G33: 1266.07 | H33: 200 | I33: 1000 | J33: 10528.04

Sheet Short Desc Summary
A3: Sum of Amount | D3: Date
A4: Category | B4: Short_Desc | C4: Reoccurring_Flag | D4: 01/2022 | E4: 02/2022 | F4: 03/2022 | G4: 04/2022 | H4: 05/2022 | I4: 06/2022 | J4: 07/2022 | K4: 08/2022 | L4: 09/2022 | M4: 10/2022 | N4: 11/2022 | O4: Grand Total
A5: Automotive | B5: car | C5: No | D5: 42.34 | J5: 21 | K5: 130.33 | L5: 13.52 | O5: 207.19
A6: Education | B6: clothing | C6: No | J6: 40 | O6: 40
A7: Education | B7: learning | C7: No | G7: 21.71 | I7: 298 | K7: 33 | O7: 352.71
A8: Education | B8: live_nba | C8: No | J8: 60.25 | O8: 60.25
A9: Gasoline | B9: conv_store | C9: No | D9: 2.99 | I9: 11.8 | O9: 14.79
A10: Gasoline | B10: gas_station | C10: No | D10: 89.42 | F10: 293.1 | G10: 3.59 | H10: 73.21 | J10: 229.64 | L10: 332.22 | M10: 111.99 | N10: 48.65 | O10: 1181.82
A11: Gasoline | B11: restaurant | C11: No | F11: 49.43 | O11: 49.43
A12: Government Services | B12: moving | C12: No | L12: 1.1 | O12: 1.1
A13: Government Services | B13: museum | C13: No | F13: 35 | O13: 35
A14: Home Improvement | B14: home_supplies | C14: No | J14: 49.46 | K14: 197.48 | M14: 7.2 | O14: 254.14
A15: Interest | B15: interest | C15: No | H15: 50.48 | I15: 99.24 | J15: 99.19 | K15: 61.69 | O15: 310.6
A16: Medical Services | B16: medical | C16: No | F16: 432 | L16: 85.76 | O16: 517.76
A17: Medical Services | B17: oculus | C17: No | H17: 37.5 | O17: 37.5
A18: Merchandise | B18: airport | C18: No | I18: 59.32 | J18: 13.96 | N18: 8.35 | O18: 81.63
A19: Merchandise | B19: amazon | C19: No | D19: 135.74 | E19: 23.31 | F19: 21.22 | G19: 277.85 | H19: 458.28 | I19: 55.16 | J19: 94.57 | K19: 52.1 | L19: 189.81 | M19: 25.04 | N19: 146.86 | O19: 1479.94
A20: Merchandise | B20: apple_tv | C20: Yes | D20: 5.29 | E20: 5.29 | F20: 5.29 | G20: 5.29 | H20: 5.29 | I20: 5.29 | J20: 5.29 | K20: 5.29 | L20: 5.29 | M20: 5.29 | N20: 5.29 | O20: 58.19
A21: Merchandise | B21: blossom | C21: Yes | G21: 31.79 | O21: 31.79
A22: Merchandise | B22: bookstore | C22: No | I22: 132.62 | O22: 132.62
A23: Merchandise | B23: breaking_points | C23: Yes | D23: 10 | E23: 10 | F23: 10 | G23: 10 | H23: 10 | I23: 10 | J23: 10 | K23: 10 | L23: 10 | M23: 10 | N23: 10 | O23: 110
A24: Merchandise | B24: cell_phone | C24: No | D24: 70 | E24: 70 | F24: 70 | G24: 70 | H24: 70 | I24: 70 | J24: 70 | K24: 70 | L24: 70 | M24: 70 | O24: 700
A25: Merchandise | B25: clothes | C25: No | F25: 239.23 | O25: 239.23
A26: Merchandise | B26: clothing | C26: No | F26: 277.61 | H26: 65.18 | I26: 30.87 | J26: 132.49 | K26: 106.07 | M26: 164.1 | O26: 776.32
A27: Merchandise | B27: concert | C27: No | F27: 22 | I27: 44 | O27: 66
A28: Merchandise | B28: concerts | C28: No | G28: 110 | O28: 110
A29: Merchandise | B29: conv_store | C29: No | D29: 30.11 | F29: 64.73 | G29: 24.02 | H29: 17.52 | I29: 125.56 | J29: 113.16 | K29: 129.1 | M29: 27.17 | N29: 61.1 | O29: 592.47
A30: Merchandise | B30: crunchy_roll | C30: Yes | E30: 10.59 | F30: 10.59 | G30: 10.59 | O30: 31.77
A31: Merchandise | B31: dad | C31: No | F31: 42 | O31: 42
A32: Merchandise | B32: disney | C32: Yes | F32: 79.99 | O32: 79.99
A33: Merchandise | B33: don | C33: No | J33: 51.5 | O33: 51.5
A34: Merchandise | B34: fast_food | C34: No | F34: 51.7 | H34: 5.3 | I34: 18.8 | J34: 36.07 | O34: 111.87
A35: Merchandise | B35: gas_station | C35: No | F35: 0.86 | H35: 4.08 | O35: 4.94
A36: Merchandise | B36: grammarly | C36: Yes | D36: 30 | E36: 30 | O36: 60
A37: Merchandise | B37: hair_supplies | C37: No | F37: 47.51 | O37: 47.51
A38: Merchandise | B38: hbo | C38: Yes | D38: 15.89 | E38: 15.89 | F38: 15.89 | G38: 15.89 | H38: 15.89 | I38: 15.89 | J38: 15.89 | K38: 15.89 | L38: 15.89 | M38: 15.89 | N38: 15.89 | O38: 174.79
A39: Merchandise | B39: home | C39: No | G39: 63.66 | O39: 63.66
A40: Merchandise | B40: home_supplies | C40: No | M40: 64.52 | N40: 37.12 | O40: 101.64
A41: Merchandise | B41: Jayelin | C41: No | K41: 25.75 | N41: 103 | O41: 128.75
A42: Merchandise | B42: learning | C42: No | L42: 10 | M42: 119 | N42: 10 | O42: 139
A43: Merchandise | B43: live_baseball | C43: No | G43: 32.57 | O43: 32.57
A44: Merchandise | B44: live_event | C44: No | F44: 11.94 | O44: 11.94
A45: Merchandise | B45: meal_lime | C45: Yes | H45: 3.17 | I45: 3.17 | J45: 3.17 | K45: 3.17 | L45: 3.17 | M45: 3.17 | O45: 19.02
A46: Merchandise | B46: moving | C46: No | K46: 39.79 | O46: 39.79
A47: Merchandise | B47: museum | C47: No | I47: 31.96 | O47: 31.96
A48: Merchandise | B48: music_festival | C48: No | L48: 43.72 | O48: 43.72
A49: Merchandise | B49: nba_league_pass | C49: Yes | E49: 14.99 | F49: 14.99 | G49: 14.99 | O49: 44.97
A50: Merchandise | B50: netflix | C50: Yes | D50: 14.83 | E50: 14.83 | F50: 16.42 | G50: 16.42 | H50: 10.59 | I50: 10.59 | J50: 10.59 | K50: 10.59 | L50: 10.59 | M50: 10.59 | N50: 10.59 | O50: 136.63
A51: Merchandise | B51: nvidia | C51: Yes | D51: 4.99 | E51: 4.99 | F51: 4.99 | G51: 4.99 | O51: 19.96
A52: Merchandise | B52: oculus | C52: No | H52: 284.7 | I52: 104.19 | O52: 388.89
A53: Merchandise | B53: onlyfans | C53: No | D53: 28.98 | E53: 23 | F53: 17.99 | G53: 58.25 | H53: 37.17 | I53: 69.05 | J53: 185.3 | K53: 29.65 | L53: 7.13 | M53: 56.71 | O53: 513.23
A54: Merchandise | B54: parking | C54: No | J54: 415 | O54: 415
A55: Merchandise | B55: pay_wall | C55: Yes | D55: 20 | E55: 29.99 | O55: 49.99
A56: Merchandise | B56: professional | C56: No | G56: 43.43 | H56: 43.43 | J56: 37.1 | K56: 132.77 | O56: 256.73
A57: Merchandise | B57: restaurant | C57: No | F57: 77 | M57: 77.95 | O57: 154.95
A58: Merchandise | B58: ride_share | C58: No | D58: 56.15 | H58: 27.99 | M58: 18.27 | N58: 10.9 | O58: 113.31
A59: Merchandise | B59: sport_stuff | C59: No | D59: 10.79 | O59: 10.79
A60: Merchandise | B60: spotify | C60: Yes | D60: 9.99 | E60: 9.99 | F60: 9.99 | G60: 9.99 | H60: 9.99 | I60: 9.99 | J60: 9.99 | K60: 9.99 | L60: 9.99 | M60: 14.98 | N60: 14.98 | O60: 119.87
A61: Merchandise | B61: staples | C61: No | D61: 20.72 | F61: 17.59 | O61: 38.31
A62: Merchandise | B62: state_farm | C62: Yes | D62: 79.38 | E62: 79.38 | F62: 79.38 | G62: 79.38 | H62: 79.38 | I62: 79.38 | J62: 79.66 | K62: 79.66 | L62: 80.08 | M62: 80.08 | N62: 80.08 | O62: 875.84
A63: Merchandise | B63: stretch_zone | C63: No | D63: 79 | E63: 5 | O63: 84
A64: Merchandise | B64: target | C64: No | D64: 153.88 | G64: 47.34 | H64: 211.57 | J64: 77.89 | K64: 55.34 | L64: 75.28 | O64: 621.3
A65: Merchandise | B65: tennis | C65: No | G65: 44 | J65: 20 | O65: 64
A66: Merchandise | B66: unsure | C66: No | D66: 26.49 | N66: 26.49 | O66: 52.98
A67: Merchandise | B67: video_games | C67: No | L67: 43.43 | O67: 43.43
A68: Merchandise | B68: wallet | C68: No | I68: 24.26 | O68: 24.26
A69: Merchandise | B69: walmart | C69: No | E69: 126.7 | O69: 126.7
A70: Merchandise | B70: youtube_tv | C70: Yes | G70: 70.58 | O70: 70.58
A71: Payments and Credits | B71: air_travel | C71: No | I71: -8 | O71: -8
A72: Payments and Credits | B72: clothing | C72: No | K72: -106.07 | O72: -106.07
A73: Payments and Credits | B73: fubo_tv | C73: Yes | J73: -1 | O73: -1
A74: Payments and Credits | B74: onlyfans | C74: No | K74: -3.72 | O74: -3.72
A75: Payments and Credits | B75: stretch_zone | C75: No | E75: -5 | O75: -5
A76: Restaurants | B76: coffee | C76: No | F76: 10 | H76: 169.8 | I76: 22.06 | K76: 16.13 | L76: 8.2 | M76: 39.74 | O76: 265.93
A77: Restaurants | B77: concert | C77: No | J77: 97.26 | O77: 97.26
A78: Restaurants | B78: fast_food | C78: No | D78: 173.63 | E78: 82.05 | F78: 380.99 | G78: 291.46 | H78: 184.81 | I78: 76.88 | J78: 208.81 | K78: 348.18 | L78: 109.29 | M78: 161.89 | N78: 38.64 | O78: 2056.63
A79: Restaurants | B79: hoover_dam | C79: No | J79: 21.22 | O79: 21.22
A80: Restaurants | B80: live_nba | C80: No | H80: 69.09 | O80: 69.09
A81: Restaurants | B81: movies | C81: No | N81: 31.79 | O81: 31.79
A82: Restaurants | B82: restaurant | C82: No | D82: 202.41 | E82: 18 | F82: 669.7 | G82: 243.61 | H82: 324.04 | I82: 319.96 | J82: 443.9 | K82: 279.35 | L82: 524.62 | M82: 391.03 | N82: 436.62 | O82: 3853.24
A83: Restaurants | B83: ride_share | C83: No | G83: 40.47 | H83: 22.56 | I83: 59.34 | O83: 122.37
A84: Restaurants | B84: vending | C84: No | J84: 5.1 | O84: 5.1
A85: Restaurants | B85: work_lunch | C85: No | D85: 12.62 | E85: 15.78 | F85: 13.16 | J85: 24.8 | O85: 66.36
A86: Services | B86: air_travel | C86: No | I86: 16 | M86: 21.88 | O86: 37.88
A87: Services | B87: aps | C87: No | D87: 182.45 | O87: 182.45
A88: Services | B88: barbershop | C88: No | F88: 80.22 | H88: 80.6 | O88: 160.82
A89: Services | B89: dad | C89: No | E89: 49 | O89: 49
A90: Services | B90: fast_food | C90: No | H90: 37.5 | O90: 37.5
A91: Services | B91: fubo_tv | C91: Yes | J91: 1 | O91: 1
A92: Services | B92: hulu | C92: Yes | D92: 12.99 | E92: 12.99 | F92: 12.99 | G92: 12.99 | O92: 51.96
A93: Services | B93: learning | C93: No | D93: 240 | H93: 10 | J93: 109.58 | N93: 119.4 | O93: 478.98
A94: Services | B94: live_nba | C94: No | J94: 79 | O94: 79
A95: Services | B95: medium | C95: Yes | G95: 50 | O95: 50
A96: Services | B96: moving | C96: No | L96: 226.84 | O96: 226.84
A97: Services | B97: museum | C97: No | F97: 145.4 | O97: 145.4
A98: Services | B98: parking | C98: No | F98: 14 | J98: 21.35 | L98: 8 | O98: 43.35
A99: Services | B99: political_cause | C99: Yes | I99: 25 | J99: 25 | K99: 25 | L99: 25 | M99: 25 | N99: 25 | O99: 150
A100: Services | B100: professional | C100: No | M100: 87 | N100: 68 | O100: 155
A101: Services | B101: restaurant | C101: No | M101: 45 | O101: 45
A102: Services | B102: tahjei | C102: No | F102: 126.2 | O102: 126.2
...

Sheet Reoccuring
A1: Reoccurring_Flag | B1: Yes
A3: Sum of Amount | C3: Date
A4: Category_2 | B4: Short_Desc | C4: 01/2022 | D4: 02/2022 | E4: 03/2022 | F4: 04/2022 | G4: 05/2022 | H4: 06/2022 | I4: 07/2022 | J4: 08/2022 | K4: 09/2022 | L4: 10/2022 | M4: 11/2022 | N4: Grand Total
A5: Insurance | B5: state_farm | C5: 79.38 | D5: 79.38 | E5: 79.38 | F5: 79.38 | G5: 79.38 | H5: 79.38 | I5: 79.66 | J5: 79.66 | K5: 80.08 | L5: 80.08 | M5: 80.08 | N5: 875.84
A6: Personal_Spending | B6: political_cause | H6: 25 | I6: 25 | J6: 25 | K6: 25 | L6: 25 | M6: 25 | N6: 150
A7: Recreation_Entertainment | B7: apple_tv | C7: 5.29 | D7: 5.29 | E7: 5.29 | F7: 5.29 | G7: 5.29 | H7: 5.29 | I7: 5.29 | J7: 5.29 | K7: 5.29 | L7: 5.29 | M7: 5.29 | N7: 58.19
A8: Recreation_Entertainment | B8: blossom | F8: 31.79 | N8: 31.79
A9: Recreation_Entertainment | B9: breaking_points | C9: 10 | D9: 10 | E9: 10 | F9: 10 | G9: 10 | H9: 10 | I9: 10 | J9: 10 | K9: 10 | L9: 10 | M9: 10 | N9: 110
A10: Recreation_Entertainment | B10: crunchy_roll | D10: 10.59 | E10: 10.59 | F10: 10.59 | N10: 31.77
A11: Recreation_Entertainment | B11: disney | E11: 79.99 | N11: 79.99
A12: Recreation_Entertainment | B12: fubo_tv | I12: 0 | N12: 0
A13: Recreation_Entertainment | B13: grammarly | C13: 30 | D13: 30 | N13: 60
A14: Recreation_Entertainment | B14: hbo | C14: 15.89 | D14: 15.89 | E14: 15.89 | F14: 15.89 | G14: 15.89 | H14: 15.89 | I14: 15.89 | J14: 15.89 | K14: 15.89 | L14: 15.89 | M14: 15.89 | N14: 174.79
A15: Recreation_Entertainment | B15: hulu | C15: 12.99 | D15: 12.99 | E15: 12.99 | F15: 12.99 | N15: 51.96
A16: Recreation_Entertainment | B16: meal_lime | G16: 3.17 | H16: 3.17 | I16: 3.17 | J16: 3.17 | K16: 3.17 | L16: 3.17 | N16: 19.02
A17: Recreation_Entertainment | B17: medium | F17: 50 | N17: 50
A18: Recreation_Entertainment | B18: nba_league_pass | D18: 14.99 | E18: 14.99 | F18: 14.99 | N18: 44.97
A19: Recreation_Entertainment | B19: netflix | C19: 14.83 | D19: 14.83 | E19: 16.42 | F19: 16.42 | G19: 10.59 | H19: 10.59 | I19: 10.59 | J19: 10.59 | K19: 10.59 | L19: 10.59 | M19: 10.59 | N19: 136.63
A20: Recreation_Entertainment | B20: nvidia | C20: 4.99 | D20: 4.99 | E20: 4.99 | F20: 4.99 | N20: 19.96
A21: Recreation_Entertainment | B21: pay_wall | C21: 20 | D21: 29.99 | N21: 49.99
A22: Recreation_Entertainment | B22: spotify | C22: 9.99 | D22: 9.99 | E22: 9.99 | F22: 9.99 | G22: 9.99 | H22: 9.99 | I22: 9.99 | J22: 9.99 | K22: 9.99 | L22: 14.98 | M22: 14.98 | N22: 119.87
A23: Recreation_Entertainment | B23: viki | G23: 10.85 | H23: 10.85 | I23: 10.85 | J23: 10.85 | N23: 43.4
A24: Recreation_Entertainment | B24: youtube_tv | D24: 70.58 | E24: 54.29 | F24: 86.47 | G24: 70.58 | K24: 64.99 | L24: 80.88 | M24: 64.99 | N24: 492.78
A25: Grand Total | C25: 203.36 | D25: 309.51 | E25: 314.81 | F25: 348.79 | G25: 215.74 | H25: 170.16 | I25: 170.44 | J25: 170.44 | K25: 225 | L25: 245.88 | M25: 226.82 | N25: 2600.95

Sheet The plan
B1: Discover | C1: Vincet | D1: Spending | E1: Saving | F1: Student Loans | G1: Rent | H1: D.Payment | I1: V. Payment | J1: Income | K1: Cum. Leftover | L1: Actual Dis BAL | M1: Actual WF BAL | N1: Actual Income | O1: Actual Payment | P1: Acutal Leftover | Q1: Actual Spending | R1: Actual Savings
A2: Today | B2: 5340.1 | C2: 3749.93
A3: 44774 | B3: 0 | C3: =C2+B2-81.42 -> 9008.61 | D3: 500 | L3: 159.81 | M3: 711.33
A4: 44785 | B4: =B3+D3-H4 -> 0 | C4: =C3-I4 -> 9008.61 | D4: 500 | H4: 500 | I4: 0 | J4: 2000 | K4: =J4-I4-H4-G4-F4-E4 -> 1500 | L4: 962.04 | M4: 2936.29 | N4: 2482.9 | O4: 962.04 | P4: =M4-O4 -> 1974.25 | Q4: 961.3
A5: =A4+14 -> 44799 | B5: =B4+D4-H5 -> 0 | C5: =C4-I5 -> 9008.61 | D5: 1200 | G5: 1073.34 | H5: 500 | I5: 0 | J5: =J4 -> 2000 | K5: =J5-I5-H5-G5-F5-E5+K4 -> 1926.66 | L5: 451.88 | M5: 1909.18 | N5: 1952.12 | O5: =L5 -> 451.88 | P5: =M5-O5 -> 1457.3
A6: =A5+14 -> 44813 | B6: =B5+D5-H6 -> 500 | C6: =C5-I6 -> 7708.61 | D6: 500 | H6: 700 | I6: 1300 | J6: =J5 -> 2000 | K6: =J6-I6-H6-G6-F6-E6+K5 -> 1926.66
A7: =A6+14 -> 44827 | B7: =B6+D6-H7 -> 0 | C7: =C6-I7 -> 7458.61 | D7: 500 | G7: 750 | H7: 1000 | I7: 250 | J7: =J6 -> 2000 | K7: =J7-I7-H7-G7-F7-E7+K6 -> 1926.66
A8: =A7+14 -> 44841 | B8: =B7+D7-H8 -> 0 | C8: =C7-I8 -> 5958.61 | D8: 500 | H8: 500 | I8: 1500 | J8: =J7 -> 2000 | K8: =J8-I8-H8-G8-F8-E8+K7 -> 1926.66
A9: =A8+14 -> 44855 | B9: =B8+D8-H9 -> 350 | C9: =C8-I9 -> 5208.61 | D9: 150 | F9: 348 | G9: 750 | H9: 150 | I9: 750 | J9: =J8 -> 2000 | K9: =J9-I9-H9-G9-F9-E9+K8 -> 1928.66
A10: =A9+14 -> 44869 | B10: =B9+D9-H10 -> 0 | C10: =C9-I10 -> 3708.61 | D10: 500 | H10: 500 | I10: 1500 | J10: =J9 -> 2000 | K10: =J10-I10-H10-G10-F10-E10+K9 -> 1928.66
A11: =A10+14 -> 44883 | B11: =B10+D10-H11 -> 350 | C11: =C10-I11 -> 2958.61 | D11: 150 | F11: 348 | G11: 750 | H11: 150 | I11: 750 | J11: =J10 -> 2000 | K11: =J11-I11-H11-G11-F11-E11+K10 -> 1930.66
A12: =A11+14 -> 44897 | B12: =B11+D11-H12 -> 0 | C12: =C11-I12 -> 1500 | D12: 500 | H12: 500 | I12: =1500-41.39 -> 1458.61 | J12: =J11 -> 2000 | K12: =J12-I12-H12-G12-F12-E12+K11 -> 1972.05
A13: =A12+14 -> 44911 | B13: =B12+D12-H13 -> 350 | C13: =C12-I13 -> 1500 | D13: 150 | F13: 348 | H13: 150 | I13: 0 | J13: =J12 -> 2000 | K13: =J13-I13-H13-G13-F13-E13+K12 -> 3474.05
A14: =A13+14 -> 44925 | B14: =B13+D13-H14 -> 0 | C14: =C13-I14 -> 1500 | D14: 500 | G14: 750 | H14: 500 | I14: 0 | J14: =J13 -> 2000 | K14: =J14-I14-H14-G14-F14-E14+K13 -> 4224.05
A15: =A14+14 -> 44939 | B15: =B14+D14-H15 -> 0 | C15: 9462 | D15: 500 | F15: 348 | H15: 500 | I15: 0 | J15: =J14 -> 2000 | K15: =J15-I15-H15-G15-F15-E15+K14 -> 5376.05
A16: =A15+14 -> 44953 | B16: =B15+D15-H16 -> 0 | C16: =C15-I16 -> 7962 | D16: 500 | G16: 750 | H16: 500 | I16: 1500 | J16: =J15 -> 2000 | K16: =J16-I16-H16-G16-F16-E16+K15 -> 4626.05
A17: =A16+14 -> 44967 | B17: =B16+D16-H17 -> 0 | C17: =C16-I17 -> 6462 | D17: 500 | F17: 348 | H17: 500 | I17: 1500 | J17: =J16 -> 2000 | K17: =J17-I17-H17-G17-F17-E17+K16 -> 4278.05
A18: =A17+14 -> 44981 | B18: =B17+D17-H18 -> 0 | C18: =C17-I18 -> 4962 | D18: 500 | G18: 750 | H18: 500 | I18: 1500 | J18: =J17 -> 2000 | K18: =J18-I18-H18-G18-F18-E18+K17 -> 3528.05
A19: =A18+14 -> 44995 | B19: =B18+D18-H19 -> 0 | C19: =C18-I19 -> 3462 | D19: 500 | F19: 348 | H19: 500 | I19: 1500 | J19: =J18 -> 2000 | K19: =J19-I19-H19-G19-F19-E19+K18 -> 3180.05
A20: =A19+14 -> 45009 | B20: =B19+D19-H20 -> 0 | C20: =C19-I20 -> 1962 | D20: 500 | G20: 750 | H20: 500 | I20: 1500 | J20: =J19 -> 2000 | K20: =J20-I20-H20-G20-F20-E20+K19 -> 2430.05
A21: =A20+14 -> 45023 | B21: =B20+D20-H21 -> 0 | C21: =C20-I21 -> 462 | D21: 500 | F21: 348 | H21: 500 | I21: 1500 | J21: =J20 -> 2000 | K21: =J21-I21-H21-G21-F21-E21+K20 -> 2082.05
A22: =A21+14 -> 45037 | B22: =B21+D21-H22 -> 0 | C22: =C21-I22 -> 0 | D22: 500 | G22: 750 | H22: 500 | I22: 462 | J22: =J21 -> 2000 | K22: =J22-I22-H22-G22-F22-E22+K21 -> 2370.05
A23: =A22+14 -> 45051 | B23: =B22+D22-H23 -> 0 | C23: =C22-I23 -> 0 | D23: 500 | E23: 1500 | F23: 348 | H23: 500 | I23: 0 | J23: =J22 -> 2000 | K23: =J23-I23-H23-G23-F23-E23+K22 -> 2022.05
A24: =A23+14 -> 45065 | B24: =B23+D23-H24 -> 0 | C24: =C23-I24 -> 0 | D24: 500 | G24: 750 | H24: 500 | I24: 0 | J24: =J23 -> 2000 | K24: =J24-I24-H24-G24-F24-E24+K23 -> 2772.05
A25: =A24+14 -> 45079 | B25: =B24+D24-H25 -> 0 | C25: =C24-I25 -> 0 | D25: 500 | E25: 1500 | H25: 500 | I25: 0 | J25: =J24 -> 2000 | K25: =J25-I25-H25-G25-F25-E25+K24 -> 2772.05
A26: =A25+14 -> 45093 | B26: =B25+D25-H26 -> 0 | C26: =C25-I26 -> 0 | D26: 500 | F26: 348 | H26: 500 | I26: 0 | J26: =J25 -> 2000 | K26: =J26-I26-H26-G26-F26-E26+K25 -> 3924.05
A27: =A26+14 -> 45107 | B27: =B26+D26-H27 -> 0 | C27: =C26-I27 -> 0 | D27: 500 | E27: 1500 | G27: 750 | H27: 500 | I27: 0 | J27: =J26 -> 2000 | K27: =J27-I27-H27-G27-F27-E27+K26 -> 3174.05
A28: =A27+14 -> 45121 | B28: =B27+D27-H28 -> 0 | C28: =C27-I28 -> 0 | D28: 500 | F28: 348 | H28: 500 | I28: 0 | J28: =J27 -> 2000 | K28: =J28-I28-H28-G28-F28-E28+K27 -> 4326.05
A29: =A28+14 -> 45135 | B29: =B28+D28-H29 -> 0 | C29: =C28-I29 -> 0 | D29: 500 | E29: 1500 | G29: 750 | H29: 500 | I29: 0 | J29: =J28 -> 2000 | K29: =J29-I29-H29-G29-F29-E29+K28 -> 3576.05
A30: =A29+14 -> 45149 | B30: =B29+D29-H30 -> 0 | C30: =C29-I30 -> 0 | D30: 500 | F30: 348 | H30: 500 | I30: 0 | J30: =J29 -> 2000 | K30: =J30-I30-H30-G30-F30-E30+K29 -> 4728.05
A31: =A30+14 -> 45163 | B31: =B30+D30-H31 -> 0 | C31: =C30-I31 -> 0 | D31: 500 | E31: 1500 | G31: 750 | H31: 500 | I31: 0 | J31: =J30 -> 2000 | K31: =J31-I31-H31-G31-F31-E31+K30 -> 3978.05
A32: =A31+14 -> 45177 | B32: =B31+D31-H32 -> 0 | C32: =C31-I32 -> 0 | D32: 500 | F32: 348 | H32: 500 | I32: 0 | J32: =J31 -> 2000 | K32: =J32-I32-H32-G32-F32-E32+K31 -> 5130.05
A33: =A32+14 -> 45191 | B33: =B32+D32-H33 -> 0 | C33: =C32-I33 -> 0 | D33: 500 | E33: 1500 | G33: 750 | H33: 500 | I33: 0 | J33: =J32 -> 2000 | K33: =J33-I33-H33-G33-F33-E33+K32 -> 4380.05
A34: =A33+14 -> 45205 | B34: =B33+D33-H34 -> 0 | C34: =C33-I34 -> 0 | D34: 500 | F34: 348 | H34: 500 | I34: 0 | J34: =J33 -> 2000 | K34: =J34-I34-H34-G34-F34-E34+K33 -> 5532.05
A35: =A34+14 -> 45219 | B35: =B34+D34-H35 -> 0 | C35: =C34-I35 -> 0 | D35: 500 | E35: 1500 | G35: 750 | H35: 500 | I35: 0 | J35: =J34 -> 2000 | K35: =J35-I35-H35-G35-F35-E35+K34 -> 4782.05
A36: =A35+14 -> 45233 | B36: =B35+D35-H36 -> 0 | C36: =C35-I36 -> 0 | D36: 500 | F36: 348 | H36: 500 | I36: 0 | J36: =J35 -> 2000 | K36: =J36-I36-H36-G36-F36-E36+K35 -> 5934.05
A37: =A36+14 -> 45247 | B37: =B36+D36-H37 -> 0 | C37: =C36-I37 -> 0 | D37: 500 | E37: 1500 | G37: 750 | H37: 500 | I37: 0 | J37: =J36 -> 2000 | K37: =J37-I37-H37-G37-F37-E37+K36 -> 5184.05
A38: =A37+14 -> 45261 | B38: =B37+D37-H38 -> 0 | C38: =C37-I38 -> 0 | D38: 500 | H38: 500 | I38: 0 | J38: =J37 -> 2000 | K38: =J38-I38-H38-G38-F38-E38+K37 -> 6684.05
A39: =A38+14 -> 45275 | B39: =B38+D38-H39 -> 0 | C39: =C38-I39 -> 0 | D39: 500 | E39: 1500 | F39: 348 | H39: 500 | I39: 0 | J39: =J38 -> 2000 | K39: =J39-I39-H39-G39-F39-E39+K38 -> 6336.05
A40: =A39+14 -> 45289 | B40: =B39+D39-H40 -> 0 | C40: =C39-I40 -> 0 | D40: 500 | G40: 750 | H40: 500 | I40: 0 | J40: =J39 -> 2000 | K40: =J40-I40-H40-G40-F40-E40+K39 -> 7086.05
E41: =SUM(E2:E40) -> 13500 | F41: =SUM(F2:F40) -> 5220 | G41: =SUM(G2:G40) -> 13073.34 | H41: =SUM(H2:H40) -> 18150 | I41: =SUM(I2:I40) -> 16970.61
