Workbook
Name AprSun1: DATE(CalendarYear,4,1)-WEEKDAY(DATE(CalendarYear,4,1))
Name AugSun1: DATE(CalendarYear,8,1)-WEEKDAY(DATE(CalendarYear,8,1))
Name budget: '[1]Pivot (2021)'!$A$2
Name CalendarYear: [0]!Year1
Name CategoryNames: 'Categories - WIP'!$A$1:$L$1
Name DecSun1: DATE(CalendarYear,12,1)-WEEKDAY(DATE(CalendarYear,12,1))
Name Essential: 'Categories - WIP'!$A$2:$A$12
Name Expense_Lookup: Discover!$T:$U
Name FebSun1: DATE(CalendarYear,2,1)-WEEKDAY(DATE(CalendarYear,2,1))
Name JanSun1: DATE(CalendarYear,1,1)-WEEKDAY(DATE(CalendarYear,1,1))
Name JulSun1: DATE(CalendarYear,7,1)-WEEKDAY(DATE(CalendarYear,7,1))
Name JunSun1: DATE(CalendarYear,6,1)-WEEKDAY(DATE(CalendarYear,6,1))
Name LastCol: COUNTA('PERSONAL BUDGET - WIP'!$4:$4)+1
Name MarSun1: DATE(CalendarYear,3,1)-WEEKDAY(DATE(CalendarYear,3,1))
Name MaySun1: DATE(CalendarYear,5,1)-WEEKDAY(DATE(CalendarYear,5,1))
Name Non_Essential: 'Categories - WIP'!$B$2:$B$12
Name NovSun1: DATE(CalendarYear,11,1)-WEEKDAY(DATE(CalendarYear,11,1))
Name OctSun1: DATE(CalendarYear,10,1)-WEEKDAY(DATE(CalendarYear,10,1))
Name PrintArea_SET: OFFSET('PERSONAL BUDGET - WIP'!$C$2,,,MATCH(REPT("z",255),'PERSONAL BUDGET - WIP'!$C:$C),LastCol)
Name SepSun1: DATE(CalendarYear,9,1)-WEEKDAY(DATE(CalendarYear,9,1))
Name Year1: VALUE(LEFT(#REF!,4))

Sheet Wells Fargo
A1: Month | B1: Day | C1: Date | D1: Description2 | E1: Description | F1: Amount | G1: Primary | H1: Main Category | I1: Secondary Category | J1: Specific Category
A2: =MONTH(C2) -> 1 | B2: =DAY(C2) -> 4 | C2: 44200 | D2: DISCOVER | E2: DISCOVER E-PAYMENT 210101 4732 LEWIS SEAN | F2: -700 | G2: Credit | H2: Essential | I2: SAVINGS, INVESTING, & DEBT | J2: Credit
A3: =MONTH(C3) -> 1 | B3: =DAY(C3) -> 4 | C3: 44200 | D3: IRS | E3: IRS TREAS 310 XXTAXEIP2 010421 XXXXXXXXXX00908 LEWIS, SEAN | F3: 600 | G3: Stimulus 1
A4: =MONTH(C4) -> 1 | B4: =DAY(C4) -> 15 | C4: 44211 | D4: DISCOVER | E4: DISCOVER E-PAYMENT 210115 4732 LEWIS SEAN | F4: -729.23 | G4: Credit | H4: Essential | I4: SAVINGS, INVESTING, & DEBT | J4: Credit
A5: =MONTH(C5) -> 1 | B5: =DAY(C5) -> 15 | C5: 44211 | D5: Elephant | E5: Elephant Ins PAYROLL 210113 2087 Lewis Sean | F5: 1459.65 | G5: Elephant
A6: =MONTH(C6) -> 1 | B6: =DAY(C6) -> 19 | C6: 44215 | D6: VENMO | E6: VENMO PAYMENT 5101219782 SEAN LEWIS | F6: -569.12 | G6: Vincent | H6: Essential | I6: SAVINGS, INVESTING, & DEBT | J6: Personal Debt
A7: =MONTH(C7) -> 1 | B7: =DAY(C7) -> 19 | C7: 44215 | D7: VENMO | E7: VENMO PAYMENT 5101208453 SEAN LEWIS | F7: -78.86 | G7: Amar - Electric | H7: Essential | I7: UTILITIES | J7: Electricity
A8: =MONTH(C8) -> 1 | B8: =DAY(C8) -> 19 | C8: 44215 | D8: VENMO | E8: VENMO CASHOUT 5117912825 SEAN LEWIS | F8: 150 | G8: Venmo Cash Out | H8: Essential | I8: SAVINGS, INVESTING, & DEBT | J8: Personal Debt
A9: =MONTH(C9) -> 1 | B9: =DAY(C9) -> 21 | C9: 44217 | D9: PURCHASE | E9: PURCHASE AUTHORIZED ON 01/20 CASH APP* 8774174551 CA S461020486646597 CARD 6634 | F9: -155 | G9: Cairo | H9: Non-Essential | I9: MISCELLANEUS | J9: Family
A10: =MONTH(C10) -> 1 | B10: =DAY(C10) -> 22 | C10: 44218 | D10: PURCHASE | E10: PURCHASE AUTHORIZED ON 01/21 SOCIETY OF ACTUARI 847-706-3620 IL S581021446560343 CARD 6634 | F10: -75 | G10: SOA | H10: Essential | I10: HOME | J10: Study Material (Pre Nationwide)
A11: =MONTH(C11) -> 1 | B11: =DAY(C11) -> 26 | C11: 44222 | D11: MONEY | E11: MONEY TRANSFER AUTHORIZED ON 01/26 FROM Sean Lewis VA S00581026542833832 CARD 6634 | F11: 155 | G11: Cairo | H11: Non-Essential | I11: MISCELLANEUS | J11: Family
A12: =MONTH(C12) -> 1 | B12: =DAY(C12) -> 28 | C12: 44224 | D12: ROBINHOOD | E12: ROBINHOOD Funds 210127 XXXXX4480 Sean Lewis | F12: -100 | G12: Investment | H12: Essential | I12: SAVINGS, INVESTING, & DEBT | J12: Securities
A13: =MONTH(C13) -> 1 | B13: =DAY(C13) -> 28 | C13: 44224 | D13: ROBINHOOD | E13: ROBINHOOD Funds 210127 XXXXX4480 Sean Lewis | F13: -50 | G13: Investment | H13: Essential | I13: SAVINGS, INVESTING, & DEBT | J13: Securities
A14: =MONTH(C14) -> 1 | B14: =DAY(C14) -> 28 | C14: 44224 | D14: ATM | E14: ATM CHECK DEPOSIT ON 01/28 3201 WEST CARY ST RICHMOND VA 0005841 ATM ID 0255N CARD 6634 | F14: 388.47 | G14: HSA
A15: =MONTH(C15) -> 1 | B15: =DAY(C15) -> 29 | C15: 44225 | D15: VENMO | E15: VENMO PAYMENT 5176119364 SEAN LEWIS | F15: -728.15 | G15: Vincent | H15: Essential | I15: SAVINGS, INVESTING, & DEBT | J15: Personal Debt
A16: =MONTH(C16) -> 1 | B16: =DAY(C16) -> 29 | C16: 44225 | D16: VENMO | E16: VENMO PAYMENT 5176123809 SEAN LEWIS | F16: -700 | G16: Amar - Rent | H16: Essential | I16: HOME | J16: Rent
A17: =MONTH(C17) -> 1 | B17: =DAY(C17) -> 29 | C17: 44225 | D17: Elephant | E17: Elephant Ins PAYROLL 210127 2087 Lewis Sean | F17: 1459.64 | G17: Elephant
A18: =MONTH(C18) -> 2 | B18: =DAY(C18) -> 2 | C18: 44229 | D18: Credit | E18: Credit Karma Transfer 210202 1416312297 Sean Lewis | F18: -1 | G18: Credit Karma | H18: Essential | I18: SAVINGS, INVESTING, & DEBT | J18: Securities
A19: =MONTH(C19) -> 2 | B19: =DAY(C19) -> 2 | C19: 44229 | D19: PURCHASE | E19: PURCHASE AUTHORIZED ON 02/02 CVS/PHARMACY #01 01988--3 RICHMOND VA P00381033853505879 CARD 6634 | F19: -36.84 | G19: Purchase | H19: Non-Essential | I19: PERSONAL SPENDING | J19: Conveinence Store
A20: =MONTH(C20) -> 2 | B20: =DAY(C20) -> 2 | C20: 44229 | D20: RTP | E20: RTP from VENMO on 02/02 Ref#20210202021000021P1BRJPM00020016153 | F20: 495 | G20: Vincent | H20: Essential | I20: SAVINGS, INVESTING, & DEBT | J20: Personal Debt
A21: =MONTH(C21) -> 2 | B21: =DAY(C21) -> 3 | C21: 44230 | D21: BEST | E21: BEST BUY PAYMENT 210202 140344289448116 SEAN LEWIS | F21: -157.47 | G21: Credit | H21: Essential | I21: SAVINGS, INVESTING, & DEBT | J21: Credit
A22: =MONTH(C22) -> 2 | B22: =DAY(C22) -> 3 | C22: 44230 | D22: PURCHASE | E22: PURCHASE AUTHORIZED ON 02/02 CASH APP*DON 8774174551 CA S381033547779628 CARD 6634 | F22: -600 | G22: Don | H22: Non-Essential | I22: MISCELLANEUS | J22: Family
A23: =MONTH(C23) -> 2 | B23: =DAY(C23) -> 4 | C23: 44231 | D23: ROBINHOOD | E23: ROBINHOOD Funds 210203 XXXXX4480 Sean Lewis | F23: -50 | G23: Investment | H23: Essential | I23: SAVINGS, INVESTING, & DEBT | J23: Securities
A24: =MONTH(C24) -> 2 | B24: =DAY(C24) -> 8 | C24: 44235 | D24: ROBINHOOD | E24: ROBINHOOD Funds 210205 XXXXX4480 Sean Lewis | F24: -40 | G24: Investment | H24: Essential | I24: SAVINGS, INVESTING, & DEBT | J24: Securities
A25: =MONTH(C25) -> 2 | B25: =DAY(C25) -> 8 | C25: 44235 | D25: ROBINHOOD | E25: ROBINHOOD Funds 210205 XXXXX4480 Sean Lewis | F25: -10 | G25: Investment | H25: Essential | I25: SAVINGS, INVESTING, & DEBT | J25: Securities
A26: =MONTH(C26) -> 2 | B26: =DAY(C26) -> 9 | C26: 44236 | D26: AVIDIA | E26: AVIDIA BANK SETL 210208 0268 LEWIS,SEAN | F26: 138.48 | G26: HSA
A27: =MONTH(C27) -> 2 | B27: =DAY(C27) -> 12 | C27: 44239 | D27: DISCOVER | E27: DISCOVER E-PAYMENT 210212 4732 LEWIS SEAN | F27: -715.37 | G27: Credit | H27: Essential | I27: SAVINGS, INVESTING, & DEBT | J27: Credit
A28: =MONTH(C28) -> 2 | B28: =DAY(C28) -> 12 | C28: 44239 | D28: VENMO | E28: VENMO PAYMENT 5259216200 SEAN LEWIS | F28: -350 | G28: Vincent | H28: Essential | I28: SAVINGS, INVESTING, & DEBT | J28: Personal Debt
A29: =MONTH(C29) -> 2 | B29: =DAY(C29) -> 12 | C29: 44239 | D29: ROBINHOOD | E29: ROBINHOOD Funds 210211 XXXXX4480 Sean Lewis | F29: -100 | G29: Investment | H29: Essential | I29: SAVINGS, INVESTING, & DEBT | J29: Securities
A30: =MONTH(C30) -> 2 | B30: =DAY(C30) -> 12 | C30: 44239 | D30: Elephant | E30: Elephant Ins PAYROLL 210210 2087 Lewis Sean | F30: 1809.65 | G30: Elephant
A31: =MONTH(C31) -> 2 | B31: =DAY(C31) -> 16 | C31: 44243 | D31: VENMO | E31: VENMO PAYMENT 5280886625 SEAN LEWIS | F31: -500 | G31: Vincent | H31: Essential | I31: SAVINGS, INVESTING, & DEBT | J31: Personal Debt
A32: =MONTH(C32) -> 2 | B32: =DAY(C32) -> 16 | C32: 44243 | D32: TD | E32: TD AMERITRADE ACH IN a9KLOZ6PGB LEWIS SEAN | F32: -100 | G32: Investment | H32: Essential | I32: SAVINGS, INVESTING, & DEBT | J32: Securities
A33: =MONTH(C33) -> 2 | B33: =DAY(C33) -> 16 | C33: 44243 | D33: ROBINHOOD | E33: ROBINHOOD Funds 210212 XXXXX4480 Sean Lewis | F33: -100 | G33: Investment | H33: Essential | I33: SAVINGS, INVESTING, & DEBT | J33: Securities
A34: =MONTH(C34) -> 2 | B34: =DAY(C34) -> 16 | C34: 44243 | D34: MONEY | E34: MONEY TRANSFER AUTHORIZED ON 02/16 FROM Sean Lewis VA S00301047447217307 CARD 6634 | F34: 492.5 | G34: Don | H34: Non-Essential | I34: MISCELLANEUS | J34: Family
A35: =MONTH(C35) -> 2 | B35: =DAY(C35) -> 17 | C35: 44244 | D35: ROBINHOOD | E35: ROBINHOOD Funds 210216 XXXXX4480 Sean Lewis | F35: -300 | G35: Investment | H35: Essential | I35: SAVINGS, INVESTING, & DEBT | J35: Securities
A36: =MONTH(C36) -> 2 | B36: =DAY(C36) -> 17 | C36: 44244 | D36: ROBINHOOD | E36: ROBINHOOD Funds 210216 XXXXX4480 Sean Lewis | F36: -150 | G36: Investment | H36: Essential | I36: SAVINGS, INVESTING, & DEBT | J36: Securities
A37: =MONTH(C37) -> 2 | B37: =DAY(C37) -> 17 | C37: 44244 | D37: ROBINHOOD | E37: ROBINHOOD Funds 210216 XXXXX4480 Sean Lewis | F37: -50 | G37: Investment | H37: Essential | I37: SAVINGS, INVESTING, & DEBT | J37: Securities
A38: =MONTH(C38) -> 2 | B38: =DAY(C38) -> 17 | C38: 44244 | D38: WEBULL | E38: WEBULL FINANCIAL ACH Feb 17 20210213000010 SEAN LEWIS | F38: 56.74 | G38: Investment | H38: Essential | I38: SAVINGS, INVESTING, & DEBT | J38: Securities
A39: =MONTH(C39) -> 2 | B39: =DAY(C39) -> 19 | C39: 44246 | D39: ROBINHOOD | E39: ROBINHOOD Funds 210218 XXXXX4480 Sean Lewis | F39: -100 | G39: Investment | H39: Essential | I39: SAVINGS, INVESTING, & DEBT | J39: Securities
A40: =MONTH(C40) -> 2 | B40: =DAY(C40) -> 19 | C40: 44246 | D40: AVIDIA | E40: AVIDIA BANK SETL 210218 0268 LEWIS,SEAN | F40: 138.47 | G40: HSA
A41: =MONTH(C41) -> 2 | B41: =DAY(C41) -> 22 | C41: 44249 | D41: VENMO | E41: VENMO PAYMENT 5302514749 SEAN LEWIS | F41: -81.32 | G41: Amar - Electric | H41: Essential | I41: UTILITIES | J41: Electricity
A42: =MONTH(C42) -> 2 | B42: =DAY(C42) -> 23 | C42: 44250 | D42: GasBuddy | E42: GasBuddy GasBuddy IVRVONZYL Sean Lewis | F42: -0.01 | G42: Gas | H42: Essential | I42: TRANSPORTATION | J42: Gas
A43: =MONTH(C43) -> 2 | B43: =DAY(C43) -> 23 | C43: 44250 | D43: GasBuddy | E43: GasBuddy GasBuddy IPZ5LNW76 | F43: 0.01 | G43: Gas
A44: =MONTH(C44) -> 2 | B44: =DAY(C44) -> 26 | C44: 44253 | D44: DISCOVER | E44: DISCOVER E-PAYMENT 210226 4732 LEWIS SEAN | F44: -770.55 | G44: Credit | H44: Essential | I44: SAVINGS, INVESTING, & DEBT | J44: Credit
A45: =MONTH(C45) -> 2 | B45: =DAY(C45) -> 26 | C45: 44253 | D45: VENMO | E45: VENMO PAYMENT 5336662518 SEAN LEWIS | F45: -700 | G45: Amar - Rent | H45: Essential | I45: HOME | J45: Rent
A46: =MONTH(C46) -> 2 | B46: =DAY(C46) -> 26 | C46: 44253 | D46: IRS | E46: IRS TREAS 310 TAX REF 022621 XXXXXXXXXX00908 LEWIS, SEAN | F46: 2420 | G46: Tax Return
A47: =MONTH(C47) -> 2 | B47: =DAY(C47) -> 26 | C47: 44253 | D47: Elephant | E47: Elephant Ins PAYROLL 210224 2087 Lewis Sean | F47: 1459.65 | G47: Elephant
A48: =MONTH(C48) -> 3 | B48: =DAY(C48) -> 1 | C48: 44256 | D48: ROBINHOOD | E48: ROBINHOOD Funds 210226 XXXXX4480 Sean Lewis | F48: -200 | G48: Investment | H48: Essential | I48: SAVINGS, INVESTING, & DEBT | J48: Securities
A49: =MONTH(C49) -> 3 | B49: =DAY(C49) -> 1 | C49: 44256 | D49: ROBINHOOD | E49: ROBINHOOD Funds 210226 XXXXX4480 Sean Lewis | F49: -200 | G49: Investment | H49: Essential | I49: SAVINGS, INVESTING, & DEBT | J49: Securities
A50: =MONTH(C50) -> 3 | B50: =DAY(C50) -> 1 | C50: 44256 | D50: PURCHASE | E50: PURCHASE AUTHORIZED ON 02/27 CASH APP*JAYELIN L 8774174551 CA S381058504895158 CARD 6634 | F50: -500 | G50: Jayelin | H50: Non-Essential | I50: MISCELLANEUS | J50: Family
A51: =MONTH(C51) -> 3 | B51: =DAY(C51) -> 2 | C51: 44257 | D51: ROBINHOOD | E51: ROBINHOOD Funds 210301 XXXXX4480 Sean Lewis | F51: -1000 | G51: Investment | H51: Essential | I51: SAVINGS, INVESTING, & DEBT | J51: Securities
A52: =MONTH(C52) -> 3 | B52: =DAY(C52) -> 2 | C52: 44257 | D52: ROBINHOOD | E52: ROBINHOOD Funds 210301 XXXXX4480 Sean Lewis | F52: -500 | G52: Investment | H52: Essential | I52: SAVINGS, INVESTING, & DEBT | J52: Securities
A53: =MONTH(C53) -> 3 | B53: =DAY(C53) -> 4 | C53: 44259 | D53: AVIDIA | E53: AVIDIA BANK SETL 210303 0268 LEWIS,SEAN | F53: 138.47 | G53: HSA
A54: =MONTH(C54) -> 3 | B54: =DAY(C54) -> 9 | C54: 44264 | D54: VENMO | E54: VENMO PAYMENT 5408451261 SEAN LEWIS | F54: -150 | G54: Amar - Water | H54: Essential | I54: UTILITIES | J54: Water
A55: =MONTH(C55) -> 3 | B55: =DAY(C55) -> 9 | C55: 44264 | D55: VA | E55: VA DEPT TAXATION VASTTAXRFD 210302 XXXXX0268 LEWIS, SEAN E | F55: 55 | G55: Tax Return
A56: =MONTH(C56) -> 3 | B56: =DAY(C56) -> 10 | C56: 44265 | D56: ROBINHOOD | E56: ROBINHOOD Funds 210309 XXXXX4480 Sean Lewis | F56: -200 | G56: Investment | H56: Essential | I56: SAVINGS, INVESTING, & DEBT | J56: Securities
A57: =MONTH(C57) -> 3 | B57: =DAY(C57) -> 10 | C57: 44265 | D57: MONEY | E57: MONEY TRANSFER AUTHORIZED ON 03/09 FROM Sean Lewis VA S00581069083988444 CARD 6634 | F57: 227.35 | G57: Jayelin | H57: Non-Essential | I57: MISCELLANEUS | J57: Family
A58: =MONTH(C58) -> 3 | B58: =DAY(C58) -> 12 | C58: 44267 | D58: DISCOVER | E58: DISCOVER E-PAYMENT 210312 4732 LEWIS SEAN | F58: -1160.38 | G58: Credit | H58: Essential | I58: SAVINGS, INVESTING, & DEBT | J58: Credit
A59: =MONTH(C59) -> 3 | B59: =DAY(C59) -> 12 | C59: 44267 | D59: Elephant | E59: Elephant Ins PAYROLL 210310 2087 Lewis Sean | F59: 1459.64 | G59: Elephant
A60: =MONTH(C60) -> 3 | B60: =DAY(C60) -> 16 | C60: 44271 | D60: GasBuddy | E60: GasBuddy GasBuddy IJPBP8EB4 Sean Lewis | F60: -25.57 | G60: Gas | H60: Essential | I60: TRANSPORTATION | J60: Gas
A61: =MONTH(C61) -> 3 | B61: =DAY(C61) -> 17 | C61: 44272 | D61: DISCOVER | E61: DISCOVER E-PAYMENT 210317 4732 LEWIS SEAN | F61: -471.27 | G61: Credit | H61: Essential | I61: SAVINGS, INVESTING, & DEBT | J61: Credit
A62: =MONTH(C62) -> 3 | B62: =DAY(C62) -> 17 | C62: 44272 | D62: VENMO | E62: VENMO PAYMENT 5451331842 SEAN LEWIS | F62: -700 | G62: Amar - Rent | H62: Essential | I62: HOME | J62: Rent
A63: =MONTH(C63) -> 3 | B63: =DAY(C63) -> 17 | C63: 44272 | D63: VENMO | E63: VENMO PAYMENT 5451317717 SEAN LEWIS | F63: -39.7 | G63: Amar - Electric | H63: Essential | I63: UTILITIES | J63: Electricity
A64: =MONTH(C64) -> 3 | B64: =DAY(C64) -> 17 | C64: 44272 | D64: TRANSFER | E64: TRANSFER TO LEWIS SHARON ON 03/17 REF #PP0B2WNZKY XXXXXXXXX5267 | F64: -1000 | G64: Mom | H64: Non-Essential | I64: MISCELLANEUS | J64: Family
A65: =MONTH(C65) -> 3 | B65: =DAY(C65) -> 17 | C65: 44272 | D65: TRANSFER | E65: TRANSFER FROM LEWIS SHARON ON 03/17 REF # PP0B2WLCG2 THANK YOU | F65: 1000 | G65: Mom | H65: Non-Essential | I65: MISCELLANEUS | J65: Family
A66: =MONTH(C66) -> 3 | B66: =DAY(C66) -> 17 | C66: 44272 | D66: IRS | E66: IRS TREAS 310 TAXEIP3 031721 XXXXXXXXXX00908 LEWIS, SEAN | F66: 2800 | G66: Stimulus 2
A67: =MONTH(C67) -> 3 | B67: =DAY(C67) -> 19 | C67: 44274 | D67: DISCOVER | E67: DISCOVER E-PAYMENT 210319 4732 LEWIS SEAN | F67: -50.34 | G67: Credit | H67: Essential | I67: SAVINGS, INVESTING, & DEBT | J67: Credit
A68: =MONTH(C68) -> 3 | B68: =DAY(C68) -> 23 | C68: 44278 | D68: VENMO | E68: VENMO PAYMENT 5493001064 SEAN LEWIS | F68: -59 | G68: Vincent | H68: Essential | I68: SAVINGS, INVESTING, & DEBT | J68: Personal Debt
A69: =MONTH(C69) -> 3 | B69: =DAY(C69) -> 23 | C69: 44278 | D69: VENMO | E69: VENMO PAYMENT 5492993326 SEAN LEWIS | F69: -40 | G69: Shelley | H69: Essential | I69: SAVINGS, INVESTING, & DEBT | J69: Personal Debt
A70: =MONTH(C70) -> 3 | B70: =DAY(C70) -> 23 | C70: 44278 | D70: VENMO | E70: VENMO PAYMENT 5492999612 SEAN LEWIS | F70: -8.33 | G70: Shelley | H70: Essential | I70: SAVINGS, INVESTING, & DEBT | J70: Personal Debt
A71: =MONTH(C71) -> 3 | B71: =DAY(C71) -> 26 | C71: 44281 | D71: DISCOVER | E71: DISCOVER E-PAYMENT 210326 4732 LEWIS SEAN | F71: -264.6 | G71: Credit | H71: Essential | I71: SAVINGS, INVESTING, & DEBT | J71: Credit
A72: =MONTH(C72) -> 3 | B72: =DAY(C72) -> 26 | C72: 44281 | D72: Elephant | E72: Elephant Ins PAYROLL 210324 2087 Lewis Sean | F72: 1457.82 | G72: Elephant
A73: =MONTH(C73) -> 3 | B73: =DAY(C73) -> 29 | C73: 44284 | D73: VENMO | E73: VENMO PAYMENT 5513431756 SEAN LEWIS | F73: -20 | G73: Danny | H73: Essential | I73: SAVINGS, INVESTING, & DEBT | J73: Personal Debt
A74: =MONTH(C74) -> 3 | B74: =DAY(C74) -> 31 | C74: 44286 | D74: DISCOVER | E74: DISCOVER E-PAYMENT 210331 4732 LEWIS SEAN | F74: -465.03 | G74: Credit | H74: Essential | I74: SAVINGS, INVESTING, & DEBT | J74: Credit
A75: =MONTH(C75) -> 4 | B75: =DAY(C75) -> 1 | C75: 44287 | D75: PURCHASE | E75: PURCHASE AUTHORIZED ON 03/31 CASH APP*SHEVON LE 8774174551 CA S461091061277016 CARD 6634 | F75: -400 | G75: Shevon | H75: Non-Essential | I75: MISCELLANEUS | J75: Family
A76: =MONTH(C76) -> 4 | B76: =DAY(C76) -> 9 | C76: 44295 | D76: DISCOVER | E76: DISCOVER E-PAYMENT 210409 7328 LEWIS SEAN | F76: -450.02 | G76: Credit | H76: Essential | I76: SAVINGS, INVESTING, & DEBT | J76: Credit
A77: =MONTH(C77) -> 4 | B77: =DAY(C77) -> 9 | C77: 44295 | D77: Elephant | E77: Elephant Ins PAYROLL 210407 2087 Lewis Sean | F77: 1242.82 | G77: Elephant
A78: =MONTH(C78) -> 4 | B78: =DAY(C78) -> 12 | C78: 44298 | D78: VENMO | E78: VENMO PAYMENT 210411 1013109381403 SEAN LEWIS | F78: -138.52 | G78: Amar - Electric | H78: Essential | I78: UTILITIES | J78: Electricity
A79: =MONTH(C79) -> 4 | B79: =DAY(C79) -> 12 | C79: 44298 | D79: VENMO | E79: VENMO PAYMENT 5603366206 SEAN LEWIS | F79: -100 | G79: Amar - Water | H79: Essential | I79: UTILITIES | J79: Water
A80: =MONTH(C80) -> 4 | B80: =DAY(C80) -> 12 | C80: 44298 | D80: PURCHASE | E80: PURCHASE AUTHORIZED ON 04/11 CASH APP*ENGAGETM 8774174551 CA S301101447514096 CARD 6634 | F80: -250 | G80: Dorry | H80: Non-Essential | I80: MISCELLANEUS | J80: Family
A81: =MONTH(C81) -> 4 | B81: =DAY(C81) -> 19 | C81: 44305 | D81: VENMO | E81: VENMO CASHOUT 5643580806 SEAN LEWIS | F81: 50 | G81: Venmo Cash Out
A82: =MONTH(C82) -> 4 | B82: =DAY(C82) -> 19 | C82: 44305 | D82: MOBILE | E82: MOBILE DEPOSIT : REF NUMBER :816170847728 | F82: 30 | G82: Income
A83: =MONTH(C83) -> 4 | B83: =DAY(C83) -> 20 | C83: 44306 | D83: MONEY | E83: MONEY TRANSFER AUTHORIZED ON 04/20 FROM Sean Lewis VA S00581110491401484 CARD 6634 | F83: 189 | G83: Jayelin | H83: Non-Essential | I83: MISCELLANEUS | J83: Family
A84: =MONTH(C84) -> 4 | B84: =DAY(C84) -> 23 | C84: 44309 | D84: VENMO | E84: VENMO PAYMENT 210423 1013303271012 SEAN LEWIS | F84: -700 | G84: Amar - Rent | H84: Essential | I84: HOME | J84: Rent
A85: =MONTH(C85) -> 4 | B85: =DAY(C85) -> 23 | C85: 44309 | D85: PURCHASE | E85: PURCHASE AUTHORIZED ON 04/22 DICK'S SPORTING GO GLEN ALLEN VA S581112824030519 CARD 6634 | F85: -10.6 | G85: Purchase | H85: Non-Essential | I85: PERSONAL SPENDING | J85: Clothes
A86: =MONTH(C86) -> 4 | B86: =DAY(C86) -> 23 | C86: 44309 | D86: Elephant | E86: Elephant Ins PAYROLL 210421 2087 Lewis Sean | F86: 1174.51 | G86: Elephant
A87: =MONTH(C87) -> 4 | B87: =DAY(C87) -> 30 | C87: 44316 | D87: PURCHASE | E87: PURCHASE AUTHORIZED ON 04/29 CASH APP*ENGAGETM 8774174551 CA S381119860065157 CARD 6634 | F87: -50 | G87: Dorry | H87: Non-Essential | I87: MISCELLANEUS | J87: Family
A88: =MONTH(C88) -> 5 | B88: =DAY(C88) -> 3 | C88: 44319 | D88: VENMO | E88: VENMO PAYMENT 210501 1013448453372 SEAN LEWIS | F88: -50 | G88: Divita | H88: Essential | I88: SAVINGS, INVESTING, & DEBT | J88: Personal Debt
A89: =MONTH(C89) -> 5 | B89: =DAY(C89) -> 5 | C89: 44321 | D89: DISCOVER | E89: DISCOVER E-PAYMENT 210505 7328 LEWIS SEAN | F89: -1404.1 | G89: Credit | H89: Essential | I89: SAVINGS, INVESTING, & DEBT | J89: Credit
A90: =MONTH(C90) -> 5 | B90: =DAY(C90) -> 6 | C90: 44322 | D90: New | E90: New Manchester F WEB PMTS 050621 GVVCH7 Sean Lewis | F90: -200 | G90: New Manchester - Fee | H90: Essential | I90: HOME | J90: Rent
A91: =MONTH(C91) -> 5 | B91: =DAY(C91) -> 6 | C91: 44322 | D91: New | E91: New Manchester F WEB PMTS 050621 FVVCH7 Sean Lewis | F91: -200 | G91: New Manchester Deposit | H91: Essential | I91: HOME | J91: Rent
A92: =MONTH(C92) -> 5 | B92: =DAY(C92) -> 7 | C92: 44323 | D92: Elephant | E92: Elephant Ins PAYROLL 210505 2087 Lewis Sean | F92: 1174.52 | G92: Elephant
A93: =MONTH(C93) -> 5 | B93: =DAY(C93) -> 7 | C93: 44323 | D93: AVIDIA | E93: AVIDIA BANK SETL 210506 0268 LEWIS,SEAN | F93: 803.91 | G93: HSA
A94: =MONTH(C94) -> 5 | B94: =DAY(C94) -> 10 | C94: 44326 | D94: VENMO | E94: VENMO PAYMENT 210509 1013594268300 SEAN LEWIS | F94: -150 | G94: Amar - Water | H94: Essential | I94: UTILITIES | J94: Water
A95: =MONTH(C95) -> 5 | B95: =DAY(C95) -> 10 | C95: 44326 | D95: VENMO | E95: VENMO PAYMENT 210509 1013594265412 SEAN LEWIS | F95: -136.14 | G95: Amar - Electric | H95: Essential | I95: UTILITIES | J95: Electricity
A96: =MONTH(C96) -> 5 | B96: =DAY(C96) -> 11 | C96: 44327 | D96: GasBuddy | E96: GasBuddy GasBuddy INXG6RPA2 Sean Lewis | F96: -28.93 | G96: Gas | H96: Essential | I96: TRANSPORTATION | J96: Gas
A97: =MONTH(C97) -> 5 | B97: =DAY(C97) -> 12 | C97: 44328 | D97: VENMO | E97: VENMO CASHOUT 210512 1013636035269 SEAN LEWIS | F97: 150 | G97: Venmo Cash Out | H97: Essential | I97: SAVINGS, INVESTING, & DEBT | J97: Personal Debt
A98: =MONTH(C98) -> 5 | B98: =DAY(C98) -> 14 | C98: 44330 | D98: GasBuddy | E98: GasBuddy GasBuddy I4YX455B2 Sean Lewis | F98: -21.39 | G98: Gas | H98: Essential | I98: TRANSPORTATION | J98: Gas
A99: =MONTH(C99) -> 5 | B99: =DAY(C99) -> 14 | C99: 44330 | D99: MONEY | E99: MONEY TRANSFER AUTHORIZED ON 05/14 FROM Sean Lewis VA S00301134489786999 CARD 6634 | F99: 136.14 | G99: Jayelin | H99: Non-Essential | I99: MISCELLANEUS | J99: Family
A100: =MONTH(C100) -> 5 | B100: =DAY(C100) -> 17 | C100: 44333 | D100: VENMO | E100: VENMO PAYMENT 210516 1013705922037 SEAN LEWIS | F100: -220 | G100: Vincent | H100: Essential | I100: SAVINGS, INVESTING, & DEBT | J100: Personal Debt
...

Sheet Sheet1
A6: Sum of Amount | B6: Column Labels
A7: Row Labels | B7: Restaurants | C7: Supermarkets | D7: Grand Total
A8: 1 | B8: 117.23 | C8: 138.14 | D8: 255.37
A9: 2 | B9: 51.96 | C9: 247.65 | D9: 299.61
A10: 3 | B10: 259.85 | C10: 132.85 | D10: 392.7
A11: 4 | B11: 487.13 | C11: 25.32 | D11: 512.45
A12: 5 | B12: 259.75 | C12: 321.42 | D12: 581.17
A13: 6 | B13: 472.59 | C13: 100.64 | D13: 573.23
A14: 7 | B14: 689.58 | C14: 328.94 | D14: 1018.52
A15: 8 | B15: 1021.47 | C15: 114.91 | D15: 1136.38
A16: 9 | B16: 1134.5 | C16: 192.66 | D16: 1327.16
A17: 10 | B17: 465.78 | C17: 218.82 | D17: 684.6
A18: 11 | B18: 697.63 | C18: 235.31 | D18: 932.94
A19: 12 | B19: 778.91 | C19: 263.92 | D19: 1042.83
A20: Grand Total | B20: 6436.38 | C20: 2320.58 | D20: 8756.96

Sheet Discover
A1: Year | B1: Month | C1: Trans. date | D1: Post date | E1: Description | F1: Amount | G1: Category | H1: Category_2 | I1: Expense Type | J1: Cumulative | K1: Association | L1: Main Category | M1: Secondary Category | N1: Specific Category | Q1: Essential | R1: =SUMIFS(Table1[Amount],Table1[Main Category], Q1) -> 14607.94
A2: =YEAR(C2) -> 2021 | B2: =MONTH(C2) -> 1 | C2: 44197 | D2: 44197 | E2: INTERNET PAYMENT - THANK YOU | F2: -700 | G2: Payments and Credits | I2: =VLOOKUP(G2,Expense_Lookup,2,0) -> Payment | J2: 728.15 | Q2: Non-Essential | R2: =SUMIFS(Table1[Amount],Table1[Main Category], Q2) -> 19966.37
A3: =YEAR(C3) -> 2021 | B3: =MONTH(C3) -> 1 | C3: 44197 | D3: 44199 | E3: NETFLIX.COM NETFLIX.COM CA44115296471 | F3: 13.99 | G3: APP | I3: =VLOOKUP(G3,Expense_Lookup,2,0) -> Fixed | J3: =J2+F3 -> 742.14 | K3: Netflix | L3: Non-Essential | M3: RECREATION & ENTERTAINMENT | N3: Streaming Services | R3: =SUM(R1:R2) -> 34574.31
A4: =YEAR(C4) -> 2021 | B4: =MONTH(C4) -> 1 | C4: 44197 | D4: 44199 | E4: SPOTIFY P12D96D434 8777781161 NY | F4: 9.99 | G4: APP | I4: =VLOOKUP(G4,Expense_Lookup,2,0) -> Fixed | J4: =J3+F4 -> 752.13 | K4: Spotify | L4: Non-Essential | M4: RECREATION & ENTERTAINMENT | N4: Streaming Services | V4: Jan | W4: Feb | X4: Mar | Y4: Apr | Z4: May | AA4: June | AB4: July | AC4: Aug | AD4: Sep | AE4: Oct | AF4: Nov | AG4: Dec | AH4: Yearly
A5: =YEAR(C5) -> 2021 | B5: =MONTH(C5) -> 1 | C5: 44197 | D5: 44199 | E5: WAWA 697 STAFFORD VA | F5: 18.87 | G5: Gasoline | I5: =VLOOKUP(G5,Expense_Lookup,2,0) -> Variable | J5: =J4+F5 -> 771 | L5: Essential | M5: TRANSPORTATION | N5: Gas | Q5: Variable | R5: =SUMIFS(F:F,I:I,Q5) -> 30647.22 | T5: {=_xlfn.UNIQUE(_xlfn._xlws.FILTER(G:G,(G:G<>0) ))} -> Category
A6: =YEAR(C6) -> 2021 | B6: =MONTH(C6) -> 1 | C6: 44201 | D6: 44201 | E6: MYFICO COM 8003194433 GA | F6: 39.95 | G6: APP | I6: =VLOOKUP(G6,Expense_Lookup,2,0) -> Fixed | J6: =J5+F6 -> 810.95 | K6: Credit Score | L6: Non-Essential | M6: PERSONAL SPENDING | N6: Subscription | Q6: Fixed | R6: =SUMIFS(F:F,I:I,Q6) -> 7246.32 | T6: Payments and Credits | U6: Payment | V6: =SUMIFS(F:F,G:G,T6,$B:$B,1) -> -2157.38 | W6: =SUMIFS(F:F,G:G,T6,$B:$B,2) -> -2256.47 | X6: =SUMIFS(F:F,G:G,T6,$B:$B,3) -> -2413.62 | Y6: =SUMIFS($F:$F,$G:$G,$T6,$B:$B,4) -> -471.07 | Z6: =SUMIFS($F:$F,$G:$G,$T6,$B:$B,5) -> -2855.16 | AA6: =SUMIFS($F:$F,$G:$G,$T6,$B:$B,6) -> -3297.83 | AB6: =SUMIFS($F:$F,$G:$G,$T6,$B:$B,7) -> -6127.09 | AC6: =SUMIFS($F:$F,$G:$G,$T6,$B:$B,8) -> -3272.24 | AD6: =SUMIFS($F:$F,$G:$G,$T6,$B:$B,9) -> -4605.13 | AE6: =SUMIFS($F:$F,$G:$G,$T6,$B:$B,10) -> -1714.73 | AF6: =SUMIFS($F:$F,$G:$G,$T6,$B:$B,11) -> -4175.51 | AG6: =SUMIFS($F:$F,$G:$G,$T6,$B:$B,12) -> -3272.92
A7: =YEAR(C7) -> 2021 | B7: =MONTH(C7) -> 1 | C7: 44201 | D7: 44201 | E7: STATE FARM INSURANCE 800-956-6310 IL | F7: 91.78 | G7: APP | I7: =VLOOKUP(G7,Expense_Lookup,2,0) -> Fixed | J7: =J6+F7 -> 902.73 | K7: State Farm | L7: Essential | M7: INSURANCE | N7: Auto Insurance | R7: =SUM(R5:R6) -> 37893.54 | T7: APP | U7: Fixed | V7: =SUMIFS(F:F,G:G,T7,$B:$B,1) -> 190.63 | W7: =SUMIFS(F:F,G:G,T7,$B:$B,2) -> 250.9 | X7: =SUMIFS(F:F,G:G,T7,$B:$B,3) -> 559.85 | Y7: =SUMIFS(F:F,G:G,T7,$B:$B,4) -> 334.83 | Z7: =SUMIFS($F:$F,$G:$G,$T7,$B:$B,5) -> 592.35 | AA7: =SUMIFS($F:$F,$G:$G,$T7,$B:$B,6) -> 579.09 | AB7: =SUMIFS($F:$F,$G:$G,$T7,$B:$B,7) -> 395.95 | AC7: =SUMIFS($F:$F,$G:$G,$T7,$B:$B,8) -> 655.42 | AD7: =SUMIFS($F:$F,$G:$G,$T7,$B:$B,9) -> 616.67 | AE7: =SUMIFS($F:$F,$G:$G,$T7,$B:$B,10) -> 833.3 | AF7: =SUMIFS($F:$F,$G:$G,$T7,$B:$B,11) -> 673.82 | AG7: =SUMIFS($F:$F,$G:$G,$T7,$B:$B,12) -> 479.27 | AH7: =SUM(V7:AG7) -> 6162.08
A8: =YEAR(C8) -> 2021 | B8: =MONTH(C8) -> 1 | C8: 44201 | D8: 44201 | E8: STEAMPOWERED.COM 425-952-2985 WA | F8: 19.99 | G8: Merchandise | I8: =VLOOKUP(G8,Expense_Lookup,2,0) -> Variable | J8: =J7+F8 -> 922.72 | K8: Neir Automata | L8: Non-Essential | M8: RECREATION & ENTERTAINMENT | N8: Video Games | Q8: Family | T8: Gasoline | U8: Variable | V8: =SUMIFS(F:F,G:G,T8,$B:$B,1) -> 67.87 | W8: =SUMIFS(F:F,G:G,T8,$B:$B,2) -> 67.47 | X8: =SUMIFS(F:F,G:G,T8,$B:$B,3) -> 80.06 | Y8: =SUMIFS(F:F,G:G,T8,$B:$B,4) -> 125.95 | Z8: =SUMIFS($F:$F,$G:$G,$T8,$B:$B,5) -> 115.16 | AA8: =SUMIFS($F:$F,$G:$G,$T8,$B:$B,6) -> 104.56 | AB8: =SUMIFS($F:$F,$G:$G,$T8,$B:$B,7) -> 71.41 | AC8: =SUMIFS($F:$F,$G:$G,$T8,$B:$B,8) -> 199.88 | AD8: =SUMIFS($F:$F,$G:$G,$T8,$B:$B,9) -> 353.18 | AE8: =SUMIFS($F:$F,$G:$G,$T8,$B:$B,10) -> 103 | AF8: =SUMIFS($F:$F,$G:$G,$T8,$B:$B,11) -> 0 | AG8: =SUMIFS($F:$F,$G:$G,$T8,$B:$B,12) -> 80.38 | AH8: =SUM(V8:AG8) -> 1368.92
A9: =YEAR(C9) -> 2021 | B9: =MONTH(C9) -> 1 | C9: 44202 | D9: 44202 | E9: LIVECAREER.COM 800652843 866-933-7587 PR | F9: 24.95 | G9: Family | I9: =VLOOKUP(G9,Expense_Lookup,2,0) -> Variable | J9: =J8+F9 -> 947.67 | K9: Jayelin | L9: Non-Essential | M9: MISCELLANEUS | N9: Family | Q9: Jayelin | R9: =SUMIFS(F:F,K:K,Q9)+SUMIFS('Cash Flow'!$B:$B,'Cash Flow'!$A:$A,Discover!Q9)*-1 -> 914.35 | T9: Merchandise | U9: Variable | V9: =SUMIFS(F:F,G:G,T9,$B:$B,1) -> 434.08 | W9: =SUMIFS(F:F,G:G,T9,$B:$B,2) -> 262.63 | X9: =SUMIFS(F:F,G:G,T9,$B:$B,3) -> 427.64 | Y9: =SUMIFS(F:F,G:G,T9,$B:$B,4) -> 334.36 | Z9: =SUMIFS($F:$F,$G:$G,$T9,$B:$B,5) -> 633.35 | AA9: =SUMIFS($F:$F,$G:$G,$T9,$B:$B,6) -> 1136.89 | AB9: =SUMIFS($F:$F,$G:$G,$T9,$B:$B,7) -> 1104.67 | AC9: =SUMIFS($F:$F,$G:$G,$T9,$B:$B,8) -> 662.17 | AD9: =SUMIFS($F:$F,$G:$G,$T9,$B:$B,9) -> 2140.89 | AE9: =SUMIFS($F:$F,$G:$G,$T9,$B:$B,10) -> 1489.4 | AF9: =SUMIFS($F:$F,$G:$G,$T9,$B:$B,11) -> 575.7 | AG9: =SUMIFS($F:$F,$G:$G,$T9,$B:$B,12) -> 872.75 | AH9: =SUM(V9:AG9) -> 10074.53
A10: =YEAR(C10) -> 2021 | B10: =MONTH(C10) -> 1 | C10: 44202 | D10: 44202 | E10: RIVER RUN SHORT PUMP HENRICO VA | F10: 30 | G10: Medical Services | I10: =VLOOKUP(G10,Expense_Lookup,2,0) -> Variable | J10: =J9+F10 -> 977.67 | K10: Dentist | L10: Essential | M10: MEDICAL & HEALTHCARE | N10: Dental Care | Q10: Shevon | R10: =SUMIFS(F:F,K:K,Q10)+SUMIFS('Cash Flow'!$B:$B,'Cash Flow'!$A:$A,Discover!Q10)*-1 -> 1774.95 | T10: Family | U10: Variable | V10: =SUMIFS(F:F,G:G,T10,$B:$B,1) -> 172.84 | W10: =SUMIFS(F:F,G:G,T10,$B:$B,2) -> 71.26 | X10: =SUMIFS(F:F,G:G,T10,$B:$B,3) -> 84.95 | Y10: =SUMIFS(F:F,G:G,T10,$B:$B,4) -> 9.95 | Z10: =SUMIFS($F:$F,$G:$G,$T10,$B:$B,5) -> 91.85 | AA10: =SUMIFS($F:$F,$G:$G,$T10,$B:$B,6) -> 0 | AB10: =SUMIFS($F:$F,$G:$G,$T10,$B:$B,7) -> 0 | AC10: =SUMIFS($F:$F,$G:$G,$T10,$B:$B,8) -> 0 | AD10: =SUMIFS($F:$F,$G:$G,$T10,$B:$B,9) -> 0 | AE10: =SUMIFS($F:$F,$G:$G,$T10,$B:$B,10) -> 0 | AF10: =SUMIFS($F:$F,$G:$G,$T10,$B:$B,11) -> 0 | AG10: =SUMIFS($F:$F,$G:$G,$T10,$B:$B,12) -> 0 | AH10: =SUM(V10:AG10) -> 430.85
A11: =YEAR(C11) -> 2021 | B11: =MONTH(C11) -> 1 | C11: 44202 | D11: 44202 | E11: THE MARKET @ 25TH RICHMOND VA | F11: 24.24 | G11: Supermarkets | I11: =VLOOKUP(G11,Expense_Lookup,2,0) -> Variable | J11: =J10+F11 -> 1001.91 | L11: Essential | M11: FOOD | N11: Groceries | Q11: Don | R11: =SUMIFS(F:F,K:K,Q11)+SUMIFS('Cash Flow'!$B:$B,'Cash Flow'!$A:$A,Discover!Q11)*-1 -> 127.5 | T11: Medical Services | U11: Variable | V11: =SUMIFS(F:F,G:G,T11,$B:$B,1) -> 70.51 | W11: =SUMIFS(F:F,G:G,T11,$B:$B,2) -> 0 | X11: =SUMIFS(F:F,G:G,T11,$B:$B,3) -> 0 | Y11: =SUMIFS(F:F,G:G,T11,$B:$B,4) -> 0 | Z11: =SUMIFS($F:$F,$G:$G,$T11,$B:$B,5) -> 0 | AA11: =SUMIFS($F:$F,$G:$G,$T11,$B:$B,6) -> 0 | AB11: =SUMIFS($F:$F,$G:$G,$T11,$B:$B,7) -> 0 | AC11: =SUMIFS($F:$F,$G:$G,$T11,$B:$B,8) -> 0 | AD11: =SUMIFS($F:$F,$G:$G,$T11,$B:$B,9) -> 0 | AE11: =SUMIFS($F:$F,$G:$G,$T11,$B:$B,10) -> 0 | AF11: =SUMIFS($F:$F,$G:$G,$T11,$B:$B,11) -> 0 | AG11: =SUMIFS($F:$F,$G:$G,$T11,$B:$B,12) -> 0 | AH11: =SUM(V11:AG11) -> 70.51
A12: =YEAR(C12) -> 2021 | B12: =MONTH(C12) -> 1 | C12: 44203 | D12: 44203 | E12: AMERICA'S BEST WINGS HENRICO VA | F12: 12.09 | G12: Restaurants | H12: fast_food | I12: =VLOOKUP(G12,Expense_Lookup,2,0) -> Variable | J12: =J11+F12 -> 1014 | L12: Non-Essential | M12: RECREATION & ENTERTAINMENT | N12: Resteraunts | Q12: Dorry | R12: =SUMIFS(F:F,K:K,Q12)+SUMIFS('Cash Flow'!$B:$B,'Cash Flow'!$A:$A,Discover!Q12)*-1 -> 455 | T12: Supermarkets | U12: Variable | V12: =SUMIFS(F:F,G:G,T12,$B:$B,1) -> 138.14 | W12: =SUMIFS(F:F,G:G,T12,$B:$B,2) -> 247.65 | X12: =SUMIFS(F:F,G:G,T12,$B:$B,3) -> 132.85 | Y12: =SUMIFS(F:F,G:G,T12,$B:$B,4) -> 25.32 | Z12: =SUMIFS($F:$F,$G:$G,$T12,$B:$B,5) -> 321.42 | AA12: =SUMIFS($F:$F,$G:$G,$T12,$B:$B,6) -> 100.64 | AB12: =SUMIFS($F:$F,$G:$G,$T12,$B:$B,7) -> 328.94 | AC12: =SUMIFS($F:$F,$G:$G,$T12,$B:$B,8) -> 114.91 | AD12: =SUMIFS($F:$F,$G:$G,$T12,$B:$B,9) -> 192.66 | AE12: =SUMIFS($F:$F,$G:$G,$T12,$B:$B,10) -> 218.82 | AF12: =SUMIFS($F:$F,$G:$G,$T12,$B:$B,11) -> 235.31 | AG12: =SUMIFS($F:$F,$G:$G,$T12,$B:$B,12) -> 263.92 | AH12: =SUM(V12:AG12) -> 2320.58
A13: =YEAR(C13) -> 2021 | B13: =MONTH(C13) -> 1 | C13: 44203 | D13: 44203 | E13: GO DRAGON ASIAN GRILL RICHMOND VA | F13: 44 | G13: Restaurants | I13: =VLOOKUP(G13,Expense_Lookup,2,0) -> Variable | J13: =J12+F13 -> 1058 | L13: Non-Essential | M13: RECREATION & ENTERTAINMENT | N13: Resteraunts | Q13: Cairo | R13: =SUMIFS(F:F,K:K,Q13)+SUMIFS('Cash Flow'!$B:$B,'Cash Flow'!$A:$A,Discover!Q13)*-1 -> 0 | T13: Restaurants | U13: Variable | V13: =SUMIFS(F:F,G:G,T13,$B:$B,1) -> 117.23 | W13: =SUMIFS(F:F,G:G,T13,$B:$B,2) -> 51.96 | X13: =SUMIFS(F:F,G:G,T13,$B:$B,3) -> 259.85 | Y13: =SUMIFS(F:F,G:G,T13,$B:$B,4) -> 487.13 | Z13: =SUMIFS($F:$F,$G:$G,$T13,$B:$B,5) -> 259.75 | AA13: =SUMIFS($F:$F,$G:$G,$T13,$B:$B,6) -> 472.59 | AB13: =SUMIFS($F:$F,$G:$G,$T13,$B:$B,7) -> 689.58 | AC13: =SUMIFS($F:$F,$G:$G,$T13,$B:$B,8) -> 1021.47 | AD13: =SUMIFS($F:$F,$G:$G,$T13,$B:$B,9) -> 1134.5 | AE13: =SUMIFS($F:$F,$G:$G,$T13,$B:$B,10) -> 465.78 | AF13: =SUMIFS($F:$F,$G:$G,$T13,$B:$B,11) -> 697.63 | AG13: =SUMIFS($F:$F,$G:$G,$T13,$B:$B,12) -> 778.91 | AH13: =SUM(V13:AG13) -> 6436.38
A14: =YEAR(C14) -> 2021 | B14: =MONTH(C14) -> 1 | C14: 44203 | D14: 44203 | E14: THE MARKET @ 25TH RICHMOND VA | F14: 14.52 | G14: Supermarkets | I14: =VLOOKUP(G14,Expense_Lookup,2,0) -> Variable | J14: =J13+F14 -> 1072.52 | L14: Essential | M14: FOOD | N14: Groceries | R14: =SUM(R9:R13) -> 3271.8 | T14: Services | U14: Variable | V14: =SUMIFS(F:F,G:G,T14,$B:$B,1) -> 29.27 | W14: =SUMIFS(F:F,G:G,T14,$B:$B,2) -> 0 | X14: =SUMIFS(F:F,G:G,T14,$B:$B,3) -> 470 | Y14: =SUMIFS(F:F,G:G,T14,$B:$B,4) -> 98 | Z14: =SUMIFS($F:$F,$G:$G,$T14,$B:$B,5) -> 1.5 | AA14: =SUMIFS($F:$F,$G:$G,$T14,$B:$B,6) -> 213.84 | AB14: =SUMIFS($F:$F,$G:$G,$T14,$B:$B,7) -> 1904.58 | AC14: =SUMIFS($F:$F,$G:$G,$T14,$B:$B,8) -> 283.03 | AD14: =SUMIFS($F:$F,$G:$G,$T14,$B:$B,9) -> 375.1 | AE14: =SUMIFS($F:$F,$G:$G,$T14,$B:$B,10) -> 352.52 | AF14: =SUMIFS($F:$F,$G:$G,$T14,$B:$B,11) -> 0 | AG14: =SUMIFS($F:$F,$G:$G,$T14,$B:$B,12) -> 237.18 | AH14: =SUM(V14:AG14) -> 3965.02
A15: =YEAR(C15) -> 2021 | B15: =MONTH(C15) -> 1 | C15: 44204 | D15: 44204 | E15: CVS/PHARMACY #01988 RICHMOND VA | F15: 3.37 | G15: Family | I15: =VLOOKUP(G15,Expense_Lookup,2,0) -> Variable | J15: =J14+F15 -> 1075.89 | K15: Jayelin | L15: Non-Essential | M15: MISCELLANEUS | N15: Family | T15: Education | U15: Variable | V15: =SUMIFS(F:F,G:G,T15,$B:$B,1) -> 49 | W15: =SUMIFS(F:F,G:G,T15,$B:$B,2) -> 215 | X15: =SUMIFS(F:F,G:G,T15,$B:$B,3) -> 0 | Y15: =SUMIFS(F:F,G:G,T15,$B:$B,4) -> 0 | Z15: =SUMIFS($F:$F,$G:$G,$T15,$B:$B,5) -> 0 | AA15: =SUMIFS($F:$F,$G:$G,$T15,$B:$B,6) -> 199 | AB15: =SUMIFS($F:$F,$G:$G,$T15,$B:$B,7) -> 0 | AC15: =SUMIFS($F:$F,$G:$G,$T15,$B:$B,8) -> 4.8 | AD15: =SUMIFS($F:$F,$G:$G,$T15,$B:$B,9) -> 0 | AE15: =SUMIFS($F:$F,$G:$G,$T15,$B:$B,10) -> 0 | AF15: =SUMIFS($F:$F,$G:$G,$T15,$B:$B,11) -> 0 | AG15: =SUMIFS($F:$F,$G:$G,$T15,$B:$B,12) -> 0 | AH15: =SUM(V15:AG15) -> 467.8
A16: =YEAR(C16) -> 2021 | B16: =MONTH(C16) -> 1 | C16: 44204 | D16: 44204 | E16: LABCORP PSCC 2 800-845-6167 NC202101072171244 | F16: 40.51 | G16: Medical Services | I16: =VLOOKUP(G16,Expense_Lookup,2,0) -> Variable | J16: =J15+F16 -> 1116.4 | K16: Doctor | L16: Essential | M16: MEDICAL & HEALTHCARE | N16: Out-of-Pocket Costs | Q16: Trips | T16: Awards and Rebate Credits | U16: Payment | V16: =SUMIFS(F:F,G:G,T16,$B:$B,1) -> -22.18 | W16: =SUMIFS(F:F,G:G,T16,$B:$B,2) -> -14 | X16: =SUMIFS(F:F,G:G,T16,$B:$B,3) -> -14.05 | Y16: =SUMIFS(F:F,G:G,T16,$B:$B,4) -> 0 | Z16: =SUMIFS($F:$F,$G:$G,$T16,$B:$B,5) -> 0 | AA16: =SUMIFS($F:$F,$G:$G,$T16,$B:$B,6) -> 0 | AB16: =SUMIFS($F:$F,$G:$G,$T16,$B:$B,7) -> 0 | AC16: =SUMIFS($F:$F,$G:$G,$T16,$B:$B,8) -> -38.86 | AD16: =SUMIFS($F:$F,$G:$G,$T16,$B:$B,9) -> 0 | AE16: =SUMIFS($F:$F,$G:$G,$T16,$B:$B,10) -> 0 | AF16: =SUMIFS($F:$F,$G:$G,$T16,$B:$B,11) -> -43.38 | AG16: =SUMIFS($F:$F,$G:$G,$T16,$B:$B,12) -> -44.4 | AH16: =SUM(V16:AG16) -> -176.87
A17: =YEAR(C17) -> 2021 | B17: =MONTH(C17) -> 1 | C17: 44205 | D17: 44205 | E17: BINGO BEER CO - GAMES PE RICHMOND VA | F17: 30 | G17: Restaurants | I17: =VLOOKUP(G17,Expense_Lookup,2,0) -> Variable | J17: =J16+F17 -> 1146.4 | K17: Akhil | L17: Non-Essential | M17: RECREATION & ENTERTAINMENT | N17: Resteraunts | Q17: New York | R17: =SUMIFS(F:F,K:K,Q17)+SUMIFS('Cash Flow'!$B:$B,'Cash Flow'!$A:$A,Discover!Q17)*-1 -> 373.46 | T17: Government Services | U17: Variable | V17: =SUMIFS(F:F,G:G,T17,$B:$B,1) -> 0 | W17: =SUMIFS(F:F,G:G,T17,$B:$B,2) -> 40.15 | X17: =SUMIFS(F:F,G:G,T17,$B:$B,3) -> 0 | Y17: =SUMIFS(F:F,G:G,T17,$B:$B,4) -> 0 | Z17: =SUMIFS($F:$F,$G:$G,$T17,$B:$B,5) -> 26.35 | AA17: =SUMIFS($F:$F,$G:$G,$T17,$B:$B,6) -> 195.05 | AB17: =SUMIFS($F:$F,$G:$G,$T17,$B:$B,7) -> 194 | AC17: =SUMIFS($F:$F,$G:$G,$T17,$B:$B,8) -> 21.51 | AD17: =SUMIFS($F:$F,$G:$G,$T17,$B:$B,9) -> 140.91 | AE17: =SUMIFS($F:$F,$G:$G,$T17,$B:$B,10) -> 0 | AF17: =SUMIFS($F:$F,$G:$G,$T17,$B:$B,11) -> 138.14 | AG17: =SUMIFS($F:$F,$G:$G,$T17,$B:$B,12) -> 20.06 | AH17: =SUM(V17:AG17) -> 776.17
A18: =YEAR(C18) -> 2021 | B18: =MONTH(C18) -> 1 | C18: 44205 | D18: 44205 | E18: WALMART SC 07032 HENRICO VA | F18: 37.5 | G18: Merchandise | I18: =VLOOKUP(G18,Expense_Lookup,2,0) -> Variable | J18: =J17+F18 -> 1183.9 | L18: Non-Essential | M18: PERSONAL SPENDING | N18: Walmart/Target Run | Q18: Brooklyn | R18: =SUMIFS(F:F,K:K,Q18)+SUMIFS('Cash Flow'!$B:$B,'Cash Flow'!$A:$A,Discover!Q18)*-1 -> 1983.8 | T18: Automotive | U18: Fixed | V18: =SUMIFS(F:F,G:G,T18,$B:$B,1) -> 0 | W18: =SUMIFS(F:F,G:G,T18,$B:$B,2) -> 0 | X18: =SUMIFS(F:F,G:G,T18,$B:$B,3) -> 86.17 | Y18: =SUMIFS(F:F,G:G,T18,$B:$B,4) -> 5.65 | Z18: =SUMIFS($F:$F,$G:$G,$T18,$B:$B,5) -> 401.19 | AA18: =SUMIFS($F:$F,$G:$G,$T18,$B:$B,6) -> 0 | AB18: =SUMIFS($F:$F,$G:$G,$T18,$B:$B,7) -> 394.26 | AC18: =SUMIFS($F:$F,$G:$G,$T18,$B:$B,8) -> 0 | AD18: =SUMIFS($F:$F,$G:$G,$T18,$B:$B,9) -> 110.71 | AE18: =SUMIFS($F:$F,$G:$G,$T18,$B:$B,10) -> 0 | AF18: =SUMIFS($F:$F,$G:$G,$T18,$B:$B,11) -> 0 | AG18: =SUMIFS($F:$F,$G:$G,$T18,$B:$B,12) -> 93.25 | AH18: =SUM(V18:AG18) -> 1091.23
A19: =YEAR(C19) -> 2021 | B19: =MONTH(C19) -> 1 | C19: 44206 | D19: 44206 | E19: APPLE.COM/BILL 866-712-7753 CAAPPLE PAY ENDING IN 4775MMW3T9K9KMA0 | F19: 14.99 | G19: APP | I19: =VLOOKUP(G19,Expense_Lookup,2,0) -> Fixed | J19: =J18+F19 -> 1198.89 | K19: HBO | L19: Non-Essential | M19: RECREATION & ENTERTAINMENT | N19: Streaming Services | R19: =SUM(R17:R18) -> 2357.26 | T19: Travel/ Entertainment | U19: Variable | V19: =SUMIFS(F:F,G:G,T19,$B:$B,1) -> 0 | W19: =SUMIFS(F:F,G:G,T19,$B:$B,2) -> 0 | X19: =SUMIFS(F:F,G:G,T19,$B:$B,3) -> 101.04 | Y19: =SUMIFS(F:F,G:G,T19,$B:$B,4) -> 4.24 | Z19: =SUMIFS($F:$F,$G:$G,$T19,$B:$B,5) -> 360.05 | AA19: =SUMIFS($F:$F,$G:$G,$T19,$B:$B,6) -> 179.77 | AB19: =SUMIFS($F:$F,$G:$G,$T19,$B:$B,7) -> 864.12 | AC19: =SUMIFS($F:$F,$G:$G,$T19,$B:$B,8) -> 241.29 | AD19: =SUMIFS($F:$F,$G:$G,$T19,$B:$B,9) -> 360.22 | AE19: =SUMIFS($F:$F,$G:$G,$T19,$B:$B,10) -> 61.14 | AF19: =SUMIFS($F:$F,$G:$G,$T19,$B:$B,11) -> 234.66 | AG19: =SUMIFS($F:$F,$G:$G,$T19,$B:$B,12) -> 543.58 | AH19: =SUM(V19:AG19) -> 2950.11
A20: =YEAR(C20) -> 2021 | B20: =MONTH(C20) -> 1 | C20: 44206 | D20: 44206 | E20: FEDEX 782422707980 800-4633339 TN | F20: 14.47 | G20: Services | I20: =VLOOKUP(G20,Expense_Lookup,2,0) -> Variable | J20: =J19+F20 -> 1213.36 | K20: Darron | L20: Non-Essential | M20: MISCELLANEUS | N20: Family | Q20: Moving | T20: Home Improvement | U20: Variable | V20: =SUMIFS(F:F,G:G,T20,$B:$B,1) -> 0 | W20: =SUMIFS(F:F,G:G,T20,$B:$B,2) -> 0 | X20: =SUMIFS(F:F,G:G,T20,$B:$B,3) -> 0 | Y20: =SUMIFS(F:F,G:G,T20,$B:$B,4) -> 92.58 | Z20: =SUMIFS($F:$F,$G:$G,$T20,$B:$B,5) -> 54.37 | AA20: =SUMIFS($F:$F,$G:$G,$T20,$B:$B,6) -> 23.13 | AB20: =SUMIFS($F:$F,$G:$G,$T20,$B:$B,7) -> 0 | AC20: =SUMIFS($F:$F,$G:$G,$T20,$B:$B,8) -> 89.51 | AD20: =SUMIFS($F:$F,$G:$G,$T20,$B:$B,9) -> 0 | AE20: =SUMIFS($F:$F,$G:$G,$T20,$B:$B,10) -> 167.01 | AF20: =SUMIFS($F:$F,$G:$G,$T20,$B:$B,11) -> 0 | AG20: =SUMIFS($F:$F,$G:$G,$T20,$B:$B,12) -> 0 | AH20: =SUM(V20:AG20) -> 426.6
A21: =YEAR(C21) -> 2021 | B21: =MONTH(C21) -> 1 | C21: 44206 | D21: 44206 | E21: FEDEX 782422725203 800-4633339 TN | F21: 11.45 | G21: Services | I21: =VLOOKUP(G21,Expense_Lookup,2,0) -> Variable | J21: =J20+F21 -> 1224.81 | K21: Darron | L21: Non-Essential | M21: MISCELLANEUS | N21: Family | Q21: Storage | R21: =SUMIFS(F:F,K:K,Q21)+SUMIFS('Cash Flow'!$B:$B,'Cash Flow'!$A:$A,Discover!Q21)*-1 -> 361.27 | T21: Car Wash | U21: Variable | V21: =SUMIFS(F:F,G:G,T21,$B:$B,1) -> 0 | W21: =SUMIFS(F:F,G:G,T21,$B:$B,2) -> 0 | X21: =SUMIFS(F:F,G:G,T21,$B:$B,3) -> 0 | Y21: =SUMIFS(F:F,G:G,T21,$B:$B,4) -> 0 | Z21: =SUMIFS($F:$F,$G:$G,$T21,$B:$B,5) -> 0 | AA21: =SUMIFS($F:$F,$G:$G,$T21,$B:$B,6) -> 0 | AB21: =SUMIFS($F:$F,$G:$G,$T21,$B:$B,7) -> 0 | AC21: =SUMIFS($F:$F,$G:$G,$T21,$B:$B,8) -> 63.08 | AD21: =SUMIFS($F:$F,$G:$G,$T21,$B:$B,9) -> 0 | AE21: =SUMIFS($F:$F,$G:$G,$T21,$B:$B,10) -> 0 | AF21: =SUMIFS($F:$F,$G:$G,$T21,$B:$B,11) -> 0 | AG21: =SUMIFS($F:$F,$G:$G,$T21,$B:$B,12) -> 0 | AH21: =SUM(V21:AG21) -> 63.08
A22: =YEAR(C22) -> 2021 | B22: =MONTH(C22) -> 1 | C22: 44206 | D22: 44206 | E22: WALMART SC 07032 HENRICO VA | F22: 74.16 | G22: Merchandise | I22: =VLOOKUP(G22,Expense_Lookup,2,0) -> Variable | J22: =J21+F22 -> 1298.97 | L22: Non-Essential | M22: PERSONAL SPENDING | N22: Walmart/Target Run | Q22: Arizona | R22: =SUMIFS(F:F,K:K,Q22)+SUMIFS('Cash Flow'!$B:$B,'Cash Flow'!$A:$A,Discover!Q22)*-1 -> 1380.63 | T22: Department Stores | U22: Variable | V22: =SUMIFS(F:F,G:G,T22,$B:$B,1) -> 0 | W22: =SUMIFS(F:F,G:G,T22,$B:$B,2) -> 0 | X22: =SUMIFS(F:F,G:G,T22,$B:$B,3) -> 0 | Y22: =SUMIFS(F:F,G:G,T22,$B:$B,4) -> 0 | Z22: =SUMIFS($F:$F,$G:$G,$T22,$B:$B,5) -> 0 | AA22: =SUMIFS($F:$F,$G:$G,$T22,$B:$B,6) -> 0 | AB22: =SUMIFS($F:$F,$G:$G,$T22,$B:$B,7) -> 0 | AC22: =SUMIFS($F:$F,$G:$G,$T22,$B:$B,8) -> 0 | AD22: =SUMIFS($F:$F,$G:$G,$T22,$B:$B,9) -> 0 | AE22: =SUMIFS($F:$F,$G:$G,$T22,$B:$B,10) -> 0 | AF22: =SUMIFS($F:$F,$G:$G,$T22,$B:$B,11) -> 1455.66 | AG22: =SUMIFS($F:$F,$G:$G,$T22,$B:$B,12) -> 0
A23: =YEAR(C23) -> 2021 | B23: =MONTH(C23) -> 1 | C23: 44207 | D23: 44207 | E23: CASH APP*SHEVON LEW 415-375-3176 CA | F23: 103 | G23: Family | I23: =VLOOKUP(G23,Expense_Lookup,2,0) -> Variable | J23: =J22+F23 -> 1401.97 | K23: Shevon | L23: Non-Essential | M23: MISCELLANEUS | N23: Family | Q23: road trip | R23: =SUMIFS(F:F,K:K,Q23)+SUMIFS('Cash Flow'!$B:$B,'Cash Flow'!$A:$A,Discover!Q23)*-1 -> 1213.29 | V23: =SUM(V6:V22) -> -909.99 | W23: =SUM(W6:W22) -> -1063.45 | X23: =SUM(X6:X22) -> -225.26 | Y23: =SUM(Y6:Y22) -> 1046.94 | Z23: =SUM(Z6:Z22) -> 2.18 | AA23: =SUM(AA6:AA22) -> -93.27 | AB23: =SUM(AB6:AB22) -> -179.58 | AC23: =SUM(AC6:AC22) -> 45.97 | ... AG23: =SUM(AG6:AG22) -> 51.98
A24: =YEAR(C24) -> 2021 | B24: =MONTH(C24) -> 1 | C24: 44207 | D24: 44207 | E24: PAYPAL *ETCHEDACTUA 402-935-7733 CA | F24: 49 | G24: Education | I24: =VLOOKUP(G24,Expense_Lookup,2,0) -> Variable | J24: =J23+F24 -> 1450.97 | L24: Essential | M24: HOME | N24: Study Material (Pre Nationwide) | R24: =SUM(R21:R22) -> 1741.9 | U24: Monthly Spending -> | V24: =SUM(V7:V15,V17:V22) -> 1269.57 | W24: =SUM(W7:W15,W17:W22) -> 1207.02 | X24: =SUM(X7:X15,X17:X22) -> 2202.41 | Y24: =SUM(Y7:Y15,Y17:Y22) -> 1518.01 | Z24: =SUM(Z7:Z15,Z17:Z22) -> 2857.34 | AA24: =SUM(AA7:AA15,AA17:AA22) -> 3204.56 | AB24: =SUM(AB7:AB15,AB17:AB22) -> 5947.51 | AC24: =SUM(AC7:AC15,AC17:AC22) -> 3357.07 | ... AG24: =SUM(AG7:AG15,AG17:AG22) -> 3369.3
A25: =YEAR(C25) -> 2021 | B25: =MONTH(C25) -> 1 | C25: 44208 | D25: 44208 | E25: EXXONMOBIL RICHMOND VA | F25: 23.27 | G25: Gasoline | I25: =VLOOKUP(G25,Expense_Lookup,2,0) -> Variable | J25: =J24+F25 -> 1474.24 | L25: Essential | M25: TRANSPORTATION | N25: Gas
A26: =YEAR(C26) -> 2021 | B26: =MONTH(C26) -> 1 | C26: 44208 | D26: 44208 | E26: FAMILY DOLLAR #5701 RICHMOND VA | F26: 3.33 | G26: Family | I26: =VLOOKUP(G26,Expense_Lookup,2,0) -> Variable | J26: =J25+F26 -> 1477.57 | K26: Jayelin | L26: Non-Essential | M26: MISCELLANEUS | N26: Family
A27: =YEAR(C27) -> 2021 | B27: =MONTH(C27) -> 1 | C27: 44208 | D27: 44208 | E27: PAYPAL *VIZMEDIALLC 888-221-1161 CA | F27: 1.99 | G27: APP | I27: =VLOOKUP(G27,Expense_Lookup,2,0) -> Fixed | J27: =J26+F27 -> 1479.56 | K27: Manga | L27: Non-Essential | M27: RECREATION & ENTERTAINMENT | N27: Streaming Services
A28: =YEAR(C28) -> 2021 | B28: =MONTH(C28) -> 1 | C28: 44211 | D28: 44211 | E28: CASHBACK BONUS REDEMPTION PYMT/STMT CRDT | F28: -22.18 | G28: Awards and Rebate Credits | I28: =VLOOKUP(G28,Expense_Lookup,2,0) -> Payment | J28: =J27+F28 -> 1457.38
A29: =YEAR(C29) -> 2021 | B29: =MONTH(C29) -> 1 | C29: 44211 | D29: 44211 | E29: DIRECTPAY FULL BALANCESEE DETAILS OF YOUR NEXT DIRECTPAY BELOW | F29: -728.15 | G29: Payments and Credits | I29: =VLOOKUP(G29,Expense_Lookup,2,0) -> Payment | J29: =J28+F29 -> 729.23
A30: =YEAR(C30) -> 2021 | B30: =MONTH(C30) -> 1 | C30: 44211 | D30: 44211 | E30: INTERNET PAYMENT - THANK YOU | F30: -729.23 | G30: Payments and Credits | I30: =VLOOKUP(G30,Expense_Lookup,2,0) -> Payment | J30: =J29+F30 -> 0
A31: =YEAR(C31) -> 2021 | B31: =MONTH(C31) -> 1 | C31: 44211 | D31: 44211 | E31: MCDONALD'S F17579 RICHMOND VA | F31: 4.32 | G31: Family | I31: =VLOOKUP(G31,Expense_Lookup,2,0) -> Variable | J31: =J30+F31 -> 4.32 | K31: Jayelin | L31: Non-Essential | M31: MISCELLANEUS | N31: Family
A32: =YEAR(C32) -> 2021 | B32: =MONTH(C32) -> 1 | C32: 44211 | D32: 44211 | E32: WALGREENS #3860 RICHMOND VA | F32: 21.19 | G32: Merchandise | I32: =VLOOKUP(G32,Expense_Lookup,2,0) -> Variable | J32: =J31+F32 -> 25.51 | K32: Draino | L32: Non-Essential | M32: PERSONAL SPENDING | N32: Conveinence Store
A33: =YEAR(C33) -> 2021 | B33: =MONTH(C33) -> 1 | C33: 44211 | D33: 44211 | E33: WALMART SC 07032 HENRICO VA | F33: 19.4 | G33: Merchandise | I33: =VLOOKUP(G33,Expense_Lookup,2,0) -> Variable | J33: =J32+F33 -> 44.91 | K33: Study | L33: Essential | M33: HOME | N33: Office Supplies
A34: =YEAR(C34) -> 2021 | B34: =MONTH(C34) -> 1 | C34: 44212 | D34: 44212 | E34: AMZN MKTP US*0H4DK7EL3 AMZN.COM/BILLWA72J9EGRQCDU | F34: 58.29 | G34: Merchandise | I34: =VLOOKUP(G34,Expense_Lookup,2,0) -> Variable | J34: =J33+F34 -> 103.2 | K34: Webcam | L34: Essential | M34: HOME | N34: Office Supplies
A35: =YEAR(C35) -> 2021 | B35: =MONTH(C35) -> 1 | C35: 44215 | D35: 44215 | E35: CHIPOTLE 1975 RICHMOND VA | F35: 8.23 | G35: Restaurants | H35: fast_food | I35: =VLOOKUP(G35,Expense_Lookup,2,0) -> Variable | J35: =J34+F35 -> 111.43 | L35: Non-Essential | M35: RECREATION & ENTERTAINMENT | N35: Resteraunts
A36: =YEAR(C36) -> 2021 | B36: =MONTH(C36) -> 1 | C36: 44215 | D36: 44215 | E36: CVS/PHARMACY #01988 RICHMOND VA | F36: 2.86 | G36: Family | I36: =VLOOKUP(G36,Expense_Lookup,2,0) -> Variable | J36: =J35+F36 -> 114.29 | K36: Jayelin | L36: Non-Essential | M36: MISCELLANEUS | N36: Family
A37: =YEAR(C37) -> 2021 | B37: =MONTH(C37) -> 1 | C37: 44215 | D37: 44215 | E37: SP * ILF, LLC 8888044453 TX | F37: 99.9 | G37: Merchandise | I37: =VLOOKUP(G37,Expense_Lookup,2,0) -> Variable | J37: =J36+F37 -> 214.19 | L37: Non-Essential | M37: PERSONAL SPENDING | N37: --
A38: =YEAR(C38) -> 2021 | B38: =MONTH(C38) -> 1 | C38: 44216 | D38: 44216 | E38: THE MARKET @ 25TH RICHMOND VA | F38: 15.15 | G38: Supermarkets | I38: =VLOOKUP(G38,Expense_Lookup,2,0) -> Variable | J38: =J37+F38 -> 229.34 | L38: Essential | M38: FOOD | N38: Groceries
A39: =YEAR(C39) -> 2021 | B39: =MONTH(C39) -> 1 | C39: 44217 | D39: 44217 | E39: KINGSISLE *PIRATE101 512-623-5983 TX00099RS900000000000000 | F39: 9.95 | G39: Family | I39: =VLOOKUP(G39,Expense_Lookup,2,0) -> Variable | J39: =J38+F39 -> 239.29 | K39: Jayelin | L39: Non-Essential | M39: MISCELLANEUS | N39: Family
A40: =YEAR(C40) -> 2021 | B40: =MONTH(C40) -> 1 | C40: 44217 | D40: 44217 | E40: PP*PP ROKU FOR CRUNCHYR 402-935-7733 CA | F40: 7.99 | G40: APP | I40: =VLOOKUP(G40,Expense_Lookup,2,0) -> Fixed | J40: =J39+F40 -> 247.28 | K40: Crunchyroll | L40: Non-Essential | M40: RECREATION & ENTERTAINMENT | N40: Streaming Services
A41: =YEAR(C41) -> 2021 | B41: =MONTH(C41) -> 1 | C41: 44218 | D41: 44218 | E41: THE MARKET @ 25TH RICHMOND VA | F41: 15.61 | G41: Supermarkets | I41: =VLOOKUP(G41,Expense_Lookup,2,0) -> Variable | J41: =J40+F41 -> 262.89 | L41: Essential | M41: FOOD | N41: Groceries
A42: =YEAR(C42) -> 2021 | B42: =MONTH(C42) -> 1 | C42: 44219 | D42: 44219 | E42: BEDBATH&BEYOND GLEN ALLEN VA | F42: 84.43 | G42: Merchandise | I42: =VLOOKUP(G42,Expense_Lookup,2,0) -> Variable | J42: =J41+F42 -> 347.32 | K42: Griddle | L42: Essential | M42: HOME | N42: Home Supplies
A43: =YEAR(C43) -> 2021 | B43: =MONTH(C43) -> 1 | C43: 44219 | D43: 44219 | E43: CITYPARKING INC 804-344-3353 VAAPPLE PAY ENDING IN 4775 | F43: 3.35 | G43: Services | I43: =VLOOKUP(G43,Expense_Lookup,2,0) -> Variable | J43: =J42+F43 -> 350.67 | K43: Akhil | L43: Essential | M43: TRANSPORTATION | N43: Parking
A44: =YEAR(C44) -> 2021 | B44: =MONTH(C44) -> 1 | C44: 44219 | D44: 44219 | E44: TST* 521 BISCUITS & WAFF RICHMOND VAAPPLE PAY ENDING IN 4775 | F44: 14.68 | G44: Restaurants | I44: =VLOOKUP(G44,Expense_Lookup,2,0) -> Variable | J44: =J43+F44 -> 365.35 | K44: Kaiya | L44: Non-Essential | M44: RECREATION & ENTERTAINMENT | N44: Resteraunts
A45: =YEAR(C45) -> 2021 | B45: =MONTH(C45) -> 1 | C45: 44221 | D45: 44221 | E45: EXXONMOBIL RICHMOND VA | F45: 2.76 | G45: Gasoline | I45: =VLOOKUP(G45,Expense_Lookup,2,0) -> Variable | J45: =J44+F45 -> 368.11 | L45: Essential | M45: TRANSPORTATION | N45: Gas
A46: =YEAR(C46) -> 2021 | B46: =MONTH(C46) -> 1 | C46: 44221 | D46: 44221 | E46: EXXONMOBIL RICHMOND VA | F46: 22.97 | G46: Gasoline | I46: =VLOOKUP(G46,Expense_Lookup,2,0) -> Variable | J46: =J45+F46 -> 391.08 | L46: Essential | M46: TRANSPORTATION | N46: Gas
A47: =YEAR(C47) -> 2021 | B47: =MONTH(C47) -> 1 | C47: 44222 | D47: 44222 | E47: CHIPOTLE 1975 RICHMOND VA | F47: 8.23 | G47: Restaurants | H47: fast_food | I47: =VLOOKUP(G47,Expense_Lookup,2,0) -> Variable | J47: =J46+F47 -> 399.31 | L47: Non-Essential | M47: RECREATION & ENTERTAINMENT | N47: Resteraunts
A48: =YEAR(C48) -> 2021 | B48: =MONTH(C48) -> 1 | C48: 44222 | D48: 44222 | E48: WHOLEFDS WBS#10598 RICHMOND VA | F48: 63.87 | G48: Supermarkets | I48: =VLOOKUP(G48,Expense_Lookup,2,0) -> Variable | J48: =J47+F48 -> 463.18 | L48: Essential | M48: FOOD | N48: Groceries
A49: =YEAR(C49) -> 2021 | B49: =MONTH(C49) -> 1 | C49: 44223 | D49: 44223 | E49: CVS/PHARMACY #01988 RICHMOND VA | F49: 1.51 | G49: Family | I49: =VLOOKUP(G49,Expense_Lookup,2,0) -> Variable | J49: =J48+F49 -> 464.69 | K49: Jayelin | L49: Non-Essential | M49: MISCELLANEUS | N49: Family
A50: =YEAR(C50) -> 2021 | B50: =MONTH(C50) -> 1 | C50: 44223 | D50: 44223 | E50: CVS/PHARMACY #01988 RICHMOND VA | F50: 2.24 | G50: Family | I50: =VLOOKUP(G50,Expense_Lookup,2,0) -> Variable | J50: =J49+F50 -> 466.93 | K50: Jayelin | L50: Non-Essential | M50: MISCELLANEUS | N50: Family
A51: =YEAR(C51) -> 2021 | B51: =MONTH(C51) -> 1 | C51: 44223 | D51: 44223 | E51: PUBLIX #1588 RICHMOND VA | F51: 4.75 | G51: Supermarkets | I51: =VLOOKUP(G51,Expense_Lookup,2,0) -> Variable | J51: =J50+F51 -> 471.68 | L51: Essential | M51: FOOD | N51: Groceries
A52: =YEAR(C52) -> 2021 | B52: =MONTH(C52) -> 1 | C52: 44224 | D52: 44224 | E52: ABC*CRUNCH FITNESS 888-827-9262 VAABC*CRUNCH FITNESS | F52: 9.95 | G52: APP | I52: =VLOOKUP(G52,Expense_Lookup,2,0) -> Fixed | J52: =J51+F52 -> 481.63 | K52: Crunch Fitness | L52: Non-Essential | M52: PERSONAL SPENDING | N52: Gym
A53: =YEAR(C53) -> 2021 | B53: =MONTH(C53) -> 1 | C53: 44226 | D53: 44226 | E53: THE MARKET @ 25TH RICHMOND VA | F53: 7.42 | G53: Family | I53: =VLOOKUP(G53,Expense_Lookup,2,0) -> Variable | J53: =J52+F53 -> 489.05 | K53: Jayelin | L53: Non-Essential | M53: MISCELLANEUS | N53: Family
A54: =YEAR(C54) -> 2021 | B54: =MONTH(C54) -> 1 | C54: 44227 | D54: 44227 | E54: DC CHARBROILED CHICKEN RICHMOND VA | F54: 9.89 | G54: Family | I54: =VLOOKUP(G54,Expense_Lookup,2,0) -> Variable | J54: =J53+F54 -> 498.94 | K54: Jayelin | L54: Non-Essential | M54: MISCELLANEUS | N54: Family
A55: =YEAR(C55) -> 2021 | B55: =MONTH(C55) -> 1 | C55: 44227 | D55: 44227 | E55: WALMART SC 07032 HENRICO VA | F55: 19.22 | G55: Merchandise | I55: =VLOOKUP(G55,Expense_Lookup,2,0) -> Variable | J55: =J54+F55 -> 518.16 | L55: Non-Essential | M55: PERSONAL SPENDING | N55: Clothes
A56: =YEAR(C56) -> 2021 | B56: =MONTH(C56) -> 2 | C56: 44228 | D56: 44228 | E56: NETFLIX.COM NETFLIX.COM CA44925167830 | F56: 13.99 | G56: APP | I56: =VLOOKUP(G56,Expense_Lookup,2,0) -> Fixed | J56: =J55+F56 -> 532.15 | K56: Netflix | L56: Non-Essential | M56: RECREATION & ENTERTAINMENT | N56: Streaming Services
A57: =YEAR(C57) -> 2021 | B57: =MONTH(C57) -> 2 | C57: 44228 | D57: 44228 | E57: SPOTIFY P1343F2886 8777781161 NY | F57: 9.99 | G57: APP | I57: =VLOOKUP(G57,Expense_Lookup,2,0) -> Fixed | J57: =J56+F57 -> 542.14 | K57: Spotify | L57: Non-Essential | M57: RECREATION & ENTERTAINMENT | N57: Streaming Services
A58: =YEAR(C58) -> 2021 | B58: =MONTH(C58) -> 2 | C58: 44228 | D58: 44230 | E58: CVS/PHARMACY #01988 RICHMOND VA | F58: 15.92 | G58: Family | I58: =VLOOKUP(G58,Expense_Lookup,2,0) -> Variable | J58: =J57+F58 -> 558.06 | K58: Jayelin | L58: Non-Essential | M58: MISCELLANEUS | N58: Family
A59: =YEAR(C59) -> 2021 | B59: =MONTH(C59) -> 2 | C59: 44229 | D59: 44230 | E59: CVS/PHARMACY #01988 RICHMOND VA | F59: 37.01 | G59: Merchandise | I59: =VLOOKUP(G59,Expense_Lookup,2,0) -> Variable | J59: =J58+F59 -> 595.07 | K59: Masks | L59: Non-Essential | M59: PERSONAL SPENDING | N59: Conveinence Store
A60: =YEAR(C60) -> 2021 | B60: =MONTH(C60) -> 2 | C60: 44229 | D60: 44230 | E60: PAYPAL *DAYNEINVEST 888-221-1161 CA | F60: 10 | G60: Merchandise | I60: =VLOOKUP(G60,Expense_Lookup,2,0) -> Variable | J60: =J59+F60 -> 605.07 | L60: Non-Essential | M60: PERSONAL SPENDING | N60: Pay Walls
A61: =YEAR(C61) -> 2021 | B61: =MONTH(C61) -> 2 | C61: 44230 | D61: 44230 | E61: STATE FARM INSURANCE 800-956-6310 IL | F61: 91.78 | G61: APP | I61: =VLOOKUP(G61,Expense_Lookup,2,0) -> Fixed | J61: =J60+F61 -> 696.85 | K61: State Farm | L61: Essential | M61: INSURANCE | N61: Auto Insurance
A62: =YEAR(C62) -> 2021 | B62: =MONTH(C62) -> 2 | C62: 44230 | D62: 44230 | E62: THE MARKET @ 25TH RICHMOND VA | F62: 15.09 | G62: Supermarkets | I62: =VLOOKUP(G62,Expense_Lookup,2,0) -> Variable | J62: =J61+F62 -> 711.94 | L62: Essential | M62: FOOD | N62: Groceries
A63: =YEAR(C63) -> 2021 | B63: =MONTH(C63) -> 2 | C63: 44232 | D63: 44232 | E63: CVS/PHARMACY #01988 RICHMOND VA | F63: 1.63 | G63: Family | I63: =VLOOKUP(G63,Expense_Lookup,2,0) -> Variable | J63: =J62+F63 -> 713.57 | K63: Jayelin | L63: Non-Essential | M63: MISCELLANEUS | N63: Family
A64: =YEAR(C64) -> 2021 | B64: =MONTH(C64) -> 2 | C64: 44232 | D64: 44232 | E64: CVS/PHARMACY #01988 RICHMOND VA | F64: 2.45 | G64: Family | I64: =VLOOKUP(G64,Expense_Lookup,2,0) -> Variable | J64: =J63+F64 -> 716.02 | K64: Jayelin | L64: Non-Essential | M64: MISCELLANEUS | N64: Family
A65: =YEAR(C65) -> 2021 | B65: =MONTH(C65) -> 2 | C65: 44234 | D65: 44234 | E65: CHIPOTLE 1975 RICHMOND VA | F65: 9.36 | G65: Family | I65: =VLOOKUP(G65,Expense_Lookup,2,0) -> Variable | J65: =J64+F65 -> 725.38 | K65: Jayelin | L65: Non-Essential | M65: MISCELLANEUS | N65: Family
A66: =YEAR(C66) -> 2021 | B66: =MONTH(C66) -> 2 | C66: 44237 | D66: 44237 | E66: APPLE.COM/BILL 866-712-7753 CAAPPLE PAY ENDING IN 4775MMW42NJ145A0 | F66: 3.99 | G66: Family | I66: =VLOOKUP(G66,Expense_Lookup,2,0) -> Variable | J66: =J65+F66 -> 729.37 | K66: Jayelin | L66: Non-Essential | M66: MISCELLANEUS | N66: Family
A67: =YEAR(C67) -> 2021 | B67: =MONTH(C67) -> 2 | C67: 44237 | D67: 44237 | E67: CVS/PHARMACY #01988 RICHMOND VA | F67: 4.73 | G67: Family | I67: =VLOOKUP(G67,Expense_Lookup,2,0) -> Variable | J67: =J66+F67 -> 734.1 | K67: Jayelin | L67: Non-Essential | M67: MISCELLANEUS | N67: Family
A68: =YEAR(C68) -> 2021 | B68: =MONTH(C68) -> 2 | C68: 44238 | D68: 44238 | E68: BIRD APP 8662052442 CA | F68: 5 | G68: Family | I68: =VLOOKUP(G68,Expense_Lookup,2,0) -> Variable | J68: =J67+F68 -> 739.1 | K68: Jayelin | L68: Non-Essential | M68: MISCELLANEUS | N68: Family
A69: =YEAR(C69) -> 2021 | B69: =MONTH(C69) -> 2 | C69: 44238 | D69: 44238 | E69: BIRD APP 8662052442 CA | F69: 5 | G69: Family | I69: =VLOOKUP(G69,Expense_Lookup,2,0) -> Variable | J69: =J68+F69 -> 744.1 | K69: Jayelin | L69: Non-Essential | M69: MISCELLANEUS | N69: Family
A70: =YEAR(C70) -> 2021 | B70: =MONTH(C70) -> 2 | C70: 44238 | D70: 44238 | E70: BIRD APP 8662052442 CA | F70: 5 | G70: Family | I70: =VLOOKUP(G70,Expense_Lookup,2,0) -> Variable | J70: =J69+F70 -> 749.1 | K70: Jayelin | L70: Non-Essential | M70: MISCELLANEUS | N70: Family
A71: =YEAR(C71) -> 2021 | B71: =MONTH(C71) -> 2 | C71: 44239 | D71: 44239 | E71: CASHBACK BONUS REDEMPTION PYMT/STMT CRDT | F71: -14 | G71: Awards and Rebate Credits | I71: =VLOOKUP(G71,Expense_Lookup,2,0) -> Payment | J71: =J70+F71 -> 735.1
A72: =YEAR(C72) -> 2021 | B72: =MONTH(C72) -> 2 | C72: 44239 | D72: 44239 | E72: INTERNET PAYMENT - THANK YOU | F72: -715.37 | G72: Payments and Credits | I72: =VLOOKUP(G72,Expense_Lookup,2,0) -> Payment | J72: =J71+F72 -> 19.73
A73: =YEAR(C73) -> 2021 | B73: =MONTH(C73) -> 2 | C73: 44239 | D73: 44239 | E73: PAYPAL *VIZMEDIALLC 888-221-1161 CA | F73: 1.99 | G73: APP | I73: =VLOOKUP(G73,Expense_Lookup,2,0) -> Fixed | J73: =J72+F73 -> 21.72 | K73: Manga | L73: Non-Essential | M73: RECREATION & ENTERTAINMENT | N73: Streaming Services
A74: =YEAR(C74) -> 2021 | B74: =MONTH(C74) -> 2 | C74: 44241 | D74: 44241 | E74: APPLE.COM/BILL 866-712-7753 CAAPPLE PAY ENDING IN 4775MMW43JVXWTA0 | F74: 14.99 | G74: APP | I74: =VLOOKUP(G74,Expense_Lookup,2,0) -> Fixed | J74: =J73+F74 -> 36.71 | K74: HBO | L74: Non-Essential | M74: RECREATION & ENTERTAINMENT | N74: Streaming Services
A75: =YEAR(C75) -> 2021 | B75: =MONTH(C75) -> 2 | C75: 44241 | D75: 44241 | E75: THE MARKET @ 25TH RICHMOND VA | F75: 7.88 | G75: Supermarkets | I75: =VLOOKUP(G75,Expense_Lookup,2,0) -> Variable | J75: =J74+F75 -> 44.59 | L75: Essential | M75: FOOD | N75: Groceries
A76: =YEAR(C76) -> 2021 | B76: =MONTH(C76) -> 2 | C76: 44241 | D76: 44241 | E76: WALMART SC 07032 HENRICO VA | F76: 48.58 | G76: Merchandise | I76: =VLOOKUP(G76,Expense_Lookup,2,0) -> Variable | J76: =J75+F76 -> 93.17 | L76: Non-Essential | M76: PERSONAL SPENDING | N76: Walmart/Target Run
A77: =YEAR(C77) -> 2021 | B77: =MONTH(C77) -> 2 | C77: 44244 | D77: 44244 | E77: TARGET RICHMOND VA | F77: 76.3 | G77: Merchandise | I77: =VLOOKUP(G77,Expense_Lookup,2,0) -> Variable | J77: =J76+F77 -> 169.47 | K77: Pants | L77: Non-Essential | M77: PERSONAL SPENDING | N77: Clothes
A78: =YEAR(C78) -> 2021 | B78: =MONTH(C78) -> 2 | C78: 44246 | D78: 44246 | E78: PUPATELLA 2 RICHMOND VA | F78: 40.42 | G78: Restaurants | I78: =VLOOKUP(G78,Expense_Lookup,2,0) -> Variable | J78: =J77+F78 -> 209.89 | L78: Non-Essential | M78: RECREATION & ENTERTAINMENT | N78: Resteraunts
A79: =YEAR(C79) -> 2021 | B79: =MONTH(C79) -> 2 | C79: 44247 | D79: 44247 | E79: PUBLIX #1588 RICHMOND VA | F79: 135.35 | G79: Supermarkets | I79: =VLOOKUP(G79,Expense_Lookup,2,0) -> Variable | J79: =J78+F79 -> 345.24 | L79: Essential | M79: FOOD | N79: Groceries
A80: =YEAR(C80) -> 2021 | B80: =MONTH(C80) -> 2 | C80: 44247 | D80: 44247 | E80: T-MOBILE PAYMENTS 800-937-8997 WAAPPLE PAY ENDING IN 4775T-MOBILE PAYMENTS | F80: 86.25 | G80: APP | I80: =VLOOKUP(G80,Expense_Lookup,2,0) -> Fixed | J80: =J79+F80 -> 431.49 | K80: T-Mobile | L80: Essential | M80: UTILITIES | N80: Phone
A81: =YEAR(C81) -> 2021 | B81: =MONTH(C81) -> 2 | C81: 44247 | D81: 44247 | E81: THE MARKET @ 25TH RICHMOND VA | F81: 10.64 | G81: Supermarkets | I81: =VLOOKUP(G81,Expense_Lookup,2,0) -> Variable | J81: =J80+F81 -> 442.13 | L81: Essential | M81: FOOD | N81: Groceries
A82: =YEAR(C82) -> 2021 | B82: =MONTH(C82) -> 2 | C82: 44247 | D82: 44247 | E82: WWW.WOLFRAMALPHA.COM 8009653726 IL | F82: 6.99 | G82: Merchandise | I82: =VLOOKUP(G82,Expense_Lookup,2,0) -> Variable | J82: =J81+F82 -> 449.12 | K82: Study tool | L82: Non-Essential | M82: PERSONAL SPENDING | N82: Pay Walls
A83: =YEAR(C83) -> 2021 | B83: =MONTH(C83) -> 2 | C83: 44248 | D83: 44248 | E83: CHIPOTLE 1975 RICHMOND VA | F83: 8.23 | G83: Family | I83: =VLOOKUP(G83,Expense_Lookup,2,0) -> Variable | J83: =J82+F83 -> 457.35 | K83: Jayelin | L83: Non-Essential | M83: MISCELLANEUS | N83: Family
A84: =YEAR(C84) -> 2021 | B84: =MONTH(C84) -> 2 | C84: 44248 | D84: 44248 | E84: KINGSISLE *PIRATE101 512-623-5983 TX0009CTVV00000000000000 | F84: 9.95 | G84: Family | I84: =VLOOKUP(G84,Expense_Lookup,2,0) -> Variable | J84: =J83+F84 -> 467.3 | K84: Jayelin | L84: Non-Essential | M84: MISCELLANEUS | N84: Family
A85: =YEAR(C85) -> 2021 | B85: =MONTH(C85) -> 2 | C85: 44248 | D85: 44248 | E85: PP*PP ROKU FOR CRUNCHYR 402-935-7733 CA | F85: 7.99 | G85: APP | I85: =VLOOKUP(G85,Expense_Lookup,2,0) -> Fixed | J85: =J84+F85 -> 475.29 | K85: Crunchyroll | L85: Non-Essential | M85: RECREATION & ENTERTAINMENT | N85: Streaming Services
A86: =YEAR(C86) -> 2021 | B86: =MONTH(C86) -> 2 | C86: 44248 | D86: 44248 | E86: SUNOCO 0113723100 RICHMOND VA | F86: 25.35 | G86: Gasoline | I86: =VLOOKUP(G86,Expense_Lookup,2,0) -> Variable | J86: =J85+F86 -> 500.64 | L86: Essential | M86: TRANSPORTATION | N86: Gas
A87: =YEAR(C87) -> 2021 | B87: =MONTH(C87) -> 2 | C87: 44248 | D87: 44248 | E87: WALMART SC 07032 HENRICO VA | F87: 11.64 | G87: Merchandise | I87: =VLOOKUP(G87,Expense_Lookup,2,0) -> Variable | J87: =J86+F87 -> 512.28 | L87: Non-Essential | M87: PERSONAL SPENDING | N87: Walmart/Target Run
A88: =YEAR(C88) -> 2021 | B88: =MONTH(C88) -> 2 | C88: 44248 | D88: 44248 | E88: WALMART SC 07032 HENRICO VA | F88: 20.14 | G88: Merchandise | I88: =VLOOKUP(G88,Expense_Lookup,2,0) -> Variable | J88: =J87+F88 -> 532.42 | L88: Non-Essential | M88: PERSONAL SPENDING | N88: Walmart/Target Run
A89: =YEAR(C89) -> 2021 | B89: =MONTH(C89) -> 2 | C89: 44248 | D89: 44248 | E89: WALMART SC 07032 HENRICO VA | F89: 21.14 | G89: Merchandise | I89: =VLOOKUP(G89,Expense_Lookup,2,0) -> Variable | J89: =J88+F89 -> 553.56 | L89: Non-Essential | M89: PERSONAL SPENDING | N89: Walmart/Target Run
A90: =YEAR(C90) -> 2021 | B90: =MONTH(C90) -> 2 | C90: 44250 | D90: 44250 | E90: PAYPAL *WEBULL TECH 402-935-7733 CA | F90: 1.99 | G90: APP | I90: =VLOOKUP(G90,Expense_Lookup,2,0) -> Fixed | J90: =J89+F90 -> 555.55 | K90: Webull | L90: Non-Essential | M90: RECREATION & ENTERTAINMENT | N90: Subscription
A91: =YEAR(C91) -> 2021 | B91: =MONTH(C91) -> 2 | C91: 44251 | D91: 44251 | E91: COACHING ACTUARIES 8324128532 IA | F91: 215 | G91: Education | I91: =VLOOKUP(G91,Expense_Lookup,2,0) -> Variable | J91: =J90+F91 -> 770.55 | K91: Adapt | L91: Essential | M91: HOME | N91: Study Material (Pre Nationwide)
A92: =YEAR(C92) -> 2021 | B92: =MONTH(C92) -> 2 | C92: 44253 | D92: 44253 | E92: INTERNET PAYMENT - THANK YOU | F92: -770.55 | G92: Payments and Credits | I92: =VLOOKUP(G92,Expense_Lookup,2,0) -> Payment | J92: =J91+F92 -> 0
A93: =YEAR(C93) -> 2021 | B93: =MONTH(C93) -> 2 | C93: 44253 | D93: 44253 | E93: DISNEYPLUS 888-905-7888 CADISNEYPLUS | F93: 6.99 | G93: Merchandise | I93: =VLOOKUP(G93,Expense_Lookup,2,0) -> Variable | J93: =J92+F93 -> 6.99 | L93: Non-Essential | M93: RECREATION & ENTERTAINMENT | N93: Streaming Services
A94: =YEAR(C94) -> 2021 | B94: =MONTH(C94) -> 2 | C94: 44253 | D94: 44253 | E94: INTERNET PAYMENT - THANK YOU | F94: -770.55 | G94: Payments and Credits | I94: =VLOOKUP(G94,Expense_Lookup,2,0) -> Payment | J94: =J93+F94 -> -763.56
A95: =YEAR(C95) -> 2021 | B95: =MONTH(C95) -> 2 | C95: 44253 | D95: 44253 | E95: WALMART SC 07032 HENRICO VA | F95: 13.67 | G95: Merchandise | I95: =VLOOKUP(G95,Expense_Lookup,2,0) -> Variable | J95: =J94+F95 -> -749.89 | L95: Non-Essential | M95: PERSONAL SPENDING | N95: Walmart/Target Run
A96: =YEAR(C96) -> 2021 | B96: =MONTH(C96) -> 2 | C96: 44254 | D96: 44254 | E96: APPLE.COM/BILL 866-712-7753 CAAPPLE PAY ENDING IN 4775MMW4751VM2A0 | F96: 1.99 | G96: APP | I96: =VLOOKUP(G96,Expense_Lookup,2,0) -> Fixed | J96: =J95+F96 -> -747.9 | K96: Manga | L96: Non-Essential | M96: RECREATION & ENTERTAINMENT | N96: Streaming Services
A97: =YEAR(C97) -> 2021 | B97: =MONTH(C97) -> 2 | C97: 44254 | D97: 44254 | E97: PAYPAL *COUPLECENTS 402-935-7733 CA | F97: 9.99 | G97: APP | I97: =VLOOKUP(G97,Expense_Lookup,2,0) -> Fixed | J97: =J96+F97 -> -737.91 | K97: Couple Cents | L97: Non-Essential | M97: RECREATION & ENTERTAINMENT | N97: Subscription
A98: =YEAR(C98) -> 2021 | B98: =MONTH(C98) -> 2 | C98: 44254 | D98: 44254 | E98: SHEETZ 267200026724498 WOODFORD VA | F98: 16.24 | G98: Gasoline | I98: =VLOOKUP(G98,Expense_Lookup,2,0) -> Variable | J98: =J97+F98 -> -721.67 | L98: Essential | M98: TRANSPORTATION | N98: Gas
A99: =YEAR(C99) -> 2021 | B99: =MONTH(C99) -> 2 | C99: 44254 | D99: 44254 | E99: TACO BELL #28942 DUMFRIES VA | F99: 11.54 | G99: Restaurants | H99: fast_food | I99: =VLOOKUP(G99,Expense_Lookup,2,0) -> Variable | J99: =J98+F99 -> -710.13 | L99: Non-Essential | M99: RECREATION & ENTERTAINMENT | N99: Resteraunts
A100: =YEAR(C100) -> 2021 | B100: =MONTH(C100) -> 2 | C100: 44254 | D100: 44254 | E100: WWW.CVS.COM 800-746-7287 RI | F100: 5 | G100: Merchandise | I100: =VLOOKUP(G100,Expense_Lookup,2,0) -> Variable | J100: =J99+F100 -> -705.13 | L100: Non-Essential | M100: PERSONAL SPENDING | N100: Conveinence Store
...

Sheet Subscriptions
A1: Name | B1: Sub Type | C1: Cancelled? | D1: Day | E1: Total Paid | F1: # | G1: Avg. Paid | H1: Jan | I1: Feb | J1: Mar | K1: Apr | L1: May | M1: June | N1: July | O1: Aug | P1: Sep | Q1: Oct | R1: Nov | S1: Dec
A2: {=_xlfn._xlws.SORT(_xlfn.UNIQUE(_xlfn.UNIQUE(_xlfn._xlws.FILTER(Discover!K:K, (Discover!G:G = "APP")*(Discover!K:K <>0)),1)))} -> Apple Music | B2: Monthly | C2: Yes | D2: {=AVERAGE(DAY(_xlfn.UNIQUE(_xlfn._xlws.FILTER(Discover!C:C, Discover!K:K = A2,0),1)))} -> 29 | E2: =SUMIFS(Discover!F:F,Discover!K:K,Subscriptions!A2) -> 21.18 | F2: =COUNTIFS(Discover!K:K,Subscriptions!A2,Discover!G:G,"APP") -> 2 | G2: =E2/F2 -> 10.59 | H2: =SUMIFS(Discover!$F:$F,Discover!$K:$K,Subscriptions!$A2,Discover!$B:$B,1) -> 0 | I2: =SUMIFS(Discover!$F:$F,Discover!$K:$K,Subscriptions!$A2,Discover!$B:$B,2) -> 0 | J2: =SUMIFS(Discover!$F:$F,Discover!$K:$K,Subscriptions!$A2,Discover!$B:$B,3) -> 0 | K2: =SUMIFS(Discover!$F:$F,Discover!$K:$K,Subscriptions!$A2,Discover!$B:$B,4) -> 0 | L2: =SUMIFS(Discover!$F:$F,Discover!$K:$K,Subscriptions!$A2,Discover!$B:$B,5) -> 0 | M2: =SUMIFS(Discover!$F:$F,Discover!$K:$K,Subscriptions!$A2,Discover!$B:$B,6) -> 0 | N2: =SUMIFS(Discover!$F:$F,Discover!$K:$K,Subscriptions!$A2,Discover!$B:$B,7) -> 0 | O2: =SUMIFS(Discover!$F:$F,Discover!$K:$K,Subscriptions!$A2,Discover!$B:$B,8) -> 10.59 | P2: =SUMIFS(Discover!$F:$F,Discover!$K:$K,Subscriptions!$A2,Discover!$B:$B,9) -> 10.59 | Q2: =SUMIFS(Discover!$F:$F,Discover!$K:$K,Subscriptions!$A2,Discover!$B:$B,10) -> 0 | R2: =SUMIFS(Discover!$F:$F,Discover!$K:$K,Subscriptions!$A2,Discover!$B:$B,11) -> 0 | S2: =SUMIFS(Discover!$F:$F,Discover!$K:$K,Subscriptions!$A2,Discover!$B:$B,12) -> 0
A3: Apple TV+ | B3: One time | C3: No | D3: {=AVERAGE(DAY(_xlfn.UNIQUE(_xlfn._xlws.FILTER(Discover!C:C, Discover!K:K = A3,0),1)))} -> 17.75 | E3: =SUMIFS(Discover!F:F,Discover!K:K,Subscriptions!A3) -> 21.16 | F3: =COUNTIFS(Discover!K:K,Subscriptions!A3,Discover!G:G,"APP") -> 4 | G3: =E3/F3 -> 5.29 | H3: =SUMIFS(Discover!$F:$F,Discover!$K:$K,Subscriptions!$A3,Discover!$B:$B,1) -> 0 | I3: =SUMIFS(Discover!$F:$F,Discover!$K:$K,Subscriptions!$A3,Discover!$B:$B,2) -> 0 | J3: =SUMIFS(Discover!$F:$F,Discover!$K:$K,Subscriptions!$A3,Discover!$B:$B,3) -> 0 | K3: =SUMIFS(Discover!$F:$F,Discover!$K:$K,Subscriptions!$A3,Discover!$B:$B,4) -> 0 | L3: =SUMIFS(Discover!$F:$F,Discover!$K:$K,Subscriptions!$A3,Discover!$B:$B,5) -> 0 | M3: =SUMIFS(Discover!$F:$F,Discover!$K:$K,Subscriptions!$A3,Discover!$B:$B,6) -> 0 | N3: =SUMIFS(Discover!$F:$F,Discover!$K:$K,Subscriptions!$A3,Discover!$B:$B,7) -> 0 | O3: =SUMIFS(Discover!$F:$F,Discover!$K:$K,Subscriptions!$A3,Discover!$B:$B,8) -> 0 | P3: =SUMIFS(Discover!$F:$F,Discover!$K:$K,Subscriptions!$A3,Discover!$B:$B,9) -> 5.29 | Q3: =SUMIFS(Discover!$F:$F,Discover!$K:$K,Subscriptions!$A3,Discover!$B:$B,10) -> 5.29 | R3: =SUMIFS(Discover!$F:$F,Discover!$K:$K,Subscriptions!$A3,Discover!$B:$B,11) -> 5.29 | S3: =SUMIFS(Discover!$F:$F,Discover!$K:$K,Subscriptions!$A3,Discover!$B:$B,12) -> 5.29
A4: Audible | B4: Monthly | C4: No | D4: {=AVERAGE(DAY(_xlfn.UNIQUE(_xlfn._xlws.FILTER(Discover!C:C, Discover!K:K = A4,0),1)))} -> 18.5 | E4: =SUMIFS(Discover!F:F,Discover!K:K,Subscriptions!A4) -> 65.2 | F4: =COUNTIFS(Discover!K:K,Subscriptions!A4,Discover!G:G,"APP") -> 4 | G4: =E4/F4 -> 16.3 | H4: =SUMIFS(Discover!$F:$F,Discover!$K:$K,Subscriptions!$A4,Discover!$B:$B,1) -> 0 | I4: =SUMIFS(Discover!$F:$F,Discover!$K:$K,Subscriptions!$A4,Discover!$B:$B,2) -> 0 | J4: =SUMIFS(Discover!$F:$F,Discover!$K:$K,Subscriptions!$A4,Discover!$B:$B,3) -> 0 | K4: =SUMIFS(Discover!$F:$F,Discover!$K:$K,Subscriptions!$A4,Discover!$B:$B,4) -> 0 | L4: =SUMIFS(Discover!$F:$F,Discover!$K:$K,Subscriptions!$A4,Discover!$B:$B,5) -> 0 | M4: =SUMIFS(Discover!$F:$F,Discover!$K:$K,Subscriptions!$A4,Discover!$B:$B,6) -> 0 | N4: =SUMIFS(Discover!$F:$F,Discover!$K:$K,Subscriptions!$A4,Discover!$B:$B,7) -> 0 | O4: =SUMIFS(Discover!$F:$F,Discover!$K:$K,Subscriptions!$A4,Discover!$B:$B,8) -> 56.52 | P4: =SUMIFS(Discover!$F:$F,Discover!$K:$K,Subscriptions!$A4,Discover!$B:$B,9) -> 8.68 | Q4: =SUMIFS(Discover!$F:$F,Discover!$K:$K,Subscriptions!$A4,Discover!$B:$B,10) -> 0 | R4: =SUMIFS(Discover!$F:$F,Discover!$K:$K,Subscriptions!$A4,Discover!$B:$B,11) -> 0 | S4: =SUMIFS(Discover!$F:$F,Discover!$K:$K,Subscriptions!$A4,Discover!$B:$B,12) -> 0
A5: Bloomberg | B5: Monthly | C5: Yes | D5: {=AVERAGE(DAY(_xlfn.UNIQUE(_xlfn._xlws.FILTER(Discover!C:C, Discover!K:K = A5,0),1)))} -> 31 | E5: =SUMIFS(Discover!F:F,Discover!K:K,Subscriptions!A5) -> 37.09 | F5: =COUNTIFS(Discover!K:K,Subscriptions!A5,Discover!G:G,"APP") -> 1 | G5: =E5/F5 -> 37.09 | H5: =SUMIFS(Discover!$F:$F,Discover!$K:$K,Subscriptions!$A5,Discover!$B:$B,1) -> 0 | I5: =SUMIFS(Discover!$F:$F,Discover!$K:$K,Subscriptions!$A5,Discover!$B:$B,2) -> 0 | J5: =SUMIFS(Discover!$F:$F,Discover!$K:$K,Subscriptions!$A5,Discover!$B:$B,3) -> 0 | K5: =SUMIFS(Discover!$F:$F,Discover!$K:$K,Subscriptions!$A5,Discover!$B:$B,4) -> 0 | L5: =SUMIFS(Discover!$F:$F,Discover!$K:$K,Subscriptions!$A5,Discover!$B:$B,5) -> 37.09 | M5: =SUMIFS(Discover!$F:$F,Discover!$K:$K,Subscriptions!$A5,Discover!$B:$B,6) -> 0 | N5: =SUMIFS(Discover!$F:$F,Discover!$K:$K,Subscriptions!$A5,Discover!$B:$B,7) -> 0 | O5: =SUMIFS(Discover!$F:$F,Discover!$K:$K,Subscriptions!$A5,Discover!$B:$B,8) -> 0 | P5: =SUMIFS(Discover!$F:$F,Discover!$K:$K,Subscriptions!$A5,Discover!$B:$B,9) -> 0 | Q5: =SUMIFS(Discover!$F:$F,Discover!$K:$K,Subscriptions!$A5,Discover!$B:$B,10) -> 0 | R5: =SUMIFS(Discover!$F:$F,Discover!$K:$K,Subscriptions!$A5,Discover!$B:$B,11) -> 0 | S5: =SUMIFS(Discover!$F:$F,Discover!$K:$K,Subscriptions!$A5,Discover!$B:$B,12) -> 0
A6: Bumble | B6: Monthly | C6: Yes | D6: {=AVERAGE(DAY(_xlfn.UNIQUE(_xlfn._xlws.FILTER(Discover!C:C, Discover!K:K = A6,0),1)))} -> 10 | E6: =SUMIFS(Discover!F:F,Discover!K:K,Subscriptions!A6) -> 126.98 | F6: =COUNTIFS(Discover!K:K,Subscriptions!A6,Discover!G:G,"APP") -> 4 | G6: =E6/F6 -> 31.745 | H6: =SUMIFS(Discover!$F:$F,Discover!$K:$K,Subscriptions!$A6,Discover!$B:$B,1) -> 0 | I6: =SUMIFS(Discover!$F:$F,Discover!$K:$K,Subscriptions!$A6,Discover!$B:$B,2) -> 0 | J6: =SUMIFS(Discover!$F:$F,Discover!$K:$K,Subscriptions!$A6,Discover!$B:$B,3) -> 0 | K6: =SUMIFS(Discover!$F:$F,Discover!$K:$K,Subscriptions!$A6,Discover!$B:$B,4) -> 0 | L6: =SUMIFS(Discover!$F:$F,Discover!$K:$K,Subscriptions!$A6,Discover!$B:$B,5) -> 0 | M6: =SUMIFS(Discover!$F:$F,Discover!$K:$K,Subscriptions!$A6,Discover!$B:$B,6) -> 0 | N6: =SUMIFS(Discover!$F:$F,Discover!$K:$K,Subscriptions!$A6,Discover!$B:$B,7) -> 0 | O6: =SUMIFS(Discover!$F:$F,Discover!$K:$K,Subscriptions!$A6,Discover!$B:$B,8) -> 84.59 | P6: =SUMIFS(Discover!$F:$F,Discover!$K:$K,Subscriptions!$A6,Discover!$B:$B,9) -> 0 | Q6: =SUMIFS(Discover!$F:$F,Discover!$K:$K,Subscriptions!$A6,Discover!$B:$B,10) -> 42.39 | R6: =SUMIFS(Discover!$F:$F,Discover!$K:$K,Subscriptions!$A6,Discover!$B:$B,11) -> 0 | S6: =SUMIFS(Discover!$F:$F,Discover!$K:$K,Subscriptions!$A6,Discover!$B:$B,12) -> 0
A7: Catan Gold | B7: Monthly | C7: No | D7: {=AVERAGE(DAY(_xlfn.UNIQUE(_xlfn._xlws.FILTER(Discover!C:C, Discover!K:K = A7,0),1)))} -> 26 | E7: =SUMIFS(Discover!F:F,Discover!K:K,Subscriptions!A7) -> 14.99 | F7: =COUNTIFS(Discover!K:K,Subscriptions!A7,Discover!G:G,"APP") -> 1 | G7: =E7/F7 -> 14.99 | H7: =SUMIFS(Discover!$F:$F,Discover!$K:$K,Subscriptions!$A7,Discover!$B:$B,1) -> 0 | I7: =SUMIFS(Discover!$F:$F,Discover!$K:$K,Subscriptions!$A7,Discover!$B:$B,2) -> 0 | J7: =SUMIFS(Discover!$F:$F,Discover!$K:$K,Subscriptions!$A7,Discover!$B:$B,3) -> 14.99 | K7: =SUMIFS(Discover!$F:$F,Discover!$K:$K,Subscriptions!$A7,Discover!$B:$B,4) -> 0 | L7: =SUMIFS(Discover!$F:$F,Discover!$K:$K,Subscriptions!$A7,Discover!$B:$B,5) -> 0 | M7: =SUMIFS(Discover!$F:$F,Discover!$K:$K,Subscriptions!$A7,Discover!$B:$B,6) -> 0 | N7: =SUMIFS(Discover!$F:$F,Discover!$K:$K,Subscriptions!$A7,Discover!$B:$B,7) -> 0 | O7: =SUMIFS(Discover!$F:$F,Discover!$K:$K,Subscriptions!$A7,Discover!$B:$B,8) -> 0 | P7: =SUMIFS(Discover!$F:$F,Discover!$K:$K,Subscriptions!$A7,Discover!$B:$B,9) -> 0 | Q7: =SUMIFS(Discover!$F:$F,Discover!$K:$K,Subscriptions!$A7,Discover!$B:$B,10) -> 0 | R7: =SUMIFS(Discover!$F:$F,Discover!$K:$K,Subscriptions!$A7,Discover!$B:$B,11) -> 0 | S7: =SUMIFS(Discover!$F:$F,Discover!$K:$K,Subscriptions!$A7,Discover!$B:$B,12) -> 0
A8: Couple Cents | B8: Annual | C8: No | D8: {=AVERAGE(DAY(_xlfn.UNIQUE(_xlfn._xlws.FILTER(Discover!C:C, Discover!K:K = A8,0),1)))} -> 27 | E8: =SUMIFS(Discover!F:F,Discover!K:K,Subscriptions!A8) -> 79.92 | F8: =COUNTIFS(Discover!K:K,Subscriptions!A8,Discover!G:G,"APP") -> 7 | G8: =E8/F8 -> 11.417143 | H8: =SUMIFS(Discover!$F:$F,Discover!$K:$K,Subscriptions!$A8,Discover!$B:$B,1) -> 0 | I8: =SUMIFS(Discover!$F:$F,Discover!$K:$K,Subscriptions!$A8,Discover!$B:$B,2) -> 9.99 | J8: =SUMIFS(Discover!$F:$F,Discover!$K:$K,Subscriptions!$A8,Discover!$B:$B,3) -> 9.99 | K8: =SUMIFS(Discover!$F:$F,Discover!$K:$K,Subscriptions!$A8,Discover!$B:$B,4) -> 9.99 | L8: =SUMIFS(Discover!$F:$F,Discover!$K:$K,Subscriptions!$A8,Discover!$B:$B,5) -> 9.99 | M8: =SUMIFS(Discover!$F:$F,Discover!$K:$K,Subscriptions!$A8,Discover!$B:$B,6) -> 9.99 | N8: =SUMIFS(Discover!$F:$F,Discover!$K:$K,Subscriptions!$A8,Discover!$B:$B,7) -> 9.99 | O8: =SUMIFS(Discover!$F:$F,Discover!$K:$K,Subscriptions!$A8,Discover!$B:$B,8) -> 9.99 | P8: =SUMIFS(Discover!$F:$F,Discover!$K:$K,Subscriptions!$A8,Discover!$B:$B,9) -> 9.99 | Q8: =SUMIFS(Discover!$F:$F,Discover!$K:$K,Subscriptions!$A8,Discover!$B:$B,10) -> 0 | R8: =SUMIFS(Discover!$F:$F,Discover!$K:$K,Subscriptions!$A8,Discover!$B:$B,11) -> 0 | S8: =SUMIFS(Discover!$F:$F,Discover!$K:$K,Subscriptions!$A8,Discover!$B:$B,12) -> 0
A9: Credit Score | B9: Monthly | C9: Yes | D9: {=AVERAGE(DAY(_xlfn.UNIQUE(_xlfn._xlws.FILTER(Discover!C:C, Discover!K:K = A9,0),1)))} -> 5 | E9: =SUMIFS(Discover!F:F,Discover!K:K,Subscriptions!A9) -> 39.95 | F9: =COUNTIFS(Discover!K:K,Subscriptions!A9,Discover!G:G,"APP") -> 1 | G9: =E9/F9 -> 39.95 | H9: =SUMIFS(Discover!$F:$F,Discover!$K:$K,Subscriptions!$A9,Discover!$B:$B,1) -> 39.95 | I9: =SUMIFS(Discover!$F:$F,Discover!$K:$K,Subscriptions!$A9,Discover!$B:$B,2) -> 0 | J9: =SUMIFS(Discover!$F:$F,Discover!$K:$K,Subscriptions!$A9,Discover!$B:$B,3) -> 0 | K9: =SUMIFS(Discover!$F:$F,Discover!$K:$K,Subscriptions!$A9,Discover!$B:$B,4) -> 0 | L9: =SUMIFS(Discover!$F:$F,Discover!$K:$K,Subscriptions!$A9,Discover!$B:$B,5) -> 0 | M9: =SUMIFS(Discover!$F:$F,Discover!$K:$K,Subscriptions!$A9,Discover!$B:$B,6) -> 0 | N9: =SUMIFS(Discover!$F:$F,Discover!$K:$K,Subscriptions!$A9,Discover!$B:$B,7) -> 0 | O9: =SUMIFS(Discover!$F:$F,Discover!$K:$K,Subscriptions!$A9,Discover!$B:$B,8) -> 0 | P9: =SUMIFS(Discover!$F:$F,Discover!$K:$K,Subscriptions!$A9,Discover!$B:$B,9) -> 0 | Q9: =SUMIFS(Discover!$F:$F,Discover!$K:$K,Subscriptions!$A9,Discover!$B:$B,10) -> 0 | R9: =SUMIFS(Discover!$F:$F,Discover!$K:$K,Subscriptions!$A9,Discover!$B:$B,11) -> 0 | S9: =SUMIFS(Discover!$F:$F,Discover!$K:$K,Subscriptions!$A9,Discover!$B:$B,12) -> 0
A10: Crunch Fitness | B10: 6-Months | C10: No | D10: {=AVERAGE(DAY(_xlfn.UNIQUE(_xlfn._xlws.FILTER(Discover!C:C, Discover!K:K = A10,0),1)))} -> 28 | E10: =SUMIFS(Discover!F:F,Discover!K:K,Subscriptions!A10) -> 29.85 | F10: =COUNTIFS(Discover!K:K,Subscriptions!A10,Discover!G:G,"APP") -> 3 | G10: =E10/F10 -> 9.95 | H10: =SUMIFS(Discover!$F:$F,Discover!$K:$K,Subscriptions!$A10,Discover!$B:$B,1) -> 9.95 | I10: =SUMIFS(Discover!$F:$F,Discover!$K:$K,Subscriptions!$A10,Discover!$B:$B,2) -> 9.95 | J10: =SUMIFS(Discover!$F:$F,Discover!$K:$K,Subscriptions!$A10,Discover!$B:$B,3) -> 9.95 | K10: =SUMIFS(Discover!$F:$F,Discover!$K:$K,Subscriptions!$A10,Discover!$B:$B,4) -> 0 | L10: =SUMIFS(Discover!$F:$F,Discover!$K:$K,Subscriptions!$A10,Discover!$B:$B,5) -> 0 | M10: =SUMIFS(Discover!$F:$F,Discover!$K:$K,Subscriptions!$A10,Discover!$B:$B,6) -> 0 | N10: =SUMIFS(Discover!$F:$F,Discover!$K:$K,Subscriptions!$A10,Discover!$B:$B,7) -> 0 | O10: =SUMIFS(Discover!$F:$F,Discover!$K:$K,Subscriptions!$A10,Discover!$B:$B,8) -> 0 | P10: =SUMIFS(Discover!$F:$F,Discover!$K:$K,Subscriptions!$A10,Discover!$B:$B,9) -> 0 | Q10: =SUMIFS(Discover!$F:$F,Discover!$K:$K,Subscriptions!$A10,Discover!$B:$B,10) -> 0 | R10: =SUMIFS(Discover!$F:$F,Discover!$K:$K,Subscriptions!$A10,Discover!$B:$B,11) -> 0 | S10: =SUMIFS(Discover!$F:$F,Discover!$K:$K,Subscriptions!$A10,Discover!$B:$B,12) -> 0
A11: Crunchyroll | B11: 1 Year | C11: Yes | D11: {=AVERAGE(DAY(_xlfn.UNIQUE(_xlfn._xlws.FILTER(Discover!C:C, Discover!K:K = A11,0),1)))} -> 21.090909 | E11: =SUMIFS(Discover!F:F,Discover!K:K,Subscriptions!A11) -> 87.89 | F11: =COUNTIFS(Discover!K:K,Subscriptions!A11,Discover!G:G,"APP") -> 11 | G11: =E11/F11 -> 7.99 | H11: =SUMIFS(Discover!$F:$F,Discover!$K:$K,Subscriptions!$A11,Discover!$B:$B,1) -> 7.99 | I11: =SUMIFS(Discover!$F:$F,Discover!$K:$K,Subscriptions!$A11,Discover!$B:$B,2) -> 7.99 | J11: =SUMIFS(Discover!$F:$F,Discover!$K:$K,Subscriptions!$A11,Discover!$B:$B,3) -> 7.99 | K11: =SUMIFS(Discover!$F:$F,Discover!$K:$K,Subscriptions!$A11,Discover!$B:$B,4) -> 7.99 | L11: =SUMIFS(Discover!$F:$F,Discover!$K:$K,Subscriptions!$A11,Discover!$B:$B,5) -> 7.99 | M11: =SUMIFS(Discover!$F:$F,Discover!$K:$K,Subscriptions!$A11,Discover!$B:$B,6) -> 7.99 | N11: =SUMIFS(Discover!$F:$F,Discover!$K:$K,Subscriptions!$A11,Discover!$B:$B,7) -> 7.99 | O11: =SUMIFS(Discover!$F:$F,Discover!$K:$K,Subscriptions!$A11,Discover!$B:$B,8) -> 7.99 | P11: =SUMIFS(Discover!$F:$F,Discover!$K:$K,Subscriptions!$A11,Discover!$B:$B,9) -> 7.99 | Q11: =SUMIFS(Discover!$F:$F,Discover!$K:$K,Subscriptions!$A11,Discover!$B:$B,10) -> 7.99 | R11: =SUMIFS(Discover!$F:$F,Discover!$K:$K,Subscriptions!$A11,Discover!$B:$B,11) -> 7.99 | S11: =SUMIFS(Discover!$F:$F,Discover!$K:$K,Subscriptions!$A11,Discover!$B:$B,12) -> 0 | T11: *Cancelled
A12: Disney | B12: 1 Month | C12: Yes | D12: {=AVERAGE(DAY(_xlfn.UNIQUE(_xlfn._xlws.FILTER(Discover!C:C, Discover!K:K = A12,0),1)))} -> 1 | E12: =SUMIFS(Discover!F:F,Discover!K:K,Subscriptions!A12) -> 69.99 | F12: =COUNTIFS(Discover!K:K,Subscriptions!A12,Discover!G:G,"APP") -> 1 | G12: =E12/F12 -> 69.99 | H12: =SUMIFS(Discover!$F:$F,Discover!$K:$K,Subscriptions!$A12,Discover!$B:$B,1) -> 0 | I12: =SUMIFS(Discover!$F:$F,Discover!$K:$K,Subscriptions!$A12,Discover!$B:$B,2) -> 0 | J12: =SUMIFS(Discover!$F:$F,Discover!$K:$K,Subscriptions!$A12,Discover!$B:$B,3) -> 69.99 | K12: =SUMIFS(Discover!$F:$F,Discover!$K:$K,Subscriptions!$A12,Discover!$B:$B,4) -> 0 | L12: =SUMIFS(Discover!$F:$F,Discover!$K:$K,Subscriptions!$A12,Discover!$B:$B,5) -> 0 | M12: =SUMIFS(Discover!$F:$F,Discover!$K:$K,Subscriptions!$A12,Discover!$B:$B,6) -> 0 | N12: =SUMIFS(Discover!$F:$F,Discover!$K:$K,Subscriptions!$A12,Discover!$B:$B,7) -> 0 | O12: =SUMIFS(Discover!$F:$F,Discover!$K:$K,Subscriptions!$A12,Discover!$B:$B,8) -> 0 | P12: =SUMIFS(Discover!$F:$F,Discover!$K:$K,Subscriptions!$A12,Discover!$B:$B,9) -> 0 | Q12: =SUMIFS(Discover!$F:$F,Discover!$K:$K,Subscriptions!$A12,Discover!$B:$B,10) -> 0 | R12: =SUMIFS(Discover!$F:$F,Discover!$K:$K,Subscriptions!$A12,Discover!$B:$B,11) -> 0 | S12: =SUMIFS(Discover!$F:$F,Discover!$K:$K,Subscriptions!$A12,Discover!$B:$B,12) -> 0
A13: Family Fitness | B13: Monthly | C13: No | D13: {=AVERAGE(DAY(_xlfn.UNIQUE(_xlfn._xlws.FILTER(Discover!C:C, Discover!K:K = A13,0),1)))} -> 6.2 | E13: =SUMIFS(Discover!F:F,Discover!K:K,Subscriptions!A13) -> 418.8 | F13: =COUNTIFS(Discover!K:K,Subscriptions!A13,Discover!G:G,"APP") -> 5 | G13: =E13/F13 -> 83.76 | H13: =SUMIFS(Discover!$F:$F,Discover!$K:$K,Subscriptions!$A13,Discover!$B:$B,1) -> 0 | I13: =SUMIFS(Discover!$F:$F,Discover!$K:$K,Subscriptions!$A13,Discover!$B:$B,2) -> 0 | J13: =SUMIFS(Discover!$F:$F,Discover!$K:$K,Subscriptions!$A13,Discover!$B:$B,3) -> 0 | K13: =SUMIFS(Discover!$F:$F,Discover!$K:$K,Subscriptions!$A13,Discover!$B:$B,4) -> 84.95 | L13: =SUMIFS(Discover!$F:$F,Discover!$K:$K,Subscriptions!$A13,Discover!$B:$B,5) -> 94.95 | M13: =SUMIFS(Discover!$F:$F,Discover!$K:$K,Subscriptions!$A13,Discover!$B:$B,6) -> 143.95 | N13: =SUMIFS(Discover!$F:$F,Discover!$K:$K,Subscriptions!$A13,Discover!$B:$B,7) -> 0 | O13: =SUMIFS(Discover!$F:$F,Discover!$K:$K,Subscriptions!$A13,Discover!$B:$B,8) -> 94.95 | P13: =SUMIFS(Discover!$F:$F,Discover!$K:$K,Subscriptions!$A13,Discover!$B:$B,9) -> 0 | Q13: =SUMIFS(Discover!$F:$F,Discover!$K:$K,Subscriptions!$A13,Discover!$B:$B,10) -> 0 | R13: =SUMIFS(Discover!$F:$F,Discover!$K:$K,Subscriptions!$A13,Discover!$B:$B,11) -> 0 | S13: =SUMIFS(Discover!$F:$F,Discover!$K:$K,Subscriptions!$A13,Discover!$B:$B,12) -> 0
A14: Final Fantasy | B14: Monthly | C14: No | D14: {=AVERAGE(DAY(_xlfn.UNIQUE(_xlfn._xlws.FILTER(Discover!C:C, Discover!K:K = A14,0),1)))} -> 9.5 | E14: =SUMIFS(Discover!F:F,Discover!K:K,Subscriptions!A14) -> 155.88 | F14: =COUNTIFS(Discover!K:K,Subscriptions!A14,Discover!G:G,"APP") -> 2 | G14: =E14/F14 -> 77.94 | H14: =SUMIFS(Discover!$F:$F,Discover!$K:$K,Subscriptions!$A14,Discover!$B:$B,1) -> 0 | I14: =SUMIFS(Discover!$F:$F,Discover!$K:$K,Subscriptions!$A14,Discover!$B:$B,2) -> 0 | J14: =SUMIFS(Discover!$F:$F,Discover!$K:$K,Subscriptions!$A14,Discover!$B:$B,3) -> 0 | K14: =SUMIFS(Discover!$F:$F,Discover!$K:$K,Subscriptions!$A14,Discover!$B:$B,4) -> 0 | L14: =SUMIFS(Discover!$F:$F,Discover!$K:$K,Subscriptions!$A14,Discover!$B:$B,5) -> 77.94 | M14: =SUMIFS(Discover!$F:$F,Discover!$K:$K,Subscriptions!$A14,Discover!$B:$B,6) -> 77.94 | N14: =SUMIFS(Discover!$F:$F,Discover!$K:$K,Subscriptions!$A14,Discover!$B:$B,7) -> 0 | O14: =SUMIFS(Discover!$F:$F,Discover!$K:$K,Subscriptions!$A14,Discover!$B:$B,8) -> 0 | P14: =SUMIFS(Discover!$F:$F,Discover!$K:$K,Subscriptions!$A14,Discover!$B:$B,9) -> 0 | Q14: =SUMIFS(Discover!$F:$F,Discover!$K:$K,Subscriptions!$A14,Discover!$B:$B,10) -> 0 | R14: =SUMIFS(Discover!$F:$F,Discover!$K:$K,Subscriptions!$A14,Discover!$B:$B,11) -> 0 | S14: =SUMIFS(Discover!$F:$F,Discover!$K:$K,Subscriptions!$A14,Discover!$B:$B,12) -> 0
A15: Finimize | E15: =SUMIFS(Discover!F:F,Discover!K:K,Subscriptions!A15) -> 79.99 | F15: =COUNTIFS(Discover!K:K,Subscriptions!A15,Discover!G:G,"APP") -> 1 | G15: =E15/F15 -> 79.99 | H15: =SUMIFS(Discover!$F:$F,Discover!$K:$K,Subscriptions!$A15,Discover!$B:$B,1) -> 0 | I15: =SUMIFS(Discover!$F:$F,Discover!$K:$K,Subscriptions!$A15,Discover!$B:$B,2) -> 0 | J15: =SUMIFS(Discover!$F:$F,Discover!$K:$K,Subscriptions!$A15,Discover!$B:$B,3) -> 79.99 | K15: =SUMIFS(Discover!$F:$F,Discover!$K:$K,Subscriptions!$A15,Discover!$B:$B,4) -> 0 | L15: =SUMIFS(Discover!$F:$F,Discover!$K:$K,Subscriptions!$A15,Discover!$B:$B,5) -> 0 | M15: =SUMIFS(Discover!$F:$F,Discover!$K:$K,Subscriptions!$A15,Discover!$B:$B,6) -> 0 | N15: =SUMIFS(Discover!$F:$F,Discover!$K:$K,Subscriptions!$A15,Discover!$B:$B,7) -> 0 | O15: =SUMIFS(Discover!$F:$F,Discover!$K:$K,Subscriptions!$A15,Discover!$B:$B,8) -> 0 | P15: =SUMIFS(Discover!$F:$F,Discover!$K:$K,Subscriptions!$A15,Discover!$B:$B,9) -> 0 | Q15: =SUMIFS(Discover!$F:$F,Discover!$K:$K,Subscriptions!$A15,Discover!$B:$B,10) -> 0 | R15: =SUMIFS(Discover!$F:$F,Discover!$K:$K,Subscriptions!$A15,Discover!$B:$B,11) -> 0 | S15: =SUMIFS(Discover!$F:$F,Discover!$K:$K,Subscriptions!$A15,Discover!$B:$B,12) -> 0
A16: Funimation | B16: Monthly | C16: No | D16: {=AVERAGE(DAY(_xlfn.UNIQUE(_xlfn._xlws.FILTER(Discover!C:C, Discover!K:K = A16,0),1)))} -> 18 | E16: =SUMIFS(Discover!F:F,Discover!K:K,Subscriptions!A16) -> 8.47 | F16: =COUNTIFS(Discover!K:K,Subscriptions!A16,Discover!G:G,"APP") -> 1 | G16: =E16/F16 -> 8.47 | H16: =SUMIFS(Discover!$F:$F,Discover!$K:$K,Subscriptions!$A16,Discover!$B:$B,1) -> 0 | I16: =SUMIFS(Discover!$F:$F,Discover!$K:$K,Subscriptions!$A16,Discover!$B:$B,2) -> 0 | J16: =SUMIFS(Discover!$F:$F,Discover!$K:$K,Subscriptions!$A16,Discover!$B:$B,3) -> 0 | K16: =SUMIFS(Discover!$F:$F,Discover!$K:$K,Subscriptions!$A16,Discover!$B:$B,4) -> 0 | L16: =SUMIFS(Discover!$F:$F,Discover!$K:$K,Subscriptions!$A16,Discover!$B:$B,5) -> 0 | M16: =SUMIFS(Discover!$F:$F,Discover!$K:$K,Subscriptions!$A16,Discover!$B:$B,6) -> 0 | N16: =SUMIFS(Discover!$F:$F,Discover!$K:$K,Subscriptions!$A16,Discover!$B:$B,7) -> 0 | O16: =SUMIFS(Discover!$F:$F,Discover!$K:$K,Subscriptions!$A16,Discover!$B:$B,8) -> 8.47 | P16: =SUMIFS(Discover!$F:$F,Discover!$K:$K,Subscriptions!$A16,Discover!$B:$B,9) -> 0 | Q16: =SUMIFS(Discover!$F:$F,Discover!$K:$K,Subscriptions!$A16,Discover!$B:$B,10) -> 0 | R16: =SUMIFS(Discover!$F:$F,Discover!$K:$K,Subscriptions!$A16,Discover!$B:$B,11) -> 0 | S16: =SUMIFS(Discover!$F:$F,Discover!$K:$K,Subscriptions!$A16,Discover!$B:$B,12) -> 0
A17: GuitarTuna | B17: Monthly | C17: No | D17: {=AVERAGE(DAY(_xlfn.UNIQUE(_xlfn._xlws.FILTER(Discover!C:C, Discover!K:K = A17,0),1)))} -> 25 | E17: =SUMIFS(Discover!F:F,Discover!K:K,Subscriptions!A17) -> 5.29 | F17: =COUNTIFS(Discover!K:K,Subscriptions!A17,Discover!G:G,"APP") -> 1 | G17: =E17/F17 -> 5.29 | H17: =SUMIFS(Discover!$F:$F,Discover!$K:$K,Subscriptions!$A17,Discover!$B:$B,1) -> 0 | I17: =SUMIFS(Discover!$F:$F,Discover!$K:$K,Subscriptions!$A17,Discover!$B:$B,2) -> 0 | J17: =SUMIFS(Discover!$F:$F,Discover!$K:$K,Subscriptions!$A17,Discover!$B:$B,3) -> 0 | K17: =SUMIFS(Discover!$F:$F,Discover!$K:$K,Subscriptions!$A17,Discover!$B:$B,4) -> 0 | L17: =SUMIFS(Discover!$F:$F,Discover!$K:$K,Subscriptions!$A17,Discover!$B:$B,5) -> 5.29 | M17: =SUMIFS(Discover!$F:$F,Discover!$K:$K,Subscriptions!$A17,Discover!$B:$B,6) -> 0 | N17: =SUMIFS(Discover!$F:$F,Discover!$K:$K,Subscriptions!$A17,Discover!$B:$B,7) -> 0 | O17: =SUMIFS(Discover!$F:$F,Discover!$K:$K,Subscriptions!$A17,Discover!$B:$B,8) -> 0 | P17: =SUMIFS(Discover!$F:$F,Discover!$K:$K,Subscriptions!$A17,Discover!$B:$B,9) -> 0 | Q17: =SUMIFS(Discover!$F:$F,Discover!$K:$K,Subscriptions!$A17,Discover!$B:$B,10) -> 0 | R17: =SUMIFS(Discover!$F:$F,Discover!$K:$K,Subscriptions!$A17,Discover!$B:$B,11) -> 0 | S17: =SUMIFS(Discover!$F:$F,Discover!$K:$K,Subscriptions!$A17,Discover!$B:$B,12) -> 0
A18: HBO | B18: Monthly | C18: No | D18: {=AVERAGE(DAY(_xlfn.UNIQUE(_xlfn._xlws.FILTER(Discover!C:C, Discover!K:K = A18,0),1)))} -> 12 | E18: =SUMIFS(Discover!F:F,Discover!K:K,Subscriptions!A18) -> 187.89 | F18: =COUNTIFS(Discover!K:K,Subscriptions!A18,Discover!G:G,"APP") -> 12 | G18: =E18/F18 -> 15.6575 | H18: =SUMIFS(Discover!$F:$F,Discover!$K:$K,Subscriptions!$A18,Discover!$B:$B,1) -> 14.99 | I18: =SUMIFS(Discover!$F:$F,Discover!$K:$K,Subscriptions!$A18,Discover!$B:$B,2) -> 14.99 | J18: =SUMIFS(Discover!$F:$F,Discover!$K:$K,Subscriptions!$A18,Discover!$B:$B,3) -> 14.99 | K18: =SUMIFS(Discover!$F:$F,Discover!$K:$K,Subscriptions!$A18,Discover!$B:$B,4) -> 15.89 | L18: =SUMIFS(Discover!$F:$F,Discover!$K:$K,Subscriptions!$A18,Discover!$B:$B,5) -> 15.89 | M18: =SUMIFS(Discover!$F:$F,Discover!$K:$K,Subscriptions!$A18,Discover!$B:$B,6) -> 15.89 | N18: =SUMIFS(Discover!$F:$F,Discover!$K:$K,Subscriptions!$A18,Discover!$B:$B,7) -> 15.89 | O18: =SUMIFS(Discover!$F:$F,Discover!$K:$K,Subscriptions!$A18,Discover!$B:$B,8) -> 16.01 | P18: =SUMIFS(Discover!$F:$F,Discover!$K:$K,Subscriptions!$A18,Discover!$B:$B,9) -> 15.68 | Q18: =SUMIFS(Discover!$F:$F,Discover!$K:$K,Subscriptions!$A18,Discover!$B:$B,10) -> 15.89 | R18: =SUMIFS(Discover!$F:$F,Discover!$K:$K,Subscriptions!$A18,Discover!$B:$B,11) -> 15.89 | S18: =SUMIFS(Discover!$F:$F,Discover!$K:$K,Subscriptions!$A18,Discover!$B:$B,12) -> 15.89
A19: Hulu | B19: Annual | C19: Yes | D19: {=AVERAGE(DAY(_xlfn.UNIQUE(_xlfn._xlws.FILTER(Discover!C:C, Discover!K:K = A19,0),1)))} -> 3 | E19: =SUMIFS(Discover!F:F,Discover!K:K,Subscriptions!A19) -> 68.33 | F19: =COUNTIFS(Discover!K:K,Subscriptions!A19,Discover!G:G,"APP") -> 8 | G19: =E19/F19 -> 8.54125 | H19: =SUMIFS(Discover!$F:$F,Discover!$K:$K,Subscriptions!$A19,Discover!$B:$B,1) -> 0 | I19: =SUMIFS(Discover!$F:$F,Discover!$K:$K,Subscriptions!$A19,Discover!$B:$B,2) -> 0 | J19: =SUMIFS(Discover!$F:$F,Discover!$K:$K,Subscriptions!$A19,Discover!$B:$B,3) -> 0 | K19: =SUMIFS(Discover!$F:$F,Discover!$K:$K,Subscriptions!$A19,Discover!$B:$B,4) -> 0.99 | L19: =SUMIFS(Discover!$F:$F,Discover!$K:$K,Subscriptions!$A19,Discover!$B:$B,5) -> 5.99 | M19: =SUMIFS(Discover!$F:$F,Discover!$K:$K,Subscriptions!$A19,Discover!$B:$B,6) -> 0.4 | N19: =SUMIFS(Discover!$F:$F,Discover!$K:$K,Subscriptions!$A19,Discover!$B:$B,7) -> 11.99 | O19: =SUMIFS(Discover!$F:$F,Discover!$K:$K,Subscriptions!$A19,Discover!$B:$B,8) -> 11.99 | P19: =SUMIFS(Discover!$F:$F,Discover!$K:$K,Subscriptions!$A19,Discover!$B:$B,9) -> 11.99 | Q19: =SUMIFS(Discover!$F:$F,Discover!$K:$K,Subscriptions!$A19,Discover!$B:$B,10) -> 11.99 | R19: =SUMIFS(Discover!$F:$F,Discover!$K:$K,Subscriptions!$A19,Discover!$B:$B,11) -> 12.99 | S19: =SUMIFS(Discover!$F:$F,Discover!$K:$K,Subscriptions!$A19,Discover!$B:$B,12) -> 0
A20: Internet | B20: Monthly | C20: No | D20: {=AVERAGE(DAY(_xlfn.UNIQUE(_xlfn._xlws.FILTER(Discover!C:C, Discover!K:K = A20,0),1)))} -> 16 | E20: =SUMIFS(Discover!F:F,Discover!K:K,Subscriptions!A20) -> 50 | F20: =COUNTIFS(Discover!K:K,Subscriptions!A20,Discover!G:G,"APP") -> 1 | G20: =E20/F20 -> 50 | H20: =SUMIFS(Discover!$F:$F,Discover!$K:$K,Subscriptions!$A20,Discover!$B:$B,1) -> 0 | I20: =SUMIFS(Discover!$F:$F,Discover!$K:$K,Subscriptions!$A20,Discover!$B:$B,2) -> 0 | J20: =SUMIFS(Discover!$F:$F,Discover!$K:$K,Subscriptions!$A20,Discover!$B:$B,3) -> 0 | K20: =SUMIFS(Discover!$F:$F,Discover!$K:$K,Subscriptions!$A20,Discover!$B:$B,4) -> 0 | L20: =SUMIFS(Discover!$F:$F,Discover!$K:$K,Subscriptions!$A20,Discover!$B:$B,5) -> 0 | M20: =SUMIFS(Discover!$F:$F,Discover!$K:$K,Subscriptions!$A20,Discover!$B:$B,6) -> 0 | N20: =SUMIFS(Discover!$F:$F,Discover!$K:$K,Subscriptions!$A20,Discover!$B:$B,7) -> 50 | O20: =SUMIFS(Discover!$F:$F,Discover!$K:$K,Subscriptions!$A20,Discover!$B:$B,8) -> 0 | P20: =SUMIFS(Discover!$F:$F,Discover!$K:$K,Subscriptions!$A20,Discover!$B:$B,9) -> 0 | Q20: =SUMIFS(Discover!$F:$F,Discover!$K:$K,Subscriptions!$A20,Discover!$B:$B,10) -> 0 | R20: =SUMIFS(Discover!$F:$F,Discover!$K:$K,Subscriptions!$A20,Discover!$B:$B,11) -> 0 | S20: =SUMIFS(Discover!$F:$F,Discover!$K:$K,Subscriptions!$A20,Discover!$B:$B,12) -> 0
A21: Jayelin | B21: Monthly | C21: No | D21: {=AVERAGE(DAY(_xlfn.UNIQUE(_xlfn._xlws.FILTER(Discover!C:C, Discover!K:K = A21,0),1)))} -> 15.36 | E21: =SUMIFS(Discover!F:F,Discover!K:K,Subscriptions!A21) -> 256.84 | F21: =COUNTIFS(Discover!K:K,Subscriptions!A21,Discover!G:G,"APP") -> 1 | G21: =E21/F21 -> 256.84 | H21: =SUMIFS(Discover!$F:$F,Discover!$K:$K,Subscriptions!$A21,Discover!$B:$B,1) -> 69.84 | I21: =SUMIFS(Discover!$F:$F,Discover!$K:$K,Subscriptions!$A21,Discover!$B:$B,2) -> 71.26 | J21: =SUMIFS(Discover!$F:$F,Discover!$K:$K,Subscriptions!$A21,Discover!$B:$B,3) -> 9.95 | K21: =SUMIFS(Discover!$F:$F,Discover!$K:$K,Subscriptions!$A21,Discover!$B:$B,4) -> 9.95 | L21: =SUMIFS(Discover!$F:$F,Discover!$K:$K,Subscriptions!$A21,Discover!$B:$B,5) -> 91.85 | M21: =SUMIFS(Discover!$F:$F,Discover!$K:$K,Subscriptions!$A21,Discover!$B:$B,6) -> 0 | N21: =SUMIFS(Discover!$F:$F,Discover!$K:$K,Subscriptions!$A21,Discover!$B:$B,7) -> 0 | O21: =SUMIFS(Discover!$F:$F,Discover!$K:$K,Subscriptions!$A21,Discover!$B:$B,8) -> 3.99 | P21: =SUMIFS(Discover!$F:$F,Discover!$K:$K,Subscriptions!$A21,Discover!$B:$B,9) -> 0 | Q21: =SUMIFS(Discover!$F:$F,Discover!$K:$K,Subscriptions!$A21,Discover!$B:$B,10) -> 0 | R21: =SUMIFS(Discover!$F:$F,Discover!$K:$K,Subscriptions!$A21,Discover!$B:$B,11) -> 0 | S21: =SUMIFS(Discover!$F:$F,Discover!$K:$K,Subscriptions!$A21,Discover!$B:$B,12) -> 0
A22: Lifetime Gym | B22: Monthly | C22: Yes | D22: {=AVERAGE(DAY(_xlfn.UNIQUE(_xlfn._xlws.FILTER(Discover!C:C, Discover!K:K = A22,0),1)))} -> 25 | E22: =SUMIFS(Discover!F:F,Discover!K:K,Subscriptions!A22) -> 16.15 | F22: =COUNTIFS(Discover!K:K,Subscriptions!A22,Discover!G:G,"APP") -> 1 | G22: =E22/F22 -> 16.15 | H22: =SUMIFS(Discover!$F:$F,Discover!$K:$K,Subscriptions!$A22,Discover!$B:$B,1) -> 0 | I22: =SUMIFS(Discover!$F:$F,Discover!$K:$K,Subscriptions!$A22,Discover!$B:$B,2) -> 0 | J22: =SUMIFS(Discover!$F:$F,Discover!$K:$K,Subscriptions!$A22,Discover!$B:$B,3) -> 0 | K22: =SUMIFS(Discover!$F:$F,Discover!$K:$K,Subscriptions!$A22,Discover!$B:$B,4) -> 0 | L22: =SUMIFS(Discover!$F:$F,Discover!$K:$K,Subscriptions!$A22,Discover!$B:$B,5) -> 0 | M22: =SUMIFS(Discover!$F:$F,Discover!$K:$K,Subscriptions!$A22,Discover!$B:$B,6) -> 0 | N22: =SUMIFS(Discover!$F:$F,Discover!$K:$K,Subscriptions!$A22,Discover!$B:$B,7) -> 0 | O22: =SUMIFS(Discover!$F:$F,Discover!$K:$K,Subscriptions!$A22,Discover!$B:$B,8) -> 0 | P22: =SUMIFS(Discover!$F:$F,Discover!$K:$K,Subscriptions!$A22,Discover!$B:$B,9) -> 0 | Q22: =SUMIFS(Discover!$F:$F,Discover!$K:$K,Subscriptions!$A22,Discover!$B:$B,10) -> 16.15 | R22: =SUMIFS(Discover!$F:$F,Discover!$K:$K,Subscriptions!$A22,Discover!$B:$B,11) -> 0 | S22: =SUMIFS(Discover!$F:$F,Discover!$K:$K,Subscriptions!$A22,Discover!$B:$B,12) -> 0
A23: Lucid | B23: Monthly | C23: No | D23: {=AVERAGE(DAY(_xlfn.UNIQUE(_xlfn._xlws.FILTER(Discover!C:C, Discover!K:K = A23,0),1)))} -> 23 | E23: =SUMIFS(Discover!F:F,Discover!K:K,Subscriptions!A23) -> 105.99 | F23: =COUNTIFS(Discover!K:K,Subscriptions!A23,Discover!G:G,"APP") -> 1 | G23: =E23/F23 -> 105.99 | H23: =SUMIFS(Discover!$F:$F,Discover!$K:$K,Subscriptions!$A23,Discover!$B:$B,1) -> 0 | I23: =SUMIFS(Discover!$F:$F,Discover!$K:$K,Subscriptions!$A23,Discover!$B:$B,2) -> 0 | J23: =SUMIFS(Discover!$F:$F,Discover!$K:$K,Subscriptions!$A23,Discover!$B:$B,3) -> 0 | K23: =SUMIFS(Discover!$F:$F,Discover!$K:$K,Subscriptions!$A23,Discover!$B:$B,4) -> 0 | L23: =SUMIFS(Discover!$F:$F,Discover!$K:$K,Subscriptions!$A23,Discover!$B:$B,5) -> 0 | M23: =SUMIFS(Discover!$F:$F,Discover!$K:$K,Subscriptions!$A23,Discover!$B:$B,6) -> 0 | N23: =SUMIFS(Discover!$F:$F,Discover!$K:$K,Subscriptions!$A23,Discover!$B:$B,7) -> 0 | O23: =SUMIFS(Discover!$F:$F,Discover!$K:$K,Subscriptions!$A23,Discover!$B:$B,8) -> 0 | P23: =SUMIFS(Discover!$F:$F,Discover!$K:$K,Subscriptions!$A23,Discover!$B:$B,9) -> 0 | Q23: =SUMIFS(Discover!$F:$F,Discover!$K:$K,Subscriptions!$A23,Discover!$B:$B,10) -> 105.99 | R23: =SUMIFS(Discover!$F:$F,Discover!$K:$K,Subscriptions!$A23,Discover!$B:$B,11) -> 0 | S23: =SUMIFS(Discover!$F:$F,Discover!$K:$K,Subscriptions!$A23,Discover!$B:$B,12) -> 0
A24: Manga | B24: Annual | C24: No | D24: {=AVERAGE(DAY(_xlfn.UNIQUE(_xlfn._xlws.FILTER(Discover!C:C, Discover!K:K = A24,0),1)))} -> 13.25 | E24: =SUMIFS(Discover!F:F,Discover!K:K,Subscriptions!A24) -> 23.88 | F24: =COUNTIFS(Discover!K:K,Subscriptions!A24,Discover!G:G,"APP") -> 12 | G24: =E24/F24 -> 1.99 | H24: =SUMIFS(Discover!$F:$F,Discover!$K:$K,Subscriptions!$A24,Discover!$B:$B,1) -> 1.99 | I24: =SUMIFS(Discover!$F:$F,Discover!$K:$K,Subscriptions!$A24,Discover!$B:$B,2) -> 3.98 | J24: =SUMIFS(Discover!$F:$F,Discover!$K:$K,Subscriptions!$A24,Discover!$B:$B,3) -> 1.99 | K24: =SUMIFS(Discover!$F:$F,Discover!$K:$K,Subscriptions!$A24,Discover!$B:$B,4) -> 1.99 | L24: =SUMIFS(Discover!$F:$F,Discover!$K:$K,Subscriptions!$A24,Discover!$B:$B,5) -> 1.99 | M24: =SUMIFS(Discover!$F:$F,Discover!$K:$K,Subscriptions!$A24,Discover!$B:$B,6) -> 1.99 | N24: =SUMIFS(Discover!$F:$F,Discover!$K:$K,Subscriptions!$A24,Discover!$B:$B,7) -> 1.99 | O24: =SUMIFS(Discover!$F:$F,Discover!$K:$K,Subscriptions!$A24,Discover!$B:$B,8) -> 1.99 | P24: =SUMIFS(Discover!$F:$F,Discover!$K:$K,Subscriptions!$A24,Discover!$B:$B,9) -> 1.99 | Q24: =SUMIFS(Discover!$F:$F,Discover!$K:$K,Subscriptions!$A24,Discover!$B:$B,10) -> 1.99 | R24: =SUMIFS(Discover!$F:$F,Discover!$K:$K,Subscriptions!$A24,Discover!$B:$B,11) -> 1.99 | S24: =SUMIFS(Discover!$F:$F,Discover!$K:$K,Subscriptions!$A24,Discover!$B:$B,12) -> 0
A25: Microsoft 365 | B25: Monthly | C25: Yes | D25: {=AVERAGE(DAY(_xlfn.UNIQUE(_xlfn._xlws.FILTER(Discover!C:C, Discover!K:K = A25,0),1)))} -> 30 | E25: =SUMIFS(Discover!F:F,Discover!K:K,Subscriptions!A25) -> 99.99 | F25: =COUNTIFS(Discover!K:K,Subscriptions!A25,Discover!G:G,"APP") -> 1 | G25: =E25/F25 -> 99.99 | H25: =SUMIFS(Discover!$F:$F,Discover!$K:$K,Subscriptions!$A25,Discover!$B:$B,1) -> 0 | I25: =SUMIFS(Discover!$F:$F,Discover!$K:$K,Subscriptions!$A25,Discover!$B:$B,2) -> 0 | J25: =SUMIFS(Discover!$F:$F,Discover!$K:$K,Subscriptions!$A25,Discover!$B:$B,3) -> 0 | K25: =SUMIFS(Discover!$F:$F,Discover!$K:$K,Subscriptions!$A25,Discover!$B:$B,4) -> 0 | L25: =SUMIFS(Discover!$F:$F,Discover!$K:$K,Subscriptions!$A25,Discover!$B:$B,5) -> 0 | M25: =SUMIFS(Discover!$F:$F,Discover!$K:$K,Subscriptions!$A25,Discover!$B:$B,6) -> 0 | N25: =SUMIFS(Discover!$F:$F,Discover!$K:$K,Subscriptions!$A25,Discover!$B:$B,7) -> 0 | O25: =SUMIFS(Discover!$F:$F,Discover!$K:$K,Subscriptions!$A25,Discover!$B:$B,8) -> 0 | P25: =SUMIFS(Discover!$F:$F,Discover!$K:$K,Subscriptions!$A25,Discover!$B:$B,9) -> 0 | Q25: =SUMIFS(Discover!$F:$F,Discover!$K:$K,Subscriptions!$A25,Discover!$B:$B,10) -> 0 | R25: =SUMIFS(Discover!$F:$F,Discover!$K:$K,Subscriptions!$A25,Discover!$B:$B,11) -> 0 | S25: =SUMIFS(Discover!$F:$F,Discover!$K:$K,Subscriptions!$A25,Discover!$B:$B,12) -> 99.99
A26: Netflix | B26: Monthly | C26: Yes | D26: {=AVERAGE(DAY(_xlfn.UNIQUE(_xlfn._xlws.FILTER(Discover!C:C, Discover!K:K = A26,0),1)))} -> 1 | E26: =SUMIFS(Discover!F:F,Discover!K:K,Subscriptions!A26) -> 175.44 | F26: =COUNTIFS(Discover!K:K,Subscriptions!A26,Discover!G:G,"APP") -> 12 | G26: =E26/F26 -> 14.62 | H26: =SUMIFS(Discover!$F:$F,Discover!$K:$K,Subscriptions!$A26,Discover!$B:$B,1) -> 13.99 | I26: =SUMIFS(Discover!$F:$F,Discover!$K:$K,Subscriptions!$A26,Discover!$B:$B,2) -> 13.99 | J26: =SUMIFS(Discover!$F:$F,Discover!$K:$K,Subscriptions!$A26,Discover!$B:$B,3) -> 13.99 | K26: =SUMIFS(Discover!$F:$F,Discover!$K:$K,Subscriptions!$A26,Discover!$B:$B,4) -> 14.83 | L26: =SUMIFS(Discover!$F:$F,Discover!$K:$K,Subscriptions!$A26,Discover!$B:$B,5) -> 14.83 | M26: =SUMIFS(Discover!$F:$F,Discover!$K:$K,Subscriptions!$A26,Discover!$B:$B,6) -> 14.83 | N26: =SUMIFS(Discover!$F:$F,Discover!$K:$K,Subscriptions!$A26,Discover!$B:$B,7) -> 14.83 | O26: =SUMIFS(Discover!$F:$F,Discover!$K:$K,Subscriptions!$A26,Discover!$B:$B,8) -> 14.83 | P26: =SUMIFS(Discover!$F:$F,Discover!$K:$K,Subscriptions!$A26,Discover!$B:$B,9) -> 14.83 | Q26: =SUMIFS(Discover!$F:$F,Discover!$K:$K,Subscriptions!$A26,Discover!$B:$B,10) -> 14.83 | R26: =SUMIFS(Discover!$F:$F,Discover!$K:$K,Subscriptions!$A26,Discover!$B:$B,11) -> 14.83 | S26: =SUMIFS(Discover!$F:$F,Discover!$K:$K,Subscriptions!$A26,Discover!$B:$B,12) -> 14.83
A27: News | D27: {=AVERAGE(DAY(_xlfn.UNIQUE(_xlfn._xlws.FILTER(Discover!C:C, Discover!K:K = A27,0),1)))} -> 2 | E27: =SUMIFS(Discover!F:F,Discover!K:K,Subscriptions!A27) -> 70 | F27: =COUNTIFS(Discover!K:K,Subscriptions!A27,Discover!G:G,"APP") -> 7 | G27: =E27/F27 -> 10 | H27: =SUMIFS(Discover!$F:$F,Discover!$K:$K,Subscriptions!$A27,Discover!$B:$B,1) -> 0 | I27: =SUMIFS(Discover!$F:$F,Discover!$K:$K,Subscriptions!$A27,Discover!$B:$B,2) -> 0 | J27: =SUMIFS(Discover!$F:$F,Discover!$K:$K,Subscriptions!$A27,Discover!$B:$B,3) -> 0 | K27: =SUMIFS(Discover!$F:$F,Discover!$K:$K,Subscriptions!$A27,Discover!$B:$B,4) -> 0 | L27: =SUMIFS(Discover!$F:$F,Discover!$K:$K,Subscriptions!$A27,Discover!$B:$B,5) -> 0 | M27: =SUMIFS(Discover!$F:$F,Discover!$K:$K,Subscriptions!$A27,Discover!$B:$B,6) -> 10 | N27: =SUMIFS(Discover!$F:$F,Discover!$K:$K,Subscriptions!$A27,Discover!$B:$B,7) -> 10 | O27: =SUMIFS(Discover!$F:$F,Discover!$K:$K,Subscriptions!$A27,Discover!$B:$B,8) -> 10 | P27: =SUMIFS(Discover!$F:$F,Discover!$K:$K,Subscriptions!$A27,Discover!$B:$B,9) -> 10 | Q27: =SUMIFS(Discover!$F:$F,Discover!$K:$K,Subscriptions!$A27,Discover!$B:$B,10) -> 10 | R27: =SUMIFS(Discover!$F:$F,Discover!$K:$K,Subscriptions!$A27,Discover!$B:$B,11) -> 10 | S27: =SUMIFS(Discover!$F:$F,Discover!$K:$K,Subscriptions!$A27,Discover!$B:$B,12) -> 10
A28: oyf | D28: {=AVERAGE(DAY(_xlfn.UNIQUE(_xlfn._xlws.FILTER(Discover!C:C, Discover!K:K = A28,0),1)))} -> 15.428571 | E28: =SUMIFS(Discover!F:F,Discover!K:K,Subscriptions!A28) -> 108.87 | F28: =COUNTIFS(Discover!K:K,Subscriptions!A28,Discover!G:G,"APP") -> 7 | G28: =E28/F28 -> 15.552857 | H28: =SUMIFS(Discover!$F:$F,Discover!$K:$K,Subscriptions!$A28,Discover!$B:$B,1) -> 0 | I28: =SUMIFS(Discover!$F:$F,Discover!$K:$K,Subscriptions!$A28,Discover!$B:$B,2) -> 0 | J28: =SUMIFS(Discover!$F:$F,Discover!$K:$K,Subscriptions!$A28,Discover!$B:$B,3) -> 0 | K28: =SUMIFS(Discover!$F:$F,Discover!$K:$K,Subscriptions!$A28,Discover!$B:$B,4) -> 0 | L28: =SUMIFS(Discover!$F:$F,Discover!$K:$K,Subscriptions!$A28,Discover!$B:$B,5) -> 0 | M28: =SUMIFS(Discover!$F:$F,Discover!$K:$K,Subscriptions!$A28,Discover!$B:$B,6) -> 47.11 | N28: =SUMIFS(Discover!$F:$F,Discover!$K:$K,Subscriptions!$A28,Discover!$B:$B,7) -> 19.99 | O28: =SUMIFS(Discover!$F:$F,Discover!$K:$K,Subscriptions!$A28,Discover!$B:$B,8) -> 4.99 | P28: =SUMIFS(Discover!$F:$F,Discover!$K:$K,Subscriptions!$A28,Discover!$B:$B,9) -> 18.99 | Q28: =SUMIFS(Discover!$F:$F,Discover!$K:$K,Subscriptions!$A28,Discover!$B:$B,10) -> 11 | R28: =SUMIFS(Discover!$F:$F,Discover!$K:$K,Subscriptions!$A28,Discover!$B:$B,11) -> 0 | S28: =SUMIFS(Discover!$F:$F,Discover!$K:$K,Subscriptions!$A28,Discover!$B:$B,12) -> 6.79
A29: Roadtrippers | D29: {=AVERAGE(DAY(_xlfn.UNIQUE(_xlfn._xlws.FILTER(Discover!C:C, Discover!K:K = A29,0),1)))} -> 16 | E29: =SUMIFS(Discover!F:F,Discover!K:K,Subscriptions!A29) -> 31.79 | F29: =COUNTIFS(Discover!K:K,Subscriptions!A29,Discover!G:G,"APP") -> 1 | G29: =E29/F29 -> 31.79 | H29: =SUMIFS(Discover!$F:$F,Discover!$K:$K,Subscriptions!$A29,Discover!$B:$B,1) -> 0 | I29: =SUMIFS(Discover!$F:$F,Discover!$K:$K,Subscriptions!$A29,Discover!$B:$B,2) -> 0 | J29: =SUMIFS(Discover!$F:$F,Discover!$K:$K,Subscriptions!$A29,Discover!$B:$B,3) -> 0 | K29: =SUMIFS(Discover!$F:$F,Discover!$K:$K,Subscriptions!$A29,Discover!$B:$B,4) -> 0 | L29: =SUMIFS(Discover!$F:$F,Discover!$K:$K,Subscriptions!$A29,Discover!$B:$B,5) -> 31.79 | M29: =SUMIFS(Discover!$F:$F,Discover!$K:$K,Subscriptions!$A29,Discover!$B:$B,6) -> 0 | N29: =SUMIFS(Discover!$F:$F,Discover!$K:$K,Subscriptions!$A29,Discover!$B:$B,7) -> 0 | O29: =SUMIFS(Discover!$F:$F,Discover!$K:$K,Subscriptions!$A29,Discover!$B:$B,8) -> 0 | P29: =SUMIFS(Discover!$F:$F,Discover!$K:$K,Subscriptions!$A29,Discover!$B:$B,9) -> 0 | Q29: =SUMIFS(Discover!$F:$F,Discover!$K:$K,Subscriptions!$A29,Discover!$B:$B,10) -> 0 | R29: =SUMIFS(Discover!$F:$F,Discover!$K:$K,Subscriptions!$A29,Discover!$B:$B,11) -> 0 | S29: =SUMIFS(Discover!$F:$F,Discover!$K:$K,Subscriptions!$A29,Discover!$B:$B,12) -> 0
A30: Spotify | D30: {=AVERAGE(DAY(_xlfn.UNIQUE(_xlfn._xlws.FILTER(Discover!C:C, Discover!K:K = A30,0),1)))} -> 1.0833333 | E30: =SUMIFS(Discover!F:F,Discover!K:K,Subscriptions!A30) -> 119.88 | F30: =COUNTIFS(Discover!K:K,Subscriptions!A30,Discover!G:G,"APP") -> 12 | G30: =E30/F30 -> 9.99 | H30: =SUMIFS(Discover!$F:$F,Discover!$K:$K,Subscriptions!$A30,Discover!$B:$B,1) -> 9.99 | I30: =SUMIFS(Discover!$F:$F,Discover!$K:$K,Subscriptions!$A30,Discover!$B:$B,2) -> 9.99 | J30: =SUMIFS(Discover!$F:$F,Discover!$K:$K,Subscriptions!$A30,Discover!$B:$B,3) -> 9.99 | K30: =SUMIFS(Discover!$F:$F,Discover!$K:$K,Subscriptions!$A30,Discover!$B:$B,4) -> 9.99 | L30: =SUMIFS(Discover!$F:$F,Discover!$K:$K,Subscriptions!$A30,Discover!$B:$B,5) -> 9.99 | M30: =SUMIFS(Discover!$F:$F,Discover!$K:$K,Subscriptions!$A30,Discover!$B:$B,6) -> 9.99 | N30: =SUMIFS(Discover!$F:$F,Discover!$K:$K,Subscriptions!$A30,Discover!$B:$B,7) -> 9.99 | O30: =SUMIFS(Discover!$F:$F,Discover!$K:$K,Subscriptions!$A30,Discover!$B:$B,8) -> 9.99 | P30: =SUMIFS(Discover!$F:$F,Discover!$K:$K,Subscriptions!$A30,Discover!$B:$B,9) -> 9.99 | Q30: =SUMIFS(Discover!$F:$F,Discover!$K:$K,Subscriptions!$A30,Discover!$B:$B,10) -> 9.99 | R30: =SUMIFS(Discover!$F:$F,Discover!$K:$K,Subscriptions!$A30,Discover!$B:$B,11) -> 9.99 | S30: =SUMIFS(Discover!$F:$F,Discover!$K:$K,Subscriptions!$A30,Discover!$B:$B,12) -> 9.99
A31: State Farm | D31: {=AVERAGE(DAY(_xlfn.UNIQUE(_xlfn._xlws.FILTER(Discover!C:C, Discover!K:K = A31,0),1)))} -> 3.5 | E31: =SUMIFS(Discover!F:F,Discover!K:K,Subscriptions!A31) -> 1029.52 | F31: =COUNTIFS(Discover!K:K,Subscriptions!A31,Discover!G:G,"APP") -> 12 | G31: =E31/F31 -> 85.793333 | H31: =SUMIFS(Discover!$F:$F,Discover!$K:$K,Subscriptions!$A31,Discover!$B:$B,1) -> 91.78 | I31: =SUMIFS(Discover!$F:$F,Discover!$K:$K,Subscriptions!$A31,Discover!$B:$B,2) -> 91.78 | J31: =SUMIFS(Discover!$F:$F,Discover!$K:$K,Subscriptions!$A31,Discover!$B:$B,3) -> 91.78 | K31: =SUMIFS(Discover!$F:$F,Discover!$K:$K,Subscriptions!$A31,Discover!$B:$B,4) -> 91.78 | L31: =SUMIFS(Discover!$F:$F,Discover!$K:$K,Subscriptions!$A31,Discover!$B:$B,5) -> 91.78 | M31: =SUMIFS(Discover!$F:$F,Discover!$K:$K,Subscriptions!$A31,Discover!$B:$B,6) -> 69.88 | N31: =SUMIFS(Discover!$F:$F,Discover!$K:$K,Subscriptions!$A31,Discover!$B:$B,7) -> 92.07 | O31: =SUMIFS(Discover!$F:$F,Discover!$K:$K,Subscriptions!$A31,Discover!$B:$B,8) -> 92.07 | P31: =SUMIFS(Discover!$F:$F,Discover!$K:$K,Subscriptions!$A31,Discover!$B:$B,9) -> 68.52 | Q31: =SUMIFS(Discover!$F:$F,Discover!$K:$K,Subscriptions!$A31,Discover!$B:$B,10) -> 84.85 | R31: =SUMIFS(Discover!$F:$F,Discover!$K:$K,Subscriptions!$A31,Discover!$B:$B,11) -> 102.79 | S31: =SUMIFS(Discover!$F:$F,Discover!$K:$K,Subscriptions!$A31,Discover!$B:$B,12) -> 60.44
A32: Storage | D32: {=AVERAGE(DAY(_xlfn.UNIQUE(_xlfn._xlws.FILTER(Discover!C:C, Discover!K:K = A32,0),1)))} -> 17.666667 | E32: =SUMIFS(Discover!F:F,Discover!K:K,Subscriptions!A32) -> 361.27 | F32: =COUNTIFS(Discover!K:K,Subscriptions!A32,Discover!G:G,"APP") -> 4 | G32: =E32/F32 -> 90.3175 | H32: =SUMIFS(Discover!$F:$F,Discover!$K:$K,Subscriptions!$A32,Discover!$B:$B,1) -> 0 | I32: =SUMIFS(Discover!$F:$F,Discover!$K:$K,Subscriptions!$A32,Discover!$B:$B,2) -> 0 | J32: =SUMIFS(Discover!$F:$F,Discover!$K:$K,Subscriptions!$A32,Discover!$B:$B,3) -> 0 | K32: =SUMIFS(Discover!$F:$F,Discover!$K:$K,Subscriptions!$A32,Discover!$B:$B,4) -> 66.4 | L32: =SUMIFS(Discover!$F:$F,Discover!$K:$K,Subscriptions!$A32,Discover!$B:$B,5) -> 216.87 | M32: =SUMIFS(Discover!$F:$F,Discover!$K:$K,Subscriptions!$A32,Discover!$B:$B,6) -> 78 | N32: =SUMIFS(Discover!$F:$F,Discover!$K:$K,Subscriptions!$A32,Discover!$B:$B,7) -> 0 | O32: =SUMIFS(Discover!$F:$F,Discover!$K:$K,Subscriptions!$A32,Discover!$B:$B,8) -> 0 | P32: =SUMIFS(Discover!$F:$F,Discover!$K:$K,Subscriptions!$A32,Discover!$B:$B,9) -> 0 | Q32: =SUMIFS(Discover!$F:$F,Discover!$K:$K,Subscriptions!$A32,Discover!$B:$B,10) -> 0 | R32: =SUMIFS(Discover!$F:$F,Discover!$K:$K,Subscriptions!$A32,Discover!$B:$B,11) -> 0 | S32: =SUMIFS(Discover!$F:$F,Discover!$K:$K,Subscriptions!$A32,Discover!$B:$B,12) -> 0
A33: Stretch Zone | D33: {=AVERAGE(DAY(_xlfn.UNIQUE(_xlfn._xlws.FILTER(Discover!C:C, Discover!K:K = A33,0),1)))} -> 25 | E33: =SUMIFS(Discover!F:F,Discover!K:K,Subscriptions!A33) -> 1039 | F33: =COUNTIFS(Discover!K:K,Subscriptions!A33,Discover!G:G,"APP") -> 4 | G33: =E33/F33 -> 259.75 | H33: =SUMIFS(Discover!$F:$F,Discover!$K:$K,Subscriptions!$A33,Discover!$B:$B,1) -> 0 | I33: =SUMIFS(Discover!$F:$F,Discover!$K:$K,Subscriptions!$A33,Discover!$B:$B,2) -> 0 | J33: =SUMIFS(Discover!$F:$F,Discover!$K:$K,Subscriptions!$A33,Discover!$B:$B,3) -> 0 | K33: =SUMIFS(Discover!$F:$F,Discover!$K:$K,Subscriptions!$A33,Discover!$B:$B,4) -> 0 | L33: =SUMIFS(Discover!$F:$F,Discover!$K:$K,Subscriptions!$A33,Discover!$B:$B,5) -> 0 | M33: =SUMIFS(Discover!$F:$F,Discover!$K:$K,Subscriptions!$A33,Discover!$B:$B,6) -> 0 | N33: =SUMIFS(Discover!$F:$F,Discover!$K:$K,Subscriptions!$A33,Discover!$B:$B,7) -> 0 | O33: =SUMIFS(Discover!$F:$F,Discover!$K:$K,Subscriptions!$A33,Discover!$B:$B,8) -> 0 | P33: =SUMIFS(Discover!$F:$F,Discover!$K:$K,Subscriptions!$A33,Discover!$B:$B,9) -> 320 | Q33: =SUMIFS(Discover!$F:$F,Discover!$K:$K,Subscriptions!$A33,Discover!$B:$B,10) -> 320 | R33: =SUMIFS(Discover!$F:$F,Discover!$K:$K,Subscriptions!$A33,Discover!$B:$B,11) -> 320 | S33: =SUMIFS(Discover!$F:$F,Discover!$K:$K,Subscriptions!$A33,Discover!$B:$B,12) -> 79
A34: The Athletic | D34: {=AVERAGE(DAY(_xlfn.UNIQUE(_xlfn._xlws.FILTER(Discover!C:C, Discover!K:K = A34,0),1)))} -> 3 | E34: =SUMIFS(Discover!F:F,Discover!K:K,Subscriptions!A34) -> 63.59 | F34: =COUNTIFS(Discover!K:K,Subscriptions!A34,Discover!G:G,"APP") -> 1 | G34: =E34/F34 -> 63.59 | H34: =SUMIFS(Discover!$F:$F,Discover!$K:$K,Subscriptions!$A34,Discover!$B:$B,1) -> 0 | I34: =SUMIFS(Discover!$F:$F,Discover!$K:$K,Subscriptions!$A34,Discover!$B:$B,2) -> 0 | J34: =SUMIFS(Discover!$F:$F,Discover!$K:$K,Subscriptions!$A34,Discover!$B:$B,3) -> 0 | K34: =SUMIFS(Discover!$F:$F,Discover!$K:$K,Subscriptions!$A34,Discover!$B:$B,4) -> 0 | L34: =SUMIFS(Discover!$F:$F,Discover!$K:$K,Subscriptions!$A34,Discover!$B:$B,5) -> 0 | M34: =SUMIFS(Discover!$F:$F,Discover!$K:$K,Subscriptions!$A34,Discover!$B:$B,6) -> 0 | N34: =SUMIFS(Discover!$F:$F,Discover!$K:$K,Subscriptions!$A34,Discover!$B:$B,7) -> 0 | O34: =SUMIFS(Discover!$F:$F,Discover!$K:$K,Subscriptions!$A34,Discover!$B:$B,8) -> 63.59 | P34: =SUMIFS(Discover!$F:$F,Discover!$K:$K,Subscriptions!$A34,Discover!$B:$B,9) -> 0 | Q34: =SUMIFS(Discover!$F:$F,Discover!$K:$K,Subscriptions!$A34,Discover!$B:$B,10) -> 0 | R34: =SUMIFS(Discover!$F:$F,Discover!$K:$K,Subscriptions!$A34,Discover!$B:$B,11) -> 0 | S34: =SUMIFS(Discover!$F:$F,Discover!$K:$K,Subscriptions!$A34,Discover!$B:$B,12) -> 0
A35: Tinder | D35: {=AVERAGE(DAY(_xlfn.UNIQUE(_xlfn._xlws.FILTER(Discover!C:C, Discover!K:K = A35,0),1)))} -> 7 | E35: =SUMIFS(Discover!F:F,Discover!K:K,Subscriptions!A35) -> 47.68 | F35: =COUNTIFS(Discover!K:K,Subscriptions!A35,Discover!G:G,"APP") -> 2 | G35: =E35/F35 -> 23.84 | H35: =SUMIFS(Discover!$F:$F,Discover!$K:$K,Subscriptions!$A35,Discover!$B:$B,1) -> 0 | I35: =SUMIFS(Discover!$F:$F,Discover!$K:$K,Subscriptions!$A35,Discover!$B:$B,2) -> 0 | J35: =SUMIFS(Discover!$F:$F,Discover!$K:$K,Subscriptions!$A35,Discover!$B:$B,3) -> 0 | K35: =SUMIFS(Discover!$F:$F,Discover!$K:$K,Subscriptions!$A35,Discover!$B:$B,4) -> 0 | L35: =SUMIFS(Discover!$F:$F,Discover!$K:$K,Subscriptions!$A35,Discover!$B:$B,5) -> 0 | M35: =SUMIFS(Discover!$F:$F,Discover!$K:$K,Subscriptions!$A35,Discover!$B:$B,6) -> 0 | N35: =SUMIFS(Discover!$F:$F,Discover!$K:$K,Subscriptions!$A35,Discover!$B:$B,7) -> 0 | O35: =SUMIFS(Discover!$F:$F,Discover!$K:$K,Subscriptions!$A35,Discover!$B:$B,8) -> 31.79 | P35: =SUMIFS(Discover!$F:$F,Discover!$K:$K,Subscriptions!$A35,Discover!$B:$B,9) -> 15.89 | Q35: =SUMIFS(Discover!$F:$F,Discover!$K:$K,Subscriptions!$A35,Discover!$B:$B,10) -> 0 | R35: =SUMIFS(Discover!$F:$F,Discover!$K:$K,Subscriptions!$A35,Discover!$B:$B,11) -> 0 | S35: =SUMIFS(Discover!$F:$F,Discover!$K:$K,Subscriptions!$A35,Discover!$B:$B,12) -> 0
A36: T-Mobile | D36: {=AVERAGE(DAY(_xlfn.UNIQUE(_xlfn._xlws.FILTER(Discover!C:C, Discover!K:K = A36,0),1)))} -> 15.444444 | E36: =SUMIFS(Discover!F:F,Discover!K:K,Subscriptions!A36) -> 737.5 | F36: =COUNTIFS(Discover!K:K,Subscriptions!A36,Discover!G:G,"APP") -> 9 | G36: =E36/F36 -> 81.944444 | H36: =SUMIFS(Discover!$F:$F,Discover!$K:$K,Subscriptions!$A36,Discover!$B:$B,1) -> 0 | I36: =SUMIFS(Discover!$F:$F,Discover!$K:$K,Subscriptions!$A36,Discover!$B:$B,2) -> 86.25 | J36: =SUMIFS(Discover!$F:$F,Discover!$K:$K,Subscriptions!$A36,Discover!$B:$B,3) -> 86.25 | K36: =SUMIFS(Discover!$F:$F,Discover!$K:$K,Subscriptions!$A36,Discover!$B:$B,4) -> 0 | L36: =SUMIFS(Discover!$F:$F,Discover!$K:$K,Subscriptions!$A36,Discover!$B:$B,5) -> 86.25 | M36: =SUMIFS(Discover!$F:$F,Discover!$K:$K,Subscriptions!$A36,Discover!$B:$B,6) -> 86.25 | N36: =SUMIFS(Discover!$F:$F,Discover!$K:$K,Subscriptions!$A36,Discover!$B:$B,7) -> 86.25 | O36: =SUMIFS(Discover!$F:$F,Discover!$K:$K,Subscriptions!$A36,Discover!$B:$B,8) -> 0 | P36: =SUMIFS(Discover!$F:$F,Discover!$K:$K,Subscriptions!$A36,Discover!$B:$B,9) -> 86.25 | Q36: =SUMIFS(Discover!$F:$F,Discover!$K:$K,Subscriptions!$A36,Discover!$B:$B,10) -> 80 | R36: =SUMIFS(Discover!$F:$F,Discover!$K:$K,Subscriptions!$A36,Discover!$B:$B,11) -> 70 | S36: =SUMIFS(Discover!$F:$F,Discover!$K:$K,Subscriptions!$A36,Discover!$B:$B,12) -> 70
A37: USTA | E37: =SUMIFS(Discover!F:F,Discover!K:K,Subscriptions!A37) -> 44 | F37: =COUNTIFS(Discover!K:K,Subscriptions!A37,Discover!G:G,"APP") -> 1 | G37: =E37/F37 -> 44 | H37: =SUMIFS(Discover!$F:$F,Discover!$K:$K,Subscriptions!$A37,Discover!$B:$B,1) -> 0 | I37: =SUMIFS(Discover!$F:$F,Discover!$K:$K,Subscriptions!$A37,Discover!$B:$B,2) -> 0 | J37: =SUMIFS(Discover!$F:$F,Discover!$K:$K,Subscriptions!$A37,Discover!$B:$B,3) -> 0 | K37: =SUMIFS(Discover!$F:$F,Discover!$K:$K,Subscriptions!$A37,Discover!$B:$B,4) -> 0 | L37: =SUMIFS(Discover!$F:$F,Discover!$K:$K,Subscriptions!$A37,Discover!$B:$B,5) -> 44 | M37: =SUMIFS(Discover!$F:$F,Discover!$K:$K,Subscriptions!$A37,Discover!$B:$B,6) -> 0 | N37: =SUMIFS(Discover!$F:$F,Discover!$K:$K,Subscriptions!$A37,Discover!$B:$B,7) -> 0 | O37: =SUMIFS(Discover!$F:$F,Discover!$K:$K,Subscriptions!$A37,Discover!$B:$B,8) -> 0 | P37: =SUMIFS(Discover!$F:$F,Discover!$K:$K,Subscriptions!$A37,Discover!$B:$B,9) -> 0 | Q37: =SUMIFS(Discover!$F:$F,Discover!$K:$K,Subscriptions!$A37,Discover!$B:$B,10) -> 0 | R37: =SUMIFS(Discover!$F:$F,Discover!$K:$K,Subscriptions!$A37,Discover!$B:$B,11) -> 0 | S37: =SUMIFS(Discover!$F:$F,Discover!$K:$K,Subscriptions!$A37,Discover!$B:$B,12) -> 0
A38: Verizon Internet | E38: =SUMIFS(Discover!F:F,Discover!K:K,Subscriptions!A38) -> 100 | F38: =COUNTIFS(Discover!K:K,Subscriptions!A38,Discover!G:G,"APP") -> 2 | G38: =E38/F38 -> 50 | H38: =SUMIFS(Discover!$F:$F,Discover!$K:$K,Subscriptions!$A38,Discover!$B:$B,1) -> 0 | I38: =SUMIFS(Discover!$F:$F,Discover!$K:$K,Subscriptions!$A38,Discover!$B:$B,2) -> 0 | J38: =SUMIFS(Discover!$F:$F,Discover!$K:$K,Subscriptions!$A38,Discover!$B:$B,3) -> 0 | K38: =SUMIFS(Discover!$F:$F,Discover!$K:$K,Subscriptions!$A38,Discover!$B:$B,4) -> 0 | L38: =SUMIFS(Discover!$F:$F,Discover!$K:$K,Subscriptions!$A38,Discover!$B:$B,5) -> 0 | M38: =SUMIFS(Discover!$F:$F,Discover!$K:$K,Subscriptions!$A38,Discover!$B:$B,6) -> 50 | N38: =SUMIFS(Discover!$F:$F,Discover!$K:$K,Subscriptions!$A38,Discover!$B:$B,7) -> 0 | O38: =SUMIFS(Discover!$F:$F,Discover!$K:$K,Subscriptions!$A38,Discover!$B:$B,8) -> 50 | P38: =SUMIFS(Discover!$F:$F,Discover!$K:$K,Subscriptions!$A38,Discover!$B:$B,9) -> 0 | Q38: =SUMIFS(Discover!$F:$F,Discover!$K:$K,Subscriptions!$A38,Discover!$B:$B,10) -> 0 | R38: =SUMIFS(Discover!$F:$F,Discover!$K:$K,Subscriptions!$A38,Discover!$B:$B,11) -> 0 | S38: =SUMIFS(Discover!$F:$F,Discover!$K:$K,Subscriptions!$A38,Discover!$B:$B,12) -> 0
A39: Webull | E39: =SUMIFS(Discover!F:F,Discover!K:K,Subscriptions!A39) -> 7.96 | F39: =COUNTIFS(Discover!K:K,Subscriptions!A39,Discover!G:G,"APP") -> 4 | G39: =E39/F39 -> 1.99 | H39: =SUMIFS(Discover!$F:$F,Discover!$K:$K,Subscriptions!$A39,Discover!$B:$B,1) -> 0 | I39: =SUMIFS(Discover!$F:$F,Discover!$K:$K,Subscriptions!$A39,Discover!$B:$B,2) -> 1.99 | J39: =SUMIFS(Discover!$F:$F,Discover!$K:$K,Subscriptions!$A39,Discover!$B:$B,3) -> 0 | K39: =SUMIFS(Discover!$F:$F,Discover!$K:$K,Subscriptions!$A39,Discover!$B:$B,4) -> 1.99 | L39: =SUMIFS(Discover!$F:$F,Discover!$K:$K,Subscriptions!$A39,Discover!$B:$B,5) -> 1.99 | M39: =SUMIFS(Discover!$F:$F,Discover!$K:$K,Subscriptions!$A39,Discover!$B:$B,6) -> 1.99 | N39: =SUMIFS(Discover!$F:$F,Discover!$K:$K,Subscriptions!$A39,Discover!$B:$B,7) -> 0 | O39: =SUMIFS(Discover!$F:$F,Discover!$K:$K,Subscriptions!$A39,Discover!$B:$B,8) -> 0 | P39: =SUMIFS(Discover!$F:$F,Discover!$K:$K,Subscriptions!$A39,Discover!$B:$B,9) -> 0 | Q39: =SUMIFS(Discover!$F:$F,Discover!$K:$K,Subscriptions!$A39,Discover!$B:$B,10) -> 0 | R39: =SUMIFS(Discover!$F:$F,Discover!$K:$K,Subscriptions!$A39,Discover!$B:$B,11) -> 0 | S39: =SUMIFS(Discover!$F:$F,Discover!$K:$K,Subscriptions!$A39,Discover!$B:$B,12) -> 0
A40: Wolfram | E40: =SUMIFS(Discover!F:F,Discover!K:K,Subscriptions!A40) -> 13.98 | F40: =COUNTIFS(Discover!K:K,Subscriptions!A40,Discover!G:G,"APP") -> 2 | G40: =E40/F40 -> 6.99 | H40: =SUMIFS(Discover!$F:$F,Discover!$K:$K,Subscriptions!$A40,Discover!$B:$B,1) -> 0 | I40: =SUMIFS(Discover!$F:$F,Discover!$K:$K,Subscriptions!$A40,Discover!$B:$B,2) -> 0 | J40: =SUMIFS(Discover!$F:$F,Discover!$K:$K,Subscriptions!$A40,Discover!$B:$B,3) -> 6.99 | K40: =SUMIFS(Discover!$F:$F,Discover!$K:$K,Subscriptions!$A40,Discover!$B:$B,4) -> 6.99 | L40: =SUMIFS(Discover!$F:$F,Discover!$K:$K,Subscriptions!$A40,Discover!$B:$B,5) -> 0 | M40: =SUMIFS(Discover!$F:$F,Discover!$K:$K,Subscriptions!$A40,Discover!$B:$B,6) -> 0 | N40: =SUMIFS(Discover!$F:$F,Discover!$K:$K,Subscriptions!$A40,Discover!$B:$B,7) -> 0 | O40: =SUMIFS(Discover!$F:$F,Discover!$K:$K,Subscriptions!$A40,Discover!$B:$B,8) -> 0 | P40: =SUMIFS(Discover!$F:$F,Discover!$K:$K,Subscriptions!$A40,Discover!$B:$B,9) -> 0 | Q40: =SUMIFS(Discover!$F:$F,Discover!$K:$K,Subscriptions!$A40,Discover!$B:$B,10) -> 0 | R40: =SUMIFS(Discover!$F:$F,Discover!$K:$K,Subscriptions!$A40,Discover!$B:$B,11) -> 0 | S40: =SUMIFS(Discover!$F:$F,Discover!$K:$K,Subscriptions!$A40,Discover!$B:$B,12) -> 0
A41: Youtube TV
E42: =SUM(E2:E41) -> 6022.18 | G42: =SUMPRODUCT(G2:G40,E2:E40)/SUM(E2:E40) -> 105.17135 | H42: =SUM(H2:H40) -> 260.47 | I42: =SUM(I2:I40) -> 322.16 | J42: =SUM(J2:J40) -> 428.83 | K42: =SUM(K2:K40) -> 323.73 | L42: =SUM(L2:L40) -> 846.47 | M42: =SUM(M2:M40) -> 626.2 | N42: =SUM(N2:N40) -> 330.98 | O42: =SUM(O2:O40) -> 584.34 | ... S42: =SUM(S2:S40) -> 372.22
E45: =E36+E33+E31+E13+E38+E32+E10 -> 3715.94
E47: =E42-E45 -> 2306.24
E49: =E30+E29+E24+E25+E26+E19+E20+E12+E11+E3+E2+E8+E17+E15+E14+E23+E28+E34 -> 1369.06
E50: =E49+E41 -> 1369.06

Sheet Cash Flow
C1: 1 | D1: 1 | E1: 1 | F1: 1 | G1: 1 | H1: 2 | I1: 2 | J1: 2 | K1: 2 | L1: 3 | M1: 3 | N1: 3 | O1: 3 | P1: 3 | Q1: 4 | R1: 4 | S1: 4 | T1: 4 | U1: 4 | V1: 5 | W1: 5 | X1: 5 | Y1: 5 | Z1: 5 | AA1: 6 | AB1: 6 | AC1: 6 | AD1: 6 | AE1: 6 | AF1: 7 | AG1: 7 | AH1: 7 | AI1: 7 | AJ1: 7 | AK1: 8 | AL1: 8 | AM1: 8 | AN1: 8 | AO1: 8 | AP1: 9 | AQ1: 9 | AR1: 9 | AS1: 9 | AT1: 9 | AU1: 10 | AV1: 10 | AW1: 10 | AX1: 10 | AY1: 10 | AZ1: 11 | BA1: 11 | BB1: 11 | BC1: 11 | BD1: 11 | BE1: 12 | BF1: 12 | BG1: 12 | BH1: 12 | BI1: 12
A2: Begin Balance | B2: 167.58 | C2: Jan | H2: Feb | L2: Mar | Q2: Apr | V2: May | AA2: Jun | AF2: Jul | AK2: Aug | AP2: Sep | AU2: Oct | AZ2: Nov | BE2: Dec
C3: 1 | D3: 8 | E3: 15 | F3: 22 | G3: 31 | H3: 5 | I3: 12 | J3: 19 | K3: 28 | L3: 5 | M3: 12 | N3: 19 | O3: 26 | P3: 31 | Q3: 2 | R3: 9 | S3: 16 | T3: 23 | U3: 30 | V3: 7 | W3: 14 | X3: 21 | Y3: 28 | Z3: 31 | AA3: 4 | AB3: 11 | AC3: 18 | AD3: 25 | AE3: 30 | AF3: 2 | AG3: 9 | AH3: 16 | AI3: 23 | AJ3: 30 | AK3: 6 | AL3: 13 | AM3: 20 | AN3: 27 | AO3: 31 | AP3: 3 | AQ3: 10 | AR3: 17 | AS3: 24 | AT3: 30 | AU3: 1 | AV3: 8 | AW3: 15 | AX3: 22 | AY3: 29 | AZ3: 5 | BA3: 12 | BB3: 19 | BC3: 26 | BD3: 30 | BE3: 3 | BF3: 10 | BG3: 17 | BH3: 24 | BI3: 31
A4: {=_xlfn._xlws.SORT(_xlfn.UNIQUE(_xlfn._xlws.FILTER('Wells Fargo'!G:G,('Wells Fargo'!G:G<>0)*('Wells Fargo'!G:G<>"Primary"))))} -> 3060 Ti GPU | B4: =SUM(C4:BI4) -> 0 | C4: =SUMIFS('Wells Fargo'!$F:$F,'Wells Fargo'!$G:$G,'Cash Flow'!$A4,'Wells Fargo'!$A:$A,C$1,'Wells Fargo'!$B:$B,"<="&'Cash Flow'!C$3) -> 0 | D4: =SUMIFS('Wells Fargo'!$F:$F,'Wells Fargo'!$G:$G,'Cash Flow'!$A4,'Wells Fargo'!$A:$A,D$1,'Wells Fargo'!$B:$B,"<="&'Cash Flow'!D$3,'Wells Fargo'!$B:$B,">"&'Cash Flow'!C$3) -> 0 | E4: =SUMIFS('Wells Fargo'!$F:$F,'Wells Fargo'!$G:$G,'Cash Flow'!$A4,'Wells Fargo'!$A:$A,E$1,'Wells Fargo'!$B:$B,"<="&'Cash Flow'!E$3,'Wells Fargo'!$B:$B,">"&'Cash Flow'!D$3) -> 0 | F4: =SUMIFS('Wells Fargo'!$F:$F,'Wells Fargo'!$G:$G,'Cash Flow'!$A4,'Wells Fargo'!$A:$A,F$1,'Wells Fargo'!$B:$B,"<="&'Cash Flow'!F$3,'Wells Fargo'!$B:$B,">"&'Cash Flow'!E$3) -> 0 | G4: =SUMIFS('Wells Fargo'!$F:$F,'Wells Fargo'!$G:$G,'Cash Flow'!$A4,'Wells Fargo'!$A:$A,G$1,'Wells Fargo'!$B:$B,"<="&'Cash Flow'!G$3,'Wells Fargo'!$B:$B,">"&'Cash Flow'!F$3) -> 0 | H4: =SUMIFS('Wells Fargo'!$F:$F,'Wells Fargo'!$G:$G,'Cash Flow'!$A4,'Wells Fargo'!$A:$A,H$1,'Wells Fargo'!$B:$B,"<="&'Cash Flow'!H$3) -> 0 | I4: =SUMIFS('Wells Fargo'!$F:$F,'Wells Fargo'!$G:$G,'Cash Flow'!$A4,'Wells Fargo'!$A:$A,I$1,'Wells Fargo'!$B:$B,"<="&'Cash Flow'!I$3,'Wells Fargo'!$B:$B,">"&'Cash Flow'!H$3) -> 0 | J4: =SUMIFS('Wells Fargo'!$F:$F,'Wells Fargo'!$G:$G,'Cash Flow'!$A4,'Wells Fargo'!$A:$A,J$1,'Wells Fargo'!$B:$B,"<="&'Cash Flow'!J$3,'Wells Fargo'!$B:$B,">"&'Cash Flow'!I$3) -> 0 | K4: =SUMIFS('Wells Fargo'!$F:$F,'Wells Fargo'!$G:$G,'Cash Flow'!$A4,'Wells Fargo'!$A:$A,K$1,'Wells Fargo'!$B:$B,"<="&'Cash Flow'!K$3,'Wells Fargo'!$B:$B,">"&'Cash Flow'!J$3) -> 0 | L4: =SUMIFS('Wells Fargo'!$F:$F,'Wells Fargo'!$G:$G,'Cash Flow'!$A4,'Wells Fargo'!$A:$A,L$1,'Wells Fargo'!$B:$B,"<="&'Cash Flow'!L$3) -> 0 | M4: =SUMIFS('Wells Fargo'!$F:$F,'Wells Fargo'!$G:$G,'Cash Flow'!$A4,'Wells Fargo'!$A:$A,M$1,'Wells Fargo'!$B:$B,"<="&'Cash Flow'!M$3,'Wells Fargo'!$B:$B,">"&'Cash Flow'!L$3) -> 0 | N4: =SUMIFS('Wells Fargo'!$F:$F,'Wells Fargo'!$G:$G,'Cash Flow'!$A4,'Wells Fargo'!$A:$A,N$1,'Wells Fargo'!$B:$B,"<="&'Cash Flow'!N$3,'Wells Fargo'!$B:$B,">"&'Cash Flow'!M$3) -> 0 | O4: =SUMIFS('Wells Fargo'!$F:$F,'Wells Fargo'!$G:$G,'Cash Flow'!$A4,'Wells Fargo'!$A:$A,O$1,'Wells Fargo'!$B:$B,"<="&'Cash Flow'!O$3,'Wells Fargo'!$B:$B,">"&'Cash Flow'!N$3) -> 0 | P4: =SUMIFS('Wells Fargo'!$F:$F,'Wells Fargo'!$G:$G,'Cash Flow'!$A4,'Wells Fargo'!$A:$A,P$1,'Wells Fargo'!$B:$B,"<="&'Cash Flow'!P$3,'Wells Fargo'!$B:$B,">"&'Cash Flow'!O$3) -> 0 | Q4: =SUMIFS('Wells Fargo'!$F:$F,'Wells Fargo'!$G:$G,'Cash Flow'!$A4,'Wells Fargo'!$A:$A,Q$1,'Wells Fargo'!$B:$B,"<="&'Cash Flow'!Q$3) -> 0 | R4: =SUMIFS('Wells Fargo'!$F:$F,'Wells Fargo'!$G:$G,'Cash Flow'!$A4,'Wells Fargo'!$A:$A,R$1,'Wells Fargo'!$B:$B,"<="&'Cash Flow'!R$3,'Wells Fargo'!$B:$B,">"&'Cash Flow'!Q$3) -> 0 | S4: =SUMIFS('Wells Fargo'!$F:$F,'Wells Fargo'!$G:$G,'Cash Flow'!$A4,'Wells Fargo'!$A:$A,S$1,'Wells Fargo'!$B:$B,"<="&'Cash Flow'!S$3,'Wells Fargo'!$B:$B,">"&'Cash Flow'!R$3) -> 0 | T4: =SUMIFS('Wells Fargo'!$F:$F,'Wells Fargo'!$G:$G,'Cash Flow'!$A4,'Wells Fargo'!$A:$A,T$1,'Wells Fargo'!$B:$B,"<="&'Cash Flow'!T$3,'Wells Fargo'!$B:$B,">"&'Cash Flow'!S$3) -> 0 | U4: =SUMIFS('Wells Fargo'!$F:$F,'Wells Fargo'!$G:$G,'Cash Flow'!$A4,'Wells Fargo'!$A:$A,U$1,'Wells Fargo'!$B:$B,"<="&'Cash Flow'!U$3,'Wells Fargo'!$B:$B,">"&'Cash Flow'!T$3) -> 0 | V4: =SUMIFS('Wells Fargo'!$F:$F,'Wells Fargo'!$G:$G,'Cash Flow'!$A4,'Wells Fargo'!$A:$A,V$1,'Wells Fargo'!$B:$B,"<="&'Cash Flow'!V$3) -> 0 | W4: =SUMIFS('Wells Fargo'!$F:$F,'Wells Fargo'!$G:$G,'Cash Flow'!$A4,'Wells Fargo'!$A:$A,W$1,'Wells Fargo'!$B:$B,"<="&'Cash Flow'!W$3,'Wells Fargo'!$B:$B,">"&'Cash Flow'!V$3) -> 0 | X4: =SUMIFS('Wells Fargo'!$F:$F,'Wells Fargo'!$G:$G,'Cash Flow'!$A4,'Wells Fargo'!$A:$A,X$1,'Wells Fargo'!$B:$B,"<="&'Cash Flow'!X$3,'Wells Fargo'!$B:$B,">"&'Cash Flow'!W$3) -> 0 | Y4: =SUMIFS('Wells Fargo'!$F:$F,'Wells Fargo'!$G:$G,'Cash Flow'!$A4,'Wells Fargo'!$A:$A,Y$1,'Wells Fargo'!$B:$B,"<="&'Cash Flow'!Y$3,'Wells Fargo'!$B:$B,">"&'Cash Flow'!X$3) -> 0 | Z4: =SUMIFS('Wells Fargo'!$F:$F,'Wells Fargo'!$G:$G,'Cash Flow'!$A4,'Wells Fargo'!$A:$A,Z$1,'Wells Fargo'!$B:$B,"<="&'Cash Flow'!Z$3,'Wells Fargo'!$B:$B,">"&'Cash Flow'!Y$3) -> 0 | AA4: =SUMIFS('Wells Fargo'!$F:$F,'Wells Fargo'!$G:$G,'Cash Flow'!$A4,'Wells Fargo'!$A:$A,AA$1,'Wells Fargo'!$B:$B,"<="&'Cash Flow'!AA$3) -> 0 | AB4: =SUMIFS('Wells Fargo'!$F:$F,'Wells Fargo'!$G:$G,'Cash Flow'!$A4,'Wells Fargo'!$A:$A,AB$1,'Wells Fargo'!$B:$B,"<="&'Cash Flow'!AB$3,'Wells Fargo'!$B:$B,">"&'Cash Flow'!AA$3) -> 0 | AC4: =SUMIFS('Wells Fargo'!$F:$F,'Wells Fargo'!$G:$G,'Cash Flow'!$A4,'Wells Fargo'!$A:$A,AC$1,'Wells Fargo'!$B:$B,"<="&'Cash Flow'!AC$3,'Wells Fargo'!$B:$B,">"&'Cash Flow'!AB$3) -> 0 | AD4: =SUMIFS('Wells Fargo'!$F:$F,'Wells Fargo'!$G:$G,'Cash Flow'!$A4,'Wells Fargo'!$A:$A,AD$1,'Wells Fargo'!$B:$B,"<="&'Cash Flow'!AD$3,'Wells Fargo'!$B:$B,">"&'Cash Flow'!AC$3) -> 0 | AE4: =SUMIFS('Wells Fargo'!$F:$F,'Wells Fargo'!$G:$G,'Cash Flow'!$A4,'Wells Fargo'!$A:$A,AE$1,'Wells Fargo'!$B:$B,"<="&'Cash Flow'!AE$3,'Wells Fargo'!$B:$B,">"&'Cash Flow'!AD$3) -> 0 | AF4: =SUMIFS('Wells Fargo'!$F:$F,'Wells Fargo'!$G:$G,'Cash Flow'!$A4,'Wells Fargo'!$A:$A,AF$1,'Wells Fargo'!$B:$B,"<="&'Cash Flow'!AF$3) -> 0 | AG4: =SUMIFS('Wells Fargo'!$F:$F,'Wells Fargo'!$G:$G,'Cash Flow'!$A4,'Wells Fargo'!$A:$A,AG$1,'Wells Fargo'!$B:$B,"<="&'Cash Flow'!AG$3,'Wells Fargo'!$B:$B,">"&'Cash Flow'!AF$3) -> 0 | AH4: =SUMIFS('Wells Fargo'!$F:$F,'Wells Fargo'!$G:$G,'Cash Flow'!$A4,'Wells Fargo'!$A:$A,AH$1,'Wells Fargo'!$B:$B,"<="&'Cash Flow'!AH$3,'Wells Fargo'!$B:$B,">"&'Cash Flow'!AG$3) -> 0 | AI4: =SUMIFS('Wells Fargo'!$F:$F,'Wells Fargo'!$G:$G,'Cash Flow'!$A4,'Wells Fargo'!$A:$A,AI$1,'Wells Fargo'!$B:$B,"<="&'Cash Flow'!AI$3,'Wells Fargo'!$B:$B,">"&'Cash Flow'!AH$3) -> 0 | AJ4: =SUMIFS('Wells Fargo'!$F:$F,'Wells Fargo'!$G:$G,'Cash Flow'!$A4,'Wells Fargo'!$A:$A,AJ$1,'Wells Fargo'!$B:$B,"<="&'Cash Flow'!AJ$3,'Wells Fargo'!$B:$B,">"&'Cash Flow'!AI$3) -> 0 | AK4: =SUMIFS('Wells Fargo'!$F:$F,'Wells Fargo'!$G:$G,'Cash Flow'!$A4,'Wells Fargo'!$A:$A,AK$1,'Wells Fargo'!$B:$B,"<="&'Cash Flow'!AK$3) -> 0 | AL4: =SUMIFS('Wells Fargo'!$F:$F,'Wells Fargo'!$G:$G,'Cash Flow'!$A4,'Wells Fargo'!$A:$A,AL$1,'Wells Fargo'!$B:$B,"<="&'Cash Flow'!AL$3,'Wells Fargo'!$B:$B,">"&'Cash Flow'!AK$3) -> 0 | AM4: =SUMIFS('Wells Fargo'!$F:$F,'Wells Fargo'!$G:$G,'Cash Flow'!$A4,'Wells Fargo'!$A:$A,AM$1,'Wells Fargo'!$B:$B,"<="&'Cash Flow'!AM$3,'Wells Fargo'!$B:$B,">"&'Cash Flow'!AL$3) -> 0 | AN4: =SUMIFS('Wells Fargo'!$F:$F,'Wells Fargo'!$G:$G,'Cash Flow'!$A4,'Wells Fargo'!$A:$A,AN$1,'Wells Fargo'!$B:$B,"<="&'Cash Flow'!AN$3,'Wells Fargo'!$B:$B,">"&'Cash Flow'!AM$3) -> 0 | AO4: =SUMIFS('Wells Fargo'!$F:$F,'Wells Fargo'!$G:$G,'Cash Flow'!$A4,'Wells Fargo'!$A:$A,AO$1,'Wells Fargo'!$B:$B,"<="&'Cash Flow'!AO$3,'Wells Fargo'!$B:$B,">"&'Cash Flow'!AN$3) -> 0 | AP4: =SUMIFS('Wells Fargo'!$F:$F,'Wells Fargo'!$G:$G,'Cash Flow'!$A4,'Wells Fargo'!$A:$A,AP$1,'Wells Fargo'!$B:$B,"<="&'Cash Flow'!AP$3) -> 0 | AQ4: =SUMIFS('Wells Fargo'!$F:$F,'Wells Fargo'!$G:$G,'Cash Flow'!$A4,'Wells Fargo'!$A:$A,AQ$1,'Wells Fargo'!$B:$B,"<="&'Cash Flow'!AQ$3,'Wells Fargo'!$B:$B,">"&'Cash Flow'!AP$3) -> 0 | AR4: =SUMIFS('Wells Fargo'!$F:$F,'Wells Fargo'!$G:$G,'Cash Flow'!$A4,'Wells Fargo'!$A:$A,AR$1,'Wells Fargo'!$B:$B,"<="&'Cash Flow'!AR$3,'Wells Fargo'!$B:$B,">"&'Cash Flow'!AQ$3) -> 0 | AS4: =SUMIFS('Wells Fargo'!$F:$F,'Wells Fargo'!$G:$G,'Cash Flow'!$A4,'Wells Fargo'!$A:$A,AS$1,'Wells Fargo'!$B:$B,"<="&'Cash Flow'!AS$3,'Wells Fargo'!$B:$B,">"&'Cash Flow'!AR$3) -> 0 | AT4: =SUMIFS('Wells Fargo'!$F:$F,'Wells Fargo'!$G:$G,'Cash Flow'!$A4,'Wells Fargo'!$A:$A,AT$1,'Wells Fargo'!$B:$B,"<="&'Cash Flow'!AT$3,'Wells Fargo'!$B:$B,">"&'Cash Flow'!AS$3) -> 0 | AU4: =SUMIFS('Wells Fargo'!$F:$F,'Wells Fargo'!$G:$G,'Cash Flow'!$A4,'Wells Fargo'!$A:$A,AU$1,'Wells Fargo'!$B:$B,"<="&'Cash Flow'!AU$3) -> 0 | AV4: =SUMIFS('Wells Fargo'!$F:$F,'Wells Fargo'!$G:$G,'Cash Flow'!$A4,'Wells Fargo'!$A:$A,AV$1,'Wells Fargo'!$B:$B,"<="&'Cash Flow'!AV$3,'Wells Fargo'!$B:$B,">"&'Cash Flow'!AU$3) -> 0 | AW4: =SUMIFS('Wells Fargo'!$F:$F,'Wells Fargo'!$G:$G,'Cash Flow'!$A4,'Wells Fargo'!$A:$A,AW$1,'Wells Fargo'!$B:$B,"<="&'Cash Flow'!AW$3,'Wells Fargo'!$B:$B,">"&'Cash Flow'!AV$3) -> 0 | AX4: =SUMIFS('Wells Fargo'!$F:$F,'Wells Fargo'!$G:$G,'Cash Flow'!$A4,'Wells Fargo'!$A:$A,AX$1,'Wells Fargo'!$B:$B,"<="&'Cash Flow'!AX$3,'Wells Fargo'!$B:$B,">"&'Cash Flow'!AW$3) -> 0 | AY4: =SUMIFS('Wells Fargo'!$F:$F,'Wells Fargo'!$G:$G,'Cash Flow'!$A4,'Wells Fargo'!$A:$A,AY$1,'Wells Fargo'!$B:$B,"<="&'Cash Flow'!AY$3,'Wells Fargo'!$B:$B,">"&'Cash Flow'!AX$3) -> 0 | AZ4: =SUMIFS('Wells Fargo'!$F:$F,'Wells Fargo'!$G:$G,'Cash Flow'!$A4,'Wells Fargo'!$A:$A,AZ$1,'Wells Fargo'!$B:$B,"<="&'Cash Flow'!AZ$3) -> 0 | BA4: =SUMIFS('Wells Fargo'!$F:$F,'Wells Fargo'!$G:$G,'Cash Flow'!$A4,'Wells Fargo'!$A:$A,BA$1,'Wells Fargo'!$B:$B,"<="&'Cash Flow'!BA$3,'Wells Fargo'!$B:$B,">"&'Cash Flow'!AZ$3) -> 0 | BB4: =SUMIFS('Wells Fargo'!$F:$F,'Wells Fargo'!$G:$G,'Cash Flow'!$A4,'Wells Fargo'!$A:$A,BB$1,'Wells Fargo'!$B:$B,"<="&'Cash Flow'!BB$3,'Wells Fargo'!$B:$B,">"&'Cash Flow'!BA$3) -> 0 | BC4: =SUMIFS('Wells Fargo'!$F:$F,'Wells Fargo'!$G:$G,'Cash Flow'!$A4,'Wells Fargo'!$A:$A,BC$1,'Wells Fargo'!$B:$B,"<="&'Cash Flow'!BC$3,'Wells Fargo'!$B:$B,">"&'Cash Flow'!BB$3) -> 0 | BD4: =SUMIFS('Wells Fargo'!$F:$F,'Wells Fargo'!$G:$G,'Cash Flow'!$A4,'Wells Fargo'!$A:$A,BD$1,'Wells Fargo'!$B:$B,"<="&'Cash Flow'!BD$3,'Wells Fargo'!$B:$B,">"&'Cash Flow'!BC$3) -> 0 | BE4: =SUMIFS('Wells Fargo'!$F:$F,'Wells Fargo'!$G:$G,'Cash Flow'!$A4,'Wells Fargo'!$A:$A,BE$1,'Wells Fargo'!$B:$B,"<="&'Cash Flow'!BE$3) -> 0 | BF4: =SUMIFS('Wells Fargo'!$F:$F,'Wells Fargo'!$G:$G,'Cash Flow'!$A4,'Wells Fargo'!$A:$A,BF$1,'Wells Fargo'!$B:$B,"<="&'Cash Flow'!BF$3,'Wells Fargo'!$B:$B,">"&'Cash Flow'!BE$3) -> 0 | BG4: =SUMIFS('Wells Fargo'!$F:$F,'Wells Fargo'!$G:$G,'Cash Flow'!$A4,'Wells Fargo'!$A:$A,BG$1,'Wells Fargo'!$B:$B,"<="&'Cash Flow'!BG$3,'Wells Fargo'!$B:$B,">"&'Cash Flow'!BF$3) -> 0 | BH4: =SUMIFS('Wells Fargo'!$F:$F,'Wells Fargo'!$G:$G,'Cash Flow'!$A4,'Wells Fargo'!$A:$A,BH$1,'Wells Fargo'!$B:$B,"<="&'Cash Flow'!BH$3,'Wells Fargo'!$B:$B,">"&'Cash Flow'!BG$3) -> 0 | BI4: =SUMIFS('Wells Fargo'!$F:$F,'Wells Fargo'!$G:$G,'Cash Flow'!$A4,'Wells Fargo'!$A:$A,BI$1,'Wells Fargo'!$B:$B,"<="&'Cash Flow'!BI$3,'Wells Fargo'!$B:$B,">"&'Cash Flow'!BH$3) -> 0
A5: 3070 GPU | B5: =SUM(C5:BI5) -> -500 | C5: =SUMIFS('Wells Fargo'!$F:$F,'Wells Fargo'!$G:$G,'Cash Flow'!$A5,'Wells Fargo'!$A:$A,C$1,'Wells Fargo'!$B:$B,"<="&'Cash Flow'!C$3) -> 0 | D5: =SUMIFS('Wells Fargo'!$F:$F,'Wells Fargo'!$G:$G,'Cash Flow'!$A5,'Wells Fargo'!$A:$A,D$1,'Wells Fargo'!$B:$B,"<="&'Cash Flow'!D$3,'Wells Fargo'!$B:$B,">"&'Cash Flow'!C$3) -> 0 | E5: =SUMIFS('Wells Fargo'!$F:$F,'Wells Fargo'!$G:$G,'Cash Flow'!$A5,'Wells Fargo'!$A:$A,E$1,'Wells Fargo'!$B:$B,"<="&'Cash Flow'!E$3,'Wells Fargo'!$B:$B,">"&'Cash Flow'!D$3) -> 0 | F5: =SUMIFS('Wells Fargo'!$F:$F,'Wells Fargo'!$G:$G,'Cash Flow'!$A5,'Wells Fargo'!$A:$A,F$1,'Wells Fargo'!$B:$B,"<="&'Cash Flow'!F$3,'Wells Fargo'!$B:$B,">"&'Cash Flow'!E$3) -> 0 | G5: =SUMIFS('Wells Fargo'!$F:$F,'Wells Fargo'!$G:$G,'Cash Flow'!$A5,'Wells Fargo'!$A:$A,G$1,'Wells Fargo'!$B:$B,"<="&'Cash Flow'!G$3,'Wells Fargo'!$B:$B,">"&'Cash Flow'!F$3) -> 0 | H5: =SUMIFS('Wells Fargo'!$F:$F,'Wells Fargo'!$G:$G,'Cash Flow'!$A5,'Wells Fargo'!$A:$A,H$1,'Wells Fargo'!$B:$B,"<="&'Cash Flow'!H$3) -> 0 | I5: =SUMIFS('Wells Fargo'!$F:$F,'Wells Fargo'!$G:$G,'Cash Flow'!$A5,'Wells Fargo'!$A:$A,I$1,'Wells Fargo'!$B:$B,"<="&'Cash Flow'!I$3,'Wells Fargo'!$B:$B,">"&'Cash Flow'!H$3) -> 0 | J5: =SUMIFS('Wells Fargo'!$F:$F,'Wells Fargo'!$G:$G,'Cash Flow'!$A5,'Wells Fargo'!$A:$A,J$1,'Wells Fargo'!$B:$B,"<="&'Cash Flow'!J$3,'Wells Fargo'!$B:$B,">"&'Cash Flow'!I$3) -> 0 | K5: =SUMIFS('Wells Fargo'!$F:$F,'Wells Fargo'!$G:$G,'Cash Flow'!$A5,'Wells Fargo'!$A:$A,K$1,'Wells Fargo'!$B:$B,"<="&'Cash Flow'!K$3,'Wells Fargo'!$B:$B,">"&'Cash Flow'!J$3) -> 0 | L5: =SUMIFS('Wells Fargo'!$F:$F,'Wells Fargo'!$G:$G,'Cash Flow'!$A5,'Wells Fargo'!$A:$A,L$1,'Wells Fargo'!$B:$B,"<="&'Cash Flow'!L$3) -> 0 | M5: =SUMIFS('Wells Fargo'!$F:$F,'Wells Fargo'!$G:$G,'Cash Flow'!$A5,'Wells Fargo'!$A:$A,M$1,'Wells Fargo'!$B:$B,"<="&'Cash Flow'!M$3,'Wells Fargo'!$B:$B,">"&'Cash Flow'!L$3) -> 0 | N5: =SUMIFS('Wells Fargo'!$F:$F,'Wells Fargo'!$G:$G,'Cash Flow'!$A5,'Wells Fargo'!$A:$A,N$1,'Wells Fargo'!$B:$B,"<="&'Cash Flow'!N$3,'Wells Fargo'!$B:$B,">"&'Cash Flow'!M$3) -> 0 | O5: =SUMIFS('Wells Fargo'!$F:$F,'Wells Fargo'!$G:$G,'Cash Flow'!$A5,'Wells Fargo'!$A:$A,O$1,'Wells Fargo'!$B:$B,"<="&'Cash Flow'!O$3,'Wells Fargo'!$B:$B,">"&'Cash Flow'!N$3) -> 0 | P5: =SUMIFS('Wells Fargo'!$F:$F,'Wells Fargo'!$G:$G,'Cash Flow'!$A5,'Wells Fargo'!$A:$A,P$1,'Wells Fargo'!$B:$B,"<="&'Cash Flow'!P$3,'Wells Fargo'!$B:$B,">"&'Cash Flow'!O$3) -> 0 | Q5: =SUMIFS('Wells Fargo'!$F:$F,'Wells Fargo'!$G:$G,'Cash Flow'!$A5,'Wells Fargo'!$A:$A,Q$1,'Wells Fargo'!$B:$B,"<="&'Cash Flow'!Q$3) -> 0 | R5: =SUMIFS('Wells Fargo'!$F:$F,'Wells Fargo'!$G:$G,'Cash Flow'!$A5,'Wells Fargo'!$A:$A,R$1,'Wells Fargo'!$B:$B,"<="&'Cash Flow'!R$3,'Wells Fargo'!$B:$B,">"&'Cash Flow'!Q$3) -> 0 | S5: =SUMIFS('Wells Fargo'!$F:$F,'Wells Fargo'!$G:$G,'Cash Flow'!$A5,'Wells Fargo'!$A:$A,S$1,'Wells Fargo'!$B:$B,"<="&'Cash Flow'!S$3,'Wells Fargo'!$B:$B,">"&'Cash Flow'!R$3) -> 0 | T5: =SUMIFS('Wells Fargo'!$F:$F,'Wells Fargo'!$G:$G,'Cash Flow'!$A5,'Wells Fargo'!$A:$A,T$1,'Wells Fargo'!$B:$B,"<="&'Cash Flow'!T$3,'Wells Fargo'!$B:$B,">"&'Cash Flow'!S$3) -> 0 | U5: =SUMIFS('Wells Fargo'!$F:$F,'Wells Fargo'!$G:$G,'Cash Flow'!$A5,'Wells Fargo'!$A:$A,U$1,'Wells Fargo'!$B:$B,"<="&'Cash Flow'!U$3,'Wells Fargo'!$B:$B,">"&'Cash Flow'!T$3) -> 0 | V5: =SUMIFS('Wells Fargo'!$F:$F,'Wells Fargo'!$G:$G,'Cash Flow'!$A5,'Wells Fargo'!$A:$A,V$1,'Wells Fargo'!$B:$B,"<="&'Cash Flow'!V$3) -> 0 | W5: =SUMIFS('Wells Fargo'!$F:$F,'Wells Fargo'!$G:$G,'Cash Flow'!$A5,'Wells Fargo'!$A:$A,W$1,'Wells Fargo'!$B:$B,"<="&'Cash Flow'!W$3,'Wells Fargo'!$B:$B,">"&'Cash Flow'!V$3) -> 0 | X5: =SUMIFS('Wells Fargo'!$F:$F,'Wells Fargo'!$G:$G,'Cash Flow'!$A5,'Wells Fargo'!$A:$A,X$1,'Wells Fargo'!$B:$B,"<="&'Cash Flow'!X$3,'Wells Fargo'!$B:$B,">"&'Cash Flow'!W$3) -> 0 | Y5: =SUMIFS('Wells Fargo'!$F:$F,'Wells Fargo'!$G:$G,'Cash Flow'!$A5,'Wells Fargo'!$A:$A,Y$1,'Wells Fargo'!$B:$B,"<="&'Cash Flow'!Y$3,'Wells Fargo'!$B:$B,">"&'Cash Flow'!X$3) -> 0 | Z5: =SUMIFS('Wells Fargo'!$F:$F,'Wells Fargo'!$G:$G,'Cash Flow'!$A5,'Wells Fargo'!$A:$A,Z$1,'Wells Fargo'!$B:$B,"<="&'Cash Flow'!Z$3,'Wells Fargo'!$B:$B,">"&'Cash Flow'!Y$3) -> 0 | AA5: =SUMIFS('Wells Fargo'!$F:$F,'Wells Fargo'!$G:$G,'Cash Flow'!$A5,'Wells Fargo'!$A:$A,AA$1,'Wells Fargo'!$B:$B,"<="&'Cash Flow'!AA$3) -> 0 | AB5: =SUMIFS('Wells Fargo'!$F:$F,'Wells Fargo'!$G:$G,'Cash Flow'!$A5,'Wells Fargo'!$A:$A,AB$1,'Wells Fargo'!$B:$B,"<="&'Cash Flow'!AB$3,'Wells Fargo'!$B:$B,">"&'Cash Flow'!AA$3) -> 0 | AC5: =SUMIFS('Wells Fargo'!$F:$F,'Wells Fargo'!$G:$G,'Cash Flow'!$A5,'Wells Fargo'!$A:$A,AC$1,'Wells Fargo'!$B:$B,"<="&'Cash Flow'!AC$3,'Wells Fargo'!$B:$B,">"&'Cash Flow'!AB$3) -> 0 | AD5: =SUMIFS('Wells Fargo'!$F:$F,'Wells Fargo'!$G:$G,'Cash Flow'!$A5,'Wells Fargo'!$A:$A,AD$1,'Wells Fargo'!$B:$B,"<="&'Cash Flow'!AD$3,'Wells Fargo'!$B:$B,">"&'Cash Flow'!AC$3) -> 0 | AE5: =SUMIFS('Wells Fargo'!$F:$F,'Wells Fargo'!$G:$G,'Cash Flow'!$A5,'Wells Fargo'!$A:$A,AE$1,'Wells Fargo'!$B:$B,"<="&'Cash Flow'!AE$3,'Wells Fargo'!$B:$B,">"&'Cash Flow'!AD$3) -> 0 | AF5: =SUMIFS('Wells Fargo'!$F:$F,'Wells Fargo'!$G:$G,'Cash Flow'!$A5,'Wells Fargo'!$A:$A,AF$1,'Wells Fargo'!$B:$B,"<="&'Cash Flow'!AF$3) -> 0 | AG5: =SUMIFS('Wells Fargo'!$F:$F,'Wells Fargo'!$G:$G,'Cash Flow'!$A5,'Wells Fargo'!$A:$A,AG$1,'Wells Fargo'!$B:$B,"<="&'Cash Flow'!AG$3,'Wells Fargo'!$B:$B,">"&'Cash Flow'!AF$3) -> 0 | AH5: =SUMIFS('Wells Fargo'!$F:$F,'Wells Fargo'!$G:$G,'Cash Flow'!$A5,'Wells Fargo'!$A:$A,AH$1,'Wells Fargo'!$B:$B,"<="&'Cash Flow'!AH$3,'Wells Fargo'!$B:$B,">"&'Cash Flow'!AG$3) -> -500 | AI5: =SUMIFS('Wells Fargo'!$F:$F,'Wells Fargo'!$G:$G,'Cash Flow'!$A5,'Wells Fargo'!$A:$A,AI$1,'Wells Fargo'!$B:$B,"<="&'Cash Flow'!AI$3,'Wells Fargo'!$B:$B,">"&'Cash Flow'!AH$3) -> 0 | AJ5: =SUMIFS('Wells Fargo'!$F:$F,'Wells Fargo'!$G:$G,'Cash Flow'!$A5,'Wells Fargo'!$A:$A,AJ$1,'Wells Fargo'!$B:$B,"<="&'Cash Flow'!AJ$3,'Wells Fargo'!$B:$B,">"&'Cash Flow'!AI$3) -> 0 | AK5: =SUMIFS('Wells Fargo'!$F:$F,'Wells Fargo'!$G:$G,'Cash Flow'!$A5,'Wells Fargo'!$A:$A,AK$1,'Wells Fargo'!$B:$B,"<="&'Cash Flow'!AK$3) -> 0 | AL5: =SUMIFS('Wells Fargo'!$F:$F,'Wells Fargo'!$G:$G,'Cash Flow'!$A5,'Wells Fargo'!$A:$A,AL$1,'Wells Fargo'!$B:$B,"<="&'Cash Flow'!AL$3,'Wells Fargo'!$B:$B,">"&'Cash Flow'!AK$3) -> 0 | AM5: =SUMIFS('Wells Fargo'!$F:$F,'Wells Fargo'!$G:$G,'Cash Flow'!$A5,'Wells Fargo'!$A:$A,AM$1,'Wells Fargo'!$B:$B,"<="&'Cash Flow'!AM$3,'Wells Fargo'!$B:$B,">"&'Cash Flow'!AL$3) -> 0 | AN5: =SUMIFS('Wells Fargo'!$F:$F,'Wells Fargo'!$G:$G,'Cash Flow'!$A5,'Wells Fargo'!$A:$A,AN$1,'Wells Fargo'!$B:$B,"<="&'Cash Flow'!AN$3,'Wells Fargo'!$B:$B,">"&'Cash Flow'!AM$3) -> 0 | AO5: =SUMIFS('Wells Fargo'!$F:$F,'Wells Fargo'!$G:$G,'Cash Flow'!$A5,'Wells Fargo'!$A:$A,AO$1,'Wells Fargo'!$B:$B,"<="&'Cash Flow'!AO$3,'Wells Fargo'!$B:$B,">"&'Cash Flow'!AN$3) -> 0 | AP5: =SUMIFS('Wells Fargo'!$F:$F,'Wells Fargo'!$G:$G,'Cash Flow'!$A5,'Wells Fargo'!$A:$A,AP$1,'Wells Fargo'!$B:$B,"<="&'Cash Flow'!AP$3) -> 0 | AQ5: =SUMIFS('Wells Fargo'!$F:$F,'Wells Fargo'!$G:$G,'Cash Flow'!$A5,'Wells Fargo'!$A:$A,AQ$1,'Wells Fargo'!$B:$B,"<="&'Cash Flow'!AQ$3,'Wells Fargo'!$B:$B,">"&'Cash Flow'!AP$3) -> 0 | AR5: =SUMIFS('Wells Fargo'!$F:$F,'Wells Fargo'!$G:$G,'Cash Flow'!$A5,'Wells Fargo'!$A:$A,AR$1,'Wells Fargo'!$B:$B,"<="&'Cash Flow'!AR$3,'Wells Fargo'!$B:$B,">"&'Cash Flow'!AQ$3) -> 0 | AS5: =SUMIFS('Wells Fargo'!$F:$F,'Wells Fargo'!$G:$G,'Cash Flow'!$A5,'Wells Fargo'!$A:$A,AS$1,'Wells Fargo'!$B:$B,"<="&'Cash Flow'!AS$3,'Wells Fargo'!$B:$B,">"&'Cash Flow'!AR$3) -> 0 | AT5: =SUMIFS('Wells Fargo'!$F:$F,'Wells Fargo'!$G:$G,'Cash Flow'!$A5,'Wells Fargo'!$A:$A,AT$1,'Wells Fargo'!$B:$B,"<="&'Cash Flow'!AT$3,'Wells Fargo'!$B:$B,">"&'Cash Flow'!AS$3) -> 0 | AU5: =SUMIFS('Wells Fargo'!$F:$F,'Wells Fargo'!$G:$G,'Cash Flow'!$A5,'Wells Fargo'!$A:$A,AU$1,'Wells Fargo'!$B:$B,"<="&'Cash Flow'!AU$3) -> 0 | AV5: =SUMIFS('Wells Fargo'!$F:$F,'Wells Fargo'!$G:$G,'Cash Flow'!$A5,'Wells Fargo'!$A:$A,AV$1,'Wells Fargo'!$B:$B,"<="&'Cash Flow'!AV$3,'Wells Fargo'!$B:$B,">"&'Cash Flow'!AU$3) -> 0 | AW5: =SUMIFS('Wells Fargo'!$F:$F,'Wells Fargo'!$G:$G,'Cash Flow'!$A5,'Wells Fargo'!$A:$A,AW$1,'Wells Fargo'!$B:$B,"<="&'Cash Flow'!AW$3,'Wells Fargo'!$B:$B,">"&'Cash Flow'!AV$3) -> 0 | AX5: =SUMIFS('Wells Fargo'!$F:$F,'Wells Fargo'!$G:$G,'Cash Flow'!$A5,'Wells Fargo'!$A:$A,AX$1,'Wells Fargo'!$B:$B,"<="&'Cash Flow'!AX$3,'Wells Fargo'!$B:$B,">"&'Cash Flow'!AW$3) -> 0 | AY5: =SUMIFS('Wells Fargo'!$F:$F,'Wells Fargo'!$G:$G,'Cash Flow'!$A5,'Wells Fargo'!$A:$A,AY$1,'Wells Fargo'!$B:$B,"<="&'Cash Flow'!AY$3,'Wells Fargo'!$B:$B,">"&'Cash Flow'!AX$3) -> 0 | AZ5: =SUMIFS('Wells Fargo'!$F:$F,'Wells Fargo'!$G:$G,'Cash Flow'!$A5,'Wells Fargo'!$A:$A,AZ$1,'Wells Fargo'!$B:$B,"<="&'Cash Flow'!AZ$3) -> 0 | BA5: =SUMIFS('Wells Fargo'!$F:$F,'Wells Fargo'!$G:$G,'Cash Flow'!$A5,'Wells Fargo'!$A:$A,BA$1,'Wells Fargo'!$B:$B,"<="&'Cash Flow'!BA$3,'Wells Fargo'!$B:$B,">"&'Cash Flow'!AZ$3) -> 0 | BB5: =SUMIFS('Wells Fargo'!$F:$F,'Wells Fargo'!$G:$G,'Cash Flow'!$A5,'Wells Fargo'!$A:$A,BB$1,'Wells Fargo'!$B:$B,"<="&'Cash Flow'!BB$3,'Wells Fargo'!$B:$B,">"&'Cash Flow'!BA$3) -> 0 | BC5: =SUMIFS('Wells Fargo'!$F:$F,'Wells Fargo'!$G:$G,'Cash Flow'!$A5,'Wells Fargo'!$A:$A,BC$1,'Wells Fargo'!$B:$B,"<="&'Cash Flow'!BC$3,'Wells Fargo'!$B:$B,">"&'Cash Flow'!BB$3) -> 0 | BD5: =SUMIFS('Wells Fargo'!$F:$F,'Wells Fargo'!$G:$G,'Cash Flow'!$A5,'Wells Fargo'!$A:$A,BD$1,'Wells Fargo'!$B:$B,"<="&'Cash Flow'!BD$3,'Wells Fargo'!$B:$B,">"&'Cash Flow'!BC$3) -> 0 | BE5: =SUMIFS('Wells Fargo'!$F:$F,'Wells Fargo'!$G:$G,'Cash Flow'!$A5,'Wells Fargo'!$A:$A,BE$1,'Wells Fargo'!$B:$B,"<="&'Cash Flow'!BE$3) -> 0 | BF5: =SUMIFS('Wells Fargo'!$F:$F,'Wells Fargo'!$G:$G,'Cash Flow'!$A5,'Wells Fargo'!$A:$A,BF$1,'Wells Fargo'!$B:$B,"<="&'Cash Flow'!BF$3,'Wells Fargo'!$B:$B,">"&'Cash Flow'!BE$3) -> 0 | BG5: =SUMIFS('Wells Fargo'!$F:$F,'Wells Fargo'!$G:$G,'Cash Flow'!$A5,'Wells Fargo'!$A:$A,BG$1,'Wells Fargo'!$B:$B,"<="&'Cash Flow'!BG$3,'Wells Fargo'!$B:$B,">"&'Cash Flow'!BF$3) -> 0 | BH5: =SUMIFS('Wells Fargo'!$F:$F,'Wells Fargo'!$G:$G,'Cash Flow'!$A5,'Wells Fargo'!$A:$A,BH$1,'Wells Fargo'!$B:$B,"<="&'Cash Flow'!BH$3,'Wells Fargo'!$B:$B,">"&'Cash Flow'!BG$3) -> 0 | BI5: =SUMIFS('Wells Fargo'!$F:$F,'Wells Fargo'!$G:$G,'Cash Flow'!$A5,'Wells Fargo'!$A:$A,BI$1,'Wells Fargo'!$B:$B,"<="&'Cash Flow'!BI$3,'Wells Fargo'!$B:$B,">"&'Cash Flow'!BH$3) -> 0
A6: 3070 GPU | B6: =SUM(C6:BI6) -> 500 | C6: =SUMIFS('Wells Fargo'!$F:$F,'Wells Fargo'!$G:$G,'Cash Flow'!$A6,'Wells Fargo'!$A:$A,C$1,'Wells Fargo'!$B:$B,"<="&'Cash Flow'!C$3) -> 0 | D6: =SUMIFS('Wells Fargo'!$F:$F,'Wells Fargo'!$G:$G,'Cash Flow'!$A6,'Wells Fargo'!$A:$A,D$1,'Wells Fargo'!$B:$B,"<="&'Cash Flow'!D$3,'Wells Fargo'!$B:$B,">"&'Cash Flow'!C$3) -> 0 | E6: =SUMIFS('Wells Fargo'!$F:$F,'Wells Fargo'!$G:$G,'Cash Flow'!$A6,'Wells Fargo'!$A:$A,E$1,'Wells Fargo'!$B:$B,"<="&'Cash Flow'!E$3,'Wells Fargo'!$B:$B,">"&'Cash Flow'!D$3) -> 0 | F6: =SUMIFS('Wells Fargo'!$F:$F,'Wells Fargo'!$G:$G,'Cash Flow'!$A6,'Wells Fargo'!$A:$A,F$1,'Wells Fargo'!$B:$B,"<="&'Cash Flow'!F$3,'Wells Fargo'!$B:$B,">"&'Cash Flow'!E$3) -> 0 | G6: =SUMIFS('Wells Fargo'!$F:$F,'Wells Fargo'!$G:$G,'Cash Flow'!$A6,'Wells Fargo'!$A:$A,G$1,'Wells Fargo'!$B:$B,"<="&'Cash Flow'!G$3,'Wells Fargo'!$B:$B,">"&'Cash Flow'!F$3) -> 0 | H6: =SUMIFS('Wells Fargo'!$F:$F,'Wells Fargo'!$G:$G,'Cash Flow'!$A6,'Wells Fargo'!$A:$A,H$1,'Wells Fargo'!$B:$B,"<="&'Cash Flow'!H$3) -> 0 | I6: =SUMIFS('Wells Fargo'!$F:$F,'Wells Fargo'!$G:$G,'Cash Flow'!$A6,'Wells Fargo'!$A:$A,I$1,'Wells Fargo'!$B:$B,"<="&'Cash Flow'!I$3,'Wells Fargo'!$B:$B,">"&'Cash Flow'!H$3) -> 0 | J6: =SUMIFS('Wells Fargo'!$F:$F,'Wells Fargo'!$G:$G,'Cash Flow'!$A6,'Wells Fargo'!$A:$A,J$1,'Wells Fargo'!$B:$B,"<="&'Cash Flow'!J$3,'Wells Fargo'!$B:$B,">"&'Cash Flow'!I$3) -> 0 | K6: =SUMIFS('Wells Fargo'!$F:$F,'Wells Fargo'!$G:$G,'Cash Flow'!$A6,'Wells Fargo'!$A:$A,K$1,'Wells Fargo'!$B:$B,"<="&'Cash Flow'!K$3,'Wells Fargo'!$B:$B,">"&'Cash Flow'!J$3) -> 0 | L6: =SUMIFS('Wells Fargo'!$F:$F,'Wells Fargo'!$G:$G,'Cash Flow'!$A6,'Wells Fargo'!$A:$A,L$1,'Wells Fargo'!$B:$B,"<="&'Cash Flow'!L$3) -> 0 | M6: =SUMIFS('Wells Fargo'!$F:$F,'Wells Fargo'!$G:$G,'Cash Flow'!$A6,'Wells Fargo'!$A:$A,M$1,'Wells Fargo'!$B:$B,"<="&'Cash Flow'!M$3,'Wells Fargo'!$B:$B,">"&'Cash Flow'!L$3) -> 0 | N6: =SUMIFS('Wells Fargo'!$F:$F,'Wells Fargo'!$G:$G,'Cash Flow'!$A6,'Wells Fargo'!$A:$A,N$1,'Wells Fargo'!$B:$B,"<="&'Cash Flow'!N$3,'Wells Fargo'!$B:$B,">"&'Cash Flow'!M$3) -> 0 | O6: =SUMIFS('Wells Fargo'!$F:$F,'Wells Fargo'!$G:$G,'Cash Flow'!$A6,'Wells Fargo'!$A:$A,O$1,'Wells Fargo'!$B:$B,"<="&'Cash Flow'!O$3,'Wells Fargo'!$B:$B,">"&'Cash Flow'!N$3) -> 0 | P6: =SUMIFS('Wells Fargo'!$F:$F,'Wells Fargo'!$G:$G,'Cash Flow'!$A6,'Wells Fargo'!$A:$A,P$1,'Wells Fargo'!$B:$B,"<="&'Cash Flow'!P$3,'Wells Fargo'!$B:$B,">"&'Cash Flow'!O$3) -> 0 | Q6: =SUMIFS('Wells Fargo'!$F:$F,'Wells Fargo'!$G:$G,'Cash Flow'!$A6,'Wells Fargo'!$A:$A,Q$1,'Wells Fargo'!$B:$B,"<="&'Cash Flow'!Q$3) -> 0 | R6: =SUMIFS('Wells Fargo'!$F:$F,'Wells Fargo'!$G:$G,'Cash Flow'!$A6,'Wells Fargo'!$A:$A,R$1,'Wells Fargo'!$B:$B,"<="&'Cash Flow'!R$3,'Wells Fargo'!$B:$B,">"&'Cash Flow'!Q$3) -> 0 | S6: =SUMIFS('Wells Fargo'!$F:$F,'Wells Fargo'!$G:$G,'Cash Flow'!$A6,'Wells Fargo'!$A:$A,S$1,'Wells Fargo'!$B:$B,"<="&'Cash Flow'!S$3,'Wells Fargo'!$B:$B,">"&'Cash Flow'!R$3) -> 0 | T6: =SUMIFS('Wells Fargo'!$F:$F,'Wells Fargo'!$G:$G,'Cash Flow'!$A6,'Wells Fargo'!$A:$A,T$1,'Wells Fargo'!$B:$B,"<="&'Cash Flow'!T$3,'Wells Fargo'!$B:$B,">"&'Cash Flow'!S$3) -> 0 | U6: =SUMIFS('Wells Fargo'!$F:$F,'Wells Fargo'!$G:$G,'Cash Flow'!$A6,'Wells Fargo'!$A:$A,U$1,'Wells Fargo'!$B:$B,"<="&'Cash Flow'!U$3,'Wells Fargo'!$B:$B,">"&'Cash Flow'!T$3) -> 0 | V6: =SUMIFS('Wells Fargo'!$F:$F,'Wells Fargo'!$G:$G,'Cash Flow'!$A6,'Wells Fargo'!$A:$A,V$1,'Wells Fargo'!$B:$B,"<="&'Cash Flow'!V$3) -> 0 | W6: =SUMIFS('Wells Fargo'!$F:$F,'Wells Fargo'!$G:$G,'Cash Flow'!$A6,'Wells Fargo'!$A:$A,W$1,'Wells Fargo'!$B:$B,"<="&'Cash Flow'!W$3,'Wells Fargo'!$B:$B,">"&'Cash Flow'!V$3) -> 0 | X6: =SUMIFS('Wells Fargo'!$F:$F,'Wells Fargo'!$G:$G,'Cash Flow'!$A6,'Wells Fargo'!$A:$A,X$1,'Wells Fargo'!$B:$B,"<="&'Cash Flow'!X$3,'Wells Fargo'!$B:$B,">"&'Cash Flow'!W$3) -> 0 | Y6: =SUMIFS('Wells Fargo'!$F:$F,'Wells Fargo'!$G:$G,'Cash Flow'!$A6,'Wells Fargo'!$A:$A,Y$1,'Wells Fargo'!$B:$B,"<="&'Cash Flow'!Y$3,'Wells Fargo'!$B:$B,">"&'Cash Flow'!X$3) -> 0 | Z6: =SUMIFS('Wells Fargo'!$F:$F,'Wells Fargo'!$G:$G,'Cash Flow'!$A6,'Wells Fargo'!$A:$A,Z$1,'Wells Fargo'!$B:$B,"<="&'Cash Flow'!Z$3,'Wells Fargo'!$B:$B,">"&'Cash Flow'!Y$3) -> 0 | AA6: =SUMIFS('Wells Fargo'!$F:$F,'Wells Fargo'!$G:$G,'Cash Flow'!$A6,'Wells Fargo'!$A:$A,AA$1,'Wells Fargo'!$B:$B,"<="&'Cash Flow'!AA$3) -> 0 | AB6: =SUMIFS('Wells Fargo'!$F:$F,'Wells Fargo'!$G:$G,'Cash Flow'!$A6,'Wells Fargo'!$A:$A,AB$1,'Wells Fargo'!$B:$B,"<="&'Cash Flow'!AB$3,'Wells Fargo'!$B:$B,">"&'Cash Flow'!AA$3) -> 0 | AC6: =SUMIFS('Wells Fargo'!$F:$F,'Wells Fargo'!$G:$G,'Cash Flow'!$A6,'Wells Fargo'!$A:$A,AC$1,'Wells Fargo'!$B:$B,"<="&'Cash Flow'!AC$3,'Wells Fargo'!$B:$B,">"&'Cash Flow'!AB$3) -> 0 | AD6: =SUMIFS('Wells Fargo'!$F:$F,'Wells Fargo'!$G:$G,'Cash Flow'!$A6,'Wells Fargo'!$A:$A,AD$1,'Wells Fargo'!$B:$B,"<="&'Cash Flow'!AD$3,'Wells Fargo'!$B:$B,">"&'Cash Flow'!AC$3) -> 0 | AE6: =SUMIFS('Wells Fargo'!$F:$F,'Wells Fargo'!$G:$G,'Cash Flow'!$A6,'Wells Fargo'!$A:$A,AE$1,'Wells Fargo'!$B:$B,"<="&'Cash Flow'!AE$3,'Wells Fargo'!$B:$B,">"&'Cash Flow'!AD$3) -> 0 | AF6: =SUMIFS('Wells Fargo'!$F:$F,'Wells Fargo'!$G:$G,'Cash Flow'!$A6,'Wells Fargo'!$A:$A,AF$1,'Wells Fargo'!$B:$B,"<="&'Cash Flow'!AF$3) -> 0 | AG6: =SUMIFS('Wells Fargo'!$F:$F,'Wells Fargo'!$G:$G,'Cash Flow'!$A6,'Wells Fargo'!$A:$A,AG$1,'Wells Fargo'!$B:$B,"<="&'Cash Flow'!AG$3,'Wells Fargo'!$B:$B,">"&'Cash Flow'!AF$3) -> 0 | AH6: =SUMIFS('Wells Fargo'!$F:$F,'Wells Fargo'!$G:$G,'Cash Flow'!$A6,'Wells Fargo'!$A:$A,AH$1,'Wells Fargo'!$B:$B,"<="&'Cash Flow'!AH$3,'Wells Fargo'!$B:$B,">"&'Cash Flow'!AG$3) -> 500 | AI6: =SUMIFS('Wells Fargo'!$F:$F,'Wells Fargo'!$G:$G,'Cash Flow'!$A6,'Wells Fargo'!$A:$A,AI$1,'Wells Fargo'!$B:$B,"<="&'Cash Flow'!AI$3,'Wells Fargo'!$B:$B,">"&'Cash Flow'!AH$3) -> 0 | AJ6: =SUMIFS('Wells Fargo'!$F:$F,'Wells Fargo'!$G:$G,'Cash Flow'!$A6,'Wells Fargo'!$A:$A,AJ$1,'Wells Fargo'!$B:$B,"<="&'Cash Flow'!AJ$3,'Wells Fargo'!$B:$B,">"&'Cash Flow'!AI$3) -> 0 | AK6: =SUMIFS('Wells Fargo'!$F:$F,'Wells Fargo'!$G:$G,'Cash Flow'!$A6,'Wells Fargo'!$A:$A,AK$1,'Wells Fargo'!$B:$B,"<="&'Cash Flow'!AK$3) -> 0 | AL6: =SUMIFS('Wells Fargo'!$F:$F,'Wells Fargo'!$G:$G,'Cash Flow'!$A6,'Wells Fargo'!$A:$A,AL$1,'Wells Fargo'!$B:$B,"<="&'Cash Flow'!AL$3,'Wells Fargo'!$B:$B,">"&'Cash Flow'!AK$3) -> 0 | AM6: =SUMIFS('Wells Fargo'!$F:$F,'Wells Fargo'!$G:$G,'Cash Flow'!$A6,'Wells Fargo'!$A:$A,AM$1,'Wells Fargo'!$B:$B,"<="&'Cash Flow'!AM$3,'Wells Fargo'!$B:$B,">"&'Cash Flow'!AL$3) -> 0 | AN6: =SUMIFS('Wells Fargo'!$F:$F,'Wells Fargo'!$G:$G,'Cash Flow'!$A6,'Wells Fargo'!$A:$A,AN$1,'Wells Fargo'!$B:$B,"<="&'Cash Flow'!AN$3,'Wells Fargo'!$B:$B,">"&'Cash Flow'!AM$3) -> 0 | AO6: =SUMIFS('Wells Fargo'!$F:$F,'Wells Fargo'!$G:$G,'Cash Flow'!$A6,'Wells Fargo'!$A:$A,AO$1,'Wells Fargo'!$B:$B,"<="&'Cash Flow'!AO$3,'Wells Fargo'!$B:$B,">"&'Cash Flow'!AN$3) -> 0 | AP6: =SUMIFS('Wells Fargo'!$F:$F,'Wells Fargo'!$G:$G,'Cash Flow'!$A6,'Wells Fargo'!$A:$A,AP$1,'Wells Fargo'!$B:$B,"<="&'Cash Flow'!AP$3) -> 0 | AQ6: =SUMIFS('Wells Fargo'!$F:$F,'Wells Fargo'!$G:$G,'Cash Flow'!$A6,'Wells Fargo'!$A:$A,AQ$1,'Wells Fargo'!$B:$B,"<="&'Cash Flow'!AQ$3,'Wells Fargo'!$B:$B,">"&'Cash Flow'!AP$3) -> 0 | AR6: =SUMIFS('Wells Fargo'!$F:$F,'Wells Fargo'!$G:$G,'Cash Flow'!$A6,'Wells Fargo'!$A:$A,AR$1,'Wells Fargo'!$B:$B,"<="&'Cash Flow'!AR$3,'Wells Fargo'!$B:$B,">"&'Cash Flow'!AQ$3) -> 0 | AS6: =SUMIFS('Wells Fargo'!$F:$F,'Wells Fargo'!$G:$G,'Cash Flow'!$A6,'Wells Fargo'!$A:$A,AS$1,'Wells Fargo'!$B:$B,"<="&'Cash Flow'!AS$3,'Wells Fargo'!$B:$B,">"&'Cash Flow'!AR$3) -> 0 | AT6: =SUMIFS('Wells Fargo'!$F:$F,'Wells Fargo'!$G:$G,'Cash Flow'!$A6,'Wells Fargo'!$A:$A,AT$1,'Wells Fargo'!$B:$B,"<="&'Cash Flow'!AT$3,'Wells Fargo'!$B:$B,">"&'Cash Flow'!AS$3) -> 0 | AU6: =SUMIFS('Wells Fargo'!$F:$F,'Wells Fargo'!$G:$G,'Cash Flow'!$A6,'Wells Fargo'!$A:$A,AU$1,'Wells Fargo'!$B:$B,"<="&'Cash Flow'!AU$3) -> 0 | AV6: =SUMIFS('Wells Fargo'!$F:$F,'Wells Fargo'!$G:$G,'Cash Flow'!$A6,'Wells Fargo'!$A:$A,AV$1,'Wells Fargo'!$B:$B,"<="&'Cash Flow'!AV$3,'Wells Fargo'!$B:$B,">"&'Cash Flow'!AU$3) -> 0 | AW6: =SUMIFS('Wells Fargo'!$F:$F,'Wells Fargo'!$G:$G,'Cash Flow'!$A6,'Wells Fargo'!$A:$A,AW$1,'Wells Fargo'!$B:$B,"<="&'Cash Flow'!AW$3,'Wells Fargo'!$B:$B,">"&'Cash Flow'!AV$3) -> 0 | AX6: =SUMIFS('Wells Fargo'!$F:$F,'Wells Fargo'!$G:$G,'Cash Flow'!$A6,'Wells Fargo'!$A:$A,AX$1,'Wells Fargo'!$B:$B,"<="&'Cash Flow'!AX$3,'Wells Fargo'!$B:$B,">"&'Cash Flow'!AW$3) -> 0 | AY6: =SUMIFS('Wells Fargo'!$F:$F,'Wells Fargo'!$G:$G,'Cash Flow'!$A6,'Wells Fargo'!$A:$A,AY$1,'Wells Fargo'!$B:$B,"<="&'Cash Flow'!AY$3,'Wells Fargo'!$B:$B,">"&'Cash Flow'!AX$3) -> 0 | AZ6: =SUMIFS('Wells Fargo'!$F:$F,'Wells Fargo'!$G:$G,'Cash Flow'!$A6,'Wells Fargo'!$A:$A,AZ$1,'Wells Fargo'!$B:$B,"<="&'Cash Flow'!AZ$3) -> 0 | BA6: =SUMIFS('Wells Fargo'!$F:$F,'Wells Fargo'!$G:$G,'Cash Flow'!$A6,'Wells Fargo'!$A:$A,BA$1,'Wells Fargo'!$B:$B,"<="&'Cash Flow'!BA$3,'Wells Fargo'!$B:$B,">"&'Cash Flow'!AZ$3) -> 0 | BB6: =SUMIFS('Wells Fargo'!$F:$F,'Wells Fargo'!$G:$G,'Cash Flow'!$A6,'Wells Fargo'!$A:$A,BB$1,'Wells Fargo'!$B:$B,"<="&'Cash Flow'!BB$3,'Wells Fargo'!$B:$B,">"&'Cash Flow'!BA$3) -> 0 | BC6: =SUMIFS('Wells Fargo'!$F:$F,'Wells Fargo'!$G:$G,'Cash Flow'!$A6,'Wells Fargo'!$A:$A,BC$1,'Wells Fargo'!$B:$B,"<="&'Cash Flow'!BC$3,'Wells Fargo'!$B:$B,">"&'Cash Flow'!BB$3) -> 0 | BD6: =SUMIFS('Wells Fargo'!$F:$F,'Wells Fargo'!$G:$G,'Cash Flow'!$A6,'Wells Fargo'!$A:$A,BD$1,'Wells Fargo'!$B:$B,"<="&'Cash Flow'!BD$3,'Wells Fargo'!$B:$B,">"&'Cash Flow'!BC$3) -> 0 | BE6: =SUMIFS('Wells Fargo'!$F:$F,'Wells Fargo'!$G:$G,'Cash Flow'!$A6,'Wells Fargo'!$A:$A,BE$1,'Wells Fargo'!$B:$B,"<="&'Cash Flow'!BE$3) -> 0 | BF6: =SUMIFS('Wells Fargo'!$F:$F,'Wells Fargo'!$G:$G,'Cash Flow'!$A6,'Wells Fargo'!$A:$A,BF$1,'Wells Fargo'!$B:$B,"<="&'Cash Flow'!BF$3,'Wells Fargo'!$B:$B,">"&'Cash Flow'!BE$3) -> 0 | BG6: =SUMIFS('Wells Fargo'!$F:$F,'Wells Fargo'!$G:$G,'Cash Flow'!$A6,'Wells Fargo'!$A:$A,BG$1,'Wells Fargo'!$B:$B,"<="&'Cash Flow'!BG$3,'Wells Fargo'!$B:$B,">"&'Cash Flow'!BF$3) -> 0 | BH6: =SUMIFS('Wells Fargo'!$F:$F,'Wells Fargo'!$G:$G,'Cash Flow'!$A6,'Wells Fargo'!$A:$A,BH$1,'Wells Fargo'!$B:$B,"<="&'Cash Flow'!BH$3,'Wells Fargo'!$B:$B,">"&'Cash Flow'!BG$3) -> 0 | BI6: =SUMIFS('Wells Fargo'!$F:$F,'Wells Fargo'!$G:$G,'Cash Flow'!$A6,'Wells Fargo'!$A:$A,BI$1,'Wells Fargo'!$B:$B,"<="&'Cash Flow'!BI$3,'Wells Fargo'!$B:$B,">"&'Cash Flow'!BH$3) -> 0
A7: Amar - Electric | B7: =SUM(C7:BI7) -> -592.54 | C7: =SUMIFS('Wells Fargo'!$F:$F,'Wells Fargo'!$G:$G,'Cash Flow'!$A7,'Wells Fargo'!$A:$A,C$1,'Wells Fargo'!$B:$B,"<="&'Cash Flow'!C$3) -> 0 | D7: =SUMIFS('Wells Fargo'!$F:$F,'Wells Fargo'!$G:$G,'Cash Flow'!$A7,'Wells Fargo'!$A:$A,D$1,'Wells Fargo'!$B:$B,"<="&'Cash Flow'!D$3,'Wells Fargo'!$B:$B,">"&'Cash Flow'!C$3) -> 0 | E7: =SUMIFS('Wells Fargo'!$F:$F,'Wells Fargo'!$G:$G,'Cash Flow'!$A7,'Wells Fargo'!$A:$A,E$1,'Wells Fargo'!$B:$B,"<="&'Cash Flow'!E$3,'Wells Fargo'!$B:$B,">"&'Cash Flow'!D$3) -> 0 | F7: =SUMIFS('Wells Fargo'!$F:$F,'Wells Fargo'!$G:$G,'Cash Flow'!$A7,'Wells Fargo'!$A:$A,F$1,'Wells Fargo'!$B:$B,"<="&'Cash Flow'!F$3,'Wells Fargo'!$B:$B,">"&'Cash Flow'!E$3) -> -78.86 | G7: =SUMIFS('Wells Fargo'!$F:$F,'Wells Fargo'!$G:$G,'Cash Flow'!$A7,'Wells Fargo'!$A:$A,G$1,'Wells Fargo'!$B:$B,"<="&'Cash Flow'!G$3,'Wells Fargo'!$B:$B,">"&'Cash Flow'!F$3) -> 0 | H7: =SUMIFS('Wells Fargo'!$F:$F,'Wells Fargo'!$G:$G,'Cash Flow'!$A7,'Wells Fargo'!$A:$A,H$1,'Wells Fargo'!$B:$B,"<="&'Cash Flow'!H$3) -> 0 | I7: =SUMIFS('Wells Fargo'!$F:$F,'Wells Fargo'!$G:$G,'Cash Flow'!$A7,'Wells Fargo'!$A:$A,I$1,'Wells Fargo'!$B:$B,"<="&'Cash Flow'!I$3,'Wells Fargo'!$B:$B,">"&'Cash Flow'!H$3) -> 0 | J7: =SUMIFS('Wells Fargo'!$F:$F,'Wells Fargo'!$G:$G,'Cash Flow'!$A7,'Wells Fargo'!$A:$A,J$1,'Wells Fargo'!$B:$B,"<="&'Cash Flow'!J$3,'Wells Fargo'!$B:$B,">"&'Cash Flow'!I$3) -> 0 | K7: =SUMIFS('Wells Fargo'!$F:$F,'Wells Fargo'!$G:$G,'Cash Flow'!$A7,'Wells Fargo'!$A:$A,K$1,'Wells Fargo'!$B:$B,"<="&'Cash Flow'!K$3,'Wells Fargo'!$B:$B,">"&'Cash Flow'!J$3) -> -81.32 | L7: =SUMIFS('Wells Fargo'!$F:$F,'Wells Fargo'!$G:$G,'Cash Flow'!$A7,'Wells Fargo'!$A:$A,L$1,'Wells Fargo'!$B:$B,"<="&'Cash Flow'!L$3) -> 0 | M7: =SUMIFS('Wells Fargo'!$F:$F,'Wells Fargo'!$G:$G,'Cash Flow'!$A7,'Wells Fargo'!$A:$A,M$1,'Wells Fargo'!$B:$B,"<="&'Cash Flow'!M$3,'Wells Fargo'!$B:$B,">"&'Cash Flow'!L$3) -> 0 | N7: =SUMIFS('Wells Fargo'!$F:$F,'Wells Fargo'!$G:$G,'Cash Flow'!$A7,'Wells Fargo'!$A:$A,N$1,'Wells Fargo'!$B:$B,"<="&'Cash Flow'!N$3,'Wells Fargo'!$B:$B,">"&'Cash Flow'!M$3) -> -39.7 | O7: =SUMIFS('Wells Fargo'!$F:$F,'Wells Fargo'!$G:$G,'Cash Flow'!$A7,'Wells Fargo'!$A:$A,O$1,'Wells Fargo'!$B:$B,"<="&'Cash Flow'!O$3,'Wells Fargo'!$B:$B,">"&'Cash Flow'!N$3) -> 0 | P7: =SUMIFS('Wells Fargo'!$F:$F,'Wells Fargo'!$G:$G,'Cash Flow'!$A7,'Wells Fargo'!$A:$A,P$1,'Wells Fargo'!$B:$B,"<="&'Cash Flow'!P$3,'Wells Fargo'!$B:$B,">"&'Cash Flow'!O$3) -> 0 | Q7: =SUMIFS('Wells Fargo'!$F:$F,'Wells Fargo'!$G:$G,'Cash Flow'!$A7,'Wells Fargo'!$A:$A,Q$1,'Wells Fargo'!$B:$B,"<="&'Cash Flow'!Q$3) -> 0 | R7: =SUMIFS('Wells Fargo'!$F:$F,'Wells Fargo'!$G:$G,'Cash Flow'!$A7,'Wells Fargo'!$A:$A,R$1,'Wells Fargo'!$B:$B,"<="&'Cash Flow'!R$3,'Wells Fargo'!$B:$B,">"&'Cash Flow'!Q$3) -> 0 | S7: =SUMIFS('Wells Fargo'!$F:$F,'Wells Fargo'!$G:$G,'Cash Flow'!$A7,'Wells Fargo'!$A:$A,S$1,'Wells Fargo'!$B:$B,"<="&'Cash Flow'!S$3,'Wells Fargo'!$B:$B,">"&'Cash Flow'!R$3) -> -138.52 | T7: =SUMIFS('Wells Fargo'!$F:$F,'Wells Fargo'!$G:$G,'Cash Flow'!$A7,'Wells Fargo'!$A:$A,T$1,'Wells Fargo'!$B:$B,"<="&'Cash Flow'!T$3,'Wells Fargo'!$B:$B,">"&'Cash Flow'!S$3) -> 0 | U7: =SUMIFS('Wells Fargo'!$F:$F,'Wells Fargo'!$G:$G,'Cash Flow'!$A7,'Wells Fargo'!$A:$A,U$1,'Wells Fargo'!$B:$B,"<="&'Cash Flow'!U$3,'Wells Fargo'!$B:$B,">"&'Cash Flow'!T$3) -> 0 | V7: =SUMIFS('Wells Fargo'!$F:$F,'Wells Fargo'!$G:$G,'Cash Flow'!$A7,'Wells Fargo'!$A:$A,V$1,'Wells Fargo'!$B:$B,"<="&'Cash Flow'!V$3) -> 0 | W7: =SUMIFS('Wells Fargo'!$F:$F,'Wells Fargo'!$G:$G,'Cash Flow'!$A7,'Wells Fargo'!$A:$A,W$1,'Wells Fargo'!$B:$B,"<="&'Cash Flow'!W$3,'Wells Fargo'!$B:$B,">"&'Cash Flow'!V$3) -> -136.14 | X7: =SUMIFS('Wells Fargo'!$F:$F,'Wells Fargo'!$G:$G,'Cash Flow'!$A7,'Wells Fargo'!$A:$A,X$1,'Wells Fargo'!$B:$B,"<="&'Cash Flow'!X$3,'Wells Fargo'!$B:$B,">"&'Cash Flow'!W$3) -> 0 | Y7: =SUMIFS('Wells Fargo'!$F:$F,'Wells Fargo'!$G:$G,'Cash Flow'!$A7,'Wells Fargo'!$A:$A,Y$1,'Wells Fargo'!$B:$B,"<="&'Cash Flow'!Y$3,'Wells Fargo'!$B:$B,">"&'Cash Flow'!X$3) -> 0 | Z7: =SUMIFS('Wells Fargo'!$F:$F,'Wells Fargo'!$G:$G,'Cash Flow'!$A7,'Wells Fargo'!$A:$A,Z$1,'Wells Fargo'!$B:$B,"<="&'Cash Flow'!Z$3,'Wells Fargo'!$B:$B,">"&'Cash Flow'!Y$3) -> 0 | AA7: =SUMIFS('Wells Fargo'!$F:$F,'Wells Fargo'!$G:$G,'Cash Flow'!$A7,'Wells Fargo'!$A:$A,AA$1,'Wells Fargo'!$B:$B,"<="&'Cash Flow'!AA$3) -> -118 | AB7: =SUMIFS('Wells Fargo'!$F:$F,'Wells Fargo'!$G:$G,'Cash Flow'!$A7,'Wells Fargo'!$A:$A,AB$1,'Wells Fargo'!$B:$B,"<="&'Cash Flow'!AB$3,'Wells Fargo'!$B:$B,">"&'Cash Flow'!AA$3) -> 0 | AC7: =SUMIFS('Wells Fargo'!$F:$F,'Wells Fargo'!$G:$G,'Cash Flow'!$A7,'Wells Fargo'!$A:$A,AC$1,'Wells Fargo'!$B:$B,"<="&'Cash Flow'!AC$3,'Wells Fargo'!$B:$B,">"&'Cash Flow'!AB$3) -> 0 | AD7: =SUMIFS('Wells Fargo'!$F:$F,'Wells Fargo'!$G:$G,'Cash Flow'!$A7,'Wells Fargo'!$A:$A,AD$1,'Wells Fargo'!$B:$B,"<="&'Cash Flow'!AD$3,'Wells Fargo'!$B:$B,">"&'Cash Flow'!AC$3) -> 0 | AE7: =SUMIFS('Wells Fargo'!$F:$F,'Wells Fargo'!$G:$G,'Cash Flow'!$A7,'Wells Fargo'!$A:$A,AE$1,'Wells Fargo'!$B:$B,"<="&'Cash Flow'!AE$3,'Wells Fargo'!$B:$B,">"&'Cash Flow'!AD$3) -> 0 | AF7: =SUMIFS('Wells Fargo'!$F:$F,'Wells Fargo'!$G:$G,'Cash Flow'!$A7,'Wells Fargo'!$A:$A,AF$1,'Wells Fargo'!$B:$B,"<="&'Cash Flow'!AF$3) -> 0 | AG7: =SUMIFS('Wells Fargo'!$F:$F,'Wells Fargo'!$G:$G,'Cash Flow'!$A7,'Wells Fargo'!$A:$A,AG$1,'Wells Fargo'!$B:$B,"<="&'Cash Flow'!AG$3,'Wells Fargo'!$B:$B,">"&'Cash Flow'!AF$3) -> 0 | AH7: =SUMIFS('Wells Fargo'!$F:$F,'Wells Fargo'!$G:$G,'Cash Flow'!$A7,'Wells Fargo'!$A:$A,AH$1,'Wells Fargo'!$B:$B,"<="&'Cash Flow'!AH$3,'Wells Fargo'!$B:$B,">"&'Cash Flow'!AG$3) -> 0 | AI7: =SUMIFS('Wells Fargo'!$F:$F,'Wells Fargo'!$G:$G,'Cash Flow'!$A7,'Wells Fargo'!$A:$A,AI$1,'Wells Fargo'!$B:$B,"<="&'Cash Flow'!AI$3,'Wells Fargo'!$B:$B,">"&'Cash Flow'!AH$3) -> 0 | AJ7: =SUMIFS('Wells Fargo'!$F:$F,'Wells Fargo'!$G:$G,'Cash Flow'!$A7,'Wells Fargo'!$A:$A,AJ$1,'Wells Fargo'!$B:$B,"<="&'Cash Flow'!AJ$3,'Wells Fargo'!$B:$B,">"&'Cash Flow'!AI$3) -> 0 | AK7: =SUMIFS('Wells Fargo'!$F:$F,'Wells Fargo'!$G:$G,'Cash Flow'!$A7,'Wells Fargo'!$A:$A,AK$1,'Wells Fargo'!$B:$B,"<="&'Cash Flow'!AK$3) -> 0 | AL7: =SUMIFS('Wells Fargo'!$F:$F,'Wells Fargo'!$G:$G,'Cash Flow'!$A7,'Wells Fargo'!$A:$A,AL$1,'Wells Fargo'!$B:$B,"<="&'Cash Flow'!AL$3,'Wells Fargo'!$B:$B,">"&'Cash Flow'!AK$3) -> 0 | AM7: =SUMIFS('Wells Fargo'!$F:$F,'Wells Fargo'!$G:$G,'Cash Flow'!$A7,'Wells Fargo'!$A:$A,AM$1,'Wells Fargo'!$B:$B,"<="&'Cash Flow'!AM$3,'Wells Fargo'!$B:$B,">"&'Cash Flow'!AL$3) -> 0 | AN7: =SUMIFS('Wells Fargo'!$F:$F,'Wells Fargo'!$G:$G,'Cash Flow'!$A7,'Wells Fargo'!$A:$A,AN$1,'Wells Fargo'!$B:$B,"<="&'Cash Flow'!AN$3,'Wells Fargo'!$B:$B,">"&'Cash Flow'!AM$3) -> 0 | AO7: =SUMIFS('Wells Fargo'!$F:$F,'Wells Fargo'!$G:$G,'Cash Flow'!$A7,'Wells Fargo'!$A:$A,AO$1,'Wells Fargo'!$B:$B,"<="&'Cash Flow'!AO$3,'Wells Fargo'!$B:$B,">"&'Cash Flow'!AN$3) -> 0 | AP7: =SUMIFS('Wells Fargo'!$F:$F,'Wells Fargo'!$G:$G,'Cash Flow'!$A7,'Wells Fargo'!$A:$A,AP$1,'Wells Fargo'!$B:$B,"<="&'Cash Flow'!AP$3) -> 0 | AQ7: =SUMIFS('Wells Fargo'!$F:$F,'Wells Fargo'!$G:$G,'Cash Flow'!$A7,'Wells Fargo'!$A:$A,AQ$1,'Wells Fargo'!$B:$B,"<="&'Cash Flow'!AQ$3,'Wells Fargo'!$B:$B,">"&'Cash Flow'!AP$3) -> 0 | AR7: =SUMIFS('Wells Fargo'!$F:$F,'Wells Fargo'!$G:$G,'Cash Flow'!$A7,'Wells Fargo'!$A:$A,AR$1,'Wells Fargo'!$B:$B,"<="&'Cash Flow'!AR$3,'Wells Fargo'!$B:$B,">"&'Cash Flow'!AQ$3) -> 0 | AS7: =SUMIFS('Wells Fargo'!$F:$F,'Wells Fargo'!$G:$G,'Cash Flow'!$A7,'Wells Fargo'!$A:$A,AS$1,'Wells Fargo'!$B:$B,"<="&'Cash Flow'!AS$3,'Wells Fargo'!$B:$B,">"&'Cash Flow'!AR$3) -> 0 | AT7: =SUMIFS('Wells Fargo'!$F:$F,'Wells Fargo'!$G:$G,'Cash Flow'!$A7,'Wells Fargo'!$A:$A,AT$1,'Wells Fargo'!$B:$B,"<="&'Cash Flow'!AT$3,'Wells Fargo'!$B:$B,">"&'Cash Flow'!AS$3) -> 0 | AU7: =SUMIFS('Wells Fargo'!$F:$F,'Wells Fargo'!$G:$G,'Cash Flow'!$A7,'Wells Fargo'!$A:$A,AU$1,'Wells Fargo'!$B:$B,"<="&'Cash Flow'!AU$3) -> 0 | AV7: =SUMIFS('Wells Fargo'!$F:$F,'Wells Fargo'!$G:$G,'Cash Flow'!$A7,'Wells Fargo'!$A:$A,AV$1,'Wells Fargo'!$B:$B,"<="&'Cash Flow'!AV$3,'Wells Fargo'!$B:$B,">"&'Cash Flow'!AU$3) -> 0 | AW7: =SUMIFS('Wells Fargo'!$F:$F,'Wells Fargo'!$G:$G,'Cash Flow'!$A7,'Wells Fargo'!$A:$A,AW$1,'Wells Fargo'!$B:$B,"<="&'Cash Flow'!AW$3,'Wells Fargo'!$B:$B,">"&'Cash Flow'!AV$3) -> 0 | AX7: =SUMIFS('Wells Fargo'!$F:$F,'Wells Fargo'!$G:$G,'Cash Flow'!$A7,'Wells Fargo'!$A:$A,AX$1,'Wells Fargo'!$B:$B,"<="&'Cash Flow'!AX$3,'Wells Fargo'!$B:$B,">"&'Cash Flow'!AW$3) -> 0 | AY7: =SUMIFS('Wells Fargo'!$F:$F,'Wells Fargo'!$G:$G,'Cash Flow'!$A7,'Wells Fargo'!$A:$A,AY$1,'Wells Fargo'!$B:$B,"<="&'Cash Flow'!AY$3,'Wells Fargo'!$B:$B,">"&'Cash Flow'!AX$3) -> 0 | AZ7: =SUMIFS('Wells Fargo'!$F:$F,'Wells Fargo'!$G:$G,'Cash Flow'!$A7,'Wells Fargo'!$A:$A,AZ$1,'Wells Fargo'!$B:$B,"<="&'Cash Flow'!AZ$3) -> 0 | BA7: =SUMIFS('Wells Fargo'!$F:$F,'Wells Fargo'!$G:$G,'Cash Flow'!$A7,'Wells Fargo'!$A:$A,BA$1,'Wells Fargo'!$B:$B,"<="&'Cash Flow'!BA$3,'Wells Fargo'!$B:$B,">"&'Cash Flow'!AZ$3) -> 0 | BB7: =SUMIFS('Wells Fargo'!$F:$F,'Wells Fargo'!$G:$G,'Cash Flow'!$A7,'Wells Fargo'!$A:$A,BB$1,'Wells Fargo'!$B:$B,"<="&'Cash Flow'!BB$3,'Wells Fargo'!$B:$B,">"&'Cash Flow'!BA$3) -> 0 | BC7: =SUMIFS('Wells Fargo'!$F:$F,'Wells Fargo'!$G:$G,'Cash Flow'!$A7,'Wells Fargo'!$A:$A,BC$1,'Wells Fargo'!$B:$B,"<="&'Cash Flow'!BC$3,'Wells Fargo'!$B:$B,">"&'Cash Flow'!BB$3) -> 0 | BD7: =SUMIFS('Wells Fargo'!$F:$F,'Wells Fargo'!$G:$G,'Cash Flow'!$A7,'Wells Fargo'!$A:$A,BD$1,'Wells Fargo'!$B:$B,"<="&'Cash Flow'!BD$3,'Wells Fargo'!$B:$B,">"&'Cash Flow'!BC$3) -> 0 | BE7: =SUMIFS('Wells Fargo'!$F:$F,'Wells Fargo'!$G:$G,'Cash Flow'!$A7,'Wells Fargo'!$A:$A,BE$1,'Wells Fargo'!$B:$B,"<="&'Cash Flow'!BE$3) -> 0 | BF7: =SUMIFS('Wells Fargo'!$F:$F,'Wells Fargo'!$G:$G,'Cash Flow'!$A7,'Wells Fargo'!$A:$A,BF$1,'Wells Fargo'!$B:$B,"<="&'Cash Flow'!BF$3,'Wells Fargo'!$B:$B,">"&'Cash Flow'!BE$3) -> 0 | BG7: =SUMIFS('Wells Fargo'!$F:$F,'Wells Fargo'!$G:$G,'Cash Flow'!$A7,'Wells Fargo'!$A:$A,BG$1,'Wells Fargo'!$B:$B,"<="&'Cash Flow'!BG$3,'Wells Fargo'!$B:$B,">"&'Cash Flow'!BF$3) -> 0 | BH7: =SUMIFS('Wells Fargo'!$F:$F,'Wells Fargo'!$G:$G,'Cash Flow'!$A7,'Wells Fargo'!$A:$A,BH$1,'Wells Fargo'!$B:$B,"<="&'Cash Flow'!BH$3,'Wells Fargo'!$B:$B,">"&'Cash Flow'!BG$3) -> 0 | BI7: =SUMIFS('Wells Fargo'!$F:$F,'Wells Fargo'!$G:$G,'Cash Flow'!$A7,'Wells Fargo'!$A:$A,BI$1,'Wells Fargo'!$B:$B,"<="&'Cash Flow'!BI$3,'Wells Fargo'!$B:$B,">"&'Cash Flow'!BH$3) -> 0
A8: Amar - Rent | B8: =SUM(C8:BI8) -> -2800 | C8: =SUMIFS('Wells Fargo'!$F:$F,'Wells Fargo'!$G:$G,'Cash Flow'!$A8,'Wells Fargo'!$A:$A,C$1,'Wells Fargo'!$B:$B,"<="&'Cash Flow'!C$3) -> 0 | D8: =SUMIFS('Wells Fargo'!$F:$F,'Wells Fargo'!$G:$G,'Cash Flow'!$A8,'Wells Fargo'!$A:$A,D$1,'Wells Fargo'!$B:$B,"<="&'Cash Flow'!D$3,'Wells Fargo'!$B:$B,">"&'Cash Flow'!C$3) -> 0 | E8: =SUMIFS('Wells Fargo'!$F:$F,'Wells Fargo'!$G:$G,'Cash Flow'!$A8,'Wells Fargo'!$A:$A,E$1,'Wells Fargo'!$B:$B,"<="&'Cash Flow'!E$3,'Wells Fargo'!$B:$B,">"&'Cash Flow'!D$3) -> 0 | F8: =SUMIFS('Wells Fargo'!$F:$F,'Wells Fargo'!$G:$G,'Cash Flow'!$A8,'Wells Fargo'!$A:$A,F$1,'Wells Fargo'!$B:$B,"<="&'Cash Flow'!F$3,'Wells Fargo'!$B:$B,">"&'Cash Flow'!E$3) -> 0 | G8: =SUMIFS('Wells Fargo'!$F:$F,'Wells Fargo'!$G:$G,'Cash Flow'!$A8,'Wells Fargo'!$A:$A,G$1,'Wells Fargo'!$B:$B,"<="&'Cash Flow'!G$3,'Wells Fargo'!$B:$B,">"&'Cash Flow'!F$3) -> -700 | H8: =SUMIFS('Wells Fargo'!$F:$F,'Wells Fargo'!$G:$G,'Cash Flow'!$A8,'Wells Fargo'!$A:$A,H$1,'Wells Fargo'!$B:$B,"<="&'Cash Flow'!H$3) -> 0 | I8: =SUMIFS('Wells Fargo'!$F:$F,'Wells Fargo'!$G:$G,'Cash Flow'!$A8,'Wells Fargo'!$A:$A,I$1,'Wells Fargo'!$B:$B,"<="&'Cash Flow'!I$3,'Wells Fargo'!$B:$B,">"&'Cash Flow'!H$3) -> 0 | J8: =SUMIFS('Wells Fargo'!$F:$F,'Wells Fargo'!$G:$G,'Cash Flow'!$A8,'Wells Fargo'!$A:$A,J$1,'Wells Fargo'!$B:$B,"<="&'Cash Flow'!J$3,'Wells Fargo'!$B:$B,">"&'Cash Flow'!I$3) -> 0 | K8: =SUMIFS('Wells Fargo'!$F:$F,'Wells Fargo'!$G:$G,'Cash Flow'!$A8,'Wells Fargo'!$A:$A,K$1,'Wells Fargo'!$B:$B,"<="&'Cash Flow'!K$3,'Wells Fargo'!$B:$B,">"&'Cash Flow'!J$3) -> -700 | L8: =SUMIFS('Wells Fargo'!$F:$F,'Wells Fargo'!$G:$G,'Cash Flow'!$A8,'Wells Fargo'!$A:$A,L$1,'Wells Fargo'!$B:$B,"<="&'Cash Flow'!L$3) -> 0 | M8: =SUMIFS('Wells Fargo'!$F:$F,'Wells Fargo'!$G:$G,'Cash Flow'!$A8,'Wells Fargo'!$A:$A,M$1,'Wells Fargo'!$B:$B,"<="&'Cash Flow'!M$3,'Wells Fargo'!$B:$B,">"&'Cash Flow'!L$3) -> 0 | N8: =SUMIFS('Wells Fargo'!$F:$F,'Wells Fargo'!$G:$G,'Cash Flow'!$A8,'Wells Fargo'!$A:$A,N$1,'Wells Fargo'!$B:$B,"<="&'Cash Flow'!N$3,'Wells Fargo'!$B:$B,">"&'Cash Flow'!M$3) -> -700 | O8: =SUMIFS('Wells Fargo'!$F:$F,'Wells Fargo'!$G:$G,'Cash Flow'!$A8,'Wells Fargo'!$A:$A,O$1,'Wells Fargo'!$B:$B,"<="&'Cash Flow'!O$3,'Wells Fargo'!$B:$B,">"&'Cash Flow'!N$3) -> 0 | P8: =SUMIFS('Wells Fargo'!$F:$F,'Wells Fargo'!$G:$G,'Cash Flow'!$A8,'Wells Fargo'!$A:$A,P$1,'Wells Fargo'!$B:$B,"<="&'Cash Flow'!P$3,'Wells Fargo'!$B:$B,">"&'Cash Flow'!O$3) -> 0 | Q8: =SUMIFS('Wells Fargo'!$F:$F,'Wells Fargo'!$G:$G,'Cash Flow'!$A8,'Wells Fargo'!$A:$A,Q$1,'Wells Fargo'!$B:$B,"<="&'Cash Flow'!Q$3) -> 0 | R8: =SUMIFS('Wells Fargo'!$F:$F,'Wells Fargo'!$G:$G,'Cash Flow'!$A8,'Wells Fargo'!$A:$A,R$1,'Wells Fargo'!$B:$B,"<="&'Cash Flow'!R$3,'Wells Fargo'!$B:$B,">"&'Cash Flow'!Q$3) -> 0 | S8: =SUMIFS('Wells Fargo'!$F:$F,'Wells Fargo'!$G:$G,'Cash Flow'!$A8,'Wells Fargo'!$A:$A,S$1,'Wells Fargo'!$B:$B,"<="&'Cash Flow'!S$3,'Wells Fargo'!$B:$B,">"&'Cash Flow'!R$3) -> 0 | T8: =SUMIFS('Wells Fargo'!$F:$F,'Wells Fargo'!$G:$G,'Cash Flow'!$A8,'Wells Fargo'!$A:$A,T$1,'Wells Fargo'!$B:$B,"<="&'Cash Flow'!T$3,'Wells Fargo'!$B:$B,">"&'Cash Flow'!S$3) -> -700 | U8: =SUMIFS('Wells Fargo'!$F:$F,'Wells Fargo'!$G:$G,'Cash Flow'!$A8,'Wells Fargo'!$A:$A,U$1,'Wells Fargo'!$B:$B,"<="&'Cash Flow'!U$3,'Wells Fargo'!$B:$B,">"&'Cash Flow'!T$3) -> 0 | V8: =SUMIFS('Wells Fargo'!$F:$F,'Wells Fargo'!$G:$G,'Cash Flow'!$A8,'Wells Fargo'!$A:$A,V$1,'Wells Fargo'!$B:$B,"<="&'Cash Flow'!V$3) -> 0 | W8: =SUMIFS('Wells Fargo'!$F:$F,'Wells Fargo'!$G:$G,'Cash Flow'!$A8,'Wells Fargo'!$A:$A,W$1,'Wells Fargo'!$B:$B,"<="&'Cash Flow'!W$3,'Wells Fargo'!$B:$B,">"&'Cash Flow'!V$3) -> 0 | X8: =SUMIFS('Wells Fargo'!$F:$F,'Wells Fargo'!$G:$G,'Cash Flow'!$A8,'Wells Fargo'!$A:$A,X$1,'Wells Fargo'!$B:$B,"<="&'Cash Flow'!X$3,'Wells Fargo'!$B:$B,">"&'Cash Flow'!W$3) -> 0 | Y8: =SUMIFS('Wells Fargo'!$F:$F,'Wells Fargo'!$G:$G,'Cash Flow'!$A8,'Wells Fargo'!$A:$A,Y$1,'Wells Fargo'!$B:$B,"<="&'Cash Flow'!Y$3,'Wells Fargo'!$B:$B,">"&'Cash Flow'!X$3) -> 0 | Z8: =SUMIFS('Wells Fargo'!$F:$F,'Wells Fargo'!$G:$G,'Cash Flow'!$A8,'Wells Fargo'!$A:$A,Z$1,'Wells Fargo'!$B:$B,"<="&'Cash Flow'!Z$3,'Wells Fargo'!$B:$B,">"&'Cash Flow'!Y$3) -> 0 | AA8: =SUMIFS('Wells Fargo'!$F:$F,'Wells Fargo'!$G:$G,'Cash Flow'!$A8,'Wells Fargo'!$A:$A,AA$1,'Wells Fargo'!$B:$B,"<="&'Cash Flow'!AA$3) -> 0 | AB8: =SUMIFS('Wells Fargo'!$F:$F,'Wells Fargo'!$G:$G,'Cash Flow'!$A8,'Wells Fargo'!$A:$A,AB$1,'Wells Fargo'!$B:$B,"<="&'Cash Flow'!AB$3,'Wells Fargo'!$B:$B,">"&'Cash Flow'!AA$3) -> 0 | AC8: =SUMIFS('Wells Fargo'!$F:$F,'Wells Fargo'!$G:$G,'Cash Flow'!$A8,'Wells Fargo'!$A:$A,AC$1,'Wells Fargo'!$B:$B,"<="&'Cash Flow'!AC$3,'Wells Fargo'!$B:$B,">"&'Cash Flow'!AB$3) -> 0 | AD8: =SUMIFS('Wells Fargo'!$F:$F,'Wells Fargo'!$G:$G,'Cash Flow'!$A8,'Wells Fargo'!$A:$A,AD$1,'Wells Fargo'!$B:$B,"<="&'Cash Flow'!AD$3,'Wells Fargo'!$B:$B,">"&'Cash Flow'!AC$3) -> 0 | AE8: =SUMIFS('Wells Fargo'!$F:$F,'Wells Fargo'!$G:$G,'Cash Flow'!$A8,'Wells Fargo'!$A:$A,AE$1,'Wells Fargo'!$B:$B,"<="&'Cash Flow'!AE$3,'Wells Fargo'!$B:$B,">"&'Cash Flow'!AD$3) -> 0 | AF8: =SUMIFS('Wells Fargo'!$F:$F,'Wells Fargo'!$G:$G,'Cash Flow'!$A8,'Wells Fargo'!$A:$A,AF$1,'Wells Fargo'!$B:$B,"<="&'Cash Flow'!AF$3) -> 0 | AG8: =SUMIFS('Wells Fargo'!$F:$F,'Wells Fargo'!$G:$G,'Cash Flow'!$A8,'Wells Fargo'!$A:$A,AG$1,'Wells Fargo'!$B:$B,"<="&'Cash Flow'!AG$3,'Wells Fargo'!$B:$B,">"&'Cash Flow'!AF$3) -> 0 | AH8: =SUMIFS('Wells Fargo'!$F:$F,'Wells Fargo'!$G:$G,'Cash Flow'!$A8,'Wells Fargo'!$A:$A,AH$1,'Wells Fargo'!$B:$B,"<="&'Cash Flow'!AH$3,'Wells Fargo'!$B:$B,">"&'Cash Flow'!AG$3) -> 0 | AI8: =SUMIFS('Wells Fargo'!$F:$F,'Wells Fargo'!$G:$G,'Cash Flow'!$A8,'Wells Fargo'!$A:$A,AI$1,'Wells Fargo'!$B:$B,"<="&'Cash Flow'!AI$3,'Wells Fargo'!$B:$B,">"&'Cash Flow'!AH$3) -> 0 | AJ8: =SUMIFS('Wells Fargo'!$F:$F,'Wells Fargo'!$G:$G,'Cash Flow'!$A8,'Wells Fargo'!$A:$A,AJ$1,'Wells Fargo'!$B:$B,"<="&'Cash Flow'!AJ$3,'Wells Fargo'!$B:$B,">"&'Cash Flow'!AI$3) -> 0 | AK8: =SUMIFS('Wells Fargo'!$F:$F,'Wells Fargo'!$G:$G,'Cash Flow'!$A8,'Wells Fargo'!$A:$A,AK$1,'Wells Fargo'!$B:$B,"<="&'Cash Flow'!AK$3) -> 0 | AL8: =SUMIFS('Wells Fargo'!$F:$F,'Wells Fargo'!$G:$G,'Cash Flow'!$A8,'Wells Fargo'!$A:$A,AL$1,'Wells Fargo'!$B:$B,"<="&'Cash Flow'!AL$3,'Wells Fargo'!$B:$B,">"&'Cash Flow'!AK$3) -> 0 | AM8: =SUMIFS('Wells Fargo'!$F:$F,'Wells Fargo'!$G:$G,'Cash Flow'!$A8,'Wells Fargo'!$A:$A,AM$1,'Wells Fargo'!$B:$B,"<="&'Cash Flow'!AM$3,'Wells Fargo'!$B:$B,">"&'Cash Flow'!AL$3) -> 0 | AN8: =SUMIFS('Wells Fargo'!$F:$F,'Wells Fargo'!$G:$G,'Cash Flow'!$A8,'Wells Fargo'!$A:$A,AN$1,'Wells Fargo'!$B:$B,"<="&'Cash Flow'!AN$3,'Wells Fargo'!$B:$B,">"&'Cash Flow'!AM$3) -> 0 | AO8: =SUMIFS('Wells Fargo'!$F:$F,'Wells Fargo'!$G:$G,'Cash Flow'!$A8,'Wells Fargo'!$A:$A,AO$1,'Wells Fargo'!$B:$B,"<="&'Cash Flow'!AO$3,'Wells Fargo'!$B:$B,">"&'Cash Flow'!AN$3) -> 0 | AP8: =SUMIFS('Wells Fargo'!$F:$F,'Wells Fargo'!$G:$G,'Cash Flow'!$A8,'Wells Fargo'!$A:$A,AP$1,'Wells Fargo'!$B:$B,"<="&'Cash Flow'!AP$3) -> 0 | AQ8: =SUMIFS('Wells Fargo'!$F:$F,'Wells Fargo'!$G:$G,'Cash Flow'!$A8,'Wells Fargo'!$A:$A,AQ$1,'Wells Fargo'!$B:$B,"<="&'Cash Flow'!AQ$3,'Wells Fargo'!$B:$B,">"&'Cash Flow'!AP$3) -> 0 | AR8: =SUMIFS('Wells Fargo'!$F:$F,'Wells Fargo'!$G:$G,'Cash Flow'!$A8,'Wells Fargo'!$A:$A,AR$1,'Wells Fargo'!$B:$B,"<="&'Cash Flow'!AR$3,'Wells Fargo'!$B:$B,">"&'Cash Flow'!AQ$3) -> 0 | AS8: =SUMIFS('Wells Fargo'!$F:$F,'Wells Fargo'!$G:$G,'Cash Flow'!$A8,'Wells Fargo'!$A:$A,AS$1,'Wells Fargo'!$B:$B,"<="&'Cash Flow'!AS$3,'Wells Fargo'!$B:$B,">"&'Cash Flow'!AR$3) -> 0 | AT8: =SUMIFS('Wells Fargo'!$F:$F,'Wells Fargo'!$G:$G,'Cash Flow'!$A8,'Wells Fargo'!$A:$A,AT$1,'Wells Fargo'!$B:$B,"<="&'Cash Flow'!AT$3,'Wells Fargo'!$B:$B,">"&'Cash Flow'!AS$3) -> 0 | AU8: =SUMIFS('Wells Fargo'!$F:$F,'Wells Fargo'!$G:$G,'Cash Flow'!$A8,'Wells Fargo'!$A:$A,AU$1,'Wells Fargo'!$B:$B,"<="&'Cash Flow'!AU$3) -> 0 | AV8: =SUMIFS('Wells Fargo'!$F:$F,'Wells Fargo'!$G:$G,'Cash Flow'!$A8,'Wells Fargo'!$A:$A,AV$1,'Wells Fargo'!$B:$B,"<="&'Cash Flow'!AV$3,'Wells Fargo'!$B:$B,">"&'Cash Flow'!AU$3) -> 0 | AW8: =SUMIFS('Wells Fargo'!$F:$F,'Wells Fargo'!$G:$G,'Cash Flow'!$A8,'Wells Fargo'!$A:$A,AW$1,'Wells Fargo'!$B:$B,"<="&'Cash Flow'!AW$3,'Wells Fargo'!$B:$B,">"&'Cash Flow'!AV$3) -> 0 | AX8: =SUMIFS('Wells Fargo'!$F:$F,'Wells Fargo'!$G:$G,'Cash Flow'!$A8,'Wells Fargo'!$A:$A,AX$1,'Wells Fargo'!$B:$B,"<="&'Cash Flow'!AX$3,'Wells Fargo'!$B:$B,">"&'Cash Flow'!AW$3) -> 0 | AY8: =SUMIFS('Wells Fargo'!$F:$F,'Wells Fargo'!$G:$G,'Cash Flow'!$A8,'Wells Fargo'!$A:$A,AY$1,'Wells Fargo'!$B:$B,"<="&'Cash Flow'!AY$3,'Wells Fargo'!$B:$B,">"&'Cash Flow'!AX$3) -> 0 | AZ8: =SUMIFS('Wells Fargo'!$F:$F,'Wells Fargo'!$G:$G,'Cash Flow'!$A8,'Wells Fargo'!$A:$A,AZ$1,'Wells Fargo'!$B:$B,"<="&'Cash Flow'!AZ$3) -> 0 | BA8: =SUMIFS('Wells Fargo'!$F:$F,'Wells Fargo'!$G:$G,'Cash Flow'!$A8,'Wells Fargo'!$A:$A,BA$1,'Wells Fargo'!$B:$B,"<="&'Cash Flow'!BA$3,'Wells Fargo'!$B:$B,">"&'Cash Flow'!AZ$3) -> 0 | BB8: =SUMIFS('Wells Fargo'!$F:$F,'Wells Fargo'!$G:$G,'Cash Flow'!$A8,'Wells Fargo'!$A:$A,BB$1,'Wells Fargo'!$B:$B,"<="&'Cash Flow'!BB$3,'Wells Fargo'!$B:$B,">"&'Cash Flow'!BA$3) -> 0 | BC8: =SUMIFS('Wells Fargo'!$F:$F,'Wells Fargo'!$G:$G,'Cash Flow'!$A8,'Wells Fargo'!$A:$A,BC$1,'Wells Fargo'!$B:$B,"<="&'Cash Flow'!BC$3,'Wells Fargo'!$B:$B,">"&'Cash Flow'!BB$3) -> 0 | BD8: =SUMIFS('Wells Fargo'!$F:$F,'Wells Fargo'!$G:$G,'Cash Flow'!$A8,'Wells Fargo'!$A:$A,BD$1,'Wells Fargo'!$B:$B,"<="&'Cash Flow'!BD$3,'Wells Fargo'!$B:$B,">"&'Cash Flow'!BC$3) -> 0 | BE8: =SUMIFS('Wells Fargo'!$F:$F,'Wells Fargo'!$G:$G,'Cash Flow'!$A8,'Wells Fargo'!$A:$A,BE$1,'Wells Fargo'!$B:$B,"<="&'Cash Flow'!BE$3) -> 0 | BF8: =SUMIFS('Wells Fargo'!$F:$F,'Wells Fargo'!$G:$G,'Cash Flow'!$A8,'Wells Fargo'!$A:$A,BF$1,'Wells Fargo'!$B:$B,"<="&'Cash Flow'!BF$3,'Wells Fargo'!$B:$B,">"&'Cash Flow'!BE$3) -> 0 | BG8: =SUMIFS('Wells Fargo'!$F:$F,'Wells Fargo'!$G:$G,'Cash Flow'!$A8,'Wells Fargo'!$A:$A,BG$1,'Wells Fargo'!$B:$B,"<="&'Cash Flow'!BG$3,'Wells Fargo'!$B:$B,">"&'Cash Flow'!BF$3) -> 0 | BH8: =SUMIFS('Wells Fargo'!$F:$F,'Wells Fargo'!$G:$G,'Cash Flow'!$A8,'Wells Fargo'!$A:$A,BH$1,'Wells Fargo'!$B:$B,"<="&'Cash Flow'!BH$3,'Wells Fargo'!$B:$B,">"&'Cash Flow'!BG$3) -> 0 | BI8: =SUMIFS('Wells Fargo'!$F:$F,'Wells Fargo'!$G:$G,'Cash Flow'!$A8,'Wells Fargo'!$A:$A,BI$1,'Wells Fargo'!$B:$B,"<="&'Cash Flow'!BI$3,'Wells Fargo'!$B:$B,">"&'Cash Flow'!BH$3) -> 0
A9: Amar - Water | B9: =SUM(C9:BI9) -> -400 | C9: =SUMIFS('Wells Fargo'!$F:$F,'Wells Fargo'!$G:$G,'Cash Flow'!$A9,'Wells Fargo'!$A:$A,C$1,'Wells Fargo'!$B:$B,"<="&'Cash Flow'!C$3) -> 0 | D9: =SUMIFS('Wells Fargo'!$F:$F,'Wells Fargo'!$G:$G,'Cash Flow'!$A9,'Wells Fargo'!$A:$A,D$1,'Wells Fargo'!$B:$B,"<="&'Cash Flow'!D$3,'Wells Fargo'!$B:$B,">"&'Cash Flow'!C$3) -> 0 | E9: =SUMIFS('Wells Fargo'!$F:$F,'Wells Fargo'!$G:$G,'Cash Flow'!$A9,'Wells Fargo'!$A:$A,E$1,'Wells Fargo'!$B:$B,"<="&'Cash Flow'!E$3,'Wells Fargo'!$B:$B,">"&'Cash Flow'!D$3) -> 0 | F9: =SUMIFS('Wells Fargo'!$F:$F,'Wells Fargo'!$G:$G,'Cash Flow'!$A9,'Wells Fargo'!$A:$A,F$1,'Wells Fargo'!$B:$B,"<="&'Cash Flow'!F$3,'Wells Fargo'!$B:$B,">"&'Cash Flow'!E$3) -> 0 | G9: =SUMIFS('Wells Fargo'!$F:$F,'Wells Fargo'!$G:$G,'Cash Flow'!$A9,'Wells Fargo'!$A:$A,G$1,'Wells Fargo'!$B:$B,"<="&'Cash Flow'!G$3,'Wells Fargo'!$B:$B,">"&'Cash Flow'!F$3) -> 0 | H9: =SUMIFS('Wells Fargo'!$F:$F,'Wells Fargo'!$G:$G,'Cash Flow'!$A9,'Wells Fargo'!$A:$A,H$1,'Wells Fargo'!$B:$B,"<="&'Cash Flow'!H$3) -> 0 | I9: =SUMIFS('Wells Fargo'!$F:$F,'Wells Fargo'!$G:$G,'Cash Flow'!$A9,'Wells Fargo'!$A:$A,I$1,'Wells Fargo'!$B:$B,"<="&'Cash Flow'!I$3,'Wells Fargo'!$B:$B,">"&'Cash Flow'!H$3) -> 0 | J9: =SUMIFS('Wells Fargo'!$F:$F,'Wells Fargo'!$G:$G,'Cash Flow'!$A9,'Wells Fargo'!$A:$A,J$1,'Wells Fargo'!$B:$B,"<="&'Cash Flow'!J$3,'Wells Fargo'!$B:$B,">"&'Cash Flow'!I$3) -> 0 | K9: =SUMIFS('Wells Fargo'!$F:$F,'Wells Fargo'!$G:$G,'Cash Flow'!$A9,'Wells Fargo'!$A:$A,K$1,'Wells Fargo'!$B:$B,"<="&'Cash Flow'!K$3,'Wells Fargo'!$B:$B,">"&'Cash Flow'!J$3) -> 0 | L9: =SUMIFS('Wells Fargo'!$F:$F,'Wells Fargo'!$G:$G,'Cash Flow'!$A9,'Wells Fargo'!$A:$A,L$1,'Wells Fargo'!$B:$B,"<="&'Cash Flow'!L$3) -> 0 | M9: =SUMIFS('Wells Fargo'!$F:$F,'Wells Fargo'!$G:$G,'Cash Flow'!$A9,'Wells Fargo'!$A:$A,M$1,'Wells Fargo'!$B:$B,"<="&'Cash Flow'!M$3,'Wells Fargo'!$B:$B,">"&'Cash Flow'!L$3) -> -150 | N9: =SUMIFS('Wells Fargo'!$F:$F,'Wells Fargo'!$G:$G,'Cash Flow'!$A9,'Wells Fargo'!$A:$A,N$1,'Wells Fargo'!$B:$B,"<="&'Cash Flow'!N$3,'Wells Fargo'!$B:$B,">"&'Cash Flow'!M$3) -> 0 | O9: =SUMIFS('Wells Fargo'!$F:$F,'Wells Fargo'!$G:$G,'Cash Flow'!$A9,'Wells Fargo'!$A:$A,O$1,'Wells Fargo'!$B:$B,"<="&'Cash Flow'!O$3,'Wells Fargo'!$B:$B,">"&'Cash Flow'!N$3) -> 0 | P9: =SUMIFS('Wells Fargo'!$F:$F,'Wells Fargo'!$G:$G,'Cash Flow'!$A9,'Wells Fargo'!$A:$A,P$1,'Wells Fargo'!$B:$B,"<="&'Cash Flow'!P$3,'Wells Fargo'!$B:$B,">"&'Cash Flow'!O$3) -> 0 | Q9: =SUMIFS('Wells Fargo'!$F:$F,'Wells Fargo'!$G:$G,'Cash Flow'!$A9,'Wells Fargo'!$A:$A,Q$1,'Wells Fargo'!$B:$B,"<="&'Cash Flow'!Q$3) -> 0 | R9: =SUMIFS('Wells Fargo'!$F:$F,'Wells Fargo'!$G:$G,'Cash Flow'!$A9,'Wells Fargo'!$A:$A,R$1,'Wells Fargo'!$B:$B,"<="&'Cash Flow'!R$3,'Wells Fargo'!$B:$B,">"&'Cash Flow'!Q$3) -> 0 | S9: =SUMIFS('Wells Fargo'!$F:$F,'Wells Fargo'!$G:$G,'Cash Flow'!$A9,'Wells Fargo'!$A:$A,S$1,'Wells Fargo'!$B:$B,"<="&'Cash Flow'!S$3,'Wells Fargo'!$B:$B,">"&'Cash Flow'!R$3) -> -100 | T9: =SUMIFS('Wells Fargo'!$F:$F,'Wells Fargo'!$G:$G,'Cash Flow'!$A9,'Wells Fargo'!$A:$A,T$1,'Wells Fargo'!$B:$B,"<="&'Cash Flow'!T$3,'Wells Fargo'!$B:$B,">"&'Cash Flow'!S$3) -> 0 | U9: =SUMIFS('Wells Fargo'!$F:$F,'Wells Fargo'!$G:$G,'Cash Flow'!$A9,'Wells Fargo'!$A:$A,U$1,'Wells Fargo'!$B:$B,"<="&'Cash Flow'!U$3,'Wells Fargo'!$B:$B,">"&'Cash Flow'!T$3) -> 0 | V9: =SUMIFS('Wells Fargo'!$F:$F,'Wells Fargo'!$G:$G,'Cash Flow'!$A9,'Wells Fargo'!$A:$A,V$1,'Wells Fargo'!$B:$B,"<="&'Cash Flow'!V$3) -> 0 | W9: =SUMIFS('Wells Fargo'!$F:$F,'Wells Fargo'!$G:$G,'Cash Flow'!$A9,'Wells Fargo'!$A:$A,W$1,'Wells Fargo'!$B:$B,"<="&'Cash Flow'!W$3,'Wells Fargo'!$B:$B,">"&'Cash Flow'!V$3) -> -150 | X9: =SUMIFS('Wells Fargo'!$F:$F,'Wells Fargo'!$G:$G,'Cash Flow'!$A9,'Wells Fargo'!$A:$A,X$1,'Wells Fargo'!$B:$B,"<="&'Cash Flow'!X$3,'Wells Fargo'!$B:$B,">"&'Cash Flow'!W$3) -> 0 | Y9: =SUMIFS('Wells Fargo'!$F:$F,'Wells Fargo'!$G:$G,'Cash Flow'!$A9,'Wells Fargo'!$A:$A,Y$1,'Wells Fargo'!$B:$B,"<="&'Cash Flow'!Y$3,'Wells Fargo'!$B:$B,">"&'Cash Flow'!X$3) -> 0 | Z9: =SUMIFS('Wells Fargo'!$F:$F,'Wells Fargo'!$G:$G,'Cash Flow'!$A9,'Wells Fargo'!$A:$A,Z$1,'Wells Fargo'!$B:$B,"<="&'Cash Flow'!Z$3,'Wells Fargo'!$B:$B,">"&'Cash Flow'!Y$3) -> 0 | AA9: =SUMIFS('Wells Fargo'!$F:$F,'Wells Fargo'!$G:$G,'Cash Flow'!$A9,'Wells Fargo'!$A:$A,AA$1,'Wells Fargo'!$B:$B,"<="&'Cash Flow'!AA$3) -> 0 | AB9: =SUMIFS('Wells Fargo'!$F:$F,'Wells Fargo'!$G:$G,'Cash Flow'!$A9,'Wells Fargo'!$A:$A,AB$1,'Wells Fargo'!$B:$B,"<="&'Cash Flow'!AB$3,'Wells Fargo'!$B:$B,">"&'Cash Flow'!AA$3) -> 0 | AC9: =SUMIFS('Wells Fargo'!$F:$F,'Wells Fargo'!$G:$G,'Cash Flow'!$A9,'Wells Fargo'!$A:$A,AC$1,'Wells Fargo'!$B:$B,"<="&'Cash Flow'!AC$3,'Wells Fargo'!$B:$B,">"&'Cash Flow'!AB$3) -> 0 | AD9: =SUMIFS('Wells Fargo'!$F:$F,'Wells Fargo'!$G:$G,'Cash Flow'!$A9,'Wells Fargo'!$A:$A,AD$1,'Wells Fargo'!$B:$B,"<="&'Cash Flow'!AD$3,'Wells Fargo'!$B:$B,">"&'Cash Flow'!AC$3) -> 0 | AE9: =SUMIFS('Wells Fargo'!$F:$F,'Wells Fargo'!$G:$G,'Cash Flow'!$A9,'Wells Fargo'!$A:$A,AE$1,'Wells Fargo'!$B:$B,"<="&'Cash Flow'!AE$3,'Wells Fargo'!$B:$B,">"&'Cash Flow'!AD$3) -> 0 | AF9: =SUMIFS('Wells Fargo'!$F:$F,'Wells Fargo'!$G:$G,'Cash Flow'!$A9,'Wells Fargo'!$A:$A,AF$1,'Wells Fargo'!$B:$B,"<="&'Cash Flow'!AF$3) -> 0 | AG9: =SUMIFS('Wells Fargo'!$F:$F,'Wells Fargo'!$G:$G,'Cash Flow'!$A9,'Wells Fargo'!$A:$A,AG$1,'Wells Fargo'!$B:$B,"<="&'Cash Flow'!AG$3,'Wells Fargo'!$B:$B,">"&'Cash Flow'!AF$3) -> 0 | AH9: =SUMIFS('Wells Fargo'!$F:$F,'Wells Fargo'!$G:$G,'Cash Flow'!$A9,'Wells Fargo'!$A:$A,AH$1,'Wells Fargo'!$B:$B,"<="&'Cash Flow'!AH$3,'Wells Fargo'!$B:$B,">"&'Cash Flow'!AG$3) -> 0 | AI9: =SUMIFS('Wells Fargo'!$F:$F,'Wells Fargo'!$G:$G,'Cash Flow'!$A9,'Wells Fargo'!$A:$A,AI$1,'Wells Fargo'!$B:$B,"<="&'Cash Flow'!AI$3,'Wells Fargo'!$B:$B,">"&'Cash Flow'!AH$3) -> 0 | AJ9: =SUMIFS('Wells Fargo'!$F:$F,'Wells Fargo'!$G:$G,'Cash Flow'!$A9,'Wells Fargo'!$A:$A,AJ$1,'Wells Fargo'!$B:$B,"<="&'Cash Flow'!AJ$3,'Wells Fargo'!$B:$B,">"&'Cash Flow'!AI$3) -> 0 | AK9: =SUMIFS('Wells Fargo'!$F:$F,'Wells Fargo'!$G:$G,'Cash Flow'!$A9,'Wells Fargo'!$A:$A,AK$1,'Wells Fargo'!$B:$B,"<="&'Cash Flow'!AK$3) -> 0 | AL9: =SUMIFS('Wells Fargo'!$F:$F,'Wells Fargo'!$G:$G,'Cash Flow'!$A9,'Wells Fargo'!$A:$A,AL$1,'Wells Fargo'!$B:$B,"<="&'Cash Flow'!AL$3,'Wells Fargo'!$B:$B,">"&'Cash Flow'!AK$3) -> 0 | AM9: =SUMIFS('Wells Fargo'!$F:$F,'Wells Fargo'!$G:$G,'Cash Flow'!$A9,'Wells Fargo'!$A:$A,AM$1,'Wells Fargo'!$B:$B,"<="&'Cash Flow'!AM$3,'Wells Fargo'!$B:$B,">"&'Cash Flow'!AL$3) -> 0 | AN9: =SUMIFS('Wells Fargo'!$F:$F,'Wells Fargo'!$G:$G,'Cash Flow'!$A9,'Wells Fargo'!$A:$A,AN$1,'Wells Fargo'!$B:$B,"<="&'Cash Flow'!AN$3,'Wells Fargo'!$B:$B,">"&'Cash Flow'!AM$3) -> 0 | AO9: =SUMIFS('Wells Fargo'!$F:$F,'Wells Fargo'!$G:$G,'Cash Flow'!$A9,'Wells Fargo'!$A:$A,AO$1,'Wells Fargo'!$B:$B,"<="&'Cash Flow'!AO$3,'Wells Fargo'!$B:$B,">"&'Cash Flow'!AN$3) -> 0 | AP9: =SUMIFS('Wells Fargo'!$F:$F,'Wells Fargo'!$G:$G,'Cash Flow'!$A9,'Wells Fargo'!$A:$A,AP$1,'Wells Fargo'!$B:$B,"<="&'Cash Flow'!AP$3) -> 0 | AQ9: =SUMIFS('Wells Fargo'!$F:$F,'Wells Fargo'!$G:$G,'Cash Flow'!$A9,'Wells Fargo'!$A:$A,AQ$1,'Wells Fargo'!$B:$B,"<="&'Cash Flow'!AQ$3,'Wells Fargo'!$B:$B,">"&'Cash Flow'!AP$3) -> 0 | AR9: =SUMIFS('Wells Fargo'!$F:$F,'Wells Fargo'!$G:$G,'Cash Flow'!$A9,'Wells Fargo'!$A:$A,AR$1,'Wells Fargo'!$B:$B,"<="&'Cash Flow'!AR$3,'Wells Fargo'!$B:$B,">"&'Cash Flow'!AQ$3) -> 0 | AS9: =SUMIFS('Wells Fargo'!$F:$F,'Wells Fargo'!$G:$G,'Cash Flow'!$A9,'Wells Fargo'!$A:$A,AS$1,'Wells Fargo'!$B:$B,"<="&'Cash Flow'!AS$3,'Wells Fargo'!$B:$B,">"&'Cash Flow'!AR$3) -> 0 | AT9: =SUMIFS('Wells Fargo'!$F:$F,'Wells Fargo'!$G:$G,'Cash Flow'!$A9,'Wells Fargo'!$A:$A,AT$1,'Wells Fargo'!$B:$B,"<="&'Cash Flow'!AT$3,'Wells Fargo'!$B:$B,">"&'Cash Flow'!AS$3) -> 0 | AU9: =SUMIFS('Wells Fargo'!$F:$F,'Wells Fargo'!$G:$G,'Cash Flow'!$A9,'Wells Fargo'!$A:$A,AU$1,'Wells Fargo'!$B:$B,"<="&'Cash Flow'!AU$3) -> 0 | AV9: =SUMIFS('Wells Fargo'!$F:$F,'Wells Fargo'!$G:$G,'Cash Flow'!$A9,'Wells Fargo'!$A:$A,AV$1,'Wells Fargo'!$B:$B,"<="&'Cash Flow'!AV$3,'Wells Fargo'!$B:$B,">"&'Cash Flow'!AU$3) -> 0 | AW9: =SUMIFS('Wells Fargo'!$F:$F,'Wells Fargo'!$G:$G,'Cash Flow'!$A9,'Wells Fargo'!$A:$A,AW$1,'Wells Fargo'!$B:$B,"<="&'Cash Flow'!AW$3,'Wells Fargo'!$B:$B,">"&'Cash Flow'!AV$3) -> 0 | AX9: =SUMIFS('Wells Fargo'!$F:$F,'Wells Fargo'!$G:$G,'Cash Flow'!$A9,'Wells Fargo'!$A:$A,AX$1,'Wells Fargo'!$B:$B,"<="&'Cash Flow'!AX$3,'Wells Fargo'!$B:$B,">"&'Cash Flow'!AW$3) -> 0 | AY9: =SUMIFS('Wells Fargo'!$F:$F,'Wells Fargo'!$G:$G,'Cash Flow'!$A9,'Wells Fargo'!$A:$A,AY$1,'Wells Fargo'!$B:$B,"<="&'Cash Flow'!AY$3,'Wells Fargo'!$B:$B,">"&'Cash Flow'!AX$3) -> 0 | AZ9: =SUMIFS('Wells Fargo'!$F:$F,'Wells Fargo'!$G:$G,'Cash Flow'!$A9,'Wells Fargo'!$A:$A,AZ$1,'Wells Fargo'!$B:$B,"<="&'Cash Flow'!AZ$3) -> 0 | BA9: =SUMIFS('Wells Fargo'!$F:$F,'Wells Fargo'!$G:$G,'Cash Flow'!$A9,'Wells Fargo'!$A:$A,BA$1,'Wells Fargo'!$B:$B,"<="&'Cash Flow'!BA$3,'Wells Fargo'!$B:$B,">"&'Cash Flow'!AZ$3) -> 0 | BB9: =SUMIFS('Wells Fargo'!$F:$F,'Wells Fargo'!$G:$G,'Cash Flow'!$A9,'Wells Fargo'!$A:$A,BB$1,'Wells Fargo'!$B:$B,"<="&'Cash Flow'!BB$3,'Wells Fargo'!$B:$B,">"&'Cash Flow'!BA$3) -> 0 | BC9: =SUMIFS('Wells Fargo'!$F:$F,'Wells Fargo'!$G:$G,'Cash Flow'!$A9,'Wells Fargo'!$A:$A,BC$1,'Wells Fargo'!$B:$B,"<="&'Cash Flow'!BC$3,'Wells Fargo'!$B:$B,">"&'Cash Flow'!BB$3) -> 0 | BD9: =SUMIFS('Wells Fargo'!$F:$F,'Wells Fargo'!$G:$G,'Cash Flow'!$A9,'Wells Fargo'!$A:$A,BD$1,'Wells Fargo'!$B:$B,"<="&'Cash Flow'!BD$3,'Wells Fargo'!$B:$B,">"&'Cash Flow'!BC$3) -> 0 | BE9: =SUMIFS('Wells Fargo'!$F:$F,'Wells Fargo'!$G:$G,'Cash Flow'!$A9,'Wells Fargo'!$A:$A,BE$1,'Wells Fargo'!$B:$B,"<="&'Cash Flow'!BE$3) -> 0 | BF9: =SUMIFS('Wells Fargo'!$F:$F,'Wells Fargo'!$G:$G,'Cash Flow'!$A9,'Wells Fargo'!$A:$A,BF$1,'Wells Fargo'!$B:$B,"<="&'Cash Flow'!BF$3,'Wells Fargo'!$B:$B,">"&'Cash Flow'!BE$3) -> 0 | BG9: =SUMIFS('Wells Fargo'!$F:$F,'Wells Fargo'!$G:$G,'Cash Flow'!$A9,'Wells Fargo'!$A:$A,BG$1,'Wells Fargo'!$B:$B,"<="&'Cash Flow'!BG$3,'Wells Fargo'!$B:$B,">"&'Cash Flow'!BF$3) -> 0 | BH9: =SUMIFS('Wells Fargo'!$F:$F,'Wells Fargo'!$G:$G,'Cash Flow'!$A9,'Wells Fargo'!$A:$A,BH$1,'Wells Fargo'!$B:$B,"<="&'Cash Flow'!BH$3,'Wells Fargo'!$B:$B,">"&'Cash Flow'!BG$3) -> 0 | BI9: =SUMIFS('Wells Fargo'!$F:$F,'Wells Fargo'!$G:$G,'Cash Flow'!$A9,'Wells Fargo'!$A:$A,BI$1,'Wells Fargo'!$B:$B,"<="&'Cash Flow'!BI$3,'Wells Fargo'!$B:$B,">"&'Cash Flow'!BH$3) -> 0
A10: Anush Rohani Shukla | B10: =SUM(C10:BI10) -> -615 | C10: =SUMIFS('Wells Fargo'!$F:$F,'Wells Fargo'!$G:$G,'Cash Flow'!$A10,'Wells Fargo'!$A:$A,C$1,'Wells Fargo'!$B:$B,"<="&'Cash Flow'!C$3) -> 0 | D10: =SUMIFS('Wells Fargo'!$F:$F,'Wells Fargo'!$G:$G,'Cash Flow'!$A10,'Wells Fargo'!$A:$A,D$1,'Wells Fargo'!$B:$B,"<="&'Cash Flow'!D$3,'Wells Fargo'!$B:$B,">"&'Cash Flow'!C$3) -> 0 | E10: =SUMIFS('Wells Fargo'!$F:$F,'Wells Fargo'!$G:$G,'Cash Flow'!$A10,'Wells Fargo'!$A:$A,E$1,'Wells Fargo'!$B:$B,"<="&'Cash Flow'!E$3,'Wells Fargo'!$B:$B,">"&'Cash Flow'!D$3) -> 0 | F10: =SUMIFS('Wells Fargo'!$F:$F,'Wells Fargo'!$G:$G,'Cash Flow'!$A10,'Wells Fargo'!$A:$A,F$1,'Wells Fargo'!$B:$B,"<="&'Cash Flow'!F$3,'Wells Fargo'!$B:$B,">"&'Cash Flow'!E$3) -> 0 | G10: =SUMIFS('Wells Fargo'!$F:$F,'Wells Fargo'!$G:$G,'Cash Flow'!$A10,'Wells Fargo'!$A:$A,G$1,'Wells Fargo'!$B:$B,"<="&'Cash Flow'!G$3,'Wells Fargo'!$B:$B,">"&'Cash Flow'!F$3) -> 0 | H10: =SUMIFS('Wells Fargo'!$F:$F,'Wells Fargo'!$G:$G,'Cash Flow'!$A10,'Wells Fargo'!$A:$A,H$1,'Wells Fargo'!$B:$B,"<="&'Cash Flow'!H$3) -> 0 | I10: =SUMIFS('Wells Fargo'!$F:$F,'Wells Fargo'!$G:$G,'Cash Flow'!$A10,'Wells Fargo'!$A:$A,I$1,'Wells Fargo'!$B:$B,"<="&'Cash Flow'!I$3,'Wells Fargo'!$B:$B,">"&'Cash Flow'!H$3) -> 0 | J10: =SUMIFS('Wells Fargo'!$F:$F,'Wells Fargo'!$G:$G,'Cash Flow'!$A10,'Wells Fargo'!$A:$A,J$1,'Wells Fargo'!$B:$B,"<="&'Cash Flow'!J$3,'Wells Fargo'!$B:$B,">"&'Cash Flow'!I$3) -> 0 | K10: =SUMIFS('Wells Fargo'!$F:$F,'Wells Fargo'!$G:$G,'Cash Flow'!$A10,'Wells Fargo'!$A:$A,K$1,'Wells Fargo'!$B:$B,"<="&'Cash Flow'!K$3,'Wells Fargo'!$B:$B,">"&'Cash Flow'!J$3) -> 0 | L10: =SUMIFS('Wells Fargo'!$F:$F,'Wells Fargo'!$G:$G,'Cash Flow'!$A10,'Wells Fargo'!$A:$A,L$1,'Wells Fargo'!$B:$B,"<="&'Cash Flow'!L$3) -> 0 | M10: =SUMIFS('Wells Fargo'!$F:$F,'Wells Fargo'!$G:$G,'Cash Flow'!$A10,'Wells Fargo'!$A:$A,M$1,'Wells Fargo'!$B:$B,"<="&'Cash Flow'!M$3,'Wells Fargo'!$B:$B,">"&'Cash Flow'!L$3) -> 0 | N10: =SUMIFS('Wells Fargo'!$F:$F,'Wells Fargo'!$G:$G,'Cash Flow'!$A10,'Wells Fargo'!$A:$A,N$1,'Wells Fargo'!$B:$B,"<="&'Cash Flow'!N$3,'Wells Fargo'!$B:$B,">"&'Cash Flow'!M$3) -> 0 | O10: =SUMIFS('Wells Fargo'!$F:$F,'Wells Fargo'!$G:$G,'Cash Flow'!$A10,'Wells Fargo'!$A:$A,O$1,'Wells Fargo'!$B:$B,"<="&'Cash Flow'!O$3,'Wells Fargo'!$B:$B,">"&'Cash Flow'!N$3) -> 0 | P10: =SUMIFS('Wells Fargo'!$F:$F,'Wells Fargo'!$G:$G,'Cash Flow'!$A10,'Wells Fargo'!$A:$A,P$1,'Wells Fargo'!$B:$B,"<="&'Cash Flow'!P$3,'Wells Fargo'!$B:$B,">"&'Cash Flow'!O$3) -> 0 | Q10: =SUMIFS('Wells Fargo'!$F:$F,'Wells Fargo'!$G:$G,'Cash Flow'!$A10,'Wells Fargo'!$A:$A,Q$1,'Wells Fargo'!$B:$B,"<="&'Cash Flow'!Q$3) -> 0 | R10: =SUMIFS('Wells Fargo'!$F:$F,'Wells Fargo'!$G:$G,'Cash Flow'!$A10,'Wells Fargo'!$A:$A,R$1,'Wells Fargo'!$B:$B,"<="&'Cash Flow'!R$3,'Wells Fargo'!$B:$B,">"&'Cash Flow'!Q$3) -> 0 | S10: =SUMIFS('Wells Fargo'!$F:$F,'Wells Fargo'!$G:$G,'Cash Flow'!$A10,'Wells Fargo'!$A:$A,S$1,'Wells Fargo'!$B:$B,"<="&'Cash Flow'!S$3,'Wells Fargo'!$B:$B,">"&'Cash Flow'!R$3) -> 0 | T10: =SUMIFS('Wells Fargo'!$F:$F,'Wells Fargo'!$G:$G,'Cash Flow'!$A10,'Wells Fargo'!$A:$A,T$1,'Wells Fargo'!$B:$B,"<="&'Cash Flow'!T$3,'Wells Fargo'!$B:$B,">"&'Cash Flow'!S$3) -> 0 | U10: =SUMIFS('Wells Fargo'!$F:$F,'Wells Fargo'!$G:$G,'Cash Flow'!$A10,'Wells Fargo'!$A:$A,U$1,'Wells Fargo'!$B:$B,"<="&'Cash Flow'!U$3,'Wells Fargo'!$B:$B,">"&'Cash Flow'!T$3) -> 0 | V10: =SUMIFS('Wells Fargo'!$F:$F,'Wells Fargo'!$G:$G,'Cash Flow'!$A10,'Wells Fargo'!$A:$A,V$1,'Wells Fargo'!$B:$B,"<="&'Cash Flow'!V$3) -> 0 | W10: =SUMIFS('Wells Fargo'!$F:$F,'Wells Fargo'!$G:$G,'Cash Flow'!$A10,'Wells Fargo'!$A:$A,W$1,'Wells Fargo'!$B:$B,"<="&'Cash Flow'!W$3,'Wells Fargo'!$B:$B,">"&'Cash Flow'!V$3) -> 0 | X10: =SUMIFS('Wells Fargo'!$F:$F,'Wells Fargo'!$G:$G,'Cash Flow'!$A10,'Wells Fargo'!$A:$A,X$1,'Wells Fargo'!$B:$B,"<="&'Cash Flow'!X$3,'Wells Fargo'!$B:$B,">"&'Cash Flow'!W$3) -> 0 | Y10: =SUMIFS('Wells Fargo'!$F:$F,'Wells Fargo'!$G:$G,'Cash Flow'!$A10,'Wells Fargo'!$A:$A,Y$1,'Wells Fargo'!$B:$B,"<="&'Cash Flow'!Y$3,'Wells Fargo'!$B:$B,">"&'Cash Flow'!X$3) -> 0 | Z10: =SUMIFS('Wells Fargo'!$F:$F,'Wells Fargo'!$G:$G,'Cash Flow'!$A10,'Wells Fargo'!$A:$A,Z$1,'Wells Fargo'!$B:$B,"<="&'Cash Flow'!Z$3,'Wells Fargo'!$B:$B,">"&'Cash Flow'!Y$3) -> 0 | AA10: =SUMIFS('Wells Fargo'!$F:$F,'Wells Fargo'!$G:$G,'Cash Flow'!$A10,'Wells Fargo'!$A:$A,AA$1,'Wells Fargo'!$B:$B,"<="&'Cash Flow'!AA$3) -> 0 | AB10: =SUMIFS('Wells Fargo'!$F:$F,'Wells Fargo'!$G:$G,'Cash Flow'!$A10,'Wells Fargo'!$A:$A,AB$1,'Wells Fargo'!$B:$B,"<="&'Cash Flow'!AB$3,'Wells Fargo'!$B:$B,">"&'Cash Flow'!AA$3) -> 0 | AC10: =SUMIFS('Wells Fargo'!$F:$F,'Wells Fargo'!$G:$G,'Cash Flow'!$A10,'Wells Fargo'!$A:$A,AC$1,'Wells Fargo'!$B:$B,"<="&'Cash Flow'!AC$3,'Wells Fargo'!$B:$B,">"&'Cash Flow'!AB$3) -> 0 | AD10: =SUMIFS('Wells Fargo'!$F:$F,'Wells Fargo'!$G:$G,'Cash Flow'!$A10,'Wells Fargo'!$A:$A,AD$1,'Wells Fargo'!$B:$B,"<="&'Cash Flow'!AD$3,'Wells Fargo'!$B:$B,">"&'Cash Flow'!AC$3) -> -615 | AE10: =SUMIFS('Wells Fargo'!$F:$F,'Wells Fargo'!$G:$G,'Cash Flow'!$A10,'Wells Fargo'!$A:$A,AE$1,'Wells Fargo'!$B:$B,"<="&'Cash Flow'!AE$3,'Wells Fargo'!$B:$B,">"&'Cash Flow'!AD$3) -> 0 | AF10: =SUMIFS('Wells Fargo'!$F:$F,'Wells Fargo'!$G:$G,'Cash Flow'!$A10,'Wells Fargo'!$A:$A,AF$1,'Wells Fargo'!$B:$B,"<="&'Cash Flow'!AF$3) -> 0 | AG10: =SUMIFS('Wells Fargo'!$F:$F,'Wells Fargo'!$G:$G,'Cash Flow'!$A10,'Wells Fargo'!$A:$A,AG$1,'Wells Fargo'!$B:$B,"<="&'Cash Flow'!AG$3,'Wells Fargo'!$B:$B,">"&'Cash Flow'!AF$3) -> 0 | AH10: =SUMIFS('Wells Fargo'!$F:$F,'Wells Fargo'!$G:$G,'Cash Flow'!$A10,'Wells Fargo'!$A:$A,AH$1,'Wells Fargo'!$B:$B,"<="&'Cash Flow'!AH$3,'Wells Fargo'!$B:$B,">"&'Cash Flow'!AG$3) -> 0 | AI10: =SUMIFS('Wells Fargo'!$F:$F,'Wells Fargo'!$G:$G,'Cash Flow'!$A10,'Wells Fargo'!$A:$A,AI$1,'Wells Fargo'!$B:$B,"<="&'Cash Flow'!AI$3,'Wells Fargo'!$B:$B,">"&'Cash Flow'!AH$3) -> 0 | AJ10: =SUMIFS('Wells Fargo'!$F:$F,'Wells Fargo'!$G:$G,'Cash Flow'!$A10,'Wells Fargo'!$A:$A,AJ$1,'Wells Fargo'!$B:$B,"<="&'Cash Flow'!AJ$3,'Wells Fargo'!$B:$B,">"&'Cash Flow'!AI$3) -> 0 | AK10: =SUMIFS('Wells Fargo'!$F:$F,'Wells Fargo'!$G:$G,'Cash Flow'!$A10,'Wells Fargo'!$A:$A,AK$1,'Wells Fargo'!$B:$B,"<="&'Cash Flow'!AK$3) -> 0 | AL10: =SUMIFS('Wells Fargo'!$F:$F,'Wells Fargo'!$G:$G,'Cash Flow'!$A10,'Wells Fargo'!$A:$A,AL$1,'Wells Fargo'!$B:$B,"<="&'Cash Flow'!AL$3,'Wells Fargo'!$B:$B,">"&'Cash Flow'!AK$3) -> 0 | AM10: =SUMIFS('Wells Fargo'!$F:$F,'Wells Fargo'!$G:$G,'Cash Flow'!$A10,'Wells Fargo'!$A:$A,AM$1,'Wells Fargo'!$B:$B,"<="&'Cash Flow'!AM$3,'Wells Fargo'!$B:$B,">"&'Cash Flow'!AL$3) -> 0 | AN10: =SUMIFS('Wells Fargo'!$F:$F,'Wells Fargo'!$G:$G,'Cash Flow'!$A10,'Wells Fargo'!$A:$A,AN$1,'Wells Fargo'!$B:$B,"<="&'Cash Flow'!AN$3,'Wells Fargo'!$B:$B,">"&'Cash Flow'!AM$3) -> 0 | AO10: =SUMIFS('Wells Fargo'!$F:$F,'Wells Fargo'!$G:$G,'Cash Flow'!$A10,'Wells Fargo'!$A:$A,AO$1,'Wells Fargo'!$B:$B,"<="&'Cash Flow'!AO$3,'Wells Fargo'!$B:$B,">"&'Cash Flow'!AN$3) -> 0 | AP10: =SUMIFS('Wells Fargo'!$F:$F,'Wells Fargo'!$G:$G,'Cash Flow'!$A10,'Wells Fargo'!$A:$A,AP$1,'Wells Fargo'!$B:$B,"<="&'Cash Flow'!AP$3) -> 0 | AQ10: =SUMIFS('Wells Fargo'!$F:$F,'Wells Fargo'!$G:$G,'Cash Flow'!$A10,'Wells Fargo'!$A:$A,AQ$1,'Wells Fargo'!$B:$B,"<="&'Cash Flow'!AQ$3,'Wells Fargo'!$B:$B,">"&'Cash Flow'!AP$3) -> 0 | AR10: =SUMIFS('Wells Fargo'!$F:$F,'Wells Fargo'!$G:$G,'Cash Flow'!$A10,'Wells Fargo'!$A:$A,AR$1,'Wells Fargo'!$B:$B,"<="&'Cash Flow'!AR$3,'Wells Fargo'!$B:$B,">"&'Cash Flow'!AQ$3) -> 0 | AS10: =SUMIFS('Wells Fargo'!$F:$F,'Wells Fargo'!$G:$G,'Cash Flow'!$A10,'Wells Fargo'!$A:$A,AS$1,'Wells Fargo'!$B:$B,"<="&'Cash Flow'!AS$3,'Wells Fargo'!$B:$B,">"&'Cash Flow'!AR$3) -> 0 | AT10: =SUMIFS('Wells Fargo'!$F:$F,'Wells Fargo'!$G:$G,'Cash Flow'!$A10,'Wells Fargo'!$A:$A,AT$1,'Wells Fargo'!$B:$B,"<="&'Cash Flow'!AT$3,'Wells Fargo'!$B:$B,">"&'Cash Flow'!AS$3) -> 0 | AU10: =SUMIFS('Wells Fargo'!$F:$F,'Wells Fargo'!$G:$G,'Cash Flow'!$A10,'Wells Fargo'!$A:$A,AU$1,'Wells Fargo'!$B:$B,"<="&'Cash Flow'!AU$3) -> 0 | AV10: =SUMIFS('Wells Fargo'!$F:$F,'Wells Fargo'!$G:$G,'Cash Flow'!$A10,'Wells Fargo'!$A:$A,AV$1,'Wells Fargo'!$B:$B,"<="&'Cash Flow'!AV$3,'Wells Fargo'!$B:$B,">"&'Cash Flow'!AU$3) -> 0 | AW10: =SUMIFS('Wells Fargo'!$F:$F,'Wells Fargo'!$G:$G,'Cash Flow'!$A10,'Wells Fargo'!$A:$A,AW$1,'Wells Fargo'!$B:$B,"<="&'Cash Flow'!AW$3,'Wells Fargo'!$B:$B,">"&'Cash Flow'!AV$3) -> 0 | AX10: =SUMIFS('Wells Fargo'!$F:$F,'Wells Fargo'!$G:$G,'Cash Flow'!$A10,'Wells Fargo'!$A:$A,AX$1,'Wells Fargo'!$B:$B,"<="&'Cash Flow'!AX$3,'Wells Fargo'!$B:$B,">"&'Cash Flow'!AW$3) -> 0 | AY10: =SUMIFS('Wells Fargo'!$F:$F,'Wells Fargo'!$G:$G,'Cash Flow'!$A10,'Wells Fargo'!$A:$A,AY$1,'Wells Fargo'!$B:$B,"<="&'Cash Flow'!AY$3,'Wells Fargo'!$B:$B,">"&'Cash Flow'!AX$3) -> 0 | AZ10: =SUMIFS('Wells Fargo'!$F:$F,'Wells Fargo'!$G:$G,'Cash Flow'!$A10,'Wells Fargo'!$A:$A,AZ$1,'Wells Fargo'!$B:$B,"<="&'Cash Flow'!AZ$3) -> 0 | BA10: =SUMIFS('Wells Fargo'!$F:$F,'Wells Fargo'!$G:$G,'Cash Flow'!$A10,'Wells Fargo'!$A:$A,BA$1,'Wells Fargo'!$B:$B,"<="&'Cash Flow'!BA$3,'Wells Fargo'!$B:$B,">"&'Cash Flow'!AZ$3) -> 0 | BB10: =SUMIFS('Wells Fargo'!$F:$F,'Wells Fargo'!$G:$G,'Cash Flow'!$A10,'Wells Fargo'!$A:$A,BB$1,'Wells Fargo'!$B:$B,"<="&'Cash Flow'!BB$3,'Wells Fargo'!$B:$B,">"&'Cash Flow'!BA$3) -> 0 | BC10: =SUMIFS('Wells Fargo'!$F:$F,'Wells Fargo'!$G:$G,'Cash Flow'!$A10,'Wells Fargo'!$A:$A,BC$1,'Wells Fargo'!$B:$B,"<="&'Cash Flow'!BC$3,'Wells Fargo'!$B:$B,">"&'Cash Flow'!BB$3) -> 0 | BD10: =SUMIFS('Wells Fargo'!$F:$F,'Wells Fargo'!$G:$G,'Cash Flow'!$A10,'Wells Fargo'!$A:$A,BD$1,'Wells Fargo'!$B:$B,"<="&'Cash Flow'!BD$3,'Wells Fargo'!$B:$B,">"&'Cash Flow'!BC$3) -> 0 | BE10: =SUMIFS('Wells Fargo'!$F:$F,'Wells Fargo'!$G:$G,'Cash Flow'!$A10,'Wells Fargo'!$A:$A,BE$1,'Wells Fargo'!$B:$B,"<="&'Cash Flow'!BE$3) -> 0 | BF10: =SUMIFS('Wells Fargo'!$F:$F,'Wells Fargo'!$G:$G,'Cash Flow'!$A10,'Wells Fargo'!$A:$A,BF$1,'Wells Fargo'!$B:$B,"<="&'Cash Flow'!BF$3,'Wells Fargo'!$B:$B,">"&'Cash Flow'!BE$3) -> 0 | BG10: =SUMIFS('Wells Fargo'!$F:$F,'Wells Fargo'!$G:$G,'Cash Flow'!$A10,'Wells Fargo'!$A:$A,BG$1,'Wells Fargo'!$B:$B,"<="&'Cash Flow'!BG$3,'Wells Fargo'!$B:$B,">"&'Cash Flow'!BF$3) -> 0 | BH10: =SUMIFS('Wells Fargo'!$F:$F,'Wells Fargo'!$G:$G,'Cash Flow'!$A10,'Wells Fargo'!$A:$A,BH$1,'Wells Fargo'!$B:$B,"<="&'Cash Flow'!BH$3,'Wells Fargo'!$B:$B,">"&'Cash Flow'!BG$3) -> 0 | BI10: =SUMIFS('Wells Fargo'!$F:$F,'Wells Fargo'!$G:$G,'Cash Flow'!$A10,'Wells Fargo'!$A:$A,BI$1,'Wells Fargo'!$B:$B,"<="&'Cash Flow'!BI$3,'Wells Fargo'!$B:$B,">"&'Cash Flow'!BH$3) -> 0
