Workbook

Sheet Pay
A1: Start | B1: 44348 | C1: =B1+13 -> 44361 | D1: =C1+14 -> 44375 | E1: =D1+14 -> 44389 | F1: =E1+14 -> 44403 | G1: =F1+14 -> 44417 | H1: =G1+14 -> 44431 | I1: =H1+14 -> 44445 | J1: =I1+14 -> 44459 | K1: =J1+14 -> 44473 | ... DO1: =DN1+14 -> 45985
A2: End | B2: =B1+12 -> 44360 | C2: =B2+14 -> 44374 | D2: =C2+14 -> 44388 | E2: =D2+14 -> 44402 | F2: =E2+14 -> 44416 | G2: =F2+14 -> 44430 | H2: =G2+14 -> 44444 | I2: =H2+14 -> 44458 | J2: =I2+14 -> 44472 | ... DO2: =DN2+14 -> 45998
A3: Pay Date | B3: =B2+5 -> 44365 | C3: =C2+5 -> 44379 | D3: =D2+5 -> 44393 | E3: =E2+5 -> 44407 | F3: =F2+5 -> 44421 | G3: =G2+5 -> 44435 | H3: =H2+5 -> 44449 | I3: =I2+5 -> 44463 | ... DO3: =DO2+5 -> 46003
A4: Start Year | B4: =YEAR(B1) -> 2021 | C4: =YEAR(C1) -> 2021 | D4: =YEAR(D1) -> 2021 | E4: =YEAR(E1) -> 2021 | F4: =YEAR(F1) -> 2021 | G4: =YEAR(G1) -> 2021 | H4: =YEAR(H1) -> 2021 | I4: =YEAR(I1) -> 2021 | ... DO4: =YEAR(DO1) -> 2025
A5: End Year | B5: =YEAR(B2) -> 2021 | C5: =YEAR(C2) -> 2021 | D5: =YEAR(D2) -> 2021 | E5: =YEAR(E2) -> 2021 | F5: =YEAR(F2) -> 2021 | G5: =YEAR(G2) -> 2021 | H5: =YEAR(H2) -> 2021 | I5: =YEAR(I2) -> 2021 | ... DO5: =YEAR(DO2) -> 2025
A6: Earnings
A7: Bonus - Non Discretionary | J7: 0 | K7: 0 | L7: 0 | M7: 0 | N7: 0 | O7: 0 | P7: 1200 | Q7: 3134.39 | CU7: 14823.77
A8: Grossed Up Earnings | B8: 4098.37 | K8: 224.74 | AX8: 101.3
A9: LTD Benefit Credit | B9: 0 | C9: 4.86 | D9: 4.86 | E9: 4.86 | F9: 4.86 | G9: 4.86 | H9: 4.86 | I9: 4.86 | J9: 4.86 | K9: 4.86 | L9: 4.86 | M9: 4.86 | N9: 4.86 | O9: 4.86 | P9: 4.86 | Q9: 4.86 | R9: 4.98 | S9: 4.98 | T9: 4.98 | U9: 5.14 | V9: 5.14 | W9: 5.14 | X9: 5.14 | Y9: 5.73 | Z9: 5.73 | AA9: 5.73 | AB9: 5.73 | AC9: 5.73 | AD9: 5.73 | AE9: 5.73 | AF9: 5.73 | AG9: 5.73 | AH9: 5.73 | AI9: 5.73 | AJ9: 5.73 | AK9: 5.73 | AL9: 5.73 | AM9: 5.73 | AN9: 5.73 | AO9: 5.73 | AP9: 5.73
A10: My Health Completion Credit | B10: 0 | C10: 20 | D10: 20 | E10: 20 | F10: 20 | G10: 20 | H10: 20 | I10: 20 | J10: 20 | K10: 20 | L10: 20 | M10: 20 | N10: 20 | O10: 20 | P10: 20 | Q10: 20 | R10: 20 | S10: 20 | T10: 20 | U10: 20 | V10: 20 | W10: 20 | X10: 20 | Y10: 20 | Z10: 20 | AA10: 20 | AB10: 20 | AC10: 20 | AD10: 20 | AE10: 20 | AF10: 20 | AG10: 20 | AH10: 20 | AI10: 20 | AJ10: 20 | AK10: 20 | AL10: 20 | AM10: 20 | AN10: 20 | AO10: 20 | AP10: 20 | AQ10: 20 | AR10: 20 | AS10: 20 | AT10: 20 | AU10: 20 | AV10: 20 | AW10: 20 | AX10: 20 | AY10: 20 | AZ10: 20 | BA10: 20 | BB10: 20 | BC10: 20 | BD10: 20 | BE10: 20 | BF10: 20 | BG10: 20 | BH10: 20 | BI10: 20 | BJ10: 20 | BK10: 20 | BL10: 20 | BM10: 20 | BN10: 20 | BO10: 20 | BP10: 20
A11: Regular | B11: 2700 | C11: 3000 | D11: 3000 | E11: 3000 | F11: 3000 | G11: 3000 | H11: 3000 | I11: 3000 | J11: 3000 | K11: 3000 | L11: 3000 | M11: 3000 | N11: 3000 | O11: 3000 | P11: 3076.93 | Q11: 3076.93 | R11: 3076.93 | S11: 3076.93 | T11: 3076.93 | U11: 3173.08 | V11: 3173.08 | W11: 3173.08 | X11: 3173.08 | Y11: 3538.47 | Z11: 3538.47 | AA11: 3538.47 | AB11: 3538.47 | AC11: 3538.47 | AD11: 3538.47 | AE11: 3538.47 | AF11: 3538.47 | AG11: 3538.47 | AH11: 3538.47 | AI11: 3538.47 | AJ11: 3538.47 | AK11: 3538.47 | AL11: 3538.47 | AM11: 3538.47 | AN11: 3538.47 | AO11: 3538.47 | AP11: 3538.47 | AQ11: 3538.47 | AR11: 3538.47 | AS11: 3538.47 | AT11: 3538.47 | AU11: 4000 | AV11: 4000 | AW11: 4000 | AX11: 4000 | AY11: 4000 | AZ11: 4000 | BA11: 4000 | BB11: 4000 | BC11: 4000 | BD11: 4000 | BE11: 4000 | BF11: 4000 | BG11: 4000 | BH11: 4000 | BI11: =129000/26 -> 4961.5385 | BJ11: =129000/26 -> 4961.5385 | BK11: =129000/26 -> 4961.5385 | BL11: =129000/26 -> 4961.5385 | BM11: =129000/26 -> 4961.5385 | BN11: 4961.5385 | BO11: 4961.5385 | BP11: 4961.5385 | BQ11: 4961.5385 | BR11: 4961.5385 | BS11: 4961.5385 | BT11: 4961.5385 | BU11: 5259.2308 | BV11: 5259.2308 | BW11: 5259.24 | BX11: 5259.24 | BY11: 5259.24 | BZ11: 5259.24 | CA11: 5259.24 | CB11: 5259.24 | CC11: 6191.24 | CD11: 5259.24 | CE11: 5259.24 | CF11: 5259.24 | CG11: 5259.24 | CH11: 5259.24 | CI11: 5259.24 | CJ11: 5259.24 | CK11: 5259.24 | CL11: 5259.24 | CM11: 5259.24 | CN11: 5259.24 | CO11: 5259.24 | CP11: 5259.24 | CQ11: 5259.24 | CR11: 5259.24 | CS11: 5259.24 | CT11: 5259.24 | CU11: 5553.75 | CV11: 5553.75 | CW11: 5553.75 | CX11: 5553.75 | CY11: 5553.75 | CZ11: 5553.75 | DA11: 5553.75 | DB11: 5553.75 | DC11: 5553.75 | DD11: 5553.75 | DE11: 5553.75 | DF11: 5553.75 | DG11: 5553.75 | DH11: 5553.75 | DI11: 6551.75 | DJ11: 5553.75 | DK11: 5553.75 | DL11: 6893.0769
A12: Job Related Education Reimb | AQ12: 1757 | BS12: 932 | CR12: 1889 | DI12: 998
A13: AIP | AR13: 3011.11 | BS13: 2381.72
A14: PIP | BU14: 2396.6
A15: Pre Tax Deductions | Q15: =4.98-4.86 -> 0.12
A16: Pre Tax Deductions
A17: Group Accident Coverage | Q17: 0.82 | R17: 0.82 | S17: 0.82 | T17: 0.82 | U17: 0.84 | V17: 0.84 | W17: 0.84 | X17: 0.84 | Y17: 0.94 | Z17: 0.94 | AA17: 0.94 | AB17: 0.94 | AC17: 0.94 | AD17: 0.94 | AE17: 0.94 | AF17: 0.94 | AG17: 0.94 | AH17: 0.94 | AI17: 0.94 | AJ17: 0.94 | AK17: 0.94 | AL17: 0.94 | AM17: 0.94 | AN17: 0.94 | AO17: 0.94 | AP17: 0.94
A18: Health Savings Account | B18: 0 | C18: 54.77 | D18: 54.77 | E18: 54.77 | F18: 54.77 | G18: 54.77 | H18: 54.77 | I18: 54.77 | J18: 54.77 | K18: 54.77 | L18: 54.77 | M18: 54.77 | N18: 54.77 | O18: 54.77 | P18: 54.77 | Q18: 111.15 | R18: 111.15 | S18: 111.15 | T18: 111.15 | U18: 111.15 | V18: 111.15 | W18: 111.15 | X18: 111.15 | Y18: 111.15 | Z18: 111.15 | AA18: 111.15 | AB18: 111.15 | AC18: 111.15 | AD18: 111.15 | AE18: 111.15 | AF18: 111.15 | AG18: 111.15 | AH18: 111.15 | AI18: 111.15 | AJ18: 111.15 | AK18: 111.15 | AL18: 111.15 | AM18: 111.15 | AN18: 111.15 | AO18: 111.15 | AP18: 111.15 | AQ18: 118.85 | AR18: 118.85 | AS18: 118.85 | AT18: 118.85 | AU18: 118.85 | AV18: 118.85 | AW18: 118.85 | AX18: 118.85 | AY18: 118.85 | AZ18: 118.85 | BA18: 118.85 | BB18: 118.85 | BC18: 118.85 | BD18: 118.85 | BE18: 118.85 | BF18: 118.85 | BG18: 118.85 | BH18: 118.85 | BI18: 118.85 | BJ18: 118.85 | BK18: 118.85 | BL18: 118.85 | BM18: 118.85 | BN18: 118.85 | BO18: 118.85 | BP18: 118.75
A19: Medical Coverage | B19: 0 | C19: 87 | D19: 87 | E19: 87 | F19: 87 | G19: 87 | H19: 87 | I19: 87 | J19: 87 | K19: 87 | L19: 87 | M19: 87 | N19: 87 | O19: 87 | P19: 87 | Q19: 66 | R19: 66 | S19: 66 | T19: 66 | U19: 66 | V19: 66 | W19: 66 | X19: 66 | Y19: 66 | Z19: 66 | AA19: 66 | AB19: 66 | AC19: 66 | AD19: 66 | AE19: 66 | AF19: 66 | AG19: 66 | AH19: 66 | AI19: 66 | AJ19: 89 | AK19: 89 | AL19: 89 | AM19: 89 | AN19: 89 | AO19: 89 | AP19: 89 | AQ19: 89 | AR19: 89 | AS19: 89 | AT19: 89 | AU19: 89 | AV19: 89 | AW19: 89 | AX19: 89 | AY19: 89 | AZ19: 89 | BA19: 89 | BB19: 89 | BC19: 89 | BD19: 89 | BE19: 89 | BF19: 89 | BG19: 89 | BH19: 89 | BI19: 89 | BJ19: 89 | BK19: 89 | BL19: 89 | BM19: 89 | BN19: 89 | BO19: 89 | BP19: 89
A20: Supplemental Accident Coverage | B20: 0 | C20: 1.6 | D20: 1.6 | E20: 1.6 | F20: 1.6 | G20: 1.6 | H20: 1.6 | I20: 1.6 | J20: 1.6 | K20: 1.6 | L20: 1.6 | M20: 1.6 | N20: 1.6 | O20: 1.6 | P20: 1.6 | Q20: 1.7 | R20: 1.7 | S20: 1.7 | T20: 1.7 | U20: 1.7 | V20: 1.7 | W20: 1.7 | X20: 1.7 | Y20: 1.7 | Z20: 1.7 | AA20: 1.7 | AB20: 1.7 | AC20: 1.7 | AD20: 1.7 | AE20: 1.7 | AF20: 1.7 | AG20: 1.7 | AH20: 1.7 | AI20: 1.7 | AJ20: 1.7 | AK20: 1.7 | AL20: 1.7 | AM20: 1.7 | AN20: 1.7 | AO20: 1.7 | AP20: 1.7 | AQ20: 1.7 | AR20: 1.7 | AS20: 1.7 | AT20: 1.7 | AU20: 1.7 | AV20: 1.7 | AW20: 1.7 | AX20: 1.7 | AY20: 1.7 | AZ20: 1.7 | BA20: 1.7 | BB20: 1.7 | BC20: 1.7 | BD20: 1.7 | BE20: 1.7 | BF20: 1.7 | BG20: 1.7 | BH20: 1.7 | BI20: 1.7 | BJ20: 1.7 | BK20: 1.7 | BL20: 1.7 | BM20: 1.7 | BN20: 1.7 | BO20: 1.7 | BP20: 1.7
A21: Vision Coverage | B21: 0 | C21: 3.79 | D21: 3.79 | E21: 3.79 | F21: 3.79 | G21: 3.79 | H21: 3.79 | I21: 3.79 | J21: 3.79 | K21: 3.79 | L21: 3.79 | M21: 3.79 | N21: 3.79 | O21: 3.79 | P21: 3.79 | Q21: 3.79 | R21: 3.79 | S21: 3.79 | T21: 3.79 | U21: 3.79 | V21: 3.79 | W21: 3.79 | X21: 3.79 | Y21: 3.79 | Z21: 3.79 | AA21: 3.79 | AB21: 3.79 | AC21: 3.79 | AD21: 3.79 | AE21: 3.79 | AF21: 3.79 | AG21: 3.79 | AH21: 3.79 | AI21: 3.79 | AJ21: 3.79 | AK21: 3.79 | AL21: 3.79 | AM21: 3.79 | AN21: 3.79 | AO21: 3.79 | AP21: 3.79 | AQ21: 4.5 | AR21: 4.5 | AS21: 4.5 | AT21: 4.5 | AU21: 4.5 | AV21: 4.5 | AW21: 4.5 | AX21: 4.5 | AY21: 4.5 | AZ21: 4.5 | BA21: 4.5 | BB21: 4.5 | BC21: 4.5 | BD21: 4.5 | BE21: 4.5 | BF21: 4.5 | BG21: 4.5 | BH21: 4.5 | BI21: 4.5 | BJ21: 4.5 | BK21: 4.5 | BL21: 4.5 | BM21: 4.5 | BN21: 4.5 | BO21: 4.5 | BP21: 4.5
A22: Nationwide Savings Plan | B22: 0 | C22: 0 | D22: 0 | E22: 0 | F22: 0 | G22: 0 | H22: 0 | I22: 0 | J22: 0 | K22: 0 | L22: 0 | M22: 0 | N22: 240 | O22: 240 | P22: 342.15 | Q22: 496.91 | R22: 615.39 | S22: 615.39 | T22: 0 | U22: 0 | V22: 0 | W22: 0 | X22: 0 | Y22: 0 | Z22: 0 | AA22: 0 | AB22: 0 | AC22: 0 | AD22: 0 | AE22: 0 | AF22: 0 | CQ22: 1577.77 | CR22: 1577.77 | CS22: 1577.77 | CT22: 1577.77 | CU22: 6113.26 | CV22: 1666.13 | CW22: 1666.13 | CX22: 1666.13 | CY22: 3887.63 | DL22: 2189.64 | DP22: =SUM(CQ22:DO22) -> 23500
A23: Federal and FICA Taxable Wages | B23: =SUM(B8:B11)-SUM(B18:B21) -> 6798.37 | C23: =SUM(C8:C11)-SUM(C18:C21) -> 2877.7 | D23: =SUM(D8:D11)-SUM(D18:D21) -> 2877.7 | E23: =SUM(E8:E11)-SUM(E18:E21) -> 2877.7 | F23: =SUM(F8:F11)-SUM(F18:F21) -> 2877.7 | G23: =SUM(G8:G11)-SUM(G18:G21) -> 2877.7 | H23: =SUM(H8:H11)-SUM(H18:H21) -> 2877.7 | I23: =SUM(I8:I11)-SUM(I18:I21) -> 2877.7 | ... M23: =SUM(M8:M11)-SUM(M18:M21) -> 2877.7 | N23: =SUM(N7:N11)-SUM(N18:N22) -> 2637.7 | O23: =SUM(O7:O11)-SUM(O18:O22) -> 2637.7 | P23: =SUM(P7:P11)-SUM(P18:P22) -> 3812.48 | Q23: =SUM(Q7:Q15)-SUM(Q18:Q22) -> 5556.75 | R23: =SUM(R7:R11)-SUM(R17:R21)+1.42 -> 2919.87 | S23: =SUM(S7:S11)-SUM(S17:S21)+1.42 -> 2919.87 | T23: =SUM(T7:T11)-SUM(T17:T22)+1.42 -> 2919.87 | U23: =SUM(U7:U11)-SUM(U17:U22)+1.55 -> 3016.29 | V23: =SUM(V7:V11)-SUM(V17:V22)+1.55 -> 3016.29 | W23: =SUM(W7:W11)-SUM(W17:W22)+1.55 -> 3016.29 | X23: =SUM(X7:X11)-SUM(X17:X22)+1.55 -> 3016.29 | Y23: =SUM(Y7:Y11)-SUM(Y17:Y22)+1.92 -> 3382.54 | Z23: =SUM(Z7:Z11)-SUM(Z17:Z22)+1.92 -> 3382.54 | AA23: =SUM(AA7:AA11)-SUM(AA17:AA22)+1.92 -> 3382.54 | AB23: =SUM(AB7:AB11)-SUM(AB17:AB22)+1.92 -> 3382.54 | AC23: =SUM(AC7:AC11)-SUM(AC17:AC22)+1.92 -> 3382.54 | AD23: =SUM(AD7:AD11)-SUM(AD17:AD22)+1.92 -> 3382.54 | AE23: =SUM(AE7:AE11)-SUM(AE17:AE22)+1.92 -> 3382.54 | AF23: =SUM(AF7:AF11)-SUM(AF17:AF22)+1.92 -> 3382.54 | ... AQ23: =SUM(AQ7:AQ11)-SUM(AQ17:AQ22)+1.92 -> 3346.34 | AR23: =SUM(AR7:AR13)-SUM(AR17:AR22)+1.92 -> 6357.45 | AS23: =SUM(AS7:AS13)-SUM(AS17:AS22)+1.92 -> 3346.34 | AT23: =SUM(AT7:AT13)-SUM(AT17:AT22)+1.92 -> 3346.34 | AU23: =SUM(AU7:AU13)-SUM(AU17:AU22)+1.92 -> 3807.87 | AV23: =SUM(AV7:AV13)-SUM(AV17:AV22)+1.92 -> 3807.87 | AW23: =SUM(AW7:AW13)-SUM(AW17:AW22)+1.92 -> 3807.87 | AX23: =SUM(AX7:AX13)-SUM(AX17:AX22)+1.92 -> 3909.17 | AY23: =SUM(AY7:AY13)-SUM(AY17:AY22)+1.92 -> 3807.87 | ... BJ23: =SUM(BJ7:BJ13)-SUM(BJ17:BJ22)+1.92 -> 4769.4085 | BK23: =SUM(BK7:BK13)-SUM(BK17:BK22) -> 4767.4885 | BL23: =SUM(BL7:BL13)-SUM(BL17:BL22) -> 4767.4885 | BM23: =SUM(BM7:BM13)-SUM(BM17:BM22) -> 4767.4885 | BN23: =SUM(BN7:BN13)-SUM(BN17:BN22) -> 4767.4885 | BO23: =SUM(BO7:BO13)-SUM(BO17:BO22) -> 4767.4885 | BP23: =SUM(BP7:BP13)-SUM(BP17:BP22) -> 4767.5885 | BQ23: =SUM(BQ7:BQ13)-SUM(BQ17:BQ22) -> 4961.5385 | BR23: =SUM(BR7:BR13)-SUM(BR17:BR22) -> 4961.5385 | BS23: =SUM(BS7:BS13)-SUM(BS17:BS22)-932 -> 7343.2585 | BT23: =SUM(BT7:BT13)-SUM(BT17:BT22) -> 4961.5385 | BU23: =SUM(BU6:BU14)-SUM(BU17:BU22) -> 7655.8308 | BV23: =SUM(BV6:BV14)-SUM(BV17:BV22) -> 5259.2308 | BW23: =SUM(BW6:BW14)-SUM(BW17:BW22) -> 5259.24 | BX23: =SUM(BX6:BX14)-SUM(BX17:BX22) -> 5259.24 | BY23: =SUM(BY6:BY14)-SUM(BY17:BY22) -> 5259.24 | BZ23: =SUM(BZ6:BZ14)-SUM(BZ17:BZ22) -> 5259.24 | CA23: =SUM(CA6:CA14)-SUM(CA17:CA22) -> 5259.24 | CB23: =SUM(CB6:CB14)-SUM(CB17:CB22) -> 5259.24 | ... CQ23: =SUM(CQ6:CQ14)-SUM(CQ17:CQ22) -> 3681.47 | CR23: =SUM(CR6:CR15)-SUM(CR17:CR22) -> 5570.47 | CS23: =SUM(CS6:CS14)-SUM(CS17:CS22) -> 3681.47 | CT23: =SUM(CT6:CT14)-SUM(CT17:CT22) -> 3681.47 | CU23: =SUM(CU6:CU14)-SUM(CU17:CU22) -> 14264.26 | CV23: =SUM(CV6:CV14)-SUM(CV17:CV22) -> 3887.62 | CW23: =SUM(CW6:CW14)-SUM(CW17:CW22) -> 3887.62 | CX23: =SUM(CX6:CX14)-SUM(CX17:CX22) -> 3887.62 | CY23: =SUM(CY6:CY14)-SUM(CY17:CY22) -> 1666.12 | CZ23: =SUM(CZ6:CZ14)-SUM(CZ17:CZ22) -> 5553.75 | ... DO23: =SUM(DO6:DO14)-SUM(DO17:DO22) -> 0 | DP23: =SUM(CQ23:DO23) -> 117552.56
A24: Taxes
A25: OASDI | B25: 421.5 | C25: 178.5 | D25: 178.5 | E25: 178.5 | F25: 178.5 | G25: 178.5 | H25: 178.5 | I25: 178.5 | J25: 178.5 | K25: 192.44 | L25: 178.5 | M25: 178.5 | N25: 178.5 | O25: 178.5 | P25: 257.67 | Q25: 375.97432 | R25: 181.03 | S25: 181.03 | T25: 181.03 | U25: 187.01 | V25: 187.01 | W25: 187.01 | X25: 187.01 | Y25: 209.72 | Z25: 209.72 | AA25: 209.72 | AB25: 209.72 | AC25: 209.72 | AD25: 209.72 | AE25: 209.72 | AF25: 209.72 | AG25: 209.72 | AH25: 209.72 | AI25: 208.3 | AJ25: 208.29 | AK25: 208.29 | AL25: 208.29 | AM25: 208.29 | AN25: 208.29 | AO25: 208.29 | AP25: 208.29 | AQ25: 207.45 | AR25: 394.14 | AS25: 207.45 | AT25: 207.45 | AU25: 236.12 | AV25: 236.09 | AW25: 236.09 | AX25: 242.38 | AY25: 236.09 | AZ25: 236.09 | BA25: 236.09 | BB25: 236.1 | BC25: 236.09 | BD25: 236.09 | BE25: 236.09 | BF25: 236.09 | BG25: 236.1 | BH25: 236.09 | BI25: =$BI$11*(BH44) -> 307.61807 | BJ25: =$BI$11*(BH44) -> 307.61807 | BK25: 295.77 | BL25: 295.76 | BM25: 295.77 | BN25: 295.76 | BO25: 295.77 | BP25: 295.77 | BQ25: 307.86 | BR25: 307.86 | BS25: 455.53 | BT25: 307.86 | BU25: 475.04 | BV25: 326.33 | BW25: 326.34 | BX25: 326.34 | BY25: 326.34 | BZ25: 326.34 | CA25: 326.34 | CB25: 326.34 | CC25: 326.34 | CD25: 326.34 | CE25: 326.34 | CF25: 326.34 | CG25: 326.34 | CH25: 326.34 | CI25: 326.34 | CJ25: 326.34 | CK25: 326.34 | CL25: 326.34 | CM25: 326.34 | CN25: 326.33 | CO25: 326.33 | CP25: 326.33 | CQ25: 326.42 | CR25: 326.41 | CS25: 326.42 | CT25: 326.42 | CU25: 1263.76 | CV25: 344.69 | CW25: 344.69 | CX25: 344.69 | CY25: 344.69 | CZ25: 344.69 | DA25: 344.69 | DB25: 344.69 | DC25: 344.69 | DD25: 344.69 | DE25: 344.69 | DF25: 344.69 | DG25: 344.69 | DH25: 344.69 | DI25: 344.69 | DJ25: 344.69 | DK25: 344.69 | DL25: 427.84
A26: Medicare | B26: 98.58 | C26: 41.74 | D26: 41.75 | E26: 41.74 | F26: 41.75 | G26: 41.75 | H26: 41.74 | I26: 41.75 | J26: 41.75 | K26: 45 | L26: 41.75 | M26: 41.74 | N26: 41.75 | O26: 41.74 | P26: 60.27 | Q26: 87.79 | R26: 42.34 | S26: 42.34 | T26: 42.33 | U26: 43.74 | V26: 43.74 | W26: 43.73 | X26: 43.74 | Y26: 49.05 | Z26: 49.04 | AA26: 49.04 | AB26: 49.05 | AC26: 49.04 | AD26: 49.05 | AE26: 49.04 | AF26: 49.04 | AG26: 49.05 | AH26: 49.05 | AI26: 48.72 | AJ26: 48.71 | AK26: 48.71 | AL26: 48.71 | AM26: 48.72 | AN26: 48.71 | AO26: 48.71 | AP26: 48.71 | AQ26: 48.52 | AR26: 92.17 | AS26: 48.52 | AT26: 48.52 | AU26: 55.22 | AV26: 55.21 | AW26: 55.22 | AX26: 56.68 | AY26: 55.22 | AZ26: 55.21 | BA26: 55.22 | BB26: 55.21 | BC26: 55.22 | BD26: 55.22 | BE26: 55.22 | BF26: 55.21 | BG26: 55.22 | BH26: 55.21 | BI26: =$BI$11*(BH45) -> 71.936946 | BJ26: =$BI$11*(BH45) -> 71.936946 | BK26: 69.17 | BL26: 69.17 | BM26: 69.17 | BN26: 69.17 | BO26: 69.17 | BP26: 69.17 | BQ26: 72 | BR26: 72 | BS26: 106.53 | BT26: 72 | BU26: 11.1 | BV26: 76.32 | BW26: 76.33 | BX26: 76.32 | BY26: 76.32 | BZ26: 76.32 | CA26: 76.32 | CB26: 76.32 | CC26: 76.33 | CD26: 76.32 | CE26: 76.32 | CF26: 76.32 | CG26: 76.32 | CH26: 76.32 | CI26: 76.32 | CJ26: 76.32 | CK26: 76.33 | CL26: 76.32 | CM26: 76.32 | CN26: 76.32 | CO26: 76.32 | CP26: 76.32 | CQ26: 76.34 | CR26: 76.34 | CS26: 76.34 | CT26: 76.34 | CU26: 295.56 | CV26: 80.61 | CW26: 80.61 | CX26: 80.61 | CY26: 80.62 | CZ26: 80.61 | DA26: 80.61 | DB26: 80.62 | DC26: 80.61 | DD26: 80.61 | DE26: 80.61 | DF26: 80.62 | DG26: 80.61 | DH26: 80.61 | DI26: 80.62 | DJ26: 80.61 | DK26: 80.61 | DL26: 100.06
A27: Federal | B27: 1225.93 | C27: 363.68 | D27: 363.68 | E27: 363.64 | F27: 363.64 | G27: 363.64 | H27: 363.64 | I27: 363.64 | J27: 363.64 | K27: 413.09 | L27: 363.64 | M27: 363.64 | N27: 310.84 | O27: 310.84 | P27: 569.29 | Q27: 944.46 | R27: 228.8 | S27: 228.8 | T27: 364.18 | U27: 385.39 | V27: 385.39 | W27: 385.39 | X27: 385.39 | Y27: 465.96 | Z27: 465.96 | AA27: 465.96 | AB27: 465.96 | AC27: 465.96 | AD27: 465.96 | AE27: 465.96 | AF27: 465.96 | AG27: 465.96 | AH27: 465.96 | AI27: 460.91 | AJ27: 460.91 | AK27: 460.91 | AL27: 460.91 | AM27: 460.91 | AN27: 460.91 | AO27: 460.91 | AP27: 460.91 | AQ27: 438.41 | AR27: 1100.84 | AS27: 438.41 | AT27: 438.41 | AU27: 540.12 | AV27: 540.04 | AW27: 540.04 | AX27: 562.32 | AY27: 540.04 | AZ27: 540.04 | BA27: 540.04 | BB27: 540.04 | BC27: 540.04 | BD27: 540.04 | BE27: 540.04 | BF27: 540.04 | BG27: 540.04 | BH27: 540.04 | BI27: =$BI$11*(BH46) -> 703.65565 | BJ27: =$BI$11*(BH46) -> 703.65565 | BK27: 762.78 | BL27: 762.78 | BM27: 762.78 | BN27: 762.78 | BO27: 762.78 | BP27: 762.81 | BQ27: 789.31 | BR27: 789.31 | BS27: 1313.29 | BT27: 789.31 | BU27: 1217.93 | BV27: 836.67 | BW27: 860.85 | BX27: 860.85 | BY27: 860.85 | BZ27: 860.85 | CA27: 860.85 | CB27: 860.85 | CC27: 860.85 | CD27: 860.85 | CE27: 860.85 | CF27: 860.85 | CG27: 860.85 | CH27: 860.85 | CI27: 860.85 | CJ27: 860.85 | CK27: 860.85 | CL27: 860.85 | CM27: 860.85 | CN27: 860.85 | CO27: 860.85 | CP27: 860.85 | CQ27: 488.57 | CR27: 488.57 | CS27: 488.57 | CT27: 488.57 | CU27: 2816.83 | CV27: 533.97 | CW27: 533.97 | CX27: 533.97 | CY27: 122.18 | CZ27: 920.67 | DA27: 920.67 | DB27: 920.67 | DC27: 920.67 | DD27: 920.67 | DE27: 920.67 | DF27: 920.67 | DG27: 920.67 | DH27: 920.67 | DI27: 920.67 | DJ27: 920.67 | DK27: 920.67 | DL27: 717.05
A28: State Tax (VA) | B28: 371.05 | C28: 145.69 | D28: 145.69 | E28: 145.69 | F28: 145.69 | G28: 145.69 | H28: 145.69 | BI28: =$BI$11*(BH47) -> 0 | BJ28: =$BI$11*(BH47) -> 0
A29: State Tax (AZ) | B29: 244.74 | C29: 103.65 | D29: 103.65 | E29: 103.65 | F29: 103.65 | G29: 103.65 | H29: 103.65 | I29: 103.65 | J29: 103.65 | K29: 111.74 | L29: 103.65 | M29: 103.65 | N29: 95.01 | O29: 95.01 | P29: 137.3 | Q29: 200.07 | R29: 82.96 | S29: 82.96 | T29: 105.12 | U29: 108.59 | V29: 108.59 | W29: 108.59 | X29: 108.59 | Y29: 121.77 | Z29: 121.77 | AA29: 121.77 | AB29: 121.77 | AC29: 121.77 | AD29: 121.77 | AE29: 121.77 | AF29: 121.77 | AG29: 121.77 | AH29: 121.77 | BI29: =$BI$11*(BH48) -> 0 | BJ29: =$BI$11*(BH48) -> 0
A30: State Tax (CA) | AI30: 209.33 | AJ30: 209.33 | AK30: 209.33 | AL30: 209.33 | AM30: 209.33 | AN30: 209.33 | AO30: 209.33 | AP30: 209.33 | AQ30: 196.63 | AR30: 504.67 | AS30: 196.63 | AT30: 196.63 | AU30: 243.93 | AV30: 243.89 | AW30: 243.89 | AX30: 254.25 | AY30: 243.89 | AZ30: 243.89 | BA30: 243.89 | BB30: 243.89 | BC30: 243.89 | BD30: 243.89 | BE30: 243.89 | BF30: 243.89 | BG30: 243.89 | BH30: 243.89 | BI30: =$BI$11*(BH49) -> 317.78123 | BJ30: =$BI$11*(BH49) -> 317.78123 | BK30: 342.35 | BL30: 342.35 | BM30: 342.35 | BN30: 342.35 | BO30: 342.35 | BP30: 342.35 | BQ30: 345.26 | BR30: 345.26 | BS30: 588.91 | BT30: 345.26 | BU30: 532.75 | BV30: 365.98 | BW30: 375.75 | BX30: 375.75 | BY30: 375.75 | BZ30: 375.75 | CA30: 375.75 | CB30: 375.75 | CC30: 375.75 | CD30: 375.75 | CE30: 375.75 | CF30: 375.75 | CG30: 375.75 | CH30: 375.75 | CI30: 375.75 | CJ30: 375.75 | CK30: 375.75 | CL30: 375.75 | CM30: 375.75 | CN30: 375.75 | CO30: 375.75 | CP30: 375.75 | CQ30: 209.1 | CR30: 209.1 | CS30: 209.1 | CT30: 209.1 | CU30: 1293.78 | CV30: 230.21 | CW30: 230.21 | CX30: 230.21 | CY30: 38.06 | CZ30: 400.66 | DA30: 400.66 | DB30: 400.66 | DC30: 400.66 | DD30: 400.66 | DE30: 400.66 | DF30: 400.66 | DG30: 400.66 | DH30: 400.66 | DI30: 400.66 | DJ30: 400.66 | DK30: 400.66 | DL30: 313.86
A31: CA SDI - CASDI | AI31: 38.18 | AJ31: 38.18 | AK31: 38.18 | AL31: 38.17 | AM31: 38.18 | AN31: 38.18 | AO31: 38.18 | AP31: 38.18 | AQ31: 33.43 | AR31: 59.36 | AS31: 32.25 | AT31: 31.29 | AU31: 35.35 | AV31: 35.34 | AW31: 35.34 | AX31: 36.25 | AY31: 35.34 | AZ31: 35.35 | BA31: 35.34 | BB31: 35.34 | BC31: 35.34 | BD31: 35.34 | BE31: 35.34 | BF31: 35.34 | BG31: 35.34 | BH31: 35.34 | BI31: =$BI$11*(BH50) -> 46.046942 | BJ31: =$BI$11*(BH50) -> 46.046942 | BK31: 44 | BL31: 44.01 | BM31: 44 | BN31: 44 | BO31: 44.01 | BP31: 44 | BQ31: 54.62 | BR31: 54.62 | BS31: 80.82 | BT31: 54.62 | BU31: 84.28 | BV31: 57.9 | BW31: 57.9 | BX31: 57.9 | BY31: 57.9 | BZ31: 57.9 | CA31: 57.9 | CB31: 57.89 | CC31: 57.9 | CD31: 57.9 | CE31: 57.9 | CF31: 57.9 | CG31: 57.9 | CH31: 57.9 | CI31: 57.9 | CJ31: 57.9 | CK31: 57.89 | CL31: 57.9 | CM31: 57.9 | CN31: 57.9 | CO31: 57.9 | CP31: 57.9 | CQ31: 63.18 | CR31: 63.17 | CS31: 63.18 | CT31: 63.18 | CU31: 244.6 | CV31: 66.71 | CW31: 66.72 | CX31: 66.71 | CY31: 66.72 | CZ31: 66.71 | DA31: 66.71 | DB31: 66.72 | DC31: 66.71 | DD31: 66.72 | DE31: 66.71 | DF31: 66.71 | DG31: 66.72 | DH31: 66.71 | DI31: 66.72 | DJ31: 66.71 | DK31: 66.71 | DL31: 82.8
A32: Post Tax Deductions
A33: Life Insurance Coverage | B33: 0 | C33: 1.13 | D33: 1.13 | E33: 1.13 | F33: 1.13 | G33: 1.13 | H33: 1.13 | I33: 1.13 | J33: 1.13 | K33: 1.13 | L33: 1.13 | M33: 1.13 | N33: 1.13 | O33: 1.13 | P33: 1.13 | Q33: 1.16 | R33: 1.16 | S33: 1.16 | T33: 1.16 | U33: 1.22 | V33: 1.22 | W33: 1.22 | X33: 1.22 | Y33: 1.33 | Z33: 1.33 | AA33: 1.33 | AB33: 1.33 | AC33: 1.33 | AD33: 1.33 | AE33: 1.33 | AF33: 1.33 | AG33: 1.33 | AH33: 1.33 | AI33: 1.33 | AJ33: 1.33 | AK33: 1.33 | AL33: 1.33 | AM33: 1.33 | AN33: 1.33 | AO33: 1.33 | AP33: 1.33 | BQ33: 3.74 | BR33: 3.74 | BS33: 3.74 | BT33: 3.74 | BU33: 3.74 | BV33: 3.74 | BW33: 3.97 | BX33: 3.97 | BY33: 3.97 | BZ33: 3.97 | CA33: 3.97 | CB33: 3.97 | CC33: 3.97 | CD33: 3.97 | CE33: 3.97 | CF33: 3.97 | CG33: 3.97 | CH33: 3.97 | CI33: 3.97 | CJ33: 3.97 | CK33: 3.97 | CL33: 3.97 | CM33: 3.97 | CN33: 3.97 | CO33: 3.97 | CP33: 3.97 | CQ33: 4.09 | CR33: 4.09 | CS33: 4.09 | CT33: 4.09 | CU33: 4.21 | CV33: 4.21 | CW33: 4.21 | CX33: 4.21 | CY33: 4.21 | CZ33: 4.21 | DA33: 4.21 | DB33: 4.21 | DC33: 4.21 | DD33: 4.21 | DE33: 4.21 | DF33: 4.21 | DG33: 4.21 | DH33: 4.21 | DI33: 4.21 | DJ33: 4.21 | DK33: 4.21 | DL33: 5.22
A34: Long Term Disability Coverage | B34: 0 | C34: 9.69 | D34: 9.69 | E34: 9.69 | F34: 9.69 | G34: 9.69 | H34: 9.69 | I34: 9.69 | J34: 9.69 | K34: 9.69 | L34: 9.69 | M34: 9.69 | N34: 9.69 | O34: 9.69 | P34: 9.69 | Q34: 9.94 | R34: 9.94 | S34: 9.94 | T34: 9.94 | U34: 10.25 | V34: 10.25 | W34: 10.25 | X34: 10.25 | Y34: 11.43 | Z34: 11.43 | AA34: 11.43 | AB34: 11.43 | AC34: 11.43 | AD34: 11.43 | AE34: 11.43 | AF34: 11.43 | AG34: 11.43 | AH34: 11.43 | AI34: 11.43 | AJ34: 11.43 | AK34: 11.43 | AL34: 11.43 | AM34: 11.43 | AN34: 11.43 | AO34: 11.43 | AP34: 11.43
A35: NSP AfterTax Deduction NonRoth | C35: 450 | D35: 450 | E35: 300
A36: Bravo Award - No Cash Net | K36: 150 | AX36: 60
A37: Charitable Giving | K37: 38.47 | L37: 38.47 | M37: 38.47 | N37: 38.47 | O37: 38.47 | P37: 38.47 | Q37: 38.47 | R37: 38.47 | S37: 38.47 | T37: 38.47 | U37: 38.47 | V37: 38.47 | W37: 38.47 | X37: 38.47 | Y37: 38.47 | Z37: 38.47 | AA37: 38.47 | AB37: 38.47 | AC37: 38.47 | AD37: 38.47 | AE37: 38.47 | AF37: 38.47 | AG37: 38.47 | AH37: 38.47 | AI37: 38.47 | AJ37: 38.47 | AK37: 38.47 | AL37: 38.47 | AM37: 38.47 | AN37: 38.47 | AO37: 38.47 | AP37: 38.47 | AQ37: 38.47 | AR37: 38.47 | AS37: 38.47 | AT37: 38.47 | AU37: 38.47 | AV37: 38.47 | AW37: 38.47 | AX37: 38.47 | AY37: 38.47 | AZ37: 38.47 | BA37: 38.47 | BB37: 38.47 | BC37: 38.47 | BD37: 38.47 | BE37: 38.47 | BF37: 38.47 | BG37: 38.47 | BH37: 38.47 | BI37: 38.47 | BJ37: 38.47 | BK37: 38.47 | BL37: 38.47 | BM37: 38.47 | BN37: 38.47 | BO37: 38.47 | BP37: 38.47 | BQ37: 38.47 | BR37: 38.47 | BS37: 38.47 | BT37: 38.47 | BU37: 38.47 | BV37: 38.47 | BW37: 38.47 | BX37: 38.47 | BY37: 38.47 | BZ37: 38.47 | CA37: 38.47 | CB37: 38.47 | CC37: 38.47 | CD37: 38.47 | CE37: 38.47 | CF37: 38.47 | CG37: 38.47 | CH37: 38.47 | CI37: 38.47 | CJ37: 38.47 | CK37: 38.47 | CL37: 38.47 | CM37: 38.47 | CN37: 38.47 | CO37: 38.47 | CP37: 38.47 | CQ37: 38.47 | CR37: 38.47 | CS37: 38.47 | CT37: 38.47 | CU37: 38.47 | CV37: 38.47 | CW37: 38.47 | CX37: 38.47 | CY37: 38.47 | CZ37: 38.47 | DA37: 38.47 | DB37: 38.47 | DC37: 38.47 | DD37: 38.47 | DE37: 38.47 | DF37: 38.47 | DG37: 38.47 | DH37: 38.47 | DI37: 38.47 | DJ37: 38.47 | DK37: 38.47 | DL37: 38.47
A38: Roth 401k Deduction - ROTH | J38: 150 | K38: 240 | L38: 240 | M38: 240 | AG38: 530.77 | AH38: 530.77 | AI38: 530.77 | AJ38: 530.77 | AK38: 530.77 | AL38: 530.77 | AM38: 530.77 | AN38: 530.77 | AO38: 530.77 | AP38: 530.77 | AQ38: 530.77 | AR38: 982.44 | AS38: 601.54 | AT38: 601.54 | AU38: 720
A39: Supplemental Accident Coverage | BQ39: 2.6 | BR39: 2.6 | BS39: 2.6 | BT39: 2.6 | BU39: 2.6 | BV39: 2.6 | BW39: 2.6 | BX39: 2.6 | BY39: 2.6 | BZ39: 2.6 | CA39: 2.6 | CB39: 2.6 | CC39: 2.6 | CD39: 2.6 | CE39: 2.6 | CF39: 2.6 | CG39: 2.6 | CH39: 2.6 | CI39: 2.6 | CJ39: 2.6 | CK39: 2.6 | CL39: 2.6 | CM39: 2.6 | CN39: 2.6 | CO39: 2.6 | CP39: 2.6 | CQ39: 2.73 | CR39: 2.73 | CS39: 2.73 | CT39: 2.73 | CU39: 2.73 | CV39: 2.73 | CW39: 2.73 | CX39: 2.73 | CY39: 2.73 | CZ39: 2.73 | DA39: 2.73 | DB39: 2.73 | DC39: 2.73 | DD39: 2.73 | DE39: 2.73 | DF39: 2.73 | DG39: 2.73 | DH39: 2.73 | DI39: 2.73 | DJ39: 2.73 | DK39: 2.73 | DL39: 2.73
Q40: 0.03
Q41: 0.25
A42: Net Income | B42: =B23-SUM(B25:B29)-SUM(B33:B38) -> 4436.57 | C42: =C23-SUM(C25:C29)-SUM(C33:C38) -> 1583.62 | D42: =D23-SUM(D25:D29)-SUM(D33:D38) -> 1583.61 | E42: =E23-SUM(E25:E29)-SUM(E33:E38) -> 1733.66 | F42: =F23-SUM(F25:F29)-SUM(F33:F38) -> 2033.65 | G42: =G23-SUM(G25:G29)-SUM(G33:G38) -> 2033.65 | H42: =H23-SUM(H25:H29)-SUM(H33:H38) -> 2033.66 | I42: =I23-SUM(I25:I29)-SUM(I33:I38) -> 2179.34 | ... P42: =P23-SUM(P25:P29)-SUM(P33:P38) -> 2738.66 | Q42: =Q23-SUM(Q25:Q29)-SUM(Q33:Q41) -> 3898.6057 | R42: =R23-SUM(R25:R29)-SUM(R33:R38)-R22-1.55 -> 1718.23 | S42: =S23-SUM(S25:S29)-SUM(S33:S38)-S22-1.55 -> 1718.23 | T42: =T23-SUM(T25:T29)-SUM(T33:T38)-1.42 -> 2176.22 | U42: =U23-SUM(U25:U29)-SUM(U33:U38)-1.55 -> 2240.07 | V42: =V23-SUM(V25:V29)-SUM(V33:V38)-1.55 -> 2240.07 | W42: =W23-SUM(W25:W29)-SUM(W33:W38)-1.55 -> 2240.08 | X42: =X23-SUM(X25:X29)-SUM(X33:X38)-1.55 -> 2240.07 | Y42: =Y23-SUM(Y25:Y29)-SUM(Y33:Y38)-1.92 -> 2482.89 | Z42: =Z23-SUM(Z25:Z29)-SUM(Z33:Z38)-1.92 -> 2482.9 | AA42: =AA23-SUM(AA25:AA29)-SUM(AA33:AA38)-1.92 -> 2482.9 | AB42: =AB23-SUM(AB25:AB29)-SUM(AB33:AB38)-1.92 -> 2482.89 | AC42: =AC23-SUM(AC25:AC29)-SUM(AC33:AC38)-1.92 -> 2482.9 | AD42: =AD23-SUM(AD25:AD29)-SUM(AD33:AD38)-1.92 -> 2482.89 | AE42: =AE23-SUM(AE25:AE29)-SUM(AE33:AE38)-1.92 -> 2482.9 | AF42: =AF23-SUM(AF25:AF29)-SUM(AF33:AF38)-1.92 -> 2482.9 | ... AH42: =AH23-SUM(AH25:AH29)-SUM(AH33:AH38)-1.92 -> 1952.12 | AI42: =AI23-SUM(AI25:AI31)-SUM(AI33:AI38)-1.92 -> 1833.18 | AJ42: =AJ23-SUM(AJ25:AJ31)-SUM(AJ33:AJ38)-1.92 -> 1810.2 | AK42: =AK23-SUM(AK25:AK31)-SUM(AK33:AK38)-1.92 -> 1810.2 | AL42: =AL23-SUM(AL25:AL31)-SUM(AL33:AL38)-1.92 -> 1810.21 | AM42: =AM23-SUM(AM25:AM31)-SUM(AM33:AM38)-1.92 -> 1810.19 | AN42: =AN23-SUM(AN25:AN31)-SUM(AN33:AN38)-1.92 -> 1810.2 | AO42: =AO23-SUM(AO25:AO31)-SUM(AO33:AO38)-1.92 -> 1810.2 | AP42: =AP23-SUM(AP25:AP31)-SUM(AP33:AP38)-1.92 -> 1810.2 | AQ42: =AQ23-SUM(AQ25:AQ31)-SUM(AQ33:AQ38)-1.92+AQ12 -> 3607.74 | AR42: =AR23-SUM(AR25:AR31)-SUM(AR33:AR38)-1.92+AR12 -> 3183.44 | AS42: =AS23-SUM(AS25:AS31)-SUM(AS33:AS38)-1.92+AS12 -> 1781.15 | AT42: =AT23-SUM(AT25:AT31)-SUM(AT33:AT38)-1.92+AT12 -> 1782.11 | AU42: =AU23-SUM(AU25:AU31)-SUM(AU33:AU38)-1.92+AU12 -> 1936.74 | AV42: =AV23-SUM(AV25:AV31)-SUM(AV33:AV38)-1.92+AV12 -> 2656.91 | AW42: =AW23-SUM(AW25:AW31)-SUM(AW33:AW38)-1.92+AW12 -> 2656.9 | AX42: =AX23-SUM(AX25:AX31)-SUM(AX33:AX38)-1.92+AX12 -> 2656.9 | ... BJ42: =BJ23-SUM(BJ25:BJ31)-SUM(BJ33:BJ38)-1.92+BJ12 -> 3281.9796 | BK42: =BK23-SUM(BK25:BK31)-SUM(BK33:BK38)+BK12 -> 3214.9485 | BL42: =BL23-SUM(BL25:BL31)-SUM(BL33:BL38)+BL12 -> 3214.9485 | BM42: =BM23-SUM(BM25:BM31)-SUM(BM33:BM38)+BM12 -> 3214.9485 | BN42: =BN23-SUM(BN25:BN31)-SUM(BN33:BN38)+BN12 -> 3214.9585 | BO42: =BO23-SUM(BO25:BO31)-SUM(BO33:BO38)+BO12 -> 3214.9385 | BP42: =BP23-SUM(BP25:BP31)-SUM(BP33:BP38)+BP12 -> 3215.0185 | BQ42: =BQ23-SUM(BQ25:BQ31)-SUM(BQ33:BQ39)+BQ12 -> 3347.6785 | BR42: =BR23-SUM(BR25:BR31)-SUM(BR33:BR39)+BR12 -> 3347.6785 | BS42: =BS23-SUM(BS25:BS31)-SUM(BS33:BS39)+BS12 -> 5685.3685 | BT42: =BT23-SUM(BT25:BT31)-SUM(BT33:BT39)+BT12 -> 3347.6785 | BU42: =BU23-SUM(BU25:BU31)-SUM(BU33:BU39)+BU12 -> 5289.9208 | BV42: =BV23-SUM(BV25:BV31)-SUM(BV33:BV39)+BV12 -> 3551.2208 | BW42: =BW23-SUM(BW25:BW31)-SUM(BW33:BW39)+BW12 -> 3517.03 | BX42: =BX23-SUM(BX25:BX31)-SUM(BX33:BX39)+BX12 -> 3517.04 | ... CQ42: =CQ23-SUM(CQ25:CQ31)-SUM(CQ33:CQ39)+CQ12 -> 2472.57 | CR42: =CR23-SUM(CR25:CR31)-SUM(CR33:CR39) -> 4361.59 | CS42: =CS23-SUM(CS25:CS31)-SUM(CS33:CS39)+CS12 -> 2472.57 | CT42: =CT23-SUM(CT25:CT31)-SUM(CT33:CT39)+CT12 -> 2472.57 | CU42: =CU23-SUM(CU25:CU31)-SUM(CU33:CU39)+CU12 -> 8304.32 | CV42: =CV23-SUM(CV25:CV31)-SUM(CV33:CV39)+CV12 -> 2586.02 | CW42: =CW23-SUM(CW25:CW31)-SUM(CW33:CW39)+CW12 -> 2586.01 | CX42: =CX23-SUM(CX25:CX31)-SUM(CX33:CX39)+CX12 -> 2586.02 | CY42: =CY23-SUM(CY25:CY31)-SUM(CY33:CY39)+CY12 -> 968.44 | CZ42: =CZ23-SUM(CZ25:CZ31)-SUM(CZ33:CZ39)+CZ12 -> 3695 | ... DH42: =DH23-SUM(DH25:DH31)-SUM(DH33:DH39)+DH12 -> 3695 | DI42: =DI23-SUM(DI25:DI31)-SUM(DI33:DI39)-DI12 -> 4692.98 | DJ42: =DJ23-SUM(DJ25:DJ31)-SUM(DJ33:DJ39)+DJ12 -> 3695 | DK42: =DK23-SUM(DK25:DK31)-SUM(DK33:DK39)+DK12 -> 3695 | DL42: =DL23-SUM(DL25:DL31)-SUM(DL33:DL39)+DL12 -> 3015.4069 | DM42: =DM23-SUM(DM25:DM31)-SUM(DM33:DM39)+DM12 -> 0 | DN42: =DN23-SUM(DN25:DN31)-SUM(DN33:DN39)+DN12 -> 0 | DO42: =DO23-SUM(DO25:DO31)-SUM(DO33:DO39)+DO12 -> 0 | DP42: =SUM(CQ42:DO42) -> 77163.447
A43: Taxes
A44: OASDI | B44: =B25/B$23 -> 0.062000156 | C44: =C25/C$23 -> 0.062028703 | D44: =D25/D$23 -> 0.062028703 | E44: =E25/E$23 -> 0.062028703 | F44: =F25/F$23 -> 0.062028703 | G44: =G25/G$23 -> 0.062028703 | H44: =H25/H$23 -> 0.062028703 | I44: =I25/I$23 -> 0.062028703 | ... DL44: =DL25/DL$23 -> 0.090963269
A45: Medicare | B45: =B26/B$23 -> 0.014500535 | C45: =C26/C$23 -> 0.014504639 | D45: =D26/D$23 -> 0.014508114 | E45: =E26/E$23 -> 0.014504639 | F45: =F26/F$23 -> 0.014508114 | G45: =G26/G$23 -> 0.014508114 | H45: =H26/H$23 -> 0.014504639 | I45: =I26/I$23 -> 0.014508114 | ... DL45: =DL26/DL$23 -> 0.021273805
A46: Federal | B46: =B27/B$23 -> 0.18032705 | C46: =C27/C$23 -> 0.12637871 | D46: =D27/D$23 -> 0.12637871 | E46: =E27/E$23 -> 0.12636481 | F46: =F27/F$23 -> 0.12636481 | G46: =G27/G$23 -> 0.12636481 | H46: =H27/H$23 -> 0.12636481 | I46: =I27/I$23 -> 0.12636481 | ... DL46: =DL27/DL$23 -> 0.15245235
A47: State Tax (VA) | B47: =B28/B$23 -> 0.054579259 | C47: =C28/C$23 -> 0.050627237 | D47: =D28/D$23 -> 0.050627237 | E47: =E28/E$23 -> 0.050627237 | F47: =F28/F$23 -> 0.050627237 | G47: =G28/G$23 -> 0.050627237 | H47: =H28/H$23 -> 0.050627237 | I47: =I28/I$23 -> 0 | ... DL47: =DL28/DL$23 -> 0
A48: State Tax (AZ) | B48: =B29/(B$23-B22) -> 0.035999806 | C48: =C29/(C$23-C22) -> 0.036018348 | D48: =D29/(D$23-D22) -> 0.036018348 | E48: =E29/(E$23-E22) -> 0.036018348 | F48: =F29/(F$23-F22) -> 0.036018348 | G48: =G29/(G$23-G22) -> 0.036018348 | H48: =H29/(H$23-H22) -> 0.036018348 | I48: =I29/(I$23-I22) -> 0.036018348 | ... DL48: =DL29/(DL$23-DL22) -> 0
A49: State Tax (CA) | AI49: =AI30/(AI$23-AI22) -> 0.061885447 | AJ49: =AJ30/(AJ$23-AJ22) -> 0.062309126 | AK49: =AK30/(AK$23-AK22) -> 0.062309126 | AL49: =AL30/(AL$23-AL22) -> 0.062309126 | AM49: =AM30/(AM$23-AM22) -> 0.062309126 | AN49: =AN30/(AN$23-AN22) -> 0.062309126 | AO49: =AO30/(AO$23-AO22) -> 0.062309126 | AP49: =AP30/(AP$23-AP22) -> 0.062309126 | ... CW49: =CW30/(CW$23-CW22) -> 0.10362865 | CX49: 0.10362865 | CY49: 0.10362865 | CZ49: 0.10362865 | DA49: 0.10362865 | DB49: 0.10362865 | DC49: 0.10362865 | DD49: 0.10362865 | DE49: 0.10362865 | DF49: 0.10362865 | DG49: 0.10362865 | DH49: 0.10362865 | DI49: 0.10362865 | DJ49: 0.10362865 | DK49: 0.10362865 | DL49: 0.10362865
A50: CA SDI - CASDI | AI50: =AI31/(AI$23-AI22) -> 0.011287376 | AJ50: =AJ31/(AJ$23-AJ22) -> 0.011364651 | AK50: =AK31/(AK$23-AK22) -> 0.011364651 | AL50: =AL31/(AL$23-AL22) -> 0.011361675 | AM50: =AM31/(AM$23-AM22) -> 0.011364651 | AN50: =AN31/(AN$23-AN22) -> 0.011364651 | AO50: =AO31/(AO$23-AO22) -> 0.011364651 | AP50: =AP31/(AP$23-AP22) -> 0.011364651 | ... CW50: =CW31/(CW$23-CW22) -> 0.030033896 | CX50: 0.030033896 | CY50: 0.030033896 | CZ50: 0.030033896 | DA50: 0.030033896 | DB50: 0.030033896 | DC50: 0.030033896 | DD50: 0.030033896 | DE50: 0.030033896 | DF50: 0.030033896 | DG50: 0.030033896 | DH50: 0.030033896 | DI50: 0.030033896 | DJ50: 0.030033896 | DK50: 0.030033896 | DL50: 0.030033896
A51: Nationwide Savings Plan | B51: =B22/B11 -> 0 | C51: =C22/C11 -> 0 | D51: =D22/D11 -> 0 | E51: =E22/E11 -> 0 | F51: =F22/F11 -> 0 | G51: =G22/G11 -> 0 | H51: =H22/H11 -> 0 | I51: =I22/I11 -> 0 | ... CT51: =CT22/CT11 -> 0.29999962 | CU51: =CU22/(CU11+CU7) -> 0.3000002 | CV51: =CV22/CV11 -> 0.3000009 | CW51: =CW22/CW11 -> 0.3000009 | CX51: =CX22/CX11 -> 0.3000009 | CY51: =CY22/CY11 -> 0.7000009 | CZ51: =CZ22/CZ11 -> 0 | DA51: =DA22/DA11 -> 0 | DB51: =DB22/DB11 -> 0 | DC51: =DC22/DC11 -> 0 | ... DL51: =DL22/DL11 -> 0.31765785
A52: Roth | B52: =B38/B11 -> 0 | C52: =C38/C11 -> 0 | D52: =D38/D11 -> 0 | E52: =E38/E11 -> 0 | F52: =F38/F11 -> 0 | G52: =G38/G11 -> 0 | H52: =H38/H11 -> 0 | I52: =I38/I11 -> 0 | ... AQ52: =AQ38/AQ11 -> 0.14999986 | AR52: =AR38/(AR11+AR13) -> 0.15000046 | AS52: =AS38/(AS11+AS13) -> 0.17000003 | AT52: =AT38/(AT11+AT13) -> 0.17000003 | AU52: =AU38/(AU11+AU13) -> 0.18 | AV52: =AV38/(AV11+AV13) -> 0 | AW52: =AW38/(AW11+AW13) -> 0 | AX52: =AX38/(AX11+AX13) -> 0 | AY52: =AY38/(AY11+AY13) -> 0 | ... DL52: =DL38/(DL11+DL13) -> 0
B53: =SUM(B51:B52) -> 0 | C53: =SUM(C51:C52) -> 0 | D53: =SUM(D51:D52) -> 0 | E53: =SUM(E51:E52) -> 0 | F53: =SUM(F51:F52) -> 0 | G53: =SUM(G51:G52) -> 0 | H53: =SUM(H51:H52) -> 0 | I53: =SUM(I51:I52) -> 0 | ... DL53: =SUM(DL51:DL52) -> 0.31765785
A55: SOFI | AQ55: =AQ42*0.85 -> 3066.579 | AR55: =AR42*0.85 -> 2705.924 | AS55: =AS42*0.85 -> 1513.9775 | AT55: =AT42*0.85 -> 1514.7935 | AU55: =AU42*0.85 -> 1646.229 | AV55: =AV42*0.85 -> 2258.3735 | AW55: =AW42*0.85 -> 2258.365 | AX55: =AX42*0.85 -> 2258.365 | ... DL55: =DL42*0.85 -> 2563.0959 | DP55: =SUM(CQ55:DO55) -> 65588.93
A56: WF | AQ56: =AQ42*0.15 -> 541.161 | AR56: =AR42*0.15 -> 477.516 | AS56: =AS42*0.15 -> 267.1725 | AT56: =AT42*0.15 -> 267.3165 | AU56: =AU42*0.15 -> 290.511 | AV56: =AV42*0.15 -> 398.5365 | AW56: =AW42*0.15 -> 398.535 | AX56: =AX42*0.15 -> 398.535 | ... DL56: =DL42*0.15 -> 452.31104 | DP56: =SUM(CQ56:DO56) -> 11574.517
A58: Base | AQ58: =AQ11*26 -> 92000.22 | AR58: =AR11*26 -> 92000.22 | AS58: =AS11*26 -> 92000.22 | AT58: =AT11*26 -> 92000.22 | AU58: =AU11*26 -> 104000 | AV58: =AV11*26 -> 104000 | AW58: =AW11*26 -> 104000 | AX58: =AX11*26 -> 104000 | ... DK58: =DK11*26 -> 144397.5 | DL58: 179220
A60: Employer Match | J60: 75 | K60: 120.01 | L60: 119.99 | M60: 120 | N60: 120 | O60: 120 | P60: 171.07 | Q60: 248.45 | R60: 123.08 | S60: 123.08 | T60: 123.07 | U60: 126.93 | V60: 119.25 | W60: -0.02 | X60: 0.01 | Y60: -0.01 | Z60: -0.01 | AA60: 0.01 | AB60: 0.02 | AC60: -0.04 | AD60: 0.01 | AE60: 0.02 | AF60: -0.01 | AG60: 265.41 | AH60: 265.37 | AI60: 265.38 | AJ60: 265.43 | AK60: 265.38 | AL60: 265.36 | AM60: 265.38 | AN60: 265.37 | AO60: 265.44 | AP60: 265.33 | AQ60: 141.54 | AR60: 261.98 | AS60: 141.54 | AT60: 141.54 | AU60: 160 | AV60: 160 | AW60: 160 | AX60: 160 | AY60: 160 | AZ60: 160 | BA60: 71.57 | BC60: -0.04 | BD60: 0.02 | BE60: 0.04 | BF60: -0.05 | BG60: 0.06 | BH60: -0.07 | BI60: 0.03 | BJ60: 0.02 | BK60: 0.02 | BL60: -0.01 | BM60: -0.04 | BN60: 0.03 | BO60: -0.05 | BP60: 0.01 | CQ60: 210.37 | CR60: 210.37 | CS60: 210.37 | CT60: 210.37 | CU60: 815.1 | CV60: 222.15 | CW60: 222.15 | CX60: 222.15 | CY60: 222.15 | CZ60: 222.15 | DA60: 222.15 | DB60: 222.15 | DC60: 222.15 | DD60: 222.15 | DE60: 222.15 | DF60: 222.15 | DG60: 222.15 | DH60: 222.15 | DI60: 222.15 | DJ60: 222.15 | DK60: 222.15 | DL60: 275.72 | DP60: =SUM(CQ60:DL60) -> 5486.7 | DQ60: =DP60/144398 -> 0.037997064
J61: =J60/J11 -> 0.025 | K61: =K60/K11 -> 0.040003333 | L61: =L60/L11 -> 0.039996667 | M61: =M60/M11 -> 0.04 | N61: =N60/N11 -> 0.04 | O61: =O60/O11 -> 0.04 | P61: =P60/SUM(P11,P7) -> 0.039998317 | Q61: =Q60/SUM(Q11,Q7) -> 0.039999549 | R61: =R60/SUM(R11,R7) -> 0.04000091 | S61: =S60/SUM(S11,S7) -> 0.04000091 | T61: =T60/SUM(T11,T7) -> 0.03999766 | U61: =U60/SUM(U11,U7) -> 0.040002143 | V61: =V60/SUM(V11,V7) -> 0.037581782 | W61: =W60/SUM(W11,W7) -> -6.3030242e-06 | ... AB61: =AB60/SUM(AB11,AB7) -> 5.6521604e-06 | AC61: =AC60/AC11 -> -1.1304321e-05 | AD61: =AD60/AD11 -> 2.8260802e-06 | AE61: =AE60/AE11 -> 5.6521604e-06 | AF61: =AF60/AF11 -> -2.8260802e-06 | AG61: =AG60/AG11 -> 0.075006995 | AH61: =AH60/AH11 -> 0.07499569 | AI61: =AI60/AI11 -> 0.074998516 | AJ61: =AJ60/AJ11 -> 0.075012647 | ... AQ61: =AQ60/AQ11 -> 0.040000339 | AR61: =AR60/(AR11+AR13) -> 0.039999511 | AS61: =AS60/AS11 -> 0.040000339 | AT61: =AT60/AT11 -> 0.040000339 | AU61: =AU60/AU11 -> 0.04 | AV61: =AV60/AV11 -> 0.04 | AW61: =AW60/AW11 -> 0.04 | AX61: =AX60/AX11 -> 0.04 | AY61: =AY60/AY11 -> 0.04 | AZ61: =AZ60/AZ11 -> 0.04 | BA61: =BA60/BA11 -> 0.0178925

Sheet Summary
B1: Base Pay | C1: Gross | D1: Net | E1: Vincent Loan Repayment | F1: Traveling | G1: Vincent Dental | H1: Student Loans | I1: Care Credit | J1: Laptop | K1: % Base | L1: 401K (pre Tax) | M1: 401k Roth | N1: 401K After Tax | P1: Rollover | Q1: Change in Market Value | R1: Withdrawals | S1: Fees | T1: Company Match | U1: Account Balance | W1: Max Company Match Reference | Y1: Actual Dollar Match Received | AC1: Date | AD1: N Days | AE1: Year
A2: =2021 -> 2021 | B2: =SUMIFS(AH:AH,AE:AE,A2) -> 45616.438 | C2: =SUMIFS(Pay!$23:$23,Pay!$4:$4,Summary!$A2) -> 53322.44 | D2: =SUMIFS(Pay!$42:$42,Pay!$4:$4,Summary!$A2) -> 35911.626 | K2: =SUM(E2:I2)/B2 -> 0 | L2: =SUMIFS(Pay!$22:$22,Pay!$5:$5,Summary!$A2) -> 822.15 | M2: =SUMIFS(Pay!$38:$38,Pay!$5:$5,Summary!$A2) -> 870 | N2: =SUMIFS(Pay!$35:$35,Pay!$5:$5,Summary!$A2) -> 1200 | O2: =SUM(L2:N2)/B2 -> 0.063401486 | Q2: 39.48 | R2: -1202 | T2: =SUMIFS(Pay!$60:$60,Pay!$5:$5,Summary!$A2) -> 846.07 | U2: =SUM(L2:T2) -> 2575.7634 | V2: =T2/SUM(L2:M2) -> 0.49999705 | W2: =0.08*B2 -> 3649.3151 | X2: =IFERROR(SUM(L2:M2)/W2,"") -> 0.46368975 | Y2: =W2/2 -> 1824.6575 | Z2: =IFERROR(T2/Y2,"") -> 0.46368701 | AB2: 179220 | AC2: 45943 | AD2: =AF2-AC2 -> 18 | AE2: 2025 | AF2: 45961 | AG2: =AD2/303 -> 0.059405941 | AH2: =SUMPRODUCT(AG2:AG4,AB2:AB4) -> 145278.37
A3: 2022 | B3: =SUMIFS(AH:AH,AE:AE,A3) -> 88613.699 | C3: =SUMIFS(Pay!$23:$23,Pay!$4:$4,Summary!$A3) -> 84895.83 | D3: =SUMIFS(Pay!$42:$42,Pay!$4:$4,Summary!$A3) -> 56452.7 | K3: =SUM(E3:I3)/B3 -> 0 | L3: =SUMIFS(Pay!$22:$22,Pay!$5:$5,Summary!$A3) -> 1727.69 | M3: =SUMIFS(Pay!$38:$38,Pay!$5:$5,Summary!$A3) -> 5307.7 | N3: =SUMIFS(Pay!$35:$35,Pay!$5:$5,Summary!$A3) -> 0 | O3: =SUM(L3:N3)/B3 -> 0.079393932 | P3: 305.53 | Q3: -609 | S3: -32 | T3: =SUMIFS(Pay!$60:$60,Pay!$5:$5,Summary!$A3) -> 3517.69 | U3: =SUM(L3:T3) -> 10217.689 | V3: =T3/SUM(L3:M3) -> 0.49999929 | W3: =0.08*B3 -> 7089.0959 | X3: =IFERROR(SUM(L3:M3)/W3,"") -> 0.99242416 | Y3: =W3/2 -> 3544.5479 | Z3: =IFERROR(T3/Y3,"") -> 0.99242274 | AB3: 144397.5 | AC3: 45705 | AD3: =AF3-AC3 -> 238 | AE3: 2025 | AF3: 45943 | AG3: =AD3/303 -> 0.78547855
A4: 2023 | B4: =SUMIFS(AH:AH,AE:AE,A4) -> 110153.42 | C4: =SUMIFS(Pay!$23:$23,Pay!$4:$4,Summary!$A4) -> 109567 | D4: =SUMIFS(Pay!$42:$42,Pay!$4:$4,Summary!$A4) -> 72424.558 | E4: 12174 | H4: =447.1+426.16 -> 873.26 | I4: 2347.03 | K4: =SUM(E4:I4)/B4 -> 0.13975317 | L4: =SUMIFS(Pay!$22:$22,Pay!$5:$5,Summary!$A4) -> 0 | M4: =SUMIFS(Pay!$38:$38,Pay!$5:$5,Summary!$A4) -> 3436.29 | N4: =SUMIFS(Pay!$35:$35,Pay!$5:$5,Summary!$A4) -> 0 | O4: =SUM(L4:N4)/B4 -> 0.031195489 | Q4: 3351.85 | S4: -14.88 | T4: =SUMIFS(Pay!$60:$60,Pay!$5:$5,Summary!$A4) -> 1718.14 | U4: =SUM(L4:T4) -> 8491.4312 | V4: =T4/SUM(L4:M4) -> 0.49999854 | W4: =0.08*B4 -> 8812.274 | X4: =IFERROR(SUM(L4:M4)/W4,"") -> 0.38994362 | Y4: =W4/2 -> 4406.137 | Z4: =IFERROR(T4/Y4,"") -> 0.38994248 | AB4: 136740 | AC4: 45658 | AD4: =AC3-AC4 -> 47 | AG4: =AD4/303 -> 0.15511551
A5: 2024 | B5: =SUMIFS(AH:AH,AE:AE,A5) -> 135700.93 | C5: =SUMIFS(Pay!$23:$23,Pay!$4:$4,Summary!$A5) -> 139979.67 | D5: =SUMIFS(Pay!$42:$42,Pay!$4:$4,Summary!$A5) -> 94967.257 | E5: 8687.32 | F5: 3000 | H5: 6169.45 | I5: 8924.44 | J5: 1409.69 | K5: =SUM(E5:J5)/B5 -> 0.20774286 | L5: =SUMIFS(Pay!$22:$22,Pay!$5:$5,Summary!$A5) -> 0 | M5: =SUMIFS(Pay!$38:$38,Pay!$5:$5,Summary!$A5) -> 0 | N5: =SUMIFS(Pay!$35:$35,Pay!$5:$5,Summary!$A5) -> 0 | O5: =SUM(L5:N5)/B5 -> 0 | Q5: 2774.81 | S5: -10.88 | T5: =SUMIFS(Pay!$60:$60,Pay!$5:$5,Summary!$A5) -> 0 | U5: =SUM(L5:T5) -> 2763.93 | V5: =IFERROR(T5/SUM(L5:M5),0) -> 0 | W5: =0.08*B5 -> 10856.075 | X5: =IFERROR(SUM(L5:M5)/W5,"") -> 0 | Y5: =W5/2 -> 5428.0373 | Z5: =IFERROR(T5/Y5,"") -> 0 | AB5: 136740 | AC5: 45341 | AD5: =AF5-AC5 -> 316 | AE5: =YEAR(AF5) -> 2024 | AF5: 45657 | AG5: =AD5/365 -> 0.86575342 | AH5: =SUMPRODUCT(AG5:AG6,AB5:AB6) -> 135700.93
A6: 2025 | B6: =SUMIFS(AH:AH,AE:AE,A6) -> 145278.37 | C6: =SUMIFS(Pay!$23:$23,Pay!$4:$4,Summary!$A6) -> 113871.09 | D6: =SUMIFS(Pay!$42:$42,Pay!$4:$4,Summary!$A6) -> 74690.877 | F6: 5724.66 | G6: =3000-2160 -> 840 | I6: 3364.89 | K6: =SUM(E6:J6)/B6 -> 0.068348442 | L6: =SUMIFS(Pay!$22:$22,Pay!$5:$5,Summary!$A6) -> 23500 | M6: =SUMIFS(Pay!$38:$38,Pay!$5:$5,Summary!$A6) -> 0 | N6: =SUMIFS(Pay!$35:$35,Pay!$5:$5,Summary!$A6) -> 0 | O6: =SUM(L6:N6)/B6 -> 0.16175843 | Q6: 5487.04 | S6: -7.04 | T6: =SUMIFS(Pay!$60:$60,Pay!$5:$5,Summary!$A6) -> 5486.7 | U6: =SUM(L6:T6) -> 34466.862 | V6: =T6/SUM(L6:M6) -> 0.2334766 | W6: =0.08*B6 -> 11622.269 | X6: =IFERROR(SUM(L6:M6)/W6,"") -> 2.0219803 | Y6: =W6/2 -> 5811.1347 | Z6: =IFERROR(T6/Y6,"") -> 0.94417017 | AB6: 129000 | AC6: 45292 | AD6: =AC5-AC6 -> 49 | AE6: =AE5 -> 2024 | AG6: =AD6/365 -> 0.13424658
A7: Total | B7: =SUM(B2:B6) -> 525362.86 | C7: =SUM(C2:C6) -> 501636.02 | D7: =SUM(D2:D6) -> 334447.02 | E7: =SUM(E2:E6) -> 20861.32 | F7: =SUM(F2:F6) -> 8724.66 | G7: =SUM(G2:G6) -> 840 | H7: =SUM(H2:H6) -> 7042.71 | I7: =SUM(I2:I6) -> 14636.36 | J7: =SUM(J2:J6) -> 1409.69 | L7: =SUM(L2:L6) -> 26049.84 | M7: =SUM(M2:M6) -> 9613.99 | N7: =SUM(N2:N6) -> 1200 | P7: =SUM(P3:P6) -> 305.53 | Q7: =SUM(Q2:Q6) -> 11044.18 | R7: =SUM(R2:R6) -> -1202 | S7: =SUM(S2:S6) -> -64.8 | T7: =SUM(T2:T6) -> 11568.6 | U7: =SUM(L7:T7) -> 58515.34 | V7: =AVERAGE(V2:V6) -> 0.3466943 | W7: =0.08*B7 -> 42029.029 | X7: =IFERROR(SUM(L7:M7)/W7,"") -> 0.84855232 | Y7: =0.08*D7 -> 26755.761 | Z7: =IFERROR(T7/Y7,"") -> 0.4323779 | AB7: 129000 | AC7: 45173 | AD7: =AF7-AC7 -> 118 | AE7: =YEAR(AF7) -> 2023 | AF7: 45291 | AG7: =AD7/365 -> 0.32328767 | AH7: =SUMPRODUCT(AG7:AG9,AB7:AB9) -> 110153.42
AB8: 104000 | AC8: 44977 | AD8: =AC7-AC8 -> 196 | AE8: =AE7 -> 2023 | AG8: =AD8/365 -> 0.5369863
AB9: =AB10 -> 92000 | AC9: 44927 | AD9: =AC8-AC9 -> 50 | AE9: =AE8 -> 2023 | AG9: =AD9/365 -> 0.1369863
AB10: 92000 | AC10: 44669 | AD10: =AF10-AC10 -> 257 | AE10: =YEAR(AF10) -> 2022 | AF10: 44926 | AG10: =AD10/365 -> 0.70410959 | AH10: =SUMPRODUCT(AG10:AG12,AB10:AB12) -> 88613.699
AB11: 82500 | AC11: 44613 | AD11: =AC10-AC11 -> 56 | AE11: =AE10 -> 2022 | AG11: =AD11/365 -> 0.15342466
AB12: =AB13 -> 80000 | AC12: 44562 | AD12: =AC11-AC12 -> 51 | AE12: =AE11 -> 2022 | AG12: =AD12/365 -> 0.13972603
AB13: 80000 | AC13: 44543 | AD13: =AF13-AC13 -> 18 | AE13: 2021 | AF13: 44561 | AG13: =AD13/365 -> 0.049315068 | AH13: =SUMPRODUCT(AG13:AG14,AB13:AB14) -> 45616.438
AB14: 78000 | AC14: 44348 | AD14: =AC13-AC14 -> 195 | AE14: 2021 | AG14: =AD14/365 -> 0.53424658
