Workbook

Sheet Data
A1: {=_xlfn._xlws.PY(0,1,Combined_Accounts[#All])} -> #VALUE!
A4: Column1 | B4: ORIG_INDEX | C4: Trans_Date | D4: Description | E4: Amount | F4: Category | G4: Short_Desc | H4: Reoccurring_Flag | I4: Category_2 | J4: Date | K4: Year | L4: Sort_Date | M4: CumAmount | N4: Counter | O4: Account | P4: Last_balance
A5: 0 | B5: 0 | C5: 44927 | D5: Balance | E5: 616.53 | G5: Balance | H5: No | I5: Balance | J5: 44927 | K5: 2023 | L5: 44927 | M5: 616.53 | N5: 1 | O5: wells_fargo_checking | P5: =IF(J5<>J6, 1, 0) -> 1 | R5: =R6+Combined_Accounts[[#This Row],[Amount]] -> 1549.47 | T5: 616.53
A6: 1 | B6: 1 | C6: 45293 | D6: PURCHASE AUTHORIZED ON 01/01 A&A GAS BURLINGAME CA P584001656812755 CARD 1081 | E6: -47.14 | G6: gas | H6: No | I6: Utilities | J6: 45292 | K6: 2024 | L6: 45293 | M6: 569.39 | N6: 1 | O6: wells_fargo_checking | P6: =IF(J6<>J7, 1, 0) -> 0 | R6: =R7+Combined_Accounts[[#This Row],[Amount]] -> 932.94 | T6: =T5+Combined_Accounts[[#This Row],[Amount]] -> 569.39
A7: 2 | B7: 2 | C7: 45293 | D7: PURCHASE AUTHORIZED ON 12/30 REDWOOD CITY PARKI REDWOOD CITY CA S303364838418587 CARD 1081 | E7: -0.5 | G7: parking | H7: No | I7: Transportation | J7: 45292 | K7: 2024 | L7: 45293 | M7: 568.89 | N7: 1 | O7: wells_fargo_checking | P7: =IF(J7<>J8, 1, 0) -> 0 | R7: =R8+Combined_Accounts[[#This Row],[Amount]] -> 980.08 | T7: =T6+Combined_Accounts[[#This Row],[Amount]] -> 568.89
A8: 3 | B8: 3 | C8: 45302 | D8: PURCHASE AUTHORIZED ON 01/11 ARCO#00524MEHRZ MILL VALLEY CA P000000381980594 CARD 1081 | E8: -33.17 | G8: gas | H8: No | I8: Utilities | J8: 45292 | K8: 2024 | L8: 45302 | M8: 535.72 | N8: 2 | O8: wells_fargo_checking | P8: =IF(J8<>J9, 1, 0) -> 0 | R8: =R9+Combined_Accounts[[#This Row],[Amount]] -> 980.58 | T8: =T7+Combined_Accounts[[#This Row],[Amount]] -> 535.72
A9: 4 | B9: 4 | C9: 45302 | D9: PURCHASE AUTHORIZED ON 01/11 ARCO#00524MEHRZ MILL VALLEY CA P000000181526744 CARD 1081 | E9: -12.06 | G9: gas | H9: No | I9: Utilities | J9: 45292 | K9: 2024 | L9: 45302 | M9: 523.66 | N9: 3 | O9: wells_fargo_checking | P9: =IF(J9<>J10, 1, 0) -> 0 | R9: =R10+Combined_Accounts[[#This Row],[Amount]] -> 1013.75 | T9: =T8+Combined_Accounts[[#This Row],[Amount]] -> 523.66
A10: 5 | B10: 5 | C10: 45302 | D10: Nationwide PAYROLL 01 HRP0009988056 Sean Lewis | E10: 502.15 | G10: income | H10: No | I10: Income | J10: 45292 | K10: 2024 | L10: 45302 | M10: 1025.81 | N10: 1 | O10: wells_fargo_checking | P10: =IF(J10<>J11, 1, 0) -> 0 | R10: 1025.81 | T10: =T9+Combined_Accounts[[#This Row],[Amount]] -> 1025.81
A11: 6 | B11: 6 | C11: 45307 | D11: DEPT EDUCATION STUDENT LN 240112 6PN51D9CCK1 SEAN LEWIS | E11: -426.16 | G11: student_loan | H11: Yes | I11: Government | J11: 45292 | K11: 2024 | L11: 45307 | M11: 599.65 | N11: 1 | O11: wells_fargo_checking | P11: =IF(J11<>J12, 1, 0) -> 0 | T11: =T10+Combined_Accounts[[#This Row],[Amount]] -> 599.65
A12: 7 | B12: 7 | C12: 45307 | D12: ZELLE FROM LEWIS JUSTINA ON 01/13 REF # PP0RVXHPT7 CARE CREDIT PAYMENT | E12: 180 | G12: family | H12: No | I12: People | J12: 45292 | K12: 2024 | L12: 45307 | M12: 779.65 | N12: 1 | O12: wells_fargo_checking | P12: =IF(J12<>J13, 1, 0) -> 0 | T12: =T11+Combined_Accounts[[#This Row],[Amount]] -> 779.65
A13: 8 | B13: 8 | C13: 45308 | D13: ZELLE TO LEWIS DORRY ON 01/17 REF #PP0RW6NBQX GIFT NO RETURN | E13: -100 | G13: family | H13: No | I13: People | J13: 45292 | K13: 2024 | L13: 45308 | M13: 679.65 | N13: 2 | O13: wells_fargo_checking | P13: =IF(J13<>J14, 1, 0) -> 0 | T13: =T12+Combined_Accounts[[#This Row],[Amount]] -> 679.65
A14: 9 | B14: 9 | C14: 45308 | D14: STUBHUB CONS PAYMENTS 240117 000000017167884 9016004299-SEAN LEWIS | E14: 123.48 | G14: refunds | H14: No | I14: Income | J14: 45292 | K14: 2024 | L14: 45308 | M14: 803.13 | N14: 1 | O14: wells_fargo_checking | P14: =IF(J14<>J15, 1, 0) -> 0 | T14: =T13+Combined_Accounts[[#This Row],[Amount]] -> 803.13
A15: 10 | B15: 10 | C15: 45309 | D15: T-MOBILE PCS SVC 240117 1121101 DON LEWIS | E15: -111.63 | G15: Don | H15: No | I15: People | J15: 45292 | K15: 2024 | L15: 45309 | M15: 691.5 | N15: 1 | O15: wells_fargo_checking | P15: =IF(J15<>J16, 1, 0) -> 0 | T15: =T14+Combined_Accounts[[#This Row],[Amount]] -> 691.5
A16: 11 | B16: 11 | C16: 45314 | D16: ZELLE TO LEWIS JAYELIN ON 01/23 REF #PP0RWMP6F2 FOR LUNCH | E16: -30 | G16: family | H16: No | I16: People | J16: 45292 | K16: 2024 | L16: 45314 | M16: 661.5 | N16: 3 | O16: wells_fargo_checking | P16: =IF(J16<>J17, 1, 0) -> 0 | T16: =T15+Combined_Accounts[[#This Row],[Amount]] -> 661.5
A17: 12 | B17: 12 | C17: 45314 | D17: VENMO CASHOUT 240123 1032084728310 SEAN LEWIS | E17: 318.83 | G17: venmo | H17: No | I17: People | J17: 45292 | K17: 2024 | L17: 45314 | M17: 980.33 | N17: 1 | O17: wells_fargo_checking | P17: =IF(J17<>J18, 1, 0) -> 0 | T17: =T16+Combined_Accounts[[#This Row],[Amount]] -> 980.33
A18: 13 | B18: 13 | C18: 45315 | D18: Synchrony Bank CC PYMT JAN 23 524306003390321 SEAN LEWIS | E18: -417.29 | G18: care_credit | H18: Yes | I18: Medical | J18: 45292 | K18: 2024 | L18: 45315 | M18: 563.04 | N18: 1 | O18: wells_fargo_checking | P18: =IF(J18<>J19, 1, 0) -> 0 | T18: =T17+Combined_Accounts[[#This Row],[Amount]] -> 563.04
A19: 14 | B19: 14 | C19: 45315 | D19: ZELLE FROM LEWIS JAYELIN ON 01/24 REF # PP0RWQ7TRW PAYING BACK SUIT 200 OUT OF 700 | E19: 200 | G19: family | H19: No | I19: People | J19: 45292 | K19: 2024 | L19: 45315 | M19: 763.04 | N19: 4 | O19: wells_fargo_checking | P19: =IF(J19<>J20, 1, 0) -> 0 | T19: =T18+Combined_Accounts[[#This Row],[Amount]] -> 763.04
A20: 15 | B20: 15 | C20: 45316 | D20: SoFi Bank TRANSFER SD1300 SLewis Sean Lewis:66864:1064 | E20: -500 | G20: misc | H20: No | I20: Misc | J20: 45292 | K20: 2024 | L20: 45316 | M20: 263.04 | N20: 1 | O20: wells_fargo_checking | P20: =IF(J20<>J21, 1, 0) -> 0 | T20: =T19+Combined_Accounts[[#This Row],[Amount]] -> 263.04
A21: 16 | B21: 16 | C21: 45316 | D21: PURCHASE AUTHORIZED ON 01/24 West Town Bank T 8332572512 IL S384025071228723 CARD 1081 | E21: -30.86 | G21: restaurants | H21: No | I21: Personal_Spending | J21: 45292 | K21: 2024 | L21: 45316 | M21: 232.18 | N21: 1 | O21: wells_fargo_checking | P21: =IF(J21<>J22, 1, 0) -> 0 | T21: =T20+Combined_Accounts[[#This Row],[Amount]] -> 232.18
A22: 17 | B22: 17 | C22: 45316 | D22: Nationwide PAYROLL 01 HRP0010014543 Sean Lewis | E22: 502.15 | G22: income | H22: No | I22: Income | J22: 45292 | K22: 2024 | L22: 45316 | M22: 734.33 | N22: 2 | O22: wells_fargo_checking | P22: =IF(J22<>J23, 1, 0) -> 1 | T22: =T21+Combined_Accounts[[#This Row],[Amount]] -> 734.33
... A53: 48 | B53: 48 | C53: 45387 | D53: ZELLE TO LEWIS DORRY ON 04/05 REF #PP0S4Q22SG HOPE THIS HELPS | E53: -200 | G53: family | H53: No | I53: People | J53: 45383 | K53: 2024 | L53: 45387 | M53: 183.6 | N53: 8 | O53: wells_fargo_checking | P53: =IF(J53<>J54, 1, 0) -> 0 | T53: =T52+Combined_Accounts[[#This Row],[Amount]] -> 183.6
A54: 49 | B54: 49 | C54: 45391 | D54: ATM WITHDRAWAL AUTHORIZED ON 04/09 100 E 4th Ave San Mateo CA 0007489 ATM ID 0520C CARD 1081 | E54: -200 | G54: ATM | H54: No | I54: Personal_Spending | J54: 45383 | K54: 2024 | L54: 45391 | M54: -16.4 | N54: 3 | O54: wells_fargo_checking | P54: =IF(J54<>J55, 1, 0) -> 0
A55: 50 | B55: 50 | C55: 45391 | D55: ZELLE FROM LEWIS DORRY ON 04/08 REF # PP0S4ZN6KM | E55: 200 | G55: family | H55: No | I55: People | J55: 45383 | K55: 2024 | L55: 45391 | M55: 183.6 | N55: 9 | O55: wells_fargo_checking | P55: =IF(J55<>J56, 1, 0) -> 0
A56: 51 | B56: 51 | C56: 45392 | D56: ATM CASH DEPOSIT ON 04/10 100 E 4th Ave San Mateo CA 0007790 ATM ID 0520C CARD 1081 | E56: 32 | G56: ATM | H56: No | I56: Personal_Spending | J56: 45383 | K56: 2024 | L56: 45392 | M56: 215.6 | N56: 4 | O56: wells_fargo_checking | P56: =IF(J56<>J57, 1, 0) -> 0
A57: 52 | B57: 52 | C57: 45392 | D57: ATM CASH DEPOSIT ON 04/10 100 E 4th Ave San Mateo CA 0007789 ATM ID 0520C CARD 1081 | E57: 269 | G57: ATM | H57: No | I57: Personal_Spending | J57: 45383 | K57: 2024 | L57: 45392 | M57: 484.6 | N57: 5 | O57: wells_fargo_checking | P57: =IF(J57<>J58, 1, 0) -> 0
A58: 53 | B58: 53 | C58: 45397 | D58: VENMO PAYMENT 240415 1033792256663 SEAN LEWIS | E58: -20 | G58: venmo | H58: No | I58: People | J58: 45383 | K58: 2024 | L58: 45397 | M58: 464.6 | N58: 5 | O58: wells_fargo_checking | P58: =IF(J58<>J59, 1, 0) -> 0
A59: 54 | B59: 54 | C59: 45397 | D59: L A FITNESS 9492558100 041524 49343747 I783466887 | E59: -220 | G59: la_fitness | H59: Yes | I59: Personal_Spending | J59: 45383 | K59: 2024 | L59: 45397 | M59: 244.6 | N59: 2 | O59: wells_fargo_checking | P59: =IF(J59<>J60, 1, 0) -> 0
A60: 55 | B60: 55 | C60: 45397 | D60: PURCHASE AUTHORIZED ON 04/12 OANH LE DDS SAN MATEO CA S464103813791194 CARD 1081 | E60: -44 | G60: dentist | H60: No | I60: Medical | J60: 45383 | K60: 2024 | L60: 45397 | M60: 200.6 | N60: 2 | O60: wells_fargo_checking | P60: =IF(J60<>J61, 1, 0) -> 0
A61: 56 | B61: 56 | C61: 45400 | D61: T-MOBILE PCS SVC 240417 9053559 DON LEWIS | E61: -65.83 | G61: Don | H61: No | I61: People | J61: 45383 | K61: 2024 | L61: 45400 | M61: 134.77 | N61: 4 | O61: wells_fargo_checking | P61: =IF(J61<>J62, 1, 0) -> 0
A62: 57 | B62: 57 | C62: 45400 | D62: Nationwide PAYROLL 01 HRP0010244110 Sean Lewis | E62: 527.56 | G62: income | H62: No | I62: Income | J62: 45383 | K62: 2024 | L62: 45400 | M62: 662.33 | N62: 8 | O62: wells_fargo_checking | P62: =IF(J62<>J63, 1, 0) -> 0
A63: 58 | B63: 58 | C63: 45400 | D63: ZELLE FROM KAI FENG PAN ON 04/17 REF # BACAIP4JOFOT FOR INVISALIGN | E63: 3000 | G63: Vincent | H63: No | I63: People | J63: 45383 | K63: 2024 | L63: 45400 | M63: 3662.33 | N63: 1 | O63: wells_fargo_checking | P63: =IF(J63<>J64, 1, 0) -> 0
A64: 59 | B64: 59 | C64: 45401 | D64: Synchrony Bank CC PYMT Apr 19 524306003390321 SEAN LEWIS | E64: -3000 | G64: care_credit | H64: Yes | I64: Medical | J64: 45383 | K64: 2024 | L64: 45401 | M64: 662.33 | N64: 4 | O64: wells_fargo_checking | P64: =IF(J64<>J65, 1, 0) -> 0
A65: 60 | B65: 60 | C65: 45404 | D65: NON-WELLS FARGO ATM TRANSACTION FEE | E65: -5 | G65: ATM | H65: No | I65: Personal_Spending | J65: 45383 | K65: 2024 | L65: 45404 | M65: 657.33 | N65: 6 | O65: wells_fargo_checking | P65: =IF(J65<>J66, 1, 0) -> 0
... A377: 372 | B377: 372 | C377: 45593 | D377: PURCHASE AUTHORIZED ON 10/26 ARCO#04495SINO SAN MATEO CA P000000172446007 CARD 1081 | E377: -43.98 | G377: gas | H377: No | I377: Utilities | J377: 45566 | K377: 2024 | L377: 45593 | M377: 473.36 | N377: 15 | O377: wells_fargo_checking | P377: =IF(J377<>J378, 1, 0) -> 0
A378: 373 | B378: 373 | C378: 45593 | D378: PURCHASE AUTHORIZED ON 10/25 STADIUM GARAGE BERKELEY CA S584300071995368 CARD 1081 | E378: -30 | G378: starting_balance | H378: No | J378: 45566 | K378: 2024 | L378: 45593 | M378: 443.36 | N378: 1 | O378: wells_fargo_checking | P378: =IF(J378<>J379, 1, 0) -> 0
A379: 374 | B379: 374 | C379: 45596 | D379: Nationwide PAYROLL 01 HRP0010768329 Sean Lewis | E379: 527.56 | G379: income | H379: No | I379: Utilities | J379: 45566 | K379: 2024 | L379: 45596 | M379: 970.92 | N379: 16 | O379: wells_fargo_checking | P379: =IF(J379<>J380, 1, 0) -> 1
A380: 375 | B380: 375 | C380: 45597 | D380: PURCHASE AUTHORIZED ON 11/01 76 ORINDA ORINDA CA P000000177866673 CARD 1081 | E380: -47.24 | G380: gas | H380: No | I380: Utilities | J380: 45597 | K380: 2024 | L380: 45597 | M380: 923.68 | N380: 17 | O380: wells_fargo_checking | P380: =IF(J380<>J381, 1, 0) -> 0
A381: 376 | B381: 376 | C381: 45600 | D381: MONEY TRANSFER AUTHORIZED ON 11/01 CASH APP*CAIRO DAN Oakland CA S304306763501389 CARD 1081 | E381: -150 | G381: gas | H381: No | I381: Utilities | J381: 45597 | K381: 2024 | L381: 45600 | M381: 773.68 | N381: 18 | O381: wells_fargo_checking | P381: =IF(J381<>J382, 1, 0) -> 0
A382: 377 | B382: 377 | C382: 45600 | D382: ZELLE FROM JONATHAN W ABADA ON 11/03 REF # JPM99AQLEFH6 FANTASY | E382: 69 | G382: venmo | H382: No | I382: People | J382: 45597 | K382: 2024 | L382: 45600 | M382: 842.68 | N382: 13 | O382: wells_fargo_checking | P382: =IF(J382<>J383, 1, 0) -> 0
A383: 378 | B383: 378 | C383: 45604 | D383: PURCHASE AUTHORIZED ON 11/08 A&A GAS BURLINGAME CA P584313515259674 CARD 1081 | E383: -37.45 | G383: gas | H383: No | I383: Utilities | J383: 45597 | K383: 2024 | L383: 45604 | M383: 805.23 | N383: 19 | O383: wells_fargo_checking | P383: =IF(J383<>J384, 1, 0) -> 0
A384: 379 | B384: 379 | C384: 45608 | D384: PURCHASE AUTHORIZED ON 11/12 SPWY66304901 OAKLAND CA P000000987765332 CARD 1081 | E384: -47.03 | G384: gas | H384: No | I384: Utilities | J384: 45597 | K384: 2024 | L384: 45608 | M384: 758.2 | N384: 20 | O384: wells_fargo_checking | P384: =IF(J384<>J385, 1, 0) -> 0
A385: 380 | B385: 380 | C385: 45610 | D385: Nationwide PAYROLL 01 HRP0010800464 Sean Lewis | E385: 527.56 | G385: income | H385: No | I385: Income | J385: 45597 | K385: 2024 | L385: 45610 | M385: 1285.76 | N385: 22 | O385: wells_fargo_checking | P385: =IF(J385<>J386, 1, 0) -> 0
A386: 381 | B386: 381 | C386: 45614 | D386: T-MOBILE PCS SVC 241117 9074296 DON LEWIS | E386: -70 | G386: Don | H386: No | I386: People | J386: 45597 | K386: 2024 | L386: 45614 | M386: 1215.76 | N386: 16 | O386: wells_fargo_checking | P386: =IF(J386<>J387, 1, 0) -> 0
A387: 382 | B387: 382 | C387: 45614 | D387: ZELLE TO LEWIS DORRY ON 11/16 REF #PP0Y85LKV3 FOR SKYLAR BDAY WIG AND CAMERA | E387: -500 | G387: family | H387: No | I387: People | J387: 45597 | K387: 2024 | L387: 45614 | M387: 715.76 | N387: 14 | O387: wells_fargo_checking | P387: =IF(J387<>J388, 1, 0) -> 0
A388: 383 | B388: 383 | C388: 45623 | D388: Nationwide PAYROLL 01 HRP0010854952 Sean Lewis | E388: 512.56 | G388: income | H388: No | I388: Income | J388: 45597 | K388: 2024 | L388: 45623 | M388: 1228.32 | N388: 23 | O388: wells_fargo_checking | P388: =IF(J388<>J389, 1, 0) -> 0
A389: 384 | B389: 384 | C389: 45625 | D389: DEPT EDUCATION STUDENT LN 241127 6QHE6VPEDF1 SEAN LEWIS | E389: -442.73 | G389: student_loan | H389: Yes | I389: Government | J389: 45597 | K389: 2024 | L389: 45625 | M389: 785.59 | N389: 5 | O389: wells_fargo_checking | P389: =IF(J389<>J390, 1, 0) -> 1
A390: 385 | B390: 385 | C390: 45638 | D390: Nationwide PAYROLL 01 HRP0010886755 Sean Lewis | E390: 527.56 | G390: income | H390: No | I390: Income | J390: 45627 | K390: 2024 | L390: 45638 | M390: 1313.15 | N390: 24 | O390: wells_fargo_checking | P390: =IF(J390<>J391, 1, 0) -> 0
... A395: 390 | B395: 390 | C395: 45652 | D395: Nationwide PAYROLL 01 HRP0010930330 Sean Lewis | E395: 527.56 | G395: income | H395: No | I395: Income | J395: 45627 | K395: 2024 | L395: 45652 | M395: 1449.98 | N395: 25 | O395: wells_fargo_checking | P395: =IF(J395<>J396, 1, 0) -> 1
A396: 391 | B396: 0 | C396: 44927 | D396: Balance | E396: 227.7 | F396: Balance | G396: Balance | H396: No | I396: Balance | J396: 44927 | K396: 2023 | L396: 44927 | M396: 227.7 | N396: 1 | O396: discover | P396: =IF(J396<>J397, 1, 0) -> 1
A397: 392 | B397: 1 | C397: 45292 | D397: CHATGPT SUBSCRIPTION 4158799686 CA | E397: 20 | F397: Merchandise | G397: chatgpt | H397: Yes | I397: Personal_Spending | J397: 45292 | K397: 2024 | L397: 45292 | M397: 247.7 | N397: 1 | O397: discover | P397: =IF(J397<>J398, 1, 0) -> 0
A398: 393 | B398: 2 | C398: 45292 | D398: JFF PUBLICATIONS WILTON MANORSFL | E398: 24.99 | F398: Merchandise | G398: movies | H398: No | I398: Recreation_Entertainment | J398: 45292 | K398: 2024 | L398: 45292 | M398: 272.69 | N398: 1 | O398: discover | P398: =IF(J398<>J399, 1, 0) -> 0
A399: 394 | B399: 3 | C399: 45292 | D399: PLANNED PARENTHOOD ACTIO NEW YORK NY | E399: 5 | F399: Services | G399: political_cause | H399: Yes | I399: Personal_Spending | J399: 45292 | K399: 2024 | L399: 45292 | M399: 277.69 | N399: 1 | O399: discover | P399: =IF(J399<>J400, 1, 0) -> 0
A400: 395 | B400: 4 | C400: 45292 | D400: SPOTIFY P286B95411 8777781161 NY | E400: 5.99 | F400: Merchandise | G400: spotify | H400: Yes | I400: Recreation_Entertainment | J400: 45292 | K400: 2024 | L400: 45292 | M400: 283.68 | N400: 1 | O400: discover | P400: =IF(J400<>J401, 1, 0) -> 0
A401: 396 | B401: 5 | C401: 45293 | D401: ONEPASS 877-515-9364 MN253067 | E401: 264.1 | F401: Services | G401: onepass | H401: Yes | I401: Personal_Spending | J401: 45292 | K401: 2024 | L401: 45293 | M401: 547.78 | N401: 1 | O401: discover | P401: =IF(J401<>J402, 1, 0) -> 0
A402: 397 | B402: 6 | C402: 45293 | D402: KRYSTAL AND SAAGAR 2025317527 DCITEM TRANSFERRED FROM PREV ACCOUNT | E402: 10 | F402: Merchandise | G402: breaking_points | H402: Yes | I402: Recreation_Entertainment | J402: 45292 | K402: 2024 | L402: 45293 | M402: 557.78 | N402: 1 | O402: discover | P402: =IF(J402<>J403, 1, 0) -> 0
A403: 398 | B403: 7 | C403: 45293 | D403: PADDLE.NET* REALPYTHON 7745236658 NY | E403: 29.99 | F403: Merchandise | G403: real_python | H403: Yes | I403: Personal_Spending | J403: 45292 | K403: 2024 | L403: 45293 | M403: 587.77 | N403: 1 | O403: discover | P403: =IF(J403<>J404, 1, 0) -> 0
A404: 399 | B404: 8 | C404: 45293 | D404: TARGET 00011221091 SAN MATEO CA | E404: 66.32 | F404: Supermarkets | G404: everything_store | H404: No | I404: Personal_Spending | J404: 45292 | K404: 2024 | L404: 45293 | M404: 654.09 | N404: 1 | O404: discover | P404: =IF(J404<>J405, 1, 0) -> 0
A405: 400 | B405: 9 | C405: 45293 | D405: VALVE BELLEVUE WA | E405: 6.99 | F405: Merchandise | G405: video_games | H405: No | I405: Recreation_Entertainment | J405: 45292 | K405: 2024 | L405: 45293 | M405: 661.08 | N405: 1 | O405: discover | P405: =IF(J405<>J406, 1, 0) -> 0
A406: 401 | B406: 10 | C406: 45294 | D406: CCBILL.COM 888-5969279 AZ | E406: 13.39 | F406: Merchandise | G406: onlyfans | H406: No | I406: Recreation_Entertainment | J406: 45292 | K406: 2024 | L406: 45294 | M406: 674.47 | N406: 1 | O406: discover | P406: =IF(J406<>J407, 1, 0) -> 0
A407: 402 | B407: 11 | C407: 45294 | D407: TARGET 00011221091 SAN MATEO CA | E407: 97.96 | F407: Supermarkets | G407: everything_store | H407: No | I407: Personal_Spending | J407: 45292 | K407: 2024 | L407: 45294 | M407: 772.43 | N407: 2 | O407: discover | P407: =IF(J407<>J408, 1, 0) -> 0
... A1124: 1119 | B1124: 728 | C1124: 45579 | D1124: ONLYFANS.COM*A 8886880458 FLITEM TRANSFERRED FROM PREV ACCOUNT | E1124: 5 | F1124: Merchandise | G1124: onlyfans | H1124: No | I1124: Recreation_Entertainment | J1124: 45566 | K1124: 2024 | L1124: 45579 | M1124: 511.11 | N1124: 79 | O1124: discover | P1124: =IF(J1124<>J1125, 1, 0) -> 0
A1125: 1120 | B1125: 729 | C1125: 45579 | D1125: RPS UNIVERSAL INC SAN MATEO CAITEM TRANSFERRED FROM PREV ACCOUNT | E1125: 21.21 | F1125: Merchandise | G1125: misc | H1125: No | I1125: Misc | J1125: 45566 | K1125: 2024 | L1125: 45579 | M1125: 532.32 | N1125: 7 | O1125: discover | P1125: =IF(J1125<>J1575, 1, 0) -> 1
A1126: 1121 | B1126: 730 | C1126: 45579 | D1126: THE HOME DEPOT #0632 SAN MATEO CAITEM TRANSFERRED FROM PREV ACCOUNT | E1126: 4.36 | F1126: Merchandise | G1126: home_supplies | H1126: No | I1126: Housing | J1126: 45566 | K1126: 2024 | L1126: 45579 | M1126: 536.68 | N1126: 3 | O1126: discover | P1126: =IF(J1126<>J1127, 1, 0) -> 0
A1127: 1122 | B1127: 731 | C1127: 45582 | D1127: DD *COBANIGYROSKEBA 6506819470 CAITEM TRANSFERRED FROM PREV ACCOUNT | E1127: 52.15 | F1127: Merchandise | G1127: restaurant | H1127: No | I1127: Food | J1127: 45566 | K1127: 2024 | L1127: 45582 | M1127: 588.83 | N1127: 64 | O1127: discover | P1127: =IF(J1127<>J1128, 1, 0) -> 0
A1128: 1123 | B1128: 732 | C1128: 45583 | D1128: TM *FOSTER THE PEOPLE- 800-653-8000 CANCA/16-46524 | E1128: 124.2 | F1128: Travel/ Entertainment | G1128: concerts | H1128: No | I1128: Recreation_Entertainment | J1128: 45566 | K1128: 2024 | L1128: 45583 | M1128: 713.03 | N1128: 8 | O1128: discover | P1128: =IF(J1128<>J1129, 1, 0) -> 0
A1129: 1124 | B1129: 733 | C1129: 45583 | D1129: TST*WALIA ETHIOPIAN CU SAN JOSE CAITEM TRANSFERRED FROM PREV ACCOUNT | E1129: 109.78 | F1129: Merchandise | G1129: Hawaii | H1129: No | I1129: Travel | J1129: 45566 | K1129: 2024 | L1129: 45583 | M1129: 822.81 | N1129: 52 | O1129: discover | P1129: =IF(J1129<>J1130, 1, 0) -> 0
A1130: 1125 | B1130: 734 | C1130: 45584 | D1130: ONLYFANS.COM*A 8886880458 FLITEM TRANSFERRED FROM PREV ACCOUNT | E1130: 20 | F1130: Merchandise | G1130: onlyfans | H1130: No | I1130: Recreation_Entertainment | J1130: 45566 | K1130: 2024 | L1130: 45584 | M1130: 842.81 | N1130: 80 | O1130: discover | P1130: =IF(J1130<>J1131, 1, 0) -> 0
A1131: 1126 | B1131: 735 | C1131: 45584 | D1131: SPEEDWAY 04976 501 SERRA DALY CITY CAITEM TRANSFERRED FROM PREV ACCOUNT | E1131: 49.06 | F1131: Merchandise | G1131: gas_station | H1131: No | I1131: Transportation | J1131: 45566 | K1131: 2024 | L1131: 45584 | M1131: 891.87 | N1131: 13 | O1131: discover | P1131: =IF(J1131<>J1132, 1, 0) -> 0
A1132: 1127 | B1132: 736 | C1132: 45584 | D1132: MCDONALD'S F3709 DALY CITY CAITEM TRANSFERRED FROM PREV ACCOUNT | E1132: 22.59 | F1132: Merchandise | G1132: fast_food | H1132: No | I1132: Food | J1132: 45566 | K1132: 2024 | L1132: 45584 | M1132: 914.46 | N1132: 35 | O1132: discover | P1132: =IF(J1132<>J1133, 1, 0) -> 0
A1133: 1128 | B1133: 737 | C1133: 45585 | D1133: LIFETIME TENNIS INC - SA SAN FRANCISCOCA | E1133: 19 | F1133: Travel/ Entertainment | G1133: misc | H1133: No | I1133: Misc | J1133: 45566 | K1133: 2024 | L1133: 45585 | M1133: 933.46 | N1133: 8 | O1133: discover | P1133: =IF(J1133<>J1134, 1, 0) -> 0
A1134: 1129 | B1134: 738 | C1134: 45585 | D1134: SOURDOUGH & CO DALY CITY DALY CITY CAITEM TRANSFERRED FROM PREV ACCOUNT | E1134: 17.4 | F1134: Merchandise | G1134: fast_food | H1134: No | I1134: Food | J1134: 45566 | K1134: 2024 | L1134: 45585 | M1134: 950.86 | N1134: 36 | O1134: discover | P1134: =IF(J1134<>J1135, 1, 0) -> 0
A1135: 1130 | B1135: 739 | C1135: 45586 | D1135: ORTHOPEDIC SPORTS MEDICI SAN MATEO CA | E1135: 30 | F1135: Medical Services | G1135: physical_therapy | H1135: Yes | I1135: Medical | J1135: 45566 | K1135: 2024 | L1135: 45586 | M1135: 980.86 | N1135: 1 | O1135: discover | P1135: =IF(J1135<>J1136, 1, 0) -> 0
A1136: 1131 | B1136: 740 | C1136: 45586 | D1136: UNIQLO USA LLC UNIQLO SAN MATEO CA | E1136: 54.7 | F1136: Merchandise | G1136: clothing | H1136: No | I1136: Personal_Spending | J1136: 45566 | K1136: 2024 | L1136: 45586 | M1136: 1035.56 | N1136: 24 | O1136: discover | P1136: =IF(J1136<>J1137, 1, 0) -> 0
A1137: 1132 | B1137: 741 | C1137: 45587 | D1137: AMAZON MKTPL*890TE3PQ3 AMZN.COM/BILLWA7C55N2ACFH9 | E1137: 18.89 | F1137: Merchandise | G1137: everything_store | H1137: No | I1137: Personal_Spending | J1137: 45566 | K1137: 2024 | L1137: 45587 | M1137: 1054.45 | N1137: 61 | O1137: discover | P1137: =IF(J1137<>J1138, 1, 0) -> 0
... A1323: 1318 | B1323: 927 | C1323: 45656 | D1323: GOOGLE *BUMBLE 855-836-3987 CAITEM TRANSFERRED FROM PREV ACCOUNT | E1323: 15.89 | F1323: Merchandise | G1323: bumble | H1323: No | I1323: Recreation_Entertainment | J1323: 45627 | K1323: 2024 | L1323: 45656 | M1323: 882.5 | N1323: 3 | O1323: discover | P1323: =IF(J1323<>J1324, 1, 0) -> 1
A1324: 1319 | B1324: 0 | C1324: 45293 | D1324: DISCOVER | E1324: -1568.14 | G1324: transfer | H1324: No | J1324: 45292 | K1324: 2024 | L1324: 45293 | M1324: 1883.61 | N1324: 1 | O1324: sofi_savings | P1324: =IF(J1324<>J1325, 1, 0) -> 0
A1325: 1320 | B1325: 1 | C1325: 45300 | D1325: Nationwide | E1325: 2845.53 | G1325: income | H1325: No | I1325: Savings | J1325: 45292 | K1325: 2024 | L1325: 45300 | M1325: 4729.14 | N1325: 1 | O1325: sofi_savings | P1325: =IF(J1325<>J1326, 1, 0) -> 0
A1326: 1321 | B1326: 2 | C1326: 45302 | D1326: DISCOVER | E1326: -1382.28 | G1326: transfer | H1326: No | J1326: 45292 | K1326: 2024 | L1326: 45302 | M1326: 3346.86 | N1326: 2 | O1326: sofi_savings | P1326: =IF(J1326<>J1327, 1, 0) -> 0
A1327: 1322 | B1327: 3 | C1327: 45307 | D1327: BOARD OF REGENTS | E1327: -932 | G1327: school | H1327: No | I1327: Personal_Spending | J1327: 45292 | K1327: 2024 | L1327: 45307 | M1327: 2414.86 | N1327: 1 | O1327: sofi_savings | P1327: =IF(J1327<>J1328, 1, 0) -> 0
A1328: 1323 | B1328: 4 | C1328: 45314 | D1328: Nationwide | E1328: 2845.53 | G1328: income | H1328: No | I1328: Savings | J1328: 45292 | K1328: 2024 | L1328: 45314 | M1328: 5105.39 | N1328: 2 | O1328: sofi_savings | P1328: =IF(J1328<>J1329, 1, 0) -> 0
A1329: 1324 | B1329: 5 | C1329: 45314 | D1329: To Checking - 8930 | E1329: -155 | G1329: transfer | H1329: No | J1329: 45292 | K1329: 2024 | L1329: 45314 | M1329: 2259.86 | N1329: 3 | O1329: sofi_savings | P1329: =IF(J1329<>J1330, 1, 0) -> 0
A1330: 1325 | B1330: 6 | C1330: 45315 | D1330: To Checking - 8930 | E1330: -1804 | G1330: transfer | H1330: No | J1330: 45292 | K1330: 2024 | L1330: 45315 | M1330: 3301.39 | N1330: 4 | O1330: sofi_savings | P1330: =IF(J1330<>J1331, 1, 0) -> 0
A1331: 1326 | B1331: 7 | C1331: 45316 | D1331: WELLS FARGO BANK NA | E1331: 500 | G1331: transfer | H1331: No | J1331: 45292 | K1331: 2024 | L1331: 45316 | M1331: 3801.39 | N1331: 5 | O1331: sofi_savings | P1331: =IF(J1331<>J1332, 1, 0) -> 0
A1332: 1327 | B1332: 8 | C1332: 45317 | D1332: DISCOVER | E1332: -2068.37 | G1332: transfer | H1332: No | J1332: 45292 | K1332: 2024 | L1332: 45317 | M1332: 1733.02 | N1332: 6 | O1332: sofi_savings | P1332: =IF(J1332<>J1333, 1, 0) -> 0
A1333: 1328 | B1333: 9 | C1333: 45322 | D1333: Interest earned | E1333: 10.14 | G1333: interest | H1333: No | I1333: Payment_and_Interest | J1333: 45292 | K1333: 2024 | L1333: 45322 | M1333: 1743.16 | N1333: 1 | O1333: sofi_savings | P1333: =IF(J1333<>J1334, 1, 0) -> 1
A1334: 1329 | B1334: 10 | C1334: 45323 | D1334: To Checking - 8930 | E1334: -450 | G1334: transfer | H1334: No | J1334: 45323 | K1334: 2024 | L1334: 45323 | M1334: 1293.16 | N1334: 7 | O1334: sofi_savings | P1334: =IF(J1334<>J1335, 1, 0) -> 0
A1335: 1330 | B1335: 11 | C1335: 45328 | D1335: Nationwide | E1335: 4832.56 | G1335: income | H1335: No | I1335: Savings | J1335: 45323 | K1335: 2024 | L1335: 45328 | M1335: 6125.72 | N1335: 3 | O1335: sofi_savings | P1335: =IF(J1335<>J1336, 1, 0) -> 0
A1336: 1331 | B1336: 12 | C1336: 45329 | D1336: To Checking - 8930 | E1336: -3610 | G1336: transfer | H1336: No | J1336: 45323 | K1336: 2024 | L1336: 45329 | M1336: 2515.72 | N1336: 8 | O1336: sofi_savings | P1336: =IF(J1336<>J1337, 1, 0) -> 0
A1337: 1332 | B1337: 13 | C1337: 45330 | D1337: DISCOVER | E1337: -1166.54 | G1337: transfer | H1337: No | J1337: 45323 | K1337: 2024 | L1337: 45330 | M1337: 1349.18 | N1337: 9 | O1337: sofi_savings | P1337: =IF(J1337<>J1338, 1, 0) -> 0
A1338: 1333 | B1338: 14 | C1338: 45330 | D1338: To Checking - 8930 | E1338: -820 | G1338: transfer | H1338: No | J1338: 45323 | K1338: 2024 | L1338: 45330 | M1338: 529.18 | N1338: 10 | O1338: sofi_savings | P1338: =IF(J1338<>J1339, 1, 0) -> 0
A1339: 1334 | B1339: 15 | C1339: 45335 | D1339: To Checking - 8930 | E1339: -155 | G1339: transfer | H1339: No | J1339: 45323 | K1339: 2024 | L1339: 45335 | M1339: 374.18 | N1339: 11 | O1339: sofi_savings | P1339: =IF(J1339<>J1340, 1, 0) -> 0
A1340: 1335 | B1340: 16 | C1340: 45335 | D1340: IRS TREAS 310 | E1340: 75 | G1340: income | H1340: No | I1340: Savings | J1340: 45323 | K1340: 2024 | L1340: 45335 | M1340: 449.18 | N1340: 4 | O1340: sofi_savings | P1340: =IF(J1340<>J1341, 1, 0) -> 0
A1341: 1336 | B1341: 17 | C1341: 45339 | D1341: To Checking - 8930 | E1341: -50 | G1341: transfer | H1341: No | J1341: 45323 | K1341: 2024 | L1341: 45339 | M1341: 399.18 | N1341: 12 | O1341: sofi_savings | P1341: =IF(J1341<>J1342, 1, 0) -> 0
A1342: 1337 | B1342: 18 | C1342: 45340 | D1342: To Checking - 8930 | E1342: -50 | G1342: transfer | H1342: No | J1342: 45323 | K1342: 2024 | L1342: 45340 | M1342: 349.18 | N1342: 13 | O1342: sofi_savings | P1342: =IF(J1342<>J1343, 1, 0) -> 0
A1343: 1338 | B1343: 19 | C1343: 45342 | D1343: Nationwide | E1343: 2845.53 | G1343: income | H1343: No | I1343: Savings | J1343: 45323 | K1343: 2024 | L1343: 45342 | M1343: 3194.71 | N1343: 5 | O1343: sofi_savings | P1343: =IF(J1343<>J1344, 1, 0) -> 0
A1344: 1339 | B1344: 20 | C1344: 45344 | D1344: DISCOVER | E1344: -1263.14 | G1344: transfer | H1344: No | J1344: 45323 | K1344: 2024 | L1344: 45344 | M1344: 1931.57 | N1344: 14 | O1344: sofi_savings | P1344: =IF(J1344<>J1345, 1, 0) -> 0
A1345: 1340 | B1345: 21 | C1345: 45344 | D1345: To Checking - 8930 | E1345: -900 | G1345: transfer | H1345: No | J1345: 45323 | K1345: 2024 | L1345: 45344 | M1345: 1031.57 | N1345: 15 | O1345: sofi_savings | P1345: =IF(J1345<>J1346, 1, 0) -> 0
A1346: 1341 | B1346: 22 | C1346: 45351 | D1346: Interest earned | E1346: 4.34 | G1346: interest | H1346: No | I1346: Payment_and_Interest | J1346: 45323 | K1346: 2024 | L1346: 45351 | M1346: 1035.91 | N1346: 2 | O1346: sofi_savings | P1346: =IF(J1346<>J1347, 1, 0) -> 1
A1347: 1342 | B1347: 23 | C1347: 45352 | D1347: To Checking - 8930 | E1347: -450 | G1347: transfer | H1347: No | J1347: 45352 | K1347: 2024 | L1347: 45352 | M1347: 585.91 | N1347: 16 | O1347: sofi_savings | P1347: =IF(J1347<>J1348, 1, 0) -> 0
A1348: 1343 | B1348: 24 | C1348: 45356 | D1348: Nationwide | E1348: 4149.3 | G1348: income | H1348: No | I1348: Savings | J1348: 45352 | K1348: 2024 | L1348: 45356 | M1348: 4735.21 | N1348: 6 | O1348: sofi_savings | P1348: =IF(J1348<>J1349, 1, 0) -> 0
...

Sheet Reoccurring
A1: Reoccurring_Flag | B1: Yes
A3: Sum of Amount | B3: Column Labels
A4: Row Labels | B4: 45292 | C4: 45323 | D4: 45352 | E4: 45383 | F4: 45413 | G4: 45444 | H4: 45474 | I4: 45505 | J4: 45536 | K4: 45566 | L4: 45597 | M4: 45627 | N4: Grand Total
A5: adobe | B5: 29.99 | C5: 29.99 | D5: 29.99 | E5: 29.99 | F5: 29.99 | G5: 29.99 | H5: 29.99 | I5: 29.99 | J5: 29.99 | K5: 29.99 | L5: 29.99 | M5: 59.99 | N5: 389.88
A6: apple_care | B6: 9.99 | C6: 9.99 | D6: 9.99 | E6: 9.99 | N6: 39.96
A7: breaking_points | B7: 10 | C7: 10 | D7: 10 | E7: 10 | F7: 10 | G7: 10 | H7: 10 | I7: 10 | J7: 10 | K7: 10 | L7: 10 | M7: 10 | N7: 120
A8: care_credit | B8: -417.29 | C8: -237.29 | D8: -458.96 | E8: -3000 | F8: -458.96 | J8: -460 | N8: -5032.5
A9: cell_phone | C9: -366.21 | D9: 91.98 | L9: 820.34 | M9: 238.98 | N9: 785.09
A10: chatgpt | B10: 20 | C10: 20 | D10: 20 | E10: 20 | F10: 20 | G10: 20 | H10: 20 | I10: 20 | J10: 20 | K10: 20 | L10: 20 | M10: 20 | N10: 240
A11: do_the_bay | B11: 5 | C11: 0 | N11: 5
A12: google_colab | D12: 10.59 | N12: 10.59
A13: gym | B13: 269.5 | C13: 220 | K13: 49.5 | L13: 49.5 | N13: 588.5
A14: hbo | B14: 15.89 | N14: 15.89
A15: interest | B15: 0.04 | C15: 0.21 | D15: 0.17 | E15: 0.12 | F15: 0.18 | G15: 0.21 | H15: 0.33 | I15: 0.37 | J15: 0.65 | K15: 0.53 | L15: 0.62 | M15: 0.68 | N15: 4.11
A16: la_fitness | D16: -220 | E16: -220 | F16: -220 | G16: -220 | H16: 440 | N16: -440
A17: laptop | B17: -155 | C17: -155 | D17: -155 | E17: -155 | F17: -155 | G17: -634.69 | N17: -1409.69
A18: lickd | B18: 15 | N18: 15
A19: onepass | B19: 273.6 | C19: 273.6 | D19: 273.6 | E19: 273.6 | F19: 273.6 | G19: 273.6 | H19: 273.6 | I19: 273.6 | J19: 273.6 | K19: 273.6 | L19: 273.6 | M19: 273.6 | N19: 3283.2
A20: political_cause | B20: 5 | C20: 5 | D20: 5 | E20: 5 | F20: 5 | G20: 5 | H20: 5 | I20: 5 | J20: 5 | K20: 5 | L20: 5 | M20: 5 | N20: 60
A21: real_python | B21: 29.99 | C21: 29.99 | N21: 59.98
A22: rent | C22: -2450.61 | N22: -2450.61
A23: spotify | B23: 5.99 | C23: 5.99 | D23: 5.99 | E23: 5.99 | F23: 5.99 | G23: 5.99 | H23: 5.99 | I23: 5.99 | J23: 5.99 | K23: 5.99 | L23: 5.99 | M23: 11.99 | N23: 77.88
A24: state_farm | B24: 90.83 | C24: 90.54 | D24: 90.54 | E24: 90.54 | F24: 90.54 | G24: 90.54 | H24: 90.54 | I24: 108.56 | J24: 108.56 | N24: 851.19
A25: student_loan | B25: -426.16 | C25: -442.73 | D25: -442.73 | E25: -442.73 | F25: -442.73 | G25: -442.73 | H25: -442.73 | I25: -442.73 | J25: -442.73 | K25: -442.73 | L25: -442.73 | M25: -442.73 | N25: -5296.19
A26: vincent_debt | B26: -1803.4 | C26: -3606.8 | D26: -3277.12 | N26: -8687.32
A27: microsoft365 | E27: 69.99 | N27: 69.99
A28: nba_league_pass | F28: 24.37 | G28: 24.37 | H28: 24.37 | K28: 20 | L28: 50 | M28: 25 | N28: 168.11
A29: google_one | I29: 2.11 | J29: 2.11 | K29: 2.11 | L29: 2.11 | M29: 2.11 | N29: 10.55
A30: physical_therapy | K30: 30 | N30: 30
A31: Grand Total | B31: -2021.03 | C31: -6563.33 | D31: -4005.96 | E31: -3302.51 | F31: -817.02 | G31: -837.72 | H31: 457.09 | I31: 12.89 | J31: -446.83 | K31: 3.99 | L31: 824.42 | M31: 204.62 | N31: -16491.39

Sheet Summary
B2: Income | C2: 45292 | D2: =EOMONTH(C2,0)+1 -> 45323 | E2: =EOMONTH(D2,0)+1 -> 45352 | F2: =EOMONTH(E2,0)+1 -> 45383 | G2: =EOMONTH(F2,0)+1 -> 45413 | H2: =EOMONTH(G2,0)+1 -> 45444 | I2: =EOMONTH(H2,0)+1 -> 45474 | J2: =EOMONTH(I2,0)+1 -> 45505 | K2: =EOMONTH(J2,0)+1 -> 45536 | ... N2: =EOMONTH(M2,0)+1 -> 45627
B3: income | C3: =SUMIFS(Combined_Accounts[Amount],Combined_Accounts[Date],C$2,Combined_Accounts[Short_Desc],$B3) -> 6695.36 | D3: =SUMIFS(Combined_Accounts[Amount],Combined_Accounts[Date],D$2,Combined_Accounts[Short_Desc],$B3) -> 9108.05 | E3: =SUMIFS(Combined_Accounts[Amount],Combined_Accounts[Date],E$2,Combined_Accounts[Short_Desc],$B3) -> 8398.56 | F3: =SUMIFS(Combined_Accounts[Amount],Combined_Accounts[Date],F$2,Combined_Accounts[Short_Desc],$B3) -> 11304.56 | G3: =SUMIFS(Combined_Accounts[Amount],Combined_Accounts[Date],G$2,Combined_Accounts[Short_Desc],$B3) -> 7561.64 | H3: =SUMIFS(Combined_Accounts[Amount],Combined_Accounts[Date],H$2,Combined_Accounts[Short_Desc],$B3) -> 7966.08 | I3: =SUMIFS(Combined_Accounts[Amount],Combined_Accounts[Date],I$2,Combined_Accounts[Short_Desc],$B3) -> 7034.08 | J3: =SUMIFS(Combined_Accounts[Amount],Combined_Accounts[Date],J$2,Combined_Accounts[Short_Desc],$B3) -> 7034.08 | ... N3: =SUMIFS(Combined_Accounts[Amount],Combined_Accounts[Date],N$2,Combined_Accounts[Short_Desc],$B3) -> 7034.08
B4: savings | C4: =SUMIFS(Combined_Accounts[Amount],Combined_Accounts[Date],C$2,Combined_Accounts[Category_2],$B4) -> 5691.06 | D4: =SUMIFS(Combined_Accounts[Amount],Combined_Accounts[Date],D$2,Combined_Accounts[Category_2],$B4) -> 7753.09 | E4: =SUMIFS(Combined_Accounts[Amount],Combined_Accounts[Date],E$2,Combined_Accounts[Category_2],$B4) -> 7138.78 | F4: =SUMIFS(Combined_Accounts[Amount],Combined_Accounts[Date],F$2,Combined_Accounts[Category_2],$B4) -> 10249.44 | G4: =SUMIFS(Combined_Accounts[Amount],Combined_Accounts[Date],G$2,Combined_Accounts[Category_2],$B4) -> 5978.96 | H4: =SUMIFS(Combined_Accounts[Amount],Combined_Accounts[Date],H$2,Combined_Accounts[Category_2],$B4) -> 6771.17 | I4: =SUMIFS(Combined_Accounts[Amount],Combined_Accounts[Date],I$2,Combined_Accounts[Category_2],$B4) -> 5978.96 | J4: =SUMIFS(Combined_Accounts[Amount],Combined_Accounts[Date],J$2,Combined_Accounts[Category_2],$B4) -> 5978.96 | ... N4: =SUMIFS(Combined_Accounts[Amount],Combined_Accounts[Date],N$2,Combined_Accounts[Category_2],$B4) -> 5978.96
B5: checking | C5: =C3-C4 -> 1004.3 | D5: =D3-D4 -> 1354.96 | E5: =E3-E4 -> 1259.78 | F5: =F3-F4 -> 1055.12 | G5: =G3-G4 -> 1582.68 | H5: =H3-H4 -> 1194.91 | I5: =I3-I4 -> 1055.12 | J5: =J3-J4 -> 1055.12 | ... N5: =N3-N4 -> 1055.12
B6: don | F6: 400 | G6: 400 | H6: 400 | I6: 400 | J6: 400 | K6: 400 | L6: 400 | M6: 400 | N6: 400
B7: insurance reimbursement
B8: Total | C8: =SUM(C6:C7)+C3 -> 6695.36 | D8: =SUM(D6:D7)+D3 -> 9108.05 | E8: =SUM(E6:E7)+E3 -> 8398.56 | F8: =SUM(F6:F7)+F3 -> 11704.56 | G8: =SUM(G6:G7)+G3 -> 7961.64 | H8: =SUM(H6:H7)+H3 -> 8366.08 | I8: =SUM(I6:I7)+I3 -> 7434.08 | J8: =SUM(J6:J7)+J3 -> 7434.08 | ... N8: =SUM(N6:N7)+N3 -> 7434.08
B10: Fixed Expenses | C10: 45292 | D10: =EOMONTH(C10,0)+1 -> 45323 | E10: =EOMONTH(D10,0)+1 -> 45352 | F10: =EOMONTH(E10,0)+1 -> 45383 | G10: =EOMONTH(F10,0)+1 -> 45413 | H10: =EOMONTH(G10,0)+1 -> 45444 | I10: =EOMONTH(H10,0)+1 -> 45474 | J10: =EOMONTH(I10,0)+1 -> 45505 | K10: =EOMONTH(J10,0)+1 -> 45536 | ... N10: =EOMONTH(M10,0)+1 -> 45627
B11: rent | C11: =SUMIFS(Combined_Accounts[Amount],Combined_Accounts[Date],C$2,Combined_Accounts[Short_Desc],$B11,Combined_Accounts[Account],"discover") + SUMIFS(Combined_Accounts[Amount],Combined_Accounts[Date],C$2,Combined_Accounts[Short_Desc],$B11,Combined_Accounts[Account],"<>" & "discover")*-1 -> 0 | D11: =SUMIFS(Combined_Accounts[Amount],Combined_Accounts[Date],D$2,Combined_Accounts[Short_Desc],$B11,Combined_Accounts[Account],"discover") + SUMIFS(Combined_Accounts[Amount],Combined_Accounts[Date],D$2,Combined_Accounts[Short_Desc],$B11,Combined_Accounts[Account],"<>" & "discover")*-1 -> 2450.61 | E11: =SUMIFS(Combined_Accounts[Amount],Combined_Accounts[Date],E$2,Combined_Accounts[Short_Desc],$B11,Combined_Accounts[Account],"discover") + SUMIFS(Combined_Accounts[Amount],Combined_Accounts[Date],E$2,Combined_Accounts[Short_Desc],$B11,Combined_Accounts[Account],"<>" & "discover")*-1 -> 0 | F11: =SUMIFS(Combined_Accounts[Amount],Combined_Accounts[Date],F$2,Combined_Accounts[Short_Desc],$B11,Combined_Accounts[Account],"discover") + SUMIFS(Combined_Accounts[Amount],Combined_Accounts[Date],F$2,Combined_Accounts[Short_Desc],$B11,Combined_Accounts[Account],"<>" & "discover")*-1 -> 0 | G11: =SUMIFS(Combined_Accounts[Amount],Combined_Accounts[Date],G$2,Combined_Accounts[Short_Desc],$B11,Combined_Accounts[Account],"discover") + SUMIFS(Combined_Accounts[Amount],Combined_Accounts[Date],G$2,Combined_Accounts[Short_Desc],$B11,Combined_Accounts[Account],"<>" & "discover")*-1 -> 0 | H11: =SUMIFS(Combined_Accounts[Amount],Combined_Accounts[Date],H$2,Combined_Accounts[Short_Desc],$B11,Combined_Accounts[Account],"discover") + SUMIFS(Combined_Accounts[Amount],Combined_Accounts[Date],H$2,Combined_Accounts[Short_Desc],$B11,Combined_Accounts[Account],"<>" & "discover")*-1 -> 0 | I11: =SUMIFS(Combined_Accounts[Amount],Combined_Accounts[Date],I$2,Combined_Accounts[Short_Desc],$B11,Combined_Accounts[Account],"discover") + SUMIFS(Combined_Accounts[Amount],Combined_Accounts[Date],I$2,Combined_Accounts[Short_Desc],$B11,Combined_Accounts[Account],"<>" & "discover")*-1 -> 0 | J11: =SUMIFS(Combined_Accounts[Amount],Combined_Accounts[Date],J$2,Combined_Accounts[Short_Desc],$B11,Combined_Accounts[Account],"discover") + SUMIFS(Combined_Accounts[Amount],Combined_Accounts[Date],J$2,Combined_Accounts[Short_Desc],$B11,Combined_Accounts[Account],"<>" & "discover")*-1 -> 0 | K11: 1633.74 | L11: 1633.74 | M11: 1633.74 | N11: 1633.74
B12: vincent_debt | C12: =SUMIFS(Combined_Accounts[Amount],Combined_Accounts[Date],C$2,Combined_Accounts[Short_Desc],$B12,Combined_Accounts[Account],"discover") + SUMIFS(Combined_Accounts[Amount],Combined_Accounts[Date],C$2,Combined_Accounts[Short_Desc],$B12,Combined_Accounts[Account],"<>" & "discover")*-1 -> 1803.4 | D12: =SUMIFS(Combined_Accounts[Amount],Combined_Accounts[Date],D$2,Combined_Accounts[Short_Desc],$B12,Combined_Accounts[Account],"discover") + SUMIFS(Combined_Accounts[Amount],Combined_Accounts[Date],D$2,Combined_Accounts[Short_Desc],$B12,Combined_Accounts[Account],"<>" & "discover")*-1 -> 3606.8 | E12: =SUMIFS(Combined_Accounts[Amount],Combined_Accounts[Date],E$2,Combined_Accounts[Short_Desc],$B12)*-1 -> 3277.12 | F12: =SUMIFS(Combined_Accounts[Amount],Combined_Accounts[Date],F$2,Combined_Accounts[Short_Desc],$B12)*-1 -> 0 | G12: =SUMIFS(Combined_Accounts[Amount],Combined_Accounts[Date],G$2,Combined_Accounts[Short_Desc],$B12)*-1 -> 0 | H12: =SUMIFS(Combined_Accounts[Amount],Combined_Accounts[Date],H$2,Combined_Accounts[Short_Desc],$B12)*-1 -> 0 | I12: =SUMIFS(Combined_Accounts[Amount],Combined_Accounts[Date],I$2,Combined_Accounts[Short_Desc],$B12)*-1 -> 0 | J12: =SUMIFS(Combined_Accounts[Amount],Combined_Accounts[Date],J$2,Combined_Accounts[Short_Desc],$B12)*-1 -> 0 | K12: =SUMIFS(Combined_Accounts[Amount],Combined_Accounts[Date],K$2,Combined_Accounts[Short_Desc],$B12)*-1 -> 0 | L12: =SUMIFS(Combined_Accounts[Amount],Combined_Accounts[Date],L$2,Combined_Accounts[Short_Desc],$B12)*-1 -> 0 | ... N12: =SUMIFS(Combined_Accounts[Amount],Combined_Accounts[Date],N$2,Combined_Accounts[Short_Desc],$B12)*-1 -> 0
B13: laptop | C13: =SUMIFS(Combined_Accounts[Amount],Combined_Accounts[Date],C$2,Combined_Accounts[Short_Desc],$B13,Combined_Accounts[Account],"discover") + SUMIFS(Combined_Accounts[Amount],Combined_Accounts[Date],C$2,Combined_Accounts[Short_Desc],$B13,Combined_Accounts[Account],"<>" & "discover")*-1 -> 155 | D13: =SUMIFS(Combined_Accounts[Amount],Combined_Accounts[Date],D$2,Combined_Accounts[Short_Desc],$B13,Combined_Accounts[Account],"discover") + SUMIFS(Combined_Accounts[Amount],Combined_Accounts[Date],D$2,Combined_Accounts[Short_Desc],$B13,Combined_Accounts[Account],"<>" & "discover")*-1 -> 155 | E13: =SUMIFS(Combined_Accounts[Amount],Combined_Accounts[Date],E$2,Combined_Accounts[Short_Desc],$B13,Combined_Accounts[Account],"discover") + SUMIFS(Combined_Accounts[Amount],Combined_Accounts[Date],E$2,Combined_Accounts[Short_Desc],$B13,Combined_Accounts[Account],"<>" & "discover")*-1 -> 155 | F13: =SUMIFS(Combined_Accounts[Amount],Combined_Accounts[Date],F$2,Combined_Accounts[Short_Desc],$B13,Combined_Accounts[Account],"discover") + SUMIFS(Combined_Accounts[Amount],Combined_Accounts[Date],F$2,Combined_Accounts[Short_Desc],$B13,Combined_Accounts[Account],"<>" & "discover")*-1 -> 155 | G13: =SUMIFS(Combined_Accounts[Amount],Combined_Accounts[Date],G$2,Combined_Accounts[Short_Desc],$B13,Combined_Accounts[Account],"discover") + SUMIFS(Combined_Accounts[Amount],Combined_Accounts[Date],G$2,Combined_Accounts[Short_Desc],$B13,Combined_Accounts[Account],"<>" & "discover")*-1 -> 155 | H13: =SUMIFS(Combined_Accounts[Amount],Combined_Accounts[Date],H$2,Combined_Accounts[Short_Desc],$B13,Combined_Accounts[Account],"discover") + SUMIFS(Combined_Accounts[Amount],Combined_Accounts[Date],H$2,Combined_Accounts[Short_Desc],$B13,Combined_Accounts[Account],"<>" & "discover")*-1 -> 634.69 | I13: =SUMIFS(Combined_Accounts[Amount],Combined_Accounts[Date],I$2,Combined_Accounts[Short_Desc],$B13,Combined_Accounts[Account],"discover") + SUMIFS(Combined_Accounts[Amount],Combined_Accounts[Date],I$2,Combined_Accounts[Short_Desc],$B13,Combined_Accounts[Account],"<>" & "discover")*-1 -> 0 | J13: =SUMIFS(Combined_Accounts[Amount],Combined_Accounts[Date],J$2,Combined_Accounts[Short_Desc],$B13,Combined_Accounts[Account],"discover") + SUMIFS(Combined_Accounts[Amount],Combined_Accounts[Date],J$2,Combined_Accounts[Short_Desc],$B13,Combined_Accounts[Account],"<>" & "discover")*-1 -> 0 | ... N13: =SUMIFS(Combined_Accounts[Amount],Combined_Accounts[Date],N$2,Combined_Accounts[Short_Desc],$B13,Combined_Accounts[Account],"discover") + SUMIFS(Combined_Accounts[Amount],Combined_Accounts[Date],N$2,Combined_Accounts[Short_Desc],$B13,Combined_Accounts[Account],"<>" & "discover")*-1 -> 0
B14: care_credit | C14: =SUMIFS(Combined_Accounts[Amount],Combined_Accounts[Date],C$2,Combined_Accounts[Short_Desc],$B14,Combined_Accounts[Account],"discover") + SUMIFS(Combined_Accounts[Amount],Combined_Accounts[Date],C$2,Combined_Accounts[Short_Desc],$B14,Combined_Accounts[Account],"<>" & "discover")*-1 -> 417.29 | D14: =SUMIFS(Combined_Accounts[Amount],Combined_Accounts[Date],D$2,Combined_Accounts[Short_Desc],$B14,Combined_Accounts[Account],"discover") + SUMIFS(Combined_Accounts[Amount],Combined_Accounts[Date],D$2,Combined_Accounts[Short_Desc],$B14,Combined_Accounts[Account],"<>" & "discover")*-1 -> 237.29 | E14: =SUMIFS(Combined_Accounts[Amount],Combined_Accounts[Date],E$2,Combined_Accounts[Short_Desc],$B14,Combined_Accounts[Account],"discover") + SUMIFS(Combined_Accounts[Amount],Combined_Accounts[Date],E$2,Combined_Accounts[Short_Desc],$B14,Combined_Accounts[Account],"<>" & "discover")*-1 -> 458.96 | F14: =SUMIFS(Combined_Accounts[Amount],Combined_Accounts[Date],F$2,Combined_Accounts[Short_Desc],$B14,Combined_Accounts[Account],"discover") + SUMIFS(Combined_Accounts[Amount],Combined_Accounts[Date],F$2,Combined_Accounts[Short_Desc],$B14,Combined_Accounts[Account],"<>" & "discover")*-1 -> 3000 | G14: =SUMIFS(Combined_Accounts[Amount],Combined_Accounts[Date],G$2,Combined_Accounts[Short_Desc],$B14,Combined_Accounts[Account],"discover") + SUMIFS(Combined_Accounts[Amount],Combined_Accounts[Date],G$2,Combined_Accounts[Short_Desc],$B14,Combined_Accounts[Account],"<>" & "discover")*-1 -> 458.96 | H14: =SUMIFS(Combined_Accounts[Amount],Combined_Accounts[Date],H$2,Combined_Accounts[Short_Desc],$B14,Combined_Accounts[Account],"discover") + SUMIFS(Combined_Accounts[Amount],Combined_Accounts[Date],H$2,Combined_Accounts[Short_Desc],$B14,Combined_Accounts[Account],"<>" & "discover")*-1 -> 460 | I14: =SUMIFS(Combined_Accounts[Amount],Combined_Accounts[Date],I$2,Combined_Accounts[Short_Desc],$B14,Combined_Accounts[Account],"discover") + SUMIFS(Combined_Accounts[Amount],Combined_Accounts[Date],I$2,Combined_Accounts[Short_Desc],$B14,Combined_Accounts[Account],"<>" & "discover")*-1 -> 460 | J14: =SUMIFS(Combined_Accounts[Amount],Combined_Accounts[Date],J$2,Combined_Accounts[Short_Desc],$B14,Combined_Accounts[Account],"discover") + SUMIFS(Combined_Accounts[Amount],Combined_Accounts[Date],J$2,Combined_Accounts[Short_Desc],$B14,Combined_Accounts[Account],"<>" & "discover")*-1 -> 460 | K14: 460 | L14: 460 | M14: 460 | N14: 460
B15: onepass | C15: =SUMIFS(Combined_Accounts[Amount],Combined_Accounts[Date],C$2,Combined_Accounts[Short_Desc],$B15,Combined_Accounts[Account],"discover") + SUMIFS(Combined_Accounts[Amount],Combined_Accounts[Date],C$2,Combined_Accounts[Short_Desc],$B15,Combined_Accounts[Account],"<>" & "discover")*-1 -> 273.6 | D15: =SUMIFS(Combined_Accounts[Amount],Combined_Accounts[Date],D$2,Combined_Accounts[Short_Desc],$B15,Combined_Accounts[Account],"discover") + SUMIFS(Combined_Accounts[Amount],Combined_Accounts[Date],D$2,Combined_Accounts[Short_Desc],$B15,Combined_Accounts[Account],"<>" & "discover")*-1 -> 273.6 | E15: =SUMIFS(Combined_Accounts[Amount],Combined_Accounts[Date],E$2,Combined_Accounts[Short_Desc],$B15,Combined_Accounts[Account],"discover") + SUMIFS(Combined_Accounts[Amount],Combined_Accounts[Date],E$2,Combined_Accounts[Short_Desc],$B15,Combined_Accounts[Account],"<>" & "discover")*-1 -> 273.6 | F15: =SUMIFS(Combined_Accounts[Amount],Combined_Accounts[Date],F$2,Combined_Accounts[Short_Desc],$B15,Combined_Accounts[Account],"discover") + SUMIFS(Combined_Accounts[Amount],Combined_Accounts[Date],F$2,Combined_Accounts[Short_Desc],$B15,Combined_Accounts[Account],"<>" & "discover")*-1 -> 273.6 | G15: =SUMIFS(Combined_Accounts[Amount],Combined_Accounts[Date],G$2,Combined_Accounts[Short_Desc],$B15,Combined_Accounts[Account],"discover") + SUMIFS(Combined_Accounts[Amount],Combined_Accounts[Date],G$2,Combined_Accounts[Short_Desc],$B15,Combined_Accounts[Account],"<>" & "discover")*-1 -> 273.6 | H15: =SUMIFS(Combined_Accounts[Amount],Combined_Accounts[Date],H$2,Combined_Accounts[Short_Desc],$B15,Combined_Accounts[Account],"discover") + SUMIFS(Combined_Accounts[Amount],Combined_Accounts[Date],H$2,Combined_Accounts[Short_Desc],$B15,Combined_Accounts[Account],"<>" & "discover")*-1 -> 273.6 | I15: =SUMIFS(Combined_Accounts[Amount],Combined_Accounts[Date],I$2,Combined_Accounts[Short_Desc],$B15,Combined_Accounts[Account],"discover") + SUMIFS(Combined_Accounts[Amount],Combined_Accounts[Date],I$2,Combined_Accounts[Short_Desc],$B15,Combined_Accounts[Account],"<>" & "discover")*-1 -> 273.6 | J15: =SUMIFS(Combined_Accounts[Amount],Combined_Accounts[Date],J$2,Combined_Accounts[Short_Desc],$B15,Combined_Accounts[Account],"discover") + SUMIFS(Combined_Accounts[Amount],Combined_Accounts[Date],J$2,Combined_Accounts[Short_Desc],$B15,Combined_Accounts[Account],"<>" & "discover")*-1 -> 273.6 | ... N15: =SUMIFS(Combined_Accounts[Amount],Combined_Accounts[Date],N$2,Combined_Accounts[Short_Desc],$B15,Combined_Accounts[Account],"discover") + SUMIFS(Combined_Accounts[Amount],Combined_Accounts[Date],N$2,Combined_Accounts[Short_Desc],$B15,Combined_Accounts[Account],"<>" & "discover")*-1 -> 273.6
B16: state_farm | C16: =SUMIFS(Combined_Accounts[Amount],Combined_Accounts[Date],C$2,Combined_Accounts[Short_Desc],$B16,Combined_Accounts[Account],"discover") + SUMIFS(Combined_Accounts[Amount],Combined_Accounts[Date],C$2,Combined_Accounts[Short_Desc],$B16,Combined_Accounts[Account],"<>" & "discover")*-1 -> 90.83 | D16: =SUMIFS(Combined_Accounts[Amount],Combined_Accounts[Date],D$2,Combined_Accounts[Short_Desc],$B16,Combined_Accounts[Account],"discover") + SUMIFS(Combined_Accounts[Amount],Combined_Accounts[Date],D$2,Combined_Accounts[Short_Desc],$B16,Combined_Accounts[Account],"<>" & "discover")*-1 -> 90.54 | E16: =SUMIFS(Combined_Accounts[Amount],Combined_Accounts[Date],E$2,Combined_Accounts[Short_Desc],$B16,Combined_Accounts[Account],"discover") + SUMIFS(Combined_Accounts[Amount],Combined_Accounts[Date],E$2,Combined_Accounts[Short_Desc],$B16,Combined_Accounts[Account],"<>" & "discover")*-1 -> 90.54 | F16: =SUMIFS(Combined_Accounts[Amount],Combined_Accounts[Date],F$2,Combined_Accounts[Short_Desc],$B16,Combined_Accounts[Account],"discover") + SUMIFS(Combined_Accounts[Amount],Combined_Accounts[Date],F$2,Combined_Accounts[Short_Desc],$B16,Combined_Accounts[Account],"<>" & "discover")*-1 -> 90.54 | G16: =SUMIFS(Combined_Accounts[Amount],Combined_Accounts[Date],G$2,Combined_Accounts[Short_Desc],$B16,Combined_Accounts[Account],"discover") + SUMIFS(Combined_Accounts[Amount],Combined_Accounts[Date],G$2,Combined_Accounts[Short_Desc],$B16,Combined_Accounts[Account],"<>" & "discover")*-1 -> 90.54 | H16: =SUMIFS(Combined_Accounts[Amount],Combined_Accounts[Date],H$2,Combined_Accounts[Short_Desc],$B16,Combined_Accounts[Account],"discover") + SUMIFS(Combined_Accounts[Amount],Combined_Accounts[Date],H$2,Combined_Accounts[Short_Desc],$B16,Combined_Accounts[Account],"<>" & "discover")*-1 -> 90.54 | I16: =SUMIFS(Combined_Accounts[Amount],Combined_Accounts[Date],I$2,Combined_Accounts[Short_Desc],$B16,Combined_Accounts[Account],"discover") + SUMIFS(Combined_Accounts[Amount],Combined_Accounts[Date],I$2,Combined_Accounts[Short_Desc],$B16,Combined_Accounts[Account],"<>" & "discover")*-1 -> 90.54 | J16: =SUMIFS(Combined_Accounts[Amount],Combined_Accounts[Date],J$2,Combined_Accounts[Short_Desc],$B16,Combined_Accounts[Account],"discover") + SUMIFS(Combined_Accounts[Amount],Combined_Accounts[Date],J$2,Combined_Accounts[Short_Desc],$B16,Combined_Accounts[Account],"<>" & "discover")*-1 -> 108.56 | K16: 108.56 | L16: 108.56 | M16: 108.56 | N16: 108.56
B17: cell_phone | C17: =SUMIFS(Combined_Accounts[Amount],Combined_Accounts[Date],C$2,Combined_Accounts[Short_Desc],$B17,Combined_Accounts[Account],"discover") + SUMIFS(Combined_Accounts[Amount],Combined_Accounts[Date],C$2,Combined_Accounts[Short_Desc],$B17,Combined_Accounts[Account],"<>" & "discover")*-1 -> 0 | D17: =SUMIFS(Combined_Accounts[Amount],Combined_Accounts[Date],D$2,Combined_Accounts[Short_Desc],$B17,Combined_Accounts[Account],"discover") + SUMIFS(Combined_Accounts[Amount],Combined_Accounts[Date],D$2,Combined_Accounts[Short_Desc],$B17,Combined_Accounts[Account],"<>" & "discover")*-1 -> 366.21 | E17: =SUMIFS(Combined_Accounts[Amount],Combined_Accounts[Date],E$2,Combined_Accounts[Short_Desc],$B17,Combined_Accounts[Account],"discover") + SUMIFS(Combined_Accounts[Amount],Combined_Accounts[Date],E$2,Combined_Accounts[Short_Desc],$B17,Combined_Accounts[Account],"<>" & "discover")*-1 -> 91.98 | F17: =SUMIFS(Combined_Accounts[Amount],Combined_Accounts[Date],F$2,Combined_Accounts[Short_Desc],$B17,Combined_Accounts[Account],"discover") + SUMIFS(Combined_Accounts[Amount],Combined_Accounts[Date],F$2,Combined_Accounts[Short_Desc],$B17,Combined_Accounts[Account],"<>" & "discover")*-1 -> 0 | G17: =SUMIFS(Combined_Accounts[Amount],Combined_Accounts[Date],G$2,Combined_Accounts[Short_Desc],$B17,Combined_Accounts[Account],"discover") + SUMIFS(Combined_Accounts[Amount],Combined_Accounts[Date],G$2,Combined_Accounts[Short_Desc],$B17,Combined_Accounts[Account],"<>" & "discover")*-1 -> 0 | H17: =SUMIFS(Combined_Accounts[Amount],Combined_Accounts[Date],H$2,Combined_Accounts[Short_Desc],$B17,Combined_Accounts[Account],"discover") + SUMIFS(Combined_Accounts[Amount],Combined_Accounts[Date],H$2,Combined_Accounts[Short_Desc],$B17,Combined_Accounts[Account],"<>" & "discover")*-1 -> 0 | I17: =SUMIFS(Combined_Accounts[Amount],Combined_Accounts[Date],I$2,Combined_Accounts[Short_Desc],$B17,Combined_Accounts[Account],"discover") + SUMIFS(Combined_Accounts[Amount],Combined_Accounts[Date],I$2,Combined_Accounts[Short_Desc],$B17,Combined_Accounts[Account],"<>" & "discover")*-1 -> 0 | J17: =SUMIFS(Combined_Accounts[Amount],Combined_Accounts[Date],J$2,Combined_Accounts[Short_Desc],$B17,Combined_Accounts[Account],"discover") + SUMIFS(Combined_Accounts[Amount],Combined_Accounts[Date],J$2,Combined_Accounts[Short_Desc],$B17,Combined_Accounts[Account],"<>" & "discover")*-1 -> 0 | K17: 65.83 | L17: 65.83 | M17: 65.83 | N17: 65.83
B18: student_loan | C18: =SUMIFS(Combined_Accounts[Amount],Combined_Accounts[Date],C$2,Combined_Accounts[Short_Desc],$B18,Combined_Accounts[Account],"discover") + SUMIFS(Combined_Accounts[Amount],Combined_Accounts[Date],C$2,Combined_Accounts[Short_Desc],$B18,Combined_Accounts[Account],"<>" & "discover")*-1 -> 426.16 | D18: =SUMIFS(Combined_Accounts[Amount],Combined_Accounts[Date],D$2,Combined_Accounts[Short_Desc],$B18,Combined_Accounts[Account],"discover") + SUMIFS(Combined_Accounts[Amount],Combined_Accounts[Date],D$2,Combined_Accounts[Short_Desc],$B18,Combined_Accounts[Account],"<>" & "discover")*-1 -> 442.73 | E18: =SUMIFS(Combined_Accounts[Amount],Combined_Accounts[Date],E$2,Combined_Accounts[Short_Desc],$B18,Combined_Accounts[Account],"discover") + SUMIFS(Combined_Accounts[Amount],Combined_Accounts[Date],E$2,Combined_Accounts[Short_Desc],$B18,Combined_Accounts[Account],"<>" & "discover")*-1 -> 442.73 | F18: =SUMIFS(Combined_Accounts[Amount],Combined_Accounts[Date],F$2,Combined_Accounts[Short_Desc],$B18,Combined_Accounts[Account],"discover") + SUMIFS(Combined_Accounts[Amount],Combined_Accounts[Date],F$2,Combined_Accounts[Short_Desc],$B18,Combined_Accounts[Account],"<>" & "discover")*-1 -> 442.73 | G18: =SUMIFS(Combined_Accounts[Amount],Combined_Accounts[Date],G$2,Combined_Accounts[Short_Desc],$B18,Combined_Accounts[Account],"discover") + SUMIFS(Combined_Accounts[Amount],Combined_Accounts[Date],G$2,Combined_Accounts[Short_Desc],$B18,Combined_Accounts[Account],"<>" & "discover")*-1 -> 442.73 | H18: =SUMIFS(Combined_Accounts[Amount],Combined_Accounts[Date],H$2,Combined_Accounts[Short_Desc],$B18,Combined_Accounts[Account],"discover") + SUMIFS(Combined_Accounts[Amount],Combined_Accounts[Date],H$2,Combined_Accounts[Short_Desc],$B18,Combined_Accounts[Account],"<>" & "discover")*-1 -> 442.73 | I18: =SUMIFS(Combined_Accounts[Amount],Combined_Accounts[Date],I$2,Combined_Accounts[Short_Desc],$B18,Combined_Accounts[Account],"discover") + SUMIFS(Combined_Accounts[Amount],Combined_Accounts[Date],I$2,Combined_Accounts[Short_Desc],$B18,Combined_Accounts[Account],"<>" & "discover")*-1 -> 442.73 | J18: =SUMIFS(Combined_Accounts[Amount],Combined_Accounts[Date],J$2,Combined_Accounts[Short_Desc],$B18,Combined_Accounts[Account],"discover") + SUMIFS(Combined_Accounts[Amount],Combined_Accounts[Date],J$2,Combined_Accounts[Short_Desc],$B18,Combined_Accounts[Account],"<>" & "discover")*-1 -> 442.73 | K18: 442.73 | L18: 442.73 | M18: 442.73 | N18: 442.73 | O18: =SUM(C18:N18) -> 5296.19 | P18: ='Loan Schedule'!B5-Summary!O18 -> 15473.5
B19: adobe | C19: =SUMIFS(Combined_Accounts[Amount],Combined_Accounts[Date],C$2,Combined_Accounts[Short_Desc],$B19,Combined_Accounts[Account],"discover") + SUMIFS(Combined_Accounts[Amount],Combined_Accounts[Date],C$2,Combined_Accounts[Short_Desc],$B19,Combined_Accounts[Account],"<>" & "discover")*-1 -> 29.99 | D19: =SUMIFS(Combined_Accounts[Amount],Combined_Accounts[Date],D$2,Combined_Accounts[Short_Desc],$B19,Combined_Accounts[Account],"discover") + SUMIFS(Combined_Accounts[Amount],Combined_Accounts[Date],D$2,Combined_Accounts[Short_Desc],$B19,Combined_Accounts[Account],"<>" & "discover")*-1 -> 29.99 | E19: =SUMIFS(Combined_Accounts[Amount],Combined_Accounts[Date],E$2,Combined_Accounts[Short_Desc],$B19,Combined_Accounts[Account],"discover") + SUMIFS(Combined_Accounts[Amount],Combined_Accounts[Date],E$2,Combined_Accounts[Short_Desc],$B19,Combined_Accounts[Account],"<>" & "discover")*-1 -> 29.99 | F19: =SUMIFS(Combined_Accounts[Amount],Combined_Accounts[Date],F$2,Combined_Accounts[Short_Desc],$B19,Combined_Accounts[Account],"discover") + SUMIFS(Combined_Accounts[Amount],Combined_Accounts[Date],F$2,Combined_Accounts[Short_Desc],$B19,Combined_Accounts[Account],"<>" & "discover")*-1 -> 29.99 | G19: =SUMIFS(Combined_Accounts[Amount],Combined_Accounts[Date],G$2,Combined_Accounts[Short_Desc],$B19,Combined_Accounts[Account],"discover") + SUMIFS(Combined_Accounts[Amount],Combined_Accounts[Date],G$2,Combined_Accounts[Short_Desc],$B19,Combined_Accounts[Account],"<>" & "discover")*-1 -> 29.99 | H19: =SUMIFS(Combined_Accounts[Amount],Combined_Accounts[Date],H$2,Combined_Accounts[Short_Desc],$B19,Combined_Accounts[Account],"discover") + SUMIFS(Combined_Accounts[Amount],Combined_Accounts[Date],H$2,Combined_Accounts[Short_Desc],$B19,Combined_Accounts[Account],"<>" & "discover")*-1 -> 29.99 | I19: =SUMIFS(Combined_Accounts[Amount],Combined_Accounts[Date],I$2,Combined_Accounts[Short_Desc],$B19,Combined_Accounts[Account],"discover") + SUMIFS(Combined_Accounts[Amount],Combined_Accounts[Date],I$2,Combined_Accounts[Short_Desc],$B19,Combined_Accounts[Account],"<>" & "discover")*-1 -> 29.99 | J19: =SUMIFS(Combined_Accounts[Amount],Combined_Accounts[Date],J$2,Combined_Accounts[Short_Desc],$B19,Combined_Accounts[Account],"discover") + SUMIFS(Combined_Accounts[Amount],Combined_Accounts[Date],J$2,Combined_Accounts[Short_Desc],$B19,Combined_Accounts[Account],"<>" & "discover")*-1 -> 29.99 | K19: 29.99 | L19: 29.99 | M19: 29.99 | N19: 29.99
B20: apple_care | C20: =SUMIFS(Combined_Accounts[Amount],Combined_Accounts[Date],C$2,Combined_Accounts[Short_Desc],$B20,Combined_Accounts[Account],"discover") + SUMIFS(Combined_Accounts[Amount],Combined_Accounts[Date],C$2,Combined_Accounts[Short_Desc],$B20,Combined_Accounts[Account],"<>" & "discover")*-1 -> 9.99 | D20: =SUMIFS(Combined_Accounts[Amount],Combined_Accounts[Date],D$2,Combined_Accounts[Short_Desc],$B20,Combined_Accounts[Account],"discover") + SUMIFS(Combined_Accounts[Amount],Combined_Accounts[Date],D$2,Combined_Accounts[Short_Desc],$B20,Combined_Accounts[Account],"<>" & "discover")*-1 -> 9.99 | E20: =SUMIFS(Combined_Accounts[Amount],Combined_Accounts[Date],E$2,Combined_Accounts[Short_Desc],$B20,Combined_Accounts[Account],"discover") + SUMIFS(Combined_Accounts[Amount],Combined_Accounts[Date],E$2,Combined_Accounts[Short_Desc],$B20,Combined_Accounts[Account],"<>" & "discover")*-1 -> 9.99 | F20: =SUMIFS(Combined_Accounts[Amount],Combined_Accounts[Date],F$2,Combined_Accounts[Short_Desc],$B20,Combined_Accounts[Account],"discover") + SUMIFS(Combined_Accounts[Amount],Combined_Accounts[Date],F$2,Combined_Accounts[Short_Desc],$B20,Combined_Accounts[Account],"<>" & "discover")*-1 -> 9.99 | G20: =SUMIFS(Combined_Accounts[Amount],Combined_Accounts[Date],G$2,Combined_Accounts[Short_Desc],$B20,Combined_Accounts[Account],"discover") + SUMIFS(Combined_Accounts[Amount],Combined_Accounts[Date],G$2,Combined_Accounts[Short_Desc],$B20,Combined_Accounts[Account],"<>" & "discover")*-1 -> 0 | H20: =SUMIFS(Combined_Accounts[Amount],Combined_Accounts[Date],H$2,Combined_Accounts[Short_Desc],$B20,Combined_Accounts[Account],"discover") + SUMIFS(Combined_Accounts[Amount],Combined_Accounts[Date],H$2,Combined_Accounts[Short_Desc],$B20,Combined_Accounts[Account],"<>" & "discover")*-1 -> 0 | I20: =SUMIFS(Combined_Accounts[Amount],Combined_Accounts[Date],I$2,Combined_Accounts[Short_Desc],$B20,Combined_Accounts[Account],"discover") + SUMIFS(Combined_Accounts[Amount],Combined_Accounts[Date],I$2,Combined_Accounts[Short_Desc],$B20,Combined_Accounts[Account],"<>" & "discover")*-1 -> 0 | J20: =SUMIFS(Combined_Accounts[Amount],Combined_Accounts[Date],J$2,Combined_Accounts[Short_Desc],$B20,Combined_Accounts[Account],"discover") + SUMIFS(Combined_Accounts[Amount],Combined_Accounts[Date],J$2,Combined_Accounts[Short_Desc],$B20,Combined_Accounts[Account],"<>" & "discover")*-1 -> 0 | ... N20: =SUMIFS(Combined_Accounts[Amount],Combined_Accounts[Date],N$2,Combined_Accounts[Short_Desc],$B20,Combined_Accounts[Account],"discover") + SUMIFS(Combined_Accounts[Amount],Combined_Accounts[Date],N$2,Combined_Accounts[Short_Desc],$B20,Combined_Accounts[Account],"<>" & "discover")*-1 -> 0
B21: breaking_points | C21: =SUMIFS(Combined_Accounts[Amount],Combined_Accounts[Date],C$2,Combined_Accounts[Short_Desc],$B21,Combined_Accounts[Account],"discover") + SUMIFS(Combined_Accounts[Amount],Combined_Accounts[Date],C$2,Combined_Accounts[Short_Desc],$B21,Combined_Accounts[Account],"<>" & "discover")*-1 -> 10 | D21: =SUMIFS(Combined_Accounts[Amount],Combined_Accounts[Date],D$2,Combined_Accounts[Short_Desc],$B21,Combined_Accounts[Account],"discover") + SUMIFS(Combined_Accounts[Amount],Combined_Accounts[Date],D$2,Combined_Accounts[Short_Desc],$B21,Combined_Accounts[Account],"<>" & "discover")*-1 -> 10 | E21: =SUMIFS(Combined_Accounts[Amount],Combined_Accounts[Date],E$2,Combined_Accounts[Short_Desc],$B21,Combined_Accounts[Account],"discover") + SUMIFS(Combined_Accounts[Amount],Combined_Accounts[Date],E$2,Combined_Accounts[Short_Desc],$B21,Combined_Accounts[Account],"<>" & "discover")*-1 -> 10 | F21: =SUMIFS(Combined_Accounts[Amount],Combined_Accounts[Date],F$2,Combined_Accounts[Short_Desc],$B21,Combined_Accounts[Account],"discover") + SUMIFS(Combined_Accounts[Amount],Combined_Accounts[Date],F$2,Combined_Accounts[Short_Desc],$B21,Combined_Accounts[Account],"<>" & "discover")*-1 -> 10 | G21: =SUMIFS(Combined_Accounts[Amount],Combined_Accounts[Date],G$2,Combined_Accounts[Short_Desc],$B21,Combined_Accounts[Account],"discover") + SUMIFS(Combined_Accounts[Amount],Combined_Accounts[Date],G$2,Combined_Accounts[Short_Desc],$B21,Combined_Accounts[Account],"<>" & "discover")*-1 -> 10 | H21: =SUMIFS(Combined_Accounts[Amount],Combined_Accounts[Date],H$2,Combined_Accounts[Short_Desc],$B21,Combined_Accounts[Account],"discover") + SUMIFS(Combined_Accounts[Amount],Combined_Accounts[Date],H$2,Combined_Accounts[Short_Desc],$B21,Combined_Accounts[Account],"<>" & "discover")*-1 -> 10 | I21: =SUMIFS(Combined_Accounts[Amount],Combined_Accounts[Date],I$2,Combined_Accounts[Short_Desc],$B21,Combined_Accounts[Account],"discover") + SUMIFS(Combined_Accounts[Amount],Combined_Accounts[Date],I$2,Combined_Accounts[Short_Desc],$B21,Combined_Accounts[Account],"<>" & "discover")*-1 -> 10 | J21: =SUMIFS(Combined_Accounts[Amount],Combined_Accounts[Date],J$2,Combined_Accounts[Short_Desc],$B21,Combined_Accounts[Account],"discover") + SUMIFS(Combined_Accounts[Amount],Combined_Accounts[Date],J$2,Combined_Accounts[Short_Desc],$B21,Combined_Accounts[Account],"<>" & "discover")*-1 -> 10 | ... N21: =SUMIFS(Combined_Accounts[Amount],Combined_Accounts[Date],N$2,Combined_Accounts[Short_Desc],$B21,Combined_Accounts[Account],"discover") + SUMIFS(Combined_Accounts[Amount],Combined_Accounts[Date],N$2,Combined_Accounts[Short_Desc],$B21,Combined_Accounts[Account],"<>" & "discover")*-1 -> 10
B22: spotify | C22: =SUMIFS(Combined_Accounts[Amount],Combined_Accounts[Date],C$2,Combined_Accounts[Short_Desc],$B22,Combined_Accounts[Account],"discover") + SUMIFS(Combined_Accounts[Amount],Combined_Accounts[Date],C$2,Combined_Accounts[Short_Desc],$B22,Combined_Accounts[Account],"<>" & "discover")*-1 -> 5.99 | D22: =SUMIFS(Combined_Accounts[Amount],Combined_Accounts[Date],D$2,Combined_Accounts[Short_Desc],$B22,Combined_Accounts[Account],"discover") + SUMIFS(Combined_Accounts[Amount],Combined_Accounts[Date],D$2,Combined_Accounts[Short_Desc],$B22,Combined_Accounts[Account],"<>" & "discover")*-1 -> 5.99 | E22: =SUMIFS(Combined_Accounts[Amount],Combined_Accounts[Date],E$2,Combined_Accounts[Short_Desc],$B22,Combined_Accounts[Account],"discover") + SUMIFS(Combined_Accounts[Amount],Combined_Accounts[Date],E$2,Combined_Accounts[Short_Desc],$B22,Combined_Accounts[Account],"<>" & "discover")*-1 -> 5.99 | F22: =SUMIFS(Combined_Accounts[Amount],Combined_Accounts[Date],F$2,Combined_Accounts[Short_Desc],$B22,Combined_Accounts[Account],"discover") + SUMIFS(Combined_Accounts[Amount],Combined_Accounts[Date],F$2,Combined_Accounts[Short_Desc],$B22,Combined_Accounts[Account],"<>" & "discover")*-1 -> 5.99 | G22: =SUMIFS(Combined_Accounts[Amount],Combined_Accounts[Date],G$2,Combined_Accounts[Short_Desc],$B22,Combined_Accounts[Account],"discover") + SUMIFS(Combined_Accounts[Amount],Combined_Accounts[Date],G$2,Combined_Accounts[Short_Desc],$B22,Combined_Accounts[Account],"<>" & "discover")*-1 -> 5.99 | H22: =SUMIFS(Combined_Accounts[Amount],Combined_Accounts[Date],H$2,Combined_Accounts[Short_Desc],$B22,Combined_Accounts[Account],"discover") + SUMIFS(Combined_Accounts[Amount],Combined_Accounts[Date],H$2,Combined_Accounts[Short_Desc],$B22,Combined_Accounts[Account],"<>" & "discover")*-1 -> 5.99 | I22: =SUMIFS(Combined_Accounts[Amount],Combined_Accounts[Date],I$2,Combined_Accounts[Short_Desc],$B22,Combined_Accounts[Account],"discover") + SUMIFS(Combined_Accounts[Amount],Combined_Accounts[Date],I$2,Combined_Accounts[Short_Desc],$B22,Combined_Accounts[Account],"<>" & "discover")*-1 -> 5.99 | J22: =SUMIFS(Combined_Accounts[Amount],Combined_Accounts[Date],J$2,Combined_Accounts[Short_Desc],$B22,Combined_Accounts[Account],"discover") + SUMIFS(Combined_Accounts[Amount],Combined_Accounts[Date],J$2,Combined_Accounts[Short_Desc],$B22,Combined_Accounts[Account],"<>" & "discover")*-1 -> 5.99 | ... N22: =SUMIFS(Combined_Accounts[Amount],Combined_Accounts[Date],N$2,Combined_Accounts[Short_Desc],$B22,Combined_Accounts[Account],"discover") + SUMIFS(Combined_Accounts[Amount],Combined_Accounts[Date],N$2,Combined_Accounts[Short_Desc],$B22,Combined_Accounts[Account],"<>" & "discover")*-1 -> 11.99
B23: onlyfans | C23: =SUMIFS(Combined_Accounts[Amount],Combined_Accounts[Date],C$2,Combined_Accounts[Short_Desc],$B23,Combined_Accounts[Account],"discover") + SUMIFS(Combined_Accounts[Amount],Combined_Accounts[Date],C$2,Combined_Accounts[Short_Desc],$B23,Combined_Accounts[Account],"<>" & "discover")*-1 -> 63.31 | D23: =SUMIFS(Combined_Accounts[Amount],Combined_Accounts[Date],D$2,Combined_Accounts[Short_Desc],$B23,Combined_Accounts[Account],"discover") + SUMIFS(Combined_Accounts[Amount],Combined_Accounts[Date],D$2,Combined_Accounts[Short_Desc],$B23,Combined_Accounts[Account],"<>" & "discover")*-1 -> 29.98 | E23: =SUMIFS(Combined_Accounts[Amount],Combined_Accounts[Date],E$2,Combined_Accounts[Short_Desc],$B23,Combined_Accounts[Account],"discover") + SUMIFS(Combined_Accounts[Amount],Combined_Accounts[Date],E$2,Combined_Accounts[Short_Desc],$B23,Combined_Accounts[Account],"<>" & "discover")*-1 -> 142.37 | F23: =SUMIFS(Combined_Accounts[Amount],Combined_Accounts[Date],F$2,Combined_Accounts[Short_Desc],$B23,Combined_Accounts[Account],"discover") + SUMIFS(Combined_Accounts[Amount],Combined_Accounts[Date],F$2,Combined_Accounts[Short_Desc],$B23,Combined_Accounts[Account],"<>" & "discover")*-1 -> 158.02 | G23: =SUMIFS(Combined_Accounts[Amount],Combined_Accounts[Date],G$2,Combined_Accounts[Short_Desc],$B23,Combined_Accounts[Account],"discover") + SUMIFS(Combined_Accounts[Amount],Combined_Accounts[Date],G$2,Combined_Accounts[Short_Desc],$B23,Combined_Accounts[Account],"<>" & "discover")*-1 -> 102.51 | H23: =SUMIFS(Combined_Accounts[Amount],Combined_Accounts[Date],H$2,Combined_Accounts[Short_Desc],$B23,Combined_Accounts[Account],"discover") + SUMIFS(Combined_Accounts[Amount],Combined_Accounts[Date],H$2,Combined_Accounts[Short_Desc],$B23,Combined_Accounts[Account],"<>" & "discover")*-1 -> 46.37 | I23: =SUMIFS(Combined_Accounts[Amount],Combined_Accounts[Date],I$2,Combined_Accounts[Short_Desc],$B23,Combined_Accounts[Account],"discover") + SUMIFS(Combined_Accounts[Amount],Combined_Accounts[Date],I$2,Combined_Accounts[Short_Desc],$B23,Combined_Accounts[Account],"<>" & "discover")*-1 -> 47.99 | J23: =SUMIFS(Combined_Accounts[Amount],Combined_Accounts[Date],J$2,Combined_Accounts[Short_Desc],$B23,Combined_Accounts[Account],"discover") + SUMIFS(Combined_Accounts[Amount],Combined_Accounts[Date],J$2,Combined_Accounts[Short_Desc],$B23,Combined_Accounts[Account],"<>" & "discover")*-1 -> 98.99 | ... N23: =SUMIFS(Combined_Accounts[Amount],Combined_Accounts[Date],N$2,Combined_Accounts[Short_Desc],$B23,Combined_Accounts[Account],"discover") + SUMIFS(Combined_Accounts[Amount],Combined_Accounts[Date],N$2,Combined_Accounts[Short_Desc],$B23,Combined_Accounts[Account],"<>" & "discover")*-1 -> 83.65
B24: Other | C24: {=SUMPRODUCT( --(Data!$J:$J = Summary!C$10), --IF(ISNUMBER(MATCH(Data!$G:$G, $B$11:$B$23, 0)),0,1), --IF(ISNUMBER(MATCH(Data!$G:$G, Categories!$A:$A, 0)),0,1), --IF(ISNUMBER(MATCH(Data!$G:$G, Categories!$E:$E, 0)),0,1), --IF(ISNUMBER(MATCH(Data!$G:$G, Categories!$G:$G, 0)),0,1), --IF(ISNUMBER(MATCH(Data!$G:$G, Categories!$C:$C, 0)),1,0), --IF(ISNUMBER(MATCH(Data!$O:$O, {"wells_fargo_checking","sofi_savings","sofi_checking"}, 0)),-1,1), IFERROR(Data!$E:$E, 0) )} -> 1361.26 | D24: {=SUMPRODUCT( --(Data!$J:$J = Summary!D$10), --IF(ISNUMBER(MATCH(Data!$G:$G, $B$11:$B$23, 0)),0,1), --IF(ISNUMBER(MATCH(Data!$G:$G, Categories!$A:$A, 0)),0,1), --IF(ISNUMBER(MATCH(Data!$G:$G, Categories!$E:$E, 0)),0,1), --IF(ISNUMBER(MATCH(Data!$G:$G, Categories!$G:$G, 0)),0,1), --IF(ISNUMBER(MATCH(Data!$G:$G, Categories!$C:$C, 0)),1,0), --IF(ISNUMBER(MATCH(Data!$O:$O, {"wells_fargo_checking","sofi_savings","sofi_checking"}, 0)),-1,1), IFERROR(Data!$E:$E, 0) )} -> 482.95 | E24: {=SUMPRODUCT( --(Data!$J:$J = Summary!E$10), --IF(ISNUMBER(MATCH(Data!$G:$G, $B$11:$B$23, 0)),0,1), --IF(ISNUMBER(MATCH(Data!$G:$G, Categories!$A:$A, 0)),0,1), --IF(ISNUMBER(MATCH(Data!$G:$G, Categories!$E:$E, 0)),0,1), --IF(ISNUMBER(MATCH(Data!$G:$G, Categories!$G:$G, 0)),0,1), --IF(ISNUMBER(MATCH(Data!$G:$G, Categories!$C:$C, 0)),1,0), --IF(ISNUMBER(MATCH(Data!$O:$O, {"wells_fargo_checking","sofi_savings","sofi_checking"}, 0)),-1,1), IFERROR(Data!$E:$E, 0) )} -> 344.69 | F24: {=SUMPRODUCT( --(Data!$J:$J = Summary!F$10), --IF(ISNUMBER(MATCH(Data!$G:$G, $B$11:$B$23, 0)),0,1), --IF(ISNUMBER(MATCH(Data!$G:$G, Categories!$A:$A, 0)),0,1), --IF(ISNUMBER(MATCH(Data!$G:$G, Categories!$E:$E, 0)),0,1), --IF(ISNUMBER(MATCH(Data!$G:$G, Categories!$G:$G, 0)),0,1), --IF(ISNUMBER(MATCH(Data!$G:$G, Categories!$C:$C, 0)),1,0), --IF(ISNUMBER(MATCH(Data!$O:$O, {"wells_fargo_checking","sofi_savings","sofi_checking"}, 0)),-1,1), IFERROR(Data!$E:$E, 0) )} -> 460.63 | G24: {=SUMPRODUCT( --(Data!$J:$J = Summary!G$10), --IF(ISNUMBER(MATCH(Data!$G:$G, $B$11:$B$23, 0)),0,1), --IF(ISNUMBER(MATCH(Data!$G:$G, Categories!$A:$A, 0)),0,1), --IF(ISNUMBER(MATCH(Data!$G:$G, Categories!$E:$E, 0)),0,1), --IF(ISNUMBER(MATCH(Data!$G:$G, Categories!$G:$G, 0)),0,1), --IF(ISNUMBER(MATCH(Data!$G:$G, Categories!$C:$C, 0)),1,0), --IF(ISNUMBER(MATCH(Data!$O:$O, {"wells_fargo_checking","sofi_savings","sofi_checking"}, 0)),-1,1), IFERROR(Data!$E:$E, 0) )} -> 317.41 | H24: {=SUMPRODUCT( --(Data!$J:$J = Summary!H$10), --IF(ISNUMBER(MATCH(Data!$G:$G, $B$11:$B$23, 0)),0,1), --IF(ISNUMBER(MATCH(Data!$G:$G, Categories!$A:$A, 0)),0,1), --IF(ISNUMBER(MATCH(Data!$G:$G, Categories!$E:$E, 0)),0,1), --IF(ISNUMBER(MATCH(Data!$G:$G, Categories!$G:$G, 0)),0,1), --IF(ISNUMBER(MATCH(Data!$G:$G, Categories!$C:$C, 0)),1,0), --IF(ISNUMBER(MATCH(Data!$O:$O, {"wells_fargo_checking","sofi_savings","sofi_checking"}, 0)),-1,1), IFERROR(Data!$E:$E, 0) )} -> 297.37 | I24: {=SUMPRODUCT( --(Data!$J:$J = Summary!I$10), --IF(ISNUMBER(MATCH(Data!$G:$G, $B$11:$B$23, 0)),0,1), --IF(ISNUMBER(MATCH(Data!$G:$G, Categories!$A:$A, 0)),0,1), --IF(ISNUMBER(MATCH(Data!$G:$G, Categories!$E:$E, 0)),0,1), --IF(ISNUMBER(MATCH(Data!$G:$G, Categories!$G:$G, 0)),0,1), --IF(ISNUMBER(MATCH(Data!$G:$G, Categories!$C:$C, 0)),1,0), --IF(ISNUMBER(MATCH(Data!$O:$O, {"wells_fargo_checking","sofi_savings","sofi_checking"}, 0)),-1,1), IFERROR(Data!$E:$E, 0) )} -> 150.25 | J24: {=SUMPRODUCT( --(Data!$J:$J = Summary!J$10), --IF(ISNUMBER(MATCH(Data!$G:$G, $B$11:$B$23, 0)),0,1), --IF(ISNUMBER(MATCH(Data!$G:$G, Categories!$A:$A, 0)),0,1), --IF(ISNUMBER(MATCH(Data!$G:$G, Categories!$E:$E, 0)),0,1), --IF(ISNUMBER(MATCH(Data!$G:$G, Categories!$G:$G, 0)),0,1), --IF(ISNUMBER(MATCH(Data!$G:$G, Categories!$C:$C, 0)),1,0), --IF(ISNUMBER(MATCH(Data!$O:$O, {"wells_fargo_checking","sofi_savings","sofi_checking"}, 0)),-1,1), IFERROR(Data!$E:$E, 0) )} -> 2091.5 | ... N24: {=SUMPRODUCT( --(Data!$J:$J = Summary!N$10), --IF(ISNUMBER(MATCH(Data!$G:$G, $B$11:$B$23, 0)),0,1), --IF(ISNUMBER(MATCH(Data!$G:$G, Categories!$A:$A, 0)),0,1), --IF(ISNUMBER(MATCH(Data!$G:$G, Categories!$E:$E, 0)),0,1), --IF(ISNUMBER(MATCH(Data!$G:$G, Categories!$G:$G, 0)),0,1), --IF(ISNUMBER(MATCH(Data!$G:$G, Categories!$C:$C, 0)),1,0), --IF(ISNUMBER(MATCH(Data!$O:$O, {"wells_fargo_checking","sofi_savings","sofi_checking"}, 0)),-1,1), IFERROR(Data!$E:$E, 0) )} -> 271.41
B25: Total | C25: =SUM(C11:C24) -> 4646.82 | D25: =SUM(D11:D24) -> 8191.68 | E25: =SUM(E11:E24) -> 5332.96 | F25: =SUM(F11:F24) -> 4636.49 | G25: =SUM(G11:G24) -> 1886.73 | H25: =SUM(H11:H24) -> 2291.28 | I25: =SUM(I11:I24) -> 1511.09 | J25: =SUM(J11:J24) -> 3521.36 | ... N25: =SUM(N11:N24) -> 3391.5
B27: Variable Expenses | C27: 45292 | D27: =EOMONTH(C27,0)+1 -> 45323 | E27: =EOMONTH(D27,0)+1 -> 45352 | F27: =EOMONTH(E27,0)+1 -> 45383 | G27: =EOMONTH(F27,0)+1 -> 45413 | H27: =EOMONTH(G27,0)+1 -> 45444 | I27: =EOMONTH(H27,0)+1 -> 45474 | J27: =EOMONTH(I27,0)+1 -> 45505 | K27: =EOMONTH(J27,0)+1 -> 45536 | ... N27: =EOMONTH(M27,0)+1 -> 45627
B28: family | C28: =SUMIFS(Combined_Accounts[Amount],Combined_Accounts[Date],C$2,Combined_Accounts[Short_Desc],$B28, Combined_Accounts[Account],"discover") +SUMIFS(Combined_Accounts[Amount],Combined_Accounts[Date],C$2,Combined_Accounts[Short_Desc],$B28)*-1 -> -250 | D28: =SUMIFS(Combined_Accounts[Amount],Combined_Accounts[Date],D$2,Combined_Accounts[Short_Desc],$B28, Combined_Accounts[Account],"discover") +SUMIFS(Combined_Accounts[Amount],Combined_Accounts[Date],D$2,Combined_Accounts[Short_Desc],$B28)*-1 -> -50 | E28: =SUMIFS(Combined_Accounts[Amount],Combined_Accounts[Date],E$2,Combined_Accounts[Short_Desc],$B28, Combined_Accounts[Account],"discover") +SUMIFS(Combined_Accounts[Amount],Combined_Accounts[Date],E$2,Combined_Accounts[Short_Desc],$B28)*-1 -> 0 | F28: =SUMIFS(Combined_Accounts[Amount],Combined_Accounts[Date],F$2,Combined_Accounts[Short_Desc],$B28, Combined_Accounts[Account],"discover") +SUMIFS(Combined_Accounts[Amount],Combined_Accounts[Date],F$2,Combined_Accounts[Short_Desc],$B28)*-1 -> 2600 | G28: =SUMIFS(Combined_Accounts[Amount],Combined_Accounts[Date],G$2,Combined_Accounts[Short_Desc],$B28, Combined_Accounts[Account],"discover") +SUMIFS(Combined_Accounts[Amount],Combined_Accounts[Date],G$2,Combined_Accounts[Short_Desc],$B28)*-1 -> -200 | H28: =SUMIFS(Combined_Accounts[Amount],Combined_Accounts[Date],H$2,Combined_Accounts[Short_Desc],$B28, Combined_Accounts[Account],"discover") +SUMIFS(Combined_Accounts[Amount],Combined_Accounts[Date],H$2,Combined_Accounts[Short_Desc],$B28)*-1 -> 0 | I28: =SUMIFS(Combined_Accounts[Amount],Combined_Accounts[Date],I$2,Combined_Accounts[Short_Desc],$B28, Combined_Accounts[Account],"discover") +SUMIFS(Combined_Accounts[Amount],Combined_Accounts[Date],I$2,Combined_Accounts[Short_Desc],$B28)*-1 -> 0 | J28: =SUMIFS(Combined_Accounts[Amount],Combined_Accounts[Date],J$2,Combined_Accounts[Short_Desc],$B28, Combined_Accounts[Account],"discover") +SUMIFS(Combined_Accounts[Amount],Combined_Accounts[Date],J$2,Combined_Accounts[Short_Desc],$B28)*-1 -> 50 | ... N28: =SUMIFS(Combined_Accounts[Amount],Combined_Accounts[Date],N$2,Combined_Accounts[Short_Desc],$B28, Combined_Accounts[Account],"discover") +SUMIFS(Combined_Accounts[Amount],Combined_Accounts[Date],N$2,Combined_Accounts[Short_Desc],$B28)*-1 -> 0 | O28: =SUM(C28:N28) -> 2640
B29: Don | C29: =SUMIFS(Combined_Accounts[Amount],Combined_Accounts[Date],C$2,Combined_Accounts[Short_Desc],$B29, Combined_Accounts[Account],"discover") +SUMIFS(Combined_Accounts[Amount],Combined_Accounts[Date],C$2,Combined_Accounts[Short_Desc],$B29)*-1 -> 111.63 | D29: =SUMIFS(Combined_Accounts[Amount],Combined_Accounts[Date],D$2,Combined_Accounts[Short_Desc],$B29, Combined_Accounts[Account],"discover") +SUMIFS(Combined_Accounts[Amount],Combined_Accounts[Date],D$2,Combined_Accounts[Short_Desc],$B29)*-1 -> 111.63 | E29: =SUMIFS(Combined_Accounts[Amount],Combined_Accounts[Date],E$2,Combined_Accounts[Short_Desc],$B29, Combined_Accounts[Account],"discover") +SUMIFS(Combined_Accounts[Amount],Combined_Accounts[Date],E$2,Combined_Accounts[Short_Desc],$B29)*-1 -> 65.83 | F29: =SUMIFS(Combined_Accounts[Amount],Combined_Accounts[Date],F$2,Combined_Accounts[Short_Desc],$B29, Combined_Accounts[Account],"discover") +SUMIFS(Combined_Accounts[Amount],Combined_Accounts[Date],F$2,Combined_Accounts[Short_Desc],$B29)*-1 -> 65.83 | G29: =SUMIFS(Combined_Accounts[Amount],Combined_Accounts[Date],G$2,Combined_Accounts[Short_Desc],$B29, Combined_Accounts[Account],"discover") +SUMIFS(Combined_Accounts[Amount],Combined_Accounts[Date],G$2,Combined_Accounts[Short_Desc],$B29)*-1 -> 76.61 | H29: =SUMIFS(Combined_Accounts[Amount],Combined_Accounts[Date],H$2,Combined_Accounts[Short_Desc],$B29, Combined_Accounts[Account],"discover") +SUMIFS(Combined_Accounts[Amount],Combined_Accounts[Date],H$2,Combined_Accounts[Short_Desc],$B29)*-1 -> 1581.33 | I29: =SUMIFS(Combined_Accounts[Amount],Combined_Accounts[Date],I$2,Combined_Accounts[Short_Desc],$B29, Combined_Accounts[Account],"discover") +SUMIFS(Combined_Accounts[Amount],Combined_Accounts[Date],I$2,Combined_Accounts[Short_Desc],$B29)*-1 -> 1142.32 | J29: =SUMIFS(Combined_Accounts[Amount],Combined_Accounts[Date],J$2,Combined_Accounts[Short_Desc],$B29, Combined_Accounts[Account],"discover") +SUMIFS(Combined_Accounts[Amount],Combined_Accounts[Date],J$2,Combined_Accounts[Short_Desc],$B29)*-1 -> 65.83 | ... N29: =SUMIFS(Combined_Accounts[Amount],Combined_Accounts[Date],N$2,Combined_Accounts[Short_Desc],$B29, Combined_Accounts[Account],"discover") +SUMIFS(Combined_Accounts[Amount],Combined_Accounts[Date],N$2,Combined_Accounts[Short_Desc],$B29)*-1 -> 70 | O29: =SUM(C29:N29) -> 3492.75
B30: Other | C30: {=SUMPRODUCT( --(Data!$J:$J = Summary!C$10), --IF(ISNUMBER(MATCH(Data!$G:$G, B28:$B$29, 0)),0,1), --IF(ISNUMBER(MATCH(Data!$G:$G, Categories!$A:$A, 0)),0,1), --IF(ISNUMBER(MATCH(Data!$G:$G, Categories!$E:$E, 0)),1,0), --IF(ISNUMBER(MATCH(Data!$G:$G, Categories!$G:$G, 0)),0,1), --IF(ISNUMBER(MATCH(Data!$G:$G, Categories!$C:$C, 0)),0,1), --IF(ISNUMBER(MATCH(Data!$O:$O, {"wells_fargo_checking","sofi_savings","sofi_checking"}, 0)),-1,1), IFERROR(Data!$E:$E, 0) )} -> 2881.14 | D30: {=SUMPRODUCT( --(Data!$J:$J = Summary!D$10), --IF(ISNUMBER(MATCH(Data!$G:$G, $B28:C$29, 0)),0,1), --IF(ISNUMBER(MATCH(Data!$G:$G, Categories!$A:$A, 0)),0,1), --IF(ISNUMBER(MATCH(Data!$G:$G, Categories!$E:$E, 0)),1,0), --IF(ISNUMBER(MATCH(Data!$G:$G, Categories!$G:$G, 0)),0,1), --IF(ISNUMBER(MATCH(Data!$G:$G, Categories!$C:$C, 0)),0,1), --IF(ISNUMBER(MATCH(Data!$O:$O, {"wells_fargo_checking","sofi_savings","sofi_checking"}, 0)),-1,1), IFERROR(Data!$E:$E, 0) )} -> 3156.45 | E30: {=SUMPRODUCT( --(Data!$J:$J = Summary!E$10), --IF(ISNUMBER(MATCH(Data!$G:$G, $B28:D$29, 0)),0,1), --IF(ISNUMBER(MATCH(Data!$G:$G, Categories!$A:$A, 0)),0,1), --IF(ISNUMBER(MATCH(Data!$G:$G, Categories!$E:$E, 0)),1,0), --IF(ISNUMBER(MATCH(Data!$G:$G, Categories!$G:$G, 0)),0,1), --IF(ISNUMBER(MATCH(Data!$G:$G, Categories!$C:$C, 0)),0,1), --IF(ISNUMBER(MATCH(Data!$O:$O, {"wells_fargo_checking","sofi_savings","sofi_checking"}, 0)),-1,1), IFERROR(Data!$E:$E, 0) )} -> 2484.23 | F30: {=SUMPRODUCT( --(Data!$J:$J = Summary!F$10), --IF(ISNUMBER(MATCH(Data!$G:$G, $B28:E$29, 0)),0,1), --IF(ISNUMBER(MATCH(Data!$G:$G, Categories!$A:$A, 0)),0,1), --IF(ISNUMBER(MATCH(Data!$G:$G, Categories!$E:$E, 0)),1,0), --IF(ISNUMBER(MATCH(Data!$G:$G, Categories!$G:$G, 0)),0,1), --IF(ISNUMBER(MATCH(Data!$G:$G, Categories!$C:$C, 0)),0,1), --IF(ISNUMBER(MATCH(Data!$O:$O, {"wells_fargo_checking","sofi_savings","sofi_checking"}, 0)),-1,1), IFERROR(Data!$E:$E, 0) )} -> 4596.98 | G30: {=SUMPRODUCT( --(Data!$J:$J = Summary!G$10), --IF(ISNUMBER(MATCH(Data!$G:$G, $B28:F$29, 0)),0,1), --IF(ISNUMBER(MATCH(Data!$G:$G, Categories!$A:$A, 0)),0,1), --IF(ISNUMBER(MATCH(Data!$G:$G, Categories!$E:$E, 0)),1,0), --IF(ISNUMBER(MATCH(Data!$G:$G, Categories!$G:$G, 0)),0,1), --IF(ISNUMBER(MATCH(Data!$G:$G, Categories!$C:$C, 0)),0,1), --IF(ISNUMBER(MATCH(Data!$O:$O, {"wells_fargo_checking","sofi_savings","sofi_checking"}, 0)),-1,1), IFERROR(Data!$E:$E, 0) )} -> 51.54 | H30: {=SUMPRODUCT( --(Data!$J:$J = Summary!H$10), --IF(ISNUMBER(MATCH(Data!$G:$G, $B28:G$29, 0)),0,1), --IF(ISNUMBER(MATCH(Data!$G:$G, Categories!$A:$A, 0)),0,1), --IF(ISNUMBER(MATCH(Data!$G:$G, Categories!$E:$E, 0)),1,0), --IF(ISNUMBER(MATCH(Data!$G:$G, Categories!$G:$G, 0)),0,1), --IF(ISNUMBER(MATCH(Data!$G:$G, Categories!$C:$C, 0)),0,1), --IF(ISNUMBER(MATCH(Data!$O:$O, {"wells_fargo_checking","sofi_savings","sofi_checking"}, 0)),-1,1), IFERROR(Data!$E:$E, 0) )} -> 2003.3 | I30: {=SUMPRODUCT( --(Data!$J:$J = Summary!I$10), --IF(ISNUMBER(MATCH(Data!$G:$G, $B28:H$29, 0)),0,1), --IF(ISNUMBER(MATCH(Data!$G:$G, Categories!$A:$A, 0)),0,1), --IF(ISNUMBER(MATCH(Data!$G:$G, Categories!$E:$E, 0)),1,0), --IF(ISNUMBER(MATCH(Data!$G:$G, Categories!$G:$G, 0)),0,1), --IF(ISNUMBER(MATCH(Data!$G:$G, Categories!$C:$C, 0)),0,1), --IF(ISNUMBER(MATCH(Data!$O:$O, {"wells_fargo_checking","sofi_savings","sofi_checking"}, 0)),-1,1), IFERROR(Data!$E:$E, 0) )} -> 1202.87 | J30: {=SUMPRODUCT( --(Data!$J:$J = Summary!J$10), --IF(ISNUMBER(MATCH(Data!$G:$G, $B28:I$29, 0)),0,1), --IF(ISNUMBER(MATCH(Data!$G:$G, Categories!$A:$A, 0)),0,1), --IF(ISNUMBER(MATCH(Data!$G:$G, Categories!$E:$E, 0)),1,0), --IF(ISNUMBER(MATCH(Data!$G:$G, Categories!$G:$G, 0)),0,1), --IF(ISNUMBER(MATCH(Data!$G:$G, Categories!$C:$C, 0)),0,1), --IF(ISNUMBER(MATCH(Data!$O:$O, {"wells_fargo_checking","sofi_savings","sofi_checking"}, 0)),-1,1), IFERROR(Data!$E:$E, 0) )} -> 3647.73 | K30: {=SUMPRODUCT( --(Data!$J:$J = Summary!K$10), --IF(ISNUMBER(MATCH(Data!$G:$G, $B28:J$29, 0)),0,1), --IF(ISNUMBER(MATCH(Data!$G:$G, Categories!$A:$A, 0)),0,1), --IF(ISNUMBER(MATCH(Data!$G:$G, Categories!$E:$E, 0)),1,0), --IF(ISNUMBER(MATCH(Data!$G:$G, Categories!$G:$G, 0)),0,1), --IF(ISNUMBER(MATCH(Data!$G:$G, Categories!$C:$C, 0)),0,1), --IF(ISNUMBER(MATCH(Data!$O:$O, {"wells_fargo_checking","sofi_savings","sofi_checking"}, 0)),-1,1), IFERROR(Data!$E:$E, 0) )} -> 4112.78 | ... N30: {=SUMPRODUCT( --(Data!$J:$J = Summary!N$10), --IF(ISNUMBER(MATCH(Data!$G:$G, $B28:M$29, 0)),0,1), --IF(ISNUMBER(MATCH(Data!$G:$G, Categories!$A:$A, 0)),0,1), --IF(ISNUMBER(MATCH(Data!$G:$G, Categories!$E:$E, 0)),1,0), --IF(ISNUMBER(MATCH(Data!$G:$G, Categories!$G:$G, 0)),0,1), --IF(ISNUMBER(MATCH(Data!$G:$G, Categories!$C:$C, 0)),0,1), --IF(ISNUMBER(MATCH(Data!$O:$O, {"wells_fargo_checking","sofi_savings","sofi_checking"}, 0)),-1,1), IFERROR(Data!$E:$E, 0) )} -> 1712.24
B31: Total | C31: =SUM(C28:C30) -> 2742.77 | D31: =SUM(D28:D30) -> 3218.08 | E31: =SUM(E28:E30) -> 2550.06 | F31: =SUM(F28:F30) -> 7262.81 | G31: =SUM(G28:G30) -> -71.85 | H31: =SUM(H28:H30) -> 3584.63 | I31: =SUM(I28:I30) -> 2345.19 | J31: =SUM(J28:J30) -> 3763.56 | ... N31: =SUM(N28:N30) -> 1782.24
B33: Travel Expenses | C33: 45292 | D33: =EOMONTH(C33,0)+1 -> 45323 | E33: =EOMONTH(D33,0)+1 -> 45352 | F33: =EOMONTH(E33,0)+1 -> 45383 | G33: =EOMONTH(F33,0)+1 -> 45413 | H33: =EOMONTH(G33,0)+1 -> 45444 | I33: =EOMONTH(H33,0)+1 -> 45474 | J33: =EOMONTH(I33,0)+1 -> 45505 | K33: =EOMONTH(J33,0)+1 -> 45536 | ... N33: =EOMONTH(M33,0)+1 -> 45627
B34: Mexico | C34: =SUMIFS(Combined_Accounts[Amount],Combined_Accounts[Date],C$2,Combined_Accounts[Short_Desc],$B34, Combined_Accounts[Account],"discover") + SUMIFS(Combined_Accounts[Amount],Combined_Accounts[Date],C$2,Combined_Accounts[Short_Desc],$B34, Combined_Accounts[Account],"wells_fargo_checking") *-1 -> 0 | D34: =SUMIFS(Combined_Accounts[Amount],Combined_Accounts[Date],D$2,Combined_Accounts[Short_Desc],$B34, Combined_Accounts[Account],"discover") + SUMIFS(Combined_Accounts[Amount],Combined_Accounts[Date],D$2,Combined_Accounts[Short_Desc],$B34, Combined_Accounts[Account],"wells_fargo_checking") *-1 -> 0 | E34: =SUMIFS(Combined_Accounts[Amount],Combined_Accounts[Date],E$2,Combined_Accounts[Short_Desc],$B34, Combined_Accounts[Account],"discover") + SUMIFS(Combined_Accounts[Amount],Combined_Accounts[Date],E$2,Combined_Accounts[Short_Desc],$B34, Combined_Accounts[Account],"wells_fargo_checking") *-1 -> 0 | F34: =SUMIFS(Combined_Accounts[Amount],Combined_Accounts[Date],F$2,Combined_Accounts[Short_Desc],$B34, Combined_Accounts[Account],"discover") + SUMIFS(Combined_Accounts[Amount],Combined_Accounts[Date],F$2,Combined_Accounts[Short_Desc],$B34, Combined_Accounts[Account],"wells_fargo_checking") *-1 -> 356.16 | G34: =SUMIFS(Combined_Accounts[Amount],Combined_Accounts[Date],G$2,Combined_Accounts[Short_Desc],$B34, Combined_Accounts[Account],"discover") + SUMIFS(Combined_Accounts[Amount],Combined_Accounts[Date],G$2,Combined_Accounts[Short_Desc],$B34, Combined_Accounts[Account],"wells_fargo_checking") *-1 -> 7.24 | H34: =SUMIFS(Combined_Accounts[Amount],Combined_Accounts[Date],H$2,Combined_Accounts[Short_Desc],$B34, Combined_Accounts[Account],"discover") + SUMIFS(Combined_Accounts[Amount],Combined_Accounts[Date],H$2,Combined_Accounts[Short_Desc],$B34, Combined_Accounts[Account],"wells_fargo_checking") *-1 -> 0 | I34: =SUMIFS(Combined_Accounts[Amount],Combined_Accounts[Date],I$2,Combined_Accounts[Short_Desc],$B34, Combined_Accounts[Account],"discover") + SUMIFS(Combined_Accounts[Amount],Combined_Accounts[Date],I$2,Combined_Accounts[Short_Desc],$B34, Combined_Accounts[Account],"wells_fargo_checking") *-1 -> 0 | J34: =SUMIFS(Combined_Accounts[Amount],Combined_Accounts[Date],J$2,Combined_Accounts[Short_Desc],$B34, Combined_Accounts[Account],"discover") + SUMIFS(Combined_Accounts[Amount],Combined_Accounts[Date],J$2,Combined_Accounts[Short_Desc],$B34, Combined_Accounts[Account],"wells_fargo_checking") *-1 -> 0 | ... N34: =SUMIFS(Combined_Accounts[Amount],Combined_Accounts[Date],N$2,Combined_Accounts[Short_Desc],$B34, Combined_Accounts[Account],"discover") + SUMIFS(Combined_Accounts[Amount],Combined_Accounts[Date],N$2,Combined_Accounts[Short_Desc],$B34, Combined_Accounts[Account],"wells_fargo_checking") *-1 -> 0 | O34: =SUM(C34:N34) -> 363.4
B35: Hawaii | C35: =SUMIFS(Combined_Accounts[Amount],Combined_Accounts[Date],C$2,Combined_Accounts[Short_Desc],$B35, Combined_Accounts[Account],"discover") + SUMIFS(Combined_Accounts[Amount],Combined_Accounts[Date],C$2,Combined_Accounts[Short_Desc],$B35, Combined_Accounts[Account],"wells_fargo_checking") *-1 -> 199.76 | D35: =SUMIFS(Combined_Accounts[Amount],Combined_Accounts[Date],D$2,Combined_Accounts[Short_Desc],$B35, Combined_Accounts[Account],"discover") + SUMIFS(Combined_Accounts[Amount],Combined_Accounts[Date],D$2,Combined_Accounts[Short_Desc],$B35, Combined_Accounts[Account],"wells_fargo_checking") *-1 -> 0 | E35: =SUMIFS(Combined_Accounts[Amount],Combined_Accounts[Date],E$2,Combined_Accounts[Short_Desc],$B35, Combined_Accounts[Account],"discover") + SUMIFS(Combined_Accounts[Amount],Combined_Accounts[Date],E$2,Combined_Accounts[Short_Desc],$B35, Combined_Accounts[Account],"wells_fargo_checking") *-1 -> 191.23 | F35: =SUMIFS(Combined_Accounts[Amount],Combined_Accounts[Date],F$2,Combined_Accounts[Short_Desc],$B35, Combined_Accounts[Account],"discover") + SUMIFS(Combined_Accounts[Amount],Combined_Accounts[Date],F$2,Combined_Accounts[Short_Desc],$B35, Combined_Accounts[Account],"wells_fargo_checking") *-1 -> 188.25 | G35: =SUMIFS(Combined_Accounts[Amount],Combined_Accounts[Date],G$2,Combined_Accounts[Short_Desc],$B35, Combined_Accounts[Account],"discover") + SUMIFS(Combined_Accounts[Amount],Combined_Accounts[Date],G$2,Combined_Accounts[Short_Desc],$B35, Combined_Accounts[Account],"wells_fargo_checking") *-1 -> 976.57 | H35: =SUMIFS(Combined_Accounts[Amount],Combined_Accounts[Date],H$2,Combined_Accounts[Short_Desc],$B35, Combined_Accounts[Account],"discover") + SUMIFS(Combined_Accounts[Amount],Combined_Accounts[Date],H$2,Combined_Accounts[Short_Desc],$B35, Combined_Accounts[Account],"wells_fargo_checking") *-1 -> 271.18 | I35: =SUMIFS(Combined_Accounts[Amount],Combined_Accounts[Date],I$2,Combined_Accounts[Short_Desc],$B35, Combined_Accounts[Account],"discover") + SUMIFS(Combined_Accounts[Amount],Combined_Accounts[Date],I$2,Combined_Accounts[Short_Desc],$B35, Combined_Accounts[Account],"wells_fargo_checking") *-1 -> 0 | J35: =SUMIFS(Combined_Accounts[Amount],Combined_Accounts[Date],J$2,Combined_Accounts[Short_Desc],$B35, Combined_Accounts[Account],"discover") + SUMIFS(Combined_Accounts[Amount],Combined_Accounts[Date],J$2,Combined_Accounts[Short_Desc],$B35, Combined_Accounts[Account],"wells_fargo_checking") *-1 -> 15 | ... N35: =SUMIFS(Combined_Accounts[Amount],Combined_Accounts[Date],N$2,Combined_Accounts[Short_Desc],$B35, Combined_Accounts[Account],"discover") + SUMIFS(Combined_Accounts[Amount],Combined_Accounts[Date],N$2,Combined_Accounts[Short_Desc],$B35, Combined_Accounts[Account],"wells_fargo_checking") *-1 -> 220.05 | O35: =SUM(C35:N35) -> 2373.54
B36: Australia | C36: =SUMIFS(Combined_Accounts[Amount],Combined_Accounts[Date],C$2,Combined_Accounts[Short_Desc],$B36, Combined_Accounts[Account],"discover") + SUMIFS(Combined_Accounts[Amount],Combined_Accounts[Date],C$2,Combined_Accounts[Short_Desc],$B36, Combined_Accounts[Account],"wells_fargo_checking") *-1 -> 0 | D36: =SUMIFS(Combined_Accounts[Amount],Combined_Accounts[Date],D$2,Combined_Accounts[Short_Desc],$B36, Combined_Accounts[Account],"discover") + SUMIFS(Combined_Accounts[Amount],Combined_Accounts[Date],D$2,Combined_Accounts[Short_Desc],$B36, Combined_Accounts[Account],"wells_fargo_checking") *-1 -> 0 | E36: =SUMIFS(Combined_Accounts[Amount],Combined_Accounts[Date],E$2,Combined_Accounts[Short_Desc],$B36, Combined_Accounts[Account],"discover") + SUMIFS(Combined_Accounts[Amount],Combined_Accounts[Date],E$2,Combined_Accounts[Short_Desc],$B36, Combined_Accounts[Account],"wells_fargo_checking") *-1 -> 13.1 | F36: =SUMIFS(Combined_Accounts[Amount],Combined_Accounts[Date],F$2,Combined_Accounts[Short_Desc],$B36, Combined_Accounts[Account],"discover") + SUMIFS(Combined_Accounts[Amount],Combined_Accounts[Date],F$2,Combined_Accounts[Short_Desc],$B36, Combined_Accounts[Account],"wells_fargo_checking") *-1 -> 0 | G36: =SUMIFS(Combined_Accounts[Amount],Combined_Accounts[Date],G$2,Combined_Accounts[Short_Desc],$B36, Combined_Accounts[Account],"discover") + SUMIFS(Combined_Accounts[Amount],Combined_Accounts[Date],G$2,Combined_Accounts[Short_Desc],$B36, Combined_Accounts[Account],"wells_fargo_checking") *-1 -> 1307.73 | H36: =SUMIFS(Combined_Accounts[Amount],Combined_Accounts[Date],H$2,Combined_Accounts[Short_Desc],$B36, Combined_Accounts[Account],"discover") + SUMIFS(Combined_Accounts[Amount],Combined_Accounts[Date],H$2,Combined_Accounts[Short_Desc],$B36, Combined_Accounts[Account],"wells_fargo_checking") *-1 -> 580.97 | I36: =SUMIFS(Combined_Accounts[Amount],Combined_Accounts[Date],I$2,Combined_Accounts[Short_Desc],$B36, Combined_Accounts[Account],"discover") + SUMIFS(Combined_Accounts[Amount],Combined_Accounts[Date],I$2,Combined_Accounts[Short_Desc],$B36, Combined_Accounts[Account],"wells_fargo_checking") *-1 -> 50.08 | J36: =SUMIFS(Combined_Accounts[Amount],Combined_Accounts[Date],J$2,Combined_Accounts[Short_Desc],$B36, Combined_Accounts[Account],"discover") + SUMIFS(Combined_Accounts[Amount],Combined_Accounts[Date],J$2,Combined_Accounts[Short_Desc],$B36, Combined_Accounts[Account],"wells_fargo_checking") *-1 -> 49.39 | ... N36: =SUMIFS(Combined_Accounts[Amount],Combined_Accounts[Date],N$2,Combined_Accounts[Short_Desc],$B36, Combined_Accounts[Account],"discover") + SUMIFS(Combined_Accounts[Amount],Combined_Accounts[Date],N$2,Combined_Accounts[Short_Desc],$B36, Combined_Accounts[Account],"wells_fargo_checking") *-1 -> 0 | O36: =SUM(C36:N36) -> 2008.04
B37: GT_China | C37: =SUMIFS(Combined_Accounts[Amount],Combined_Accounts[Date],C$2,Combined_Accounts[Short_Desc],$B37, Combined_Accounts[Account],"discover") + SUMIFS(Combined_Accounts[Amount],Combined_Accounts[Date],C$2,Combined_Accounts[Short_Desc],$B37, Combined_Accounts[Account],"wells_fargo_checking") *-1 -> 0 | D37: =SUMIFS(Combined_Accounts[Amount],Combined_Accounts[Date],D$2,Combined_Accounts[Short_Desc],$B37, Combined_Accounts[Account],"discover") + SUMIFS(Combined_Accounts[Amount],Combined_Accounts[Date],D$2,Combined_Accounts[Short_Desc],$B37, Combined_Accounts[Account],"wells_fargo_checking") *-1 -> 0 | E37: =SUMIFS(Combined_Accounts[Amount],Combined_Accounts[Date],E$2,Combined_Accounts[Short_Desc],$B37, Combined_Accounts[Account],"discover") + SUMIFS(Combined_Accounts[Amount],Combined_Accounts[Date],E$2,Combined_Accounts[Short_Desc],$B37, Combined_Accounts[Account],"wells_fargo_checking") *-1 -> 199.82 | F37: =SUMIFS(Combined_Accounts[Amount],Combined_Accounts[Date],F$2,Combined_Accounts[Short_Desc],$B37, Combined_Accounts[Account],"discover") + SUMIFS(Combined_Accounts[Amount],Combined_Accounts[Date],F$2,Combined_Accounts[Short_Desc],$B37, Combined_Accounts[Account],"wells_fargo_checking") *-1 -> 0 | G37: =SUMIFS(Combined_Accounts[Amount],Combined_Accounts[Date],G$2,Combined_Accounts[Short_Desc],$B37, Combined_Accounts[Account],"discover") + SUMIFS(Combined_Accounts[Amount],Combined_Accounts[Date],G$2,Combined_Accounts[Short_Desc],$B37, Combined_Accounts[Account],"wells_fargo_checking") *-1 -> 0 | H37: =SUMIFS(Combined_Accounts[Amount],Combined_Accounts[Date],H$2,Combined_Accounts[Short_Desc],$B37, Combined_Accounts[Account],"discover") + SUMIFS(Combined_Accounts[Amount],Combined_Accounts[Date],H$2,Combined_Accounts[Short_Desc],$B37, Combined_Accounts[Account],"wells_fargo_checking") *-1 -> 487.4 | I37: =SUMIFS(Combined_Accounts[Amount],Combined_Accounts[Date],I$2,Combined_Accounts[Short_Desc],$B37, Combined_Accounts[Account],"discover") + SUMIFS(Combined_Accounts[Amount],Combined_Accounts[Date],I$2,Combined_Accounts[Short_Desc],$B37, Combined_Accounts[Account],"wells_fargo_checking") *-1 -> 454.5 | J37: =SUMIFS(Combined_Accounts[Amount],Combined_Accounts[Date],J$2,Combined_Accounts[Short_Desc],$B37, Combined_Accounts[Account],"discover") + SUMIFS(Combined_Accounts[Amount],Combined_Accounts[Date],J$2,Combined_Accounts[Short_Desc],$B37, Combined_Accounts[Account],"wells_fargo_checking") *-1 -> -43.88 | ... N37: =SUMIFS(Combined_Accounts[Amount],Combined_Accounts[Date],N$2,Combined_Accounts[Short_Desc],$B37, Combined_Accounts[Account],"discover") + SUMIFS(Combined_Accounts[Amount],Combined_Accounts[Date],N$2,Combined_Accounts[Short_Desc],$B37, Combined_Accounts[Account],"wells_fargo_checking") *-1 -> 0 | O37: =SUM(C37:N37) -> 1097.84
B38: Other | C38: {=SUMPRODUCT( --(Data!$J:$J = Summary!C$10), --IF(ISNUMBER(MATCH(Data!$G:$G, $B$34:$B$37, 0)),0,1), --IF(ISNUMBER(MATCH(Data!$G:$G, Categories!$A:$A, 0)),0,1), --IF(ISNUMBER(MATCH(Data!$G:$G, Categories!$E:$E, 0)),0,1), --IF(ISNUMBER(MATCH(Data!$G:$G, Categories!$G:$G, 0)),1,0), --IF(ISNUMBER(MATCH(Data!$G:$G, Categories!$C:$C, 0)),0,1), --IF(ISNUMBER(MATCH(Data!$O:$O, {"wells_fargo_checking","sofi_savings","sofi_checking"}, 0)),-1,1), IFERROR(Data!$E:$E, 0) )} -> 110.44 | D38: {=SUMPRODUCT( --(Data!$J:$J = Summary!D$10), --IF(ISNUMBER(MATCH(Data!$G:$G, $B$34:$B$37, 0)),0,1), --IF(ISNUMBER(MATCH(Data!$G:$G, Categories!$A:$A, 0)),0,1), --IF(ISNUMBER(MATCH(Data!$G:$G, Categories!$E:$E, 0)),0,1), --IF(ISNUMBER(MATCH(Data!$G:$G, Categories!$G:$G, 0)),1,0), --IF(ISNUMBER(MATCH(Data!$G:$G, Categories!$C:$C, 0)),0,1), --IF(ISNUMBER(MATCH(Data!$O:$O, {"wells_fargo_checking","sofi_savings","sofi_checking"}, 0)),-1,1), IFERROR(Data!$E:$E, 0) )} -> 0 | E38: {=SUMPRODUCT( --(Data!$J:$J = Summary!E$10), --IF(ISNUMBER(MATCH(Data!$G:$G, $B$34:$B$37, 0)),0,1), --IF(ISNUMBER(MATCH(Data!$G:$G, Categories!$A:$A, 0)),0,1), --IF(ISNUMBER(MATCH(Data!$G:$G, Categories!$E:$E, 0)),0,1), --IF(ISNUMBER(MATCH(Data!$G:$G, Categories!$G:$G, 0)),1,0), --IF(ISNUMBER(MATCH(Data!$G:$G, Categories!$C:$C, 0)),0,1), --IF(ISNUMBER(MATCH(Data!$O:$O, {"wells_fargo_checking","sofi_savings","sofi_checking"}, 0)),-1,1), IFERROR(Data!$E:$E, 0) )} -> 0 | F38: {=SUMPRODUCT( --(Data!$J:$J = Summary!F$10), --IF(ISNUMBER(MATCH(Data!$G:$G, $B$34:$B$37, 0)),0,1), --IF(ISNUMBER(MATCH(Data!$G:$G, Categories!$A:$A, 0)),0,1), --IF(ISNUMBER(MATCH(Data!$G:$G, Categories!$E:$E, 0)),0,1), --IF(ISNUMBER(MATCH(Data!$G:$G, Categories!$G:$G, 0)),1,0), --IF(ISNUMBER(MATCH(Data!$G:$G, Categories!$C:$C, 0)),0,1), --IF(ISNUMBER(MATCH(Data!$O:$O, {"wells_fargo_checking","sofi_savings","sofi_checking"}, 0)),-1,1), IFERROR(Data!$E:$E, 0) )} -> 0 | G38: {=SUMPRODUCT( --(Data!$J:$J = Summary!G$10), --IF(ISNUMBER(MATCH(Data!$G:$G, $B$34:$B$37, 0)),0,1), --IF(ISNUMBER(MATCH(Data!$G:$G, Categories!$A:$A, 0)),0,1), --IF(ISNUMBER(MATCH(Data!$G:$G, Categories!$E:$E, 0)),0,1), --IF(ISNUMBER(MATCH(Data!$G:$G, Categories!$G:$G, 0)),1,0), --IF(ISNUMBER(MATCH(Data!$G:$G, Categories!$C:$C, 0)),0,1), --IF(ISNUMBER(MATCH(Data!$O:$O, {"wells_fargo_checking","sofi_savings","sofi_checking"}, 0)),-1,1), IFERROR(Data!$E:$E, 0) )} -> 100 | H38: {=SUMPRODUCT( --(Data!$J:$J = Summary!H$10), --IF(ISNUMBER(MATCH(Data!$G:$G, $B$34:$B$37, 0)),0,1), --IF(ISNUMBER(MATCH(Data!$G:$G, Categories!$A:$A, 0)),0,1), --IF(ISNUMBER(MATCH(Data!$G:$G, Categories!$E:$E, 0)),0,1), --IF(ISNUMBER(MATCH(Data!$G:$G, Categories!$G:$G, 0)),1,0), --IF(ISNUMBER(MATCH(Data!$G:$G, Categories!$C:$C, 0)),0,1), --IF(ISNUMBER(MATCH(Data!$O:$O, {"wells_fargo_checking","sofi_savings","sofi_checking"}, 0)),-1,1), IFERROR(Data!$E:$E, 0) )} -> 0 | I38: {=SUMPRODUCT( --(Data!$J:$J = Summary!I$10), --IF(ISNUMBER(MATCH(Data!$G:$G, $B$34:$B$37, 0)),0,1), --IF(ISNUMBER(MATCH(Data!$G:$G, Categories!$A:$A, 0)),0,1), --IF(ISNUMBER(MATCH(Data!$G:$G, Categories!$E:$E, 0)),0,1), --IF(ISNUMBER(MATCH(Data!$G:$G, Categories!$G:$G, 0)),1,0), --IF(ISNUMBER(MATCH(Data!$G:$G, Categories!$C:$C, 0)),0,1), --IF(ISNUMBER(MATCH(Data!$O:$O, {"wells_fargo_checking","sofi_savings","sofi_checking"}, 0)),-1,1), IFERROR(Data!$E:$E, 0) )} -> 55.26 | J38: {=SUMPRODUCT( --(Data!$J:$J = Summary!J$10), --IF(ISNUMBER(MATCH(Data!$G:$G, $B$34:$B$37, 0)),0,1), --IF(ISNUMBER(MATCH(Data!$G:$G, Categories!$A:$A, 0)),0,1), --IF(ISNUMBER(MATCH(Data!$G:$G, Categories!$E:$E, 0)),0,1), --IF(ISNUMBER(MATCH(Data!$G:$G, Categories!$G:$G, 0)),1,0), --IF(ISNUMBER(MATCH(Data!$G:$G, Categories!$C:$C, 0)),0,1), --IF(ISNUMBER(MATCH(Data!$O:$O, {"wells_fargo_checking","sofi_savings","sofi_checking"}, 0)),-1,1), IFERROR(Data!$E:$E, 0) )} -> 0 | ... N38: {=SUMPRODUCT( --(Data!$J:$J = Summary!N$10), --IF(ISNUMBER(MATCH(Data!$G:$G, $B$34:$B$37, 0)),0,1), --IF(ISNUMBER(MATCH(Data!$G:$G, Categories!$A:$A, 0)),0,1), --IF(ISNUMBER(MATCH(Data!$G:$G, Categories!$E:$E, 0)),0,1), --IF(ISNUMBER(MATCH(Data!$G:$G, Categories!$G:$G, 0)),1,0), --IF(ISNUMBER(MATCH(Data!$G:$G, Categories!$C:$C, 0)),0,1), --IF(ISNUMBER(MATCH(Data!$O:$O, {"wells_fargo_checking","sofi_savings","sofi_checking"}, 0)),-1,1), IFERROR(Data!$E:$E, 0) )} -> 67.75
B39: Total | C39: =SUM(C34:C38) -> 310.2 | D39: =SUM(D34:D37) -> 0 | E39: =SUM(E34:E37)-E35-E36 -> 199.82 | F39: =SUM(F34:F37)-F34-F37 -> 188.25 | G39: =SUM(G34:G37)-G34-G35-G36 -> 0 | H39: =SUM(H34:H37)-H37 -> 852.15 | I39: =SUM(I34:I37)-I37 -> 50.08 | J39: =SUM(J34:J37) -> 20.51 | K39: =SUM(K34:K37) -> 128.27 | L39: =SUM(L34:L37) -> 134.61 | M39: =SUM(M34:M37) -> 55.39 | N39: =SUM(N34:N37) -> 220.05 | O39: =SUM(C39:N39) -> 2159.33
O40: =SUM(O34:O39) -> 8002.15
B42: Balances | C42: 45292 | D42: =EOMONTH(C42,0)+1 -> 45323 | E42: =EOMONTH(D42,0)+1 -> 45352 | F42: =EOMONTH(E42,0)+1 -> 45383 | G42: =EOMONTH(F42,0)+1 -> 45413 | H42: =EOMONTH(G42,0)+1 -> 45444 | I42: =EOMONTH(H42,0)+1 -> 45474 | J42: =EOMONTH(I42,0)+1 -> 45505 | K42: =EOMONTH(J42,0)+1 -> 45536 | ... N42: =EOMONTH(M42,0)+1 -> 45627
A43: 0.2 | B43: wells_fargo_checking | C43: =SUMIFS(Combined_Accounts[CumAmount],Combined_Accounts[Date],C$2,Combined_Accounts[Account],$B43,Combined_Accounts[Last_balance],1) -> 734.33 | D43: =SUMIFS(Combined_Accounts[CumAmount],Combined_Accounts[Date],D$2,Combined_Accounts[Account],$B43,Combined_Accounts[Last_balance],1) -> 52.95 | E43: =SUMIFS(Combined_Accounts[CumAmount],Combined_Accounts[Date],E$2,Combined_Accounts[Account],$B43,Combined_Accounts[Last_balance],1) -> 668.68 | F43: =SUMIFS(Combined_Accounts[CumAmount],Combined_Accounts[Date],F$2,Combined_Accounts[Account],$B43,Combined_Accounts[Last_balance],1) -> 1314.06 | G43: =SUMIFS(Combined_Accounts[CumAmount],Combined_Accounts[Date],G$2,Combined_Accounts[Account],$B43,Combined_Accounts[Last_balance],1) -> 1185.66 | H43: =SUMIFS(Combined_Accounts[CumAmount],Combined_Accounts[Date],H$2,Combined_Accounts[Account],$B43,Combined_Accounts[Last_balance],1) -> 1051.62 | I43: =SUMIFS(Combined_Accounts[CumAmount],Combined_Accounts[Date],I$2,Combined_Accounts[Account],$B43,Combined_Accounts[Last_balance],1) -> 450.03 | J43: =SUMIFS(Combined_Accounts[CumAmount],Combined_Accounts[Date],J$2,Combined_Accounts[Account],$B43,Combined_Accounts[Last_balance],1) -> 635.8 | ... N43: =SUMIFS(Combined_Accounts[CumAmount],Combined_Accounts[Date],N$2,Combined_Accounts[Account],$B43,Combined_Accounts[Last_balance],1) -> 1449.98
A44: 0.6 | B44: sofi_savings | C44: =SUMIFS(Combined_Accounts[CumAmount],Combined_Accounts[Date],C$2,Combined_Accounts[Account],$B44,Combined_Accounts[Last_balance],1) -> 1743.16 | D44: =SUMIFS(Combined_Accounts[CumAmount],Combined_Accounts[Date],D$2,Combined_Accounts[Account],$B44,Combined_Accounts[Last_balance],1) -> 1035.91 | E44: =SUMIFS(Combined_Accounts[CumAmount],Combined_Accounts[Date],E$2,Combined_Accounts[Account],$B44,Combined_Accounts[Last_balance],1) -> 1332.58 | F44: =SUMIFS(Combined_Accounts[CumAmount],Combined_Accounts[Date],F$2,Combined_Accounts[Account],$B44,Combined_Accounts[Last_balance],1) -> 4016.73 | G44: =SUMIFS(Combined_Accounts[CumAmount],Combined_Accounts[Date],G$2,Combined_Accounts[Account],$B44,Combined_Accounts[Last_balance],1) -> 5168.64 | H44: =SUMIFS(Combined_Accounts[CumAmount],Combined_Accounts[Date],H$2,Combined_Accounts[Account],$B44,Combined_Accounts[Last_balance],1) -> 6974.21 | I44: =SUMIFS(Combined_Accounts[CumAmount],Combined_Accounts[Date],I$2,Combined_Accounts[Account],$B44,Combined_Accounts[Last_balance],1) -> 5471.73 | J44: =SUMIFS(Combined_Accounts[CumAmount],Combined_Accounts[Date],J$2,Combined_Accounts[Account],$B44,Combined_Accounts[Last_balance],1) -> 6267.74 | ... N44: =SUMIFS(Combined_Accounts[CumAmount],Combined_Accounts[Date],N$2,Combined_Accounts[Account],$B44,Combined_Accounts[Last_balance],1) -> 5075.54
A45: 0.1 | B45: sofi_checking | C45: =SUMIFS(Combined_Accounts[CumAmount],Combined_Accounts[Date],C$2,Combined_Accounts[Account],$B45,Combined_Accounts[Last_balance],1) -> 33.22 | D45: =SUMIFS(Combined_Accounts[CumAmount],Combined_Accounts[Date],D$2,Combined_Accounts[Account],$B45,Combined_Accounts[Last_balance],1) -> 110.29 | E45: =SUMIFS(Combined_Accounts[CumAmount],Combined_Accounts[Date],E$2,Combined_Accounts[Account],$B45,Combined_Accounts[Last_balance],1) -> 167.73 | F45: =SUMIFS(Combined_Accounts[CumAmount],Combined_Accounts[Date],F$2,Combined_Accounts[Account],$B45,Combined_Accounts[Last_balance],1) -> 175.12 | G45: =SUMIFS(Combined_Accounts[CumAmount],Combined_Accounts[Date],G$2,Combined_Accounts[Account],$B45,Combined_Accounts[Last_balance],1) -> 188.83 | H45: =SUMIFS(Combined_Accounts[CumAmount],Combined_Accounts[Date],H$2,Combined_Accounts[Account],$B45,Combined_Accounts[Last_balance],1) -> 416.62 | I45: =SUMIFS(Combined_Accounts[CumAmount],Combined_Accounts[Date],I$2,Combined_Accounts[Account],$B45,Combined_Accounts[Last_balance],1) -> 302.85 | J45: =SUMIFS(Combined_Accounts[CumAmount],Combined_Accounts[Date],J$2,Combined_Accounts[Account],$B45,Combined_Accounts[Last_balance],1) -> 939.04 | ... N45: =SUMIFS(Combined_Accounts[CumAmount],Combined_Accounts[Date],N$2,Combined_Accounts[Account],$B45,Combined_Accounts[Last_balance],1) -> 1202.43
B47: interest | C47: =SUMIFS(Combined_Accounts[Amount],Combined_Accounts[Date],C$2,Combined_Accounts[Short_Desc],$B47) -> 10.18 | D47: =SUMIFS(Combined_Accounts[Amount],Combined_Accounts[Date],D$2,Combined_Accounts[Short_Desc],$B47) -> 4.55 | E47: =SUMIFS(Combined_Accounts[Amount],Combined_Accounts[Date],E$2,Combined_Accounts[Short_Desc],$B47) -> 4.98 | F47: =SUMIFS(Combined_Accounts[Amount],Combined_Accounts[Date],F$2,Combined_Accounts[Short_Desc],$B47) -> 6.84 | G47: =SUMIFS(Combined_Accounts[Amount],Combined_Accounts[Date],G$2,Combined_Accounts[Short_Desc],$B47) -> 12.75 | H47: =SUMIFS(Combined_Accounts[Amount],Combined_Accounts[Date],H$2,Combined_Accounts[Short_Desc],$B47) -> 19.79 | I47: =SUMIFS(Combined_Accounts[Amount],Combined_Accounts[Date],I$2,Combined_Accounts[Short_Desc],$B47) -> 17.99 | J47: =SUMIFS(Combined_Accounts[Amount],Combined_Accounts[Date],J$2,Combined_Accounts[Short_Desc],$B47) -> 22.72 | ... N47: =SUMIFS(Combined_Accounts[Amount],Combined_Accounts[Date],N$2,Combined_Accounts[Short_Desc],$B47) -> 13.11
B49: Total Balance Calculated | C49: 45292 | D49: =EOMONTH(C49,0)+1 -> 45323 | E49: =EOMONTH(D49,0)+1 -> 45352 | F49: =EOMONTH(E49,0)+1 -> 45383 | G49: =EOMONTH(F49,0)+1 -> 45413 | H49: =EOMONTH(G49,0)+1 -> 45444 | I49: =EOMONTH(H49,0)+1 -> 45474 | J49: =EOMONTH(I49,0)+1 -> 45505 | K49: =EOMONTH(J49,0)+1 -> 45536 | ... N49: =EOMONTH(M49,0)+1 -> 45627
B50: Total Balance Actual | C50: =SUM(C43:C45) -> 2510.71 | D50: =SUM(D43:D45) -> 1199.15 | E50: =SUM(E43:E45) -> 2168.99 | F50: =SUM(F43:F45) -> 5505.91 | G50: =SUM(G43:G45) -> 6543.13 | H50: =SUM(H43:H45) -> 8442.45 | I50: =SUM(I43:I45) -> 6224.61 | J50: =SUM(J43:J45) -> 7842.58 | ... N50: =SUM(N43:N45) -> 7727.95
B51: Monthly Cash Flow | C51: =C3-C25-C31-C39 -> -1004.43 | D51: =D3-D25-D31-D39 -> -2301.71 | E51: =E3-E25-E31-E39 -> 315.72 | F51: =F3-F25-F31-F39 -> -782.99 | G51: =G3-G25-G31-G39 -> 5746.76 | H51: =H3-H25-H31-H39 -> 1238.02 | I51: =I3-I25-I31-I39 -> 3127.72 | J51: =J3-J25-J31-J39 -> -271.35 | ... N51: =N3-N25-N31-N39 -> 1640.29

Sheet Categories
A3: Ignore | C3: Fixed Expenses | E3: Variable Expenses | G3: Travel Expenses | I3: blocklist
A4: Short_Desc | C4: gas | E4: family | G4: Australia | I4: rent
A5: Balance | C5: parking | E5: Don | G5: Mexico | I5: vincent_debt
A6: income | C6: student_loan | E6: venmo | G6: GT_China | I6: laptop
A7: refunds | C7: care_credit | E7: misc | G7: Hawaii | I7: care_credit
A8: transfer | C8: cell_phone | E8: other_people | G8: air_travel | I8: onepass
A9: starting_balance | C9: laundry | E9: ATM | G9: airport | I9: state_farm
A10: credits | C10: la_fitness | E10: fees | I10: cell_phone
A11: payment | C11: chatgpt | E11: learning | I11: student_loan
A12: interest | C12: spotify | E12: general_festival | I12: adobe
A13: Vincent | C13: onepass | E13: restaurants | I13: apple_care
C14: breaking_points | E14: movies | I14: breaking_points
C15: hbo | E15: purchases | I15: spotify
C16: apple_care | E16: political_cause | I16: onlyfans
C17: gym | E17: real_python
C18: tolls | E18: everything_store
C19: state_farm | E19: video_games
C20: adobe | E20: onlyfans
C21: fitness | E21: restaurant
C22: microsoft365 | E22: do_the_bay
C23: car | E23: live_event
C24: nba_league_pass | E24: coffee
C25: google_one | E25: concerts
C26: school | E26: gas_station
C27: laptop | E27: amazon
C28: vincent_debt | E28: fast_food
C29: rent | E29: parks_rec
E30: self_care
E31: live_nba
E32: lickd
E33: clothing
E34: audiobooks
E35: museum
E36: medical
E37: jewelry
E38: desk_supplies
E39: concert_merch
E40: date_w_vincent
E41: conv_store
... E74: physical_therapy

Sheet Check
A2: gas | B2: -48.61 | C2: wells_fargo_checking | D2: =IF(ISNUMBER(MATCH(A2, Categories!$I$4:$I$16, 0)), "Blocklist_A", IF(ISNUMBER(MATCH(A2, Categories!$A:$A, 0)), "Blocklist_B", IF(ISNUMBER(MATCH(A2, Categories!$E:$E, 0)), "Blocklist_C", IF(ISNUMBER(MATCH(A2, Categories!$G:$G, 0)), "Blocklist_D", IF(ISNUMBER(MATCH(A2, Categories!$C:$C, 0)), "Include_List", "Unclassified"))))) -> Include_List
A3: income | B3: 527.56 | C3: wells_fargo_checking | D3: =IF(ISNUMBER(MATCH(A3, Categories!$I$4:$I$16, 0)), "Blocklist_A", IF(ISNUMBER(MATCH(A3, Categories!$A:$A, 0)), "Blocklist_B", IF(ISNUMBER(MATCH(A3, Categories!$E:$E, 0)), "Blocklist_C", IF(ISNUMBER(MATCH(A3, Categories!$G:$G, 0)), "Blocklist_D", IF(ISNUMBER(MATCH(A3, Categories!$C:$C, 0)), "Include_List", "Unclassified"))))) -> Blocklist_B
A4: gas | B4: -43.78 | C4: wells_fargo_checking | D4: =IF(ISNUMBER(MATCH(A4, Categories!$I$4:$I$16, 0)), "Blocklist_A", IF(ISNUMBER(MATCH(A4, Categories!$A:$A, 0)), "Blocklist_B", IF(ISNUMBER(MATCH(A4, Categories!$E:$E, 0)), "Blocklist_C", IF(ISNUMBER(MATCH(A4, Categories!$G:$G, 0)), "Blocklist_D", IF(ISNUMBER(MATCH(A4, Categories!$C:$C, 0)), "Include_List", "Unclassified"))))) -> Include_List
A5: purchases | B5: -108.16 | C5: wells_fargo_checking | D5: =IF(ISNUMBER(MATCH(A5, Categories!$I$4:$I$16, 0)), "Blocklist_A", IF(ISNUMBER(MATCH(A5, Categories!$A:$A, 0)), "Blocklist_B", IF(ISNUMBER(MATCH(A5, Categories!$E:$E, 0)), "Blocklist_C", IF(ISNUMBER(MATCH(A5, Categories!$G:$G, 0)), "Blocklist_D", IF(ISNUMBER(MATCH(A5, Categories!$C:$C, 0)), "Include_List", "Unclassified"))))) -> Blocklist_C
A6: purchases | B6: -223.9 | C6: wells_fargo_checking | D6: =IF(ISNUMBER(MATCH(A6, Categories!$I$4:$I$16, 0)), "Blocklist_A", IF(ISNUMBER(MATCH(A6, Categories!$A:$A, 0)), "Blocklist_B", IF(ISNUMBER(MATCH(A6, Categories!$E:$E, 0)), "Blocklist_C", IF(ISNUMBER(MATCH(A6, Categories!$G:$G, 0)), "Blocklist_D", IF(ISNUMBER(MATCH(A6, Categories!$C:$C, 0)), "Include_List", "Unclassified"))))) -> Blocklist_C
A7: purchases | B7: -326.68 | C7: wells_fargo_checking | D7: =IF(ISNUMBER(MATCH(A7, Categories!$I$4:$I$16, 0)), "Blocklist_A", IF(ISNUMBER(MATCH(A7, Categories!$A:$A, 0)), "Blocklist_B", IF(ISNUMBER(MATCH(A7, Categories!$E:$E, 0)), "Blocklist_C", IF(ISNUMBER(MATCH(A7, Categories!$G:$G, 0)), "Blocklist_D", IF(ISNUMBER(MATCH(A7, Categories!$C:$C, 0)), "Include_List", "Unclassified"))))) -> Blocklist_C
A8: income | B8: 527.56 | C8: wells_fargo_checking | D8: =IF(ISNUMBER(MATCH(A8, Categories!$I$4:$I$16, 0)), "Blocklist_A", IF(ISNUMBER(MATCH(A8, Categories!$A:$A, 0)), "Blocklist_B", IF(ISNUMBER(MATCH(A8, Categories!$E:$E, 0)), "Blocklist_C", IF(ISNUMBER(MATCH(A8, Categories!$G:$G, 0)), "Blocklist_D", IF(ISNUMBER(MATCH(A8, Categories!$C:$C, 0)), "Include_List", "Unclassified"))))) -> Blocklist_B
A9: Don | B9: -65.91 | C9: wells_fargo_checking | D9: =IF(ISNUMBER(MATCH(A9, Categories!$I$4:$I$16, 0)), "Blocklist_A", IF(ISNUMBER(MATCH(A9, Categories!$A:$A, 0)), "Blocklist_B", IF(ISNUMBER(MATCH(A9, Categories!$E:$E, 0)), "Blocklist_C", IF(ISNUMBER(MATCH(A9, Categories!$G:$G, 0)), "Blocklist_D", IF(ISNUMBER(MATCH(A9, Categories!$C:$C, 0)), "Include_List", "Unclassified"))))) -> Blocklist_C
A10: gas | B10: -43.98 | C10: wells_fargo_checking | D10: =IF(ISNUMBER(MATCH(A10, Categories!$I$4:$I$16, 0)), "Blocklist_A", IF(ISNUMBER(MATCH(A10, Categories!$A:$A, 0)), "Blocklist_B", IF(ISNUMBER(MATCH(A10, Categories!$E:$E, 0)), "Blocklist_C", IF(ISNUMBER(MATCH(A10, Categories!$G:$G, 0)), "Blocklist_D", IF(ISNUMBER(MATCH(A10, Categories!$C:$C, 0)), "Include_List", "Unclassified"))))) -> Include_List
A11: starting_balance | B11: -30 | C11: wells_fargo_checking | D11: =IF(ISNUMBER(MATCH(A11, Categories!$I$4:$I$16, 0)), "Blocklist_A", IF(ISNUMBER(MATCH(A11, Categories!$A:$A, 0)), "Blocklist_B", IF(ISNUMBER(MATCH(A11, Categories!$E:$E, 0)), "Blocklist_C", IF(ISNUMBER(MATCH(A11, Categories!$G:$G, 0)), "Blocklist_D", IF(ISNUMBER(MATCH(A11, Categories!$C:$C, 0)), "Include_List", "Unclassified"))))) -> Blocklist_B
A12: gas | B12: 527.56 | C12: wells_fargo_checking | D12: =IF(ISNUMBER(MATCH(A12, Categories!$I$4:$I$16, 0)), "Blocklist_A", IF(ISNUMBER(MATCH(A12, Categories!$A:$A, 0)), "Blocklist_B", IF(ISNUMBER(MATCH(A12, Categories!$E:$E, 0)), "Blocklist_C", IF(ISNUMBER(MATCH(A12, Categories!$G:$G, 0)), "Blocklist_D", IF(ISNUMBER(MATCH(A12, Categories!$C:$C, 0)), "Include_List", "Unclassified"))))) -> Include_List
A13: political_cause | B13: 5 | C13: discover | D13: =IF(ISNUMBER(MATCH(A13, Categories!$I$4:$I$16, 0)), "Blocklist_A", IF(ISNUMBER(MATCH(A13, Categories!$A:$A, 0)), "Blocklist_B", IF(ISNUMBER(MATCH(A13, Categories!$E:$E, 0)), "Blocklist_C", IF(ISNUMBER(MATCH(A13, Categories!$G:$G, 0)), "Blocklist_D", IF(ISNUMBER(MATCH(A13, Categories!$C:$C, 0)), "Include_List", "Unclassified"))))) -> Blocklist_C
... A120: interest | B120: 0.53 | C120: sofi_checking | D120: =IF(ISNUMBER(MATCH(A120, Categories!$I$4:$I$16, 0)), "Blocklist_A", IF(ISNUMBER(MATCH(A120, Categories!$A:$A, 0)), "Blocklist_B", IF(ISNUMBER(MATCH(A120, Categories!$E:$E, 0)), "Blocklist_C", IF(ISNUMBER(MATCH(A120, Categories!$G:$G, 0)), "Blocklist_D", IF(ISNUMBER(MATCH(A120, Categories!$C:$C, 0)), "Include_List", "Unclassified"))))) -> Blocklist_B
D121: =IF(ISNUMBER(MATCH(A121, Categories!$I$4:$I$16, 0)), "Blocklist_A", IF(ISNUMBER(MATCH(A121, Categories!$A:$A, 0)), "Blocklist_B", IF(ISNUMBER(MATCH(A121, Categories!$E:$E, 0)), "Blocklist_C", IF(ISNUMBER(MATCH(A121, Categories!$G:$G, 0)), "Blocklist_D", IF(ISNUMBER(MATCH(A121, Categories!$C:$C, 0)), "Include_List", "Unclassified"))))) -> Unclassified
D122: =IF(ISNUMBER(MATCH(A122, Categories!$I$4:$I$16, 0)), "Blocklist_A", IF(ISNUMBER(MATCH(A122, Categories!$A:$A, 0)), "Blocklist_B", IF(ISNUMBER(MATCH(A122, Categories!$E:$E, 0)), "Blocklist_C", IF(ISNUMBER(MATCH(A122, Categories!$G:$G, 0)), "Blocklist_D", IF(ISNUMBER(MATCH(A122, Categories!$C:$C, 0)), "Include_List", "Unclassified"))))) -> Unclassified
D123: =IF(ISNUMBER(MATCH(A123, Categories!$I$4:$I$16, 0)), "Blocklist_A", IF(ISNUMBER(MATCH(A123, Categories!$A:$A, 0)), "Blocklist_B", IF(ISNUMBER(MATCH(A123, Categories!$E:$E, 0)), "Blocklist_C", IF(ISNUMBER(MATCH(A123, Categories!$G:$G, 0)), "Blocklist_D", IF(ISNUMBER(MATCH(A123, Categories!$C:$C, 0)), "Include_List", "Unclassified"))))) -> Unclassified
D124: =IF(ISNUMBER(MATCH(A124, Categories!$I$4:$I$16, 0)), "Blocklist_A", IF(ISNUMBER(MATCH(A124, Categories!$A:$A, 0)), "Blocklist_B", IF(ISNUMBER(MATCH(A124, Categories!$E:$E, 0)), "Blocklist_C", IF(ISNUMBER(MATCH(A124, Categories!$G:$G, 0)), "Blocklist_D", IF(ISNUMBER(MATCH(A124, Categories!$C:$C, 0)), "Include_List", "Unclassified"))))) -> Unclassified
D125: =IF(ISNUMBER(MATCH(A125, Categories!$I$4:$I$16, 0)), "Blocklist_A", IF(ISNUMBER(MATCH(A125, Categories!$A:$A, 0)), "Blocklist_B", IF(ISNUMBER(MATCH(A125, Categories!$E:$E, 0)), "Blocklist_C", IF(ISNUMBER(MATCH(A125, Categories!$G:$G, 0)), "Blocklist_D", IF(ISNUMBER(MATCH(A125, Categories!$C:$C, 0)), "Include_List", "Unclassified"))))) -> Unclassified
D126: =IF(ISNUMBER(MATCH(A126, Categories!$I$4:$I$16, 0)), "Blocklist_A", IF(ISNUMBER(MATCH(A126, Categories!$A:$A, 0)), "Blocklist_B", IF(ISNUMBER(MATCH(A126, Categories!$E:$E, 0)), "Blocklist_C", IF(ISNUMBER(MATCH(A126, Categories!$G:$G, 0)), "Blocklist_D", IF(ISNUMBER(MATCH(A126, Categories!$C:$C, 0)), "Include_List", "Unclassified"))))) -> Unclassified
D127: =IF(ISNUMBER(MATCH(A127, Categories!$I$4:$I$16, 0)), "Blocklist_A", IF(ISNUMBER(MATCH(A127, Categories!$A:$A, 0)), "Blocklist_B", IF(ISNUMBER(MATCH(A127, Categories!$E:$E, 0)), "Blocklist_C", IF(ISNUMBER(MATCH(A127, Categories!$G:$G, 0)), "Blocklist_D", IF(ISNUMBER(MATCH(A127, Categories!$C:$C, 0)), "Include_List", "Unclassified"))))) -> Unclassified
D128: =IF(ISNUMBER(MATCH(A128, Categories!$I$4:$I$16, 0)), "Blocklist_A", IF(ISNUMBER(MATCH(A128, Categories!$A:$A, 0)), "Blocklist_B", IF(ISNUMBER(MATCH(A128, Categories!$E:$E, 0)), "Blocklist_C", IF(ISNUMBER(MATCH(A128, Categories!$G:$G, 0)), "Blocklist_D", IF(ISNUMBER(MATCH(A128, Categories!$C:$C, 0)), "Include_List", "Unclassified"))))) -> Unclassified
D129: =IF(ISNUMBER(MATCH(A129, Categories!$I$4:$I$16, 0)), "Blocklist_A", IF(ISNUMBER(MATCH(A129, Categories!$A:$A, 0)), "Blocklist_B", IF(ISNUMBER(MATCH(A129, Categories!$E:$E, 0)), "Blocklist_C", IF(ISNUMBER(MATCH(A129, Categories!$G:$G, 0)), "Blocklist_D", IF(ISNUMBER(MATCH(A129, Categories!$C:$C, 0)), "Include_List", "Unclassified"))))) -> Unclassified
D130: =IF(ISNUMBER(MATCH(A130, Categories!$I$4:$I$16, 0)), "Blocklist_A", IF(ISNUMBER(MATCH(A130, Categories!$A:$A, 0)), "Blocklist_B", IF(ISNUMBER(MATCH(A130, Categories!$E:$E, 0)), "Blocklist_C", IF(ISNUMBER(MATCH(A130, Categories!$G:$G, 0)), "Blocklist_D", IF(ISNUMBER(MATCH(A130, Categories!$C:$C, 0)), "Include_List", "Unclassified"))))) -> Unclassified
D131: =IF(ISNUMBER(MATCH(A131, Categories!$I$4:$I$16, 0)), "Blocklist_A", IF(ISNUMBER(MATCH(A131, Categories!$A:$A, 0)), "Blocklist_B", IF(ISNUMBER(MATCH(A131, Categories!$E:$E, 0)), "Blocklist_C", IF(ISNUMBER(MATCH(A131, Categories!$G:$G, 0)), "Blocklist_D", IF(ISNUMBER(MATCH(A131, Categories!$C:$C, 0)), "Include_List", "Unclassified"))))) -> Unclassified
D132: =IF(ISNUMBER(MATCH(A132, Categories!$I$4:$I$16, 0)), "Blocklist_A", IF(ISNUMBER(MATCH(A132, Categories!$A:$A, 0)), "Blocklist_B", IF(ISNUMBER(MATCH(A132, Categories!$E:$E, 0)), "Blocklist_C", IF(ISNUMBER(MATCH(A132, Categories!$G:$G, 0)), "Blocklist_D", IF(ISNUMBER(MATCH(A132, Categories!$C:$C, 0)), "Include_List", "Unclassified"))))) -> Unclassified
... D156: =IF(ISNUMBER(MATCH(A156, Categories!$I$4:$I$16, 0)), "Blocklist_A", IF(ISNUMBER(MATCH(A156, Categories!$A:$A, 0)), "Blocklist_B", IF(ISNUMBER(MATCH(A156, Categories!$E:$E, 0)), "Blocklist_C", IF(ISNUMBER(MATCH(A156, Categories!$G:$G, 0)), "Blocklist_D", IF(ISNUMBER(MATCH(A156, Categories!$C:$C, 0)), "Include_List", "Unclassified"))))) -> Unclassified

Sheet Loan Schedule
A1: Group | B1: Principal | C1: Interest Rate | D1: Monthly Payment | E1: 365 | H1: 1800 | I1: =H1-D5 -> 1357.27 | J1: Total Interest | K1: =SUM(R8:R21) -> 531.96708 | M1: =H1-SUM(D2:D3) -> 1590.11
A2: AA | B2: 5413.04 | C2: 0.0315 | D2: 113.8 | E2: =D2/$D$5 -> 0.25704154 | G2: =E8 -> 5513.07 | H2: =H3 -> 0.2 | I2: =H2*$I$1+D2 -> 385.254 | L2: 0.5 | M2: =L2*$M$1 -> 795.055
A3: AC | B3: 4570.98 | C3: 0.0315 | D3: 96.09 | E3: =D3/$D$5 -> 0.21703973 | G3: =J8 -> 4655.45 | H3: =(1/2)*(H5-H4) -> 0.2 | I3: =H3*$I$1+D3 -> 367.544 | L3: 0.5 | M3: =L3*$M$1 -> 795.055
A4: AE | B4: 10785.67 | C4: 0.0516 | D4: 232.84 | E4: =D4/$D$5 -> 0.52591873 | G4: =O8 -> 10973.66 | H4: 0.6 | I4: =H4*$I$1+D4 -> 1047.202
B5: =SUM(B2:B4) -> 20769.69 | D5: =SUM(D2:D4) -> 442.73 | G5: =SUM(G2:G4) -> 21142.18 | H5: 1
Q6: Total | V6: =K1 -> 531.96708
A7: Month | B7: Interest Payment | C7: Principal Payment | D7: Total Payment | E7: Remaining Balance | G7: Interest Payment | H7: Principal Payment | I7: Total Payment | J7: Remaining Balance | L7: Interest Payment | M7: Principal Payment | N7: Total Payment | O7: Remaining Balance | Q7: Balance | R7: Interest | S7: Payments | U7: 0.55 | V7: 536.73888
A8: 45359 | B8: 13.77 | C8: 100.03 | D8: =C8+B8 -> 113.8 | E8: =B2+C8 -> 5513.07 | G8: 11.62 | H8: 84.47 | I8: =D3 -> 96.09 | J8: =B3+H8 -> 4655.45 | L8: 44.85 | M8: 187.99 | N8: 232.84 | O8: =M8+B4 -> 10973.66 | Q8: =SUM(O8,J8,E8) -> 21142.18 | R8: =SUM(L8,G8,B8) -> 70.24 | S8: =N8+I8+D8 -> 442.73 | U8: =U7+1% -> 0.56 | V8: 535.41557
A9: 45390 | B9: =IF(E8=D9,0,$C$2/$E$1*E9*(A9-A8)) -> 14.481736 | C9: =D9-B9 -> 370.77226 | D9: =IF(E9<$I$2, E9,$I$2) -> 385.254 | E9: =E8-C8 -> 5413.04 | G9: =$C$3/$E$1*J9*(A9-A8) -> 12.228937 | H9: =I9-G9 -> 355.31506 | I9: =IF(J9<$I$3,J9,$I$3) -> 367.544 | J9: =J8-H8 -> 4570.98 | L9: =$C$4/$E$1*O9*(A9-A8) -> 47.267829 | M9: =N9-L9 -> 999.93417 | N9: =IF(O9<$I$4,O9,$I$4) -> 1047.202 | O9: =O8-M8 -> 10785.67 | Q9: =SUM(O9,J9,E9) -> 20769.69 | R9: =SUM(L9,G9,B9) -> 73.978502 | S9: =N9+I9+D9 -> 1800 | U9: =U8+1% -> 0.57 | V9: 534.12442
A10: =EOMONTH(A9,0)+8 -> 45420 | B10: =IF(E9=D10,0,$C$2/$E$1*E10*(A10-A9)) -> 13.054638 | C10: =D10-B10 -> 372.19936 | D10: =IF(E10<$I$2, E10,$I$2) -> 385.254 | E10: =E9-C9 -> 5042.2677 | G10: =$C$3/$E$1*J10*(A10-A9) -> 10.91453 | H10: =I10-G10 -> 356.62947 | I10: =IF(J10<$I$3,J10,$I$3) -> 367.544 | J10: =J9-H9 -> 4215.6649 | L10: =$C$4/$E$1*O10*(A10-A9) -> 41.502244 | M10: =N10-L10 -> 1005.6998 | N10: =IF(O10<$I$4,O10,$I$4) -> 1047.202 | O10: =O9-M9 -> 9785.7358 | Q10: =SUM(O10,J10,E10) -> 19043.669 | R10: =SUM(L10,G10,B10) -> 65.471412 | S10: =N10+I10+D10 -> 1800 | U10: =U9+1% -> 0.58 | V10: 533.40531
A11: =EOMONTH(A10,0)+8 -> 45451 | B11: =IF(E10=D11,0,$C$2/$E$1*E11*(A11-A10)) -> 12.494032 | C11: =D11-B11 -> 372.75997 | D11: =IF(E11<$I$2, E11,$I$2) -> 385.254 | E11: =E10-C10 -> 4670.0684 | G11: =$C$3/$E$1*J11*(A11-A10) -> 10.324241 | H11: =I11-G11 -> 357.21976 | I11: =IF(J11<$I$3,J11,$I$3) -> 367.544 | J11: =J10-H10 -> 3859.0355 | L11: =$C$4/$E$1*O11*(A11-A10) -> 38.478207 | M11: =N11-L11 -> 1008.7238 | N11: =IF(O11<$I$4,O11,$I$4) -> 1047.202 | O11: =O10-M10 -> 8780.0361 | Q11: =SUM(O11,J11,E11) -> 17309.14 | R11: =SUM(L11,G11,B11) -> 61.296481 | S11: =N11+I11+D11 -> 1800 | U11: =U10+1% -> 0.59 | V11: 532.6862
A12: =EOMONTH(A11,0)+8 -> 45481 | B12: =IF(E11=D12,0,$C$2/$E$1*E12*(A12-A11)) -> 11.125908 | C12: =D12-B12 -> 374.12809 | D12: =IF(E12<$I$2, E12,$I$2) -> 385.254 | E12: =E11-C11 -> 4297.3084 | G12: =$C$3/$E$1*J12*(A12-A11) -> 9.0663448 | H12: =I12-G12 -> 358.47766 | I12: =IF(J12<$I$3,J12,$I$3) -> 367.544 | J12: =J11-H11 -> 3501.8157 | L12: =$C$4/$E$1*O12*(A12-A11) -> 32.958881 | M12: =N12-L12 -> 1014.2431 | N12: =IF(O12<$I$4,O12,$I$4) -> 1047.202 | O12: =O11-M11 -> 7771.3123 | Q12: =SUM(O12,J12,E12) -> 15570.436 | R12: =SUM(L12,G12,B12) -> 53.151133 | S12: =N12+I12+D12 -> 1800 | U12: =U11+1% -> 0.6 | V12: 531.96708
A13: =EOMONTH(A12,0)+8 -> 45512 | B13: =IF(E12=D13,0,$C$2/$E$1*E13*(A13-A12)) -> 10.495851 | C13: =D13-B13 -> 374.75815 | D13: =IF(E13<$I$2, E13,$I$2) -> 385.254 | E13: =E12-C12 -> 3923.1803 | G13: =$C$3/$E$1*J13*(A13-A12) -> 8.4095058 | H13: =I13-G13 -> 359.13449 | I13: =IF(J13<$I$3,J13,$I$3) -> 367.544 | J13: =J12-H12 -> 3143.3381 | L13: =$C$4/$E$1*O13*(A13-A12) -> 29.612624 | M13: =N13-L13 -> 1017.5894 | N13: =IF(O13<$I$4,O13,$I$4) -> 1047.202 | O13: =O12-M12 -> 6757.0692 | Q13: =SUM(O13,J13,E13) -> 13823.588 | R13: =SUM(L13,G13,B13) -> 48.517981 | S13: =N13+I13+D13 -> 1800 | U13: =U12+1% -> 0.61 | V13: 531.24797
A14: =EOMONTH(A13,0)+8 -> 45543 | B14: =IF(E13=D14,0,$C$2/$E$1*E14*(A14-A13)) -> 9.4932445 | C14: =D14-B14 -> 375.76076 | D14: =IF(E14<$I$2, E14,$I$2) -> 385.254 | E14: =E13-C13 -> 3548.4222 | G14: =$C$3/$E$1*J14*(A14-A13) -> 7.448698 | H14: =I14-G14 -> 360.0953 | I14: =IF(J14<$I$3,J14,$I$3) -> 367.544 | J14: =J13-H13 -> 2784.2036 | L14: =$C$4/$E$1*O14*(A14-A13) -> 25.153074 | M14: =N14-L14 -> 1022.0489 | N14: =IF(O14<$I$4,O14,$I$4) -> 1047.202 | O14: =O13-M13 -> 5739.4798 | Q14: =SUM(O14,J14,E14) -> 12072.106 | R14: =SUM(L14,G14,B14) -> 42.095016 | S14: =N14+I14+D14 -> 1800 | U14: =U13+1% -> 0.62 | V14: 530.52886
A15: =EOMONTH(A14,0)+8 -> 45573 | B15: =IF(E14=D15,0,$C$2/$E$1*E15*(A15-A14)) -> 8.2141508 | C15: =D15-B15 -> 377.03985 | D15: =IF(E15<$I$2, E15,$I$2) -> 385.254 | E15: =E14-C14 -> 3172.6614 | G15: =$C$3/$E$1*J15*(A15-A14) -> 6.2761159 | H15: =I15-G15 -> 361.26788 | I15: =IF(J15<$I$3,J15,$I$3) -> 367.544 | J15: =J14-H14 -> 2424.1083 | L15: =$C$4/$E$1*O15*(A15-A14) -> 20.007077 | M15: =N15-L15 -> 1027.1949 | N15: =IF(O15<$I$4,O15,$I$4) -> 1047.202 | O15: =O14-M14 -> 4717.4309 | Q15: =SUM(O15,J15,E15) -> 10314.201 | R15: =SUM(L15,G15,B15) -> 34.497343 | S15: =N15+I15+D15 -> 1800 | U15: =U14+1% -> 0.63 | V15: 529.9185
A16: =EOMONTH(A15,0)+8 -> 45604 | B16: =IF(E15=D16,0,$C$2/$E$1*E16*(A16-A15)) -> 7.4792451 | C16: =D16-B16 -> 377.77475 | D16: =IF(E16<$I$2, E16,$I$2) -> 385.254 | E16: =E15-C15 -> 2795.6216 | G16: =$C$3/$E$1*J16*(A16-A15) -> 5.5188044 | H16: =I16-G16 -> 362.0252 | I16: =IF(J16<$I$3,J16,$I$3) -> 367.544 | J16: =J15-H15 -> 2062.8404 | L16: =$C$4/$E$1*O16*(A16-A15) -> 16.172333 | M16: =N16-L16 -> 1031.0297 | N16: =IF(O16<$I$4,O16,$I$4) -> 1047.202 | O16: =O15-M15 -> 3690.2359 | Q16: =SUM(O16,J16,E16) -> 8548.6979 | R16: =SUM(L16,G16,B16) -> 29.170382 | S16: =N16+I16+D16 -> 1800 | U16: =U15+1% -> 0.64 | V16: 529.40177
A17: =EOMONTH(A16,0)+8 -> 45634 | B17: =IF(E16=D17,0,$C$2/$E$1*E17*(A17-A16)) -> 6.2599047 | C17: =D17-B17 -> 378.9941 | D17: =IF(E17<$I$2, E17,$I$2) -> 385.254 | E17: =E16-C16 -> 2417.8468 | G17: =$C$3/$E$1*J17*(A17-A16) -> 4.4034804 | H17: =I17-G17 -> 363.14052 | I17: =IF(J17<$I$3,J17,$I$3) -> 367.544 | J17: =J16-H16 -> 1700.8152 | L17: =$C$4/$E$1*O17*(A17-A16) -> 11.277949 | M17: =N17-L17 -> 1035.9241 | N17: =IF(O17<$I$4,O17,$I$4) -> 1047.202 | O17: =O16-M16 -> 2659.2063 | Q17: =SUM(O17,J17,E17) -> 6777.8683 | R17: =SUM(L17,G17,B17) -> 21.941334 | S17: =N17+I17+D17 -> 1800 | U17: =U16+1% -> 0.65 | V17: 529.38111
A18: =EOMONTH(A17,0)+8 -> 45665 | B18: =IF(E17=D18,0,$C$2/$E$1*E18*(A18-A17)) -> 5.4546292 | C18: =D18-B18 -> 379.79937 | D18: =IF(E18<$I$2, E18,$I$2) -> 385.254 | E18: =E17-C17 -> 2038.8527 | G18: =$C$3/$E$1*J18*(A18-A17) -> 3.5787378 | H18: =I18-G18 -> 363.96526 | I18: =IF(J18<$I$3,J18,$I$3) -> 367.544 | J18: =J17-H17 -> 1337.6747 | L18: =$C$4/$E$1*O18*(A18-A17) -> 7.1139787 | M18: =N18-L18 -> 1040.088 | N18: =IF(O18<$I$4,O18,$I$4) -> 1047.202 | O18: =O17-M17 -> 1623.2822 | Q18: =SUM(O18,J18,E18) -> 4999.8096 | R18: =SUM(L18,G18,B18) -> 16.147346 | S18: =N18+I18+D18 -> 1800
A19: =EOMONTH(A18,0)+8 -> 45696 | B19: =IF(E18=D19,0,$C$2/$E$1*E19*(A19-A18)) -> 4.4385359 | C19: =D19-B19 -> 380.81546 | D19: =IF(E19<$I$2, E19,$I$2) -> 385.254 | E19: =E18-C18 -> 1659.0533 | G19: =$C$3/$E$1*J19*(A19-A18) -> 2.6050061 | H19: =I19-G19 -> 364.93899 | I19: =IF(J19<$I$3,J19,$I$3) -> 367.544 | J19: =J18-H18 -> 973.7094 | L19: =$C$4/$E$1*O19*(A19-A18) -> 2.5558286 | M19: =N19-L19 -> 583.1942 | N19: =IF(O19<$I$4,O19,$I$4)+($C$4/$E$1*O19*(A19-A18)) -> 585.75002 | O19: =O18-M18 -> 583.1942 | Q19: =SUM(O19,J19,E19) -> 3215.9569 | R19: =SUM(L19,G19,B19) -> 9.5993705 | S19: =N19+I19+D19 -> 1338.548
A20: =EOMONTH(A19,0)+8 -> 45724 | B20: =IF(E19=D20,0,$C$2/$E$1*E20*(A20-A19)) -> 3.088783 | C20: =D20-B20 -> 791.96622 | D20: =IF(E20<$M$2, E20,$M$2) -> 795.055 | E20: =E19-C19 -> 1278.2379 | G20: =$C$3/$E$1*J20*(A20-A19) -> 1.4710561 | H20: =I20-G20 -> 608.7704 | I20: =IF(J20<$M$3,J20,$M$3)+($C$3/$E$1*J20*(A20-A19)) -> 610.24146 | J20: =J19-H19 -> 608.7704 | L20: =$C$4/$E$1*O20*(A20-A19) -> 0 | M20: =N20-L20 -> 0 | N20: =IF(O20<$I$4,O20,$I$4) -> 0 | O20: =O19-M19 -> 0 | Q20: =SUM(O20,J20,E20) -> 1887.0083 | R20: =SUM(L20,G20,B20) -> 4.5598392 | S20: =N20+I20+D20 -> 1405.2965
A21: =EOMONTH(A20,0)+8 -> 45755 | B21: =IF(E20=D21,0,$C$2/$E$1*E21*(A21-A20)) -> 1.3009432 | C21: =D21-B21 -> 486.27166 | D21: =IF(E21<$M$2, E21,$M$2)+($C$2/$E$1*E21*(A21-A20)) -> 487.5726 | E21: =E20-C20 -> 486.27166 | G21: =$C$3/$E$1*J21*(A21-A20) -> 0 | H21: =I21-G21 -> 0 | I21: =IF(J21<$I$3,J21,$I$3) -> 0 | J21: =J20-H20 -> 0 | L21: =$C$4/$E$1*O21*(A21-A20) -> 0 | M21: =N21-L21 -> 0 | N21: =IF(O21<$I$4,O21,$I$4) -> 0 | O21: =O20-M20 -> 0 | Q21: =SUM(O21,J21,E21) -> 486.27166 | R21: =SUM(L21,G21,B21) -> 1.3009432 | S21: =N21+I21+D21 -> 487.5726
J26: 1800
J27: 1800
J28: 1800
J29: 1800
J30: 1800
J31: 1800
J32: 1800
J33: 1800
J34: 1800
J35: 1800
J36: 1338.548
J37: 1405.2965
J38: 487.5726
XFD1048550: {=solver_pre} -> #NAME?
XFD1048551: {=solver_scl} -> #NAME?
XFD1048552: {=solver_rlx} -> #NAME?
XFD1048553: {=solver_tol} -> #NAME?
XFD1048554: {=solver_cvg} -> #NAME?
XFD1048555: {=AREAS(solver_adj1)} -> #NAME?
XFD1048556: {=solver_ssz} -> #NAME?
XFD1048557: {=solver_rsd} -> #NAME?
XFD1048558: {=solver_mrt} -> #NAME?
XFD1048559: {=solver_mni} -> #NAME?
XFD1048560: {=solver_rbv} -> #NAME?
XFD1048561: {=solver_neg} -> #NAME?
XFD1048562: {=solver_ntr} -> #NAME?
XFD1048563: {=solver_acc} -> #NAME?
XFD1048564: {=solver_res} -> #NAME?
XFD1048565: {=solver_ars} -> #NAME?
XFD1048566: {=solver_sta} -> #NAME?
XFD1048567: {=solver_met} -> #NAME?
XFD1048568: {=solver_soc} -> #NAME?
XFD1048569: {=solver_lpt} -> #NAME?
XFD1048570: {=solver_lpp} -> #NAME?
XFD1048571: {=solver_gap} -> #NAME?
XFD1048572: {=solver_ips} -> #NAME?
XFD1048573: {=solver_fea} -> #NAME?
XFD1048574: {=solver_ipi} -> #NAME?
XFD1048575: {=solver_ipd} -> #NAME?

Sheet Lasik
B2: 5535.28
A3: 45090
A4: =EOMONTH(A3,0)+10 -> 45117 | B4: =$B$2/20 -> 276.764 | C4: =B2-B4 -> 5258.516 | D4: 1
A5: =EOMONTH(A4,0)+10 -> 45148 | B5: =$B$2/20 -> 276.764 | C5: =C4-B5 -> 4981.752 | D5: 1
A6: =EOMONTH(A5,0)+10 -> 45179 | B6: =$B$2/20 -> 276.764 | C6: =C5-B6 -> 4704.988 | D6: 1
A7: =EOMONTH(A6,0)+10 -> 45209 | B7: =$B$2/20 -> 276.764 | C7: =C6-B7 -> 4428.224 | D7: 1
A8: =EOMONTH(A7,0)+10 -> 45240 | B8: =$B$2/20 -> 276.764 | C8: =C7-B8 -> 4151.46 | D8: 1
A9: =EOMONTH(A8,0)+10 -> 45270 | B9: =$B$2/20 -> 276.764 | C9: =C8-B9 -> 3874.696 | D9: 1
A10: =EOMONTH(A9,0)+10 -> 45301 | B10: =$B$2/20 -> 276.764 | C10: =C9-B10 -> 3597.932 | D10: 1
A11: =EOMONTH(A10,0)+10 -> 45332 | B11: =$B$2/20 -> 276.764 | C11: =C10-B11 -> 3321.168 | D11: 1
A12: =EOMONTH(A11,0)+10 -> 45361 | B12: =$B$2/20 -> 276.764 | C12: =C11-B12 -> 3044.404 | D12: 1
A13: =EOMONTH(A12,0)+10 -> 45392 | B13: =$B$2/20 -> 276.764 | C13: =C12-B13 -> 2767.64
A14: =EOMONTH(A13,0)+10 -> 45422 | B14: =$B$2/20 -> 276.764 | C14: =C13-B14 -> 2490.876
A15: =EOMONTH(A14,0)+10 -> 45453 | B15: =$B$2/20 -> 276.764 | C15: =C14-B15 -> 2214.112
A16: =EOMONTH(A15,0)+10 -> 45483 | B16: =$B$2/20 -> 276.764 | C16: =C15-B16 -> 1937.348
A17: =EOMONTH(A16,0)+10 -> 45514 | B17: =$B$2/20 -> 276.764 | C17: =C16-B17 -> 1660.584
A18: =EOMONTH(A17,0)+10 -> 45545 | B18: =$B$2/20 -> 276.764 | C18: =C17-B18 -> 1383.82
A19: =EOMONTH(A18,0)+10 -> 45575 | B19: =$B$2/20 -> 276.764 | C19: =C18-B19 -> 1107.056
A20: =EOMONTH(A19,0)+10 -> 45606 | B20: =$B$2/20 -> 276.764 | C20: =C19-B20 -> 830.292
A21: =EOMONTH(A20,0)+10 -> 45636 | B21: =$B$2/20 -> 276.764 | C21: =C20-B21 -> 553.528
A22: =EOMONTH(A21,0)+10 -> 45667 | B22: =$B$2/20 -> 276.764 | C22: =C21-B22 -> 276.764
A23: =EOMONTH(A22,0)+10 -> 45698 | B23: =$B$2/20 -> 276.764 | C23: =C22-B23 -> -2.2737368e-12
A24: =EOMONTH(A23,0)+10 -> 45726 | B24: =$B$2/20 -> 276.764 | C24: =C23-B24 -> -276.764
... A28: =EOMONTH(A27,0)+10 -> 45848 | B28: =$B$2/20 -> 276.764 | C28: =C27-B28 -> -1383.82
