Workbook

Sheet June Plan
A1: Sean Account Start | B1: 919.69 | C1: =750 -> 750
A2: Vincent Principal | B2: 18404.81 | C2: =SUM(Vincent!$D:$D) -> 14427.18 | D2: 16 | E2: =C2/D2 -> 901.69875 | F2: =SUM(J19:AI19) -> 9016.9875
A3: Lasik | C3: =Care_Credit!D26 -> 5695 | D3: 24 | E3: =C3/D3 -> 237.29167
A4: Student Loan | C4: 22430.56 | D4: =C4/E4 -> 64.62276 | E4: 347.1 | J4: 2732.7
C5: 5765.25 | D5: 0.034 | J5: 482.24
C6: 4868.38 | D6: 0.034 | J6: =SUM(J4:J5) -> 3214.94
C7: 11796.93 | D7: 0.0541
M8: Milestone 1 | Y8: Milestone 2
A10: Pay Date | B10: 45090 | C10: =B10+14 -> 45104 | D10: =C10+14 -> 45118 | E10: =D10+14 -> 45132 | F10: =E10+14 -> 45146 | G10: =F10+14 -> 45160 | H10: =G10+14 -> 45174 | I10: =H10+14 -> 45188 | J10: =I10+14 -> 45202 | ... AI10: =AH10+14 -> 45552
A11: Sofi | B11: 2258.37 | C11: =B11 -> 2258.37 | D11: =C11 -> 2258.37 | E11: =D11 -> 2258.37 | F11: =E11 -> 2258.37 | G11: =F11 -> 2258.37 | H11: =G11 -> 2258.37 | I11: 2732.7 | J11: 2732.7 | K11: 2732.7 | L11: 2732.7 | M11: 2732.7 | N11: 2732.7 | O11: 2732.7 | P11: 2732.7 | Q11: 2732.7 | R11: 2732.7 | S11: 2732.7 | T11: 2732.7 | U11: 2732.7 | V11: 2732.7 | W11: 2732.7 | X11: 2732.7 | Y11: 2732.7 | Z11: 2732.7 | AA11: 2732.7 | AB11: 2732.7 | AC11: 2732.7 | AD11: 2732.7 | AE11: 2732.7 | AF11: 2732.7 | AG11: 2732.7 | AH11: 2732.7 | AI11: 2732.7
A12: Wells Fargo | B12: 398.53 | C12: 398.53 | D12: 398.53 | E12: 398.53 | F12: 398.53 | G12: 398.53 | H12: 398.53 | I12: 482.24 | J12: 482.24 | K12: 482.24 | L12: 482.24 | M12: 482.24 | N12: 482.24 | O12: 482.24 | P12: 482.24 | Q12: 482.24 | R12: 482.24 | S12: 482.24 | T12: 482.24 | U12: 482.24 | V12: 482.24 | W12: 482.24 | X12: 482.24 | Y12: 482.24 | Z12: 482.24 | AA12: 482.24 | AB12: 482.24 | AC12: 482.24 | AD12: 482.24 | AE12: 482.24 | AF12: 482.24 | AG12: 482.24 | AH12: 482.24 | AI12: 482.24
B13: 2656.9 | C13: 2656.9 | D13: 2656.9 | E13: 2656.9 | F13: 2656.91 | G13: 2656.89 | H13: 2656.91 | I13: =SUM(I11:I12) -> 3214.94 | J13: =SUM(J11:J12) -> 3214.94 | K13: =SUM(K11:K12) -> 3214.94 | L13: =SUM(L11:L12) -> 3214.94 | M13: =SUM(M11:M12) -> 3214.94 | N13: =SUM(N11:N12) -> 3214.94 | O13: =SUM(O11:O12) -> 3214.94 | P13: =SUM(P11:P12) -> 3214.94 | ... AI13: =SUM(AI11:AI12) -> 3214.94
A15: Prev balance | B15: =B1 -> 919.69 | C15: =B32 -> 319.41722 | D15: =C32 -> 2068.8944 | E15: =D32 -> 1195.9957 | F15: =E32 -> 2701.1969 | G15: =F32 -> 2068.8082 | H15: =G32 -> 2804.1994 | I15: =H32 -> 1770.0807 | J15: =I32 -> 3681.6003 | ... AI15: =AH32 -> 35775.873
B17: TRUE | C17: TRUE | D17: TRUE | E17: TRUE | F17: TRUE | G17: TRUE | H17: TRUE | I17: TRUE | J17: TRUE | K17: TRUE | L17: TRUE | M17: TRUE | N17: TRUE | O17: TRUE | P17: TRUE | Q17: TRUE | R17: TRUE | S17: FALSE
B18: =EOMONTH(B10,-1)+1 -> 45078 | D18: =EOMONTH(D10,-1)+1 -> 45108 | F18: =EOMONTH(F10,-1)+1 -> 45139 | H18: =EOMONTH(H10,-1)+1 -> 45170 | J18: =EOMONTH(J10,-1)+1 -> 45200 | M18: =EOMONTH(M10,-1)+1 -> 45231 | O18: =EOMONTH(O10,-1)+1 -> 45261 | Q18: =EOMONTH(Q10,-1)+1 -> 45292 | S18: =EOMONTH(S10,-1)+1 -> 45323 | U18: =EOMONTH(U10,-1)+1 -> 45352 | W18: =EOMONTH(W10,-1)+1 -> 45383 | Z18: =EOMONTH(Z10,-1)+1 -> 45413 | AB18: =EOMONTH(AB10,-1)+1 -> 45444 | AD18: =EOMONTH(AD10,-1)+1 -> 45474 | AF18: =EOMONTH(AF10,-1)+1 -> 45505 | AH18: =EOMONTH(AH10,-1)+1 -> 45536
A19: Vincent Payment | B19: 907.42278 | C19: 907.42278 | D19: =$E$2 -> 901.69875 | E19: =$E$2 -> 901.69875 | F19: =$E$2 -> 901.69875 | G19: =$E$2 -> 901.69875 | H19: =$E$2 -> 901.69875 | I19: =$E$2 -> 901.69875 | J19: =$E$2 -> 901.69875 | K19: =$E$2 -> 901.69875 | ... S19: =$E$2 -> 901.69875 | T19: 0 | U19: 0 | V19: 0 | W19: 0 | X19: 0 | Y19: 0 | Z19: 0 | AA19: 0 | AB19: 0 | AC19: 0 | AD19: 0 | AE19: 0 | AF19: 0 | AG19: 0 | AH19: 0 | AI19: 0
A20: Lasik Payment | D20: 428 | E20: 250 | H20: 237.29 | I20: =$E$3 -> 237.29167 | J20: =$E$3 -> 237.29167 | K20: =$E$3 -> 237.29167 | L20: =$E$3 -> 237.29167 | M20: =$E$3 -> 237.29167 | N20: =$E$3 -> 237.29167 | O20: =$E$3 -> 237.29167 | P20: =$E$3 -> 237.29167 | ... AA20: =$E$3 -> 237.29167 | AB20: 0 | AC20: 0 | AD20: 0 | AE20: 0 | AF20: 0 | AG20: 0 | AH20: 0 | AI20: 0
A21: Student Loan Payment | J21: 347.1 | M21: 347.1 | O21: 347.1 | Q21: 347.1 | S21: 347.1 | U21: =$E$4 -> 347.1 | W21: =$E$4 -> 347.1 | Z21: =$E$4 -> 347.1 | AB21: =$E$4 -> 347.1 | AD21: =$E$4 -> 347.1 | AF21: =$E$4 -> 347.1 | AH21: =$E$4 -> 347.1
A22: Best Buy Payment | J22: 153.81 | L22: 153.81 | N22: 153.81 | P22: 153.81 | R22: 153.81 | T22: 153.81 | V22: 153.81 | X22: 153.81 | Z22: 153.81 | AB22: 153.81 | AD22: 153.81 | AF22: 153.81
A23: American Express Payment
A24: Slinger Payment | H24: 164.44 | I24: 164.43 | J24: 164.43 | K24: 164.44
A25: Stutter Health
A26: One Pass | B26: 125.1 | D26: 125.1 | F26: 125.1 | H26: 125.1 | J26: 125.1 | M26: 125.1 | O26: 125.1 | Q26: 125.1 | S26: 125.1 | U26: 125.1 | W26: 125.1 | Z26: 125.1 | AB26: 125.1 | AD26: 125.1 | AF26: 125.1 | AH26: 125.1
A27: Rent | B27: 625 | D27: 625 | F27: 812.5 | H27: 812.5 | J27: 812.5 | M27: 812.5 | O27: 812.5 | Q27: 812.5 | S27: 812.5 | U27: 812.5 | W27: 812.5 | Z27: 812.5 | AB27: 812.5 | AD27: 812.5 | AF27: 812.5 | AH27: 812.5
A28: Bills (Fixed Expense) | B28: =Summary!J45 -> 849.65 | D28: 700 | F28: 700 | H28: 700 | J28: 700 | M28: 700 | O28: 700 | Q28: 700 | S28: 700 | U28: 700 | W28: 700 | Z28: 700 | AB28: 700 | AD28: 700 | AF28: 700 | AH28: 700
A29: Spending Estimate | B29: =$C$1 -> 750 | D29: =$C$1 -> 750 | F29: =$C$1 -> 750 | H29: =$C$1 -> 750 | J29: =$C$1 -> 750 | M29: =$C$1 -> 750 | O29: =$C$1 -> 750 | Q29: =$C$1 -> 750 | S29: =$C$1 -> 750 | U29: =$C$1 -> 750 | W29: =$C$1 -> 750 | Z29: =$C$1 -> 750 | AB29: =$C$1 -> 750 | AD29: =$C$1 -> 750 | AF29: =$C$1 -> 750 | AH29: =$C$1 -> 750
A30: Car Repair | G30: 1019.8
A32: Cash Flow | B32: =B13+B15-SUM(B19:B29) -> 319.41722 | C32: =C13+C15-SUM(C19:C29) -> 2068.8944 | D32: =D13+D15-SUM(D19:D29) -> 1195.9957 | E32: =E13+E15-SUM(E19:E29) -> 2701.1969 | F32: =F13+F15-SUM(F19:F29) -> 2068.8082 | G32: =G13+G15-SUM(G19:G30) -> 2804.1994 | H32: =H13+H15-SUM(H19:H29) -> 1770.0807 | I32: =I13+I15-SUM(I19:I29) -> 3681.6003 | J32: =J13+J15-SUM(J19:J29) -> 2704.6099 | K32: =K13+K15-SUM(K19:K29) -> 4616.1194 | L32: =L13+L15-SUM(L19:L29) -> 6538.259 | M32: =M13+M15-SUM(M19:M29) -> 5879.5086 | N32: =N13+N15-SUM(N19:N29) -> 7801.6482 | O32: =O13+O15-SUM(O19:O29) -> 7142.8978 | ... AI32: =AI13+AI15-SUM(AI19:AI29) -> 38990.813
A33: Vincent Debt Princpal | D33: =C2-D19 -> 13525.481 | E33: =D33-E19 -> 12623.782 | F33: =E33-F19 -> 11722.084 | G33: =F33-G19 -> 10820.385 | H33: =G33-H19 -> 9918.6863 | I33: =H33-I19 -> 9016.9875 | J33: =I33-J19 -> 8115.2888 | K33: =J33-K19 -> 7213.59 | L33: =K33-L19 -> 6311.8913 | ... AI33: =AH33-AI19 -> 3.4106051e-12
A34: LASIK Debt Principal | D34: =C3-D20 -> 5267 | E34: =D34-E20 -> 5017 | F34: =E34-F20 -> 5017 | G34: =F34-G20 -> 5017 | H34: =G34-H20 -> 4779.71 | I34: =H34-I20 -> 4542.4183 | J34: =I34-J20 -> 4305.1267 | K34: =J34-K20 -> 4067.835 | L34: =K34-L20 -> 3830.5433 | ... AI34: =AH34-AI20 -> 271.16833
A35: Student Loan Principal | D35: =C4-D21 -> 22430.56 | E35: =D35-E21 -> 22430.56 | F35: =E35-F21 -> 22430.56 | G35: =F35-G21 -> 22430.56 | H35: =G35-H21 -> 22430.56 | I35: =H35-I21 -> 22430.56 | J35: =I35-J21 -> 22083.46 | K35: =J35-K21 -> 22083.46 | L35: =K35-L21 -> 22083.46 | ... AI35: =AH35-AI21 -> 18265.36

Sheet Student Loan Amort
C1: AA | D1: AC | E1: AE | F1: Total
B2: Estimated Years | C2: 6
B3: Annual Interest Rate | C3: 0.034 | D3: 0.034 | E3: 0.0541
B4: Monthly Interest Rate | C4: =C3/12 -> 0.0028333333 | D4: =D3/12 -> 0.0028333333 | E4: =E3/12 -> 0.0045083333
B5: Principal | C5: 5765.25 | D5: 4868.38 | E5: 11796.93 | F5: =SUM(C5:E5) -> 22430.56
B6: Payment | C6: =PMT(C3/12,$C$2*12,-C5) -> 88.630846 | D6: =PMT(D3/12,$C$2*12,-D5) -> 74.843006 | E6: =PMT(E3/12,$C$2*12,-E5) -> 192.24046 | F6: =SUM(C6:E6) -> 355.71431
C8: AA Payment | D8: AA Principal | E8: AA Interest | F8: AA Balance | G8: AC Payment | H8: AC Principal | I8: AC Interest | J8: AC Balance | K8: AE Payment | L8: AE Principal | M8: AE Interest | N8: AE Balance | O8: Principal | P8: Interest | Q8: Total Interest | R8: Total Balance
A9: {=_xlfn.SEQUENCE(C2*12)} -> 1 | B9: 45200 | C9: =$C$6 -> 88.630846 | D9: =C6-E9 -> 72.295971 | E9: =C4*C5 -> 16.334875 | F9: =C5-D9 -> 5692.954 | G9: =$D$6 -> 74.843006 | H9: =D6-I9 -> 61.049262 | I9: =D4*D5 -> 13.793743 | J9: =D5-H9 -> 4807.3307 | K9: =$E$6 -> 192.24046 | L9: =E6-M9 -> 139.05597 | M9: =E4*E5 -> 53.184493 | N9: =E5-L9 -> 11657.874 | O9: =SUM(D9,H9,L9) -> 272.4012 | P9: =SUM(E9,I9,M9) -> 83.313111 | Q9: =P9 -> 83.313111 | R9: =SUM(F9,J9,N9) -> 22158.159
A10: 2 | B10: =EOMONTH(B9,0)+1 -> 45231 | C10: =$C$6 -> 88.630846 | D10: =C10-E10 -> 72.50081 | E10: =$C$4*F9 -> 16.130036 | F10: =F9-D10 -> 5620.4532 | G10: =$D$6 -> 74.843006 | H10: =G10-I10 -> 61.222235 | I10: =$D$4*J9 -> 13.62077 | J10: =J9-H10 -> 4746.1085 | K10: =$E$6 -> 192.24046 | L10: =K10-M10 -> 139.68288 | M10: =$E$4*N9 -> 52.557582 | N10: =N9-L10 -> 11518.191 | O10: =SUM(D10,H10,L10) -> 273.40592 | P10: =SUM(E10,I10,M10) -> 82.308389 | Q10: =P10+Q9 -> 165.6215 | R10: =SUM(F10,J10,N10) -> 21884.753
A11: 3 | B11: =EOMONTH(B10,0)+1 -> 45261 | C11: =$C$6 -> 88.630846 | D11: =C11-E11 -> 72.706228 | E11: =$C$4*F10 -> 15.924617 | F11: =F10-D11 -> 5547.747 | G11: =$D$6 -> 74.843006 | H11: =G11-I11 -> 61.395698 | I11: =$D$4*J10 -> 13.447307 | J11: =J10-H11 -> 4684.7128 | K11: =$E$6 -> 192.24046 | L11: =K11-M11 -> 140.31262 | M11: =$E$4*N10 -> 51.927845 | N11: =N10-L11 -> 11377.879 | O11: =SUM(D11,H11,L11) -> 274.41454 | P11: =SUM(E11,I11,M11) -> 81.29977 | Q11: =P11+Q10 -> 246.92127 | R11: =SUM(F11,J11,N11) -> 21610.338
A12: 4 | B12: =EOMONTH(B11,0)+1 -> 45292 | C12: =$C$6 -> 88.630846 | D12: =C12-E12 -> 72.912229 | E12: =$C$4*F11 -> 15.718616 | F12: =F11-D12 -> 5474.8348 | G12: =$D$6 -> 74.843006 | H12: =G12-I12 -> 61.569653 | I12: =$D$4*J11 -> 13.273353 | J12: =J11-H12 -> 4623.1432 | K12: =$E$6 -> 192.24046 | L12: =K12-M12 -> 140.94519 | M12: =$E$4*N11 -> 51.295269 | N12: =N11-L12 -> 11236.933 | O12: =SUM(D12,H12,L12) -> 275.42707 | P12: =SUM(E12,I12,M12) -> 80.287238 | Q12: =P12+Q11 -> 327.20851 | R12: =SUM(F12,J12,N12) -> 21334.911
A13: 5 | B13: =EOMONTH(B12,0)+1 -> 45323 | C13: =$C$6 -> 88.630846 | D13: =C13-E13 -> 73.118814 | E13: =$C$4*F12 -> 15.512032 | F13: =F12-D13 -> 5401.7159 | G13: =$D$6 -> 74.843006 | H13: =G13-I13 -> 61.7441 | I13: =$D$4*J12 -> 13.098906 | J13: =J12-H13 -> 4561.3991 | K13: =$E$6 -> 192.24046 | L13: =K13-M13 -> 141.58062 | M13: =$E$4*N12 -> 50.659841 | N13: =N12-L13 -> 11095.353 | O13: =SUM(D13,H13,L13) -> 276.44353 | P13: =SUM(E13,I13,M13) -> 79.270779 | Q13: =P13+Q12 -> 406.47929 | R13: =SUM(F13,J13,N13) -> 21058.468
A14: 6 | B14: =EOMONTH(B13,0)+1 -> 45352 | C14: =$C$6 -> 88.630846 | D14: =C14-E14 -> 73.325984 | E14: =$C$4*F13 -> 15.304862 | F14: =F13-D14 -> 5328.39 | G14: =$D$6 -> 74.843006 | H14: =G14-I14 -> 61.919042 | I14: =$D$4*J13 -> 12.923964 | J14: =J13-H14 -> 4499.48 | K14: =$E$6 -> 192.24046 | L14: =K14-M14 -> 142.21891 | M14: =$E$4*N13 -> 50.021549 | N14: =N13-L14 -> 10953.134 | O14: =SUM(D14,H14,L14) -> 277.46394 | P14: =SUM(E14,I14,M14) -> 78.250374 | Q14: =P14+Q13 -> 484.72966 | R14: =SUM(F14,J14,N14) -> 20781.004
A15: 7 | B15: =EOMONTH(B14,0)+1 -> 45383 | C15: =$C$6 -> 88.630846 | D15: =C15-E15 -> 73.533741 | E15: =$C$4*F14 -> 15.097105 | F15: =F14-D15 -> 5254.8562 | G15: =$D$6 -> 74.843006 | H15: =G15-I15 -> 62.094479 | I15: =$D$4*J14 -> 12.748527 | J15: =J14-H15 -> 4437.3855 | K15: =$E$6 -> 192.24046 | L15: =K15-M15 -> 142.86008 | M15: =$E$4*N14 -> 49.380378 | N15: =N14-L15 -> 10810.274 | O15: =SUM(D15,H15,L15) -> 278.4883 | P15: =SUM(E15,I15,M15) -> 77.22601 | Q15: =P15+Q14 -> 561.95567 | R15: =SUM(F15,J15,N15) -> 20502.515
A16: 8 | B16: =EOMONTH(B15,0)+1 -> 45413 | C16: =$C$6 -> 88.630846 | D16: =C16-E16 -> 73.742087 | E16: =$C$4*F15 -> 14.888759 | F16: =F15-D16 -> 5181.1141 | G16: =$D$6 -> 74.843006 | H16: =G16-I16 -> 62.270413 | I16: =$D$4*J15 -> 12.572592 | J16: =J15-H16 -> 4375.1151 | K16: =$E$6 -> 192.24046 | L16: =K16-M16 -> 143.50414 | M16: =$E$4*N15 -> 48.736317 | N16: =N15-L16 -> 10666.77 | O16: =SUM(D16,H16,L16) -> 279.51664 | P16: =SUM(E16,I16,M16) -> 76.197669 | Q16: =P16+Q15 -> 638.15334 | R16: =SUM(F16,J16,N16) -> 20222.999
A17: 9 | B17: =EOMONTH(B16,0)+1 -> 45444 | C17: =$C$6 -> 88.630846 | D17: =C17-E17 -> 73.951023 | E17: =$C$4*F16 -> 14.679823 | F17: =F16-D17 -> 5107.1631 | G17: =$D$6 -> 74.843006 | H17: =G17-I17 -> 62.446846 | I17: =$D$4*J16 -> 12.39616 | J17: =J16-H17 -> 4312.6683 | K17: =$E$6 -> 192.24046 | L17: =K17-M17 -> 144.15111 | M17: =$E$4*N16 -> 48.089353 | N17: =N16-L17 -> 10522.618 | O17: =SUM(D17,H17,L17) -> 280.54898 | P17: =SUM(E17,I17,M17) -> 75.165336 | Q17: =P17+Q16 -> 713.31868 | R17: =SUM(F17,J17,N17) -> 19942.45
A18: 10 | B18: =EOMONTH(B17,0)+1 -> 45474 | C18: =$C$6 -> 88.630846 | D18: =C18-E18 -> 74.16055 | E18: =$C$4*F17 -> 14.470295 | F18: =F17-D18 -> 5033.0026 | G18: =$D$6 -> 74.843006 | H18: =G18-I18 -> 62.623779 | I18: =$D$4*J17 -> 12.219227 | J18: =J17-H18 -> 4250.0445 | K18: =$E$6 -> 192.24046 | L18: =K18-M18 -> 144.80099 | M18: =$E$4*N17 -> 47.439472 | N18: =N17-L18 -> 10377.817 | O18: =SUM(D18,H18,L18) -> 281.58532 | P18: =SUM(E18,I18,M18) -> 74.128994 | Q18: =P18+Q17 -> 787.44767 | R18: =SUM(F18,J18,N18) -> 19660.865
A19: 11 | B19: =EOMONTH(B18,0)+1 -> 45505 | C19: =$C$6 -> 88.630846 | D19: =C19-E19 -> 74.370672 | E19: =$C$4*F18 -> 14.260174 | F19: =F18-D19 -> 4958.6319 | G19: =$D$6 -> 74.843006 | H19: =G19-I19 -> 62.801213 | I19: =$D$4*J18 -> 12.041793 | J19: =J18-H19 -> 4187.2433 | K19: =$E$6 -> 192.24046 | L19: =K19-M19 -> 145.4538 | M19: =$E$4*N18 -> 46.786661 | N19: =N18-L19 -> 10232.364 | O19: =SUM(D19,H19,L19) -> 282.62568 | P19: =SUM(E19,I19,M19) -> 73.088627 | Q19: =P19+Q18 -> 860.5363 | R19: =SUM(F19,J19,N19) -> 19378.239
A20: 12 | B20: =EOMONTH(B19,0)+1 -> 45536 | C20: =$C$6 -> 88.630846 | D20: =C20-E20 -> 74.581389 | E20: =$C$4*F19 -> 14.049457 | F20: =F19-D20 -> 4884.0505 | G20: =$D$6 -> 74.843006 | H20: =G20-I20 -> 62.97915 | I20: =$D$4*J19 -> 11.863856 | J20: =J19-H20 -> 4124.2641 | K20: =$E$6 -> 192.24046 | L20: =K20-M20 -> 146.10955 | M20: =$E$4*N19 -> 46.130906 | N20: =N19-L20 -> 10086.254 | O20: =SUM(D20,H20,L20) -> 283.67009 | P20: =SUM(E20,I20,M20) -> 72.044219 | Q20: =P20+Q19 -> 932.58052 | R20: =SUM(F20,J20,N20) -> 19094.569
A21: 13 | B21: =EOMONTH(B20,0)+1 -> 45566 | C21: =$C$6 -> 88.630846 | D21: =C21-E21 -> 74.792703 | E21: =$C$4*F20 -> 13.838143 | F21: =F20-D21 -> 4809.2578 | G21: =$D$6 -> 74.843006 | H21: =G21-I21 -> 63.15759 | I21: =$D$4*J20 -> 11.685415 | J21: =J20-H21 -> 4061.1065 | K21: =$E$6 -> 192.24046 | L21: =K21-M21 -> 146.76826 | M21: =$E$4*N20 -> 45.472196 | N21: =N20-L21 -> 9939.4859 | O21: =SUM(D21,H21,L21) -> 284.71856 | P21: =SUM(E21,I21,M21) -> 70.995754 | Q21: =P21+Q20 -> 1003.5763 | R21: =SUM(F21,J21,N21) -> 18809.85
... A80: 72 | B80: =EOMONTH(B79,0)+1 -> 47362 | C80: =$C$6 -> 88.630846 | D80: =C80-E80 -> 88.380435 | E80: =$C$4*F79 -> 0.25041123 | F80: =F79-D80 -> 2.6005864e-12 | G80: =$D$6 -> 74.843006 | H80: =G80-I80 -> 74.631549 | I80: =$D$4*J79 -> 0.21145606 | J80: =J79-H80 -> 2.9700686e-12 | K80: =$E$6 -> 192.24046 | L80: =K80-M80 -> 191.37767 | M80: =$E$4*N79 -> 0.86279431 | N80: =N79-L80 -> -1.9326762e-12 | O80: =SUM(D80,H80,L80) -> 354.38965 | P80: =SUM(E80,I80,M80) -> 1.3246616 | Q80: =P80+Q79 -> 3180.8705 | R80: =SUM(F80,J80,N80) -> 3.6379788e-12

Sheet Lasik
B2: 5535.28
A3: 45090
A4: =EOMONTH(A3,0)+10 -> 45117 | B4: =$B$2/20 -> 276.764 | C4: =B2-B4 -> 5258.516 | D4: 1
A5: =EOMONTH(A4,0)+10 -> 45148 | B5: =$B$2/20 -> 276.764 | C5: =C4-B5 -> 4981.752 | D5: 1
A6: =EOMONTH(A5,0)+10 -> 45179 | B6: =$B$2/20 -> 276.764 | C6: =C5-B6 -> 4704.988 | D6: 1
A7: =EOMONTH(A6,0)+10 -> 45209 | B7: =$B$2/20 -> 276.764 | C7: =C6-B7 -> 4428.224 | D7: 1
A8: =EOMONTH(A7,0)+10 -> 45240 | B8: =$B$2/20 -> 276.764 | C8: =C7-B8 -> 4151.46 | D8: 1
A9: =EOMONTH(A8,0)+10 -> 45270 | B9: =$B$2/20 -> 276.764 | C9: =C8-B9 -> 3874.696 | D9: 1
A10: =EOMONTH(A9,0)+10 -> 45301 | B10: =$B$2/20 -> 276.764 | C10: =C9-B10 -> 3597.932 | D10: 1
A11: =EOMONTH(A10,0)+10 -> 45332 | B11: =$B$2/20 -> 276.764 | C11: =C10-B11 -> 3321.168 | D11: 1
A12: =EOMONTH(A11,0)+10 -> 45361 | B12: =$B$2/20 -> 276.764 | C12: =C11-B12 -> 3044.404 | D12: 1
A13: =EOMONTH(A12,0)+10 -> 45392 | B13: =$B$2/20 -> 276.764 | C13: =C12-B13 -> 2767.64
A14: =EOMONTH(A13,0)+10 -> 45422 | B14: =$B$2/20 -> 276.764 | C14: =C13-B14 -> 2490.876
A15: =EOMONTH(A14,0)+10 -> 45453 | B15: =$B$2/20 -> 276.764 | C15: =C14-B15 -> 2214.112
A16: =EOMONTH(A15,0)+10 -> 45483 | B16: =$B$2/20 -> 276.764 | C16: =C15-B16 -> 1937.348
A17: =EOMONTH(A16,0)+10 -> 45514 | B17: =$B$2/20 -> 276.764 | C17: =C16-B17 -> 1660.584
A18: =EOMONTH(A17,0)+10 -> 45545 | B18: =$B$2/20 -> 276.764 | C18: =C17-B18 -> 1383.82
A19: =EOMONTH(A18,0)+10 -> 45575 | B19: =$B$2/20 -> 276.764 | C19: =C18-B19 -> 1107.056
A20: =EOMONTH(A19,0)+10 -> 45606 | B20: =$B$2/20 -> 276.764 | C20: =C19-B20 -> 830.292
A21: =EOMONTH(A20,0)+10 -> 45636 | B21: =$B$2/20 -> 276.764 | C21: =C20-B21 -> 553.528
A22: =EOMONTH(A21,0)+10 -> 45667 | B22: =$B$2/20 -> 276.764 | C22: =C21-B22 -> 276.764
A23: =EOMONTH(A22,0)+10 -> 45698 | B23: =$B$2/20 -> 276.764 | C23: =C22-B23 -> -2.2737368e-12
A24: =EOMONTH(A23,0)+10 -> 45726 | B24: =$B$2/20 -> 276.764 | C24: =C23-B24 -> -276.764
... A28: =EOMONTH(A27,0)+10 -> 45848 | B28: =$B$2/20 -> 276.764 | C28: =C27-B28 -> -1383.82

Sheet Wells Fargo
A1: Month | B1: Trans Date | C1: Debit_Amount | D1: Column1 | E1: Column2 | F1: Column22 | G1: Description | H1: Column3 | I1: Column4 | N1: {=_xlfn.UNIQUE('Discover Data'!J2:J361)} -> Balance
A2: =MONTH(wf_table[[#This Row],[Trans Date]]) -> 1 | B2: 44927 | C2: =D3-C3 -> 406.52 | E2: =IF(wf_table[[#This Row],[Debit_Amount]]<0,"debit","-") -> - | G2: Balance | N2: Recreation_Entertainment
A3: =MONTH(wf_table[[#This Row],[Trans Date]]) -> 1 | B3: 44929 | C3: -80 | D3: 326.52 | E3: =IF(wf_table[[#This Row],[Debit_Amount]]<0,"debit","-") -> debit | G3: PURCHASE AUTHORIZED ON 01/01 CASH APP*ANUSH ROH 8774174551 CA S383001689612697 CARD 6659 | N3: Food
A4: =MONTH(wf_table[[#This Row],[Trans Date]]) -> 1 | B4: 44936 | C4: -200 | D4: =D3+wf_table[[#This Row],[Debit_Amount]] -> 126.52 | E4: =IF(wf_table[[#This Row],[Debit_Amount]]<0,"debit","-") -> debit | G4: ZELLE TO LEWIS SHEVON ON 01/10 REF #RP0QXXRHQF EARLY INVESTMENT | N4: Personal_Spending
A5: =MONTH(wf_table[[#This Row],[Trans Date]]) -> 1 | B5: 44936 | C5: -50 | D5: =D4+wf_table[[#This Row],[Debit_Amount]] -> 76.52 | E5: =IF(wf_table[[#This Row],[Debit_Amount]]<0,"debit","-") -> debit | G5: PURCHASE AUTHORIZED ON 01/09 CASH APP*CYANFACE 8774174551 CA S463009600364898 CARD 6659 | N5: Medical
A6: =MONTH(wf_table[[#This Row],[Trans Date]]) -> 1 | B6: 44937 | C6: -182 | D6: =D5+wf_table[[#This Row],[Debit_Amount]] -> -105.48 | E6: =IF(wf_table[[#This Row],[Debit_Amount]]<0,"debit","-") -> debit | G6: VENMO PAYMENT 230111 1024637239631 SEAN LEWIS | N6: Payment_and_Interest
A7: =MONTH(wf_table[[#This Row],[Trans Date]]) -> 1 | B7: 44937 | C7: -24.14 | D7: =D6+wf_table[[#This Row],[Debit_Amount]] -> -129.62 | E7: =IF(wf_table[[#This Row],[Debit_Amount]]<0,"debit","-") -> debit | G7: VENMO PAYMENT 230111 1024637259890 SEAN LEWIS | N7: Transportation
A8: =MONTH(wf_table[[#This Row],[Trans Date]]) -> 1 | B8: 44938 | C8: 541.16 | D8: =D7+wf_table[[#This Row],[Debit_Amount]] -> 411.54 | E8: =IF(wf_table[[#This Row],[Debit_Amount]]<0,"debit","-") -> - | F8: deposit | G8: Nationwide PAYROLL 01 HRP0008984397 Sean Lewis | N8: Misc
A9: =MONTH(wf_table[[#This Row],[Trans Date]]) -> 1 | B9: 44939 | C9: -200 | D9: =D8+wf_table[[#This Row],[Debit_Amount]] -> 211.54 | E9: =IF(wf_table[[#This Row],[Debit_Amount]]<0,"debit","-") -> debit | G9: TRANSFER TO LEWIS SHARON ON 01/13 REF #PP0QY4HH2S TAX PT2 | N9: Insurance
A10: =MONTH(wf_table[[#This Row],[Trans Date]]) -> 1 | B10: 44939 | C10: -500 | D10: =D9+wf_table[[#This Row],[Debit_Amount]] -> -288.46 | E10: =IF(wf_table[[#This Row],[Debit_Amount]]<0,"debit","-") -> debit | G10: TRANSFER TO LEWIS SHARON ON 01/13 REF #PP0QY4CRFP FOR TAXES | N10: Utilities
A11: =MONTH(wf_table[[#This Row],[Trans Date]]) -> 1 | B11: 44939 | C11: 400 | D11: =D10+wf_table[[#This Row],[Debit_Amount]] -> 111.54 | E11: =IF(wf_table[[#This Row],[Debit_Amount]]<0,"debit","-") -> - | G11: ATM CASH DEPOSIT ON 01/13 1435 Burlingame Ave Burlingame CA 0000637 ATM ID 0165J CARD 6659 | N11: Housing
A12: =MONTH(wf_table[[#This Row],[Trans Date]]) -> 1 | B12: 44939 | C12: 106 | D12: =D11+wf_table[[#This Row],[Debit_Amount]] -> 217.54 | E12: =IF(wf_table[[#This Row],[Debit_Amount]]<0,"debit","-") -> - | G12: MONEY TRANSFER AUTHORIZED ON 01/13 FROM Sean Lewis VA S463013513474302 CARD 6659 | N12: People
A13: =MONTH(wf_table[[#This Row],[Trans Date]]) -> 1 | B13: 44943 | C13: -25.48 | D13: =D12+wf_table[[#This Row],[Debit_Amount]] -> 192.06 | E13: =IF(wf_table[[#This Row],[Debit_Amount]]<0,"debit","-") -> debit | G13: PLANET FIT CLUB FEES 2301306620293 623-439-5550 | N13: Government
A14: =MONTH(wf_table[[#This Row],[Trans Date]]) -> 1 | B14: 44949 | C14: -25 | D14: =D13+wf_table[[#This Row],[Debit_Amount]] -> 167.06 | E14: =IF(wf_table[[#This Row],[Debit_Amount]]<0,"debit","-") -> debit | G14: VENMO PAYMENT 230121 1024827296273 SEAN LEWIS
A15: =MONTH(wf_table[[#This Row],[Trans Date]]) -> 1 | B15: 44949 | C15: -65.61 | D15: =D14+wf_table[[#This Row],[Debit_Amount]] -> 101.45 | E15: =IF(wf_table[[#This Row],[Debit_Amount]]<0,"debit","-") -> debit | G15: PURCHASE AUTHORIZED ON 01/20 STREET FOOD CAFE SAN MATEO CA S303021134090263 CARD 6659
A16: =MONTH(wf_table[[#This Row],[Trans Date]]) -> 1 | B16: 44952 | C16: -100 | D16: =D15+wf_table[[#This Row],[Debit_Amount]] -> 1.45 | E16: =IF(wf_table[[#This Row],[Debit_Amount]]<0,"debit","-") -> debit | G16: ZELLE TO LEWIS SHEVON ON 01/26 REF #RP0QYXPP3Q FOR GAS
A17: =MONTH(wf_table[[#This Row],[Trans Date]]) -> 1 | B17: 44952 | C17: 477.52 | D17: =D16+wf_table[[#This Row],[Debit_Amount]] -> 478.97 | E17: =IF(wf_table[[#This Row],[Debit_Amount]]<0,"debit","-") -> - | F17: deposit | G17: Nationwide PAYROLL 01 HRP0009017504 Sean Lewis
A18: =MONTH(wf_table[[#This Row],[Trans Date]]) -> 1 | B18: 44952 | C18: 75 | D18: =D17+wf_table[[#This Row],[Debit_Amount]] -> 553.97 | E18: =IF(wf_table[[#This Row],[Debit_Amount]]<0,"debit","-") -> - | G18: Square Inc * Cash App 230126 T3EC2YGP8SHTR06 Sean Lewis
A19: =MONTH(wf_table[[#This Row],[Trans Date]]) -> 2 | B19: 44958 | C19: -158 | D19: =D18+wf_table[[#This Row],[Debit_Amount]] -> 395.97 | E19: =IF(wf_table[[#This Row],[Debit_Amount]]<0,"debit","-") -> debit | G19: VENMO PAYMENT 230201 1025016489585 SEAN LEWIS
A20: =MONTH(wf_table[[#This Row],[Trans Date]]) -> 2 | B20: 44963 | C20: -53.01 | D20: =D19+wf_table[[#This Row],[Debit_Amount]] -> 342.96 | E20: =IF(wf_table[[#This Row],[Debit_Amount]]<0,"debit","-") -> debit | G20: PURCHASE AUTHORIZED ON 02/03 CHEVRON/CSI-092600/1556 FOSTER CITY CA P383035071538454 CARD 1081
A21: =MONTH(wf_table[[#This Row],[Trans Date]]) -> 2 | B21: 44965 | C21: -500 | D21: =D20+wf_table[[#This Row],[Debit_Amount]] -> -157.04 | E21: - | G21: SoFi Bank TRANSFER SD1300 SLewis Sean Lewis:66513:690
A22: =MONTH(wf_table[[#This Row],[Trans Date]]) -> 2 | B22: 44965 | C22: 87 | D22: =D21+wf_table[[#This Row],[Debit_Amount]] -> -70.04 | E22: =IF(wf_table[[#This Row],[Debit_Amount]]<0,"debit","-") -> - | G22: VENMO CASHOUT 230207 1025155149107 SEAN LEWIS
A23: =MONTH(wf_table[[#This Row],[Trans Date]]) -> 2 | B23: 44966 | C23: 267.17 | D23: =D22+wf_table[[#This Row],[Debit_Amount]] -> 197.13 | E23: =IF(wf_table[[#This Row],[Debit_Amount]]<0,"debit","-") -> - | F23: deposit | G23: Nationwide PAYROLL 01 HRP0009061376 Sean Lewis
A24: =MONTH(wf_table[[#This Row],[Trans Date]]) -> 2 | B24: 44967 | C24: -21.21 | D24: =D23+wf_table[[#This Row],[Debit_Amount]] -> 175.92 | E24: =IF(wf_table[[#This Row],[Debit_Amount]]<0,"debit","-") -> debit | G24: VENMO PAYMENT 230210 1025196796049 SEAN LEWIS
A25: =MONTH(wf_table[[#This Row],[Trans Date]]) -> 2 | B25: 44970 | C25: -43.39 | D25: =D24+wf_table[[#This Row],[Debit_Amount]] -> 132.53 | E25: =IF(wf_table[[#This Row],[Debit_Amount]]<0,"debit","-") -> debit | G25: VENMO PAYMENT 230213 1025255412913 SEAN LEWIS
A26: =MONTH(wf_table[[#This Row],[Trans Date]]) -> 2 | B26: 44970 | C26: -17.5 | D26: =D25+wf_table[[#This Row],[Debit_Amount]] -> 115.03 | E26: =IF(wf_table[[#This Row],[Debit_Amount]]<0,"debit","-") -> debit | G26: VENMO PAYMENT 230211 1025215575532 SEAN LEWIS
A27: =MONTH(wf_table[[#This Row],[Trans Date]]) -> 2 | B27: 44971 | C27: 200 | D27: =D26+wf_table[[#This Row],[Debit_Amount]] -> 315.03 | E27: =IF(wf_table[[#This Row],[Debit_Amount]]<0,"debit","-") -> - | G27: ATM CASH DEPOSIT ON 02/13 632 Eastern Blvd Essex MD 0008972 ATM ID 0282M CARD 1081
A28: =MONTH(wf_table[[#This Row],[Trans Date]]) -> 2 | B28: 44974 | C28: -25.48 | D28: =D27+wf_table[[#This Row],[Debit_Amount]] -> 289.55 | E28: =IF(wf_table[[#This Row],[Debit_Amount]]<0,"debit","-") -> debit | G28: PLANET FIT CLUB FEES 2304706550250 623-439-5550
A29: =MONTH(wf_table[[#This Row],[Trans Date]]) -> 2 | B29: 44974 | C29: 136 | D29: =D28+wf_table[[#This Row],[Debit_Amount]] -> 425.55 | E29: =IF(wf_table[[#This Row],[Debit_Amount]]<0,"debit","-") -> - | G29: HEALTHEQUITY INC HealthEqui 16 Feb 22317048 Sean Lewis (22317048)
A30: =MONTH(wf_table[[#This Row],[Trans Date]]) -> 2 | B30: 44978 | C30: -194.5 | D30: =D29+wf_table[[#This Row],[Debit_Amount]] -> 231.05 | E30: =IF(wf_table[[#This Row],[Debit_Amount]]<0,"debit","-") -> debit | G30: VENMO PAYMENT 230218 1025351910082 SEAN LEWIS
A31: =MONTH(wf_table[[#This Row],[Trans Date]]) -> 2 | B31: 44978 | C31: -265 | D31: =D30+wf_table[[#This Row],[Debit_Amount]] -> -33.95 | E31: =IF(wf_table[[#This Row],[Debit_Amount]]<0,"debit","-") -> debit | G31: ZELLE TO LEWIS SHARON ON 02/20 REF #PP0R2LTMPW BDAY PARTY EXCEPT DON SEAN
A32: =MONTH(wf_table[[#This Row],[Trans Date]]) -> 2 | B32: 44978 | C32: -2.5 | D32: =D31+wf_table[[#This Row],[Debit_Amount]] -> -36.45 | E32: =IF(wf_table[[#This Row],[Debit_Amount]]<0,"debit","-") -> debit | G32: NON-WELLS FARGO ATM TRANSACTION FEE
A33: =MONTH(wf_table[[#This Row],[Trans Date]]) -> 2 | B33: 44978 | C33: -23 | D33: =D32+wf_table[[#This Row],[Debit_Amount]] -> -59.45 | E33: =IF(wf_table[[#This Row],[Debit_Amount]]<0,"debit","-") -> debit | G33: NON-WF ATM WITHDRAWAL AUTHORIZED ON 02/18 M&T 5980 KINGSTOWN ALEXANDR1A VA 463049709972404 ATM ID SA1847 CARD 1081
A34: =MONTH(wf_table[[#This Row],[Trans Date]]) -> 2 | B34: 44978 | C34: 100 | D34: =D33+wf_table[[#This Row],[Debit_Amount]] -> 40.55 | E34: =IF(wf_table[[#This Row],[Debit_Amount]]<0,"debit","-") -> - | G34: SoFi Bank TRANSFER SD1700 SLewis Sean Lewis:66526:32382
A35: =MONTH(wf_table[[#This Row],[Trans Date]]) -> 2 | B35: 44979 | C35: -650 | D35: =D34+wf_table[[#This Row],[Debit_Amount]] -> -609.45 | E35: =IF(wf_table[[#This Row],[Debit_Amount]]<0,"debit","-") -> debit | G35: ZELLE TO LEWIS SHEVON ON 02/22 REF #RP0R2Q2L33 MARCH SUB
... A45: =MONTH(wf_table[[#This Row],[Trans Date]]) -> 3 | B45: 44993 | C45: -2 | D45: =D44+wf_table[[#This Row],[Debit_Amount]] -> 303.11 | E45: =IF(wf_table[[#This Row],[Debit_Amount]]<0,"debit","-") -> debit | G45: VENMO PAYMENT 230308 1025696123572 SEAN LEWIS
A46: =MONTH(wf_table[[#This Row],[Trans Date]]) -> 3 | B46: 44994 | C46: 290.51 | D46: =D45+wf_table[[#This Row],[Debit_Amount]] -> 593.62 | E46: =IF(wf_table[[#This Row],[Debit_Amount]]<0,"debit","-") -> - | F46: deposit | G46: Nationwide PAYROLL 01 HRP0009139641 Sean Lewis
A47: =MONTH(wf_table[[#This Row],[Trans Date]]) -> 3 | B47: 44994 | C47: 165.84 | D47: =D46+wf_table[[#This Row],[Debit_Amount]] -> 759.46 | E47: =IF(wf_table[[#This Row],[Debit_Amount]]<0,"debit","-") -> - | G47: Cash App * Cash App 230309 T36VMBW9GF2GB15 Sean Lewis
A48: =MONTH(wf_table[[#This Row],[Trans Date]]) -> 3 | B48: 44995 | C48: -500 | D48: =D47+wf_table[[#This Row],[Debit_Amount]] -> 259.46 | E48: - | G48: SoFi Bank TRANSFER SD1300 SLewis Sean Lewis:66543:1977
A49: =MONTH(wf_table[[#This Row],[Trans Date]]) -> 3 | B49: 44995 | C49: -180.41 | D49: =D48+wf_table[[#This Row],[Debit_Amount]] -> 79.05 | E49: =IF(wf_table[[#This Row],[Debit_Amount]]<0,"debit","-") -> debit | G49: BEST BUY PAYMENT 230309 631006869237022 SEAN LEWIS
A50: =MONTH(wf_table[[#This Row],[Trans Date]]) -> 3 | B50: 44998 | C50: 210 | D50: =D49+wf_table[[#This Row],[Debit_Amount]] -> 289.05 | E50: =IF(wf_table[[#This Row],[Debit_Amount]]<0,"debit","-") -> - | G50: ATM CASH DEPOSIT ON 03/12 655 8th Street San Francisco CA 0007219 ATM ID 1568E CARD 1081
A51: =MONTH(wf_table[[#This Row],[Trans Date]]) -> 3 | B51: 45000 | C51: -28.63 | D51: =D50+wf_table[[#This Row],[Debit_Amount]] -> 260.42 | E51: =IF(wf_table[[#This Row],[Debit_Amount]]<0,"debit","-") -> debit | G51: PURCHASE AUTHORIZED ON 03/14 CHEVRON 0093989 SAN MATEO CA S463073731068937 CARD 1081
A52: =MONTH(wf_table[[#This Row],[Trans Date]]) -> 3 | B52: 45001 | C52: -5 | D52: =D51+wf_table[[#This Row],[Debit_Amount]] -> 255.42 | E52: =IF(wf_table[[#This Row],[Debit_Amount]]<0,"debit","-") -> debit | G52: DEPT OF COMM FCU ACH Item MAR 15 000000006906695 LEWIS,SEAN
A53: =MONTH(wf_table[[#This Row],[Trans Date]]) -> 3 | B53: 45002 | C53: -700 | D53: =D52+wf_table[[#This Row],[Debit_Amount]] -> -444.58 | E53: - | G53: SoFi Bank TRANSFER SD1700 SLewis Sean Lewis:66550:11734
A54: =MONTH(wf_table[[#This Row],[Trans Date]]) -> 3 | B54: 45002 | C54: -20 | D54: =D53+wf_table[[#This Row],[Debit_Amount]] -> -464.58 | E54: =IF(wf_table[[#This Row],[Debit_Amount]]<0,"debit","-") -> debit | G54: ATM WITHDRAWAL AUTHORIZED ON 03/17 2075 Broadway St Redwood City CA 0004578 ATM ID 0003T CARD 1081
A55: =MONTH(wf_table[[#This Row],[Trans Date]]) -> 3 | B55: 45002 | C55: 600 | D55: =D54+wf_table[[#This Row],[Debit_Amount]] -> 135.42 | E55: =IF(wf_table[[#This Row],[Debit_Amount]]<0,"debit","-") -> - | G55: ZELLE FROM LEWIS SHARON ON 03/17 REF # PP0R4BR8MM THANKS FOR THE LOAN
A56: =MONTH(wf_table[[#This Row],[Trans Date]]) -> 3 | B56: 45005 | C56: -49.02 | D56: =D55+wf_table[[#This Row],[Debit_Amount]] -> 86.4 | E56: =IF(wf_table[[#This Row],[Debit_Amount]]<0,"debit","-") -> debit | G56: PURCHASE AUTHORIZED ON 03/19 SHELL SERVICE STATION SAN MATEO CA P463078717139825 CARD 1081
A57: =MONTH(wf_table[[#This Row],[Trans Date]]) -> 3 | B57: 45005 | C57: 125.1 | D57: =D56+wf_table[[#This Row],[Debit_Amount]] -> 211.5 | E57: =IF(wf_table[[#This Row],[Debit_Amount]]<0,"debit","-") -> - | G57: VENMO CASHOUT 230320 1025934244148 SEAN LEWIS
A58: =MONTH(wf_table[[#This Row],[Trans Date]]) -> 3 | B58: 45006 | C58: -80 | D58: =D57+wf_table[[#This Row],[Debit_Amount]] -> 131.5 | E58: =IF(wf_table[[#This Row],[Debit_Amount]]<0,"debit","-") -> debit | G58: ATM WITHDRAWAL AUTHORIZED ON 03/21 1435 Burlingame Ave Burlingame CA 0007476 ATM ID 0165J CARD 1081
A59: =MONTH(wf_table[[#This Row],[Trans Date]]) -> 3 | B59: 45007 | C59: -650 | D59: =D58+wf_table[[#This Row],[Debit_Amount]] -> -518.5 | E59: =IF(wf_table[[#This Row],[Debit_Amount]]<0,"debit","-") -> debit | G59: ZELLE TO LEWIS SHEVON ON 03/22 REF #RP0R4NJ6DM APRIL RENT
A60: =MONTH(wf_table[[#This Row],[Trans Date]]) -> 3 | B60: 45007 | C60: 300 | D60: =D59+wf_table[[#This Row],[Debit_Amount]] -> -218.5 | E60: =IF(wf_table[[#This Row],[Debit_Amount]]<0,"debit","-") -> - | G60: SoFi Bank TRANSFER SD1300 SLewis Sean Lewis:66555:4733
A61: =MONTH(wf_table[[#This Row],[Trans Date]]) -> 3 | B61: 45008 | C61: 70 | D61: =D60+wf_table[[#This Row],[Debit_Amount]] -> -148.5 | E61: =IF(wf_table[[#This Row],[Debit_Amount]]<0,"debit","-") -> - | G61: VENMO CASHOUT 230323 1025985341278 SEAN LEWIS
A62: =MONTH(wf_table[[#This Row],[Trans Date]]) -> 3 | B62: 45008 | C62: 398.54 | D62: =D61+wf_table[[#This Row],[Debit_Amount]] -> 250.04 | E62: =IF(wf_table[[#This Row],[Debit_Amount]]<0,"debit","-") -> - | F62: deposit | G62: Nationwide PAYROLL 01 HRP0009182441 Sean Lewis
A63: =MONTH(wf_table[[#This Row],[Trans Date]]) -> 3 | B63: 45012 | C63: 15 | D63: =D62+wf_table[[#This Row],[Debit_Amount]] -> 265.04 | E63: =IF(wf_table[[#This Row],[Debit_Amount]]<0,"debit","-") -> - | G63: Cash App * Cash App 230325 T3RMNME7PX9EYE2 Sean Lewis
A64: =MONTH(wf_table[[#This Row],[Trans Date]]) -> 4 | B64: 45019 | C64: -50.06 | D64: =D63+wf_table[[#This Row],[Debit_Amount]] -> 214.98 | E64: =IF(wf_table[[#This Row],[Debit_Amount]]<0,"debit","-") -> debit | G64: PURCHASE AUTHORIZED ON 04/02 SHELL SERVICE STATION SAN MATEO CA P303092745786604 CARD 1081
A65: =MONTH(wf_table[[#This Row],[Trans Date]]) -> 4 | B65: 45019 | C65: -20 | D65: =D64+wf_table[[#This Row],[Debit_Amount]] -> 194.98 | E65: =IF(wf_table[[#This Row],[Debit_Amount]]<0,"debit","-") -> debit | G65: PURCHASE AUTHORIZED ON 04/02 CASH APP*CYANFACE 8774174551 CA S463092590316949 CARD 1081
A66: =MONTH(wf_table[[#This Row],[Trans Date]]) -> 4 | B66: 45019 | C66: 119 | D66: =D65+wf_table[[#This Row],[Debit_Amount]] -> 313.98 | E66: =IF(wf_table[[#This Row],[Debit_Amount]]<0,"debit","-") -> - | G66: VENMO CASHOUT 230403 1026206756036 SEAN LEWIS
A67: =MONTH(wf_table[[#This Row],[Trans Date]]) -> 4 | B67: 45019 | C67: 5 | D67: =D66+wf_table[[#This Row],[Debit_Amount]] -> 318.98 | E67: =IF(wf_table[[#This Row],[Debit_Amount]]<0,"debit","-") -> - | G67: ATM CASH DEPOSIT ON 04/01 1435 Burlingame Ave Burlingame CA 0008502 ATM ID 0165J CARD 1081
A68: =MONTH(wf_table[[#This Row],[Trans Date]]) -> 4 | B68: 45019 | C68: 32 | D68: =D67+wf_table[[#This Row],[Debit_Amount]] -> 350.98 | E68: =IF(wf_table[[#This Row],[Debit_Amount]]<0,"debit","-") -> - | G68: ATM CASH DEPOSIT ON 04/01 1435 Burlingame Ave Burlingame CA 0008501 ATM ID 0165J CARD 1081
A69: =MONTH(wf_table[[#This Row],[Trans Date]]) -> 4 | B69: 45020 | C69: -50 | D69: =D68+wf_table[[#This Row],[Debit_Amount]] -> 300.98 | E69: =IF(wf_table[[#This Row],[Debit_Amount]]<0,"debit","-") -> debit | G69: PURCHASE AUTHORIZED ON 04/03 CASH APP*CYANFACE 8774174551 CA S583093644926287 CARD 1081
A70: =MONTH(wf_table[[#This Row],[Trans Date]]) -> 4 | B70: 45020 | C70: 476 | D70: =D69+wf_table[[#This Row],[Debit_Amount]] -> 776.98 | E70: =IF(wf_table[[#This Row],[Debit_Amount]]<0,"debit","-") -> - | G70: MOBILE DEPOSIT : REF NUMBER :014040501256
A71: =MONTH(wf_table[[#This Row],[Trans Date]]) -> 4 | B71: 45020 | C71: 34.98 | D71: =D70+wf_table[[#This Row],[Debit_Amount]] -> 811.96 | E71: =IF(wf_table[[#This Row],[Debit_Amount]]<0,"debit","-") -> - | G71: Cash App * Cash App 230404 T3SK4TZHB4P1HAS Sean Lewis
A72: =MONTH(wf_table[[#This Row],[Trans Date]]) -> 4 | B72: 45021 | C72: -59.6 | D72: =D71+wf_table[[#This Row],[Debit_Amount]] -> 752.36 | E72: =IF(wf_table[[#This Row],[Debit_Amount]]<0,"debit","-") -> debit | G72: VENMO PAYMENT 230405 1026246105110 SEAN LEWIS
A73: =MONTH(wf_table[[#This Row],[Trans Date]]) -> 4 | B73: 45021 | C73: -500 | D73: =D72+wf_table[[#This Row],[Debit_Amount]] -> 252.36 | E73: - | G73: SoFi Bank TRANSFER SD1300 SLewis Sean Lewis:66569:829
A74: =MONTH(wf_table[[#This Row],[Trans Date]]) -> 4 | B74: 45021 | C74: -300 | D74: =D73+wf_table[[#This Row],[Debit_Amount]] -> -47.64 | E74: - | G74: SoFi Bank TRANSFER SD1300 SLewis Sean Lewis:66569:830
A75: =MONTH(wf_table[[#This Row],[Trans Date]]) -> 4 | B75: 45022 | C75: -100 | D75: =D74+wf_table[[#This Row],[Debit_Amount]] -> -147.64 | E75: =IF(wf_table[[#This Row],[Debit_Amount]]<0,"debit","-") -> debit | G75: ATM WITHDRAWAL AUTHORIZED ON 04/06 1435 Burlingame Ave Burlingame CA 0009077 ATM ID 0165J CARD 1081
A76: =MONTH(wf_table[[#This Row],[Trans Date]]) -> 4 | B76: 45022 | C76: 398.53 | D76: =D75+wf_table[[#This Row],[Debit_Amount]] -> 250.89 | E76: =IF(wf_table[[#This Row],[Debit_Amount]]<0,"debit","-") -> - | F76: deposit | G76: Nationwide PAYROLL 01 HRP0009197834 Sean Lewis
A77: =MONTH(wf_table[[#This Row],[Trans Date]]) -> 4 | B77: 45023 | C77: -25.09 | D77: =D76+wf_table[[#This Row],[Debit_Amount]] -> 225.8 | E77: =IF(wf_table[[#This Row],[Debit_Amount]]<0,"debit","-") -> debit | G77: PURCHASE AUTHORIZED ON 04/07 SHELL SERVICE STATION SAN FRANCISCO CA P303098027924484 CARD 1081
A78: =MONTH(wf_table[[#This Row],[Trans Date]]) -> 4 | B78: 45023 | C78: 70 | D78: =D77+wf_table[[#This Row],[Debit_Amount]] -> 295.8 | E78: =IF(wf_table[[#This Row],[Debit_Amount]]<0,"debit","-") -> - | G78: MONEY TRANSFER AUTHORIZED ON 04/07 FROM Sean Lewis VA S583097501342948 CARD 1081
A79: =MONTH(wf_table[[#This Row],[Trans Date]]) -> 4 | B79: 45026 | C79: -50 | D79: =D78+wf_table[[#This Row],[Debit_Amount]] -> 245.8 | E79: =IF(wf_table[[#This Row],[Debit_Amount]]<0,"debit","-") -> debit | G79: ZELLE TO LEWIS DORRY ON 04/08 REF #PP0R5VMVRT FOR MOMS CAKE
A80: =MONTH(wf_table[[#This Row],[Trans Date]]) -> 4 | B80: 45026 | C80: -150 | D80: =D79+wf_table[[#This Row],[Debit_Amount]] -> 95.8 | E80: =IF(wf_table[[#This Row],[Debit_Amount]]<0,"debit","-") -> debit | G80: ZELLE TO LEWIS SHARON ON 04/08 REF #PP0R5VLC65 HAPPY BIRTHDAY
A81: =MONTH(wf_table[[#This Row],[Trans Date]]) -> 4 | B81: 45026 | C81: 40 | D81: =D80+wf_table[[#This Row],[Debit_Amount]] -> 135.8 | E81: =IF(wf_table[[#This Row],[Debit_Amount]]<0,"debit","-") -> - | G81: VENMO CASHOUT 230408 1026306767303 SEAN LEWIS
A82: =MONTH(wf_table[[#This Row],[Trans Date]]) -> 4 | B82: 45033 | C82: -100 | D82: =D81+wf_table[[#This Row],[Debit_Amount]] -> 35.8 | E82: =IF(wf_table[[#This Row],[Debit_Amount]]<0,"debit","-") -> debit | G82: ZELLE TO LEWIS SHARON ON 04/17 REF #PP0R6H8XTV FOR BDAY FUN
A83: =MONTH(wf_table[[#This Row],[Trans Date]]) -> 4 | B83: 45033 | C83: -100 | D83: =D82+wf_table[[#This Row],[Debit_Amount]] -> -64.2 | E83: =IF(wf_table[[#This Row],[Debit_Amount]]<0,"debit","-") -> debit | G83: ZELLE TO LEWIS SHARON ON 04/16 REF #PP0R6FF793 4 21 RETURN
A84: =MONTH(wf_table[[#This Row],[Trans Date]]) -> 4 | B84: 45033 | C84: 150 | D84: =D83+wf_table[[#This Row],[Debit_Amount]] -> 85.8 | E84: =IF(wf_table[[#This Row],[Debit_Amount]]<0,"debit","-") -> - | G84: SoFi Bank TRANSFER SD1300 SLewis Sean Lewis:66581:17523
A85: =MONTH(wf_table[[#This Row],[Trans Date]]) -> 4 | B85: 45035 | C85: -650 | D85: =D84+wf_table[[#This Row],[Debit_Amount]] -> -564.2 | E85: =IF(wf_table[[#This Row],[Debit_Amount]]<0,"debit","-") -> debit | G85: ZELLE TO LEWIS SHEVON ON 04/19 REF #RP0R6M2J76 MAY RENT
A86: =MONTH(wf_table[[#This Row],[Trans Date]]) -> 4 | B86: 45035 | C86: 250 | D86: =D85+wf_table[[#This Row],[Debit_Amount]] -> -314.2 | E86: =IF(wf_table[[#This Row],[Debit_Amount]]<0,"debit","-") -> - | G86: SoFi Bank TRANSFER SD1300 SLewis Sean Lewis:66583:5671
A87: =MONTH(wf_table[[#This Row],[Trans Date]]) -> 4 | B87: 45036 | C87: 398.53 | D87: =D86+wf_table[[#This Row],[Debit_Amount]] -> 84.33 | E87: =IF(wf_table[[#This Row],[Debit_Amount]]<0,"debit","-") -> - | F87: deposit | G87: Nationwide PAYROLL 01 HRP0009254185 Sean Lewis
A88: =MONTH(wf_table[[#This Row],[Trans Date]]) -> 4 | B88: 45040 | C88: -80 | D88: =D87+wf_table[[#This Row],[Debit_Amount]] -> 4.33 | E88: =IF(wf_table[[#This Row],[Debit_Amount]]<0,"debit","-") -> debit | G88: ATM WITHDRAWAL AUTHORIZED ON 04/23 655 8th Street San Francisco CA 0009349 ATM ID 1568E CARD 1081
A89: =MONTH(wf_table[[#This Row],[Trans Date]]) -> 5 | B89: 45049 | C89: 1 | D89: =D88+wf_table[[#This Row],[Debit_Amount]] -> 5.33 | E89: =IF(wf_table[[#This Row],[Debit_Amount]]<0,"debit","-") -> - | G89: Credit Karma Transfer 230503 7569763190 Sean Lewis
A90: =MONTH(wf_table[[#This Row],[Trans Date]]) -> 5 | B90: 45050 | C90: 398.53 | D90: =D89+wf_table[[#This Row],[Debit_Amount]] -> 403.86 | E90: =IF(wf_table[[#This Row],[Debit_Amount]]<0,"debit","-") -> - | F90: deposit | G90: Nationwide PAYROLL 01 HRP0009291854 Sean Lewis
A91: =MONTH(wf_table[[#This Row],[Trans Date]]) -> 5 | B91: 45057 | C91: -27.58 | D91: =D90+wf_table[[#This Row],[Debit_Amount]] -> 376.28 | E91: =IF(wf_table[[#This Row],[Debit_Amount]]<0,"debit","-") -> debit | G91: VENMO PAYMENT 230511 1026954938969 SEAN LEWIS
A92: =MONTH(wf_table[[#This Row],[Trans Date]]) -> 5 | B92: 45058 | C92: -100 | D92: =D91+wf_table[[#This Row],[Debit_Amount]] -> 276.28 | E92: =IF(wf_table[[#This Row],[Debit_Amount]]<0,"debit","-") -> debit | G92: ATM WITHDRAWAL AUTHORIZED ON 05/12 1435 Burlingame Ave Burlingame CA 0002981 ATM ID 0165J CARD 1081
A93: =MONTH(wf_table[[#This Row],[Trans Date]]) -> 5 | B93: 45061 | C93: -34.5 | D93: =D92+wf_table[[#This Row],[Debit_Amount]] -> 241.78 | E93: =IF(wf_table[[#This Row],[Debit_Amount]]<0,"debit","-") -> debit | G93: VENMO PAYMENT 230513 1026999598173 SEAN LEWIS
A94: =MONTH(wf_table[[#This Row],[Trans Date]]) -> 5 | B94: 45061 | C94: 134.78 | D94: =D93+wf_table[[#This Row],[Debit_Amount]] -> 376.56 | E94: =IF(wf_table[[#This Row],[Debit_Amount]]<0,"debit","-") -> - | G94: VENMO CASHOUT 230515 1027038784162 SEAN LEWIS
A95: =MONTH(wf_table[[#This Row],[Trans Date]]) -> 5 | B95: 45062 | C95: -650 | D95: =D94+wf_table[[#This Row],[Debit_Amount]] -> -273.44 | E95: =IF(wf_table[[#This Row],[Debit_Amount]]<0,"debit","-") -> debit | G95: ZELLE TO LEWIS SHEVON ON 05/16 REF #RP0R8LMDVF JUNE RENT
A96: =MONTH(wf_table[[#This Row],[Trans Date]]) -> 5 | B96: 45064 | C96: 398.53 | D96: =D95+wf_table[[#This Row],[Debit_Amount]] -> 125.09 | E96: =IF(wf_table[[#This Row],[Debit_Amount]]<0,"debit","-") -> - | F96: deposit | G96: Nationwide PAYROLL 01 HRP0009321511 Sean Lewis
A97: =MONTH(wf_table[[#This Row],[Trans Date]]) -> 5 | B97: 45068 | C97: -100 | D97: =D96+wf_table[[#This Row],[Debit_Amount]] -> 25.09 | E97: =IF(wf_table[[#This Row],[Debit_Amount]]<0,"debit","-") -> debit | G97: BEST BUY PAYMENT 230521 601069035023175 SEAN LEWIS
A98: =MONTH(wf_table[[#This Row],[Trans Date]]) -> 5 | B98: 45076 | C98: -0.27 | D98: =D97+wf_table[[#This Row],[Debit_Amount]] -> 24.82 | E98: =IF(wf_table[[#This Row],[Debit_Amount]]<0,"debit","-") -> debit | G98: INTERNATIONAL PURCHASE TRANSACTION FEE
A99: =MONTH(wf_table[[#This Row],[Trans Date]]) -> 5 | B99: 45076 | C99: -9.04 | D99: =D98+wf_table[[#This Row],[Debit_Amount]] -> 15.78 | E99: =IF(wf_table[[#This Row],[Debit_Amount]]<0,"debit","-") -> debit | G99: PURCHASE INTL AUTHORIZED ON 05/27 RATP PARIS FRA S303147423332504 CARD 1081
A100: =MONTH(wf_table[[#This Row],[Trans Date]]) -> 6 | B100: 45078 | C100: 538.33 | D100: =D99+wf_table[[#This Row],[Debit_Amount]] -> 554.11 | E100: =IF(wf_table[[#This Row],[Debit_Amount]]<0,"debit","-") -> - | G100: Nationwide PAYROLL 01 HRP0009361777 Sean Lewis
A101: =MONTH(wf_table[[#This Row],[Trans Date]]) -> 6 | B101: 45082 | C101: -0.15 | D101: =D100+wf_table[[#This Row],[Debit_Amount]] -> 553.96 | E101: =IF(wf_table[[#This Row],[Debit_Amount]]<0,"debit","-") -> debit | G101: INTERNATIONAL PURCHASE TRANSACTION FEE
A102: =MONTH(wf_table[[#This Row],[Trans Date]]) -> 6 | B102: 45082 | C102: -5.17 | D102: =D101+wf_table[[#This Row],[Debit_Amount]] -> 548.79 | E102: =IF(wf_table[[#This Row],[Debit_Amount]]<0,"debit","-") -> debit | G102: PURCHASE INTL AUTHORIZED ON 06/04 GELAAATI DI MARCO BARCELONA ESP S303155757160995 CARD 1081
A103: =MONTH(wf_table[[#This Row],[Trans Date]]) -> 6 | B103: 45082 | C103: -0.25 | D103: =D102+wf_table[[#This Row],[Debit_Amount]] -> 548.54 | E103: =IF(wf_table[[#This Row],[Debit_Amount]]<0,"debit","-") -> debit | G103: INTERNATIONAL PURCHASE TRANSACTION FEE
A104: =MONTH(wf_table[[#This Row],[Trans Date]]) -> 6 | B104: 45082 | C104: -8.62 | D104: =D103+wf_table[[#This Row],[Debit_Amount]] -> 539.92 | E104: =IF(wf_table[[#This Row],[Debit_Amount]]<0,"debit","-") -> debit | G104: PURCHASE INTL AUTHORIZED ON 06/04 AKATSUKI BARCELONA ESP S303155541745657 CARD 1081
A105: =MONTH(wf_table[[#This Row],[Trans Date]]) -> 6 | B105: 45082 | C105: -0.48 | D105: =D104+wf_table[[#This Row],[Debit_Amount]] -> 539.44 | E105: =IF(wf_table[[#This Row],[Debit_Amount]]<0,"debit","-") -> debit | G105: INTERNATIONAL PURCHASE TRANSACTION FEE
A106: =MONTH(wf_table[[#This Row],[Trans Date]]) -> 6 | B106: 45082 | C106: -16.17 | D106: =D105+wf_table[[#This Row],[Debit_Amount]] -> 523.27 | E106: =IF(wf_table[[#This Row],[Debit_Amount]]<0,"debit","-") -> debit | G106: PURCHASE INTL AUTHORIZED ON 06/03 SQ *PRIMAVERA SOUN Barcelona IRL S463154804564412 CARD 1081
A107: =MONTH(wf_table[[#This Row],[Trans Date]]) -> 6 | B107: 45082 | C107: -0.29 | D107: =D106+wf_table[[#This Row],[Debit_Amount]] -> 522.98 | E107: =IF(wf_table[[#This Row],[Debit_Amount]]<0,"debit","-") -> debit | G107: INTERNATIONAL PURCHASE TRANSACTION FEE
A108: =MONTH(wf_table[[#This Row],[Trans Date]]) -> 6 | B108: 45082 | C108: -9.7 | D108: =D107+wf_table[[#This Row],[Debit_Amount]] -> 513.28 | E108: =IF(wf_table[[#This Row],[Debit_Amount]]<0,"debit","-") -> debit | G108: PURCHASE INTL AUTHORIZED ON 06/03 SQ *BABY JALEBI Barcelona IRL S303154708777719 CARD 1081
... A151: =MONTH(wf_table[[#This Row],[Trans Date]]) -> 6 | B151: 45090 | C151: -135 | D151: =D150+wf_table[[#This Row],[Debit_Amount]] -> 182.87 | E151: =IF(wf_table[[#This Row],[Debit_Amount]]<0,"debit","-") -> debit | G151: VENMO PAYMENT 230613 1027594599507 SEAN LEWIS
...

Sheet SOFI_CHECKING
A1: Month | B1: Transaction Date | C1: Description | D1: Type | E1: Amount | F1: Column1 | G1: Short_Desc | H1: Category_2
A2: =MONTH(sofiC_table[[#This Row],[Transaction Date]]) -> 1 | B2: 44927 | C2: Balance | E2: =F3-E3 -> 60.34
A3: =MONTH(sofiC_table[[#This Row],[Transaction Date]]) -> 1 | B3: 44928 | C3: OAKLAND PARKMOBILE PAY | D3: Debit Card | E3: -4.25 | F3: 56.09 | G3: parking | H3: transportation
A4: =MONTH(sofiC_table[[#This Row],[Transaction Date]]) -> 1 | B4: 44931 | C4: From Savings - 3552 | D4: Deposit | E4: 750 | F4: 806.09
A5: =MONTH(sofiC_table[[#This Row],[Transaction Date]]) -> 1 | B5: 44932 | C5: VENMO | D5: Direct Payment | E5: -750 | F5: 56.09
A6: =MONTH(sofiC_table[[#This Row],[Transaction Date]]) -> 1 | B6: 44939 | C6: 1435 Burlingame Ave | D6: ATM | E6: -403 | F6: 253.09
A7: =MONTH(sofiC_table[[#This Row],[Transaction Date]]) -> 1 | B7: 44939 | C7: From Savings - 3552 | D7: Deposit | E7: 600 | F7: 656.09
A8: =MONTH(sofiC_table[[#This Row],[Transaction Date]]) -> 1 | B8: 44941 | C8: To Emergency Fund Vault | D8: Withdrawal | E8: -253.09 | F8: 0
A9: =MONTH(sofiC_table[[#This Row],[Transaction Date]]) -> 1 | B9: 44951 | C9: From Savings - 3552 | D9: Deposit | E9: 100 | F9: 150
A10: =MONTH(sofiC_table[[#This Row],[Transaction Date]]) -> 1 | B10: 44951 | C10: From Savings - 3552 | D10: Deposit | E10: 50 | F10: 50
A11: =MONTH(sofiC_table[[#This Row],[Transaction Date]]) -> 1 | B11: 44953 | C11: Roundup *CITY OF SM PARKPAYBYPH | D11: Roundup | E11: -0.4 | F11: 144.2
A12: =MONTH(sofiC_table[[#This Row],[Transaction Date]]) -> 1 | B12: 44953 | C12: Roundup *PENINSULA JEWISH COMMU | D12: Roundup | E12: -0.2 | F12: 144.6
A13: =MONTH(sofiC_table[[#This Row],[Transaction Date]]) -> 1 | B13: 44953 | C13: CITY OF SM PARKPAYBYPH | D13: Debit Card | E13: -0.4 | F13: 144.8
A14: =MONTH(sofiC_table[[#This Row],[Transaction Date]]) -> 1 | B14: 44953 | C14: PENINSULA JEWISH COMMU | D14: Debit Card | E14: -4.8 | F14: 145.2
A15: =MONTH(sofiC_table[[#This Row],[Transaction Date]]) -> 1 | B15: 44954 | C15: CITY OF BURLINGAME-PAR | D15: Debit Card | E15: -1 | F15: 143.2
A16: =MONTH(sofiC_table[[#This Row],[Transaction Date]]) -> 1 | B16: 44956 | C16: CASH APP*CYANFACE | D16: Debit Card | E16: -50 | F16: 93.2 | G16: jayelin | H16: people
A17: =MONTH(sofiC_table[[#This Row],[Transaction Date]]) -> 1 | B17: 44957 | C17: Interest earned | D17: Interest Earned | E17: 0.19 | F17: 93.39
A18: =MONTH(sofiC_table[[#This Row],[Transaction Date]]) -> 2 | B18: 44961 | C18: PENINSULA JEWISH COMMU | D18: Debit Card | E18: -73 | F18: 20.39 | G18: gym
A19: =MONTH(sofiC_table[[#This Row],[Transaction Date]]) -> 2 | B19: 44962 | C19: From Savings - 3552 | D19: Deposit | E19: 50 | F19: 120.39
A20: =MONTH(sofiC_table[[#This Row],[Transaction Date]]) -> 2 | B20: 44962 | C20: From Savings - 3552 | D20: Deposit | E20: 50 | F20: 70.39
A21: =MONTH(sofiC_table[[#This Row],[Transaction Date]]) -> 2 | B21: 44964 | C21: CASH APP*CYANFACE | D21: Debit Card | E21: -55 | F21: 65.39 | G21: jayelin | H21: people
A22: =MONTH(sofiC_table[[#This Row],[Transaction Date]]) -> 2 | B22: 44967 | C22: CASH APP*KAIYA | D22: Debit Card | E22: -20 | F22: 25.39
A23: =MONTH(sofiC_table[[#This Row],[Transaction Date]]) -> 2 | B23: 44967 | C23: CASH APP*ROBIN JOSEPH | D23: Debit Card | E23: -20 | F23: 45.39
A24: =MONTH(sofiC_table[[#This Row],[Transaction Date]]) -> 2 | B24: 44978 | C24: CVS STORE #09940 | D24: ATM | E24: -100 | F24: 25.39
A25: =MONTH(sofiC_table[[#This Row],[Transaction Date]]) -> 2 | B25: 44978 | C25: From Savings - 3552 | D25: Deposit | E25: 100 | F25: 125.39
A26: =MONTH(sofiC_table[[#This Row],[Transaction Date]]) -> 2 | B26: 44985 | C26: Interest earned | D26: Interest Earned | E26: 0.08 | F26: 25.47
A27: =MONTH(sofiC_table[[#This Row],[Transaction Date]]) -> 3 | B27: 44986 | C27: From Savings - 3552 | D27: Deposit | E27: 150 | F27: 175.47
A28: =MONTH(sofiC_table[[#This Row],[Transaction Date]]) -> 3 | B28: 44989 | C28: PENINSULA JEWISH COMMU | D28: Debit Card | E28: -146 | F28: 29.47 | G28: gym
A29: =MONTH(sofiC_table[[#This Row],[Transaction Date]]) -> 3 | B29: 44995 | C29: From Savings - 3552 | D29: Deposit | E29: 800 | F29: 829.47
A30: =MONTH(sofiC_table[[#This Row],[Transaction Date]]) -> 3 | B30: 44998 | C30: VENMO | D30: Direct Payment | E30: -772.3 | F30: 57.17
A31: =MONTH(sofiC_table[[#This Row],[Transaction Date]]) -> 3 | B31: 45002 | C31: From Savings - 3552 | D31: Deposit | E31: 141.6 | F31: 198.77
A32: =MONTH(sofiC_table[[#This Row],[Transaction Date]]) -> 3 | B32: 45005 | C32: CASH APP*CYANFACE | D32: Debit Card | E32: -15 | F32: 42.17 | G32: jayelin | H32: people
A33: =MONTH(sofiC_table[[#This Row],[Transaction Date]]) -> 3 | B33: 45005 | C33: VENMO | D33: Direct Payment | E33: -141.6 | F33: 57.17
A34: =MONTH(sofiC_table[[#This Row],[Transaction Date]]) -> 3 | B34: 45016 | C34: Interest earned | D34: Interest Earned | E34: 0.27 | F34: 42.44
A35: =MONTH(sofiC_table[[#This Row],[Transaction Date]]) -> 4 | B35: 45024 | C35: TCB*MTA METER MTA PBP | D35: Debit Card | E35: -3.5 | F35: 38.94
A36: =MONTH(sofiC_table[[#This Row],[Transaction Date]]) -> 4 | B36: 45026 | C36: Mobile Check Deposit | D36: Check Deposit | E36: 217.6 | F36: 256.54
A37: =MONTH(sofiC_table[[#This Row],[Transaction Date]]) -> 4 | B37: 45027 | C37: BEST BUY | D37: Direct Payment | E37: -153.1 | F37: 103.44
A38: =MONTH(sofiC_table[[#This Row],[Transaction Date]]) -> 4 | B38: 45032 | C38: To Savings - 3552 | D38: Withdrawal | E38: -100 | F38: 3.44
A39: =MONTH(sofiC_table[[#This Row],[Transaction Date]]) -> 4 | B39: 45036 | C39: CITY OF SM PARKPAYBYPH | D39: Debit Card | E39: -0.1 | F39: 2.61
A40: =MONTH(sofiC_table[[#This Row],[Transaction Date]]) -> 4 | B40: 45036 | C40: CITY OF SM PARKPAYBYPH | D40: Debit Card | E40: -0.63 | F40: 2.71
A41: =MONTH(sofiC_table[[#This Row],[Transaction Date]]) -> 4 | B41: 45036 | C41: CITY OF SM PARKPAYBYPH | D41: Debit Card | E41: -0.1 | F41: 3.34
A42: =MONTH(sofiC_table[[#This Row],[Transaction Date]]) -> 4 | B42: 45042 | C42: From Savings - 3552 | D42: Deposit | E42: 50 | F42: 52.61
A43: =MONTH(sofiC_table[[#This Row],[Transaction Date]]) -> 4 | B43: 45043 | C43: BEST BUY | D43: Direct Payment | E43: -49.32 | F43: 3.29
A44: =MONTH(sofiC_table[[#This Row],[Transaction Date]]) -> 4 | B44: 45044 | C44: From Savings - 3552 | D44: Deposit | E44: 200 | F44: 203.29
... A69: =MONTH(sofiC_table[[#This Row],[Transaction Date]]) -> 7 | B69: 45110 | C69: Synchrony Bank | D69: Direct Payment | E69: -178 | F69: 5.18
A70: =MONTH(sofiC_table[[#This Row],[Transaction Date]]) -> 7 | B70: 45113 | C70: From Savings - 3552 | E70: 10
A71: =MONTH(sofiC_table[[#This Row],[Transaction Date]]) -> 7 | B71: 45113 | C71: From Savings - 3552 | E71: 90
A72: =MONTH(sofiC_table[[#This Row],[Transaction Date]]) -> 7 | B72: 45115 | C72: Cash App*engagetm | E72: -105
A73: =MONTH(sofiC_table[[#This Row],[Transaction Date]]) -> 7 | B73: 45119 | C73: From Savings - 3552 | E73: 2
A74: =MONTH(sofiC_table[[#This Row],[Transaction Date]]) -> 7 | B74: 45122 | C74: City of Sm Parkpaybyph | E74: -0.1
A75: =MONTH(sofiC_table[[#This Row],[Transaction Date]]) -> 7 | B75: 45122 | C75: City of Sm Parkpaybyph | E75: -1.25
A76: =MONTH(sofiC_table[[#This Row],[Transaction Date]]) -> 7 | B76: 45132 | C76: From Savings - 3552 | E76: 1803.4
A77: =MONTH(sofiC_table[[#This Row],[Transaction Date]]) -> 7 | B77: 45133 | C77: From Savings - 3552 | E77: 200
A78: =MONTH(sofiC_table[[#This Row],[Transaction Date]]) -> 7 | B78: 45133 | C78: Venmo | E78: -1803.4
A79: =MONTH(sofiC_table[[#This Row],[Transaction Date]]) -> 7 | B79: 45135 | C79: Synchrony Bank | E79: -200
A80: =MONTH(sofiC_table[[#This Row],[Transaction Date]]) -> 7 | B80: 45138 | C80: Interest earned | E80: 0.05
A81: =MONTH(sofiC_table[[#This Row],[Transaction Date]]) -> 8 | B81: 45142 | C81: From Savings - 3552 | E81: 5
... A93: =MONTH(sofiC_table[[#This Row],[Transaction Date]]) -> 9 | B93: 45190 | C93: Venmo | E93: -1803.4

Sheet SOFI_SAVINGS
A1: Month | B1: Transaction Date | C1: Description | D1: Type | E1: Amount | F1: Cumulative | G1: incremental | H1: Short_Desc | I1: Category_2
A2: =MONTH(sofiS_table[[#This Row],[Transaction Date]]) -> 1 | B2: 44927 | C2: Balance | E2: =F3-E3 -> 1148.39 | G2: =IFERROR(sofiS_table[[#This Row],[Cumulative]]-F1,0) -> 0
A3: =MONTH(sofiS_table[[#This Row],[Transaction Date]]) -> 1 | B3: 44931 | C3: To Checking - 8930 | D3: Withdrawal | E3: -750 | F3: 398.39 | G3: =IFERROR(sofiS_table[[#This Row],[Cumulative]]-F1,0) -> 0
A4: =MONTH(sofiS_table[[#This Row],[Transaction Date]]) -> 1 | B4: 44936 | C4: Nationwide | D4: Direct Deposit | E4: 3066.58 | F4: 3464.97 | G4: =IFERROR(sofiS_table[[#This Row],[Cumulative]]-F3,0) -> 3066.58
A5: =MONTH(sofiS_table[[#This Row],[Transaction Date]]) -> 1 | B5: 44938 | C5: DISCOVER | D5: Direct Payment | E5: -552.53 | F5: 2912.44 | G5: =IFERROR(sofiS_table[[#This Row],[Cumulative]]-F4,0) -> -552.53
A6: =MONTH(sofiS_table[[#This Row],[Transaction Date]]) -> 1 | B6: 44939 | C6: To Checking - 8930 | D6: Withdrawal | E6: -600 | F6: 2312.44 | G6: =IFERROR(sofiS_table[[#This Row],[Cumulative]]-F5,0) -> -600
A7: =MONTH(sofiS_table[[#This Row],[Transaction Date]]) -> 1 | B7: 44941 | C7: From Emergency Fund Vault | D7: Deposit | E7: 253.09 | F7: 2565.53 | G7: =IFERROR(sofiS_table[[#This Row],[Cumulative]]-F6,0) -> 253.09
A8: =MONTH(sofiS_table[[#This Row],[Transaction Date]]) -> 1 | B8: 44943 | C8: BOARD OF REGENTS | D8: Direct Payment | E8: -932 | F8: 1633.53 | G8: =IFERROR(sofiS_table[[#This Row],[Cumulative]]-F7,0) -> -932
A9: =MONTH(sofiS_table[[#This Row],[Transaction Date]]) -> 1 | B9: 44949 | C9: DISCOVER | D9: Direct Payment | E9: -1000 | F9: 633.53 | G9: =IFERROR(sofiS_table[[#This Row],[Cumulative]]-F8,0) -> -1000
A10: =MONTH(sofiS_table[[#This Row],[Transaction Date]]) -> 1 | B10: 44950 | C10: Nationwide | D10: Direct Deposit | E10: 2705.92 | F10: 3339.45 | G10: =IFERROR(sofiS_table[[#This Row],[Cumulative]]-F9,0) -> 2705.92
A11: =MONTH(sofiS_table[[#This Row],[Transaction Date]]) -> 1 | B11: 44951 | C11: SoFi Rewards Redemption | D11: Other | E11: 4.1 | F11: 3193.55 | G11: =IFERROR(sofiS_table[[#This Row],[Cumulative]]-F10,0) -> -145.9
A12: =MONTH(sofiS_table[[#This Row],[Transaction Date]]) -> 1 | B12: 44951 | C12: To Checking - 8930 | D12: Withdrawal | E12: -100 | F12: 3189.45 | G12: =IFERROR(sofiS_table[[#This Row],[Cumulative]]-F11,0) -> -4.1
A13: =MONTH(sofiS_table[[#This Row],[Transaction Date]]) -> 1 | B13: 44951 | C13: To Checking - 8930 | D13: Withdrawal | E13: -50 | F13: 3289.45 | G13: =IFERROR(sofiS_table[[#This Row],[Cumulative]]-F12,0) -> 100
A14: =MONTH(sofiS_table[[#This Row],[Transaction Date]]) -> 1 | B14: 44952 | C14: DISCOVER | D14: Direct Payment | E14: -2071.58 | F14: 1121.97 | G14: =IFERROR(sofiS_table[[#This Row],[Cumulative]]-F13,0) -> -2167.48
A15: =MONTH(sofiS_table[[#This Row],[Transaction Date]]) -> 1 | B15: 44957 | C15: Interest earned | D15: Interest Earned | E15: 5.02 | F15: 1126.99 | G15: =IFERROR(sofiS_table[[#This Row],[Cumulative]]-F14,0) -> 5.02
... A74: =MONTH(sofiS_table[[#This Row],[Transaction Date]]) -> 7 | B74: 45113 | C74: HEALTHEQUITY INC | D74: Deposit | E74: 499.64 | F74: 764.66 | G74: =IFERROR(sofiS_table[[#This Row],[Cumulative]]-F73,0) -> 321.64
A75: =MONTH(sofiS_table[[#This Row],[Transaction Date]]) -> 7 | B75: 45114 | C75: Instamed | E75: -599.64 | F75: =F74+sofiS_table[[#This Row],[Amount]] -> 165.02 | G75: =IFERROR(sofiS_table[[#This Row],[Cumulative]]-F74,0) -> -599.64
A76: =MONTH(sofiS_table[[#This Row],[Transaction Date]]) -> 7 | B76: 45118 | C76: Nationwide | D76: Direct Deposit | E76: 2258.37 | F76: =F75+sofiS_table[[#This Row],[Amount]] -> 2423.39 | G76: =IFERROR(sofiS_table[[#This Row],[Cumulative]]-F75,0) -> 2258.37
A77: =MONTH(sofiS_table[[#This Row],[Transaction Date]]) -> 7 | B77: 45119 | C77: To Checking - 8930 | E77: -2 | F77: =F76+sofiS_table[[#This Row],[Amount]] -> 2421.39 | G77: =IFERROR(sofiS_table[[#This Row],[Cumulative]]-F76,0) -> -2
A78: =MONTH(sofiS_table[[#This Row],[Transaction Date]]) -> 7 | B78: 45120 | C78: Discover | E78: -2118.23 | F78: =F77+sofiS_table[[#This Row],[Amount]] -> 303.16 | G78: =IFERROR(sofiS_table[[#This Row],[Cumulative]]-F77,0) -> -2118.23
A79: =MONTH(sofiS_table[[#This Row],[Transaction Date]]) -> 7 | B79: 45132 | C79: To Checking - 8930 | E79: -1803.4 | F79: =F78+sofiS_table[[#This Row],[Amount]] -> -1500.24 | G79: =IFERROR(sofiS_table[[#This Row],[Cumulative]]-F78,0) -> -1803.4
A80: =MONTH(sofiS_table[[#This Row],[Transaction Date]]) -> 7 | B80: 45132 | C80: Nationwide | D80: Direct Deposit | E80: 2258.37 | F80: =F79+sofiS_table[[#This Row],[Amount]] -> 758.13 | G80: =IFERROR(sofiS_table[[#This Row],[Cumulative]]-F79,0) -> 2258.37
A81: =MONTH(sofiS_table[[#This Row],[Transaction Date]]) -> 7 | B81: 45132 | C81: Healthequity Inc | E81: 100 | F81: =F80+sofiS_table[[#This Row],[Amount]] -> 858.13 | G81: =IFERROR(sofiS_table[[#This Row],[Cumulative]]-F80,0) -> 100
A82: =MONTH(sofiS_table[[#This Row],[Transaction Date]]) -> 7 | B82: 45133 | C82: To Checking - 8930 | E82: -200 | F82: =F81+sofiS_table[[#This Row],[Amount]] -> 658.13 | G82: =IFERROR(sofiS_table[[#This Row],[Cumulative]]-F81,0) -> -200
A83: =MONTH(sofiS_table[[#This Row],[Transaction Date]]) -> 7 | B83: 45134 | C83: Discover | E83: -500 | F83: =F82+sofiS_table[[#This Row],[Amount]] -> 158.13 | G83: =IFERROR(sofiS_table[[#This Row],[Cumulative]]-F82,0) -> -500
A84: =MONTH(sofiS_table[[#This Row],[Transaction Date]]) -> 7 | B84: 45138 | C84: Interest earned | E84: 1.28 | F84: =F83+sofiS_table[[#This Row],[Amount]] -> 159.41 | G84: =IFERROR(sofiS_table[[#This Row],[Cumulative]]-F83,0) -> 1.28
A85: =MONTH(sofiS_table[[#This Row],[Transaction Date]]) -> 7 | B85: 45138 | C85: Wells Fargo Bank Na | E85: -50 | F85: =F84+sofiS_table[[#This Row],[Amount]] -> 109.41 | G85: =IFERROR(sofiS_table[[#This Row],[Cumulative]]-F84,0) -> -50
A86: =MONTH(sofiS_table[[#This Row],[Transaction Date]]) -> 8 | B86: 45142 | C86: To Checking - 8930 | E86: -5 | F86: =F85+sofiS_table[[#This Row],[Amount]] -> 104.41 | G86: =IFERROR(sofiS_table[[#This Row],[Cumulative]]-F85,0) -> -5
A87: =MONTH(sofiS_table[[#This Row],[Transaction Date]]) -> 8 | B87: 45144 | C87: Cash App | E87: 100 | F87: =F86+sofiS_table[[#This Row],[Amount]] -> 204.41 | G87: =IFERROR(sofiS_table[[#This Row],[Cumulative]]-F86,0) -> 100
A88: =MONTH(sofiS_table[[#This Row],[Transaction Date]]) -> 8 | B88: 45146 | C88: To Emergency Fund Vault | E88: -901.7 | F88: =F87+sofiS_table[[#This Row],[Amount]] -> -697.29 | G88: =IFERROR(sofiS_table[[#This Row],[Cumulative]]-F87,0) -> -901.7
A89: =MONTH(sofiS_table[[#This Row],[Transaction Date]]) -> 8 | B89: 45146 | C89: Nationwide | D89: Direct Deposit | E89: 2258.37 | F89: =F88+sofiS_table[[#This Row],[Amount]] -> 1561.08 | G89: =IFERROR(sofiS_table[[#This Row],[Cumulative]]-F88,0) -> 2258.37
A90: =MONTH(sofiS_table[[#This Row],[Transaction Date]]) -> 8 | B90: 45148 | C90: Discover | E90: -1027.93 | F90: =F89+sofiS_table[[#This Row],[Amount]] -> 533.15 | G90: =IFERROR(sofiS_table[[#This Row],[Cumulative]]-F89,0) -> -1027.93
A91: =MONTH(sofiS_table[[#This Row],[Transaction Date]]) -> 8 | B91: 45160 | C91: Nationwide | D91: Direct Deposit | E91: 3050.56 | F91: =F90+sofiS_table[[#This Row],[Amount]] -> 3583.71 | G91: =IFERROR(sofiS_table[[#This Row],[Cumulative]]-F90,0) -> 3050.56
A92: =MONTH(sofiS_table[[#This Row],[Transaction Date]]) -> 8 | B92: 45162 | C92: To Checking - 8930 | E92: -932 | F92: =F91+sofiS_table[[#This Row],[Amount]] -> 2651.71 | G92: =IFERROR(sofiS_table[[#This Row],[Cumulative]]-F91,0) -> -932
A93: =MONTH(sofiS_table[[#This Row],[Transaction Date]]) -> 8 | B93: 45163 | C93: To Checking - 8930 | E93: -816.87 | F93: =F92+sofiS_table[[#This Row],[Amount]] -> 1834.84 | G93: =IFERROR(sofiS_table[[#This Row],[Cumulative]]-F92,0) -> -816.87
A94: =MONTH(sofiS_table[[#This Row],[Transaction Date]]) -> 8 | B94: 45163 | C94: Discover | E94: -2000 | F94: =F93+sofiS_table[[#This Row],[Amount]] -> -165.16 | G94: =IFERROR(sofiS_table[[#This Row],[Cumulative]]-F93,0) -> -2000
A95: =MONTH(sofiS_table[[#This Row],[Transaction Date]]) -> 8 | B95: 45163 | C95: From Emergency Fund Vault | E95: 902.3 | F95: =F94+sofiS_table[[#This Row],[Amount]] -> 737.14 | G95: =IFERROR(sofiS_table[[#This Row],[Cumulative]]-F94,0) -> 902.3
A96: =MONTH(sofiS_table[[#This Row],[Transaction Date]]) -> 8 | B96: 45166 | C96: To Checking - 8930 | E96: -793.5 | F96: =F95+sofiS_table[[#This Row],[Amount]] -> -56.36 | G96: =IFERROR(sofiS_table[[#This Row],[Cumulative]]-F95,0) -> -793.5
A97: =MONTH(sofiS_table[[#This Row],[Transaction Date]]) -> 8 | B97: 45166 | C97: Wells Fargo Bank Na | E97: 300 | F97: =F96+sofiS_table[[#This Row],[Amount]] -> 243.64 | G97: =IFERROR(sofiS_table[[#This Row],[Cumulative]]-F96,0) -> 300
A98: =MONTH(sofiS_table[[#This Row],[Transaction Date]]) -> 8 | B98: 45169 | C98: Interest earned | E98: 2.45 | F98: =F97+sofiS_table[[#This Row],[Amount]] -> 246.09 | G98: =IFERROR(sofiS_table[[#This Row],[Cumulative]]-F97,0) -> 2.45
A99: =MONTH(sofiS_table[[#This Row],[Transaction Date]]) -> 8 | B99: 45169 | C99: To Checking - 8930 | E99: -100 | F99: =F98+sofiS_table[[#This Row],[Amount]] -> 146.09 | G99: =IFERROR(sofiS_table[[#This Row],[Cumulative]]-F98,0) -> -100
A100: =MONTH(sofiS_table[[#This Row],[Transaction Date]]) -> 9 | B100: 45174 | C100: Nationwide | D100: Direct Deposit | E100: 2258.37 | F100: =F99+sofiS_table[[#This Row],[Amount]] -> 2404.46 | G100: =IFERROR(sofiS_table[[#This Row],[Cumulative]]-F99,0) -> 2258.37
A101: =MONTH(sofiS_table[[#This Row],[Transaction Date]]) -> 9 | B101: 45176 | C101: Discover | E101: -2133.04 | F101: =F100+sofiS_table[[#This Row],[Amount]] -> 271.42 | G101: =IFERROR(sofiS_table[[#This Row],[Cumulative]]-F100,0) -> -2133.04
A102: =MONTH(sofiS_table[[#This Row],[Transaction Date]]) -> 9 | B102: 45188 | C102: Nationwide | D102: Direct Deposit | E102: 2732.7 | F102: =F101+sofiS_table[[#This Row],[Amount]] -> 3004.12 | G102: =IFERROR(sofiS_table[[#This Row],[Cumulative]]-F101,0) -> 2732.7
A103: =MONTH(sofiS_table[[#This Row],[Transaction Date]]) -> 9 | B103: 45189 | C103: To Checking - 8930 | E103: -1810 | F103: =F102+sofiS_table[[#This Row],[Amount]] -> 1194.12 | G103: =IFERROR(sofiS_table[[#This Row],[Cumulative]]-F102,0) -> -1810
A104: =MONTH(sofiS_table[[#This Row],[Transaction Date]]) -> 9 | B104: 45199 | C104: Interest earned | D104: Interest Earned | E104: 2.63 | F104: 1096.75 | G104: =IFERROR(sofiS_table[[#This Row],[Cumulative]]-F103,0) -> -97.37
A105: =MONTH(sofiS_table[[#This Row],[Transaction Date]]) -> 10 | B105: 45202 | C105: Nationwide | D105: Direct Deposit | E105: 2732.71 | F105: 3829.46 | G105: =IFERROR(sofiS_table[[#This Row],[Cumulative]]-F104,0) -> 2732.71
A106: =MONTH(sofiS_table[[#This Row],[Transaction Date]]) -> 10 | B106: 45204 | C106: DISCOVER | D106: Direct Payment | E106: -1900 | F106: 1929.46 | G106: =IFERROR(sofiS_table[[#This Row],[Cumulative]]-F105,0) -> -1900
A107: =MONTH(sofiS_table[[#This Row],[Transaction Date]]) -> 10 | B107: 45206 | C107: To Checking - 8930 | D107: Withdrawal | E107: -447.1 | F107: 1482.36 | G107: =IFERROR(sofiS_table[[#This Row],[Cumulative]]-F106,0) -> -447.1
A108: =MONTH(sofiS_table[[#This Row],[Transaction Date]]) -> 10 | B108: 45208 | C108: To Checking - 8930 | D108: Withdrawal | E108: -200 | F108: 1282.36 | G108: =IFERROR(sofiS_table[[#This Row],[Cumulative]]-F107,0) -> -200
A109: =MONTH(sofiS_table[[#This Row],[Transaction Date]]) -> 10 | B109: 45216 | C109: Nationwide | D109: Direct Deposit | E109: 2732.71 | F109: 4015.07 | G109: =IFERROR(sofiS_table[[#This Row],[Cumulative]]-F108,0) -> 2732.71
A110: =MONTH(sofiS_table[[#This Row],[Transaction Date]]) -> 10 | B110: 45218 | C110: DISCOVER | D110: Direct Payment | E110: -1582.98 | F110: 2432.09 | G110: =IFERROR(sofiS_table[[#This Row],[Cumulative]]-F109,0) -> -1582.98
A111: =MONTH(sofiS_table[[#This Row],[Transaction Date]]) -> 10 | B111: 45223 | C111: To Checking - 8930 | D111: Withdrawal | E111: -500 | F111: 1932.09 | G111: =IFERROR(sofiS_table[[#This Row],[Cumulative]]-F110,0) -> -500
A112: =MONTH(sofiS_table[[#This Row],[Transaction Date]]) -> 10 | B112: 45230 | C112: Interest earned | D112: Interest Earned | E112: 7.94 | F112: 4672.74 | G112: =IFERROR(sofiS_table[[#This Row],[Cumulative]]-F111,0) -> 2740.65
A113: =MONTH(sofiS_table[[#This Row],[Transaction Date]]) -> 10 | B113: 45230 | C113: Nationwide | D113: Direct Deposit | E113: 2732.71 | F113: 4664.8 | G113: =IFERROR(sofiS_table[[#This Row],[Cumulative]]-F112,0) -> -7.94
A114: =MONTH(sofiS_table[[#This Row],[Transaction Date]]) -> 11 | B114: 45233 | C114: DISCOVER | D114: Direct Payment | E114: -1065.5 | F114: 3607.24 | G114: =IFERROR(sofiS_table[[#This Row],[Cumulative]]-F113,0) -> -1057.56
A115: =MONTH(sofiS_table[[#This Row],[Transaction Date]]) -> 11 | B115: 45243 | C115: DISCOVER | D115: Direct Payment | E115: -2089.04 | F115: 1518.2 | G115: =IFERROR(sofiS_table[[#This Row],[Cumulative]]-F114,0) -> -2089.04
... A131: =MONTH(sofiS_table[[#This Row],[Transaction Date]]) -> 12 | B131: 45291 | C131: Interest earned | D131: Interest Earned | E131: 7.87 | F131: 3451.75 | G131: =IFERROR(sofiS_table[[#This Row],[Cumulative]]-F130,0) -> 7.87

Sheet HSA
A1: Column1 | B1: Date | C1: Transaction | D1: Amount | E1: HSA Cash Balance
A2: =(MONTH(B2))+0 -> 1 | B2: 44938 | C2: Employer Contribution (Tax year: 2023) (Tax year: 2023) | D2: 250 | E2: 500.71
A3: =(MONTH(B3))+0 -> 1 | B3: 44938 | C3: Employee Contribution (Tax year: 2023) (Tax year: 2023) | D3: 118.85 | E3: 250.71
A4: =(MONTH(B4))+0 -> 1 | B4: 44938 | C4: Balance Forward | D4: 131.86 | E4: 131.86 | F4: 0
A5: =(MONTH(B5))+0 -> 1 | B5: 44945 | C5: A Plus Dental Center - Sa, San Mateo, CA (Card Transaction ID: 0it8ihn) | D5: -234.4 | E5: 526.31
A6: =(MONTH(B6))+0 -> 1 | B6: 44945 | C6: Employer Contribution (Tax year: 2023) (Tax year: 2023) | D6: 260 | E6: 760.71
A7: =(MONTH(B7))+0 -> 1 | B7: 44952 | C7: Employee Contribution (Tax year: 2023) (Tax year: 2023) | D7: 118.85 | E7: 764.01
A8: =(MONTH(B8))+0 -> 1 | B8: 44952 | C8: Employer Contribution (Tax year: 2023) (Tax year: 2023) | D8: 118.85 | E8: 645.16
A9: =(MONTH(B9))+0 -> 1 | B9: 44957 | C9: Interest for Jan-23 | D9: 0.04 | E9: 764.05
A10: =(MONTH(B10))+0 -> 2 | B10: 44973 | C10: Arman Kirakosian Dpm (Claim ID:22317048-0006) | D10: -103.02 | E10: 447.88
A11: =(MONTH(B11))+0 -> 2 | B11: 44974 | C11: Wells Fargo (Claim ID:22317048-0005) | D11: -136 | E11: 311.88
A12: =(MONTH(B12))+0 -> 2 | B12: 44980 | C12: Sq *ayurbliss Physical, San Mateo, CA (Card Transaction ID: vp35vwm) | D12: -68 | E12: 375.03
A13: =(MONTH(B13))+0 -> 2 | B13: 44980 | C13: Employee Contribution (Tax year: 2023) (Tax year: 2023) | D13: 118.85 | E13: 443.03
A14: =(MONTH(B14))+0 -> 2 | B14: 44980 | C14: Employer Contribution (Tax year: 2023) (Tax year: 2023) | D14: 12.3 | E14: 324.18
A15: =(MONTH(B15))+0 -> 2 | B15: 44981 | C15: Sq *ayurbliss Physical Th, San Mateo, CA (Card Transaction ID: nt9xxgb) | D15: -68 | E15: 307.03
A16: =(MONTH(B16))+0 -> 2 | B16: 44985 | C16: Interest for Feb-23 | D16: 0.04 | E16: 307.07
... A49: =(MONTH(B49))+0 -> 6 | B49: 45092 | C49: Employee Contribution (Tax year: 2023) (Tax year: 2023) | D49: 118.85 | E49: 686.34
A50: =(MONTH(B50))+0 -> 6 | B50: 6/29/2023 | C50: Employee Contribution (Tax year: 2023) (Tax year: 2023) | D50: 118.85 | E50: 605.19
A51: =(MONTH(B51))+0 -> 6 | B51: 6/30/2023 | C51: Interest for Jun-23 | D51: 0.04 | E51: 605.23
A52: =(MONTH(B52))+0 -> 7 | B52: 7/6/2023 | C52: SOFI (Claim ID:22317048-0008) | D52: -499.64 | E52: 105.59
A53: =(MONTH(B53))+0 -> 7 | B53: 45120 | C53: Employee Contribution (tax year: 2023) | D53: 118.85 | E53: =E52+hsa_table[[#This Row],[Amount]] -> 224.44
A54: =(MONTH(B54))+0 -> 7 | B54: 45133 | C54: Sofi (claim ID:x-0008) Eft to Sofi | D54: -100 | E54: =E53+hsa_table[[#This Row],[Amount]] -> 124.44
A55: =(MONTH(B55))+0 -> 7 | B55: 45134 | C55: Employee Contribution (tax year: 2023) | D55: 118.85 | E55: =E54+hsa_table[[#This Row],[Amount]] -> 243.29
A56: =(MONTH(B56))+0 -> 7 | B56: 45138 | C56: Interest for Jul-23 | D56: 0.02 | E56: =E55+hsa_table[[#This Row],[Amount]] -> 243.31
A57: =(MONTH(B57))+0 -> 8 | B57: 45148 | C57: Employee Contribution (tax year: 2023) | D57: 118.85 | E57: =E56+hsa_table[[#This Row],[Amount]] -> 362.16
A58: =(MONTH(B58))+0 -> 8 | B58: 45154 | C58: Suttr Hlth Pcr Mho Hosp, x-x-1633, CA (card Transaction Id: iqbxey8) | D58: -199.72 | E58: =E57+hsa_table[[#This Row],[Amount]] -> 162.44
A59: =(MONTH(B59))+0 -> 8 | B59: 45162 | C59: Employee Contribution (tax year: 2023) | D59: 118.85 | E59: =E58+hsa_table[[#This Row],[Amount]] -> 281.29
A60: =(MONTH(B60))+0 -> 8 | B60: 45169 | C60: Interest for Aug-23 | D60: 0.02 | E60: =E59+hsa_table[[#This Row],[Amount]] -> 281.31
A61: =(MONTH(B61))+0 -> 9 | B61: 45175 | C61: North Peninsula Podiatry, San Bruno, CA (card Transaction Id: 3t62tix) | D61: -210 | E61: =E60+hsa_table[[#This Row],[Amount]] -> 71.31
A62: =(MONTH(B62))+0 -> 9 | B62: 45176 | C62: Employee Contribution (tax year: 2023) | D62: 118.85 | E62: =E61+hsa_table[[#This Row],[Amount]] -> 190.16
A63: =(MONTH(B63))+0 -> 9 | B63: 45190 | C63: Employee Contribution (tax year: 2023) | D63: 118.85 | E63: =E62+hsa_table[[#This Row],[Amount]] -> 309.01

Sheet Fidelity
A1: Month | B1: Date | C1: Investment | D1: Transaction Type | E1: Amount | F1: Shares/Unit
A2: =MONTH(sofiS_table8910[[#This Row],[Date]]) -> 1 | B2: 44927 | C2: 2055 FUND | D2: Balance Forward | E2: 12785.41 | F2: 0
A3: =MONTH(sofiS_table8910[[#This Row],[Date]]) -> 1 | B3: 44939 | C3: 2055 FUND | D3: Contributions | E3: 672.31 | F3: 61.736 | H3: 0
A4: =MONTH(sofiS_table8910[[#This Row],[Date]]) -> 1 | B4: 44953 | C4: 2055 FUND | D4: Contributions | E4: 1244.42 | F4: 112.414
A5: =MONTH(sofiS_table8910[[#This Row],[Date]]) -> 2 | B5: 44967 | C5: 2055 FUND | D5: Contributions | E5: 743.08 | F5: 67.308
A6: =MONTH(sofiS_table8910[[#This Row],[Date]]) -> 2 | B6: 44981 | C6: 2055 FUND | D6: Contributions | E6: 743.08 | F6: 68.868
A7: =MONTH(sofiS_table8910[[#This Row],[Date]]) -> 2 | B7: 44984 | C7: 2055 FUND | D7: RECORDKEEPING FEE | E7: -4.02 | F7: -0.371
A8: =MONTH(sofiS_table8910[[#This Row],[Date]]) -> 2 | B8: 44984 | C8: 2055 FUND | D8: Change in Market Value | E8: 0.1 | F8: 0
A9: =MONTH(sofiS_table8910[[#This Row],[Date]]) -> 3 | B9: 44995 | C9: 2055 FUND | D9: Contributions | E9: 880 | F9: 83.019
A10: =MONTH(sofiS_table8910[[#This Row],[Date]]) -> 3 | B10: 45009 | C10: 2055 FUND | D10: Contributions | E10: 160 | F10: 15.009
A11: =MONTH(sofiS_table8910[[#This Row],[Date]]) -> 4 | B11: 45026 | C11: 2055 FUND | D11: Contributions | E11: 160 | F11: 14.585
A12: =MONTH(sofiS_table8910[[#This Row],[Date]]) -> 4 | B12: 45037 | C12: 2055 FUND | D12: Contributions | E12: 160 | F12: 14.401
A13: =MONTH(sofiS_table8910[[#This Row],[Date]]) -> 5 | B13: 45051 | C13: 2055 FUND | D13: Contributions | E13: 160 | F13: 14.409
A14: =MONTH(sofiS_table8910[[#This Row],[Date]]) -> 5 | B14: 45057 | C14: 2055 FUND | D14: RECORDKEEPING FEE | E14: -2.51 | F14: -0.227
A15: =MONTH(sofiS_table8910[[#This Row],[Date]]) -> 5 | B15: 45057 | C15: 2055 FUND | D15: Change in Market Value | E15: 0.11 | F15: 0
... A18: =MONTH(sofiS_table8910[[#This Row],[Date]]) -> 6 | B18: 45095 | C18: 2055 FUND | D18: Change in Market Value | E18: 1860.16 | F18: 11.57
A19: =MONTH(sofiS_table8910[[#This Row],[Date]]) -> 7 | B19: 45121 | C19: 2055 FUND | D19: Contributions | E19: 0.02
A20: =MONTH(sofiS_table8910[[#This Row],[Date]]) -> 7 | B20: 45135 | C20: 2055 FUND | D20: Contributions | E20: 0.04
A21: =MONTH(sofiS_table8910[[#This Row],[Date]]) -> 8 | B21: 45147 | C21: 2055 FUND | D21: RECORDKEEPING FEE | E21: -4.24
A22: =MONTH(sofiS_table8910[[#This Row],[Date]]) -> 8 | B22: 45163 | C22: 2055 FUND | D22: Contributions | E22: 0.06
A23: =MONTH(sofiS_table8910[[#This Row],[Date]]) -> 9 | B23: 45191 | C23: 2055 FUND | D23: Contributions | E23: 0.03

Sheet Discover Data
B1: Month | C1: Trans. date | D1: Post date | E1: Description | F1: Amount | G1: Category | H1: Short_Desc | I1: Reoccurring_Flag | J1: Category_2 | K1: Date | L1: Year | M1: Sort_Date | N1: CumAmount | O1: Counter | S1: 44927 | T1: 44958 | U1: 44986 | V1: 45017 | W1: 45047 | X1: 45078 | Y1: 45108 | Z1: 08/2023 | AA1: 09/2023 | AB1: 10/2023 | AC1: 11/2023 | AD1: 12/2023
A2: 0 | B2: =MONTH(dis_table[[#This Row],[Date]]) -> 1 | C2: 44927 | D2: 44927 | E2: Balance | F2: 577.5 | G2: Balance | H2: Balance | I2: No | J2: Balance | K2: 44927 | L2: 2023 | M2: 44927 | N2: 577.5 | O2: 1 | R2: Automotive | S2: =SUMIFS(dis_table[Amount],dis_table[Category],$R2,dis_table[Date],S$1) -> 16.4 | T2: =SUMIFS(dis_table[Amount],dis_table[Category],$R2,dis_table[Date],T$1) -> 279.89 | U2: =SUMIFS(dis_table[Amount],dis_table[Category],$R2,dis_table[Date],U$1) -> 106.56 | V2: =SUMIFS(dis_table[Amount],dis_table[Category],$R2,dis_table[Date],V$1) -> 0 | W2: =SUMIFS(dis_table[Amount],dis_table[Category],$R2,dis_table[Date],W$1) -> 0 | X2: =SUMIFS(dis_table[Amount],dis_table[Category],$R2,dis_table[Date],X$1) -> 0 | Y2: =SUMIFS(dis_table[Amount],dis_table[Category],$R2,dis_table[Date],Y$1) -> 0 | Z2: =SUMIFS(dis_table[Amount],dis_table[Category],$R2,dis_table[Date],Z$1) -> 0 | ... AD2: =SUMIFS(dis_table[Amount],dis_table[Category],$R2,dis_table[Date],AD$1) -> 151.04
A3: 1 | B3: =MONTH(dis_table[[#This Row],[Date]]) -> 1 | C3: 44927 | D3: 44927 | E3: SPOTIFY P1FEF894B5 8777781161 NY | F3: 4.99 | G3: Merchandise | H3: spotify | I3: Yes | J3: Recreation_Entertainment | K3: 44927 | L3: 2023 | M3: 44927 | N3: 582.49 | O3: 1 | R3: Education | S3: =SUMIFS(dis_table[Amount],dis_table[Category],$R3,dis_table[Date],S$1) -> 49 | T3: =SUMIFS(dis_table[Amount],dis_table[Category],$R3,dis_table[Date],T$1) -> 98 | U3: =SUMIFS(dis_table[Amount],dis_table[Category],$R3,dis_table[Date],U$1) -> 448 | V3: =SUMIFS(dis_table[Amount],dis_table[Category],$R3,dis_table[Date],V$1) -> 0 | W3: =SUMIFS(dis_table[Amount],dis_table[Category],$R3,dis_table[Date],W$1) -> 1057.49 | X3: =SUMIFS(dis_table[Amount],dis_table[Category],$R3,dis_table[Date],X$1) -> 19.99 | Y3: =SUMIFS(dis_table[Amount],dis_table[Category],$R3,dis_table[Date],Y$1) -> 7.99 | Z3: =SUMIFS(dis_table[Amount],dis_table[Category],$R3,dis_table[Date],Z$1) -> 49 | ... AD3: =SUMIFS(dis_table[Amount],dis_table[Category],$R3,dis_table[Date],AD$1) -> 0
A4: 2 | B4: =MONTH(dis_table[[#This Row],[Date]]) -> 1 | C4: 44927 | D4: 44929 | E4: NETFLIX.COM NETFLIX.COM CAITEM TRANSFERRED FROM PREV ACCOUNT | F4: 10.59 | G4: Merchandise | H4: netflix | I4: Yes | J4: Recreation_Entertainment | K4: 44927 | L4: 2023 | M4: 44927 | N4: 593.08 | O4: 1 | Q4: 0 | R4: Gasoline | S4: =SUMIFS(dis_table[Amount],dis_table[Category],$R4,dis_table[Date],S$1) -> 132.49 | T4: =SUMIFS(dis_table[Amount],dis_table[Category],$R4,dis_table[Date],T$1) -> 15.5 | U4: =SUMIFS(dis_table[Amount],dis_table[Category],$R4,dis_table[Date],U$1) -> 99.56 | V4: =SUMIFS(dis_table[Amount],dis_table[Category],$R4,dis_table[Date],V$1) -> 148.38 | W4: =SUMIFS(dis_table[Amount],dis_table[Category],$R4,dis_table[Date],W$1) -> 161.57 | X4: =SUMIFS(dis_table[Amount],dis_table[Category],$R4,dis_table[Date],X$1) -> 0 | Y4: =SUMIFS(dis_table[Amount],dis_table[Category],$R4,dis_table[Date],Y$1) -> 0 | Z4: =SUMIFS(dis_table[Amount],dis_table[Category],$R4,dis_table[Date],Z$1) -> 2100.1 | ... AD4: =SUMIFS(dis_table[Amount],dis_table[Category],$R4,dis_table[Date],AD$1) -> 50.16
A5: 3 | B5: =MONTH(dis_table[[#This Row],[Date]]) -> 1 | C5: 44927 | D5: 44929 | E5: SAFEWAY #1547 BURLINGAME CA | F5: 34.46 | G5: Supermarkets | H5: groceries | I5: No | J5: Food | K5: 44927 | L5: 2023 | M5: 44927 | N5: 627.54 | O5: 1 | R5: Government Services | S5: =SUMIFS(dis_table[Amount],dis_table[Category],$R5,dis_table[Date],S$1) -> 260.36 | T5: =SUMIFS(dis_table[Amount],dis_table[Category],$R5,dis_table[Date],T$1) -> 0 | U5: =SUMIFS(dis_table[Amount],dis_table[Category],$R5,dis_table[Date],U$1) -> 17.1 | V5: =SUMIFS(dis_table[Amount],dis_table[Category],$R5,dis_table[Date],V$1) -> 16.94 | W5: =SUMIFS(dis_table[Amount],dis_table[Category],$R5,dis_table[Date],W$1) -> 80.75 | X5: =SUMIFS(dis_table[Amount],dis_table[Category],$R5,dis_table[Date],X$1) -> 46.33 | Y5: =SUMIFS(dis_table[Amount],dis_table[Category],$R5,dis_table[Date],Y$1) -> 0 | Z5: =SUMIFS(dis_table[Amount],dis_table[Category],$R5,dis_table[Date],Z$1) -> 0 | ... AD5: =SUMIFS(dis_table[Amount],dis_table[Category],$R5,dis_table[Date],AD$1) -> 0
A6: 4 | B6: =MONTH(dis_table[[#This Row],[Date]]) -> 1 | C6: 44928 | D6: 44929 | E6: KRYSTAL AND SAAGAR 2025317527 DCITEM TRANSFERRED FROM PREV ACCOUNT | F6: 10 | G6: Merchandise | H6: breaking_points | I6: Yes | J6: Recreation_Entertainment | K6: 44927 | L6: 2023 | M6: 44928 | N6: 637.54 | O6: 1 | R6: Home Improvement | S6: =SUMIFS(dis_table[Amount],dis_table[Category],$R6,dis_table[Date],S$1) -> 0 | T6: =SUMIFS(dis_table[Amount],dis_table[Category],$R6,dis_table[Date],T$1) -> 0 | U6: =SUMIFS(dis_table[Amount],dis_table[Category],$R6,dis_table[Date],U$1) -> 0 | V6: =SUMIFS(dis_table[Amount],dis_table[Category],$R6,dis_table[Date],V$1) -> 23.91 | W6: =SUMIFS(dis_table[Amount],dis_table[Category],$R6,dis_table[Date],W$1) -> 0 | X6: =SUMIFS(dis_table[Amount],dis_table[Category],$R6,dis_table[Date],X$1) -> 0 | Y6: =SUMIFS(dis_table[Amount],dis_table[Category],$R6,dis_table[Date],Y$1) -> 0 | Z6: =SUMIFS(dis_table[Amount],dis_table[Category],$R6,dis_table[Date],Z$1) -> 0 | ... AD6: =SUMIFS(dis_table[Amount],dis_table[Category],$R6,dis_table[Date],AD$1) -> 0
A7: 5 | B7: =MONTH(dis_table[[#This Row],[Date]]) -> 1 | C7: 44928 | D7: 44929 | E7: OBSIDIAN.MD 2262203323 CAN | F7: 10 | G7: Merchandise | H7: obsidian | I7: Yes | J7: Personal_Spending | K7: 44927 | L7: 2023 | M7: 44928 | N7: 647.54 | O7: 1 | R7: Interest | S7: =SUMIFS(dis_table[Amount],dis_table[Category],$R7,dis_table[Date],S$1) -> 0 | T7: =SUMIFS(dis_table[Amount],dis_table[Category],$R7,dis_table[Date],T$1) -> 0 | U7: =SUMIFS(dis_table[Amount],dis_table[Category],$R7,dis_table[Date],U$1) -> 0 | V7: =SUMIFS(dis_table[Amount],dis_table[Category],$R7,dis_table[Date],V$1) -> 0 | W7: =SUMIFS(dis_table[Amount],dis_table[Category],$R7,dis_table[Date],W$1) -> 0 | X7: =SUMIFS(dis_table[Amount],dis_table[Category],$R7,dis_table[Date],X$1) -> 0 | Y7: =SUMIFS(dis_table[Amount],dis_table[Category],$R7,dis_table[Date],Y$1) -> 0 | Z7: =SUMIFS(dis_table[Amount],dis_table[Category],$R7,dis_table[Date],Z$1) -> 0 | ... AD7: =SUMIFS(dis_table[Amount],dis_table[Category],$R7,dis_table[Date],AD$1) -> 0
A8: 6 | B8: =MONTH(dis_table[[#This Row],[Date]]) -> 1 | C8: 44929 | D8: 44929 | E8: A PLUS DENTAL CENTER - S SAN MATEO CA | F8: 549.6 | G8: Medical Services | H8: dental | I8: No | J8: Medical | K8: 44927 | L8: 2023 | M8: 44929 | N8: 1197.14 | O8: 1 | R8: Medical Services | S8: =SUMIFS(dis_table[Amount],dis_table[Category],$R8,dis_table[Date],S$1) -> 656.1 | T8: =SUMIFS(dis_table[Amount],dis_table[Category],$R8,dis_table[Date],T$1) -> 299.32 | U8: =SUMIFS(dis_table[Amount],dis_table[Category],$R8,dis_table[Date],U$1) -> 1174.21 | V8: =SUMIFS(dis_table[Amount],dis_table[Category],$R8,dis_table[Date],V$1) -> 66.53 | W8: =SUMIFS(dis_table[Amount],dis_table[Category],$R8,dis_table[Date],W$1) -> 178.08 | X8: =SUMIFS(dis_table[Amount],dis_table[Category],$R8,dis_table[Date],X$1) -> 0 | Y8: =SUMIFS(dis_table[Amount],dis_table[Category],$R8,dis_table[Date],Y$1) -> 266.7 | Z8: =SUMIFS(dis_table[Amount],dis_table[Category],$R8,dis_table[Date],Z$1) -> 0 | ... AD8: =SUMIFS(dis_table[Amount],dis_table[Category],$R8,dis_table[Date],AD$1) -> 40.65
A9: 7 | B9: =MONTH(dis_table[[#This Row],[Date]]) -> 1 | C9: 44929 | D9: 44929 | E9: AMAZON.COM*7H1T34W33 AMZN.COM/BILLWA7CGLY7QDYF3 | F9: 42.12 | G9: Merchandise | H9: everything_store | I9: No | J9: Personal_Spending | K9: 44927 | L9: 2023 | M9: 44929 | N9: 1239.26 | O9: 1 | R9: Merchandise | S9: =SUMIFS(dis_table[Amount],dis_table[Category],$R9,dis_table[Date],S$1) -> 654.74 | T9: =SUMIFS(dis_table[Amount],dis_table[Category],$R9,dis_table[Date],T$1) -> 1246.36 | U9: =SUMIFS(dis_table[Amount],dis_table[Category],$R9,dis_table[Date],U$1) -> 1452.31 | V9: =SUMIFS(dis_table[Amount],dis_table[Category],$R9,dis_table[Date],V$1) -> 2083.87 | W9: =SUMIFS(dis_table[Amount],dis_table[Category],$R9,dis_table[Date],W$1) -> 2565.32 | X9: =SUMIFS(dis_table[Amount],dis_table[Category],$R9,dis_table[Date],X$1) -> 741.64 | Y9: =SUMIFS(dis_table[Amount],dis_table[Category],$R9,dis_table[Date],Y$1) -> 849.87 | Z9: =SUMIFS(dis_table[Amount],dis_table[Category],$R9,dis_table[Date],Z$1) -> 1024.45 | ... AD9: =SUMIFS(dis_table[Amount],dis_table[Category],$R9,dis_table[Date],AD$1) -> 1094.63
A10: 8 | B10: =MONTH(dis_table[[#This Row],[Date]]) -> 1 | C10: 44929 | D10: 44929 | E10: AUTOMATIC STATEMENT CREDIT | F10: -41.41 | G10: Awards and Rebate Credits | H10: credits | I10: No | J10: Payment_and_Interest | K10: 44927 | L10: 2023 | M10: 44929 | N10: 1197.85 | O10: 1 | R10: Restaurants | S10: =SUMIFS(dis_table[Amount],dis_table[Category],$R10,dis_table[Date],S$1) -> 318.3 | T10: =SUMIFS(dis_table[Amount],dis_table[Category],$R10,dis_table[Date],T$1) -> 657.48 | U10: =SUMIFS(dis_table[Amount],dis_table[Category],$R10,dis_table[Date],U$1) -> 482.18 | V10: =SUMIFS(dis_table[Amount],dis_table[Category],$R10,dis_table[Date],V$1) -> 270.53 | W10: =SUMIFS(dis_table[Amount],dis_table[Category],$R10,dis_table[Date],W$1) -> 556.46 | X10: =SUMIFS(dis_table[Amount],dis_table[Category],$R10,dis_table[Date],X$1) -> 41.37 | Y10: =SUMIFS(dis_table[Amount],dis_table[Category],$R10,dis_table[Date],Y$1) -> 62.19 | Z10: =SUMIFS(dis_table[Amount],dis_table[Category],$R10,dis_table[Date],Z$1) -> 337.29 | ... AD10: =SUMIFS(dis_table[Amount],dis_table[Category],$R10,dis_table[Date],AD$1) -> 543.97
A11: 9 | B11: =MONTH(dis_table[[#This Row],[Date]]) -> 1 | C11: 44929 | D11: 44929 | E11: CAMINO PETROLEUM S SAN FRANCISCA | F11: 40.96 | G11: Gasoline | H11: gas_station | I11: No | J11: Transportation | K11: 44927 | L11: 2023 | M11: 44929 | N11: 1238.81 | O11: 1 | R11: Services | S11: =SUMIFS(dis_table[Amount],dis_table[Category],$R11,dis_table[Date],S$1) -> 473.35 | T11: =SUMIFS(dis_table[Amount],dis_table[Category],$R11,dis_table[Date],T$1) -> 474.01 | U11: =SUMIFS(dis_table[Amount],dis_table[Category],$R11,dis_table[Date],U$1) -> 658.3 | V11: =SUMIFS(dis_table[Amount],dis_table[Category],$R11,dis_table[Date],V$1) -> 648.06 | W11: =SUMIFS(dis_table[Amount],dis_table[Category],$R11,dis_table[Date],W$1) -> 680.7 | X11: =SUMIFS(dis_table[Amount],dis_table[Category],$R11,dis_table[Date],X$1) -> 454.36 | Y11: =SUMIFS(dis_table[Amount],dis_table[Category],$R11,dis_table[Date],Y$1) -> 327.09 | Z11: =SUMIFS(dis_table[Amount],dis_table[Category],$R11,dis_table[Date],Z$1) -> 295.82 | ... AD11: =SUMIFS(dis_table[Amount],dis_table[Category],$R11,dis_table[Date],AD$1) -> 340.36
A12: 10 | B12: =MONTH(dis_table[[#This Row],[Date]]) -> 1 | C12: 44929 | D12: 44929 | E12: GOOGLE *YT PRIMETIME G.CO/HELPPAY#CAP0OW57KF | F12: 15.89 | G12: Services | H12: youtube_tv | I12: Yes | J12: Recreation_Entertainment | K12: 44927 | L12: 2023 | M12: 44929 | N12: 1254.7 | O12: 1 | R12: Supermarkets | S12: =SUMIFS(dis_table[Amount],dis_table[Category],$R12,dis_table[Date],S$1) -> 204.34 | T12: =SUMIFS(dis_table[Amount],dis_table[Category],$R12,dis_table[Date],T$1) -> 423.11 | U12: =SUMIFS(dis_table[Amount],dis_table[Category],$R12,dis_table[Date],U$1) -> 443.98 | V12: =SUMIFS(dis_table[Amount],dis_table[Category],$R12,dis_table[Date],V$1) -> 551.59 | W12: =SUMIFS(dis_table[Amount],dis_table[Category],$R12,dis_table[Date],W$1) -> 866.32 | X12: =SUMIFS(dis_table[Amount],dis_table[Category],$R12,dis_table[Date],X$1) -> 103.69 | Y12: =SUMIFS(dis_table[Amount],dis_table[Category],$R12,dis_table[Date],Y$1) -> 558.17 | Z12: =SUMIFS(dis_table[Amount],dis_table[Category],$R12,dis_table[Date],Z$1) -> 335.62 | ... AD12: =SUMIFS(dis_table[Amount],dis_table[Category],$R12,dis_table[Date],AD$1) -> 488.47
A13: 11 | B13: =MONTH(dis_table[[#This Row],[Date]]) -> 1 | C13: 44929 | D13: 44929 | E13: TACO BELL 30785 SOUTH SAN FRACA | F13: 7.13 | G13: Restaurants | H13: fast_food | I13: No | J13: Food | K13: 44927 | L13: 2023 | M13: 44929 | N13: 1261.83 | O13: 1 | R13: Travel/ Entertainment | S13: =SUMIFS(dis_table[Amount],dis_table[Category],$R13,dis_table[Date],S$1) -> 1624.06 | T13: =SUMIFS(dis_table[Amount],dis_table[Category],$R13,dis_table[Date],T$1) -> 583.99 | U13: =SUMIFS(dis_table[Amount],dis_table[Category],$R13,dis_table[Date],U$1) -> 461.24 | V13: =SUMIFS(dis_table[Amount],dis_table[Category],$R13,dis_table[Date],V$1) -> 345.46 | W13: =SUMIFS(dis_table[Amount],dis_table[Category],$R13,dis_table[Date],W$1) -> 1384.17 | X13: =SUMIFS(dis_table[Amount],dis_table[Category],$R13,dis_table[Date],X$1) -> 98.77 | Y13: =SUMIFS(dis_table[Amount],dis_table[Category],$R13,dis_table[Date],Y$1) -> 110.16 | Z13: =SUMIFS(dis_table[Amount],dis_table[Category],$R13,dis_table[Date],Z$1) -> 267.02 | ... AD13: =SUMIFS(dis_table[Amount],dis_table[Category],$R13,dis_table[Date],AD$1) -> 690.38
A14: 12 | B14: =MONTH(dis_table[[#This Row],[Date]]) -> 1 | C14: 44929 | D14: 44929 | E14: WALGREENS #3346 S SAN FRAN CA | F14: 27.15 | G14: Merchandise | H14: conv_store | I14: No | J14: Personal_Spending | K14: 44927 | L14: 2023 | M14: 44929 | N14: 1288.98 | O14: 1 | R14: Balance | S14: =SUMIFS(dis_table[Amount],dis_table[Category],$R14,dis_table[Date],S$1) -> 577.5 | T14: =SUMIFS(dis_table[Amount],dis_table[Category],$R14,dis_table[Date],T$1) -> 0 | U14: =SUMIFS(dis_table[Amount],dis_table[Category],$R14,dis_table[Date],U$1) -> 0 | V14: =SUMIFS(dis_table[Amount],dis_table[Category],$R14,dis_table[Date],V$1) -> 0 | W14: =SUMIFS(dis_table[Amount],dis_table[Category],$R14,dis_table[Date],W$1) -> 0 | X14: =SUMIFS(dis_table[Amount],dis_table[Category],$R14,dis_table[Date],X$1) -> 0 | Y14: =SUMIFS(dis_table[Amount],dis_table[Category],$R14,dis_table[Date],Y$1) -> 0 | Z14: =SUMIFS(dis_table[Amount],dis_table[Category],$R14,dis_table[Date],Z$1) -> 0 | ... AD14: =SUMIFS(dis_table[Amount],dis_table[Category],$R14,dis_table[Date],AD$1) -> 0
A15: 13 | B15: =MONTH(dis_table[[#This Row],[Date]]) -> 1 | C15: 44930 | D15: 44930 | E15: COURSRA5IM7YPM1EY6M1D 650-963-9884 CA | F15: 49 | G15: Education | H15: coursera | I15: Yes | J15: Personal_Spending | K15: 44927 | L15: 2023 | M15: 44930 | N15: 1337.98 | O15: 1 | R15: Payments and Credits | S15: =SUMIFS(dis_table[Amount],dis_table[Category],$R15,dis_table[Date],S$1) -> -3624.11 | T15: =SUMIFS(dis_table[Amount],dis_table[Category],$R15,dis_table[Date],T$1) -> -4427.6 | U15: =SUMIFS(dis_table[Amount],dis_table[Category],$R15,dis_table[Date],U$1) -> -3761.69 | V15: =SUMIFS(dis_table[Amount],dis_table[Category],$R15,dis_table[Date],V$1) -> -4428.21 | W15: =SUMIFS(dis_table[Amount],dis_table[Category],$R15,dis_table[Date],W$1) -> -7363.89 | X15: =SUMIFS(dis_table[Amount],dis_table[Category],$R15,dis_table[Date],X$1) -> -2487.02 | Y15: =SUMIFS(dis_table[Amount],dis_table[Category],$R15,dis_table[Date],Y$1) -> -2781.25 | Z15: =SUMIFS(dis_table[Amount],dis_table[Category],$R15,dis_table[Date],Z$1) -> -3027.93 | ... AD15: =SUMIFS(dis_table[Amount],dis_table[Category],$R15,dis_table[Date],AD$1) -> -5279.76
A16: 14 | B16: =MONTH(dis_table[[#This Row],[Date]]) -> 1 | C16: 44930 | D16: 44930 | E16: EXTRA SPACE 1461 BURLINGAME CA | F16: 241.6 | G16: Services | H16: moving | I16: No | J16: Misc | K16: 44927 | L16: 2023 | M16: 44930 | N16: 1579.58 | O16: 1 | R16: Awards and Rebate Credits | S16: =SUMIFS(dis_table[Amount],dis_table[Category],$R16,dis_table[Date],S$1) -> -41.41 | T16: =SUMIFS(dis_table[Amount],dis_table[Category],$R16,dis_table[Date],T$1) -> -55.37 | U16: =SUMIFS(dis_table[Amount],dis_table[Category],$R16,dis_table[Date],U$1) -> -47.46 | V16: =SUMIFS(dis_table[Amount],dis_table[Category],$R16,dis_table[Date],V$1) -> -57.91 | W16: =SUMIFS(dis_table[Amount],dis_table[Category],$R16,dis_table[Date],W$1) -> -46.32 | X16: =SUMIFS(dis_table[Amount],dis_table[Category],$R16,dis_table[Date],X$1) -> -80.78 | Y16: =SUMIFS(dis_table[Amount],dis_table[Category],$R16,dis_table[Date],Y$1) -> -17.19 | Z16: =SUMIFS(dis_table[Amount],dis_table[Category],$R16,dis_table[Date],Z$1) -> -24.69 | ... AD16: =SUMIFS(dis_table[Amount],dis_table[Category],$R16,dis_table[Date],AD$1) -> -53.36
A17: 15 | B17: =MONTH(dis_table[[#This Row],[Date]]) -> 1 | C17: 44930 | D17: 44930 | E17: STATE FARM INSURANCE 800-956-6310 ILITEM TRANSFERRED FROM PREV ACCOUNT | F17: 90.09 | G17: Merchandise | H17: state_farm | I17: Yes | J17: Insurance | K17: 44927 | L17: 2023 | M17: 44930 | N17: 1669.67 | O17: 1
A18: 16 | B18: =MONTH(dis_table[[#This Row],[Date]]) -> 1 | C18: 44931 | D18: 44931 | E18: SQ *LOVE BURN CHICKEN SOUTH SAN FRACA0001152921512348130249 | F18: 36.26 | G18: Restaurants | H18: restaurant | I18: No | J18: Food | K18: 44927 | L18: 2023 | M18: 44931 | N18: 1705.93 | O18: 1 | S18: 01/2022 | T18: 44958 | U18: 44986 | V18: 45017 | W18: 45047 | X18: 45078 | Y18: 45108 | Z18: 45139 | AA18: 45170 | AB18: 45200 | AC18: 45231 | AD18: 45261
A19: 17 | B19: =MONTH(dis_table[[#This Row],[Date]]) -> 1 | C19: 44931 | D19: 44931 | E19: AMZN MKTP US*RZ4YB1HY3 AMZN.COM/BILLWA2IAOP636RTD | F19: 54.8 | G19: Merchandise | H19: amazon | I19: No | J19: Personal_Spending | K19: 44927 | L19: 2023 | M19: 44931 | N19: 1760.73 | O19: 1 | R19: =R14 -> Balance | S19: =N2 -> 577.5 | T19: =INDEX($K:$N,MATCH(T$18,$K:$K,0),4) -> 1320.03 | U19: =INDEX($K:$N,MATCH(U$18,$K:$K,0),4) -> 906.4 | V19: =INDEX($K:$N,MATCH(V$18,$K:$K,0),4) -> 2435.1 | W19: =INDEX($K:$N,MATCH(W$18,$K:$K,0),4) -> 2104.25 | X19: =INDEX($K:$N,MATCH(X$18,$K:$K,0),4) -> 2224.9 | Y19: =INDEX($K:$N,MATCH(Y$18,$K:$K,0),4) -> 1178.25 | Z19: =INDEX($K:$N,MATCH(Z$18,$K:$K,0),4) -> 546.98 | AA19: =INDEX($K:$N,MATCH(AA$18,$K:$K,0),4) -> 1918.66 | ... AD19: =INDEX($K:$N,MATCH(AD$18,$K:$K,0),4) -> 2244.61
A20: 18 | B20: =MONTH(dis_table[[#This Row],[Date]]) -> 1 | C20: 44931 | D20: 44931 | E20: AMAZON.COM*533DL0GN3 AMZN.COM/BILLWA656UQI8895R | F20: 13.85 | G20: Merchandise | H20: everything_store | I20: No | J20: Personal_Spending | K20: 44927 | L20: 2023 | M20: 44931 | N20: 1774.58 | O20: 2 | R20: =R15 -> Payments and Credits | S20: =S15*-1 -> 3624.11 | T20: =T15*-1 -> 4427.6 | U20: =U15*-1 -> 3761.69 | V20: =V15*-1 -> 4428.21 | W20: =W15*-1 -> 7363.89 | X20: =X15*-1 -> 2487.02 | Y20: =Y15*-1 -> 2781.25 | Z20: =Z15*-1 -> 3027.93 | ... AD20: =AD15*-1 -> 5279.76
A21: 19 | B21: =MONTH(dis_table[[#This Row],[Date]]) -> 1 | C21: 44932 | D21: 44932 | E21: APPLE.COM/BILL 111-111-1111 CA | F21: 9.99 | G21: Merchandise | H21: apple_care | I21: Yes | J21: Personal_Spending | K21: 44927 | L21: 2023 | M21: 44932 | N21: 1784.57 | O21: 1
A22: 20 | B22: =MONTH(dis_table[[#This Row],[Date]]) -> 1 | C22: 44932 | D22: 44932 | E22: LYFT *2 RIDES 01-04 855-865-9553 CAITEM TRANSFERRED FROM PREV ACCOUNT | F22: 24.59 | G22: Merchandise | H22: ride_share | I22: No | J22: Transportation | K22: 44927 | L22: 2023 | M22: 44932 | N22: 1809.16 | O22: 1
A23: 21 | B23: =MONTH(dis_table[[#This Row],[Date]]) -> 1 | C23: 44933 | D23: 44933 | E23: SEE TICKETS *FRED ARMISE 323-908-0607 CASEE TICKETS *FRED ARMISE | F23: 102.02 | G23: Travel/ Entertainment | H23: jewelry | I23: No | J23: Personal_Spending | K23: 44927 | L23: 2023 | M23: 44933 | N23: 1911.18 | O23: 1 | R23: 0
A24: 22 | B24: =MONTH(dis_table[[#This Row],[Date]]) -> 1 | C24: 44933 | D24: 44933 | E24: SQ *HILARY CHIEM, O.D. SAN MATEO CA0001152921512353344153 | F24: 106.5 | G24: Medical Services | H24: vision | I24: No | J24: Medical | K24: 44927 | L24: 2023 | M24: 44933 | N24: 2017.68 | O24: 1
A25: 23 | B25: =MONTH(dis_table[[#This Row],[Date]]) -> 1 | C25: 44934 | D25: 44934 | E25: LYFT *2 RIDES 01-07 855-865-9553 CAITEM TRANSFERRED FROM PREV ACCOUNT | F25: 28.67 | G25: Merchandise | H25: ride_share | I25: No | J25: Transportation | K25: 44927 | L25: 2023 | M25: 44934 | N25: 2046.35 | O25: 2
A26: 24 | B26: =MONTH(dis_table[[#This Row],[Date]]) -> 1 | C26: 44935 | D26: 44935 | E26: STEAM PURCHASE 425-952-2985 WA | F26: 29.99 | G26: Travel/ Entertainment | H26: video_games | I26: No | J26: Recreation_Entertainment | K26: 44927 | L26: 2023 | M26: 44935 | N26: 2076.34 | O26: 1
A27: 25 | B27: =MONTH(dis_table[[#This Row],[Date]]) -> 1 | C27: 44935 | D27: 44935 | E27: GOOGLE *YOUTUBE TV G.CO/HELPPAY#CAP0OFLGPQ | F27: 64.99 | G27: Services | H27: youtube_tv | I27: Yes | J27: Recreation_Entertainment | K27: 44927 | L27: 2023 | M27: 44935 | N27: 2141.33 | O27: 2
A28: 26 | B28: =MONTH(dis_table[[#This Row],[Date]]) -> 1 | C28: 44935 | D28: 44935 | E28: AMZN MKTP US*O74QU7HY3 AMZN.COM/BILLWA77RIRA85W99 | F28: 9.86 | G28: Merchandise | H28: amazon | I28: No | J28: Personal_Spending | K28: 44927 | L28: 2023 | M28: 44935 | N28: 2151.19 | O28: 2
A29: 27 | B29: =MONTH(dis_table[[#This Row],[Date]]) -> 1 | C29: 44935 | D29: 44935 | E29: AMZN MKTP US*P98A92243 AMZN.COM/BILLWA1F2157UKMEK | F29: 32.88 | G29: Merchandise | H29: amazon | I29: No | J29: Personal_Spending | K29: 44927 | L29: 2023 | M29: 44935 | N29: 2184.07 | O29: 3
A30: 28 | B30: =MONTH(dis_table[[#This Row],[Date]]) -> 1 | C30: 44936 | D30: 44936 | E30: LYFT *1 RIDE 01-08 855-865-9553 CAITEM TRANSFERRED FROM PREV ACCOUNT | F30: 11.99 | G30: Merchandise | H30: ride_share | I30: No | J30: Transportation | K30: 44927 | L30: 2023 | M30: 44936 | N30: 2196.06 | O30: 3
A31: 29 | B31: =MONTH(dis_table[[#This Row],[Date]]) -> 1 | C31: 44936 | D31: 44936 | E31: PANDA EXPRESS #907 P 800-877-8988 CA | F31: 10.85 | G31: Restaurants | H31: fast_food | I31: No | J31: Food | K31: 44927 | L31: 2023 | M31: 44936 | N31: 2206.91 | O31: 2
A32: 30 | B32: =MONTH(dis_table[[#This Row],[Date]]) -> 1 | C32: 44937 | D32: 44937 | E32: TRAVEL GUARD GROUP INC 877-934-8308 WI | F32: 21.91 | G32: Services | H32: air_travel | I32: No | J32: Transportation | K32: 44927 | L32: 2023 | M32: 44937 | N32: 2228.82 | O32: 1
A33: 31 | B33: =MONTH(dis_table[[#This Row],[Date]]) -> 1 | C33: 44937 | D33: 44937 | E33: APPLE.COM/BILL 866-712-7753 CAAPPLE PAY ENDING IN 1455MMWBZ5629BA0 | F33: 15.89 | G33: Merchandise | H33: hbo | I33: Yes | J33: Recreation_Entertainment | K33: 44927 | L33: 2023 | M33: 44937 | N33: 2244.71 | O33: 1
A34: 32 | B34: =MONTH(dis_table[[#This Row],[Date]]) -> 1 | C34: 44937 | D34: 44937 | E34: EB OPEN MIKE EAGLEES 801-413-7200 CA | F34: 24.97 | G34: Services | H34: fast_food | I34: No | J34: Food | K34: 44927 | L34: 2023 | M34: 44937 | N34: 2269.68 | O34: 3
A35: 33 | B35: =MONTH(dis_table[[#This Row],[Date]]) -> 1 | C35: 44937 | D35: 44937 | E35: INTERNET PAYMENT - THANK YOU | F35: -552.53 | G35: Payments and Credits | H35: payment | I35: No | J35: Payment_and_Interest | K35: 44927 | L35: 2023 | M35: 44937 | N35: 1717.15 | O35: 1
... A84: 82 | B84: =MONTH(dis_table[[#This Row],[Date]]) -> 1 | C84: 44955 | D84: 44955 | E84: UBER TRIP 866-576-1039 CA | F84: 5 | G84: Travel/ Entertainment | H84: ride_share | I84: No | J84: Transportation | K84: 44927 | L84: 2023 | M84: 44955 | N84: 895.69 | O84: 11
A85: 83 | B85: =MONTH(dis_table[[#This Row],[Date]]) -> 1 | C85: 44955 | D85: 44955 | E85: SQ *BORDER X BREWING- SAN DIEGO CA0001152921512418764739 | F85: 12.16 | G85: Restaurants | H85: restaurant | I85: No | J85: Food | K85: 44927 | L85: 2023 | M85: 44955 | N85: 907.85 | O85: 7 | Q85: =0 -> 0
A86: 84 | B86: =MONTH(dis_table[[#This Row],[Date]]) -> 1 | C86: 44955 | D86: 44955 | E86: SQ *NEVERIA LOS MOCHIS SAN DIEGO CA0001152921512419051683 | F86: 11.75 | G86: Restaurants | H86: restaurant | I86: No | J86: Food | K86: 44927 | L86: 2023 | M86: 44955 | N86: 919.6 | O86: 8
A87: 85 | B87: =MONTH(dis_table[[#This Row],[Date]]) -> 1 | C87: 44955 | D87: 44955 | E87: SWAMIS NORTH PARK SAN DIEGO CA | F87: 31.22 | G87: Restaurants | H87: restaurant | I87: No | J87: Food | K87: 44927 | L87: 2023 | M87: 44955 | N87: 950.82 | O87: 9
A88: 86 | B88: =MONTH(dis_table[[#This Row],[Date]]) -> 1 | C88: 44956 | D88: 44956 | E88: UBER TRIP 866-576-1039 CA | F88: 5 | G88: Travel/ Entertainment | H88: ride_share | I88: No | J88: Transportation | K88: 44927 | L88: 2023 | M88: 44956 | N88: 955.82 | O88: 12
A89: 87 | B89: =MONTH(dis_table[[#This Row],[Date]]) -> 1 | C89: 44956 | D89: 44956 | E89: WWW.WEWORK.COM 6467604450 NY | F89: 29 | G89: Services | H89: professional | I89: No | J89: Personal_Spending | K89: 44927 | L89: 2023 | M89: 44956 | N89: 984.82 | O89: 1
A90: 88 | B90: =MONTH(dis_table[[#This Row],[Date]]) -> 1 | C90: 44956 | D90: 44956 | E90: UBER TRIP 866-576-1039 CA | F90: 22.04 | G90: Travel/ Entertainment | H90: ride_share | I90: No | J90: Transportation | K90: 44927 | L90: 2023 | M90: 44956 | N90: 1006.86 | O90: 13
A91: 89 | B91: =MONTH(dis_table[[#This Row],[Date]]) -> 1 | C91: 44956 | D91: 44956 | E91: UBER TRIP 866-576-1039 CA | F91: 8.66 | G91: Travel/ Entertainment | H91: ride_share | I91: No | J91: Transportation | K91: 44927 | L91: 2023 | M91: 44956 | N91: 1015.52 | O91: 14
A92: 90 | B92: =MONTH(dis_table[[#This Row],[Date]]) -> 1 | C92: 44956 | D92: 44956 | E92: UBER TRIP 866-576-1039 CA | F92: 3.28 | G92: Travel/ Entertainment | H92: ride_share | I92: No | J92: Transportation | K92: 44927 | L92: 2023 | M92: 44956 | N92: 1018.8 | O92: 15
A93: 91 | B93: =MONTH(dis_table[[#This Row],[Date]]) -> 1 | C93: 44956 | D93: 44956 | E93: SQ *SANDBOX VR MISSION GOSQ.COM CA0002305843016976425532 | F93: 150 | G93: Travel/ Entertainment | H93: vr_arcade | I93: No | J93: Recreation_Entertainment | K93: 44927 | L93: 2023 | M93: 44956 | N93: 1168.8 | O93: 1
A94: 92 | B94: =MONTH(dis_table[[#This Row],[Date]]) -> 1 | C94: 44956 | D94: 44956 | E94: TST* SMOKING GUN - SAN SAN DIEGO CA00013131010229654110AA | F94: 8.52 | G94: Restaurants | H94: restaurant | I94: No | J94: Food | K94: 44927 | L94: 2023 | M94: 44956 | N94: 1177.32 | O94: 10
A95: 93 | B95: =MONTH(dis_table[[#This Row],[Date]]) -> 1 | C95: 44956 | D95: 44956 | E95: CCBILL.COM 888-5969279 AZ | F95: 12.76 | G95: Merchandise | H95: onlyfans | I95: No | J95: Recreation_Entertainment | K95: 44927 | L95: 2023 | M95: 44956 | N95: 1190.08 | O95: 2
A96: 94 | B96: =MONTH(dis_table[[#This Row],[Date]]) -> 1 | C96: 44956 | D96: 44956 | E96: CCBILL.COM 888-5969279 AZ | F96: 7.43 | G96: Merchandise | H96: onlyfans | I96: No | J96: Recreation_Entertainment | K96: 44927 | L96: 2023 | M96: 44956 | N96: 1197.51 | O96: 3
A97: 95 | B97: =MONTH(dis_table[[#This Row],[Date]]) -> 1 | C97: 44956 | D97: 44956 | E97: TST* TACO STAND DOWNTO SAN DIEGO CA00072507010231353549AA | F97: 28.35 | G97: Restaurants | H97: fast_food | I97: No | J97: Food | K97: 44927 | L97: 2023 | M97: 44956 | N97: 1225.86 | O97: 7
... A1155: 1153 | B1155: =MONTH(dis_table[[#This Row],[Date]]) -> 12 | C1155: 45291 | D1155: 45291 | E1155: SQ *ZAREEN'S RESTAURAN REDWOOD CITY CA0001152921513549215564 | F1155: 84.34 | G1155: Restaurants | H1155: restaurant | I1155: No | J1155: Food | K1155: 45261 | L1155: 2023 | M1155: 45291 | N1155: 257.7 | O1155: 121

Sheet Care_Credit
A1: Month | B1: Transaction Date | C1: Description2 | D1: Amount | E1: Cumulative | F1: incremental | G1: Short_Desc | H1: Category_2
A2: =MONTH(sofiS_table8[[#This Row],[Transaction Date]]) -> 5 | B2: 45062 | C2: 5548077486132SF6W NORTH PENINSULA PODIAT SAN BRUNO CA | D2: 525
A3: =MONTH(sofiS_table8[[#This Row],[Transaction Date]]) -> 5 | B3: 45074 | C3: 15136004L8YXE532B RESTAURANT AQUAR PARIS FR | D3: 8.61
A4: =MONTH(sofiS_table8[[#This Row],[Transaction Date]]) -> 5 | B4: 45074 | C4: 15136004M8YXDL17F PERLE PARMENTIER PARIS FR | D4: 8.66
A5: =MONTH(sofiS_table8[[#This Row],[Transaction Date]]) -> 5 | B5: 45074 | C5: 75131824M532HY8J8 CULTURESPACES PARIS 8 FR | D5: 21.41 | E5: s
A6: =MONTH(sofiS_table8[[#This Row],[Transaction Date]]) -> 5 | B6: 45074 | C6: 05135064M598NA6Q8 LE CAFE DES VEDE PARIS FR | D6: 5.38
A7: =MONTH(sofiS_table8[[#This Row],[Transaction Date]]) -> 5 | B7: 45075 | C7: 75542354M8THNPG98 FFT PARIS FR | D7: 77.35 | E7: s
A8: =MONTH(sofiS_table8[[#This Row],[Transaction Date]]) -> 5 | B8: 45075 | C8: 15132494M36PNSPB0 MUSIAM16282STAR2 PARIS FR | D8: 9.15
A9: =MONTH(sofiS_table8[[#This Row],[Transaction Date]]) -> 5 | B9: 45075 | C9: 05130124N95Q3Y1FL RATP PARIS FR | D9: 20.55
A10: =MONTH(sofiS_table8[[#This Row],[Transaction Date]]) -> 5 | B10: 45075 | C10: 75139114N687R72XE ETS PUBLIC DU MUSEE DU PARIS 1 FR | D10: 5.38
A11: =MONTH(sofiS_table8[[#This Row],[Transaction Date]]) -> 5 | B11: 45077 | C11: 75468014P63LG1RF9 RENFE CERCANIAS TNA 08 BARCELONA ES | D11: 2.58
A12: =MONTH(sofiS_table8[[#This Row],[Transaction Date]]) -> 5 | B12: 45077 | C12: 75468014P63LTGAN5 RENFE CERCANIAS TNA 08 BARCELONA ES | D12: 2.58
A13: =MONTH(sofiS_table8[[#This Row],[Transaction Date]]) -> 5 | B13: 45077 | C13: 75260714P07KSPQ1V NEWREST WAGONS LITS FR PARIS FR | D13: 15.37
A14: =MONTH(sofiS_table8[[#This Row],[Transaction Date]]) -> 5 | B14: 45077 | C14: 15132494PR65W5A0X SM CASINO CS962 PARIS FR | D14: 7.4
A15: =MONTH(sofiS_table8[[#This Row],[Transaction Date]]) -> 5 | B15: 45077 | C15: 15132494PR65W5A27 SM CASINO CS962 PARIS FR | D15: 10.75
A16: =MONTH(sofiS_table8[[#This Row],[Transaction Date]]) -> 5 | B16: 45077 | C16: 05137004R95GRXMHZ GRIBAUDO PARIS 9 FR | D16: 10.75
A17: =MONTH(sofiS_table8[[#This Row],[Transaction Date]]) -> 5 | B17: 45077 | C17: 05133004P95FLD7Z6 OSSTINA PARIS FR | D17: 134.25 | E17: s
A18: =MONTH(sofiS_table8[[#This Row],[Transaction Date]]) -> 5 | B18: 45077 | C18: 85348124P01R9R8PH PAYMENT - THANK YOU | D18: -681.49 | E18: p
A19: =MONTH(sofiS_table8[[#This Row],[Transaction Date]]) -> 6 | B19: 45078 | C19: 75413114R0GYMAR67 SUPERMERCADO VIA LAIET BARCELONA ES | D19: 11.76
A20: =MONTH(sofiS_table8[[#This Row],[Transaction Date]]) -> 6 | B20: 45078 | C20: 75468014R63M425EP PULL AND BEAR NARON ES | D20: 75.25
A21: =MONTH(sofiS_table8[[#This Row],[Transaction Date]]) -> 6 | B21: 45078 | C21: 02709754RA1F2S7AG SQ *PRIMAVERA SOUND SL BARCELONA CT | D21: 11.83
A22: =MONTH(sofiS_table8[[#This Row],[Transaction Date]]) -> 6 | B22: 45079 | C22: 75402054T07KQXG01 MC DONALDS RONDA SANT BARCELONA ES | D22: 3.67
A23: =MONTH(sofiS_table8[[#This Row],[Transaction Date]]) -> 6 | B23: 45079 | C23: 75402054T07K6L5FE LCCB LHOSPITALET ES | D23: 12.91
A24: =MONTH(sofiS_table8[[#This Row],[Transaction Date]]) -> 6 | B24: 45079 | C24: 02709754TA1F8YGRT SQ *PRIMAVERA SOUND SL BARCELONA CT | D24: 3.76
A25: =MONTH(sofiS_table8[[#This Row],[Transaction Date]]) -> 6 | B25: 45086 | C25: PYMT CARD SECURITY 800-8154051 | D25: 5.03
A26: =MONTH(sofiS_table8[[#This Row],[Transaction Date]]) -> 6 | B26: 45090 | C26: 853481255GFRW8XE5 SCOTT HYVER VISIONCARE SANTA CLARA CA | D26: 5695
A27: =MONTH(sofiS_table8[[#This Row],[Transaction Date]]) -> 6 | B27: 45105 | C27: F8395005M000Q5001 ADJUSTMENT-PAYMENTS | D27: 178
A28: =MONTH(sofiS_table8[[#This Row],[Transaction Date]]) -> 6 | B28: 45105 | C28: 85348125L01SV1ZHH PAYMENT - THANK YOU | D28: -130 | E28: p
A29: =MONTH(sofiS_table8[[#This Row],[Transaction Date]]) -> 6 | B29: 45105 | C29: 85348125L01SV26AM PAYMENT - THANK YOU | D29: -178
A30: =MONTH(sofiS_table8[[#This Row],[Transaction Date]]) -> 7 | B30: 45108 | C30: 85348125P01V6FE46 PAYMENT - THANK YOU | D30: -178 | E30: p
A31: =MONTH(sofiS_table8[[#This Row],[Transaction Date]]) -> 7 | B31: 45117 | C31: Rewards Statement Credit | D31: -250 | E31: p
A32: =MONTH(sofiS_table8[[#This Row],[Transaction Date]]) -> 7 | B32: 45117 | C32: Pymt Card Security x-x4051 | D32: -90.39 | E32: p
A33: =MONTH(sofiS_table8[[#This Row],[Transaction Date]]) -> 7 | B33: 45133 | C33: Payment - Thank You | D33: -200 | E33: p
A34: =MONTH(sofiS_table8[[#This Row],[Transaction Date]]) -> 7 | B34: 45134 | C34: State of the Art Dental Grockville MD | D34: -1514.22 | G34: Don
A35: =MONTH(sofiS_table8[[#This Row],[Transaction Date]]) -> 8 | B35: 45148 | C35: Rewards Statement Credit | D35: 50
A36: =MONTH(sofiS_table8[[#This Row],[Transaction Date]]) -> 8 | B36: 45149 | C36: Payment - Thank You | D36: 130 | G36: Don
A37: =MONTH(sofiS_table8[[#This Row],[Transaction Date]]) -> 9 | B37: 45170 | C37: Automatic Payment - Thank You | D37: 91
A38: =MONTH(sofiS_table8[[#This Row],[Transaction Date]]) -> 9 | B38: 45175 | C38: Payment - Thank You | D38: 237.29 | E38: p
A39: =MONTH(sofiS_table8[[#This Row],[Transaction Date]]) -> 9 | B39: 45185 | C39: Target x8978 District Heigmd | D39: -214.11 | G39: Don

Sheet Best Buy
A1: Month | B1: Transaction Date | C1: Amount | D1: Description | E1: Category | F1: Short_Desc | G1: Category_2 | H1: Category_3
A2: =MONTH(bb_table[[#This Row],[Transaction Date]]) -> 3 | B2: 44994 | C2: -180.41 | D2: ONLINE PAYMENT DEERFIELD IL | E2: payment
A3: =MONTH(bb_table[[#This Row],[Transaction Date]]) -> 3 | B3: 44986 | C3: 180.41 | D3: BESTBUY.COM, 888-BESTBUY | E3: purchase | F3: shevon | G3: people
A4: =MONTH(bb_table[[#This Row],[Transaction Date]]) -> 3 | B4: 45005 | C4: 0 | D4: INTEREST CHARGE ON PURCHASES | E4: interest charged
A5: =MONTH(bb_table[[#This Row],[Transaction Date]]) -> 3 | B5: 45005 | C5: 0 | D5: INTEREST CHARGE ON CASH ADVANCES | E5: interest charged
A6: =MONTH(bb_table[[#This Row],[Transaction Date]]) -> 4 | B6: 45019 | C6: 40.83 | D6: BESTBUY.COM, 888-BESTBUY | E6: purchase
A7: =MONTH(bb_table[[#This Row],[Transaction Date]]) -> 4 | B7: 45020 | C7: 112.27 | D7: BESTBUY.COM, 888-BESTBUY | E7: purchase
A8: =MONTH(bb_table[[#This Row],[Transaction Date]]) -> 4 | B8: 45026 | C8: -153.1 | D8: ONLINE PAYMENT DEERFIELD IL | E8: payment
A9: =MONTH(bb_table[[#This Row],[Transaction Date]]) -> 4 | B9: 45029 | C9: 49.32 | D9: BESTBUY.COM, 888-BESTBUY | E9: purchase
A10: =MONTH(bb_table[[#This Row],[Transaction Date]]) -> 4 | B10: 45035 | C10: 0 | D10: INTEREST CHARGE ON CASH ADVANCES | E10: interest charged
A11: =MONTH(bb_table[[#This Row],[Transaction Date]]) -> 4 | B11: 45035 | C11: 0 | D11: INTEREST CHARGE ON PURCHASES | E11: interest charged
A12: =MONTH(bb_table[[#This Row],[Transaction Date]]) -> 4 | B12: 45042 | C12: -49.32 | D12: ONLINE PAYMENT DEERFIELD IL | E12: payment
A13: =MONTH(bb_table[[#This Row],[Transaction Date]]) -> 4 | B13: 45043 | C13: 393.74 | D13: BESTBUY.COM, 888-BESTBUY | E13: purchase
A14: =MONTH(bb_table[[#This Row],[Transaction Date]]) -> 5 | B14: 45057 | C14: 27.33 | D14: BESTBUY.COM, 888-BESTBUY | E14: purchase
A15: =MONTH(bb_table[[#This Row],[Transaction Date]]) -> 5 | B15: 45065 | C15: 0 | D15: INTEREST CHARGE ON CASH ADVANCES | E15: interest charged
... A18: =MONTH(bb_table[[#This Row],[Transaction Date]]) -> 5 | B18: 45067 | C18: -321.07 | D18: ONLINE PAYMENT DEERFIELD IL | E18: payment
A19: =MONTH(bb_table[[#This Row],[Transaction Date]]) -> 9 | B19: 45183 | C19: 1845.69 | D19: Bestbuy.com, 888-bestbuy | E19: purchase | H19: =bb_table[[#This Row],[Amount]]/12 -> 153.8075

Sheet American Express
A1: Date | B1: Description | C1: Amount
A2: 45154 | B2: Safeway #x 1547 Burlingame CA | C2: -84.02
A3: 45176 | B3: United Airlines Houston TX | C3: -377.15
A4: 45176 | B4: United Airlines Houston TX | C4: -10.65
A5: 45190 | B5: Safeway #x 1547 Burlingame CA | C5: -80.06

Sheet Vincent
A1: Month | B1: Transaction Date | C1: Description | D1: Amount | E1: Date of Item | F1: Category
A2: =MONTH(sofiS_table89[[#This Row],[Transaction Date]]) -> 1 | B2: 44927 | C2: Loan | D2: 5000 | E2: 43374
A3: =MONTH(sofiS_table89[[#This Row],[Transaction Date]]) -> 1 | B3: 44927 | C3: Loan | D3: 5032 | E3: 43678
A4: =MONTH(sofiS_table89[[#This Row],[Transaction Date]]) -> 1 | B4: 44927 | C4: Weddings | D4: 2629.34 | E4: 44775
A5: =MONTH(sofiS_table89[[#This Row],[Transaction Date]]) -> 1 | B5: 44927 | C5: Ga Tech | D5: 1757 | E5: 44792
A6: =MONTH(sofiS_table89[[#This Row],[Transaction Date]]) -> 1 | B6: 44927 | D6: -420 | E6: 44010 | F6: p
A7: =MONTH(sofiS_table89[[#This Row],[Transaction Date]]) -> 1 | B7: 44927 | D7: -150 | E7: 44036 | F7: p
A8: =MONTH(sofiS_table89[[#This Row],[Transaction Date]]) -> 4 | B8: 45017 | C8: One Pass | D8: -125.1 | F8: p
A9: =MONTH(sofiS_table89[[#This Row],[Transaction Date]]) -> 5 | B9: 45047 | C9: One Pass | D9: -125.1 | F9: p
A10: =MONTH(sofiS_table89[[#This Row],[Transaction Date]]) -> 6 | B10: 45078 | C10: One Pass | D10: -125.1 | F10: p
A11: =MONTH(sofiS_table89[[#This Row],[Transaction Date]]) -> 6 | B11: 45087 | C11: Pre Europe | D11: 1998.74 | E11: 45087
A12: =MONTH(sofiS_table89[[#This Row],[Transaction Date]]) -> 6 | B12: 45087 | C12: Europe | D12: 1987.73 | E12: 45087
A13: =MONTH(sofiS_table89[[#This Row],[Transaction Date]]) -> 6 | B13: 45092 | C13: Europe CC Split | D13: =SUMIFS(Care_Credit!$D:$D,Care_Credit!$E:$E,"s")/2*-1 -> -116.505 | E13: 45092 | F13: p
A14: 6 | B14: 45092 | C14: Europe D Split | D14: =(SUMIFS('Discover Data'!$F:$F,'Discover Data'!$H:$H,"Europe_Trip")-7.99)/2*-1 -> -100.175 | F14: p
A15: =MONTH(sofiS_table89[[#This Row],[Transaction Date]]) -> 6 | B15: 45106 | C15: Direct Payment | D15: -1814.85 | F15: p
C16: One Pass July - February | D16: =(125.1*8)*-1 -> -1000.8

Sheet Summary
D1: Year | E1: 2023 | F1: 2023 | G1: 2023 | H1: 2023 | I1: 2023 | J1: 2023 | K1: 2023 | L1: 2023 | M1: 2023 | N1: 2023 | O1: 2023 | P1: 2023
B2: Grade | D2: Month | E2: January | F2: February | G2: March | H2: April | I2: May | J2: June | K2: July | L2: August | M2: September | N2: October | O2: November | P2: December
E3: 1 | F3: =E3+1 -> 2 | G3: =F3+1 -> 3 | H3: =G3+1 -> 4 | I3: =H3+1 -> 5 | J3: =I3+1 -> 6 | K3: =J3+1 -> 7 | L3: =K3+1 -> 8 | M3: =L3+1 -> 9 | ... P3: =O3+1 -> 12
A4: Cash | B4: A | C4: Wells Fargo | E4: =SUMIFS('Wells Fargo'!$C:$C,'Wells Fargo'!$A:$A,Summary!E$3) -> 553.97 | F4: =SUMIFS('Wells Fargo'!$C:$C,'Wells Fargo'!$A:$A,Summary!F$3)+IF(F3<=MONTH(TODAY()), E4,0) -> 223.11 | G4: =SUMIFS('Wells Fargo'!$C:$C,'Wells Fargo'!$A:$A,Summary!G$3)+IF(G3<=MONTH(TODAY()), F4,0) -> 265.04 | H4: =SUMIFS('Wells Fargo'!$C:$C,'Wells Fargo'!$A:$A,Summary!H$3)+IF(H3<=MONTH(TODAY()), G4,0) -> 4.33 | I4: =SUMIFS('Wells Fargo'!$C:$C,'Wells Fargo'!$A:$A,Summary!I$3)+IF(I3<=MONTH(TODAY()), H4,0) -> 15.78 | J4: =SUMIFS('Wells Fargo'!$C:$C,'Wells Fargo'!$A:$A,Summary!J$3)+IF(J3<=MONTH(TODAY()), I4,0) -> 7.74 | K4: =SUMIFS('Wells Fargo'!$C:$C,'Wells Fargo'!$A:$A,Summary!K$3)+IF(K3<=MONTH(TODAY()), J4,0) -> 2.95 | L4: =SUMIFS('Wells Fargo'!$C:$C,'Wells Fargo'!$A:$A,Summary!L$3)+IF(L3<=MONTH(TODAY()), K4,0) -> 32.75 | M4: =SUMIFS('Wells Fargo'!$C:$C,'Wells Fargo'!$A:$A,Summary!M$3)+IF(M3<=MONTH(TODAY()), L4,0) -> 786.82 | ... P4: =SUMIFS('Wells Fargo'!$C:$C,'Wells Fargo'!$A:$A,Summary!P$3)+IF(P3<=MONTH(TODAY()), O4,0) -> 616.53
E5: =SUMIFS('Wells Fargo'!$C:$C,'Wells Fargo'!$A:$A,Summary!E$3,'Wells Fargo'!$E:$E,"debit") -> -1452.23 | F5: =SUMIFS('Wells Fargo'!$C:$C,'Wells Fargo'!$A:$A,Summary!F$3,'Wells Fargo'!$E:$E,"debit") -> -1638.35 | G5: =SUMIFS('Wells Fargo'!$C:$C,'Wells Fargo'!$A:$A,Summary!G$3,'Wells Fargo'!$E:$E,"debit") -> -1138.06 | H5: =SUMIFS('Wells Fargo'!$C:$C,'Wells Fargo'!$A:$A,Summary!H$3,'Wells Fargo'!$E:$E,"debit") -> -1434.75 | I5: =SUMIFS('Wells Fargo'!$C:$C,'Wells Fargo'!$A:$A,Summary!I$3,'Wells Fargo'!$E:$E,"debit") -> -921.39 | J5: =SUMIFS('Wells Fargo'!$C:$C,'Wells Fargo'!$A:$A,Summary!J$3,'Wells Fargo'!$E:$E,"debit") -> -1193.43 | K5: =SUMIFS('Wells Fargo'!$C:$C,'Wells Fargo'!$A:$A,Summary!K$3,'Wells Fargo'!$E:$E,"debit") -> -1082.86 | L5: =SUMIFS('Wells Fargo'!$C:$C,'Wells Fargo'!$A:$A,Summary!L$3,'Wells Fargo'!$E:$E,"debit") -> -1007.07 | ... P5: =SUMIFS('Wells Fargo'!$C:$C,'Wells Fargo'!$A:$A,Summary!P$3,'Wells Fargo'!$E:$E,"debit") -> -1192.15
A6: Cash | B6: A | C6: SOFI Checking | E6: =SUMIFS(SOFI_CHECKING!$E:$E,SOFI_CHECKING!$A:$A,Summary!E$3) -> 93.39 | F6: =SUMIFS(SOFI_CHECKING!$E:$E,SOFI_CHECKING!$A:$A,Summary!F$3)+IF(F3<=MONTH(TODAY()), E6,0) -> 25.47 | G6: =SUMIFS(SOFI_CHECKING!$E:$E,SOFI_CHECKING!$A:$A,Summary!G$3)+IF(G3<=MONTH(TODAY()), F6,0) -> 42.44 | H6: =SUMIFS(SOFI_CHECKING!$E:$E,SOFI_CHECKING!$A:$A,Summary!H$3)+IF(H3<=MONTH(TODAY()), G6,0) -> 53.35 | I6: =SUMIFS(SOFI_CHECKING!$E:$E,SOFI_CHECKING!$A:$A,Summary!I$3)+IF(I3<=MONTH(TODAY()), H6,0) -> 691.11 | J6: =SUMIFS(SOFI_CHECKING!$E:$E,SOFI_CHECKING!$A:$A,Summary!J$3)+IF(J3<=MONTH(TODAY()), I6,0) -> 5.18 | K6: =SUMIFS(SOFI_CHECKING!$E:$E,SOFI_CHECKING!$A:$A,Summary!K$3)+IF(K3<=MONTH(TODAY()), J6,0) -> 0.88 | L6: =SUMIFS(SOFI_CHECKING!$E:$E,SOFI_CHECKING!$A:$A,Summary!L$3)+IF(L3<=MONTH(TODAY()), K6,0) -> 105.17 | M6: =SUMIFS(SOFI_CHECKING!$E:$E,SOFI_CHECKING!$A:$A,Summary!M$3)+IF(M3<=MONTH(TODAY()), L6,0) -> 11.77 | ... P6: =SUMIFS(SOFI_CHECKING!$E:$E,SOFI_CHECKING!$A:$A,Summary!P$3)+IF(P3<=MONTH(TODAY()), O6,0) -> 11.77
E7: {=SUM(SUMIFS(SOFI_CHECKING!$E:$E,SOFI_CHECKING!$A:$A,Summary!E$3,SOFI_CHECKING!$D:$D,{"Direct Payment","Debit Card"}))} -> -810.45 | F7: {=SUM(SUMIFS(SOFI_CHECKING!$E:$E,SOFI_CHECKING!$A:$A,Summary!F$3,SOFI_CHECKING!$D:$D,{"Direct Payment","Debit Card"}))} -> -168 | G7: {=SUM(SUMIFS(SOFI_CHECKING!$E:$E,SOFI_CHECKING!$A:$A,Summary!G$3,SOFI_CHECKING!$D:$D,{"Direct Payment","Debit Card"}))} -> -1074.9 | H7: {=SUM(SUMIFS(SOFI_CHECKING!$E:$E,SOFI_CHECKING!$A:$A,Summary!H$3,SOFI_CHECKING!$D:$D,{"Direct Payment","Debit Card"}))} -> -356.75 | I7: {=SUM(SUMIFS(SOFI_CHECKING!$E:$E,SOFI_CHECKING!$A:$A,Summary!I$3,SOFI_CHECKING!$D:$D,{"Direct Payment","Debit Card"}))} -> -407.31 | J7: {=SUM(SUMIFS(SOFI_CHECKING!$E:$E,SOFI_CHECKING!$A:$A,Summary!J$3,SOFI_CHECKING!$D:$D,{"Direct Payment","Debit Card"}))} -> -2520.84 | K7: {=SUM(SUMIFS(SOFI_CHECKING!$E:$E,SOFI_CHECKING!$A:$A,Summary!K$3,SOFI_CHECKING!$D:$D,{"Direct Payment","Debit Card"}))} -> -178 | L7: {=SUM(SUMIFS(SOFI_CHECKING!$E:$E,SOFI_CHECKING!$A:$A,Summary!L$3,SOFI_CHECKING!$D:$D,{"Direct Payment","Debit Card"}))} -> 0 | ... P7: {=SUM(SUMIFS(SOFI_CHECKING!$E:$E,SOFI_CHECKING!$A:$A,Summary!P$3,SOFI_CHECKING!$D:$D,{"Direct Payment","Debit Card"}))} -> 0
A8: Cash | B8: B | C8: SOFI Savings | E8: =SUMIFS(SOFI_SAVINGS!$E:$E,SOFI_SAVINGS!$A:$A,Summary!E$3) -> 1126.99 | F8: =SUMIFS(SOFI_SAVINGS!$E:$E,SOFI_SAVINGS!$A:$A,Summary!F$3)+IF(F3<=MONTH(TODAY()), E8,0) -> 1439.96 | G8: =SUMIFS(SOFI_SAVINGS!$E:$E,SOFI_SAVINGS!$A:$A,Summary!G$3)+IF(G3<=MONTH(TODAY()), F8,0) -> 414.14 | H8: =SUMIFS(SOFI_SAVINGS!$E:$E,SOFI_SAVINGS!$A:$A,Summary!H$3)+IF(H3<=MONTH(TODAY()), G8,0) -> 800.44 | I8: =SUMIFS(SOFI_SAVINGS!$E:$E,SOFI_SAVINGS!$A:$A,Summary!I$3)+IF(I3<=MONTH(TODAY()), H8,0) -> 2527.41 | J8: =SUMIFS(SOFI_SAVINGS!$E:$E,SOFI_SAVINGS!$A:$A,Summary!J$3)+IF(J3<=MONTH(TODAY()), I8,0) -> 441.42 | K8: =SUMIFS(SOFI_SAVINGS!$E:$E,SOFI_SAVINGS!$A:$A,Summary!K$3)+IF(K3<=MONTH(TODAY()), J8,0) -> 109.41 | L8: =SUMIFS(SOFI_SAVINGS!$E:$E,SOFI_SAVINGS!$A:$A,Summary!L$3)+IF(L3<=MONTH(TODAY()), K8,0) -> 146.09 | M8: =SUMIFS(SOFI_SAVINGS!$E:$E,SOFI_SAVINGS!$A:$A,Summary!M$3)+IF(M3<=MONTH(TODAY()), L8,0) -> 1196.75 | ... P8: =SUMIFS(SOFI_SAVINGS!$E:$E,SOFI_SAVINGS!$A:$A,Summary!P$3)+IF(P3<=MONTH(TODAY()), O8,0) -> 3551.75
A9: Cash | B9: B | C9: DOCFU | E9: 0 | F9: 0 | G9: 5 | H9: 5 | I9: 5 | J9: 5 | K9: 5 | L9: 6 | M9: 7 | N9: 8 | O9: 9 | P9: 10
A10: Cash | B10: H | C10: Health Equity | E10: =SUMIFS(HSA!$D:$D,HSA!$A:$A,Summary!E$3) -> 764.05 | F10: =SUMIFS(HSA!$D:$D,HSA!$A:$A,Summary!F$3)+IF(F3<=MONTH(TODAY()), E10,0) -> 307.07 | G10: =SUMIFS(HSA!$D:$D,HSA!$A:$A,Summary!G$3)+IF(G3<=MONTH(TODAY()), F10,0) -> 204.79 | H10: =SUMIFS(HSA!$D:$D,HSA!$A:$A,Summary!H$3)+IF(H3<=MONTH(TODAY()), G10,0) -> 274.51 | I10: =SUMIFS(HSA!$D:$D,HSA!$A:$A,Summary!I$3)+IF(I3<=MONTH(TODAY()), H10,0) -> 448.64 | J10: =SUMIFS(HSA!$D:$D,HSA!$A:$A,Summary!J$3)+IF(J3<=MONTH(TODAY()), I10,0) -> 605.23 | K10: =SUMIFS(HSA!$D:$D,HSA!$A:$A,Summary!K$3)+IF(K3<=MONTH(TODAY()), J10,0) -> 243.31 | L10: =SUMIFS(HSA!$D:$D,HSA!$A:$A,Summary!L$3)+IF(L3<=MONTH(TODAY()), K10,0) -> 281.31 | M10: =SUMIFS(HSA!$D:$D,HSA!$A:$A,Summary!M$3)+IF(M3<=MONTH(TODAY()), L10,0) -> 309.01 | ... P10: =SUMIFS(HSA!$D:$D,HSA!$A:$A,Summary!P$3)+IF(P3<=MONTH(TODAY()), O10,0) -> 309.01
A11: Investments | B11: I | C11: Fidelity | E11: =SUMIFS(Fidelity!$E:$E,Fidelity!$A:$A,Summary!E$3) -> 14702.14 | F11: =SUMIFS(Fidelity!$E:$E,Fidelity!$A:$A,Summary!F$3)+IF(F3<=MONTH(TODAY()), E11,0) -> 16184.38 | G11: =SUMIFS(Fidelity!$E:$E,Fidelity!$A:$A,Summary!G$3)+IF(G3<=MONTH(TODAY()), F11,0) -> 17224.38 | H11: =SUMIFS(Fidelity!$E:$E,Fidelity!$A:$A,Summary!H$3)+IF(H3<=MONTH(TODAY()), G11,0) -> 17544.38 | I11: =SUMIFS(Fidelity!$E:$E,Fidelity!$A:$A,Summary!I$3)+IF(I3<=MONTH(TODAY()), H11,0) -> 17861.98 | J11: =SUMIFS(Fidelity!$E:$E,Fidelity!$A:$A,Summary!J$3)+IF(J3<=MONTH(TODAY()), I11,0) -> 19793.71 | K11: =SUMIFS(Fidelity!$E:$E,Fidelity!$A:$A,Summary!K$3)+IF(K3<=MONTH(TODAY()), J11,0) -> 19793.77 | L11: =SUMIFS(Fidelity!$E:$E,Fidelity!$A:$A,Summary!L$3)+IF(L3<=MONTH(TODAY()), K11,0) -> 19789.59 | M11: =SUMIFS(Fidelity!$E:$E,Fidelity!$A:$A,Summary!M$3)+IF(M3<=MONTH(TODAY()), L11,0) -> 19789.62 | ... P11: =SUMIFS(Fidelity!$E:$E,Fidelity!$A:$A,Summary!P$3)+IF(P3<=MONTH(TODAY()), O11,0) -> 19789.62
A12: Medical Debt | B12: D | C12: Care Credit | E12: 0 | F12: 0 | G12: 0 | H12: 0 | I12: 0 | J12: =SUMIFS(Care_Credit!$D:$D,Care_Credit!$A:$A,Summary!J$3)+SUMIFS(Care_Credit!$D:$D,Care_Credit!$A:$A,"<="&Summary!I$3) -> 5872.89 | K12: =SUMIFS(Care_Credit!$D:$D,Care_Credit!$A:$A,Summary!K$3)+IF(K3<=MONTH(TODAY()), J12,0) -> 3640.28 | L12: =SUMIFS(Care_Credit!$D:$D,Care_Credit!$A:$A,Summary!L$3)+IF(L3<=MONTH(TODAY()), K12,0) -> 3820.28 | M12: =SUMIFS(Care_Credit!$D:$D,Care_Credit!$A:$A,Summary!M$3)+IF(M3<=MONTH(TODAY()), L12,0) -> 3934.46 | N12: =SUMIFS(Care_Credit!$D:$D,Care_Credit!$A:$A,Summary!N$3)+IF(N3<=MONTH(TODAY()), M12,0) -> 3934.46 | O12: =SUMIFS(Care_Credit!$D:$D,Care_Credit!$A:$A,Summary!O$3)+IF(O3<=MONTH(TODAY()), N12,0) -> 3934.46 | P12: =SUMIFS(Care_Credit!$D:$D,Care_Credit!$A:$A,Summary!P$3)+IF(P3<=MONTH(TODAY()), O12,0) -> 3934.46
E13: =SUMIFS(Care_Credit!$D:$D,Care_Credit!$A:$A,Summary!E$3,Care_Credit!$E:$E,"p") -> 0 | F13: =SUMIFS(Care_Credit!$D:$D,Care_Credit!$A:$A,Summary!F$3,Care_Credit!$E:$E,"p") -> 0 | G13: =SUMIFS(Care_Credit!$D:$D,Care_Credit!$A:$A,Summary!G$3,Care_Credit!$E:$E,"p") -> 0 | H13: =SUMIFS(Care_Credit!$D:$D,Care_Credit!$A:$A,Summary!H$3,Care_Credit!$E:$E,"p") -> 0 | I13: =SUMIFS(Care_Credit!$D:$D,Care_Credit!$A:$A,Summary!I$3,Care_Credit!$E:$E,"p") -> -681.49 | J13: =SUMIFS(Care_Credit!$D:$D,Care_Credit!$A:$A,Summary!J$3,Care_Credit!$E:$E,"p") -> -130 | K13: =SUMIFS(Care_Credit!$D:$D,Care_Credit!$A:$A,Summary!K$3,Care_Credit!$E:$E,"p") -> -718.39 | L13: =SUMIFS(Care_Credit!$D:$D,Care_Credit!$A:$A,Summary!L$3,Care_Credit!$E:$E,"p") -> 0 | ... P13: =SUMIFS(Care_Credit!$D:$D,Care_Credit!$A:$A,Summary!P$3,Care_Credit!$E:$E,"p") -> 0
A14: Credit Card Debt | B14: D | C14: Discover | E14: 0 | F14: 0 | G14: 0 | H14: 0 | I14: 0 | J14: =SUMIFS('Discover Data'!$F:$F,'Discover Data'!$B:$B,Summary!J$3)+SUMIFS('Discover Data'!$F:$F,'Discover Data'!$B:$B,"<="&Summary!I$3) -> 1158.25 | K14: =SUMIFS('Discover Data'!$F:$F,'Discover Data'!$B:$B,Summary!K$3)+IF(K3<=MONTH(TODAY()), J14,0) -> 541.98 | L14: =SUMIFS('Discover Data'!$F:$F,'Discover Data'!$B:$B,Summary!L$3)+IF(L3<=MONTH(TODAY()), K14,0) -> 1898.66 | M14: =SUMIFS('Discover Data'!$F:$F,'Discover Data'!$B:$B,Summary!M$3)+IF(M3<=MONTH(TODAY()), L14,0) -> 1680.39 | N14: =SUMIFS('Discover Data'!$F:$F,'Discover Data'!$B:$B,Summary!N$3)+IF(N3<=MONTH(TODAY()), M14,0) -> 1117.9 | O14: =SUMIFS('Discover Data'!$F:$F,'Discover Data'!$B:$B,Summary!O$3)+IF(O3<=MONTH(TODAY()), N14,0) -> 2191.16 | P14: =SUMIFS('Discover Data'!$F:$F,'Discover Data'!$B:$B,Summary!P$3)+IF(P3<=MONTH(TODAY()), O14,0) -> 257.7
E15: =SUMIFS('Discover Data'!$F:$F,'Discover Data'!$B:$B,Summary!E$3,'Discover Data'!$G:$G,"Payments and Credits") -> -3624.11 | F15: =SUMIFS('Discover Data'!$F:$F,'Discover Data'!$B:$B,Summary!F$3,'Discover Data'!$G:$G,"Payments and Credits") -> -4427.6 | G15: =SUMIFS('Discover Data'!$F:$F,'Discover Data'!$B:$B,Summary!G$3,'Discover Data'!$G:$G,"Payments and Credits") -> -3761.69 | H15: =SUMIFS('Discover Data'!$F:$F,'Discover Data'!$B:$B,Summary!H$3,'Discover Data'!$G:$G,"Payments and Credits") -> -4428.21 | I15: =SUMIFS('Discover Data'!$F:$F,'Discover Data'!$B:$B,Summary!I$3,'Discover Data'!$G:$G,"Payments and Credits") -> -7363.89 | J15: =SUMIFS('Discover Data'!$F:$F,'Discover Data'!$B:$B,Summary!J$3,'Discover Data'!$G:$G,"Payments and Credits") -> -2487.02 | K15: =SUMIFS('Discover Data'!$F:$F,'Discover Data'!$B:$B,Summary!K$3,'Discover Data'!$G:$G,"Payments and Credits") -> -2781.25 | L15: =SUMIFS('Discover Data'!$F:$F,'Discover Data'!$B:$B,Summary!L$3,'Discover Data'!$G:$G,"Payments and Credits") -> -3027.93 | ... P15: =SUMIFS('Discover Data'!$F:$F,'Discover Data'!$B:$B,Summary!P$3,'Discover Data'!$G:$G,"Payments and Credits") -> -5279.76
A16: Credit Card Debt | B16: D | C16: Best Buy | E16: =SUMIFS('Best Buy'!$C:$C,'Best Buy'!$A:$A,Summary!E$3) -> 0 | F16: =SUMIFS('Best Buy'!$C:$C,'Best Buy'!$A:$A,Summary!F$3)+IF(F3<=MONTH(TODAY()), E16,0) -> 0 | G16: =SUMIFS('Best Buy'!$C:$C,'Best Buy'!$A:$A,Summary!G$3)+IF(G3<=MONTH(TODAY()), F16,0) -> 0 | H16: 0 | I16: 0 | J16: =SUMIFS('Best Buy'!$C:$C,'Best Buy'!$A:$A,Summary!J$3)+SUMIFS('Best Buy'!$C:$C,'Best Buy'!$A:$A,"<="&Summary!I$3) -> 0 | K16: =SUMIFS('Best Buy'!$C:$C,'Best Buy'!$A:$A,Summary!K$3)+SUMIFS('Best Buy'!$C:$C,'Best Buy'!$A:$A,"<="&Summary!J$3) -> 0 | L16: =SUMIFS('Best Buy'!$C:$C,'Best Buy'!$A:$A,Summary!L$3)+SUMIFS('Best Buy'!$C:$C,'Best Buy'!$A:$A,"<="&Summary!K$3) -> 0 | M16: =SUMIFS('Best Buy'!$C:$C,'Best Buy'!$A:$A,Summary!M$3)+SUMIFS('Best Buy'!$C:$C,'Best Buy'!$A:$A,"<="&Summary!L$3) -> 1845.69 | N16: =SUMIFS('Best Buy'!$C:$C,'Best Buy'!$A:$A,Summary!N$3)+SUMIFS('Best Buy'!$C:$C,'Best Buy'!$A:$A,"<="&Summary!M$3) -> 1845.69 | O16: =SUMIFS('Best Buy'!$C:$C,'Best Buy'!$A:$A,Summary!O$3)+SUMIFS('Best Buy'!$C:$C,'Best Buy'!$A:$A,"<="&Summary!N$3) -> 1845.69 | P16: =SUMIFS('Best Buy'!$C:$C,'Best Buy'!$A:$A,Summary!P$3)+SUMIFS('Best Buy'!$C:$C,'Best Buy'!$A:$A,"<="&Summary!O$3) -> 1845.69
E17: =SUMIFS('Best Buy'!$C:$C,'Best Buy'!$A:$A,Summary!E$3,'Best Buy'!$E:$E,"payment") -> 0 | F17: =SUMIFS('Best Buy'!$C:$C,'Best Buy'!$A:$A,Summary!F$3,'Best Buy'!$E:$E,"payment") -> 0 | G17: =SUMIFS('Best Buy'!$C:$C,'Best Buy'!$A:$A,Summary!G$3,'Best Buy'!$E:$E,"payment") -> -180.41 | H17: =SUMIFS('Best Buy'!$C:$C,'Best Buy'!$A:$A,Summary!H$3,'Best Buy'!$E:$E,"payment") -> -202.42 | I17: =SUMIFS('Best Buy'!$C:$C,'Best Buy'!$A:$A,Summary!I$3,'Best Buy'!$E:$E,"payment") -> -421.07 | J17: =SUMIFS('Best Buy'!$C:$C,'Best Buy'!$A:$A,Summary!J$3,'Best Buy'!$E:$E,"payment") -> 0 | K17: =SUMIFS('Best Buy'!$C:$C,'Best Buy'!$A:$A,Summary!K$3,'Best Buy'!$E:$E,"payment") -> 0 | L17: =SUMIFS('Best Buy'!$C:$C,'Best Buy'!$A:$A,Summary!L$3,'Best Buy'!$E:$E,"payment") -> 0 | ... P17: =SUMIFS('Best Buy'!$C:$C,'Best Buy'!$A:$A,Summary!P$3,'Best Buy'!$E:$E,"payment") -> 0
A18: Credit Card Debt | B18: V | C18: Vincent | E18: =SUMIFS(Vincent!$D:$D,Vincent!$A:$A,Summary!E$3) -> 13848.34 | F18: =SUMIFS(Vincent!$D:$D,Vincent!$A:$A,Summary!F$3)+IF(F3<=MONTH(TODAY()), E18,0) -> 13848.34 | G18: =SUMIFS(Vincent!$D:$D,Vincent!$A:$A,Summary!G$3)+IF(G3<=MONTH(TODAY()), F18,0) -> 13848.34 | H18: =SUMIFS(Vincent!$D:$D,Vincent!$A:$A,Summary!H$3)+IF(H3<=MONTH(TODAY()), G18,0) -> 13723.24 | I18: =SUMIFS(Vincent!$D:$D,Vincent!$A:$A,Summary!I$3)+IF(I3<=MONTH(TODAY()), H18,0) -> 13598.14 | J18: =SUMIFS(Vincent!$D:$D,Vincent!$A:$A,Summary!J$3)+IF(J3<=MONTH(TODAY()), I18,0) -> 15427.98 | K18: =SUMIFS(Vincent!$D:$D,Vincent!$A:$A,Summary!K$3)+IF(K3<=MONTH(TODAY()), J18,0) -> 15427.98 | L18: =SUMIFS(Vincent!$D:$D,Vincent!$A:$A,Summary!L$3)+IF(L3<=MONTH(TODAY()), K18,0) -> 15427.98 | M18: =SUMIFS(Vincent!$D:$D,Vincent!$A:$A,Summary!M$3)+IF(M3<=MONTH(TODAY()), L18,0) -> 15427.98 | ... P18: =SUMIFS(Vincent!$D:$D,Vincent!$A:$A,Summary!P$3)+IF(P3<=MONTH(TODAY()), O18,0) -> 15427.98
E19: =SUMIFS(Vincent!$D:$D,Vincent!$F:$F,"p",Vincent!$A:$A,Summary!E$3) -> -570 | F19: =SUMIFS(Vincent!$D:$D,Vincent!$F:$F,"p",Vincent!$A:$A,Summary!F$3) -> 0 | G19: =SUMIFS(Vincent!$D:$D,Vincent!$F:$F,"p",Vincent!$A:$A,Summary!G$3) -> 0 | H19: =SUMIFS(Vincent!$D:$D,Vincent!$F:$F,"p",Vincent!$A:$A,Summary!H$3) -> -125.1 | I19: =SUMIFS(Vincent!$D:$D,Vincent!$F:$F,"p",Vincent!$A:$A,Summary!I$3) -> -125.1 | J19: =SUMIFS(Vincent!$D:$D,Vincent!$F:$F,"p",Vincent!$A:$A,Summary!J$3) -> -2156.63 | K19: =SUMIFS(Vincent!$D:$D,Vincent!$F:$F,"p",Vincent!$A:$A,Summary!K$3) -> 0 | L19: =SUMIFS(Vincent!$D:$D,Vincent!$F:$F,"p",Vincent!$A:$A,Summary!L$3) -> 0 | ... P19: =SUMIFS(Vincent!$D:$D,Vincent!$F:$F,"p",Vincent!$A:$A,Summary!P$3) -> 0
A20: Student Loans | B20: S | C20: Nelnet | E20: 22430.56 | F20: 22430.56 | G20: 22430.56 | H20: 22430.56 | I20: 22430.56 | J20: 22430.56 | K20: 22430.56 | L20: 22431.56 | M20: 22432.56 | N20: 22433.56 | O20: 22434.56 | P20: 22435.56
A22: Total | B22: Grade
A23: Investments | B23: I | E23: =SUMIFS(E$4:E$20,$B$4:$B$20,$B23) -> 14702.14 | F23: =SUMIFS(F$4:F$20,$B$4:$B$20,$B23) -> 16184.38 | G23: =SUMIFS(G$4:G$20,$B$4:$B$20,$B23) -> 17224.38 | H23: =SUMIFS(H$4:H$20,$B$4:$B$20,$B23) -> 17544.38 | I23: =SUMIFS(I$4:I$20,$B$4:$B$20,$B23) -> 17861.98 | J23: =SUMIFS(J$4:J$20,$B$4:$B$20,$B23) -> 19793.71 | K23: =SUMIFS(K$4:K$20,$B$4:$B$20,$B23) -> 19793.77 | L23: =SUMIFS(L$4:L$20,$B$4:$B$20,$B23) -> 19789.59 | ... P23: =SUMIFS(P$4:P$20,$B$4:$B$20,$B23) -> 19789.62
A24: Cash | B24: A | E24: =SUMIFS(E$4:E$20,$B$4:$B$20,$B24) -> 647.36 | F24: =SUMIFS(F$4:F$20,$B$4:$B$20,$B24) -> 248.58 | G24: =SUMIFS(G$4:G$20,$B$4:$B$20,$B24) -> 307.48 | H24: =SUMIFS(H$4:H$20,$B$4:$B$20,$B24) -> 57.68 | I24: =SUMIFS(I$4:I$20,$B$4:$B$20,$B24) -> 706.89 | J24: =SUMIFS(J$4:J$20,$B$4:$B$20,$B24) -> 12.92 | K24: =SUMIFS(K$4:K$20,$B$4:$B$20,$B24) -> 3.83 | L24: =SUMIFS(L$4:L$20,$B$4:$B$20,$B24) -> 137.92 | ... P24: =SUMIFS(P$4:P$20,$B$4:$B$20,$B24) -> 628.3
A25: Cash | B25: B | E25: =SUMIFS(E$4:E$20,$B$4:$B$20,$B25) -> 1126.99 | F25: =SUMIFS(F$4:F$20,$B$4:$B$20,$B25) -> 1439.96 | G25: =SUMIFS(G$4:G$20,$B$4:$B$20,$B25) -> 419.14 | H25: =SUMIFS(H$4:H$20,$B$4:$B$20,$B25) -> 805.44 | I25: =SUMIFS(I$4:I$20,$B$4:$B$20,$B25) -> 2532.41 | J25: =SUMIFS(J$4:J$20,$B$4:$B$20,$B25) -> 446.42 | K25: =SUMIFS(K$4:K$20,$B$4:$B$20,$B25) -> 114.41 | L25: =SUMIFS(L$4:L$20,$B$4:$B$20,$B25) -> 152.09 | ... P25: =SUMIFS(P$4:P$20,$B$4:$B$20,$B25) -> 3561.75
A26: Cash | B26: H | E26: =SUMIFS(E$4:E$20,$B$4:$B$20,$B26) -> 764.05 | F26: =SUMIFS(F$4:F$20,$B$4:$B$20,$B26) -> 307.07 | G26: =SUMIFS(G$4:G$20,$B$4:$B$20,$B26) -> 204.79 | H26: =SUMIFS(H$4:H$20,$B$4:$B$20,$B26) -> 274.51 | I26: =SUMIFS(I$4:I$20,$B$4:$B$20,$B26) -> 448.64 | J26: =SUMIFS(J$4:J$20,$B$4:$B$20,$B26) -> 605.23 | K26: =SUMIFS(K$4:K$20,$B$4:$B$20,$B26) -> 243.31 | L26: =SUMIFS(L$4:L$20,$B$4:$B$20,$B26) -> 281.31 | ... P26: =SUMIFS(P$4:P$20,$B$4:$B$20,$B26) -> 309.01
A27: Debt | B27: D | E27: =SUMIFS(E$4:E$20,$B$4:$B$20,$B27) -> 0 | F27: =SUMIFS(F$4:F$20,$B$4:$B$20,$B27) -> 0 | G27: =SUMIFS(G$4:G$20,$B$4:$B$20,$B27) -> 0 | H27: =SUMIFS(H$4:H$20,$B$4:$B$20,$B27) -> 0 | I27: =SUMIFS(I$4:I$20,$B$4:$B$20,$B27) -> 0 | J27: =SUMIFS(J$4:J$20,$B$4:$B$20,$B27) -> 7031.14 | K27: =SUMIFS(K$4:K$20,$B$4:$B$20,$B27) -> 4182.26 | L27: =SUMIFS(L$4:L$20,$B$4:$B$20,$B27) -> 5718.94 | ... P27: =SUMIFS(P$4:P$20,$B$4:$B$20,$B27) -> 6037.85
A28: Debt | B28: V | E28: =SUMIFS(E$4:E$20,$B$4:$B$20,$B28) -> 13848.34 | F28: =SUMIFS(F$4:F$20,$B$4:$B$20,$B28) -> 13848.34 | G28: =SUMIFS(G$4:G$20,$B$4:$B$20,$B28) -> 13848.34 | H28: =SUMIFS(H$4:H$20,$B$4:$B$20,$B28) -> 13723.24 | I28: =SUMIFS(I$4:I$20,$B$4:$B$20,$B28) -> 13598.14 | J28: =SUMIFS(J$4:J$20,$B$4:$B$20,$B28) -> 15427.98 | K28: =SUMIFS(K$4:K$20,$B$4:$B$20,$B28) -> 15427.98 | L28: =SUMIFS(L$4:L$20,$B$4:$B$20,$B28) -> 15427.98 | ... P28: =SUMIFS(P$4:P$20,$B$4:$B$20,$B28) -> 15427.98
A29: Student Loans | B29: S | E29: =SUMIFS(E$4:E$20,$B$4:$B$20,$B29) -> 22430.56 | F29: =SUMIFS(F$4:F$20,$B$4:$B$20,$B29) -> 22430.56 | G29: =SUMIFS(G$4:G$20,$B$4:$B$20,$B29) -> 22430.56 | H29: =SUMIFS(H$4:H$20,$B$4:$B$20,$B29) -> 22430.56 | I29: =SUMIFS(I$4:I$20,$B$4:$B$20,$B29) -> 22430.56 | J29: =SUMIFS(J$4:J$20,$B$4:$B$20,$B29) -> 22430.56 | K29: =SUMIFS(K$4:K$20,$B$4:$B$20,$B29) -> 22430.56 | L29: =SUMIFS(L$4:L$20,$B$4:$B$20,$B29) -> 22431.56 | ... P29: =SUMIFS(P$4:P$20,$B$4:$B$20,$B29) -> 22435.56
A31: Investments | E31: =SUMIFS(E23:E29,$A$23:$A$29,$A31) -> 14702.14 | F31: =SUMIFS(F23:F29,$A$23:$A$29,$A31) -> 16184.38 | G31: =SUMIFS(G23:G29,$A$23:$A$29,$A31) -> 17224.38 | H31: =SUMIFS(H23:H29,$A$23:$A$29,$A31) -> 17544.38 | I31: =SUMIFS(I23:I29,$A$23:$A$29,$A31) -> 17861.98 | J31: =SUMIFS(J23:J29,$A$23:$A$29,$A31) -> 19793.71 | K31: =SUMIFS(K23:K29,$A$23:$A$29,$A31) -> 19793.77 | L31: =SUMIFS(L23:L29,$A$23:$A$29,$A31) -> 19789.59 | ... P31: =SUMIFS(P23:P29,$A$23:$A$29,$A31) -> 19789.62
A32: Cash | E32: =SUMIFS(E23:E29,$A$23:$A$29,$A32) -> 2538.4 | F32: =SUMIFS(F23:F29,$A$23:$A$29,$A32) -> 1995.61 | G32: =SUMIFS(G23:G29,$A$23:$A$29,$A32) -> 931.41 | H32: =SUMIFS(H23:H29,$A$23:$A$29,$A32) -> 1137.63 | I32: =SUMIFS(I23:I29,$A$23:$A$29,$A32) -> 3687.94 | J32: =SUMIFS(J23:J29,$A$23:$A$29,$A32) -> 1064.57 | K32: =SUMIFS(K23:K29,$A$23:$A$29,$A32) -> 361.55 | L32: =SUMIFS(L23:L29,$A$23:$A$29,$A32) -> 571.32 | ... P32: =SUMIFS(P23:P29,$A$23:$A$29,$A32) -> 4499.06
A33: Debt | E33: =SUMIFS(E23:E29,$A$23:$A$29,$A33) -> 13848.34 | F33: =SUMIFS(F23:F29,$A$23:$A$29,$A33) -> 13848.34 | G33: =SUMIFS(G23:G29,$A$23:$A$29,$A33) -> 13848.34 | H33: =SUMIFS(H23:H29,$A$23:$A$29,$A33) -> 13723.24 | I33: =SUMIFS(I23:I29,$A$23:$A$29,$A33) -> 13598.14 | J33: =SUMIFS(J23:J29,$A$23:$A$29,$A33) -> 22459.12 | K33: =SUMIFS(K23:K29,$A$23:$A$29,$A33) -> 19610.24 | L33: =SUMIFS(L23:L29,$A$23:$A$29,$A33) -> 21146.92 | ... P33: =SUMIFS(P23:P29,$A$23:$A$29,$A33) -> 21465.83
A34: Student Loans | E34: =SUMIFS(E23:E29,$A$23:$A$29,$A34) -> 22430.56 | F34: =SUMIFS(F23:F29,$A$23:$A$29,$A34) -> 22430.56 | G34: =SUMIFS(G23:G29,$A$23:$A$29,$A34) -> 22430.56 | H34: =SUMIFS(H23:H29,$A$23:$A$29,$A34) -> 22430.56 | I34: =SUMIFS(I23:I29,$A$23:$A$29,$A34) -> 22430.56 | J34: =SUMIFS(J23:J29,$A$23:$A$29,$A34) -> 22430.56 | K34: =SUMIFS(K23:K29,$A$23:$A$29,$A34) -> 22430.56 | L34: =SUMIFS(L23:L29,$A$23:$A$29,$A34) -> 22431.56 | ... P34: =SUMIFS(P23:P29,$A$23:$A$29,$A34) -> 22435.56
A36: Assets - Debts | E36: =SUM(E31:E32)-SUM(E33) -> 3392.2 | F36: =SUM(F31:F32)-SUM(F33) -> 4331.65 | G36: =SUM(G31:G32)-SUM(G33) -> 4307.45 | H36: =SUM(H31:H32)-SUM(H33) -> 4958.77 | I36: =SUM(I31:I32)-SUM(I33) -> 7951.78 | J36: =SUM(J31:J32)-SUM(J33) -> -1600.84 | K36: =SUM(K31:K32)-SUM(K33) -> 545.08 | L36: =SUM(L31:L32)-SUM(L33) -> -786.01 | ... P36: =SUM(P31:P32)-SUM(P33) -> 2822.85
A37: Assets - Debts & Student Loans | E37: =SUM(E31:E32)-SUM(E33:E34) -> -19038.36 | F37: =SUM(F31:F32)-SUM(F33:F34) -> -18098.91 | G37: =SUM(G31:G32)-SUM(G33:G34) -> -18123.11 | H37: =SUM(H31:H32)-SUM(H33:H34) -> -17471.79 | I37: =SUM(I31:I32)-SUM(I33:I34) -> -14478.78 | J37: =SUM(J31:J32)-SUM(J33:J34) -> -24031.4 | K37: =SUM(K31:K32)-SUM(K33:K34) -> -21885.48 | L37: =SUM(L31:L32)-SUM(L33:L34) -> -23217.57 | ... P37: =SUM(P31:P32)-SUM(P33:P34) -> -19612.71
A38: Notes
B39: Growth | F39: =F36-E36 -> 939.45 | G39: =G36-F36 -> -24.2 | H39: =H36-G36 -> 651.32 | I39: =I36-H36 -> 2993.01 | J39: =J36-I36 -> -9552.62 | K39: =K36-J36 -> 2145.92 | L39: =L36-K36 -> -1331.09 | M39: =M36-L36 -> -1.54 | ... P39: =P36-O36 -> 764.23
A41: Total Spending | E41: =E5+E7+E15+E13++E17 -> -5886.79 | F41: =F5+F7+F15+F13++F17 -> -6233.95 | G41: =G5+G7+G15+G13++G17 -> -6155.06 | H41: =H5+H7+H15+H13++H17 -> -6422.13 | I41: =I5+I7+I15+I13++I17 -> -9795.15 | J41: =J5+J7+J15+J13++J17 -> -6331.29 | K41: =K5+K7+K15+K13++K17 -> -4760.5 | L41: =L5+L7+L15+L13++L17 -> -4035 | ... P41: =P5+P7+P15+P13++P17 -> -6471.91
A42: -Rent | E42: 750 | F42: 750 | G42: 650 | H42: 650 | I42: 650 | J42: 650 | K42: 650 | L42: 650 | M42: 816.87 | N42: 816.87 | O42: 816.87 | P42: 816.87
A43: -Cell Phone | E43: 111.63 | F43: 111.63 | G43: 111.63 | H43: 111.63 | I43: 111.63 | J43: 111.63 | K43: 111.63 | L43: 111.63 | M43: 111.63 | N43: 111.63 | O43: 111.63 | P43: 111.63
A44: -Insurance | E44: 90.09 | F44: 178.11 | H44: 80.04 | I44: 88.02 | J44: 88.02 | K44: 88.02 | L44: 88.02 | M44: 88.02 | N44: 88.02 | O44: 88.02 | P44: 88.02
A45: Total Fixed Spending | D45: =SUM(E45:P45) -> 11059.44 | E45: =SUM(E42:E44) -> 951.72 | F45: =SUM(F42:F44) -> 1039.74 | G45: =SUM(G42:G44) -> 761.63 | H45: =SUM(H42:H44) -> 841.67 | I45: =SUM(I42:I44) -> 849.65 | J45: =SUM(J42:J44) -> 849.65 | K45: =SUM(K42:K44) -> 849.65 | L45: =SUM(L42:L44) -> 849.65 | ... P45: =SUM(P42:P44) -> 1016.52
A46: Spending - Fixed | E46: =E41+E45 -> -4935.07 | F46: =F41+F45 -> -5194.21 | G46: =G41+G45 -> -5393.43 | H46: =H41+H45 -> -5580.46 | I46: =I41+I45 -> -8945.5 | J46: =J41+J45 -> -5481.64 | K46: =K41+K45 -> -3910.85 | L46: =L41+L45 -> -3185.35 | ... P46: =P41+P45 -> -5455.39
A47: apple_care | E47: 9.99 | F47: 9.99 | G47: 9.99 | H47: 9.99 | I47: 9.99 | J47: 9.99 | K47: 9.99 | L47: 9.99 | M47: 9.99 | N47: 9.99 | O47: 9.99 | P47: 9.99
A48: apple_tv | E48: 0 | F48: 0 | G48: 5.29 | H48: 7.41 | I48: 7.41 | J48: 7.41 | K48: 0 | L48: 7.41 | M48: 7.41 | N48: 7.41 | O48: 7.41 | P48: 7.41
A49: babbel | E49: 0 | F49: 0 | G49: 0 | H49: 0 | I49: 38.14 | J49: 0 | K49: 0 | L49: 0 | M49: 0 | N49: 0 | O49: 0 | P49: 0
A50: breaking_points | E50: 10 | F50: 10 | G50: 10 | H50: 10 | I50: 10 | J50: 10 | K50: 10 | L50: 10 | M50: 10 | N50: 10 | O50: 10 | P50: 10
A51: chatgpt | E51: 0 | F51: 0 | G51: 0 | H51: 0 | I51: 20 | J51: 20 | K51: 20 | L51: 20 | M51: 20 | N51: 20 | O51: 20 | P51: 20
A52: coursera | E52: 49 | F52: 98 | G52: 98 | H52: 0 | I52: 98 | J52: 0 | K52: 0 | L52: 0 | M52: 0 | N52: 0 | O52: 0 | P52: 0
A53: crunchy_roll | E53: 7.99 | F53: 7.99 | G53: 7.99 | H53: 7.99 | I53: 7.99 | J53: 7.99 | K53: 7.99 | L53: 7.99 | M53: 7.99 | N53: 7.99 | O53: 7.99 | P53: 7.99
A54: disney | E54: 0 | F54: 0 | G54: 109.99 | H54: 0 | I54: 0 | J54: 0 | K54: 0 | L54: 0 | M54: 0 | N54: 0 | O54: 0 | P54: 0
A55: hbo | E55: 15.89 | F55: 15.89 | G55: 16.95 | H55: 28.31 | I55: 16.95 | J55: 20.12 | K55: 16.95 | L55: 16.95 | M55: 16.95 | N55: 16.95 | O55: 16.95 | P55: 16.95
A56: meal_lime | E56: 0 | F56: 0 | G56: 0 | H56: 0 | I56: 3.17 | J56: 0 | K56: 0 | L56: 0 | M56: 0 | N56: 0 | O56: 0 | P56: 0
A57: medium | E57: 0 | F57: 0 | G57: 0 | H57: 50 | I57: 0 | J57: 0 | K57: 0 | L57: 0 | M57: 0 | N57: 0 | O57: 0 | P57: 0
A58: nba_league_pass | E58: 0 | F58: 142 | G58: 0 | H58: 0 | I58: 0 | J58: 0 | K58: 0 | L58: 0 | M58: 0 | N58: 0 | O58: 0 | P58: 0
... A63: youtube_tv | E63: 80.88 | F63: 80.88 | G63: 80.88 | H63: 80.88 | I63: 88.88 | J63: 88.88 | K63: 0 | L63: 0 | M63: 0 | N63: 0 | O63: 0 | P63: 0
A64: Subscriptions | D64: =SUM(E64:P64) -> 2201.52 | E64: =SUM(E47:E63) -> 199.33 | F64: =SUM(F47:F63) -> 395.75 | G64: =SUM(G47:G63) -> 370.09 | H64: =SUM(H47:H63) -> 220.16 | I64: =SUM(I47:I63) -> 316.11 | J64: =SUM(J47:J63) -> 179.97 | K64: =SUM(K47:K63) -> 80.51 | L64: =SUM(L47:L63) -> 87.92 | ... P64: =SUM(P47:P63) -> 87.92
A65: Spending - Subs | E65: =E46+E64 -> -4735.74 | F65: =F46+F64 -> -4798.46 | G65: =G46+G64 -> -5023.34 | H65: =H46+H64 -> -5360.3 | I65: =I46+I64 -> -8629.39 | J65: =J46+J64 -> -5301.67 | K65: =K46+K64 -> -3830.34 | L65: =L46+L64 -> -3097.43 | ... P65: =P46+P64 -> -5367.47
A66: onepass | E66: 0 | F66: 0 | G66: 289.1 | H66: 264.1 | I66: 264.1 | J66: 264.1 | K66: 264.1 | L66: 264.1 | M66: 264.1 | N66: 264.1 | O66: 264.1 | P66: 264.1
A67: LASIK | E67: 0 | F67: 0 | G67: 0 | H67: 0 | I67: 0 | J67: 0 | K67: 200 | L67: 280 | M67: 280 | N67: 280 | O67: 280 | P67: 280
A68: physical_therapy | E68: 0 | F68: 299.32 | G68: 218 | H68: 0 | I68: 0 | J68: 0 | K68: 0 | L68: 0 | M68: 0 | N68: 0 | O68: 0 | P68: 0
A69: vision | E69: 106.5 | F69: 0 | G69: 938.85 | H69: 0 | I69: 0 | J69: 0 | K69: 243.74 | L69: 0 | M69: 0 | N69: 0 | O69: 0 | P69: 0
A70: dental | E70: 549.6 | F70: 0 | G70: 0 | H70: 0 | I70: 0 | J70: 0 | K70: 0 | L70: 0 | M70: 0 | N70: 0 | O70: 0 | P70: 0
A71: Other Health | E71: 1.75 | F71: 152.89 | G71: 211.63 | H71: 96.3 | I71: 478.86 | J71: 0 | K71: 14.87 | L71: 0 | M71: 0 | N71: 0 | O71: 0 | P71: 0
A72: medical | E72: 0 | F72: 0 | G72: 0 | H72: 66.53 | I72: 48.1 | J72: 0 | K72: 22.96 | L72: 0 | M72: 0 | N72: 0 | O72: 0 | P72: 0
A73: Sports Consumables | E73: 0 | F73: 43.34 | G73: 105.41 | H73: 0 | I73: 0 | J73: 0 | K73: 0 | L73: 0 | M73: 0 | N73: 0 | O73: 0 | P73: 0
A74: Medical | D74: =SUM(E74:P74) -> 7864.65 | E74: =SUM(E66:E73) -> 657.85 | F74: =SUM(F66:F73) -> 495.55 | G74: =SUM(G66:G73) -> 1762.99 | H74: =SUM(H66:H73) -> 426.93 | I74: =SUM(I66:I73) -> 791.06 | J74: =SUM(J66:J73) -> 264.1 | K74: =SUM(K66:K73) -> 745.67 | L74: =SUM(L66:L73) -> 544.1 | ... P74: =SUM(P66:P73) -> 544.1
A75: Spending - Medical | E75: =E65+E74 -> -4077.89 | F75: =F65+F74 -> -4302.91 | G75: =G65+G74 -> -3260.35 | H75: =H65+H74 -> -4933.37 | I75: =I65+I74 -> -7838.33 | J75: =J65+J74 -> -5037.57 | K75: =K65+K74 -> -3084.67 | L75: =L65+L74 -> -2553.33 | ... P75: =P65+P74 -> -4823.37
A76: - GA tech | D76: =SUM(E76:P76) -> 932 | I76: 932
A77: Spending - Education | E77: =E75+E76 -> -4077.89 | F77: =F75+F76 -> -4302.91 | G77: =G75+G76 -> -3260.35 | H77: =H75+H76 -> -4933.37 | I77: =I75+I76 -> -6906.33 | J77: =J75+J76 -> -5037.57 | K77: =K75+K76 -> -3084.67 | L77: =L75+L76 -> -2553.33 | ... P77: =P75+P76 -> -4823.37
E78: 216.14 | F78: 298.47 | G78: 641.03 | H78: 457.06 | I78: 433.42 | J78: 91.74 | K78: 106.34
E79: 419.14 | F79: 667.4 | G79: 546.74 | H79: 233.12 | I79: 628.16 | J79: 53.32 | K79: 62.19
A80: Food | E80: =SUM(E78:E79) -> 635.28 | F80: =SUM(F78:F79) -> 965.87 | G80: =SUM(G78:G79) -> 1187.77 | H80: =SUM(H78:H79) -> 690.18 | I80: =SUM(I78:I79) -> 1061.58 | J80: =SUM(J78:J79) -> 145.06 | K80: =SUM(K78:K79) -> 168.53 | L80: =SUM(L78:L79) -> 0 | ... P80: =SUM(P78:P79) -> 0
A81: Spending -Food | E81: =E77+E80 -> -3442.61 | F81: =F77+F80 -> -3337.04 | G81: =G77+G80 -> -2072.58 | H81: =H77+H80 -> -4243.19 | I81: =I77+I80 -> -5844.75 | J81: =J77+J80 -> -4892.51 | K81: =K77+K80 -> -2916.14 | L81: =L77+L80 -> -2553.33 | ... P81: =P77+P80 -> -4823.37
E84: {=SUM(SUMIFS(SOFI_SAVINGS!$E:$E,SOFI_SAVINGS!$A:$A,Summary!E$3,SOFI_SAVINGS!$D:$D,{"Deposit","Direct Deposit"}))} -> 6025.59 | F84: {=SUM(SUMIFS(SOFI_SAVINGS!$E:$E,SOFI_SAVINGS!$A:$A,Summary!F$3,SOFI_SAVINGS!$D:$D,{"Deposit","Direct Deposit"}))} -> 4686.77 | G84: {=SUM(SUMIFS(SOFI_SAVINGS!$E:$E,SOFI_SAVINGS!$A:$A,Summary!G$3,SOFI_SAVINGS!$D:$D,{"Deposit","Direct Deposit"}))} -> 5104.58 | H84: {=SUM(SUMIFS(SOFI_SAVINGS!$E:$E,SOFI_SAVINGS!$A:$A,Summary!H$3,SOFI_SAVINGS!$D:$D,{"Deposit","Direct Deposit"}))} -> 5416.74 | I84: {=SUM(SUMIFS(SOFI_SAVINGS!$E:$E,SOFI_SAVINGS!$A:$A,Summary!I$3,SOFI_SAVINGS!$D:$D,{"Deposit","Direct Deposit"}))} -> 7567.31 | J84: {=SUM(SUMIFS(SOFI_SAVINGS!$E:$E,SOFI_SAVINGS!$A:$A,Summary!J$3,SOFI_SAVINGS!$D:$D,{"Deposit","Direct Deposit"}))} -> 5016.74 | K84: {=SUM(SUMIFS(SOFI_SAVINGS!$E:$E,SOFI_SAVINGS!$A:$A,Summary!K$3,SOFI_SAVINGS!$D:$D,{"Deposit","Direct Deposit"}))} -> 5016.38 | L84: {=SUM(SUMIFS(SOFI_SAVINGS!$E:$E,SOFI_SAVINGS!$A:$A,Summary!L$3,SOFI_SAVINGS!$D:$D,{"Deposit","Direct Deposit"}))} -> 5308.93 | ... P84: {=SUM(SUMIFS(SOFI_SAVINGS!$E:$E,SOFI_SAVINGS!$A:$A,Summary!P$3,SOFI_SAVINGS!$D:$D,{"Deposit","Direct Deposit"}))} -> 5465.47
E85: =SUMIFS('Wells Fargo'!$C:$C,'Wells Fargo'!$A:$A,Summary!E$3,'Wells Fargo'!$F:$F,"deposit") -> 1018.68 | F85: =SUMIFS('Wells Fargo'!$C:$C,'Wells Fargo'!$A:$A,Summary!F$3,'Wells Fargo'!$F:$F,"deposit") -> 267.17 | G85: =SUMIFS('Wells Fargo'!$C:$C,'Wells Fargo'!$A:$A,Summary!G$3,'Wells Fargo'!$F:$F,"deposit") -> 689.05 | H85: =SUMIFS('Wells Fargo'!$C:$C,'Wells Fargo'!$A:$A,Summary!H$3,'Wells Fargo'!$F:$F,"deposit") -> 797.06 | I85: =SUMIFS('Wells Fargo'!$C:$C,'Wells Fargo'!$A:$A,Summary!I$3,'Wells Fargo'!$F:$F,"deposit") -> 797.06 | J85: =SUMIFS('Wells Fargo'!$C:$C,'Wells Fargo'!$A:$A,Summary!J$3,'Wells Fargo'!$F:$F,"deposit") -> 797.06 | K85: =SUMIFS('Wells Fargo'!$C:$C,'Wells Fargo'!$A:$A,Summary!K$3,'Wells Fargo'!$F:$F,"deposit") -> 797.07 | L85: =SUMIFS('Wells Fargo'!$C:$C,'Wells Fargo'!$A:$A,Summary!L$3,'Wells Fargo'!$F:$F,"deposit") -> 936.87 | ... P85: =SUMIFS('Wells Fargo'!$C:$C,'Wells Fargo'!$A:$A,Summary!P$3,'Wells Fargo'!$F:$F,"deposit") -> 964.49
A86: Total Income | D86: =SUM(E86:P86) -> 79619.63 | E86: =SUM(E84:E85) -> 7044.27 | F86: =SUM(F84:F85) -> 4953.94 | G86: =SUM(G84:G85) -> 5793.63 | H86: =SUM(H84:H85) -> 6213.8 | I86: =SUM(I84:I85) -> 8364.37 | J86: =SUM(J84:J85) -> 5813.8 | K86: =SUM(K84:K85) -> 5813.45 | L86: =SUM(L84:L85) -> 6245.8 | ... P86: =SUM(P84:P85) -> 6429.96
A87: Variable Spending/Income | E87: =E81*-1/E86 -> 0.48871068 | F87: =F81*-1/F86 -> 0.67361333 | G87: =G81*-1/G86 -> 0.35773427 | H87: =H81*-1/H86 -> 0.68286556 | I87: =I81*-1/I86 -> 0.69876751 | J87: =J81*-1/J86 -> 0.84153394 | K87: =K81*-1/K86 -> 0.50161952 | L87: =L77*-1/L86 -> 0.40880752 | M87: =M77*-1/M86 -> 0.16586255 | N87: =N77*-1/N86 -> 0.39876302 | O87: =O77*-1/O86 -> 0.48680068 | P87: =P77*-1/P86 -> 0.75013997
A88: Fixed Spending/Income | E88: =SUM(E45,E64,E74,E76)/E86 -> 0.25679027 | F88: =SUM(F45,F64,F74,F76)/F86 -> 0.38979883 | G88: =SUM(G45,G64,G74,G76)/G86 -> 0.49963667 | H88: =SUM(H45,H64,H74,H76)/H86 -> 0.2395893 | I88: =SUM(I45,I64,I74,I76)/I86 -> 0.3453721 | J88: =SUM(J45,J64,J74,J76)/J86 -> 0.22252571 | K88: =SUM(K45,K64,K74,K76)/K86 -> 0.28826772 | L88: =SUM(L45,L64,L74,L76)/L86 -> 0.23722662 | ... P88: =SUM(P45,P64,P74,P76)/P86 -> 0.25638418
E89: =SUM(E87:E88) -> 0.74550095 | F89: =SUM(F87:F88) -> 1.0634122 | G89: =SUM(G87:G88) -> 0.85737094 | H89: =SUM(H87:H88) -> 0.92245486 | I89: =SUM(I87:I88) -> 1.0441396 | J89: =SUM(J87:J88) -> 1.0640597 | K89: =SUM(K87:K88) -> 0.78988724 | L89: =SUM(L87:L88) -> 0.64603413 | ... P89: =SUM(P87:P88) -> 1.0065241
E91: =E77/2 -> -2038.945 | F91: =F77/2 -> -2151.455 | G91: =G77/2 -> -1630.175 | H91: =H77/2 -> -2466.685 | I91: =I77/2 -> -3453.165 | J91: =J77/2 -> -2518.785 | K91: =K77/2 -> -1542.335 | L91: =L77/2 -> -1276.665 | ... P91: =P77/2 -> -2411.685

Sheet Detailed Summary
B1: Year | D1: 2023 | E1: 2023 | F1: 2023 | G1: 2023 | H1: 2023 | I1: 2023 | J1: 2023 | K1: 2023 | L1: 2023 | M1: 2023 | N1: 2023
B2: Month | C2: 1 | D2: =C2+1 -> 2 | E2: =D2+1 -> 3 | F2: =E2+1 -> 4 | G2: =F2+1 -> 5 | H2: =G2+1 -> 6 | I2: =H2+1 -> 7 | J2: =I2+1 -> 8 | K2: =J2+1 -> 9 | ... N2: =M2+1 -> 12
A4: Fixed Expenses | B4: Rent | C4: 750 | D4: 750 | E4: 650 | F4: 650 | G4: 650 | H4: 650 | I4: 650 | J4: 650 | K4: 816.87 | L4: 816.87 | M4: 816.87 | N4: 816.87
B5: cell_phone | C5: =SUM(SUMIFS('Discover Data'!$F:$F,'Discover Data'!$H:$H,$B5,'Discover Data'!$B:$B,'Detailed Summary'!C$2)) -> 111.63 | D5: =SUM(SUMIFS('Discover Data'!$F:$F,'Discover Data'!$H:$H,$B5,'Discover Data'!$B:$B,'Detailed Summary'!D$2)) -> 111.63 | E5: =SUM(SUMIFS('Discover Data'!$F:$F,'Discover Data'!$H:$H,$B5,'Discover Data'!$B:$B,'Detailed Summary'!E$2)) -> 111.63 | F5: =SUM(SUMIFS('Discover Data'!$F:$F,'Discover Data'!$H:$H,$B5,'Discover Data'!$B:$B,'Detailed Summary'!F$2)) -> 111.63 | G5: =SUM(SUMIFS('Discover Data'!$F:$F,'Discover Data'!$H:$H,$B5,'Discover Data'!$B:$B,'Detailed Summary'!G$2)) -> 111.63 | H5: =SUM(SUMIFS('Discover Data'!$F:$F,'Discover Data'!$H:$H,$B5,'Discover Data'!$B:$B,'Detailed Summary'!H$2)) -> 111.63 | I5: =SUM(SUMIFS('Discover Data'!$F:$F,'Discover Data'!$H:$H,$B5,'Discover Data'!$B:$B,'Detailed Summary'!I$2)) -> 232.39 | J5: 111.63 | K5: 111.63 | L5: 111.63 | M5: 111.63 | N5: 111.63
B6: state_farm | C6: =SUM(SUMIFS('Discover Data'!$F:$F,'Discover Data'!$H:$H,$B6,'Discover Data'!$B:$B,'Detailed Summary'!C$2)) -> 90.09 | D6: =SUM(SUMIFS('Discover Data'!$F:$F,'Discover Data'!$H:$H,$B6,'Discover Data'!$B:$B,'Detailed Summary'!D$2)) -> 178.11 | E6: =SUM(SUMIFS('Discover Data'!$F:$F,'Discover Data'!$H:$H,$B6,'Discover Data'!$B:$B,'Detailed Summary'!E$2)) -> 0 | F6: =SUM(SUMIFS('Discover Data'!$F:$F,'Discover Data'!$H:$H,$B6,'Discover Data'!$B:$B,'Detailed Summary'!F$2)) -> 80.04 | G6: =SUM(SUMIFS('Discover Data'!$F:$F,'Discover Data'!$H:$H,$B6,'Discover Data'!$B:$B,'Detailed Summary'!G$2)) -> 88.02 | H6: =SUM(SUMIFS('Discover Data'!$F:$F,'Discover Data'!$H:$H,$B6,'Discover Data'!$B:$B,'Detailed Summary'!H$2)) -> 88.02 | I6: =SUM(SUMIFS('Discover Data'!$F:$F,'Discover Data'!$H:$H,$B6,'Discover Data'!$B:$B,'Detailed Summary'!I$2)) -> 88.02 | J6: =SUM(SUMIFS('Discover Data'!$F:$F,'Discover Data'!$H:$H,$B6,'Discover Data'!$B:$B,'Detailed Summary'!J$2)) -> 90.83 | K6: =J6 -> 90.83 | L6: =K6 -> 90.83 | M6: =L6 -> 90.83 | N6: =M6 -> 90.83
B7: Student Loans
B8: Debt Payments | H8: 1814.85 | I8: 1803.4 | J8: 1803.4 | K8: 1803.4 | L8: 1803.4 | M8: 1803.4 | N8: 1803.4 | AJ8: onlyfans
A9: Subscriptions | B9: apple_care | C9: =SUM(SUMIFS('Discover Data'!$F:$F,'Discover Data'!$H:$H,$B9,'Discover Data'!$B:$B,'Detailed Summary'!C$2)) -> 9.99 | D9: =SUM(SUMIFS('Discover Data'!$F:$F,'Discover Data'!$H:$H,$B9,'Discover Data'!$B:$B,'Detailed Summary'!D$2)) -> 9.99 | E9: =SUM(SUMIFS('Discover Data'!$F:$F,'Discover Data'!$H:$H,$B9,'Discover Data'!$B:$B,'Detailed Summary'!E$2)) -> 9.99 | F9: =SUM(SUMIFS('Discover Data'!$F:$F,'Discover Data'!$H:$H,$B9,'Discover Data'!$B:$B,'Detailed Summary'!F$2)) -> 9.99 | G9: =SUM(SUMIFS('Discover Data'!$F:$F,'Discover Data'!$H:$H,$B9,'Discover Data'!$B:$B,'Detailed Summary'!G$2)) -> 9.99 | H9: =SUM(SUMIFS('Discover Data'!$F:$F,'Discover Data'!$H:$H,$B9,'Discover Data'!$B:$B,'Detailed Summary'!H$2)) -> 9.99 | I9: =SUM(SUMIFS('Discover Data'!$F:$F,'Discover Data'!$H:$H,$B9,'Discover Data'!$B:$B,'Detailed Summary'!I$2)) -> 9.99 | J9: =SUM(SUMIFS('Discover Data'!$F:$F,'Discover Data'!$H:$H,$B9,'Discover Data'!$B:$B,'Detailed Summary'!J$2)) -> 9.99 | ... N9: =SUM(SUMIFS('Discover Data'!$F:$F,'Discover Data'!$H:$H,$B9,'Discover Data'!$B:$B,'Detailed Summary'!N$2)) -> 9.99
B10: apple_tv | C10: =SUM(SUMIFS('Discover Data'!$F:$F,'Discover Data'!$H:$H,$B10,'Discover Data'!$B:$B,'Detailed Summary'!C$2)) -> 0 | D10: =SUM(SUMIFS('Discover Data'!$F:$F,'Discover Data'!$H:$H,$B10,'Discover Data'!$B:$B,'Detailed Summary'!D$2)) -> 0 | E10: =SUM(SUMIFS('Discover Data'!$F:$F,'Discover Data'!$H:$H,$B10,'Discover Data'!$B:$B,'Detailed Summary'!E$2)) -> 5.29 | F10: =SUM(SUMIFS('Discover Data'!$F:$F,'Discover Data'!$H:$H,$B10,'Discover Data'!$B:$B,'Detailed Summary'!F$2)) -> 7.41 | G10: =SUM(SUMIFS('Discover Data'!$F:$F,'Discover Data'!$H:$H,$B10,'Discover Data'!$B:$B,'Detailed Summary'!G$2)) -> 7.41 | H10: =SUM(SUMIFS('Discover Data'!$F:$F,'Discover Data'!$H:$H,$B10,'Discover Data'!$B:$B,'Detailed Summary'!H$2)) -> 7.41 | I10: =SUM(SUMIFS('Discover Data'!$F:$F,'Discover Data'!$H:$H,$B10,'Discover Data'!$B:$B,'Detailed Summary'!I$2)) -> 0 | J10: =SUM(SUMIFS('Discover Data'!$F:$F,'Discover Data'!$H:$H,$B10,'Discover Data'!$B:$B,'Detailed Summary'!J$2)) -> 0 | ... N10: =SUM(SUMIFS('Discover Data'!$F:$F,'Discover Data'!$H:$H,$B10,'Discover Data'!$B:$B,'Detailed Summary'!N$2)) -> 0
B11: babbel | C11: =SUM(SUMIFS('Discover Data'!$F:$F,'Discover Data'!$H:$H,$B11,'Discover Data'!$B:$B,'Detailed Summary'!C$2)) -> 0 | D11: =SUM(SUMIFS('Discover Data'!$F:$F,'Discover Data'!$H:$H,$B11,'Discover Data'!$B:$B,'Detailed Summary'!D$2)) -> 0 | E11: =SUM(SUMIFS('Discover Data'!$F:$F,'Discover Data'!$H:$H,$B11,'Discover Data'!$B:$B,'Detailed Summary'!E$2)) -> 0 | F11: =SUM(SUMIFS('Discover Data'!$F:$F,'Discover Data'!$H:$H,$B11,'Discover Data'!$B:$B,'Detailed Summary'!F$2)) -> 0 | G11: =SUM(SUMIFS('Discover Data'!$F:$F,'Discover Data'!$H:$H,$B11,'Discover Data'!$B:$B,'Detailed Summary'!G$2)) -> 38.14 | H11: =SUM(SUMIFS('Discover Data'!$F:$F,'Discover Data'!$H:$H,$B11,'Discover Data'!$B:$B,'Detailed Summary'!H$2)) -> 0 | I11: =SUM(SUMIFS('Discover Data'!$F:$F,'Discover Data'!$H:$H,$B11,'Discover Data'!$B:$B,'Detailed Summary'!I$2)) -> 0 | J11: =SUM(SUMIFS('Discover Data'!$F:$F,'Discover Data'!$H:$H,$B11,'Discover Data'!$B:$B,'Detailed Summary'!J$2)) -> 0 | ... N11: =SUM(SUMIFS('Discover Data'!$F:$F,'Discover Data'!$H:$H,$B11,'Discover Data'!$B:$B,'Detailed Summary'!N$2)) -> 0
B12: breaking_points | C12: =SUM(SUMIFS('Discover Data'!$F:$F,'Discover Data'!$H:$H,$B12,'Discover Data'!$B:$B,'Detailed Summary'!C$2)) -> 10 | D12: =SUM(SUMIFS('Discover Data'!$F:$F,'Discover Data'!$H:$H,$B12,'Discover Data'!$B:$B,'Detailed Summary'!D$2)) -> 10 | E12: =SUM(SUMIFS('Discover Data'!$F:$F,'Discover Data'!$H:$H,$B12,'Discover Data'!$B:$B,'Detailed Summary'!E$2)) -> 10 | F12: =SUM(SUMIFS('Discover Data'!$F:$F,'Discover Data'!$H:$H,$B12,'Discover Data'!$B:$B,'Detailed Summary'!F$2)) -> 10 | G12: =SUM(SUMIFS('Discover Data'!$F:$F,'Discover Data'!$H:$H,$B12,'Discover Data'!$B:$B,'Detailed Summary'!G$2)) -> 10 | H12: =SUM(SUMIFS('Discover Data'!$F:$F,'Discover Data'!$H:$H,$B12,'Discover Data'!$B:$B,'Detailed Summary'!H$2)) -> 10 | I12: =SUM(SUMIFS('Discover Data'!$F:$F,'Discover Data'!$H:$H,$B12,'Discover Data'!$B:$B,'Detailed Summary'!I$2)) -> 10 | J12: =SUM(SUMIFS('Discover Data'!$F:$F,'Discover Data'!$H:$H,$B12,'Discover Data'!$B:$B,'Detailed Summary'!J$2)) -> 10 | ... N12: =SUM(SUMIFS('Discover Data'!$F:$F,'Discover Data'!$H:$H,$B12,'Discover Data'!$B:$B,'Detailed Summary'!N$2)) -> 10
B13: chatgpt | C13: =SUM(SUMIFS('Discover Data'!$F:$F,'Discover Data'!$H:$H,$B13,'Discover Data'!$B:$B,'Detailed Summary'!C$2)) -> 0 | D13: =SUM(SUMIFS('Discover Data'!$F:$F,'Discover Data'!$H:$H,$B13,'Discover Data'!$B:$B,'Detailed Summary'!D$2)) -> 0 | E13: =SUM(SUMIFS('Discover Data'!$F:$F,'Discover Data'!$H:$H,$B13,'Discover Data'!$B:$B,'Detailed Summary'!E$2)) -> 0 | F13: =SUM(SUMIFS('Discover Data'!$F:$F,'Discover Data'!$H:$H,$B13,'Discover Data'!$B:$B,'Detailed Summary'!F$2)) -> 0 | G13: =SUM(SUMIFS('Discover Data'!$F:$F,'Discover Data'!$H:$H,$B13,'Discover Data'!$B:$B,'Detailed Summary'!G$2)) -> 20 | H13: =SUM(SUMIFS('Discover Data'!$F:$F,'Discover Data'!$H:$H,$B13,'Discover Data'!$B:$B,'Detailed Summary'!H$2)) -> 20 | I13: =SUM(SUMIFS('Discover Data'!$F:$F,'Discover Data'!$H:$H,$B13,'Discover Data'!$B:$B,'Detailed Summary'!I$2)) -> 20 | J13: =SUM(SUMIFS('Discover Data'!$F:$F,'Discover Data'!$H:$H,$B13,'Discover Data'!$B:$B,'Detailed Summary'!J$2)) -> 20 | ... N13: =SUM(SUMIFS('Discover Data'!$F:$F,'Discover Data'!$H:$H,$B13,'Discover Data'!$B:$B,'Detailed Summary'!N$2)) -> 20
B14: coursera | C14: =SUM(SUMIFS('Discover Data'!$F:$F,'Discover Data'!$H:$H,$B14,'Discover Data'!$B:$B,'Detailed Summary'!C$2)) -> 49 | D14: =SUM(SUMIFS('Discover Data'!$F:$F,'Discover Data'!$H:$H,$B14,'Discover Data'!$B:$B,'Detailed Summary'!D$2)) -> 98 | E14: =SUM(SUMIFS('Discover Data'!$F:$F,'Discover Data'!$H:$H,$B14,'Discover Data'!$B:$B,'Detailed Summary'!E$2)) -> 98 | F14: =SUM(SUMIFS('Discover Data'!$F:$F,'Discover Data'!$H:$H,$B14,'Discover Data'!$B:$B,'Detailed Summary'!F$2)) -> 0 | G14: =SUM(SUMIFS('Discover Data'!$F:$F,'Discover Data'!$H:$H,$B14,'Discover Data'!$B:$B,'Detailed Summary'!G$2)) -> 98 | H14: =SUM(SUMIFS('Discover Data'!$F:$F,'Discover Data'!$H:$H,$B14,'Discover Data'!$B:$B,'Detailed Summary'!H$2)) -> 0 | I14: =SUM(SUMIFS('Discover Data'!$F:$F,'Discover Data'!$H:$H,$B14,'Discover Data'!$B:$B,'Detailed Summary'!I$2)) -> 0 | J14: =SUM(SUMIFS('Discover Data'!$F:$F,'Discover Data'!$H:$H,$B14,'Discover Data'!$B:$B,'Detailed Summary'!J$2)) -> 49 | ... N14: =SUM(SUMIFS('Discover Data'!$F:$F,'Discover Data'!$H:$H,$B14,'Discover Data'!$B:$B,'Detailed Summary'!N$2)) -> 0
B15: crunchy_roll | C15: =SUM(SUMIFS('Discover Data'!$F:$F,'Discover Data'!$H:$H,$B15,'Discover Data'!$B:$B,'Detailed Summary'!C$2)) -> 7.99 | D15: =SUM(SUMIFS('Discover Data'!$F:$F,'Discover Data'!$H:$H,$B15,'Discover Data'!$B:$B,'Detailed Summary'!D$2)) -> 7.99 | E15: =SUM(SUMIFS('Discover Data'!$F:$F,'Discover Data'!$H:$H,$B15,'Discover Data'!$B:$B,'Detailed Summary'!E$2)) -> 7.99 | F15: =SUM(SUMIFS('Discover Data'!$F:$F,'Discover Data'!$H:$H,$B15,'Discover Data'!$B:$B,'Detailed Summary'!F$2)) -> 7.99 | G15: =SUM(SUMIFS('Discover Data'!$F:$F,'Discover Data'!$H:$H,$B15,'Discover Data'!$B:$B,'Detailed Summary'!G$2)) -> 7.99 | H15: =SUM(SUMIFS('Discover Data'!$F:$F,'Discover Data'!$H:$H,$B15,'Discover Data'!$B:$B,'Detailed Summary'!H$2)) -> 7.99 | I15: =SUM(SUMIFS('Discover Data'!$F:$F,'Discover Data'!$H:$H,$B15,'Discover Data'!$B:$B,'Detailed Summary'!I$2)) -> 7.99 | J15: =SUM(SUMIFS('Discover Data'!$F:$F,'Discover Data'!$H:$H,$B15,'Discover Data'!$B:$B,'Detailed Summary'!J$2)) -> 7.99 | K15: =J15 -> 7.99 | L15: =K15 -> 7.99 | M15: =L15 -> 7.99 | N15: =M15 -> 7.99
B16: disney | C16: =SUM(SUMIFS('Discover Data'!$F:$F,'Discover Data'!$H:$H,$B16,'Discover Data'!$B:$B,'Detailed Summary'!C$2)) -> 0 | D16: =SUM(SUMIFS('Discover Data'!$F:$F,'Discover Data'!$H:$H,$B16,'Discover Data'!$B:$B,'Detailed Summary'!D$2)) -> 0 | E16: =SUM(SUMIFS('Discover Data'!$F:$F,'Discover Data'!$H:$H,$B16,'Discover Data'!$B:$B,'Detailed Summary'!E$2)) -> 109.99 | F16: =SUM(SUMIFS('Discover Data'!$F:$F,'Discover Data'!$H:$H,$B16,'Discover Data'!$B:$B,'Detailed Summary'!F$2)) -> 0 | G16: =SUM(SUMIFS('Discover Data'!$F:$F,'Discover Data'!$H:$H,$B16,'Discover Data'!$B:$B,'Detailed Summary'!G$2)) -> 0 | H16: =SUM(SUMIFS('Discover Data'!$F:$F,'Discover Data'!$H:$H,$B16,'Discover Data'!$B:$B,'Detailed Summary'!H$2)) -> 0 | I16: =SUM(SUMIFS('Discover Data'!$F:$F,'Discover Data'!$H:$H,$B16,'Discover Data'!$B:$B,'Detailed Summary'!I$2)) -> 0 | J16: =SUM(SUMIFS('Discover Data'!$F:$F,'Discover Data'!$H:$H,$B16,'Discover Data'!$B:$B,'Detailed Summary'!J$2)) -> 0 | ... N16: =SUM(SUMIFS('Discover Data'!$F:$F,'Discover Data'!$H:$H,$B16,'Discover Data'!$B:$B,'Detailed Summary'!N$2)) -> 0
B17: hbo | C17: =SUM(SUMIFS('Discover Data'!$F:$F,'Discover Data'!$H:$H,$B17,'Discover Data'!$B:$B,'Detailed Summary'!C$2)) -> 15.89 | D17: =SUM(SUMIFS('Discover Data'!$F:$F,'Discover Data'!$H:$H,$B17,'Discover Data'!$B:$B,'Detailed Summary'!D$2)) -> 15.89 | E17: =SUM(SUMIFS('Discover Data'!$F:$F,'Discover Data'!$H:$H,$B17,'Discover Data'!$B:$B,'Detailed Summary'!E$2)) -> 16.95 | F17: =SUM(SUMIFS('Discover Data'!$F:$F,'Discover Data'!$H:$H,$B17,'Discover Data'!$B:$B,'Detailed Summary'!F$2)) -> 28.31 | G17: =SUM(SUMIFS('Discover Data'!$F:$F,'Discover Data'!$H:$H,$B17,'Discover Data'!$B:$B,'Detailed Summary'!G$2)) -> 16.95 | H17: =SUM(SUMIFS('Discover Data'!$F:$F,'Discover Data'!$H:$H,$B17,'Discover Data'!$B:$B,'Detailed Summary'!H$2)) -> 20.12 | I17: =SUM(SUMIFS('Discover Data'!$F:$F,'Discover Data'!$H:$H,$B17,'Discover Data'!$B:$B,'Detailed Summary'!I$2)) -> 16.95 | J17: =SUM(SUMIFS('Discover Data'!$F:$F,'Discover Data'!$H:$H,$B17,'Discover Data'!$B:$B,'Detailed Summary'!J$2)) -> 16.95 | K17: =J17 -> 16.95 | L17: =K17 -> 16.95 | M17: =L17 -> 16.95 | N17: =M17 -> 16.95
B18: meal_lime | C18: =SUM(SUMIFS('Discover Data'!$F:$F,'Discover Data'!$H:$H,$B18,'Discover Data'!$B:$B,'Detailed Summary'!C$2)) -> 0 | D18: =SUM(SUMIFS('Discover Data'!$F:$F,'Discover Data'!$H:$H,$B18,'Discover Data'!$B:$B,'Detailed Summary'!D$2)) -> 0 | E18: =SUM(SUMIFS('Discover Data'!$F:$F,'Discover Data'!$H:$H,$B18,'Discover Data'!$B:$B,'Detailed Summary'!E$2)) -> 0 | F18: =SUM(SUMIFS('Discover Data'!$F:$F,'Discover Data'!$H:$H,$B18,'Discover Data'!$B:$B,'Detailed Summary'!F$2)) -> 0 | G18: =SUM(SUMIFS('Discover Data'!$F:$F,'Discover Data'!$H:$H,$B18,'Discover Data'!$B:$B,'Detailed Summary'!G$2)) -> 3.17 | H18: =SUM(SUMIFS('Discover Data'!$F:$F,'Discover Data'!$H:$H,$B18,'Discover Data'!$B:$B,'Detailed Summary'!H$2)) -> 0 | I18: =SUM(SUMIFS('Discover Data'!$F:$F,'Discover Data'!$H:$H,$B18,'Discover Data'!$B:$B,'Detailed Summary'!I$2)) -> 0 | J18: =SUM(SUMIFS('Discover Data'!$F:$F,'Discover Data'!$H:$H,$B18,'Discover Data'!$B:$B,'Detailed Summary'!J$2)) -> 0 | ... N18: =SUM(SUMIFS('Discover Data'!$F:$F,'Discover Data'!$H:$H,$B18,'Discover Data'!$B:$B,'Detailed Summary'!N$2)) -> 0
B19: medium | C19: =SUM(SUMIFS('Discover Data'!$F:$F,'Discover Data'!$H:$H,$B19,'Discover Data'!$B:$B,'Detailed Summary'!C$2)) -> 0 | D19: =SUM(SUMIFS('Discover Data'!$F:$F,'Discover Data'!$H:$H,$B19,'Discover Data'!$B:$B,'Detailed Summary'!D$2)) -> 0 | E19: =SUM(SUMIFS('Discover Data'!$F:$F,'Discover Data'!$H:$H,$B19,'Discover Data'!$B:$B,'Detailed Summary'!E$2)) -> 0 | F19: =SUM(SUMIFS('Discover Data'!$F:$F,'Discover Data'!$H:$H,$B19,'Discover Data'!$B:$B,'Detailed Summary'!F$2)) -> 0 | G19: =SUM(SUMIFS('Discover Data'!$F:$F,'Discover Data'!$H:$H,$B19,'Discover Data'!$B:$B,'Detailed Summary'!G$2)) -> 0 | H19: =SUM(SUMIFS('Discover Data'!$F:$F,'Discover Data'!$H:$H,$B19,'Discover Data'!$B:$B,'Detailed Summary'!H$2)) -> 0 | I19: =SUM(SUMIFS('Discover Data'!$F:$F,'Discover Data'!$H:$H,$B19,'Discover Data'!$B:$B,'Detailed Summary'!I$2)) -> 0 | J19: =SUM(SUMIFS('Discover Data'!$F:$F,'Discover Data'!$H:$H,$B19,'Discover Data'!$B:$B,'Detailed Summary'!J$2)) -> 0 | ... N19: =SUM(SUMIFS('Discover Data'!$F:$F,'Discover Data'!$H:$H,$B19,'Discover Data'!$B:$B,'Detailed Summary'!N$2)) -> 0
B20: nba_league_pass | C20: =SUM(SUMIFS('Discover Data'!$F:$F,'Discover Data'!$H:$H,$B20,'Discover Data'!$B:$B,'Detailed Summary'!C$2)) -> 0 | D20: =SUM(SUMIFS('Discover Data'!$F:$F,'Discover Data'!$H:$H,$B20,'Discover Data'!$B:$B,'Detailed Summary'!D$2)) -> 142 | E20: =SUM(SUMIFS('Discover Data'!$F:$F,'Discover Data'!$H:$H,$B20,'Discover Data'!$B:$B,'Detailed Summary'!E$2)) -> 0 | F20: =SUM(SUMIFS('Discover Data'!$F:$F,'Discover Data'!$H:$H,$B20,'Discover Data'!$B:$B,'Detailed Summary'!F$2)) -> 0 | G20: =SUM(SUMIFS('Discover Data'!$F:$F,'Discover Data'!$H:$H,$B20,'Discover Data'!$B:$B,'Detailed Summary'!G$2)) -> 0 | H20: =SUM(SUMIFS('Discover Data'!$F:$F,'Discover Data'!$H:$H,$B20,'Discover Data'!$B:$B,'Detailed Summary'!H$2)) -> 0 | I20: =SUM(SUMIFS('Discover Data'!$F:$F,'Discover Data'!$H:$H,$B20,'Discover Data'!$B:$B,'Detailed Summary'!I$2)) -> 0 | J20: =SUM(SUMIFS('Discover Data'!$F:$F,'Discover Data'!$H:$H,$B20,'Discover Data'!$B:$B,'Detailed Summary'!J$2)) -> 0 | ... N20: =SUM(SUMIFS('Discover Data'!$F:$F,'Discover Data'!$H:$H,$B20,'Discover Data'!$B:$B,'Detailed Summary'!N$2)) -> 0
B21: netflix | C21: =SUM(SUMIFS('Discover Data'!$F:$F,'Discover Data'!$H:$H,$B21,'Discover Data'!$B:$B,'Detailed Summary'!C$2)) -> 10.59 | D21: =SUM(SUMIFS('Discover Data'!$F:$F,'Discover Data'!$H:$H,$B21,'Discover Data'!$B:$B,'Detailed Summary'!D$2)) -> 10.59 | E21: =SUM(SUMIFS('Discover Data'!$F:$F,'Discover Data'!$H:$H,$B21,'Discover Data'!$B:$B,'Detailed Summary'!E$2)) -> 10.59 | F21: =SUM(SUMIFS('Discover Data'!$F:$F,'Discover Data'!$H:$H,$B21,'Discover Data'!$B:$B,'Detailed Summary'!F$2)) -> 10.59 | G21: =SUM(SUMIFS('Discover Data'!$F:$F,'Discover Data'!$H:$H,$B21,'Discover Data'!$B:$B,'Detailed Summary'!G$2)) -> 10.59 | H21: =SUM(SUMIFS('Discover Data'!$F:$F,'Discover Data'!$H:$H,$B21,'Discover Data'!$B:$B,'Detailed Summary'!H$2)) -> 10.59 | I21: =SUM(SUMIFS('Discover Data'!$F:$F,'Discover Data'!$H:$H,$B21,'Discover Data'!$B:$B,'Detailed Summary'!I$2)) -> 10.59 | J21: =SUM(SUMIFS('Discover Data'!$F:$F,'Discover Data'!$H:$H,$B21,'Discover Data'!$B:$B,'Detailed Summary'!J$2)) -> 10.59 | ... N21: =SUM(SUMIFS('Discover Data'!$F:$F,'Discover Data'!$H:$H,$B21,'Discover Data'!$B:$B,'Detailed Summary'!N$2)) -> 0
B22: obsidian | C22: =SUM(SUMIFS('Discover Data'!$F:$F,'Discover Data'!$H:$H,$B22,'Discover Data'!$B:$B,'Detailed Summary'!C$2)) -> 10 | D22: =SUM(SUMIFS('Discover Data'!$F:$F,'Discover Data'!$H:$H,$B22,'Discover Data'!$B:$B,'Detailed Summary'!D$2)) -> 10 | E22: =SUM(SUMIFS('Discover Data'!$F:$F,'Discover Data'!$H:$H,$B22,'Discover Data'!$B:$B,'Detailed Summary'!E$2)) -> 10 | F22: =SUM(SUMIFS('Discover Data'!$F:$F,'Discover Data'!$H:$H,$B22,'Discover Data'!$B:$B,'Detailed Summary'!F$2)) -> 10 | G22: =SUM(SUMIFS('Discover Data'!$F:$F,'Discover Data'!$H:$H,$B22,'Discover Data'!$B:$B,'Detailed Summary'!G$2)) -> 0 | H22: =SUM(SUMIFS('Discover Data'!$F:$F,'Discover Data'!$H:$H,$B22,'Discover Data'!$B:$B,'Detailed Summary'!H$2)) -> 0 | I22: =SUM(SUMIFS('Discover Data'!$F:$F,'Discover Data'!$H:$H,$B22,'Discover Data'!$B:$B,'Detailed Summary'!I$2)) -> 0 | J22: =SUM(SUMIFS('Discover Data'!$F:$F,'Discover Data'!$H:$H,$B22,'Discover Data'!$B:$B,'Detailed Summary'!J$2)) -> 0 | ... N22: =SUM(SUMIFS('Discover Data'!$F:$F,'Discover Data'!$H:$H,$B22,'Discover Data'!$B:$B,'Detailed Summary'!N$2)) -> 0
B23: paramount_plus | C23: =SUM(SUMIFS('Discover Data'!$F:$F,'Discover Data'!$H:$H,$B23,'Discover Data'!$B:$B,'Detailed Summary'!C$2)) -> 0 | D23: =SUM(SUMIFS('Discover Data'!$F:$F,'Discover Data'!$H:$H,$B23,'Discover Data'!$B:$B,'Detailed Summary'!D$2)) -> 5.42 | E23: =SUM(SUMIFS('Discover Data'!$F:$F,'Discover Data'!$H:$H,$B23,'Discover Data'!$B:$B,'Detailed Summary'!E$2)) -> 5.42 | F23: =SUM(SUMIFS('Discover Data'!$F:$F,'Discover Data'!$H:$H,$B23,'Discover Data'!$B:$B,'Detailed Summary'!F$2)) -> 0 | G23: =SUM(SUMIFS('Discover Data'!$F:$F,'Discover Data'!$H:$H,$B23,'Discover Data'!$B:$B,'Detailed Summary'!G$2)) -> 0 | H23: =SUM(SUMIFS('Discover Data'!$F:$F,'Discover Data'!$H:$H,$B23,'Discover Data'!$B:$B,'Detailed Summary'!H$2)) -> 0 | I23: =SUM(SUMIFS('Discover Data'!$F:$F,'Discover Data'!$H:$H,$B23,'Discover Data'!$B:$B,'Detailed Summary'!I$2)) -> 0 | J23: =SUM(SUMIFS('Discover Data'!$F:$F,'Discover Data'!$H:$H,$B23,'Discover Data'!$B:$B,'Detailed Summary'!J$2)) -> 0 | ... N23: =SUM(SUMIFS('Discover Data'!$F:$F,'Discover Data'!$H:$H,$B23,'Discover Data'!$B:$B,'Detailed Summary'!N$2)) -> 0
B24: spotify | C24: =SUM(SUMIFS('Discover Data'!$F:$F,'Discover Data'!$H:$H,$B24,'Discover Data'!$B:$B,'Detailed Summary'!C$2)) -> 4.99 | D24: =SUM(SUMIFS('Discover Data'!$F:$F,'Discover Data'!$H:$H,$B24,'Discover Data'!$B:$B,'Detailed Summary'!D$2)) -> 4.99 | E24: =SUM(SUMIFS('Discover Data'!$F:$F,'Discover Data'!$H:$H,$B24,'Discover Data'!$B:$B,'Detailed Summary'!E$2)) -> 4.99 | F24: =SUM(SUMIFS('Discover Data'!$F:$F,'Discover Data'!$H:$H,$B24,'Discover Data'!$B:$B,'Detailed Summary'!F$2)) -> 4.99 | G24: =SUM(SUMIFS('Discover Data'!$F:$F,'Discover Data'!$H:$H,$B24,'Discover Data'!$B:$B,'Detailed Summary'!G$2)) -> 4.99 | H24: =SUM(SUMIFS('Discover Data'!$F:$F,'Discover Data'!$H:$H,$B24,'Discover Data'!$B:$B,'Detailed Summary'!H$2)) -> 4.99 | I24: =SUM(SUMIFS('Discover Data'!$F:$F,'Discover Data'!$H:$H,$B24,'Discover Data'!$B:$B,'Detailed Summary'!I$2)) -> 4.99 | J24: =SUM(SUMIFS('Discover Data'!$F:$F,'Discover Data'!$H:$H,$B24,'Discover Data'!$B:$B,'Detailed Summary'!J$2)) -> 4.99 | ... N24: =SUM(SUMIFS('Discover Data'!$F:$F,'Discover Data'!$H:$H,$B24,'Discover Data'!$B:$B,'Detailed Summary'!N$2)) -> 5.99
B25: youtube_tv | C25: =SUM(SUMIFS('Discover Data'!$F:$F,'Discover Data'!$H:$H,$B25,'Discover Data'!$B:$B,'Detailed Summary'!C$2)) -> 80.88 | D25: =SUM(SUMIFS('Discover Data'!$F:$F,'Discover Data'!$H:$H,$B25,'Discover Data'!$B:$B,'Detailed Summary'!D$2)) -> 80.88 | E25: =SUM(SUMIFS('Discover Data'!$F:$F,'Discover Data'!$H:$H,$B25,'Discover Data'!$B:$B,'Detailed Summary'!E$2)) -> 80.88 | F25: =SUM(SUMIFS('Discover Data'!$F:$F,'Discover Data'!$H:$H,$B25,'Discover Data'!$B:$B,'Detailed Summary'!F$2)) -> 80.88 | G25: =SUM(SUMIFS('Discover Data'!$F:$F,'Discover Data'!$H:$H,$B25,'Discover Data'!$B:$B,'Detailed Summary'!G$2)) -> 88.88 | H25: =SUM(SUMIFS('Discover Data'!$F:$F,'Discover Data'!$H:$H,$B25,'Discover Data'!$B:$B,'Detailed Summary'!H$2)) -> 88.88 | I25: =SUM(SUMIFS('Discover Data'!$F:$F,'Discover Data'!$H:$H,$B25,'Discover Data'!$B:$B,'Detailed Summary'!I$2)) -> 0 | J25: =SUM(SUMIFS('Discover Data'!$F:$F,'Discover Data'!$H:$H,$B25,'Discover Data'!$B:$B,'Detailed Summary'!J$2)) -> 0 | ... N25: =SUM(SUMIFS('Discover Data'!$F:$F,'Discover Data'!$H:$H,$B25,'Discover Data'!$B:$B,'Detailed Summary'!N$2)) -> 0
A26: Health and Medical | B26: onepass | C26: =SUM(SUMIFS('Discover Data'!$F:$F,'Discover Data'!$H:$H,$B26,'Discover Data'!$B:$B,'Detailed Summary'!C$2)) -> 0 | D26: =SUM(SUMIFS('Discover Data'!$F:$F,'Discover Data'!$H:$H,$B26,'Discover Data'!$B:$B,'Detailed Summary'!D$2)) -> 0 | E26: =SUM(SUMIFS('Discover Data'!$F:$F,'Discover Data'!$H:$H,$B26,'Discover Data'!$B:$B,'Detailed Summary'!E$2)) -> 289.1 | F26: =SUM(SUMIFS('Discover Data'!$F:$F,'Discover Data'!$H:$H,$B26,'Discover Data'!$B:$B,'Detailed Summary'!F$2)) -> 264.1 | G26: =SUM(SUMIFS('Discover Data'!$F:$F,'Discover Data'!$H:$H,$B26,'Discover Data'!$B:$B,'Detailed Summary'!G$2)) -> 264.1 | H26: =SUM(SUMIFS('Discover Data'!$F:$F,'Discover Data'!$H:$H,$B26,'Discover Data'!$B:$B,'Detailed Summary'!H$2)) -> 264.1 | I26: =SUM(SUMIFS('Discover Data'!$F:$F,'Discover Data'!$H:$H,$B26,'Discover Data'!$B:$B,'Detailed Summary'!I$2)) -> 264.1 | J26: =SUM(SUMIFS('Discover Data'!$F:$F,'Discover Data'!$H:$H,$B26,'Discover Data'!$B:$B,'Detailed Summary'!J$2)) -> 264.1 | ... N26: =SUM(SUMIFS('Discover Data'!$F:$F,'Discover Data'!$H:$H,$B26,'Discover Data'!$B:$B,'Detailed Summary'!N$2)) -> 264.1
B27: physical_therapy | C27: =SUM(SUMIFS('Discover Data'!$F:$F,'Discover Data'!$H:$H,$B27,'Discover Data'!$B:$B,'Detailed Summary'!C$2)) -> 0 | D27: =SUM(SUMIFS('Discover Data'!$F:$F,'Discover Data'!$H:$H,$B27,'Discover Data'!$B:$B,'Detailed Summary'!D$2)) -> 299.32 | E27: =SUM(SUMIFS('Discover Data'!$F:$F,'Discover Data'!$H:$H,$B27,'Discover Data'!$B:$B,'Detailed Summary'!E$2)) -> 218 | F27: =SUM(SUMIFS('Discover Data'!$F:$F,'Discover Data'!$H:$H,$B27,'Discover Data'!$B:$B,'Detailed Summary'!F$2)) -> 0 | G27: =SUM(SUMIFS('Discover Data'!$F:$F,'Discover Data'!$H:$H,$B27,'Discover Data'!$B:$B,'Detailed Summary'!G$2)) -> 0 | H27: =SUM(SUMIFS('Discover Data'!$F:$F,'Discover Data'!$H:$H,$B27,'Discover Data'!$B:$B,'Detailed Summary'!H$2)) -> 0 | I27: =SUM(SUMIFS('Discover Data'!$F:$F,'Discover Data'!$H:$H,$B27,'Discover Data'!$B:$B,'Detailed Summary'!I$2)) -> 0 | J27: =SUM(SUMIFS('Discover Data'!$F:$F,'Discover Data'!$H:$H,$B27,'Discover Data'!$B:$B,'Detailed Summary'!J$2)) -> 0 | ... N27: =SUM(SUMIFS('Discover Data'!$F:$F,'Discover Data'!$H:$H,$B27,'Discover Data'!$B:$B,'Detailed Summary'!N$2)) -> 0
B28: vision | C28: =SUM(SUMIFS('Discover Data'!$F:$F,'Discover Data'!$H:$H,$B28,'Discover Data'!$B:$B,'Detailed Summary'!C$2)) -> 106.5 | D28: =SUM(SUMIFS('Discover Data'!$F:$F,'Discover Data'!$H:$H,$B28,'Discover Data'!$B:$B,'Detailed Summary'!D$2)) -> 0 | E28: =SUM(SUMIFS('Discover Data'!$F:$F,'Discover Data'!$H:$H,$B28,'Discover Data'!$B:$B,'Detailed Summary'!E$2)) -> 938.85 | F28: =SUM(SUMIFS('Discover Data'!$F:$F,'Discover Data'!$H:$H,$B28,'Discover Data'!$B:$B,'Detailed Summary'!F$2)) -> 0 | G28: =SUM(SUMIFS('Discover Data'!$F:$F,'Discover Data'!$H:$H,$B28,'Discover Data'!$B:$B,'Detailed Summary'!G$2)) -> 0 | H28: =SUM(SUMIFS('Discover Data'!$F:$F,'Discover Data'!$H:$H,$B28,'Discover Data'!$B:$B,'Detailed Summary'!H$2)) -> 0 | I28: =SUM(SUMIFS('Discover Data'!$F:$F,'Discover Data'!$H:$H,$B28,'Discover Data'!$B:$B,'Detailed Summary'!I$2)) -> 243.74 | J28: =SUM(SUMIFS('Discover Data'!$F:$F,'Discover Data'!$H:$H,$B28,'Discover Data'!$B:$B,'Detailed Summary'!J$2)) -> 0 | ... N28: =SUM(SUMIFS('Discover Data'!$F:$F,'Discover Data'!$H:$H,$B28,'Discover Data'!$B:$B,'Detailed Summary'!N$2)) -> 0
B29: dental | C29: =SUM(SUMIFS('Discover Data'!$F:$F,'Discover Data'!$H:$H,$B29,'Discover Data'!$B:$B,'Detailed Summary'!C$2)) -> 549.6 | D29: =SUM(SUMIFS('Discover Data'!$F:$F,'Discover Data'!$H:$H,$B29,'Discover Data'!$B:$B,'Detailed Summary'!D$2)) -> 0 | E29: =SUM(SUMIFS('Discover Data'!$F:$F,'Discover Data'!$H:$H,$B29,'Discover Data'!$B:$B,'Detailed Summary'!E$2)) -> 0 | F29: =SUM(SUMIFS('Discover Data'!$F:$F,'Discover Data'!$H:$H,$B29,'Discover Data'!$B:$B,'Detailed Summary'!F$2)) -> 0 | G29: =SUM(SUMIFS('Discover Data'!$F:$F,'Discover Data'!$H:$H,$B29,'Discover Data'!$B:$B,'Detailed Summary'!G$2)) -> 0 | H29: =SUM(SUMIFS('Discover Data'!$F:$F,'Discover Data'!$H:$H,$B29,'Discover Data'!$B:$B,'Detailed Summary'!H$2)) -> 0 | I29: =SUM(SUMIFS('Discover Data'!$F:$F,'Discover Data'!$H:$H,$B29,'Discover Data'!$B:$B,'Detailed Summary'!I$2)) -> 0 | J29: =SUM(SUMIFS('Discover Data'!$F:$F,'Discover Data'!$H:$H,$B29,'Discover Data'!$B:$B,'Detailed Summary'!J$2)) -> 0 | ... N29: =SUM(SUMIFS('Discover Data'!$F:$F,'Discover Data'!$H:$H,$B29,'Discover Data'!$B:$B,'Detailed Summary'!N$2)) -> 0
B30: Other Health | C30: {=SUM(SUMIFS('Discover Data'!$F:$F,'Discover Data'!$H:$H,{"barbershop";"fitness"},'Discover Data'!$B:$B,'Detailed Summary'!C$2))} -> 1.75 | D30: {=SUM(SUMIFS('Discover Data'!$F:$F,'Discover Data'!$H:$H,{"barbershop";"fitness"},'Discover Data'!$B:$B,'Detailed Summary'!D$2))} -> 152.89 | E30: {=SUM(SUMIFS('Discover Data'!$F:$F,'Discover Data'!$H:$H,{"barbershop";"fitness"},'Discover Data'!$B:$B,'Detailed Summary'!E$2))} -> 211.63 | F30: {=SUM(SUMIFS('Discover Data'!$F:$F,'Discover Data'!$H:$H,{"barbershop";"fitness"},'Discover Data'!$B:$B,'Detailed Summary'!F$2))} -> 96.3 | G30: {=SUM(SUMIFS('Discover Data'!$F:$F,'Discover Data'!$H:$H,{"barbershop";"fitness"},'Discover Data'!$B:$B,'Detailed Summary'!G$2))} -> 478.86 | H30: {=SUM(SUMIFS('Discover Data'!$F:$F,'Discover Data'!$H:$H,{"barbershop";"fitness"},'Discover Data'!$B:$B,'Detailed Summary'!H$2))} -> 0 | I30: {=SUM(SUMIFS('Discover Data'!$F:$F,'Discover Data'!$H:$H,{"barbershop";"fitness"},'Discover Data'!$B:$B,'Detailed Summary'!I$2))} -> 14.87 | J30: {=SUM(SUMIFS('Discover Data'!$F:$F,'Discover Data'!$H:$H,{"barbershop";"fitness"},'Discover Data'!$B:$B,'Detailed Summary'!J$2))} -> 0 | ... N30: {=SUM(SUMIFS('Discover Data'!$F:$F,'Discover Data'!$H:$H,{"barbershop";"fitness"},'Discover Data'!$B:$B,'Detailed Summary'!N$2))} -> 0
B31: medical | C31: =SUM(SUMIFS('Discover Data'!$F:$F,'Discover Data'!$H:$H,$B31,'Discover Data'!$B:$B,'Detailed Summary'!C$2)) -> 0 | D31: =SUM(SUMIFS('Discover Data'!$F:$F,'Discover Data'!$H:$H,$B31,'Discover Data'!$B:$B,'Detailed Summary'!D$2)) -> 0 | E31: =SUM(SUMIFS('Discover Data'!$F:$F,'Discover Data'!$H:$H,$B31,'Discover Data'!$B:$B,'Detailed Summary'!E$2)) -> 0 | F31: =SUM(SUMIFS('Discover Data'!$F:$F,'Discover Data'!$H:$H,$B31,'Discover Data'!$B:$B,'Detailed Summary'!F$2)) -> 66.53 | G31: =SUM(SUMIFS('Discover Data'!$F:$F,'Discover Data'!$H:$H,$B31,'Discover Data'!$B:$B,'Detailed Summary'!G$2)) -> 48.1 | H31: =SUM(SUMIFS('Discover Data'!$F:$F,'Discover Data'!$H:$H,$B31,'Discover Data'!$B:$B,'Detailed Summary'!H$2)) -> 0 | I31: =SUM(SUMIFS('Discover Data'!$F:$F,'Discover Data'!$H:$H,$B31,'Discover Data'!$B:$B,'Detailed Summary'!I$2)) -> 22.96 | J31: =SUM(SUMIFS('Discover Data'!$F:$F,'Discover Data'!$H:$H,$B31,'Discover Data'!$B:$B,'Detailed Summary'!J$2)) -> 0 | ... N31: =SUM(SUMIFS('Discover Data'!$F:$F,'Discover Data'!$H:$H,$B31,'Discover Data'!$B:$B,'Detailed Summary'!N$2)) -> 40.65
B32: Sports Consumables | C32: {=SUM(SUMIFS('Discover Data'!$F:$F,'Discover Data'!$H:$H,{"sports_stuff";"sports_gear"},'Discover Data'!$B:$B,'Detailed Summary'!C$2))} -> 0 | D32: {=SUM(SUMIFS('Discover Data'!$F:$F,'Discover Data'!$H:$H,{"sports_stuff";"sports_gear"},'Discover Data'!$B:$B,'Detailed Summary'!D$2))} -> 43.34 | E32: {=SUM(SUMIFS('Discover Data'!$F:$F,'Discover Data'!$H:$H,{"sports_stuff";"sports_gear"},'Discover Data'!$B:$B,'Detailed Summary'!E$2))} -> 105.41 | F32: {=SUM(SUMIFS('Discover Data'!$F:$F,'Discover Data'!$H:$H,{"sports_stuff";"sports_gear"},'Discover Data'!$B:$B,'Detailed Summary'!F$2))} -> 0 | G32: {=SUM(SUMIFS('Discover Data'!$F:$F,'Discover Data'!$H:$H,{"sports_stuff";"sports_gear"},'Discover Data'!$B:$B,'Detailed Summary'!G$2))} -> 0 | H32: {=SUM(SUMIFS('Discover Data'!$F:$F,'Discover Data'!$H:$H,{"sports_stuff";"sports_gear"},'Discover Data'!$B:$B,'Detailed Summary'!H$2))} -> 0 | I32: {=SUM(SUMIFS('Discover Data'!$F:$F,'Discover Data'!$H:$H,{"sports_stuff";"sports_gear"},'Discover Data'!$B:$B,'Detailed Summary'!I$2))} -> 0 | J32: {=SUM(SUMIFS('Discover Data'!$F:$F,'Discover Data'!$H:$H,{"sports_stuff";"sports_gear"},'Discover Data'!$B:$B,'Detailed Summary'!J$2))} -> 0 | ... N32: {=SUM(SUMIFS('Discover Data'!$F:$F,'Discover Data'!$H:$H,{"sports_stuff";"sports_gear"},'Discover Data'!$B:$B,'Detailed Summary'!N$2))} -> 0
A33: Food | B33: Grocery | C33: {=SUM(SUMIFS('Discover Data'!$F:$F,'Discover Data'!$H:$H,{"groceries";"live_nba";"concerts"},'Discover Data'!$B:$B,'Detailed Summary'!C$2))} -> 216.14 | D33: {=SUM(SUMIFS('Discover Data'!$F:$F,'Discover Data'!$H:$H,{"groceries";"live_nba";"concerts"},'Discover Data'!$B:$B,'Detailed Summary'!D$2))} -> 298.47 | E33: {=SUM(SUMIFS('Discover Data'!$F:$F,'Discover Data'!$H:$H,{"groceries";"live_nba";"concerts"},'Discover Data'!$B:$B,'Detailed Summary'!E$2))} -> 600.37 | F33: {=SUM(SUMIFS('Discover Data'!$F:$F,'Discover Data'!$H:$H,{"groceries";"live_nba";"concerts"},'Discover Data'!$B:$B,'Detailed Summary'!F$2))} -> 457.06 | G33: {=SUM(SUMIFS('Discover Data'!$F:$F,'Discover Data'!$H:$H,{"groceries";"live_nba";"concerts"},'Discover Data'!$B:$B,'Detailed Summary'!G$2))} -> 433.42 | H33: {=SUM(SUMIFS('Discover Data'!$F:$F,'Discover Data'!$H:$H,{"groceries";"live_nba";"concerts"},'Discover Data'!$B:$B,'Detailed Summary'!H$2))} -> 91.74 | I33: {=SUM(SUMIFS('Discover Data'!$F:$F,'Discover Data'!$H:$H,{"groceries";"live_nba";"concerts"},'Discover Data'!$B:$B,'Detailed Summary'!I$2))} -> 155.46 | J33: {=SUM(SUMIFS('Discover Data'!$F:$F,'Discover Data'!$H:$H,{"groceries";"live_nba";"concerts"},'Discover Data'!$B:$B,'Detailed Summary'!J$2))} -> 338.97 | ... N33: {=SUM(SUMIFS('Discover Data'!$F:$F,'Discover Data'!$H:$H,{"groceries";"live_nba";"concerts"},'Discover Data'!$B:$B,'Detailed Summary'!N$2))} -> 503.29
B34: Eating Out | C34: {=SUM(SUMIFS('Discover Data'!$F:$F,'Discover Data'!$H:$H,{"coffee";"fast_food";"restaurant"},'Discover Data'!$B:$B,'Detailed Summary'!C$2))} -> 419.14 | D34: {=SUM(SUMIFS('Discover Data'!$F:$F,'Discover Data'!$H:$H,{"coffee";"fast_food";"restaurant"},'Discover Data'!$B:$B,'Detailed Summary'!D$2))} -> 644.88 | E34: {=SUM(SUMIFS('Discover Data'!$F:$F,'Discover Data'!$H:$H,{"coffee";"fast_food";"restaurant"},'Discover Data'!$B:$B,'Detailed Summary'!E$2))} -> 546.74 | F34: {=SUM(SUMIFS('Discover Data'!$F:$F,'Discover Data'!$H:$H,{"coffee";"fast_food";"restaurant"},'Discover Data'!$B:$B,'Detailed Summary'!F$2))} -> 233.12 | G34: {=SUM(SUMIFS('Discover Data'!$F:$F,'Discover Data'!$H:$H,{"coffee";"fast_food";"restaurant"},'Discover Data'!$B:$B,'Detailed Summary'!G$2))} -> 628.16 | H34: {=SUM(SUMIFS('Discover Data'!$F:$F,'Discover Data'!$H:$H,{"coffee";"fast_food";"restaurant"},'Discover Data'!$B:$B,'Detailed Summary'!H$2))} -> 53.32 | I34: {=SUM(SUMIFS('Discover Data'!$F:$F,'Discover Data'!$H:$H,{"coffee";"fast_food";"restaurant"},'Discover Data'!$B:$B,'Detailed Summary'!I$2))} -> 62.19 | J34: {=SUM(SUMIFS('Discover Data'!$F:$F,'Discover Data'!$H:$H,{"coffee";"fast_food";"restaurant"},'Discover Data'!$B:$B,'Detailed Summary'!J$2))} -> 275.12 | ... N34: {=SUM(SUMIFS('Discover Data'!$F:$F,'Discover Data'!$H:$H,{"coffee";"fast_food";"restaurant"},'Discover Data'!$B:$B,'Detailed Summary'!N$2))} -> 600.63
A35: Shopping | B35: clothing | C35: {=SUM(SUMIFS('Discover Data'!$F:$F,'Discover Data'!$H:$H,{"clothing";"motor_gear";""},'Discover Data'!$B:$B,'Detailed Summary'!C$2))} -> 16.4 | D35: {=SUM(SUMIFS('Discover Data'!$F:$F,'Discover Data'!$H:$H,{"clothing";"motor_gear";""},'Discover Data'!$B:$B,'Detailed Summary'!D$2))} -> 138.88 | E35: {=SUM(SUMIFS('Discover Data'!$F:$F,'Discover Data'!$H:$H,{"clothing";"motor_gear";""},'Discover Data'!$B:$B,'Detailed Summary'!E$2))} -> 347.38 | F35: {=SUM(SUMIFS('Discover Data'!$F:$F,'Discover Data'!$H:$H,{"clothing";"motor_gear";""},'Discover Data'!$B:$B,'Detailed Summary'!F$2))} -> 40 | G35: {=SUM(SUMIFS('Discover Data'!$F:$F,'Discover Data'!$H:$H,{"clothing";"motor_gear";""},'Discover Data'!$B:$B,'Detailed Summary'!G$2))} -> 513.89 | H35: {=SUM(SUMIFS('Discover Data'!$F:$F,'Discover Data'!$H:$H,{"clothing";"motor_gear";""},'Discover Data'!$B:$B,'Detailed Summary'!H$2))} -> 0 | I35: {=SUM(SUMIFS('Discover Data'!$F:$F,'Discover Data'!$H:$H,{"clothing";"motor_gear";""},'Discover Data'!$B:$B,'Detailed Summary'!I$2))} -> 0 | J35: {=SUM(SUMIFS('Discover Data'!$F:$F,'Discover Data'!$H:$H,{"clothing";"motor_gear";""},'Discover Data'!$B:$B,'Detailed Summary'!J$2))} -> 0 | ... N35: {=SUM(SUMIFS('Discover Data'!$F:$F,'Discover Data'!$H:$H,{"clothing";"motor_gear";""},'Discover Data'!$B:$B,'Detailed Summary'!N$2))} -> 0
B36: Electronics | C36: {=SUM(SUMIFS('Discover Data'!$F:$F,'Discover Data'!$H:$H,{"electronics";"";""},'Discover Data'!$B:$B,'Detailed Summary'!C$2))} -> 0 | D36: {=SUM(SUMIFS('Discover Data'!$F:$F,'Discover Data'!$H:$H,{"electronics";"";""},'Discover Data'!$B:$B,'Detailed Summary'!D$2))} -> 225 | E36: {=SUM(SUMIFS('Discover Data'!$F:$F,'Discover Data'!$H:$H,{"electronics";"";""},'Discover Data'!$B:$B,'Detailed Summary'!E$2))} -> 0 | F36: {=SUM(SUMIFS('Discover Data'!$F:$F,'Discover Data'!$H:$H,{"electronics";"";""},'Discover Data'!$B:$B,'Detailed Summary'!F$2))} -> 157.47 | G36: {=SUM(SUMIFS('Discover Data'!$F:$F,'Discover Data'!$H:$H,{"electronics";"";""},'Discover Data'!$B:$B,'Detailed Summary'!G$2))} -> 0 | H36: {=SUM(SUMIFS('Discover Data'!$F:$F,'Discover Data'!$H:$H,{"electronics";"";""},'Discover Data'!$B:$B,'Detailed Summary'!H$2))} -> 0 | I36: {=SUM(SUMIFS('Discover Data'!$F:$F,'Discover Data'!$H:$H,{"electronics";"";""},'Discover Data'!$B:$B,'Detailed Summary'!I$2))} -> 0 | J36: {=SUM(SUMIFS('Discover Data'!$F:$F,'Discover Data'!$H:$H,{"electronics";"";""},'Discover Data'!$B:$B,'Detailed Summary'!J$2))} -> 413.59 | ... N36: {=SUM(SUMIFS('Discover Data'!$F:$F,'Discover Data'!$H:$H,{"electronics";"";""},'Discover Data'!$B:$B,'Detailed Summary'!N$2))} -> 0
B37: jewelry | C37: =SUM(SUMIFS('Discover Data'!$F:$F,'Discover Data'!$H:$H,$B37,'Discover Data'!$B:$B,'Detailed Summary'!C$2)) -> 102.02 | D37: =SUM(SUMIFS('Discover Data'!$F:$F,'Discover Data'!$H:$H,$B37,'Discover Data'!$B:$B,'Detailed Summary'!D$2)) -> 0 | E37: =SUM(SUMIFS('Discover Data'!$F:$F,'Discover Data'!$H:$H,$B37,'Discover Data'!$B:$B,'Detailed Summary'!E$2)) -> 255.88 | F37: =SUM(SUMIFS('Discover Data'!$F:$F,'Discover Data'!$H:$H,$B37,'Discover Data'!$B:$B,'Detailed Summary'!F$2)) -> 395.7 | G37: =SUM(SUMIFS('Discover Data'!$F:$F,'Discover Data'!$H:$H,$B37,'Discover Data'!$B:$B,'Detailed Summary'!G$2)) -> 0 | H37: =SUM(SUMIFS('Discover Data'!$F:$F,'Discover Data'!$H:$H,$B37,'Discover Data'!$B:$B,'Detailed Summary'!H$2)) -> 44.95 | I37: =SUM(SUMIFS('Discover Data'!$F:$F,'Discover Data'!$H:$H,$B37,'Discover Data'!$B:$B,'Detailed Summary'!I$2)) -> 0 | J37: =SUM(SUMIFS('Discover Data'!$F:$F,'Discover Data'!$H:$H,$B37,'Discover Data'!$B:$B,'Detailed Summary'!J$2)) -> 0 | ... N37: =SUM(SUMIFS('Discover Data'!$F:$F,'Discover Data'!$H:$H,$B37,'Discover Data'!$B:$B,'Detailed Summary'!N$2)) -> 0
B38: Other Shopping | C38: {=SUM(SUMIFS('Discover Data'!$F:$F,'Discover Data'!$H:$H,{"amazon";"conv_store";"everything_store";"home"},'Discover Data'!$B:$B,'Detailed Summary'!C$2))} -> 251.54 | D38: {=SUM(SUMIFS('Discover Data'!$F:$F,'Discover Data'!$H:$H,{"amazon";"conv_store";"everything_store";"home"},'Discover Data'!$B:$B,'Detailed Summary'!D$2))} -> 255.4 | E38: {=SUM(SUMIFS('Discover Data'!$F:$F,'Discover Data'!$H:$H,{"amazon";"conv_store";"everything_store";"home"},'Discover Data'!$B:$B,'Detailed Summary'!E$2))} -> 514.77 | F38: {=SUM(SUMIFS('Discover Data'!$F:$F,'Discover Data'!$H:$H,{"amazon";"conv_store";"everything_store";"home"},'Discover Data'!$B:$B,'Detailed Summary'!F$2))} -> 867.93 | G38: {=SUM(SUMIFS('Discover Data'!$F:$F,'Discover Data'!$H:$H,{"amazon";"conv_store";"everything_store";"home"},'Discover Data'!$B:$B,'Detailed Summary'!G$2))} -> 800.79 | H38: {=SUM(SUMIFS('Discover Data'!$F:$F,'Discover Data'!$H:$H,{"amazon";"conv_store";"everything_store";"home"},'Discover Data'!$B:$B,'Detailed Summary'!H$2))} -> 120.97 | I38: {=SUM(SUMIFS('Discover Data'!$F:$F,'Discover Data'!$H:$H,{"amazon";"conv_store";"everything_store";"home"},'Discover Data'!$B:$B,'Detailed Summary'!I$2))} -> 651.99 | J38: {=SUM(SUMIFS('Discover Data'!$F:$F,'Discover Data'!$H:$H,{"amazon";"conv_store";"everything_store";"home"},'Discover Data'!$B:$B,'Detailed Summary'!J$2))} -> 281.81 | ... N38: {=SUM(SUMIFS('Discover Data'!$F:$F,'Discover Data'!$H:$H,{"amazon";"conv_store";"everything_store";"home"},'Discover Data'!$B:$B,'Detailed Summary'!N$2))} -> 700.93
A39: Entertainment and Leisure | B39: Movies | C39: =SUMIFS('Discover Data'!$F:$F,'Discover Data'!$H:$H,"movies",'Discover Data'!$B:$B,'Detailed Summary'!C$2) -> 0 | D39: =SUMIFS('Discover Data'!$F:$F,'Discover Data'!$H:$H,"movies",'Discover Data'!$B:$B,'Detailed Summary'!D$2) -> 22.52 | E39: =SUMIFS('Discover Data'!$F:$F,'Discover Data'!$H:$H,"movies",'Discover Data'!$B:$B,'Detailed Summary'!E$2) -> 51.65 | F39: =SUMIFS('Discover Data'!$F:$F,'Discover Data'!$H:$H,"movies",'Discover Data'!$B:$B,'Detailed Summary'!F$2) -> 50 | G39: =SUMIFS('Discover Data'!$F:$F,'Discover Data'!$H:$H,"movies",'Discover Data'!$B:$B,'Detailed Summary'!G$2) -> 231.7 | H39: =SUMIFS('Discover Data'!$F:$F,'Discover Data'!$H:$H,"movies",'Discover Data'!$B:$B,'Detailed Summary'!H$2) -> 49.98 | I39: =SUMIFS('Discover Data'!$F:$F,'Discover Data'!$H:$H,"movies",'Discover Data'!$B:$B,'Detailed Summary'!I$2) -> 47.25 | J39: =SUMIFS('Discover Data'!$F:$F,'Discover Data'!$H:$H,"movies",'Discover Data'!$B:$B,'Detailed Summary'!J$2) -> 0 | ... N39: =SUMIFS('Discover Data'!$F:$F,'Discover Data'!$H:$H,"movies",'Discover Data'!$B:$B,'Detailed Summary'!N$2) -> 156.41
B40: Tickets | C40: {=SUM(SUMIFS('Discover Data'!$F:$F,'Discover Data'!$H:$H,{"live_event";"live_nba";"concerts";"convention";"vr_arcade"},'Discover Data'!$B:$B,'Detailed Summary'!C$2))} -> 311.8 | D40: {=SUM(SUMIFS('Discover Data'!$F:$F,'Discover Data'!$H:$H,{"live_event";"live_nba";"concerts";"convention";"vr_arcade"},'Discover Data'!$B:$B,'Detailed Summary'!D$2))} -> 441.41 | E40: {=SUM(SUMIFS('Discover Data'!$F:$F,'Discover Data'!$H:$H,{"live_event";"live_nba";"concerts";"convention";"vr_arcade"},'Discover Data'!$B:$B,'Detailed Summary'!E$2))} -> 360.73 | F40: {=SUM(SUMIFS('Discover Data'!$F:$F,'Discover Data'!$H:$H,{"live_event";"live_nba";"concerts";"convention";"vr_arcade"},'Discover Data'!$B:$B,'Detailed Summary'!F$2))} -> 36.23 | G40: {=SUM(SUMIFS('Discover Data'!$F:$F,'Discover Data'!$H:$H,{"live_event";"live_nba";"concerts";"convention";"vr_arcade"},'Discover Data'!$B:$B,'Detailed Summary'!G$2))} -> 0 | H40: {=SUM(SUMIFS('Discover Data'!$F:$F,'Discover Data'!$H:$H,{"live_event";"live_nba";"concerts";"convention";"vr_arcade"},'Discover Data'!$B:$B,'Detailed Summary'!H$2))} -> 0 | I40: {=SUM(SUMIFS('Discover Data'!$F:$F,'Discover Data'!$H:$H,{"live_event";"live_nba";"concerts";"convention";"vr_arcade"},'Discover Data'!$B:$B,'Detailed Summary'!I$2))} -> 0 | J40: {=SUM(SUMIFS('Discover Data'!$F:$F,'Discover Data'!$H:$H,{"live_event";"live_nba";"concerts";"convention";"vr_arcade"},'Discover Data'!$B:$B,'Detailed Summary'!J$2))} -> 108.09 | ... N40: {=SUM(SUMIFS('Discover Data'!$F:$F,'Discover Data'!$H:$H,{"live_event";"live_nba";"concerts";"convention";"vr_arcade"},'Discover Data'!$B:$B,'Detailed Summary'!N$2))} -> 361.6
B41: Social Events | C41: {=SUM(SUMIFS('Discover Data'!$F:$F,'Discover Data'!$H:$H,{"adity";"nick&julie";"Kaiya_Birthday"},'Discover Data'!$B:$B,'Detailed Summary'!C$2))} -> 0 | D41: {=SUM(SUMIFS('Discover Data'!$F:$F,'Discover Data'!$H:$H,{"adity";"nick&julie";"Kaiya_Birthday"},'Discover Data'!$B:$B,'Detailed Summary'!D$2))} -> 0 | E41: {=SUM(SUMIFS('Discover Data'!$F:$F,'Discover Data'!$H:$H,{"adity";"nick&julie";"Kaiya_Birthday"},'Discover Data'!$B:$B,'Detailed Summary'!E$2))} -> 0 | F41: {=SUM(SUMIFS('Discover Data'!$F:$F,'Discover Data'!$H:$H,{"adity";"nick&julie";"Kaiya_Birthday"},'Discover Data'!$B:$B,'Detailed Summary'!F$2))} -> 0 | G41: {=SUM(SUMIFS('Discover Data'!$F:$F,'Discover Data'!$H:$H,{"adity";"nick&julie";"Kaiya_Birthday"},'Discover Data'!$B:$B,'Detailed Summary'!G$2))} -> 182.72 | H41: {=SUM(SUMIFS('Discover Data'!$F:$F,'Discover Data'!$H:$H,{"adity";"nick&julie";"Kaiya_Birthday"},'Discover Data'!$B:$B,'Detailed Summary'!H$2))} -> 88.39 | I41: {=SUM(SUMIFS('Discover Data'!$F:$F,'Discover Data'!$H:$H,{"adity";"nick&julie";"Kaiya_Birthday"},'Discover Data'!$B:$B,'Detailed Summary'!I$2))} -> 0 | J41: {=SUM(SUMIFS('Discover Data'!$F:$F,'Discover Data'!$H:$H,{"adity";"nick&julie";"Kaiya_Birthday"},'Discover Data'!$B:$B,'Detailed Summary'!J$2))} -> 0 | ... N41: {=SUM(SUMIFS('Discover Data'!$F:$F,'Discover Data'!$H:$H,{"adity";"nick&julie";"Kaiya_Birthday"},'Discover Data'!$B:$B,'Detailed Summary'!N$2))} -> 0
B42: Other Entertainment | C42: {=SUM(SUMIFS('Discover Data'!$F:$F,'Discover Data'!$H:$H,{"museum";"vr_arcade";"video_games"},'Discover Data'!$B:$B,'Detailed Summary'!C$2))} -> 179.99 | D42: {=SUM(SUMIFS('Discover Data'!$F:$F,'Discover Data'!$H:$H,{"museum";"vr_arcade";"video_games"},'Discover Data'!$B:$B,'Detailed Summary'!D$2))} -> 63.37 | E42: {=SUM(SUMIFS('Discover Data'!$F:$F,'Discover Data'!$H:$H,{"museum";"vr_arcade";"video_games"},'Discover Data'!$B:$B,'Detailed Summary'!E$2))} -> 0 | F42: {=SUM(SUMIFS('Discover Data'!$F:$F,'Discover Data'!$H:$H,{"museum";"vr_arcade";"video_games"},'Discover Data'!$B:$B,'Detailed Summary'!F$2))} -> 174.91 | G42: {=SUM(SUMIFS('Discover Data'!$F:$F,'Discover Data'!$H:$H,{"museum";"vr_arcade";"video_games"},'Discover Data'!$B:$B,'Detailed Summary'!G$2))} -> 107.53 | H42: {=SUM(SUMIFS('Discover Data'!$F:$F,'Discover Data'!$H:$H,{"museum";"vr_arcade";"video_games"},'Discover Data'!$B:$B,'Detailed Summary'!H$2))} -> 0 | I42: {=SUM(SUMIFS('Discover Data'!$F:$F,'Discover Data'!$H:$H,{"museum";"vr_arcade";"video_games"},'Discover Data'!$B:$B,'Detailed Summary'!I$2))} -> 13.04 | J42: {=SUM(SUMIFS('Discover Data'!$F:$F,'Discover Data'!$H:$H,{"museum";"vr_arcade";"video_games"},'Discover Data'!$B:$B,'Detailed Summary'!J$2))} -> 59.99 | ... N42: {=SUM(SUMIFS('Discover Data'!$F:$F,'Discover Data'!$H:$H,{"museum";"vr_arcade";"video_games"},'Discover Data'!$B:$B,'Detailed Summary'!N$2))} -> 26.99
A43: Travel | B43: ride_share | C43: =SUM(SUMIFS('Discover Data'!$F:$F,'Discover Data'!$H:$H,$B43,'Discover Data'!$B:$B,'Detailed Summary'!C$2)) -> 223.84 | D43: =SUM(SUMIFS('Discover Data'!$F:$F,'Discover Data'!$H:$H,$B43,'Discover Data'!$B:$B,'Detailed Summary'!D$2)) -> 202.79 | E43: =SUM(SUMIFS('Discover Data'!$F:$F,'Discover Data'!$H:$H,$B43,'Discover Data'!$B:$B,'Detailed Summary'!E$2)) -> 114.37 | F43: =SUM(SUMIFS('Discover Data'!$F:$F,'Discover Data'!$H:$H,$B43,'Discover Data'!$B:$B,'Detailed Summary'!F$2)) -> 63.04 | G43: =SUM(SUMIFS('Discover Data'!$F:$F,'Discover Data'!$H:$H,$B43,'Discover Data'!$B:$B,'Detailed Summary'!G$2)) -> 681.13 | H43: =SUM(SUMIFS('Discover Data'!$F:$F,'Discover Data'!$H:$H,$B43,'Discover Data'!$B:$B,'Detailed Summary'!H$2)) -> 9.99 | I43: =SUM(SUMIFS('Discover Data'!$F:$F,'Discover Data'!$H:$H,$B43,'Discover Data'!$B:$B,'Detailed Summary'!I$2)) -> 0 | J43: =SUM(SUMIFS('Discover Data'!$F:$F,'Discover Data'!$H:$H,$B43,'Discover Data'!$B:$B,'Detailed Summary'!J$2)) -> 207.03 | ... N43: =SUM(SUMIFS('Discover Data'!$F:$F,'Discover Data'!$H:$H,$B43,'Discover Data'!$B:$B,'Detailed Summary'!N$2)) -> 0
B44: air_travel | C44: =SUM(SUMIFS('Discover Data'!$F:$F,'Discover Data'!$H:$H,$B44,'Discover Data'!$B:$B,'Detailed Summary'!C$2)) -> 736.81 | D44: =SUM(SUMIFS('Discover Data'!$F:$F,'Discover Data'!$H:$H,$B44,'Discover Data'!$B:$B,'Detailed Summary'!D$2)) -> 86 | E44: =SUM(SUMIFS('Discover Data'!$F:$F,'Discover Data'!$H:$H,$B44,'Discover Data'!$B:$B,'Detailed Summary'!E$2)) -> 0 | F44: =SUM(SUMIFS('Discover Data'!$F:$F,'Discover Data'!$H:$H,$B44,'Discover Data'!$B:$B,'Detailed Summary'!F$2)) -> 210 | G44: =SUM(SUMIFS('Discover Data'!$F:$F,'Discover Data'!$H:$H,$B44,'Discover Data'!$B:$B,'Detailed Summary'!G$2)) -> 0 | H44: =SUM(SUMIFS('Discover Data'!$F:$F,'Discover Data'!$H:$H,$B44,'Discover Data'!$B:$B,'Detailed Summary'!H$2)) -> 0 | I44: =SUM(SUMIFS('Discover Data'!$F:$F,'Discover Data'!$H:$H,$B44,'Discover Data'!$B:$B,'Detailed Summary'!I$2)) -> 0 | J44: =SUM(SUMIFS('Discover Data'!$F:$F,'Discover Data'!$H:$H,$B44,'Discover Data'!$B:$B,'Detailed Summary'!J$2)) -> 0 | ... N44: =SUM(SUMIFS('Discover Data'!$F:$F,'Discover Data'!$H:$H,$B44,'Discover Data'!$B:$B,'Detailed Summary'!N$2)) -> 35
B45: gas_station | C45: =SUM(SUMIFS('Discover Data'!$F:$F,'Discover Data'!$H:$H,$B45,'Discover Data'!$B:$B,'Detailed Summary'!C$2)) -> 132.49 | D45: =SUM(SUMIFS('Discover Data'!$F:$F,'Discover Data'!$H:$H,$B45,'Discover Data'!$B:$B,'Detailed Summary'!D$2)) -> 15.5 | E45: =SUM(SUMIFS('Discover Data'!$F:$F,'Discover Data'!$H:$H,$B45,'Discover Data'!$B:$B,'Detailed Summary'!E$2)) -> 48.12 | F45: =SUM(SUMIFS('Discover Data'!$F:$F,'Discover Data'!$H:$H,$B45,'Discover Data'!$B:$B,'Detailed Summary'!F$2)) -> 99.5 | G45: =SUM(SUMIFS('Discover Data'!$F:$F,'Discover Data'!$H:$H,$B45,'Discover Data'!$B:$B,'Detailed Summary'!G$2)) -> 154.34 | H45: =SUM(SUMIFS('Discover Data'!$F:$F,'Discover Data'!$H:$H,$B45,'Discover Data'!$B:$B,'Detailed Summary'!H$2)) -> 0 | I45: =SUM(SUMIFS('Discover Data'!$F:$F,'Discover Data'!$H:$H,$B45,'Discover Data'!$B:$B,'Detailed Summary'!I$2)) -> 0 | J45: =SUM(SUMIFS('Discover Data'!$F:$F,'Discover Data'!$H:$H,$B45,'Discover Data'!$B:$B,'Detailed Summary'!J$2)) -> 80.3 | ... N45: =SUM(SUMIFS('Discover Data'!$F:$F,'Discover Data'!$H:$H,$B45,'Discover Data'!$B:$B,'Detailed Summary'!N$2)) -> 0
B46: Accommodation | C46: {=SUM(SUMIFS('Discover Data'!$F:$F,'Discover Data'!$H:$H,{"lodging";""},'Discover Data'!$B:$B,'Detailed Summary'!C$2))} -> 102.14 | D46: {=SUM(SUMIFS('Discover Data'!$F:$F,'Discover Data'!$H:$H,{"lodging";""},'Discover Data'!$B:$B,'Detailed Summary'!D$2))} -> 0 | E46: {=SUM(SUMIFS('Discover Data'!$F:$F,'Discover Data'!$H:$H,{"lodging";""},'Discover Data'!$B:$B,'Detailed Summary'!E$2))} -> 0 | F46: {=SUM(SUMIFS('Discover Data'!$F:$F,'Discover Data'!$H:$H,{"lodging";""},'Discover Data'!$B:$B,'Detailed Summary'!F$2))} -> 0 | G46: {=SUM(SUMIFS('Discover Data'!$F:$F,'Discover Data'!$H:$H,{"lodging";""},'Discover Data'!$B:$B,'Detailed Summary'!G$2))} -> 190.4 | H46: {=SUM(SUMIFS('Discover Data'!$F:$F,'Discover Data'!$H:$H,{"lodging";""},'Discover Data'!$B:$B,'Detailed Summary'!H$2))} -> 0 | I46: {=SUM(SUMIFS('Discover Data'!$F:$F,'Discover Data'!$H:$H,{"lodging";""},'Discover Data'!$B:$B,'Detailed Summary'!I$2))} -> 0 | J46: {=SUM(SUMIFS('Discover Data'!$F:$F,'Discover Data'!$H:$H,{"lodging";""},'Discover Data'!$B:$B,'Detailed Summary'!J$2))} -> 0 | ... N46: {=SUM(SUMIFS('Discover Data'!$F:$F,'Discover Data'!$H:$H,{"lodging";""},'Discover Data'!$B:$B,'Detailed Summary'!N$2))} -> 0
B47: Car Repairs/Maintanence | C47: {=SUM(SUMIFS('Discover Data'!$F:$F,'Discover Data'!$H:$H,{"car";""},'Discover Data'!$B:$B,'Detailed Summary'!C$2))} -> 260.36 | D47: {=SUM(SUMIFS('Discover Data'!$F:$F,'Discover Data'!$H:$H,{"car";""},'Discover Data'!$B:$B,'Detailed Summary'!D$2))} -> 279.89 | E47: {=SUM(SUMIFS('Discover Data'!$F:$F,'Discover Data'!$H:$H,{"car";""},'Discover Data'!$B:$B,'Detailed Summary'!E$2))} -> 39 | F47: {=SUM(SUMIFS('Discover Data'!$F:$F,'Discover Data'!$H:$H,{"car";""},'Discover Data'!$B:$B,'Detailed Summary'!F$2))} -> 0 | G47: {=SUM(SUMIFS('Discover Data'!$F:$F,'Discover Data'!$H:$H,{"car";""},'Discover Data'!$B:$B,'Detailed Summary'!G$2))} -> 41.87 | H47: {=SUM(SUMIFS('Discover Data'!$F:$F,'Discover Data'!$H:$H,{"car";""},'Discover Data'!$B:$B,'Detailed Summary'!H$2))} -> 0 | I47: {=SUM(SUMIFS('Discover Data'!$F:$F,'Discover Data'!$H:$H,{"car";""},'Discover Data'!$B:$B,'Detailed Summary'!I$2))} -> 0 | J47: {=SUM(SUMIFS('Discover Data'!$F:$F,'Discover Data'!$H:$H,{"car";""},'Discover Data'!$B:$B,'Detailed Summary'!J$2))} -> 2019.8 | ... N47: {=SUM(SUMIFS('Discover Data'!$F:$F,'Discover Data'!$H:$H,{"car";""},'Discover Data'!$B:$B,'Detailed Summary'!N$2))} -> 151.04
B48: Europe | C48: {=SUM(SUMIFS('Discover Data'!$F:$F,'Discover Data'!$H:$H,{"Europe_Trip";"Pre_Europe_Trip"},'Discover Data'!$B:$B,'Detailed Summary'!C$2))} -> 0 | D48: {=SUM(SUMIFS('Discover Data'!$F:$F,'Discover Data'!$H:$H,{"Europe_Trip";"Pre_Europe_Trip"},'Discover Data'!$B:$B,'Detailed Summary'!D$2))} -> 0 | E48: {=SUM(SUMIFS('Discover Data'!$F:$F,'Discover Data'!$H:$H,{"Europe_Trip";"Pre_Europe_Trip"},'Discover Data'!$B:$B,'Detailed Summary'!E$2))} -> 0 | F48: {=SUM(SUMIFS('Discover Data'!$F:$F,'Discover Data'!$H:$H,{"Europe_Trip";"Pre_Europe_Trip"},'Discover Data'!$B:$B,'Detailed Summary'!F$2))} -> 111.82 | G48: {=SUM(SUMIFS('Discover Data'!$F:$F,'Discover Data'!$H:$H,{"Europe_Trip";"Pre_Europe_Trip"},'Discover Data'!$B:$B,'Detailed Summary'!G$2))} -> 681.62 | H48: {=SUM(SUMIFS('Discover Data'!$F:$F,'Discover Data'!$H:$H,{"Europe_Trip";"Pre_Europe_Trip"},'Discover Data'!$B:$B,'Detailed Summary'!H$2))} -> 46.79 | I48: {=SUM(SUMIFS('Discover Data'!$F:$F,'Discover Data'!$H:$H,{"Europe_Trip";"Pre_Europe_Trip"},'Discover Data'!$B:$B,'Detailed Summary'!I$2))} -> 0 | J48: {=SUM(SUMIFS('Discover Data'!$F:$F,'Discover Data'!$H:$H,{"Europe_Trip";"Pre_Europe_Trip"},'Discover Data'!$B:$B,'Detailed Summary'!J$2))} -> 0 | ... N48: {=SUM(SUMIFS('Discover Data'!$F:$F,'Discover Data'!$H:$H,{"Europe_Trip";"Pre_Europe_Trip"},'Discover Data'!$B:$B,'Detailed Summary'!N$2))} -> 0
B49: parking | C49: =SUM(SUMIFS('Discover Data'!$F:$F,'Discover Data'!$H:$H,$B49,'Discover Data'!$B:$B,'Detailed Summary'!C$2)) -> 12.35 | D49: =SUM(SUMIFS('Discover Data'!$F:$F,'Discover Data'!$H:$H,$B49,'Discover Data'!$B:$B,'Detailed Summary'!D$2)) -> 57.23 | E49: =SUM(SUMIFS('Discover Data'!$F:$F,'Discover Data'!$H:$H,$B49,'Discover Data'!$B:$B,'Detailed Summary'!E$2)) -> 32.2 | F49: =SUM(SUMIFS('Discover Data'!$F:$F,'Discover Data'!$H:$H,$B49,'Discover Data'!$B:$B,'Detailed Summary'!F$2)) -> 52.34 | G49: =SUM(SUMIFS('Discover Data'!$F:$F,'Discover Data'!$H:$H,$B49,'Discover Data'!$B:$B,'Detailed Summary'!G$2)) -> 7 | H49: =SUM(SUMIFS('Discover Data'!$F:$F,'Discover Data'!$H:$H,$B49,'Discover Data'!$B:$B,'Detailed Summary'!H$2)) -> 0 | I49: =SUM(SUMIFS('Discover Data'!$F:$F,'Discover Data'!$H:$H,$B49,'Discover Data'!$B:$B,'Detailed Summary'!I$2)) -> 0 | J49: =SUM(SUMIFS('Discover Data'!$F:$F,'Discover Data'!$H:$H,$B49,'Discover Data'!$B:$B,'Detailed Summary'!J$2)) -> 0 | ... N49: =SUM(SUMIFS('Discover Data'!$F:$F,'Discover Data'!$H:$H,$B49,'Discover Data'!$B:$B,'Detailed Summary'!N$2)) -> 0
B50: Fees | C50: {=SUM(SUMIFS('Discover Data'!$F:$F,'Discover Data'!$H:$H,{"motor_cycle_license";"taxes";"tolls"},'Discover Data'!$B:$B,'Detailed Summary'!C$2))} -> 125 | D50: {=SUM(SUMIFS('Discover Data'!$F:$F,'Discover Data'!$H:$H,{"motor_cycle_license";"taxes";"tolls"},'Discover Data'!$B:$B,'Detailed Summary'!D$2))} -> 29.98 | E50: {=SUM(SUMIFS('Discover Data'!$F:$F,'Discover Data'!$H:$H,{"motor_cycle_license";"taxes";"tolls"},'Discover Data'!$B:$B,'Detailed Summary'!E$2))} -> 375 | F50: {=SUM(SUMIFS('Discover Data'!$F:$F,'Discover Data'!$H:$H,{"motor_cycle_license";"taxes";"tolls"},'Discover Data'!$B:$B,'Detailed Summary'!F$2))} -> 279.27 | G50: {=SUM(SUMIFS('Discover Data'!$F:$F,'Discover Data'!$H:$H,{"motor_cycle_license";"taxes";"tolls"},'Discover Data'!$B:$B,'Detailed Summary'!G$2))} -> 50 | H50: {=SUM(SUMIFS('Discover Data'!$F:$F,'Discover Data'!$H:$H,{"motor_cycle_license";"taxes";"tolls"},'Discover Data'!$B:$B,'Detailed Summary'!H$2))} -> 0 | I50: {=SUM(SUMIFS('Discover Data'!$F:$F,'Discover Data'!$H:$H,{"motor_cycle_license";"taxes";"tolls"},'Discover Data'!$B:$B,'Detailed Summary'!I$2))} -> 35 | J50: {=SUM(SUMIFS('Discover Data'!$F:$F,'Discover Data'!$H:$H,{"motor_cycle_license";"taxes";"tolls"},'Discover Data'!$B:$B,'Detailed Summary'!J$2))} -> 0 | ... N50: {=SUM(SUMIFS('Discover Data'!$F:$F,'Discover Data'!$H:$H,{"motor_cycle_license";"taxes";"tolls"},'Discover Data'!$B:$B,'Detailed Summary'!N$2))} -> 0
B51: Education and Hobbies | C51: {=SUM(SUMIFS('Discover Data'!$F:$F,'Discover Data'!$H:$H,{"learning";"professional"},'Discover Data'!$B:$B,'Detailed Summary'!C$2))} -> 72.99 | D51: {=SUM(SUMIFS('Discover Data'!$F:$F,'Discover Data'!$H:$H,{"learning";"professional"},'Discover Data'!$B:$B,'Detailed Summary'!D$2))} -> 58 | E51: {=SUM(SUMIFS('Discover Data'!$F:$F,'Discover Data'!$H:$H,{"learning";"professional"},'Discover Data'!$B:$B,'Detailed Summary'!E$2))} -> 50.72 | F51: {=SUM(SUMIFS('Discover Data'!$F:$F,'Discover Data'!$H:$H,{"learning";"professional"},'Discover Data'!$B:$B,'Detailed Summary'!F$2))} -> 0 | G51: {=SUM(SUMIFS('Discover Data'!$F:$F,'Discover Data'!$H:$H,{"learning";"professional"},'Discover Data'!$B:$B,'Detailed Summary'!G$2))} -> 1183.74 | H51: {=SUM(SUMIFS('Discover Data'!$F:$F,'Discover Data'!$H:$H,{"learning";"professional"},'Discover Data'!$B:$B,'Detailed Summary'!H$2))} -> 192.99 | I51: {=SUM(SUMIFS('Discover Data'!$F:$F,'Discover Data'!$H:$H,{"learning";"professional"},'Discover Data'!$B:$B,'Detailed Summary'!I$2))} -> 7.99 | J51: {=SUM(SUMIFS('Discover Data'!$F:$F,'Discover Data'!$H:$H,{"learning";"professional"},'Discover Data'!$B:$B,'Detailed Summary'!J$2))} -> 67 | ... N51: {=SUM(SUMIFS('Discover Data'!$F:$F,'Discover Data'!$H:$H,{"learning";"professional"},'Discover Data'!$B:$B,'Detailed Summary'!N$2))} -> 0
B52: Family | C52: {=SUM(SUMIFS('Discover Data'!$F:$F,'Discover Data'!$H:$H,{"kids";"dad";"shiloh"},'Discover Data'!$B:$B,'Detailed Summary'!C$2))} -> 0 | D52: {=SUM(SUMIFS('Discover Data'!$F:$F,'Discover Data'!$H:$H,{"kids";"dad";"shiloh"},'Discover Data'!$B:$B,'Detailed Summary'!D$2))} -> 44.7 | E52: {=SUM(SUMIFS('Discover Data'!$F:$F,'Discover Data'!$H:$H,{"kids";"dad";"shiloh"},'Discover Data'!$B:$B,'Detailed Summary'!E$2))} -> 6.35 | F52: {=SUM(SUMIFS('Discover Data'!$F:$F,'Discover Data'!$H:$H,{"kids";"dad";"shiloh"},'Discover Data'!$B:$B,'Detailed Summary'!F$2))} -> 22.43 | G52: {=SUM(SUMIFS('Discover Data'!$F:$F,'Discover Data'!$H:$H,{"kids";"dad";"shiloh"},'Discover Data'!$B:$B,'Detailed Summary'!G$2))} -> 0 | H52: {=SUM(SUMIFS('Discover Data'!$F:$F,'Discover Data'!$H:$H,{"kids";"dad";"shiloh"},'Discover Data'!$B:$B,'Detailed Summary'!H$2))} -> 0 | I52: {=SUM(SUMIFS('Discover Data'!$F:$F,'Discover Data'!$H:$H,{"kids";"dad";"shiloh"},'Discover Data'!$B:$B,'Detailed Summary'!I$2))} -> 0 | J52: {=SUM(SUMIFS('Discover Data'!$F:$F,'Discover Data'!$H:$H,{"kids";"dad";"shiloh"},'Discover Data'!$B:$B,'Detailed Summary'!J$2))} -> 0 | ... N52: {=SUM(SUMIFS('Discover Data'!$F:$F,'Discover Data'!$H:$H,{"kids";"dad";"shiloh"},'Discover Data'!$B:$B,'Detailed Summary'!N$2))} -> 0
B53: self_care | C53: =SUM(SUMIFS('Discover Data'!$F:$F,'Discover Data'!$H:$H,$B53,'Discover Data'!$B:$B,'Detailed Summary'!C$2)) -> 0 | D53: =SUM(SUMIFS('Discover Data'!$F:$F,'Discover Data'!$H:$H,$B53,'Discover Data'!$B:$B,'Detailed Summary'!D$2)) -> 0 | E53: =SUM(SUMIFS('Discover Data'!$F:$F,'Discover Data'!$H:$H,$B53,'Discover Data'!$B:$B,'Detailed Summary'!E$2)) -> 17.36 | F53: =SUM(SUMIFS('Discover Data'!$F:$F,'Discover Data'!$H:$H,$B53,'Discover Data'!$B:$B,'Detailed Summary'!F$2)) -> 0 | G53: =SUM(SUMIFS('Discover Data'!$F:$F,'Discover Data'!$H:$H,$B53,'Discover Data'!$B:$B,'Detailed Summary'!G$2)) -> 0 | H53: =SUM(SUMIFS('Discover Data'!$F:$F,'Discover Data'!$H:$H,$B53,'Discover Data'!$B:$B,'Detailed Summary'!H$2)) -> 0 | I53: =SUM(SUMIFS('Discover Data'!$F:$F,'Discover Data'!$H:$H,$B53,'Discover Data'!$B:$B,'Detailed Summary'!I$2)) -> 0 | J53: =SUM(SUMIFS('Discover Data'!$F:$F,'Discover Data'!$H:$H,$B53,'Discover Data'!$B:$B,'Detailed Summary'!J$2)) -> 0 | ... N53: =SUM(SUMIFS('Discover Data'!$F:$F,'Discover Data'!$H:$H,$B53,'Discover Data'!$B:$B,'Detailed Summary'!N$2)) -> 0
